{
  "type": "Feature",
  "properties": {
    "iso:country":"DE",
    "sg:address":"B\u00e4ckerstr. 105",
    "sg:city":"Goslar",
    "sg:phone":"+49 5321/43611",
    "sg:postcode":"38640",
    "sg:province":"Niedersachsen",
    "wof:name":"Antikes Gmbh",
    "wof:placetype":"venue"
},
  "geometry": {"coordinates":[10.427311,51.907341],"type":"Point"}
}