{
  "type": "Feature",
  "properties": {
    "iso:country":"DE",
    "sg:address":"Parlamentsstr. 38",
    "sg:city":"Frankfurt",
    "sg:phone":"+49 69/439711",
    "sg:postcode":"60385",
    "sg:province":"Hessen",
    "wof:name":"Walter Haas Ingenieur",
    "wof:placetype":"venue"
},
  "geometry": {"coordinates":[8.7168445587,50.1216964722],"type":"Point"}
}