{
  "type": "Feature",
  "properties": {
    "iso:country":"DE",
    "sg:address":"Rosenweg 20",
    "sg:city":"Freudenberg",
    "sg:phone":"+49 2734/2661",
    "sg:postcode":"57258",
    "sg:province":"Nordrhein-Westfalen",
    "wof:name":"Erfried Bender Ingenieurin",
    "wof:placetype":"venue"
},
  "geometry": {"coordinates":[7.9266347885,50.8993377686],"type":"Point"}
}