{
  "type": "Feature",
  "properties": {
    "iso:country":"DE",
    "sg:address":"Rosenbergstr. 6",
    "sg:city":"Grenderich",
    "sg:postcode":"56858",
    "sg:province":"Rheinland-Pfalz",
    "wof:name":"Rost Gmbh",
    "wof:placetype":"venue"
},
  "geometry": {"coordinates":[7.22875,50.066685],"type":"Point"}
}