{
  "type": "Feature",
  "properties": {
    "iso:country":"DE",
    "sg:address":"Kustrenaer Str. 65",
    "sg:city":"Bernburg",
    "sg:phone":"+49 3471/317677",
    "sg:postcode":"06406",
    "sg:province":"Sachsen-Anhalt",
    "wof:name":"J. Burchert",
    "wof:placetype":"venue"
},
  "geometry": {"coordinates":[11.73847,51.791779],"type":"Point"}
}