{
  "type": "Feature",
  "properties": {
    "iso:country":"DE",
    "sg:address":"Varrelheide 19b",
    "sg:city":"Hannover",
    "sg:phone":"+49 511/2831212",
    "sg:postcode":"30657",
    "sg:province":"Niedersachsen",
    "wof:name":"Bautr\u00e4ger & Planungs-gmbh Elmo-haus",
    "wof:placetype":"venue"
},
  "geometry": {"coordinates":[9.8316040039,52.4244537354],"type":"Point"}
}