{
  "type": "Feature",
  "properties": {
    "iso:country":"DE",
    "sg:address":"Neidinger Str.",
    "sg:city":"Beuron",
    "sg:phone":"+49 7579/523",
    "sg:postcode":"88631",
    "sg:province":"Baden-W\u00fcrttemberg",
    "wof:name":"Gasthaus Neidinger M\u00fchle",
    "wof:placetype":"venue"
},
  "geometry": {"coordinates":[9.0421895981,48.0867347717],"type":"Point"}
}