{
  "type": "Feature",
  "properties": {
    "iso:country":"DE",
    "sg:address":"Am Tivoli 19",
    "sg:city":"Horneburg",
    "sg:phone":"+49 4163/3005",
    "sg:postcode":"21640",
    "sg:province":"Niedersachsen",
    "wof:name":"Hans Von Der Lieth",
    "wof:placetype":"venue"
},
  "geometry": {"coordinates":[9.5872182846,53.5030212402],"type":"Point"}
}