{
  "type": "Feature",
  "properties": {
    "iso:country":"DE",
    "sg:address":"Valentinskamp 18",
    "sg:city":"Hamburg",
    "sg:phone":"+49 40/2880940",
    "sg:postcode":"20354",
    "sg:province":"Hamburg",
    "wof:name":"Stilwerk Holding Gmbh",
    "wof:placetype":"venue"
},
  "geometry": {"coordinates":[9.9862,53.555542],"type":"Point"}
}