{
  "type": "Feature",
  "properties": {
    "iso:country":"DE",
    "sg:address":"Hesseweg 1",
    "sg:city":"Bempflingen",
    "sg:phone":"+49 7123/32583",
    "sg:postcode":"72658",
    "sg:province":"Baden-W\u00fcrttemberg",
    "wof:name":"Hans G. Knecht Architekt",
    "wof:placetype":"venue"
},
  "geometry": {"coordinates":[9.271113,48.574909],"type":"Point"}
}