{
  "type": "Feature",
  "properties": {
    "iso:country":"DE",
    "sg:address":"Kolpingstr. 6",
    "sg:city":"Bad K\u00f6nigshofen",
    "sg:phone":"+49 9761/6413",
    "sg:postcode":"97631",
    "sg:province":"Bayern",
    "wof:name":"Dr. Bernhard Suren Vet. Direktor",
    "wof:placetype":"venue"
},
  "geometry": {"coordinates":[10.4625482559,50.3014717102],"type":"Point"}
}