{
  "type": "Feature",
  "properties": {
    "iso:country":"DE",
    "sg:address":"Hauptstr 343",
    "sg:city":"Saterland",
    "sg:phone":"+49 4492/925820",
    "sg:postcode":"26683",
    "sg:province":"Niedersachsen",
    "wof:name":"Griendtsveen Ag",
    "wof:placetype":"venue"
},
  "geometry": {"coordinates":[7.69685,53.074699],"type":"Point"}
}