{
  "type": "Feature",
  "properties": {
    "iso:country":"DE",
    "sg:address":"Marktstr. 139",
    "sg:city":"Hamburg",
    "sg:phone":"+49 40/4394949",
    "sg:postcode":"20357",
    "sg:province":"Hamburg",
    "wof:name":"Amad",
    "wof:placetype":"venue"
},
  "geometry": {"coordinates":[9.974042,53.558582],"type":"Point"}
}