{
  "type": "Feature",
  "properties": {
    "iso:country":"DE",
    "sg:address":"49393",
    "sg:city":"Oldenburg",
    "sg:phone":"+49 4442/8820",
    "sg:postcode":"49393",
    "sg:province":"Niedersachsen",
    "wof:name":"Volksbank Lohne-m\u00fchlen Eg",
    "wof:placetype":"venue"
},
  "geometry": {"coordinates":[-85.206238,39.339813],"type":"Point"}
}