{
  "type": "Feature",
  "properties": {
    "iso:country":"DE",
    "sg:address":"Alter Postweg 172",
    "sg:city":"Bad Oeynhausen",
    "sg:phone":"+49 5731/53116",
    "sg:postcode":"32549",
    "sg:province":"Nordrhein-Westfalen",
    "wof:name":"Adelheid B\u00f6ttger",
    "wof:placetype":"venue"
},
  "geometry": {"coordinates":[8.8323469162,52.2330436707],"type":"Point"}
}