{
  "type": "Feature",
  "properties": {
    "iso:country":"DE",
    "sg:address":"Dellbusch 222",
    "sg:city":"Wuppertal",
    "sg:postcode":"42279",
    "sg:province":"Nordrhein-Westfalen",
    "wof:name":"Dr.harms Consulting Qualit\u00e4ts- Management Haco Gmbh",
    "wof:placetype":"venue"
},
  "geometry": {"coordinates":[7.21354,51.30024],"type":"Point"}
}