{
  "type": "Feature",
  "properties": {
    "iso:country":"DE",
    "sg:address":"Tannenweg 21",
    "sg:city":"Gondershausen",
    "sg:phone":"+49 6745/1318",
    "sg:postcode":"56283",
    "sg:province":"Rheinland-Pfalz",
    "wof:name":"Eppelsheim Ingenieur",
    "wof:placetype":"venue"
},
  "geometry": {"coordinates":[7.4900507927,50.1621437073],"type":"Point"}
}