{
  "type": "Feature",
  "properties": {
    "iso:country":"DE",
    "sg:address":"Kirchstr. 50",
    "sg:city":"Finnentrop",
    "sg:phone":"+49 2721/7231",
    "sg:postcode":"57413",
    "sg:province":"Nordrhein-Westfalen",
    "wof:name":"Sch\u00fctzenhof-lichtspiele",
    "wof:placetype":"venue"
},
  "geometry": {"coordinates":[7.9684119225,51.1749343872],"type":"Point"}
}