{
  "type": "Feature",
  "properties": {
    "iso:country":"DE",
    "sg:address":"Hessenring 3",
    "sg:city":"Horn-Bad Meinberg",
    "sg:phone":"+49 5234/99036",
    "sg:postcode":"32805",
    "sg:province":"Nordrhein-Westfalen",
    "wof:name":"Martin Schnittcher",
    "wof:placetype":"venue"
},
  "geometry": {"coordinates":[8.955955,51.87682],"type":"Point"}
}