{
  "type": "Feature",
  "properties": {
    "iso:country":"DE",
    "sg:address":"\u00d6jendorfer Steinkamp 19",
    "sg:city":"Hamburg",
    "sg:postcode":"22117",
    "sg:province":"Hamburg",
    "wof:name":"Hans-j\u00fcrgen Johannsen",
    "wof:placetype":"venue"
},
  "geometry": {"coordinates":[10.132267,53.541035],"type":"Point"}
}