{
  "type": "Feature",
  "properties": {
    "iso:country":"DE",
    "sg:address":"Lange Str. 55",
    "sg:city":"Lingen",
    "sg:phone":"+49 5907/581",
    "sg:postcode":"49808",
    "sg:province":"Niedersachsen",
    "wof:name":"Heinrich Hemker Elektro Mstr.",
    "wof:placetype":"venue"
},
  "geometry": {"coordinates":[7.31586,52.521549],"type":"Point"}
}