{
  "type": "Feature",
  "properties": {
    "iso:country":"DE",
    "sg:address":"Hindenburgstr. 28",
    "sg:city":"Cremlingen",
    "sg:phone":"+49 5306/970303",
    "sg:postcode":"38162",
    "sg:province":"Niedersachsen",
    "wof:name":"Frank-m. Neubert Neubert",
    "wof:placetype":"venue"
},
  "geometry": {"coordinates":[10.683369,52.271866],"type":"Point"}
}