{
  "type": "Feature",
  "properties": {
    "iso:country":"DE",
    "sg:address":"Gartroper Str. 42",
    "sg:city":"Duisburg",
    "sg:phone":"+49 203/4292223",
    "sg:postcode":"47138",
    "sg:province":"Nordrhein-Westfalen",
    "wof:name":"Redaktionsb\u00fcro Blindtext",
    "wof:placetype":"venue"
},
  "geometry": {"coordinates":[6.80844,51.470997],"type":"Point"}
}