{
  "type": "Feature",
  "properties": {
    "iso:country":"DE",
    "sg:address":"D\u00fcppenweilerstr. 56",
    "sg:city":"Schmelz",
    "sg:phone":"+49 6887/2795",
    "sg:postcode":"66839",
    "sg:province":"Saarland",
    "wof:name":"Friedrich Becker",
    "wof:placetype":"venue"
},
  "geometry": {"coordinates":[6.8354668617,49.4239616394],"type":"Point"}
}