{
  "type": "Feature",
  "properties": {
    "iso:country":"DE",
    "sg:address":"Gablonzer Ring 6 A",
    "sg:city":"Kaufbeuren",
    "sg:phone":"+49 8341/68788",
    "sg:postcode":"87600",
    "sg:province":"Bayern",
    "wof:name":"Sudeten-apotheke",
    "wof:placetype":"venue"
},
  "geometry": {"coordinates":[10.636298,47.912617],"type":"Point"}
}