{
  "type": "Feature",
  "properties": {
    "iso:country":"DE",
    "sg:address":"Lilienthalstr. 9",
    "sg:city":"Saarlouis",
    "sg:postcode":"66740",
    "sg:province":"Saarland",
    "wof:name":"Friedrich-wilhelm-pfister- Stiftung",
    "wof:placetype":"venue"
},
  "geometry": {"coordinates":[6.7351770401,49.3102874756],"type":"Point"}
}