{
  "type": "Feature",
  "properties": {
    "iso:country":"DE",
    "sg:address":"Rainweg 68",
    "sg:city":"Saalfeld",
    "sg:phone":"+49 3671/540",
    "sg:postcode":"07318",
    "sg:province":"Th\u00fcringen",
    "wof:name":"Apotheke Am Agricola- Krankenhaus Saalfeld",
    "wof:placetype":"venue"
},
  "geometry": {"coordinates":[11.344814,50.644638],"type":"Point"}
}