{
  "type": "Feature",
  "properties": {
    "iso:country":"DE",
    "sg:address":"Gro\u00dfe Trift 10",
    "sg:city":"Minden",
    "sg:phone":"+49 571/37523",
    "sg:postcode":"32423",
    "sg:province":"Nordrhein-Westfalen",
    "wof:name":"Lothar Reipa",
    "wof:placetype":"venue"
},
  "geometry": {"coordinates":[8.9377384186,52.3168449402],"type":"Point"}
}