{
  "type": "Feature",
  "properties": {
    "iso:country":"DE",
    "sg:address":"Alter Markt 4",
    "sg:city":"Quierschied",
    "sg:phone":"+49 6897/64414",
    "sg:postcode":"66287",
    "sg:province":"Saarland",
    "wof:name":"Jutta Burgardt Rechtsanw\u00e4ltin",
    "wof:placetype":"venue"
},
  "geometry": {"coordinates":[7.0530400276,49.3246803284],"type":"Point"}
}