{
  "type": "Feature",
  "properties": {
    "iso:country":"DE",
    "sg:address":"Tolnauer Str 3-4",
    "sg:city":"Tettnang",
    "sg:phone":"+49 4975/4293330",
    "sg:postcode":"88069",
    "sg:province":"Baden-W\u00fcrttemberg",
    "wof:name":"Bartsch Gmbh Engineering",
    "wof:placetype":"venue"
},
  "geometry": {"coordinates":[9.56563,47.659431],"type":"Point"}
}