{
  "type": "Feature",
  "properties": {
    "iso:country":"DE",
    "sg:address":"Am Mittelburgwall 24",
    "sg:city":"Friedrichstadt",
    "sg:phone":"+49 4881/93900",
    "sg:postcode":"25840",
    "sg:province":"Schleswig-Holstein",
    "wof:name":"Hotel-restaurant Holl\u00e4ndische Stube",
    "wof:placetype":"venue"
},
  "geometry": {"coordinates":[9.0894441605,54.3768997192],"type":"Point"}
}