{
  "type": "Feature",
  "properties": {
    "iso:country":"DE",
    "sg:address":"Sattelstr. 85",
    "sg:city":"Stuttgart",
    "sg:phone":"+49 711/339513",
    "sg:postcode":"70327",
    "sg:province":"Baden-W\u00fcrttemberg",
    "wof:name":"Dietbachhof",
    "wof:placetype":"venue"
},
  "geometry": {"coordinates":[9.2480230331,48.7901687622],"type":"Point"}
}