{
  "type": "Feature",
  "properties": {
    "iso:country":"DE",
    "sg:address":"Am Ring 30c",
    "sg:city":"Tecklenburg",
    "sg:phone":"+49 5482/1659",
    "sg:postcode":"49545",
    "sg:province":"Nordrhein-Westfalen",
    "wof:name":"Trib\u00fcnenbau Grosse-erdmann",
    "wof:placetype":"venue"
},
  "geometry": {"coordinates":[7.821339,52.233963],"type":"Point"}
}