{
  "type": "Feature",
  "properties": {
    "iso:country":"DE",
    "sg:address":"Carl-Kistner-Str. 2 a",
    "sg:city":"Freiburg",
    "sg:phone":"+49 761/472256",
    "sg:postcode":"79115",
    "sg:province":"Baden-W\u00fcrttemberg",
    "wof:name":"Gerhard L\u00f6ffler",
    "wof:placetype":"venue"
},
  "geometry": {"coordinates":[7.8157930374,47.9910926819],"type":"Point"}
}