{
  "type": "Feature",
  "properties": {
    "iso:country":"DE",
    "sg:address":"Falkenweg 4",
    "sg:city":"Erftstadt",
    "sg:phone":"+49 2235/75457",
    "sg:postcode":"50374",
    "sg:province":"Nordrhein-Westfalen",
    "wof:name":"Helga Steffen-kuphal",
    "wof:placetype":"venue"
},
  "geometry": {"coordinates":[6.7748160362,50.8039894104],"type":"Point"}
}