{
  "type": "Feature",
  "properties": {
    "iso:country":"DE",
    "sg:address":"Marienweg 4",
    "sg:city":"Kelberg",
    "sg:phone":"+49 2692/85848",
    "sg:postcode":"53539",
    "sg:province":"Rheinland-Pfalz",
    "wof:name":"T. Schilberg Finanzberater",
    "wof:placetype":"venue"
},
  "geometry": {"coordinates":[6.9176688194,50.2873649597],"type":"Point"}
}