{
  "type": "Feature",
  "properties": {
    "iso:country":"DE",
    "sg:address":"Fliederstr. 28",
    "sg:city":"Weiden",
    "sg:phone":"+49 961/25169",
    "sg:postcode":"92637",
    "sg:province":"Bayern",
    "wof:name":"Karl Lindner",
    "wof:placetype":"venue"
},
  "geometry": {"coordinates":[12.1440467834,49.6890678406],"type":"Point"}
}