{
  "type": "Feature",
  "properties": {
    "iso:country":"DE",
    "sg:address":"Neusser Str. 116",
    "sg:city":"J\u00fcchen",
    "sg:phone":"+49 2165/7033",
    "sg:postcode":"41363",
    "sg:province":"Nordrhein-Westfalen",
    "wof:name":"Dielmann Karton Gmbh",
    "wof:placetype":"venue"
},
  "geometry": {"coordinates":[6.5199990273,51.0993843079],"type":"Point"}
}