{
  "type": "Feature",
  "properties": {
    "iso:country":"DE",
    "sg:address":"Hufelandstr 21",
    "sg:city":"M\u00fcnchen",
    "sg:phone":"+49 89/3169360",
    "sg:postcode":"80939",
    "sg:province":"Bayern",
    "wof:name":"Dr.-ing. A. Haenlein Gmbh",
    "wof:placetype":"venue"
},
  "geometry": {"coordinates":[11.583805,48.193565],"type":"Point"}
}