{
  "type": "Feature",
  "properties": {
    "iso:country":"DE",
    "sg:address":"Industriestr. 3",
    "sg:city":"Saterland",
    "sg:phone":"+49 4498/92530",
    "sg:postcode":"26683",
    "sg:province":"Niedersachsen",
    "wof:name":"B\u00f6ckmann Gmbh",
    "wof:placetype":"venue"
},
  "geometry": {"coordinates":[7.684375,53.102978],"type":"Point"}
}