{
  "type": "Feature",
  "properties": {
    "iso:country":"DE",
    "sg:address":"Algershausener Str. 45",
    "sg:city":"Wittmund",
    "sg:phone":"+49 4462/5494",
    "sg:postcode":"26409",
    "sg:province":"Niedersachsen",
    "wof:name":"Siemen Wichmann",
    "wof:placetype":"venue"
},
  "geometry": {"coordinates":[7.77175,53.587158],"type":"Point"}
}