{
  "type": "Feature",
  "properties": {
    "iso:country":"DE",
    "sg:address":"Hanauer Pfad 5",
    "sg:city":"Sch\u00f6neck",
    "sg:phone":"+49 6187/91948",
    "sg:postcode":"61137",
    "sg:province":"Hessen",
    "wof:name":"Eva Schmidt",
    "wof:placetype":"venue"
},
  "geometry": {"coordinates":[8.8412046432,50.2166137695],"type":"Point"}
}