{
  "type": "Feature",
  "properties": {
    "iso:country":"DE",
    "sg:address":"Auf der Eich 37",
    "sg:city":"Mayen",
    "sg:phone":"+49 2651/73904",
    "sg:postcode":"56727",
    "sg:province":"Rheinland-Pfalz",
    "wof:name":"Siegfried Legler",
    "wof:placetype":"venue"
},
  "geometry": {"coordinates":[7.2294230461,50.3342857361],"type":"Point"}
}