{
  "type": "Feature",
  "properties": {
    "iso:country":"DE",
    "sg:address":"Zeller Str. 10",
    "sg:city":"Ruhpolding",
    "sg:phone":"+49 8663/658",
    "sg:postcode":"83324",
    "sg:province":"Bayern",
    "wof:name":"G\u00e4stehaus Am Zellerberg",
    "wof:placetype":"venue"
},
  "geometry": {"coordinates":[12.6507387161,47.7598342896],"type":"Point"}
}