{
  "type": "Feature",
  "properties": {
    "iso:country":"DE",
    "sg:address":"Rottstr. 18",
    "sg:city":"Datteln",
    "sg:phone":"+49 2363/55597",
    "sg:postcode":"45711",
    "sg:province":"Nordrhein-Westfalen",
    "wof:name":"D. V. G. Handel Mit Lichtsystemen",
    "wof:placetype":"venue"
},
  "geometry": {"coordinates":[7.3425731659,51.6523704529],"type":"Point"}
}