{
  "type": "Feature",
  "properties": {
    "iso:country":"DE",
    "sg:address":"Zurmaiener Str. 13",
    "sg:city":"Trier",
    "sg:phone":"+49 651/26360",
    "sg:postcode":"54292",
    "sg:province":"Rheinland-Pfalz",
    "wof:name":"Albert Benz",
    "wof:placetype":"venue"
},
  "geometry": {"coordinates":[6.637075901,49.764995575],"type":"Point"}
}