{
  "type": "Feature",
  "properties": {
    "iso:country":"DE",
    "sg:address":"Unter dem Rotdorn 2",
    "sg:city":"Wetzlar",
    "sg:postcode":"35578",
    "sg:province":"Hessen",
    "wof:name":"Witec Wiegetechnik Gmbh",
    "wof:placetype":"venue"
},
  "geometry": {"coordinates":[8.536975,50.542522],"type":"Point"}
}