{
  "type": "Feature",
  "properties": {
    "iso:country":"DE",
    "sg:address":"Heimatliebe 1",
    "sg:city":"Sparneck",
    "sg:phone":"+49 9251/8113",
    "sg:postcode":"95234",
    "sg:province":"Bayern",
    "wof:name":"Waldhotel Heimatliebe",
    "wof:placetype":"venue"
},
  "geometry": {"coordinates":[11.8424444199,50.1581420898],"type":"Point"}
}