{
  "type": "Feature",
  "properties": {
    "iso:country":"DE",
    "sg:address":"Buckelgarten 9",
    "sg:city":"Gro\u00df-Umstadt",
    "sg:phone":"+49 6078",
    "sg:postcode":"64823",
    "sg:province":"Hessen",
    "wof:name":"Eine Brilliante Verdienstm\u00f6glichkeit",
    "wof:placetype":"venue"
},
  "geometry": {"coordinates":[8.941603,49.820244],"type":"Point"}
}