{
  "type": "Feature",
  "properties": {
    "iso:country":"DE",
    "sg:address":"B\u00fcrgermeister-Schmidt-Platz 21",
    "sg:city":"Wurzen",
    "sg:postcode":"04808",
    "sg:province":"Sachsen",
    "wof:name":"C. Bigalke",
    "wof:placetype":"venue"
},
  "geometry": {"coordinates":[12.742356,51.371613],"type":"Point"}
}