{
  "type": "Feature",
  "properties": {
    "iso:country":"DE",
    "sg:address":"Alte Landstr. 1",
    "sg:city":"Weinheim",
    "sg:phone":"+49 6201/12653",
    "sg:postcode":"69469",
    "sg:province":"Baden-W\u00fcrttemberg",
    "wof:name":"Heinrich Weber",
    "wof:placetype":"venue"
},
  "geometry": {"coordinates":[8.669549942,49.5560569763],"type":"Point"}
}