{
  "type": "Feature",
  "properties": {
    "iso:country":"DE",
    "sg:address":"Kleiberweg 19",
    "sg:city":"Leverkusen",
    "sg:phone":"+49 214/64203",
    "sg:postcode":"51373",
    "sg:province":"Nordrhein-Westfalen",
    "wof:name":"Rudi Reinartz Architekt",
    "wof:placetype":"venue"
},
  "geometry": {"coordinates":[6.989488,51.052773],"type":"Point"}
}