{
  "type": "Feature",
  "properties": {
    "iso:country":"DE",
    "sg:address":"Hauptstr. 52",
    "sg:city":"H\u00fcckelhoven",
    "sg:phone":"+49 2462/8134",
    "sg:postcode":"41836",
    "sg:province":"Nordrhein-Westfalen",
    "wof:name":"Fleischerei Wilms Gmbh",
    "wof:placetype":"venue"
},
  "geometry": {"coordinates":[6.2411408424,51.0046234131],"type":"Point"}
}