{
  "type": "Feature",
  "properties": {
    "iso:country":"DE",
    "sg:address":"Stau 19",
    "sg:city":"Oldenburg",
    "sg:phone":"+49 441/24210",
    "sg:postcode":"26122",
    "sg:province":"Niedersachsen",
    "wof:name":"China Restaurant Hong-kong",
    "wof:placetype":"venue"
},
  "geometry": {"coordinates":[8.2195005417,53.1406745911],"type":"Point"}
}