{
  "type": "Feature",
  "properties": {
    "iso:country":"DE",
    "sg:address":"Am Eichbaum 5",
    "sg:city":"Frankfurt",
    "sg:phone":"+49 4961/0142334",
    "sg:postcode":"60437",
    "sg:province":"Hessen",
    "wof:name":"Art Kaze",
    "wof:placetype":"venue"
},
  "geometry": {"coordinates":[8.715411,50.201996],"type":"Point"}
}