{
  "type": "Feature",
  "properties": {
    "iso:country":"DE",
    "sg:address":"Nettelseer Str. 21",
    "sg:city":"Preetz",
    "sg:phone":"+49 4342/2885",
    "sg:postcode":"24211",
    "sg:province":"Schleswig-Holstein",
    "wof:name":"Gisela Bredereck",
    "wof:placetype":"venue"
},
  "geometry": {"coordinates":[10.261972,54.215099],"type":"Point"}
}