{
  "type": "Feature",
  "properties": {
    "iso:country":"DE",
    "sg:address":"Im Nahner Feld 1",
    "sg:city":"Osnabr\u00fcck",
    "sg:phone":"+49 541/505810",
    "sg:postcode":"49082",
    "sg:province":"Niedersachsen",
    "wof:name":"Der Hei\u00dfe Draht",
    "wof:placetype":"venue"
},
  "geometry": {"coordinates":[8.0633020401,52.2489700317],"type":"Point"}
}