{
  "type": "Feature",
  "properties": {
    "iso:country":"DE",
    "sg:address":"Hans-B\u00f6ckler-Str. 2",
    "sg:city":"Bochum",
    "sg:phone":"+49 234/60871",
    "sg:postcode":"44787",
    "sg:province":"Nordrhein-Westfalen",
    "wof:name":"Kopierladen Th\u00f6ne Gmbh",
    "wof:placetype":"venue"
},
  "geometry": {"coordinates":[7.2161951065,51.4821472168],"type":"Point"}
}