{
  "type": "Feature",
  "properties": {
    "iso:country":"DE",
    "sg:address":"Waldenstr. 21 c",
    "sg:city":"Erfurt",
    "sg:phone":"+49 361/5667327",
    "sg:postcode":"99084",
    "sg:province":"Th\u00fcringen",
    "wof:name":"Scheele Erfurt",
    "wof:placetype":"venue"
},
  "geometry": {"coordinates":[11.02983284,50.9825706482],"type":"Point"}
}