{
  "type": "Feature",
  "properties": {
    "iso:country":"DE",
    "sg:address":"Heinrichstra\u00dfe 51",
    "sg:city":"L\u00fcnen",
    "sg:phone":"+49 4923/188080",
    "sg:postcode":"44536",
    "sg:province":"Nordrhein-Westfalen",
    "wof:name":"Pgpa Werbeagentur Ag",
    "wof:placetype":"venue"
},
  "geometry": {"coordinates":[7.452046,51.604546],"type":"Point"}
}