{
  "type": "Feature",
  "properties": {
    "iso:country":"DE",
    "sg:address":"Ziegelweg 104",
    "sg:city":"Reichenbach",
    "sg:phone":"+49 3765/14841",
    "sg:postcode":"08468",
    "sg:province":"Sachsen",
    "wof:name":"B. Schmutzler",
    "wof:placetype":"venue"
},
  "geometry": {"coordinates":[12.309841,50.635284],"type":"Point"}
}