{
  "type": "Feature",
  "properties": {
    "iso:country":"DE",
    "sg:address":"Finninger Str. 561/3",
    "sg:city":"Neu-Ulm",
    "sg:phone":"+49 731/9707860",
    "sg:postcode":"89231",
    "sg:province":"Bayern",
    "wof:name":"B & W Engineering Verwaltungsges. Mbh",
    "wof:placetype":"venue"
},
  "geometry": {"coordinates":[10.0262699127,48.3897399902],"type":"Point"}
}