{
  "type": "Feature",
  "properties": {
    "iso:country":"DE",
    "sg:address":"In der Au 9",
    "sg:city":"Langenenslingen",
    "sg:phone":"+49 7376/449",
    "sg:postcode":"88515",
    "sg:province":"Baden-W\u00fcrttemberg",
    "wof:name":"Heinz Justus",
    "wof:placetype":"venue"
},
  "geometry": {"coordinates":[9.372234,48.146992],"type":"Point"}
}