{
  "type": "Feature",
  "properties": {
    "iso:country":"DE",
    "sg:address":"Brunhildestr. 18",
    "sg:city":"Bad Oeynhausen",
    "sg:phone":"+49 5731/9008",
    "sg:postcode":"32547",
    "sg:province":"Nordrhein-Westfalen",
    "wof:name":"Gutmann Schaumstoffe Gmbh",
    "wof:placetype":"venue"
},
  "geometry": {"coordinates":[8.812982,52.196835],"type":"Point"}
}