{
  "type": "Feature",
  "properties": {
    "iso:country":"DE",
    "sg:address":"Hauptstr. 22",
    "sg:city":"Schnabelwaid",
    "sg:phone":"+49 9270/241",
    "sg:postcode":"91289",
    "sg:province":"Bayern",
    "wof:name":"Arno Hartmann",
    "wof:placetype":"venue"
},
  "geometry": {"coordinates":[11.584796,49.812885],"type":"Point"}
}