{
  "type": "Feature",
  "properties": {
    "iso:country":"DE",
    "sg:address":"Landgrafenstr. 31",
    "sg:city":"Bad Neuenahr-Ahrweiler",
    "sg:phone":"+49 2641/21550",
    "sg:postcode":"53474",
    "sg:province":"Rheinland-Pfalz",
    "wof:name":"Hemmer & M\u00fcller",
    "wof:placetype":"venue"
},
  "geometry": {"coordinates":[7.1449379921,50.5444946289],"type":"Point"}
}