{
  "type": "Feature",
  "properties": {
    "iso:country":"DE",
    "sg:address":"Liebknechtstr 33",
    "sg:city":"Stuttgart",
    "sg:phone":"+49 711/7811755",
    "sg:postcode":"70565",
    "sg:province":"Baden-W\u00fcrttemberg",
    "wof:name":"Astech Solutions Software Technologie Consulting Und Service Gmbh",
    "wof:placetype":"venue"
},
  "geometry": {"coordinates":[9.111166954,48.7246437073],"type":"Point"}
}