{
  "type": "Feature",
  "properties": {
    "iso:country":"DE",
    "sg:address":"Hamburger Str. 22",
    "sg:city":"Bargteheide",
    "sg:phone":"+49 4532/21616",
    "sg:postcode":"22941",
    "sg:province":"Schleswig-Holstein",
    "wof:name":"Both",
    "wof:placetype":"venue"
},
  "geometry": {"coordinates":[10.255976,53.725292],"type":"Point"}
}