{
  "type": "Feature",
  "properties": {
    "iso:country":"DE",
    "sg:address":"Rosenheimer Landstr. 60",
    "sg:city":"Ottobrunn",
    "sg:phone":"+49 89/6099074",
    "sg:postcode":"85521",
    "sg:province":"Bayern",
    "wof:name":"Call A Pizza Mayr & Baumann",
    "wof:placetype":"venue"
},
  "geometry": {"coordinates":[11.6624593735,48.0629005432],"type":"Point"}
}