{
  "type": "Feature",
  "properties": {
    "iso:country":"DE",
    "sg:address":"Auguste-Viktoria-Str. 118",
    "sg:city":"Berlin",
    "sg:postcode":"14193",
    "sg:province":"Berlin",
    "wof:name":"R-con Achtzehnte Verm\u00f6gensverwaltungs Gmbh",
    "wof:placetype":"venue"
},
  "geometry": {"coordinates":[13.290465,52.493435],"type":"Point"}
}