{
  "type": "Feature",
  "properties": {
    "iso:country":"DE",
    "sg:address":"Irmelastr. 5-7",
    "sg:city":"M\u00fcnchen",
    "sg:phone":"+49 89/4394416",
    "sg:postcode":"81825",
    "sg:province":"Bayern",
    "wof:name":"Josef Eckl Elektroanlagen Gmbh",
    "wof:placetype":"venue"
},
  "geometry": {"coordinates":[11.674575,48.118111],"type":"Point"}
}