{
  "type": "Feature",
  "properties": {
    "iso:country":"DE",
    "sg:address":"Wutachstr. 15",
    "sg:city":"Karlsruhe",
    "sg:postcode":"76199",
    "sg:province":"Baden-W\u00fcrttemberg",
    "wof:name":"Luxor - Hauser Gmbh & Co. Kg",
    "wof:placetype":"venue"
},
  "geometry": {"coordinates":[8.3937044144,48.9811096191],"type":"Point"}
}