{
  "type": "Feature",
  "properties": {
    "iso:country":"DE",
    "sg:address":"Weidenweg 3",
    "sg:city":"Edemissen",
    "sg:phone":"+49 5176/1383",
    "sg:postcode":"31234",
    "sg:province":"Niedersachsen",
    "wof:name":"Microfilm Sabine Christl-",
    "wof:placetype":"venue"
},
  "geometry": {"coordinates":[10.3025741577,52.3810920715],"type":"Point"}
}