{
  "type": "Feature",
  "properties": {
    "iso:country":"DE",
    "sg:address":"Sophienstr. 24",
    "sg:city":"Jena",
    "sg:phone":"+49 3641/443190",
    "sg:postcode":"07743",
    "sg:province":"Th\u00fcringen",
    "wof:name":"Dr. Med. Michael Winkler Arzt F\u00fcr Innere Medizin",
    "wof:placetype":"venue"
},
  "geometry": {"coordinates":[11.588932991,50.9333305359],"type":"Point"}
}