{
  "type": "Feature",
  "properties": {
    "iso:country":"DE",
    "sg:address":"N\u00fcrnberger Str. 14",
    "sg:city":"K\u00f6rle",
    "sg:phone":"+49 5665/94950",
    "sg:postcode":"34327",
    "sg:province":"Hessen",
    "wof:name":"Ing. Wilhelm Schmidt Inh. Dirk H\u00fchne E.k.",
    "wof:placetype":"venue"
},
  "geometry": {"coordinates":[9.5123586655,51.1733932495],"type":"Point"}
}