{
  "type": "Feature",
  "properties": {
    "iso:country":"DE",
    "sg:address":"Holler Landstr. 72a",
    "sg:city":"Oldenburg",
    "sg:phone":"+49 441/202268",
    "sg:postcode":"26135",
    "sg:province":"Niedersachsen",
    "wof:name":"J\u00fcrgen Meyer Metallbau Gmbh",
    "wof:placetype":"venue"
},
  "geometry": {"coordinates":[8.2372398376,53.1379318237],"type":"Point"}
}