{
  "type": "Feature",
  "properties": {
    "iso:country":"DE",
    "sg:address":"Langgasse 16",
    "sg:city":"Lauterbach",
    "sg:phone":"+49 6641/96430",
    "sg:postcode":"36341",
    "sg:province":"Hessen",
    "wof:name":"Hamburg-mannheimer Versicherungs Ag",
    "wof:placetype":"venue"
},
  "geometry": {"coordinates":[9.3976078033,50.6353378296],"type":"Point"}
}