{
  "type": "Feature",
  "properties": {
    "iso:country":"DE",
    "sg:address":"Jahnstr. 9",
    "sg:city":"Niederwerrn",
    "sg:phone":"+49 9721/749444",
    "sg:postcode":"97464",
    "sg:province":"Bayern",
    "wof:name":"H. H\u00e4usler",
    "wof:placetype":"venue"
},
  "geometry": {"coordinates":[10.1758680344,50.0610313416],"type":"Point"}
}