{
  "type": "Feature",
  "properties": {
    "iso:country":"DE",
    "sg:address":"Marktplatz 1",
    "sg:city":"Karlstadt",
    "sg:phone":"+49 9353/3770",
    "sg:postcode":"97753",
    "sg:province":"Bayern",
    "wof:name":"Restaurant Ratskeller",
    "wof:placetype":"venue"
},
  "geometry": {"coordinates":[9.7640237808,49.9614982605],"type":"Point"}
}