{
  "type": "Feature",
  "properties": {
    "iso:country":"DE",
    "sg:address":"Aachener Str. 269",
    "sg:city":"M\u00f6nchengladbach",
    "sg:phone":"+49 2161/837099",
    "sg:postcode":"41061",
    "sg:province":"Nordrhein-Westfalen",
    "wof:name":"Pizza-welt",
    "wof:placetype":"venue"
},
  "geometry": {"coordinates":[6.4177241325,51.1874771118],"type":"Point"}
}