{
  "type": "Feature",
  "properties": {
    "iso:country":"DE",
    "sg:address":"Kanalweg 27",
    "sg:city":"Nordhorn",
    "sg:phone":"+49 5921/5253",
    "sg:postcode":"48529",
    "sg:province":"Niedersachsen",
    "wof:name":"Schulten",
    "wof:placetype":"venue"
},
  "geometry": {"coordinates":[7.0613069534,52.4219207764],"type":"Point"}
}