{
  "type": "Feature",
  "properties": {
    "iso:country":"DE",
    "sg:address":"Neust\u00e4dter Str. 26",
    "sg:city":"Lenzkirch",
    "sg:phone":"+49 7653/318",
    "sg:postcode":"79853",
    "sg:province":"Baden-W\u00fcrttemberg",
    "wof:name":"Hermann Feser",
    "wof:placetype":"venue"
},
  "geometry": {"coordinates":[8.227739,47.874954],"type":"Point"}
}