{
  "type": "Feature",
  "properties": {
    "iso:country":"DE",
    "sg:address":"Dr.-Josef-Holik-Str. 13",
    "sg:city":"Ochsenfurt",
    "sg:phone":"+49 9331/2534",
    "sg:postcode":"97199",
    "sg:province":"Bayern",
    "wof:name":"Gesellschaft F\u00fcr Lagereibetriebe Mbh",
    "wof:placetype":"venue"
},
  "geometry": {"coordinates":[10.079991,49.664642],"type":"Point"}
}