{
  "type": "Feature",
  "properties": {
    "iso:country":"DE",
    "sg:address":"Geestensether Str. 40",
    "sg:city":"Schiffdorf",
    "sg:phone":"+49 4703/268",
    "sg:postcode":"27619",
    "sg:province":"Niedersachsen",
    "wof:name":"W. Schmidt",
    "wof:placetype":"venue"
},
  "geometry": {"coordinates":[8.743642807,53.5188179016],"type":"Point"}
}