{
  "type": "Feature",
  "properties": {
    "iso:country":"DE",
    "sg:address":"Am Wasserturm 53",
    "sg:city":"Coesfeld",
    "sg:phone":"+49 2541/5155",
    "sg:postcode":"48653",
    "sg:province":"Nordrhein-Westfalen",
    "wof:name":"Ronglewicz Gmbh",
    "wof:placetype":"venue"
},
  "geometry": {"coordinates":[7.161355,51.929325],"type":"Point"}
}