{
  "type": "Feature",
  "properties": {
    "iso:country":"DE",
    "sg:address":"Friedenheimer Str. 92",
    "sg:city":"M\u00fcnchen",
    "sg:phone":"+49 89/561476",
    "sg:postcode":"80686",
    "sg:province":"Bayern",
    "wof:name":"R. Schamper Architekt",
    "wof:placetype":"venue"
},
  "geometry": {"coordinates":[11.509121,48.134583],"type":"Point"}
}