{
  "type": "Feature",
  "properties": {
    "iso:country":"DE",
    "sg:address":"Erlenweg 2",
    "sg:city":"Petershagen",
    "sg:phone":"+49 5707/2156",
    "sg:postcode":"32469",
    "sg:province":"Nordrhein-Westfalen",
    "wof:name":"Maiwald Immobilien Gmbh",
    "wof:placetype":"venue"
},
  "geometry": {"coordinates":[8.956908226,52.374420166],"type":"Point"}
}