{
  "type": "Feature",
  "properties": {
    "iso:country":"DE",
    "sg:address":"Klosterbergstr. 40",
    "sg:city":"Bonn",
    "sg:phone":"+49 228",
    "sg:postcode":"53177",
    "sg:province":"Nordrhein-Westfalen",
    "wof:name":"Edv-service Beatrix Kr\u00e4mer Und Frank Spinat Gbr",
    "wof:placetype":"venue"
},
  "geometry": {"coordinates":[7.1565628052,50.6711463928],"type":"Point"}
}