{
  "type": "Feature",
  "properties": {
    "iso:country":"DE",
    "sg:address":"Prinzregentenplatz 19",
    "sg:city":"M\u00fcnchen",
    "sg:phone":"+49 89/477838",
    "sg:postcode":"81675",
    "sg:province":"Bayern",
    "wof:name":"Sehr Fotografie",
    "wof:placetype":"venue"
},
  "geometry": {"coordinates":[11.6072597504,48.139289856],"type":"Point"}
}