{
  "type": "Feature",
  "properties": {
    "iso:country":"DE",
    "sg:address":"Burgfelder Str. 26",
    "sg:city":"Bad Zwischenahn",
    "sg:postcode":"26160",
    "sg:province":"Niedersachsen",
    "wof:name":"Michels Fliesen Meisterbetrieb E. K.",
    "wof:placetype":"venue"
},
  "geometry": {"coordinates":[7.9848470688,53.15858078],"type":"Point"}
}