{
  "type": "Feature",
  "properties": {
    "iso:country":"DE",
    "sg:address":"M\u00fcnchner Str. 7",
    "sg:city":"Bad F\u00fcssing",
    "sg:phone":"+49 8531/972525",
    "sg:postcode":"94072",
    "sg:province":"Bayern",
    "wof:name":"H. Eller",
    "wof:placetype":"venue"
},
  "geometry": {"coordinates":[13.307169,48.34906],"type":"Point"}
}