{
  "type": "Feature",
  "properties": {
    "iso:country":"DE",
    "sg:address":"Im Bohlgarten 8",
    "sg:city":"Schwerte",
    "sg:phone":"+49 2304/15543",
    "sg:postcode":"58239",
    "sg:province":"Nordrhein-Westfalen",
    "wof:name":"J\u00f6rg Andexer",
    "wof:placetype":"venue"
},
  "geometry": {"coordinates":[7.5555391312,51.4446754456],"type":"Point"}
}