{
  "type": "Feature",
  "properties": {
    "iso:country":"DE",
    "sg:address":"Robert-Bosch-Str. 30 Sprendlingen",
    "sg:city":"Dreieich",
    "sg:phone":"+49 6103/373612",
    "sg:postcode":"63303",
    "sg:province":"Hessen",
    "wof:name":"Landgraf Gmbh & Co. Kg",
    "wof:placetype":"venue"
},
  "geometry": {"coordinates":[8.714835,50.001701],"type":"Point"}
}