{
  "type": "Feature",
  "properties": {
    "iso:country":"DE",
    "sg:address":"Ei\u00dfendorfer Str. 21",
    "sg:city":"Hamburg",
    "sg:phone":"+49 40/7664523",
    "sg:postcode":"21073",
    "sg:province":"Hamburg",
    "wof:name":"Grillhaus",
    "wof:placetype":"venue"
},
  "geometry": {"coordinates":[9.9754056931,53.4600982666],"type":"Point"}
}