{
  "type": "Feature",
  "properties": {
    "iso:country":"DE",
    "sg:address":"Leipziger Str. 62",
    "sg:city":"Achim",
    "sg:phone":"+49 4202/882073",
    "sg:postcode":"28832",
    "sg:province":"Niedersachsen",
    "wof:name":"First Trading Service Warenhandels Gmbh",
    "wof:placetype":"venue"
},
  "geometry": {"coordinates":[9.0450153351,53.0203437805],"type":"Point"}
}