{
  "type": "Feature",
  "properties": {
    "iso:country":"DE",
    "sg:address":"Freihofstr. 2",
    "sg:city":"Dortmund",
    "sg:phone":"+49 231/337146",
    "sg:postcode":"44359",
    "sg:province":"Nordrhein-Westfalen",
    "wof:name":"Cafe Chaos",
    "wof:placetype":"venue"
},
  "geometry": {"coordinates":[7.3829479218,51.5744552612],"type":"Point"}
}