{
  "type": "Feature",
  "properties": {
    "iso:country":"DE",
    "sg:address":"Schulstr. 7",
    "sg:city":"Bammental",
    "sg:phone":"+49 6223/47572",
    "sg:postcode":"69245",
    "sg:province":"Baden-W\u00fcrttemberg",
    "wof:name":"Hermann Zimmermann",
    "wof:placetype":"venue"
},
  "geometry": {"coordinates":[8.7772474289,49.3469200134],"type":"Point"}
}