{
  "type": "Feature",
  "properties": {
    "iso:country":"DE",
    "sg:address":"Friedensstr. 31",
    "sg:city":"Schwerte",
    "sg:phone":"+49 2304/18088",
    "sg:postcode":"58239",
    "sg:province":"Nordrhein-Westfalen",
    "wof:name":"Dat Pr\u00fcf- Und Sch\u00e4tzungsstelle",
    "wof:placetype":"venue"
},
  "geometry": {"coordinates":[7.565466,51.440384],"type":"Point"}
}