{
  "type": "Feature",
  "properties": {
    "iso:country":"DE",
    "sg:address":"K\u00fcrner Str. 1",
    "sg:city":"Bernhardswald",
    "sg:phone":"+49 9463/1263",
    "sg:postcode":"93170",
    "sg:province":"Bayern",
    "wof:name":"Sch\u00f6pperl & Rieger",
    "wof:placetype":"venue"
},
  "geometry": {"coordinates":[12.254754,49.131165],"type":"Point"}
}