{
  "type": "Feature",
  "properties": {
    "iso:country":"DE",
    "sg:address":"Auf der Rotenburg 22",
    "sg:city":"Lengerich",
    "sg:postcode":"49525",
    "sg:province":"Nordrhein-Westfalen",
    "wof:name":"Holland-qualit\u00e4ts-haus Gmbh",
    "wof:placetype":"venue"
},
  "geometry": {"coordinates":[7.8577489853,52.1723976135],"type":"Point"}
}