{
  "type": "Feature",
  "properties": {
    "iso:country":"DE",
    "sg:address":"Jebbenberg 41a",
    "sg:city":"Rellingen",
    "sg:phone":"+49 4101/209194",
    "sg:postcode":"25462",
    "sg:province":"Schleswig-Holstein",
    "wof:name":"Malereibetrieb Krahl & Timm Gmbh",
    "wof:placetype":"venue"
},
  "geometry": {"coordinates":[9.84909,53.660374],"type":"Point"}
}