{
  "type": "Feature",
  "properties": {
    "iso:country":"DE",
    "sg:address":"An der Br\u00fccke 11",
    "sg:city":"Leipzig",
    "sg:phone":"+49 341/5904235",
    "sg:postcode":"04178",
    "sg:province":"Sachsen",
    "wof:name":"K.s.a. Bandrock Gbr",
    "wof:placetype":"venue"
},
  "geometry": {"coordinates":[12.265755,51.353844],"type":"Point"}
}