{
  "type": "Feature",
  "properties": {
    "iso:country":"DE",
    "sg:address":"Turmstr. 16",
    "sg:city":"Gladenbach",
    "sg:phone":"+49 6462/1544",
    "sg:postcode":"35075",
    "sg:province":"Hessen",
    "wof:name":"O. U. E. Wagner",
    "wof:placetype":"venue"
},
  "geometry": {"coordinates":[8.5676202774,50.7539710999],"type":"Point"}
}