{
  "type": "Feature",
  "properties": {
    "iso:country":"DE",
    "sg:address":"Zum Brandb\u00fchl 19",
    "sg:city":"\u00dcberlingen-Andelshofen",
    "sg:phone":"+49 7551",
    "sg:postcode":"88662",
    "sg:province":"Baden-W\u00fcrttemberg",
    "wof:name":"Hotel Sonnenb\u00fchl Garni",
    "wof:placetype":"venue"
},
  "geometry": {"coordinates":[9.1851119995,47.7795295715],"type":"Point"}
}