{
  "type": "Feature",
  "properties": {
    "iso:country":"DE",
    "sg:address":"Vorhofstr. 34",
    "sg:city":"Ludwigsburg",
    "sg:phone":"+49 7141/290371",
    "sg:postcode":"71640",
    "sg:province":"Baden-W\u00fcrttemberg",
    "wof:name":"Oliver Haug Holzbau",
    "wof:placetype":"venue"
},
  "geometry": {"coordinates":[9.231423378,48.8934555054],"type":"Point"}
}