{
  "type": "Feature",
  "properties": {
    "iso:country":"DE",
    "sg:address":"Donauw\u00f6rther Str. 61",
    "sg:city":"Augsburg",
    "sg:phone":"+49 821/419383",
    "sg:postcode":"86154",
    "sg:province":"Bayern",
    "wof:name":"Apotheke Hubertus Am B\u00e4renwirt",
    "wof:placetype":"venue"
},
  "geometry": {"coordinates":[10.88048,48.386101],"type":"Point"}
}