{
  "type": "Feature",
  "properties": {
    "iso:country":"DE",
    "sg:address":"Illungshofstr. 21",
    "sg:city":"M\u00fcnchen",
    "sg:phone":"+49 89/35663164",
    "sg:postcode":"80807",
    "sg:province":"Bayern",
    "wof:name":"Delphin-apotheke Eva Fr\u00f6hlich-sporer E. K.",
    "wof:placetype":"venue"
},
  "geometry": {"coordinates":[11.57308,48.186657],"type":"Point"}
}