{
  "type": "Feature",
  "properties": {
    "iso:country":"DE",
    "sg:address":"An der Kammerschleuse 7",
    "sg:city":"Mannheim",
    "sg:phone":"+49 621/311001",
    "sg:postcode":"68169",
    "sg:province":"Baden-W\u00fcrttemberg",
    "wof:name":"Nowag Gmbh",
    "wof:placetype":"venue"
},
  "geometry": {"coordinates":[8.449213028,49.5110206604],"type":"Point"}
}