{
  "type": "Feature",
  "properties": {
    "iso:country":"DE",
    "sg:address":"Weilertalweg 2 b",
    "sg:city":"St\u00fchlingen",
    "sg:phone":"+49 7744/6520",
    "sg:postcode":"79780",
    "sg:province":"Baden-W\u00fcrttemberg",
    "wof:name":"B\u00e4rbel Westphal Hebamme",
    "wof:placetype":"venue"
},
  "geometry": {"coordinates":[8.442399,47.747894],"type":"Point"}
}