{
  "type": "Feature",
  "properties": {
    "iso:country":"DE",
    "sg:address":"Seu\u00dflitzer Str. 12a",
    "sg:city":"Diesbar-Seu\u00dflitz",
    "sg:phone":"+49 35267/50781",
    "sg:postcode":"01612",
    "sg:province":"Sachsen",
    "wof:name":"Carmen Zocher",
    "wof:placetype":"venue"
},
  "geometry": {"coordinates":[13.3953895569,51.2980995178],"type":"Point"}
}