{
  "type": "Feature",
  "properties": {
    "iso:country":"DE",
    "sg:address":"Lessingstr. 28",
    "sg:city":"Saarbr\u00fccken",
    "sg:phone":"+49 681/61723",
    "sg:postcode":"66121",
    "sg:province":"Saarland",
    "wof:name":"Miroslav Volf Architekt",
    "wof:placetype":"venue"
},
  "geometry": {"coordinates":[7.009988,49.228756],"type":"Point"}
}