{
  "type": "Feature",
  "properties": {
    "iso:country":"DE",
    "sg:address":"L\u00fctt D\u00f6rp 8",
    "sg:city":"Winnert",
    "sg:phone":"+49 4845/916",
    "sg:postcode":"25887",
    "sg:province":"Schleswig-Holstein",
    "wof:name":"K. Wok\u00f6ck",
    "wof:placetype":"venue"
},
  "geometry": {"coordinates":[9.204758,54.431896],"type":"Point"}
}