{
  "type": "Feature",
  "properties": {
    "iso:country":"DE",
    "sg:address":"Hauptstr. 4",
    "sg:city":"B\u00fchlertann",
    "sg:phone":"+49 4979/736011",
    "sg:postcode":"74424",
    "sg:province":"Baden-W\u00fcrttemberg",
    "wof:name":"Raiffeisenbank B\u00fchlertann Eg",
    "wof:placetype":"venue"
},
  "geometry": {"coordinates":[9.909842,49.040703],"type":"Point"}
}