{
  "type": "Feature",
  "properties": {
    "iso:country":"DE",
    "sg:address":"Auf der Burg 3",
    "sg:city":"Medebach",
    "sg:phone":"+49 2982/207",
    "sg:postcode":"59964",
    "sg:province":"Nordrhein-Westfalen",
    "wof:name":"Friedrich Becker Jun.",
    "wof:placetype":"venue"
},
  "geometry": {"coordinates":[8.703077,51.197292],"type":"Point"}
}