{
  "type": "Feature",
  "properties": {
    "iso:country":"DE",
    "sg:address":"Wilischstr. 5",
    "sg:city":"Dresden",
    "sg:phone":"+49 351/2512071",
    "sg:postcode":"01279",
    "sg:province":"Sachsen",
    "wof:name":"Frank Wie\u00dfner",
    "wof:placetype":"venue"
},
  "geometry": {"coordinates":[13.817996,51.030331],"type":"Point"}
}