{
  "type": "Feature",
  "properties": {
    "iso:country":"DE",
    "sg:address":"Hauptstr. 37",
    "sg:city":"Kettig",
    "sg:phone":"+49 2637/8327",
    "sg:postcode":"56220",
    "sg:province":"Rheinland-Pfalz",
    "wof:name":"Michael M\u00fcller",
    "wof:placetype":"venue"
},
  "geometry": {"coordinates":[7.4602718353,50.39585495],"type":"Point"}
}