{
  "type": "Feature",
  "properties": {
    "iso:country":"DE",
    "sg:address":"Rudolf-Breitscheid-Str. 5",
    "sg:city":"Gerbstedt",
    "sg:phone":"+49 34783/29287",
    "sg:postcode":"06347",
    "sg:province":"Sachsen-Anhalt",
    "wof:name":"G. Heine",
    "wof:placetype":"venue"
},
  "geometry": {"coordinates":[11.628139,51.633026],"type":"Point"}
}