{
  "type": "Feature",
  "properties": {
    "iso:country":"DE",
    "sg:address":"Heimertsberg 22",
    "sg:city":"Mechernich",
    "sg:phone":"+49 2443/5144",
    "sg:postcode":"53894",
    "sg:province":"Nordrhein-Westfalen",
    "wof:name":"H. Schmitz",
    "wof:placetype":"venue"
},
  "geometry": {"coordinates":[6.6190748215,50.6270561218],"type":"Point"}
}