{
  "type": "Feature",
  "properties": {
    "iso:country":"DE",
    "sg:address":"Backhausstr. 31",
    "sg:city":"Horrweiler",
    "sg:phone":"+49 6727/332",
    "sg:postcode":"55457",
    "sg:province":"Rheinland-Pfalz",
    "wof:name":"Karl Gr\u00fcnler",
    "wof:placetype":"venue"
},
  "geometry": {"coordinates":[7.9656429291,49.8983612061],"type":"Point"}
}