{
  "type": "Feature",
  "properties": {
    "iso:country":"DE",
    "sg:address":"G\u00f6pfersgr\u00fcn 60",
    "sg:city":"Wunsiedel",
    "sg:phone":"+49 9232/3818",
    "sg:postcode":"95632",
    "sg:province":"Bayern",
    "wof:name":"Winfried Eberl",
    "wof:placetype":"venue"
},
  "geometry": {"coordinates":[12.064683,50.058083],"type":"Point"}
}