{
  "type": "Feature",
  "properties": {
    "iso:country":"DE",
    "sg:address":"Daimlerstr. 3",
    "sg:city":"T\u00fcbingen",
    "sg:phone":"+49 7071/81695",
    "sg:postcode":"72074",
    "sg:province":"Baden-W\u00fcrttemberg",
    "wof:name":"Dr. Med. Thorgerd Linca",
    "wof:placetype":"venue"
},
  "geometry": {"coordinates":[9.0784416199,48.5292243958],"type":"Point"}
}