{
  "type": "Feature",
  "properties": {
    "iso:country":"DE",
    "sg:address":"Waschleither Str. 8",
    "sg:city":"Beierfeld",
    "sg:phone":"+49 3774/62026",
    "sg:postcode":"08340",
    "sg:province":"Sachsen",
    "wof:name":"Sabine Kraus",
    "wof:placetype":"venue"
},
  "geometry": {"coordinates":[12.7905979156,50.5629768372],"type":"Point"}
}