{
  "type": "Feature",
  "properties": {
    "iso:country":"DE",
    "sg:address":"Donaustaufer Str. 118",
    "sg:city":"Regensburg",
    "sg:postcode":"93059",
    "sg:province":"Bayern",
    "wof:name":"Aldi Gmbh & Co. Kg",
    "wof:placetype":"venue"
},
  "geometry": {"coordinates":[12.1199350357,49.0289802551],"type":"Point"}
}