{
  "type": "Feature",
  "properties": {
    "iso:country":"DE",
    "sg:address":"Johannesstr. 3a",
    "sg:city":"Stuttgart",
    "sg:phone":"+49 711/625001",
    "sg:postcode":"70176",
    "sg:province":"Baden-W\u00fcrttemberg",
    "wof:name":"Red. Mitteilungen D. Inter.- Vereinigung F. Theoretische U.",
    "wof:placetype":"venue"
},
  "geometry": {"coordinates":[9.1638889313,48.7739944458],"type":"Point"}
}