{
  "type": "Feature",
  "properties": {
    "iso:country":"DE",
    "sg:address":"Karl-Liebknecht-Str. 31",
    "sg:city":"Doberlug-Kirchhain",
    "sg:phone":"+49 35322/5910",
    "sg:postcode":"03253",
    "sg:province":"Brandenburg",
    "wof:name":"Harbs Und Kollegen Rechtsanw\u00e4lte",
    "wof:placetype":"venue"
},
  "geometry": {"coordinates":[13.5638017654,51.6288757324],"type":"Point"}
}