{
  "type": "Feature",
  "properties": {
    "iso:country":"DE",
    "sg:address":"Offenbacher Landstra\u00dfe 70",
    "sg:city":"Frankfurt",
    "sg:phone":"+49 69/625332",
    "sg:postcode":"60559",
    "sg:province":"Brandenburg",
    "wof:name":"Lk Reisen Gmbh",
    "wof:placetype":"venue"
},
  "geometry": {"coordinates":[8.699291,50.101826],"type":"Point"}
}