{
  "type": "Feature",
  "properties": {
    "iso:country":"DE",
    "sg:address":"Hindenburgstr. 21a",
    "sg:city":"Garmisch-Partenkirchen",
    "sg:phone":"+49 8821/76167",
    "sg:postcode":"82467",
    "sg:province":"Bayern",
    "wof:name":"W. Krieg Und Gertrud Haydn",
    "wof:placetype":"venue"
},
  "geometry": {"coordinates":[11.1052742004,47.4963722229],"type":"Point"}
}