{
  "type": "Feature",
  "properties": {
    "iso:country":"DE",
    "sg:address":"Lohen 30",
    "sg:city":"Thalm\u00e4ssing",
    "sg:phone":"+49 9173/1312",
    "sg:postcode":"91177",
    "sg:province":"Bayern",
    "wof:name":"R. Forchheimer",
    "wof:placetype":"venue"
},
  "geometry": {"coordinates":[11.2781362534,49.1096763611],"type":"Point"}
}