{
  "type": "Feature",
  "properties": {
    "iso:country":"DE",
    "sg:address":"Etkar-Andre-Str. 45",
    "sg:city":"Rostock",
    "sg:phone":"+49 381/83253",
    "sg:postcode":"18069",
    "sg:province":"Mecklenburg-Vorpommern",
    "wof:name":"J\u00fcrgen Staben",
    "wof:placetype":"venue"
},
  "geometry": {"coordinates":[12.067366,54.097961],"type":"Point"}
}