{
  "type": "Feature",
  "properties": {
    "iso:country":"DE",
    "sg:address":"Eichkamp 13",
    "sg:city":"Oldenburg",
    "sg:phone":"+49 441/955700",
    "sg:postcode":"26131",
    "sg:province":"Niedersachsen",
    "wof:name":"Ebsen & Partner Steuerberatungs-gmbh",
    "wof:placetype":"venue"
},
  "geometry": {"coordinates":[8.1962985992,53.1272544861],"type":"Point"}
}