{
  "type": "Feature",
  "properties": {
    "iso:country":"DE",
    "sg:address":"Drei-Br\u00fccken-Weg 4",
    "sg:city":"Garrel",
    "sg:phone":"+49 4495/282",
    "sg:postcode":"49681",
    "sg:province":"Niedersachsen",
    "wof:name":"Wilhelm Einhaus",
    "wof:placetype":"venue"
},
  "geometry": {"coordinates":[7.946644783,52.9171524048],"type":"Point"}
}