{
  "type": "Feature",
  "properties": {
    "iso:country":"DE",
    "sg:address":"Husumer Str. 94",
    "sg:city":"Bielefeld",
    "sg:phone":"+49 521/76912",
    "sg:postcode":"33729",
    "sg:province":"Nordrhein-Westfalen",
    "wof:name":"W. Strangh\u00f6ner",
    "wof:placetype":"venue"
},
  "geometry": {"coordinates":[8.5984582901,52.0784568787],"type":"Point"}
}