{
  "type": "Feature",
  "properties": {
    "iso:country":"DE",
    "sg:address":"79356",
    "sg:city":"Eichstetten",
    "sg:postcode":"79356",
    "sg:province":"Baden-W\u00fcrttemberg",
    "wof:name":"Raiffeisen-volksbank Kaiserstuhl-march Eg",
    "wof:placetype":"venue"
},
  "geometry": {"coordinates":[7.72887,48.09343],"type":"Point"}
}