{
  "type": "Feature",
  "properties": {
    "iso:country":"DE",
    "sg:address":"Bodmanstr. 17",
    "sg:city":"Kempten",
    "sg:phone":"+49 831/12200",
    "sg:postcode":"87439",
    "sg:province":"Bayern",
    "wof:name":"M. Unglert Immobilienmakler",
    "wof:placetype":"venue"
},
  "geometry": {"coordinates":[10.3082923889,47.7249526978],"type":"Point"}
}