{
  "type": "Feature",
  "properties": {
    "iso:country":"DE",
    "sg:address":"Stuttgarter Str. 175",
    "sg:city":"Fellbach",
    "sg:phone":"+49 711/5281484",
    "sg:postcode":"70734",
    "sg:province":"Baden-W\u00fcrttemberg",
    "wof:name":"Ursula Neuwirth",
    "wof:placetype":"venue"
},
  "geometry": {"coordinates":[9.253742,48.809933],"type":"Point"}
}