{
  "type": "Feature",
  "properties": {
    "iso:country":"DE",
    "sg:address":"Welzheimer Str. 15",
    "sg:city":"Stuttgart",
    "sg:phone":"+49 711/486892",
    "sg:postcode":"70188",
    "sg:province":"Baden-W\u00fcrttemberg",
    "wof:name":"Sabine Sperling",
    "wof:placetype":"venue"
},
  "geometry": {"coordinates":[9.216028,48.782928],"type":"Point"}
}