{
  "type": "Feature",
  "properties": {
    "iso:country":"DE",
    "sg:address":"Schenkweg 10",
    "sg:city":"Zinna",
    "sg:phone":"+49 3421/712716",
    "sg:postcode":"04860",
    "sg:province":"Sachsen",
    "wof:name":"Beth & Behrens Gmbh",
    "wof:placetype":"venue"
},
  "geometry": {"coordinates":[12.9694242477,51.5751991272],"type":"Point"}
}