{
  "type": "Feature",
  "properties": {
    "iso:country":"DE",
    "sg:address":"Birkenallee 119",
    "sg:city":"Osnabr\u00fcck",
    "sg:phone":"+49 5405/1018",
    "sg:postcode":"49076",
    "sg:province":"Niedersachsen",
    "wof:name":"Tankstellen W. Riechel Gmbh",
    "wof:placetype":"venue"
},
  "geometry": {"coordinates":[7.955968,52.274269],"type":"Point"}
}