{
  "type": "Feature",
  "properties": {
    "iso:country":"DE",
    "sg:address":"Br\u00fcnseer Str. 5",
    "sg:city":"Harburg",
    "sg:phone":"+49 9080/597",
    "sg:postcode":"86655",
    "sg:province":"Bayern",
    "wof:name":"Harburger Schlo\u00dfhexen Margit Huber",
    "wof:placetype":"venue"
},
  "geometry": {"coordinates":[10.7106809616,48.7688484192],"type":"Point"}
}