{
  "type": "Feature",
  "properties": {
    "iso:country":"DE",
    "sg:address":"Grashoffstr. 37 a",
    "sg:city":"Bremerhaven",
    "sg:phone":"+49 471/34409",
    "sg:postcode":"27570",
    "sg:province":"Bremen",
    "wof:name":"B. Schnackenberg",
    "wof:placetype":"venue"
},
  "geometry": {"coordinates":[8.596979,53.533054],"type":"Point"}
}