{
  "type": "Feature",
  "properties": {
    "iso:country":"DE",
    "sg:address":"Mozartstr. 20",
    "sg:city":"Pirmasens",
    "sg:phone":"+49 6331/70885",
    "sg:postcode":"66954",
    "sg:province":"Rheinland-Pfalz",
    "wof:name":"C. Adolph",
    "wof:placetype":"venue"
},
  "geometry": {"coordinates":[7.5998339653,49.1984596252],"type":"Point"}
}