{
  "type": "Feature",
  "properties": {
    "iso:country":"DE",
    "sg:address":"Schwerter Str. 159",
    "sg:city":"Hagen",
    "sg:phone":"+49 2331/63957",
    "sg:postcode":"58099",
    "sg:province":"Nordrhein-Westfalen",
    "wof:name":"Ragtime",
    "wof:placetype":"venue"
},
  "geometry": {"coordinates":[7.4725608826,51.3984031677],"type":"Point"}
}