{
  "type": "Feature",
  "properties": {
    "iso:country":"DE",
    "sg:address":"Rainweg 10",
    "sg:city":"Hamburg",
    "sg:phone":"+49 40/4804262",
    "sg:postcode":"20249",
    "sg:province":"Hamburg",
    "wof:name":"Wolfram Hubert Rechtsanwalt",
    "wof:placetype":"venue"
},
  "geometry": {"coordinates":[9.9915218353,53.5863418579],"type":"Point"}
}