{
  "type": "Feature",
  "properties": {
    "iso:country":"DE",
    "sg:address":"Nelkenstr. 16",
    "sg:city":"Recke",
    "sg:phone":"+49 5453/1704",
    "sg:postcode":"49509",
    "sg:province":"Nordrhein-Westfalen",
    "wof:name":"Anke St\u00fcrenburg",
    "wof:placetype":"venue"
},
  "geometry": {"coordinates":[7.714177,52.374813],"type":"Point"}
}