{
  "type": "Feature",
  "properties": {
    "iso:country":"DE",
    "sg:address":"Leonrodplatz 2",
    "sg:city":"M\u00fcnchen",
    "sg:phone":"+49 89/185813",
    "sg:postcode":"80636",
    "sg:province":"Bayern",
    "wof:name":"Volker Beck",
    "wof:placetype":"venue"
},
  "geometry": {"coordinates":[11.547057,48.158752],"type":"Point"}
}