{
  "type": "Feature",
  "properties": {
    "iso:country":"DE",
    "sg:address":"Dorfstr. 40",
    "sg:city":"Gernsbach",
    "sg:phone":"+49 7224/7477",
    "sg:postcode":"76593",
    "sg:province":"Baden-W\u00fcrttemberg",
    "wof:name":"Heinrich Fortenbacher",
    "wof:placetype":"venue"
},
  "geometry": {"coordinates":[8.34359,48.743359],"type":"Point"}
}