{
  "type": "Feature",
  "properties": {
    "iso:country":"DE",
    "sg:address":"Glockengie\u00dfereistr. 11",
    "sg:city":"Apolda",
    "sg:phone":"+49 3644/563395",
    "sg:postcode":"99510",
    "sg:province":"Th\u00fcringen",
    "wof:name":"Bernd Rost",
    "wof:placetype":"venue"
},
  "geometry": {"coordinates":[11.511283,51.027672],"type":"Point"}
}