{
  "type": "Feature",
  "properties": {
    "iso:country":"DE",
    "sg:address":"Schlo\u00dfstr. 10-12",
    "sg:city":"Spenge",
    "sg:postcode":"32139",
    "sg:province":"Nordrhein-Westfalen",
    "wof:name":"Kurt Behm Gmbh",
    "wof:placetype":"venue"
},
  "geometry": {"coordinates":[8.47488,52.137157],"type":"Point"}
}