{
  "type": "Feature",
  "properties": {
    "iso:country":"DE",
    "sg:address":"Plan 94",
    "sg:city":"Gro\u00dfenlupnitz",
    "sg:phone":"+49 36920/296",
    "sg:postcode":"99819",
    "sg:province":"Th\u00fcringen",
    "wof:name":"S. Wolf",
    "wof:placetype":"venue"
},
  "geometry": {"coordinates":[10.40799,50.992012],"type":"Point"}
}