{
  "type": "Feature",
  "properties": {
    "iso:country":"DE",
    "sg:address":"Richardstr. 147",
    "sg:city":"D\u00fcsseldorf",
    "sg:phone":"+49 211/216269",
    "sg:postcode":"40231",
    "sg:province":"Nordrhein-Westfalen",
    "wof:name":"Peter Kruhm Anlageberater",
    "wof:placetype":"venue"
},
  "geometry": {"coordinates":[6.836868763,51.2119407654],"type":"Point"}
}