{
  "type": "Feature",
  "properties": {
    "iso:country":"DE",
    "sg:address":"Lindenstr. 40",
    "sg:city":"Saarlouis",
    "sg:phone":"+49 6831/81333",
    "sg:postcode":"66740",
    "sg:province":"Saarland",
    "wof:name":"A. Gergen",
    "wof:placetype":"venue"
},
  "geometry": {"coordinates":[6.7483701706,49.3307342529],"type":"Point"}
}