{
  "type": "Feature",
  "properties": {
    "iso:country":"DE",
    "sg:address":"Eckdahl 33",
    "sg:city":"Buxtehude",
    "sg:postcode":"21614",
    "sg:province":"Niedersachsen",
    "wof:name":"Esbo Geb\u00e4udereinigung Und Gro\u00dfhandels Gmbh",
    "wof:placetype":"venue"
},
  "geometry": {"coordinates":[9.6737146378,53.4575271606],"type":"Point"}
}