{
  "type": "Feature",
  "properties": {
    "iso:country":"DE",
    "sg:address":"Vorderstr. 10",
    "sg:city":"Stockstadt",
    "sg:phone":"+49 6158/83290",
    "sg:postcode":"64589",
    "sg:province":"Hessen",
    "wof:name":"Artur Schneider",
    "wof:placetype":"venue"
},
  "geometry": {"coordinates":[8.46681,49.811031],"type":"Point"}
}