{
  "type": "Feature",
  "properties": {
    "iso:country":"DE",
    "sg:address":"Schwalbenweg 1",
    "sg:city":"W\u00f6rthsee",
    "sg:postcode":"82237",
    "sg:province":"Bayern",
    "wof:name":"J. B. Martin Deutschland Gmbh",
    "wof:placetype":"venue"
},
  "geometry": {"coordinates":[11.200720787,48.082447052],"type":"Point"}
}