{
  "type": "Feature",
  "properties": {
    "iso:country":"DE",
    "sg:address":"Dockenhudener Chaussee 24 a",
    "sg:city":"Halstenbek",
    "sg:phone":"+49 4101/45111",
    "sg:postcode":"25469",
    "sg:province":"Schleswig-Holstein",
    "wof:name":"Sabine Sellmer Immobilienmaklerin",
    "wof:placetype":"venue"
},
  "geometry": {"coordinates":[9.8347759247,53.6292457581],"type":"Point"}
}