{
  "type": "Feature",
  "properties": {
    "iso:country":"DE",
    "sg:address":"Konstantinstr. 70",
    "sg:city":"Bonn",
    "sg:postcode":"53179",
    "sg:province":"Nordrhein-Westfalen",
    "wof:name":"Delam Europa Gmbh",
    "wof:placetype":"venue"
},
  "geometry": {"coordinates":[7.172615,50.679623],"type":"Point"}
}