{
  "type": "Feature",
  "properties": {
    "iso:country":"DE",
    "sg:address":"Tersteegenstr. 9",
    "sg:city":"Solingen",
    "sg:phone":"+49 212/592381",
    "sg:postcode":"42653",
    "sg:province":"Nordrhein-Westfalen",
    "wof:name":"W. Wolter",
    "wof:placetype":"venue"
},
  "geometry": {"coordinates":[7.078689,51.197002],"type":"Point"}
}