{
  "type": "Feature",
  "properties": {
    "iso:country":"DE",
    "sg:address":"Kaiserstr. 19",
    "sg:city":"Hanerau-Hademarschen",
    "sg:phone":"+49 4872/2509",
    "sg:postcode":"25557",
    "sg:province":"Schleswig-Holstein",
    "wof:name":"Johannes Siebke",
    "wof:placetype":"venue"
},
  "geometry": {"coordinates":[9.4144039154,54.1269989014],"type":"Point"}
}