{
  "type": "Feature",
  "properties": {
    "iso:country":"DE",
    "sg:address":"Bahnhofstr. 19",
    "sg:city":"Aying",
    "sg:phone":"+49 8095/449",
    "sg:postcode":"85653",
    "sg:province":"Bayern",
    "wof:name":"Renate Baumhakl Masseurin",
    "wof:placetype":"venue"
},
  "geometry": {"coordinates":[11.773596,47.969673],"type":"Point"}
}