{
  "type": "Feature",
  "properties": {
    "iso:country":"DE",
    "sg:address":"Friedbergstr. 47",
    "sg:city":"Berlin",
    "sg:phone":"+49 30",
    "sg:postcode":"14057",
    "sg:province":"Berlin",
    "wof:name":"Anwaltskanzlei Schultze",
    "wof:placetype":"venue"
},
  "geometry": {"coordinates":[13.292232,52.503613],"type":"Point"}
}