{
  "type": "Feature",
  "properties": {
    "iso:country":"DE",
    "sg:address":"Widumer Str. 8",
    "sg:city":"Herne",
    "sg:postcode":"44627",
    "sg:province":"Nordrhein-Westfalen",
    "wof:name":"F\u00f6rderverein Deutsches Med. Forschungszentrum F. Geriatrie",
    "wof:placetype":"venue"
},
  "geometry": {"coordinates":[7.2615318298,51.5431976318],"type":"Point"}
}