{
  "type": "Feature",
  "properties": {
    "iso:country":"DE",
    "sg:address":"Alte Dorfstr. 30",
    "sg:city":"Binau",
    "sg:phone":"+49 6263/240",
    "sg:postcode":"74862",
    "sg:province":"Baden-W\u00fcrttemberg",
    "wof:name":"Ev. Pfarramt",
    "wof:placetype":"venue"
},
  "geometry": {"coordinates":[9.0569400787,49.3667106628],"type":"Point"}
}