{
  "type": "Feature",
  "properties": {
    "iso:country":"DE",
    "sg:address":"Landskroner Str. 110",
    "sg:city":"Bad Neuenahr-Ahrweiler",
    "sg:phone":"+49 2641/94860",
    "sg:postcode":"53474",
    "sg:province":"Rheinland-Pfalz",
    "wof:name":"Hotel-restaurant Zur Alten Post",
    "wof:placetype":"venue"
},
  "geometry": {"coordinates":[7.1637620926,50.5510520935],"type":"Point"}
}