{
  "type": "Feature",
  "properties": {
    "iso:country":"DE",
    "sg:address":"Hauptstr. 36",
    "sg:city":"Heubach",
    "sg:phone":"+49 7173/13408",
    "sg:postcode":"73540",
    "sg:province":"Baden-W\u00fcrttemberg",
    "wof:name":"Fashion-land",
    "wof:placetype":"venue"
},
  "geometry": {"coordinates":[9.934606,48.789093],"type":"Point"}
}