{
  "type": "Feature",
  "properties": {
    "iso:country":"DE",
    "sg:address":"Frankenberger Str. 67",
    "sg:city":"Chemnitz",
    "sg:phone":"+49 371/420077",
    "sg:postcode":"09131",
    "sg:province":"Sachsen",
    "wof:name":"Frank Steinhof",
    "wof:placetype":"venue"
},
  "geometry": {"coordinates":[12.9466257095,50.8532752991],"type":"Point"}
}