{
  "type": "Feature",
  "properties": {
    "iso:country":"DE",
    "sg:address":"M\u00fchlenstr. 14",
    "sg:city":"Schwalbach",
    "sg:phone":"+49 6834/95160",
    "sg:postcode":"66773",
    "sg:province":"Saarland",
    "wof:name":"Hermann Werner Finanzberater",
    "wof:placetype":"venue"
},
  "geometry": {"coordinates":[6.8007440567,49.2922744751],"type":"Point"}
}