{
  "type": "Feature",
  "properties": {
    "iso:country":"DE",
    "sg:address":"Schlo\u00dfstr. 19",
    "sg:city":"Korschenbroich",
    "sg:phone":"+49 2166/82877",
    "sg:postcode":"41352",
    "sg:province":"Nordrhein-Westfalen",
    "wof:name":"Naumann Gmbh",
    "wof:placetype":"venue"
},
  "geometry": {"coordinates":[6.54259,51.164867],"type":"Point"}
}