{
  "type": "Feature",
  "properties": {
    "iso:country":"DE",
    "sg:address":"Schulzendorfer Str. 7",
    "sg:city":"Dierberg",
    "sg:phone":"+49 33933/70818",
    "sg:postcode":"16835",
    "sg:province":"Brandenburg",
    "wof:name":"Milchhof Dierberg Gmbh",
    "wof:placetype":"venue"
},
  "geometry": {"coordinates":[12.9880800247,52.9716835022],"type":"Point"}
}