{
  "type": "Feature",
  "properties": {
    "iso:country":"DE",
    "sg:address":"Bodmanstr. 22",
    "sg:city":"Kempten",
    "sg:phone":"+49 831/523120",
    "sg:postcode":"87439",
    "sg:province":"Bayern",
    "wof:name":"Dassler & Beerbaum Gmbh",
    "wof:placetype":"venue"
},
  "geometry": {"coordinates":[10.3077812195,47.725151062],"type":"Point"}
}