{
  "type": "Feature",
  "properties": {
    "iso:country":"DE",
    "sg:address":"Kreuzstr. 64",
    "sg:city":"Linnich",
    "sg:phone":"+49 2462/3538",
    "sg:postcode":"52441",
    "sg:province":"Nordrhein-Westfalen",
    "wof:name":"T. Geradts",
    "wof:placetype":"venue"
},
  "geometry": {"coordinates":[6.305355072,50.9890823364],"type":"Point"}
}