{
  "type": "Feature",
  "properties": {
    "iso:country":"DE",
    "sg:address":"Forbacher Str. 12",
    "sg:city":"Saarbr\u00fccken",
    "sg:phone":"+49 681/57017",
    "sg:postcode":"66117",
    "sg:province":"Saarland",
    "wof:name":"Bernd Sarner Architekt",
    "wof:placetype":"venue"
},
  "geometry": {"coordinates":[6.981599,49.229767],"type":"Point"}
}