{
  "type": "Feature",
  "properties": {
    "iso:country":"DE",
    "sg:address":"Adalbertstr. 23 a",
    "sg:city":"Berlin",
    "sg:phone":"+49 30/6152366",
    "sg:postcode":"10997",
    "sg:province":"Berlin",
    "wof:name":"Beratungsstelle Und Freizeitheim T\u00fcrk. Arbeitnehm.",
    "wof:placetype":"venue"
},
  "geometry": {"coordinates":[13.421518,52.504124],"type":"Point"}
}