{
  "type": "Feature",
  "properties": {
    "iso:country":"DE",
    "sg:address":"Saselbergweg 27",
    "sg:city":"Hamburg",
    "sg:postcode":"22395",
    "sg:province":"Hamburg",
    "wof:name":"Hbi Handelskontor Berliner Immobilien Gmbh",
    "wof:placetype":"venue"
},
  "geometry": {"coordinates":[10.0956859589,53.6619758606],"type":"Point"}
}