{
  "type": "Feature",
  "properties": {
    "iso:country":"DE",
    "sg:address":"Zehdenicker Chaussee 49/50",
    "sg:city":"Gransee",
    "sg:postcode":"16775",
    "sg:province":"Brandenburg",
    "wof:name":"Tischlerei Karnies Gmbh",
    "wof:placetype":"venue"
},
  "geometry": {"coordinates":[13.153723,52.897305],"type":"Point"}
}