{
  "type": "Feature",
  "properties": {
    "iso:country":"DE",
    "sg:address":"Klosterberg",
    "sg:city":"Passau",
    "sg:postcode":"94034",
    "sg:province":"Bayern",
    "wof:name":"Salvator-missionen Gmbh",
    "wof:placetype":"venue"
},
  "geometry": {"coordinates":[13.4770832062,48.5777206421],"type":"Point"}
}