{
  "type": "Feature",
  "properties": {
    "iso:country":"DE",
    "sg:address":"Biberacher Str. 101",
    "sg:city":"Ulm",
    "sg:phone":"+49 731/482256",
    "sg:postcode":"89079",
    "sg:province":"Baden-W\u00fcrttemberg",
    "wof:name":"Roland Luhmert",
    "wof:placetype":"venue"
},
  "geometry": {"coordinates":[9.968644,48.352013],"type":"Point"}
}