{
  "type": "Feature",
  "properties": {
    "iso:country":"DE",
    "sg:address":"Richard-Strau\u00df-Str. 33",
    "sg:city":"Pfedelbach",
    "sg:phone":"+49 7941/8899",
    "sg:postcode":"74629",
    "sg:province":"Baden-W\u00fcrttemberg",
    "wof:name":"Karl Volz Architekt",
    "wof:placetype":"venue"
},
  "geometry": {"coordinates":[9.516735,49.180996],"type":"Point"}
}