{
  "type": "Feature",
  "properties": {
    "iso:country":"DE",
    "sg:address":"Lohm\u00fchlenweg 2",
    "sg:city":"Arnstadt",
    "sg:postcode":"99310",
    "sg:province":"Th\u00fcringen",
    "wof:name":"Mission Level Design Gmbh",
    "wof:placetype":"venue"
},
  "geometry": {"coordinates":[10.949269,50.828758],"type":"Point"}
}