{
  "type": "Feature",
  "properties": {
    "iso:country":"DE",
    "sg:address":"Wilhelmstr. 4",
    "sg:city":"Bernburg",
    "sg:phone":"+49 3471/626919",
    "sg:postcode":"06406",
    "sg:province":"Sachsen-Anhalt",
    "wof:name":"K. Bergholz",
    "wof:placetype":"venue"
},
  "geometry": {"coordinates":[11.7399282455,51.7969741821],"type":"Point"}
}