{
  "type": "Feature",
  "properties": {
    "iso:country":"DE",
    "sg:address":"Treysaer Str. 8",
    "sg:city":"Kassel",
    "sg:postcode":"34127",
    "sg:province":"Hessen",
    "wof:name":"Quick-term Gmbh",
    "wof:placetype":"venue"
},
  "geometry": {"coordinates":[9.4840965271,51.3287773132],"type":"Point"}
}