{
  "type": "Feature",
  "properties": {
    "iso:country":"DE",
    "sg:address":"Sonnenwaldstr. 11",
    "sg:city":"Sch\u00f6fweg",
    "sg:phone":"+49 9908/269",
    "sg:postcode":"94572",
    "sg:province":"Bayern",
    "wof:name":"J. Und R. Weber",
    "wof:placetype":"venue"
},
  "geometry": {"coordinates":[13.230856,48.840111],"type":"Point"}
}