{
  "type": "Feature",
  "properties": {
    "iso:country":"DE",
    "sg:address":"Franziskanerstr. 1-3",
    "sg:city":"\u00dcberlingen",
    "sg:phone":"+49 7551/95050",
    "sg:postcode":"88662",
    "sg:province":"Baden-W\u00fcrttemberg",
    "wof:name":"Konrad Kitt Gmbh",
    "wof:placetype":"venue"
},
  "geometry": {"coordinates":[9.1590747833,47.7670974731],"type":"Point"}
}