{
  "type": "Feature",
  "properties": {
    "iso:country":"DE",
    "sg:address":"Auerbacher Str. 28",
    "sg:city":"Pfungstadt",
    "sg:phone":"+49 6157/2442",
    "sg:postcode":"64319",
    "sg:province":"Hessen",
    "wof:name":"Bauunternehmen R. Meusel Gmbh",
    "wof:placetype":"venue"
},
  "geometry": {"coordinates":[8.599637,49.796272],"type":"Point"}
}