{
  "type": "Feature",
  "properties": {
    "iso:country":"DE",
    "sg:address":"Lonsstr. 7",
    "sg:city":"Offenburg",
    "sg:postcode":"77654",
    "sg:province":"Baden-W\u00fcrttemberg",
    "wof:name":"G\u00fcnther Marckwardt Architekt",
    "wof:placetype":"venue"
},
  "geometry": {"coordinates":[7.96127,48.476917],"type":"Point"}
}