{
  "type": "Feature",
  "properties": {
    "iso:country":"DE",
    "sg:address":"Friedenstrasse 24a",
    "sg:city":"Pforzheim",
    "sg:phone":"+49 7231/92160",
    "sg:postcode":"75173",
    "sg:province":"Baden-W\u00fcrttemberg",
    "wof:name":"Adolf Schweickert Gmbh & Co.",
    "wof:placetype":"venue"
},
  "geometry": {"coordinates":[8.6927843094,48.8831748962],"type":"Point"}
}