{
  "type": "Feature",
  "properties": {
    "iso:country":"DE",
    "sg:address":"Raiffeisenstr. 33a",
    "sg:city":"Kleinwallstadt",
    "sg:phone":"+49 6022/24792",
    "sg:postcode":"63839",
    "sg:province":"Bayern",
    "wof:name":"Heinz Rohs Ingenieur",
    "wof:placetype":"venue"
},
  "geometry": {"coordinates":[9.167183,49.873619],"type":"Point"}
}