{
  "type": "Feature",
  "properties": {
    "iso:country":"DE",
    "sg:address":"Dr.-Paul-Weinhart-Str. 6",
    "sg:city":"Prien",
    "sg:phone":"+49 8051/1539",
    "sg:postcode":"83209",
    "sg:province":"Bayern",
    "wof:name":"E. Angert",
    "wof:placetype":"venue"
},
  "geometry": {"coordinates":[12.3410615921,47.8527107239],"type":"Point"}
}