{
  "type": "Feature",
  "properties": {
    "iso:country":"DE",
    "sg:address":"Apfelallee 14",
    "sg:city":"Neuberg",
    "sg:phone":"+49 6183/73290",
    "sg:postcode":"63543",
    "sg:province":"Hessen",
    "wof:name":"Bohring Speditions Gmbh",
    "wof:placetype":"venue"
},
  "geometry": {"coordinates":[8.9891691208,50.1876487732],"type":"Point"}
}