{
  "type": "Feature",
  "properties": {
    "iso:country":"DE",
    "sg:address":"Mittelstr. 2",
    "sg:city":"Korbu\u00dfen",
    "sg:phone":"+49 36602/34484",
    "sg:postcode":"07554",
    "sg:province":"Th\u00fcringen",
    "wof:name":"Weidelt Gmbh",
    "wof:placetype":"venue"
},
  "geometry": {"coordinates":[12.172445,50.879688],"type":"Point"}
}