{
  "type": "Feature",
  "properties": {
    "iso:country":"DE",
    "sg:address":"Nebelhornring 5",
    "sg:city":"N\u00fcrnberg",
    "sg:postcode":"90471",
    "sg:province":"Bayern",
    "wof:name":"Gierth Gmbh",
    "wof:placetype":"venue"
},
  "geometry": {"coordinates":[11.1201324463,49.4068183899],"type":"Point"}
}