{
  "type": "Feature",
  "properties": {
    "iso:country":"DE",
    "sg:address":"Kronenstr. 5",
    "sg:city":"Solingen",
    "sg:phone":"+49 212/329873",
    "sg:postcode":"42699",
    "sg:province":"Nordrhein-Westfalen",
    "wof:name":"Kramp & Breer",
    "wof:placetype":"venue"
},
  "geometry": {"coordinates":[7.013381,51.161114],"type":"Point"}
}