{
  "type": "Feature",
  "properties": {
    "iso:country":"DE",
    "sg:address":"Auf dem Burghof 6",
    "sg:city":"Vahlbruch",
    "sg:phone":"+49 5535/527",
    "sg:postcode":"37647",
    "sg:province":"Niedersachsen",
    "wof:name":"Friedrich Meyer",
    "wof:placetype":"venue"
},
  "geometry": {"coordinates":[9.342185,51.91893],"type":"Point"}
}