{
  "type": "Feature",
  "properties": {
    "iso:country":"DE",
    "sg:address":"Dickerstr. 203",
    "sg:city":"Dinslaken",
    "sg:phone":"+49 2064/93949",
    "sg:postcode":"46539",
    "sg:province":"Nordrhein-Westfalen",
    "wof:name":"M. Becker",
    "wof:placetype":"venue"
},
  "geometry": {"coordinates":[6.786813,51.580437],"type":"Point"}
}