{
  "type": "Feature",
  "properties": {
    "iso:country":"DE",
    "sg:address":"Adalbert-Stifter-Weg 29",
    "sg:city":"Markt Schwaben",
    "sg:phone":"+49 8121/47110",
    "sg:postcode":"85570",
    "sg:province":"Bayern",
    "wof:name":"Hoser Bauunternehmung Gmbh",
    "wof:placetype":"venue"
},
  "geometry": {"coordinates":[11.857463,48.195057],"type":"Point"}
}