{
  "type": "Feature",
  "properties": {
    "iso:country":"DE",
    "sg:address":"Am Halberg",
    "sg:city":"Saarbr\u00fccken",
    "sg:phone":"+49 681/687920",
    "sg:postcode":"66121",
    "sg:province":"Saarland",
    "wof:name":"Werbefunk-saar Gesellschaft F\u00fcr Funk- Und",
    "wof:placetype":"venue"
},
  "geometry": {"coordinates":[7.0420780182,49.2241706848],"type":"Point"}
}