{
  "type": "Feature",
  "properties": {
    "iso:country":"DE",
    "sg:address":"Sportplatzstr. 2",
    "sg:city":"Rheinm\u00fcnster",
    "sg:phone":"+49 7227/2286",
    "sg:postcode":"77836",
    "sg:province":"Baden-W\u00fcrttemberg",
    "wof:name":"Helmut Schwab",
    "wof:placetype":"venue"
},
  "geometry": {"coordinates":[8.0453290939,48.7472267151],"type":"Point"}
}