{
  "type": "Feature",
  "properties": {
    "iso:country":"DE",
    "sg:address":"Scheffelstr. 2",
    "sg:city":"Bad D\u00fcrrheim",
    "sg:phone":"+49 7726/221",
    "sg:postcode":"78073",
    "sg:province":"Baden-W\u00fcrttemberg",
    "wof:name":"Hotel R\u00f6ssle",
    "wof:placetype":"venue"
},
  "geometry": {"coordinates":[8.5291204453,48.0192298889],"type":"Point"}
}