{
  "type": "Feature",
  "properties": {
    "iso:country":"DE",
    "sg:address":"Obertorstr. 40",
    "sg:city":"Schl\u00fcchtern",
    "sg:phone":"+49 6661/916371",
    "sg:postcode":"36381",
    "sg:province":"Hessen",
    "wof:name":"Gastst\u00e4tte L\u00e4mpchen",
    "wof:placetype":"venue"
},
  "geometry": {"coordinates":[9.5244846344,50.3497543335],"type":"Point"}
}