{
  "type": "Feature",
  "properties": {
    "iso:country":"DE",
    "sg:address":"Volkswohlstrasse 25",
    "sg:city":"N\u00fcrnberg",
    "sg:phone":"+49 911/6493021",
    "sg:postcode":"90451",
    "sg:province":"Bayern",
    "wof:name":"Ksn-n\u00fcrnberg",
    "wof:placetype":"venue"
},
  "geometry": {"coordinates":[11.0309152603,49.4110336304],"type":"Point"}
}