{
  "type": "Feature",
  "properties": {
    "iso:country":"DE",
    "sg:address":"Rohrbacher Str. 20",
    "sg:city":"Heidelberg",
    "sg:phone":"+49 6221/181581",
    "sg:postcode":"69115",
    "sg:province":"Baden-W\u00fcrttemberg",
    "wof:name":"Ambitec Entsorgungstechnik Gmbh",
    "wof:placetype":"venue"
},
  "geometry": {"coordinates":[8.6923942566,49.405544281],"type":"Point"}
}