{
  "type": "Feature",
  "properties": {
    "iso:country":"DE",
    "sg:address":"Dorfstr. 38",
    "sg:city":"Travenhorst",
    "sg:phone":"+49 4556/1072",
    "sg:postcode":"23827",
    "sg:province":"Schleswig-Holstein",
    "wof:name":"Biohof Kluever",
    "wof:placetype":"venue"
},
  "geometry": {"coordinates":[10.454531,54.018997],"type":"Point"}
}