{
  "type": "Feature",
  "properties": {
    "iso:country":"DE",
    "sg:address":"Ringstr. 39",
    "sg:city":"Wesenberg",
    "sg:phone":"+49 39832/20908",
    "sg:postcode":"17255",
    "sg:province":"Mecklenburg-Vorpommern",
    "wof:name":"E. Diehr",
    "wof:placetype":"venue"
},
  "geometry": {"coordinates":[12.967141,53.282589],"type":"Point"}
}