{
  "type": "Feature",
  "properties": {
    "iso:country":"DE",
    "sg:address":"Wagener Stra\u00dfe 11",
    "sg:city":"Idstein",
    "sg:phone":"+49 6126/998850",
    "sg:postcode":"65510",
    "sg:province":"Hessen",
    "wof:name":"Vermessungsb\u00fcro M\u00fcller, Idstein",
    "wof:placetype":"venue"
},
  "geometry": {"coordinates":[8.267013,50.220798],"type":"Point"}
}