{
  "type": "Feature",
  "properties": {
    "iso:country":"DE",
    "sg:address":"Wiesenstr 9",
    "sg:city":"Kreuztal",
    "sg:phone":"+49 2732/28041",
    "sg:postcode":"57223",
    "sg:province":"Nordrhein-Westfalen",
    "wof:name":"Victon H\u00f6rger\u00e4te Friedrich Scheinhardt",
    "wof:placetype":"venue"
},
  "geometry": {"coordinates":[7.9866428375,50.9630775452],"type":"Point"}
}