{
  "type": "Feature",
  "properties": {
    "iso:country":"DE",
    "sg:address":"Ringstr. 19",
    "sg:city":"Heinsberg",
    "sg:phone":"+49 2452/86362",
    "sg:postcode":"52525",
    "sg:province":"Nordrhein-Westfalen",
    "wof:name":"G. Krifft",
    "wof:placetype":"venue"
},
  "geometry": {"coordinates":[6.0863370895,51.0706214905],"type":"Point"}
}