{
  "type": "Feature",
  "properties": {
    "iso:country":"DE",
    "sg:address":"Hauptstr. 51",
    "sg:city":"Gemmrigheim",
    "sg:phone":"+49 7143/91115",
    "sg:postcode":"74376",
    "sg:province":"Baden-W\u00fcrttemberg",
    "wof:name":"Weinstube Traube",
    "wof:placetype":"venue"
},
  "geometry": {"coordinates":[9.1551523209,49.0257148743],"type":"Point"}
}