{
  "type": "Feature",
  "properties": {
    "iso:country":"DE",
    "sg:address":"Hahnenkammstr. 13",
    "sg:city":"Karlstein",
    "sg:phone":"+49 4961/885005",
    "sg:postcode":"63791",
    "sg:province":"Bayern",
    "wof:name":"Raiffeisen-volksbank Vorspessart Eg",
    "wof:placetype":"venue"
},
  "geometry": {"coordinates":[9.035469,50.040398],"type":"Point"}
}