{
  "type": "Feature",
  "properties": {
    "iso:country":"DE",
    "sg:address":"P\u00f6tzling 13",
    "sg:city":"Leinburg",
    "sg:phone":"+49 9120/9819",
    "sg:postcode":"91227",
    "sg:province":"Bayern",
    "wof:name":"Konrad Schreimel",
    "wof:placetype":"venue"
},
  "geometry": {"coordinates":[11.3380489349,49.4535522461],"type":"Point"}
}