{
  "type": "Feature",
  "properties": {
    "iso:country":"DE",
    "sg:address":"Bahnhofstr. 14",
    "sg:city":"Alfeld",
    "sg:phone":"+49 5181/828621",
    "sg:postcode":"31061",
    "sg:province":"Niedersachsen",
    "wof:name":"Phone As Telekommunikation Gmbh",
    "wof:placetype":"venue"
},
  "geometry": {"coordinates":[9.8199291229,51.9813041687],"type":"Point"}
}