{
  "type": "Feature",
  "properties": {
    "iso:country":"DE",
    "sg:address":"Luegallee 52",
    "sg:city":"D\u00fcsseldorf",
    "sg:postcode":"40545",
    "sg:province":"Nordrhein-Westfalen",
    "wof:name":"Actimed Krafttraining Gmbh",
    "wof:placetype":"venue"
},
  "geometry": {"coordinates":[6.7551050186,51.2317695618],"type":"Point"}
}