{
  "type": "Feature",
  "properties": {
    "iso:country":"DE",
    "sg:address":"Kehn 19",
    "sg:city":"T\u00f6nisvorst",
    "sg:phone":"+49 2156/8511",
    "sg:postcode":"47918",
    "sg:province":"Nordrhein-Westfalen",
    "wof:name":"Arnold K\u00e4mmer",
    "wof:placetype":"venue"
},
  "geometry": {"coordinates":[6.46278,51.301998],"type":"Point"}
}