{
  "type": "Feature",
  "properties": {
    "iso:country":"DE",
    "sg:address":"Dyckburgstr. 403",
    "sg:city":"M\u00fcnster",
    "sg:phone":"+49 251/32038",
    "sg:postcode":"48157",
    "sg:province":"Nordrhein-Westfalen",
    "wof:name":"Beaufays Inh. Peter Beaufays",
    "wof:placetype":"venue"
},
  "geometry": {"coordinates":[7.69226,51.998501],"type":"Point"}
}