{
  "type": "Feature",
  "properties": {
    "iso:country":"DE",
    "sg:address":"Bizetstr. 134",
    "sg:city":"Berlin",
    "sg:postcode":"13088",
    "sg:province":"Berlin",
    "wof:name":"Gerhard Wunsch",
    "wof:placetype":"venue"
},
  "geometry": {"coordinates":[13.464637,52.549999],"type":"Point"}
}