{
  "type": "Feature",
  "properties": {
    "iso:country":"DE",
    "sg:address":"Breslauer Str. 17-19",
    "sg:city":"M\u00f6lln",
    "sg:phone":"+49 4945/4284710",
    "sg:postcode":"23879",
    "sg:province":"Schleswig-Holstein",
    "wof:name":"Schlummergl\u00dcck - Werke M\u00d6ller Gmbh Co.kg",
    "wof:placetype":"venue"
},
  "geometry": {"coordinates":[10.6970272064,53.6036682129],"type":"Point"}
}