{
  "type": "Feature",
  "properties": {
    "iso:country":"DE",
    "sg:address":"Frankenstr. 2",
    "sg:city":"Laufach",
    "sg:phone":"+49 6093/1346",
    "sg:postcode":"63846",
    "sg:province":"Bayern",
    "wof:name":"H. Petermann",
    "wof:placetype":"venue"
},
  "geometry": {"coordinates":[9.3273019791,50.0121841431],"type":"Point"}
}