{
  "type": "Feature",
  "properties": {
    "iso:country":"DE",
    "sg:address":"Prinz-Ludwig-Str. 14",
    "sg:city":"Waldsassen",
    "sg:phone":"+49 9632/2190",
    "sg:postcode":"95652",
    "sg:province":"Bayern",
    "wof:name":"Ledi",
    "wof:placetype":"venue"
},
  "geometry": {"coordinates":[12.3040933609,50.0035209656],"type":"Point"}
}