{
  "type": "Feature",
  "properties": {
    "iso:country":"DE",
    "sg:address":"Georg-Richter-Str. 5",
    "sg:city":"Frankfurt",
    "sg:phone":"+49 335/4002035",
    "sg:postcode":"15234",
    "sg:province":"Brandenburg",
    "wof:name":"Oder Hefeklo\u00df Gmbh",
    "wof:placetype":"venue"
},
  "geometry": {"coordinates":[14.511964798,52.3528327942],"type":"Point"}
}