{
  "type": "Feature",
  "properties": {
    "iso:country":"DE",
    "sg:address":"Diedenhofener Strasse 13",
    "sg:city":"Trier",
    "sg:phone":"+49 651/9980380",
    "sg:postcode":"54294",
    "sg:province":"Rheinland-Pfalz",
    "wof:name":"Reingungsprodukte Bartelmes",
    "wof:placetype":"venue"
},
  "geometry": {"coordinates":[6.611082,49.730648],"type":"Point"}
}