{
  "type": "Feature",
  "properties": {
    "iso:country":"DE",
    "sg:address":"Regentenstr. 99",
    "sg:city":"M\u00f6nchengladbach",
    "sg:postcode":"41061",
    "sg:province":"Nordrhein-Westfalen",
    "wof:name":"S. Laifi",
    "wof:placetype":"venue"
},
  "geometry": {"coordinates":[6.4408521652,51.20054245],"type":"Point"}
}