{
  "type": "Feature",
  "properties": {
    "iso:country":"DE",
    "sg:address":"Weidengasse 5",
    "sg:city":"Stetten",
    "sg:phone":"+49 7573/2150",
    "sg:postcode":"72510",
    "sg:province":"Baden-W\u00fcrttemberg",
    "wof:name":"Theophil Mogg",
    "wof:placetype":"venue"
},
  "geometry": {"coordinates":[9.0832967758,48.1185913086],"type":"Point"}
}