{
  "type": "Feature",
  "properties": {
    "iso:country":"DE",
    "sg:address":"Am Rathaus 14",
    "sg:city":"Hauzenberg",
    "sg:phone":"+49 8586/1207",
    "sg:postcode":"94051",
    "sg:province":"Bayern",
    "wof:name":"Martin Pangerl",
    "wof:placetype":"venue"
},
  "geometry": {"coordinates":[13.624266,48.651085],"type":"Point"}
}