{
  "type": "Feature",
  "properties": {
    "iso:country":"DE",
    "sg:address":"Tiroler Str. 30 a",
    "sg:city":"Rostock",
    "sg:postcode":"18069",
    "sg:province":"Mecklenburg-Vorpommern",
    "wof:name":"Bcs Baltic Car Sharing Autovermietung",
    "wof:placetype":"venue"
},
  "geometry": {"coordinates":[12.078931,54.096622],"type":"Point"}
}