{
  "type": "Feature",
  "properties": {
    "iso:country":"DE",
    "sg:address":"Am Gottebach 35",
    "sg:city":"Paderborn",
    "sg:phone":"+49 5252/930313",
    "sg:postcode":"33100",
    "sg:province":"Nordrhein-Westfalen",
    "wof:name":"Udo U. Annegret R\u00f6mer",
    "wof:placetype":"venue"
},
  "geometry": {"coordinates":[8.830366,51.739094],"type":"Point"}
}