{
  "type": "Feature",
  "properties": {
    "iso:country":"DE",
    "sg:address":"Veilchenweg 8",
    "sg:city":"Dormagen",
    "sg:phone":"+49 2182/6443",
    "sg:postcode":"41542",
    "sg:province":"Nordrhein-Westfalen",
    "wof:name":"Immobilien- Und Verm\u00f6gensver- Waltung A & F Herbertz Gmbh",
    "wof:placetype":"venue"
},
  "geometry": {"coordinates":[6.7220721245,51.1031036377],"type":"Point"}
}