{
  "type": "Feature",
  "properties": {
    "iso:country":"DE",
    "sg:address":"Eifelweg 4",
    "sg:city":"Bielefeld",
    "sg:phone":"+49 521/331356",
    "sg:postcode":"33719",
    "sg:province":"Nordrhein-Westfalen",
    "wof:name":"M. Huss Elektroinstallation",
    "wof:placetype":"venue"
},
  "geometry": {"coordinates":[8.601808,52.025871],"type":"Point"}
}