{
  "type": "Feature",
  "properties": {
    "iso:country":"DE",
    "sg:address":"Hauptstr. 85",
    "sg:city":"Karlshagen",
    "sg:phone":"+49 38371/20227",
    "sg:postcode":"17449",
    "sg:province":"Mecklenburg-Vorpommern",
    "wof:name":"W. L\u00fcder",
    "wof:placetype":"venue"
},
  "geometry": {"coordinates":[13.841143,54.108486],"type":"Point"}
}