{
  "type": "Feature",
  "properties": {
    "iso:country":"DE",
    "sg:address":"Otto-Hahn-Str. 13",
    "sg:city":"Friedrichsdorf",
    "sg:postcode":"61381",
    "sg:province":"Hessen",
    "wof:name":"Capmoon Gmbh",
    "wof:placetype":"venue"
},
  "geometry": {"coordinates":[8.657211,50.280434],"type":"Point"}
}