{
  "type": "Feature",
  "properties": {
    "iso:country":"DE",
    "sg:address":"Klockenberg 28",
    "sg:city":"Ueckerm\u00fcnde",
    "sg:phone":"+49 39771/23537",
    "sg:postcode":"17373",
    "sg:province":"Mecklenburg-Vorpommern",
    "wof:name":"Willi Klotz",
    "wof:placetype":"venue"
},
  "geometry": {"coordinates":[14.059547,53.733337],"type":"Point"}
}