{
  "type": "Feature",
  "properties": {
    "iso:country":"DE",
    "sg:address":"Werster Str. 80",
    "sg:city":"Bad Oeynhausen",
    "sg:phone":"+49 5731/260131",
    "sg:postcode":"32549",
    "sg:province":"Nordrhein-Westfalen",
    "wof:name":"Georg Jatzenko Masseur",
    "wof:placetype":"venue"
},
  "geometry": {"coordinates":[8.786205,52.215611],"type":"Point"}
}