{
  "type": "Feature",
  "properties": {
    "iso:country":"DE",
    "sg:address":"Alexanderstr. 2",
    "sg:city":"Aachen",
    "sg:phone":"+49 241/30152",
    "sg:postcode":"52062",
    "sg:province":"Nordrhein-Westfalen",
    "wof:name":"Eiscafe Romagna",
    "wof:placetype":"venue"
},
  "geometry": {"coordinates":[6.088294,50.777946],"type":"Point"}
}