{
  "type": "Feature",
  "properties": {
    "iso:country":"DE",
    "sg:address":"Unterstr. 42 a",
    "sg:city":"Weinbach",
    "sg:phone":"+49 6474/243",
    "sg:postcode":"35796",
    "sg:province":"Hessen",
    "wof:name":"Becker B\u00fcroservice Gmbh",
    "wof:placetype":"venue"
},
  "geometry": {"coordinates":[8.3076753616,50.4102783203],"type":"Point"}
}