{
  "type": "Feature",
  "properties": {
    "iso:country":"DE",
    "sg:address":"Weserstr. 110",
    "sg:city":"Vlotho",
    "sg:phone":"+49 5733/2302",
    "sg:postcode":"32602",
    "sg:province":"Nordrhein-Westfalen",
    "wof:name":"Weserlust",
    "wof:placetype":"venue"
},
  "geometry": {"coordinates":[8.9050693512,52.1656646729],"type":"Point"}
}