{
  "type": "Feature",
  "properties": {
    "iso:country":"DE",
    "sg:address":"Haidenkofen",
    "sg:city":"Wallersdorf",
    "sg:phone":"+49 9933/695",
    "sg:postcode":"94522",
    "sg:province":"Bayern",
    "wof:name":"Rosa Santl",
    "wof:placetype":"venue"
},
  "geometry": {"coordinates":[12.6868400574,48.7450218201],"type":"Point"}
}