{
  "type": "Feature",
  "properties": {
    "iso:country":"DE",
    "sg:address":"Ronheider Weg 76 c",
    "sg:city":"Aachen",
    "sg:postcode":"52066",
    "sg:province":"Nordrhein-Westfalen",
    "wof:name":"Vsp-aachen Gmbh",
    "wof:placetype":"venue"
},
  "geometry": {"coordinates":[6.0768809319,50.7527198792],"type":"Point"}
}