{
  "type": "Feature",
  "properties": {
    "iso:country":"DE",
    "sg:address":"Ottmannshofer Str. 29",
    "sg:city":"Leutkirch",
    "sg:phone":"+49 7561/3232",
    "sg:postcode":"88299",
    "sg:province":"Baden-W\u00fcrttemberg",
    "wof:name":"Brandeck",
    "wof:placetype":"venue"
},
  "geometry": {"coordinates":[10.0235509872,47.83203125],"type":"Point"}
}