{
  "type": "Feature",
  "properties": {
    "iso:country":"DE",
    "sg:address":"Massenbergstr. 3",
    "sg:city":"Bochum",
    "sg:phone":"+49 234/12011",
    "sg:postcode":"44787",
    "sg:province":"Nordrhein-Westfalen",
    "wof:name":"Pfaff",
    "wof:placetype":"venue"
},
  "geometry": {"coordinates":[7.2203540802,51.4809188843],"type":"Point"}
}