{
  "type": "Feature",
  "properties": {
    "iso:country":"DE",
    "sg:address":"M\u00fchlh\u00e4userstra\u00dfe",
    "sg:city":"Oberdorla",
    "sg:phone":"+49 36014/27411",
    "sg:postcode":"99986",
    "sg:province":"Th\u00fcringen",
    "wof:name":"Oberdorlaer Carnevals Verein",
    "wof:placetype":"venue"
},
  "geometry": {"coordinates":[10.4298,51.16819],"type":"Point"}
}