{
  "type": "Feature",
  "properties": {
    "iso:country":"DE",
    "sg:address":"Lahmertstr. 8",
    "sg:city":"Berlin",
    "sg:phone":"+49 30/6747182",
    "sg:postcode":"12527",
    "sg:province":"Berlin",
    "wof:name":"Claus K\u00f6nig",
    "wof:placetype":"venue"
},
  "geometry": {"coordinates":[13.573794,52.421841],"type":"Point"}
}