{
  "type": "Feature",
  "properties": {
    "iso:country":"DE",
    "sg:address":"Zellauerweg 14",
    "sg:city":"F\u00fcrstenzell",
    "sg:phone":"+49 8502/922333",
    "sg:postcode":"94081",
    "sg:province":"Bayern",
    "wof:name":"K.-m. Hutsteiner",
    "wof:placetype":"venue"
},
  "geometry": {"coordinates":[13.3107147217,48.52501297],"type":"Point"}
}