{
  "type": "Feature",
  "properties": {
    "iso:country":"DE",
    "sg:address":"Kalbhenstr 5",
    "sg:city":"Nottuln",
    "sg:phone":"+49 2502/224850",
    "sg:postcode":"48301",
    "sg:province":"Nordrhein-Westfalen",
    "wof:name":"Garntec Garnet",
    "wof:placetype":"venue"
},
  "geometry": {"coordinates":[7.35554,51.924065],"type":"Point"}
}