{
  "type": "Feature",
  "properties": {
    "iso:country":"DE",
    "sg:address":"Bergstr. 40",
    "sg:city":"Ellhofen",
    "sg:phone":"+49 7134/3774",
    "sg:postcode":"74248",
    "sg:province":"Baden-W\u00fcrttemberg",
    "wof:name":"Paul Schrempf",
    "wof:placetype":"venue"
},
  "geometry": {"coordinates":[9.3182706833,49.143032074],"type":"Point"}
}