{
  "type": "Feature",
  "properties": {
    "iso:country":"DE",
    "sg:address":"Bahnhofstr. 18",
    "sg:city":"G\u00f6\u00dfnitz",
    "sg:phone":"+49 34493/30887",
    "sg:postcode":"04639",
    "sg:province":"Th\u00fcringen",
    "wof:name":"Klaus St\u00f6tzner",
    "wof:placetype":"venue"
},
  "geometry": {"coordinates":[12.429561615,50.8895988464],"type":"Point"}
}