{
  "type": "Feature",
  "properties": {
    "iso:country":"DE",
    "sg:address":"Achatiusstr. 4",
    "sg:city":"Lichtenau",
    "sg:phone":"+49 5295/1035",
    "sg:postcode":"33165",
    "sg:province":"Nordrhein-Westfalen",
    "wof:name":"Ev. Pfarramt",
    "wof:placetype":"venue"
},
  "geometry": {"coordinates":[8.8000974655,51.5949897766],"type":"Point"}
}