{
  "type": "Feature",
  "properties": {
    "iso:country":"DE",
    "sg:address":"Frankfurter Str. 137",
    "sg:city":"Kassel",
    "sg:phone":"+49 561/281082",
    "sg:postcode":"34121",
    "sg:province":"Hessen",
    "wof:name":"Annette Kohl",
    "wof:placetype":"venue"
},
  "geometry": {"coordinates":[9.4817819595,51.2994003296],"type":"Point"}
}