{
  "type": "Feature",
  "properties": {
    "iso:country":"DE",
    "sg:address":"Friedenstr. 14",
    "sg:city":"Giebelstadt",
    "sg:phone":"+49 9334/528",
    "sg:postcode":"97232",
    "sg:province":"Bayern",
    "wof:name":"Emil Leimig Ingenieurb\u00fcro",
    "wof:placetype":"venue"
},
  "geometry": {"coordinates":[9.9450759888,49.6561851501],"type":"Point"}
}