{
  "type": "Feature",
  "properties": {
    "iso:country":"DE",
    "sg:address":"Auf der Hahnau 37",
    "sg:city":"Weilburg",
    "sg:postcode":"35781",
    "sg:province":"Hessen",
    "wof:name":"Nepalreisen Hartmut Schaefer",
    "wof:placetype":"venue"
},
  "geometry": {"coordinates":[8.257109642,50.496181488],"type":"Point"}
}