{
  "type": "Feature",
  "properties": {
    "iso:country":"DE",
    "sg:address":"Kendelstr. 18",
    "sg:city":"Bad Kreuznach",
    "sg:phone":"+49 671/31967",
    "sg:postcode":"55545",
    "sg:province":"Rheinland-Pfalz",
    "wof:name":"Norbert Butzbach Gmbh",
    "wof:placetype":"venue"
},
  "geometry": {"coordinates":[7.8659210205,49.8723106384],"type":"Point"}
}