{
  "type": "Feature",
  "properties": {
    "iso:country":"DE",
    "sg:address":"Auerbacherstr.6",
    "sg:city":"Auerbach",
    "sg:postcode":"94530",
    "sg:province":"Bayern",
    "wof:name":"Fa. Weber-bau/engolling - Bauunternehmen, Planung",
    "wof:placetype":"venue"
},
  "geometry": {"coordinates":[13.100986,48.794544],"type":"Point"}
}