{
  "type": "Feature",
  "properties": {
    "iso:country":"DE",
    "sg:address":"Fr\u00fchlingstr. 8",
    "sg:city":"Hutthurm",
    "sg:phone":"+49 8505/830",
    "sg:postcode":"94116",
    "sg:province":"Bayern",
    "wof:name":"Helmut Stadler",
    "wof:placetype":"venue"
},
  "geometry": {"coordinates":[13.4801120758,48.6709671021],"type":"Point"}
}