{
  "type": "Feature",
  "properties": {
    "iso:country":"DE",
    "sg:address":"Pfingstrosenstr. 38",
    "sg:city":"M\u00fcnchen",
    "sg:phone":"+49 89/7144390",
    "sg:postcode":"81377",
    "sg:province":"Bayern",
    "wof:name":"Josef Laus Architekt",
    "wof:placetype":"venue"
},
  "geometry": {"coordinates":[11.48352,48.109707],"type":"Point"}
}