{
  "type": "Feature",
  "properties": {
    "iso:country":"DE",
    "sg:address":"Haller Str. 14",
    "sg:city":"Schw\u00e4bisch Hall",
    "sg:phone":"+49 791/47671",
    "sg:postcode":"74523",
    "sg:province":"Baden-W\u00fcrttemberg",
    "wof:name":"H. Stuber",
    "wof:placetype":"venue"
},
  "geometry": {"coordinates":[9.74606,49.113312],"type":"Point"}
}