{
  "type": "Feature",
  "properties": {
    "iso:country":"DE",
    "sg:address":"Vordere Str. 10",
    "sg:city":"Beimerstetten",
    "sg:phone":"+49 7348/6340",
    "sg:postcode":"89179",
    "sg:province":"Baden-W\u00fcrttemberg",
    "wof:name":"Georg Bosch",
    "wof:placetype":"venue"
},
  "geometry": {"coordinates":[9.987378,48.48328],"type":"Point"}
}