{
  "type": "Feature",
  "properties": {
    "iso:country":"DE",
    "sg:address":"Hauptstr. 14",
    "sg:city":"Weisweil",
    "sg:postcode":"79367",
    "sg:province":"Baden-W\u00fcrttemberg",
    "wof:name":"Gemeindeb\u00fccherei Z. Hd. L. Sch\u00f6nw\u00e4lder",
    "wof:placetype":"venue"
},
  "geometry": {"coordinates":[7.674285,48.197056],"type":"Point"}
}