{
  "type": "Feature",
  "properties": {
    "iso:country":"DE",
    "sg:address":"Hohe Str. 83",
    "sg:city":"Dortmund",
    "sg:phone":"+49 231/7213241",
    "sg:postcode":"44139",
    "sg:province":"Nordrhein-Westfalen",
    "wof:name":"Postkutsche",
    "wof:placetype":"venue"
},
  "geometry": {"coordinates":[7.4586620331,51.5028457642],"type":"Point"}
}