{
  "type": "Feature",
  "properties": {
    "iso:country":"DE",
    "sg:address":"Rosenstr. 22",
    "sg:city":"Boblitz",
    "sg:phone":"+49 3542/3181",
    "sg:postcode":"03222",
    "sg:province":"Brandenburg",
    "wof:name":"Reinhard Biela",
    "wof:placetype":"venue"
},
  "geometry": {"coordinates":[13.98502,51.841221],"type":"Point"}
}