{
  "type": "Feature",
  "properties": {
    "iso:country":"DE",
    "sg:address":"Leipziger Str. 19",
    "sg:city":"Meinhard",
    "sg:phone":"+49 5651/50921",
    "sg:postcode":"37276",
    "sg:province":"Hessen",
    "wof:name":"Albert Brand",
    "wof:placetype":"venue"
},
  "geometry": {"coordinates":[10.1264057159,51.1904296875],"type":"Point"}
}