{
  "type": "Feature",
  "properties": {
    "iso:country":"DE",
    "sg:address":"Hochbergweg 4",
    "sg:city":"Wangen",
    "sg:phone":"+49 7528",
    "sg:postcode":"88239",
    "sg:province":"Baden-W\u00fcrttemberg",
    "wof:name":"Rasen-komplett-system",
    "wof:placetype":"venue"
},
  "geometry": {"coordinates":[9.7473106384,47.6254959106],"type":"Point"}
}