{
  "type": "Feature",
  "properties": {
    "iso:country":"DE",
    "sg:address":"Beuggener Str. 39",
    "sg:city":"Rheinfelden",
    "sg:phone":"+49 7623/2306",
    "sg:postcode":"79618",
    "sg:province":"Baden-W\u00fcrttemberg",
    "wof:name":"Ewald Senger",
    "wof:placetype":"venue"
},
  "geometry": {"coordinates":[7.7720589638,47.5735702515],"type":"Point"}
}