{
  "type": "Feature",
  "properties": {
    "iso:country":"DE",
    "sg:address":"Niedersachsenstr. 10 C",
    "sg:city":"Winsen",
    "sg:postcode":"21423",
    "sg:province":"Niedersachsen",
    "wof:name":"Oertzen Projektentwicklung Immobilien Gmbh",
    "wof:placetype":"venue"
},
  "geometry": {"coordinates":[10.210881,53.356712],"type":"Point"}
}