{
  "type": "Feature",
  "properties": {
    "iso:country":"DE",
    "sg:address":"Haubensteigweg 25",
    "sg:city":"Kempten",
    "sg:postcode":"87439",
    "sg:province":"Bayern",
    "wof:name":"In Voga Gmbh & Co. Kg",
    "wof:placetype":"venue"
},
  "geometry": {"coordinates":[10.301817,47.72612],"type":"Point"}
}