{
  "type": "Feature",
  "properties": {
    "iso:country":"DE",
    "sg:address":"Bahnhofstr. 44",
    "sg:city":"Sch\u00f6naich",
    "sg:phone":"+49 7031/758575",
    "sg:postcode":"71101",
    "sg:province":"Baden-W\u00fcrttemberg",
    "wof:name":"Dialog Professionelle Datenausgabe Gmbh",
    "wof:placetype":"venue"
},
  "geometry": {"coordinates":[9.059496,48.664284],"type":"Point"}
}