{
  "type": "Feature",
  "properties": {
    "iso:country":"DE",
    "sg:address":"Doberluger Str.",
    "sg:city":"Tr\u00f6bitz",
    "sg:phone":"+49 35326/867",
    "sg:postcode":"03253",
    "sg:province":"Brandenburg",
    "wof:name":"J\u00fcrgen Lorenz",
    "wof:placetype":"venue"
},
  "geometry": {"coordinates":[13.43433,51.598068],"type":"Point"}
}