{
  "type": "Feature",
  "properties": {
    "iso:country":"DE",
    "sg:address":"Bedburdycker Str.7",
    "sg:city":"J\u00fcchen",
    "sg:phone":"+49 2181/490955",
    "sg:postcode":"41363",
    "sg:province":"Nordrhein-Westfalen",
    "wof:name":"Nudera Dv",
    "wof:placetype":"venue"
},
  "geometry": {"coordinates":[6.5444068909,51.1127967834],"type":"Point"}
}