{
  "type": "Feature",
  "properties": {
    "iso:country":"DE",
    "sg:address":"Schwabacher Str. 121",
    "sg:city":"F\u00fcrth",
    "sg:phone":"+49 911/7419381",
    "sg:postcode":"90763",
    "sg:province":"Bayern",
    "wof:name":"Ambulanter Sozialdienst Und Betreuung Alten- Und",
    "wof:placetype":"venue"
},
  "geometry": {"coordinates":[10.98599,49.46524],"type":"Point"}
}