{
  "type": "Feature",
  "properties": {
    "iso:country":"DE",
    "sg:address":"Graf-Recke-Str. 7",
    "sg:city":"D\u00fcsseldorf",
    "sg:phone":"+49 211/675556",
    "sg:postcode":"40239",
    "sg:province":"Nordrhein-Westfalen",
    "wof:name":"Chr. Tap Bb\u00dc Exper Team",
    "wof:placetype":"venue"
},
  "geometry": {"coordinates":[6.803848,51.238647],"type":"Point"}
}