{
  "type": "Feature",
  "properties": {
    "iso:country":"DE",
    "sg:address":"Eisensteinstr. 7",
    "sg:city":"Trusetal",
    "sg:phone":"+49 36840/81451",
    "sg:postcode":"98596",
    "sg:province":"Th\u00fcringen",
    "wof:name":"W. Storch",
    "wof:placetype":"venue"
},
  "geometry": {"coordinates":[10.4095783234,50.7863731384],"type":"Point"}
}