{
  "type": "Feature",
  "properties": {
    "iso:country":"DE",
    "sg:address":"Obergeorgswerder Deich 64",
    "sg:city":"Hamburg",
    "sg:postcode":"21109",
    "sg:province":"Hamburg",
    "wof:name":"Kultur Und Management Gmbh",
    "wof:placetype":"venue"
},
  "geometry": {"coordinates":[10.0443782806,53.5034790039],"type":"Point"}
}