{
  "type": "Feature",
  "properties": {
    "iso:country":"DE",
    "sg:address":"Kaltbrunner Str. 40a",
    "sg:city":"Allensbach",
    "sg:phone":"+49 7533/5658",
    "sg:postcode":"78476",
    "sg:province":"Baden-W\u00fcrttemberg",
    "wof:name":"Getreidem\u00fchle Otto Hierling",
    "wof:placetype":"venue"
},
  "geometry": {"coordinates":[9.0726699829,47.7208786011],"type":"Point"}
}