{
  "type": "Feature",
  "properties": {
    "iso:country":"DE",
    "sg:address":"Gr\u00fcnwalder Str. 242",
    "sg:city":"M\u00fcnchen",
    "sg:phone":"+49 89/646629",
    "sg:postcode":"81545",
    "sg:province":"Bayern",
    "wof:name":"Helmut Katzl Architekt",
    "wof:placetype":"venue"
},
  "geometry": {"coordinates":[11.562517,48.092388],"type":"Point"}
}