{
  "type": "Feature",
  "properties": {
    "iso:country":"DE",
    "sg:address":"Ernst-Schneller-Str. 2",
    "sg:city":"Heidenau",
    "sg:phone":"+49 3529/512573",
    "sg:postcode":"01809",
    "sg:province":"Sachsen",
    "wof:name":"Rewe Markt Andreas Gommlich Ohg",
    "wof:placetype":"venue"
},
  "geometry": {"coordinates":[13.8640222549,50.9697570801],"type":"Point"}
}