{
  "type": "Feature",
  "properties": {
    "iso:country":"DE",
    "sg:address":"An den Bleichen 48",
    "sg:city":"Stralsund",
    "sg:phone":"+49 3831/390112",
    "sg:postcode":"18435",
    "sg:province":"Mecklenburg-Vorpommern",
    "wof:name":"Dr. Med. Bernd Freitag",
    "wof:placetype":"venue"
},
  "geometry": {"coordinates":[13.07372,54.318581],"type":"Point"}
}