{
  "type": "Feature",
  "properties": {
    "iso:country":"DE",
    "sg:address":"Bosettistr. 4",
    "sg:city":"M\u00fcnchen",
    "sg:postcode":"81247",
    "sg:province":"Bayern",
    "wof:name":"Achill Ag",
    "wof:placetype":"venue"
},
  "geometry": {"coordinates":[11.467269,48.17054],"type":"Point"}
}