{
  "type": "Feature",
  "properties": {
    "iso:country":"DE",
    "sg:address":"Vollmerhauser Str. 52",
    "sg:city":"Gummersbach",
    "sg:postcode":"51645",
    "sg:province":"Nordrhein-Westfalen",
    "wof:name":"Holzbau Ohg",
    "wof:placetype":"venue"
},
  "geometry": {"coordinates":[7.555034,50.989922],"type":"Point"}
}