{
  "type": "Feature",
  "properties": {
    "iso:country":"DE",
    "sg:address":"Belmer Stra\u00dfe 330",
    "sg:city":"Osnabr\u00fcck",
    "sg:phone":"+49 541/37182",
    "sg:postcode":"49086",
    "sg:province":"Niedersachsen",
    "wof:name":"Heinrich Duhme Gmbh",
    "wof:placetype":"venue"
},
  "geometry": {"coordinates":[8.1190099716,52.2783584595],"type":"Point"}
}