{
  "type": "Feature",
  "properties": {
    "iso:country":"DE",
    "sg:address":"Neum\u00fchler Str. 1",
    "sg:city":"Amberg",
    "sg:phone":"+49 9621/673383",
    "sg:postcode":"92224",
    "sg:province":"Bayern",
    "wof:name":"Comet",
    "wof:placetype":"venue"
},
  "geometry": {"coordinates":[11.8503541946,49.4688148499],"type":"Point"}
}