{
  "type": "Feature",
  "properties": {
    "iso:country":"DE",
    "sg:address":"Weddigenstr. 27",
    "sg:city":"M\u00fcnchen",
    "sg:postcode":"81737",
    "sg:province":"Bayern",
    "wof:name":"Money Plus E. K.",
    "wof:placetype":"venue"
},
  "geometry": {"coordinates":[11.6264734268,48.1048088074],"type":"Point"}
}