{
  "type": "Feature",
  "properties": {
    "iso:country":"DE",
    "sg:address":"Hohe Geest 106",
    "sg:city":"M\u00fcnster",
    "sg:phone":"+49 2501/6596",
    "sg:postcode":"48165",
    "sg:province":"Nordrhein-Westfalen",
    "wof:name":"M. Wilmes",
    "wof:placetype":"venue"
},
  "geometry": {"coordinates":[7.6369838715,51.9119796753],"type":"Point"}
}