{
  "type": "Feature",
  "properties": {
    "iso:country":"DE",
    "sg:address":"Am Schwimmbad",
    "sg:city":"Fr\u00f6ndenberg",
    "sg:phone":"+49 2378/2504",
    "sg:postcode":"58730",
    "sg:province":"Nordrhein-Westfalen",
    "wof:name":"Freibad",
    "wof:placetype":"venue"
},
  "geometry": {"coordinates":[7.6931362152,51.4820175171],"type":"Point"}
}