{
  "type": "Feature",
  "properties": {
    "iso:country":"DE",
    "sg:address":"Dorfstr. 23-25",
    "sg:city":"Idar-Oberstein",
    "sg:phone":"+49 6784/2547",
    "sg:postcode":"55743",
    "sg:province":"Rheinland-Pfalz",
    "wof:name":"Kleiderfabrik Deckert Ohg",
    "wof:placetype":"venue"
},
  "geometry": {"coordinates":[7.396597,49.725826],"type":"Point"}
}