{
  "type": "Feature",
  "properties": {
    "iso:country":"DE",
    "sg:address":"L\u00fcnsingskuhle 20",
    "sg:city":"Dorsten",
    "sg:phone":"+49 2362/3024",
    "sg:postcode":"46282",
    "sg:province":"Nordrhein-Westfalen",
    "wof:name":"Spedition Markus Nitz Gmbh",
    "wof:placetype":"venue"
},
  "geometry": {"coordinates":[7.015250206,51.6588745117],"type":"Point"}
}