{
  "type": "Feature",
  "properties": {
    "iso:country":"DE",
    "sg:address":"Dorfstr. 11",
    "sg:city":"Haibach",
    "sg:phone":"+49 6021/610400",
    "sg:postcode":"63808",
    "sg:province":"Bayern",
    "wof:name":"Kpl Finanz- Und Versicherungs- Makler Kompetent Preisbewu\u00dft",
    "wof:placetype":"venue"
},
  "geometry": {"coordinates":[9.2124567032,49.9602890015],"type":"Point"}
}