{
  "type": "Feature",
  "properties": {
    "iso:country":"DE",
    "sg:address":"D\u00f6rrh\u00f6fer Weg 14",
    "sg:city":"Rosenberg",
    "sg:phone":"+49 6295/92000",
    "sg:postcode":"74749",
    "sg:province":"Baden-W\u00fcrttemberg",
    "wof:name":"Bleichert-rohr Gmbh",
    "wof:placetype":"venue"
},
  "geometry": {"coordinates":[9.468308,49.457817],"type":"Point"}
}