{
  "type": "Feature",
  "properties": {
    "iso:country":"DE",
    "sg:address":"Karlstr. 11",
    "sg:city":"Gerstetten",
    "sg:phone":"+49 7323/5602",
    "sg:postcode":"89547",
    "sg:province":"Baden-W\u00fcrttemberg",
    "wof:name":"J. Junginger",
    "wof:placetype":"venue"
},
  "geometry": {"coordinates":[10.01949,48.623653],"type":"Point"}
}