{
  "type": "Feature",
  "properties": {
    "iso:country":"DE",
    "sg:address":"Breitscheidstr. 26",
    "sg:city":"Gotha",
    "sg:phone":"+49 3621/401170",
    "sg:postcode":"99867",
    "sg:province":"Th\u00fcringen",
    "wof:name":"Annette Rieger",
    "wof:placetype":"venue"
},
  "geometry": {"coordinates":[10.7232255936,50.9434928894],"type":"Point"}
}