{
  "type": "Feature",
  "properties": {
    "iso:country":"DE",
    "sg:address":"Am End 2",
    "sg:city":"M\u00f6nchengladbach",
    "sg:phone":"+49 2166/30707",
    "sg:postcode":"41189",
    "sg:province":"Nordrhein-Westfalen",
    "wof:name":"Helmut Rechner Bedachungs Gmbh",
    "wof:placetype":"venue"
},
  "geometry": {"coordinates":[6.3815999031,51.1067314148],"type":"Point"}
}