{
  "type": "Feature",
  "properties": {
    "iso:country":"DE",
    "sg:address":"K\u00f6nigstr. 47",
    "sg:city":"Bad Laasphe",
    "sg:phone":"+49 2752/9419",
    "sg:postcode":"57334",
    "sg:province":"Nordrhein-Westfalen",
    "wof:name":"Werner Schuppert",
    "wof:placetype":"venue"
},
  "geometry": {"coordinates":[8.40738,50.927422],"type":"Point"}
}