{
  "type": "Feature",
  "properties": {
    "iso:country":"DE",
    "sg:address":"Kirchstr. 43",
    "sg:city":"Ludwigsh\u00f6he",
    "sg:phone":"+49 6249/1565",
    "sg:postcode":"55278",
    "sg:province":"Rheinland-Pfalz",
    "wof:name":"Siegfried Best Weingut Winckler",
    "wof:placetype":"venue"
},
  "geometry": {"coordinates":[8.3492879868,49.8161659241],"type":"Point"}
}