{
  "type": "Feature",
  "properties": {
    "iso:country":"DE",
    "sg:address":"Eggerstr. 2",
    "sg:city":"Deggendorf",
    "sg:phone":"+49 991/38760",
    "sg:postcode":"94469",
    "sg:province":"Bayern",
    "wof:name":"Sparkasse Deggendorf",
    "wof:placetype":"venue"
},
  "geometry": {"coordinates":[12.957148,48.841736],"type":"Point"}
}