{
  "type": "Feature",
  "properties": {
    "iso:country":"DE",
    "sg:address":"Denisstr. 12-14",
    "sg:city":"Kaiserslautern",
    "sg:postcode":"67663",
    "sg:province":"Rheinland-Pfalz",
    "wof:name":"Pirminus Teeverarbeitungs- Und Vertriebsgesellschaft Mbh",
    "wof:placetype":"venue"
},
  "geometry": {"coordinates":[7.7247581482,49.4450912476],"type":"Point"}
}