{
  "type": "Feature",
  "properties": {
    "iso:country":"DE",
    "sg:address":"Campingstr. 81",
    "sg:city":"Erlangen",
    "sg:phone":"+49 9135/6893",
    "sg:postcode":"91056",
    "sg:province":"Bayern",
    "wof:name":"Bierg\u00e4rtla",
    "wof:placetype":"venue"
},
  "geometry": {"coordinates":[10.9523229599,49.6289901733],"type":"Point"}
}