{
  "type": "Feature",
  "properties": {
    "iso:country":"DE",
    "sg:address":"Iphofener Str. 3a",
    "sg:city":"N\u00fcrnberg",
    "sg:phone":"+49 911/3071342",
    "sg:postcode":"90427",
    "sg:province":"Bayern",
    "wof:name":"Peter Tost",
    "wof:placetype":"venue"
},
  "geometry": {"coordinates":[11.01537323,49.5241127014],"type":"Point"}
}