{
  "type": "Feature",
  "properties": {
    "iso:country":"DE",
    "sg:address":"Ledergasse 53",
    "sg:city":"Schw\u00e4bisch Gm\u00fcnd",
    "sg:phone":"+49 7171/65203",
    "sg:postcode":"73525",
    "sg:province":"Baden-W\u00fcrttemberg",
    "wof:name":"E. Quiten Augenoptiker",
    "wof:placetype":"venue"
},
  "geometry": {"coordinates":[9.7934160233,48.8006477356],"type":"Point"}
}