{
  "type": "Feature",
  "properties": {
    "iso:country":"DE",
    "sg:address":"Burgundenstra\u00dfe 6",
    "sg:city":"Bockenheim",
    "sg:phone":"+49 6359/4922",
    "sg:postcode":"67278",
    "sg:province":"Rheinland-Pfalz",
    "wof:name":"Ddc-dr. Dingler Consulting Gmbh",
    "wof:placetype":"venue"
},
  "geometry": {"coordinates":[8.1790208817,49.6052322388],"type":"Point"}
}