{
  "type": "Feature",
  "properties": {
    "iso:country":"DE",
    "sg:address":"Kirschbusch 18",
    "sg:city":"Fritzlar",
    "sg:phone":"+49 5622/4800",
    "sg:postcode":"34560",
    "sg:province":"Hessen",
    "wof:name":"Roland Ninke",
    "wof:placetype":"venue"
},
  "geometry": {"coordinates":[9.25020504,51.1396751404],"type":"Point"}
}