{
  "type": "Feature",
  "properties": {
    "iso:country":"DE",
    "sg:address":"Riedstr. 22",
    "sg:city":"Bingen",
    "sg:phone":"+49 7571/13254",
    "sg:postcode":"72511",
    "sg:province":"Baden-W\u00fcrttemberg",
    "wof:name":"Gastst\u00e4tte Willi Obert",
    "wof:placetype":"venue"
},
  "geometry": {"coordinates":[9.2869777679,48.1064147949],"type":"Point"}
}