{
  "type": "Feature",
  "properties": {
    "iso:country":"DE",
    "sg:address":"Herrengasse 18",
    "sg:city":"Eckental",
    "sg:phone":"+49 9126/1850",
    "sg:postcode":"90542",
    "sg:province":"Bayern",
    "wof:name":"Hans Schmidt",
    "wof:placetype":"venue"
},
  "geometry": {"coordinates":[11.1988840103,49.5723953247],"type":"Point"}
}