{
  "type": "Feature",
  "properties": {
    "iso:country":"DE",
    "sg:address":"K\u00f6lner Str. 117",
    "sg:city":"Bergheim",
    "sg:phone":"+49 2271/767756",
    "sg:postcode":"50126",
    "sg:province":"Nordrhein-Westfalen",
    "wof:name":"Hans Sch\u00e4fer",
    "wof:placetype":"venue"
},
  "geometry": {"coordinates":[6.6552090645,50.9503326416],"type":"Point"}
}