{
  "type": "Feature",
  "properties": {
    "iso:country":"DE",
    "sg:address":"Ernst-Mehlich-Str. 4 a",
    "sg:city":"Dortmund",
    "sg:postcode":"44141",
    "sg:province":"Nordrhein-Westfalen",
    "wof:name":"Pv-engineering Gmbh",
    "wof:placetype":"venue"
},
  "geometry": {"coordinates":[7.4724550247,51.5072784424],"type":"Point"}
}