{
  "type": "Feature",
  "properties": {
    "iso:country":"DE",
    "sg:address":"Halener Str. 96",
    "sg:city":"Duisburg",
    "sg:phone":"+49 2066/55163",
    "sg:postcode":"47198",
    "sg:province":"Nordrhein-Westfalen",
    "wof:name":"K\u00f6nig Quelle",
    "wof:placetype":"venue"
},
  "geometry": {"coordinates":[6.6923742294,51.4631538391],"type":"Point"}
}