{
  "type": "Feature",
  "properties": {
    "iso:country":"DE",
    "sg:address":"Schrakampstr. 10",
    "sg:city":"L\u00f6hne",
    "sg:phone":"+49 5732/6460",
    "sg:postcode":"32584",
    "sg:province":"Nordrhein-Westfalen",
    "wof:name":"Ev. Pfarramt Ev. Freikirchl. Gemeinde",
    "wof:placetype":"venue"
},
  "geometry": {"coordinates":[8.7204303741,52.1989974976],"type":"Point"}
}