{
  "type": "Feature",
  "properties": {
    "iso:country":"DE",
    "sg:address":"Alt-Rudow 31",
    "sg:city":"Berlin",
    "sg:phone":"+49 30/6632971",
    "sg:postcode":"12357",
    "sg:province":"Berlin",
    "wof:name":"Mohamed Madarati",
    "wof:placetype":"venue"
},
  "geometry": {"coordinates":[13.4934549332,52.4195976257],"type":"Point"}
}