{
  "type": "Feature",
  "properties": {
    "iso:country":"DE",
    "sg:address":"Mozartstr. 1",
    "sg:city":"Butzbach",
    "sg:phone":"+49 6033/65617",
    "sg:postcode":"35510",
    "sg:province":"Hessen",
    "wof:name":"Ulrike Schwarz",
    "wof:placetype":"venue"
},
  "geometry": {"coordinates":[8.6546201706,50.4422187805],"type":"Point"}
}