{
  "type": "Feature",
  "properties": {
    "iso:country":"DE",
    "sg:address":"Braunkohlenrevier Profen",
    "sg:city":"Profen",
    "sg:postcode":"06725",
    "sg:province":"Sachsen-Anhalt",
    "wof:name":"Roba Quarzitsplittwerk Profen Gmbh",
    "wof:placetype":"venue"
},
  "geometry": {"coordinates":[12.2067098618,51.1212310791],"type":"Point"}
}