{
  "type": "Feature",
  "properties": {
    "iso:country":"DE",
    "sg:address":"S\u00fcdstr. 131",
    "sg:city":"Backnang",
    "sg:phone":"+49 7191/65372",
    "sg:postcode":"71522",
    "sg:province":"Baden-W\u00fcrttemberg",
    "wof:name":"Dr. Erhard Beck Tierarzt",
    "wof:placetype":"venue"
},
  "geometry": {"coordinates":[9.42116642,48.9394836426],"type":"Point"}
}