{
  "type": "Feature",
  "properties": {
    "iso:country":"DE",
    "sg:address":"Friedrichstr. 17",
    "sg:city":"Heppenheim",
    "sg:phone":"+49 6252/2610",
    "sg:postcode":"64646",
    "sg:province":"Hessen",
    "wof:name":"Hillenbrand-herold",
    "wof:placetype":"venue"
},
  "geometry": {"coordinates":[8.64116,49.642609],"type":"Point"}
}