{
  "type": "Feature",
  "properties": {
    "iso:country":"DE",
    "sg:address":"Hauptstr. 27",
    "sg:city":"Reichenbach-Steegen",
    "sg:phone":"+49 6385/277",
    "sg:postcode":"66879",
    "sg:province":"Rheinland-Pfalz",
    "wof:name":"L. Andres",
    "wof:placetype":"venue"
},
  "geometry": {"coordinates":[7.536951,49.502178],"type":"Point"}
}