{
  "type": "Feature",
  "properties": {
    "iso:country":"DE",
    "sg:address":"Teutoburger Str. 232",
    "sg:city":"Oberhausen",
    "sg:phone":"+49 208/600195",
    "sg:postcode":"46119",
    "sg:province":"Nordrhein-Westfalen",
    "wof:name":"Anneliese Lemmen Inh. Frank Maschewski",
    "wof:placetype":"venue"
},
  "geometry": {"coordinates":[6.885547,51.518211],"type":"Point"}
}