{
  "type": "Feature",
  "properties": {
    "iso:country":"DE",
    "sg:address":"Lilienstr. 54",
    "sg:city":"M\u00fcnchen",
    "sg:postcode":"81669",
    "sg:province":"Bayern",
    "wof:name":"Backshop Fachbetr. F\u00fcr Ortho- P\u00e4dische Korsette Band. Und",
    "wof:placetype":"venue"
},
  "geometry": {"coordinates":[11.5848178864,48.1280937195],"type":"Point"}
}