{
  "type": "Feature",
  "properties": {
    "iso:country":"DE",
    "sg:address":"Egerer Str. 27b",
    "sg:city":"Stuttgart",
    "sg:phone":"+49 711/7280523",
    "sg:postcode":"70567",
    "sg:province":"Baden-W\u00fcrttemberg",
    "wof:name":"Dr. Sch\u00e4ffler-expert Gmbh",
    "wof:placetype":"venue"
},
  "geometry": {"coordinates":[9.157746,48.729023],"type":"Point"}
}