{
  "type": "Feature",
  "properties": {
    "iso:country":"DE",
    "sg:address":"Puttschen 43",
    "sg:city":"M\u00f6nchengladbach",
    "sg:phone":"+49 2166/859954",
    "sg:postcode":"41238",
    "sg:province":"Nordrhein-Westfalen",
    "wof:name":"J\u00e4ger",
    "wof:placetype":"venue"
},
  "geometry": {"coordinates":[6.4907331467,51.1668891907],"type":"Point"}
}