{
  "type": "Feature",
  "properties": {
    "iso:country":"DE",
    "sg:address":"Nossener Str. 28",
    "sg:city":"Ro\u00dfwein",
    "sg:phone":"+49 34322/42264",
    "sg:postcode":"04741",
    "sg:province":"Sachsen",
    "wof:name":"Lothar Beyer",
    "wof:placetype":"venue"
},
  "geometry": {"coordinates":[13.1876220703,51.064907074],"type":"Point"}
}