{
  "type": "Feature",
  "properties": {
    "iso:country":"DE",
    "sg:address":"Ellerstr. 5",
    "sg:city":"Hilden",
    "sg:phone":"+49 2103/53347",
    "sg:postcode":"40721",
    "sg:province":"Nordrhein-Westfalen",
    "wof:name":"Wilfried Balkenhol",
    "wof:placetype":"venue"
},
  "geometry": {"coordinates":[6.92789,51.168671],"type":"Point"}
}