{
  "type": "Feature",
  "properties": {
    "iso:country":"DE",
    "sg:address":"Schmalkalder Str.",
    "sg:city":"Christes",
    "sg:postcode":"98547",
    "sg:province":"Th\u00fcringen",
    "wof:name":"Haushaltswaren Gmbh",
    "wof:placetype":"venue"
},
  "geometry": {"coordinates":[10.476644,50.662228],"type":"Point"}
}