{
  "type": "Feature",
  "properties": {
    "iso:country":"DE",
    "sg:address":"Ermlandstr. 2",
    "sg:city":"Neu-Ulm",
    "sg:phone":"+49 731/9717200",
    "sg:postcode":"89233",
    "sg:province":"Bayern",
    "wof:name":"Sabine Retter Ergotherapiepraxis",
    "wof:placetype":"venue"
},
  "geometry": {"coordinates":[10.033111,48.407211],"type":"Point"}
}