{
  "type": "Feature",
  "properties": {
    "iso:country":"DE",
    "sg:address":"Hauptstr. 55",
    "sg:city":"Roschbach",
    "sg:phone":"+49 6323/2271",
    "sg:postcode":"76835",
    "sg:province":"Rheinland-Pfalz",
    "wof:name":"Walter Minges",
    "wof:placetype":"venue"
},
  "geometry": {"coordinates":[8.1203813553,49.2469825745],"type":"Point"}
}