{
  "type": "Feature",
  "properties": {
    "iso:country":"DE",
    "sg:address":"Hamminkelner Landstr. 58",
    "sg:city":"Wesel",
    "sg:phone":"+49 281/61400",
    "sg:postcode":"46483",
    "sg:province":"Nordrhein-Westfalen",
    "wof:name":"Dieter Hertrampf Inh. Hans-dieter Hertrampf",
    "wof:placetype":"venue"
},
  "geometry": {"coordinates":[6.609553,51.68082],"type":"Point"}
}