{
  "type": "Feature",
  "properties": {
    "iso:country":"DE",
    "sg:address":"Landgrafenstieg 3a",
    "sg:city":"Jena",
    "sg:phone":"+49 3641/829362",
    "sg:postcode":"07743",
    "sg:province":"Th\u00fcringen",
    "wof:name":"Adam-werbung",
    "wof:placetype":"venue"
},
  "geometry": {"coordinates":[11.5832834244,50.934803009],"type":"Point"}
}