{
  "type": "Feature",
  "properties": {
    "iso:country":"DE",
    "sg:address":"Nadorster Str. 126",
    "sg:city":"Oldenburg",
    "sg:phone":"+49 441/81969",
    "sg:postcode":"26123",
    "sg:province":"Niedersachsen",
    "wof:name":"Eis-cafe",
    "wof:placetype":"venue"
},
  "geometry": {"coordinates":[8.220172,53.15527],"type":"Point"}
}