{
  "type": "Feature",
  "properties": {
    "iso:country":"DE",
    "sg:address":"D\u00e4fernstr. 11-13",
    "sg:city":"Auenwald",
    "sg:phone":"+49 7191/35350",
    "sg:postcode":"71549",
    "sg:province":"Baden-W\u00fcrttemberg",
    "wof:name":"August Wendler Ohg",
    "wof:placetype":"venue"
},
  "geometry": {"coordinates":[9.524042,48.928596],"type":"Point"}
}