{
  "type": "Feature",
  "properties": {
    "iso:country":"DE",
    "sg:address":"H\u00f6festr 34",
    "sg:city":"Hannover",
    "sg:phone":"+49 511/671055",
    "sg:postcode":"30163",
    "sg:province":"Niedersachsen",
    "wof:name":"Verlagshaus Hans-joachim Schmidt Gmbh",
    "wof:placetype":"venue"
},
  "geometry": {"coordinates":[9.7542409897,52.3964691162],"type":"Point"}
}