{
  "type": "Feature",
  "properties": {
    "iso:country":"DE",
    "sg:address":"Alte Str. 3",
    "sg:city":"Willingshausen",
    "sg:phone":"+49 6697/579",
    "sg:postcode":"34628",
    "sg:province":"Hessen",
    "wof:name":"Hans Faust",
    "wof:placetype":"venue"
},
  "geometry": {"coordinates":[9.202389,50.852779],"type":"Point"}
}