{
  "type": "Feature",
  "properties": {
    "iso:country":"DE",
    "sg:address":"Adolf-Reichwein-Str. 9-11",
    "sg:city":"Rosbach",
    "sg:phone":"+49 6003/1359",
    "sg:postcode":"61191",
    "sg:province":"Hessen",
    "wof:name":"Karl G. Rahn Spedition Gmbh",
    "wof:placetype":"venue"
},
  "geometry": {"coordinates":[8.6935434341,50.303604126],"type":"Point"}
}