{
  "type": "Feature",
  "properties": {
    "iso:country":"DE",
    "sg:address":"Poststr. 4",
    "sg:city":"Friedrichshafen",
    "sg:phone":"+49 7541/41667",
    "sg:postcode":"88048",
    "sg:province":"Baden-W\u00fcrttemberg",
    "wof:name":"Andrea Bubeck",
    "wof:placetype":"venue"
},
  "geometry": {"coordinates":[9.4152889252,47.6699981689],"type":"Point"}
}