{
  "type": "Feature",
  "properties": {
    "iso:country":"DE",
    "sg:address":"Neugasse 2",
    "sg:city":"Merxheim",
    "sg:postcode":"55627",
    "sg:province":"Rheinland-Pfalz",
    "wof:name":"Bib Beton-industrieb\u00f6den Gmbh",
    "wof:placetype":"venue"
},
  "geometry": {"coordinates":[7.5602622032,49.7944412231],"type":"Point"}
}