{
  "type": "Feature",
  "properties": {
    "iso:country":"DE",
    "sg:address":"Am Bahnhofsplatz 8",
    "sg:city":"Gaggenau",
    "sg:phone":"+49 4972/16830",
    "sg:postcode":"76571",
    "sg:province":"Baden-W\u00fcrttemberg",
    "wof:name":"Stadtsparkasse Gaggenau",
    "wof:placetype":"venue"
},
  "geometry": {"coordinates":[8.319709,48.805286],"type":"Point"}
}