{
  "type": "Feature",
  "properties": {
    "iso:country":"DE",
    "sg:address":"Bahnhofstr 25-27",
    "sg:city":"Remshalden",
    "sg:phone":"+49 7151/977710",
    "sg:postcode":"73630",
    "sg:province":"Baden-W\u00fcrttemberg",
    "wof:name":"Bornschlegl-software & Systems Gmbh",
    "wof:placetype":"venue"
},
  "geometry": {"coordinates":[9.41867,48.814739],"type":"Point"}
}