{
  "type": "Feature",
  "properties": {
    "iso:country":"DE",
    "sg:address":"Klempauer Str. 24",
    "sg:city":"Krummesse",
    "sg:phone":"+49 4508/318",
    "sg:postcode":"23628",
    "sg:province":"Schleswig-Holstein",
    "wof:name":"Dietrich Klemp",
    "wof:placetype":"venue"
},
  "geometry": {"coordinates":[10.6430397034,53.779548645],"type":"Point"}
}