{
  "type": "Feature",
  "properties": {
    "iso:country":"DE",
    "sg:address":"Seelhorster Str. 19",
    "sg:city":"Petershagen",
    "sg:phone":"+49 5726/648",
    "sg:postcode":"32469",
    "sg:province":"Nordrhein-Westfalen",
    "wof:name":"Christiane Albach",
    "wof:placetype":"venue"
},
  "geometry": {"coordinates":[9.1198177338,52.4076538086],"type":"Point"}
}