{
  "type": "Feature",
  "properties": {
    "iso:country":"DE",
    "sg:address":"Adelmannsgasse 1",
    "sg:city":"Ellwangen",
    "sg:phone":"+49 7961/6734",
    "sg:postcode":"73479",
    "sg:province":"Baden-W\u00fcrttemberg",
    "wof:name":"Welt Weit Touristik",
    "wof:placetype":"venue"
},
  "geometry": {"coordinates":[10.1346120834,48.9611473083],"type":"Point"}
}