{
  "type": "Feature",
  "properties": {
    "iso:country":"DE",
    "sg:address":"Stein\u00e4ckerstr. 21",
    "sg:city":"Sulz",
    "sg:phone":"+49 7454/8674",
    "sg:postcode":"72172",
    "sg:province":"Baden-W\u00fcrttemberg",
    "wof:name":"Hubert Hipp",
    "wof:placetype":"venue"
},
  "geometry": {"coordinates":[8.674004,48.387905],"type":"Point"}
}