{
  "type": "Feature",
  "properties": {
    "iso:country":"DE",
    "sg:address":"Rosmarinstr. 12",
    "sg:city":"D\u00fcsseldorf",
    "sg:phone":"+49 211/236328",
    "sg:postcode":"40235",
    "sg:province":"Nordrhein-Westfalen",
    "wof:name":"J. Storch",
    "wof:placetype":"venue"
},
  "geometry": {"coordinates":[6.8219871521,51.2290458679],"type":"Point"}
}