{
  "type": "Feature",
  "properties": {
    "iso:country":"DE",
    "sg:address":"Ulmenweg 63",
    "sg:city":"Zwickau",
    "sg:phone":"+49 375/523360",
    "sg:postcode":"08060",
    "sg:province":"Sachsen",
    "wof:name":"Dr. Med. Frank Dr\u00f6\u00dfler",
    "wof:placetype":"venue"
},
  "geometry": {"coordinates":[12.440343,50.729889],"type":"Point"}
}