{
  "type": "Feature",
  "properties": {
    "iso:country":"DE",
    "sg:address":"Heidenfahrt 24",
    "sg:city":"Heidesheim",
    "sg:phone":"+49 6132/58984",
    "sg:postcode":"55262",
    "sg:province":"Rheinland-Pfalz",
    "wof:name":"Georg Bieger",
    "wof:placetype":"venue"
},
  "geometry": {"coordinates":[8.098347,50.009014],"type":"Point"}
}