{
  "type": "Feature",
  "properties": {
    "iso:country":"DE",
    "sg:address":"Am Schliepsteiner Tor 1",
    "sg:city":"Bad Salzuflen",
    "sg:phone":"+49 5222/16161",
    "sg:postcode":"32105",
    "sg:province":"Nordrhein-Westfalen",
    "wof:name":"Hans Leo Firmenich",
    "wof:placetype":"venue"
},
  "geometry": {"coordinates":[8.7453,52.086632],"type":"Point"}
}