{
  "type": "Feature",
  "properties": {
    "iso:country":"DE",
    "sg:address":"Rheinstr. 21",
    "sg:city":"Trier",
    "sg:phone":"+49 651/53299",
    "sg:postcode":"54292",
    "sg:province":"Rheinland-Pfalz",
    "wof:name":"Jochen M\u00fcller Drogerie",
    "wof:placetype":"venue"
},
  "geometry": {"coordinates":[6.709243,49.785038],"type":"Point"}
}