{
  "type": "Feature",
  "properties": {
    "iso:country":"DE",
    "sg:address":"Degernauer Str.",
    "sg:city":"Wut\u00f6schingen",
    "sg:phone":"+49 7746/920928",
    "sg:postcode":"79793",
    "sg:province":"Baden-W\u00fcrttemberg",
    "wof:name":"Aluminium Konstruktionsteile Gmbh",
    "wof:placetype":"venue"
},
  "geometry": {"coordinates":[8.368177,47.663517],"type":"Point"}
}