{
  "type": "Feature",
  "properties": {
    "iso:country":"DE",
    "sg:address":"Sonnenstr. 49",
    "sg:city":"Landstuhl",
    "sg:phone":"+49 6371/2717",
    "sg:postcode":"66849",
    "sg:province":"Rheinland-Pfalz",
    "wof:name":"Alfred Ultes",
    "wof:placetype":"venue"
},
  "geometry": {"coordinates":[7.5746350288,49.4007034302],"type":"Point"}
}