{
  "type": "Feature",
  "properties": {
    "iso:country":"DE",
    "sg:address":"Eichendorffstr.",
    "sg:city":"Erfurt",
    "sg:phone":"+49 361/3459094",
    "sg:postcode":"99096",
    "sg:province":"Th\u00fcringen",
    "wof:name":"Florito Blumenhandelsges. Mbh",
    "wof:placetype":"venue"
},
  "geometry": {"coordinates":[11.025905,50.962128],"type":"Point"}
}