{
  "type": "Feature",
  "properties": {
    "iso:country":"DE",
    "sg:address":"78357",
    "sg:city":"M\u00fchlingen",
    "sg:phone":"+49 7775/19222",
    "sg:postcode":"78357",
    "sg:province":"Baden-W\u00fcrttemberg",
    "wof:name":"Deutsches Rotes Kreuz",
    "wof:placetype":"venue"
},
  "geometry": {"coordinates":[9.015545,47.911919],"type":"Point"}
}