{
  "type": "Feature",
  "properties": {
    "iso:country":"DE",
    "sg:address":"Forstweg 3",
    "sg:city":"Greiz",
    "sg:phone":"+49 3661/3044",
    "sg:postcode":"07973",
    "sg:province":"Th\u00fcringen",
    "wof:name":"A. Dietzel",
    "wof:placetype":"venue"
},
  "geometry": {"coordinates":[12.1789512634,50.6412200928],"type":"Point"}
}