{
  "type": "Feature",
  "properties": {
    "iso:country":"DE",
    "sg:address":"Gutenbergstr. 55",
    "sg:city":"Hamburg",
    "sg:phone":"+49 40/5400820",
    "sg:postcode":"22525",
    "sg:province":"Hamburg",
    "wof:name":"Hans Dassler Gmbh & Co. Kg",
    "wof:placetype":"venue"
},
  "geometry": {"coordinates":[9.9247150421,53.5872116089],"type":"Point"}
}