{
  "type": "Feature",
  "properties": {
    "iso:country":"DE",
    "sg:address":"Langwiese 24",
    "sg:city":"Maintal",
    "sg:phone":"+49 6109/66881",
    "sg:postcode":"63477",
    "sg:province":"Hessen",
    "wof:name":"R. M. Hofmann Gmbh",
    "wof:placetype":"venue"
},
  "geometry": {"coordinates":[8.806025,50.154102],"type":"Point"}
}