{
  "type": "Feature",
  "properties": {
    "iso:country":"DE",
    "sg:address":"Frieth\u00f6fer Kamp 1",
    "sg:city":"Billerbeck",
    "sg:postcode":"48727",
    "sg:province":"Nordrhein-Westfalen",
    "wof:name":"Bbf Besitz- Und Beteiligungsgesellschaft Mbh",
    "wof:placetype":"venue"
},
  "geometry": {"coordinates":[7.2834210396,51.9693489075],"type":"Point"}
}