{
  "type": "Feature",
  "properties": {
    "iso:country":"DE",
    "sg:address":"Karl-Laux-Str. 52",
    "sg:city":"Dresden",
    "sg:phone":"+49 351/2753932",
    "sg:postcode":"01219",
    "sg:province":"Sachsen",
    "wof:name":"Kathrin Kunze",
    "wof:placetype":"venue"
},
  "geometry": {"coordinates":[13.7761535645,51.0111885071],"type":"Point"}
}