{
  "type": "Feature",
  "properties": {
    "iso:country":"DE",
    "sg:address":"Schlachthofstr. 3",
    "sg:city":"Zwickau",
    "sg:phone":"+49 375/301017",
    "sg:postcode":"08058",
    "sg:province":"Sachsen",
    "wof:name":"Fleitec Dietmar Kallweit Fleischereibedarf",
    "wof:placetype":"venue"
},
  "geometry": {"coordinates":[12.48419,50.735725],"type":"Point"}
}