{
  "type": "Feature",
  "properties": {
    "iso:country":"DE",
    "sg:address":"Niedervellmarer Str. 8",
    "sg:city":"Kassel",
    "sg:phone":"+49 4956/1983840",
    "sg:postcode":"34127",
    "sg:province":"Hessen",
    "wof:name":"Sch\u00c4fer Tapeten Walther Sch\u00c4fer",
    "wof:placetype":"venue"
},
  "geometry": {"coordinates":[9.4884414673,51.3388938904],"type":"Point"}
}