{
  "type": "Feature",
  "properties": {
    "iso:country":"DE",
    "sg:address":"K\u00f6lner Str. 16",
    "sg:city":"Stuttgart",
    "sg:phone":"+49 711/9559760",
    "sg:postcode":"70376",
    "sg:province":"Baden-W\u00fcrttemberg",
    "wof:name":"Phoenix Product Design",
    "wof:placetype":"venue"
},
  "geometry": {"coordinates":[9.204267,48.819664],"type":"Point"}
}