{
  "type": "Feature",
  "properties": {
    "iso:country":"DE",
    "sg:address":"Gartenstr. 12",
    "sg:city":"Letschin",
    "sg:postcode":"15324",
    "sg:province":"Brandenburg",
    "wof:name":"Allianz Versicherungs Ag",
    "wof:placetype":"venue"
},
  "geometry": {"coordinates":[14.363240242,52.645198822],"type":"Point"}
}