{
  "type": "Feature",
  "properties": {
    "iso:country":"DE",
    "sg:address":"Eugen-Richter-Str. 33",
    "sg:city":"K\u00f6lleda",
    "sg:phone":"+49 3635/46030",
    "sg:postcode":"99625",
    "sg:province":"Th\u00fcringen",
    "wof:name":"Agrar- Und Transportservice K\u00f6lleda Gmbh",
    "wof:placetype":"venue"
},
  "geometry": {"coordinates":[11.2266378403,51.1835021973],"type":"Point"}
}