{
  "type": "Feature",
  "properties": {
    "iso:country":"DE",
    "sg:address":"Unteraicher Weg 3",
    "sg:city":"Leinfelden-Echterdingen",
    "sg:phone":"+49 711/7543011",
    "sg:postcode":"70771",
    "sg:province":"Baden-W\u00fcrttemberg",
    "wof:name":"Varionorm Gesellschaft F\u00fcr Flexiblen Wohnbau Mbh",
    "wof:placetype":"venue"
},
  "geometry": {"coordinates":[9.12377,48.695236],"type":"Point"}
}