{
  "type": "Feature",
  "properties": {
    "iso:country":"DE",
    "sg:address":"Gretchenstr. 31",
    "sg:city":"Hannover",
    "sg:phone":"+49 511/3482275",
    "sg:postcode":"30161",
    "sg:province":"Niedersachsen",
    "wof:name":"Eva-maria Eilhardt Architektin",
    "wof:placetype":"venue"
},
  "geometry": {"coordinates":[9.752114,52.384109],"type":"Point"}
}