{
  "type": "Feature",
  "properties": {
    "iso:country":"DE",
    "sg:address":"Ortsstr. 27",
    "sg:city":"Dachsbach",
    "sg:phone":"+49 9163/348",
    "sg:postcode":"91462",
    "sg:province":"Bayern",
    "wof:name":"Holztreppenbau R. B\u00e4rthlein",
    "wof:placetype":"venue"
},
  "geometry": {"coordinates":[10.6977949142,49.6494369507],"type":"Point"}
}