{
  "type": "Feature",
  "properties": {
    "iso:country":"DE",
    "sg:address":"Forstallee 64-68",
    "sg:city":"Zeuthen",
    "sg:phone":"+49 33762/756",
    "sg:postcode":"15738",
    "sg:province":"Brandenburg",
    "wof:name":"Berlux Gmbh",
    "wof:placetype":"venue"
},
  "geometry": {"coordinates":[13.6164503098,52.3452072144],"type":"Point"}
}