{
  "type": "Feature",
  "properties": {
    "iso:country":"DE",
    "sg:address":"Kollaustr. 91-93",
    "sg:city":"Hamburg",
    "sg:phone":"+49 40/580033",
    "sg:postcode":"22453",
    "sg:province":"Hamburg",
    "wof:name":"Cr Cyron Und Reitenbach Gmbh",
    "wof:placetype":"venue"
},
  "geometry": {"coordinates":[9.9607477188,53.6071777344],"type":"Point"}
}