{
  "type": "Feature",
  "properties": {
    "iso:country":"DE",
    "sg:address":"Schmiedgasse 6",
    "sg:city":"Miesbach",
    "sg:postcode":"83714",
    "sg:province":"Bayern",
    "wof:name":"Rundschau Verlag Gmbh",
    "wof:placetype":"venue"
},
  "geometry": {"coordinates":[11.832526207,47.7881355286],"type":"Point"}
}