{
  "type": "Feature",
  "properties": {
    "iso:country":"DE",
    "sg:address":"Wiffertshauser Str. 12",
    "sg:city":"Friedberg",
    "sg:postcode":"86316",
    "sg:province":"Bayern",
    "wof:name":"Falkenapotheke Elfriede Hader E. K.",
    "wof:placetype":"venue"
},
  "geometry": {"coordinates":[10.987205,48.354836],"type":"Point"}
}