{
  "type": "Feature",
  "properties": {
    "iso:country":"DE",
    "sg:address":"Hauptstr. 38a",
    "sg:city":"Bad Nenndorf",
    "sg:phone":"+49 5723/4217",
    "sg:postcode":"31542",
    "sg:province":"Niedersachsen",
    "wof:name":"Ernst Juretzka",
    "wof:placetype":"venue"
},
  "geometry": {"coordinates":[9.3822345734,52.3372764587],"type":"Point"}
}