{
  "type": "Feature",
  "properties": {
    "iso:country":"DE",
    "sg:address":"Karl-Marx-Str. 184",
    "sg:city":"Frankfurt",
    "sg:phone":"+49 335/24677",
    "sg:postcode":"15230",
    "sg:province":"Brandenburg",
    "wof:name":"D. K\u00fchn",
    "wof:placetype":"venue"
},
  "geometry": {"coordinates":[14.550658,52.345337],"type":"Point"}
}