{
  "type": "Feature",
  "properties": {
    "iso:country":"DE",
    "sg:address":"Brunnader",
    "sg:city":"Pocking",
    "sg:phone":"+49 8531/8746",
    "sg:postcode":"94060",
    "sg:province":"Bayern",
    "wof:name":"Christian Buttinger",
    "wof:placetype":"venue"
},
  "geometry": {"coordinates":[13.256962,48.396214],"type":"Point"}
}