{
  "type": "Feature",
  "properties": {
    "iso:country":"DE",
    "sg:address":"Bahnhofstr. 17",
    "sg:city":"Hemmoor",
    "sg:phone":"+49 4771/2555",
    "sg:postcode":"21745",
    "sg:province":"Niedersachsen",
    "wof:name":"Volksbank Stade Eg",
    "wof:placetype":"venue"
},
  "geometry": {"coordinates":[9.169275,53.685066],"type":"Point"}
}