{
  "type": "Feature",
  "properties": {
    "iso:country":"DE",
    "sg:address":"Bachtalstr. 187",
    "sg:city":"Schwalbach",
    "sg:phone":"+49 6834/51338",
    "sg:postcode":"66773",
    "sg:province":"Saarland",
    "wof:name":"Theo Haas",
    "wof:placetype":"venue"
},
  "geometry": {"coordinates":[6.840343,49.2952],"type":"Point"}
}