{
  "type": "Feature",
  "properties": {
    "iso:country":"DE",
    "sg:address":"Gewerbering 10",
    "sg:city":"Ellefeld",
    "sg:phone":"+49 3745/310",
    "sg:postcode":"08236",
    "sg:province":"Sachsen",
    "wof:name":"Auerbach Maschinenfabrik Gmbh",
    "wof:placetype":"venue"
},
  "geometry": {"coordinates":[12.382891,50.486252],"type":"Point"}
}