{
  "type": "Feature",
  "properties": {
    "iso:country":"DE",
    "sg:address":"Antsanvia 1",
    "sg:city":"Eiterfeld",
    "sg:phone":"+49 6676/716",
    "sg:postcode":"36132",
    "sg:province":"Hessen",
    "wof:name":"Walter Kimpel",
    "wof:placetype":"venue"
},
  "geometry": {"coordinates":[9.8966007233,50.7634506226],"type":"Point"}
}