{
  "type": "Feature",
  "properties": {
    "iso:country":"DE",
    "sg:address":"Austr. 18",
    "sg:city":"Bedesbach",
    "sg:phone":"+49 6381/994422",
    "sg:postcode":"66885",
    "sg:province":"Rheinland-Pfalz",
    "wof:name":"Zur Rose",
    "wof:placetype":"venue"
},
  "geometry": {"coordinates":[7.4565320015,49.569480896],"type":"Point"}
}