{
  "type": "Feature",
  "properties": {
    "iso:country":"DE",
    "sg:address":"Alzeyer Str. 25",
    "sg:city":"Flonheim",
    "sg:phone":"+49 6734/8271",
    "sg:postcode":"55237",
    "sg:province":"Rheinland-Pfalz",
    "wof:name":"Werner Und Elfriede W\u00f6rner",
    "wof:placetype":"venue"
},
  "geometry": {"coordinates":[8.0393285751,49.7850074768],"type":"Point"}
}