{
  "type": "Feature",
  "properties": {
    "iso:country":"DE",
    "sg:address":"Bahnstr. 9",
    "sg:city":"W\u00f6rth",
    "sg:phone":"+49 9372/5605",
    "sg:postcode":"63939",
    "sg:province":"Bayern",
    "wof:name":"Alois Arnreiter Schiffahrt",
    "wof:placetype":"venue"
},
  "geometry": {"coordinates":[9.154569,49.794041],"type":"Point"}
}