{
  "type": "Feature",
  "properties": {
    "iso:country":"DE",
    "sg:address":"Zur Potmere 6",
    "sg:city":"Dorsten",
    "sg:phone":"+49 2369/4208",
    "sg:postcode":"46286",
    "sg:province":"Nordrhein-Westfalen",
    "wof:name":"Franz Schl\u00fcter",
    "wof:placetype":"venue"
},
  "geometry": {"coordinates":[7.02013,51.70686],"type":"Point"}
}