{
  "type": "Feature",
  "properties": {
    "iso:country":"DE",
    "sg:address":"Heinrich-von-Kleist-Str. 28",
    "sg:city":"Biebesheim",
    "sg:phone":"+49 6258/6305",
    "sg:postcode":"64584",
    "sg:province":"Hessen",
    "wof:name":"Erwin Hammann",
    "wof:placetype":"venue"
},
  "geometry": {"coordinates":[8.4651432037,49.7739562988],"type":"Point"}
}