{
  "type": "Feature",
  "properties": {
    "iso:country":"DE",
    "sg:address":"Marktplatz 6",
    "sg:city":"Neu-Isenburg",
    "sg:phone":"+49 6102/328810",
    "sg:postcode":"63263",
    "sg:province":"Hessen",
    "wof:name":"M. Frey",
    "wof:placetype":"venue"
},
  "geometry": {"coordinates":[8.69729,50.055855],"type":"Point"}
}