{
  "type": "Feature",
  "properties": {
    "iso:country":"DE",
    "sg:address":"Elbstr. 25",
    "sg:city":"Belgern",
    "sg:phone":"+49 34224/49660",
    "sg:postcode":"04874",
    "sg:province":"Sachsen",
    "wof:name":"Ines Papenfu\u00df-werner Rechtsanw\u00e4ltin",
    "wof:placetype":"venue"
},
  "geometry": {"coordinates":[13.1251497269,51.4832801819],"type":"Point"}
}