{
  "type": "Feature",
  "properties": {
    "iso:country":"DE",
    "sg:address":"Quellenstr. 113",
    "sg:city":"Remagen",
    "sg:phone":"+49 2642/44172",
    "sg:postcode":"53424",
    "sg:province":"Rheinland-Pfalz",
    "wof:name":"Otto F\u00f6hr",
    "wof:placetype":"venue"
},
  "geometry": {"coordinates":[7.266169,50.558861],"type":"Point"}
}