{
  "type": "Feature",
  "properties": {
    "iso:country":"DE",
    "sg:address":"Buchenweg 14",
    "sg:city":"Rosenheim",
    "sg:postcode":"83022",
    "sg:province":"Bayern",
    "wof:name":"Klepper-faltboot Export Gmbh",
    "wof:placetype":"venue"
},
  "geometry": {"coordinates":[12.1430101395,47.8468818665],"type":"Point"}
}