{
  "type": "Feature",
  "properties": {
    "iso:country":"DE",
    "sg:address":"Kasernenstr. 7b",
    "sg:city":"Bonn",
    "sg:phone":"+49 228/691929",
    "sg:postcode":"53111",
    "sg:province":"Nordrhein-Westfalen",
    "wof:name":"Sprungbrett E. V.",
    "wof:placetype":"venue"
},
  "geometry": {"coordinates":[7.0981898308,50.7377166748],"type":"Point"}
}