{
  "type": "Feature",
  "properties": {
    "iso:country":"DE",
    "sg:address":"Steintorwall 17",
    "sg:city":"Herford",
    "sg:phone":"+49 5221/59910",
    "sg:postcode":"32052",
    "sg:province":"Nordrhein-Westfalen",
    "wof:name":"Redaktion K\u00f6hlers Flottenkalender",
    "wof:placetype":"venue"
},
  "geometry": {"coordinates":[8.6692695618,52.1175041199],"type":"Point"}
}