{
  "type": "Feature",
  "properties": {
    "iso:country":"DE",
    "sg:address":"Spielbergtor 17",
    "sg:city":"Erfurt",
    "sg:phone":"+49 361/3453817",
    "sg:postcode":"99099",
    "sg:province":"Th\u00fcringen",
    "wof:name":"Hdl Hanseatische Sreuerberatungs-gmbh",
    "wof:placetype":"venue"
},
  "geometry": {"coordinates":[11.0435466766,50.9721450806],"type":"Point"}
}