{
  "type": "Feature",
  "properties": {
    "iso:country":"DE",
    "sg:address":"Wenningweg 63",
    "sg:city":"M\u00fcnster",
    "sg:phone":"+49 2534/2512",
    "sg:postcode":"48161",
    "sg:province":"Nordrhein-Westfalen",
    "wof:name":"Hans-dieter Thiemann",
    "wof:placetype":"venue"
},
  "geometry": {"coordinates":[7.525186,51.948811],"type":"Point"}
}