{
  "type": "Feature",
  "properties": {
    "iso:country":"DE",
    "sg:address":"Feldbrunnenstr. 52",
    "sg:city":"Hamburg",
    "sg:phone":"+49 40/4411300",
    "sg:postcode":"20148",
    "sg:province":"Hamburg",
    "wof:name":"Heide Schwarzweller Segmenta Pr",
    "wof:placetype":"venue"
},
  "geometry": {"coordinates":[9.990984,53.567581],"type":"Point"}
}