{
  "type": "Feature",
  "properties": {
    "iso:country":"DE",
    "sg:address":"Altheim",
    "sg:city":"Staig",
    "sg:phone":"+49 7346/2558",
    "sg:postcode":"89195",
    "sg:province":"Baden-W\u00fcrttemberg",
    "wof:name":"Aline Reichart",
    "wof:placetype":"venue"
},
  "geometry": {"coordinates":[9.97761,48.301842],"type":"Point"}
}