{
  "type": "Feature",
  "properties": {
    "iso:country":"DE",
    "sg:address":"Feldstr. 22",
    "sg:city":"Bremen",
    "sg:phone":"+49 421/700525",
    "sg:postcode":"28203",
    "sg:province":"Bremen",
    "wof:name":"T. Turner Architekt",
    "wof:placetype":"venue"
},
  "geometry": {"coordinates":[8.827825,53.076599],"type":"Point"}
}