{
  "type": "Feature",
  "properties": {
    "iso:country":"DE",
    "sg:address":"Melanchthonstr. 19",
    "sg:city":"Bretten",
    "sg:phone":"+49 7252/3051",
    "sg:postcode":"75015",
    "sg:province":"Baden-W\u00fcrttemberg",
    "wof:name":"Alexander Ketzel Architekt",
    "wof:placetype":"venue"
},
  "geometry": {"coordinates":[8.705336,49.037079],"type":"Point"}
}