{
  "type": "Feature",
  "properties": {
    "iso:country":"DE",
    "sg:address":"Auf'm Ohl 12 C",
    "sg:city":"Lennestadt",
    "sg:phone":"+49 2721/80213",
    "sg:postcode":"57368",
    "sg:province":"Nordrhein-Westfalen",
    "wof:name":"Lenne Therme Gmbh & Co. Kg",
    "wof:placetype":"venue"
},
  "geometry": {"coordinates":[8.0653028488,51.1153068542],"type":"Point"}
}