{
  "type": "Feature",
  "properties": {
    "iso:country":"DE",
    "sg:address":"Hauptstr. 23",
    "sg:city":"Arzfeld",
    "sg:phone":"+49 6550/4387",
    "sg:postcode":"54687",
    "sg:province":"Rheinland-Pfalz",
    "wof:name":"Hotel K\u00f6lner Hof",
    "wof:placetype":"venue"
},
  "geometry": {"coordinates":[6.2741818428,50.0877532959],"type":"Point"}
}