{
  "type": "Feature",
  "properties": {
    "iso:country":"DE",
    "sg:address":"Wilhelm-Weindler-Str. 11",
    "sg:city":"Erding",
    "sg:phone":"+49 8122/10808",
    "sg:postcode":"85435",
    "sg:province":"Bayern",
    "wof:name":"Vvs Holding Vertriebs- Verwaltungs- Und Service Gmbh",
    "wof:placetype":"venue"
},
  "geometry": {"coordinates":[11.9142856598,48.3021850586],"type":"Point"}
}