{
  "type": "Feature",
  "properties": {
    "iso:country":"DE",
    "sg:address":"Seestr. 18",
    "sg:city":"Ludwigsburg",
    "sg:phone":"+49 7141/925447",
    "sg:postcode":"71638",
    "sg:province":"Baden-W\u00fcrttemberg",
    "wof:name":"Tontr\u00e4ger Verlags Gmbh",
    "wof:placetype":"venue"
},
  "geometry": {"coordinates":[9.1900873184,48.8944396973],"type":"Point"}
}