{
  "type": "Feature",
  "properties": {
    "iso:country":"DE",
    "sg:address":"Kepplerstr. 16",
    "sg:city":"Rottweil",
    "sg:phone":"+49 7427/2641",
    "sg:postcode":"78628",
    "sg:province":"Baden-W\u00fcrttemberg",
    "wof:name":"Josef Gfr\u00f6rer",
    "wof:placetype":"venue"
},
  "geometry": {"coordinates":[8.712833,48.192131],"type":"Point"}
}