{
  "type": "Feature",
  "properties": {
    "iso:country":"DE",
    "sg:address":"Bahnstr. 98",
    "sg:city":"Landstuhl",
    "sg:phone":"+49 6371/914491",
    "sg:postcode":"66849",
    "sg:province":"Rheinland-Pfalz",
    "wof:name":"Dietmar Habelitz",
    "wof:placetype":"venue"
},
  "geometry": {"coordinates":[7.5865020752,49.4154853821],"type":"Point"}
}