{
  "type": "Feature",
  "properties": {
    "iso:country":"DE",
    "sg:address":"Obers\u00fclzer Str. 14",
    "sg:city":"Gr\u00fcnstadt",
    "sg:phone":"+49 6359/9520",
    "sg:postcode":"67269",
    "sg:province":"Rheinland-Pfalz",
    "wof:name":"Weber & Jost Verwaltungs-gmbh",
    "wof:placetype":"venue"
},
  "geometry": {"coordinates":[8.168448,49.562576],"type":"Point"}
}