{
  "type": "Feature",
  "properties": {
    "iso:country":"DE",
    "sg:address":"Stadtplatz 8",
    "sg:city":"Bad D\u00fcrkheim",
    "sg:phone":"+49 6322/7010",
    "sg:postcode":"67098",
    "sg:province":"Rheinland-Pfalz",
    "wof:name":"Lenz",
    "wof:placetype":"venue"
},
  "geometry": {"coordinates":[8.1671895981,49.4601593018],"type":"Point"}
}