{
  "type": "Feature",
  "properties": {
    "iso:country":"DE",
    "sg:address":"Ostrauer Str. 8",
    "sg:city":"Schrebitz",
    "sg:phone":"+49 34362/32987",
    "sg:postcode":"04720",
    "sg:province":"Sachsen",
    "wof:name":"A. Oehmichen",
    "wof:placetype":"venue"
},
  "geometry": {"coordinates":[13.0697278976,51.2053527832],"type":"Point"}
}