{
  "type": "Feature",
  "properties": {
    "iso:country":"DE",
    "sg:address":"Karlstr. 1",
    "sg:city":"Eisenach",
    "sg:phone":"+49 3691/75059",
    "sg:postcode":"99817",
    "sg:province":"Th\u00fcringen",
    "wof:name":"Annegret Siefert",
    "wof:placetype":"venue"
},
  "geometry": {"coordinates":[10.320742,50.975182],"type":"Point"}
}