{
  "type": "Feature",
  "properties": {
    "iso:country":"DE",
    "sg:address":"Lausaer Str. 10",
    "sg:city":"Dresden",
    "sg:phone":"+49 351/8809675",
    "sg:postcode":"01109",
    "sg:province":"Sachsen",
    "wof:name":"Gertraude Wagner",
    "wof:placetype":"venue"
},
  "geometry": {"coordinates":[13.7425384521,51.1181373596],"type":"Point"}
}