{
  "type": "Feature",
  "properties": {
    "iso:country":"DE",
    "sg:address":"Sendlinger Str. 14",
    "sg:city":"M\u00fcnchen",
    "sg:phone":"+49 89/2607021",
    "sg:postcode":"80331",
    "sg:province":"Bayern",
    "wof:name":"Rainer D. Kaben Rechtsanwalt",
    "wof:placetype":"venue"
},
  "geometry": {"coordinates":[11.5712947845,48.1358375549],"type":"Point"}
}