{
  "type": "Feature",
  "properties": {
    "iso:country":"DE",
    "sg:address":"Tradtstr. 12",
    "sg:city":"Furth im Wald",
    "sg:postcode":"93437",
    "sg:province":"Bayern",
    "wof:name":"Multitrans Ag",
    "wof:placetype":"venue"
},
  "geometry": {"coordinates":[12.839259,49.308437],"type":"Point"}
}