{
  "type": "Feature",
  "properties": {
    "iso:country":"DE",
    "sg:address":"Vor'm Busch 6",
    "sg:city":"Bad Oeynhausen",
    "sg:phone":"+49 5731/41223",
    "sg:postcode":"32549",
    "sg:province":"Nordrhein-Westfalen",
    "wof:name":"Wolfgang Maih\u00f6fer Architekt",
    "wof:placetype":"venue"
},
  "geometry": {"coordinates":[8.784063,52.226936],"type":"Point"}
}