{
  "type": "Feature",
  "properties": {
    "iso:country":"DE",
    "sg:address":"Felix-Fechenbach-Str. 23",
    "sg:city":"Detmold",
    "sg:phone":"+49 5231/628459",
    "sg:postcode":"32756",
    "sg:province":"Nordrhein-Westfalen",
    "wof:name":"V. Peters",
    "wof:placetype":"venue"
},
  "geometry": {"coordinates":[8.8487272263,51.9344749451],"type":"Point"}
}