{
  "type": "Feature",
  "properties": {
    "iso:country":"DE",
    "sg:address":"Adelheider Str. 50",
    "sg:city":"Delmenhorst",
    "sg:phone":"+49 4221/2863",
    "sg:postcode":"27755",
    "sg:province":"Niedersachsen",
    "wof:name":"Abf Electronik",
    "wof:placetype":"venue"
},
  "geometry": {"coordinates":[8.6225442886,53.0335350037],"type":"Point"}
}