{
  "type": "Feature",
  "properties": {
    "iso:country":"DE",
    "sg:address":"Linsenhofer Str. 59-63",
    "sg:city":"Beuren",
    "sg:postcode":"72660",
    "sg:province":"Baden-W\u00fcrttemberg",
    "wof:name":"Ludwig Brummer Export-import Gmbh",
    "wof:placetype":"venue"
},
  "geometry": {"coordinates":[9.3970060349,48.5712394714],"type":"Point"}
}