{
  "type": "Feature",
  "properties": {
    "iso:country":"DE",
    "sg:address":"Preystr. 9",
    "sg:city":"Hamburg",
    "sg:phone":"+49 40/2794200",
    "sg:postcode":"22303",
    "sg:province":"Hamburg",
    "wof:name":"Holger Grantz Architekt",
    "wof:placetype":"venue"
},
  "geometry": {"coordinates":[10.01269,53.582516],"type":"Point"}
}