{
  "type": "Feature",
  "properties": {
    "iso:country":"DE",
    "sg:address":"Schillerstr. 5a",
    "sg:city":"Losheim",
    "sg:phone":"+49 6872/505194",
    "sg:postcode":"66679",
    "sg:province":"Saarland",
    "wof:name":"Anlagentechnik Hochwald Gmbh",
    "wof:placetype":"venue"
},
  "geometry": {"coordinates":[6.748998,49.511574],"type":"Point"}
}