{
  "type": "Feature",
  "properties": {
    "iso:country":"DE",
    "sg:address":"Kaiser-Friedrich-Ring 32",
    "sg:city":"Wiesbaden",
    "sg:phone":"+49 611/371735",
    "sg:postcode":"65185",
    "sg:province":"Hessen",
    "wof:name":"Rudi Flemming Drogerie",
    "wof:placetype":"venue"
},
  "geometry": {"coordinates":[8.232022,50.074375],"type":"Point"}
}