{
  "type": "Feature",
  "properties": {
    "iso:country":"DE",
    "sg:address":"Focher Str. 139",
    "sg:city":"Solingen",
    "sg:phone":"+49 212/311393",
    "sg:postcode":"42719",
    "sg:province":"Nordrhein-Westfalen",
    "wof:name":"Herbert Schuchert",
    "wof:placetype":"venue"
},
  "geometry": {"coordinates":[7.0587220192,51.1885299683],"type":"Point"}
}