{
  "type": "Feature",
  "properties": {
    "iso:country":"DE",
    "sg:address":"Im Weidenthal 5",
    "sg:city":"R\u00f6srath",
    "sg:phone":"+49 2205/83377",
    "sg:postcode":"51503",
    "sg:province":"Nordrhein-Westfalen",
    "wof:name":"Ev. Pfarramt Pfarrbez. I",
    "wof:placetype":"venue"
},
  "geometry": {"coordinates":[7.1820020676,50.9274368286],"type":"Point"}
}