{
  "type": "Feature",
  "properties": {
    "iso:country":"DE",
    "sg:address":"Landschadh\u00f6fe 4",
    "sg:city":"Heidelberg",
    "sg:phone":"+49 6221/836190",
    "sg:postcode":"69123",
    "sg:province":"Baden-W\u00fcrttemberg",
    "wof:name":"Wilhelm L. Welk",
    "wof:placetype":"venue"
},
  "geometry": {"coordinates":[8.628239,49.427933],"type":"Point"}
}