{
  "type": "Feature",
  "properties": {
    "iso:country":"DE",
    "sg:address":"Duisburger Str. 227",
    "sg:city":"Duisburg",
    "sg:phone":"+49 203/555170",
    "sg:postcode":"47166",
    "sg:province":"Nordrhein-Westfalen",
    "wof:name":"Claus Lohscheller Steuerberater",
    "wof:placetype":"venue"
},
  "geometry": {"coordinates":[6.77267313,51.4940452576],"type":"Point"}
}