{
  "type": "Feature",
  "properties": {
    "iso:country":"DE",
    "sg:address":"Heidenheimer Str. 42",
    "sg:city":"Oberkochen",
    "sg:phone":"+49 7364/8393",
    "sg:postcode":"73447",
    "sg:province":"Baden-W\u00fcrttemberg",
    "wof:name":"Ludwig Wunderle Anlageberater",
    "wof:placetype":"venue"
},
  "geometry": {"coordinates":[10.103931427,48.7821311951],"type":"Point"}
}