{
  "type": "Feature",
  "properties": {
    "iso:country":"DE",
    "sg:address":"Neutorstr. 25",
    "sg:city":"Schweinfurt",
    "sg:phone":"+49 9721/28010",
    "sg:postcode":"97421",
    "sg:province":"Bayern",
    "wof:name":"G. Moll",
    "wof:placetype":"venue"
},
  "geometry": {"coordinates":[10.2267770767,50.0486793518],"type":"Point"}
}