{
  "type": "Feature",
  "properties": {
    "iso:country":"DE",
    "sg:address":"EKZ Shop West",
    "sg:city":"Neu-Isenburg",
    "sg:phone":"+49 6102/31299",
    "sg:postcode":"63263",
    "sg:province":"Hessen",
    "wof:name":"Inge Streb",
    "wof:placetype":"venue"
},
  "geometry": {"coordinates":[8.6951436996,50.0565185547],"type":"Point"}
}