{
  "type": "Feature",
  "properties": {
    "iso:country":"DE",
    "sg:address":"Hofener Str 64",
    "sg:city":"Fellbach",
    "sg:phone":"+49 711/9519410",
    "sg:postcode":"70736",
    "sg:province":"Baden-W\u00fcrttemberg",
    "wof:name":"J\u00f6rg Paule Informationssysteme Gmbh",
    "wof:placetype":"venue"
},
  "geometry": {"coordinates":[9.253658,48.842819],"type":"Point"}
}