{
  "type": "Feature",
  "properties": {
    "iso:country":"DE",
    "sg:address":"Hofstattstr. 51",
    "sg:city":"Heilbronn",
    "sg:phone":"+49 7131/34940",
    "sg:postcode":"74080",
    "sg:province":"Baden-W\u00fcrttemberg",
    "wof:name":"Fred Seyfarth",
    "wof:placetype":"venue"
},
  "geometry": {"coordinates":[9.187129,49.128815],"type":"Point"}
}