{
  "type": "Feature",
  "properties": {
    "iso:country":"DE",
    "sg:address":"Ferdinand-Lassalle-Str. 30",
    "sg:city":"Reutlingen",
    "sg:phone":"+49 7121/95970",
    "sg:postcode":"72770",
    "sg:province":"Baden-W\u00fcrttemberg",
    "wof:name":"Feral Verwaltungs Gmbh",
    "wof:placetype":"venue"
},
  "geometry": {"coordinates":[9.156091,48.491096],"type":"Point"}
}