{
  "type": "Feature",
  "properties": {
    "iso:country":"DE",
    "sg:address":"Hauptstra\u00dfe 55",
    "sg:city":"Erlangen",
    "sg:postcode":"91054",
    "sg:province":"Bayern",
    "wof:name":"Erotic Shop",
    "wof:placetype":"venue"
},
  "geometry": {"coordinates":[11.0029029846,49.5996360779],"type":"Point"}
}