{
  "type": "Feature",
  "properties": {
    "iso:country":"DE",
    "sg:address":"St.-Vitus-Sch\u00fctzenstr. 7",
    "sg:city":"Schmallenberg",
    "sg:phone":"+49 2972/255",
    "sg:postcode":"57392",
    "sg:province":"Nordrhein-Westfalen",
    "wof:name":"T. Klauke",
    "wof:placetype":"venue"
},
  "geometry": {"coordinates":[8.392701,51.246929],"type":"Point"}
}