{
  "type": "Feature",
  "properties": {
    "iso:country":"DE",
    "sg:address":"Rubinstr. 43",
    "sg:city":"Dortmund",
    "sg:phone":"+49 231/480159",
    "sg:postcode":"44267",
    "sg:province":"Nordrhein-Westfalen",
    "wof:name":"Herbert Blume",
    "wof:placetype":"venue"
},
  "geometry": {"coordinates":[7.529192,51.4748],"type":"Point"}
}