{
  "type": "Feature",
  "properties": {
    "iso:country":"DE",
    "sg:address":"K\u00f6nigstr. 84",
    "sg:city":"Bonn",
    "sg:phone":"+49 228/220650",
    "sg:postcode":"53115",
    "sg:province":"Nordrhein-Westfalen",
    "wof:name":"Restaurant Il Cavallino",
    "wof:placetype":"venue"
},
  "geometry": {"coordinates":[7.0963149071,50.7265357971],"type":"Point"}
}