{
  "type": "Feature",
  "properties": {
    "iso:country":"DE",
    "sg:address":"Bismarckstr. 16",
    "sg:city":"Oftersheim",
    "sg:phone":"+49 6202/54149",
    "sg:postcode":"68723",
    "sg:province":"Baden-W\u00fcrttemberg",
    "wof:name":"Hermann Mehner Architekt",
    "wof:placetype":"venue"
},
  "geometry": {"coordinates":[8.582543,49.371635],"type":"Point"}
}