{
  "type": "Feature",
  "properties": {
    "iso:country":"DE",
    "sg:address":"Frankfurter Str. 57",
    "sg:city":"Heusenstamm",
    "sg:phone":"+49 6104/2674",
    "sg:postcode":"63150",
    "sg:province":"Hessen",
    "wof:name":"Farben- Und Tapetenmarkt Georg Bohland",
    "wof:placetype":"venue"
},
  "geometry": {"coordinates":[8.803027,50.059025],"type":"Point"}
}