{
  "type": "Feature",
  "properties": {
    "iso:country":"DE",
    "sg:address":"Dorfstr. 13",
    "sg:city":"Sch\u00f6nw\u00f6lkau",
    "sg:phone":"+49 34295/550",
    "sg:postcode":"04509",
    "sg:province":"Sachsen",
    "wof:name":"Lebak Gesell. F\u00fcr Sozialwissenschaft Mbh",
    "wof:placetype":"venue"
},
  "geometry": {"coordinates":[12.4277429581,51.4990005493],"type":"Point"}
}