{
  "type": "Feature",
  "properties": {
    "iso:country":"DE",
    "sg:address":"Zottelstedter Str. 17",
    "sg:city":"Niederro\u00dfla",
    "sg:phone":"+49 3644/556897",
    "sg:postcode":"99510",
    "sg:province":"Th\u00fcringen",
    "wof:name":"H. Gro\u00df",
    "wof:placetype":"venue"
},
  "geometry": {"coordinates":[11.4851617813,51.0413894653],"type":"Point"}
}