{
  "type": "Feature",
  "properties": {
    "iso:country":"DE",
    "sg:address":"Rh\u00f6nweg 20",
    "sg:city":"Villingen-Schwenningen",
    "sg:phone":"+49 7720/7762",
    "sg:postcode":"78056",
    "sg:province":"Baden-W\u00fcrttemberg",
    "wof:name":"Sanimed Ges. F\u00fcr Unternehmens- Analyse Und Beteiligungs-",
    "wof:placetype":"venue"
},
  "geometry": {"coordinates":[8.5484,48.071236],"type":"Point"}
}