{
  "type": "Feature",
  "properties": {
    "iso:country":"DE",
    "sg:address":"Vor dem Neuperver Tor 10",
    "sg:city":"Salzwedel",
    "sg:phone":"+49 3901/25014",
    "sg:postcode":"29410",
    "sg:province":"Sachsen-Anhalt",
    "wof:name":"Restaurant Kulturhaus",
    "wof:placetype":"venue"
},
  "geometry": {"coordinates":[11.1583757401,52.8501625061],"type":"Point"}
}