{
  "type": "Feature",
  "properties": {
    "iso:country":"DE",
    "sg:address":"Alte Dieburger Str. 20",
    "sg:city":"M\u00fchltal",
    "sg:phone":"+49 6151/147165",
    "sg:postcode":"64367",
    "sg:province":"Hessen",
    "wof:name":"Herbert Roth Architekt",
    "wof:placetype":"venue"
},
  "geometry": {"coordinates":[8.689312,49.828625],"type":"Point"}
}