{
  "type": "Feature",
  "properties": {
    "iso:country":"DE",
    "sg:address":"Von-Alten-Allee 2",
    "sg:city":"Hannover",
    "sg:phone":"+49 511/4581091",
    "sg:postcode":"30449",
    "sg:province":"Niedersachsen",
    "wof:name":"Agsta Arbeitsgemeinschaft F\u00fcr Stadt- Und Altbauerneuerung",
    "wof:placetype":"venue"
},
  "geometry": {"coordinates":[9.71833,52.365631],"type":"Point"}
}