{
  "type": "Feature",
  "properties": {
    "iso:country":"DE",
    "sg:address":"Birkenweg 7",
    "sg:city":"Buchloe",
    "sg:phone":"+49 8241/6848",
    "sg:postcode":"86807",
    "sg:province":"Bayern",
    "wof:name":"Michael Singer",
    "wof:placetype":"venue"
},
  "geometry": {"coordinates":[10.723847,48.03133],"type":"Point"}
}