{
  "type": "Feature",
  "properties": {
    "iso:country":"DE",
    "sg:address":"Binterimstr. 12",
    "sg:city":"D\u00fcsseldorf",
    "sg:phone":"+49 211/333005",
    "sg:postcode":"40223",
    "sg:province":"Nordrhein-Westfalen",
    "wof:name":"Josef Holzleitner Elektroger\u00e4te Gmbh & Co.",
    "wof:placetype":"venue"
},
  "geometry": {"coordinates":[6.7729110718,51.2066001892],"type":"Point"}
}