{
  "type": "Feature",
  "properties": {
    "iso:country":"DE",
    "sg:address":"Zur Silberkuhle 47",
    "sg:city":"Drolshagen",
    "sg:phone":"+49 2761/71896",
    "sg:postcode":"57489",
    "sg:province":"Nordrhein-Westfalen",
    "wof:name":"Hermann Feldmann",
    "wof:placetype":"venue"
},
  "geometry": {"coordinates":[7.7612528801,50.9934463501],"type":"Point"}
}