{
  "type": "Feature",
  "properties": {
    "iso:country":"DE",
    "sg:address":"Kurze Str. 6",
    "sg:city":"Alfeld",
    "sg:phone":"+49 5181/4623",
    "sg:postcode":"31061",
    "sg:province":"Niedersachsen",
    "wof:name":"Ernst Terwort",
    "wof:placetype":"venue"
},
  "geometry": {"coordinates":[9.871855,51.958954],"type":"Point"}
}