{
  "type": "Feature",
  "properties": {
    "iso:country":"DE",
    "sg:address":"Am Eichenrangen 10b",
    "sg:city":"Schwaig",
    "sg:phone":"+49 911/5075039",
    "sg:postcode":"90571",
    "sg:province":"Bayern",
    "wof:name":"Weinzierl Gmbh",
    "wof:placetype":"venue"
},
  "geometry": {"coordinates":[11.2125320435,49.4849662781],"type":"Point"}
}