{
  "type": "Feature",
  "properties": {
    "iso:country":"DE",
    "sg:address":"Aegidiikirchplatz 5",
    "sg:city":"M\u00fcnster",
    "sg:phone":"+49 251/5050",
    "sg:postcode":"48143",
    "sg:province":"Nordrhein-Westfalen",
    "wof:name":"Oberverwaltungsgericht F\u00fcr Das Land Nordrhein-westf.",
    "wof:placetype":"venue"
},
  "geometry": {"coordinates":[7.624789,51.959484],"type":"Point"}
}