{
  "type": "Feature",
  "properties": {
    "iso:country":"DE",
    "sg:address":"Fangdieckstr. 75a",
    "sg:city":"Hamburg",
    "sg:phone":"+49 40/5405723",
    "sg:postcode":"22547",
    "sg:province":"Hamburg",
    "wof:name":"Golf Professional Service Gps Gmbh",
    "wof:placetype":"venue"
},
  "geometry": {"coordinates":[9.8987445831,53.5981216431],"type":"Point"}
}