{
  "type": "Feature",
  "properties": {
    "iso:country":"DE",
    "sg:address":"Herzog-Wilhelm-Str. 30",
    "sg:city":"Braunlage",
    "sg:phone":"+49 5520/3519",
    "sg:postcode":"38700",
    "sg:province":"Niedersachsen",
    "wof:name":"F. C. L. Automaten Gmbh",
    "wof:placetype":"venue"
},
  "geometry": {"coordinates":[10.609664917,51.7260894775],"type":"Point"}
}