{
  "type": "Feature",
  "properties": {
    "iso:country":"DE",
    "sg:address":"Grasweg 4",
    "sg:city":"Deutsch Evern",
    "sg:phone":"+49 4131/790077",
    "sg:postcode":"21407",
    "sg:province":"Niedersachsen",
    "wof:name":"I-color Gmbh",
    "wof:placetype":"venue"
},
  "geometry": {"coordinates":[10.4410943985,53.1994132996],"type":"Point"}
}