{
  "type": "Feature",
  "properties": {
    "iso:country":"DE",
    "sg:address":"Altneudorfer Str. 29",
    "sg:city":"Sch\u00f6nau",
    "sg:phone":"+49 6228/743",
    "sg:postcode":"69250",
    "sg:province":"Baden-W\u00fcrttemberg",
    "wof:name":"Kurt Hoffst\u00e4tter",
    "wof:placetype":"venue"
},
  "geometry": {"coordinates":[8.8035411835,49.4681854248],"type":"Point"}
}