{
  "type": "Feature",
  "properties": {
    "iso:country":"DE",
    "sg:address":"Gr\u00e4fenau 32",
    "sg:city":"H\u00f6fen",
    "sg:phone":"+49 7081/5507",
    "sg:postcode":"75339",
    "sg:province":"Baden-W\u00fcrttemberg",
    "wof:name":"Lothar Blaich Elektroinstallation",
    "wof:placetype":"venue"
},
  "geometry": {"coordinates":[8.578912,48.793072],"type":"Point"}
}