{
  "type": "Feature",
  "properties": {
    "iso:country":"DE",
    "sg:address":"Gottfried-Keller-Str. 50",
    "sg:city":"Dresden",
    "sg:postcode":"01157",
    "sg:province":"Sachsen",
    "wof:name":"Katholisches Pfarramt Unserer Lieben Frau",
    "wof:placetype":"venue"
},
  "geometry": {"coordinates":[13.6786355972,51.0561408997],"type":"Point"}
}