{
  "type": "Feature",
  "properties": {
    "iso:country":"DE",
    "sg:address":"Kreuzauer Str. 62",
    "sg:city":"D\u00fcren",
    "sg:phone":"+49 2421/958480",
    "sg:postcode":"52355",
    "sg:province":"Nordrhein-Westfalen",
    "wof:name":"Heinr. Sch\u00e4fer & Sohn Gmbh Inh. Heinz Sch\u00e4fer",
    "wof:placetype":"venue"
},
  "geometry": {"coordinates":[6.4919128418,50.770866394],"type":"Point"}
}