{
  "type": "Feature",
  "properties": {
    "iso:country":"DE",
    "sg:address":"Ey\u00dfelheideweg 70",
    "sg:city":"Gifhorn",
    "sg:phone":"+49 5371/14353",
    "sg:postcode":"38518",
    "sg:province":"Niedersachsen",
    "wof:name":"Bernhard Lohse",
    "wof:placetype":"venue"
},
  "geometry": {"coordinates":[10.5041255951,52.4579429626],"type":"Point"}
}