{
  "type": "Feature",
  "properties": {
    "iso:country":"DE",
    "sg:address":"Braunsh\u00e4user Str. 22",
    "sg:city":"Frankenberg",
    "sg:phone":"+49 2984/745",
    "sg:postcode":"35066",
    "sg:province":"Hessen",
    "wof:name":"G\u00e4stehaus Marlene Kessler",
    "wof:placetype":"venue"
},
  "geometry": {"coordinates":[8.7049236298,51.1065635681],"type":"Point"}
}