{
  "type": "Feature",
  "properties": {
    "iso:country":"DE",
    "sg:address":"Schillerstr. 1",
    "sg:city":"Oldenburg",
    "sg:postcode":"26122",
    "sg:province":"Niedersachsen",
    "wof:name":"Rwb Dienstleistungs- Gesellschaft F\u00fcr Soziale",
    "wof:placetype":"venue"
},
  "geometry": {"coordinates":[8.2014865875,53.1334648132],"type":"Point"}
}