{
  "type": "Feature",
  "properties": {
    "iso:country":"DE",
    "sg:address":"Steinge 14",
    "sg:city":"Ehingen",
    "sg:phone":"+49 7393/1015",
    "sg:postcode":"89584",
    "sg:province":"Baden-W\u00fcrttemberg",
    "wof:name":"Marcus Amann",
    "wof:placetype":"venue"
},
  "geometry": {"coordinates":[9.634454,48.2738],"type":"Point"}
}