{
  "type": "Feature",
  "properties": {
    "iso:country":"DE",
    "sg:address":"Birkenweg 9",
    "sg:city":"Lalling",
    "sg:phone":"+49 9904/1668",
    "sg:postcode":"94551",
    "sg:province":"Bayern",
    "wof:name":"Obst Und Gem\u00fcse K. Und E. Lemberger",
    "wof:placetype":"venue"
},
  "geometry": {"coordinates":[13.1362190247,48.8426971436],"type":"Point"}
}