{
  "type": "Feature",
  "properties": {
    "iso:country":"DE",
    "sg:address":"Aschaffenburger Str. 14",
    "sg:city":"Bremen",
    "sg:phone":"+49 421/372403",
    "sg:postcode":"28215",
    "sg:province":"Bremen",
    "wof:name":"Wolfgang Coors Architekt",
    "wof:placetype":"venue"
},
  "geometry": {"coordinates":[8.80793,53.094574],"type":"Point"}
}