{
  "type": "Feature",
  "properties": {
    "iso:country":"DE",
    "sg:address":"Boschstr. 8",
    "sg:city":"Ulm",
    "sg:phone":"+49 731/401020",
    "sg:postcode":"89079",
    "sg:province":"Baden-W\u00fcrttemberg",
    "wof:name":"Raizner Gmbh Planen Und Bauen",
    "wof:placetype":"venue"
},
  "geometry": {"coordinates":[9.9518671036,48.3713607788],"type":"Point"}
}