{
  "type": "Feature",
  "properties": {
    "iso:country":"DE",
    "sg:address":"Menkestr. 9",
    "sg:city":"Osnabr\u00fcck",
    "sg:phone":"+49 541/64849",
    "sg:postcode":"49076",
    "sg:province":"Niedersachsen",
    "wof:name":"Dieter Kunisch Architekt",
    "wof:placetype":"venue"
},
  "geometry": {"coordinates":[8.017127,52.2859],"type":"Point"}
}