{
  "type": "Feature",
  "properties": {
    "iso:country":"DE",
    "sg:address":"Am Bonneshof 6",
    "sg:city":"D\u00fcsseldorf",
    "sg:phone":"+49 211/666903",
    "sg:postcode":"40474",
    "sg:province":"Nordrhein-Westfalen",
    "wof:name":"Peter Welbers Rechtsanwalt",
    "wof:placetype":"venue"
},
  "geometry": {"coordinates":[6.7656898499,51.2531394958],"type":"Point"}
}