{
  "type": "Feature",
  "properties": {
    "iso:country":"DE",
    "sg:address":"Lochhamer Str. 11",
    "sg:city":"Planegg",
    "sg:phone":"+49 89/89567822",
    "sg:postcode":"82152",
    "sg:province":"Bayern",
    "wof:name":"Peter Spohrer Rechtsanwalt",
    "wof:placetype":"venue"
},
  "geometry": {"coordinates":[11.4517202377,48.1105194092],"type":"Point"}
}