{
  "type": "Feature",
  "properties": {
    "iso:country":"DE",
    "sg:address":"Am Meerkamp 23",
    "sg:city":"Meerbusch",
    "sg:phone":"+49 2132/769720",
    "sg:postcode":"40667",
    "sg:province":"Nordrhein-Westfalen",
    "wof:name":"Interiorforum.de Wohnkultur, Accessoires & Geschenke",
    "wof:placetype":"venue"
},
  "geometry": {"coordinates":[6.6908149719,51.2471656799],"type":"Point"}
}