{
  "type": "Feature",
  "properties": {
    "iso:country":"DE",
    "sg:address":"Lorsbacher Str. 36",
    "sg:city":"Hofheim",
    "sg:phone":"+49 6192/7605",
    "sg:postcode":"65719",
    "sg:province":"Hessen",
    "wof:name":"Barbara Pauli-tetkov Rechtsanw\u00e4ltin",
    "wof:placetype":"venue"
},
  "geometry": {"coordinates":[8.437869072,50.0868530273],"type":"Point"}
}