{
  "type": "Feature",
  "properties": {
    "iso:country":"DE",
    "sg:address":"Koblenzer Str. 72",
    "sg:city":"Bad Ems",
    "sg:phone":"+49 2603/934340",
    "sg:postcode":"56130",
    "sg:province":"Rheinland-Pfalz",
    "wof:name":"Ludwig Lotz",
    "wof:placetype":"venue"
},
  "geometry": {"coordinates":[7.7077879906,50.3354949951],"type":"Point"}
}