{
  "type": "Feature",
  "properties": {
    "iso:country":"DE",
    "sg:address":"M\u00fcnsterer Str. 27a",
    "sg:city":"Hofheim",
    "sg:phone":"+49 6192/25613",
    "sg:postcode":"65719",
    "sg:province":"Hessen",
    "wof:name":"G\u00fcnter Kraus",
    "wof:placetype":"venue"
},
  "geometry": {"coordinates":[8.4231729507,50.1221313477],"type":"Point"}
}