{
  "type": "Feature",
  "properties": {
    "iso:country":"DE",
    "sg:address":"Im Martelacker 16",
    "sg:city":"Efringen-Kirchen",
    "sg:postcode":"79588",
    "sg:province":"Baden-W\u00fcrttemberg",
    "wof:name":"Spedition Guiseppe Gruber",
    "wof:placetype":"venue"
},
  "geometry": {"coordinates":[7.5724639893,47.6559295654],"type":"Point"}
}