{
  "type": "Feature",
  "properties": {
    "iso:country":"DE",
    "sg:address":"Viktoriastr. 78",
    "sg:city":"Darmstadt",
    "sg:phone":"+49 6151/24023",
    "sg:postcode":"64293",
    "sg:province":"Hessen",
    "wof:name":"C. Pr\u00e4ger Bildhauer",
    "wof:placetype":"venue"
},
  "geometry": {"coordinates":[8.64906,49.881905],"type":"Point"}
}