{
  "type": "Feature",
  "properties": {
    "iso:country":"DE",
    "sg:address":"Erlenweg 7",
    "sg:city":"G\u00fctersloh",
    "sg:phone":"+49 5241/77150",
    "sg:postcode":"33335",
    "sg:province":"Nordrhein-Westfalen",
    "wof:name":"K. Rogge Heissmangel",
    "wof:placetype":"venue"
},
  "geometry": {"coordinates":[8.4316673279,51.9253997803],"type":"Point"}
}