{
  "type": "Feature",
  "properties": {
    "iso:country":"DE",
    "sg:address":"Cramerweg 6",
    "sg:city":"Gelsenkirchen",
    "sg:postcode":"45886",
    "sg:province":"Nordrhein-Westfalen",
    "wof:name":"Gbl-landschaftsbau- Verwaltungs Gmbh",
    "wof:placetype":"venue"
},
  "geometry": {"coordinates":[7.10926,51.502258],"type":"Point"}
}