{
  "type": "Feature",
  "properties": {
    "iso:country":"DE",
    "sg:address":"Hauptstr. 117",
    "sg:city":"H\u00fcttenberg",
    "sg:phone":"+49 6403/4334",
    "sg:postcode":"35625",
    "sg:province":"Hessen",
    "wof:name":"Willi Sch\u00e4fer",
    "wof:placetype":"venue"
},
  "geometry": {"coordinates":[8.623961,50.517467],"type":"Point"}
}