{
  "type": "Feature",
  "properties": {
    "iso:country":"DE",
    "sg:address":"Bahnstr. 78",
    "sg:city":"Wittenberge",
    "sg:phone":"+49 3877/60721",
    "sg:postcode":"19322",
    "sg:province":"Brandenburg",
    "wof:name":"Ivs Immobilien -und Ver- Sicherungs-service Gmbh",
    "wof:placetype":"venue"
},
  "geometry": {"coordinates":[11.7538986206,52.995262146],"type":"Point"}
}