{
  "type": "Feature",
  "properties": {
    "iso:country":"DE",
    "sg:address":"P\u00fcttlinger Weg 4",
    "sg:city":"Zierenberg",
    "sg:phone":"+49 5606/3375",
    "sg:postcode":"34289",
    "sg:province":"Hessen",
    "wof:name":"Kath. Pfarramt Hl. Kreuz",
    "wof:placetype":"venue"
},
  "geometry": {"coordinates":[9.2961702347,51.3621482849],"type":"Point"}
}