{
  "type": "Feature",
  "properties": {
    "iso:country":"DE",
    "sg:address":"Niederstadt 34",
    "sg:city":"Sontra",
    "sg:phone":"+49 5653/91138",
    "sg:postcode":"36205",
    "sg:province":"Hessen",
    "wof:name":"J. H. Gro\u00dfmann",
    "wof:placetype":"venue"
},
  "geometry": {"coordinates":[9.9362888336,51.0711479187],"type":"Point"}
}