{
  "type": "Feature",
  "properties": {
    "iso:country":"DE",
    "sg:address":"Adolf-Diesterweg-Str. 75",
    "sg:city":"Ludwigshafen",
    "sg:phone":"+49 621/677080",
    "sg:postcode":"67071",
    "sg:province":"Rheinland-Pfalz",
    "wof:name":"D. Sch\u00f6tz-ehrsam Und B. Jakob Krankengymnasten",
    "wof:placetype":"venue"
},
  "geometry": {"coordinates":[8.363879,49.492062],"type":"Point"}
}