{
  "type": "Feature",
  "properties": {
    "iso:country":"DE",
    "sg:address":"Hackerstr. 18",
    "sg:city":"Oberschlei\u00dfheim",
    "sg:phone":"+49 89/3750720",
    "sg:postcode":"85764",
    "sg:province":"Bayern",
    "wof:name":"Maschinenbau Eggerstorfer Gmbh",
    "wof:placetype":"venue"
},
  "geometry": {"coordinates":[11.529648,48.256054],"type":"Point"}
}