{
  "type": "Feature",
  "properties": {
    "iso:country":"DE",
    "sg:address":"Bahnhofstr. 11",
    "sg:city":"Schwarzenbek",
    "sg:phone":"+49 4151/895333",
    "sg:postcode":"21493",
    "sg:province":"Schleswig-Holstein",
    "wof:name":"Peter Alten K\u00fcchen Gmbh",
    "wof:placetype":"venue"
},
  "geometry": {"coordinates":[10.4824838638,53.5036010742],"type":"Point"}
}