{
  "type": "Feature",
  "properties": {
    "iso:country":"DE",
    "sg:address":"M\u00fchlenholzstr. 8",
    "sg:city":"Neubrandenburg",
    "sg:phone":"+49 395/5823392",
    "sg:postcode":"17033",
    "sg:province":"Mecklenburg-Vorpommern",
    "wof:name":"Klaus Janner",
    "wof:placetype":"venue"
},
  "geometry": {"coordinates":[13.2734975815,53.5546379089],"type":"Point"}
}