{
  "type": "Feature",
  "properties": {
    "iso:country":"DE",
    "sg:address":"Obere Ortsstr. 12",
    "sg:city":"Schiltberg",
    "sg:phone":"+49 8259/301",
    "sg:postcode":"86576",
    "sg:province":"Bayern",
    "wof:name":"Alois Kaupp",
    "wof:placetype":"venue"
},
  "geometry": {"coordinates":[11.250043869,48.4584655762],"type":"Point"}
}