{
  "type": "Feature",
  "properties": {
    "iso:country":"DE",
    "sg:address":"51069",
    "sg:city":"Cologne",
    "sg:postcode":"51069",
    "sg:province":"Nordrhein-Westfalen",
    "wof:name":"Dellbr\u00fccker Volksbank Eg",
    "wof:placetype":"venue"
},
  "geometry": {"coordinates":[7.05738,50.986061],"type":"Point"}
}