{
  "type": "Feature",
  "properties": {
    "iso:country":"DE",
    "sg:address":"Windelsbleicher Str. 246",
    "sg:city":"Bielefeld",
    "sg:phone":"+49 521/40666",
    "sg:postcode":"33659",
    "sg:province":"Nordrhein-Westfalen",
    "wof:name":"Pizzeria Italia",
    "wof:placetype":"venue"
},
  "geometry": {"coordinates":[8.5209798813,51.95753479],"type":"Point"}
}