{
  "type": "Feature",
  "properties": {
    "iso:country":"DE",
    "sg:address":"Hannoversche Neustadt 40",
    "sg:city":"Burgdorf",
    "sg:phone":"+49 5136/81122",
    "sg:postcode":"31303",
    "sg:province":"Niedersachsen",
    "wof:name":"Monika Und Klaus Queck",
    "wof:placetype":"venue"
},
  "geometry": {"coordinates":[10.0066843033,52.4482955933],"type":"Point"}
}