{
  "type": "Feature",
  "properties": {
    "iso:country":"DE",
    "sg:address":"Hermann-Hesse-Str. 21",
    "sg:city":"M\u00fchlacker",
    "sg:phone":"+49 7041/7480",
    "sg:postcode":"75417",
    "sg:province":"Baden-W\u00fcrttemberg",
    "wof:name":"Dr. Helmut Zeile Heilpraktiker",
    "wof:placetype":"venue"
},
  "geometry": {"coordinates":[8.8528308868,48.9491920471],"type":"Point"}
}