{
  "type": "Feature",
  "properties": {
    "iso:country":"DE",
    "sg:address":"Burgdorfer Str. 63",
    "sg:city":"Lehrte",
    "sg:postcode":"31275",
    "sg:province":"Niedersachsen",
    "wof:name":"Si Quiang Gmbh",
    "wof:placetype":"venue"
},
  "geometry": {"coordinates":[9.9756422043,52.3812637329],"type":"Point"}
}