{
  "type": "Feature",
  "properties": {
    "iso:country":"DE",
    "sg:address":"Pfalzstr. 24",
    "sg:city":"D\u00fcsseldorf",
    "sg:phone":"+49 211/5580527",
    "sg:postcode":"40477",
    "sg:province":"Nordrhein-Westfalen",
    "wof:name":"Ca Brachtendorf",
    "wof:placetype":"venue"
},
  "geometry": {"coordinates":[6.7812771797,51.2410964966],"type":"Point"}
}