{
  "type": "Feature",
  "properties": {
    "iso:country":"DE",
    "sg:address":"Schlossergasse 7",
    "sg:city":"Kempten",
    "sg:phone":"+49 831/2540895",
    "sg:postcode":"87439",
    "sg:province":"Bayern",
    "wof:name":"Otto Hertel",
    "wof:placetype":"venue"
},
  "geometry": {"coordinates":[10.307943,47.729546],"type":"Point"}
}