{
  "type": "Feature",
  "properties": {
    "iso:country":"DE",
    "sg:address":"Kleine Ringstr 1",
    "sg:city":"Oederan",
    "sg:phone":"+49 37292/30030",
    "sg:postcode":"09569",
    "sg:province":"Sachsen",
    "wof:name":"Ralf Emele",
    "wof:placetype":"venue"
},
  "geometry": {"coordinates":[13.187972,50.868389],"type":"Point"}
}