{
  "type": "Feature",
  "properties": {
    "iso:country":"DE",
    "sg:address":"Bergstr. 10",
    "sg:city":"Merkelbach",
    "sg:phone":"+49 2662/4139",
    "sg:postcode":"57629",
    "sg:province":"Rheinland-Pfalz",
    "wof:name":"Norbert Wessler",
    "wof:placetype":"venue"
},
  "geometry": {"coordinates":[7.770164,50.642731],"type":"Point"}
}