{
  "type": "Feature",
  "properties": {
    "iso:country":"DE",
    "sg:address":"Tullastr. 28",
    "sg:city":"Karlsruhe",
    "sg:phone":"+49 721/9614344",
    "sg:postcode":"76131",
    "sg:province":"Baden-W\u00fcrttemberg",
    "wof:name":"Vivatech Software Verwaltungs Gmbh",
    "wof:placetype":"venue"
},
  "geometry": {"coordinates":[8.4313411713,49.011505127],"type":"Point"}
}