{
  "type": "Feature",
  "properties": {
    "iso:country":"DE",
    "sg:address":"Stra\u00dfe der Jugend 63",
    "sg:city":"Eilenburg",
    "sg:phone":"+49 3423/600317",
    "sg:postcode":"04838",
    "sg:province":"Sachsen",
    "wof:name":"Ronald Wolff",
    "wof:placetype":"venue"
},
  "geometry": {"coordinates":[12.6131067276,51.4538230896],"type":"Point"}
}