{
  "type": "Feature",
  "properties": {
    "iso:country":"DE",
    "sg:address":"Mettmanner Str. 65",
    "sg:city":"D\u00fcsseldorf",
    "sg:postcode":"40233",
    "sg:province":"Nordrhein-Westfalen",
    "wof:name":"Omnikono Design Constructors Gmbh",
    "wof:placetype":"venue"
},
  "geometry": {"coordinates":[6.804922,51.222729],"type":"Point"}
}