{
  "type": "Feature",
  "properties": {
    "iso:country":"DE",
    "sg:address":"Geringhoffstr. 48",
    "sg:city":"M\u00fcnster",
    "sg:postcode":"48163",
    "sg:province":"Nordrhein-Westfalen",
    "wof:name":"Winkels Und Behrens Ingenieure",
    "wof:placetype":"venue"
},
  "geometry": {"coordinates":[7.5999660492,51.9297981262],"type":"Point"}
}