{
  "type": "Feature",
  "properties": {
    "iso:country":"DE",
    "sg:address":"Bahnhofstr. 2",
    "sg:city":"Hoppenwalde",
    "sg:phone":"+49 39779/27318",
    "sg:postcode":"17375",
    "sg:province":"Mecklenburg-Vorpommern",
    "wof:name":"Frithjof Freese",
    "wof:placetype":"venue"
},
  "geometry": {"coordinates":[-77.202591,40.014359],"type":"Point"}
}