{
  "type": "Feature",
  "properties": {
    "iso:country":"DE",
    "sg:address":"Hofstr. 12",
    "sg:city":"Rottendorf",
    "sg:phone":"+49 9302/4111",
    "sg:postcode":"97228",
    "sg:province":"Bayern",
    "wof:name":"Pumpen Cohak Inh. Ernst Kaupel",
    "wof:placetype":"venue"
},
  "geometry": {"coordinates":[10.023214,49.791901],"type":"Point"}
}