{
  "type": "Feature",
  "properties": {
    "iso:country":"DE",
    "sg:address":"Marienfelder Allee 133",
    "sg:city":"Berlin",
    "sg:phone":"+49 30/7216011",
    "sg:postcode":"12277",
    "sg:province":"Berlin",
    "wof:name":"Ulrike Riedel Masseurin",
    "wof:placetype":"venue"
},
  "geometry": {"coordinates":[13.364655,52.414829],"type":"Point"}
}