{
  "type": "Feature",
  "properties": {
    "iso:country":"DE",
    "sg:address":"Bruno-Baum-Ring 52",
    "sg:city":"Rathenow",
    "sg:phone":"+49 3385/514214",
    "sg:postcode":"14712",
    "sg:province":"Brandenburg",
    "wof:name":"Kaffeeberge Gastst\u00e4tte",
    "wof:placetype":"venue"
},
  "geometry": {"coordinates":[12.3581886292,52.6048774719],"type":"Point"}
}