{
  "type": "Feature",
  "properties": {
    "iso:country":"DE",
    "sg:city":"Bondorf",
    "sg:phone":"+49 7457",
    "sg:postcode":"71149",
    "sg:province":"Baden-W\u00fcrttemberg",
    "wof:name":"Tanzband Albatros",
    "wof:placetype":"venue"
},
  "geometry": {"coordinates":[8.83696,48.522453],"type":"Point"}
}