{
  "type": "Feature",
  "properties": {
    "iso:country":"DE",
    "sg:address":"Gievitzer Str. 58",
    "sg:city":"Waren",
    "sg:phone":"+49 3991/663349",
    "sg:postcode":"17192",
    "sg:province":"Mecklenburg-Vorpommern",
    "wof:name":"Gabriele Breiter Rechtsanw\u00e4ltin",
    "wof:placetype":"venue"
},
  "geometry": {"coordinates":[12.7829904556,53.5109405518],"type":"Point"}
}