{
  "type": "Feature",
  "properties": {
    "iso:country":"DE",
    "sg:address":"Zum Silberkamp 9 A",
    "sg:city":"Marxen",
    "sg:postcode":"21439",
    "sg:province":"Niedersachsen",
    "wof:name":"Image-bau-gmbh",
    "wof:placetype":"venue"
},
  "geometry": {"coordinates":[10.0071811676,53.308303833],"type":"Point"}
}