{
  "type": "Feature",
  "properties": {
    "iso:country":"DE",
    "sg:address":"Auf der Kunst 2",
    "sg:city":"Siegen",
    "sg:phone":"+49 271/353936",
    "sg:postcode":"57080",
    "sg:province":"Nordrhein-Westfalen",
    "wof:name":"Alfred Wirths",
    "wof:placetype":"venue"
},
  "geometry": {"coordinates":[7.960711956,50.8554763794],"type":"Point"}
}