{
  "type": "Feature",
  "properties": {
    "iso:country":"DE",
    "sg:address":"Goldener Reif 113",
    "sg:city":"Bremen",
    "sg:phone":"+49 421/581776",
    "sg:postcode":"28259",
    "sg:province":"Bremen",
    "wof:name":"Bernhard Saage",
    "wof:placetype":"venue"
},
  "geometry": {"coordinates":[8.743155,53.058098],"type":"Point"}
}