{
  "type": "Feature",
  "properties": {
    "iso:country":"DE",
    "sg:address":"Pausaer Str. 14",
    "sg:city":"Plauen",
    "sg:phone":"+49 3741/523466",
    "sg:postcode":"08525",
    "sg:province":"Sachsen",
    "wof:name":"Hapa Ag",
    "wof:placetype":"venue"
},
  "geometry": {"coordinates":[12.130399,50.507263],"type":"Point"}
}