{
  "type": "Feature",
  "properties": {
    "iso:country":"DE",
    "sg:address":"Horster Str. 59 a",
    "sg:city":"Hamm",
    "sg:phone":"+49 2381/70051",
    "sg:postcode":"59075",
    "sg:province":"Nordrhein-Westfalen",
    "wof:name":"H.-j. Kuhlmann Gmbh",
    "wof:placetype":"venue"
},
  "geometry": {"coordinates":[7.7441301346,51.7002410889],"type":"Point"}
}