{
  "type": "Feature",
  "properties": {
    "iso:country":"DE",
    "sg:address":"Huttenstr. 13",
    "sg:city":"Dresden",
    "sg:phone":"+49 351/3108500",
    "sg:postcode":"01309",
    "sg:province":"Sachsen",
    "wof:name":"Dr. Ulrich Carraro Ingenieur",
    "wof:placetype":"venue"
},
  "geometry": {"coordinates":[13.7791185379,51.0503807068],"type":"Point"}
}