{
  "type": "Feature",
  "properties": {
    "iso:country":"DE",
    "sg:address":"B\u00fcrgerm.-Franz-Str. 10",
    "sg:city":"Fuldatal",
    "sg:phone":"+49 561/811150",
    "sg:postcode":"34233",
    "sg:province":"Hessen",
    "wof:name":"Adolf K\u00f6hler Architekt",
    "wof:placetype":"venue"
},
  "geometry": {"coordinates":[9.52606,51.350334],"type":"Point"}
}