{
  "type": "Feature",
  "properties": {
    "iso:country":"DE",
    "sg:address":"J.-F.-Weishaar-Str. 24",
    "sg:city":"Korb",
    "sg:phone":"+49 7151/33195",
    "sg:postcode":"71404",
    "sg:province":"Baden-W\u00fcrttemberg",
    "wof:name":"Werner Layer",
    "wof:placetype":"venue"
},
  "geometry": {"coordinates":[9.361164093,48.8446388245],"type":"Point"}
}