{
  "type": "Feature",
  "properties": {
    "iso:country":"DE",
    "sg:address":"Sterndamm 122",
    "sg:city":"Berlin",
    "sg:phone":"+49 30/6357083",
    "sg:postcode":"12487",
    "sg:province":"Berlin",
    "wof:name":"Heinz Raschke Architekt",
    "wof:placetype":"venue"
},
  "geometry": {"coordinates":[13.500613,52.441673],"type":"Point"}
}