{
  "type": "Feature",
  "properties": {
    "iso:country":"DE",
    "sg:address":"Schmiedgasse 8-10",
    "sg:city":"Frankenthal",
    "sg:phone":"+49 6233/327800",
    "sg:postcode":"67227",
    "sg:province":"Rheinland-Pfalz",
    "wof:name":"H. Graebke & N. Mohn Rechtsanw\u00e4lte",
    "wof:placetype":"venue"
},
  "geometry": {"coordinates":[8.3518838882,49.5363883972],"type":"Point"}
}