{
  "type": "Feature",
  "properties": {
    "iso:country":"DE",
    "sg:address":"Merowingerstr. 87",
    "sg:city":"Kleve",
    "sg:phone":"+49 2821/24391",
    "sg:postcode":"47533",
    "sg:province":"Nordrhein-Westfalen",
    "wof:name":"Pizza Express Al Gusto",
    "wof:placetype":"venue"
},
  "geometry": {"coordinates":[6.1193180084,51.7826881409],"type":"Point"}
}