{
  "type": "Feature",
  "properties": {
    "iso:country":"DE",
    "sg:address":"Schulstr.",
    "sg:city":"Wallenborn",
    "sg:phone":"+49 6599/333",
    "sg:postcode":"54570",
    "sg:province":"Rheinland-Pfalz",
    "wof:name":"Edgar Und Hilde Clemens",
    "wof:placetype":"venue"
},
  "geometry": {"coordinates":[6.717415,50.1549],"type":"Point"}
}