{
  "type": "Feature",
  "properties": {
    "iso:country":"DE",
    "sg:address":"Steinf\u00f6rder Stra\u00dfe 4",
    "sg:city":"Wietze",
    "sg:phone":"+49 5146",
    "sg:postcode":"29323",
    "sg:province":"Niedersachsen",
    "wof:name":"Gemeinde Wietze",
    "wof:placetype":"venue"
},
  "geometry": {"coordinates":[9.8401317596,52.6545753479],"type":"Point"}
}