{
  "type": "Feature",
  "properties": {
    "iso:country":"DE",
    "sg:address":"Roemheldstr. 22",
    "sg:city":"Gundelsheim",
    "sg:phone":"+49 6269/2104",
    "sg:postcode":"74831",
    "sg:province":"Baden-W\u00fcrttemberg",
    "wof:name":"Freibad",
    "wof:placetype":"venue"
},
  "geometry": {"coordinates":[9.1585922241,49.2875289917],"type":"Point"}
}