{
  "type": "Feature",
  "properties": {
    "iso:country":"DE",
    "sg:address":"Schoenermarker Weg 2",
    "sg:city":"Barenthin",
    "sg:phone":"+49 33972/40283",
    "sg:postcode":"16866",
    "sg:province":"Brandenburg",
    "wof:name":"Agrargenossenschaft Barenthin-koetzlin Eg",
    "wof:placetype":"venue"
},
  "geometry": {"coordinates":[12.244195,52.925655],"type":"Point"}
}