{
  "type": "Feature",
  "properties": {
    "iso:country":"DE",
    "sg:address":"Am Bahnhof",
    "sg:city":"Jahnsdorf",
    "sg:phone":"+49 3721/22572",
    "sg:postcode":"09387",
    "sg:province":"Sachsen",
    "wof:name":"Krause Garten- Und",
    "wof:placetype":"venue"
},
  "geometry": {"coordinates":[12.82428,50.750099],"type":"Point"}
}