{
  "type": "Feature",
  "properties": {
    "iso:country":"DE",
    "sg:address":"Ahornweg 3",
    "sg:city":"Titisee-Neustadt",
    "sg:phone":"+49 171 5703300",
    "sg:postcode":"79822",
    "sg:province":"Baden-W\u00fcrttemberg",
    "wof:name":"Andorf - Schwarzwaldgalerie",
    "wof:placetype":"venue"
},
  "geometry": {"coordinates":[8.1998052597,47.9226341248],"type":"Point"}
}