{
  "type": "Feature",
  "properties": {
    "iso:country":"DE",
    "sg:address":"Egestorfer Landstr. 50",
    "sg:city":"Garlstorf",
    "sg:phone":"+49 4172/7556",
    "sg:postcode":"21376",
    "sg:province":"Niedersachsen",
    "wof:name":"Garlstorfer Forst Campingplatz",
    "wof:placetype":"venue"
},
  "geometry": {"coordinates":[10.092764,53.230789],"type":"Point"}
}