{
  "type": "Feature",
  "properties": {
    "iso:country":"DE",
    "sg:address":"Nei\u00dfestr. 8 a",
    "sg:city":"Bramsche",
    "sg:phone":"+49 5461/3340",
    "sg:postcode":"49565",
    "sg:province":"Niedersachsen",
    "wof:name":"V. Piel",
    "wof:placetype":"venue"
},
  "geometry": {"coordinates":[8.0100746155,52.4026908875],"type":"Point"}
}