{
  "type": "Feature",
  "properties": {
    "iso:country":"DE",
    "sg:address":"Am Eisenborn 23",
    "sg:city":"Saulheim",
    "sg:phone":"+49 6732/4096",
    "sg:postcode":"55291",
    "sg:province":"Rheinland-Pfalz",
    "wof:name":"Karl Und Viorica Szekely",
    "wof:placetype":"venue"
},
  "geometry": {"coordinates":[8.154106,49.875473],"type":"Point"}
}