{
  "type": "Feature",
  "properties": {
    "iso:country":"DE",
    "sg:address":"Moritzstr. 18",
    "sg:city":"Bad Gandersheim",
    "sg:phone":"+49 5382/2833",
    "sg:postcode":"37581",
    "sg:province":"Niedersachsen",
    "wof:name":"Manfred Becker",
    "wof:placetype":"venue"
},
  "geometry": {"coordinates":[10.0243549347,51.8700256348],"type":"Point"}
}