{
  "type": "Feature",
  "properties": {
    "iso:country":"DE",
    "sg:address":"Agnesstr. 25",
    "sg:city":"Nienburg",
    "sg:phone":"+49 34721/23517",
    "sg:postcode":"06429",
    "sg:province":"Sachsen-Anhalt",
    "wof:name":"Andrea G\u00fcnzler",
    "wof:placetype":"venue"
},
  "geometry": {"coordinates":[11.7653980255,51.8395576477],"type":"Point"}
}