{
  "type": "Feature",
  "properties": {
    "iso:country":"DE",
    "sg:address":"Humboldtstr. 88",
    "sg:city":"N\u00fcrnberg",
    "sg:phone":"+49 911/457444",
    "sg:postcode":"90459",
    "sg:province":"Bayern",
    "wof:name":"Pizzeria Amalfi",
    "wof:placetype":"venue"
},
  "geometry": {"coordinates":[11.0784578323,49.4384346008],"type":"Point"}
}