{
  "type": "Feature",
  "properties": {
    "iso:country":"DE",
    "sg:address":"Ursulastr. 39",
    "sg:city":"Neustadt",
    "sg:phone":"+49 6321/80818",
    "sg:postcode":"67434",
    "sg:province":"Rheinland-Pfalz",
    "wof:name":"J\u00fcrgen Herman Elektromeister",
    "wof:placetype":"venue"
},
  "geometry": {"coordinates":[8.140807,49.322865],"type":"Point"}
}