{
  "type": "Feature",
  "properties": {
    "iso:country":"DE",
    "sg:address":"Oldenfelder Str. 26",
    "sg:city":"Hamburg",
    "sg:phone":"+49 40/6756630",
    "sg:postcode":"22143",
    "sg:province":"Hamburg",
    "wof:name":"Gemeinsam In Die Zukunft- Verwaltungs Gmbh",
    "wof:placetype":"venue"
},
  "geometry": {"coordinates":[10.1567687988,53.6084327698],"type":"Point"}
}