{
  "type": "Feature",
  "properties": {
    "iso:country":"DE",
    "sg:address":"Silcherstr. 2",
    "sg:city":"Eichstetten",
    "sg:phone":"+49 7663/912040",
    "sg:postcode":"79356",
    "sg:province":"Baden-W\u00fcrttemberg",
    "wof:name":"Facilities Management Gmbh",
    "wof:placetype":"venue"
},
  "geometry": {"coordinates":[7.7499117851,48.0964164734],"type":"Point"}
}