{
  "type": "Feature",
  "properties": {
    "iso:country":"DE",
    "sg:address":"Lohkamp 6",
    "sg:city":"Nortorf",
    "sg:phone":"+49 4392/4440",
    "sg:postcode":"24589",
    "sg:province":"Schleswig-Holstein",
    "wof:name":"Monika Werner",
    "wof:placetype":"venue"
},
  "geometry": {"coordinates":[9.8568820953,54.1658668518],"type":"Point"}
}