{
  "type": "Feature",
  "properties": {
    "iso:country":"DE",
    "sg:address":"Merziger Str. 18",
    "sg:city":"Losheim",
    "sg:phone":"+49 6872/2425",
    "sg:postcode":"66679",
    "sg:province":"Saarland",
    "wof:name":"Schmitt",
    "wof:placetype":"venue"
},
  "geometry": {"coordinates":[6.7425198555,49.507522583],"type":"Point"}
}