{
  "type": "Feature",
  "properties": {
    "iso:country":"DE",
    "sg:address":"Zehnthausstr. 10",
    "sg:city":"Sankt Aldegund",
    "sg:phone":"+49 6542/22463",
    "sg:postcode":"56858",
    "sg:province":"Rheinland-Pfalz",
    "wof:name":"A. Reis Weinanbau",
    "wof:placetype":"venue"
},
  "geometry": {"coordinates":[7.1311888695,50.0829963684],"type":"Point"}
}