{
  "type": "Feature",
  "properties": {
    "iso:country":"DE",
    "sg:address":"Blumenstr. 5",
    "sg:city":"Dachau",
    "sg:phone":"+49 8131/80908",
    "sg:postcode":"85221",
    "sg:province":"Bayern",
    "wof:name":"Bernd Wildner",
    "wof:placetype":"venue"
},
  "geometry": {"coordinates":[11.443481,48.261875],"type":"Point"}
}