{
  "type": "Feature",
  "properties": {
    "iso:country":"DE",
    "sg:address":"K\u00f6hler Str. 41-45",
    "sg:city":"Dorsten",
    "sg:phone":"+49 2369/2010",
    "sg:postcode":"46286",
    "sg:province":"Nordrhein-Westfalen",
    "wof:name":"Johne & Co. Pr\u00e4szisionswerkzeuge Gmbh",
    "wof:placetype":"venue"
},
  "geometry": {"coordinates":[7.004294,51.711376],"type":"Point"}
}