{
  "type": "Feature",
  "properties": {
    "iso:country":"DE",
    "sg:address":"Mittlere Gasse 10",
    "sg:city":"Schwaigern",
    "sg:phone":"+49 7138/6634",
    "sg:postcode":"74193",
    "sg:province":"Baden-W\u00fcrttemberg",
    "wof:name":"Wolfgang Haagen",
    "wof:placetype":"venue"
},
  "geometry": {"coordinates":[9.005776,49.130074],"type":"Point"}
}