{
  "type": "Feature",
  "properties": {
    "iso:country":"DE",
    "sg:address":"H\u00fcfnerweg 39",
    "sg:city":"Berlin",
    "sg:phone":"+49 30/66709021",
    "sg:postcode":"12349",
    "sg:province":"Berlin",
    "wof:name":"Berthold Landgraf Inh. Erika Krause",
    "wof:placetype":"venue"
},
  "geometry": {"coordinates":[13.431834,52.43058],"type":"Point"}
}