{
  "type": "Feature",
  "properties": {
    "iso:country":"DE",
    "sg:address":"Max-Planck-Str. 13",
    "sg:city":"Nordhorn",
    "sg:phone":"+49 5921/2166",
    "sg:postcode":"48529",
    "sg:province":"Niedersachsen",
    "wof:name":"Enderlein-project-engineering Gmbh & Co. Kg",
    "wof:placetype":"venue"
},
  "geometry": {"coordinates":[7.0807218552,52.409450531],"type":"Point"}
}