{
  "type": "Feature",
  "properties": {
    "iso:country":"DE",
    "sg:address":"Schwalbacher Str. 97",
    "sg:city":"Saarwellingen",
    "sg:phone":"+49 6838/3450",
    "sg:postcode":"66793",
    "sg:province":"Saarland",
    "wof:name":"Roland Grund",
    "wof:placetype":"venue"
},
  "geometry": {"coordinates":[6.8522081375,49.3218688965],"type":"Point"}
}