{
  "type": "Feature",
  "properties": {
    "iso:country":"DE",
    "sg:address":"Stechbahn 78",
    "sg:city":"Kleve",
    "sg:phone":"+49 2821/28044",
    "sg:postcode":"47533",
    "sg:province":"Nordrhein-Westfalen",
    "wof:name":"Susanne Peters Steuerberaterin",
    "wof:placetype":"venue"
},
  "geometry": {"coordinates":[6.1309990883,51.7870788574],"type":"Point"}
}