{
  "type": "Feature",
  "properties": {
    "iso:country":"DE",
    "sg:address":"Dreik\u00f6nigstr. 7",
    "sg:city":"Schwetzingen",
    "sg:phone":"+49 4962/0225011",
    "sg:postcode":"68723",
    "sg:province":"Baden-W\u00fcrttemberg",
    "wof:name":"Citibank Privatkunden Ag",
    "wof:placetype":"venue"
},
  "geometry": {"coordinates":[8.571648,49.385799],"type":"Point"}
}