{
  "type": "Feature",
  "properties": {
    "iso:country":"DE",
    "sg:address":"Gro\u00dfe Str. 68",
    "sg:city":"Lahstedt",
    "sg:phone":"+49 5172/6274",
    "sg:postcode":"31246",
    "sg:province":"Niedersachsen",
    "wof:name":"Gemeindeb\u00fccherei Adenstedt Schulgeb\u00e4ude",
    "wof:placetype":"venue"
},
  "geometry": {"coordinates":[10.167372,52.244495],"type":"Point"}
}