{
  "type": "Feature",
  "properties": {
    "iso:country":"DE",
    "sg:address":"Pariner Str. 62",
    "sg:city":"Bad Schwartau",
    "sg:phone":"+49 451/21605",
    "sg:postcode":"23611",
    "sg:province":"Schleswig-Holstein",
    "wof:name":"J\u00fcrgen Kayser",
    "wof:placetype":"venue"
},
  "geometry": {"coordinates":[10.6922140121,53.931137085],"type":"Point"}
}