{
  "type": "Feature",
  "properties": {
    "iso:country":"DE",
    "sg:address":"Kylische Str. 58",
    "sg:city":"Sangerhausen",
    "sg:phone":"+49 3464/572946",
    "sg:postcode":"06526",
    "sg:province":"Sachsen-Anhalt",
    "wof:name":"Sangersh\u00e4user Versicherungs- Vermittlungs Gmbh",
    "wof:placetype":"venue"
},
  "geometry": {"coordinates":[11.2938346863,51.4722251892],"type":"Point"}
}