{
  "type": "Feature",
  "properties": {
    "iso:country":"DE",
    "sg:address":"Zeulsdorfer Str. 18",
    "sg:city":"Gera",
    "sg:phone":"+49 365/35117",
    "sg:postcode":"07549",
    "sg:province":"Th\u00fcringen",
    "wof:name":"Kato-fitness Gbr",
    "wof:placetype":"venue"
},
  "geometry": {"coordinates":[12.0689620972,50.8455696106],"type":"Point"}
}