{
  "type": "Feature",
  "properties": {
    "iso:country":"DE",
    "sg:address":"Stuttgarter Str. 10",
    "sg:city":"Karlsruhe",
    "sg:phone":"+49 721/964660",
    "sg:postcode":"76137",
    "sg:province":"Baden-W\u00fcrttemberg",
    "wof:name":"Holzwelt Bumb",
    "wof:placetype":"venue"
},
  "geometry": {"coordinates":[8.4233293533,49.0012512207],"type":"Point"}
}