{
  "type": "Feature",
  "properties": {
    "iso:country":"DE",
    "sg:address":"M\u00fchlenstr. 43",
    "sg:city":"Cottbus",
    "sg:phone":"+49 355/22404",
    "sg:postcode":"03046",
    "sg:province":"Brandenburg",
    "wof:name":"Kurt Prommersberger Rechtsanwalt",
    "wof:placetype":"venue"
},
  "geometry": {"coordinates":[14.3341588974,51.7596282959],"type":"Point"}
}