{
  "type": "Feature",
  "properties": {
    "iso:country":"DE",
    "sg:address":"Montebradoni",
    "sg:city":"Volterra",
    "sg:phone":"+49 39058/842055",
    "sg:postcode":"56048",
    "wof:name":"Ferien In Der Podere Cortilla",
    "wof:placetype":"venue"
},
  "geometry": {"coordinates":[10.853092,43.417446],"type":"Point"}
}