{
  "type": "Feature",
  "properties": {
    "iso:country":"DE",
    "sg:address":"Tann",
    "sg:city":"Tann",
    "sg:phone":"+49 8572/287",
    "sg:postcode":"84367",
    "sg:province":"Bayern",
    "wof:name":"Volksbank Simbach-pfarrkirchen Eg",
    "wof:placetype":"venue"
},
  "geometry": {"coordinates":[12.8963,48.327492],"type":"Point"}
}