{
  "type": "Feature",
  "properties": {
    "iso:country":"DE",
    "sg:address":"Goethestr. 13 e",
    "sg:city":"Dippoldiswalde",
    "sg:phone":"+49 3504/612305",
    "sg:postcode":"01744",
    "sg:province":"Sachsen",
    "wof:name":"Manfred Gei\u00dfler",
    "wof:placetype":"venue"
},
  "geometry": {"coordinates":[13.654849,50.896839],"type":"Point"}
}