{
  "type": "Feature",
  "properties": {
    "iso:country":"DE",
    "sg:address":"Holzkamp 24",
    "sg:city":"Itzehoe",
    "sg:phone":"+49 4821/3066",
    "sg:postcode":"25524",
    "sg:province":"Schleswig-Holstein",
    "wof:name":"Zahntechnik Willh\u00f6ft Gmbh & Co. Kg",
    "wof:placetype":"venue"
},
  "geometry": {"coordinates":[9.522576,53.92345],"type":"Point"}
}