{
  "type": "Feature",
  "properties": {
    "iso:country":"DE",
    "sg:address":"Fuchslochstr. 26",
    "sg:city":"Bretten",
    "sg:phone":"+49 7252/84051",
    "sg:postcode":"75015",
    "sg:province":"Baden-W\u00fcrttemberg",
    "wof:name":"Matthias Kuhn",
    "wof:placetype":"venue"
},
  "geometry": {"coordinates":[8.724991,49.013668],"type":"Point"}
}