{
  "type": "Feature",
  "properties": {
    "iso:country":"DE",
    "sg:address":"Albert-Schweitzer-Str. 2a",
    "sg:city":"Tauberbischofsheim",
    "sg:phone":"+49 9341/41577",
    "sg:postcode":"97941",
    "sg:province":"Baden-W\u00fcrttemberg",
    "wof:name":"Vertrauens\u00e4rztlicher-dienst Der Lva W\u00fcrttemberg",
    "wof:placetype":"venue"
},
  "geometry": {"coordinates":[9.6683359146,49.6239738464],"type":"Point"}
}