{
  "type": "Feature",
  "properties": {
    "iso:country":"DE",
    "sg:address":"Niederhutstr. 7",
    "sg:city":"Bad Neuenahr-Ahrweiler",
    "sg:phone":"+49 2641/34340",
    "sg:postcode":"53474",
    "sg:province":"Rheinland-Pfalz",
    "wof:name":"Anton B\u00f6cker Eisenwaren",
    "wof:placetype":"venue"
},
  "geometry": {"coordinates":[7.0971879959,50.5432319641],"type":"Point"}
}