{
  "type": "Feature",
  "properties": {
    "iso:country":"DE",
    "sg:address":"Am Pestalozziring 8",
    "sg:city":"Erlangen",
    "sg:phone":"+49 9131/77320",
    "sg:postcode":"91058",
    "sg:province":"Bayern",
    "wof:name":"Fink Gmbh",
    "wof:placetype":"venue"
},
  "geometry": {"coordinates":[11.0043649673,49.5546607971],"type":"Point"}
}