{
  "type": "Feature",
  "properties": {
    "iso:country":"DE",
    "sg:address":"Ihlbrocker Damm 21",
    "sg:city":"Drebber",
    "sg:phone":"+49 5445/554",
    "sg:postcode":"49457",
    "sg:province":"Niedersachsen",
    "wof:name":"Rolf Br\u00fcggemann",
    "wof:placetype":"venue"
},
  "geometry": {"coordinates":[8.4525604248,52.6596183777],"type":"Point"}
}