{
  "type": "Feature",
  "properties": {
    "iso:country":"DE",
    "sg:address":"Gro\u00dfe Str. 8",
    "sg:city":"Schiffdorf",
    "sg:phone":"+49 4703/365",
    "sg:postcode":"27619",
    "sg:province":"Niedersachsen",
    "wof:name":"Gastst\u00e4tte J.-j. Petersen",
    "wof:placetype":"venue"
},
  "geometry": {"coordinates":[8.7410898209,53.5239181519],"type":"Point"}
}