{
  "type": "Feature",
  "properties": {
    "iso:country":"DE",
    "sg:address":"Ringstr. 2",
    "sg:city":"Glandorf",
    "sg:phone":"+49 5426/1633",
    "sg:postcode":"49219",
    "sg:province":"Niedersachsen",
    "wof:name":"Guntram Jan\u00dfen Masseur",
    "wof:placetype":"venue"
},
  "geometry": {"coordinates":[8.006908,52.083019],"type":"Point"}
}