{
  "type": "Feature",
  "properties": {
    "iso:country":"DE",
    "sg:address":"Kaiserhaus 79",
    "sg:city":"Bernau",
    "sg:phone":"+49 7675/819",
    "sg:postcode":"79872",
    "sg:province":"Baden-W\u00fcrttemberg",
    "wof:name":"G\u00e4stehaus Sonneneck",
    "wof:placetype":"venue"
},
  "geometry": {"coordinates":[8.0621337891,47.7975234985],"type":"Point"}
}