{
  "type": "Feature",
  "properties": {
    "iso:country":"DE",
    "sg:address":"Sieglindenstr. 4",
    "sg:city":"Augsburg",
    "sg:phone":"+49 821/156510",
    "sg:postcode":"86152",
    "sg:province":"Bayern",
    "wof:name":"Berufsverband Der Deutschen Kieferorthp\u00e4den",
    "wof:placetype":"venue"
},
  "geometry": {"coordinates":[10.8861646652,48.3685569763],"type":"Point"}
}