{
  "type": "Feature",
  "properties": {
    "iso:country":"DE",
    "sg:address":"Graf-Sponheim-Str. 10",
    "sg:city":"Winningen",
    "sg:phone":"+49 2606/2110",
    "sg:postcode":"56333",
    "sg:province":"Rheinland-Pfalz",
    "wof:name":"Wolfgang Von Canal",
    "wof:placetype":"venue"
},
  "geometry": {"coordinates":[7.5209860802,50.3138580322],"type":"Point"}
}