{
  "type": "Feature",
  "properties": {
    "iso:country":"DE",
    "sg:address":"Kuseler Str. 2",
    "sg:city":"K\u00f6ln",
    "sg:phone":"+49 221/9171713",
    "sg:postcode":"50739",
    "sg:province":"Nordrhein-Westfalen",
    "wof:name":"Ernst Essers",
    "wof:placetype":"venue"
},
  "geometry": {"coordinates":[6.9305210114,50.9691390991],"type":"Point"}
}