{
  "type": "Feature",
  "properties": {
    "iso:country":"DE",
    "sg:address":"Starenweg 26",
    "sg:city":"Dessau",
    "sg:phone":"+49 340/8581306",
    "sg:postcode":"06849",
    "sg:province":"Sachsen-Anhalt",
    "wof:name":"Ic Falkenberg Karsten Giersch",
    "wof:placetype":"venue"
},
  "geometry": {"coordinates":[12.2574243546,51.8053283691],"type":"Point"}
}