{
  "type": "Feature",
  "properties": {
    "iso:country":"DE",
    "sg:address":"Im Kreut 2",
    "sg:city":"Strullendorf",
    "sg:phone":"+49 9543/3499",
    "sg:postcode":"96129",
    "sg:province":"Bayern",
    "wof:name":"Horst Tuffner",
    "wof:placetype":"venue"
},
  "geometry": {"coordinates":[10.9725246429,49.8455886841],"type":"Point"}
}