{
  "type": "Feature",
  "properties": {
    "iso:country":"DE",
    "sg:address":"Alte Ziegelei 4",
    "sg:city":"Hannover",
    "sg:phone":"+49 511/797013",
    "sg:postcode":"30419",
    "sg:province":"Niedersachsen",
    "wof:name":"Partner-reisen",
    "wof:placetype":"venue"
},
  "geometry": {"coordinates":[9.6654081345,52.4015693665],"type":"Point"}
}