{
  "type": "Feature",
  "properties": {
    "iso:country":"DE",
    "sg:address":"Unter der Burg 17",
    "sg:city":"Zell",
    "sg:postcode":"93199",
    "sg:province":"Bayern",
    "wof:name":"Aichinger & Wagner Zimmerei Gmbh & Co. Kg",
    "wof:placetype":"venue"
},
  "geometry": {"coordinates":[12.4093742371,49.1447906494],"type":"Point"}
}