{
  "type": "Feature",
  "properties": {
    "iso:country":"DE",
    "sg:address":"Hauptstr. 5",
    "sg:city":"Ipsheim",
    "sg:postcode":"91472",
    "sg:province":"Bayern",
    "wof:name":"Raiffeisenbank Bad Wurzach Eg",
    "wof:placetype":"venue"
},
  "geometry": {"coordinates":[9.89666,47.854519],"type":"Point"}
}