{
  "type": "Feature",
  "properties": {
    "iso:country":"DE",
    "sg:address":"Eiffestr 632",
    "sg:city":"Hamburg",
    "sg:phone":"+49 40/21098290",
    "sg:postcode":"20537",
    "sg:province":"Hamburg",
    "wof:name":"Jourist Verlags Gmbh",
    "wof:placetype":"venue"
},
  "geometry": {"coordinates":[10.059861,53.550713],"type":"Point"}
}