{
  "type": "Feature",
  "properties": {
    "iso:country":"DE",
    "sg:address":"Alemannenstr. 15",
    "sg:city":"Elsdorf",
    "sg:phone":"+49 2274/6232",
    "sg:postcode":"50189",
    "sg:province":"Nordrhein-Westfalen",
    "wof:name":"Franz-peter Hofmeister Rechtsanwalt",
    "wof:placetype":"venue"
},
  "geometry": {"coordinates":[6.5593109131,50.9426460266],"type":"Point"}
}