{
  "type": "Feature",
  "properties": {
    "iso:country":"DE",
    "sg:address":"Sitterswalder Str. 5",
    "sg:city":"Kleinblittersdorf",
    "sg:phone":"+49 6805/8314",
    "sg:postcode":"66271",
    "sg:province":"Saarland",
    "wof:name":"Zur Schwemm",
    "wof:placetype":"venue"
},
  "geometry": {"coordinates":[7.0565190315,49.1419906616],"type":"Point"}
}