{
  "type": "Feature",
  "properties": {
    "iso:country":"DE",
    "sg:address":"Winklerstr. 42",
    "sg:city":"Chemnitz",
    "sg:postcode":"09113",
    "sg:province":"Sachsen",
    "wof:name":"Gfba Gesellschaft Zur F\u00f6rderung Der Betrieblichen",
    "wof:placetype":"venue"
},
  "geometry": {"coordinates":[12.909187,50.846165],"type":"Point"}
}