{
  "type": "Feature",
  "properties": {
    "iso:country":"DE",
    "sg:address":"Sibyllenstr. 22",
    "sg:city":"Weilheim",
    "sg:phone":"+49 7023/71411",
    "sg:postcode":"73235",
    "sg:province":"Baden-W\u00fcrttemberg",
    "wof:name":"F. Bachofer",
    "wof:placetype":"venue"
},
  "geometry": {"coordinates":[9.5235052109,48.624797821],"type":"Point"}
}