{
  "type": "Feature",
  "properties": {
    "iso:country":"DE",
    "sg:address":"Schnepfenreuther Weg 4",
    "sg:city":"Berlin",
    "sg:phone":"+49 30/3367059",
    "sg:postcode":"13587",
    "sg:province":"Berlin",
    "wof:name":"Orpheus",
    "wof:placetype":"venue"
},
  "geometry": {"coordinates":[13.201665,52.555828],"type":"Point"}
}