{
  "type": "Feature",
  "properties": {
    "iso:country":"DE",
    "sg:address":"Zum J\u00e4gerberg 45",
    "sg:city":"Hagen",
    "sg:phone":"+49 5405/3367",
    "sg:postcode":"49170",
    "sg:province":"Niedersachsen",
    "wof:name":"Hermann Schulte To B\u00fchne Vers. Hof Meyer To Bergte",
    "wof:placetype":"venue"
},
  "geometry": {"coordinates":[7.9637908936,52.2137374878],"type":"Point"}
}