{
  "type": "Feature",
  "properties": {
    "iso:country":"DE",
    "sg:address":"Treitschkestr. 31",
    "sg:city":"Berlin",
    "sg:phone":"+49 30/8216852",
    "sg:postcode":"12163",
    "sg:province":"Berlin",
    "wof:name":"Ev. Pfarramt Patmos-gemeinde",
    "wof:placetype":"venue"
},
  "geometry": {"coordinates":[13.3168210983,52.4656333923],"type":"Point"}
}