{
  "type": "Feature",
  "properties": {
    "iso:country":"DE",
    "sg:address":"Kraftenbuckelweg 25",
    "sg:city":"Baiersbronn",
    "sg:phone":"+49 7449/91081",
    "sg:postcode":"72270",
    "sg:province":"Baden-W\u00fcrttemberg",
    "wof:name":"Franz Waltersbacher Gmbh",
    "wof:placetype":"venue"
},
  "geometry": {"coordinates":[8.2805213928,48.5346984863],"type":"Point"}
}