{
  "type": "Feature",
  "properties": {
    "iso:country":"DE",
    "sg:address":"Marienstrasse 72",
    "sg:city":"Wuppertal",
    "sg:phone":"+49 202/3097010",
    "sg:postcode":"42105",
    "sg:province":"Nordrhein-Westfalen",
    "wof:name":"Deutsche Automobil Datenbank",
    "wof:placetype":"venue"
},
  "geometry": {"coordinates":[7.1353478432,51.2586021423],"type":"Point"}
}