{
  "type": "Feature",
  "properties": {
    "iso:country":"DE",
    "sg:address":"An den Feldk\u00e4mpen 19",
    "sg:city":"Bad Zwischenahn",
    "sg:phone":"+49 4403",
    "sg:postcode":"26160",
    "sg:province":"Niedersachsen",
    "wof:name":"Harald Eilers Baumschulen",
    "wof:placetype":"venue"
},
  "geometry": {"coordinates":[7.9642300606,53.1766548157],"type":"Point"}
}