{
  "type": "Feature",
  "properties": {
    "iso:country":"DE",
    "sg:address":"Hufweg 25",
    "sg:city":"Goch",
    "sg:phone":"+49 2827/305",
    "sg:postcode":"47574",
    "sg:province":"Nordrhein-Westfalen",
    "wof:name":"Heinrich Broeckmann",
    "wof:placetype":"venue"
},
  "geometry": {"coordinates":[6.105391,51.672527],"type":"Point"}
}