{
  "type": "Feature",
  "properties": {
    "iso:country":"DE",
    "sg:address":"Virchowstr. 15",
    "sg:city":"Hamburg",
    "sg:phone":"+49 40/38021701",
    "sg:postcode":"22767",
    "sg:province":"Hamburg",
    "wof:name":"Norddeutsche Gew\u00fcrzm\u00fchle Walter Schwere Gmbh",
    "wof:placetype":"venue"
},
  "geometry": {"coordinates":[9.946917,53.549812],"type":"Point"}
}