{
  "type": "Feature",
  "properties": {
    "iso:country":"DE",
    "sg:address":"Senftlstr. 4",
    "sg:city":"M\u00fcnchen",
    "sg:phone":"+49 89/4891730",
    "sg:postcode":"81541",
    "sg:province":"Bayern",
    "wof:name":"Roland G\u00f6r\u00f6g E. K.",
    "wof:placetype":"venue"
},
  "geometry": {"coordinates":[11.5882415771,48.1230049133],"type":"Point"}
}