{
  "type": "Feature",
  "properties": {
    "iso:country":"DE",
    "sg:address":"Heinrich-Heine-Str. 17",
    "sg:city":"Schneidlingen",
    "sg:phone":"+49 39267/590",
    "sg:postcode":"39435",
    "sg:province":"Sachsen-Anhalt",
    "wof:name":"Helmut G\u00f6bke Ingenieur",
    "wof:placetype":"venue"
},
  "geometry": {"coordinates":[11.4258651733,51.9413108826],"type":"Point"}
}