{
  "type": "Feature",
  "properties": {
    "iso:country":"DE",
    "sg:address":"Hauptstr 15",
    "sg:city":"Siebenbrunn",
    "sg:phone":"+49 37422/3125",
    "sg:postcode":"08258",
    "sg:province":"Sachsen",
    "wof:name":"Estoma Inh. Klaus-peter Brussig",
    "wof:placetype":"venue"
},
  "geometry": {"coordinates":[12.303599,50.309452],"type":"Point"}
}