{
  "type": "Feature",
  "properties": {
    "iso:country":"DE",
    "sg:address":"Karl-Nagel-Str. 1",
    "sg:city":"Augsburg",
    "sg:phone":"+49 821/93091",
    "sg:postcode":"86199",
    "sg:province":"Bayern",
    "wof:name":"Praxis Dr. Med. N\u00fcbling \u00c4rzte F\u00fcr Orthop\u00e4die",
    "wof:placetype":"venue"
},
  "geometry": {"coordinates":[10.8757953644,48.3506698608],"type":"Point"}
}