{
  "type": "Feature",
  "properties": {
    "iso:country":"DE",
    "sg:address":"Wilhelmstr. 22 A Voerde",
    "sg:city":"Ennepetal",
    "sg:phone":"+49 4923/332037",
    "sg:postcode":"58256",
    "sg:province":"Nordrhein-Westfalen",
    "wof:name":"Fritz Dannert Gmbh & Co. Kg",
    "wof:placetype":"venue"
},
  "geometry": {"coordinates":[7.369048,51.296734],"type":"Point"}
}