{
  "type": "Feature",
  "properties": {
    "iso:country":"DE",
    "sg:address":"Eichenweg 1",
    "sg:city":"Petersberg",
    "sg:phone":"+49 36691/43263",
    "sg:postcode":"07616",
    "sg:province":"Th\u00fcringen",
    "wof:name":"Autohaus Klein Gmbh",
    "wof:placetype":"venue"
},
  "geometry": {"coordinates":[11.8525209427,50.9689216614],"type":"Point"}
}