{
  "type": "Feature",
  "properties": {
    "iso:country":"DE",
    "sg:address":"Gailling 5 a",
    "sg:city":"Baiern",
    "sg:phone":"+49 8093/628",
    "sg:postcode":"85625",
    "sg:province":"Bayern",
    "wof:name":"Edv-beratung Englhart Gmbh",
    "wof:placetype":"venue"
},
  "geometry": {"coordinates":[11.9016103745,47.9911193848],"type":"Point"}
}