{
  "type": "Feature",
  "properties": {
    "iso:country":"DE",
    "sg:address":"Gerhart-Hauptmann-Str. 14",
    "sg:city":"Hoyerswerda",
    "sg:phone":"+49 3571/417730",
    "sg:postcode":"02977",
    "sg:province":"Sachsen",
    "wof:name":"Reinhard Hoppe",
    "wof:placetype":"venue"
},
  "geometry": {"coordinates":[14.2350788116,51.4350700378],"type":"Point"}
}