{
  "type": "Feature",
  "properties": {
    "iso:country":"DE",
    "sg:address":"Am Waldwinkel 73",
    "sg:city":"Hannover",
    "sg:phone":"+49 511/582937",
    "sg:postcode":"30629",
    "sg:province":"Niedersachsen",
    "wof:name":"Ingo K\u00f6nig",
    "wof:placetype":"venue"
},
  "geometry": {"coordinates":[9.8475627899,52.3977737427],"type":"Point"}
}