{
  "type": "Feature",
  "properties": {
    "iso:country":"DE",
    "sg:address":"Gartenstr. 7",
    "sg:city":"Bedesbach",
    "sg:phone":"+49 6381/6322",
    "sg:postcode":"66885",
    "sg:province":"Rheinland-Pfalz",
    "wof:name":"Paul Leyser",
    "wof:placetype":"venue"
},
  "geometry": {"coordinates":[7.4572358131,49.5694084167],"type":"Point"}
}