{
  "type": "Feature",
  "properties": {
    "iso:country":"DE",
    "sg:address":"Pfalzstr. 40",
    "sg:city":"K\u00f6nigsbrunn",
    "sg:phone":"+49 8231/5314",
    "sg:postcode":"86343",
    "sg:province":"Bayern",
    "wof:name":"Ullsperger",
    "wof:placetype":"venue"
},
  "geometry": {"coordinates":[10.8919410706,48.2663955688],"type":"Point"}
}