{
  "type": "Feature",
  "properties": {
    "iso:country":"DE",
    "sg:address":"Pegauer Str. 10",
    "sg:city":"Lucka",
    "sg:phone":"+49 34492/24391",
    "sg:postcode":"04613",
    "sg:province":"Th\u00fcringen",
    "wof:name":"Optik Zimmerling Gmbh",
    "wof:placetype":"venue"
},
  "geometry": {"coordinates":[12.3320627213,51.0993766785],"type":"Point"}
}