{
  "type": "Feature",
  "properties": {
    "iso:country":"DE",
    "sg:address":"Ringstr. 6",
    "sg:city":"Lisberg",
    "sg:phone":"+49 9549/921068",
    "sg:postcode":"96170",
    "sg:province":"Bayern",
    "wof:name":"Hans Steinh\u00e4user",
    "wof:placetype":"venue"
},
  "geometry": {"coordinates":[10.7299442291,49.8960418701],"type":"Point"}
}