{
  "type": "Feature",
  "properties": {
    "iso:country":"DE",
    "sg:address":"Berge",
    "sg:city":"Meschede",
    "sg:phone":"+49 2903/536",
    "sg:postcode":"59872",
    "sg:province":"Nordrhein-Westfalen",
    "wof:name":"Dolerit-basalt Grundwert- Und Beteiligungs- Ag",
    "wof:placetype":"venue"
},
  "geometry": {"coordinates":[8.1717195511,51.3746833801],"type":"Point"}
}