{
  "type": "Feature",
  "properties": {
    "iso:country":"DE",
    "sg:address":"Windenstr. 2-4",
    "sg:city":"Witten",
    "sg:phone":"+49 2302/2080",
    "sg:postcode":"58455",
    "sg:province":"Nordrhein-Westfalen",
    "wof:name":"Hebezeug-museum",
    "wof:placetype":"venue"
},
  "geometry": {"coordinates":[7.291836,51.436779],"type":"Point"}
}