{
  "type": "Feature",
  "properties": {
    "iso:country":"DE",
    "sg:address":"Robert-Bosch-Str. 20",
    "sg:city":"Linden",
    "sg:postcode":"35440",
    "sg:province":"Hessen",
    "wof:name":"Sirius Production Gmbh",
    "wof:placetype":"venue"
},
  "geometry": {"coordinates":[8.654917717,50.5377616882],"type":"Point"}
}