{
  "type": "Feature",
  "properties": {
    "iso:country":"DE",
    "sg:address":"Probelokal (Schulstra\u00dfe)",
    "sg:city":"Br\u00e4unlingen",
    "sg:postcode":"78199",
    "sg:province":"Baden-W\u00fcrttemberg",
    "wof:name":"Stadtkapelle Br\u00e4unlingen E.v.",
    "wof:placetype":"venue"
},
  "geometry": {"coordinates":[8.447654,47.930107],"type":"Point"}
}