{
  "type": "Feature",
  "properties": {
    "iso:country":"DE",
    "sg:address":"Schwabh\u00e4user Str. 12",
    "sg:city":"Boxberg",
    "sg:phone":"+49 7930/6153",
    "sg:postcode":"97944",
    "sg:province":"Baden-W\u00fcrttemberg",
    "wof:name":"Helga Fischer",
    "wof:placetype":"venue"
},
  "geometry": {"coordinates":[9.6022930145,49.4555511475],"type":"Point"}
}