{
  "type": "Feature",
  "properties": {
    "iso:country":"DE",
    "sg:address":"Ackersweg 5 a",
    "sg:city":"Neuwied",
    "sg:phone":"+49 2622/837699",
    "sg:postcode":"56566",
    "sg:province":"Rheinland-Pfalz",
    "wof:name":"Franz Kraus",
    "wof:placetype":"venue"
},
  "geometry": {"coordinates":[7.5493202209,50.4460906982],"type":"Point"}
}