{
  "type": "Feature",
  "properties": {
    "iso:country":"DE",
    "sg:address":"Aubruchsgraben 50",
    "sg:city":"Duisburg",
    "sg:phone":"+49 2151/403746",
    "sg:postcode":"47239",
    "sg:province":"Nordrhein-Westfalen",
    "wof:name":"Dr. Med. Ralf Werner",
    "wof:placetype":"venue"
},
  "geometry": {"coordinates":[6.635032177,51.4057044983],"type":"Point"}
}