{
  "type": "Feature",
  "properties": {
    "iso:country":"DE",
    "sg:address":"Tiergartenstr. 47",
    "sg:city":"J\u00fcnkerath",
    "sg:phone":"+49 6597/5292",
    "sg:postcode":"54584",
    "sg:province":"Rheinland-Pfalz",
    "wof:name":"R. Und M. Cremer Immobilienmakler",
    "wof:placetype":"venue"
},
  "geometry": {"coordinates":[6.5827322006,50.3464164734],"type":"Point"}
}