{
  "type": "Feature",
  "properties": {
    "iso:country":"DE",
    "sg:address":"Schlei\u00dfheimer Str. 34",
    "sg:city":"M\u00fcnchen",
    "sg:postcode":"80333",
    "sg:province":"Bayern",
    "wof:name":"Elev 8 Visual Projekts Feuerer Und Nitsch Partnersch.",
    "wof:placetype":"venue"
},
  "geometry": {"coordinates":[11.559991,48.150295],"type":"Point"}
}