{
  "type": "Feature",
  "properties": {
    "iso:country":"DE",
    "sg:address":"Saonestr. 10",
    "sg:city":"Frankfurt",
    "sg:postcode":"60528",
    "sg:province":"Hessen",
    "wof:name":"Optimail Services Gmbh",
    "wof:placetype":"venue"
},
  "geometry": {"coordinates":[8.631077,50.082073],"type":"Point"}
}