{
  "type": "Feature",
  "properties": {
    "iso:country":"DE",
    "sg:address":"Am Altenbruch 15",
    "sg:city":"Mettmann",
    "sg:phone":"+49 2104/805669",
    "sg:postcode":"40822",
    "sg:province":"Nordrhein-Westfalen",
    "wof:name":"Wolf Holtgreve",
    "wof:placetype":"venue"
},
  "geometry": {"coordinates":[6.9658899307,51.2635917664],"type":"Point"}
}