{
  "type": "Feature",
  "properties": {
    "iso:country":"DE",
    "sg:address":"Belfortstr. 9",
    "sg:city":"K\u00f6ln",
    "sg:phone":"+49 9573/96900",
    "sg:postcode":"50668",
    "sg:province":"Nordrhein-Westfalen",
    "wof:name":"Schorr & Co",
    "wof:placetype":"venue"
},
  "geometry": {"coordinates":[10.9963064194,50.0992355347],"type":"Point"}
}