{
  "type": "Feature",
  "properties": {
    "iso:country":"DE",
    "sg:address":"Auf der Olk 7",
    "sg:city":"Veldenz",
    "sg:phone":"+49 6534/8734",
    "sg:postcode":"54472",
    "sg:province":"Rheinland-Pfalz",
    "wof:name":"Pension Ewald Kruft-kiefer",
    "wof:placetype":"venue"
},
  "geometry": {"coordinates":[7.0268001556,49.8884887695],"type":"Point"}
}