{
  "type": "Feature",
  "properties": {
    "iso:country":"DE",
    "sg:address":"Markusplatz 39",
    "sg:city":"K\u00f6ln",
    "sg:phone":"+49 221/383887",
    "sg:postcode":"50968",
    "sg:province":"Nordrhein-Westfalen",
    "wof:name":"Obstwolf Gmbh",
    "wof:placetype":"venue"
},
  "geometry": {"coordinates":[6.947529,50.899063],"type":"Point"}
}