{
  "type": "Feature",
  "properties": {
    "iso:country":"DE",
    "sg:address":"Breite Str. 15",
    "sg:city":"Torgau",
    "sg:phone":"+49 3421/903313",
    "sg:postcode":"04860",
    "sg:province":"Sachsen",
    "wof:name":"Croissanterie Frieder Francke Gmbh",
    "wof:placetype":"venue"
},
  "geometry": {"coordinates":[13.002365,51.559639],"type":"Point"}
}