{
  "type": "Feature",
  "properties": {
    "iso:country":"DE",
    "sg:address":"Neufriedenheim 14",
    "sg:city":"Treuchtlingen",
    "sg:phone":"+49 9142",
    "sg:postcode":"91757",
    "sg:province":"Bayern",
    "wof:name":"Automatisierung, Sondermaschinen, Vorrichtungen",
    "wof:placetype":"venue"
},
  "geometry": {"coordinates":[10.908255,48.968811],"type":"Point"}
}