{
  "type": "Feature",
  "properties": {
    "iso:country":"DE",
    "sg:address":"Breite Str. 6",
    "sg:city":"Ravensburg",
    "sg:phone":"+49 751/62976",
    "sg:postcode":"88214",
    "sg:province":"Baden-W\u00fcrttemberg",
    "wof:name":"Fritz H\u00fcbner",
    "wof:placetype":"venue"
},
  "geometry": {"coordinates":[9.602973,47.766525],"type":"Point"}
}