{
  "type": "Feature",
  "properties": {
    "iso:country":"DE",
    "sg:address":"P\u00fctzgasse 5",
    "sg:city":"Remagen",
    "sg:phone":"+49 2228/910145",
    "sg:postcode":"53424",
    "sg:province":"Rheinland-Pfalz",
    "wof:name":"Albert Zettelmeier Rechtsanwalt",
    "wof:placetype":"venue"
},
  "geometry": {"coordinates":[7.2068638802,50.6153068542],"type":"Point"}
}