{
  "type": "Feature",
  "properties": {
    "iso:country":"DE",
    "sg:address":"Oldenburger Str. 95",
    "sg:city":"Vechta",
    "sg:phone":"+49 4441/92920",
    "sg:postcode":"49377",
    "sg:province":"Niedersachsen",
    "wof:name":"J\u00fcrgen F. Kurzbach B\u00fcroeinrichtungen",
    "wof:placetype":"venue"
},
  "geometry": {"coordinates":[8.2837972641,52.7394866943],"type":"Point"}
}