{
  "type": "Feature",
  "properties": {
    "iso:country":"DE",
    "sg:address":"Bahnhofstr. 51a",
    "sg:city":"Bad Sachsa",
    "sg:phone":"+49 5523/94400",
    "sg:postcode":"37441",
    "sg:province":"Niedersachsen",
    "wof:name":"Dietrich Brand",
    "wof:placetype":"venue"
},
  "geometry": {"coordinates":[10.568288,51.590145],"type":"Point"}
}