{
  "type": "Feature",
  "properties": {
    "iso:country":"DE",
    "sg:address":"Siegener Str. 174",
    "sg:city":"Kreuztal",
    "sg:phone":"+49 2732/6522",
    "sg:postcode":"57223",
    "sg:province":"Nordrhein-Westfalen",
    "wof:name":"Zur Hube",
    "wof:placetype":"venue"
},
  "geometry": {"coordinates":[8.0065755844,50.9328193665],"type":"Point"}
}