{
  "type": "Feature",
  "properties": {
    "iso:country":"DE",
    "sg:address":"Schwabacher Str. 19",
    "sg:city":"F\u00fcrth",
    "sg:phone":"+49 911/7432863",
    "sg:postcode":"90762",
    "sg:province":"Bayern",
    "wof:name":"Nordsee-quick",
    "wof:placetype":"venue"
},
  "geometry": {"coordinates":[10.98873806,49.4738197327],"type":"Point"}
}