{
  "type": "Feature",
  "properties": {
    "iso:country":"DE",
    "sg:address":"Boschstr. 19",
    "sg:city":"Westerburg",
    "sg:phone":"+49 2663/94040",
    "sg:postcode":"56457",
    "sg:province":"Rheinland-Pfalz",
    "wof:name":"Bauschlosserei Und Metallbau Hans Gmbh",
    "wof:placetype":"venue"
},
  "geometry": {"coordinates":[7.947503,50.546162],"type":"Point"}
}