{
  "type": "Feature",
  "properties": {
    "iso:country":"DE",
    "sg:address":"Bahnhofstr. 9a",
    "sg:city":"Eschwege",
    "sg:phone":"+49 5651/7837",
    "sg:postcode":"37269",
    "sg:province":"Hessen",
    "wof:name":"Werkstatt F\u00fcr Junge Menschen Eschwege E. V.",
    "wof:placetype":"venue"
},
  "geometry": {"coordinates":[10.04662,51.191311],"type":"Point"}
}