{
  "type": "Feature",
  "properties": {
    "iso:country":"DE",
    "sg:address":"\u00d6jendorfer Weg 32",
    "sg:city":"Hamburg",
    "sg:phone":"+49 40/7322896",
    "sg:postcode":"22119",
    "sg:province":"Hamburg",
    "wof:name":"Eiscafe Gerold Hillmann",
    "wof:placetype":"venue"
},
  "geometry": {"coordinates":[10.110552,53.542435],"type":"Point"}
}