{
  "type": "Feature",
  "properties": {
    "iso:country":"DE",
    "sg:address":"Fr\u00fchlingstr. 62",
    "sg:city":"Bad Reichenhall",
    "sg:phone":"+49 8651/78070",
    "sg:postcode":"83435",
    "sg:province":"Bayern",
    "wof:name":"D\u00fcrk Gmbh & Co. Hoch- Und Tiefbau Kg",
    "wof:placetype":"venue"
},
  "geometry": {"coordinates":[12.886628,47.736244],"type":"Point"}
}