{
  "type": "Feature",
  "properties": {
    "iso:country":"DE",
    "sg:address":"Kirchstr. 16",
    "sg:city":"S\u00fcnching",
    "sg:phone":"+49 9480/737",
    "sg:postcode":"93104",
    "sg:province":"Bayern",
    "wof:name":"Bernd Wolfsperger Med. B\u00e4der",
    "wof:placetype":"venue"
},
  "geometry": {"coordinates":[12.35405,48.879269],"type":"Point"}
}