{
  "type": "Feature",
  "properties": {
    "iso:country":"DE",
    "sg:address":"Redwitzstr. 21",
    "sg:city":"K\u00f6ln",
    "sg:phone":"+49 221/413835",
    "sg:postcode":"50937",
    "sg:province":"Nordrhein-Westfalen",
    "wof:name":"Activa Hausverwaltungs-gmbh",
    "wof:placetype":"venue"
},
  "geometry": {"coordinates":[6.9252519608,50.9205818176],"type":"Point"}
}