{
  "type": "Feature",
  "properties": {
    "iso:country":"DE",
    "sg:address":"Poststr. 51-53",
    "sg:city":"B\u00f6blingen",
    "sg:phone":"+49 7031/220106",
    "sg:postcode":"71032",
    "sg:province":"Baden-W\u00fcrttemberg",
    "wof:name":"Daniel Gmbh",
    "wof:placetype":"venue"
},
  "geometry": {"coordinates":[9.0148220062,48.6853065491],"type":"Point"}
}