{
  "type": "Feature",
  "properties": {
    "iso:country":"DE",
    "sg:address":"M\u00fchlenstr. 7",
    "sg:city":"Br\u00fchl",
    "sg:phone":"+49 2232/49373",
    "sg:postcode":"50321",
    "sg:province":"Nordrhein-Westfalen",
    "wof:name":"Cafe",
    "wof:placetype":"venue"
},
  "geometry": {"coordinates":[6.901634,50.826763],"type":"Point"}
}