{
  "type": "Feature",
  "properties": {
    "iso:country":"DE",
    "sg:address":"Martin-Luther-Str. 16",
    "sg:city":"Landau",
    "sg:phone":"+49 6341/4354",
    "sg:postcode":"76829",
    "sg:province":"Rheinland-Pfalz",
    "wof:name":"Martin-luther-stube",
    "wof:placetype":"venue"
},
  "geometry": {"coordinates":[8.1134443283,49.1960067749],"type":"Point"}
}