{
  "type": "Feature",
  "properties": {
    "iso:country":"DE",
    "sg:address":"Charlottenstr. 12",
    "sg:city":"Schw\u00e4bisch Gm\u00fcnd",
    "sg:phone":"+49 7171/36633",
    "sg:postcode":"73525",
    "sg:province":"Baden-W\u00fcrttemberg",
    "wof:name":"City Garage",
    "wof:placetype":"venue"
},
  "geometry": {"coordinates":[9.8055353165,48.7998275757],"type":"Point"}
}