{
  "type": "Feature",
  "properties": {
    "iso:country":"DE",
    "sg:address":"Graumannsweg 55",
    "sg:city":"Hamburg",
    "sg:phone":"+49 40/2299390",
    "sg:postcode":"22087",
    "sg:province":"Hamburg",
    "wof:name":"Baukontakt Gmbh",
    "wof:placetype":"venue"
},
  "geometry": {"coordinates":[10.02216,53.564095],"type":"Point"}
}