{
  "type": "Feature",
  "properties": {
    "iso:country":"DE",
    "sg:address":"Linnicher Str. 9",
    "sg:city":"J\u00fclich",
    "sg:phone":"+49 2461/4974",
    "sg:postcode":"52428",
    "sg:province":"Nordrhein-Westfalen",
    "wof:name":"F.-j. Wick Architekt",
    "wof:placetype":"venue"
},
  "geometry": {"coordinates":[6.355302,50.927345],"type":"Point"}
}