{
  "type": "Feature",
  "properties": {
    "iso:country":"DE",
    "sg:address":"Dechaneystr. 3",
    "sg:city":"R\u00fcdesheim am Rhein",
    "sg:phone":"+49 6722/3333",
    "sg:postcode":"65385",
    "sg:province":"Hessen",
    "wof:name":"Josef Gilles",
    "wof:placetype":"venue"
},
  "geometry": {"coordinates":[7.9322180748,49.9877586365],"type":"Point"}
}