{
  "type": "Feature",
  "properties": {
    "iso:country":"DE",
    "sg:address":"Brucker Str. 19",
    "sg:city":"Einsbach",
    "sg:phone":"+49 8135/993726",
    "sg:postcode":"85254",
    "sg:province":"Bayern",
    "wof:name":"Chempress Gmbh",
    "wof:placetype":"venue"
},
  "geometry": {"coordinates":[11.266841,48.269421],"type":"Point"}
}