{
  "type": "Feature",
  "properties": {
    "iso:country":"DE",
    "sg:address":"Beiertheimer Allee 18",
    "sg:city":"Karlsruhe",
    "sg:phone":"+49 721/34044",
    "sg:postcode":"76137",
    "sg:province":"Baden-W\u00fcrttemberg",
    "wof:name":"Alter Brauhof",
    "wof:placetype":"venue"
},
  "geometry": {"coordinates":[8.3971595764,49.0011062622],"type":"Point"}
}