{
  "type": "Feature",
  "properties": {
    "iso:country":"DE",
    "sg:address":"Marktplatz 8",
    "sg:city":"Neustadt",
    "sg:phone":"+49 6321/92460",
    "sg:postcode":"67433",
    "sg:province":"Rheinland-Pfalz",
    "wof:name":"Securitas Bremer Allgemeine Versicherungs- Ag",
    "wof:placetype":"venue"
},
  "geometry": {"coordinates":[8.1361026764,49.3532714844],"type":"Point"}
}