{
  "type": "Feature",
  "properties": {
    "iso:country":"DE",
    "sg:address":"Talstr. 13",
    "sg:city":"Egloffstein",
    "sg:phone":"+49 9197/1800",
    "sg:postcode":"91349",
    "sg:province":"Bayern",
    "wof:name":"Paul Schelhorn",
    "wof:placetype":"venue"
},
  "geometry": {"coordinates":[11.2601633072,49.7013816833],"type":"Point"}
}