{
  "type": "Feature",
  "properties": {
    "iso:country":"DE",
    "sg:address":"Bossestr. 15",
    "sg:city":"Bielefeld",
    "sg:phone":"+49 521/132460",
    "sg:postcode":"33615",
    "sg:province":"Nordrhein-Westfalen",
    "wof:name":"Karl-heinz Bungert",
    "wof:placetype":"venue"
},
  "geometry": {"coordinates":[8.5175657272,52.0296096802],"type":"Point"}
}