{
  "type": "Feature",
  "properties": {
    "iso:country":"DE",
    "sg:address":"Hagenauerstr. 9",
    "sg:city":"M\u00fcnchen",
    "sg:phone":"+49 89/7915633",
    "sg:postcode":"81479",
    "sg:province":"Bayern",
    "wof:name":"H\u00f6ng Wohnbau Gmbh Warenhandel-beteiligungs Gmbh",
    "wof:placetype":"venue"
},
  "geometry": {"coordinates":[11.525528,48.074814],"type":"Point"}
}