{
  "type": "Feature",
  "properties": {
    "iso:country":"DE",
    "sg:address":"Penningsfelderweg",
    "sg:city":"K\u00f6ln",
    "sg:phone":"+49 221/4747902",
    "sg:postcode":"51069",
    "sg:province":"Nordrhein-Westfalen",
    "wof:name":"Lenze Garten U Anlagenbau",
    "wof:placetype":"venue"
},
  "geometry": {"coordinates":[7.0930151939,50.9661102295],"type":"Point"}
}