{
  "type": "Feature",
  "properties": {
    "iso:country":"DE",
    "sg:address":"Althansstr. 20",
    "sg:city":"Bottrop",
    "sg:postcode":"46240",
    "sg:province":"Nordrhein-Westfalen",
    "wof:name":"Brwin Datenbank- Software-internet Ohg",
    "wof:placetype":"venue"
},
  "geometry": {"coordinates":[6.9499440193,51.5406608582],"type":"Point"}
}