{
  "type": "Feature",
  "properties": {
    "iso:country":"DE",
    "sg:address":"Strelitzer Str. 9",
    "sg:city":"Neustrelitz",
    "sg:phone":"+49 3981/204322",
    "sg:postcode":"17235",
    "sg:province":"Mecklenburg-Vorpommern",
    "wof:name":"Petra Behnke",
    "wof:placetype":"venue"
},
  "geometry": {"coordinates":[13.0653743744,53.3614120483],"type":"Point"}
}