{
  "type": "Feature",
  "properties": {
    "iso:country":"DE",
    "sg:address":"Pfingstwiese 1",
    "sg:city":"Bad Ems",
    "sg:phone":"+49 2603/4533",
    "sg:postcode":"56130",
    "sg:province":"Rheinland-Pfalz",
    "wof:name":"Dieter Breuer",
    "wof:placetype":"venue"
},
  "geometry": {"coordinates":[7.723397,50.35268],"type":"Point"}
}