{
  "type": "Feature",
  "properties": {
    "iso:country":"DE",
    "sg:address":"Johannes-Schleich-Str. 3",
    "sg:city":"Birstein",
    "sg:phone":"+49 6054/900151",
    "sg:postcode":"63633",
    "sg:province":"Hessen",
    "wof:name":"Konrad Schleich",
    "wof:placetype":"venue"
},
  "geometry": {"coordinates":[9.3162097931,50.3660545349],"type":"Point"}
}