{
  "type": "Feature",
  "properties": {
    "iso:country":"DE",
    "sg:address":"Dorfstr. 18",
    "sg:city":"Estorf",
    "sg:phone":"+49 4140/232",
    "sg:postcode":"21727",
    "sg:province":"Niedersachsen",
    "wof:name":"Pension Heinrich Meier",
    "wof:placetype":"venue"
},
  "geometry": {"coordinates":[9.1796960831,53.5661010742],"type":"Point"}
}