{
  "type": "Feature",
  "properties": {
    "iso:country":"DE",
    "sg:address":"Riedstr. 2",
    "sg:city":"Dannstadt-Schauernheim",
    "sg:phone":"+49 6231/915310",
    "sg:postcode":"67125",
    "sg:province":"Rheinland-Pfalz",
    "wof:name":"Penny-markt Gmbh",
    "wof:placetype":"venue"
},
  "geometry": {"coordinates":[8.3209905624,49.4296188354],"type":"Point"}
}