{
  "type": "Feature",
  "properties": {
    "iso:country":"DE",
    "sg:address":"Veldener Str. 1",
    "sg:city":"Taufkirchen",
    "sg:phone":"+49 8084/7080",
    "sg:postcode":"82024",
    "sg:province":"Bayern",
    "wof:name":"Westermaier & Kern Gmbh",
    "wof:placetype":"venue"
},
  "geometry": {"coordinates":[11.61564,48.046207],"type":"Point"}
}