{
  "type": "Feature",
  "properties": {
    "iso:country":"DE",
    "sg:address":"K\u00fcferstr. 42",
    "sg:city":"Esslingen",
    "sg:phone":"+49 711/359864",
    "sg:postcode":"73728",
    "sg:province":"Baden-W\u00fcrttemberg",
    "wof:name":"Rolf Wenger",
    "wof:placetype":"venue"
},
  "geometry": {"coordinates":[9.3112163544,48.7398834229],"type":"Point"}
}