{
  "type": "Feature",
  "properties": {
    "iso:country":"DE",
    "sg:address":"Kerkerfeld 12",
    "sg:city":"Schermbeck",
    "sg:phone":"+49 2853/635",
    "sg:postcode":"46514",
    "sg:province":"Nordrhein-Westfalen",
    "wof:name":"Brigitte Straus Steuerbevollm\u00e4chtigte Und",
    "wof:placetype":"venue"
},
  "geometry": {"coordinates":[6.8787808418,51.6963348389],"type":"Point"}
}