{
  "type": "Feature",
  "properties": {
    "iso:country":"DE",
    "sg:address":"Goerdelerstr. 160",
    "sg:city":"N\u00fcrnberg",
    "sg:postcode":"90439",
    "sg:province":"Bayern",
    "wof:name":"World Of Dulitz",
    "wof:placetype":"venue"
},
  "geometry": {"coordinates":[11.041228,49.436466],"type":"Point"}
}