{
  "type": "Feature",
  "properties": {
    "iso:country":"DE",
    "sg:address":"Ostersoder Str 14",
    "sg:city":"Breddorf",
    "sg:phone":"+49 4285/95114",
    "sg:postcode":"27412",
    "sg:province":"Niedersachsen",
    "wof:name":"Pro Tec Systembau Gmbh",
    "wof:placetype":"venue"
},
  "geometry": {"coordinates":[9.0759963989,53.2941436768],"type":"Point"}
}