{
  "type": "Feature",
  "properties": {
    "iso:country":"DE",
    "sg:address":"Gerokstr. 11 b",
    "sg:city":"Stuttgart",
    "sg:phone":"+49 711/240097",
    "sg:postcode":"70184",
    "sg:province":"Baden-W\u00fcrttemberg",
    "wof:name":"Eckhardt Und G\u00f6ritz Rechtsanw\u00e4lte",
    "wof:placetype":"venue"
},
  "geometry": {"coordinates":[9.1926965714,48.7782707214],"type":"Point"}
}