{
  "type": "Feature",
  "properties": {
    "iso:country":"DE",
    "sg:address":"Haidgraben 2",
    "sg:city":"Ottobrunn",
    "sg:phone":"+49 89/66085073",
    "sg:postcode":"85521",
    "sg:province":"Bayern",
    "wof:name":"Trattoria La Ciacolada",
    "wof:placetype":"venue"
},
  "geometry": {"coordinates":[11.6529760361,48.0740890503],"type":"Point"}
}