{
  "type": "Feature",
  "properties": {
    "iso:country":"DE",
    "sg:address":"im Rueckerttal 32",
    "sg:city":"Blieskastel",
    "sg:phone":"+49 6842/507537",
    "sg:postcode":"66440",
    "sg:province":"Saarland",
    "wof:name":"A-schuff",
    "wof:placetype":"venue"
},
  "geometry": {"coordinates":[7.245141983,49.2162895203],"type":"Point"}
}