{
  "type": "Feature",
  "properties": {
    "iso:country":"DE",
    "sg:address":"Unnerweg 88",
    "sg:city":"Lastrup",
    "sg:phone":"+49 4472/68800",
    "sg:postcode":"49688",
    "sg:province":"Niedersachsen",
    "wof:name":"Perso Plankontor Gmbh",
    "wof:placetype":"venue"
},
  "geometry": {"coordinates":[7.8911299706,52.8026504517],"type":"Point"}
}