{
  "type": "Feature",
  "properties": {
    "iso:country":"DE",
    "sg:address":"Erhardtstr. 8",
    "sg:city":"M\u00fcnchen",
    "sg:phone":"+49 89/2014010",
    "sg:postcode":"80469",
    "sg:province":"Bayern",
    "wof:name":"Gudrun Schr\u00f6der",
    "wof:placetype":"venue"
},
  "geometry": {"coordinates":[11.5775604248,48.1287078857],"type":"Point"}
}