{
  "type": "Feature",
  "properties": {
    "iso:country":"DE",
    "sg:address":"Eckstr. 17",
    "sg:city":"Usingen",
    "sg:phone":"+49 6081/3237",
    "sg:postcode":"61250",
    "sg:province":"Hessen",
    "wof:name":"Brendel Sf Bau Gmbh",
    "wof:placetype":"venue"
},
  "geometry": {"coordinates":[8.56955,50.36047],"type":"Point"}
}