{
  "type": "Feature",
  "properties": {
    "iso:country":"DE",
    "sg:address":"Neue Bergstr. 21",
    "sg:city":"Scharbeutz",
    "sg:phone":"+49 4503/72079",
    "sg:postcode":"23683",
    "sg:province":"Schleswig-Holstein",
    "wof:name":"M. Bruhn",
    "wof:placetype":"venue"
},
  "geometry": {"coordinates":[10.7496776581,54.0291404724],"type":"Point"}
}