{
  "type": "Feature",
  "properties": {
    "iso:country":"DE",
    "sg:address":"Hauptstr. 27",
    "sg:city":"M\u00fcden",
    "sg:phone":"+49 5375/1282",
    "sg:postcode":"38539",
    "sg:province":"Niedersachsen",
    "wof:name":"Heinrich Schacht",
    "wof:placetype":"venue"
},
  "geometry": {"coordinates":[10.362209,52.525787],"type":"Point"}
}