{
  "type": "Feature",
  "properties": {
    "iso:country":"DE",
    "sg:address":"Adalbertstr. 68",
    "sg:city":"Aachen",
    "sg:phone":"+49 241/21245",
    "sg:postcode":"52062",
    "sg:province":"Nordrhein-Westfalen",
    "wof:name":"Bijou Brigitte Modische Accessoires Ag",
    "wof:placetype":"venue"
},
  "geometry": {"coordinates":[6.091931,50.775242],"type":"Point"}
}