{
  "type": "Feature",
  "properties": {
    "iso:country":"DE",
    "sg:address":"Osnabr\u00fccker Str. 2",
    "sg:city":"Borgholzhausen",
    "sg:phone":"+49 5425/284",
    "sg:postcode":"33829",
    "sg:province":"Nordrhein-Westfalen",
    "wof:name":"Julius Schulte Inh. A. Brauner",
    "wof:placetype":"venue"
},
  "geometry": {"coordinates":[8.2631101608,52.087348938],"type":"Point"}
}