{
  "type": "Feature",
  "properties": {
    "iso:country":"DE",
    "sg:address":"Lichtensteinstr. 6",
    "sg:city":"Ulm",
    "sg:phone":"+49 731/66722",
    "sg:postcode":"89075",
    "sg:province":"Baden-W\u00fcrttemberg",
    "wof:name":"Karin Wegener Innenarchitektin",
    "wof:placetype":"venue"
},
  "geometry": {"coordinates":[9.98564,48.407833],"type":"Point"}
}