{
  "type": "Feature",
  "properties": {
    "iso:country":"DE",
    "sg:address":"Geschwister-Scholl-Str. 9",
    "sg:city":"Sibbesse",
    "sg:phone":"+49 5065/9297",
    "sg:postcode":"31079",
    "sg:province":"Niedersachsen",
    "wof:name":"Rommy Krone Rechtsanw\u00e4ltin",
    "wof:placetype":"venue"
},
  "geometry": {"coordinates":[9.9063234329,52.0522575378],"type":"Point"}
}