{
  "type": "Feature",
  "properties": {
    "iso:country":"DE",
    "sg:address":"Rheinbacher Str. 54",
    "sg:city":"Berg",
    "sg:phone":"+49 2643/7099",
    "sg:postcode":"53505",
    "sg:province":"Rheinland-Pfalz",
    "wof:name":"H. Phiesel",
    "wof:placetype":"venue"
},
  "geometry": {"coordinates":[6.948539,50.555683],"type":"Point"}
}