{
  "type": "Feature",
  "properties": {
    "iso:country":"DE",
    "sg:address":"Holzstr. 16",
    "sg:city":"Berlin",
    "sg:postcode":"13359",
    "sg:province":"Berlin",
    "wof:name":"Thermo Technik Service Gmbh",
    "wof:placetype":"venue"
},
  "geometry": {"coordinates":[13.3799448013,52.5633888245],"type":"Point"}
}