{
  "type": "Feature",
  "properties": {
    "iso:country":"DE",
    "sg:address":"Feldbergstr. 89",
    "sg:city":"Mannheim",
    "sg:phone":"+49 621/814301",
    "sg:postcode":"68163",
    "sg:province":"Baden-W\u00fcrttemberg",
    "wof:name":"G. Seibert",
    "wof:placetype":"venue"
},
  "geometry": {"coordinates":[8.477942,49.460262],"type":"Point"}
}