{
  "type": "Feature",
  "properties": {
    "iso:country":"DE",
    "sg:address":"Maiergschwendterstr. 26",
    "sg:city":"Ruhpolding",
    "sg:phone":"+49 8663/1793",
    "sg:postcode":"83324",
    "sg:province":"Bayern",
    "wof:name":"Johannes Amort",
    "wof:placetype":"venue"
},
  "geometry": {"coordinates":[12.63924,47.761616],"type":"Point"}
}