{
  "type": "Feature",
  "properties": {
    "iso:country":"DE",
    "sg:address":"Lilienthalstr. 14",
    "sg:city":"Neufahrn",
    "sg:phone":"+49 8165/799700",
    "sg:postcode":"85375",
    "sg:province":"Bayern",
    "wof:name":"Mechanikon Onlineservice Gmbh",
    "wof:placetype":"venue"
},
  "geometry": {"coordinates":[11.6494617462,48.3088874817],"type":"Point"}
}