{
  "type": "Feature",
  "properties": {
    "iso:country":"DE",
    "sg:address":"Hauptstr. 32",
    "sg:city":"Lorup",
    "sg:phone":"+49 5954/386",
    "sg:postcode":"26901",
    "sg:province":"Niedersachsen",
    "wof:name":"Nikolaus Pohlgeers",
    "wof:placetype":"venue"
},
  "geometry": {"coordinates":[7.638925,52.925606],"type":"Point"}
}