{
  "type": "Feature",
  "properties": {
    "iso:country":"DE",
    "sg:address":"Waisenhofstr. 44",
    "sg:city":"Kiel",
    "sg:phone":"+49 431/93535",
    "sg:postcode":"24103",
    "sg:province":"Schleswig-Holstein",
    "wof:name":"Treuhandstelle F\u00fcr Dauergrab- Pflege Schleswig-holstein Gmbh",
    "wof:placetype":"venue"
},
  "geometry": {"coordinates":[10.127781,54.323944],"type":"Point"}
}