{
  "type": "Feature",
  "properties": {
    "iso:country":"DE",
    "sg:address":"Unkenbachstr. 10",
    "sg:city":"Dingolshausen",
    "sg:phone":"+49 9382/8250",
    "sg:postcode":"97497",
    "sg:province":"Bayern",
    "wof:name":"H\u00fcmmer Transport Gmbh",
    "wof:placetype":"venue"
},
  "geometry": {"coordinates":[10.4007997513,49.9234886169],"type":"Point"}
}