{
  "type": "Feature",
  "properties": {
    "iso:country":"DE",
    "sg:address":"Heinrich-Sch\u00fctz-Allee 29",
    "sg:city":"Kassel",
    "sg:phone":"+49 561/938930",
    "sg:postcode":"34131",
    "sg:province":"Hessen",
    "wof:name":"Roberts Werbeagentur Gmbh",
    "wof:placetype":"venue"
},
  "geometry": {"coordinates":[9.4276227951,51.3027305603],"type":"Point"}
}