{
  "type": "Feature",
  "properties": {
    "iso:country":"DE",
    "sg:address":"Mehring 8",
    "sg:city":"Teisendorf",
    "sg:phone":"+49 8666/471",
    "sg:postcode":"83317",
    "sg:province":"Bayern",
    "wof:name":"G\u00e4stehaus Ottilie Warislohner",
    "wof:placetype":"venue"
},
  "geometry": {"coordinates":[12.7976760864,47.8629226685],"type":"Point"}
}