{
  "type": "Feature",
  "properties": {
    "iso:country":"DE",
    "sg:address":"Zum Sprakel 206",
    "sg:city":"Vrees",
    "sg:phone":"+49 5956/261",
    "sg:postcode":"49757",
    "sg:province":"Niedersachsen",
    "wof:name":"Gerhard Jansen",
    "wof:placetype":"venue"
},
  "geometry": {"coordinates":[7.67801,52.850975],"type":"Point"}
}