{
  "type": "Feature",
  "properties": {
    "iso:country":"DE",
    "sg:address":"Gereonstr. 16",
    "sg:city":"K\u00f6ln",
    "sg:phone":"+49 221/1390230",
    "sg:postcode":"50670",
    "sg:province":"Nordrhein-Westfalen",
    "wof:name":"Safef Stahlhandel Gmbh",
    "wof:placetype":"venue"
},
  "geometry": {"coordinates":[6.9488501549,50.9429702759],"type":"Point"}
}