{
  "type": "Feature",
  "properties": {
    "iso:country":"DE",
    "sg:address":"Gustav-Mahler-Str. 29",
    "sg:city":"Leipzig",
    "sg:phone":"+49 341/9902931",
    "sg:postcode":"04109",
    "sg:province":"Sachsen",
    "wof:name":"Euro Concept Gbr Brigitte Haarbach",
    "wof:placetype":"venue"
},
  "geometry": {"coordinates":[12.361548,51.338161],"type":"Point"}
}