{
  "type": "Feature",
  "properties": {
    "iso:country":"DE",
    "sg:address":"Karl-Friedrich-Benz-Str. 6-8",
    "sg:city":"Neuenburg",
    "sg:phone":"+49 7631/79010",
    "sg:postcode":"79395",
    "sg:province":"Baden-W\u00fcrttemberg",
    "wof:name":"F\u00f6rster Gmbh & Co. Grundst\u00fccksverwaltungs Kg",
    "wof:placetype":"venue"
},
  "geometry": {"coordinates":[7.5588159561,47.8084602356],"type":"Point"}
}