{
  "type": "Feature",
  "properties": {
    "iso:country":"DE",
    "sg:address":"Ulzburger Str. 8b",
    "sg:city":"Norderstedt",
    "sg:phone":"+49 40/5279907",
    "sg:postcode":"22850",
    "sg:province":"Schleswig-Holstein",
    "wof:name":"Offset-service Norderstedt",
    "wof:placetype":"venue"
},
  "geometry": {"coordinates":[9.998376,53.683537],"type":"Point"}
}