{
  "type": "Feature",
  "properties": {
    "iso:country":"DE",
    "sg:address":"Bebraer Str. 6",
    "sg:city":"Eschwege",
    "sg:phone":"+49 5651/92050",
    "sg:postcode":"37269",
    "sg:province":"Hessen",
    "wof:name":"Autohaus Rabe Gmbh & Co. Kg",
    "wof:placetype":"venue"
},
  "geometry": {"coordinates":[10.02685,51.176998],"type":"Point"}
}