{
  "type": "Feature",
  "properties": {
    "iso:country":"DE",
    "sg:address":"Bonner Wall 31",
    "sg:city":"K\u00f6ln",
    "sg:phone":"+49 221/9370310",
    "sg:postcode":"50677",
    "sg:province":"Nordrhein-Westfalen",
    "wof:name":"Lienenl\u00fcke & Reinsch Gmbh",
    "wof:placetype":"venue"
},
  "geometry": {"coordinates":[6.9538378716,50.9170455933],"type":"Point"}
}