{
  "type": "Feature",
  "properties": {
    "iso:country":"DE",
    "sg:address":"Industriestr. 34",
    "sg:city":"Coswig",
    "sg:phone":"+49 3523/62777",
    "sg:postcode":"01640",
    "sg:province":"Sachsen",
    "wof:name":"Winner Spedition Gmbh & Co. Kg",
    "wof:placetype":"venue"
},
  "geometry": {"coordinates":[13.5697517395,51.1288642883],"type":"Point"}
}