{
  "type": "Feature",
  "properties": {
    "iso:country":"DE",
    "sg:address":"Berliner Str. 4",
    "sg:city":"B\u00f6nningstedt",
    "sg:phone":"+49 40/5566737",
    "sg:postcode":"25474",
    "sg:province":"Schleswig-Holstein",
    "wof:name":"Heino Von Heimburg Mess- Und Regeltechnik Gmbh",
    "wof:placetype":"venue"
},
  "geometry": {"coordinates":[9.9077568054,53.6755981445],"type":"Point"}
}