{
  "type": "Feature",
  "properties": {
    "iso:country":"DE",
    "sg:address":"Gartenweg 19",
    "sg:city":"Schwerin",
    "sg:phone":"+49 385/85660",
    "sg:postcode":"19057",
    "sg:province":"Mecklenburg-Vorpommern",
    "wof:name":"Ulrich Flieth",
    "wof:placetype":"venue"
},
  "geometry": {"coordinates":[11.3298501968,53.660572052],"type":"Point"}
}