{
  "type": "Feature",
  "properties": {
    "iso:country":"DE",
    "sg:address":"Hans-En\u00dfner-Str. 6",
    "sg:city":"Gro\u00dfhabersdorf",
    "sg:phone":"+49 9105/990672",
    "sg:postcode":"90613",
    "sg:province":"Bayern",
    "wof:name":"Georg Schulthei\u00df",
    "wof:placetype":"venue"
},
  "geometry": {"coordinates":[10.761858,49.411022],"type":"Point"}
}