{
  "type": "Feature",
  "properties": {
    "iso:country":"DE",
    "sg:address":"Illinger Str. 36",
    "sg:city":"Marpingen",
    "sg:phone":"+49 6827/433",
    "sg:postcode":"66646",
    "sg:province":"Saarland",
    "wof:name":"Otto Kunz Architekt",
    "wof:placetype":"venue"
},
  "geometry": {"coordinates":[7.075701,49.423527],"type":"Point"}
}