{
  "type": "Feature",
  "properties": {
    "iso:country":"DE",
    "sg:address":"Roquetteweg 45",
    "sg:city":"Darmstadt",
    "sg:postcode":"64285",
    "sg:province":"Hessen",
    "wof:name":"Gruwobau Grundst\u00fccks Und Wohnungsbaugesellschaft Mbh",
    "wof:placetype":"venue"
},
  "geometry": {"coordinates":[8.666718,49.861832],"type":"Point"}
}