{
  "type": "Feature",
  "properties": {
    "iso:country":"DE",
    "sg:address":"Dr.-Rau-Allee 79",
    "sg:city":"Warendorf",
    "sg:postcode":"48231",
    "sg:province":"Nordrhein-Westfalen",
    "wof:name":"Eas Energie Und Abrechnungsservice",
    "wof:placetype":"venue"
},
  "geometry": {"coordinates":[7.9936938286,51.9736251831],"type":"Point"}
}