{
  "type": "Feature",
  "properties": {
    "iso:country":"DE",
    "sg:address":"Hauptstr. 29",
    "sg:city":"Dittmannsdorf",
    "sg:phone":"+49 3725/5354",
    "sg:postcode":"09573",
    "sg:province":"Sachsen",
    "wof:name":"Georg Wei\u00dfbach",
    "wof:placetype":"venue"
},
  "geometry": {"coordinates":[13.0549106598,50.7915534973],"type":"Point"}
}