{
  "type": "Feature",
  "properties": {
    "iso:country":"DE",
    "sg:address":"B\u00f6lschestra\u00dfe 116",
    "sg:city":"Berlin",
    "sg:phone":"+49 30/64092525",
    "sg:postcode":"12587",
    "sg:province":"Berlin",
    "wof:name":"Your Home International Ltd.",
    "wof:placetype":"venue"
},
  "geometry": {"coordinates":[13.6243095398,52.4500427246],"type":"Point"}
}