{
  "type": "Feature",
  "properties": {
    "iso:country":"DE",
    "sg:address":"Badener Str. 24",
    "sg:city":"Rheinstetten",
    "sg:phone":"+49 7242/952402",
    "sg:postcode":"76287",
    "sg:province":"Baden-W\u00fcrttemberg",
    "wof:name":"G\u00fcnter Hauns Gmbh",
    "wof:placetype":"venue"
},
  "geometry": {"coordinates":[8.297443,48.961212],"type":"Point"}
}