{
  "type": "Feature",
  "properties": {
    "iso:country":"DE",
    "sg:address":"Schweinfurter Weg 61",
    "sg:city":"Frankfurt",
    "sg:postcode":"60599",
    "sg:province":"Hessen",
    "wof:name":"Thiele Kfz-werkstatt Verwaltungs-gmbh",
    "wof:placetype":"venue"
},
  "geometry": {"coordinates":[8.6981515884,50.0943756104],"type":"Point"}
}