{
  "type": "Feature",
  "properties": {
    "iso:country":"DE",
    "sg:address":"Marxheimer Str. 4",
    "sg:city":"Hofheim",
    "sg:phone":"+49 6192/3065",
    "sg:postcode":"65719",
    "sg:province":"Hessen",
    "wof:name":"V\u00f6lkers Hotel-restaurant",
    "wof:placetype":"venue"
},
  "geometry": {"coordinates":[8.4236803055,50.0641365051],"type":"Point"}
}