{
  "type": "Feature",
  "properties": {
    "iso:country":"DE",
    "sg:address":"Schulstr. 12",
    "sg:city":"Kirchwald",
    "sg:phone":"+49 2651/2152",
    "sg:postcode":"56729",
    "sg:province":"Rheinland-Pfalz",
    "wof:name":"Gottfried Schmitz",
    "wof:placetype":"venue"
},
  "geometry": {"coordinates":[7.1505608559,50.3680267334],"type":"Point"}
}