{
  "type": "Feature",
  "properties": {
    "iso:country":"DE",
    "sg:address":"S\u00f6deler Str. 16",
    "sg:city":"Rockenberg",
    "sg:phone":"+49 6033/67479",
    "sg:postcode":"35519",
    "sg:province":"Hessen",
    "wof:name":"Kath. Pfarramt St. Laurentius",
    "wof:placetype":"venue"
},
  "geometry": {"coordinates":[8.7409162521,50.4175682068],"type":"Point"}
}