{
  "type": "Feature",
  "properties": {
    "iso:country":"DE",
    "sg:address":"R\u00f6merstr. 2",
    "sg:city":"Wagh\u00e4usel",
    "sg:phone":"+49 7254/1585",
    "sg:postcode":"68753",
    "sg:province":"Baden-W\u00fcrttemberg",
    "wof:name":"W. Martus Und H. Ueltzh\u00f6ffer",
    "wof:placetype":"venue"
},
  "geometry": {"coordinates":[8.515748024,49.2349357605],"type":"Point"}
}