{
  "type": "Feature",
  "properties": {
    "iso:country":"DE",
    "sg:address":"Alsterdorferstr. 513a",
    "sg:city":"Hamburg",
    "sg:phone":"+49 40/63976142",
    "sg:postcode":"22337",
    "sg:province":"Hamburg",
    "wof:name":"Theracosm Gmbh: Die Theta-creme",
    "wof:placetype":"venue"
},
  "geometry": {"coordinates":[10.033995,53.619389],"type":"Point"}
}