{
  "type": "Feature",
  "properties": {
    "iso:country":"DE",
    "sg:address":"Dr.-Wirtz-Str. 3",
    "sg:city":"Much",
    "sg:phone":"+49 2245/91650",
    "sg:postcode":"53804",
    "sg:province":"Nordrhein-Westfalen",
    "wof:name":"Burg-apotheke",
    "wof:placetype":"venue"
},
  "geometry": {"coordinates":[7.407993,50.906212],"type":"Point"}
}