{
  "type": "Feature",
  "properties": {
    "iso:country":"DE",
    "sg:address":"Am Spitzberg",
    "sg:city":"Possendorf",
    "sg:phone":"+49 351/4213057",
    "sg:postcode":"01728",
    "sg:province":"Sachsen",
    "wof:name":"Psd Pumpenservice Dresden Gmbh",
    "wof:placetype":"venue"
},
  "geometry": {"coordinates":[13.716841,50.993298],"type":"Point"}
}