{
  "type": "Feature",
  "properties": {
    "iso:country":"DE",
    "sg:address":"Rathausstr. 52",
    "sg:city":"Winsen",
    "sg:phone":"+49 4171/884150",
    "sg:postcode":"21423",
    "sg:province":"Niedersachsen",
    "wof:name":"Vbn Immobilien Gmbh",
    "wof:placetype":"venue"
},
  "geometry": {"coordinates":[10.2066221237,53.3610916138],"type":"Point"}
}