{
  "type": "Feature",
  "properties": {
    "iso:country":"DE",
    "sg:address":"Wolfgang-Wagner-Str. 9 A",
    "sg:city":"Glonn",
    "sg:phone":"+49 8093/9419",
    "sg:postcode":"85625",
    "sg:province":"Bayern",
    "wof:name":"Huber Ingenieur",
    "wof:placetype":"venue"
},
  "geometry": {"coordinates":[11.8683204651,47.9880599976],"type":"Point"}
}