{
  "type": "Feature",
  "properties": {
    "iso:country":"DE",
    "sg:address":"Happenweiler 811",
    "sg:city":"Horgenzell",
    "sg:phone":"+49 7504/97040",
    "sg:postcode":"88263",
    "sg:province":"Baden-W\u00fcrttemberg",
    "wof:name":"Girosoft Systemhaus Gmbh",
    "wof:placetype":"venue"
},
  "geometry": {"coordinates":[9.457551,47.773842],"type":"Point"}
}