{
  "type": "Feature",
  "properties": {
    "iso:country":"DE",
    "sg:address":"Schwanner Str. 12",
    "sg:city":"Straubenhardt",
    "sg:phone":"+49 7082/8649",
    "sg:postcode":"75334",
    "sg:province":"Baden-W\u00fcrttemberg",
    "wof:name":"Achim Stoll",
    "wof:placetype":"venue"
},
  "geometry": {"coordinates":[8.531370163,48.8537788391],"type":"Point"}
}