{
  "type": "Feature",
  "properties": {
    "iso:country":"DE",
    "sg:address":"Uferstr. 13",
    "sg:city":"Dillenburg",
    "sg:phone":"+49 2771/87220",
    "sg:postcode":"35683",
    "sg:province":"Hessen",
    "wof:name":"Kirschbaum Und Partner Gbr",
    "wof:placetype":"venue"
},
  "geometry": {"coordinates":[8.2914524078,50.7360572815],"type":"Point"}
}