{
  "type": "Feature",
  "properties": {
    "iso:country":"DE",
    "sg:address":"Schlo\u00dfstr. 43c",
    "sg:city":"Calbe",
    "sg:phone":"+49 39291/2204",
    "sg:postcode":"39240",
    "sg:province":"Sachsen-Anhalt",
    "wof:name":"Maria Behrend",
    "wof:placetype":"venue"
},
  "geometry": {"coordinates":[11.7799501419,51.9087715149],"type":"Point"}
}