{
  "type": "Feature",
  "properties": {
    "iso:country":"DE",
    "sg:address":"H\u00e4ndelstr. 21",
    "sg:city":"Karlsruhe",
    "sg:phone":"+49 721/85236",
    "sg:postcode":"76185",
    "sg:province":"Baden-W\u00fcrttemberg",
    "wof:name":"Betonschutz Gmbh Ges. F\u00fcr Schutz Und Sanierung",
    "wof:placetype":"venue"
},
  "geometry": {"coordinates":[8.3690633774,49.011844635],"type":"Point"}
}