{
  "type": "Feature",
  "properties": {
    "iso:country":"DE",
    "sg:address":"Georgstr. 25",
    "sg:city":"Bad Rothenfelde",
    "sg:phone":"+49 5424/5802",
    "sg:postcode":"49214",
    "sg:province":"Niedersachsen",
    "wof:name":"Sal Derman Dermatologisches Institut Gmbh & Co. Kg",
    "wof:placetype":"venue"
},
  "geometry": {"coordinates":[8.1556739807,52.107334137],"type":"Point"}
}