{
  "type": "Feature",
  "properties": {
    "iso:country":"DE",
    "sg:address":"Oberer Rosberg 20",
    "sg:city":"Waiblingen",
    "sg:phone":"+49 7151/22664",
    "sg:postcode":"71334",
    "sg:province":"Baden-W\u00fcrttemberg",
    "wof:name":"Walter Stecher",
    "wof:placetype":"venue"
},
  "geometry": {"coordinates":[9.3195323944,48.8377304077],"type":"Point"}
}