{
  "type": "Feature",
  "properties": {
    "iso:country":"DE",
    "sg:address":"Bahnhofstr. 6",
    "sg:city":"Simmelsdorf",
    "sg:phone":"+49 4955/456090",
    "sg:postcode":"91245",
    "sg:province":"Bayern",
    "wof:name":"Aldi Gmbh & Co Kg",
    "wof:placetype":"venue"
},
  "geometry": {"coordinates":[9.761314,51.392765],"type":"Point"}
}