{
  "type": "Feature",
  "properties": {
    "iso:country":"DE",
    "sg:address":"Uhlbacher Str. 68",
    "sg:city":"Stuttgart",
    "sg:phone":"+49 711/323778",
    "sg:postcode":"70329",
    "sg:province":"Baden-W\u00fcrttemberg",
    "wof:name":"Ev. Pfarramt",
    "wof:placetype":"venue"
},
  "geometry": {"coordinates":[9.2703514099,48.7667312622],"type":"Point"}
}