{
  "type": "Feature",
  "properties": {
    "iso:country":"DE",
    "sg:address":"Am Weissiger Bach 135",
    "sg:city":"Dresden",
    "sg:postcode":"01328",
    "sg:province":"Sachsen",
    "wof:name":"Cb-funk Im Schoenfelder Hochland",
    "wof:placetype":"venue"
},
  "geometry": {"coordinates":[13.883893,51.069199],"type":"Point"}
}