{
  "type": "Feature",
  "properties": {
    "iso:country":"DE",
    "sg:address":"Theodor-Heuss-Ring 22",
    "sg:city":"K\u00f6ln",
    "sg:phone":"+49 221/121045",
    "sg:postcode":"50668",
    "sg:province":"Nordrhein-Westfalen",
    "wof:name":"Vinoteca Dornack",
    "wof:placetype":"venue"
},
  "geometry": {"coordinates":[6.9611020088,50.9499282837],"type":"Point"}
}