{
  "type": "Feature",
  "properties": {
    "iso:country":"DE",
    "sg:address":"Luisenstr. 13",
    "sg:city":"Rostock",
    "sg:phone":"+49 381/4996594",
    "sg:postcode":"18057",
    "sg:province":"Mecklenburg-Vorpommern",
    "wof:name":"K. Oldenburg Immobilienmakler",
    "wof:placetype":"venue"
},
  "geometry": {"coordinates":[12.1248626709,54.0899581909],"type":"Point"}
}