{
  "type": "Feature",
  "properties": {
    "iso:country":"DE",
    "sg:address":"Karl-Gerharts-Str. 14",
    "sg:city":"Schwerte",
    "sg:phone":"+49 2304/942260",
    "sg:postcode":"58239",
    "sg:province":"Nordrhein-Westfalen",
    "wof:name":"Autopark-schwerte Gmbh",
    "wof:placetype":"venue"
},
  "geometry": {"coordinates":[7.566698,51.440285],"type":"Point"}
}