{
  "type": "Feature",
  "properties": {
    "iso:country":"DE",
    "sg:address":"Am Goldacker 2",
    "sg:city":"Wabern",
    "sg:phone":"+49 5683/93100",
    "sg:postcode":"34590",
    "sg:province":"Hessen",
    "wof:name":"S.g.k. Speditionsges. M.b.h.",
    "wof:placetype":"venue"
},
  "geometry": {"coordinates":[9.3799648285,51.0998191833],"type":"Point"}
}