{
  "type": "Feature",
  "properties": {
    "iso:country":"DE",
    "sg:address":"Limesstr. 2",
    "sg:city":"Pohlheim",
    "sg:phone":"+49 6403/63105",
    "sg:postcode":"35415",
    "sg:province":"Hessen",
    "wof:name":"Ev. Pfarramt Gr\u00fcningen",
    "wof:placetype":"venue"
},
  "geometry": {"coordinates":[8.7300424576,50.505279541],"type":"Point"}
}