{
  "type": "Feature",
  "properties": {
    "iso:country":"DE",
    "sg:address":"Paul-Lincke-Str. 2",
    "sg:city":"Emmerich",
    "sg:phone":"+49 2828/2350",
    "sg:postcode":"46446",
    "sg:province":"Nordrhein-Westfalen",
    "wof:name":"E. Anker",
    "wof:placetype":"venue"
},
  "geometry": {"coordinates":[6.1609711647,51.8731384277],"type":"Point"}
}