{
  "type": "Feature",
  "properties": {
    "iso:country":"DE",
    "sg:address":"Ludgeristr. 51",
    "sg:city":"M\u00fcnster",
    "sg:phone":"+49 251/46469",
    "sg:postcode":"48143",
    "sg:province":"Nordrhein-Westfalen",
    "wof:name":"Mc Donalds",
    "wof:placetype":"venue"
},
  "geometry": {"coordinates":[7.6276450157,51.9577522278],"type":"Point"}
}