{
  "type": "Feature",
  "properties": {
    "iso:country":"DE",
    "sg:address":"Steinmarkt 5",
    "sg:city":"Cham",
    "sg:phone":"+49 9971/79797",
    "sg:postcode":"93413",
    "sg:province":"Bayern",
    "wof:name":"Kloster-apotheke",
    "wof:placetype":"venue"
},
  "geometry": {"coordinates":[12.666729,49.213417],"type":"Point"}
}