{
  "type": "Feature",
  "properties": {
    "iso:country":"DE",
    "sg:address":"Wrangelstr. 108",
    "sg:city":"Hamburg",
    "sg:phone":"+49 40/406136",
    "sg:postcode":"20253",
    "sg:province":"Hamburg",
    "wof:name":"Alwin Zentner",
    "wof:placetype":"venue"
},
  "geometry": {"coordinates":[9.9655599594,53.5833892822],"type":"Point"}
}