{
  "type": "Feature",
  "properties": {
    "iso:country":"DE",
    "sg:address":"K\u00f6nigsteiner Str. 48",
    "sg:city":"Bad Soden",
    "sg:phone":"+49 6196/643010",
    "sg:postcode":"65812",
    "sg:province":"Hessen",
    "wof:name":"Dombrowski Und Kohnert Rechtsanw\u00e4lte Und Notare",
    "wof:placetype":"venue"
},
  "geometry": {"coordinates":[8.5045127869,50.1412887573],"type":"Point"}
}