{
  "type": "Feature",
  "properties": {
    "iso:country":"DE",
    "sg:address":"Stiftstr. 2",
    "sg:city":"Kronberg",
    "sg:phone":"+49 6173/640629",
    "sg:postcode":"61476",
    "sg:province":"Hessen",
    "wof:name":"Dr. J. Kuhn Steuerberater Und",
    "wof:placetype":"venue"
},
  "geometry": {"coordinates":[8.5209531784,50.1815681458],"type":"Point"}
}