{
  "type": "Feature",
  "properties": {
    "iso:country":"DE",
    "sg:address":"Haintorstr. 24",
    "sg:city":"Freinsheim",
    "sg:phone":"+49 6353/1842",
    "sg:postcode":"67251",
    "sg:province":"Rheinland-Pfalz",
    "wof:name":"Hotel-restaurant Landhaus G\u00f6ller",
    "wof:placetype":"venue"
},
  "geometry": {"coordinates":[8.2099409103,49.5055961609],"type":"Point"}
}