{
  "type": "Feature",
  "properties": {
    "iso:country":"DE",
    "sg:address":"Wiesenstra\u00dfe 10",
    "sg:city":"Sinsheim-Reihen",
    "sg:phone":"+49 7261/13140",
    "sg:postcode":"74889",
    "sg:province":"Baden-W\u00fcrttemberg",
    "wof:name":"Sbl Maschinenbau Gmbh",
    "wof:placetype":"venue"
},
  "geometry": {"coordinates":[8.9182729721,49.2181930542],"type":"Point"}
}