{
  "type": "Feature",
  "properties": {
    "iso:country":"DE",
    "sg:address":"Schafhofstrasse 42",
    "sg:city":"W\u00fcrzburg",
    "sg:postcode":"97080",
    "sg:province":"Bayern",
    "wof:name":"Weatherpage",
    "wof:placetype":"venue"
},
  "geometry": {"coordinates":[9.918321,49.828541],"type":"Point"}
}