{
  "type": "Feature",
  "properties": {
    "iso:country":"DE",
    "sg:address":"Ohrnbachtalstr. 8",
    "sg:city":"Michelstadt",
    "sg:phone":"+49 6066/990036",
    "sg:postcode":"64720",
    "sg:province":"Hessen",
    "wof:name":"Weyrich Und Pfennig Rechtsanw\u00e4lte",
    "wof:placetype":"venue"
},
  "geometry": {"coordinates":[9.0975551605,49.7143363953],"type":"Point"}
}