{
  "type": "Feature",
  "properties": {
    "iso:country":"DE",
    "sg:address":"Odenwaldring 76",
    "sg:city":"Dreieich",
    "sg:phone":"+49 6103/81924",
    "sg:postcode":"63303",
    "sg:province":"Hessen",
    "wof:name":"Hermann Miltenberger Steuerberater",
    "wof:placetype":"venue"
},
  "geometry": {"coordinates":[8.7107391357,50.0079803467],"type":"Point"}
}