{
  "type": "Feature",
  "properties": {
    "iso:country":"DE",
    "sg:address":"Hauptstr. 12",
    "sg:city":"Gelsenkirchen",
    "sg:phone":"+49 209/23306",
    "sg:postcode":"45879",
    "sg:province":"Nordrhein-Westfalen",
    "wof:name":"Klaus Hoffmann",
    "wof:placetype":"venue"
},
  "geometry": {"coordinates":[7.0957131386,51.51121521],"type":"Point"}
}