{
  "type": "Feature",
  "properties": {
    "iso:country":"DE",
    "sg:address":"Zweite Allee",
    "sg:city":"Rothenburg",
    "sg:phone":"+49 35891/410",
    "sg:postcode":"02929",
    "sg:province":"Sachsen",
    "wof:name":"E.s.t. Entsorgungsanlagen Betriebsgesellschaft Mbh",
    "wof:placetype":"venue"
},
  "geometry": {"coordinates":[14.93564,51.410439],"type":"Point"}
}