{
  "type": "Feature",
  "properties": {
    "iso:country":"DE",
    "sg:address":"aaaaaa",
    "sg:city":"Aachen",
    "sg:phone":"+49 11111111111",
    "sg:postcode":"55234",
    "sg:province":"Rheinland-Pfalz",
    "wof:name":"Tacho,tachodienst",
    "wof:placetype":"venue"
},
  "geometry": {"coordinates":[8.11732,49.772671],"type":"Point"}
}