{
  "type": "Feature",
  "properties": {
    "iso:country":"DE",
    "sg:address":"Heckenstr. 10",
    "sg:city":"Sachsenheim",
    "sg:phone":"+49 7147/14384",
    "sg:postcode":"74343",
    "sg:province":"Baden-W\u00fcrttemberg",
    "wof:name":"Walter Heider Ingenieur",
    "wof:placetype":"venue"
},
  "geometry": {"coordinates":[9.0174760818,49.0018577576],"type":"Point"}
}