{
  "type": "Feature",
  "properties": {
    "iso:country":"DE",
    "sg:address":"Dom\u00e4nenstr. 9",
    "sg:city":"Wustrow",
    "sg:phone":"+49 5843/266",
    "sg:postcode":"29462",
    "sg:province":"Niedersachsen",
    "wof:name":"Mediline Sozialwirtschaftliche Betreuungs- Und",
    "wof:placetype":"venue"
},
  "geometry": {"coordinates":[11.127674,52.920528],"type":"Point"}
}