{
  "type": "Feature",
  "properties": {
    "iso:country":"DE",
    "sg:address":"Wenckstr. 3",
    "sg:city":"Hanau",
    "sg:phone":"+49 6181/663929",
    "sg:postcode":"63456",
    "sg:province":"Hessen",
    "wof:name":"Wenckscher Hof",
    "wof:placetype":"venue"
},
  "geometry": {"coordinates":[8.9148139954,50.1063728333],"type":"Point"}
}