{
  "type": "Feature",
  "properties": {
    "iso:country":"DE",
    "sg:address":"Baerlo 1",
    "sg:city":"Nettetal",
    "sg:phone":"+49 2157/811926",
    "sg:postcode":"41334",
    "sg:province":"Nordrhein-Westfalen",
    "wof:name":"Prorema Gesellschaft F\u00fcr Abfallsammel & Recycling-",
    "wof:placetype":"venue"
},
  "geometry": {"coordinates":[6.2279548645,51.3182029724],"type":"Point"}
}