{
  "type": "Feature",
  "properties": {
    "iso:country":"DE",
    "sg:address":"Bergblick 2",
    "sg:city":"Holzminden",
    "sg:phone":"+49 5531/4634",
    "sg:postcode":"37603",
    "sg:province":"Niedersachsen",
    "wof:name":"Bruno F\u00e4rber Steuerberater",
    "wof:placetype":"venue"
},
  "geometry": {"coordinates":[9.4576616287,51.8169021606],"type":"Point"}
}