{
  "type": "Feature",
  "properties": {
    "iso:country":"DE",
    "sg:address":"Buchhagenweg 10",
    "sg:city":"Schmallenberg",
    "sg:phone":"+49 2974/6656",
    "sg:postcode":"57392",
    "sg:province":"Nordrhein-Westfalen",
    "wof:name":"Franz-josef Lingemann",
    "wof:placetype":"venue"
},
  "geometry": {"coordinates":[8.303036,51.197102],"type":"Point"}
}