{
  "type": "Feature",
  "properties": {
    "iso:country":"DE",
    "sg:address":"Pfaffenweg 10",
    "sg:city":"Bonn",
    "sg:postcode":"53227",
    "sg:province":"Nordrhein-Westfalen",
    "wof:name":"Trans Projekt Gesellschaft F\u00fcr \u00dcbersetzungen Mbh",
    "wof:placetype":"venue"
},
  "geometry": {"coordinates":[7.135637,50.741207],"type":"Point"}
}