{
  "type": "Feature",
  "properties": {
    "iso:country":"DE",
    "sg:address":"B\u00f6blinger Str. 18",
    "sg:city":"Stuttgart",
    "sg:phone":"+49 711/6487878",
    "sg:postcode":"70178",
    "sg:province":"Baden-W\u00fcrttemberg",
    "wof:name":"Redaktion Visier Pietsch & Scholten",
    "wof:placetype":"venue"
},
  "geometry": {"coordinates":[9.1657991409,48.7641677856],"type":"Point"}
}