{
  "type": "Feature",
  "properties": {
    "iso:country":"DE",
    "sg:address":"Marienstr 10",
    "sg:city":"Buchholz",
    "sg:phone":"+49 4181/99410",
    "sg:postcode":"21244",
    "sg:province":"Niedersachsen",
    "wof:name":"Ballonfreunde Nordheide E.v. - Ballonfahrten",
    "wof:placetype":"venue"
},
  "geometry": {"coordinates":[9.8883924484,53.3354568481],"type":"Point"}
}