{
  "type": "Feature",
  "properties": {
    "iso:country":"DE",
    "sg:address":"Emkendorfer Str 25",
    "sg:city":"Emkendorf-Kleinvollstedt",
    "sg:phone":"+49 4330/9700",
    "sg:postcode":"24802",
    "sg:province":"Schleswig-Holstein",
    "wof:name":"Brunnenbau Und Wassertechnik, Manfred Puch",
    "wof:placetype":"venue"
},
  "geometry": {"coordinates":[9.849512,54.260986],"type":"Point"}
}