{
  "type": "Feature",
  "properties": {
    "iso:country":"DE",
    "sg:address":"Friedensstr. 2",
    "sg:city":"Lebach",
    "sg:postcode":"66822",
    "sg:province":"Saarland",
    "wof:name":"Fitness Und Fun Im Fitness Gym Schmitt Gmbh",
    "wof:placetype":"venue"
},
  "geometry": {"coordinates":[6.910004,49.412582],"type":"Point"}
}