{
  "type": "Feature",
  "properties": {
    "iso:country":"DE",
    "sg:address":"Westendstr. 1",
    "sg:city":"Kirchheim",
    "sg:phone":"+49 89/90098530",
    "sg:postcode":"85551",
    "sg:province":"Bayern",
    "wof:name":"Vertical Networks Gmbh",
    "wof:placetype":"venue"
},
  "geometry": {"coordinates":[11.7494659424,48.1746177673],"type":"Point"}
}