{
  "type": "Feature",
  "properties": {
    "iso:country":"DE",
    "sg:address":"Burgstr. 40",
    "sg:city":"Schifferstadt",
    "sg:phone":"+49 6235/4077",
    "sg:postcode":"67105",
    "sg:province":"Rheinland-Pfalz",
    "wof:name":"Bernd Melcher Architekt",
    "wof:placetype":"venue"
},
  "geometry": {"coordinates":[8.370332,49.383968],"type":"Point"}
}