{
  "type": "Feature",
  "properties": {
    "iso:country":"DE",
    "sg:address":"Ernst-Ludwig-Str 36",
    "sg:city":"Alzey",
    "sg:phone":"+49 6731/408102",
    "sg:postcode":"55232",
    "sg:province":"Rheinland-Pfalz",
    "wof:name":"Wirtschaftsf\u00f6rderungsgesellschaft F\u00fcr Den Landkreis Alzey-worms Mbh",
    "wof:placetype":"venue"
},
  "geometry": {"coordinates":[8.1090011597,49.7425270081],"type":"Point"}
}