{
  "type": "Feature",
  "properties": {
    "iso:country":"DE",
    "sg:address":"Stralsunder Str. 15 c",
    "sg:city":"Bergen auf R\u00fcgen",
    "sg:phone":"+49 3838/252481",
    "sg:postcode":"18528",
    "sg:province":"Mecklenburg-Vorpommern",
    "wof:name":"Wir Sind Die Besten - Nord\u00f6stlich Vom Westen",
    "wof:placetype":"venue"
},
  "geometry": {"coordinates":[13.423672,54.413956],"type":"Point"}
}