{
  "type": "Feature",
  "properties": {
    "iso:country":"DE",
    "sg:address":"Gelsenkircher Str. 24a",
    "sg:city":"Herne",
    "sg:phone":"+49 2325/75856",
    "sg:postcode":"44649",
    "sg:province":"Nordrhein-Westfalen",
    "wof:name":"K.-h. Gr\u00fcter",
    "wof:placetype":"venue"
},
  "geometry": {"coordinates":[7.158395,51.527008],"type":"Point"}
}