{
  "type": "Feature",
  "properties": {
    "iso:country":"DE",
    "sg:address":"Gerhardstr. 16",
    "sg:city":"Hamburg",
    "sg:phone":"+49 40/312547",
    "sg:postcode":"20359",
    "sg:province":"Hamburg",
    "wof:name":"Lounge",
    "wof:placetype":"venue"
},
  "geometry": {"coordinates":[9.961285,53.548176],"type":"Point"}
}