{
  "type": "Feature",
  "properties": {
    "iso:country":"DE",
    "sg:address":"Biedenkamp 5h",
    "sg:city":"Glinde",
    "sg:phone":"+49 40/710060",
    "sg:postcode":"21509",
    "sg:province":"Schleswig-Holstein",
    "wof:name":"Flashpoint Ag",
    "wof:placetype":"venue"
},
  "geometry": {"coordinates":[10.229114,53.546871],"type":"Point"}
}