{
  "type": "Feature",
  "properties": {
    "iso:country":"DE",
    "sg:address":"Gornewitzer Str. 1a",
    "sg:city":"Nerchau",
    "sg:phone":"+49 34382/72020",
    "sg:postcode":"04685",
    "sg:province":"Sachsen",
    "wof:name":"Evers Kommunikationssysteme Gmbh",
    "wof:placetype":"venue"
},
  "geometry": {"coordinates":[12.789522,51.271782],"type":"Point"}
}