{
  "type": "Feature",
  "properties": {
    "iso:country":"DE",
    "sg:address":"M\u00fcnchner Str. 6 a",
    "sg:city":"Aschheim",
    "sg:phone":"+49 89/9031048",
    "sg:postcode":"85609",
    "sg:province":"Bayern",
    "wof:name":"Luc Moel Vertriebs Gmbh",
    "wof:placetype":"venue"
},
  "geometry": {"coordinates":[11.7151889801,48.1710929871],"type":"Point"}
}