{
  "type": "Feature",
  "properties": {
    "iso:country":"DE",
    "sg:address":"Wagenhofer Str. 27",
    "sg:city":"Dischingen",
    "sg:phone":"+49 7327/5157",
    "sg:postcode":"89561",
    "sg:province":"Baden-W\u00fcrttemberg",
    "wof:name":"G\u00fcnther Ro\u00dfmann Gmbh & Co. Schreinerei Kg",
    "wof:placetype":"venue"
},
  "geometry": {"coordinates":[10.441679,48.677734],"type":"Point"}
}