{
  "type": "Feature",
  "properties": {
    "iso:country":"DE",
    "sg:address":"Theodor-Storm-Str. 5f",
    "sg:city":"Bad Homburg",
    "sg:phone":"+49 6172/84753",
    "sg:postcode":"61350",
    "sg:province":"Hessen",
    "wof:name":"Dr. Bernhard Uhlig Steuerberater Und",
    "wof:placetype":"venue"
},
  "geometry": {"coordinates":[8.6178693771,50.2374420166],"type":"Point"}
}