{
  "type": "Feature",
  "properties": {
    "iso:country":"DE",
    "sg:address":"Rechtstr. 2",
    "sg:city":"Essen",
    "sg:phone":"+49 201/867130",
    "sg:postcode":"45355",
    "sg:province":"Nordrhein-Westfalen",
    "wof:name":"Friedhelm Kindermann Architekt",
    "wof:placetype":"venue"
},
  "geometry": {"coordinates":[6.951014,51.473927],"type":"Point"}
}