{
  "type": "Feature",
  "properties": {
    "iso:country":"DE",
    "sg:address":"Nonenstr. 98",
    "sg:city":"Rheda-Wiedenbr\u00fcck",
    "sg:phone":"+49 5242/966950",
    "sg:postcode":"33378",
    "sg:province":"Nordrhein-Westfalen",
    "wof:name":"Kath. Pfarramt St. Johannes",
    "wof:placetype":"venue"
},
  "geometry": {"coordinates":[8.2785377502,51.8490180969],"type":"Point"}
}