{
  "type": "Feature",
  "properties": {
    "iso:country":"DE",
    "sg:address":"Krusendorfer Str. 5",
    "sg:city":"Osdorf",
    "sg:phone":"+49 4346/1888",
    "sg:postcode":"24251",
    "sg:province":"Schleswig-Holstein",
    "wof:name":"Abacom Edv-organisation Gmbh",
    "wof:placetype":"venue"
},
  "geometry": {"coordinates":[10.019908905,54.4436302185],"type":"Point"}
}