{
  "type": "Feature",
  "properties": {
    "iso:country":"DE",
    "sg:address":"Nauener Str. 21",
    "sg:city":"B\u00f6rnicke",
    "sg:phone":"+49 33230/51497",
    "sg:postcode":"14641",
    "sg:province":"Brandenburg",
    "wof:name":"Hoffmanns Fliesen Gmbh",
    "wof:placetype":"venue"
},
  "geometry": {"coordinates":[12.9362945557,52.682384491],"type":"Point"}
}