{
  "type": "Feature",
  "properties": {
    "iso:country":"DE",
    "sg:address":"Carl-Spaeter-Str. 13",
    "sg:city":"Koblenz",
    "sg:phone":"+49 261/804796",
    "sg:postcode":"56070",
    "sg:province":"Rheinland-Pfalz",
    "wof:name":"Gebr. K\u00f6hler Beteiligungs Gmbh",
    "wof:placetype":"venue"
},
  "geometry": {"coordinates":[7.583665,50.389545],"type":"Point"}
}