{
  "type": "Feature",
  "properties": {
    "iso:country":"DE",
    "sg:address":"Siedlung 13a",
    "sg:city":"Rangsdorf",
    "sg:postcode":"15834",
    "sg:province":"Brandenburg",
    "wof:name":"Computertechnik Berger E. K.",
    "wof:placetype":"venue"
},
  "geometry": {"coordinates":[13.481068,52.304901],"type":"Point"}
}