{
  "type": "Feature",
  "properties": {
    "iso:country":"DE",
    "sg:address":"Forstweg 7",
    "sg:city":"Hagen",
    "sg:phone":"+49 5401/9384",
    "sg:postcode":"49170",
    "sg:province":"Niedersachsen",
    "wof:name":"Heinrich V\u00f6ller",
    "wof:placetype":"venue"
},
  "geometry": {"coordinates":[8.008518,52.193626],"type":"Point"}
}