{
  "type": "Feature",
  "properties": {
    "iso:country":"DE",
    "sg:address":"Fichtenstr. 10",
    "sg:city":"Remchingen",
    "sg:phone":"+49 7232/70863",
    "sg:postcode":"75196",
    "sg:province":"Baden-W\u00fcrttemberg",
    "wof:name":"Werner St\u00e4chele",
    "wof:placetype":"venue"
},
  "geometry": {"coordinates":[8.564925,48.943569],"type":"Point"}
}