{
  "type": "Feature",
  "properties": {
    "iso:country":"DE",
    "sg:address":"Sch\u00f6nhausenstr. 12",
    "sg:city":"Bremen",
    "sg:phone":"+49 421/702905",
    "sg:postcode":"28203",
    "sg:province":"Bremen",
    "wof:name":"J\u00fcrgen Schmitz",
    "wof:placetype":"venue"
},
  "geometry": {"coordinates":[8.828961,53.076988],"type":"Point"}
}