{
  "type": "Feature",
  "properties": {
    "iso:country":"DE",
    "sg:address":"Am Schildkamp 18",
    "sg:city":"Herford",
    "sg:phone":"+49 5221/70782",
    "sg:postcode":"32052",
    "sg:province":"Nordrhein-Westfalen",
    "wof:name":"F. Lehmann Mech. Werkstatt",
    "wof:placetype":"venue"
},
  "geometry": {"coordinates":[8.674173,52.105904],"type":"Point"}
}