{
  "type": "Feature",
  "properties": {
    "iso:country":"DE",
    "sg:address":"Ottostr. 24",
    "sg:city":"Blaustein",
    "sg:phone":"+49 7304/5409",
    "sg:postcode":"89134",
    "sg:province":"Baden-W\u00fcrttemberg",
    "wof:name":"Peter Baumann",
    "wof:placetype":"venue"
},
  "geometry": {"coordinates":[9.904933,48.418522],"type":"Point"}
}