{
  "type": "Feature",
  "properties": {
    "iso:country":"DE",
    "sg:address":"Lassallestr. 34",
    "sg:city":"Zwickau",
    "sg:phone":"+49 375/212821",
    "sg:postcode":"08058",
    "sg:province":"Sachsen",
    "wof:name":"Peter Scholz",
    "wof:placetype":"venue"
},
  "geometry": {"coordinates":[12.4886741638,50.7297210693],"type":"Point"}
}