{
  "type": "Feature",
  "properties": {
    "iso:country":"DE",
    "sg:address":"Mitterfeldweg 3",
    "sg:city":"Dachau",
    "sg:phone":"+49 8131/87910",
    "sg:postcode":"85221",
    "sg:province":"Bayern",
    "wof:name":"Naturheilpraxis Seitz \u00b7 Heilpraktiker",
    "wof:placetype":"venue"
},
  "geometry": {"coordinates":[11.423446,48.259052],"type":"Point"}
}