{
  "type": "Feature",
  "properties": {
    "iso:country":"DE",
    "sg:address":"Kuhheide",
    "sg:city":"Schwedt",
    "sg:phone":"+49 3332/510402",
    "sg:postcode":"16303",
    "sg:province":"Brandenburg",
    "wof:name":"Nlk-celpap Deutschland Gmbh",
    "wof:placetype":"venue"
},
  "geometry": {"coordinates":[14.311744,53.078815],"type":"Point"}
}