{
  "type": "Feature",
  "properties": {
    "iso:country":"DE",
    "sg:address":"Am Untertor 8",
    "sg:city":"Wetter",
    "sg:phone":"+49 6423/3877",
    "sg:postcode":"35083",
    "sg:province":"Hessen",
    "wof:name":"F. Stingel",
    "wof:placetype":"venue"
},
  "geometry": {"coordinates":[8.7219400406,50.9047431946],"type":"Point"}
}