{
  "type": "Feature",
  "properties": {
    "iso:country":"DE",
    "sg:address":"Hirtenweg 48",
    "sg:city":"Rotenburg",
    "sg:phone":"+49 4261/63292",
    "sg:postcode":"27356",
    "sg:province":"Niedersachsen",
    "wof:name":"A. Lanz",
    "wof:placetype":"venue"
},
  "geometry": {"coordinates":[9.424383,53.123127],"type":"Point"}
}