{
  "type": "Feature",
  "properties": {
    "iso:country":"DE",
    "sg:address":"Hauptstr. 47",
    "sg:city":"Mehlbach",
    "sg:phone":"+49 6301/1430",
    "sg:postcode":"67735",
    "sg:province":"Rheinland-Pfalz",
    "wof:name":"Siegfried G\u00f6tz",
    "wof:placetype":"venue"
},
  "geometry": {"coordinates":[7.7158751488,49.5209465027],"type":"Point"}
}