{
  "type": "Feature",
  "properties": {
    "iso:country":"DE",
    "sg:address":"Am Bahnhof 2",
    "sg:city":"Soltau",
    "sg:phone":"+49 5191/2469",
    "sg:postcode":"29614",
    "sg:province":"Niedersachsen",
    "wof:name":"M\u00fcnch Und Potulski Rechtsanw\u00e4lte Und Notare",
    "wof:placetype":"venue"
},
  "geometry": {"coordinates":[9.8321304321,52.9834213257],"type":"Point"}
}