{
  "type": "Feature",
  "properties": {
    "iso:country":"DE",
    "sg:address":"Kirtaweg 24 A",
    "sg:city":"M\u00fcnchen",
    "sg:phone":"+49 89/422101",
    "sg:postcode":"81829",
    "sg:province":"Bayern",
    "wof:name":"Veronika Und A. Ben Smida Masseure",
    "wof:placetype":"venue"
},
  "geometry": {"coordinates":[11.674091,48.13121],"type":"Point"}
}