{
  "type": "Feature",
  "properties": {
    "iso:country":"DE",
    "sg:address":"Carl-Bosch-Str. 193",
    "sg:city":"Ludwigshafen",
    "sg:phone":"+49 621/697488",
    "sg:postcode":"67063",
    "sg:province":"Rheinland-Pfalz",
    "wof:name":"Royal",
    "wof:placetype":"venue"
},
  "geometry": {"coordinates":[8.42163,49.497131],"type":"Point"}
}