{
  "type": "Feature",
  "properties": {
    "iso:country":"DE",
    "sg:address":"P\u00f6hlenweg 30",
    "sg:city":"D\u00fcsseldorf",
    "sg:phone":"+49 211/682842",
    "sg:postcode":"40629",
    "sg:province":"Nordrhein-Westfalen",
    "wof:name":"Helmut Wolf Ingenieur Und Architekt",
    "wof:placetype":"venue"
},
  "geometry": {"coordinates":[6.835668,51.238903],"type":"Point"}
}