{
  "type": "Feature",
  "properties": {
    "iso:country":"DE",
    "sg:address":"Am Volkspark 23",
    "sg:city":"Papenburg",
    "sg:phone":"+49 4961/768498",
    "sg:postcode":"26871",
    "sg:province":"Niedersachsen",
    "wof:name":"Ostfriesland",
    "wof:placetype":"venue"
},
  "geometry": {"coordinates":[7.374735,53.071896],"type":"Point"}
}