{
  "type": "Feature",
  "properties": {
    "iso:country":"DE",
    "sg:address":"Am Sonnenberg 3",
    "sg:city":"Bockenheim",
    "sg:phone":"+49 6359/4319",
    "sg:postcode":"67278",
    "sg:province":"Rheinland-Pfalz",
    "wof:name":"Werner Kohl",
    "wof:placetype":"venue"
},
  "geometry": {"coordinates":[8.1792764664,49.5991859436],"type":"Point"}
}