{
  "type": "Feature",
  "properties": {
    "iso:country":"DE",
    "sg:address":"Krumme Gasse 150",
    "sg:city":"Hardisleben",
    "sg:phone":"+49 36377/4570",
    "sg:postcode":"99628",
    "sg:province":"Th\u00fcringen",
    "wof:name":"Eberhard Bauer",
    "wof:placetype":"venue"
},
  "geometry": {"coordinates":[11.424756,51.154259],"type":"Point"}
}