{
  "type": "Feature",
  "properties": {
    "iso:country":"DE",
    "sg:address":"Rudolf-Diesel-Str 5-7",
    "sg:city":"Erbach",
    "sg:phone":"+49 6062/912730",
    "sg:postcode":"64711",
    "sg:province":"Hessen",
    "wof:name":"G.+ W.quality + Control Gmbh",
    "wof:placetype":"venue"
},
  "geometry": {"coordinates":[8.989122,49.666241],"type":"Point"}
}