{
  "type": "Feature",
  "properties": {
    "iso:country":"DE",
    "sg:address":"Keltenweg 14",
    "sg:city":"Gauting",
    "sg:phone":"+49 89/8501232",
    "sg:postcode":"82131",
    "sg:province":"Bayern",
    "wof:name":"Die Engel Eva Duschl E. K.",
    "wof:placetype":"venue"
},
  "geometry": {"coordinates":[11.3736143112,48.0706939697],"type":"Point"}
}