{
  "type": "Feature",
  "properties": {
    "iso:country":"DE",
    "sg:address":"Turmstiege 11",
    "sg:city":"M\u00f6nchengladbach",
    "sg:phone":"+49 2161/180914",
    "sg:postcode":"41061",
    "sg:province":"Nordrhein-Westfalen",
    "wof:name":"Gatsby",
    "wof:placetype":"venue"
},
  "geometry": {"coordinates":[6.4303641319,51.195148468],"type":"Point"}
}