{
  "type": "Feature",
  "properties": {
    "iso:country":"DE",
    "sg:address":"Saarstr. 52",
    "sg:city":"Friedberg",
    "sg:phone":"+49 6031/2665",
    "sg:postcode":"61169",
    "sg:province":"Hessen",
    "wof:name":"Apotheke Am Bahnhof Inh. Kai-uwe Wenke",
    "wof:placetype":"venue"
},
  "geometry": {"coordinates":[8.758954,50.332371],"type":"Point"}
}