{
  "type": "Feature",
  "properties": {
    "iso:country":"DE",
    "sg:address":"Neue Str. 89",
    "sg:city":"Bremerv\u00f6rde",
    "sg:phone":"+49 4761/70202",
    "sg:postcode":"27432",
    "sg:province":"Niedersachsen",
    "wof:name":"J. Schallock",
    "wof:placetype":"venue"
},
  "geometry": {"coordinates":[9.1442155838,53.4875411987],"type":"Point"}
}