{
  "type": "Feature",
  "properties": {
    "iso:country":"DE",
    "sg:address":"Poppenreuth",
    "sg:city":"Kammerstein",
    "sg:phone":"+49 9122/2285",
    "sg:postcode":"91126",
    "sg:province":"Bayern",
    "wof:name":"H. Vitzthum",
    "wof:placetype":"venue"
},
  "geometry": {"coordinates":[10.9604797363,49.2837905884],"type":"Point"}
}