{
  "type": "Feature",
  "properties": {
    "iso:country":"DE",
    "sg:address":"Sterneckbergstr. 2",
    "sg:city":"Wiesensteig",
    "sg:phone":"+49 7335/1820",
    "sg:postcode":"73349",
    "sg:province":"Baden-W\u00fcrttemberg",
    "wof:name":"Weinmayr Verwaltungs Gmbh",
    "wof:placetype":"venue"
},
  "geometry": {"coordinates":[9.634869,48.569946],"type":"Point"}
}