{
  "type": "Feature",
  "properties": {
    "iso:country":"DE",
    "sg:address":"Termeerh\u00f6fe 35",
    "sg:city":"Essen",
    "sg:phone":"+49 201/307439",
    "sg:postcode":"45327",
    "sg:province":"Nordrhein-Westfalen",
    "wof:name":"Thei\u00dfen",
    "wof:placetype":"venue"
},
  "geometry": {"coordinates":[7.0485072136,51.5022010803],"type":"Point"}
}