{
  "type": "Feature",
  "properties": {
    "iso:country":"DE",
    "sg:address":"Gebeschusstr. 9",
    "sg:city":"Frankfurt",
    "sg:phone":"+49 69/316969",
    "sg:postcode":"65929",
    "sg:province":"Hessen",
    "wof:name":"Bikuz",
    "wof:placetype":"venue"
},
  "geometry": {"coordinates":[8.54316,50.105091],"type":"Point"}
}