{
  "type": "Feature",
  "properties": {
    "iso:country":"DE",
    "sg:address":"Bahnhofstr. 70b",
    "sg:city":"Neckargem\u00fcnd",
    "sg:phone":"+49 6223/809380",
    "sg:postcode":"69151",
    "sg:province":"Baden-W\u00fcrttemberg",
    "wof:name":"Shell Tankstelle",
    "wof:placetype":"venue"
},
  "geometry": {"coordinates":[8.7862548828,49.3940849304],"type":"Point"}
}