{
  "type": "Feature",
  "properties": {
    "iso:country":"DE",
    "sg:address":"Brunnenstr. 17",
    "sg:city":"Zweibr\u00fccken",
    "sg:phone":"+49 6332/43041",
    "sg:postcode":"66482",
    "sg:province":"Rheinland-Pfalz",
    "wof:name":"Fsm-treuhand Und Steuerberatungsges. Mbh",
    "wof:placetype":"venue"
},
  "geometry": {"coordinates":[7.3883390427,49.2558555603],"type":"Point"}
}