{
  "type": "Feature",
  "properties": {
    "iso:country":"DE",
    "sg:address":"Galenusstr. 23",
    "sg:city":"Geldern",
    "sg:phone":"+49 2831/88555",
    "sg:postcode":"47608",
    "sg:province":"Nordrhein-Westfalen",
    "wof:name":"Wilhelm Kastir",
    "wof:placetype":"venue"
},
  "geometry": {"coordinates":[6.3411197662,51.5154533386],"type":"Point"}
}