{
  "type": "Feature",
  "properties": {
    "iso:country":"DE",
    "sg:address":"Esborner Str. 29",
    "sg:city":"Wetter",
    "sg:phone":"+49 2335/7906",
    "sg:postcode":"58300",
    "sg:province":"Nordrhein-Westfalen",
    "wof:name":"Wilhelm Schmidt Inh. Wilhelm Walter",
    "wof:placetype":"venue"
},
  "geometry": {"coordinates":[7.33714,51.38686],"type":"Point"}
}