{
  "type": "Feature",
  "properties": {
    "iso:country":"DE",
    "sg:address":"Wolfsberger Str. 17",
    "sg:city":"L\u00fcdinghausen",
    "sg:phone":"+49 2591/78822",
    "sg:postcode":"59348",
    "sg:province":"Nordrhein-Westfalen",
    "wof:name":"Joachim Wachowski Praxis F\u00fcr Ergotherapie",
    "wof:placetype":"venue"
},
  "geometry": {"coordinates":[7.443767,51.768021],"type":"Point"}
}