{
  "type": "Feature",
  "properties": {
    "iso:country":"DE",
    "sg:address":"Unterlandstr. 33",
    "sg:city":"Heilbronn",
    "sg:phone":"+49 7066/1238",
    "sg:postcode":"74078",
    "sg:province":"Baden-W\u00fcrttemberg",
    "wof:name":"Gebert & Mack Gmbh",
    "wof:placetype":"venue"
},
  "geometry": {"coordinates":[9.14518,49.192905],"type":"Point"}
}