{
  "type": "Feature",
  "properties": {
    "iso:country":"DE",
    "sg:address":"Dr.-Jakob-Hector-Str. 10",
    "sg:city":"Saarlouis",
    "sg:postcode":"66740",
    "sg:province":"Saarland",
    "wof:name":"Stockart Gmbh",
    "wof:placetype":"venue"
},
  "geometry": {"coordinates":[6.743011,49.311596],"type":"Point"}
}