{
  "type": "Feature",
  "properties": {
    "iso:country":"DE",
    "sg:address":"Saalburgstr. 46",
    "sg:city":"Oberursel",
    "sg:phone":"+49 4961/7236669",
    "sg:postcode":"61440",
    "sg:province":"Hessen",
    "wof:name":"Hans-peter Both",
    "wof:placetype":"venue"
},
  "geometry": {"coordinates":[8.5745019913,50.2288017273],"type":"Point"}
}