{
  "type": "Feature",
  "properties": {
    "iso:country":"DE",
    "sg:address":"St.-Erasmus-Str. 13",
    "sg:city":"Ballrechten",
    "sg:phone":"+49 4976/348878",
    "sg:postcode":"79282",
    "sg:province":"Baden-W\u00fcrttemberg",
    "wof:name":"Sparkasse Staufen",
    "wof:placetype":"venue"
},
  "geometry": {"coordinates":[7.702725,47.8606],"type":"Point"}
}