{
  "type": "Feature",
  "properties": {
    "iso:country":"DE",
    "sg:address":"Dohnaer Str. 45",
    "sg:city":"Dresden",
    "sg:phone":"+49 351/2703760",
    "sg:postcode":"01219",
    "sg:province":"Sachsen",
    "wof:name":"Scharf Ohg",
    "wof:placetype":"venue"
},
  "geometry": {"coordinates":[13.767987,51.022526],"type":"Point"}
}