{
  "type": "Feature",
  "properties": {
    "iso:country":"DE",
    "sg:address":"Am Hemel 14",
    "sg:city":"Mainz",
    "sg:phone":"+49 6131/44233",
    "sg:postcode":"55124",
    "sg:province":"Rheinland-Pfalz",
    "wof:name":"Hermann Korneck Bau- Und Kunstschlosserei",
    "wof:placetype":"venue"
},
  "geometry": {"coordinates":[8.2146129608,49.9975662231],"type":"Point"}
}