{
  "type": "Feature",
  "properties": {
    "iso:country":"DE",
    "sg:address":"Gr\u00fcner Winkel 2",
    "sg:city":"Kappelrodeck",
    "sg:phone":"+49 7842/2128",
    "sg:postcode":"77876",
    "sg:province":"Baden-W\u00fcrttemberg",
    "wof:name":"Societ\u00e4t F\u00fcr Unternehmensbe- Ratung Bdu Huber & Huber Gmbh",
    "wof:placetype":"venue"
},
  "geometry": {"coordinates":[8.1189479828,48.5895805359],"type":"Point"}
}