{
  "type": "Feature",
  "properties": {
    "iso:country":"DE",
    "sg:address":"Merianstr. 8",
    "sg:city":"Emmendingen",
    "sg:phone":"+49 7641/3388",
    "sg:postcode":"79312",
    "sg:province":"Baden-W\u00fcrttemberg",
    "wof:name":"Frank Siegwarth",
    "wof:placetype":"venue"
},
  "geometry": {"coordinates":[7.853937,48.123405],"type":"Point"}
}