{
  "type": "Feature",
  "properties": {
    "iso:country":"DE",
    "sg:address":"Bannwaldallee 40",
    "sg:city":"Karlsruhe",
    "sg:postcode":"76185",
    "sg:province":"Baden-W\u00fcrttemberg",
    "wof:name":"Alois K\u00fchn Ohg",
    "wof:placetype":"venue"
},
  "geometry": {"coordinates":[8.3690948486,48.9998207092],"type":"Point"}
}