{
  "type": "Feature",
  "properties": {
    "iso:country":"DE",
    "sg:address":"Th\u00fcringer Str. 33",
    "sg:city":"K\u00fcnzell",
    "sg:phone":"+49 661/35458",
    "sg:postcode":"36093",
    "sg:province":"Hessen",
    "wof:name":"H. Kl\u00f6de Immobilienmakler",
    "wof:placetype":"venue"
},
  "geometry": {"coordinates":[9.7195539474,50.5482292175],"type":"Point"}
}