{
  "type": "Feature",
  "properties": {
    "iso:country":"DE",
    "sg:address":"Hartwicusstr. 20",
    "sg:city":"Hamburg",
    "sg:phone":"+49 4102/30644",
    "sg:postcode":"22087",
    "sg:province":"Hamburg",
    "wof:name":"F. Wackeldehne",
    "wof:placetype":"venue"
},
  "geometry": {"coordinates":[10.0243186951,53.5662918091],"type":"Point"}
}