{
  "type": "Feature",
  "properties": {
    "iso:country":"DE",
    "sg:address":"Fasanenstr. 81a",
    "sg:city":"Berlin",
    "sg:postcode":"10623",
    "sg:province":"Berlin",
    "wof:name":"Acr Cafe Kantdreieck",
    "wof:placetype":"venue"
},
  "geometry": {"coordinates":[13.3280096054,52.5051307678],"type":"Point"}
}