{
  "type": "Feature",
  "properties": {
    "iso:country":"DE",
    "sg:address":"Schmiedestr. 1 b",
    "sg:city":"L\u00fcchow",
    "sg:phone":"+49 5841/4550",
    "sg:postcode":"29439",
    "sg:province":"Niedersachsen",
    "wof:name":"Jacqueline Behrens",
    "wof:placetype":"venue"
},
  "geometry": {"coordinates":[11.155054,52.967369],"type":"Point"}
}