{
  "type": "Feature",
  "properties": {
    "iso:country":"DE",
    "sg:address":"Langener Str. 100",
    "sg:city":"M\u00f6rfelden-Walldorf",
    "sg:phone":"+49 6105/22626",
    "sg:postcode":"64546",
    "sg:province":"Hessen",
    "wof:name":"Motorenfabrik Hatz Gmbh & Co. Kg",
    "wof:placetype":"venue"
},
  "geometry": {"coordinates":[8.5785245895,49.9783554077],"type":"Point"}
}