{
  "type": "Feature",
  "properties": {
    "iso:country":"DE",
    "sg:address":"D\u00fcsseler Feld 1",
    "sg:city":"W\u00fclfrath",
    "sg:phone":"+49 2058/8572",
    "sg:postcode":"42489",
    "sg:province":"Nordrhein-Westfalen",
    "wof:name":"Aprather M\u00fchle",
    "wof:placetype":"venue"
},
  "geometry": {"coordinates":[7.0710139275,51.2706871033],"type":"Point"}
}