{
  "type": "Feature",
  "properties": {
    "iso:country":"DE",
    "sg:address":"Bahnhofstr. 11",
    "sg:city":"Oelsnitz",
    "sg:phone":"+49 37298/2219",
    "sg:postcode":"09376",
    "sg:province":"Sachsen",
    "wof:name":"R. K\u00f6hler",
    "wof:placetype":"venue"
},
  "geometry": {"coordinates":[12.701584816,50.7261657715],"type":"Point"}
}