{
  "type": "Feature",
  "properties": {
    "iso:country":"DE",
    "sg:address":"Stockheimer Seite 1",
    "sg:city":"Gr\u00e4venwiesbach",
    "sg:phone":"+49 6086/551",
    "sg:postcode":"61279",
    "sg:province":"Hessen",
    "wof:name":"Metallbau Stamm Gmbh",
    "wof:placetype":"venue"
},
  "geometry": {"coordinates":[8.429875,50.361572],"type":"Point"}
}