{
  "type": "Feature",
  "properties": {
    "iso:country":"DE",
    "sg:address":"Bahnhofstr. 22",
    "sg:city":"Georgenthal",
    "sg:postcode":"99887",
    "sg:province":"Th\u00fcringen",
    "wof:name":"Uni Inves Kg",
    "wof:placetype":"venue"
},
  "geometry": {"coordinates":[10.662812233,50.8325958252],"type":"Point"}
}