{
  "type": "Feature",
  "properties": {
    "iso:country":"DE",
    "sg:address":"Lehmkaute 32",
    "sg:city":"Neustadt",
    "sg:phone":"+49 6692/7947",
    "sg:postcode":"35279",
    "sg:province":"Hessen",
    "wof:name":"Mawex-maschinen- Und Werkzeugbau Gmbh",
    "wof:placetype":"venue"
},
  "geometry": {"coordinates":[9.1088542938,50.8554496765],"type":"Point"}
}