{
  "type": "Feature",
  "properties": {
    "iso:country":"DE",
    "sg:address":"Erpen 21",
    "sg:city":"Heinsberg",
    "sg:phone":"+49 2452/5579",
    "sg:postcode":"52525",
    "sg:province":"Nordrhein-Westfalen",
    "wof:name":"Johannes Von Den Driesch",
    "wof:placetype":"venue"
},
  "geometry": {"coordinates":[6.093414,51.030819],"type":"Point"}
}