{
  "type": "Feature",
  "properties": {
    "iso:country":"DE",
    "sg:address":"Schillerstr. 3",
    "sg:city":"Petershagen",
    "sg:phone":"+49 5702/1296",
    "sg:postcode":"32469",
    "sg:province":"Nordrhein-Westfalen",
    "wof:name":"Siegfried Burkhardt Heilpraktiker",
    "wof:placetype":"venue"
},
  "geometry": {"coordinates":[9.0108442307,52.3780822754],"type":"Point"}
}