{
  "type": "Feature",
  "properties": {
    "iso:country":"DE",
    "sg:address":"Lummertskeller 9",
    "sg:city":"Kehl",
    "sg:phone":"+49 7851/3374",
    "sg:postcode":"77694",
    "sg:province":"Baden-W\u00fcrttemberg",
    "wof:name":"Ludwig J\u00f6rger",
    "wof:placetype":"venue"
},
  "geometry": {"coordinates":[7.87457,48.56311],"type":"Point"}
}