{
  "type": "Feature",
  "properties": {
    "iso:country":"DE",
    "sg:address":"Mariendorfer Str. 19",
    "sg:city":"Kassel",
    "sg:phone":"+49 561/9833710",
    "sg:postcode":"34127",
    "sg:province":"Hessen",
    "wof:name":"Dausend Gmbh",
    "wof:placetype":"venue"
},
  "geometry": {"coordinates":[9.4991207123,51.3369255066],"type":"Point"}
}