{
  "type": "Feature",
  "properties": {
    "iso:country":"DE",
    "sg:address":"Schaibing",
    "sg:city":"Untergriesbach",
    "sg:phone":"+49 8593/1234",
    "sg:postcode":"94107",
    "sg:province":"Bayern",
    "wof:name":"Ludwig Wimmer",
    "wof:placetype":"venue"
},
  "geometry": {"coordinates":[13.6497125626,48.5993614197],"type":"Point"}
}