{
  "type": "Feature",
  "properties": {
    "iso:country":"DE",
    "sg:address":"Jacobstr. 23",
    "sg:city":"Brandenburg",
    "sg:phone":"+49 3381/223438",
    "sg:postcode":"14776",
    "sg:province":"Brandenburg",
    "wof:name":"Francke & Dulder Bauten Gmbh",
    "wof:placetype":"venue"
},
  "geometry": {"coordinates":[12.55617,52.40403],"type":"Point"}
}