{
  "type": "Feature",
  "properties": {
    "iso:country":"DE",
    "sg:address":"Eckernf\u00f6rder Str. 37",
    "sg:city":"Frankfurt",
    "sg:phone":"+49 69/561894",
    "sg:postcode":"60435",
    "sg:province":"Hessen",
    "wof:name":"Joachim Friedrich Gmbh",
    "wof:placetype":"venue"
},
  "geometry": {"coordinates":[8.6782636642,50.1426582336],"type":"Point"}
}