{
  "type": "Feature",
  "properties": {
    "iso:country":"DE",
    "sg:address":"Fasanenweg 4",
    "sg:city":"Neustadt",
    "sg:phone":"+49 5032/1235",
    "sg:postcode":"31535",
    "sg:province":"Niedersachsen",
    "wof:name":"Ernst Karl",
    "wof:placetype":"venue"
},
  "geometry": {"coordinates":[9.4478807449,52.4821014404],"type":"Point"}
}