{
  "type": "Feature",
  "properties": {
    "iso:country":"DE",
    "sg:address":"Brauereistr. 16a",
    "sg:city":"Neustadt-Glewe",
    "sg:phone":"+49 38757/54597",
    "sg:postcode":"19306",
    "sg:province":"Mecklenburg-Vorpommern",
    "wof:name":"Bau- Und M\u00f6beltischlerei Riebe Gmbh",
    "wof:placetype":"venue"
},
  "geometry": {"coordinates":[11.586829,53.376015],"type":"Point"}
}