{
  "type": "Feature",
  "properties": {
    "iso:country":"DE",
    "sg:address":"Am Eisenborn 5",
    "sg:city":"Saulheim",
    "sg:phone":"+49 6732/5376",
    "sg:postcode":"55291",
    "sg:province":"Rheinland-Pfalz",
    "wof:name":"Andreas Eby",
    "wof:placetype":"venue"
},
  "geometry": {"coordinates":[8.1522035599,49.8765296936],"type":"Point"}
}