{
  "type": "Feature",
  "properties": {
    "iso:country":"DE",
    "sg:address":"Schwarzwaldstr. 144",
    "sg:city":"Freiburg",
    "sg:phone":"+49 761/73879",
    "sg:postcode":"79102",
    "sg:province":"Baden-W\u00fcrttemberg",
    "wof:name":"Anton Flaig B\u00e4ckerei",
    "wof:placetype":"venue"
},
  "geometry": {"coordinates":[7.85877,47.989151],"type":"Point"}
}