{
  "type": "Feature",
  "properties": {
    "iso:country":"DE",
    "sg:address":"Karolingerweg 24",
    "sg:city":"Dietzenbach",
    "sg:phone":"+49 6074/42860",
    "sg:postcode":"63128",
    "sg:province":"Hessen",
    "wof:name":"Stoffel Und R\u00fchl Rechtsanw\u00e4lte",
    "wof:placetype":"venue"
},
  "geometry": {"coordinates":[8.7885456085,50.0246620178],"type":"Point"}
}