{
  "type": "Feature",
  "properties": {
    "iso:country":"DE",
    "sg:address":"Schneegl\u00f6ckchenweg 14",
    "sg:city":"Halle",
    "sg:phone":"+49 345/5224521",
    "sg:postcode":"06118",
    "sg:province":"Sachsen-Anhalt",
    "wof:name":"Taxi-transport- Und Kurierdienst Ronald Kobsch",
    "wof:placetype":"venue"
},
  "geometry": {"coordinates":[11.9704627991,51.5089454651],"type":"Point"}
}