{
  "type": "Feature",
  "properties": {
    "iso:country":"DE",
    "sg:address":"Udostr. 6",
    "sg:city":"Boppard",
    "sg:phone":"+49 6742/3830",
    "sg:postcode":"56154",
    "sg:province":"Rheinland-Pfalz",
    "wof:name":"M. U. H. Hildner",
    "wof:placetype":"venue"
},
  "geometry": {"coordinates":[7.510473,50.229156],"type":"Point"}
}