{
  "type": "Feature",
  "properties": {
    "iso:country":"DE",
    "sg:address":"Alte Dorfstr. 18 a",
    "sg:city":"D\u00f6rentrup",
    "sg:phone":"+49 5265/94980",
    "sg:postcode":"32694",
    "sg:province":"Nordrhein-Westfalen",
    "wof:name":"Helga Ungermann Steuerberaterin",
    "wof:placetype":"venue"
},
  "geometry": {"coordinates":[9.0275287628,52.0613632202],"type":"Point"}
}