{
  "type": "Feature",
  "properties": {
    "iso:country":"DE",
    "sg:address":"Neustadt 5-7 Tiefenweg 4-6",
    "sg:city":"Gie\u00dfen",
    "sg:phone":"+49 641/71327",
    "sg:postcode":"35390",
    "sg:province":"Hessen",
    "wof:name":"Reeh-verwaltungs Gmbh",
    "wof:placetype":"venue"
},
  "geometry": {"coordinates":[8.676334,50.586613],"type":"Point"}
}