{
  "type": "Feature",
  "properties": {
    "iso:country":"DE",
    "sg:address":"Wohlers Allee 32",
    "sg:city":"Hamburg",
    "sg:phone":"+49 40/4393691",
    "sg:postcode":"22767",
    "sg:province":"Hamburg",
    "wof:name":"Reinhard Bogdanski Innenausbau",
    "wof:placetype":"venue"
},
  "geometry": {"coordinates":[9.9550762177,53.5588493347],"type":"Point"}
}