{
  "type": "Feature",
  "properties": {
    "iso:country":"DE",
    "sg:address":"Alter Steig 2",
    "sg:city":"Ro\u00dftal",
    "sg:phone":"+49 9127/951433",
    "sg:postcode":"90574",
    "sg:province":"Bayern",
    "wof:name":"Klupper & Leicht",
    "wof:placetype":"venue"
},
  "geometry": {"coordinates":[10.906293,49.403076],"type":"Point"}
}