{
  "type": "Feature",
  "properties": {
    "iso:country":"DE",
    "sg:address":"Gr\u00fcneburgweg 94",
    "sg:city":"Frankfurt",
    "sg:phone":"+49 69/594399",
    "sg:postcode":"60323",
    "sg:province":"Hessen",
    "wof:name":"Oeco-linea Patentverwertung E. K.",
    "wof:placetype":"venue"
},
  "geometry": {"coordinates":[8.6674575806,50.1225585938],"type":"Point"}
}