{
  "type": "Feature",
  "properties": {
    "iso:country":"DE",
    "sg:address":"M\u00fcllerwegstannen 13a",
    "sg:city":"Stadtallendorf",
    "sg:postcode":"35260",
    "sg:province":"Hessen",
    "wof:name":"Jutta Herbst Verwaltungs- Gesellschaft Mbh",
    "wof:placetype":"venue"
},
  "geometry": {"coordinates":[8.996574,50.810791],"type":"Point"}
}