{
  "type": "Feature",
  "properties": {
    "iso:country":"DE",
    "sg:address":"Am Lohm\u00fchlbach 12",
    "sg:city":"Freising",
    "sg:phone":"+49 8161/82068",
    "sg:postcode":"85356",
    "sg:province":"Bayern",
    "wof:name":"A. Milchgie\u00dfer",
    "wof:placetype":"venue"
},
  "geometry": {"coordinates":[11.7615804672,48.387928009],"type":"Point"}
}