{
  "type": "Feature",
  "properties": {
    "iso:country":"DE",
    "sg:address":"Sedanstr. 22",
    "sg:city":"Hannover",
    "sg:phone":"+49 511/332672",
    "sg:postcode":"30161",
    "sg:province":"Niedersachsen",
    "wof:name":"Frank Pantel Architekt",
    "wof:placetype":"venue"
},
  "geometry": {"coordinates":[9.747649,52.381695],"type":"Point"}
}