{
  "type": "Feature",
  "properties": {
    "iso:country":"DE",
    "sg:address":"Schulstr. 35",
    "sg:city":"Barleben",
    "sg:phone":"+49 39203/5236",
    "sg:postcode":"39179",
    "sg:province":"Sachsen-Anhalt",
    "wof:name":"Pension Zur Tenne",
    "wof:placetype":"venue"
},
  "geometry": {"coordinates":[11.6204938889,52.2051887512],"type":"Point"}
}