{
  "type": "Feature",
  "properties": {
    "iso:country":"DE",
    "sg:address":"Weinbergstr. 27",
    "sg:city":"Triftern",
    "sg:phone":"+49 8562/1235",
    "sg:postcode":"84371",
    "sg:province":"Bayern",
    "wof:name":"Mathias Schmidt Floristenbedarfgro\u00dfhandel",
    "wof:placetype":"venue"
},
  "geometry": {"coordinates":[13.0085220337,48.398109436],"type":"Point"}
}