{
  "type": "Feature",
  "properties": {
    "iso:country":"DE",
    "sg:address":"Schrenker Feld 36",
    "sg:city":"Siegen",
    "sg:phone":"+49 271/353755",
    "sg:postcode":"57080",
    "sg:province":"Nordrhein-Westfalen",
    "wof:name":"P.-g. Georg",
    "wof:placetype":"venue"
},
  "geometry": {"coordinates":[7.973731041,50.8574562073],"type":"Point"}
}