{
  "type": "Feature",
  "properties": {
    "iso:country":"DE",
    "sg:address":"Adam-Weise-Str. 28",
    "sg:city":"Gr\u00e4fenhainichen",
    "sg:phone":"+49 34953/23135",
    "sg:postcode":"06773",
    "sg:province":"Sachsen-Anhalt",
    "wof:name":"Wohnungsgenossenschaft Gr\u00e4fenhainichen Eg",
    "wof:placetype":"venue"
},
  "geometry": {"coordinates":[12.4578914642,51.7265663147],"type":"Point"}
}