{
  "type": "Feature",
  "properties": {
    "iso:country":"DE",
    "sg:address":"Jahnstr. 1",
    "sg:city":"M\u00fclheim-K\u00e4rlich",
    "sg:phone":"+49 2630/3621",
    "sg:postcode":"56218",
    "sg:province":"Rheinland-Pfalz",
    "wof:name":"Hans Koch",
    "wof:placetype":"venue"
},
  "geometry": {"coordinates":[7.5038151741,50.3884468079],"type":"Point"}
}