{
  "type": "Feature",
  "properties": {
    "iso:country":"DE",
    "sg:address":"Am Lehester Deich 11",
    "sg:city":"Bremen",
    "sg:phone":"+49 421/253918",
    "sg:postcode":"28357",
    "sg:province":"Bremen",
    "wof:name":"Felske Immobilien",
    "wof:placetype":"venue"
},
  "geometry": {"coordinates":[8.8835296631,53.1211090088],"type":"Point"}
}