{
  "type": "Feature",
  "properties": {
    "iso:country":"DE",
    "sg:address":"Grafenhof 4 City-Center",
    "sg:city":"Northeim",
    "sg:phone":"+49 5551/8761",
    "sg:postcode":"37154",
    "sg:province":"Niedersachsen",
    "wof:name":"Siegfried Pirente Masseur",
    "wof:placetype":"venue"
},
  "geometry": {"coordinates":[10.0068,51.70665],"type":"Point"}
}