{
  "type": "Feature",
  "properties": {
    "iso:country":"DE",
    "sg:address":"M\u00fchlhohlstr 7",
    "sg:city":"Sulzfeld",
    "sg:phone":"+49 7269/91250",
    "sg:postcode":"75056",
    "sg:province":"Baden-W\u00fcrttemberg",
    "wof:name":"Walter Pottiez Gmbh",
    "wof:placetype":"venue"
},
  "geometry": {"coordinates":[8.851009,49.107029],"type":"Point"}
}