{
  "type": "Feature",
  "properties": {
    "iso:country":"DE",
    "sg:address":"Jahnstr 29",
    "sg:city":"Berlin",
    "sg:phone":"+49 30/68500431",
    "sg:postcode":"12347",
    "sg:province":"Berlin",
    "wof:name":"Julius Reisinger Elektronik Gmbh",
    "wof:placetype":"venue"
},
  "geometry": {"coordinates":[13.4426488876,52.4608535767],"type":"Point"}
}