{
  "type": "Feature",
  "properties": {
    "iso:country":"DE",
    "sg:address":"Am Gallberg 4",
    "sg:city":"Brandenburg an der Havel",
    "sg:phone":"+49 3381",
    "sg:postcode":"14770",
    "sg:province":"Brandenburg",
    "wof:name":"Osz Gebr\u00fcder Reichstein Brandenburg",
    "wof:placetype":"venue"
},
  "geometry": {"coordinates":[12.534454,52.422787],"type":"Point"}
}