{
  "type": "Feature",
  "properties": {
    "iso:country":"DE",
    "sg:address":"Leyentalstr. 67",
    "sg:city":"Krefeld",
    "sg:phone":"+49 2151/24305",
    "sg:postcode":"47799",
    "sg:province":"Nordrhein-Westfalen",
    "wof:name":"H.-g. Beele",
    "wof:placetype":"venue"
},
  "geometry": {"coordinates":[6.5694642067,51.3389091492],"type":"Point"}
}