{
  "type": "Feature",
  "properties": {
    "iso:country":"DE",
    "sg:address":"Hauptstr. 33",
    "sg:city":"Landstuhl",
    "sg:phone":"+49 6371/3847",
    "sg:postcode":"66849",
    "sg:province":"Rheinland-Pfalz",
    "wof:name":"Robert Schohl",
    "wof:placetype":"venue"
},
  "geometry": {"coordinates":[7.5700039864,49.4097633362],"type":"Point"}
}