{
  "type": "Feature",
  "properties": {
    "iso:country":"DE",
    "sg:address":"Klosterstr.",
    "sg:city":"Schleusingen",
    "sg:phone":"+49 36841/42722",
    "sg:postcode":"98553",
    "sg:province":"Th\u00fcringen",
    "wof:name":"U. Maresch",
    "wof:placetype":"venue"
},
  "geometry": {"coordinates":[10.7545061111,50.5097198486],"type":"Point"}
}