{
  "type": "Feature",
  "properties": {
    "iso:country":"DE",
    "sg:address":"Ottenser Hauptstr. 20",
    "sg:city":"Hamburg",
    "sg:phone":"+49 40/3908848",
    "sg:postcode":"22765",
    "sg:province":"Hamburg",
    "wof:name":"Restaurant Indian Tandoori",
    "wof:placetype":"venue"
},
  "geometry": {"coordinates":[9.9309520721,53.5522422791],"type":"Point"}
}