{
  "type": "Feature",
  "properties": {
    "iso:country":"DE",
    "sg:address":"Ostenhellweg",
    "sg:city":"Dortmund",
    "sg:phone":"+49 231/5569310",
    "sg:postcode":"44135",
    "sg:province":"Nordrhein-Westfalen",
    "wof:name":"Ne-metallhandel Gmbh",
    "wof:placetype":"venue"
},
  "geometry": {"coordinates":[7.471555,51.514309],"type":"Point"}
}