{
  "type": "Feature",
  "properties": {
    "iso:country":"DE",
    "sg:address":"Fraunhoferstr. 28",
    "sg:city":"Bremerhaven",
    "sg:phone":"+49 471/88891",
    "sg:postcode":"27580",
    "sg:province":"Bremen",
    "wof:name":"Lemos-veiga",
    "wof:placetype":"venue"
},
  "geometry": {"coordinates":[8.58183,53.57515],"type":"Point"}
}