{
  "type": "Feature",
  "properties": {
    "iso:country":"DE",
    "sg:address":"Zur Alten Kolonie 9",
    "sg:city":"Holzwickede",
    "sg:phone":"+49 2301/5039",
    "sg:postcode":"59439",
    "sg:province":"Nordrhein-Westfalen",
    "wof:name":"Harald Koechlin",
    "wof:placetype":"venue"
},
  "geometry": {"coordinates":[7.6199150085,51.5156517029],"type":"Point"}
}