{
  "type": "Feature",
  "properties": {
    "iso:country":"DE",
    "sg:address":"Rembrandtstr. 1",
    "sg:city":"Langerwisch",
    "sg:phone":"+49 33205/62054",
    "sg:postcode":"14557",
    "wof:name":"F. Draband Ingenieur",
    "wof:placetype":"venue"
},
  "geometry": {"coordinates":[13.0720834732,52.3298912048],"type":"Point"}
}