{
  "type": "Feature",
  "properties": {
    "iso:country":"DE",
    "sg:address":"Schlo\u00dffeldweg 48",
    "sg:city":"Bergisch Gladbach",
    "sg:phone":"+49 2204/52230",
    "sg:postcode":"51429",
    "sg:province":"Nordrhein-Westfalen",
    "wof:name":"J\u00fcrgen Patermann",
    "wof:placetype":"venue"
},
  "geometry": {"coordinates":[7.1548900604,50.9589271545],"type":"Point"}
}