{
  "type": "Feature",
  "properties": {
    "iso:country":"DE",
    "sg:address":"Bahnhofstr. 12-14",
    "sg:city":"Weida",
    "sg:phone":"+49 36603/40806",
    "sg:postcode":"07570",
    "sg:province":"Th\u00fcringen",
    "wof:name":"Bock Verwaltungs Gmbh",
    "wof:placetype":"venue"
},
  "geometry": {"coordinates":[12.063017,50.777348],"type":"Point"}
}