{
  "type": "Feature",
  "properties": {
    "iso:country":"DE",
    "sg:address":"Wiesenstr. 71",
    "sg:city":"Lambrecht",
    "sg:phone":"+49 4963/258036",
    "sg:postcode":"67466",
    "sg:province":"Rheinland-Pfalz",
    "wof:name":"Heka Elektronik Dr Schulze Gmbh",
    "wof:placetype":"venue"
},
  "geometry": {"coordinates":[8.06855,49.373058],"type":"Point"}
}