{
  "type": "Feature",
  "properties": {
    "iso:country":"DE",
    "sg:address":"Bad Windsheimer Str. 3",
    "sg:city":"Uffenheim",
    "sg:phone":"+49 9842/98130",
    "sg:postcode":"97215",
    "sg:province":"Bayern",
    "wof:name":"Reichart Blusen Gmbh",
    "wof:placetype":"venue"
},
  "geometry": {"coordinates":[10.2400941849,49.5401496887],"type":"Point"}
}