{
  "type": "Feature",
  "properties": {
    "iso:country":"DE",
    "sg:address":"Im Dreieck 1",
    "sg:city":"Damme",
    "sg:phone":"+49 5491/96680",
    "sg:postcode":"49401",
    "sg:province":"Niedersachsen",
    "wof:name":"R\u00f6mer Spedition Gmbh",
    "wof:placetype":"venue"
},
  "geometry": {"coordinates":[8.1724586487,52.4917831421],"type":"Point"}
}