{
  "type": "Feature",
  "properties": {
    "iso:country":"DE",
    "sg:address":"Sch\u00fctzenstr. 8",
    "sg:city":"Ochtrup",
    "sg:phone":"+49 2553/2110",
    "sg:postcode":"48607",
    "sg:province":"Nordrhein-Westfalen",
    "wof:name":"Erwin Bertels Gmbh",
    "wof:placetype":"venue"
},
  "geometry": {"coordinates":[7.1888,52.200371],"type":"Point"}
}