{
  "type": "Feature",
  "properties": {
    "iso:country":"DE",
    "sg:address":"Speestr. 2",
    "sg:city":"Ratingen",
    "sg:phone":"+49 2102/893994",
    "sg:postcode":"40885",
    "sg:province":"Nordrhein-Westfalen",
    "wof:name":"Reichert Und Walsh Ergotherapeutische Praxis",
    "wof:placetype":"venue"
},
  "geometry": {"coordinates":[6.831205,51.333076],"type":"Point"}
}