{
  "type": "Feature",
  "properties": {
    "iso:country":"DE",
    "sg:address":"Lindauer Str. 1",
    "sg:city":"Gro\u00dfaitingen",
    "sg:phone":"+49 8203/1754",
    "sg:postcode":"86845",
    "sg:province":"Bayern",
    "wof:name":"Il Pescatore",
    "wof:placetype":"venue"
},
  "geometry": {"coordinates":[10.7808599472,48.2281761169],"type":"Point"}
}