{
  "type": "Feature",
  "properties": {
    "iso:country":"DE",
    "sg:address":"Offenthaler Str. 26",
    "sg:city":"Dietzenbach",
    "sg:phone":"+49 6074/31627",
    "sg:postcode":"63128",
    "sg:province":"Hessen",
    "wof:name":"La Lanterna",
    "wof:placetype":"venue"
},
  "geometry": {"coordinates":[8.7688713074,49.9990272522],"type":"Point"}
}