{
  "type": "Feature",
  "properties": {
    "iso:country":"DE",
    "sg:address":"Diemelstr. 23",
    "sg:city":"Minden",
    "sg:phone":"+49 571/62230",
    "sg:postcode":"32425",
    "sg:province":"Nordrhein-Westfalen",
    "wof:name":"Karl-friedrich Weber",
    "wof:placetype":"venue"
},
  "geometry": {"coordinates":[8.8995847702,52.3053855896],"type":"Point"}
}