{
  "type": "Feature",
  "properties": {
    "iso:country":"DE",
    "sg:address":"Hermann-L\u00f6ns-Weg 12",
    "sg:city":"Kellinghusen",
    "sg:phone":"+49 4822/6119",
    "sg:postcode":"25548",
    "sg:province":"Schleswig-Holstein",
    "wof:name":"Techau",
    "wof:placetype":"venue"
},
  "geometry": {"coordinates":[9.7400045395,53.956451416],"type":"Point"}
}