{
  "type": "Feature",
  "properties": {
    "iso:country":"DE",
    "sg:address":"Hachener Str. 76",
    "sg:city":"Sundern",
    "sg:phone":"+49 4929/351031",
    "sg:postcode":"59846",
    "sg:province":"Nordrhein-Westfalen",
    "wof:name":"Franz H\u00d6lter Leichtmetallwerkst\u00c4tten Gmbh & Co. Kg",
    "wof:placetype":"venue"
},
  "geometry": {"coordinates":[7.981448,51.375507],"type":"Point"}
}