{
  "type": "Feature",
  "properties": {
    "iso:country":"DE",
    "sg:address":"Gotthold Roth Stra\u00dfe",
    "sg:city":"Greiz",
    "sg:postcode":"07973",
    "sg:province":"Th\u00fcringen",
    "wof:name":"Tontechnik - Der (gute) Ton Macht Die Musik",
    "wof:placetype":"venue"
},
  "geometry": {"coordinates":[12.197424,50.651089],"type":"Point"}
}