{
  "type": "Feature",
  "properties": {
    "iso:country":"DE",
    "sg:address":"Tucherstr. 20",
    "sg:city":"N\u00fcrnberg",
    "sg:phone":"+49 911/221118",
    "sg:postcode":"90403",
    "sg:province":"Bayern",
    "wof:name":"H. Meier",
    "wof:placetype":"venue"
},
  "geometry": {"coordinates":[11.080904,49.454338],"type":"Point"}
}