{
  "type": "Feature",
  "properties": {
    "iso:country":"DE",
    "sg:address":"Carlsplatz 10",
    "sg:city":"\u00dcbach-Palenberg",
    "sg:phone":"+49 2451/49299",
    "sg:postcode":"52531",
    "sg:province":"Nordrhein-Westfalen",
    "wof:name":"Handels",
    "wof:placetype":"venue"
},
  "geometry": {"coordinates":[6.112883,50.921734],"type":"Point"}
}