{
  "type": "Feature",
  "properties": {
    "iso:country":"DE",
    "sg:address":"Am Hang 7",
    "sg:city":"Hamm",
    "sg:phone":"+49 2381/71042",
    "sg:postcode":"59075",
    "sg:province":"Nordrhein-Westfalen",
    "wof:name":"Paul-w. L\u00f6bert Architekt",
    "wof:placetype":"venue"
},
  "geometry": {"coordinates":[7.726901,51.693333],"type":"Point"}
}