{
  "type": "Feature",
  "properties": {
    "iso:country":"DE",
    "sg:address":"Mainburger Str. 20",
    "sg:city":"Freising",
    "sg:phone":"+49 8161/63629",
    "sg:postcode":"85356",
    "sg:province":"Bayern",
    "wof:name":"Johann Filser Kg",
    "wof:placetype":"venue"
},
  "geometry": {"coordinates":[11.747231,48.404739],"type":"Point"}
}