{
  "type": "Feature",
  "properties": {
    "iso:country":"DE",
    "sg:address":"Rondorfer Hauptstr. 45",
    "sg:city":"K\u00f6ln",
    "sg:phone":"+49 2233/2781",
    "sg:postcode":"50997",
    "sg:province":"Nordrhein-Westfalen",
    "wof:name":"Haenlein Link Chapman Taylor Architekten",
    "wof:placetype":"venue"
},
  "geometry": {"coordinates":[6.953974,50.872459],"type":"Point"}
}