{
  "type": "Feature",
  "properties": {
    "iso:country":"DE",
    "sg:address":"Postfach 1266",
    "sg:city":"Rotenburg",
    "sg:postcode":"36188",
    "sg:province":"Hessen",
    "wof:name":"Wilhelm Hoffmann Immobilienmakler",
    "wof:placetype":"venue"
},
  "geometry": {"coordinates":[9.7268800735,50.9951705933],"type":"Point"}
}