{
  "type": "Feature",
  "properties": {
    "iso:country":"DE",
    "sg:address":"Zum Hohen Moor 6",
    "sg:city":"L\u00fcbberstedt",
    "sg:phone":"+49 4793/1732",
    "sg:postcode":"27729",
    "sg:province":"Niedersachsen",
    "wof:name":"Rudolf Von Tils E. K.",
    "wof:placetype":"venue"
},
  "geometry": {"coordinates":[8.8169584274,53.3449287415],"type":"Point"}
}