{
  "type": "Feature",
  "properties": {
    "iso:country":"DE",
    "sg:address":"Petelgasse 11",
    "sg:city":"Weilheim",
    "sg:phone":"+49 881/5415",
    "sg:postcode":"82362",
    "sg:province":"Bayern",
    "wof:name":"Immobilien Forster Gmbh Harald Forster",
    "wof:placetype":"venue"
},
  "geometry": {"coordinates":[11.1452713013,47.8377494812],"type":"Point"}
}