{
  "type": "Feature",
  "properties": {
    "iso:country":"DE",
    "sg:address":"Hauptstr. 33",
    "sg:city":"Markdorf",
    "sg:postcode":"88677",
    "sg:province":"Baden-W\u00fcrttemberg",
    "wof:name":"Escamat Ag",
    "wof:placetype":"venue"
},
  "geometry": {"coordinates":[9.3844356537,47.7218132019],"type":"Point"}
}