{
  "type": "Feature",
  "properties": {
    "iso:country":"DE",
    "sg:address":"Naundorfer Str. 24",
    "sg:city":"Gau\u00dfig",
    "sg:postcode":"02633",
    "sg:province":"Sachsen",
    "wof:name":"G\u00fcnther Hirsch",
    "wof:placetype":"venue"
},
  "geometry": {"coordinates":[14.30938,51.132191],"type":"Point"}
}