{
  "type": "Feature",
  "properties": {
    "iso:country":"DE",
    "sg:address":"Adolf-Pompe-Str. 2",
    "sg:city":"Demmin",
    "sg:phone":"+49 3998/222254",
    "sg:postcode":"17109",
    "sg:province":"Mecklenburg-Vorpommern",
    "wof:name":"Heike Karl Hannelore Hoth Hella Alschweig",
    "wof:placetype":"venue"
},
  "geometry": {"coordinates":[13.043541,53.90247],"type":"Point"}
}