{
  "type": "Feature",
  "properties": {
    "iso:country":"DE",
    "sg:address":"Alter Deutzer Postweg 221",
    "sg:city":"K\u00f6ln",
    "sg:postcode":"51107",
    "sg:province":"Nordrhein-Westfalen",
    "wof:name":"Hicosoft Gesellschaft F\u00fcr Softwareentwicklung System-",
    "wof:placetype":"venue"
},
  "geometry": {"coordinates":[7.0724492073,50.9194564819],"type":"Point"}
}