{
  "type": "Feature",
  "properties": {
    "iso:country":"DE",
    "sg:address":"Dr.-Grundh\u00f6fer-Str. 6",
    "sg:city":"R\u00f6merberg",
    "sg:phone":"+49 6232/82057",
    "sg:postcode":"67354",
    "sg:province":"Rheinland-Pfalz",
    "wof:name":"Edwin Etzkorn",
    "wof:placetype":"venue"
},
  "geometry": {"coordinates":[8.400809288,49.2863464355],"type":"Point"}
}