{
  "type": "Feature",
  "properties": {
    "iso:country":"DE",
    "sg:address":"Gro\u00dfe Str. 80",
    "sg:city":"Ottersberg",
    "sg:phone":"+49 4205/605",
    "sg:postcode":"28870",
    "sg:province":"Niedersachsen",
    "wof:name":"Anita Sch\u00fctte",
    "wof:placetype":"venue"
},
  "geometry": {"coordinates":[9.157336,53.107059],"type":"Point"}
}