{
  "type": "Feature",
  "properties": {
    "iso:country":"DE",
    "sg:address":"Hauptstr. 48",
    "sg:city":"Stein",
    "sg:phone":"+49 911/687282",
    "sg:postcode":"90547",
    "sg:province":"Bayern",
    "wof:name":"Hans W. Voit",
    "wof:placetype":"venue"
},
  "geometry": {"coordinates":[11.0125741959,49.4131240845],"type":"Point"}
}