{
  "type": "Feature",
  "properties": {
    "iso:country":"DE",
    "sg:address":"Hubertusstr. 1",
    "sg:city":"Berlin",
    "sg:phone":"+49 4930/5597298",
    "sg:postcode":"10365",
    "sg:province":"Berlin",
    "wof:name":"Pc Service",
    "wof:placetype":"venue"
},
  "geometry": {"coordinates":[13.494279,52.512115],"type":"Point"}
}