{
  "type": "Feature",
  "properties": {
    "iso:country":"DE",
    "sg:address":"Hoher Weg 391",
    "sg:city":"Moers",
    "sg:phone":"+49 2841/73443",
    "sg:postcode":"47445",
    "sg:province":"Nordrhein-Westfalen",
    "wof:name":"Theodor Lange",
    "wof:placetype":"venue"
},
  "geometry": {"coordinates":[6.621135,51.503151],"type":"Point"}
}