{
  "type": "Feature",
  "properties": {
    "iso:country":"DE",
    "sg:address":"Uffenheimer Str. 2",
    "sg:city":"Obernzenn",
    "sg:phone":"+49 9844/521",
    "sg:postcode":"91619",
    "sg:province":"Bayern",
    "wof:name":"Margret Hostetler",
    "wof:placetype":"venue"
},
  "geometry": {"coordinates":[10.464433,49.451878],"type":"Point"}
}