{
  "type": "Feature",
  "properties": {
    "iso:country":"DE",
    "sg:address":"Alleestr. 7",
    "sg:city":"Salzhemmendorf",
    "sg:phone":"+49 5153/5852",
    "sg:postcode":"31020",
    "sg:province":"Niedersachsen",
    "wof:name":"Parkresidenz An Der Alleestr.",
    "wof:placetype":"venue"
},
  "geometry": {"coordinates":[9.592275,52.066971],"type":"Point"}
}