{
  "type": "Feature",
  "properties": {
    "iso:country":"DE",
    "sg:address":"Rischenweg 5",
    "sg:city":"Rosdorf",
    "sg:phone":"+49 551/782755",
    "sg:postcode":"37124",
    "sg:province":"Niedersachsen",
    "wof:name":"Quelle",
    "wof:placetype":"venue"
},
  "geometry": {"coordinates":[9.908966,51.509533],"type":"Point"}
}