{
  "type": "Feature",
  "properties": {
    "iso:country":"DE",
    "sg:address":"Graf-Landsberg-Str. 1 C",
    "sg:city":"Neuss",
    "sg:phone":"+49 2131/952601",
    "sg:postcode":"41460",
    "sg:province":"Nordrhein-Westfalen",
    "wof:name":"Itm-gesellschaft F. Informationstransport Und Management Mbh",
    "wof:placetype":"venue"
},
  "geometry": {"coordinates":[6.6941027641,51.1962928772],"type":"Point"}
}