{
  "type": "Feature",
  "properties": {
    "iso:country":"DE",
    "sg:address":"Zollernstra\u00dfe 4",
    "sg:city":"Aachen",
    "sg:phone":"+49 241/946620",
    "sg:postcode":"52070",
    "sg:province":"Nordrhein-Westfalen",
    "wof:name":"Avantel Hotel Reservierung Gmbh",
    "wof:placetype":"venue"
},
  "geometry": {"coordinates":[6.0959830284,50.7688751221],"type":"Point"}
}