{
  "type": "Feature",
  "properties": {
    "iso:country":"DE",
    "sg:address":"Lindental 1",
    "sg:city":"Passau",
    "sg:phone":"+49 851/2183",
    "sg:postcode":"94032",
    "sg:province":"Bayern",
    "wof:name":"Donau-radfreunde Radreisen Gmbh",
    "wof:placetype":"venue"
},
  "geometry": {"coordinates":[13.4620065689,48.5689964294],"type":"Point"}
}