{
  "type": "Feature",
  "properties": {
    "iso:country":"DE",
    "sg:address":"Mechower Str. 15",
    "sg:city":"B\u00e4k",
    "sg:phone":"+49 4541/3600",
    "sg:postcode":"23909",
    "sg:province":"Schleswig-Holstein",
    "wof:name":"Karl-heinz Diederichs",
    "wof:placetype":"venue"
},
  "geometry": {"coordinates":[10.7869606018,53.7163391113],"type":"Point"}
}