{
  "type": "Feature",
  "properties": {
    "iso:country":"DE",
    "sg:address":"Melkerstieg 1",
    "sg:city":"L\u00fcbeck",
    "sg:phone":"+49 177",
    "sg:postcode":"23556",
    "sg:province":"Schleswig-Holstein",
    "wof:name":"Www.melaniesieling.de - Pferdewirtin Fn",
    "wof:placetype":"venue"
},
  "geometry": {"coordinates":[10.60499,53.879982],"type":"Point"}
}