{
  "type": "Feature",
  "properties": {
    "iso:country":"DE",
    "sg:address":"Weg beim J\u00e4ger 206",
    "sg:city":"Hamburg",
    "sg:postcode":"22335",
    "sg:province":"Hamburg",
    "wof:name":"Verwaltung Commander Flugzeugverleih Gmbh",
    "wof:placetype":"venue"
},
  "geometry": {"coordinates":[10.00702,53.623058],"type":"Point"}
}