{
  "type": "Feature",
  "properties": {
    "iso:country":"DE",
    "sg:address":"Atzelbergplatz 9",
    "sg:city":"Frankfurt",
    "sg:phone":"+49 69/94734135",
    "sg:postcode":"60389",
    "sg:province":"Hessen",
    "wof:name":"Plus Gmbh & Co. Ohg",
    "wof:placetype":"venue"
},
  "geometry": {"coordinates":[8.7204446793,50.1414718628],"type":"Point"}
}