{
  "type": "Feature",
  "properties": {
    "iso:country":"DE",
    "sg:address":"Schuhgasse 8",
    "sg:city":"Dippoldiswalde",
    "sg:phone":"+49 3504/612168",
    "sg:postcode":"01744",
    "sg:province":"Sachsen",
    "wof:name":"Rita Legler",
    "wof:placetype":"venue"
},
  "geometry": {"coordinates":[13.6681022644,50.8957748413],"type":"Point"}
}