{
  "type": "Feature",
  "properties": {
    "iso:country":"DE",
    "sg:address":"Lange Str. 72-76",
    "sg:city":"B\u00fcnde",
    "sg:phone":"+49 5223/4006",
    "sg:postcode":"32257",
    "sg:province":"Nordrhein-Westfalen",
    "wof:name":"Avr Abfall-verwertungs- Recycling Gmbh",
    "wof:placetype":"venue"
},
  "geometry": {"coordinates":[8.575626,52.206402],"type":"Point"}
}