{
  "type": "Feature",
  "properties": {
    "iso:country":"DE",
    "sg:address":"Pf\u00e4lzerstr. 17",
    "sg:city":"Denzlingen",
    "sg:phone":"+49 7666/5250",
    "sg:postcode":"79211",
    "sg:province":"Baden-W\u00fcrttemberg",
    "wof:name":"J\u00fcrgen Uhl Architekt",
    "wof:placetype":"venue"
},
  "geometry": {"coordinates":[7.901723,48.07],"type":"Point"}
}