{
  "type": "Feature",
  "properties": {
    "iso:country":"DE",
    "sg:address":"Hohe Str. 20",
    "sg:city":"Grefrath",
    "sg:phone":"+49 2158/3656",
    "sg:postcode":"47929",
    "sg:province":"Nordrhein-Westfalen",
    "wof:name":"Georgios Gogos",
    "wof:placetype":"venue"
},
  "geometry": {"coordinates":[6.3405990601,51.3359870911],"type":"Point"}
}