{
  "type": "Feature",
  "properties": {
    "iso:country":"DE",
    "sg:address":"Dorfstr. 52",
    "sg:city":"Dortmund",
    "sg:postcode":"44143",
    "sg:province":"Nordrhein-Westfalen",
    "wof:name":"H. H. Holding Gmbh",
    "wof:placetype":"venue"
},
  "geometry": {"coordinates":[7.523406,51.522472],"type":"Point"}
}