{
  "type": "Feature",
  "properties": {
    "iso:country":"DE",
    "sg:address":"Am Wetzelsberg 48",
    "sg:city":"Gorxheimertal",
    "sg:phone":"+49 6201/2072",
    "sg:postcode":"69517",
    "sg:province":"Hessen",
    "wof:name":"Dr. V. Gallandi Rechtsanwalt",
    "wof:placetype":"venue"
},
  "geometry": {"coordinates":[8.7237472534,49.5297393799],"type":"Point"}
}