{
  "type": "Feature",
  "properties": {
    "iso:country":"DE",
    "sg:address":"R\u00fcdesheimer Str. 19",
    "sg:city":"Roxheim",
    "sg:phone":"+49 671/27203",
    "sg:postcode":"55595",
    "sg:province":"Rheinland-Pfalz",
    "wof:name":"Partenheimer Fahrzeugbau Gmbh & Co. Kg",
    "wof:placetype":"venue"
},
  "geometry": {"coordinates":[7.808549881,49.8609199524],"type":"Point"}
}