{
  "type": "Feature",
  "properties": {
    "iso:country":"DE",
    "sg:address":"Gustav-Rau-Str. 14",
    "sg:city":"Bietigheim-Bissingen",
    "sg:phone":"+49 7142/56632",
    "sg:postcode":"74321",
    "sg:province":"Baden-W\u00fcrttemberg",
    "wof:name":"Fun Bike",
    "wof:placetype":"venue"
},
  "geometry": {"coordinates":[9.1479625702,48.9495582581],"type":"Point"}
}