{
  "type": "Feature",
  "properties": {
    "iso:country":"DE",
    "sg:address":"Tannenweg 1",
    "sg:city":"Erkelenz",
    "sg:phone":"+49 2431/5522",
    "sg:postcode":"41812",
    "sg:province":"Nordrhein-Westfalen",
    "wof:name":"E. Landmesser",
    "wof:placetype":"venue"
},
  "geometry": {"coordinates":[6.270715,51.102684],"type":"Point"}
}