{
  "type": "Feature",
  "properties": {
    "iso:country":"DE",
    "sg:address":"Seppel-Gl\u00fcckert-Passage 8",
    "sg:city":"Mainz",
    "sg:phone":"+49 6131/231604",
    "sg:postcode":"55116",
    "sg:province":"Rheinland-Pfalz",
    "wof:name":"Optik Bouffier Augenoptiker",
    "wof:placetype":"venue"
},
  "geometry": {"coordinates":[8.2713499069,49.9998092651],"type":"Point"}
}