{
  "type": "Feature",
  "properties": {
    "iso:country":"DE",
    "sg:address":"Merzenstr. 17",
    "sg:city":"Frankfurt",
    "sg:phone":"+49 6101/989605",
    "sg:postcode":"60437",
    "sg:province":"Hessen",
    "wof:name":"H. Ulrich",
    "wof:placetype":"venue"
},
  "geometry": {"coordinates":[8.694847,50.186314],"type":"Point"}
}