{
  "type": "Feature",
  "properties": {
    "iso:country":"DE",
    "sg:address":"Riebeckplatz 4",
    "sg:city":"Halle",
    "sg:phone":"+49 345/2035400",
    "sg:postcode":"06110",
    "sg:province":"Sachsen-Anhalt",
    "wof:name":"K. Leischke",
    "wof:placetype":"venue"
},
  "geometry": {"coordinates":[11.983433,51.476429],"type":"Point"}
}