{
  "type": "Feature",
  "properties": {
    "iso:country":"DE",
    "sg:address":"Heidsieker Heide 114",
    "sg:city":"Bielefeld",
    "sg:phone":"+49 5206/918380",
    "sg:postcode":"33739",
    "sg:province":"Nordrhein-Westfalen",
    "wof:name":"Bional Pharma Deutschland Gmbh & Co Kg",
    "wof:placetype":"venue"
},
  "geometry": {"coordinates":[8.5100326538,52.0866584778],"type":"Point"}
}