{
  "type": "Feature",
  "properties": {
    "iso:country":"DE",
    "sg:address":"Neue Baruther Str. 26",
    "sg:city":"Luckenwalde",
    "sg:phone":"+49 3371/610366",
    "sg:postcode":"14943",
    "sg:province":"Brandenburg",
    "wof:name":"Thomas Burczyk",
    "wof:placetype":"venue"
},
  "geometry": {"coordinates":[13.1794185638,52.086265564],"type":"Point"}
}