{
  "type": "Feature",
  "properties": {
    "iso:country":"DE",
    "sg:address":"Tiefensteiner Str. 396",
    "sg:city":"Idar-Oberstein",
    "sg:phone":"+49 6781/93550",
    "sg:postcode":"55743",
    "sg:province":"Rheinland-Pfalz",
    "wof:name":"Haag Verwaltungs Gmbh",
    "wof:placetype":"venue"
},
  "geometry": {"coordinates":[7.28915,49.727928],"type":"Point"}
}