{
  "type": "Feature",
  "properties": {
    "iso:country":"DE",
    "sg:address":"Frankfurter Allee 73 c",
    "sg:city":"Berlin",
    "sg:phone":"+49 30/2830200",
    "sg:postcode":"10247",
    "sg:province":"Berlin",
    "wof:name":"Tcb Reiseb\u00fcro Gmbh",
    "wof:placetype":"venue"
},
  "geometry": {"coordinates":[13.4683637619,52.5145645142],"type":"Point"}
}