{
  "type": "Feature",
  "properties": {
    "iso:country":"DE",
    "sg:address":"Pischekstr. 1",
    "sg:city":"Stuttgart",
    "sg:phone":"+49 711/241676",
    "sg:postcode":"70184",
    "sg:province":"Baden-W\u00fcrttemberg",
    "wof:name":"Kohler & Steinhauer Architekten",
    "wof:placetype":"venue"
},
  "geometry": {"coordinates":[9.19585,48.769413],"type":"Point"}
}