{
  "type": "Feature",
  "properties": {
    "iso:country":"DE",
    "sg:address":"Brunnenstr. 5",
    "sg:city":"Rieden",
    "sg:phone":"+49 2655/3947",
    "sg:postcode":"56745",
    "sg:province":"Rheinland-Pfalz",
    "wof:name":"Robert Nett Steinmetzbetrieb",
    "wof:placetype":"venue"
},
  "geometry": {"coordinates":[7.1797471046,50.3940544128],"type":"Point"}
}