{
  "type": "Feature",
  "properties": {
    "iso:country":"DE",
    "sg:address":"Wittenberger Str. 87",
    "sg:city":"Berlin",
    "sg:phone":"+49 30/93523120",
    "sg:postcode":"12689",
    "sg:province":"Berlin",
    "wof:name":"Holger Kott",
    "wof:placetype":"venue"
},
  "geometry": {"coordinates":[13.5720062256,52.5664787292],"type":"Point"}
}