{
  "type": "Feature",
  "properties": {
    "iso:country":"DE",
    "sg:address":"Kardinal-Wendel-Str. 16",
    "sg:city":"Speyer",
    "sg:phone":"+49 6232",
    "sg:postcode":"67346",
    "sg:province":"Rheinland-Pfalz",
    "wof:name":"Hadeko Wohnbau Gmbh In 67346 Speyer",
    "wof:placetype":"venue"
},
  "geometry": {"coordinates":[8.43459,49.304825],"type":"Point"}
}