{
  "type": "Feature",
  "properties": {
    "iso:country":"DE",
    "sg:address":"Zschortauer Str. 18",
    "sg:city":"Leipzig",
    "sg:phone":"+49 341/9608181",
    "sg:postcode":"04129",
    "sg:province":"Sachsen",
    "wof:name":"Crossi-croissantspezialit\u00e4ten Internationale Backwaren Und",
    "wof:placetype":"venue"
},
  "geometry": {"coordinates":[12.396402,51.373245],"type":"Point"}
}