{
  "type": "Feature",
  "properties": {
    "iso:country":"DE",
    "sg:address":"Otto-Hahn-Str. 19",
    "sg:city":"M\u00fcnster",
    "sg:phone":"+49 2534/65432",
    "sg:postcode":"48161",
    "sg:province":"Nordrhein-Westfalen",
    "wof:name":"Hdt Innenausbau Inh. Hans-dieter Thiemann",
    "wof:placetype":"venue"
},
  "geometry": {"coordinates":[7.532466,51.944687],"type":"Point"}
}