{
  "type": "Feature",
  "properties": {
    "iso:country":"DE",
    "sg:address":"K\u00fcllenhahner Str. 44",
    "sg:city":"Wuppertal",
    "sg:phone":"+49 4920/240541",
    "sg:postcode":"42349",
    "sg:province":"Nordrhein-Westfalen",
    "wof:name":"Buco Gmbh",
    "wof:placetype":"venue"
},
  "geometry": {"coordinates":[7.146865,51.229534],"type":"Point"}
}