{
  "type": "Feature",
  "properties": {
    "iso:country":"DE",
    "sg:address":"Brauhausstra\u00dfe 24",
    "sg:city":"Barby",
    "sg:phone":"+49 39298",
    "sg:postcode":"39249",
    "sg:province":"Sachsen-Anhalt",
    "wof:name":"Kunst- Und Seminarzentrum Barby",
    "wof:placetype":"venue"
},
  "geometry": {"coordinates":[11.886675,51.964241],"type":"Point"}
}