{
  "type": "Feature",
  "properties": {
    "iso:country":"DE",
    "sg:address":"Wiesenweg 3",
    "sg:city":"Remplin",
    "sg:phone":"+49 3994/633809",
    "sg:postcode":"17139",
    "sg:province":"Mecklenburg-Vorpommern",
    "wof:name":"D\u00fcring Bert Dachdeckerei",
    "wof:placetype":"venue"
},
  "geometry": {"coordinates":[12.696767,53.750992],"type":"Point"}
}