{
  "type": "Feature",
  "properties": {
    "iso:country":"DE",
    "sg:address":"Montgelasstr. 2",
    "sg:city":"M\u00fcnchen",
    "sg:phone":"+49 89/984934",
    "sg:postcode":"81679",
    "sg:province":"Bayern",
    "wof:name":"G\u00fcnther P\u00f6hner Steuerberater",
    "wof:placetype":"venue"
},
  "geometry": {"coordinates":[11.5994873047,48.1486778259],"type":"Point"}
}