{
  "type": "Feature",
  "properties": {
    "iso:country":"DE",
    "sg:address":"Durlacher Allee 1",
    "sg:city":"Walzbachtal",
    "sg:phone":"+49 7203/6125",
    "sg:postcode":"75045",
    "sg:province":"Baden-W\u00fcrttemberg",
    "wof:name":"Jelsi",
    "wof:placetype":"venue"
},
  "geometry": {"coordinates":[8.6029529572,49.0146789551],"type":"Point"}
}