{
  "type": "Feature",
  "properties": {
    "iso:country":"DE",
    "sg:address":"Wildeshauser Str. 53",
    "sg:city":"Gro\u00dfenkneten",
    "sg:phone":"+49 4435/1273",
    "sg:postcode":"26197",
    "sg:province":"Niedersachsen",
    "wof:name":"Hans Meiners",
    "wof:placetype":"venue"
},
  "geometry": {"coordinates":[8.22475,52.899021],"type":"Point"}
}