{
  "type": "Feature",
  "properties": {
    "iso:country":"DE",
    "sg:address":"Eschenbreite 55",
    "sg:city":"Haldensleben",
    "sg:phone":"+49 3904/43176",
    "sg:postcode":"39340",
    "sg:province":"Sachsen-Anhalt",
    "wof:name":"Holger Schindler",
    "wof:placetype":"venue"
},
  "geometry": {"coordinates":[11.3818855286,52.2802047729],"type":"Point"}
}