{
  "type": "Feature",
  "properties": {
    "iso:country":"DE",
    "sg:address":"Geisseestr. 89",
    "sg:city":"N\u00fcrnberg",
    "sg:phone":"+49 911/652545",
    "sg:postcode":"90439",
    "sg:province":"Bayern",
    "wof:name":"Bahr Baumarkt",
    "wof:placetype":"venue"
},
  "geometry": {"coordinates":[11.038458,49.434097],"type":"Point"}
}