{
  "type": "Feature",
  "properties": {
    "iso:country":"DE",
    "sg:address":"Vo\u00dfstr. 56-62",
    "sg:city":"Goch",
    "sg:phone":"+49 2823/6095",
    "sg:postcode":"47574",
    "sg:province":"Nordrhein-Westfalen",
    "wof:name":"Gocher Kaufhaus Gmbh",
    "wof:placetype":"venue"
},
  "geometry": {"coordinates":[6.158829,51.67461],"type":"Point"}
}