{
  "type": "Feature",
  "properties": {
    "iso:country":"DE",
    "sg:address":"Waldhausenstr. 1 A",
    "sg:city":"Hannover",
    "sg:phone":"+49 511/8444200",
    "sg:postcode":"30519",
    "sg:province":"Niedersachsen",
    "wof:name":"Regula Marquardsen Praxis F Ergotherapie",
    "wof:placetype":"venue"
},
  "geometry": {"coordinates":[9.761545,52.346664],"type":"Point"}
}