{
  "type": "Feature",
  "properties": {
    "iso:country":"DE",
    "sg:address":"Schopenhauerstr. 20",
    "sg:city":"Heusenstamm",
    "sg:phone":"+49 6104/63349",
    "sg:postcode":"63150",
    "sg:province":"Hessen",
    "wof:name":"Hungaro Technik Consulting Und Service Gmbh",
    "wof:placetype":"venue"
},
  "geometry": {"coordinates":[8.793386,50.053455],"type":"Point"}
}