{
  "type": "Feature",
  "properties": {
    "iso:country":"DE",
    "sg:address":"Industriestr. 4",
    "sg:city":"Spiegelau",
    "sg:phone":"+49 8553/6966",
    "sg:postcode":"94518",
    "sg:province":"Bayern",
    "wof:name":"Friedl & Harant Metallbau Gmbh",
    "wof:placetype":"venue"
},
  "geometry": {"coordinates":[13.335113,48.888794],"type":"Point"}
}