{
  "type": "Feature",
  "properties": {
    "iso:country":"DE",
    "sg:address":"Waldstr. 49",
    "sg:city":"Steinbach",
    "sg:phone":"+49 6171/97630",
    "sg:postcode":"61449",
    "sg:province":"Hessen",
    "wof:name":"Sport- Und Fitne\u00dfpark Gmbh",
    "wof:placetype":"venue"
},
  "geometry": {"coordinates":[8.5641555786,50.1755027771],"type":"Point"}
}