{
  "type": "Feature",
  "properties": {
    "iso:country":"DE",
    "sg:address":"Waldstr. 4",
    "sg:city":"Birlenbach",
    "sg:postcode":"65626",
    "sg:province":"Rheinland-Pfalz",
    "wof:name":"Martin L\u00f6ber",
    "wof:placetype":"venue"
},
  "geometry": {"coordinates":[7.9999070168,50.3575325012],"type":"Point"}
}