{
  "type": "Feature",
  "properties": {
    "iso:country":"DE",
    "sg:address":"Tegernseer Landstr. 2",
    "sg:city":"Sauerlach",
    "sg:phone":"+49 8104/830",
    "sg:postcode":"82054",
    "sg:province":"Bayern",
    "wof:name":"Hotel Sauerlacher Post Verwaltungs Gmbh",
    "wof:placetype":"venue"
},
  "geometry": {"coordinates":[11.6537637711,47.971572876],"type":"Point"}
}