{
  "type": "Feature",
  "properties": {
    "iso:country":"DE",
    "sg:address":"Am Birkenhain 7",
    "sg:city":"Neustadt",
    "sg:phone":"+49 9568/5714",
    "sg:postcode":"96465",
    "sg:province":"Bayern",
    "wof:name":"Siegfried Faber",
    "wof:placetype":"venue"
},
  "geometry": {"coordinates":[11.0988693237,50.3215293884],"type":"Point"}
}