{
  "type": "Feature",
  "properties": {
    "iso:country":"DE",
    "sg:address":"Wieselweg 3",
    "sg:city":"Haar",
    "sg:phone":"+49 89/4604269",
    "sg:postcode":"85540",
    "sg:province":"Bayern",
    "wof:name":"Papeterie Bathelt Gmbh",
    "wof:placetype":"venue"
},
  "geometry": {"coordinates":[11.7169866562,48.1067237854],"type":"Point"}
}