{
  "type": "Feature",
  "properties": {
    "iso:country":"DE",
    "sg:address":"Buttermarkt 39",
    "sg:city":"K\u00f6ln",
    "sg:phone":"+49 221/2577802",
    "sg:postcode":"50667",
    "sg:province":"Nordrhein-Westfalen",
    "wof:name":"Biermuseum",
    "wof:placetype":"venue"
},
  "geometry": {"coordinates":[6.9620308876,50.9381561279],"type":"Point"}
}