{
  "type": "Feature",
  "properties": {
    "iso:country":"DE",
    "sg:address":"R\u00fcschenweg 63",
    "sg:city":"Verl",
    "sg:phone":"+49 5246/3584",
    "sg:postcode":"33415",
    "sg:province":"Nordrhein-Westfalen",
    "wof:name":"Berthold Gro\u00dfe-r\u00fcschkamp",
    "wof:placetype":"venue"
},
  "geometry": {"coordinates":[8.534464,51.905888],"type":"Point"}
}