{
  "type": "Feature",
  "properties": {
    "iso:country":"DE",
    "sg:address":"Matthias-Bauer-Ring 30",
    "sg:city":"Hohensch\u00e4ftlarn",
    "sg:phone":"+49 8178/4246",
    "sg:postcode":"82069",
    "sg:province":"Bayern",
    "wof:name":"Dr. Helmut Schneidawind St\u00e4dt. Vet. Dir.",
    "wof:placetype":"venue"
},
  "geometry": {"coordinates":[11.4553785324,47.9862251282],"type":"Point"}
}