{
  "type": "Feature",
  "properties": {
    "iso:country":"DE",
    "sg:address":"Grenzstr. 7",
    "sg:city":"Fichtenau",
    "sg:phone":"+49 7962/447",
    "sg:postcode":"74579",
    "sg:province":"Baden-W\u00fcrttemberg",
    "wof:name":"Ernst Neu",
    "wof:placetype":"venue"
},
  "geometry": {"coordinates":[10.2191476822,49.0946540833],"type":"Point"}
}