{
  "type": "Feature",
  "properties": {
    "iso:country":"DE",
    "sg:address":"Oheweg 5",
    "sg:city":"Hamb\u00fchren",
    "sg:phone":"+49 5143/93350",
    "sg:postcode":"29313",
    "sg:province":"Niedersachsen",
    "wof:name":"Aring Planungsgesellschaft Mbh",
    "wof:placetype":"venue"
},
  "geometry": {"coordinates":[9.930409,52.66074],"type":"Point"}
}