{
  "type": "Feature",
  "properties": {
    "iso:country":"DE",
    "sg:address":"Neschener Str. 3",
    "sg:city":"Neustadt",
    "sg:phone":"+49 2683/98650",
    "sg:postcode":"53577",
    "sg:province":"Rheinland-Pfalz",
    "wof:name":"Jamann & Co.",
    "wof:placetype":"venue"
},
  "geometry": {"coordinates":[7.4414258003,50.5991973877],"type":"Point"}
}