{
  "type": "Feature",
  "properties": {
    "iso:country":"DE",
    "sg:address":"Marktstr. 9",
    "sg:city":"Grabow",
    "sg:postcode":"19300",
    "sg:province":"Mecklenburg-Vorpommern",
    "wof:name":"Salon",
    "wof:placetype":"venue"
},
  "geometry": {"coordinates":[11.563705,53.279228],"type":"Point"}
}