{
  "type": "Feature",
  "properties": {
    "iso:country":"DE",
    "sg:address":"Br\u00fcckes 65",
    "sg:city":"Bad Kreuznach",
    "sg:postcode":"55545",
    "sg:province":"Rheinland-Pfalz",
    "wof:name":"Kreuznacher Maschinenhandel E. K.",
    "wof:placetype":"venue"
},
  "geometry": {"coordinates":[7.8675570488,49.8559875488],"type":"Point"}
}