{
  "type": "Feature",
  "properties": {
    "iso:country":"DE",
    "sg:address":"Postfach 3",
    "sg:city":"Kyritz",
    "sg:postcode":"16856",
    "sg:province":"Brandenburg",
    "wof:name":"Dr. Hassfeld",
    "wof:placetype":"venue"
},
  "geometry": {"coordinates":[12.39763,52.940689],"type":"Point"}
}