{
  "type": "Feature",
  "properties": {
    "iso:country":"DE",
    "sg:address":"Paulinenstr. 8",
    "sg:city":"Detmold",
    "sg:phone":"+49 4952/3161760",
    "sg:postcode":"32756",
    "sg:province":"Nordrhein-Westfalen",
    "wof:name":"Beyer Umz\u00dcge Gmbh",
    "wof:placetype":"venue"
},
  "geometry": {"coordinates":[8.8759965897,51.9332237244],"type":"Point"}
}