{
  "type": "Feature",
  "properties": {
    "iso:country":"DE",
    "sg:address":"Gro\u00dfer Br\u00fchl 12-14",
    "sg:city":"Eisenberg",
    "sg:phone":"+49 36691/42434",
    "sg:postcode":"07607",
    "sg:province":"Th\u00fcringen",
    "wof:name":"Carl Daum",
    "wof:placetype":"venue"
},
  "geometry": {"coordinates":[11.901052,50.967537],"type":"Point"}
}