{
  "type": "Feature",
  "properties": {
    "iso:country":"DE",
    "sg:address":"Feuerbachstr. 70",
    "sg:city":"Berlin",
    "sg:phone":"+49 30/8559466",
    "sg:postcode":"12163",
    "sg:province":"Berlin",
    "wof:name":"Drogista Drogerie Gmbh",
    "wof:placetype":"venue"
},
  "geometry": {"coordinates":[13.339809,52.464466],"type":"Point"}
}