{
  "type": "Feature",
  "properties": {
    "iso:country":"DE",
    "sg:address":"Reiherstr. 19/6",
    "sg:city":"Aalen",
    "sg:phone":"+49 7361/970483",
    "sg:postcode":"73434",
    "sg:province":"Baden-W\u00fcrttemberg",
    "wof:name":"Susann Heigl-k\u00f6d\u00fctz Heilpraktikerin",
    "wof:placetype":"venue"
},
  "geometry": {"coordinates":[10.0605602264,48.8307571411],"type":"Point"}
}