{
  "type": "Feature",
  "properties": {
    "iso:country":"DE",
    "sg:address":"Koppelweg 2",
    "sg:city":"Wiehl",
    "sg:phone":"+49 2262/701295",
    "sg:postcode":"51674",
    "sg:province":"Nordrhein-Westfalen",
    "wof:name":"G. Bartesch",
    "wof:placetype":"venue"
},
  "geometry": {"coordinates":[7.450644,50.943115],"type":"Point"}
}