{
  "type": "Feature",
  "properties": {
    "iso:country":"DE",
    "sg:address":"Haldernerstr.2",
    "sg:city":"Hamminklen",
    "sg:phone":"+49 2857/901435",
    "sg:postcode":"46499",
    "sg:province":"Nordrhein-Westfalen",
    "wof:name":"@lpha.com Gbr",
    "wof:placetype":"venue"
},
  "geometry": {"coordinates":[6.590165,51.728859],"type":"Point"}
}