{
  "type": "Feature",
  "properties": {
    "iso:country":"DE",
    "sg:address":"Lilienthalstr. 2",
    "sg:city":"Korntal-M\u00fcnchingen",
    "sg:postcode":"70825",
    "sg:province":"Baden-W\u00fcrttemberg",
    "wof:name":"Thales Atm Navigation Gmbh",
    "wof:placetype":"venue"
},
  "geometry": {"coordinates":[9.110231,48.825558],"type":"Point"}
}