{
  "type": "Feature",
  "properties": {
    "iso:country":"DE",
    "sg:address":"Gabelentzstr. 6",
    "sg:city":"Altenburg",
    "sg:phone":"+49 3447/500807",
    "sg:postcode":"04600",
    "sg:province":"Th\u00fcringen",
    "wof:name":"Frank-olaf Sch\u00fctze",
    "wof:placetype":"venue"
},
  "geometry": {"coordinates":[12.443977356,50.9923057556],"type":"Point"}
}