{
  "type": "Feature",
  "properties": {
    "iso:country":"DE",
    "sg:address":"Bahnhofstr. 27",
    "sg:city":"Buchloe",
    "sg:phone":"+49 8241/90006",
    "sg:postcode":"86807",
    "sg:province":"Bayern",
    "wof:name":"Nkd Vertriebsges. Mbh",
    "wof:placetype":"venue"
},
  "geometry": {"coordinates":[10.7221698761,48.0352935791],"type":"Point"}
}