{
  "type": "Feature",
  "properties": {
    "iso:country":"DE",
    "sg:address":"Groner Allee 32",
    "sg:city":"Ibbenb\u00fcren",
    "sg:phone":"+49 5451/94320",
    "sg:postcode":"49477",
    "sg:province":"Nordrhein-Westfalen",
    "wof:name":"Johannes Lewe Architekt",
    "wof:placetype":"venue"
},
  "geometry": {"coordinates":[7.711627,52.27129],"type":"Point"}
}