{
  "type": "Feature",
  "properties": {
    "iso:country":"DE",
    "sg:address":"In der Kirchhalde 2",
    "sg:city":"Maulburg",
    "sg:phone":"+49 7622/9396",
    "sg:postcode":"79689",
    "sg:province":"Baden-W\u00fcrttemberg",
    "wof:name":"Friedrich Itzin Ingenieur",
    "wof:placetype":"venue"
},
  "geometry": {"coordinates":[7.7751660347,47.6387062073],"type":"Point"}
}