{
  "type": "Feature",
  "properties": {
    "iso:country":"DE",
    "sg:address":"Weygangstr. 34",
    "sg:city":"\u00d6hringen",
    "sg:phone":"+49 7941/2842",
    "sg:postcode":"74613",
    "sg:province":"Baden-W\u00fcrttemberg",
    "wof:name":"Otto Sahm Steuerberater",
    "wof:placetype":"venue"
},
  "geometry": {"coordinates":[9.5098905563,49.1998596191],"type":"Point"}
}