{
  "type": "Feature",
  "properties": {
    "iso:country":"DE",
    "sg:address":"Hans-Heinrich-Ehrler-Platz 23",
    "sg:city":"Bad Mergentheim",
    "sg:phone":"+49 7931/561500",
    "sg:postcode":"97980",
    "sg:province":"Baden-W\u00fcrttemberg",
    "wof:name":"A. Markert",
    "wof:placetype":"venue"
},
  "geometry": {"coordinates":[9.7732229233,49.4899978638],"type":"Point"}
}