{
  "type": "Feature",
  "properties": {
    "iso:country":"DE",
    "sg:address":"Zur Dorfeiche 15",
    "sg:city":"Undeloh",
    "sg:phone":"+49 4189/205",
    "sg:postcode":"21274",
    "sg:province":"Niedersachsen",
    "wof:name":"Margot Dempwolf",
    "wof:placetype":"venue"
},
  "geometry": {"coordinates":[9.977268219,53.1977615356],"type":"Point"}
}