{
  "type": "Feature",
  "properties": {
    "iso:country":"DE",
    "sg:address":"Im Wiesengrund 20",
    "sg:city":"Rottenburg",
    "sg:phone":"+49 7457/5252",
    "sg:postcode":"72108",
    "sg:province":"Baden-W\u00fcrttemberg",
    "wof:name":"Heinrich Et Par Gmbh",
    "wof:placetype":"venue"
},
  "geometry": {"coordinates":[8.8806934357,48.5074272156],"type":"Point"}
}