{
  "type": "Feature",
  "properties": {
    "iso:country":"DE",
    "sg:address":"Thadd\u00e4us-Eck-Str. 62",
    "sg:city":"M\u00fcnchen",
    "sg:phone":"+49 89/8115933",
    "sg:postcode":"81247",
    "sg:province":"Bayern",
    "wof:name":"Dr. Med. Ekkehard Weiss Arzt F\u00fcr Innere Medizin",
    "wof:placetype":"venue"
},
  "geometry": {"coordinates":[11.4542970657,48.1731262207],"type":"Point"}
}