{
  "type": "Feature",
  "properties": {
    "iso:country":"DE",
    "sg:address":"Scheergasse 4",
    "sg:city":"K\u00fcssaberg",
    "sg:phone":"+49 7741/3621",
    "sg:postcode":"79790",
    "sg:province":"Baden-W\u00fcrttemberg",
    "wof:name":"Bruno Roder",
    "wof:placetype":"venue"
},
  "geometry": {"coordinates":[8.324008,47.596306],"type":"Point"}
}