{
  "type": "Feature",
  "properties": {
    "iso:country":"DE",
    "sg:address":"Dorfstr. 33",
    "sg:city":"Kossebau",
    "sg:postcode":"39606",
    "sg:province":"Sachsen-Anhalt",
    "wof:name":"Zareck Haus- Und Wohnungsbau Gmbh",
    "wof:placetype":"venue"
},
  "geometry": {"coordinates":[11.5626983643,52.8149986267],"type":"Point"}
}