{
  "type": "Feature",
  "properties": {
    "iso:country":"DE",
    "sg:address":"Augustastr. 4",
    "sg:city":"Grieben",
    "sg:phone":"+49 39362/81342",
    "sg:postcode":"39517",
    "sg:province":"Sachsen-Anhalt",
    "wof:name":"Hans Konrad Strassenbau Gmbh",
    "wof:placetype":"venue"
},
  "geometry": {"coordinates":[11.95856,52.434921],"type":"Point"}
}