{
  "type": "Feature",
  "properties": {
    "iso:country":"DE",
    "sg:address":"Liselotte-Herrmann-Str. 21",
    "sg:city":"Bergholz-Rehbr\u00fccke",
    "sg:phone":"+49 33200/81546",
    "sg:postcode":"14558",
    "sg:province":"Brandenburg",
    "wof:name":"Hartmut Kuler Architekt",
    "wof:placetype":"venue"
},
  "geometry": {"coordinates":[13.107043,52.345997],"type":"Point"}
}