{
  "type": "Feature",
  "properties": {
    "iso:country":"DE",
    "sg:address":"Neust\u00e4dter Str. 4",
    "sg:city":"Parkstein",
    "sg:phone":"+49 9602/615541",
    "sg:postcode":"92711",
    "sg:province":"Bayern",
    "wof:name":"Richard Kick",
    "wof:placetype":"venue"
},
  "geometry": {"coordinates":[12.072419,49.732845],"type":"Point"}
}