{
  "type": "Feature",
  "properties": {
    "iso:country":"DE",
    "sg:address":"K\u00f6nig-Konrad-Str. 19",
    "sg:city":"Villmaer",
    "sg:postcode":"65606",
    "sg:province":"Hessen",
    "wof:name":"Bibbi\u00b4s Fahrschule",
    "wof:placetype":"venue"
},
  "geometry": {"coordinates":[8.1895198822,50.3909873962],"type":"Point"}
}