{
  "type": "Feature",
  "properties": {
    "iso:country":"DE",
    "sg:address":"Bergstr. 8",
    "sg:city":"Freilassing",
    "sg:phone":"+49 8654/64529",
    "sg:postcode":"83395",
    "sg:province":"Bayern",
    "wof:name":"Bernd Hofmann",
    "wof:placetype":"venue"
},
  "geometry": {"coordinates":[12.96182,47.843014],"type":"Point"}
}