{
  "type": "Feature",
  "properties": {
    "iso:country":"DE",
    "sg:address":"Robert-Friese- Strasse 3::",
    "sg:city":"Hermsdorf/Th\u00fcringen",
    "sg:phone":"+49 36601/81529",
    "sg:postcode":"07629",
    "sg:province":"Th\u00fcringen",
    "wof:name":"Via Electronic Gmbh",
    "wof:placetype":"venue"
},
  "geometry": {"coordinates":[11.855701,50.897533],"type":"Point"}
}