{
  "type": "Feature",
  "properties": {
    "iso:country":"DE",
    "sg:address":"Rothwestenerstr. 5",
    "sg:city":"Fuldatal",
    "sg:postcode":"34233",
    "sg:province":"Hessen",
    "wof:name":"Orthcom",
    "wof:placetype":"venue"
},
  "geometry": {"coordinates":[9.52606,51.350334],"type":"Point"}
}