{
  "type": "Feature",
  "properties": {
    "iso:country":"DE",
    "sg:address":"Ro\u00dfmarktstr. 29-31",
    "sg:city":"Leipzig",
    "sg:phone":"+49 341/4774693",
    "sg:postcode":"04177",
    "sg:province":"Sachsen",
    "wof:name":"A. Hinsch & Co. Gmbh",
    "wof:placetype":"venue"
},
  "geometry": {"coordinates":[12.3321847916,51.3384017944],"type":"Point"}
}