{
  "type": "Feature",
  "properties": {
    "iso:country":"DE",
    "sg:address":"Dessauerstr. 34",
    "sg:city":"Berlin",
    "sg:phone":"+49 30/76704604",
    "sg:postcode":"12249",
    "sg:province":"Berlin",
    "wof:name":"J\u00fcrgen Dymke Generalbauunternehmen Gmbh",
    "wof:placetype":"venue"
},
  "geometry": {"coordinates":[13.3406581879,52.4268875122],"type":"Point"}
}