{
  "type": "Feature",
  "properties": {
    "iso:country":"DE",
    "sg:address":"Talstr. 25",
    "sg:city":"Friedland",
    "sg:phone":"+49 5504/1293",
    "sg:postcode":"37133",
    "sg:province":"Niedersachsen",
    "wof:name":"Kurt B\u00f6ning",
    "wof:placetype":"venue"
},
  "geometry": {"coordinates":[9.976532,51.409557],"type":"Point"}
}