{
  "type": "Feature",
  "properties": {
    "iso:country":"DE",
    "sg:address":"Erkelenzer Str. 4",
    "sg:city":"D\u00fcsseldorf",
    "sg:phone":"+49 211/154520",
    "sg:postcode":"40223",
    "sg:province":"Nordrhein-Westfalen",
    "wof:name":"K. S\u00e4ger",
    "wof:placetype":"venue"
},
  "geometry": {"coordinates":[6.766429,51.193649],"type":"Point"}
}