{
  "type": "Feature",
  "properties": {
    "iso:country":"DE",
    "sg:address":"K\u00e4stleinsm\u00fchlenstr.",
    "sg:city":"Treuchtlingen",
    "sg:phone":"+49 9142/967810",
    "sg:postcode":"91757",
    "sg:province":"Bayern",
    "wof:name":"Tennishalle",
    "wof:placetype":"venue"
},
  "geometry": {"coordinates":[10.917714119,48.9622840881],"type":"Point"}
}