{
  "type": "Feature",
  "properties": {
    "iso:country":"DE",
    "sg:address":"Teichweg 6",
    "sg:city":"Jesteburg",
    "sg:phone":"+49 4183/3333",
    "sg:postcode":"21266",
    "sg:province":"Niedersachsen",
    "wof:name":"Werner Meyer",
    "wof:placetype":"venue"
},
  "geometry": {"coordinates":[9.95204,53.307472],"type":"Point"}
}