{
  "type": "Feature",
  "properties": {
    "iso:country":"DE",
    "sg:address":"Quellenstr. 150",
    "sg:city":"Remagen",
    "sg:phone":"+49 2642/44514",
    "sg:postcode":"53424",
    "sg:province":"Rheinland-Pfalz",
    "wof:name":"Hans-friedrich Ueberbach",
    "wof:placetype":"venue"
},
  "geometry": {"coordinates":[7.2252960205,50.579334259],"type":"Point"}
}