{
  "type": "Feature",
  "properties": {
    "iso:country":"DE",
    "sg:address":"Unterer Kaulberg 13",
    "sg:city":"Bamberg",
    "sg:phone":"+49 951/52610",
    "sg:postcode":"96049",
    "sg:province":"Bayern",
    "wof:name":"Optimal",
    "wof:placetype":"venue"
},
  "geometry": {"coordinates":[10.88258,49.88871],"type":"Point"}
}