{
  "type": "Feature",
  "properties": {
    "iso:country":"DE",
    "sg:address":"Wiesecker Weg 18",
    "sg:city":"Gie\u00dfen",
    "sg:phone":"+49 641/932520",
    "sg:postcode":"35396",
    "sg:province":"Hessen",
    "wof:name":"Werner Gr\u00f6lz",
    "wof:placetype":"venue"
},
  "geometry": {"coordinates":[8.6848869324,50.5960121155],"type":"Point"}
}