{
  "type": "Feature",
  "properties": {
    "iso:country":"DE",
    "sg:address":"Rebenring 2",
    "sg:city":"Braunschweig",
    "sg:postcode":"38106",
    "sg:province":"Niedersachsen",
    "wof:name":"Verein T\u00fcrkischer Arbeitnehmer In Braunschweig Und",
    "wof:placetype":"venue"
},
  "geometry": {"coordinates":[10.5220518112,52.2753219604],"type":"Point"}
}