{
  "type": "Feature",
  "properties": {
    "iso:country":"DE",
    "sg:address":"Hauptstr. 40",
    "sg:city":"Schwarzenbach a Wald",
    "sg:phone":"+49 9289/236",
    "sg:postcode":"95131",
    "sg:province":"Bayern",
    "wof:name":"G. Rank",
    "wof:placetype":"venue"
},
  "geometry": {"coordinates":[11.6221809387,50.2829170227],"type":"Point"}
}