{
  "type": "Feature",
  "properties": {
    "iso:country":"DE",
    "sg:address":"Am Wammesknopf 1",
    "sg:city":"Stuttgart",
    "sg:phone":"+49 711/802378",
    "sg:postcode":"70439",
    "sg:province":"Baden-W\u00fcrttemberg",
    "wof:name":"Walter Scheck Gmbh",
    "wof:placetype":"venue"
},
  "geometry": {"coordinates":[9.148955,48.853584],"type":"Point"}
}