{
  "type": "Feature",
  "properties": {
    "iso:country":"DE",
    "sg:address":"Am Pantaleonsberg 3",
    "sg:city":"K\u00f6ln",
    "sg:phone":"+49 221/3604945",
    "sg:postcode":"50676",
    "sg:province":"Nordrhein-Westfalen",
    "wof:name":"Thomas Lieser",
    "wof:placetype":"venue"
},
  "geometry": {"coordinates":[6.9471530914,50.9280395508],"type":"Point"}
}