{
  "type": "Feature",
  "properties": {
    "iso:country":"DE",
    "sg:address":"Tulpenstr. 4",
    "sg:city":"Allendorf/Eder",
    "sg:phone":"+49 4906/452",
    "sg:postcode":"35108",
    "sg:province":"Hessen",
    "wof:name":"Kratzert Werbung,druckgestaltung,internet,service",
    "wof:placetype":"venue"
},
  "geometry": {"coordinates":[8.663005,51.020142],"type":"Point"}
}