{
  "type": "Feature",
  "properties": {
    "iso:country":"DE",
    "sg:address":"Sommerbergstr. 3",
    "sg:city":"Lambrecht",
    "sg:phone":"+49 6325/1810",
    "sg:postcode":"67466",
    "sg:province":"Rheinland-Pfalz",
    "wof:name":"Verbandsgemeindebauamt Rathaus",
    "wof:placetype":"venue"
},
  "geometry": {"coordinates":[8.073434,49.373508],"type":"Point"}
}