{
  "type": "Feature",
  "properties": {
    "iso:country":"DE",
    "sg:address":"95126",
    "sg:city":"Schwarzenbach a d Saale",
    "sg:phone":"+49 9284/93349",
    "sg:postcode":"95126",
    "sg:province":"Bayern",
    "wof:name":"St\u00e4dt. Hallenbad",
    "wof:placetype":"venue"
},
  "geometry": {"coordinates":[11.9368495941,50.2030792236],"type":"Point"}
}