{
  "type": "Feature",
  "properties": {
    "iso:country":"DE",
    "sg:address":"Altenberger Str. 45",
    "sg:city":"Dippoldiswalde",
    "sg:phone":"+49 3504/614495",
    "sg:postcode":"01744",
    "sg:province":"Sachsen",
    "wof:name":"Gustav Schuster",
    "wof:placetype":"venue"
},
  "geometry": {"coordinates":[13.6674432755,50.8925018311],"type":"Point"}
}