{
  "type": "Feature",
  "properties": {
    "iso:country":"DE",
    "sg:address":"Hauptstr. 119",
    "sg:city":"Lemf\u00f6rde",
    "sg:phone":"+49 5443/91060",
    "sg:postcode":"49448",
    "sg:province":"Niedersachsen",
    "wof:name":"Eberhard Langer",
    "wof:placetype":"venue"
},
  "geometry": {"coordinates":[8.3763723373,52.4646835327],"type":"Point"}
}