{
  "type": "Feature",
  "properties": {
    "iso:country":"DE",
    "sg:address":"Zum Hakenmoor 8",
    "sg:city":"Bahrenborstel",
    "sg:postcode":"27245",
    "sg:province":"Niedersachsen",
    "wof:name":"Rolf Scharinghausen",
    "wof:placetype":"venue"
},
  "geometry": {"coordinates":[8.738459,52.558174],"type":"Point"}
}