{
  "type": "Feature",
  "properties": {
    "iso:country":"DE",
    "sg:address":"Beuelsweg 7",
    "sg:city":"K\u00f6ln",
    "sg:phone":"+49 221/7201825",
    "sg:postcode":"50733",
    "sg:province":"Nordrhein-Westfalen",
    "wof:name":"Alois Slatinschek",
    "wof:placetype":"venue"
},
  "geometry": {"coordinates":[6.9594922066,50.9624938965],"type":"Point"}
}