{
  "type": "Feature",
  "properties": {
    "iso:country":"DE",
    "sg:address":"H\u00fcttenstr. 13",
    "sg:city":"D\u00fcsseldorf",
    "sg:phone":"+49 211/8632630",
    "sg:postcode":"40215",
    "sg:province":"Nordrhein-Westfalen",
    "wof:name":"Bbw Family-haus Verwaltungs Gmbh",
    "wof:placetype":"venue"
},
  "geometry": {"coordinates":[6.782020092,51.2175559998],"type":"Point"}
}