{
  "type": "Feature",
  "properties": {
    "iso:country":"DE",
    "sg:address":"Alpe Eck",
    "sg:city":"Ofterschwang",
    "sg:phone":"+49 8321/4061",
    "sg:postcode":"87527",
    "sg:province":"Bayern",
    "wof:name":"Allg\u00e4uer Berghof Reichert & Neusch Gmbh",
    "wof:placetype":"venue"
},
  "geometry": {"coordinates":[10.2215690613,47.5075836182],"type":"Point"}
}