{
  "type": "Feature",
  "properties": {
    "iso:country":"DE",
    "sg:address":"Friedrich-Ebert-Str. 16-18",
    "sg:city":"Datteln",
    "sg:phone":"+49 2363/31607",
    "sg:postcode":"45711",
    "sg:province":"Nordrhein-Westfalen",
    "wof:name":"Vestia-wp Gmbh",
    "wof:placetype":"venue"
},
  "geometry": {"coordinates":[7.3366007805,51.6518135071],"type":"Point"}
}