{
  "type": "Feature",
  "properties": {
    "iso:country":"DE",
    "sg:address":"Hohenzollernstr. 67",
    "sg:city":"Pforzheim",
    "sg:phone":"+49 7231/358919",
    "sg:postcode":"75177",
    "sg:province":"Baden-W\u00fcrttemberg",
    "wof:name":"Nordstadt",
    "wof:placetype":"venue"
},
  "geometry": {"coordinates":[8.7025337219,48.8968811035],"type":"Point"}
}