{
  "type": "Feature",
  "properties": {
    "iso:country":"DE",
    "sg:address":"Osterbekstr. 90a",
    "sg:city":"Hamburg",
    "sg:phone":"+49 40/28803120",
    "sg:postcode":"22083",
    "sg:province":"Hamburg",
    "wof:name":"Bdl Internet Gmbh",
    "wof:placetype":"venue"
},
  "geometry": {"coordinates":[10.029127121,53.5834274292],"type":"Point"}
}