{
  "type": "Feature",
  "properties": {
    "iso:country":"DE",
    "sg:address":"Siegelsdorfer Str. 18",
    "sg:city":"Veitsbronn",
    "sg:phone":"+49 911/751718",
    "sg:postcode":"90587",
    "sg:province":"Bayern",
    "wof:name":"Georg Greller",
    "wof:placetype":"venue"
},
  "geometry": {"coordinates":[10.880995,49.511501],"type":"Point"}
}