{
  "type": "Feature",
  "properties": {
    "iso:country":"DE",
    "sg:address":"Kamenzer Bogen",
    "sg:city":"Hoyerswerda",
    "sg:postcode":"02977",
    "sg:province":"Sachsen",
    "wof:name":"Globus",
    "wof:placetype":"venue"
},
  "geometry": {"coordinates":[14.235042572,51.4241218567],"type":"Point"}
}