{
  "type": "Feature",
  "properties": {
    "iso:country":"DE",
    "sg:address":"Neuwerk 14",
    "sg:city":"Merzenich",
    "sg:phone":"+49 2421/770234",
    "sg:postcode":"52399",
    "sg:province":"Nordrhein-Westfalen",
    "wof:name":"Wilhelm Stoffels",
    "wof:placetype":"venue"
},
  "geometry": {"coordinates":[6.545996,50.809841],"type":"Point"}
}