{
  "type": "Feature",
  "properties": {
    "iso:country":"DE",
    "sg:address":"Kortumstr. 35",
    "sg:city":"Bochum",
    "sg:phone":"+49 234/9160532",
    "sg:postcode":"44787",
    "sg:province":"Nordrhein-Westfalen",
    "wof:name":"Henry Fashion Concept Gmbh",
    "wof:placetype":"venue"
},
  "geometry": {"coordinates":[7.216651,51.478123],"type":"Point"}
}