{
  "type": "Feature",
  "properties": {
    "iso:country":"DE",
    "sg:address":"Severinstr 93-95a",
    "sg:city":"K\u00f6ln",
    "sg:phone":"+49 221/8017577",
    "sg:postcode":"50678",
    "sg:province":"Nordrhein-Westfalen",
    "wof:name":"Condortech",
    "wof:placetype":"venue"
},
  "geometry": {"coordinates":[6.958019,50.925991],"type":"Point"}
}