{
  "type": "Feature",
  "properties": {
    "iso:country":"DE",
    "sg:address":"M\u00e4hlersbeck 81",
    "sg:city":"Wuppertal",
    "sg:phone":"+49 202/2641111",
    "sg:postcode":"42279",
    "sg:province":"Nordrhein-Westfalen",
    "wof:name":"Dresen Und Busenbecker",
    "wof:placetype":"venue"
},
  "geometry": {"coordinates":[7.23081,51.293201],"type":"Point"}
}