{
  "type": "Feature",
  "properties": {
    "iso:country":"DE",
    "sg:address":"Kr\u00fcgerstr. 14",
    "sg:city":"S\u00fcdlohn",
    "sg:phone":"+49 2862/6237",
    "sg:postcode":"46354",
    "sg:province":"Nordrhein-Westfalen",
    "wof:name":"Ev. Pfarramt Oeding",
    "wof:placetype":"venue"
},
  "geometry": {"coordinates":[6.8132009506,51.9327316284],"type":"Point"}
}