{
  "type": "Feature",
  "properties": {
    "iso:country":"DE",
    "sg:address":"Haunerting 4",
    "sg:city":"Lauter",
    "sg:phone":"+49 861/4208",
    "sg:postcode":"83362",
    "sg:province":"Bayern",
    "wof:name":"Alois Wastlhuber Fleisch- Und Wurst-",
    "wof:placetype":"venue"
},
  "geometry": {"coordinates":[12.7055501938,47.8622207642],"type":"Point"}
}