{
  "type": "Feature",
  "properties": {
    "iso:country":"DE",
    "sg:address":"Nelkenstr. 16",
    "sg:city":"Neum\u00fcnster",
    "sg:phone":"+49 4321/46323",
    "sg:postcode":"24536",
    "sg:province":"Schleswig-Holstein",
    "wof:name":"Imbiss Good By Jonny",
    "wof:placetype":"venue"
},
  "geometry": {"coordinates":[9.9917297363,54.0977630615],"type":"Point"}
}