{
  "type": "Feature",
  "properties": {
    "iso:country":"DE",
    "sg:address":"Hoppengrund 4",
    "sg:city":"Warburg",
    "sg:phone":"+49 5642/6950",
    "sg:postcode":"34414",
    "sg:province":"Nordrhein-Westfalen",
    "wof:name":"Peter Stoll",
    "wof:placetype":"venue"
},
  "geometry": {"coordinates":[9.025027,51.531132],"type":"Point"}
}