{
  "type": "Feature",
  "properties": {
    "iso:country":"DE",
    "sg:address":"Neue Reihe 46a",
    "sg:city":"Bad Doberan",
    "sg:postcode":"18209",
    "sg:province":"Mecklenburg-Vorpommern",
    "wof:name":"Wasserversorgung Und Abwasser- Behandlung Rostock Gmbh",
    "wof:placetype":"venue"
},
  "geometry": {"coordinates":[11.8942632675,54.107875824],"type":"Point"}
}