{
  "type": "Feature",
  "properties": {
    "iso:country":"DE",
    "sg:address":"Venloer Str. 30",
    "sg:city":"K\u00f6ln",
    "sg:postcode":"50672",
    "sg:province":"Nordrhein-Westfalen",
    "wof:name":"Prostadtgarten E.v.",
    "wof:placetype":"venue"
},
  "geometry": {"coordinates":[6.935819,50.942261],"type":"Point"}
}