{
  "type": "Feature",
  "properties": {
    "iso:country":"DE",
    "sg:address":"Jahnstr. 12",
    "sg:city":"Meschede",
    "sg:phone":"+49 291/9083253",
    "sg:postcode":"59872",
    "sg:province":"Nordrhein-Westfalen",
    "wof:name":"Fachmarkt G\u00fcnther Ohg",
    "wof:placetype":"venue"
},
  "geometry": {"coordinates":[8.2830438614,51.3532676697],"type":"Point"}
}