{
  "type": "Feature",
  "properties": {
    "iso:country":"DE",
    "sg:address":"Wilhelmstr. 34",
    "sg:city":"Siegburg",
    "sg:phone":"+49 2241/51200",
    "sg:postcode":"53721",
    "sg:province":"Nordrhein-Westfalen",
    "wof:name":"Karl-rudolf Kuhn Rechtsanwalt",
    "wof:placetype":"venue"
},
  "geometry": {"coordinates":[7.2038898468,50.7942619324],"type":"Point"}
}