{
  "type": "Feature",
  "properties": {
    "iso:country":"DE",
    "sg:address":"Franzstr. 1",
    "sg:city":"Kassel",
    "sg:phone":"+49 561/886987",
    "sg:postcode":"34128",
    "sg:province":"Hessen",
    "wof:name":"Ellen Burghardt Steuerberaterin",
    "wof:placetype":"venue"
},
  "geometry": {"coordinates":[9.4321584702,51.3395500183],"type":"Point"}
}