{
  "type": "Feature",
  "properties": {
    "iso:country":"DE",
    "sg:address":"Rheinstr. 70",
    "sg:city":"Wesseling",
    "sg:phone":"+49 2236/2908",
    "sg:postcode":"50389",
    "sg:province":"Nordrhein-Westfalen",
    "wof:name":"Leonhard Bilau",
    "wof:placetype":"venue"
},
  "geometry": {"coordinates":[7.017855,50.806255],"type":"Point"}
}