{
  "type": "Feature",
  "properties": {
    "iso:country":"DE",
    "sg:address":"Neumarkter Str. 24",
    "sg:city":"Osnabr\u00fcck",
    "sg:phone":"+49 541/124405",
    "sg:postcode":"49076",
    "sg:province":"Niedersachsen",
    "wof:name":"K. Elm",
    "wof:placetype":"venue"
},
  "geometry": {"coordinates":[7.9746479988,52.3002243042],"type":"Point"}
}