{
  "type": "Feature",
  "properties": {
    "iso:country":"DE",
    "sg:address":"St\u00fcbekamp 124",
    "sg:city":"Hamburg",
    "sg:phone":"+49 40/505011",
    "sg:postcode":"22337",
    "sg:province":"Hamburg",
    "wof:name":"M. Schlumbohm",
    "wof:placetype":"venue"
},
  "geometry": {"coordinates":[10.0512742996,53.6328048706],"type":"Point"}
}