{
  "type": "Feature",
  "properties": {
    "iso:country":"DE",
    "sg:address":"Am Holderbusch 10",
    "sg:city":"D\u00fcsseldorf",
    "sg:phone":"+49 211",
    "sg:postcode":"40627",
    "sg:province":"Nordrhein-Westfalen",
    "wof:name":"Ferienh\u00e4user Und Ferienwohnungen Am Balaton",
    "wof:placetype":"venue"
},
  "geometry": {"coordinates":[6.849656,51.207695],"type":"Point"}
}