{
  "type": "Feature",
  "properties": {
    "iso:country":"DE",
    "sg:address":"Weilerstr. 33",
    "sg:city":"K\u00f6ln",
    "sg:phone":"+49 221/5908484",
    "sg:postcode":"50765",
    "sg:province":"Nordrhein-Westfalen",
    "wof:name":"G. Gornicki",
    "wof:placetype":"venue"
},
  "geometry": {"coordinates":[6.858271122,51.0147247314],"type":"Point"}
}