{
  "type": "Feature",
  "properties": {
    "iso:country":"DE",
    "sg:address":"Wilhelmstr. 1",
    "sg:city":"Dillingen",
    "sg:phone":"+49 6831/706111",
    "sg:postcode":"66763",
    "sg:province":"Saarland",
    "wof:name":"A. Zenk",
    "wof:placetype":"venue"
},
  "geometry": {"coordinates":[6.711126,49.354782],"type":"Point"}
}