{
  "type": "Feature",
  "properties": {
    "iso:country":"DE",
    "sg:address":"Bundesallee 93",
    "sg:city":"Berlin",
    "sg:phone":"+49 30/8519070",
    "sg:postcode":"12161",
    "sg:province":"Berlin",
    "wof:name":"Alex Lange",
    "wof:placetype":"venue"
},
  "geometry": {"coordinates":[13.327997,52.466908],"type":"Point"}
}