{
  "type": "Feature",
  "properties": {
    "iso:country":"DE",
    "sg:address":"Goethestr. 5",
    "sg:city":"Ebernhahn",
    "sg:phone":"+49 2623/6386",
    "sg:postcode":"56424",
    "sg:province":"Rheinland-Pfalz",
    "wof:name":"Ludwig Anders",
    "wof:placetype":"venue"
},
  "geometry": {"coordinates":[7.768782,50.470856],"type":"Point"}
}