{
  "type": "Feature",
  "properties": {
    "iso:country":"DE",
    "sg:address":"H\u00fcnteler Str. 1",
    "sg:city":"Meppen",
    "sg:phone":"+49 5932/2986",
    "sg:postcode":"49716",
    "sg:province":"Niedersachsen",
    "wof:name":"Hans Fehren",
    "wof:placetype":"venue"
},
  "geometry": {"coordinates":[7.258503,52.748116],"type":"Point"}
}