{
  "type": "Feature",
  "properties": {
    "iso:country":"DE",
    "sg:address":"Grevener Damm 40",
    "sg:city":"Emsdetten",
    "sg:phone":"+49 2572/83733",
    "sg:postcode":"48282",
    "sg:province":"Nordrhein-Westfalen",
    "wof:name":"Benson M\u00f6bel Fachgesch\u00e4ft F\u00fcr Stil- Und K\u00fcchenm\u00f6bel Gmbh",
    "wof:placetype":"venue"
},
  "geometry": {"coordinates":[7.5397958755,52.1702346802],"type":"Point"}
}