{
  "type": "Feature",
  "properties": {
    "iso:country":"DE",
    "sg:address":"Riedweg 32",
    "sg:city":"Bad Salzuflen",
    "sg:phone":"+49 5222/59408",
    "sg:postcode":"32107",
    "sg:province":"Nordrhein-Westfalen",
    "wof:name":"G. Schweppe",
    "wof:placetype":"venue"
},
  "geometry": {"coordinates":[8.715123,52.08358],"type":"Point"}
}