{
  "type": "Feature",
  "properties": {
    "iso:country":"DE",
    "sg:address":"H\u00f6lderlinstr. 22",
    "sg:city":"N\u00fcrnberg",
    "sg:phone":"+49 911/592154",
    "sg:postcode":"90491",
    "sg:province":"Bayern",
    "wof:name":"E. J. Reinwald Ingenieur",
    "wof:placetype":"venue"
},
  "geometry": {"coordinates":[11.1193552017,49.4725875854],"type":"Point"}
}