{
  "type": "Feature",
  "properties": {
    "iso:country":"DE",
    "sg:address":"Wallbergstr. 2",
    "sg:city":"Unterhaching",
    "sg:postcode":"82008",
    "sg:province":"Bayern",
    "wof:name":"Optima Immobilien E. K.",
    "wof:placetype":"venue"
},
  "geometry": {"coordinates":[11.6076660156,48.0657730103],"type":"Point"}
}