{
  "type": "Feature",
  "properties": {
    "iso:country":"DE",
    "sg:address":"Eiserfelder Str. 435",
    "sg:city":"Siegen",
    "sg:phone":"+49 271/381516",
    "sg:postcode":"57080",
    "sg:province":"Nordrhein-Westfalen",
    "wof:name":"Horst Giebeler Rechtsanwalt",
    "wof:placetype":"venue"
},
  "geometry": {"coordinates":[7.9881529808,50.8362236023],"type":"Point"}
}