{
  "type": "Feature",
  "properties": {
    "iso:country":"DE",
    "sg:address":"Philipp-Reis-Str. 2",
    "sg:city":"Hildesheim",
    "sg:phone":"+49 5121/45030",
    "sg:postcode":"31137",
    "sg:province":"Niedersachsen",
    "wof:name":"Metallbau Gesellschaft Himmelsth\u00fcr Mbh",
    "wof:placetype":"venue"
},
  "geometry": {"coordinates":[9.918068,52.167255],"type":"Point"}
}