{
  "type": "Feature",
  "properties": {
    "iso:country":"DE",
    "sg:address":"Posthausen 48",
    "sg:city":"Ottersberg",
    "sg:phone":"+49 4297/212",
    "sg:postcode":"28870",
    "sg:province":"Niedersachsen",
    "wof:name":"Eger Wrede",
    "wof:placetype":"venue"
},
  "geometry": {"coordinates":[9.171663,53.067459],"type":"Point"}
}