{
  "type": "Feature",
  "properties": {
    "iso:country":"DE",
    "sg:address":"Lechtinger Kirchweg 16",
    "sg:city":"Wallenhorst",
    "sg:postcode":"49134",
    "sg:province":"Niedersachsen",
    "wof:name":"Detlef Albrecht E. K.",
    "wof:placetype":"venue"
},
  "geometry": {"coordinates":[8.0248022079,52.3439254761],"type":"Point"}
}