{
  "type": "Feature",
  "properties": {
    "iso:country":"DE",
    "sg:city":"Birkenheide",
    "sg:phone":"+49 6237",
    "sg:postcode":"67134",
    "sg:province":"Rheinland-Pfalz",
    "wof:name":"Uebersetzungsteam Guerrero De Stoehr",
    "wof:placetype":"venue"
},
  "geometry": {"coordinates":[8.263625,49.479816],"type":"Point"}
}