{
  "type": "Feature",
  "properties": {
    "iso:country":"DE",
    "sg:address":"Sattlerstra\u00dfe 7",
    "sg:city":"Luebeck",
    "sg:phone":"+49 451",
    "sg:postcode":"23556",
    "sg:province":"Schleswig-Holstein",
    "wof:name":"Jk Verlag",
    "wof:placetype":"venue"
},
  "geometry": {"coordinates":[10.6028423309,53.8591461182],"type":"Point"}
}