{
  "type": "Feature",
  "properties": {
    "iso:country":"DE",
    "sg:address":"Hauptstr. 87",
    "sg:city":"Sch\u00f6llkrippen",
    "sg:phone":"+49 6024/67150",
    "sg:postcode":"63825",
    "sg:province":"Bayern",
    "wof:name":"Reuter-pr\u00e4zision Gmbh",
    "wof:placetype":"venue"
},
  "geometry": {"coordinates":[9.227057457,50.1008682251],"type":"Point"}
}