{
  "type": "Feature",
  "properties": {
    "iso:country":"DE",
    "sg:address":"Gr\u00fcntaler Str. 9",
    "sg:city":"Berlin",
    "sg:phone":"+49 30/49771779",
    "sg:postcode":"13357",
    "sg:province":"Berlin",
    "wof:name":"Fernsehdienst Blue-city-line Seyhm\u00fcsl\u00fcm Arslan",
    "wof:placetype":"venue"
},
  "geometry": {"coordinates":[13.3865871429,52.5518417358],"type":"Point"}
}