{
  "type": "Feature",
  "properties": {
    "iso:country":"DE",
    "sg:address":"Panoramastr. 8",
    "sg:city":"Epfenbach",
    "sg:phone":"+49 7263/1416",
    "sg:postcode":"74925",
    "sg:province":"Baden-W\u00fcrttemberg",
    "wof:name":"Dr. Rer. Nat. Werner Lauer Dipl.-chem.",
    "wof:placetype":"venue"
},
  "geometry": {"coordinates":[8.9112758636,49.3335723877],"type":"Point"}
}