{
  "type": "Feature",
  "properties": {
    "iso:country":"DE",
    "sg:address":"Niendorfer Gartenweg 2A",
    "sg:city":"Magdeburg",
    "sg:postcode":"39116",
    "sg:province":"Sachsen-Anhalt",
    "wof:name":"Dr. Med. Hans-georg Birkigt",
    "wof:placetype":"venue"
},
  "geometry": {"coordinates":[11.570745,52.09869],"type":"Point"}
}