{
  "type": "Feature",
  "properties": {
    "iso:country":"DE",
    "sg:address":"Schillerstr. 1",
    "sg:city":"Wetzlar",
    "sg:phone":"+49 6441/31768",
    "sg:postcode":"35584",
    "sg:province":"Hessen",
    "wof:name":"Hans Neeb Gmbh & Co. Kg",
    "wof:placetype":"venue"
},
  "geometry": {"coordinates":[8.518462,50.585121],"type":"Point"}
}