{
  "type": "Feature",
  "properties": {
    "iso:country":"DE",
    "sg:address":"Wiesbadener Str. 3",
    "sg:city":"Niedernhausen",
    "sg:phone":"+49 6127/5211",
    "sg:postcode":"65527",
    "sg:province":"Hessen",
    "wof:name":"I. Andr\u00e4",
    "wof:placetype":"venue"
},
  "geometry": {"coordinates":[8.31798,50.159691],"type":"Point"}
}