{
  "type": "Feature",
  "properties": {
    "iso:country":"DE",
    "sg:address":"Eugen-Roth-Weg 7",
    "sg:city":"Eberdingen",
    "sg:phone":"+49 7042/880018",
    "sg:postcode":"71735",
    "sg:province":"Baden-W\u00fcrttemberg",
    "wof:name":"Zinsler Infoselect Gmbh & Co. Kg",
    "wof:placetype":"venue"
},
  "geometry": {"coordinates":[8.95934,48.879337],"type":"Point"}
}