{
  "type": "Feature",
  "properties": {
    "iso:country":"DE",
    "sg:address":"Nikolaus-Hofmann-Str. 2",
    "sg:city":"Schweinfurt",
    "sg:phone":"+49 9721/21810",
    "sg:postcode":"97421",
    "sg:province":"Bayern",
    "wof:name":"Michels Fleischwaren Inh. Peter Michel",
    "wof:placetype":"venue"
},
  "geometry": {"coordinates":[10.2194318771,50.0479125977],"type":"Point"}
}