{
  "type": "Feature",
  "properties": {
    "iso:country":"DE",
    "sg:address":"Laberstr. 7",
    "sg:city":"Sinzing",
    "sg:phone":"+49 941/51006",
    "sg:postcode":"93161",
    "sg:province":"Bayern",
    "wof:name":"Gebr\u00fcder Bernard Ag",
    "wof:placetype":"venue"
},
  "geometry": {"coordinates":[12.0336284637,48.991065979],"type":"Point"}
}