{
  "type": "Feature",
  "properties": {
    "iso:country":"DE",
    "sg:address":"Theresienstr. 37",
    "sg:city":"M\u00fcnchen",
    "sg:phone":"+49 89/23944384",
    "sg:postcode":"80333",
    "sg:province":"Bayern",
    "wof:name":"Meteorologisches Institut Der Universit\u00e4t M\u00fcnchen",
    "wof:placetype":"venue"
},
  "geometry": {"coordinates":[11.5724153519,48.1486549377],"type":"Point"}
}