{
  "type": "Feature",
  "properties": {
    "iso:country":"DE",
    "sg:address":"Murtzaner Ring 31",
    "sg:city":"Berlin",
    "sg:phone":"+49 30",
    "sg:postcode":"12681",
    "sg:province":"Berlin",
    "wof:name":"B\u00fcroservice Brandt Berlin",
    "wof:placetype":"venue"
},
  "geometry": {"coordinates":[13.543939,52.530621],"type":"Point"}
}