{
  "type": "Feature",
  "properties": {
    "iso:country":"DE",
    "sg:address":"Kaiserstr. 39",
    "sg:city":"Frankfurt",
    "sg:phone":"+49 69/232482",
    "sg:postcode":"60329",
    "sg:province":"Hessen",
    "wof:name":"K\u00e4pernick Gmbh",
    "wof:placetype":"venue"
},
  "geometry": {"coordinates":[8.670884,50.108898],"type":"Point"}
}