{
  "type": "Feature",
  "properties": {
    "iso:country":"DE",
    "sg:address":"K\u00f6nigsberger Str. 6",
    "sg:city":"Friedberg",
    "sg:phone":"+49 6031/5075",
    "sg:postcode":"61169",
    "sg:province":"Hessen",
    "wof:name":"Shell Direct Gmbh",
    "wof:placetype":"venue"
},
  "geometry": {"coordinates":[8.761071,50.326183],"type":"Point"}
}