{
  "type": "Feature",
  "properties": {
    "iso:country":"DE",
    "sg:address":"Tannenweg 2",
    "sg:city":"Einsbach",
    "sg:phone":"+49 8135/8333",
    "sg:postcode":"85254",
    "sg:province":"Bayern",
    "wof:name":"Infors Gmbh",
    "wof:placetype":"venue"
},
  "geometry": {"coordinates":[11.270556,48.270081],"type":"Point"}
}