{
  "type": "Feature",
  "properties": {
    "iso:country":"DE",
    "sg:address":"Kreuzlinger Str.26",
    "sg:city":"Konstanz",
    "sg:phone":"+49 7531/25980",
    "sg:postcode":"78462",
    "sg:province":"Baden-W\u00fcrttemberg",
    "wof:name":"Fiberflon Technische Gewebe",
    "wof:placetype":"venue"
},
  "geometry": {"coordinates":[9.1715631485,47.6570701599],"type":"Point"}
}