{
  "type": "Feature",
  "properties": {
    "iso:country":"DE",
    "sg:address":"Verdener Str. 33",
    "sg:city":"Nienburg",
    "sg:phone":"+49 5021/97890",
    "sg:postcode":"31582",
    "sg:province":"Niedersachsen",
    "wof:name":"Friedrich B\u00f6ger Inh. Martha Czepak",
    "wof:placetype":"venue"
},
  "geometry": {"coordinates":[9.212439,52.64698],"type":"Point"}
}