{
  "type": "Feature",
  "properties": {
    "iso:country":"DE",
    "sg:address":"Schweriner Str. 12 b",
    "sg:city":"Essen",
    "sg:phone":"+49 201/8745170",
    "sg:postcode":"45147",
    "sg:province":"Nordrhein-Westfalen",
    "wof:name":"Internet Service Professional Gmbh",
    "wof:placetype":"venue"
},
  "geometry": {"coordinates":[6.9622378349,51.4407653809],"type":"Point"}
}