{
  "type": "Feature",
  "properties": {
    "iso:country":"DE",
    "sg:address":"Herrenstr. 2",
    "sg:city":"Ernst",
    "sg:phone":"+49 2671/7502",
    "sg:postcode":"56814",
    "sg:province":"Rheinland-Pfalz",
    "wof:name":"Paul Reitz",
    "wof:placetype":"venue"
},
  "geometry": {"coordinates":[7.2281870842,50.1450195312],"type":"Point"}
}