{
  "type": "Feature",
  "properties": {
    "iso:country":"DE",
    "sg:address":"De Gr\u00f6ne Eck 2",
    "sg:city":"Nieblum",
    "sg:phone":"+49 4681/1850",
    "sg:postcode":"25938",
    "sg:province":"Schleswig-Holstein",
    "wof:name":"Kapit\u00e4n Bors Inh. Nolte",
    "wof:placetype":"venue"
},
  "geometry": {"coordinates":[8.4898090363,54.6924209595],"type":"Point"}
}