{
  "type": "Feature",
  "properties": {
    "iso:country":"DE",
    "sg:address":"Fasaneninsel 1",
    "sg:city":"Gera",
    "sg:phone":"+49 365/7375410",
    "sg:postcode":"07548",
    "sg:province":"Th\u00fcringen",
    "wof:name":"Seifert & Partner Steuerberatungs Gmbh",
    "wof:placetype":"venue"
},
  "geometry": {"coordinates":[12.0698261261,50.8952331543],"type":"Point"}
}