{
  "type": "Feature",
  "properties": {
    "iso:country":"DE",
    "sg:address":"Kaiserstr. 55",
    "sg:city":"Waldshut-Tiengen",
    "sg:phone":"+49 7751/3432",
    "sg:postcode":"79761",
    "sg:province":"Baden-W\u00fcrttemberg",
    "wof:name":"Pro Optiker F\u00fcnfer Gmbh",
    "wof:placetype":"venue"
},
  "geometry": {"coordinates":[8.2115678787,47.6225547791],"type":"Point"}
}