{
  "type": "Feature",
  "properties": {
    "iso:country":"DE",
    "sg:address":"Germaniastr. 29-30",
    "sg:city":"Berlin",
    "sg:phone":"+49 4930/756880",
    "sg:postcode":"12099",
    "sg:province":"Berlin",
    "wof:name":"Kahler Gew\u00dcrze Gmbh",
    "wof:placetype":"venue"
},
  "geometry": {"coordinates":[13.4022359848,52.4627494812],"type":"Point"}
}