{
  "type": "Feature",
  "properties": {
    "iso:country":"DE",
    "sg:address":"Reiterweg 2",
    "sg:city":"Wurz",
    "sg:phone":"+49 9602",
    "sg:postcode":"92715",
    "sg:province":"Bayern",
    "wof:name":"Islandpferde-reitschule Lipperthof",
    "wof:placetype":"venue"
},
  "geometry": {"coordinates":[12.1823749542,49.7721138],"type":"Point"}
}