{
  "type": "Feature",
  "properties": {
    "iso:country":"DE",
    "sg:address":"Brackestr. 40",
    "sg:city":"Leipzig",
    "sg:phone":"+49 341/4114245",
    "sg:postcode":"04207",
    "sg:province":"Sachsen",
    "wof:name":"P. Miksa Anlageberater",
    "wof:placetype":"venue"
},
  "geometry": {"coordinates":[12.2662639618,51.3127059937],"type":"Point"}
}