{
  "type": "Feature",
  "properties": {
    "iso:country":"DE",
    "sg:address":"\u00dcbelherrgasse 1",
    "sg:city":"H\u00f6chst\u00e4dt",
    "sg:phone":"+49 9074/1323",
    "sg:postcode":"89420",
    "sg:province":"Bayern",
    "wof:name":"Franz Schickinger",
    "wof:placetype":"venue"
},
  "geometry": {"coordinates":[10.570358,48.611198],"type":"Point"}
}