{
  "type": "Feature",
  "properties": {
    "iso:country":"DE",
    "sg:address":"Im Hermeshain 15",
    "sg:city":"Frankfurt",
    "sg:phone":"+49 69/42098555",
    "sg:postcode":"60388",
    "sg:province":"Hessen",
    "wof:name":"B & P Immobilien Gmbh",
    "wof:placetype":"venue"
},
  "geometry": {"coordinates":[8.7577972412,50.1517906189],"type":"Point"}
}