{
  "type": "Feature",
  "properties": {
    "iso:country":"DE",
    "sg:address":"Neue Str. 17",
    "sg:city":"Sch\u00f6ppenstedt",
    "sg:phone":"+49 5332/1337",
    "sg:postcode":"38170",
    "sg:province":"Niedersachsen",
    "wof:name":"Sommerfeld Und Partner",
    "wof:placetype":"venue"
},
  "geometry": {"coordinates":[10.7797193527,52.1427726746],"type":"Point"}
}