{
  "type": "Feature",
  "properties": {
    "iso:country":"DE",
    "sg:address":"Am Goldkindstein 33",
    "sg:city":"Marienberg",
    "sg:phone":"+49 3735/22103",
    "sg:postcode":"09496",
    "sg:province":"Sachsen",
    "wof:name":"Rfe Radio Fernsehen Elektronik",
    "wof:placetype":"venue"
},
  "geometry": {"coordinates":[13.161792,50.645859],"type":"Point"}
}