{
  "type": "Feature",
  "properties": {
    "iso:country":"DE",
    "sg:address":"Baumhofstr. 13",
    "sg:city":"Bochum",
    "sg:phone":"+49 234/9731777",
    "sg:postcode":"44799",
    "sg:province":"Nordrhein-Westfalen",
    "wof:name":"Kaiser Wohnungsbau Gmbh",
    "wof:placetype":"venue"
},
  "geometry": {"coordinates":[7.23808,51.439171],"type":"Point"}
}