{
  "type": "Feature",
  "properties": {
    "iso:country":"DE",
    "sg:address":"Ortsstr. 2",
    "sg:city":"Lausnitz",
    "sg:phone":"+49 36481/24043",
    "sg:postcode":"07806",
    "sg:province":"Th\u00fcringen",
    "wof:name":"Osbahr Gmbh",
    "wof:placetype":"venue"
},
  "geometry": {"coordinates":[11.6908388138,50.7289352417],"type":"Point"}
}