{
  "type": "Feature",
  "properties": {
    "iso:country":"DE",
    "sg:address":"M\u00fchl\u00e4ckerstr. 13",
    "sg:city":"Calw",
    "sg:postcode":"75365",
    "sg:province":"Baden-W\u00fcrttemberg",
    "wof:name":"Alho Systembau Gmbh",
    "wof:placetype":"venue"
},
  "geometry": {"coordinates":[8.761991,48.696629],"type":"Point"}
}