{
  "type": "Feature",
  "properties": {
    "iso:country":"DE",
    "sg:address":"K\u00f6nigstr. 21",
    "sg:city":"L\u00fcbeck",
    "sg:phone":"+49 451/77339",
    "sg:postcode":"23552",
    "sg:province":"Schleswig-Holstein",
    "wof:name":"Archiv Der Stiftung Schleswig- Hosteinische Cinematheque",
    "wof:placetype":"venue"
},
  "geometry": {"coordinates":[10.689534,53.869778],"type":"Point"}
}