{
  "type": "Feature",
  "properties": {
    "iso:country":"DE",
    "sg:address":"Burgstr.",
    "sg:city":"Harpstedt",
    "sg:phone":"+49 4244/7188",
    "sg:postcode":"27243",
    "sg:province":"Niedersachsen",
    "wof:name":"Manfred Menges Engl. Antiquit\u00e4ten",
    "wof:placetype":"venue"
},
  "geometry": {"coordinates":[8.58793,52.909328],"type":"Point"}
}