{
  "type": "Feature",
  "properties": {
    "iso:country":"DE",
    "sg:address":"Georg-Kraushaar-Str. 14",
    "sg:city":"Emmerich",
    "sg:phone":"+49 2822/96940",
    "sg:postcode":"46446",
    "sg:province":"Nordrhein-Westfalen",
    "wof:name":"Georg Faulseit",
    "wof:placetype":"venue"
},
  "geometry": {"coordinates":[6.254787,51.841873],"type":"Point"}
}