{
  "type": "Feature",
  "properties": {
    "iso:country":"DE",
    "sg:address":"Ostring 72",
    "sg:city":"Bitburg",
    "sg:phone":"+49 6561/4138",
    "sg:postcode":"54634",
    "sg:province":"Rheinland-Pfalz",
    "wof:name":"Heinz Laub",
    "wof:placetype":"venue"
},
  "geometry": {"coordinates":[6.5386919975,49.9783782959],"type":"Point"}
}