{
  "type": "Feature",
  "properties": {
    "iso:country":"DE",
    "sg:address":"Neulandstr. 2a",
    "sg:city":"Achern",
    "sg:phone":"+49 7841/21084",
    "sg:postcode":"77855",
    "sg:province":"Baden-W\u00fcrttemberg",
    "wof:name":"Dieter Schnur",
    "wof:placetype":"venue"
},
  "geometry": {"coordinates":[8.061436,48.635216],"type":"Point"}
}