{
  "type": "Feature",
  "properties": {
    "iso:country":"DE",
    "sg:address":"Biberm\u00fchle",
    "sg:city":"Wackersberg",
    "sg:phone":"+49 8041/6634",
    "sg:postcode":"83646",
    "sg:province":"Bayern",
    "wof:name":"G\u00e4stehaus Kaspar Trischberger",
    "wof:placetype":"venue"
},
  "geometry": {"coordinates":[11.5547475815,47.7293052673],"type":"Point"}
}