{
  "type": "Feature",
  "properties": {
    "iso:country":"DE",
    "sg:address":"Bleichstr. 41",
    "sg:city":"Offenbach",
    "sg:phone":"+49 69/811310",
    "sg:postcode":"63065",
    "sg:province":"Hessen",
    "wof:name":"F. Reuter",
    "wof:placetype":"venue"
},
  "geometry": {"coordinates":[8.7663812637,50.1027870178],"type":"Point"}
}