{
  "type": "Feature",
  "properties": {
    "iso:country":"DE",
    "sg:address":"Honnschaftenstr. 21",
    "sg:city":"Essen",
    "sg:phone":"+49 201/402907",
    "sg:postcode":"45239",
    "sg:province":"Nordrhein-Westfalen",
    "wof:name":"Claus Lepper",
    "wof:placetype":"venue"
},
  "geometry": {"coordinates":[7.0102062225,51.3709182739],"type":"Point"}
}