{
  "type": "Feature",
  "properties": {
    "iso:country":"DE",
    "sg:address":"Am Pfusteracker 4",
    "sg:city":"Unterw\u00f6ssen",
    "sg:phone":"+49 8641/8340",
    "sg:postcode":"83246",
    "sg:province":"Bayern",
    "wof:name":"Hans Schreiber Architekt",
    "wof:placetype":"venue"
},
  "geometry": {"coordinates":[12.461481,47.73436],"type":"Point"}
}