{
  "type": "Feature",
  "properties": {
    "iso:country":"DE",
    "sg:address":"Meltewitzer Str. 41-43",
    "sg:city":"Meltewitz",
    "sg:phone":"+49 34261/61010",
    "sg:postcode":"04808",
    "sg:province":"Sachsen",
    "wof:name":"Allclean Reinigungs- Und Umwelt-technik Gmbh",
    "wof:placetype":"venue"
},
  "geometry": {"coordinates":[12.791865,51.392357],"type":"Point"}
}