{
  "type": "Feature",
  "properties": {
    "iso:country":"DE",
    "sg:address":"Wilhelm-Leuschner-Str. 14",
    "sg:city":"Heilbronn",
    "sg:phone":"+49 7131/42113",
    "sg:postcode":"74080",
    "sg:province":"Baden-W\u00fcrttemberg",
    "wof:name":"A. Holaschke",
    "wof:placetype":"venue"
},
  "geometry": {"coordinates":[9.1965179443,49.1417655945],"type":"Point"}
}