{
  "type": "Feature",
  "properties": {
    "iso:country":"DE",
    "sg:address":"Matthiasstr.19",
    "sg:city":"M\u00f6nchengladbach",
    "sg:phone":"+49 2161/179230",
    "sg:postcode":"41063",
    "sg:province":"Nordrhein-Westfalen",
    "wof:name":"Reisevermittlung 3ws",
    "wof:placetype":"venue"
},
  "geometry": {"coordinates":[6.446603775,51.2028617859],"type":"Point"}
}