{
  "type": "Feature",
  "properties": {
    "iso:country":"DE",
    "sg:city":"Rodgau",
    "sg:phone":"+49 6106",
    "sg:postcode":"63110",
    "sg:province":"Hessen",
    "wof:name":"Oberfl\u00e4cheninfoservice",
    "wof:placetype":"venue"
},
  "geometry": {"coordinates":[8.885336,50.025585],"type":"Point"}
}