{
  "type": "Feature",
  "properties": {
    "iso:country":"DE",
    "sg:address":"Raiffeisenstr. 17",
    "sg:city":"Neuberg",
    "sg:phone":"+49 6183/900426",
    "sg:postcode":"63543",
    "sg:province":"Hessen",
    "wof:name":"Hubert Jakob Steuerberater",
    "wof:placetype":"venue"
},
  "geometry": {"coordinates":[8.9920797348,50.1924324036],"type":"Point"}
}