{
  "type": "Feature",
  "properties": {
    "iso:country":"DE",
    "sg:address":"Steendiek 43",
    "sg:city":"Hamburg",
    "sg:postcode":"21129",
    "sg:province":"Hamburg",
    "wof:name":"Budnikowsky Drogeriemarkt",
    "wof:placetype":"venue"
},
  "geometry": {"coordinates":[9.879419,53.532978],"type":"Point"}
}