{
  "type": "Feature",
  "properties": {
    "iso:country":"DE",
    "sg:address":"Blumenstr. 3a",
    "sg:city":"Bad Rodach",
    "sg:phone":"+49 9564/1284",
    "sg:postcode":"96476",
    "sg:province":"Bayern",
    "wof:name":"Herbert V\u00f6lker Architekt",
    "wof:placetype":"venue"
},
  "geometry": {"coordinates":[10.77744,50.343731],"type":"Point"}
}