{
  "type": "Feature",
  "properties": {
    "iso:country":"DE",
    "sg:address":"Neuer Weg 3",
    "sg:city":"Lautertal",
    "sg:phone":"+49 6643/8639",
    "sg:postcode":"36369",
    "sg:province":"Hessen",
    "wof:name":"Helmut Hanisch",
    "wof:placetype":"venue"
},
  "geometry": {"coordinates":[9.278845787,50.5688514709],"type":"Point"}
}