{
  "type": "Feature",
  "properties": {
    "iso:country":"DE",
    "sg:address":"Klingenhofstr 71",
    "sg:city":"N\u00fcrnberg",
    "sg:phone":"+49 911/56930",
    "sg:postcode":"90411",
    "sg:province":"Bayern",
    "wof:name":"Eberle Controls Gmbh",
    "wof:placetype":"venue"
},
  "geometry": {"coordinates":[11.1154356003,49.4776687622],"type":"Point"}
}