{
  "type": "Feature",
  "properties": {
    "iso:country":"DE",
    "sg:address":"Schwedter Str. 32",
    "sg:city":"Prenzlau",
    "sg:phone":"+49 3984/4110",
    "sg:postcode":"17291",
    "sg:province":"Brandenburg",
    "wof:name":"Pension Wessolowski",
    "wof:placetype":"venue"
},
  "geometry": {"coordinates":[13.8682527542,53.3091278076],"type":"Point"}
}