{
  "type": "Feature",
  "properties": {
    "iso:country":"DE",
    "sg:address":"Bl\u00fctenstr. 2",
    "sg:city":"Gro\u00dfostheim",
    "sg:postcode":"63762",
    "sg:province":"Bayern",
    "wof:name":"Fitness-oase Gmbh",
    "wof:placetype":"venue"
},
  "geometry": {"coordinates":[9.0845775604,49.9196968079],"type":"Point"}
}