{
  "type": "Feature",
  "properties": {
    "iso:country":"DE",
    "sg:address":"Beerenstr. 26",
    "sg:city":"Leverkusen",
    "sg:phone":"+49 2171/29747",
    "sg:postcode":"51379",
    "sg:province":"Nordrhein-Westfalen",
    "wof:name":"E. Rose-tkacz",
    "wof:placetype":"venue"
},
  "geometry": {"coordinates":[6.999418,51.078976],"type":"Point"}
}