{
  "type": "Feature",
  "properties": {
    "iso:country":"DE",
    "sg:address":"K\u00f6lner Str. 195",
    "sg:city":"Bergneustadt",
    "sg:phone":"+49 2261/41387",
    "sg:postcode":"51702",
    "sg:province":"Nordrhein-Westfalen",
    "wof:name":"Masters Marx",
    "wof:placetype":"venue"
},
  "geometry": {"coordinates":[7.6452789307,51.0202255249],"type":"Point"}
}