{
  "type": "Feature",
  "properties": {
    "iso:country":"DE",
    "sg:address":"Postfach 62",
    "sg:city":"Wolfegg",
    "sg:postcode":"88362",
    "sg:province":"Baden-W\u00fcrttemberg",
    "wof:name":"Kommunales Kino",
    "wof:placetype":"venue"
},
  "geometry": {"coordinates":[9.792464,47.819038],"type":"Point"}
}