{
  "type": "Feature",
  "properties": {
    "iso:country":"DE",
    "sg:address":"Wehme 168",
    "sg:city":"Rahden",
    "sg:phone":"+49 5771/94710",
    "sg:postcode":"32369",
    "sg:province":"Nordrhein-Westfalen",
    "wof:name":"Udo Knost",
    "wof:placetype":"venue"
},
  "geometry": {"coordinates":[8.6148967743,52.4341201782],"type":"Point"}
}