{
  "type": "Feature",
  "properties": {
    "iso:country":"DE",
    "sg:address":"Riesweg 74",
    "sg:city":"Essen",
    "sg:phone":"+49 201/841100",
    "sg:postcode":"45134",
    "sg:province":"Nordrhein-Westfalen",
    "wof:name":"Gothe Immobilien Gmbh",
    "wof:placetype":"venue"
},
  "geometry": {"coordinates":[7.03617,51.420807],"type":"Point"}
}