{
  "type": "Feature",
  "properties": {
    "iso:country":"DE",
    "sg:address":"Wettringer Str 41",
    "sg:city":"Steinfurt",
    "sg:phone":"+49 2551/640",
    "sg:postcode":"48565",
    "sg:province":"Nordrhein-Westfalen",
    "wof:name":"Alex Rolinck Privatbrauerei Gmbh & Co",
    "wof:placetype":"venue"
},
  "geometry": {"coordinates":[7.340673,52.152798],"type":"Point"}
}