{
  "type": "Feature",
  "properties": {
    "iso:country":"DE",
    "sg:address":"Berenbrock",
    "sg:city":"L\u00fcdinghausen",
    "sg:phone":"+49 2591/4531",
    "sg:postcode":"59348",
    "sg:province":"Nordrhein-Westfalen",
    "wof:name":"Braun",
    "wof:placetype":"venue"
},
  "geometry": {"coordinates":[7.4257278442,51.7897186279],"type":"Point"}
}