{
  "type": "Feature",
  "properties": {
    "iso:country":"DE",
    "sg:address":"Sandstr. 30",
    "sg:city":"Leverkusen",
    "sg:phone":"+49 2171/43427",
    "sg:postcode":"51379",
    "sg:province":"Nordrhein-Westfalen",
    "wof:name":"Kurt Stich",
    "wof:placetype":"venue"
},
  "geometry": {"coordinates":[6.995321,51.078732],"type":"Point"}
}