{
  "type": "Feature",
  "properties": {
    "iso:country":"DE",
    "sg:address":"Sandf\u00f6rth 49",
    "sg:city":"Nienhagen",
    "sg:phone":"+49 5144/5530",
    "sg:postcode":"29336",
    "sg:province":"Niedersachsen",
    "wof:name":"Karin Hirtz Heilpraktikerin",
    "wof:placetype":"venue"
},
  "geometry": {"coordinates":[10.0960025787,52.5543060303],"type":"Point"}
}