{
  "type": "Feature",
  "properties": {
    "iso:country":"DE",
    "sg:address":"Veringstr. 43",
    "sg:city":"Hamburg",
    "sg:phone":"+49 40/758423",
    "sg:postcode":"21107",
    "sg:province":"Hamburg",
    "wof:name":"Wolfgang Pribert Rechtsanwalt",
    "wof:placetype":"venue"
},
  "geometry": {"coordinates":[9.9869937897,53.5146713257],"type":"Point"}
}