{
  "type": "Feature",
  "properties": {
    "iso:country":"DE",
    "sg:address":"Am Kiekenbusch 4",
    "sg:city":"Duisburg",
    "sg:phone":"+49 203/76840",
    "sg:postcode":"47269",
    "sg:province":"Nordrhein-Westfalen",
    "wof:name":"B\u00e4ko-zentrale Nord Eg",
    "wof:placetype":"venue"
},
  "geometry": {"coordinates":[6.774802,51.369286],"type":"Point"}
}