{
  "type": "Feature",
  "properties": {
    "iso:country":"DE",
    "sg:address":"Gro\u00dfe Wasserpfortstr. 4",
    "sg:city":"Jever",
    "sg:postcode":"26441",
    "sg:province":"Niedersachsen",
    "wof:name":"Kaisers Drugstore",
    "wof:placetype":"venue"
},
  "geometry": {"coordinates":[7.899086,53.573265],"type":"Point"}
}