{
  "type": "Feature",
  "properties": {
    "iso:country":"DE",
    "sg:address":"Popenser Str. 2",
    "sg:city":"Aurich",
    "sg:phone":"+49 4941/65802",
    "sg:postcode":"26603",
    "sg:province":"Niedersachsen",
    "wof:name":"R. Hainke Gmbh",
    "wof:placetype":"venue"
},
  "geometry": {"coordinates":[7.4918961525,53.4618225098],"type":"Point"}
}