{
  "type": "Feature",
  "properties": {
    "iso:country":"DE",
    "sg:address":"Beckhausstr. 168",
    "sg:city":"Bielefeld",
    "sg:phone":"+49 521/82160",
    "sg:postcode":"33611",
    "sg:province":"Nordrhein-Westfalen",
    "wof:name":"Detektei Holler Gmbh",
    "wof:placetype":"venue"
},
  "geometry": {"coordinates":[8.546164,52.04982],"type":"Point"}
}