{
  "type": "Feature",
  "properties": {
    "iso:country":"DE",
    "sg:address":"Mainstr. 7",
    "sg:city":"Gro\u00dfheubach",
    "sg:phone":"+49 9371/2712",
    "sg:postcode":"63920",
    "sg:province":"Bayern",
    "wof:name":"Thomas Bischof",
    "wof:placetype":"venue"
},
  "geometry": {"coordinates":[9.2215557098,49.7263336182],"type":"Point"}
}