{
  "type": "Feature",
  "properties": {
    "iso:country":"DE",
    "sg:address":"P\u00f6ntertalstr. 31",
    "sg:city":"Andernach",
    "sg:phone":"+49 2636/2418",
    "sg:postcode":"56626",
    "sg:province":"Rheinland-Pfalz",
    "wof:name":"Uwe Kriechel",
    "wof:placetype":"venue"
},
  "geometry": {"coordinates":[7.3097438812,50.4475288391],"type":"Point"}
}