{
  "type": "Feature",
  "properties": {
    "iso:country":"DE",
    "sg:address":"N\u00fcrnberger Str. 249",
    "sg:city":"Regensburg",
    "sg:phone":"+49 941/87475",
    "sg:postcode":"93059",
    "sg:province":"Bayern",
    "wof:name":"Berts Weinexpress Seiter & Troge Ohg",
    "wof:placetype":"venue"
},
  "geometry": {"coordinates":[12.0616016388,49.0327911377],"type":"Point"}
}