{
  "type": "Feature",
  "properties": {
    "iso:country":"DE",
    "sg:address":"Goethestr. 1 a",
    "sg:city":"Stavenhagen",
    "sg:phone":"+49 39954/21594",
    "sg:postcode":"17153",
    "sg:province":"Mecklenburg-Vorpommern",
    "wof:name":"Pension Garni",
    "wof:placetype":"venue"
},
  "geometry": {"coordinates":[12.9049873352,53.6977844238],"type":"Point"}
}