{
  "type": "Feature",
  "properties": {
    "iso:country":"DE",
    "sg:address":"Friedenbachstr.",
    "sg:city":"Weilburg",
    "sg:phone":"+49 6471/39017",
    "sg:postcode":"35781",
    "sg:province":"Hessen",
    "wof:name":"Minimal",
    "wof:placetype":"venue"
},
  "geometry": {"coordinates":[8.2888002396,50.4806060791],"type":"Point"}
}