{
  "type": "Feature",
  "properties": {
    "iso:country":"DE",
    "sg:address":"Rosenheimer Str. 62",
    "sg:city":"Kolbermoor",
    "sg:phone":"+49 8031/97560",
    "sg:postcode":"83059",
    "sg:province":"Bayern",
    "wof:name":"Mues Products Gmbh",
    "wof:placetype":"venue"
},
  "geometry": {"coordinates":[12.07803,47.849144],"type":"Point"}
}