{
  "type": "Feature",
  "properties": {
    "iso:country":"DE",
    "sg:address":"P\u00fctzst\u00fccker Str. 19",
    "sg:city":"K\u00f6nigswinter",
    "sg:phone":"+49 2244/2009",
    "sg:postcode":"53639",
    "sg:province":"Nordrhein-Westfalen",
    "wof:name":"Gerhard Hering Ingenieur",
    "wof:placetype":"venue"
},
  "geometry": {"coordinates":[7.3022170067,50.7151412964],"type":"Point"}
}