{
  "type": "Feature",
  "properties": {
    "iso:country":"DE",
    "sg:address":"Weidengasse 5",
    "sg:city":"Freiberg",
    "sg:postcode":"71691",
    "sg:province":"Baden-W\u00fcrttemberg",
    "wof:name":"Aldi Gmbh & Co. Kg",
    "wof:placetype":"venue"
},
  "geometry": {"coordinates":[9.1815052032,48.9290542603],"type":"Point"}
}