{
  "type": "Feature",
  "properties": {
    "iso:country":"DE",
    "sg:address":"Ringelhauser Allee 18",
    "sg:city":"Laupheim",
    "sg:phone":"+49 7392/8328",
    "sg:postcode":"88471",
    "sg:province":"Baden-W\u00fcrttemberg",
    "wof:name":"Hildegard Tempelmann Hebamme",
    "wof:placetype":"venue"
},
  "geometry": {"coordinates":[9.891878,48.235073],"type":"Point"}
}