{
  "type": "Feature",
  "properties": {
    "iso:country":"DE",
    "sg:address":"Hirschsprungallee 7",
    "sg:city":"Stuttgart",
    "sg:phone":"+49 711/822156",
    "sg:postcode":"70435",
    "sg:province":"Baden-W\u00fcrttemberg",
    "wof:name":"Tsv Vereinsgastst\u00e4tte",
    "wof:placetype":"venue"
},
  "geometry": {"coordinates":[9.1528167725,48.827041626],"type":"Point"}
}