{
  "type": "Feature",
  "properties": {
    "iso:country":"DE",
    "sg:address":"Hauptstr. 67",
    "sg:city":"Aulendorf",
    "sg:phone":"+49 7525/2646",
    "sg:postcode":"88326",
    "sg:province":"Baden-W\u00fcrttemberg",
    "wof:name":"Dr. Med. Gerd-dieter Guddat",
    "wof:placetype":"venue"
},
  "geometry": {"coordinates":[9.6362104416,47.9524345398],"type":"Point"}
}