{
  "type": "Feature",
  "properties": {
    "iso:country":"DE",
    "sg:address":"Bergedorfer Str. 69",
    "sg:city":"Geesthacht",
    "sg:phone":"+49 4152/2402",
    "sg:postcode":"21502",
    "sg:province":"Schleswig-Holstein",
    "wof:name":"Vo\u00df",
    "wof:placetype":"venue"
},
  "geometry": {"coordinates":[10.3695278168,53.4364471436],"type":"Point"}
}