{
  "type": "Feature",
  "properties": {
    "iso:country":"DE",
    "sg:address":"Bergstr. 34",
    "sg:city":"Solingen",
    "sg:phone":"+49 212/209178",
    "sg:postcode":"42651",
    "sg:province":"Nordrhein-Westfalen",
    "wof:name":"Rendevouz",
    "wof:placetype":"venue"
},
  "geometry": {"coordinates":[7.0793709755,51.1701202393],"type":"Point"}
}