{
  "type": "Feature",
  "properties": {
    "iso:country":"DE",
    "sg:address":"Hauptstr. 54",
    "sg:city":"Renchen",
    "sg:phone":"+49 7843/2253",
    "sg:postcode":"77871",
    "sg:province":"Baden-W\u00fcrttemberg",
    "wof:name":"Pizzeria La Barca",
    "wof:placetype":"venue"
},
  "geometry": {"coordinates":[8.0113115311,48.5863113403],"type":"Point"}
}