{
  "type": "Feature",
  "properties": {
    "iso:country":"DE",
    "sg:address":"Ludwigstr. 1",
    "sg:city":"Gie\u00dfen",
    "sg:phone":"+49 641/77941",
    "sg:postcode":"35390",
    "sg:province":"Hessen",
    "wof:name":"Comet Reinigung",
    "wof:placetype":"venue"
},
  "geometry": {"coordinates":[8.680047,50.582203],"type":"Point"}
}