{
  "type": "Feature",
  "properties": {
    "iso:country":"DE",
    "sg:address":"Mahlbergstr. 1",
    "sg:city":"Keltern",
    "sg:phone":"+49 7236/8325",
    "sg:postcode":"75210",
    "sg:province":"Baden-W\u00fcrttemberg",
    "wof:name":"Otto Schl\u00f6gel",
    "wof:placetype":"venue"
},
  "geometry": {"coordinates":[8.5739984512,48.8993415833],"type":"Point"}
}