{
  "type": "Feature",
  "properties": {
    "iso:country":"DE",
    "sg:address":"Baumwall 5",
    "sg:city":"Hamburg",
    "sg:postcode":"20459",
    "sg:province":"Hamburg",
    "wof:name":"Bbv Ag",
    "wof:placetype":"venue"
},
  "geometry": {"coordinates":[9.982501,53.544628],"type":"Point"}
}