{
  "type": "Feature",
  "properties": {
    "iso:country":"DE",
    "sg:address":"Hauptstr. 144",
    "sg:city":"Gornsdorf",
    "sg:phone":"+49 3721/23943",
    "sg:postcode":"09390",
    "sg:province":"Sachsen",
    "wof:name":"Lindensch\u00e4nke",
    "wof:placetype":"venue"
},
  "geometry": {"coordinates":[12.8834896088,50.700428009],"type":"Point"}
}