{
  "type": "Feature",
  "properties": {
    "iso:country":"DE",
    "sg:address":"M\u00fchlenanger 44",
    "sg:city":"Adelebsen",
    "sg:phone":"+49 5506/657",
    "sg:postcode":"37139",
    "sg:province":"Niedersachsen",
    "wof:name":"Guenter Ausmeyer",
    "wof:placetype":"venue"
},
  "geometry": {"coordinates":[9.757458,51.582241],"type":"Point"}
}