{
  "type": "Feature",
  "properties": {
    "iso:country":"DE",
    "sg:address":"Hermenweg 5",
    "sg:city":"Hannover",
    "sg:phone":"+49 511/793920",
    "sg:postcode":"30419",
    "sg:province":"Niedersachsen",
    "wof:name":"Binder Funktaxen Hannover Gmbh",
    "wof:placetype":"venue"
},
  "geometry": {"coordinates":[9.686188,52.410229],"type":"Point"}
}