{
  "type": "Feature",
  "properties": {
    "iso:country":"DE",
    "sg:address":"Br\u00fcder-Grimm-Str. 23",
    "sg:city":"Fulda",
    "sg:postcode":"36037",
    "sg:province":"Hessen",
    "wof:name":"Monopol Handelsges. Mbh",
    "wof:placetype":"venue"
},
  "geometry": {"coordinates":[9.674695015,50.5535583496],"type":"Point"}
}