{
  "type": "Feature",
  "properties": {
    "iso:country":"DE",
    "sg:address":"K\u00f6lner Str. 51",
    "sg:city":"Mechernich",
    "sg:postcode":"53894",
    "sg:province":"Nordrhein-Westfalen",
    "wof:name":"Cmcs Computer Partner Gmbh",
    "wof:placetype":"venue"
},
  "geometry": {"coordinates":[6.6479330063,50.6127700806],"type":"Point"}
}