{
  "type": "Feature",
  "properties": {
    "iso:country":"DE",
    "sg:address":"N\u00fcrnberger Str. 79a",
    "sg:city":"Schnaittach",
    "sg:phone":"+49 9153/8322",
    "sg:postcode":"91220",
    "sg:province":"Bayern",
    "wof:name":"H. W. Berthold",
    "wof:placetype":"venue"
},
  "geometry": {"coordinates":[11.335726,49.553665],"type":"Point"}
}