{
  "type": "Feature",
  "properties": {
    "iso:country":"DE",
    "sg:address":"Bismarckstr. 2",
    "sg:city":"Braunlage",
    "sg:phone":"+49 5520/2284",
    "sg:postcode":"38700",
    "sg:province":"Niedersachsen",
    "wof:name":"G\u00e4stehaus Alice",
    "wof:placetype":"venue"
},
  "geometry": {"coordinates":[10.6102542877,51.7290687561],"type":"Point"}
}