{
  "type": "Feature",
  "properties": {
    "iso:country":"DE",
    "sg:address":"Schmelzer Str. 21",
    "sg:city":"Inzell",
    "sg:phone":"+49 8665/98640",
    "sg:postcode":"83334",
    "sg:province":"Bayern",
    "wof:name":"G\u00e4stehaus Andrea",
    "wof:placetype":"venue"
},
  "geometry": {"coordinates":[12.7426948547,47.7613983154],"type":"Point"}
}