{
  "type": "Feature",
  "properties": {
    "iso:country":"DE",
    "sg:address":"Donat-Gr\u00f6mling-Str. 5",
    "sg:city":"Rimpar",
    "sg:phone":"+49 9365/9788",
    "sg:postcode":"97222",
    "sg:province":"Bayern",
    "wof:name":"Walter Stein Ingenieur",
    "wof:placetype":"venue"
},
  "geometry": {"coordinates":[9.9641008377,49.8534126282],"type":"Point"}
}