{
  "type": "Feature",
  "properties": {
    "iso:country":"DE",
    "sg:address":"Ernst-Heilmann-Weg",
    "sg:city":"Cottbus",
    "sg:phone":"+49 355/702210",
    "sg:postcode":"03044",
    "sg:province":"Brandenburg",
    "wof:name":"Elektro Bracher Gmbh",
    "wof:placetype":"venue"
},
  "geometry": {"coordinates":[14.3136100769,51.7716827393],"type":"Point"}
}