{
  "type": "Feature",
  "properties": {
    "iso:country":"DE",
    "sg:address":"Schwalbacher Str. 18",
    "sg:city":"Schlangenbad",
    "sg:phone":"+49 6129/9945",
    "sg:postcode":"65388",
    "sg:province":"Hessen",
    "wof:name":"Karl D\u00f6rner",
    "wof:placetype":"venue"
},
  "geometry": {"coordinates":[8.097867012,50.1088218689],"type":"Point"}
}