{
  "type": "Feature",
  "properties": {
    "iso:country":"DE",
    "sg:address":"Reiherstr. 229",
    "sg:city":"Bremen",
    "sg:phone":"+49 421/643850",
    "sg:postcode":"28239",
    "sg:province":"Bremen",
    "wof:name":"Recke Fleischwaren- Spezialit\u00e4ten Vertriebs Gmbh",
    "wof:placetype":"venue"
},
  "geometry": {"coordinates":[8.7216501236,53.1419487],"type":"Point"}
}