{
  "type": "Feature",
  "properties": {
    "iso:country":"DE",
    "sg:address":"Nicolaistr. 5",
    "sg:city":"H\u00f6xter",
    "sg:phone":"+49 5271/31894",
    "sg:postcode":"37671",
    "sg:province":"Nordrhein-Westfalen",
    "wof:name":"Restaurant Mediterranee",
    "wof:placetype":"venue"
},
  "geometry": {"coordinates":[9.3816289902,51.776889801],"type":"Point"}
}