{
  "type": "Feature",
  "properties": {
    "iso:country":"DE",
    "sg:address":"Hauptstr. 65",
    "sg:city":"Seth",
    "sg:phone":"+49 4194/7336",
    "sg:postcode":"23845",
    "sg:province":"Schleswig-Holstein",
    "wof:name":"Kuno Selk",
    "wof:placetype":"venue"
},
  "geometry": {"coordinates":[10.175162,53.847408],"type":"Point"}
}