{
  "type": "Feature",
  "properties": {
    "iso:country":"DE",
    "sg:address":"Pescher Str. 9",
    "sg:city":"Erkelenz",
    "sg:phone":"+49 2164/4568",
    "sg:postcode":"41812",
    "sg:province":"Nordrhein-Westfalen",
    "wof:name":"G. Abels Hebamme",
    "wof:placetype":"venue"
},
  "geometry": {"coordinates":[6.439547,51.05159],"type":"Point"}
}