{
  "type": "Feature",
  "properties": {
    "iso:country":"DE",
    "sg:address":"Benzstr. 1-3",
    "sg:city":"Leverkusen",
    "sg:phone":"+49 2171/706670",
    "sg:postcode":"51381",
    "sg:province":"Nordrhein-Westfalen",
    "wof:name":"Gerd Loser & Co. Gmbh",
    "wof:placetype":"venue"
},
  "geometry": {"coordinates":[7.012359,51.052784],"type":"Point"}
}