{
  "type": "Feature",
  "properties": {
    "iso:country":"DE",
    "sg:address":"Auedeich 24",
    "sg:city":"Hamburg",
    "sg:phone":"+49 40/7429638",
    "sg:postcode":"21129",
    "sg:province":"Hamburg",
    "wof:name":"Joachim K\u00e4hne Ingenieur",
    "wof:placetype":"venue"
},
  "geometry": {"coordinates":[9.883734,53.529781],"type":"Point"}
}