{
  "type": "Feature",
  "properties": {
    "iso:country":"DE",
    "sg:address":"Pfarrer-Krenb\u00f6ck-Str. 6",
    "sg:city":"Frauenau",
    "sg:phone":"+49 9926/902000",
    "sg:postcode":"94258",
    "sg:province":"Bayern",
    "wof:name":"Franz Brunner Finanzberater",
    "wof:placetype":"venue"
},
  "geometry": {"coordinates":[13.3085632324,48.9892692566],"type":"Point"}
}