{
  "type": "Feature",
  "properties": {
    "iso:country":"DE",
    "sg:address":"Merseburger Str. 109e",
    "sg:city":"Wei\u00dfenfels",
    "sg:phone":"+49 3443/279101",
    "sg:postcode":"06667",
    "sg:province":"Sachsen-Anhalt",
    "wof:name":"Jet-tankstelle",
    "wof:placetype":"venue"
},
  "geometry": {"coordinates":[11.9692869186,51.217540741],"type":"Point"}
}