{
  "type": "Feature",
  "properties": {
    "iso:country":"DE",
    "sg:address":"Reisbacher Str. 43",
    "sg:city":"Saarwellingen",
    "sg:phone":"+49 6838/2693",
    "sg:postcode":"66793",
    "sg:province":"Saarland",
    "wof:name":"Retter Gmbh",
    "wof:placetype":"venue"
},
  "geometry": {"coordinates":[6.8327407837,49.3514671326],"type":"Point"}
}