{
  "type": "Feature",
  "properties": {
    "iso:country":"DE",
    "sg:address":"Karl-Arnold-Str. 17",
    "sg:city":"Meerbusch",
    "sg:phone":"+49 2132/70141",
    "sg:postcode":"40667",
    "sg:province":"Nordrhein-Westfalen",
    "wof:name":"Manfred Polaczek Ingenieur",
    "wof:placetype":"venue"
},
  "geometry": {"coordinates":[6.6931910515,51.2416992188],"type":"Point"}
}