{
  "type": "Feature",
  "properties": {
    "iso:country":"DE",
    "sg:address":"Baumschulenweg 26",
    "sg:city":"Hiddenhausen",
    "sg:phone":"+49 5223/84949",
    "sg:postcode":"32120",
    "sg:province":"Nordrhein-Westfalen",
    "wof:name":"Bergmeier Elementebau",
    "wof:placetype":"venue"
},
  "geometry": {"coordinates":[8.623202,52.179596],"type":"Point"}
}