{
  "type": "Feature",
  "properties": {
    "iso:country":"DE",
    "sg:address":"Marlowring 22",
    "sg:city":"Hamburg",
    "sg:phone":"+49 40/8505766",
    "sg:postcode":"22525",
    "sg:province":"Hamburg",
    "wof:name":"Erich Berg",
    "wof:placetype":"venue"
},
  "geometry": {"coordinates":[9.927287,53.573231],"type":"Point"}
}