{
  "type": "Feature",
  "properties": {
    "iso:country":"DE",
    "sg:address":"Kierweg 10",
    "sg:city":"Simmerath",
    "sg:phone":"+49 2473/5046",
    "sg:postcode":"52152",
    "sg:province":"Nordrhein-Westfalen",
    "wof:name":"Kuss",
    "wof:placetype":"venue"
},
  "geometry": {"coordinates":[6.377991,50.624294],"type":"Point"}
}