{
  "type": "Feature",
  "properties": {
    "iso:country":"DE",
    "sg:address":"Oberd\u00fcsseler Weg 77",
    "sg:city":"W\u00fclfrath",
    "sg:phone":"+49 202/2729371",
    "sg:postcode":"42489",
    "sg:province":"Nordrhein-Westfalen",
    "wof:name":"Haus-karl-heinersdorff Seniorenheim",
    "wof:placetype":"venue"
},
  "geometry": {"coordinates":[7.090268,51.282711],"type":"Point"}
}