{
  "type": "Feature",
  "properties": {
    "iso:country":"DE",
    "sg:address":"Gladbacher Str. 58",
    "sg:city":"D\u00fcsseldorf",
    "sg:phone":"+49 211/306627",
    "sg:postcode":"40219",
    "sg:province":"Nordrhein-Westfalen",
    "wof:name":"H. J. Ochsenfort Gmbh",
    "wof:placetype":"venue"
},
  "geometry": {"coordinates":[6.757288,51.212055],"type":"Point"}
}