{
  "type": "Feature",
  "properties": {
    "iso:country":"DE",
    "sg:address":"K\u00f6lner Str. 291b",
    "sg:city":"D\u00fcsseldorf",
    "sg:phone":"+49 211/782093",
    "sg:postcode":"40227",
    "sg:province":"Nordrhein-Westfalen",
    "wof:name":"Renate Kaufmann-marx",
    "wof:placetype":"venue"
},
  "geometry": {"coordinates":[6.8056120872,51.2136154175],"type":"Point"}
}