{
  "type": "Feature",
  "properties": {
    "iso:country":"DE",
    "sg:address":"Moseluferstr. 22",
    "sg:city":"Neef",
    "sg:phone":"+49 6542/21019",
    "sg:postcode":"56858",
    "sg:province":"Rheinland-Pfalz",
    "wof:name":"Karl L\u00f6wen Weinanbau",
    "wof:placetype":"venue"
},
  "geometry": {"coordinates":[7.1363768578,50.0887641907],"type":"Point"}
}