{
  "type": "Feature",
  "properties": {
    "iso:country":"DE",
    "sg:address":"Pfahlb\u00fchlstr. 7",
    "sg:city":"Weinstadt",
    "sg:phone":"+49 7151/61603",
    "sg:postcode":"71384",
    "sg:province":"Baden-W\u00fcrttemberg",
    "wof:name":"C. Sigle",
    "wof:placetype":"venue"
},
  "geometry": {"coordinates":[9.3866796494,48.8171463013],"type":"Point"}
}