{
  "type": "Feature",
  "properties": {
    "iso:country":"DE",
    "sg:address":"M\u00f6rikestr. 4",
    "sg:city":"Heusweiler",
    "sg:phone":"+49 6806/5135",
    "sg:postcode":"66265",
    "sg:province":"Saarland",
    "wof:name":"Rainer Hilt Ingenieur",
    "wof:placetype":"venue"
},
  "geometry": {"coordinates":[6.9215259552,49.3339042664],"type":"Point"}
}