{
  "type": "Feature",
  "properties": {
    "iso:country":"DE",
    "sg:address":"Mainzer Str 115",
    "sg:city":"Bingen",
    "sg:phone":"+49 6721/14827",
    "sg:postcode":"55411",
    "sg:province":"Rheinland-Pfalz",
    "wof:name":"Quint Stahl-und Metallbau Inhaber Enk Gmbh",
    "wof:placetype":"venue"
},
  "geometry": {"coordinates":[7.918771,49.969624],"type":"Point"}
}