{
  "type": "Feature",
  "properties": {
    "iso:country":"DE",
    "sg:address":"Krumme Str. 1",
    "sg:city":"Sta\u00dffurt",
    "sg:phone":"+49 3925/622945",
    "sg:postcode":"39418",
    "sg:province":"Sachsen-Anhalt",
    "wof:name":"Thiele Und Stiens Architekten",
    "wof:placetype":"venue"
},
  "geometry": {"coordinates":[11.576514,51.855125],"type":"Point"}
}