{
  "type": "Feature",
  "properties": {
    "iso:country":"DE",
    "sg:address":"H\u00f6lderlinstr. 6",
    "sg:city":"Hamburg",
    "sg:phone":"+49 40/8226861",
    "sg:postcode":"22607",
    "sg:province":"Hamburg",
    "wof:name":"G\u00fcldenpfennig Bauges. Mbh",
    "wof:placetype":"venue"
},
  "geometry": {"coordinates":[9.868136,53.560425],"type":"Point"}
}