{
  "type": "Feature",
  "properties": {
    "iso:country":"DE",
    "sg:address":"Robert-Bosch-Str. 32",
    "sg:city":"Dreieich",
    "sg:postcode":"63303",
    "sg:province":"Hessen",
    "wof:name":"P-card System- Gmbh",
    "wof:placetype":"venue"
},
  "geometry": {"coordinates":[8.704831,50.03196],"type":"Point"}
}