{
  "type": "Feature",
  "properties": {
    "iso:country":"DE",
    "sg:address":"Donaustr. 75",
    "sg:city":"N\u00fcrnberg",
    "sg:phone":"+49 911/962880",
    "sg:postcode":"90451",
    "sg:province":"Bayern",
    "wof:name":"Gebr. Markewitsch Gmbh",
    "wof:placetype":"venue"
},
  "geometry": {"coordinates":[11.0643100739,49.4106521606],"type":"Point"}
}