{
  "type": "Feature",
  "properties": {
    "iso:country":"DE",
    "sg:address":"Marktplatz 3",
    "sg:city":"Hallstadt",
    "sg:phone":"+49 951/71325",
    "sg:postcode":"96103",
    "sg:province":"Bayern",
    "wof:name":"J\u00e4gers Urfa\u00df",
    "wof:placetype":"venue"
},
  "geometry": {"coordinates":[10.8754501343,49.9291496277],"type":"Point"}
}