{
  "type": "Feature",
  "properties": {
    "iso:country":"DE",
    "sg:address":"Hauptstr. 44",
    "sg:city":"Heek",
    "sg:phone":"+49 2568/1262",
    "sg:postcode":"48619",
    "sg:province":"Nordrhein-Westfalen",
    "wof:name":"Johann L\u00f6hring Kohlen-u. Brennstoff-handlung",
    "wof:placetype":"venue"
},
  "geometry": {"coordinates":[7.1013860703,52.1341133118],"type":"Point"}
}