{
  "type": "Feature",
  "properties": {
    "iso:country":"DE",
    "sg:address":"Quellenstr. 27",
    "sg:city":"Lage",
    "sg:phone":"+49 5232/87858",
    "sg:postcode":"32791",
    "sg:province":"Nordrhein-Westfalen",
    "wof:name":"Owb Gesellschaft F\u00fcr Baustoffrecycling Mbh",
    "wof:placetype":"venue"
},
  "geometry": {"coordinates":[8.7661819458,51.9325866699],"type":"Point"}
}