{
  "type": "Feature",
  "properties": {
    "iso:country":"DE",
    "sg:city":"M\u00fcnster",
    "sg:postcode":"48145",
    "sg:province":"Nordrhein-Westfalen",
    "wof:name":"Www.lolita-cam.de",
    "wof:placetype":"venue"
},
  "geometry": {"coordinates":[7.617817,51.96302],"type":"Point"}
}