{
  "type": "Feature",
  "properties": {
    "iso:country":"DE",
    "sg:address":"Am Eggenkamp 8",
    "sg:city":"Greven",
    "sg:phone":"+49 2571/5070",
    "sg:postcode":"48268",
    "sg:province":"Nordrhein-Westfalen",
    "wof:name":"Gefriertrocknung Greven Gmbh",
    "wof:placetype":"venue"
},
  "geometry": {"coordinates":[7.6230301857,52.1045799255],"type":"Point"}
}