{
  "type": "Feature",
  "properties": {
    "iso:country":"DE",
    "sg:address":"Keplerstr 30",
    "sg:city":"Frankfurt",
    "sg:phone":"+49 4969/9433490",
    "sg:postcode":"60318",
    "sg:province":"Hessen",
    "wof:name":"Wagner Alliance",
    "wof:placetype":"venue"
},
  "geometry": {"coordinates":[8.682917,50.125313],"type":"Point"}
}