{
  "type": "Feature",
  "properties": {
    "iso:country":"DE",
    "sg:address":"Goslarsche Str. 60",
    "sg:city":"Langelsheim",
    "sg:phone":"+49 5326/8187",
    "sg:postcode":"38685",
    "sg:province":"Niedersachsen",
    "wof:name":"Pizzeria Capri",
    "wof:placetype":"venue"
},
  "geometry": {"coordinates":[10.3674478531,51.9296607971],"type":"Point"}
}