{
  "type": "Feature",
  "properties": {
    "iso:country":"DE",
    "sg:address":"Berliner Str. 81",
    "sg:city":"L\u00fcdenscheid",
    "sg:phone":"+49 2351/85650",
    "sg:postcode":"58511",
    "sg:province":"Nordrhein-Westfalen",
    "wof:name":"Simon",
    "wof:placetype":"venue"
},
  "geometry": {"coordinates":[7.652589798,51.2206916809],"type":"Point"}
}