{
  "type": "Feature",
  "properties": {
    "iso:country":"DE",
    "sg:address":"Am Hainberg 3 a",
    "sg:city":"K\u00f6nigstein",
    "sg:phone":"+49 6174/1425",
    "sg:postcode":"61462",
    "sg:province":"Hessen",
    "wof:name":"Karin J\u00fcttner Rechtsanw\u00e4ltin",
    "wof:placetype":"venue"
},
  "geometry": {"coordinates":[8.4781646729,50.1918106079],"type":"Point"}
}