{
  "type": "Feature",
  "properties": {
    "iso:country":"DE",
    "sg:address":"Nordwall 1",
    "sg:city":"Schwerte",
    "sg:postcode":"58239",
    "sg:province":"Nordrhein-Westfalen",
    "wof:name":"Bul Dialyse- Und Sozialzentrum Gmbh & Co. Kg",
    "wof:placetype":"venue"
},
  "geometry": {"coordinates":[7.5662770271,51.4416770935],"type":"Point"}
}