{
  "type": "Feature",
  "properties": {
    "iso:country":"DE",
    "sg:address":"Lise-Meitner-Str. 20",
    "sg:city":"Pulheim",
    "sg:phone":"+49 2234/98710",
    "sg:postcode":"50259",
    "sg:province":"Nordrhein-Westfalen",
    "wof:name":"Reinhold Kluck Gmbh",
    "wof:placetype":"venue"
},
  "geometry": {"coordinates":[6.809398,50.961063],"type":"Point"}
}