{
  "type": "Feature",
  "properties": {
    "iso:country":"DE",
    "sg:address":"Kurze Str. 24",
    "sg:city":"Abbenrode",
    "sg:phone":"+49 39452/86057",
    "sg:postcode":"38871",
    "sg:province":"Sachsen-Anhalt",
    "wof:name":"Michael Brandes",
    "wof:placetype":"venue"
},
  "geometry": {"coordinates":[10.624575,51.928585],"type":"Point"}
}