{
  "type": "Feature",
  "properties": {
    "iso:country":"DE",
    "sg:address":"Eichendorffstr. 6",
    "sg:city":"Neuhausen",
    "sg:phone":"+49 7234/981123",
    "sg:postcode":"75242",
    "sg:province":"Baden-W\u00fcrttemberg",
    "wof:name":"Krankenpflegeverein Pflegedienstleitung",
    "wof:placetype":"venue"
},
  "geometry": {"coordinates":[8.792212,48.812981],"type":"Point"}
}