{
  "type": "Feature",
  "properties": {
    "iso:country":"DE",
    "sg:address":"M\u00f6nchbruchstr. 15a",
    "sg:city":"R\u00fcsselsheim",
    "sg:phone":"+49 6142/958080",
    "sg:postcode":"65428",
    "sg:province":"Hessen",
    "wof:name":"Ricken Oruc Metzgerei Gmbh",
    "wof:placetype":"venue"
},
  "geometry": {"coordinates":[8.4597349167,49.9850502014],"type":"Point"}
}