{
  "type": "Feature",
  "properties": {
    "iso:country":"DE",
    "sg:address":"Walkstr. 29",
    "sg:city":"Markt Schwaben",
    "sg:phone":"+49 8121/1299",
    "sg:postcode":"85570",
    "sg:province":"Bayern",
    "wof:name":"Isola",
    "wof:placetype":"venue"
},
  "geometry": {"coordinates":[11.8798913956,48.190284729],"type":"Point"}
}