{
  "type": "Feature",
  "properties": {
    "iso:country":"DE",
    "sg:address":"Str\u00fcmpfelbacher Str. 64",
    "sg:city":"Weinstadt",
    "sg:phone":"+49 7151/606102",
    "sg:postcode":"71384",
    "sg:province":"Baden-W\u00fcrttemberg",
    "wof:name":"P. K. Dotten Und Raab-fichtner Rechtsanw\u00e4lte",
    "wof:placetype":"venue"
},
  "geometry": {"coordinates":[9.3598089218,48.811126709],"type":"Point"}
}