{
  "type": "Feature",
  "properties": {
    "iso:country":"DE",
    "sg:address":"Gerberm\u00fchlstr. 342",
    "sg:city":"Frankfurt",
    "sg:postcode":"60594",
    "sg:province":"Hessen",
    "wof:name":"Ke\u00dfler Immobilien Gmbh",
    "wof:placetype":"venue"
},
  "geometry": {"coordinates":[8.7030200958,50.1042518616],"type":"Point"}
}