{
  "type": "Feature",
  "properties": {
    "iso:country":"DE",
    "sg:address":"Lupinenstr. 3",
    "sg:city":"Iserlohn",
    "sg:phone":"+49 2371/41444",
    "sg:postcode":"58640",
    "sg:province":"Nordrhein-Westfalen",
    "wof:name":"Ruth Schmidt",
    "wof:placetype":"venue"
},
  "geometry": {"coordinates":[7.7163500786,51.4126777649],"type":"Point"}
}