{
  "type": "Feature",
  "properties": {
    "iso:country":"DE",
    "sg:address":"Kaiserstr. 68",
    "sg:city":"Kirkel",
    "sg:phone":"+49 6849/1717",
    "sg:postcode":"66459",
    "sg:province":"Saarland",
    "wof:name":"J. Erbelding Lebensmittelgro\u00dfhandelung Gmbh",
    "wof:placetype":"venue"
},
  "geometry": {"coordinates":[7.219329834,49.2801818848],"type":"Point"}
}