{
  "type": "Feature",
  "properties": {
    "iso:country":"DE",
    "sg:address":"Kasseler Landstr. 91",
    "sg:city":"G\u00f6ttingen",
    "sg:phone":"+49 551/92264",
    "sg:postcode":"37081",
    "sg:province":"Niedersachsen",
    "wof:name":"Eisenpfanne",
    "wof:placetype":"venue"
},
  "geometry": {"coordinates":[9.8924303055,51.5288505554],"type":"Point"}
}