{
  "type": "Feature",
  "properties": {
    "iso:country":"DE",
    "sg:address":"Auf dem Berg 37",
    "sg:city":"Kirchheim",
    "sg:phone":"+49 7021/44744",
    "sg:postcode":"73230",
    "sg:province":"Baden-W\u00fcrttemberg",
    "wof:name":"R. Und H. P. Hamann Immobilienmakler",
    "wof:placetype":"venue"
},
  "geometry": {"coordinates":[9.4176559448,48.6541557312],"type":"Point"}
}