{
  "type": "Feature",
  "properties": {
    "iso:country":"DE",
    "sg:address":"Bosenheimer Str. 214",
    "sg:city":"Bad Kreuznach",
    "sg:postcode":"55543",
    "sg:province":"Rheinland-Pfalz",
    "wof:name":"Hela Baupark",
    "wof:placetype":"venue"
},
  "geometry": {"coordinates":[7.8863611221,49.8471260071],"type":"Point"}
}