{
  "type": "Feature",
  "properties": {
    "iso:country":"DE",
    "sg:address":"Schillerstr. 5",
    "sg:city":"Bad Pyrmont",
    "sg:phone":"+49 5281/2129",
    "sg:postcode":"31812",
    "sg:province":"Niedersachsen",
    "wof:name":"Restaurant Balkan-stube",
    "wof:placetype":"venue"
},
  "geometry": {"coordinates":[9.2432527542,51.9836502075],"type":"Point"}
}