{
  "type": "Feature",
  "properties": {
    "iso:country":"DE",
    "sg:address":"08539",
    "sg:city":"Rodau",
    "sg:phone":"+49 37435/5241",
    "sg:postcode":"08539",
    "sg:province":"Sachsen",
    "wof:name":"Freibad",
    "wof:placetype":"venue"
},
  "geometry": {"coordinates":[11.9915704727,50.5054016113],"type":"Point"}
}