{
  "type": "Feature",
  "properties": {
    "iso:country":"DE",
    "sg:address":"Rayskistr. 1-5",
    "sg:city":"Dresden",
    "sg:phone":"+49 351/2706288",
    "sg:postcode":"01219",
    "sg:province":"Sachsen",
    "wof:name":"Klaus Jentsch",
    "wof:placetype":"venue"
},
  "geometry": {"coordinates":[13.76848,51.026989],"type":"Point"}
}