{
  "type": "Feature",
  "properties": {
    "iso:country":"DE",
    "sg:address":"Beiersdorfer Str. 8",
    "sg:city":"Sch\u00f6nbach",
    "sg:phone":"+49 35872/33322",
    "sg:postcode":"02708",
    "sg:province":"Sachsen",
    "wof:name":"Detlef Schmidt",
    "wof:placetype":"venue"
},
  "geometry": {"coordinates":[14.5711984634,51.0612373352],"type":"Point"}
}