{
  "type": "Feature",
  "properties": {
    "iso:country":"DE",
    "sg:address":"Bahlenstr. 100",
    "sg:city":"Diepenau",
    "sg:phone":"+49 5775/252",
    "sg:postcode":"31603",
    "sg:province":"Niedersachsen",
    "wof:name":"Willy Nordhorn",
    "wof:placetype":"venue"
},
  "geometry": {"coordinates":[8.7230901718,52.4274597168],"type":"Point"}
}