{
  "type": "Feature",
  "properties": {
    "iso:country":"DE",
    "sg:address":"Karlstr. 22",
    "sg:city":"Langenfeld",
    "sg:phone":"+49 2173/77104",
    "sg:postcode":"40764",
    "sg:province":"Nordrhein-Westfalen",
    "wof:name":"Georg Sczodrok Steuerbevollm\u00e4chtigter",
    "wof:placetype":"venue"
},
  "geometry": {"coordinates":[6.9464612007,51.1059837341],"type":"Point"}
}