{
  "type": "Feature",
  "properties": {
    "iso:country":"DE",
    "sg:address":"Niedereschacher Str. 44",
    "sg:city":"Villingen-Schwenningen",
    "sg:phone":"+49 7721/70594",
    "sg:postcode":"78052",
    "sg:province":"Baden-W\u00fcrttemberg",
    "wof:name":"Dieter Riegger Landhandel",
    "wof:placetype":"venue"
},
  "geometry": {"coordinates":[8.477319,48.108006],"type":"Point"}
}