{
  "type": "Feature",
  "properties": {
    "iso:country":"DE",
    "sg:address":"Stockfeldstr. 5a",
    "sg:city":"Herbolzheim",
    "sg:postcode":"79336",
    "sg:province":"Baden-W\u00fcrttemberg",
    "wof:name":"General-host-services Gmbh",
    "wof:placetype":"venue"
},
  "geometry": {"coordinates":[7.7646369934,48.2258338928],"type":"Point"}
}