{
  "type": "Feature",
  "properties": {
    "iso:country":"DE",
    "sg:address":"Obstmarschenweg 259",
    "sg:city":"Stade",
    "sg:phone":"+49 4146/422",
    "sg:postcode":"21683",
    "sg:province":"Niedersachsen",
    "wof:name":"Werner Meyer",
    "wof:placetype":"venue"
},
  "geometry": {"coordinates":[9.47898,53.637482],"type":"Point"}
}