{
  "type": "Feature",
  "properties": {
    "iso:country":"DE",
    "sg:address":"M\u00fcnsterstr. 44",
    "sg:city":"Nottuln",
    "sg:phone":"+49 2509/226",
    "sg:postcode":"48301",
    "sg:province":"Nordrhein-Westfalen",
    "wof:name":"H. Kollenberg",
    "wof:placetype":"venue"
},
  "geometry": {"coordinates":[7.434322834,51.9002571106],"type":"Point"}
}