{
  "type": "Feature",
  "properties": {
    "iso:country":"DE",
    "sg:address":"Untere M\u00fchle",
    "sg:city":"Dillst\u00e4dt",
    "sg:phone":"+49 36846/61439",
    "sg:postcode":"98530",
    "sg:province":"Th\u00fcringen",
    "wof:name":"M. Friedrich",
    "wof:placetype":"venue"
},
  "geometry": {"coordinates":[10.5342845917,50.5799255371],"type":"Point"}
}