{
  "type": "Feature",
  "properties": {
    "iso:country":"DE",
    "sg:address":"Gasselstiege 22",
    "sg:city":"M\u00fcnster",
    "sg:phone":"+49 251/296382",
    "sg:postcode":"48159",
    "sg:province":"Nordrhein-Westfalen",
    "wof:name":"Heidi Sievert Tanz- Und Ballettschule",
    "wof:placetype":"venue"
},
  "geometry": {"coordinates":[7.6065201759,51.9763298035],"type":"Point"}
}