{
  "type": "Feature",
  "properties": {
    "iso:country":"DE",
    "sg:address":"Neureuthstr. 23",
    "sg:city":"Tegernsee",
    "sg:phone":"+49 8022/1820",
    "sg:postcode":"83684",
    "sg:province":"Bayern",
    "wof:name":"Hotel Bayern",
    "wof:placetype":"venue"
},
  "geometry": {"coordinates":[11.7582187653,47.7162818909],"type":"Point"}
}