{
  "type": "Feature",
  "properties": {
    "iso:country":"DE",
    "sg:address":"Wagenfeldstr. 18",
    "sg:city":"Neuenkirchen",
    "sg:phone":"+49 5973/94820",
    "sg:postcode":"48485",
    "sg:province":"Nordrhein-Westfalen",
    "wof:name":"Klei - Hues Betonbauteile Verwaltungs Gmbh",
    "wof:placetype":"venue"
},
  "geometry": {"coordinates":[7.403055191,52.210231781],"type":"Point"}
}