{
  "type": "Feature",
  "properties": {
    "iso:country":"DE",
    "sg:address":"Lange Str. 20",
    "sg:city":"Niesky",
    "sg:phone":"+49 3588/207744",
    "sg:postcode":"02906",
    "sg:province":"Sachsen",
    "wof:name":"Werner M\u00fcller",
    "wof:placetype":"venue"
},
  "geometry": {"coordinates":[14.7353439331,51.2884941101],"type":"Point"}
}