{
  "type": "Feature",
  "properties": {
    "iso:country":"DE",
    "sg:address":"Adolfstr. 26",
    "sg:city":"Westerburg",
    "sg:phone":"+49 2663/917937",
    "sg:postcode":"56457",
    "sg:province":"Rheinland-Pfalz",
    "wof:name":"Der Handyladen Inh. Petra Simon",
    "wof:placetype":"venue"
},
  "geometry": {"coordinates":[7.9719009399,50.5617408752],"type":"Point"}
}