{
  "type": "Feature",
  "properties": {
    "iso:country":"DE",
    "sg:address":"Wiesenweg 9",
    "sg:city":"Ihringen",
    "sg:phone":"+49 7668/5973",
    "sg:postcode":"79241",
    "sg:province":"Baden-W\u00fcrttemberg",
    "wof:name":"Jutta Strobel",
    "wof:placetype":"venue"
},
  "geometry": {"coordinates":[7.682456,48.04924],"type":"Point"}
}