{
  "type": "Feature",
  "properties": {
    "iso:country":"DE",
    "sg:address":"Sch\u00fctzenstr. 57",
    "sg:city":"Ochtrup",
    "sg:phone":"+49 2553/3166",
    "sg:postcode":"48607",
    "sg:province":"Nordrhein-Westfalen",
    "wof:name":"Franz Wesbuer",
    "wof:placetype":"venue"
},
  "geometry": {"coordinates":[7.1966719627,52.2012786865],"type":"Point"}
}