{
  "type": "Feature",
  "properties": {
    "iso:country":"DE",
    "sg:address":"Niels-Bohr-Ring 2",
    "sg:city":"L\u00fcbeck",
    "sg:postcode":"23568",
    "sg:province":"Schleswig-Holstein",
    "wof:name":"Hanse Party- Und Festausstatter Gmbh",
    "wof:placetype":"venue"
},
  "geometry": {"coordinates":[10.707483,53.896633],"type":"Point"}
}