{
  "type": "Feature",
  "properties": {
    "iso:country":"DE",
    "sg:address":"Daimlerstr. 9",
    "sg:city":"Korb",
    "sg:phone":"+49 7151/31812",
    "sg:postcode":"71404",
    "sg:province":"Baden-W\u00fcrttemberg",
    "wof:name":"Siegfried Haug",
    "wof:placetype":"venue"
},
  "geometry": {"coordinates":[9.365991,48.837509],"type":"Point"}
}