{
  "type": "Feature",
  "properties": {
    "iso:country":"DE",
    "sg:address":"Waldstr. 6",
    "sg:city":"Ziegenr\u00fcck",
    "sg:phone":"+49 36483/22651",
    "sg:postcode":"07924",
    "sg:province":"Th\u00fcringen",
    "wof:name":"Ingolf Wei\u00df Architekt",
    "wof:placetype":"venue"
},
  "geometry": {"coordinates":[11.651385,50.606262],"type":"Point"}
}