{
  "type": "Feature",
  "properties": {
    "iso:country":"DE",
    "sg:address":"Kidlerstrasse 1",
    "sg:city":"M\u00fcnchen",
    "sg:phone":"+49 89/9583850",
    "sg:postcode":"81371",
    "sg:province":"Bayern",
    "wof:name":"Cup-service Gmbh // Drink-man (r)",
    "wof:placetype":"venue"
},
  "geometry": {"coordinates":[11.542707,48.121967],"type":"Point"}
}