{
  "type": "Feature",
  "properties": {
    "iso:country":"DE",
    "sg:address":"Lausitzer Str. 46",
    "sg:city":"Berlin",
    "sg:phone":"+49 30/6112008",
    "sg:postcode":"10999",
    "sg:province":"Berlin",
    "wof:name":"Neriman Fahrali",
    "wof:placetype":"venue"
},
  "geometry": {"coordinates":[13.4292736053,52.4975662231],"type":"Point"}
}