{
  "type": "Feature",
  "properties": {
    "iso:country":"DE",
    "sg:address":"Hauptstr. 31",
    "sg:city":"Mainhardt",
    "sg:phone":"+49 7903/2237",
    "sg:postcode":"74535",
    "sg:province":"Baden-W\u00fcrttemberg",
    "wof:name":"Alfred K\u00fcbler",
    "wof:placetype":"venue"
},
  "geometry": {"coordinates":[9.5571365356,49.0789871216],"type":"Point"}
}