{
  "type": "Feature",
  "properties": {
    "iso:country":"DE",
    "sg:address":"Friedrich-Bergius-Str. 10",
    "sg:city":"Grevenbroich",
    "sg:phone":"+49 2181/27010",
    "sg:postcode":"41516",
    "sg:province":"Nordrhein-Westfalen",
    "wof:name":"Dunlop-enerka Gesellschaft F\u00fcr Gummi- Und Kunststoff Mbh",
    "wof:placetype":"venue"
},
  "geometry": {"coordinates":[6.632915,51.110325],"type":"Point"}
}