{
  "type": "Feature",
  "properties": {
    "iso:country":"DE",
    "sg:address":"Isabellastr. 6",
    "sg:city":"M\u00fcnchen",
    "sg:phone":"+49 89/2721309",
    "sg:postcode":"80798",
    "sg:province":"Bayern",
    "wof:name":"Caravanserai Heidrun Niemann",
    "wof:placetype":"venue"
},
  "geometry": {"coordinates":[11.57049,48.155762],"type":"Point"}
}