{
  "type": "Feature",
  "properties": {
    "iso:country":"DE",
    "sg:city":"Nienst\u00e4dt",
    "sg:postcode":"31688",
    "sg:province":"Niedersachsen",
    "wof:name":"Druck Werk Peter-michael-thiem E. K.",
    "wof:placetype":"venue"
},
  "geometry": {"coordinates":[9.166137,52.294262],"type":"Point"}
}