{
  "type": "Feature",
  "properties": {
    "iso:country":"DE",
    "sg:address":"Benesisstr. 57",
    "sg:city":"K\u00f6ln",
    "sg:phone":"+49 221/256104",
    "sg:postcode":"50672",
    "sg:province":"Nordrhein-Westfalen",
    "wof:name":"Amato Mio",
    "wof:placetype":"venue"
},
  "geometry": {"coordinates":[6.9420771599,50.9379806519],"type":"Point"}
}