{
  "type": "Feature",
  "properties": {
    "iso:country":"DE",
    "sg:address":"Hoopter Elbdeich 124",
    "sg:city":"Winsen",
    "sg:phone":"+49 4171/4702",
    "sg:postcode":"21423",
    "sg:province":"Niedersachsen",
    "wof:name":"Heinrich Beecken",
    "wof:placetype":"venue"
},
  "geometry": {"coordinates":[10.1472,53.407185],"type":"Point"}
}