{
  "type": "Feature",
  "properties": {
    "iso:country":"DE",
    "sg:address":"Tattersall Stra\u00dfe 8",
    "sg:city":"Mannheim",
    "sg:phone":"+49 621/102210",
    "sg:postcode":"68165",
    "sg:province":"Baden-W\u00fcrttemberg",
    "wof:name":"Friseur-greving In Mannheim Und Deidesheim (pfalz)",
    "wof:placetype":"venue"
},
  "geometry": {"coordinates":[8.47346,49.48172],"type":"Point"}
}