{
  "type": "Feature",
  "properties": {
    "iso:country":"DE",
    "sg:address":"Christoffelstr. 34",
    "sg:city":"M\u00f6nchengladbach",
    "sg:phone":"+49 2166/47403",
    "sg:postcode":"41236",
    "sg:province":"Nordrhein-Westfalen",
    "wof:name":"Ev. Pfarramt Rheydt",
    "wof:placetype":"venue"
},
  "geometry": {"coordinates":[6.4450769424,51.1531677246],"type":"Point"}
}