{
  "type": "Feature",
  "properties": {
    "iso:country":"DE",
    "sg:address":"Gartenstr. 71",
    "sg:city":"Spaichingen",
    "sg:phone":"+49 7424/5808",
    "sg:postcode":"78549",
    "sg:province":"Baden-W\u00fcrttemberg",
    "wof:name":"A. Dettling",
    "wof:placetype":"venue"
},
  "geometry": {"coordinates":[8.7401895523,48.0764694214],"type":"Point"}
}