{
  "type": "Feature",
  "properties": {
    "iso:country":"DE",
    "sg:address":"Industriestr. 85/95",
    "sg:city":"Leipzig",
    "sg:postcode":"04229",
    "sg:province":"Sachsen",
    "wof:name":"Winfried Binger",
    "wof:placetype":"venue"
},
  "geometry": {"coordinates":[12.330641,51.328037],"type":"Point"}
}