{
  "type": "Feature",
  "properties": {
    "iso:country":"DE",
    "sg:address":"Am J\u00e4ger 35",
    "sg:city":"Wesel",
    "sg:phone":"+49 2859/17274",
    "sg:postcode":"46487",
    "sg:province":"Nordrhein-Westfalen",
    "wof:name":"J & J Immobilien Gmbh",
    "wof:placetype":"venue"
},
  "geometry": {"coordinates":[6.550332,51.69117],"type":"Point"}
}