{
  "type": "Feature",
  "properties": {
    "iso:country":"DE",
    "sg:address":"An der Schlo\u00dffabrik 27",
    "sg:city":"H\u00fcckeswagen",
    "sg:phone":"+49 2192/5778",
    "sg:postcode":"42499",
    "sg:province":"Nordrhein-Westfalen",
    "wof:name":"Frank Hunker Bedachungs Gmbh",
    "wof:placetype":"venue"
},
  "geometry": {"coordinates":[7.3517680168,51.1403656006],"type":"Point"}
}