{
  "type": "Feature",
  "properties": {
    "iso:country":"DE",
    "sg:address":"Bennewohlder Weg 9",
    "sg:city":"Nordhastedt",
    "sg:phone":"+49 4804/858",
    "sg:postcode":"25785",
    "sg:province":"Schleswig-Holstein",
    "wof:name":"Claus-otto Clau\u00dfen",
    "wof:placetype":"venue"
},
  "geometry": {"coordinates":[9.184102,54.17812],"type":"Point"}
}