{
  "type": "Feature",
  "properties": {
    "iso:country":"DE",
    "sg:address":"Am Markt 16",
    "sg:city":"Stadthagen",
    "sg:phone":"+49 5721/1859",
    "sg:postcode":"31655",
    "sg:province":"Niedersachsen",
    "wof:name":"Fuji Bilder Center",
    "wof:placetype":"venue"
},
  "geometry": {"coordinates":[9.203684,52.320206],"type":"Point"}
}