{
  "type": "Feature",
  "properties": {
    "iso:country":"DE",
    "sg:address":"Kathi-Kobus-Str. 20-24",
    "sg:city":"M\u00fcnchen",
    "sg:postcode":"80797",
    "sg:province":"Bayern",
    "wof:name":"Zwei P Gmbh",
    "wof:placetype":"venue"
},
  "geometry": {"coordinates":[11.5580215454,48.159866333],"type":"Point"}
}