{
  "type": "Feature",
  "properties": {
    "iso:country":"DE",
    "sg:address":"Friedrich-Engels-Str. 72",
    "sg:city":"Wildau",
    "sg:phone":"+49 3375/504000",
    "sg:postcode":"15745",
    "sg:province":"Brandenburg",
    "wof:name":"Vega Komforthaus Gmbh",
    "wof:placetype":"venue"
},
  "geometry": {"coordinates":[13.637891,52.325874],"type":"Point"}
}