{
  "type": "Feature",
  "properties": {
    "iso:country":"DE",
    "sg:address":"Max-Stromeyer-Str. 108",
    "sg:city":"Konstanz",
    "sg:phone":"+49 7531/898116",
    "sg:postcode":"78467",
    "sg:province":"Baden-W\u00fcrttemberg",
    "wof:name":"Stadler Verlagsgesellschaft Mbh",
    "wof:placetype":"venue"
},
  "geometry": {"coordinates":[9.167218,47.674217],"type":"Point"}
}