{
  "type": "Feature",
  "properties": {
    "iso:country":"DE",
    "sg:address":"Traminer Str. 13",
    "sg:city":"Friedberg",
    "sg:phone":"+49 821/607328",
    "sg:postcode":"86316",
    "sg:province":"Bayern",
    "wof:name":"S.-a. Hwang-nitzschke Masseur",
    "wof:placetype":"venue"
},
  "geometry": {"coordinates":[10.997926,48.361843],"type":"Point"}
}