{
  "type": "Feature",
  "properties": {
    "iso:country":"DE",
    "sg:address":"Hoherainstr. 21",
    "sg:city":"Gladenbach",
    "sg:phone":"+49 6462/7996",
    "sg:postcode":"35075",
    "sg:province":"Hessen",
    "wof:name":"August Wagner",
    "wof:placetype":"venue"
},
  "geometry": {"coordinates":[8.580308,50.772785],"type":"Point"}
}