{
  "type": "Feature",
  "properties": {
    "iso:country":"DE",
    "sg:address":"Karl-Jarres-Str. 131",
    "sg:city":"Duisburg",
    "sg:phone":"+49 203/660759",
    "sg:postcode":"47053",
    "sg:province":"Nordrhein-Westfalen",
    "wof:name":"B\u00f6ninger M\u00fchle",
    "wof:placetype":"venue"
},
  "geometry": {"coordinates":[6.7623181343,51.4195861816],"type":"Point"}
}