{
  "type": "Feature",
  "properties": {
    "iso:country":"DE",
    "sg:address":"Wilhelminenstr. 14",
    "sg:city":"N\u00fcrnberg",
    "sg:phone":"+49 911/4719017",
    "sg:postcode":"90461",
    "sg:province":"Bayern",
    "wof:name":"Pilsbar Schnecke",
    "wof:placetype":"venue"
},
  "geometry": {"coordinates":[11.0920543671,49.4394378662],"type":"Point"}
}