{
  "type": "Feature",
  "properties": {
    "iso:country":"DE",
    "sg:address":"Lommatzscher Str. 4",
    "sg:city":"Leuben-Schleinitz",
    "sg:phone":"+49 35241/58707",
    "sg:postcode":"01623",
    "sg:province":"Sachsen",
    "wof:name":"H. Pfennig",
    "wof:placetype":"venue"
},
  "geometry": {"coordinates":[13.29385,51.164791],"type":"Point"}
}