{
  "type": "Feature",
  "properties": {
    "iso:country":"DE",
    "sg:address":"Mozartstr. 76",
    "sg:city":"Mettmann",
    "sg:postcode":"40822",
    "sg:province":"Nordrhein-Westfalen",
    "wof:name":"Puk Advance Verm\u00f6gensverwatlung Gmbh",
    "wof:placetype":"venue"
},
  "geometry": {"coordinates":[6.9807958603,51.240814209],"type":"Point"}
}