{
  "type": "Feature",
  "properties": {
    "iso:country":"DE",
    "sg:address":"Bockelsdorf 39",
    "sg:city":"Billerbeck",
    "sg:phone":"+49 2543/25345",
    "sg:postcode":"48727",
    "sg:province":"Nordrhein-Westfalen",
    "wof:name":"Ludger Ahlers",
    "wof:placetype":"venue"
},
  "geometry": {"coordinates":[7.3177537918,51.9874801636],"type":"Point"}
}