{
  "type": "Feature",
  "properties": {
    "iso:country":"DE",
    "sg:address":"Feldstrasse 18",
    "sg:city":"Hildesheim",
    "sg:phone":"+49 5121/884131",
    "sg:postcode":"31141",
    "sg:province":"Niedersachsen",
    "wof:name":"Webconcept-e: Alles F\u00fcr Die Internet-pr\u00e4sentation",
    "wof:placetype":"venue"
},
  "geometry": {"coordinates":[9.9633722305,52.1437683105],"type":"Point"}
}