{
  "type": "Feature",
  "properties": {
    "iso:country":"DE",
    "sg:address":"M\u00fchlgasse 1",
    "sg:city":"Sulzbach",
    "sg:phone":"+49 7193/900086",
    "sg:postcode":"71560",
    "sg:province":"Baden-W\u00fcrttemberg",
    "wof:name":"Eugen Metzger",
    "wof:placetype":"venue"
},
  "geometry": {"coordinates":[9.2226362228,49.3481712341],"type":"Point"}
}