{
  "type": "Feature",
  "properties": {
    "iso:country":"DE",
    "sg:address":"Sokelantstr. 35",
    "sg:city":"Hannover",
    "sg:phone":"+49 511/3585380",
    "sg:postcode":"30165",
    "sg:province":"Niedersachsen",
    "wof:name":"Bally Wulff Beteiligungs Gmbh",
    "wof:placetype":"venue"
},
  "geometry": {"coordinates":[9.705662,52.408974],"type":"Point"}
}