{
  "type": "Feature",
  "properties": {
    "iso:country":"DE",
    "sg:address":"Gleimstr. 31",
    "sg:city":"Halberstadt",
    "sg:phone":"+49 3941/24642",
    "sg:postcode":"38820",
    "sg:province":"Sachsen-Anhalt",
    "wof:name":"Horst Meldau",
    "wof:placetype":"venue"
},
  "geometry": {"coordinates":[11.0539865494,51.8995170593],"type":"Point"}
}