{
  "type": "Feature",
  "properties": {
    "iso:country":"DE",
    "sg:address":"Alte Allee 78",
    "sg:city":"M\u00fcnchen",
    "sg:postcode":"81245",
    "sg:province":"Bayern",
    "wof:name":"Ingenieur- Und Grafikb\u00fcro Reue Gmbh",
    "wof:placetype":"venue"
},
  "geometry": {"coordinates":[11.4459657669,48.1605911255],"type":"Point"}
}