{
  "type": "Feature",
  "properties": {
    "iso:country":"DE",
    "sg:address":"Lange Str. 67",
    "sg:city":"Sulingen",
    "sg:phone":"+49 4271/880",
    "sg:postcode":"27232",
    "sg:province":"Niedersachsen",
    "wof:name":"Stadtarchiv",
    "wof:placetype":"venue"
},
  "geometry": {"coordinates":[8.800199,52.681801],"type":"Point"}
}