{
  "type": "Feature",
  "properties": {
    "iso:country":"DE",
    "sg:address":"Stolberger Str. 125",
    "sg:city":"Nordhausen",
    "sg:postcode":"99734",
    "sg:province":"Th\u00fcringen",
    "wof:name":"Sabacos Baumaschinen Gmbh",
    "wof:placetype":"venue"
},
  "geometry": {"coordinates":[10.803233,51.51368],"type":"Point"}
}