{
  "type": "Feature",
  "properties": {
    "iso:country":"DE",
    "sg:address":"Drebkauer Str. 56",
    "sg:city":"Kolkwitz",
    "sg:phone":"+49 355/523196",
    "sg:postcode":"03099",
    "sg:province":"Brandenburg",
    "wof:name":"Jurisch & Junior",
    "wof:placetype":"venue"
},
  "geometry": {"coordinates":[14.2961,51.721512],"type":"Point"}
}