{
  "type": "Feature",
  "properties": {
    "iso:country":"DE",
    "sg:address":"Bussardstr. 5",
    "sg:city":"Herzogenrath",
    "sg:phone":"+49 2407/8224",
    "sg:postcode":"52134",
    "sg:province":"Nordrhein-Westfalen",
    "wof:name":"Hermann Stolten",
    "wof:placetype":"venue"
},
  "geometry": {"coordinates":[6.072421,50.835545],"type":"Point"}
}