{
  "type": "Feature",
  "properties": {
    "iso:country":"DE",
    "sg:address":"Lagesche Str. 12",
    "sg:city":"Detmold",
    "sg:phone":"+49 5231/974940",
    "sg:postcode":"32756",
    "sg:province":"Nordrhein-Westfalen",
    "wof:name":"Grosshandel F\u00fcr Malerbedarf Johann Willer Gmbh",
    "wof:placetype":"venue"
},
  "geometry": {"coordinates":[8.875849,51.943394],"type":"Point"}
}