{
  "type": "Feature",
  "properties": {
    "iso:country":"DE",
    "sg:address":"Hauptstr. 75",
    "sg:city":"Remchingen",
    "sg:phone":"+49 7232/734481",
    "sg:postcode":"75196",
    "sg:province":"Baden-W\u00fcrttemberg",
    "wof:name":"Schleicher Fashion",
    "wof:placetype":"venue"
},
  "geometry": {"coordinates":[8.572159,48.949581],"type":"Point"}
}