{
  "type": "Feature",
  "properties": {
    "iso:country":"DE",
    "sg:address":"Zainach 26",
    "sg:city":"Rott",
    "sg:phone":"+49 8039/2815",
    "sg:postcode":"83543",
    "sg:province":"Bayern",
    "wof:name":"Georg Und Antonie Ganslmaier",
    "wof:placetype":"venue"
},
  "geometry": {"coordinates":[12.15002,47.99509],"type":"Point"}
}