{
  "type": "Feature",
  "properties": {
    "iso:country":"DE",
    "sg:address":"Friedhofsweg 11",
    "sg:city":"Beckum",
    "sg:phone":"+49 2521/13984",
    "sg:postcode":"59269",
    "sg:province":"Nordrhein-Westfalen",
    "wof:name":"Franz-josef Knepper",
    "wof:placetype":"venue"
},
  "geometry": {"coordinates":[8.073846,51.78896],"type":"Point"}
}