{
  "type": "Feature",
  "properties": {
    "iso:country":"DE",
    "sg:address":"Hauptstr. 115",
    "sg:city":"Lemf\u00f6rde",
    "sg:phone":"+49 5443/327",
    "sg:postcode":"49448",
    "sg:province":"Niedersachsen",
    "wof:name":"F. Krummhauer",
    "wof:placetype":"venue"
},
  "geometry": {"coordinates":[8.3761606216,52.4653244019],"type":"Point"}
}