{
  "type": "Feature",
  "properties": {
    "iso:country":"DE",
    "sg:address":"Hauptstr. 21",
    "sg:city":"Wittgert",
    "sg:phone":"+49 2623/2251",
    "sg:postcode":"56237",
    "sg:province":"Rheinland-Pfalz",
    "wof:name":"Hehl Raucher Gmbh",
    "wof:placetype":"venue"
},
  "geometry": {"coordinates":[7.6976528168,50.4968223572],"type":"Point"}
}