{
  "type": "Feature",
  "properties": {
    "iso:country":"DE",
    "sg:address":"Rothenburgstr. 28",
    "sg:city":"Berlin",
    "sg:postcode":"12165",
    "sg:province":"Berlin",
    "wof:name":"Foss Baubetreuungs- Und Beteiligungs Gmbh",
    "wof:placetype":"venue"
},
  "geometry": {"coordinates":[13.315456,52.455521],"type":"Point"}
}