{
  "type": "Feature",
  "properties": {
    "iso:country":"DE",
    "sg:address":"Grimmestr. 17a",
    "sg:city":"Arnsberg",
    "sg:postcode":"59821",
    "sg:province":"Nordrhein-Westfalen",
    "wof:name":"Friedhelm F. M\u00f6ller",
    "wof:placetype":"venue"
},
  "geometry": {"coordinates":[8.062078476,51.4039573669],"type":"Point"}
}