{
  "type": "Feature",
  "properties": {
    "iso:country":"DE",
    "sg:address":"Tannenstr. 7",
    "sg:city":"Eltville",
    "sg:phone":"+49 6123/62905",
    "sg:postcode":"65346",
    "sg:province":"Hessen",
    "wof:name":"P. Und E. Koch Weinanbau",
    "wof:placetype":"venue"
},
  "geometry": {"coordinates":[8.0877342224,50.0227928162],"type":"Point"}
}