{
  "type": "Feature",
  "properties": {
    "iso:country":"DE",
    "sg:address":"Pionierstr. 17b",
    "sg:city":"Aseleben",
    "sg:phone":"+49 34774/20574",
    "sg:postcode":"06317",
    "sg:province":"Sachsen-Anhalt",
    "wof:name":"Hans-albert Koch Bauunternehmung Gmbh",
    "wof:placetype":"venue"
},
  "geometry": {"coordinates":[11.668741,51.488544],"type":"Point"}
}