{
  "type": "Feature",
  "properties": {
    "iso:country":"DE",
    "sg:address":"Lange Str. 88",
    "sg:city":"Liebenau",
    "sg:phone":"+49 5023/4517",
    "sg:postcode":"31618",
    "sg:province":"Niedersachsen",
    "wof:name":"Karl-heinz Niemeyer",
    "wof:placetype":"venue"
},
  "geometry": {"coordinates":[9.098968,52.599972],"type":"Point"}
}