{
  "type": "Feature",
  "properties": {
    "iso:country":"DE",
    "sg:address":"Fla\u00dfheide 18",
    "sg:city":"Hamburg",
    "sg:phone":"+49 40/546276",
    "sg:postcode":"22525",
    "sg:province":"Hamburg",
    "wof:name":"Gerhard Goldschmidt",
    "wof:placetype":"venue"
},
  "geometry": {"coordinates":[9.91752,53.593288],"type":"Point"}
}