{
  "type": "Feature",
  "properties": {
    "iso:country":"DE",
    "sg:address":"Dreim\u00fchlenstr. 4",
    "sg:city":"M\u00fcnchen",
    "sg:phone":"+49 89/2021615",
    "sg:postcode":"80469",
    "sg:province":"Bayern",
    "wof:name":"Agora Film Gmbh",
    "wof:placetype":"venue"
},
  "geometry": {"coordinates":[11.562035,48.122517],"type":"Point"}
}