{
  "type": "Feature",
  "properties": {
    "iso:country":"DE",
    "sg:address":"Kaiserin - Augusta - Str. 69",
    "sg:city":"Berlin",
    "sg:phone":"+49 30/7517560",
    "sg:postcode":"12103",
    "sg:province":"Berlin",
    "wof:name":"Fahrschule In Berlin Tempelhof",
    "wof:placetype":"venue"
},
  "geometry": {"coordinates":[13.3802928925,52.4595832825],"type":"Point"}
}