{
  "type": "Feature",
  "properties": {
    "iso:country":"DE",
    "sg:address":"Hauptstr. 27",
    "sg:city":"Wangenheim",
    "sg:phone":"+49 36255/81154",
    "sg:postcode":"99869",
    "sg:province":"Th\u00fcringen",
    "wof:name":"Beate Walger",
    "wof:placetype":"venue"
},
  "geometry": {"coordinates":[10.6279373169,51.0196838379],"type":"Point"}
}