{
  "type": "Feature",
  "properties": {
    "iso:country":"DE",
    "sg:address":"Sprucker Str. 9",
    "sg:city":"Guben",
    "sg:phone":"+49 3561/2485",
    "sg:postcode":"03172",
    "sg:province":"Brandenburg",
    "wof:name":"Manfred Wolf Ingenieur",
    "wof:placetype":"venue"
},
  "geometry": {"coordinates":[14.7079019547,51.949054718],"type":"Point"}
}