{
  "type": "Feature",
  "properties": {
    "iso:country":"DE",
    "sg:address":"Marktplatz 4",
    "sg:city":"R\u00f6ttingen",
    "sg:phone":"+49 9338/1018",
    "sg:postcode":"97285",
    "sg:province":"Bayern",
    "wof:name":"Ingeborg Copp-menth Rechtsanw\u00e4ltin",
    "wof:placetype":"venue"
},
  "geometry": {"coordinates":[9.9685993195,49.5098266602],"type":"Point"}
}