{
  "type": "Feature",
  "properties": {
    "iso:country":"DE",
    "sg:address":"Robert-Koch-Str. 48",
    "sg:city":"Bonn",
    "sg:phone":"+49 228/212593",
    "sg:postcode":"53115",
    "sg:province":"Nordrhein-Westfalen",
    "wof:name":"A. Voss Rechtsanwalt",
    "wof:placetype":"venue"
},
  "geometry": {"coordinates":[7.0903258324,50.7157859802],"type":"Point"}
}