{
  "type": "Feature",
  "properties": {
    "iso:country":"DE",
    "sg:address":"Steinweg 31",
    "sg:city":"Tann",
    "sg:phone":"+49 6682/8463",
    "sg:postcode":"36142",
    "sg:province":"Hessen",
    "wof:name":"G. Walter",
    "wof:placetype":"venue"
},
  "geometry": {"coordinates":[10.023022,50.644325],"type":"Point"}
}