{
  "type": "Feature",
  "properties": {
    "iso:country":"DE",
    "sg:address":"Zanderstr. 2",
    "sg:city":"Otterstadt",
    "sg:phone":"+49 6232/490750",
    "sg:postcode":"67166",
    "sg:province":"Rheinland-Pfalz",
    "wof:name":"J\u00fcrgen Gruber Baubetreuung Gmbh",
    "wof:placetype":"venue"
},
  "geometry": {"coordinates":[8.4496555328,49.3765716553],"type":"Point"}
}