{
  "type": "Feature",
  "properties": {
    "iso:country":"DE",
    "sg:address":"Tuninger Str. 30",
    "sg:city":"Villingen-Schwenningen",
    "sg:phone":"+49 7720/62913",
    "sg:postcode":"78056",
    "sg:province":"Baden-W\u00fcrttemberg",
    "wof:name":"Valentin-walter Schwager",
    "wof:placetype":"venue"
},
  "geometry": {"coordinates":[8.5795221329,48.0511322021],"type":"Point"}
}