{
  "type": "Feature",
  "properties": {
    "iso:country":"DE",
    "sg:address":"Wanderslebener Str. 79",
    "sg:city":"M\u00fchlberg",
    "sg:postcode":"99869",
    "sg:province":"Th\u00fcringen",
    "wof:name":"Agrarprodukt Gmbh",
    "wof:placetype":"venue"
},
  "geometry": {"coordinates":[10.82721,50.871841],"type":"Point"}
}