{
  "type": "Feature",
  "properties": {
    "iso:country":"DE",
    "sg:address":"Hauptstr. 17",
    "sg:city":"Binnen",
    "sg:phone":"+49 5023/94194",
    "sg:postcode":"31619",
    "sg:province":"Niedersachsen",
    "wof:name":"Schomburg Gmbh",
    "wof:placetype":"venue"
},
  "geometry": {"coordinates":[9.130459,52.619148],"type":"Point"}
}