{
  "type": "Feature",
  "properties": {
    "iso:country":"DE",
    "sg:address":"Hauptstr. 32",
    "sg:city":"Eichstetten",
    "sg:phone":"+49 7663/1335",
    "sg:postcode":"79356",
    "sg:province":"Baden-W\u00fcrttemberg",
    "wof:name":"Winzergenossenschaft Eich- Stetten Am Kaiserstuhl Eg",
    "wof:placetype":"venue"
},
  "geometry": {"coordinates":[7.728869915,48.0934295654],"type":"Point"}
}