{
  "type": "Feature",
  "properties": {
    "iso:country":"DE",
    "sg:address":"Dr.-Franz-Langecker-Str. 6a",
    "sg:city":"Hausham",
    "sg:phone":"+49 8026/8912",
    "sg:postcode":"83734",
    "sg:province":"Bayern",
    "wof:name":"Blumen Doris",
    "wof:placetype":"venue"
},
  "geometry": {"coordinates":[11.839404,47.749264],"type":"Point"}
}