{
  "type": "Feature",
  "properties": {
    "iso:country":"DE",
    "sg:address":"Briandring 23",
    "sg:city":"Frankfurt",
    "sg:phone":"+49 69/685444",
    "sg:postcode":"60598",
    "sg:province":"Hessen",
    "wof:name":"Dr. Ulf R. Siebel Rechtsanwalt",
    "wof:placetype":"venue"
},
  "geometry": {"coordinates":[8.6763029099,50.0799255371],"type":"Point"}
}