{
  "type": "Feature",
  "properties": {
    "iso:country":"DE",
    "sg:address":"R\u00fcdenhausener Str. 2",
    "sg:city":"Wiesentheid",
    "sg:phone":"+49 9383/821",
    "sg:postcode":"97353",
    "sg:province":"Bayern",
    "wof:name":"Bay Wa Ag",
    "wof:placetype":"venue"
},
  "geometry": {"coordinates":[10.3405199051,49.7885284424],"type":"Point"}
}