{
  "type": "Feature",
  "properties": {
    "iso:country":"DE",
    "sg:address":"Grabengasse 2",
    "sg:city":"Borna",
    "sg:phone":"+49 3433/4101",
    "sg:postcode":"04552",
    "sg:province":"Sachsen",
    "wof:name":"Verband Der Privaten Landwirte Und Grund-",
    "wof:placetype":"venue"
},
  "geometry": {"coordinates":[12.5002880096,51.1241340637],"type":"Point"}
}