{
  "type": "Feature",
  "properties": {
    "iso:country":"DE",
    "sg:address":"Marktplatz 17",
    "sg:city":"Kastl",
    "sg:phone":"+49 9625/1778",
    "sg:postcode":"92280",
    "sg:province":"Bayern",
    "wof:name":"U. Sch\u00f6berlein",
    "wof:placetype":"venue"
},
  "geometry": {"coordinates":[11.6802110672,49.3691711426],"type":"Point"}
}