{
  "type": "Feature",
  "properties": {
    "iso:country":"DE",
    "sg:address":"Siemensstr. 43 - 45",
    "sg:city":"Bad Salzuflen",
    "sg:phone":"+49 5222/95490",
    "sg:postcode":"32105",
    "sg:province":"Nordrhein-Westfalen",
    "wof:name":"August Riemeier Gmbh",
    "wof:placetype":"venue"
},
  "geometry": {"coordinates":[8.731238,52.08754],"type":"Point"}
}