{
  "type": "Feature",
  "properties": {
    "iso:country":"DE",
    "sg:address":"Am Antritt 18",
    "sg:city":"Schliersee",
    "sg:phone":"+49 8026/6317",
    "sg:postcode":"83727",
    "sg:province":"Bayern",
    "wof:name":"Erika Schmid",
    "wof:placetype":"venue"
},
  "geometry": {"coordinates":[11.8505268097,47.7377624512],"type":"Point"}
}