{
  "type": "Feature",
  "properties": {
    "iso:country":"DE",
    "sg:address":"Thie\u00dfener Weg 47a",
    "sg:city":"Rag\u00f6sen",
    "sg:phone":"+49 34907/21025",
    "sg:postcode":"06862",
    "sg:province":"Sachsen-Anhalt",
    "wof:name":"Bdh Bau-, Dienstleistungs- Und Handelsgesellschaft Mbh",
    "wof:placetype":"venue"
},
  "geometry": {"coordinates":[12.297851,51.979408],"type":"Point"}
}