{
  "type": "Feature",
  "properties": {
    "iso:country":"DE",
    "sg:address":"Nelkenstr. 8",
    "sg:city":"Rheinm\u00fcnster",
    "sg:phone":"+49 7227/2356",
    "sg:postcode":"77836",
    "sg:province":"Baden-W\u00fcrttemberg",
    "wof:name":"Erich Tschan Gmbh",
    "wof:placetype":"venue"
},
  "geometry": {"coordinates":[8.002951622,48.7496261597],"type":"Point"}
}