{
  "type": "Feature",
  "properties": {
    "iso:country":"DE",
    "sg:address":"F\u00e4hrgasse 6a",
    "sg:city":"Dehlitz",
    "sg:phone":"+49 3443/232870",
    "sg:postcode":"06686",
    "sg:province":"Sachsen-Anhalt",
    "wof:name":"Gei\u00dfler & H\u00f6lzer",
    "wof:placetype":"venue"
},
  "geometry": {"coordinates":[12.020405,51.232685],"type":"Point"}
}