{
  "type": "Feature",
  "properties": {
    "iso:country":"DE",
    "sg:address":"Beckestr. 1",
    "sg:city":"Schwerte",
    "sg:phone":"+49 2304/17280",
    "sg:postcode":"58239",
    "sg:province":"Nordrhein-Westfalen",
    "wof:name":"Restaurant Artemis",
    "wof:placetype":"venue"
},
  "geometry": {"coordinates":[7.5611810684,51.4420318604],"type":"Point"}
}