{
  "type": "Feature",
  "properties": {
    "iso:country":"DE",
    "sg:address":"Bahnhofstr. 3",
    "sg:city":"Osterhofen",
    "sg:phone":"+49 9932/90565",
    "sg:postcode":"94486",
    "sg:province":"Bayern",
    "wof:name":"L\u00f6wen-apotheke",
    "wof:placetype":"venue"
},
  "geometry": {"coordinates":[13.019644,48.694256],"type":"Point"}
}