{
  "type": "Feature",
  "properties": {
    "iso:country":"DE",
    "sg:address":"R\u00fcdigsdorf",
    "sg:city":"Kohren-Sahlis",
    "sg:phone":"+49 34344/61440",
    "sg:postcode":"04655",
    "sg:province":"Sachsen",
    "wof:name":"Helmut Gerhardt",
    "wof:placetype":"venue"
},
  "geometry": {"coordinates":[12.600073,51.009117],"type":"Point"}
}