{
  "type": "Feature",
  "properties": {
    "iso:country":"DE",
    "sg:address":"Rhedebr\u00fcgger Str. 82",
    "sg:city":"Borken",
    "sg:phone":"+49 2872/2826",
    "sg:postcode":"46325",
    "sg:province":"Nordrhein-Westfalen",
    "wof:name":"Gastst\u00e4tte Haus Hambrock Inh. B. H\u00fcls",
    "wof:placetype":"venue"
},
  "geometry": {"coordinates":[6.7546138763,51.8035888672],"type":"Point"}
}