{
  "type": "Feature",
  "properties": {
    "iso:country":"DE",
    "sg:address":"Auf dem Bergkamp 52",
    "sg:city":"Dorsten",
    "sg:phone":"+49 2362/26056",
    "sg:postcode":"46282",
    "sg:province":"Nordrhein-Westfalen",
    "wof:name":"Gis Maschinenfabrik Hardt Gmbh",
    "wof:placetype":"venue"
},
  "geometry": {"coordinates":[6.957957,51.661377],"type":"Point"}
}