{
  "type": "Feature",
  "properties": {
    "iso:country":"DE",
    "sg:address":"Krefelder Str. 82",
    "sg:city":"Dormagen",
    "sg:phone":"+49 2133/245340",
    "sg:postcode":"41539",
    "sg:province":"Nordrhein-Westfalen",
    "wof:name":"Augustinus-haus Altenheim",
    "wof:placetype":"venue"
},
  "geometry": {"coordinates":[6.835075,51.099709],"type":"Point"}
}