{
  "type": "Feature",
  "properties": {
    "iso:country":"DE",
    "sg:address":"Steinacker 26",
    "sg:city":"Bremerhaven",
    "sg:phone":"+49 471/73264",
    "sg:postcode":"27572",
    "sg:province":"Bremen",
    "wof:name":"Edith Thaden Und Ude",
    "wof:placetype":"venue"
},
  "geometry": {"coordinates":[8.5965299606,53.4981117249],"type":"Point"}
}