{
  "type": "Feature",
  "properties": {
    "iso:country":"DE",
    "sg:address":"M\u00fchlensteige 20",
    "sg:city":"Wertheim",
    "sg:phone":"+49 9342/4081",
    "sg:postcode":"97877",
    "sg:province":"Baden-W\u00fcrttemberg",
    "wof:name":"Weingut A. Steinmann Inh. Michael Steinmann",
    "wof:placetype":"venue"
},
  "geometry": {"coordinates":[9.5236616135,49.7517204285],"type":"Point"}
}