{
  "type": "Feature",
  "properties": {
    "iso:country":"DE",
    "sg:address":"Saarstr. 19",
    "sg:city":"Stuttgart",
    "sg:phone":"+49 711/525207",
    "sg:postcode":"70374",
    "sg:province":"Baden-W\u00fcrttemberg",
    "wof:name":"W. Duppui Architekt",
    "wof:placetype":"venue"
},
  "geometry": {"coordinates":[9.233721,48.805637],"type":"Point"}
}