{
  "type": "Feature",
  "properties": {
    "iso:country":"DE",
    "sg:address":"Unterer H\u00e4rling 15",
    "sg:city":"St. Wendel",
    "sg:phone":"+49 6851/81208",
    "sg:postcode":"66606",
    "sg:province":"Saarland",
    "wof:name":"Werob Michael Welker Industrieroboter-",
    "wof:placetype":"venue"
},
  "geometry": {"coordinates":[7.1596889496,49.4680938721],"type":"Point"}
}