{
  "type": "Feature",
  "properties": {
    "iso:country":"DE",
    "sg:address":"An der Grotte 2",
    "sg:city":"Hilders",
    "sg:phone":"+49 6681/7173",
    "sg:postcode":"36115",
    "sg:province":"Hessen",
    "wof:name":"Pension Magdalena Hohmann",
    "wof:placetype":"venue"
},
  "geometry": {"coordinates":[10.0061836243,50.5734977722],"type":"Point"}
}