{
  "type": "Feature",
  "properties": {
    "iso:country":"DE",
    "sg:address":"Br\u00fcnnlfeldstr. 9",
    "sg:city":"Bad T\u00f6lz",
    "sg:phone":"+49 8041/3599",
    "sg:postcode":"83646",
    "sg:province":"Bayern",
    "wof:name":"Klaus Happach Heilpraktiker",
    "wof:placetype":"venue"
},
  "geometry": {"coordinates":[11.5526990891,47.7577781677],"type":"Point"}
}