{
  "type": "Feature",
  "properties": {
    "iso:country":"DE",
    "sg:address":"Im Holz 60",
    "sg:city":"Lingen",
    "sg:phone":"+49 591/73237",
    "sg:postcode":"49811",
    "sg:province":"Niedersachsen",
    "wof:name":"M. Gels",
    "wof:placetype":"venue"
},
  "geometry": {"coordinates":[7.364356,52.549908],"type":"Point"}
}