{
  "type": "Feature",
  "properties": {
    "iso:country":"DE",
    "sg:address":"Kreuzweg 2",
    "sg:city":"Sch\u00f6ffengrund",
    "sg:phone":"+49 6445/808",
    "sg:postcode":"35641",
    "sg:province":"Hessen",
    "wof:name":"Hans Werth",
    "wof:placetype":"venue"
},
  "geometry": {"coordinates":[8.508674,50.473213],"type":"Point"}
}