{
  "type": "Feature",
  "properties": {
    "iso:country":"DE",
    "sg:address":"Einzendobl 1",
    "sg:city":"Eging",
    "sg:phone":"+49 8544/1866",
    "sg:postcode":"94535",
    "sg:province":"Bayern",
    "wof:name":"Peter Neissendorfer",
    "wof:placetype":"venue"
},
  "geometry": {"coordinates":[13.2920722961,48.7138671875],"type":"Point"}
}