{
  "type": "Feature",
  "properties": {
    "iso:country":"DE",
    "sg:address":"Dresdener Str. 5",
    "sg:city":"Ruhland",
    "sg:phone":"+49 35752/30417",
    "sg:postcode":"01945",
    "sg:province":"Brandenburg",
    "wof:name":"Eis-cafe",
    "wof:placetype":"venue"
},
  "geometry": {"coordinates":[13.865491,51.458076],"type":"Point"}
}