{
  "type": "Feature",
  "properties": {
    "iso:country":"DE",
    "sg:address":"Dietrich-Bonhoeffer-Str. 21",
    "sg:city":"Donaueschingen",
    "sg:phone":"+49 771/5742",
    "sg:postcode":"78166",
    "sg:province":"Baden-W\u00fcrttemberg",
    "wof:name":"Hans-peter Gaisser",
    "wof:placetype":"venue"
},
  "geometry": {"coordinates":[8.4946975708,47.944770813],"type":"Point"}
}