{
  "type": "Feature",
  "properties": {
    "iso:country":"DE",
    "sg:address":"Oderstr. 74-76",
    "sg:city":"Teltow",
    "sg:postcode":"14513",
    "sg:province":"Brandenburg",
    "wof:name":"P & F Paech & Funk Repro-service Gmbh",
    "wof:placetype":"venue"
},
  "geometry": {"coordinates":[13.2351589203,52.3968963623],"type":"Point"}
}