{
  "type": "Feature",
  "properties": {
    "iso:country":"DE",
    "sg:address":"Ahnfeldstr. 37",
    "sg:city":"D\u00fcsseldorf",
    "sg:phone":"+49 211/623185",
    "sg:postcode":"40239",
    "sg:province":"Nordrhein-Westfalen",
    "wof:name":"Waaga Und Skrzipietz Rechtsanw\u00e4lte",
    "wof:placetype":"venue"
},
  "geometry": {"coordinates":[6.7978668213,51.2401351929],"type":"Point"}
}