{
  "type": "Feature",
  "properties": {
    "iso:country":"DE",
    "sg:address":"France Spain England Germany Italy Irela",
    "sg:city":"Lunel",
    "sg:postcode":"34400",
    "wof:name":"Hotrod In Europe !",
    "wof:placetype":"venue"
},
  "geometry": {"coordinates":[4.138675,43.6758],"type":"Point"}
}