{
  "type": "Feature",
  "properties": {
    "iso:country":"DE",
    "sg:address":"Nothmannstr. 20",
    "sg:city":"Uelzen",
    "sg:phone":"+49 581/2601",
    "sg:postcode":"29525",
    "sg:province":"Niedersachsen",
    "wof:name":"Paul Sommer",
    "wof:placetype":"venue"
},
  "geometry": {"coordinates":[10.5499830246,52.9726409912],"type":"Point"}
}