{
  "type": "Feature",
  "properties": {
    "iso:country":"DE",
    "sg:address":"Am Unteren Schlo\u00dfberg 57",
    "sg:city":"Remseck",
    "sg:postcode":"71686",
    "sg:province":"Baden-W\u00fcrttemberg",
    "wof:name":"Andrea Aurenz Grundst\u00fccks- Verwaltungs- Gmbh & Co. Kg",
    "wof:placetype":"venue"
},
  "geometry": {"coordinates":[9.2666454315,48.8656044006],"type":"Point"}
}