{
  "type": "Feature",
  "properties": {
    "iso:country":"DE",
    "sg:address":"Enzstr. 1",
    "sg:city":"Eberdingen",
    "sg:postcode":"71735",
    "sg:province":"Baden-W\u00fcrttemberg",
    "wof:name":"Ukr-agro Gmbh",
    "wof:placetype":"venue"
},
  "geometry": {"coordinates":[8.945178,48.896381],"type":"Point"}
}