{
  "type": "Feature",
  "properties": {
    "iso:country":"DE",
    "sg:address":"Lengatz 1",
    "sg:city":"Hergatz",
    "sg:postcode":"88145",
    "sg:province":"Bayern",
    "wof:name":"Achberger Gmbh",
    "wof:placetype":"venue"
},
  "geometry": {"coordinates":[9.893358,47.652603],"type":"Point"}
}