{
  "type": "Feature",
  "properties": {
    "iso:country":"DE",
    "sg:address":"Graf-Albrecht-Str. 24",
    "sg:city":"Dornstadt",
    "sg:postcode":"89160",
    "sg:province":"Baden-W\u00fcrttemberg",
    "wof:name":"Boin Gmbh",
    "wof:placetype":"venue"
},
  "geometry": {"coordinates":[9.9093542099,48.4818496704],"type":"Point"}
}