{
  "type": "Feature",
  "properties": {
    "iso:country":"DE",
    "sg:address":"Schulstr 5",
    "sg:city":"Holzkirchen",
    "sg:phone":"+49 8024/4774450",
    "sg:postcode":"83607",
    "sg:province":"Bayern",
    "wof:name":"Communication Service Zehnder + Partner Gbr",
    "wof:placetype":"venue"
},
  "geometry": {"coordinates":[11.7153778076,47.895652771],"type":"Point"}
}