{
  "type": "Feature",
  "properties": {
    "iso:country":"DE",
    "sg:address":"Cecilienstr. 15",
    "sg:city":"Saarbr\u00fccken",
    "sg:phone":"+49 681/3908772",
    "sg:postcode":"66111",
    "sg:province":"Saarland",
    "wof:name":"Ubu Roi",
    "wof:placetype":"venue"
},
  "geometry": {"coordinates":[6.998128891,49.2362937927],"type":"Point"}
}