{
  "type": "Feature",
  "properties": {
    "iso:country":"DE",
    "sg:address":"Karlstr. 11",
    "sg:city":"Frankfurt",
    "sg:phone":"+49 69/232093",
    "sg:postcode":"60329",
    "sg:province":"Hessen",
    "wof:name":"Carlton-hotel Har Gmbh",
    "wof:placetype":"venue"
},
  "geometry": {"coordinates":[8.6634817123,50.1089859009],"type":"Point"}
}