{
  "type": "Feature",
  "properties": {
    "iso:country":"DE",
    "sg:address":"Im Hofgraben 6",
    "sg:city":"Briedern",
    "sg:phone":"+49 2673/1718",
    "sg:postcode":"56820",
    "sg:province":"Rheinland-Pfalz",
    "wof:name":"Adam Lademann",
    "wof:placetype":"venue"
},
  "geometry": {"coordinates":[7.208327,50.109695],"type":"Point"}
}