{
  "type": "Feature",
  "properties": {
    "iso:country":"DE",
    "sg:address":"Lortzingstr. 61",
    "sg:city":"Darmstadt",
    "sg:phone":"+49 6150/82332",
    "sg:postcode":"64291",
    "sg:province":"Hessen",
    "wof:name":"Achim Berger Ingenieur",
    "wof:placetype":"venue"
},
  "geometry": {"coordinates":[8.6523036957,49.9287986755],"type":"Point"}
}