{
  "type": "Feature",
  "properties": {
    "iso:country":"DE",
    "sg:address":"Ortsstr. 34",
    "sg:city":"Drognitz",
    "sg:phone":"+49 36737/22250",
    "sg:postcode":"07338",
    "sg:province":"Th\u00fcringen",
    "wof:name":"Gastst\u00e4tte Zum Wolf Inh. B. Hofmann",
    "wof:placetype":"venue"
},
  "geometry": {"coordinates":[11.5715293884,50.5884437561],"type":"Point"}
}