{
  "type": "Feature",
  "properties": {
    "iso:country":"DE",
    "sg:address":"Friedrichstal 28",
    "sg:city":"Solingen",
    "sg:phone":"+49 212/819561",
    "sg:postcode":"42657",
    "sg:province":"Nordrhein-Westfalen",
    "wof:name":"Peter Oberhoff",
    "wof:placetype":"venue"
},
  "geometry": {"coordinates":[7.054785,51.128151],"type":"Point"}
}