{
  "type": "Feature",
  "properties": {
    "iso:country":"DE",
    "sg:address":"Gerhart-Hauptmann-Str. 2",
    "sg:city":"Strullendorf",
    "sg:phone":"+49 9543/9583",
    "sg:postcode":"96129",
    "sg:province":"Bayern",
    "wof:name":"Rainer Kauer",
    "wof:placetype":"venue"
},
  "geometry": {"coordinates":[10.9756822586,49.846950531],"type":"Point"}
}