{
  "type": "Feature",
  "properties": {
    "iso:country":"DE",
    "sg:address":"Hauptstr. 436-440",
    "sg:city":"Siegburg",
    "sg:phone":"+49 4922/4288910",
    "sg:postcode":"53721",
    "sg:province":"Nordrhein-Westfalen",
    "wof:name":"Blumen- U. Garten-center Ahrens U. Sieberz Kg",
    "wof:placetype":"venue"
},
  "geometry": {"coordinates":[7.248826,50.806644],"type":"Point"}
}