{
  "type": "Feature",
  "properties": {
    "iso:country":"DE",
    "sg:address":"Voerder Str. 53",
    "sg:city":"Hagen",
    "sg:phone":"+49 4923/3141580",
    "sg:postcode":"58135",
    "sg:province":"Nordrhein-Westfalen",
    "wof:name":"Verzinkerei Pfingsten Gmbh & Co",
    "wof:placetype":"venue"
},
  "geometry": {"coordinates":[7.427992,51.340839],"type":"Point"}
}