{
  "type": "Feature",
  "properties": {
    "iso:country":"DE",
    "sg:address":"Wormser Str. 66",
    "sg:city":"Dresden",
    "sg:phone":"+49 351/3179378",
    "sg:postcode":"01309",
    "sg:province":"Sachsen",
    "wof:name":"Wirtschaftstreuhand Gmbh",
    "wof:placetype":"venue"
},
  "geometry": {"coordinates":[13.7881603241,51.0456352234],"type":"Point"}
}