{
  "type": "Feature",
  "properties": {
    "iso:country":"DE",
    "sg:address":"J\u00e4gerweg 8",
    "sg:city":"Wischhafen",
    "sg:phone":"+49 4770/287",
    "sg:postcode":"21737",
    "sg:province":"Niedersachsen",
    "wof:name":"Albert Otto",
    "wof:placetype":"venue"
},
  "geometry": {"coordinates":[9.281513,53.757664],"type":"Point"}
}