{
  "type": "Feature",
  "properties": {
    "iso:country":"DE",
    "sg:address":"Dieselstr 20",
    "sg:city":"Rottenburg",
    "sg:phone":"+49 8781/550",
    "sg:postcode":"84056",
    "sg:province":"Bayern",
    "wof:name":"Buchbinderei Obermeier",
    "wof:placetype":"venue"
},
  "geometry": {"coordinates":[12.033333,48.690754],"type":"Point"}
}