{
  "type": "Feature",
  "properties": {
    "iso:country":"DE",
    "sg:address":"Klosterstr. 2",
    "sg:city":"Wallenhorst",
    "sg:phone":"+49 5407/6159",
    "sg:postcode":"49134",
    "sg:province":"Niedersachsen",
    "wof:name":"U. Wahmhoff",
    "wof:placetype":"venue"
},
  "geometry": {"coordinates":[8.05286026,52.3391304016],"type":"Point"}
}