{
  "type": "Feature",
  "properties": {
    "iso:country":"DE",
    "sg:address":"Westerwaldstr. 32",
    "sg:city":"Mengerskirchen",
    "sg:phone":"+49 6476/537",
    "sg:postcode":"35794",
    "sg:province":"Hessen",
    "wof:name":"Diskothek Captn Cook",
    "wof:placetype":"venue"
},
  "geometry": {"coordinates":[8.144651,50.539474],"type":"Point"}
}