{
  "type": "Feature",
  "properties": {
    "iso:country":"DE",
    "sg:address":"Kokenhorststr. 13",
    "sg:city":"Burgwedel",
    "sg:phone":"+49 5139/80095",
    "sg:postcode":"30938",
    "sg:province":"Niedersachsen",
    "wof:name":"H. Biedermann Gmbh",
    "wof:placetype":"venue"
},
  "geometry": {"coordinates":[9.842199,52.489395],"type":"Point"}
}