{
  "type": "Feature",
  "properties": {
    "iso:country":"DE",
    "sg:address":"M\u00fchlh\u00e4ule 3",
    "sg:city":"Blaustein",
    "sg:phone":"+49 7304/3490",
    "sg:postcode":"89134",
    "sg:province":"Baden-W\u00fcrttemberg",
    "wof:name":"Rath & Schissler Gbr",
    "wof:placetype":"venue"
},
  "geometry": {"coordinates":[9.8755092621,48.412727356],"type":"Point"}
}