{
  "type": "Feature",
  "properties": {
    "iso:country":"DE",
    "sg:address":"Nestle-Weg 6",
    "sg:city":"Kappeln",
    "sg:phone":"+49 4642/2722",
    "sg:postcode":"24376",
    "sg:province":"Schleswig-Holstein",
    "wof:name":"Mittelmanns Werft",
    "wof:placetype":"venue"
},
  "geometry": {"coordinates":[9.934916,54.653488],"type":"Point"}
}