{
  "type": "Feature",
  "properties": {
    "iso:country":"DE",
    "sg:address":"Dom\u00e4nenweg 1 d",
    "sg:city":"Nordstemmen",
    "sg:phone":"+49 5069/8566",
    "sg:postcode":"31171",
    "sg:province":"Niedersachsen",
    "wof:name":"Sch\u00f6ne Massiv-haus Gmbh",
    "wof:placetype":"venue"
},
  "geometry": {"coordinates":[9.770679,52.149765],"type":"Point"}
}