{
  "type": "Feature",
  "properties": {
    "iso:country":"DE",
    "sg:address":"H\u00f6henrg. 2",
    "sg:city":"Oberthal",
    "sg:phone":"+49 4968/5490900",
    "sg:postcode":"66649",
    "sg:province":"Saarland",
    "wof:name":"Gebr. Pelz Ohg",
    "wof:placetype":"venue"
},
  "geometry": {"coordinates":[7.0922899246,49.5148887634],"type":"Point"}
}