{
  "type": "Feature",
  "properties": {
    "iso:country":"DE",
    "sg:address":"Untere Dorfstr. 8",
    "sg:city":"Gro\u00df Schierstedt",
    "sg:phone":"+49 3473/801126",
    "sg:postcode":"06449",
    "sg:province":"Sachsen-Anhalt",
    "wof:name":"Dr. Junghanns Gmbh",
    "wof:placetype":"venue"
},
  "geometry": {"coordinates":[11.5236625671,51.7485466003],"type":"Point"}
}