{
  "type": "Feature",
  "properties": {
    "iso:country":"DE",
    "sg:address":"Oberneulander Heerstr. 30",
    "sg:city":"Bremen",
    "sg:phone":"+49 421/255065",
    "sg:postcode":"28355",
    "sg:province":"Bremen",
    "wof:name":"Leder Und Mode Birgit Naubarth",
    "wof:placetype":"venue"
},
  "geometry": {"coordinates":[8.901279,53.099915],"type":"Point"}
}