{
  "type": "Feature",
  "properties": {
    "iso:country":"DE",
    "sg:address":"Gottlieb-Daimler-Str. 7",
    "sg:city":"Schwebheim",
    "sg:phone":"+49 9723/3257",
    "sg:postcode":"97525",
    "sg:province":"Bayern",
    "wof:name":"Hans Karl Kirchner",
    "wof:placetype":"venue"
},
  "geometry": {"coordinates":[10.2483901978,49.9839515686],"type":"Point"}
}