{
  "type": "Feature",
  "properties": {
    "iso:country":"DE",
    "sg:address":"Elberfelderstr.",
    "sg:city":"Mettmann",
    "sg:phone":"+49 2104/13249",
    "sg:postcode":"40822",
    "sg:province":"Nordrhein-Westfalen",
    "wof:name":"R S Technik Gmbh",
    "wof:placetype":"venue"
},
  "geometry": {"coordinates":[6.9795198441,51.2494812012],"type":"Point"}
}