{
  "type": "Feature",
  "properties": {
    "iso:country":"DE",
    "sg:address":"Dieselweg 5",
    "sg:city":"Wettringen",
    "sg:phone":"+49 2557/93900",
    "sg:postcode":"48493",
    "sg:province":"Nordrhein-Westfalen",
    "wof:name":"2 H Kunststoff Gmbh",
    "wof:placetype":"venue"
},
  "geometry": {"coordinates":[7.315251,52.214798],"type":"Point"}
}