{
  "type": "Feature",
  "properties": {
    "iso:country":"DE",
    "sg:address":"W\u00f6hrdstr. 5-9",
    "sg:city":"T\u00fcbingen",
    "sg:phone":"+49 7071/1390",
    "sg:postcode":"72072",
    "sg:province":"Baden-W\u00fcrttemberg",
    "wof:name":"Hotel Domizil Verwaltungsgesellschaft Mbh",
    "wof:placetype":"venue"
},
  "geometry": {"coordinates":[9.058759,48.518547],"type":"Point"}
}