{
  "type": "Feature",
  "properties": {
    "iso:country":"DE",
    "sg:address":"Friedenstr. 12",
    "sg:city":"L\u00fcneburg",
    "sg:phone":"+49 4131/45205",
    "sg:postcode":"21335",
    "sg:province":"Niedersachsen",
    "wof:name":"Michael Schweinfest Steuerberater",
    "wof:placetype":"venue"
},
  "geometry": {"coordinates":[10.4127416611,53.2456283569],"type":"Point"}
}