{
  "type": "Feature",
  "properties": {
    "iso:country":"DE",
    "sg:address":"Stegangerstr. 3",
    "sg:city":"Irschenberg",
    "sg:phone":"+49 8062/1528",
    "sg:postcode":"83737",
    "sg:province":"Bayern",
    "wof:name":"Katholisches Pfarramt St. Johann Baptist",
    "wof:placetype":"venue"
},
  "geometry": {"coordinates":[11.9203853607,47.8330535889],"type":"Point"}
}