{
  "type": "Feature",
  "properties": {
    "iso:country":"DE",
    "sg:address":"Wimpfener Str. 122",
    "sg:city":"Heilbronn",
    "sg:postcode":"74078",
    "sg:province":"Baden-W\u00fcrttemberg",
    "wof:name":"Autec Autotechnik Gmbh",
    "wof:placetype":"venue"
},
  "geometry": {"coordinates":[9.199079,49.184601],"type":"Point"}
}