{
  "type": "Feature",
  "properties": {
    "iso:country":"DE",
    "sg:city":"Waischenfeld",
    "sg:phone":"+49 9202/95123",
    "sg:postcode":"91344",
    "sg:province":"Bayern",
    "wof:name":"F. Rost",
    "wof:placetype":"venue"
},
  "geometry": {"coordinates":[11.343393,49.847481],"type":"Point"}
}