{
  "type": "Feature",
  "properties": {
    "iso:country":"DE",
    "sg:address":"Wilhelm-Klein-Str. 18",
    "sg:city":"Bergisch Gladbach",
    "sg:phone":"+49 2204/64499",
    "sg:postcode":"51427",
    "sg:province":"Nordrhein-Westfalen",
    "wof:name":"Restaurant Gambrinus",
    "wof:placetype":"venue"
},
  "geometry": {"coordinates":[7.1176872253,50.9547080994],"type":"Point"}
}