{
  "type": "Feature",
  "properties": {
    "iso:country":"DE",
    "sg:address":"Biegenstr. 12",
    "sg:city":"Marburg",
    "sg:postcode":"35037",
    "sg:province":"Hessen",
    "wof:name":"Institut F\u00fcr Kernchemie",
    "wof:placetype":"venue"
},
  "geometry": {"coordinates":[8.7734060287,50.8100624084],"type":"Point"}
}