{
  "type": "Feature",
  "properties": {
    "iso:country":"DE",
    "sg:address":"Melscher Str. 1",
    "sg:city":"Leipzig",
    "sg:phone":"+49 4934/1868610",
    "sg:postcode":"04299",
    "sg:province":"Sachsen",
    "wof:name":"Druckerei Karlheinz Koch",
    "wof:placetype":"venue"
},
  "geometry": {"coordinates":[12.4144439697,51.3257865906],"type":"Point"}
}