{
  "type": "Feature",
  "properties": {
    "iso:country":"DE",
    "sg:address":"Haigerer Strasse 10",
    "sg:city":"Frankfurt",
    "sg:postcode":"65936",
    "sg:province":"Hessen",
    "wof:name":"Versicherung-online - Versicherungsvergleiche - Un",
    "wof:placetype":"venue"
},
  "geometry": {"coordinates":[8.577291,50.12447],"type":"Point"}
}