{
  "type": "Feature",
  "properties": {
    "iso:country":"DE",
    "sg:address":"Brotmarkt 4",
    "sg:city":"F\u00fcssen",
    "sg:phone":"+49 8362/38828",
    "sg:postcode":"87629",
    "sg:province":"Bayern",
    "wof:name":"Oliver Radke",
    "wof:placetype":"venue"
},
  "geometry": {"coordinates":[10.7003984451,47.5669631958],"type":"Point"}
}