{
  "type": "Feature",
  "properties": {
    "iso:country":"DE",
    "sg:address":"Hauptstr. 18",
    "sg:city":"Aurachtal",
    "sg:phone":"+49 9132/9167",
    "sg:postcode":"91086",
    "sg:province":"Bayern",
    "wof:name":"Jordan",
    "wof:placetype":"venue"
},
  "geometry": {"coordinates":[10.8413572311,49.5778808594],"type":"Point"}
}