{
  "type": "Feature",
  "properties": {
    "iso:country":"DE",
    "sg:address":"Elbchaussee 139",
    "sg:city":"Hamburg",
    "sg:postcode":"22763",
    "sg:province":"Hamburg",
    "wof:name":"Gmp International Gmbh",
    "wof:placetype":"venue"
},
  "geometry": {"coordinates":[9.91419,53.54612],"type":"Point"}
}