{
  "type": "Feature",
  "properties": {
    "iso:country":"DE",
    "sg:address":"Pescher Str. 1",
    "sg:city":"Erkelenz",
    "sg:phone":"+49 2164/950925",
    "sg:postcode":"41812",
    "sg:province":"Nordrhein-Westfalen",
    "wof:name":"Mieves",
    "wof:placetype":"venue"
},
  "geometry": {"coordinates":[6.43897295,51.0515403748],"type":"Point"}
}