{
  "type": "Feature",
  "properties": {
    "iso:country":"DE",
    "sg:address":"Bahnhofstr. 2",
    "sg:city":"Bad Lausick",
    "sg:postcode":"04651",
    "sg:province":"Sachsen",
    "wof:name":"Eta-bad Lausick Gmbh",
    "wof:placetype":"venue"
},
  "geometry": {"coordinates":[12.645101,51.143166],"type":"Point"}
}