{
  "type": "Feature",
  "properties": {
    "iso:country":"DE",
    "sg:address":"Kirchweyher Str. 3",
    "sg:city":"Weyhe",
    "sg:phone":"+49 4203/2706",
    "sg:postcode":"28844",
    "sg:province":"Niedersachsen",
    "wof:name":"Van Hoorn, Maack, Feldhoff Und Partner",
    "wof:placetype":"venue"
},
  "geometry": {"coordinates":[8.872391,52.999668],"type":"Point"}
}