{
  "type": "Feature",
  "properties": {
    "iso:country":"DE",
    "sg:address":"Schwiepinghook 54",
    "sg:city":"Ahaus",
    "sg:phone":"+49 2567/1358",
    "sg:postcode":"48683",
    "sg:province":"Nordrhein-Westfalen",
    "wof:name":"Johannes Lentfort",
    "wof:placetype":"venue"
},
  "geometry": {"coordinates":[6.949503,52.137424],"type":"Point"}
}