{
  "type": "Feature",
  "properties": {
    "iso:country":"DE",
    "sg:address":"Rommersdorfer Str. 2/3",
    "sg:city":"Bad Honnef",
    "sg:phone":"+49 2224/5180",
    "sg:postcode":"53604",
    "sg:province":"Nordrhein-Westfalen",
    "wof:name":"F. M\u00fcller",
    "wof:placetype":"venue"
},
  "geometry": {"coordinates":[7.2277050018,50.6461372375],"type":"Point"}
}