{
  "type": "Feature",
  "properties": {
    "iso:country":"DE",
    "sg:address":"Overdamm 1",
    "sg:city":"Seevetal",
    "sg:phone":"+49 40/7682584",
    "sg:postcode":"21217",
    "sg:province":"Niedersachsen",
    "wof:name":"Over Gmbh",
    "wof:placetype":"venue"
},
  "geometry": {"coordinates":[10.09053,53.430721],"type":"Point"}
}