{
  "type": "Feature",
  "properties": {
    "iso:country":"DE",
    "sg:address":"Pfeifferweg 51",
    "sg:city":"Radebeul",
    "sg:phone":"+49 351/839870",
    "sg:postcode":"01445",
    "sg:province":"Sachsen",
    "wof:name":"Hotel Zum Pfeiffer",
    "wof:placetype":"venue"
},
  "geometry": {"coordinates":[13.6584701538,51.1185798645],"type":"Point"}
}