{
  "type": "Feature",
  "properties": {
    "iso:country":"DE",
    "sg:address":"Rote Erde 51",
    "sg:city":"Bad Salzuflen",
    "sg:phone":"+49 5222/20002",
    "sg:postcode":"32107",
    "sg:province":"Nordrhein-Westfalen",
    "wof:name":"Peter Evers Nachfolger Gmbh",
    "wof:placetype":"venue"
},
  "geometry": {"coordinates":[8.7525873184,52.0463485718],"type":"Point"}
}