{
  "type": "Feature",
  "properties": {
    "iso:country":"DE",
    "sg:address":"Pr\u00fcssingstr 27",
    "sg:city":"Jena",
    "sg:phone":"+49 3641/66880",
    "sg:postcode":"07745",
    "sg:province":"Th\u00fcringen",
    "wof:name":"Piezosystem Jena Gmbh",
    "wof:placetype":"venue"
},
  "geometry": {"coordinates":[11.597738,50.883694],"type":"Point"}
}