{
  "type": "Feature",
  "properties": {
    "iso:country":"DE",
    "sg:address":"J-Adm-Kleinschroth-Str 4",
    "sg:city":"Kitzingen",
    "sg:phone":"+49 9321/8695",
    "sg:postcode":"97318",
    "sg:province":"Bayern",
    "wof:name":"Christian Neubeck Wing Tsun Kampfkunstschule",
    "wof:placetype":"venue"
},
  "geometry": {"coordinates":[10.1552619934,49.7293548584],"type":"Point"}
}