{
  "type": "Feature",
  "properties": {
    "iso:country":"DE",
    "sg:address":"An der Bleiche 2",
    "sg:city":"Oerlinghausen",
    "sg:postcode":"33813",
    "sg:province":"Nordrhein-Westfalen",
    "wof:name":"Aldi Gmbh & Co. Kg",
    "wof:placetype":"venue"
},
  "geometry": {"coordinates":[8.6565570831,51.9471206665],"type":"Point"}
}