{
  "type": "Feature",
  "properties": {
    "iso:country":"DE",
    "sg:address":"Bahnhofstr. 11",
    "sg:city":"Eddelak",
    "sg:phone":"+49 4855/766",
    "sg:postcode":"25715",
    "sg:province":"Schleswig-Holstein",
    "wof:name":"Peter Bielenberg",
    "wof:placetype":"venue"
},
  "geometry": {"coordinates":[9.1449,53.948971],"type":"Point"}
}