{
  "type": "Feature",
  "properties": {
    "iso:country":"DE",
    "sg:address":"St.-Michael-Str. 42",
    "sg:city":"D\u00fcren",
    "sg:phone":"+49 2421/98500",
    "sg:postcode":"52353",
    "sg:province":"Nordrhein-Westfalen",
    "wof:name":"Alten- Und Pflegeheim Latz",
    "wof:placetype":"venue"
},
  "geometry": {"coordinates":[6.420802,50.826843],"type":"Point"}
}