{
  "type": "Feature",
  "properties": {
    "iso:country":"DE",
    "sg:address":"D\u00f6belner Str.",
    "sg:city":"Dresden",
    "sg:phone":"+49 351/5670773",
    "sg:postcode":"01129",
    "sg:province":"Sachsen",
    "wof:name":"Lidl Gmbh & Co. Kg",
    "wof:placetype":"venue"
},
  "geometry": {"coordinates":[13.7199716568,51.0964584351],"type":"Point"}
}