{
  "type": "Feature",
  "properties": {
    "iso:country":"DE",
    "sg:address":"Friedrichstr. 62 - 78",
    "sg:city":"D\u00fcsseldorf",
    "sg:phone":"+49 211/8762345",
    "sg:postcode":"40217",
    "sg:province":"Nordrhein-Westfalen",
    "wof:name":"Archiv Der Provinzial- Versicherungsanstalten",
    "wof:placetype":"venue"
},
  "geometry": {"coordinates":[6.777042,51.21365],"type":"Point"}
}