{
  "type": "Feature",
  "properties": {
    "iso:country":"DE",
    "sg:address":"Husumer Str. 19",
    "sg:city":"B\u00fchren",
    "sg:phone":"+49 4447/666",
    "sg:postcode":"49685",
    "sg:province":"Niedersachsen",
    "wof:name":"Nkb Gartengestaltung Und Sb Pflanzen-grosshandel Gmbh",
    "wof:placetype":"venue"
},
  "geometry": {"coordinates":[8.22099,52.809151],"type":"Point"}
}