{
  "type": "Feature",
  "properties": {
    "iso:country":"DE",
    "sg:address":"Obergasse 22",
    "sg:city":"Heyerode",
    "sg:phone":"+49 36024/89138",
    "sg:postcode":"99988",
    "sg:province":"Th\u00fcringen",
    "wof:name":"Annemarie Ellerich",
    "wof:placetype":"venue"
},
  "geometry": {"coordinates":[10.32303,51.165112],"type":"Point"}
}