{
  "type": "Feature",
  "properties": {
    "iso:country":"DE",
    "sg:address":"L\u00f6\u00dfniger Str. 7",
    "sg:city":"Markkleeberg",
    "sg:phone":"+49 341/358240304",
    "sg:postcode":"04416",
    "sg:province":"Sachsen",
    "wof:name":"Ingenieurb\u00fcro Dornbusch Und Partner Gmbh",
    "wof:placetype":"venue"
},
  "geometry": {"coordinates":[12.3733997345,51.2888450623],"type":"Point"}
}