{
  "type": "Feature",
  "properties": {
    "iso:country":"DE",
    "sg:address":"Friedrich-Ebert-Anlage 45-47",
    "sg:city":"Frankfurt",
    "sg:phone":"+49 69/75320",
    "sg:postcode":"60327",
    "sg:province":"Hessen",
    "wof:name":"Goldman Sachs & Co. Finanz Gmbh",
    "wof:placetype":"venue"
},
  "geometry": {"coordinates":[8.6560201645,50.1113891602],"type":"Point"}
}