{
  "type": "Feature",
  "properties": {
    "iso:country":"DE",
    "sg:address":"Kirchstr. 65",
    "sg:city":"Reinheim",
    "sg:phone":"+49 6162/3386",
    "sg:postcode":"64354",
    "sg:province":"Hessen",
    "wof:name":"Ev. Pfarramt Dreifaltigkeits Bz.",
    "wof:placetype":"venue"
},
  "geometry": {"coordinates":[8.8388204575,49.8269805908],"type":"Point"}
}