{
  "type": "Feature",
  "properties": {
    "iso:country":"DE",
    "sg:address":"Lupinenweg 10",
    "sg:city":"Marlow",
    "sg:postcode":"18337",
    "sg:province":"Mecklenburg-Vorpommern",
    "wof:name":"Lorex Gmbh",
    "wof:placetype":"venue"
},
  "geometry": {"coordinates":[12.4412517548,54.1751785278],"type":"Point"}
}