{
  "type": "Feature",
  "properties": {
    "iso:country":"DE",
    "sg:address":"Breite Str. 7",
    "sg:city":"Ovelg\u00f6nne",
    "sg:phone":"+49 4401/982363",
    "sg:postcode":"26939",
    "sg:province":"Niedersachsen",
    "wof:name":"Schwarzes Ro\u00df",
    "wof:placetype":"venue"
},
  "geometry": {"coordinates":[8.420460701,53.3419723511],"type":"Point"}
}