{
  "type": "Feature",
  "properties": {
    "iso:country":"DE",
    "sg:address":"Bahnhofstr. 33",
    "sg:city":"Soltau",
    "sg:phone":"+49 5191/2206",
    "sg:postcode":"29614",
    "sg:province":"Niedersachsen",
    "wof:name":"Fenner Und Moog-steffens Rechtsanw\u00e4lte",
    "wof:placetype":"venue"
},
  "geometry": {"coordinates":[9.8316879272,52.9850540161],"type":"Point"}
}