{
  "type": "Feature",
  "properties": {
    "iso:country":"DE",
    "sg:address":"Justus-von-Liebig-Str 8a",
    "sg:city":"Elmshorn",
    "sg:phone":"+49 4121/579990",
    "sg:postcode":"25335",
    "sg:province":"Schleswig-Holstein",
    "wof:name":"Jakob Thaler Gmbh Kabelverlege- Und Spulmaschinenfabrik",
    "wof:placetype":"venue"
},
  "geometry": {"coordinates":[9.654443,53.776283],"type":"Point"}
}