{
  "type": "Feature",
  "properties": {
    "iso:country":"DE",
    "sg:address":"Berkerlerstr. 5",
    "sg:city":"Emmerthal",
    "sg:phone":"+49 5151",
    "sg:postcode":"31860",
    "sg:province":"Niedersachsen",
    "wof:name":"Freli,dies Und Das",
    "wof:placetype":"venue"
},
  "geometry": {"coordinates":[9.352617,52.062344],"type":"Point"}
}