{
  "type": "Feature",
  "properties": {
    "iso:country":"DE",
    "sg:address":"Moritzburger Str. 8",
    "sg:city":"Radebeul",
    "sg:phone":"+49 351/8385990",
    "sg:postcode":"01445",
    "sg:province":"Sachsen",
    "wof:name":"Arbitec Gmbh",
    "wof:placetype":"venue"
},
  "geometry": {"coordinates":[13.631367,51.109192],"type":"Point"}
}