{
  "type": "Feature",
  "properties": {
    "iso:country":"DE",
    "sg:address":"Wiesenweg 2",
    "sg:city":"Sengenthal",
    "sg:phone":"+49 9181/21589",
    "sg:postcode":"92369",
    "sg:province":"Bayern",
    "wof:name":"Gerhard Meier Architekt",
    "wof:placetype":"venue"
},
  "geometry": {"coordinates":[11.439469,49.237038],"type":"Point"}
}