{
  "type": "Feature",
  "properties": {
    "iso:country":"DE",
    "sg:address":"Alter Damm 1",
    "sg:city":"Barenburg",
    "sg:phone":"+49 4273/444",
    "sg:postcode":"27245",
    "sg:province":"Niedersachsen",
    "wof:name":"Heinfried Schwier Gmbh",
    "wof:placetype":"venue"
},
  "geometry": {"coordinates":[8.7996692657,52.6206817627],"type":"Point"}
}