{
  "type": "Feature",
  "properties": {
    "iso:country":"DE",
    "sg:address":"Riedwiesenweg 69",
    "sg:city":"Ulm",
    "sg:phone":"+49 731/385555",
    "sg:postcode":"89081",
    "sg:province":"Baden-W\u00fcrttemberg",
    "wof:name":"J. Stichler",
    "wof:placetype":"venue"
},
  "geometry": {"coordinates":[9.9421901703,48.4035606384],"type":"Point"}
}