{
  "type": "Feature",
  "properties": {
    "iso:country":"DE",
    "sg:address":"Am Scheerhof 12",
    "sg:city":"Flieden",
    "sg:phone":"+49 6655/1493",
    "sg:postcode":"36103",
    "sg:province":"Hessen",
    "wof:name":"Ewald Schneider",
    "wof:placetype":"venue"
},
  "geometry": {"coordinates":[9.536107,50.414276],"type":"Point"}
}