{
  "type": "Feature",
  "properties": {
    "iso:country":"DE",
    "sg:address":"Edelwei\u00dfweg 4",
    "sg:city":"Friedrichshafen",
    "sg:phone":"+49 7541/6666",
    "sg:postcode":"88046",
    "sg:province":"Baden-W\u00fcrttemberg",
    "wof:name":"Heinz Cordel",
    "wof:placetype":"venue"
},
  "geometry": {"coordinates":[9.4902210236,47.6696281433],"type":"Point"}
}