{
  "type": "Feature",
  "properties": {
    "iso:country":"DE",
    "sg:address":"Achtern Tun 4",
    "sg:city":"Friedeburg",
    "sg:phone":"+49 4465/77003",
    "sg:postcode":"26446",
    "sg:province":"Niedersachsen",
    "wof:name":"G\u00fcnter Weidh\u00fcner",
    "wof:placetype":"venue"
},
  "geometry": {"coordinates":[7.892693,53.460564],"type":"Point"}
}