{
  "type": "Feature",
  "properties": {
    "iso:country":"DE",
    "sg:address":"Kapellenweg 22",
    "sg:city":"Wienhausen",
    "sg:phone":"+49 5149/1421",
    "sg:postcode":"29342",
    "sg:province":"Niedersachsen",
    "wof:name":"J. H. Dobson Medizintechnik Gmbh",
    "wof:placetype":"venue"
},
  "geometry": {"coordinates":[10.199268,52.587589],"type":"Point"}
}