{
  "type": "Feature",
  "properties": {
    "iso:country":"DE",
    "sg:address":"B\u00fcdenholzer Str. 39",
    "sg:city":"Brachbach",
    "sg:phone":"+49 2745/275",
    "sg:postcode":"57555",
    "sg:province":"Rheinland-Pfalz",
    "wof:name":"Kies Becher Hans-peter Becher",
    "wof:placetype":"venue"
},
  "geometry": {"coordinates":[7.9322919846,50.8188743591],"type":"Point"}
}