{
  "type": "Feature",
  "properties": {
    "iso:country":"DE",
    "sg:address":"P\u00f6ltnerstr. 20",
    "sg:city":"Weilheim",
    "sg:phone":"+49 881/41470",
    "sg:postcode":"82362",
    "sg:province":"Bayern",
    "wof:name":"Rolf R. Carl Ingenieur",
    "wof:placetype":"venue"
},
  "geometry": {"coordinates":[11.1415710449,47.8379402161],"type":"Point"}
}