{
  "type": "Feature",
  "properties": {
    "iso:country":"DE",
    "sg:address":"Wohnlichstr. 6-8",
    "sg:city":"Pforzheim",
    "sg:phone":"+49 7231/440751",
    "sg:postcode":"75179",
    "sg:province":"Baden-W\u00fcrttemberg",
    "wof:name":"Walter Dumbert Ohg",
    "wof:placetype":"venue"
},
  "geometry": {"coordinates":[8.654094696,48.8798065186],"type":"Point"}
}