{
  "type": "Feature",
  "properties": {
    "iso:country":"DE",
    "sg:address":"Heide 21",
    "sg:city":"Grefrath",
    "sg:phone":"+49 2158/3308",
    "sg:postcode":"47929",
    "sg:province":"Nordrhein-Westfalen",
    "wof:name":"Siegfried K\u00f6rner",
    "wof:placetype":"venue"
},
  "geometry": {"coordinates":[6.3409261703,51.3509483337],"type":"Point"}
}