{
  "type": "Feature",
  "properties": {
    "iso:country":"DE",
    "sg:address":"Theisbr\u00fcgger Str. 19",
    "sg:city":"Drochtersen",
    "sg:phone":"+49 4143/6632",
    "sg:postcode":"21706",
    "sg:province":"Niedersachsen",
    "wof:name":"Helmut Maak",
    "wof:placetype":"venue"
},
  "geometry": {"coordinates":[9.3406295776,53.7039299011],"type":"Point"}
}