{
  "type": "Feature",
  "properties": {
    "iso:country":"DE",
    "sg:address":"Industriestr. 1",
    "sg:city":"Adelsheim",
    "sg:phone":"+49 6291/41660",
    "sg:postcode":"74740",
    "sg:province":"Baden-W\u00fcrttemberg",
    "wof:name":"Trefz Gmbh",
    "wof:placetype":"venue"
},
  "geometry": {"coordinates":[9.385919,49.412449],"type":"Point"}
}