{
  "type": "Feature",
  "properties": {
    "iso:country":"DE",
    "sg:address":"Auf der L\u00e4ng 7",
    "sg:city":"W\u00fcrzburg",
    "sg:phone":"+49 931/272273",
    "sg:postcode":"97076",
    "sg:province":"Bayern",
    "wof:name":"Dorothea Zuber",
    "wof:placetype":"venue"
},
  "geometry": {"coordinates":[9.9865903854,49.8141746521],"type":"Point"}
}