{
  "type": "Feature",
  "properties": {
    "iso:country":"DE",
    "sg:address":"Gollierstr. 3",
    "sg:city":"M\u00fcnchen",
    "sg:phone":"+49 89/5020300",
    "sg:postcode":"80339",
    "sg:province":"Bayern",
    "wof:name":"Barbara Brolski",
    "wof:placetype":"venue"
},
  "geometry": {"coordinates":[11.5471839905,48.1354789734],"type":"Point"}
}