{
  "type": "Feature",
  "properties": {
    "iso:country":"DE",
    "sg:address":"Waldstr. 18",
    "sg:city":"Albersdorf",
    "sg:phone":"+49 4835/9040",
    "sg:postcode":"25767",
    "sg:province":"Schleswig-Holstein",
    "wof:name":"Nordmarkhaus Gmbh",
    "wof:placetype":"venue"
},
  "geometry": {"coordinates":[9.2992649078,54.1454277039],"type":"Point"}
}