{
  "type": "Feature",
  "properties": {
    "iso:country":"DE",
    "sg:address":"Froelichstr. 6",
    "sg:city":"Zweibr\u00fccken",
    "sg:phone":"+49 6332/46124",
    "sg:postcode":"66482",
    "sg:province":"Rheinland-Pfalz",
    "wof:name":"Max W. Geminn Ingenieur",
    "wof:placetype":"venue"
},
  "geometry": {"coordinates":[7.3817539215,49.2482261658],"type":"Point"}
}