{
  "type": "Feature",
  "properties": {
    "iso:country":"DE",
    "sg:address":"Diemershaldenstr. 11",
    "sg:city":"Stuttgart",
    "sg:phone":"+49 711/239250",
    "sg:postcode":"70184",
    "sg:province":"Baden-W\u00fcrttemberg",
    "wof:name":"Franz\u00f6sisches Institut",
    "wof:placetype":"venue"
},
  "geometry": {"coordinates":[9.1909093857,48.7772293091],"type":"Point"}
}