{
  "type": "Feature",
  "properties": {
    "iso:country":"DE",
    "sg:address":"M\u00e4rkische Str. 13",
    "sg:city":"Wetter",
    "sg:phone":"+49 2335/3238",
    "sg:postcode":"58300",
    "sg:province":"Nordrhein-Westfalen",
    "wof:name":"J\u00fcrgen Sauer",
    "wof:placetype":"venue"
},
  "geometry": {"coordinates":[7.392565,51.385376],"type":"Point"}
}