{
  "type": "Feature",
  "properties": {
    "iso:country":"DE",
    "sg:address":"Lempstr. 24",
    "sg:city":"Remscheid",
    "sg:postcode":"42859",
    "sg:province":"Nordrhein-Westfalen",
    "wof:name":"Atr Armaturen-technik Remscheid Gmbh & Co. Kg",
    "wof:placetype":"venue"
},
  "geometry": {"coordinates":[7.20649,51.166904],"type":"Point"}
}