{
  "type": "Feature",
  "properties": {
    "iso:country":"DE",
    "sg:address":"Uferstr. 10",
    "sg:city":"Sch\u00f6ppenstedt",
    "sg:phone":"+49 5332/1430",
    "sg:postcode":"38170",
    "sg:province":"Niedersachsen",
    "wof:name":"Heinrich Oppermann",
    "wof:placetype":"venue"
},
  "geometry": {"coordinates":[10.788734,52.144554],"type":"Point"}
}