{
  "type": "Feature",
  "properties": {
    "iso:country":"DE",
    "sg:address":"Gustav-Schwab-Str. 5",
    "sg:city":"Reutlingen",
    "sg:postcode":"72762",
    "sg:province":"Baden-W\u00fcrttemberg",
    "wof:name":"Richard Staiger Gmbh",
    "wof:placetype":"venue"
},
  "geometry": {"coordinates":[9.1921653748,48.4904403687],"type":"Point"}
}