{
  "type": "Feature",
  "properties": {
    "iso:country":"DE",
    "sg:address":"Weiherstr. 7",
    "sg:city":"Kirkel",
    "sg:phone":"+49 6841/81545",
    "sg:postcode":"66459",
    "sg:province":"Saarland",
    "wof:name":"Gerd Klein",
    "wof:placetype":"venue"
},
  "geometry": {"coordinates":[7.269443,49.315697],"type":"Point"}
}