{
  "type": "Feature",
  "properties": {
    "iso:country":"DE",
    "sg:address":"Talstr. 40",
    "sg:city":"Gummersbach",
    "sg:phone":"+49 2261/81050",
    "sg:postcode":"51643",
    "sg:province":"Nordrhein-Westfalen",
    "wof:name":"Rothstein Vitrinen Gmbh",
    "wof:placetype":"venue"
},
  "geometry": {"coordinates":[7.5759902,51.0249710083],"type":"Point"}
}