{
  "type": "Feature",
  "properties": {
    "iso:country":"DE",
    "sg:address":"Ratsstr. 15",
    "sg:city":"Langewiesen",
    "sg:phone":"+49 3677/801607",
    "sg:postcode":"98704",
    "sg:province":"Th\u00fcringen",
    "wof:name":"Textilreinigung Langewiesen",
    "wof:placetype":"venue"
},
  "geometry": {"coordinates":[10.973909,50.670868],"type":"Point"}
}