{
  "type": "Feature",
  "properties": {
    "iso:country":"DE",
    "sg:address":"In den Lachen\u00e4ckern 1",
    "sg:city":"Lingenfeld",
    "sg:phone":"+49 6344/938544",
    "sg:postcode":"67360",
    "sg:province":"Rheinland-Pfalz",
    "wof:name":"Wetzel Gmbh",
    "wof:placetype":"venue"
},
  "geometry": {"coordinates":[8.3571071625,49.2365112305],"type":"Point"}
}