{
  "type": "Feature",
  "properties": {
    "iso:country":"DE",
    "sg:address":"Ziegelstr. 68",
    "sg:city":"Bielefeld",
    "sg:phone":"+49 521/750484",
    "sg:postcode":"33609",
    "sg:province":"Nordrhein-Westfalen",
    "wof:name":"Olaf G\u00f6decke E. K.",
    "wof:placetype":"venue"
},
  "geometry": {"coordinates":[8.5721206665,52.0354385376],"type":"Point"}
}