{
  "type": "Feature",
  "properties": {
    "iso:country":"DE",
    "sg:address":"Memelstr. 5",
    "sg:city":"Minden",
    "sg:postcode":"32423",
    "sg:province":"Nordrhein-Westfalen",
    "wof:name":"Freizeitbad Herford Bautr\u00e4ger Gmbh",
    "wof:placetype":"venue"
},
  "geometry": {"coordinates":[8.925797,52.29705],"type":"Point"}
}