{
  "type": "Feature",
  "properties": {
    "iso:country":"DE",
    "sg:address":"Friedrich-Fleischhauer-Str. 34",
    "sg:city":"Nachterstedt",
    "sg:phone":"+49 34741/6315",
    "sg:postcode":"06469",
    "sg:province":"Sachsen-Anhalt",
    "wof:name":"Wohnungsgesellschaft Mbh",
    "wof:placetype":"venue"
},
  "geometry": {"coordinates":[11.332662,51.801132],"type":"Point"}
}