{
  "type": "Feature",
  "properties": {
    "iso:country":"DE",
    "sg:address":"Zur Eisernen Hand 25 B",
    "sg:city":"M\u00fchltal / Traisa",
    "sg:postcode":"64367",
    "sg:province":"Hessen",
    "wof:name":"Daf\u00dcr Gmbh, Datenfern\u00fcbertragung Rohm",
    "wof:placetype":"venue"
},
  "geometry": {"coordinates":[8.712108,49.844421],"type":"Point"}
}