{
  "type": "Feature",
  "properties": {
    "iso:country":"DE",
    "sg:address":"Schwedenweg 2",
    "sg:city":"Mittelstetten",
    "sg:phone":"+49 8141/21703",
    "sg:postcode":"82293",
    "sg:province":"Bayern",
    "wof:name":"L. Niederreiner",
    "wof:placetype":"venue"
},
  "geometry": {"coordinates":[11.12312,48.24511],"type":"Point"}
}