{
  "type": "Feature",
  "properties": {
    "iso:country":"DE",
    "sg:address":"Malensteinweg 14",
    "sg:city":"Oberammergau",
    "sg:phone":"+49 8822/7154",
    "sg:postcode":"82487",
    "sg:province":"Bayern",
    "wof:name":"U. Fischer",
    "wof:placetype":"venue"
},
  "geometry": {"coordinates":[11.0641946793,47.5915870667],"type":"Point"}
}