{
  "type": "Feature",
  "properties": {
    "iso:country":"DE",
    "sg:address":"Albanstr. 15",
    "sg:city":"Pulheim",
    "sg:phone":"+49 2238/51342",
    "sg:postcode":"50259",
    "sg:province":"Nordrhein-Westfalen",
    "wof:name":"Gerhard Fensterer",
    "wof:placetype":"venue"
},
  "geometry": {"coordinates":[6.787797,50.978844],"type":"Point"}
}