{
  "type": "Feature",
  "properties": {
    "iso:country":"DE",
    "sg:address":"Neue Kantstr. 31",
    "sg:city":"Berlin",
    "sg:phone":"+49 30/3218292",
    "sg:postcode":"14057",
    "sg:province":"Berlin",
    "wof:name":"Restaurant Marija Sucic",
    "wof:placetype":"venue"
},
  "geometry": {"coordinates":[13.2941331863,52.5065994263],"type":"Point"}
}