{
  "type": "Feature",
  "properties": {
    "iso:country":"DE",
    "sg:address":"Schwarzachstr. 9",
    "sg:city":"Burgthann",
    "sg:phone":"+49 9183/93070",
    "sg:postcode":"90559",
    "sg:province":"Bayern",
    "wof:name":"A. C. Gr\u00d6tsch Kunststoffteile Gmbh",
    "wof:placetype":"venue"
},
  "geometry": {"coordinates":[11.3185386658,49.3570785522],"type":"Point"}
}