{
  "type": "Feature",
  "properties": {
    "iso:country":"DE",
    "sg:address":"Altsiedlung 17",
    "sg:city":"Pegau",
    "sg:phone":"+49 34296/76148",
    "sg:postcode":"04523",
    "sg:province":"Sachsen",
    "wof:name":"Erwin Littmann",
    "wof:placetype":"venue"
},
  "geometry": {"coordinates":[12.28194,51.193859],"type":"Point"}
}