{
  "type": "Feature",
  "properties": {
    "iso:country":"DE",
    "sg:address":"Enge Str. 4",
    "sg:city":"Wietzendorf",
    "sg:phone":"+49 5196/641",
    "sg:postcode":"29649",
    "sg:province":"Niedersachsen",
    "wof:name":"E. Schr\u00f6der",
    "wof:placetype":"venue"
},
  "geometry": {"coordinates":[9.97651577,52.9183387756],"type":"Point"}
}