{
  "type": "Feature",
  "properties": {
    "iso:country":"DE",
    "sg:address":"Hohe Str. 16",
    "sg:city":"Datteln",
    "sg:postcode":"45711",
    "sg:province":"Nordrhein-Westfalen",
    "wof:name":"I & U City Handel Export-import Gmbh",
    "wof:placetype":"venue"
},
  "geometry": {"coordinates":[7.3427920341,51.6533470154],"type":"Point"}
}