{
  "type": "Feature",
  "properties": {
    "iso:country":"DE",
    "sg:address":"Unterstr. 6",
    "sg:city":"Sondershausen",
    "sg:phone":"+49 3632/602571",
    "sg:postcode":"99706",
    "sg:province":"Th\u00fcringen",
    "wof:name":"Karl-heinz Blossey",
    "wof:placetype":"venue"
},
  "geometry": {"coordinates":[10.835258,51.372665],"type":"Point"}
}