{
  "type": "Feature",
  "properties": {
    "iso:country":"DE",
    "sg:address":"Widayweg 2",
    "sg:city":"Arnsberg",
    "sg:postcode":"59823",
    "sg:province":"Nordrhein-Westfalen",
    "wof:name":"Combi",
    "wof:placetype":"venue"
},
  "geometry": {"coordinates":[8.1349668503,51.3963356018],"type":"Point"}
}