{
  "type": "Feature",
  "properties": {
    "iso:country":"DE",
    "sg:address":"J\u00e4uchstr. 2",
    "sg:city":"Frittlingen",
    "sg:phone":"+49 7426/7246",
    "sg:postcode":"78665",
    "sg:province":"Baden-W\u00fcrttemberg",
    "wof:name":"Frittrang Gmbh",
    "wof:placetype":"venue"
},
  "geometry": {"coordinates":[8.70394,48.129726],"type":"Point"}
}