{
  "type": "Feature",
  "properties": {
    "iso:country":"DE",
    "sg:address":"Bayreuther Str. 18",
    "sg:city":"Igensdorf",
    "sg:phone":"+49 9192/4777",
    "sg:postcode":"91338",
    "sg:province":"Bayern",
    "wof:name":"Manfred Eckert",
    "wof:placetype":"venue"
},
  "geometry": {"coordinates":[11.2356185913,49.6208267212],"type":"Point"}
}