{
  "type": "Feature",
  "properties": {
    "iso:country":"DE",
    "sg:address":"Wielandstr. 2",
    "sg:city":"Halle",
    "sg:phone":"+49 5201/7090",
    "sg:postcode":"33790",
    "sg:province":"Nordrhein-Westfalen",
    "wof:name":"Nordenia Deutschland Halle Gmbh",
    "wof:placetype":"venue"
},
  "geometry": {"coordinates":[8.3809871674,52.0415344238],"type":"Point"}
}