{
  "type": "Feature",
  "properties": {
    "iso:country":"DE",
    "sg:address":"Lindenstr. 6",
    "sg:city":"Schwerin",
    "sg:phone":"+49 385/5571840",
    "sg:postcode":"19055",
    "sg:province":"Mecklenburg-Vorpommern",
    "wof:name":"Kristensen Und Partner Verwaltungs Bauges. Mbh",
    "wof:placetype":"venue"
},
  "geometry": {"coordinates":[11.4183588028,53.6322631836],"type":"Point"}
}