{
  "type": "Feature",
  "properties": {
    "iso:country":"DE",
    "sg:address":"Lammstr. 1",
    "sg:city":"Sachsenheim",
    "sg:phone":"+49 7147/3335",
    "sg:postcode":"74343",
    "sg:province":"Baden-W\u00fcrttemberg",
    "wof:name":"Gastst\u00e4tte Bierf\u00e4\u00dfle",
    "wof:placetype":"venue"
},
  "geometry": {"coordinates":[9.0631799698,48.9595603943],"type":"Point"}
}