{
  "type": "Feature",
  "properties": {
    "iso:country":"DE",
    "sg:address":"Max-Planck-Str 8",
    "sg:city":"Ditzingen",
    "sg:phone":"+49 711/88080",
    "sg:postcode":"71254",
    "sg:province":"Baden-W\u00fcrttemberg",
    "wof:name":"Siegle & Epple Gmbh & Co Kg",
    "wof:placetype":"venue"
},
  "geometry": {"coordinates":[8.99465,48.855518],"type":"Point"}
}