{
  "type": "Feature",
  "properties": {
    "iso:country":"DE",
    "sg:address":"Anton-Aulke-Str. 1",
    "sg:city":"Billerbeck",
    "sg:phone":"+49 2543/23094",
    "sg:postcode":"48727",
    "sg:province":"Nordrhein-Westfalen",
    "wof:name":"Albo-data-system Gmbh",
    "wof:placetype":"venue"
},
  "geometry": {"coordinates":[7.282506,51.976021],"type":"Point"}
}