{
  "type": "Feature",
  "properties": {
    "iso:country":"DE",
    "sg:address":"Eckartstr. 37",
    "sg:city":"Wegberg",
    "sg:phone":"+49 2432/6837",
    "sg:postcode":"41844",
    "sg:province":"Nordrhein-Westfalen",
    "wof:name":"Karl Hoffmann",
    "wof:placetype":"venue"
},
  "geometry": {"coordinates":[6.206576,51.123951],"type":"Point"}
}