{
  "type": "Feature",
  "properties": {
    "iso:country":"DE",
    "sg:address":"Kuttelweg 7",
    "sg:city":"Dormagen",
    "sg:phone":"+49 2133/92609",
    "sg:postcode":"41542",
    "sg:province":"Nordrhein-Westfalen",
    "wof:name":"Birgit Kollenbroich Rechtsaw\u00e4ltin",
    "wof:placetype":"venue"
},
  "geometry": {"coordinates":[6.7719941139,51.1225891113],"type":"Point"}
}