{
  "type": "Feature",
  "properties": {
    "iso:country":"DE",
    "sg:address":"Simbacher Str. 26",
    "sg:city":"Pocking",
    "sg:phone":"+49 8531/7806",
    "sg:postcode":"94060",
    "sg:province":"Bayern",
    "wof:name":"Adolf \u00d6ller",
    "wof:placetype":"venue"
},
  "geometry": {"coordinates":[13.3109378815,48.3980178833],"type":"Point"}
}