{
  "type": "Feature",
  "properties": {
    "iso:country":"DE",
    "sg:address":"Lange Str. 94",
    "sg:city":"Osnabr\u00fcck",
    "sg:phone":"+49 541/84770",
    "sg:postcode":"49080",
    "sg:province":"Niedersachsen",
    "wof:name":"I. Poo Carrera",
    "wof:placetype":"venue"
},
  "geometry": {"coordinates":[8.0443382263,52.2654724121],"type":"Point"}
}