{
  "type": "Feature",
  "properties": {
    "iso:country":"DE",
    "sg:address":"Tulpenstrasse 20",
    "sg:city":"Stuttgart",
    "sg:phone":"+49 711",
    "sg:postcode":"70180",
    "sg:province":"Baden-W\u00fcrttemberg",
    "wof:name":"Csg Clean-service Geb\u00e4udereinigung Gmbh",
    "wof:placetype":"venue"
},
  "geometry": {"coordinates":[9.176459,48.763008],"type":"Point"}
}