{
  "type": "Feature",
  "properties": {
    "iso:country":"DE",
    "sg:address":"Alfred-Nobel-Str. 10",
    "sg:city":"Monheim",
    "sg:phone":"+49 9131/746431",
    "sg:postcode":"40789",
    "sg:province":"Nordrhein-Westfalen",
    "wof:name":"Siemens Airfield Solutions",
    "wof:placetype":"venue"
},
  "geometry": {"coordinates":[11.0025749207,49.5979537964],"type":"Point"}
}