{
  "type": "Feature",
  "properties": {
    "iso:country":"DE",
    "sg:address":"Herderstr. 3",
    "sg:city":"Sch\u00f6nberg",
    "sg:phone":"+49 4344/3481",
    "sg:postcode":"24217",
    "sg:province":"Schleswig-Holstein",
    "wof:name":"Smp Stelck Marten Projekte Gmbh",
    "wof:placetype":"venue"
},
  "geometry": {"coordinates":[10.375639,54.389088],"type":"Point"}
}