{
  "type": "Feature",
  "properties": {
    "iso:country":"DE",
    "sg:address":"Hafenstr. 193",
    "sg:city":"Bremerhaven",
    "sg:phone":"+49 471/52161",
    "sg:postcode":"27568",
    "sg:province":"Bremen",
    "wof:name":"Peter Block",
    "wof:placetype":"venue"
},
  "geometry": {"coordinates":[8.5861034393,53.5638465881],"type":"Point"}
}