{
  "type": "Feature",
  "properties": {
    "iso:country":"DE",
    "sg:address":"Schwarztorweg 6",
    "sg:city":"Buseck",
    "sg:phone":"+49 6408/547206",
    "sg:postcode":"35418",
    "sg:province":"Hessen",
    "wof:name":"Neukauf",
    "wof:placetype":"venue"
},
  "geometry": {"coordinates":[8.7496967316,50.6211051941],"type":"Point"}
}