{
  "type": "Feature",
  "properties": {
    "iso:country":"DE",
    "sg:address":"Roseninsel 18",
    "sg:city":"Nordhalben",
    "sg:phone":"+49 9267/246",
    "sg:postcode":"96365",
    "sg:province":"Bayern",
    "wof:name":"Joh. C. Schlee Drogen-u. Farben-grosshandel",
    "wof:placetype":"venue"
},
  "geometry": {"coordinates":[11.5136642456,50.3741798401],"type":"Point"}
}