{
  "type": "Feature",
  "properties": {
    "iso:country":"DE",
    "sg:address":"Hauptstr. 95",
    "sg:city":"Dischingen",
    "sg:phone":"+49 7327/460",
    "sg:postcode":"89561",
    "sg:province":"Baden-W\u00fcrttemberg",
    "wof:name":"Gepa Hausbau Gmbh & Co. Kg",
    "wof:placetype":"venue"
},
  "geometry": {"coordinates":[10.3639497757,48.6960906982],"type":"Point"}
}