{
  "type": "Feature",
  "properties": {
    "iso:country":"DE",
    "sg:address":"Am R\u00f6mertor 3",
    "sg:city":"Wiesbaden",
    "sg:phone":"+49 611/304416",
    "sg:postcode":"65183",
    "sg:province":"Hessen",
    "wof:name":"G. W. O. Meya",
    "wof:placetype":"venue"
},
  "geometry": {"coordinates":[8.239648819,50.0842247009],"type":"Point"}
}