{
  "type": "Feature",
  "properties": {
    "iso:country":"DE",
    "sg:address":"Nollb\u00f6hlstr. 4",
    "sg:city":"Trebur",
    "sg:phone":"+49 6147/2520",
    "sg:postcode":"65468",
    "sg:province":"Hessen",
    "wof:name":"G\u00fcnter H\u00f6hler",
    "wof:placetype":"venue"
},
  "geometry": {"coordinates":[8.3996162415,49.9292068481],"type":"Point"}
}