{
  "type": "Feature",
  "properties": {
    "iso:country":"DE",
    "sg:address":"Otto-Schwabe-Str. 1",
    "sg:city":"Hochheim",
    "sg:phone":"+49 6146/2721",
    "sg:postcode":"65239",
    "sg:province":"Hessen",
    "wof:name":"V. Petry Lotterie",
    "wof:placetype":"venue"
},
  "geometry": {"coordinates":[8.351527,50.017403],"type":"Point"}
}