{
  "type": "Feature",
  "properties": {
    "iso:country":"DE",
    "sg:address":"Flurbachstr. 2",
    "sg:city":"Gro\u00df-Bieberau",
    "sg:phone":"+49 6162/3643",
    "sg:postcode":"64401",
    "sg:province":"Hessen",
    "wof:name":"Krebo-elektro-service Gmbh",
    "wof:placetype":"venue"
},
  "geometry": {"coordinates":[8.822187,49.798054],"type":"Point"}
}