{
  "type": "Feature",
  "properties": {
    "iso:country":"DE",
    "sg:address":"Eckgasse 2",
    "sg:city":"Wiesbaden",
    "sg:phone":"+49 611/1885736",
    "sg:postcode":"65207",
    "sg:province":"Hessen",
    "wof:name":"First-service Multimedia Gmbh & Co. Kg",
    "wof:placetype":"venue"
},
  "geometry": {"coordinates":[8.275014,50.116123],"type":"Point"}
}