{
  "type": "Feature",
  "properties": {
    "iso:country":"DE",
    "sg:address":"Moltkestr. 5",
    "sg:city":"W\u00fcrzburg",
    "sg:phone":"+49 931/4501750",
    "sg:postcode":"97082",
    "sg:province":"Bayern",
    "wof:name":"Teamwork New Media Gmbh",
    "wof:placetype":"venue"
},
  "geometry": {"coordinates":[9.912752,49.793438],"type":"Point"}
}