{
  "type": "Feature",
  "properties": {
    "iso:country":"DE",
    "sg:address":"Salzburger Str. 22",
    "sg:city":"Bad Reichenhall",
    "sg:phone":"+49 8651/96950",
    "sg:postcode":"83435",
    "sg:province":"Bayern",
    "wof:name":"Schwabenbr\u00e4u",
    "wof:placetype":"venue"
},
  "geometry": {"coordinates":[12.8846311569,47.7282905579],"type":"Point"}
}