{
  "type": "Feature",
  "properties": {
    "iso:country":"DE",
    "sg:address":"Karl-Marx-Str. 84-86",
    "sg:city":"Berlin",
    "sg:phone":"+49 30/6872878",
    "sg:postcode":"12043",
    "sg:province":"Berlin",
    "wof:name":"Praxis Dr. Med. Ramdohr",
    "wof:placetype":"venue"
},
  "geometry": {"coordinates":[13.4349403381,52.4808807373],"type":"Point"}
}