{
  "type": "Feature",
  "properties": {
    "iso:country":"DE",
    "sg:address":"Flughafenstr. 38",
    "sg:city":"Berlin",
    "sg:phone":"+49 30/6248390",
    "sg:postcode":"12053",
    "sg:province":"Berlin",
    "wof:name":"Korner",
    "wof:placetype":"venue"
},
  "geometry": {"coordinates":[13.4280395508,52.4813156128],"type":"Point"}
}