{
  "type": "Feature",
  "properties": {
    "iso:country":"DE",
    "sg:address":"Gistlstr. 96",
    "sg:city":"Pullach",
    "sg:phone":"+49 89/7253486",
    "sg:postcode":"82049",
    "sg:province":"Bayern",
    "wof:name":"Gilg & Schweiger Gmbh",
    "wof:placetype":"venue"
},
  "geometry": {"coordinates":[11.512196,48.048],"type":"Point"}
}