{
  "type": "Feature",
  "properties": {
    "iso:country":"DE",
    "sg:address":"Gro\u00dfe Steinstr. 25",
    "sg:city":"Halle",
    "sg:phone":"+49 345/2026410",
    "sg:postcode":"06108",
    "sg:province":"Sachsen-Anhalt",
    "wof:name":"Carl G\u00fcstel",
    "wof:placetype":"venue"
},
  "geometry": {"coordinates":[11.9746189117,51.4861755371],"type":"Point"}
}