{
  "type": "Feature",
  "properties": {
    "iso:country":"DE",
    "sg:address":"Birkenweg 1",
    "sg:city":"Br\u00e4unlingen",
    "sg:phone":"+49 7707/530",
    "sg:postcode":"78199",
    "sg:province":"Baden-W\u00fcrttemberg",
    "wof:name":"Bernhard Peter Gmbh",
    "wof:placetype":"venue"
},
  "geometry": {"coordinates":[8.440224,47.932606],"type":"Point"}
}