{
  "type": "Feature",
  "properties": {
    "iso:country":"DE",
    "sg:address":"Siemensstr. 21",
    "sg:city":"Untermeitingen",
    "sg:phone":"+49 8232/908661",
    "sg:postcode":"86836",
    "sg:province":"Bayern",
    "wof:name":"Wms Walter Meile System Verwaltungsgesellschaft Mbh",
    "wof:placetype":"venue"
},
  "geometry": {"coordinates":[10.8314695358,48.1669311523],"type":"Point"}
}