{
  "type": "Feature",
  "properties": {
    "iso:country":"DE",
    "sg:address":"Rudolf-Breitscheid-Str. 44",
    "sg:city":"Fl\u00f6ha",
    "sg:phone":"+49 3726/2427",
    "sg:postcode":"09557",
    "sg:province":"Sachsen",
    "wof:name":"Helfried Barth",
    "wof:placetype":"venue"
},
  "geometry": {"coordinates":[13.077151,50.856476],"type":"Point"}
}