{
  "type": "Feature",
  "properties": {
    "iso:country":"DE",
    "sg:city":"Steinhausen",
    "sg:phone":"+49 4973/523288",
    "sg:postcode":"88416",
    "sg:province":"Baden-W\u00fcrttemberg",
    "wof:name":"Raiffeisenbank Rottum Eg",
    "wof:placetype":"venue"
},
  "geometry": {"coordinates":[9.974845,48.063354],"type":"Point"}
}