{
  "type": "Feature",
  "properties": {
    "iso:country":"DE",
    "sg:address":"Rabanusstr. 32",
    "sg:city":"Fulda",
    "sg:phone":"+49 661/928770",
    "sg:postcode":"36037",
    "sg:province":"Hessen",
    "wof:name":"Werner Knorn Buchhandlung",
    "wof:placetype":"venue"
},
  "geometry": {"coordinates":[9.6804447174,50.5510864258],"type":"Point"}
}