{
  "type": "Feature",
  "properties": {
    "iso:country":"DE",
    "sg:address":"Vl\u00e4mische Str. 15",
    "sg:city":"Lastrup",
    "sg:phone":"+49 4472/1584",
    "sg:postcode":"49688",
    "sg:province":"Niedersachsen",
    "wof:name":"Heinz Siemer",
    "wof:placetype":"venue"
},
  "geometry": {"coordinates":[7.8620419502,52.7961082458],"type":"Point"}
}