{
  "type": "Feature",
  "properties": {
    "iso:country":"DE",
    "sg:address":"August-Bebel-Str. 32",
    "sg:city":"Neugersdorf",
    "sg:phone":"+49 3586/702606",
    "sg:postcode":"02727",
    "sg:province":"Sachsen",
    "wof:name":"Michael Heller",
    "wof:placetype":"venue"
},
  "geometry": {"coordinates":[14.60069,50.975975],"type":"Point"}
}