{
  "type": "Feature",
  "properties": {
    "iso:country":"DE",
    "sg:address":"Lindenstr. 63",
    "sg:city":"Wadgassen",
    "sg:phone":"+49 6834/42021",
    "sg:postcode":"66787",
    "sg:province":"Saarland",
    "wof:name":"Reise-treff Wadgassen Reiseb\u00fcro Gmbh",
    "wof:placetype":"venue"
},
  "geometry": {"coordinates":[6.7975430489,49.267490387],"type":"Point"}
}