{
  "type": "Feature",
  "properties": {
    "iso:country":"DE",
    "sg:address":"Burgsteinfurter Str. 3",
    "sg:city":"Steinfurt",
    "sg:phone":"+49 2552/939570",
    "sg:postcode":"48565",
    "sg:province":"Nordrhein-Westfalen",
    "wof:name":"Redaktion Steinfurter Anzeiger",
    "wof:placetype":"venue"
},
  "geometry": {"coordinates":[7.3946108818,52.1257171631],"type":"Point"}
}