{
  "type": "Feature",
  "properties": {
    "iso:country":"DE",
    "sg:address":"Brauerstrasse 43-45",
    "sg:city":"Kellinghusen",
    "sg:phone":"+49 4948/2237800",
    "sg:postcode":"25548",
    "sg:province":"Schleswig-Holstein",
    "wof:name":"Hans Windecker Kg",
    "wof:placetype":"venue"
},
  "geometry": {"coordinates":[9.72846,53.954937],"type":"Point"}
}