{
  "type": "Feature",
  "properties": {
    "iso:country":"DE",
    "sg:address":"Plaggenhau 5",
    "sg:city":"Martfeld",
    "sg:phone":"+49 4255/209",
    "sg:postcode":"27327",
    "sg:province":"Niedersachsen",
    "wof:name":"Hans Wieneke",
    "wof:placetype":"venue"
},
  "geometry": {"coordinates":[9.084832,52.885723],"type":"Point"}
}