{
  "type": "Feature",
  "properties": {
    "iso:country":"DE",
    "sg:address":"Wolfskuhlen 1",
    "sg:city":"Burgdorf",
    "sg:phone":"+49 5136/800550",
    "sg:postcode":"31303",
    "sg:province":"Niedersachsen",
    "wof:name":"Restaurant Reiterklause",
    "wof:placetype":"venue"
},
  "geometry": {"coordinates":[9.9897251129,52.4639015198],"type":"Point"}
}