{
  "type": "Feature",
  "properties": {
    "iso:country":"DE",
    "sg:address":"Birkenstr. 16",
    "sg:city":"Weilburg",
    "sg:phone":"+49 6471/30986",
    "sg:postcode":"35781",
    "sg:province":"Hessen",
    "wof:name":"Haus Hubertus",
    "wof:placetype":"venue"
},
  "geometry": {"coordinates":[8.2535009384,50.4982261658],"type":"Point"}
}