{
  "type": "Feature",
  "properties": {
    "iso:country":"DE",
    "sg:address":"Seestr. 18",
    "sg:city":"Nonnenhorn",
    "sg:phone":"+49 8382/8415",
    "sg:postcode":"88149",
    "sg:province":"Bayern",
    "wof:name":"H.-j. Bindsch\u00e4del Architekt",
    "wof:placetype":"venue"
},
  "geometry": {"coordinates":[9.608023,47.574589],"type":"Point"}
}