{
  "type": "Feature",
  "properties": {
    "iso:country":"DE",
    "sg:address":"Fredelaker Str. 7",
    "sg:city":"Goldenstedt",
    "sg:phone":"+49 4444/2421",
    "sg:postcode":"49424",
    "sg:province":"Niedersachsen",
    "wof:name":"Heinrich Lask",
    "wof:placetype":"venue"
},
  "geometry": {"coordinates":[8.447219,52.775185],"type":"Point"}
}