{
  "type": "Feature",
  "properties": {
    "iso:country":"DE",
    "sg:address":"Dieckstr. 65",
    "sg:city":"M\u00fcnster",
    "sg:phone":"+49 251/285030",
    "sg:postcode":"48145",
    "sg:province":"Nordrhein-Westfalen",
    "wof:name":"W\u00e4chter Gmbh",
    "wof:placetype":"venue"
},
  "geometry": {"coordinates":[7.6529588699,51.9737739563],"type":"Point"}
}