{
  "type": "Feature",
  "properties": {
    "iso:country":"DE",
    "sg:address":"Nierenberger Str. 150",
    "sg:city":"Emmerich",
    "sg:phone":"+49 2822/976260",
    "sg:postcode":"46446",
    "sg:province":"Nordrhein-Westfalen",
    "wof:name":"L. Hesse Nachf.",
    "wof:placetype":"venue"
},
  "geometry": {"coordinates":[6.2668018341,51.8338012695],"type":"Point"}
}