{
  "type": "Feature",
  "properties": {
    "iso:country":"DE",
    "sg:address":"Burgstr. 38",
    "sg:city":"Kinheim",
    "sg:phone":"+49 6532/4643",
    "sg:postcode":"54538",
    "sg:province":"Rheinland-Pfalz",
    "wof:name":"Henn-schwab Weinanbau",
    "wof:placetype":"venue"
},
  "geometry": {"coordinates":[7.0535497665,49.9739837646],"type":"Point"}
}