{
  "type": "Feature",
  "properties": {
    "iso:country":"DE",
    "sg:address":"Eugenbacher Str. 45",
    "sg:city":"Altdorf",
    "sg:phone":"+49 871/35346",
    "sg:postcode":"84032",
    "sg:province":"Bayern",
    "wof:name":"Cafe Waldeck",
    "wof:placetype":"venue"
},
  "geometry": {"coordinates":[12.0963029861,48.5509223938],"type":"Point"}
}