{
  "type": "Feature",
  "properties": {
    "iso:country":"DE",
    "sg:address":"L\u00e4rchenweg 6",
    "sg:city":"Schnaitsee",
    "sg:phone":"+49 8074/176818",
    "sg:postcode":"83530",
    "sg:province":"Bayern",
    "wof:name":"H\u00e4uslicher Pflegedienst Lebensonne Sybille Gertitschke",
    "wof:placetype":"venue"
},
  "geometry": {"coordinates":[12.407828,48.108284],"type":"Point"}
}