{
  "type": "Feature",
  "properties": {
    "iso:country":"DE",
    "sg:address":"Carl-Friedrich-Benz-Str. 2",
    "sg:city":"Kaiserslautern",
    "sg:postcode":"67657",
    "sg:province":"Rheinland-Pfalz",
    "wof:name":"Ecs-solution Gmbh",
    "wof:placetype":"venue"
},
  "geometry": {"coordinates":[7.7617721558,49.4509735107],"type":"Point"}
}