{
  "type": "Feature",
  "properties": {
    "iso:country":"DE",
    "sg:address":"Kirchstr. 14",
    "sg:city":"Seesbach",
    "sg:phone":"+49 6754/8179",
    "sg:postcode":"55629",
    "sg:province":"Rheinland-Pfalz",
    "wof:name":"Ev. Pfarramt Seesbach",
    "wof:placetype":"venue"
},
  "geometry": {"coordinates":[7.5491800308,49.8456993103],"type":"Point"}
}