{
  "type": "Feature",
  "properties": {
    "iso:country":"DE",
    "sg:address":"Wilhelmstr. 24",
    "sg:city":"Altenkirchen",
    "sg:phone":"+49 2681/1498",
    "sg:postcode":"57610",
    "sg:province":"Rheinland-Pfalz",
    "wof:name":"Renate Bansemeier",
    "wof:placetype":"venue"
},
  "geometry": {"coordinates":[7.644824028,50.6868896484],"type":"Point"}
}