{
  "type": "Feature",
  "properties": {
    "iso:country":"DE",
    "sg:address":"H\u00e4rtsfeldstr. 25",
    "sg:city":"Lauchheim",
    "sg:phone":"+49 7363/919491",
    "sg:postcode":"73466",
    "sg:province":"Baden-W\u00fcrttemberg",
    "wof:name":"Bfw Immobilien Und Wohnbau Gmbh",
    "wof:placetype":"venue"
},
  "geometry": {"coordinates":[10.224602,48.861324],"type":"Point"}
}