{
  "type": "Feature",
  "properties": {
    "iso:country":"DE",
    "sg:address":"Stra\u00dfe des Friedens 15",
    "sg:city":"Limbach-Oberfrohna",
    "sg:phone":"+49 3722/92657",
    "sg:postcode":"09212",
    "sg:province":"Sachsen",
    "wof:name":"Gert Zimmermann",
    "wof:placetype":"venue"
},
  "geometry": {"coordinates":[12.7571868896,50.8594818115],"type":"Point"}
}