{
  "type": "Feature",
  "properties": {
    "iso:country":"DE",
    "sg:address":"Am Ostkai 11",
    "sg:city":"Stuttgart",
    "sg:phone":"+49 711/9323930",
    "sg:postcode":"70327",
    "sg:province":"Baden-W\u00fcrttemberg",
    "wof:name":"E-pc Ag",
    "wof:placetype":"venue"
},
  "geometry": {"coordinates":[9.2583618164,48.7703514099],"type":"Point"}
}