{
  "type": "Feature",
  "properties": {
    "iso:country":"DE",
    "sg:address":"Annaberg 21",
    "sg:city":"Haltern",
    "sg:phone":"+49 2364/108496",
    "sg:postcode":"45721",
    "sg:province":"Nordrhein-Westfalen",
    "wof:name":"Annaberger Hof",
    "wof:placetype":"venue"
},
  "geometry": {"coordinates":[7.1548228264,51.7260627747],"type":"Point"}
}