{
  "type": "Feature",
  "properties": {
    "iso:country":"DE",
    "sg:address":"Ruppertskirchner Str. 5",
    "sg:city":"Altom\u00fcnster",
    "sg:phone":"+49 8254/8623",
    "sg:postcode":"85250",
    "sg:province":"Bayern",
    "wof:name":"Isolierglasfabrik Gmbh",
    "wof:placetype":"venue"
},
  "geometry": {"coordinates":[11.2558355331,48.3822288513],"type":"Point"}
}