{
  "type": "Feature",
  "properties": {
    "iso:country":"DE",
    "sg:address":"Ohmder Str. 12",
    "sg:city":"Zell",
    "sg:phone":"+49 7164/94160",
    "sg:postcode":"73119",
    "sg:province":"Baden-W\u00fcrttemberg",
    "wof:name":"Alm\u00fc Pr\u00e4zisionswerkzeug Gmbh",
    "wof:placetype":"venue"
},
  "geometry": {"coordinates":[9.574941,48.650585],"type":"Point"}
}