{
  "type": "Feature",
  "properties": {
    "iso:country":"DE",
    "sg:address":"Dreieichstr. 11",
    "sg:city":"Obertshausen",
    "sg:phone":"+49 6104/75051",
    "sg:postcode":"63179",
    "sg:province":"Hessen",
    "wof:name":"Virgils & Co. Lederwaren Gmbh",
    "wof:placetype":"venue"
},
  "geometry": {"coordinates":[8.861933,50.079575],"type":"Point"}
}