{
  "type": "Feature",
  "properties": {
    "iso:country":"DE",
    "sg:address":"Kochstr. 18",
    "sg:city":"Berlin",
    "sg:phone":"+49 30/259020",
    "sg:postcode":"10969",
    "sg:province":"Berlin",
    "wof:name":"Redaktion Taz",
    "wof:placetype":"venue"
},
  "geometry": {"coordinates":[13.3893470764,52.506778717],"type":"Point"}
}