{
  "type": "Feature",
  "properties": {
    "iso:country":"DE",
    "sg:address":"In der Hude 17",
    "sg:city":"Biebertal",
    "sg:phone":"+49 6409/2863",
    "sg:postcode":"35444",
    "sg:province":"Hessen",
    "wof:name":"K.-h. Wagner",
    "wof:placetype":"venue"
},
  "geometry": {"coordinates":[8.603435,50.666843],"type":"Point"}
}