{
  "type": "Feature",
  "properties": {
    "iso:country":"DE",
    "sg:address":"Pastor-Mensinga-Str. 11",
    "sg:city":"Friedrichstadt",
    "sg:phone":"+49 4881/7284",
    "sg:postcode":"25840",
    "sg:province":"Schleswig-Holstein",
    "wof:name":"G. Jensen",
    "wof:placetype":"venue"
},
  "geometry": {"coordinates":[9.0971765518,54.3753166199],"type":"Point"}
}