{
  "type": "Feature",
  "properties": {
    "iso:country":"DE",
    "sg:address":"Gutleutstr. 13",
    "sg:city":"Frankfurt",
    "sg:phone":"+49 69/231203",
    "sg:postcode":"60329",
    "sg:province":"Hessen",
    "wof:name":"Wiemann Gmbh",
    "wof:placetype":"venue"
},
  "geometry": {"coordinates":[8.671609,50.10738],"type":"Point"}
}