{
  "type": "Feature",
  "properties": {
    "iso:country":"DE",
    "sg:address":"Am Winkelsteig 1",
    "sg:city":"Lauf",
    "sg:phone":"+49 9123/984021",
    "sg:postcode":"91207",
    "sg:province":"Bayern",
    "wof:name":"Brinda Import-export Gmbh",
    "wof:placetype":"venue"
},
  "geometry": {"coordinates":[11.2638244629,49.4979133606],"type":"Point"}
}