{
  "type": "Feature",
  "properties": {
    "iso:country":"DE",
    "sg:address":"Blicken",
    "sg:city":"Ruhpolding",
    "sg:phone":"+49 8663/9195",
    "sg:postcode":"83324",
    "sg:province":"Bayern",
    "wof:name":"Fernsebner",
    "wof:placetype":"venue"
},
  "geometry": {"coordinates":[12.63264,47.757469],"type":"Point"}
}