{
  "type": "Feature",
  "properties": {
    "iso:country":"DE",
    "sg:address":"Bahnhofstr. 16",
    "sg:city":"Bruckm\u00fchl",
    "sg:phone":"+49 8062/9795",
    "sg:postcode":"83052",
    "sg:province":"Bayern",
    "wof:name":"Hamit G\u00fcndoglu",
    "wof:placetype":"venue"
},
  "geometry": {"coordinates":[11.9141597748,47.8815002441],"type":"Point"}
}