{
  "type": "Feature",
  "properties": {
    "iso:country":"DE",
    "sg:address":"Windm\u00fcllerstr 30",
    "sg:city":"Lippstadt",
    "sg:phone":"+49 2941/28010",
    "sg:postcode":"59557",
    "sg:province":"Nordrhein-Westfalen",
    "wof:name":"Quad Gmbh",
    "wof:placetype":"venue"
},
  "geometry": {"coordinates":[8.358004,51.656265],"type":"Point"}
}