{
  "type": "Feature",
  "properties": {
    "iso:country":"DE",
    "sg:address":"Schubertstr. 3",
    "sg:city":"Linden",
    "sg:phone":"+49 6403/96196",
    "sg:postcode":"35440",
    "sg:province":"Hessen",
    "wof:name":"Atec Gmbh",
    "wof:placetype":"venue"
},
  "geometry": {"coordinates":[8.6843862534,50.5284461975],"type":"Point"}
}