{
  "type": "Feature",
  "properties": {
    "iso:country":"DE",
    "sg:address":"Am Weiher 4",
    "sg:city":"Kelsterbach",
    "sg:phone":"+49 6107/90410",
    "sg:postcode":"65451",
    "sg:province":"Hessen",
    "wof:name":"Carmax Autovermietung",
    "wof:placetype":"venue"
},
  "geometry": {"coordinates":[8.525167,50.053673],"type":"Point"}
}