{
  "type": "Feature",
  "properties": {
    "iso:country":"DE",
    "sg:city":"Stei\u00dflingen",
    "sg:phone":"+49 7738/262",
    "sg:postcode":"78256",
    "sg:province":"Baden-W\u00fcrttemberg",
    "wof:name":"Kath. \u00d6ffentliche Bibliothek Kath. Pfarramt St. Remigius",
    "wof:placetype":"venue"
},
  "geometry": {"coordinates":[8.922095,47.802967],"type":"Point"}
}