{
  "type": "Feature",
  "properties": {
    "iso:country":"DE",
    "sg:address":"Josef-Hebel-Str. 21",
    "sg:city":"Emmering",
    "sg:phone":"+49 8141/6549",
    "sg:postcode":"82275",
    "sg:province":"Bayern",
    "wof:name":"O. Altbauer",
    "wof:placetype":"venue"
},
  "geometry": {"coordinates":[11.2991800308,48.1806182861],"type":"Point"}
}