{
  "type": "Feature",
  "properties": {
    "iso:country":"DE",
    "sg:address":"Georgstr. 17",
    "sg:city":"Wannweil",
    "sg:postcode":"72827",
    "sg:province":"Baden-W\u00fcrttemberg",
    "wof:name":"Ms-datendienst Und Service Gmbh",
    "wof:placetype":"venue"
},
  "geometry": {"coordinates":[9.1613941193,48.5126228333],"type":"Point"}
}