{
  "type": "Feature",
  "properties": {
    "iso:country":"DE",
    "sg:address":"Stolkerfelder Str. 19",
    "sg:city":"Stolk",
    "sg:phone":"+49 4623/1566",
    "sg:postcode":"24890",
    "sg:province":"Schleswig-Holstein",
    "wof:name":"Frenz Peters",
    "wof:placetype":"venue"
},
  "geometry": {"coordinates":[9.521718,54.600147],"type":"Point"}
}