{
  "type": "Feature",
  "properties": {
    "iso:country":"DE",
    "sg:address":"Westfalenstr. 88",
    "sg:city":"D\u00fcsseldorf",
    "sg:phone":"+49 211/656568",
    "sg:postcode":"40472",
    "sg:province":"Nordrhein-Westfalen",
    "wof:name":"Peter Rost",
    "wof:placetype":"venue"
},
  "geometry": {"coordinates":[6.819355011,51.2635879517],"type":"Point"}
}