{
  "type": "Feature",
  "properties": {
    "iso:country":"DE",
    "sg:address":"Hofweg 12",
    "sg:city":"Hamburg",
    "sg:phone":"+49 40/4396777",
    "sg:postcode":"22085",
    "sg:province":"Hamburg",
    "wof:name":"Hka H\u00e4usliche Kranken- Und Altenbetreuung",
    "wof:placetype":"venue"
},
  "geometry": {"coordinates":[10.017809,53.569576],"type":"Point"}
}