{
  "type": "Feature",
  "properties": {
    "iso:country":"DE",
    "sg:address":"Karl-Theodor-Str. 84",
    "sg:city":"M\u00fcnchen",
    "sg:phone":"+49 89/3081567",
    "sg:postcode":"80803",
    "sg:province":"Bayern",
    "wof:name":"Fsi Innovations Gmbh",
    "wof:placetype":"venue"
},
  "geometry": {"coordinates":[11.574344,48.167271],"type":"Point"}
}