{
  "type": "Feature",
  "properties": {
    "iso:country":"DE",
    "sg:address":"Hirschstr 85-93",
    "sg:city":"Lorsch",
    "sg:phone":"+49 6251/53344",
    "sg:postcode":"64653",
    "sg:province":"Hessen",
    "wof:name":"Plast-pt Gmbh",
    "wof:placetype":"venue"
},
  "geometry": {"coordinates":[8.567453,49.644207],"type":"Point"}
}