{
  "type": "Feature",
  "properties": {
    "iso:country":"DE",
    "sg:address":"Geschwister - Scholl Str.",
    "sg:city":"Krauschwitz",
    "sg:postcode":"02957",
    "sg:province":"Sachsen",
    "wof:name":"Techkeram-keramische Erzeugnisse Gmbh Krauschwitz",
    "wof:placetype":"venue"
},
  "geometry": {"coordinates":[14.713676,51.520542],"type":"Point"}
}