{
  "type": "Feature",
  "properties": {
    "iso:country":"DE",
    "sg:address":"Ringstr. 5",
    "sg:city":"Velbert",
    "sg:phone":"+49 2053/504190",
    "sg:postcode":"42553",
    "sg:province":"Nordrhein-Westfalen",
    "wof:name":"Gt Geb\u00e4udereinigung K\u00e4the Knoll Gmbh",
    "wof:placetype":"venue"
},
  "geometry": {"coordinates":[7.113634,51.307053],"type":"Point"}
}