{
  "type": "Feature",
  "properties": {
    "iso:country":"DE",
    "sg:address":"Georg-Todt-Str. 1",
    "sg:city":"Kandel",
    "sg:phone":"+49 7275/1290",
    "sg:postcode":"76870",
    "sg:province":"Rheinland-Pfalz",
    "wof:name":"Deutsche Bahn Ag",
    "wof:placetype":"venue"
},
  "geometry": {"coordinates":[8.1965103149,49.0793190002],"type":"Point"}
}