{
  "type": "Feature",
  "properties": {
    "iso:country":"DE",
    "sg:address":"Blaustein",
    "sg:city":"Blaustein",
    "sg:phone":"+49 4973/043463",
    "sg:postcode":"89134",
    "sg:province":"Baden-W\u00fcrttemberg",
    "wof:name":"Raiffeisenbank Wippingen",
    "wof:placetype":"venue"
},
  "geometry": {"coordinates":[9.87024,48.433208],"type":"Point"}
}