{
  "type": "Feature",
  "properties": {
    "iso:country":"DE",
    "sg:address":"Am Friedhof 1",
    "sg:city":"Arnstadt",
    "sg:phone":"+49 3628/602144",
    "sg:postcode":"99310",
    "sg:province":"Th\u00fcringen",
    "wof:name":"B\u00d6ttner & Reif Gmbh",
    "wof:placetype":"venue"
},
  "geometry": {"coordinates":[10.960073,50.838123],"type":"Point"}
}