{
  "type": "Feature",
  "properties": {
    "iso:country":"DE",
    "sg:address":"Gr\u00fcnwalder Str. 197a",
    "sg:city":"M\u00fcnchen",
    "sg:phone":"+49 89/648334",
    "sg:postcode":"81545",
    "sg:province":"Bayern",
    "wof:name":"W\u00fcrmisar Finanz- Und Immobilientreuhand Gmbh",
    "wof:placetype":"venue"
},
  "geometry": {"coordinates":[11.5632772446,48.0933952332],"type":"Point"}
}