{
  "type": "Feature",
  "properties": {
    "iso:country":"DE",
    "sg:address":"Oststr. 10",
    "sg:city":"Sonthofen",
    "sg:phone":"+49 8321/723532",
    "sg:postcode":"87527",
    "sg:province":"Bayern",
    "wof:name":"Australian Import Traders Gmbh",
    "wof:placetype":"venue"
},
  "geometry": {"coordinates":[10.29047966,47.5140380859],"type":"Point"}
}