{
  "type": "Feature",
  "properties": {
    "iso:country":"DE",
    "sg:address":"Grundweg 8",
    "sg:city":"Allendorf",
    "sg:postcode":"35108",
    "sg:province":"Hessen",
    "wof:name":"Eintrag-profis",
    "wof:placetype":"venue"
},
  "geometry": {"coordinates":[8.719649,51.042046],"type":"Point"}
}