{
  "type": "Feature",
  "properties": {
    "iso:country":"DE",
    "sg:address":"Altengronauer Str. 22",
    "sg:city":"Zeitlofs",
    "sg:phone":"+49 9746/274",
    "sg:postcode":"97799",
    "sg:province":"Bayern",
    "wof:name":"Freiherr Hans-wolf V. L\u00fcttwitz",
    "wof:placetype":"venue"
},
  "geometry": {"coordinates":[9.6714763641,50.262966156],"type":"Point"}
}