{
  "type": "Feature",
  "properties": {
    "iso:country":"DE",
    "sg:address":"Bauernstr. 19",
    "sg:city":"Lippetal",
    "sg:phone":"+49 2527/919325",
    "sg:postcode":"59510",
    "sg:province":"Nordrhein-Westfalen",
    "wof:name":"Tischlerwerkst. Vernhold Gmbh",
    "wof:placetype":"venue"
},
  "geometry": {"coordinates":[8.035659,51.653278],"type":"Point"}
}