{
  "type": "Feature",
  "properties": {
    "iso:country":"DE",
    "sg:address":"Eichendorffstr. 15",
    "sg:city":"Ingelfingen",
    "sg:phone":"+49 7940/59397",
    "sg:postcode":"74653",
    "sg:province":"Baden-W\u00fcrttemberg",
    "wof:name":"Klaus Denninger",
    "wof:placetype":"venue"
},
  "geometry": {"coordinates":[9.661536,49.297218],"type":"Point"}
}