{
  "type": "Feature",
  "properties": {
    "iso:country":"DE",
    "sg:address":"Hillebachstr. 5",
    "sg:city":"Eimen",
    "sg:phone":"+49 5565/245",
    "sg:postcode":"37632",
    "sg:province":"Niedersachsen",
    "wof:name":"Wilhelm Ude",
    "wof:placetype":"venue"
},
  "geometry": {"coordinates":[9.7807607651,51.8776245117],"type":"Point"}
}