{
  "type": "Feature",
  "properties": {
    "iso:country":"DE",
    "sg:address":"C-Theo-Reiffenstein-Pl 11",
    "sg:city":"Frankfurt",
    "sg:phone":"+49 69/298940",
    "sg:postcode":"60313",
    "sg:province":"Hessen",
    "wof:name":"Advanced Mp Technology (deutschland) Gmbh",
    "wof:placetype":"venue"
},
  "geometry": {"coordinates":[8.6823301315,50.1148490906],"type":"Point"}
}