{
  "type": "Feature",
  "properties": {
    "iso:country":"DE",
    "sg:address":"Karl-Tauchnitz-Str. 3",
    "sg:city":"Leipzig",
    "sg:postcode":"04107",
    "sg:province":"Sachsen",
    "wof:name":"Kiebitz Familienzentrum Leipzig E. V.",
    "wof:placetype":"venue"
},
  "geometry": {"coordinates":[12.3690080643,51.3346862793],"type":"Point"}
}