{
  "type": "Feature",
  "properties": {
    "iso:country":"DE",
    "sg:address":"Wexstr. 2",
    "sg:city":"Berlin",
    "sg:phone":"+49 30/7825003",
    "sg:postcode":"10825",
    "sg:province":"Berlin",
    "wof:name":"Heinz Paetsch",
    "wof:placetype":"venue"
},
  "geometry": {"coordinates":[13.34257,52.479],"type":"Point"}
}