{
  "type": "Feature",
  "properties": {
    "iso:country":"DE",
    "sg:address":"Am Auernberg 12",
    "sg:city":"Kronberg",
    "sg:postcode":"61476",
    "sg:province":"Hessen",
    "wof:name":"Hermann Und Edgar Oberhansl",
    "wof:placetype":"venue"
},
  "geometry": {"coordinates":[8.5316982269,50.172454834],"type":"Point"}
}