{
  "type": "Feature",
  "properties": {
    "iso:country":"DE",
    "sg:address":"Birkenweg 26",
    "sg:city":"Dillenburg",
    "sg:postcode":"35687",
    "sg:province":"Hessen",
    "wof:name":"Horst Lindtner Gmbh",
    "wof:placetype":"venue"
},
  "geometry": {"coordinates":[8.307195,50.724831],"type":"Point"}
}