{
  "type": "Feature",
  "properties": {
    "iso:country":"DE",
    "sg:address":"Backhausstr. 6",
    "sg:city":"Lampertheim",
    "sg:phone":"+49 6241/80269",
    "sg:postcode":"68623",
    "sg:province":"Hessen",
    "wof:name":"Willi Kaiser",
    "wof:placetype":"venue"
},
  "geometry": {"coordinates":[8.410145,49.65844],"type":"Point"}
}