{
  "type": "Feature",
  "properties": {
    "iso:country":"DE",
    "sg:address":"Hochstr. 27",
    "sg:city":"Frankfurt",
    "sg:phone":"+49 69/292867",
    "sg:postcode":"60313",
    "sg:province":"Hessen",
    "wof:name":"Le Bistro Avocado",
    "wof:placetype":"venue"
},
  "geometry": {"coordinates":[8.6763839722,50.1162033081],"type":"Point"}
}