{
  "type": "Feature",
  "properties": {
    "iso:country":"DE",
    "sg:address":"Reininghauser Str. 3 - 5",
    "sg:city":"Gummersbach",
    "sg:phone":"+49 2261/5416",
    "sg:postcode":"51643",
    "sg:province":"Nordrhein-Westfalen",
    "wof:name":"Evangelische Altenhilfe Gmbh",
    "wof:placetype":"venue"
},
  "geometry": {"coordinates":[7.565845,51.030632],"type":"Point"}
}