{
  "type": "Feature",
  "properties": {
    "iso:country":"DE",
    "sg:address":"Angerm\u00fcnder Str.",
    "sg:city":"Alth\u00fcttendorf",
    "sg:postcode":"16247",
    "sg:province":"Brandenburg",
    "wof:name":"Agrochemisches Zentrum",
    "wof:placetype":"venue"
},
  "geometry": {"coordinates":[13.7888650894,52.9592208862],"type":"Point"}
}