{
  "type": "Feature",
  "properties": {
    "iso:country":"DE",
    "sg:address":"S\u00fcdwestkorso 20",
    "sg:city":"Berlin",
    "sg:phone":"+49 30/21401141",
    "sg:postcode":"14197",
    "sg:province":"Berlin",
    "wof:name":"Teleconsult Ingenieurges. F\u00fcr Kommunikationstechnik Mbh",
    "wof:placetype":"venue"
},
  "geometry": {"coordinates":[13.319044,52.4716],"type":"Point"}
}