{
  "type": "Feature",
  "properties": {
    "iso:country":"DE",
    "sg:address":"F\u00e4cherstr. 10",
    "sg:city":"Kamen",
    "sg:postcode":"59174",
    "sg:province":"Nordrhein-Westfalen",
    "wof:name":"Mvs Marketing Vertriebs Service Gmbh",
    "wof:placetype":"venue"
},
  "geometry": {"coordinates":[7.665139,51.597103],"type":"Point"}
}