{
  "type": "Feature",
  "properties": {
    "iso:country":"DE",
    "sg:address":"Gablonzer Rg 21",
    "sg:city":"Kaufbeuren",
    "sg:phone":"+49 8341/966820",
    "sg:postcode":"87600",
    "sg:province":"Bayern",
    "wof:name":"Leukert Gmbh Metallwarenfabrik",
    "wof:placetype":"venue"
},
  "geometry": {"coordinates":[10.639265,47.913174],"type":"Point"}
}