{
  "type": "Feature",
  "properties": {
    "iso:country":"DE",
    "sg:address":"Wallstr. 4",
    "sg:city":"Waldshut-Tiengen",
    "sg:phone":"+49 7751/2279",
    "sg:postcode":"79761",
    "sg:province":"Baden-W\u00fcrttemberg",
    "wof:name":"Markus Fleck",
    "wof:placetype":"venue"
},
  "geometry": {"coordinates":[8.2143535614,47.6231079102],"type":"Point"}
}