{
  "type": "Feature",
  "properties": {
    "iso:country":"DE",
    "sg:address":"Bahnhofstr. 54",
    "sg:city":"Hammelburg",
    "sg:phone":"+49 9732/2285",
    "sg:postcode":"97762",
    "sg:province":"Bayern",
    "wof:name":"Tribo Chemie Gmbh",
    "wof:placetype":"venue"
},
  "geometry": {"coordinates":[9.8861303329,50.1183815002],"type":"Point"}
}