{
  "type": "Feature",
  "properties": {
    "iso:country":"DE",
    "sg:address":"Postfach 4440",
    "sg:city":"Schweinfurt",
    "sg:postcode":"97412",
    "sg:province":"Bayern",
    "wof:name":"Stadthalle",
    "wof:placetype":"venue"
},
  "geometry": {"coordinates":[10.23114,50.04911],"type":"Point"}
}