{
  "type": "Feature",
  "properties": {
    "iso:country":"DE",
    "sg:city":"Beuren",
    "sg:phone":"+49 4975/722752",
    "sg:postcode":"88512",
    "sg:province":"Baden-W\u00fcrttemberg",
    "wof:name":"Volksbank Saulgau Eg",
    "wof:placetype":"venue"
},
  "geometry": {"coordinates":[9.375681,48.080463],"type":"Point"}
}