{
  "type": "Feature",
  "properties": {
    "iso:country":"DE",
    "sg:address":"Ebersbergstr. 27",
    "sg:city":"Bad Zwesten",
    "sg:phone":"+49 5621/3896",
    "sg:postcode":"34596",
    "sg:province":"Hessen",
    "wof:name":"Haus Ebersberg Altenheim",
    "wof:placetype":"venue"
},
  "geometry": {"coordinates":[9.178367,51.083858],"type":"Point"}
}