{
  "type": "Feature",
  "properties": {
    "iso:country":"DE",
    "sg:address":"Am Steinbruch 20",
    "sg:city":"Kelkheim",
    "sg:phone":"+49 6174/61264",
    "sg:postcode":"65779",
    "sg:province":"Hessen",
    "wof:name":"R. John",
    "wof:placetype":"venue"
},
  "geometry": {"coordinates":[8.3985109329,50.1725273132],"type":"Point"}
}