{
  "type": "Feature",
  "properties": {
    "iso:country":"DE",
    "sg:address":"Quellenstr. 23",
    "sg:city":"Heidenrod",
    "sg:postcode":"65321",
    "sg:province":"Hessen",
    "wof:name":"A. Pickardt-krug",
    "wof:placetype":"venue"
},
  "geometry": {"coordinates":[8.0026836395,50.1720848083],"type":"Point"}
}