{
  "type": "Feature",
  "properties": {
    "iso:country":"DE",
    "sg:address":"Am Rahmer Bach 133 A",
    "sg:city":"Duisburg",
    "sg:phone":"+49 203/713343",
    "sg:postcode":"47269",
    "sg:province":"Nordrhein-Westfalen",
    "wof:name":"Flick & Limper Objektbau Gmbh",
    "wof:placetype":"venue"
},
  "geometry": {"coordinates":[6.787007,51.346199],"type":"Point"}
}