{
  "type": "Feature",
  "properties": {
    "iso:country":"DE",
    "sg:address":"Krachtstr. 31",
    "sg:city":"Gelsenkirchen",
    "sg:phone":"+49 209/819157",
    "sg:postcode":"45889",
    "sg:province":"Nordrhein-Westfalen",
    "wof:name":"Vip-mobil-hotline- Express E. K.",
    "wof:placetype":"venue"
},
  "geometry": {"coordinates":[7.1028738022,51.5424575806],"type":"Point"}
}