{
  "type": "Feature",
  "properties": {
    "iso:country":"DE",
    "sg:address":"Krurstr. 47",
    "sg:city":"Neuss",
    "sg:phone":"+49 2131/220100",
    "sg:postcode":"41460",
    "sg:province":"Nordrhein-Westfalen",
    "wof:name":"Hans Karl Breuer Rechtsanwalt",
    "wof:placetype":"venue"
},
  "geometry": {"coordinates":[6.6805782318,51.1958656311],"type":"Point"}
}