{
  "type": "Feature",
  "properties": {
    "iso:country":"DE",
    "sg:address":"Robert-Koch-Str. 1",
    "sg:city":"Erding",
    "sg:phone":"+49 8122/6011",
    "sg:postcode":"85435",
    "sg:province":"Bayern",
    "wof:name":"Groschberger Gmbh G Und S Druck",
    "wof:placetype":"venue"
},
  "geometry": {"coordinates":[11.895528,48.287685],"type":"Point"}
}