{
  "type": "Feature",
  "properties": {
    "iso:country":"DE",
    "sg:address":"Kreisstr. 16",
    "sg:city":"Halle",
    "sg:phone":"+49 5201/7081",
    "sg:postcode":"33790",
    "sg:province":"Nordrhein-Westfalen",
    "wof:name":"Sengewald Verpackungen Gmbh & Co. Kg",
    "wof:placetype":"venue"
},
  "geometry": {"coordinates":[8.3304300308,52.0443611145],"type":"Point"}
}