{
  "type": "Feature",
  "properties": {
    "iso:country":"DE",
    "sg:address":"Kleingem\u00fcnder Str. 72/2",
    "sg:city":"Heidelberg",
    "sg:postcode":"69118",
    "sg:province":"Baden-W\u00fcrttemberg",
    "wof:name":"Security Center Heidelberg Gmbh",
    "wof:placetype":"venue"
},
  "geometry": {"coordinates":[8.773366,49.414711],"type":"Point"}
}