{
  "type": "Feature",
  "properties": {
    "iso:country":"DE",
    "sg:address":"Spitalbachstr. 39",
    "sg:city":"Neustadt",
    "sg:phone":"+49 6321/16700",
    "sg:postcode":"67433",
    "sg:province":"Rheinland-Pfalz",
    "wof:name":"Rosemarie Brombacher",
    "wof:placetype":"venue"
},
  "geometry": {"coordinates":[8.157822,49.349022],"type":"Point"}
}