{
  "type": "Feature",
  "properties": {
    "iso:country":"DE",
    "sg:address":"Postfach 2638",
    "sg:city":"G\u00fctersloh",
    "sg:postcode":"33256",
    "sg:province":"Nordrhein-Westfalen",
    "wof:name":"Quermann Gmbh",
    "wof:placetype":"venue"
},
  "geometry": {"coordinates":[8.3927898407,51.9048995972],"type":"Point"}
}