{
  "type": "Feature",
  "properties": {
    "iso:country":"DE",
    "sg:address":"Wollenhausweg 1",
    "sg:city":"Mettmann",
    "sg:phone":"+49 2104/52870",
    "sg:postcode":"40822",
    "sg:province":"Nordrhein-Westfalen",
    "wof:name":"Hotel-restaurant Ratskeller",
    "wof:placetype":"venue"
},
  "geometry": {"coordinates":[6.9498848915,51.2640342712],"type":"Point"}
}