{
  "type": "Feature",
  "properties": {
    "iso:country":"DE",
    "sg:address":"Vossekuhle 4a",
    "sg:city":"Hamminkeln",
    "sg:phone":"+49 2857/2562",
    "sg:postcode":"46499",
    "sg:province":"Nordrhein-Westfalen",
    "wof:name":"Harald Rathmer Ingenieur",
    "wof:placetype":"venue"
},
  "geometry": {"coordinates":[6.5030431747,51.7382240295],"type":"Point"}
}