{
  "type": "Feature",
  "properties": {
    "iso:country":"DE",
    "sg:address":"Rohrkamp 28",
    "sg:city":"L\u00fcdinghausen",
    "sg:phone":"+49 2591/21709",
    "sg:postcode":"59348",
    "sg:province":"Nordrhein-Westfalen",
    "wof:name":"Bernhard Heitkamp",
    "wof:placetype":"venue"
},
  "geometry": {"coordinates":[7.4287838936,51.7706413269],"type":"Point"}
}