{
  "type": "Feature",
  "properties": {
    "iso:country":"DE",
    "sg:address":"Balduinstr. 77",
    "sg:city":"Zell",
    "sg:phone":"+49 6542/4580",
    "sg:postcode":"56856",
    "sg:province":"Rheinland-Pfalz",
    "wof:name":"Weinstube-cafe Reinisch Franz E. Reinisch",
    "wof:placetype":"venue"
},
  "geometry": {"coordinates":[7.181511879,50.0263710022],"type":"Point"}
}