{
  "type": "Feature",
  "properties": {
    "iso:country":"DE",
    "sg:address":"Elsheimer Str. 25",
    "sg:city":"Schwabenheim",
    "sg:phone":"+49 6130/592",
    "sg:postcode":"55270",
    "sg:province":"Rheinland-Pfalz",
    "wof:name":"Rudolf Renth",
    "wof:placetype":"venue"
},
  "geometry": {"coordinates":[8.1931533813,49.9384918213],"type":"Point"}
}