{
  "type": "Feature",
  "properties": {
    "iso:country":"DE",
    "sg:address":"Hindenburgstr. 3",
    "sg:city":"Lahstedt",
    "sg:phone":"+49 5174/920595",
    "sg:postcode":"31246",
    "sg:province":"Niedersachsen",
    "wof:name":"Fairworx Gmbh",
    "wof:placetype":"venue"
},
  "geometry": {"coordinates":[10.2429,52.224983],"type":"Point"}
}