{
  "type": "Feature",
  "properties": {
    "iso:country":"DE",
    "sg:address":"Heinrich-Hertz-Str. 10",
    "sg:city":"Verden",
    "sg:phone":"+49 4231/2491",
    "sg:postcode":"27283",
    "sg:province":"Niedersachsen",
    "wof:name":"M\u00fcller Gmbh",
    "wof:placetype":"venue"
},
  "geometry": {"coordinates":[9.246854,52.911377],"type":"Point"}
}