{
  "type": "Feature",
  "properties": {
    "iso:country":"DE",
    "sg:address":"Rosenheimer Landstr. 106",
    "sg:city":"Ottobrunn",
    "sg:phone":"+49 89/6099448",
    "sg:postcode":"85521",
    "sg:province":"Bayern",
    "wof:name":"Florales & Keramik Karin Paulsen",
    "wof:placetype":"venue"
},
  "geometry": {"coordinates":[11.666732,48.056854],"type":"Point"}
}