{
  "type": "Feature",
  "properties": {
    "iso:country":"DE",
    "sg:address":"Franz-Lenze-Platz 2",
    "sg:city":"Duisburg",
    "sg:phone":"+49 203/471642",
    "sg:postcode":"47178",
    "sg:province":"Nordrhein-Westfalen",
    "wof:name":"Zoo-rauch Gmbh",
    "wof:placetype":"venue"
},
  "geometry": {"coordinates":[6.7261,51.534981],"type":"Point"}
}