{
  "type": "Feature",
  "properties": {
    "iso:country":"DE",
    "sg:address":"Herrenstr. 3",
    "sg:city":"Freyburg",
    "sg:phone":"+49 34464/28670",
    "sg:postcode":"06632",
    "sg:province":"Sachsen-Anhalt",
    "wof:name":"Freyburger Wohnungsbaugesellschaft Mbh",
    "wof:placetype":"venue"
},
  "geometry": {"coordinates":[11.770453,51.213249],"type":"Point"}
}