{
  "type": "Feature",
  "properties": {
    "iso:country":"DE",
    "sg:address":"Im Oberdorf 33",
    "sg:city":"Villingen-Schwenningen",
    "sg:postcode":"78052",
    "sg:province":"Baden-W\u00fcrttemberg",
    "wof:name":"Reiko-trenkle Gmbh",
    "wof:placetype":"venue"
},
  "geometry": {"coordinates":[8.4113,48.037056],"type":"Point"}
}