{
  "type": "Feature",
  "properties": {
    "iso:country":"DE",
    "sg:address":"Schillerstr. 3",
    "sg:city":"Estenfeld",
    "sg:phone":"+49 9305/519",
    "sg:postcode":"97230",
    "sg:province":"Bayern",
    "wof:name":"Dimax Gmbh",
    "wof:placetype":"venue"
},
  "geometry": {"coordinates":[10.001615,49.826328],"type":"Point"}
}