{
  "type": "Feature",
  "properties": {
    "iso:country":"DE",
    "sg:address":"Talweg 4",
    "sg:city":"Limeshain",
    "sg:postcode":"63694",
    "sg:province":"Hessen",
    "wof:name":"Pilzhof Limeshain Verwaltungs-gmbh",
    "wof:placetype":"venue"
},
  "geometry": {"coordinates":[8.9776258469,50.260974884],"type":"Point"}
}