{
  "type": "Feature",
  "properties": {
    "iso:country":"DE",
    "sg:address":"Grunewaldstr. 59",
    "sg:city":"Berlin",
    "sg:phone":"+49 30/7824231",
    "sg:postcode":"10825",
    "sg:province":"Berlin",
    "wof:name":"M. Nadolski Schl\u00fcsseldienst",
    "wof:placetype":"venue"
},
  "geometry": {"coordinates":[13.3416662216,52.4885292053],"type":"Point"}
}