{
  "type": "Feature",
  "properties": {
    "iso:country":"DE",
    "sg:address":"Altenburg 9",
    "sg:city":"Laer",
    "sg:phone":"+49 2554/8160",
    "sg:postcode":"48366",
    "sg:province":"Nordrhein-Westfalen",
    "wof:name":"Heinrich Dillmann",
    "wof:placetype":"venue"
},
  "geometry": {"coordinates":[7.319743,52.059795],"type":"Point"}
}