{
  "type": "Feature",
  "properties": {
    "iso:country":"DE",
    "sg:address":"Kampstr. 1",
    "sg:city":"Meinerzhagen",
    "sg:phone":"+49 2354/2266",
    "sg:postcode":"58540",
    "sg:province":"Nordrhein-Westfalen",
    "wof:name":"Kath. Pfarramt St. Marien Unbefl. Empf.",
    "wof:placetype":"venue"
},
  "geometry": {"coordinates":[7.6396231651,51.1049995422],"type":"Point"}
}