{
  "type": "Feature",
  "properties": {
    "iso:country":"DE",
    "sg:address":"Guttauer Str. 20",
    "sg:city":"Malschwitz",
    "sg:phone":"+49 35932/30525",
    "sg:postcode":"02694",
    "sg:province":"Sachsen",
    "wof:name":"R. P\u00f6tschke",
    "wof:placetype":"venue"
},
  "geometry": {"coordinates":[14.561685,51.240208],"type":"Point"}
}