{
  "type": "Feature",
  "properties": {
    "iso:country":"DE",
    "sg:address":"Albanusstr. 22",
    "sg:city":"Frankfurt",
    "sg:phone":"+49 69/313380",
    "sg:postcode":"65929",
    "sg:province":"Hessen",
    "wof:name":"Albanus-apotheke",
    "wof:placetype":"venue"
},
  "geometry": {"coordinates":[8.54682,50.101105],"type":"Point"}
}