{
  "type": "Feature",
  "properties": {
    "iso:country":"DE",
    "sg:address":"Waldschmidtstr. 6",
    "sg:city":"Arnbruck",
    "sg:phone":"+49 9945/1630",
    "sg:postcode":"93471",
    "sg:province":"Bayern",
    "wof:name":"U. Amberger",
    "wof:placetype":"venue"
},
  "geometry": {"coordinates":[12.9940500259,49.1307563782],"type":"Point"}
}