{
  "type": "Feature",
  "properties": {
    "iso:country":"DE",
    "sg:address":"Dellbusch 151",
    "sg:city":"Wuppertal",
    "sg:phone":"+49 202/524205",
    "sg:postcode":"42279",
    "sg:province":"Nordrhein-Westfalen",
    "wof:name":"Klaus Von Dombrowski",
    "wof:placetype":"venue"
},
  "geometry": {"coordinates":[7.2105741501,51.3011398315],"type":"Point"}
}