{
  "type": "Feature",
  "properties": {
    "iso:country":"DE",
    "sg:address":"Martinstr. 19",
    "sg:city":"Solingen",
    "sg:phone":"+49 4921/2205395",
    "sg:postcode":"42655",
    "sg:province":"Nordrhein-Westfalen",
    "wof:name":"Vorrichtungs- U. Formenbau Gmbh & Co Kg",
    "wof:placetype":"venue"
},
  "geometry": {"coordinates":[7.0501899719,51.1712799072],"type":"Point"}
}