{
  "type": "Feature",
  "properties": {
    "iso:country":"DE",
    "sg:address":"Marienstr. 6",
    "sg:city":"Bad Saulgau",
    "sg:phone":"+49 7581/8312",
    "sg:postcode":"88348",
    "sg:province":"Baden-W\u00fcrttemberg",
    "wof:name":"E. Seelig",
    "wof:placetype":"venue"
},
  "geometry": {"coordinates":[9.5083351135,48.0113754272],"type":"Point"}
}