{
  "type": "Feature",
  "properties": {
    "iso:country":"DE",
    "sg:address":"Stra\u00dfe 251 2",
    "sg:city":"Berlin",
    "sg:phone":"+49 30/9250297",
    "sg:postcode":"13088",
    "sg:province":"Berlin",
    "wof:name":"Klaus Talatzko",
    "wof:placetype":"venue"
},
  "geometry": {"coordinates":[13.49082,52.559555],"type":"Point"}
}