{
  "type": "Feature",
  "properties": {
    "iso:country":"DE",
    "sg:address":"L\u00e4rchenweg 1",
    "sg:city":"Ravenstein",
    "sg:phone":"+49 6297/554",
    "sg:postcode":"74747",
    "sg:province":"Baden-W\u00fcrttemberg",
    "wof:name":"L. Zweig",
    "wof:placetype":"venue"
},
  "geometry": {"coordinates":[9.5041666031,49.3995132446],"type":"Point"}
}