{
  "type": "Feature",
  "properties": {
    "iso:country":"DE",
    "sg:address":"Wackenroder Weg 17",
    "sg:city":"Burgdorf",
    "sg:postcode":"31303",
    "sg:province":"Niedersachsen",
    "wof:name":"Netzwerk Service 2000 Gmbh",
    "wof:placetype":"venue"
},
  "geometry": {"coordinates":[10.008568,52.450478],"type":"Point"}
}