{
  "type": "Feature",
  "properties": {
    "iso:country":"DE",
    "sg:address":"Gewerbering 2",
    "sg:city":"Gr\u00f6ditz",
    "sg:phone":"+49 35263/61179",
    "sg:postcode":"01609",
    "sg:province":"Sachsen",
    "wof:name":"H. Agater",
    "wof:placetype":"venue"
},
  "geometry": {"coordinates":[13.435038,51.403404],"type":"Point"}
}