{
  "type": "Feature",
  "properties": {
    "iso:country":"DE",
    "sg:address":"Zienestra\u00dfe 11a",
    "sg:city":"Wolfach",
    "sg:phone":"+49 7834",
    "sg:postcode":"77709",
    "sg:province":"Baden-W\u00fcrttemberg",
    "wof:name":"N\u00fctzliche Programme Zum Download Und Div. Links",
    "wof:placetype":"venue"
},
  "geometry": {"coordinates":[8.2151403427,48.2910881042],"type":"Point"}
}