{
  "type": "Feature",
  "properties": {
    "iso:country":"DE",
    "sg:address":"Cordobastr. 1",
    "sg:city":"D\u00fcsseldorf",
    "sg:phone":"+49 211/5134080",
    "sg:postcode":"40477",
    "sg:province":"Nordrhein-Westfalen",
    "wof:name":"M. Kascha Steuerberater",
    "wof:placetype":"venue"
},
  "geometry": {"coordinates":[6.7758579254,51.2386245728],"type":"Point"}
}