{
  "type": "Feature",
  "properties": {
    "iso:country":"DE",
    "sg:address":"Zum Heister 10",
    "sg:city":"Visselh\u00f6vede",
    "sg:postcode":"27374",
    "sg:province":"Niedersachsen",
    "wof:name":"Gebr. Bornemann",
    "wof:placetype":"venue"
},
  "geometry": {"coordinates":[9.567792,52.982285],"type":"Point"}
}