{
  "type": "Feature",
  "properties": {
    "iso:country":"DE",
    "sg:address":"Postfach 310:: 91544 Dinkelsb\u00fchl:: Germany.^^Weinmarkt 14::",
    "sg:city":"Dinkelsb\u00fchl",
    "sg:phone":"+49 9851/5800",
    "sg:postcode":"91550",
    "sg:province":"Bayern",
    "wof:name":"Volksbank Dinkelsb\u00fchl Eg",
    "wof:placetype":"venue"
},
  "geometry": {"coordinates":[10.319678,49.069038],"type":"Point"}
}