{
  "type": "Feature",
  "properties": {
    "iso:country":"DE",
    "sg:address":"Rottenbucher Str. 9",
    "sg:city":"Osterzell",
    "sg:phone":"+49 8345/1378",
    "sg:postcode":"87662",
    "sg:province":"Bayern",
    "wof:name":"Gastst\u00e4tte Rasso Prestele",
    "wof:placetype":"venue"
},
  "geometry": {"coordinates":[10.7438001633,47.877948761],"type":"Point"}
}