{
  "type": "Feature",
  "properties": {
    "iso:country":"DE",
    "sg:address":"Gartenstr. 7",
    "sg:city":"Heidenau",
    "sg:postcode":"01809",
    "sg:province":"Sachsen",
    "wof:name":"H. Bresch & Sohn Gmbh",
    "wof:placetype":"venue"
},
  "geometry": {"coordinates":[13.8416748047,50.9811058044],"type":"Point"}
}