{
  "type": "Feature",
  "properties": {
    "iso:country":"DE",
    "sg:address":"Rheintorstr. 46",
    "sg:city":"Breisach",
    "sg:postcode":"79206",
    "sg:province":"Baden-W\u00fcrttemberg",
    "wof:name":"Nomad Verlag E. K.",
    "wof:placetype":"venue"
},
  "geometry": {"coordinates":[7.5755000114,48.0337181091],"type":"Point"}
}