{
  "type": "Feature",
  "properties": {
    "iso:country":"DE",
    "sg:address":"S\u00fcdstr. 7",
    "sg:city":"Hilden",
    "sg:phone":"+49 2103/242350",
    "sg:postcode":"40721",
    "sg:province":"Nordrhein-Westfalen",
    "wof:name":"Joseph & Joseph Gmbh",
    "wof:placetype":"venue"
},
  "geometry": {"coordinates":[6.937194,51.165997],"type":"Point"}
}