{
  "type": "Feature",
  "properties": {
    "iso:country":"DE",
    "sg:address":"Bahnhofstr. 13",
    "sg:city":"Gunzenhausen",
    "sg:phone":"+49 9831/4706",
    "sg:postcode":"91710",
    "sg:province":"Bayern",
    "wof:name":"China Restaurant Peking",
    "wof:placetype":"venue"
},
  "geometry": {"coordinates":[10.7547283173,49.1172943115],"type":"Point"}
}