{
  "type": "Feature",
  "properties": {
    "iso:country":"DE",
    "sg:address":"Schwalbenstr. 18 b",
    "sg:city":"Cloppenburg",
    "sg:postcode":"49661",
    "sg:province":"Niedersachsen",
    "wof:name":"Tt Textilhandelsges. Mbh",
    "wof:placetype":"venue"
},
  "geometry": {"coordinates":[8.0419597626,52.8306121826],"type":"Point"}
}