{
  "type": "Feature",
  "properties": {
    "iso:country":"DE",
    "sg:address":"Akazienweg 1",
    "sg:city":"Burgdorf",
    "sg:phone":"+49 5085/7776",
    "sg:postcode":"31303",
    "sg:province":"Niedersachsen",
    "wof:name":"Heinr. W\u00f6hler",
    "wof:placetype":"venue"
},
  "geometry": {"coordinates":[9.991298,52.511292],"type":"Point"}
}