{
  "type": "Feature",
  "properties": {
    "iso:country":"DE",
    "sg:address":"Neuer Markt 42",
    "sg:city":"Meckenheim",
    "sg:phone":"+49 2225/14901",
    "sg:postcode":"53340",
    "sg:province":"Nordrhein-Westfalen",
    "wof:name":"B. Friese Gmbh",
    "wof:placetype":"venue"
},
  "geometry": {"coordinates":[7.0406370163,50.6264457703],"type":"Point"}
}