{
  "type": "Feature",
  "properties": {
    "iso:country":"DE",
    "sg:address":"Schlo\u00dfstr. 17",
    "sg:city":"Gundelsheim",
    "sg:phone":"+49 6269/330",
    "sg:postcode":"74831",
    "sg:province":"Baden-W\u00fcrttemberg",
    "wof:name":"St. Elisabeth-apotheke Apothekerin Carola Conrad E.k.",
    "wof:placetype":"venue"
},
  "geometry": {"coordinates":[9.158624,49.285259],"type":"Point"}
}