{
  "type": "Feature",
  "properties": {
    "iso:country":"DE",
    "sg:address":"Reichskanzlerstr. 22",
    "sg:city":"Hamburg",
    "sg:phone":"+49 40/4505364",
    "sg:postcode":"22609",
    "sg:province":"Hamburg",
    "wof:name":"Wolfgang Ohlmeier",
    "wof:placetype":"venue"
},
  "geometry": {"coordinates":[9.8455848694,53.5655021667],"type":"Point"}
}