{
  "type": "Feature",
  "properties": {
    "iso:country":"DE",
    "sg:address":"Wittener Str. 3",
    "sg:city":"Dortmund",
    "sg:phone":"+49 231/170426",
    "sg:postcode":"44149",
    "sg:province":"Nordrhein-Westfalen",
    "wof:name":"Johannis-apotheke",
    "wof:placetype":"venue"
},
  "geometry": {"coordinates":[7.40043,51.494381],"type":"Point"}
}