{
  "type": "Feature",
  "properties": {
    "iso:country":"DE",
    "sg:address":"Herrensand 42",
    "sg:city":"Mannheim",
    "sg:phone":"+49 621/872838",
    "sg:postcode":"68219",
    "sg:province":"Baden-W\u00fcrttemberg",
    "wof:name":"K.-h. \u00d6hlmann",
    "wof:placetype":"venue"
},
  "geometry": {"coordinates":[8.533114,49.444885],"type":"Point"}
}