{
  "type": "Feature",
  "properties": {
    "iso:country":"DE",
    "sg:address":"Rathausstr. 123",
    "sg:city":"Viernheim",
    "sg:phone":"+49 6204/4414",
    "sg:postcode":"68519",
    "sg:province":"Hessen",
    "wof:name":"G\u00fcnter Gutperle",
    "wof:placetype":"venue"
},
  "geometry": {"coordinates":[8.5720024109,49.5309371948],"type":"Point"}
}