{
  "type": "Feature",
  "properties": {
    "iso:country":"DE",
    "sg:address":"Gr\u00f6bitzer Weg 32",
    "sg:city":"Finsterwalde",
    "sg:postcode":"03238",
    "sg:province":"Brandenburg",
    "wof:name":"Auto-lehmann- Gmbh",
    "wof:placetype":"venue"
},
  "geometry": {"coordinates":[13.708504,51.6395],"type":"Point"}
}