{
  "type": "Feature",
  "properties": {
    "iso:country":"DE",
    "sg:address":"Rathausstr. 23",
    "sg:city":"Langenneufnach",
    "sg:phone":"+49 8239/356",
    "sg:postcode":"86863",
    "sg:province":"Bayern",
    "wof:name":"Kath. \u00d6ffentliche B\u00fccherei",
    "wof:placetype":"venue"
},
  "geometry": {"coordinates":[10.605431,48.257374],"type":"Point"}
}