{
  "type": "Feature",
  "properties": {
    "iso:country":"DE",
    "sg:address":"Wildenbruchplatz 5",
    "sg:city":"Berlin",
    "sg:phone":"+49 30/6877091",
    "sg:postcode":"12045",
    "sg:province":"Berlin",
    "wof:name":"Horst Marks",
    "wof:placetype":"venue"
},
  "geometry": {"coordinates":[13.4443149567,52.4835128784],"type":"Point"}
}