{
  "type": "Feature",
  "properties": {
    "iso:country":"DE",
    "sg:address":"Branchweilerhofstr. 190",
    "sg:city":"Neustadt",
    "sg:phone":"+49 6321/14096",
    "sg:postcode":"67433",
    "sg:province":"Rheinland-Pfalz",
    "wof:name":"Werner Klingelh\u00f6fer",
    "wof:placetype":"venue"
},
  "geometry": {"coordinates":[8.1687278748,49.3506736755],"type":"Point"}
}