{
  "type": "Feature",
  "properties": {
    "iso:country":"DE",
    "sg:address":"Waldstr. 78",
    "sg:city":"Wachenheim",
    "sg:phone":"+49 6322/8140",
    "sg:postcode":"67157",
    "sg:province":"Rheinland-Pfalz",
    "wof:name":"Albert Wehr",
    "wof:placetype":"venue"
},
  "geometry": {"coordinates":[8.1809463501,49.4393196106],"type":"Point"}
}