{
  "type": "Feature",
  "properties": {
    "iso:country":"DE",
    "sg:address":"Wilhelm-Maybach-Str. 5",
    "sg:city":"Mainz",
    "sg:phone":"+49 6131/508852",
    "sg:postcode":"55129",
    "sg:province":"Rheinland-Pfalz",
    "wof:name":"Gerhard Schlacht Tief- Und Stra\u00dfenbau Gmbh",
    "wof:placetype":"venue"
},
  "geometry": {"coordinates":[8.2558860779,49.9611206055],"type":"Point"}
}