{
  "type": "Feature",
  "properties": {
    "iso:country":"DE",
    "sg:address":"Kaiser-Friedrich-Str. 35",
    "sg:city":"Berlin",
    "sg:phone":"+49 4930/3124234",
    "sg:postcode":"10627",
    "sg:province":"Berlin",
    "wof:name":"Bender Schnelldruck Gmbh",
    "wof:placetype":"venue"
},
  "geometry": {"coordinates":[13.3013753891,52.5103759766],"type":"Point"}
}