{
  "type": "Feature",
  "properties": {
    "iso:country":"DE",
    "sg:address":"Birkenweg 5",
    "sg:city":"Gammelsdorf",
    "sg:phone":"+49 8766/920363",
    "sg:postcode":"85408",
    "sg:province":"Bayern",
    "wof:name":"Auto-zellner",
    "wof:placetype":"venue"
},
  "geometry": {"coordinates":[11.9408254623,48.5543327332],"type":"Point"}
}