{
  "type": "Feature",
  "properties": {
    "iso:country":"DE",
    "sg:address":"Breitenbrunner Str. 11",
    "sg:city":"Seubersdorf",
    "sg:phone":"+49 9497/258",
    "sg:postcode":"92358",
    "sg:province":"Bayern",
    "wof:name":"Josef Hofmann Lagerhaus",
    "wof:placetype":"venue"
},
  "geometry": {"coordinates":[11.62589,49.162045],"type":"Point"}
}