{
  "type": "Feature",
  "properties": {
    "iso:country":"DE",
    "sg:address":"Friedrich-Ebert-Str. 11",
    "sg:city":"Obernkirchen",
    "sg:phone":"+49 5724/2968",
    "sg:postcode":"31683",
    "sg:province":"Niedersachsen",
    "wof:name":"B. Heine",
    "wof:placetype":"venue"
},
  "geometry": {"coordinates":[9.128932,52.271194],"type":"Point"}
}