{
  "type": "Feature",
  "properties": {
    "iso:country":"DE",
    "sg:address":"St.-Barbara-Ufer 42",
    "sg:city":"Trier",
    "sg:phone":"+49 651/40495",
    "sg:postcode":"54290",
    "sg:province":"Rheinland-Pfalz",
    "wof:name":"Deutsche Shell Ag",
    "wof:placetype":"venue"
},
  "geometry": {"coordinates":[6.6283860207,49.7455482483],"type":"Point"}
}