{
  "type": "Feature",
  "properties": {
    "iso:country":"DE",
    "sg:address":"Bahnhofstr. 75",
    "sg:city":"Wiesbaden",
    "sg:phone":"+49 611/373655",
    "sg:postcode":"65185",
    "sg:province":"Hessen",
    "wof:name":"Pizzeria Fontana Gmbh",
    "wof:placetype":"venue"
},
  "geometry": {"coordinates":[8.2428712845,50.0719299316],"type":"Point"}
}