{
  "type": "Feature",
  "properties": {
    "iso:country":"DE",
    "sg:address":"Sudweyher Str. 74",
    "sg:city":"Weyhe",
    "sg:phone":"+49 4203/6162",
    "sg:postcode":"28844",
    "sg:province":"Niedersachsen",
    "wof:name":"Glade Gmbh",
    "wof:placetype":"venue"
},
  "geometry": {"coordinates":[8.877699852,52.983341217],"type":"Point"}
}