{
  "type": "Feature",
  "properties": {
    "iso:country":"DE",
    "sg:address":"Eisenbahnstr. 2",
    "sg:city":"R\u00f6merberg",
    "sg:phone":"+49 6232/84109",
    "sg:postcode":"67354",
    "sg:province":"Rheinland-Pfalz",
    "wof:name":"Werner Debold",
    "wof:placetype":"venue"
},
  "geometry": {"coordinates":[8.409969,49.29467],"type":"Point"}
}