{
  "type": "Feature",
  "properties": {
    "iso:country":"DE",
    "sg:address":"Haller Str. 209",
    "sg:city":"G\u00fctersloh",
    "sg:phone":"+49 5241/6687",
    "sg:postcode":"33334",
    "sg:province":"Nordrhein-Westfalen",
    "wof:name":"W. Und W. Schniedermann Gmbh & Co.",
    "wof:placetype":"venue"
},
  "geometry": {"coordinates":[8.39656,51.955688],"type":"Point"}
}