{
  "type": "Feature",
  "properties": {
    "iso:country":"DE",
    "sg:address":"In Folz 8",
    "sg:city":"Neumagen-Dhron",
    "sg:phone":"+49 6507/2613",
    "sg:postcode":"54347",
    "sg:province":"Rheinland-Pfalz",
    "wof:name":"Leo Becker",
    "wof:placetype":"venue"
},
  "geometry": {"coordinates":[6.9062209129,49.8630371094],"type":"Point"}
}