{
  "type": "Feature",
  "properties": {
    "iso:country":"DE",
    "sg:address":"Reichsforststr. 2",
    "sg:city":"Frankfurt",
    "sg:phone":"+49 69/6665322",
    "sg:postcode":"60528",
    "sg:province":"Hessen",
    "wof:name":"Ottokar Adolf Lipka Rechtsanwalt Und Notar",
    "wof:placetype":"venue"
},
  "geometry": {"coordinates":[8.648018837,50.0782203674],"type":"Point"}
}