{
  "type": "Feature",
  "properties": {
    "iso:country":"DE",
    "sg:address":"Am Bornholdsberg 12",
    "sg:city":"Kellinghusen",
    "sg:phone":"+49 4822/7634",
    "sg:postcode":"25548",
    "sg:province":"Schleswig-Holstein",
    "wof:name":"Re Ga Gabriele Reese Dienstleistungs Gmbh",
    "wof:placetype":"venue"
},
  "geometry": {"coordinates":[9.701125,53.949818],"type":"Point"}
}