{
  "type": "Feature",
  "properties": {
    "iso:country":"DE",
    "sg:address":"Heerdter Lohweg 87",
    "sg:city":"D\u00fcsseldorf",
    "sg:phone":"+49 211/5990613",
    "sg:postcode":"40549",
    "sg:province":"Nordrhein-Westfalen",
    "wof:name":"Attalus Germany Gmbh",
    "wof:placetype":"venue"
},
  "geometry": {"coordinates":[6.7275710106,51.2390556335],"type":"Point"}
}