{
  "type": "Feature",
  "properties": {
    "iso:country":"DE",
    "sg:address":"Gutenbergstr. 12",
    "sg:city":"Flensburg",
    "sg:postcode":"24941",
    "sg:province":"Schleswig-Holstein",
    "wof:name":"Beate U. Ulrich Rotermund Gmbh",
    "wof:placetype":"venue"
},
  "geometry": {"coordinates":[9.438808,54.766399],"type":"Point"}
}