{
  "type": "Feature",
  "properties": {
    "iso:country":"DE",
    "sg:address":"Uphovener Weg 5",
    "sg:city":"Nottuln",
    "sg:phone":"+49 2502/2200",
    "sg:postcode":"48301",
    "sg:province":"Nordrhein-Westfalen",
    "wof:name":"St.- Elisabeth-stift Gmbh",
    "wof:placetype":"venue"
},
  "geometry": {"coordinates":[7.354991,51.934029],"type":"Point"}
}