{
  "type": "Feature",
  "properties": {
    "iso:country":"DE",
    "sg:address":"Arndtstr. 34",
    "sg:city":"Magdeburg",
    "sg:phone":"+49 391/7317281",
    "sg:postcode":"39108",
    "sg:province":"Sachsen-Anhalt",
    "wof:name":"Weinmann Immobilien Gmbh",
    "wof:placetype":"venue"
},
  "geometry": {"coordinates":[11.6127519608,52.1255607605],"type":"Point"}
}