{
  "type": "Feature",
  "properties": {
    "iso:country":"DE",
    "sg:address":"Schwarzenbergstr. 16",
    "sg:city":"Aschaffenburg",
    "sg:phone":"+49 6021/91942",
    "sg:postcode":"63739",
    "sg:province":"Bayern",
    "wof:name":"Richard Geis Steuerberater",
    "wof:placetype":"venue"
},
  "geometry": {"coordinates":[9.1717710495,49.9768104553],"type":"Point"}
}