{
  "type": "Feature",
  "properties": {
    "iso:country":"DE",
    "sg:address":"Rh\u00f6nstr. 18 a",
    "sg:city":"Fulda",
    "sg:phone":"+49 661/72271",
    "sg:postcode":"36037",
    "sg:province":"Hessen",
    "wof:name":"Fliesen Sch\u00e4fer Gmbh",
    "wof:placetype":"venue"
},
  "geometry": {"coordinates":[9.6857538223,50.5519523621],"type":"Point"}
}