{
  "type": "Feature",
  "properties": {
    "iso:country":"DE",
    "sg:address":"Fichtenhof 9",
    "sg:city":"Fichtenau",
    "sg:phone":"+49 7962/2610",
    "sg:postcode":"74579",
    "sg:province":"Baden-W\u00fcrttemberg",
    "wof:name":"Karl Beck",
    "wof:placetype":"venue"
},
  "geometry": {"coordinates":[10.180439,49.076538],"type":"Point"}
}