{
  "type": "Feature",
  "properties": {
    "iso:country":"DE",
    "sg:address":"Holztorstr. 19",
    "sg:city":"Sarstedt",
    "sg:phone":"+49 5066/7529",
    "sg:postcode":"31157",
    "sg:province":"Niedersachsen",
    "wof:name":"L\u00f6wen-apotheke",
    "wof:placetype":"venue"
},
  "geometry": {"coordinates":[9.847002,52.232708],"type":"Point"}
}