{
  "type": "Feature",
  "properties": {
    "iso:country":"DE",
    "sg:address":"Am Herrschaftsweiher 31",
    "sg:city":"Ludwigshafen",
    "sg:phone":"+49 6237/40380",
    "sg:postcode":"67071",
    "sg:province":"Rheinland-Pfalz",
    "wof:name":"Dieter Meyer Rohrleitungsbau Gmbh",
    "wof:placetype":"venue"
},
  "geometry": {"coordinates":[8.332087,49.480556],"type":"Point"}
}