{
  "type": "Feature",
  "properties": {
    "iso:country":"DE",
    "sg:address":"Warnstedtstra\u00dfe 57-59",
    "sg:city":"Hamburg",
    "sg:phone":"+49 40",
    "sg:postcode":"22525",
    "sg:province":"Hamburg",
    "wof:name":"Schaltex Gmbh, Hamburg",
    "wof:placetype":"venue"
},
  "geometry": {"coordinates":[9.928092,53.587364],"type":"Point"}
}