{
  "type": "Feature",
  "properties": {
    "iso:country":"DE",
    "sg:address":"Apianstr. 2-6",
    "sg:city":"Unterf\u00f6hring",
    "sg:postcode":"85774",
    "sg:province":"Bayern",
    "wof:name":"Hvb Systems Gmbh",
    "wof:placetype":"venue"
},
  "geometry": {"coordinates":[11.6411819458,48.1753501892],"type":"Point"}
}