{
  "type": "Feature",
  "properties": {
    "iso:country":"DE",
    "sg:address":"Gustav-Adolf-Str. 5",
    "sg:city":"N\u00fcrnberg",
    "sg:phone":"+49 911/613954",
    "sg:postcode":"90439",
    "sg:province":"Bayern",
    "wof:name":"D & I Haarstudio D. L\u00f6sel Und I. Grigat",
    "wof:placetype":"venue"
},
  "geometry": {"coordinates":[11.0368490219,49.4387397766],"type":"Point"}
}