{
  "type": "Feature",
  "properties": {
    "iso:country":"DE",
    "sg:address":"Ke\u00dflerweg 22",
    "sg:city":"Leinfelden-Echterdingen",
    "sg:phone":"+49 711/975580",
    "sg:postcode":"70771",
    "sg:province":"Baden-W\u00fcrttemberg",
    "wof:name":"Wr-service Gmbh & Co. Kg",
    "wof:placetype":"venue"
},
  "geometry": {"coordinates":[9.120798111,48.706489563],"type":"Point"}
}