{
  "type": "Feature",
  "properties": {
    "iso:country":"DE",
    "sg:address":"Erkrather Str. 68",
    "sg:city":"D\u00fcsseldorf",
    "sg:phone":"+49 211/7334671",
    "sg:postcode":"40233",
    "sg:province":"Nordrhein-Westfalen",
    "wof:name":"Claudia Kreuzer",
    "wof:placetype":"venue"
},
  "geometry": {"coordinates":[6.8017950058,51.2227325439],"type":"Point"}
}