{
  "type": "Feature",
  "properties": {
    "iso:country":"DE",
    "sg:address":"Stockenend 7",
    "sg:city":"Titz",
    "sg:phone":"+49 2164/4181",
    "sg:postcode":"52445",
    "sg:province":"Nordrhein-Westfalen",
    "wof:name":"Josef Schl\u00e4ger",
    "wof:placetype":"venue"
},
  "geometry": {"coordinates":[6.454231,51.034973],"type":"Point"}
}