{
  "type": "Feature",
  "properties": {
    "iso:country":"DE",
    "sg:address":"Schwarzer Weg 25",
    "sg:city":"K\u00f6nigsbronn",
    "sg:phone":"+49 7328/6418",
    "sg:postcode":"89551",
    "sg:province":"Baden-W\u00fcrttemberg",
    "wof:name":"Georg Strau\u00df Baugesch\u00e4ft",
    "wof:placetype":"venue"
},
  "geometry": {"coordinates":[10.124704,48.738735],"type":"Point"}
}