{
  "type": "Feature",
  "properties": {
    "iso:country":"DE",
    "sg:address":"Matterhornstr. 44",
    "sg:city":"Berlin",
    "sg:postcode":"14129",
    "sg:province":"Berlin",
    "wof:name":"Gramex Gmbh",
    "wof:placetype":"venue"
},
  "geometry": {"coordinates":[13.219048,52.43819],"type":"Point"}
}