{
  "type": "Feature",
  "properties": {
    "iso:country":"DE",
    "sg:address":"Alte Str. 1",
    "sg:city":"Murrhardt",
    "sg:phone":"+49 7192/6460",
    "sg:postcode":"71540",
    "sg:province":"Baden-W\u00fcrttemberg",
    "wof:name":"Wolfgang Und Alfred Weller",
    "wof:placetype":"venue"
},
  "geometry": {"coordinates":[9.57963,48.979698],"type":"Point"}
}