{
  "type": "Feature",
  "properties": {
    "iso:country":"DE",
    "sg:address":"Scharnhorststr. 38",
    "sg:city":"Dinslaken",
    "sg:phone":"+49 2064/13273",
    "sg:postcode":"46535",
    "sg:province":"Nordrhein-Westfalen",
    "wof:name":"Angelika Marquis Heilpraktikerin",
    "wof:placetype":"venue"
},
  "geometry": {"coordinates":[6.7305669785,51.5666656494],"type":"Point"}
}