{
  "type": "Feature",
  "properties": {
    "iso:country":"DE",
    "sg:address":"Krumbacher Str. 24",
    "sg:city":"Aletshausen",
    "sg:phone":"+49 8282/2707",
    "sg:postcode":"86480",
    "sg:province":"Bayern",
    "wof:name":"Stefan Michelberger",
    "wof:placetype":"venue"
},
  "geometry": {"coordinates":[10.389535,48.197788],"type":"Point"}
}