{
  "type": "Feature",
  "properties": {
    "iso:country":"DE",
    "sg:address":"Hauptstr. 11",
    "sg:city":"Moorhusen",
    "sg:phone":"+49 4823/8846",
    "sg:postcode":"25554",
    "sg:province":"Schleswig-Holstein",
    "wof:name":"Holger Dunker",
    "wof:placetype":"venue"
},
  "geometry": {"coordinates":[9.382394,53.958569],"type":"Point"}
}