{
  "type": "Feature",
  "properties": {
    "iso:country":"DE",
    "sg:address":"Hubenstr. 20",
    "sg:city":"Mannheim",
    "sg:phone":"+49 621/745050",
    "sg:postcode":"68305",
    "sg:province":"Baden-W\u00fcrttemberg",
    "wof:name":"Die Trepp Ruff",
    "wof:placetype":"venue"
},
  "geometry": {"coordinates":[8.4801111221,49.526676178],"type":"Point"}
}