{
  "type": "Feature",
  "properties": {
    "iso:country":"DE",
    "sg:address":"Hubertusstr. 3",
    "sg:city":"Gr\u00fcnheide",
    "sg:postcode":"15537",
    "sg:province":"Brandenburg",
    "wof:name":"Marita Suter",
    "wof:placetype":"venue"
},
  "geometry": {"coordinates":[13.833372,52.43248],"type":"Point"}
}