{
  "type": "Feature",
  "properties": {
    "iso:country":"DE",
    "sg:address":"Austr. 92",
    "sg:city":"Heilbronn",
    "sg:phone":"+49 7131/15060",
    "sg:postcode":"74076",
    "sg:province":"Baden-W\u00fcrttemberg",
    "wof:name":"Eugen Dierolf Beteiligungs- Gmbh",
    "wof:placetype":"venue"
},
  "geometry": {"coordinates":[9.219122,49.169529],"type":"Point"}
}