{
  "type": "Feature",
  "properties": {
    "iso:country":"DE",
    "sg:address":"Hasselbecker Str 16",
    "sg:city":"Heiligenhaus",
    "sg:phone":"+49 2056/2640",
    "sg:postcode":"42579",
    "sg:province":"Nordrhein-Westfalen",
    "wof:name":"Dietrich L\u00fcttgens Gmbh & Co Kg",
    "wof:placetype":"venue"
},
  "geometry": {"coordinates":[6.9529237747,51.3279457092],"type":"Point"}
}