{
  "type": "Feature",
  "properties": {
    "iso:country":"DE",
    "sg:address":"Derchinger Str. 12 a",
    "sg:city":"Affing",
    "sg:phone":"+49 8207/1708",
    "sg:postcode":"86444",
    "sg:province":"Bayern",
    "wof:name":"Prof. Dr. Eberhard P. Hilbich Ingenieur Und Architekt",
    "wof:placetype":"venue"
},
  "geometry": {"coordinates":[10.945915,48.438519],"type":"Point"}
}