{
  "type": "Feature",
  "properties": {
    "iso:country":"DE",
    "sg:address":"Bischofstr. 5",
    "sg:city":"Oberau",
    "sg:phone":"+49 8824/290",
    "sg:postcode":"82496",
    "sg:province":"Bayern",
    "wof:name":"W. Schwarz",
    "wof:placetype":"venue"
},
  "geometry": {"coordinates":[11.136047,47.561256],"type":"Point"}
}