{
  "type": "Feature",
  "properties": {
    "iso:country":"DE",
    "sg:address":"Waldhausener Str. 158",
    "sg:city":"M\u00f6nchengladbach",
    "sg:phone":"+49 2161/180613",
    "sg:postcode":"41061",
    "sg:province":"Nordrhein-Westfalen",
    "wof:name":"Thiele",
    "wof:placetype":"venue"
},
  "geometry": {"coordinates":[6.4219880104,51.1968612671],"type":"Point"}
}