{
  "type": "Feature",
  "properties": {
    "iso:country":"DE",
    "sg:address":"Skagerrakstr. 17",
    "sg:city":"Gelsenkirchen",
    "sg:phone":"+49 209/202106",
    "sg:postcode":"45888",
    "sg:province":"Nordrhein-Westfalen",
    "wof:name":"D. Meier",
    "wof:placetype":"venue"
},
  "geometry": {"coordinates":[7.1298780441,51.5165977478],"type":"Point"}
}