{
  "type": "Feature",
  "properties": {
    "iso:country":"DE",
    "sg:address":"Kaufingerstr. 12",
    "sg:city":"M\u00fcnchen",
    "sg:phone":"+49 89/221760",
    "sg:postcode":"80331",
    "sg:province":"Bayern",
    "wof:name":"Duffek Duffek Und Duffek Rechtsanw\u00e4lte",
    "wof:placetype":"venue"
},
  "geometry": {"coordinates":[11.5739946365,48.1374893188],"type":"Point"}
}