{
  "type": "Feature",
  "properties": {
    "iso:country":"DE",
    "sg:address":"Am Kieselgraben 1",
    "sg:city":"Allersberg",
    "sg:phone":"+49 9176/353",
    "sg:postcode":"90584",
    "sg:province":"Bayern",
    "wof:name":"Alois Krillmayer",
    "wof:placetype":"venue"
},
  "geometry": {"coordinates":[11.2404470444,49.2508049011],"type":"Point"}
}