{
  "type": "Feature",
  "properties": {
    "iso:country":"DE",
    "sg:address":"Steinweg 10",
    "sg:city":"Etzenricht",
    "sg:phone":"+49 961/46256",
    "sg:postcode":"92694",
    "sg:province":"Bayern",
    "wof:name":"Inge Gr\u00fcssner U. Anita Schwarz",
    "wof:placetype":"venue"
},
  "geometry": {"coordinates":[12.0890493393,49.6195259094],"type":"Point"}
}