{
  "type": "Feature",
  "properties": {
    "iso:country":"DE",
    "sg:address":"Hauptstr. 2",
    "sg:city":"Mihla",
    "sg:phone":"+49 36924/42907",
    "sg:postcode":"99826",
    "sg:province":"Th\u00fcringen",
    "wof:name":"Kuehl- Und Melktechnik Thueringen Gmbh",
    "wof:placetype":"venue"
},
  "geometry": {"coordinates":[10.273776,51.073215],"type":"Point"}
}