{
  "type": "Feature",
  "properties": {
    "iso:country":"DE",
    "sg:address":"Hag 2",
    "sg:city":"Ludwigsburg",
    "sg:phone":"+49 7141/506836",
    "sg:postcode":"71642",
    "sg:province":"Baden-W\u00fcrttemberg",
    "wof:name":"Paul Stadelmaier",
    "wof:placetype":"venue"
},
  "geometry": {"coordinates":[9.237125,48.917564],"type":"Point"}
}