{
  "type": "Feature",
  "properties": {
    "iso:country":"DE",
    "sg:address":"Holzwiesenstr.",
    "sg:city":"Leinfelden-Echterdingen",
    "sg:phone":"+49 711/791970",
    "sg:postcode":"70771",
    "sg:province":"Baden-W\u00fcrttemberg",
    "wof:name":"Justo Schikora Architekt",
    "wof:placetype":"venue"
},
  "geometry": {"coordinates":[9.159874,48.686771],"type":"Point"}
}