{
  "type": "Feature",
  "properties": {
    "iso:country":"DE",
    "sg:address":"Stadtrandsiedlung 59",
    "sg:city":"Bad Freienwalde",
    "sg:postcode":"16259",
    "sg:province":"Brandenburg",
    "wof:name":"Weprajetzky",
    "wof:placetype":"venue"
},
  "geometry": {"coordinates":[14.0565,52.77528],"type":"Point"}
}