{
  "type": "Feature",
  "properties": {
    "iso:country":"DE",
    "sg:address":"Oberdessing 5",
    "sg:city":"Kumhausen",
    "sg:phone":"+49 8705/1607",
    "sg:postcode":"84036",
    "sg:province":"Bayern",
    "wof:name":"Hohenester",
    "wof:placetype":"venue"
},
  "geometry": {"coordinates":[12.163788,48.472111],"type":"Point"}
}