{
  "type": "Feature",
  "properties": {
    "iso:country":"DE",
    "sg:address":"Max-Eyth-Str. 17",
    "sg:city":"Albershausen",
    "sg:phone":"+49 7161/33529",
    "sg:postcode":"73095",
    "sg:province":"Baden-W\u00fcrttemberg",
    "wof:name":"Mr Reiss Gmbh",
    "wof:placetype":"venue"
},
  "geometry": {"coordinates":[9.5556526184,48.6881713867],"type":"Point"}
}