{
  "type": "Feature",
  "properties": {
    "iso:country":"DE",
    "sg:address":"Marktoberdorfer Str. 6",
    "sg:city":"Wildpoldsried",
    "sg:phone":"+49 8304/92080",
    "sg:postcode":"87499",
    "sg:province":"Bayern",
    "wof:name":"Imka Immobilien- Und Ver- M\u00f6gensanlagen Gesch\u00e4fts-",
    "wof:placetype":"venue"
},
  "geometry": {"coordinates":[10.4026422501,47.7672691345],"type":"Point"}
}