{
  "type": "Feature",
  "properties": {
    "iso:country":"DE",
    "sg:address":"Kalvarienbergstr. 4",
    "sg:city":"Pr\u00fcm",
    "sg:phone":"+49 6551/3052",
    "sg:postcode":"54595",
    "sg:province":"Rheinland-Pfalz",
    "wof:name":"Kreiswasserwerk Bitburg-pr\u00fcm",
    "wof:placetype":"venue"
},
  "geometry": {"coordinates":[6.4211301804,50.2063407898],"type":"Point"}
}