{
  "type": "Feature",
  "properties": {
    "iso:country":"DE",
    "sg:address":"Oberer Krankenhausweg 4",
    "sg:city":"Schneeberg",
    "sg:phone":"+49 3772/35080",
    "sg:postcode":"08289",
    "sg:province":"Sachsen",
    "wof:name":"B\u00f6hm Geb\u00e4udereinigung Gmbh",
    "wof:placetype":"venue"
},
  "geometry": {"coordinates":[12.63829,50.592793],"type":"Point"}
}