{
  "type": "Feature",
  "properties": {
    "iso:country":"DE",
    "sg:address":"Stadl\u00e4nder Str. 39",
    "sg:city":"Nordenham",
    "sg:phone":"+49 4731/7194",
    "sg:postcode":"26954",
    "sg:province":"Niedersachsen",
    "wof:name":"Hans Ca\u00dfens",
    "wof:placetype":"venue"
},
  "geometry": {"coordinates":[8.452891,53.475029],"type":"Point"}
}