{
  "type": "Feature",
  "properties": {
    "iso:country":"DE",
    "sg:address":"Yorckstr. 29",
    "sg:city":"Karlsruhe",
    "sg:phone":"+49 721/856482",
    "sg:postcode":"76185",
    "sg:province":"Baden-W\u00fcrttemberg",
    "wof:name":"Bernhard R\u00f6singer Heilpraktiker",
    "wof:placetype":"venue"
},
  "geometry": {"coordinates":[8.3737859726,49.0087242126],"type":"Point"}
}