{
  "type": "Feature",
  "properties": {
    "iso:country":"DE",
    "sg:address":"Fliedener Str. 40",
    "sg:city":"Neuhof",
    "sg:phone":"+49 4966/552035",
    "sg:postcode":"36119",
    "sg:province":"Hessen",
    "wof:name":"Helmut Heil Gmbh",
    "wof:placetype":"venue"
},
  "geometry": {"coordinates":[9.5783214569,50.445098877],"type":"Point"}
}