{
  "type": "Feature",
  "properties": {
    "iso:country":"DE",
    "sg:address":"H\u00f6ngener Weg 5",
    "sg:city":"Selfkant",
    "sg:phone":"+49 2456/1085",
    "sg:postcode":"52538",
    "sg:province":"Nordrhein-Westfalen",
    "wof:name":"Beyers Taxi",
    "wof:placetype":"venue"
},
  "geometry": {"coordinates":[5.931701,50.998501],"type":"Point"}
}