{
  "type": "Feature",
  "properties": {
    "iso:country":"DE",
    "sg:address":"Bahnhofstr. 124",
    "sg:city":"Vaihingen",
    "sg:phone":"+49 7042/4143",
    "sg:postcode":"71665",
    "sg:province":"Baden-W\u00fcrttemberg",
    "wof:name":"Klaus Baumann",
    "wof:placetype":"venue"
},
  "geometry": {"coordinates":[8.982721,48.954475],"type":"Point"}
}