{
  "type": "Feature",
  "properties": {
    "iso:country":"DE",
    "sg:address":"Schie\u00dfhausstr. 16",
    "sg:city":"Teuschnitz",
    "sg:phone":"+49 9268/217",
    "sg:postcode":"96358",
    "sg:province":"Bayern",
    "wof:name":"Helmut Knauer",
    "wof:placetype":"venue"
},
  "geometry": {"coordinates":[11.3841085434,50.3993339539],"type":"Point"}
}