{
  "type": "Feature",
  "properties": {
    "iso:country":"DE",
    "sg:address":"Marktplatz 11",
    "sg:city":"Amberg",
    "sg:phone":"+49 9621/12057",
    "sg:postcode":"92224",
    "sg:province":"Bayern",
    "wof:name":"Abr Reiseb\u00fcro Gmbh",
    "wof:placetype":"venue"
},
  "geometry": {"coordinates":[11.8585348129,49.4450798035],"type":"Point"}
}