{
  "type": "Feature",
  "properties": {
    "iso:country":"DE",
    "sg:address":"Voita 1",
    "sg:city":"Prebitz",
    "sg:postcode":"95473",
    "sg:province":"Bayern",
    "wof:name":"Wafa Beteiligungs Gmbh",
    "wof:placetype":"venue"
},
  "geometry": {"coordinates":[11.710055,49.823055],"type":"Point"}
}