{
  "type": "Feature",
  "properties": {
    "iso:country":"DE",
    "sg:address":"Am Alten Bahnhof 4",
    "sg:city":"Kehl",
    "sg:phone":"+49 4978/5193360",
    "sg:postcode":"77694",
    "sg:province":"Baden-W\u00fcrttemberg",
    "wof:name":"Pack & Zack Direktkurier Gmbh",
    "wof:placetype":"venue"
},
  "geometry": {"coordinates":[7.8212089539,48.5785980225],"type":"Point"}
}