{
  "type": "Feature",
  "properties": {
    "iso:country":"DE",
    "sg:address":"Oranienstr 10-11",
    "sg:city":"Berlin",
    "sg:phone":"+49 30/6178970",
    "sg:postcode":"10997",
    "sg:province":"Berlin",
    "wof:name":"Theco.de Ag",
    "wof:placetype":"venue"
},
  "geometry": {"coordinates":[13.424179,52.500076],"type":"Point"}
}