{
  "type": "Feature",
  "properties": {
    "iso:country":"DE",
    "sg:address":"Osterstr. 27 a",
    "sg:city":"Schellerten",
    "sg:phone":"+49 5123/1011",
    "sg:postcode":"31174",
    "sg:province":"Niedersachsen",
    "wof:name":"G\u00fcnther Umlauf Steuerberater",
    "wof:placetype":"venue"
},
  "geometry": {"coordinates":[10.0885448456,52.1521835327],"type":"Point"}
}