{
  "type": "Feature",
  "properties": {
    "iso:country":"DE",
    "sg:address":"Rielasinger Str. 16",
    "sg:city":"Rielasingen-Worblingen",
    "sg:phone":"+49 7731/52618",
    "sg:postcode":"78239",
    "sg:province":"Baden-W\u00fcrttemberg",
    "wof:name":"Manuela Schreindorfer Hebamme",
    "wof:placetype":"venue"
},
  "geometry": {"coordinates":[8.854699,47.728291],"type":"Point"}
}