{
  "type": "Feature",
  "properties": {
    "iso:country":"DE",
    "sg:address":"Hessenauer Str. 2",
    "sg:city":"Trebur",
    "sg:phone":"+49 6147/1651",
    "sg:postcode":"65468",
    "sg:province":"Hessen",
    "wof:name":"Mc-v Beteiligung Verwaltungsgesellschaft Mbh",
    "wof:placetype":"venue"
},
  "geometry": {"coordinates":[8.402069,49.893574],"type":"Point"}
}