{
  "type": "Feature",
  "properties": {
    "iso:country":"DE",
    "sg:address":"Hebbelstr. 3",
    "sg:city":"Weiden",
    "sg:postcode":"92637",
    "sg:province":"Bayern",
    "wof:name":"Hans-j\u00f6rg Rose E. K.",
    "wof:placetype":"venue"
},
  "geometry": {"coordinates":[12.1414709091,49.654083252],"type":"Point"}
}