{
  "type": "Feature",
  "properties": {
    "iso:country":"DE",
    "sg:address":"Mehringdamm 66",
    "sg:city":"Berlin",
    "sg:phone":"+49 30/78990950",
    "sg:postcode":"10961",
    "sg:province":"Berlin",
    "wof:name":"Karl-ernst Giese Rechtsanwalt",
    "wof:placetype":"venue"
},
  "geometry": {"coordinates":[13.3863267899,52.4906730652],"type":"Point"}
}