{
  "type": "Feature",
  "properties": {
    "iso:country":"DE",
    "sg:address":"Hindenburgstr. 4",
    "sg:city":"Siegen",
    "sg:phone":"+49 271/54535",
    "sg:postcode":"57072",
    "sg:province":"Nordrhein-Westfalen",
    "wof:name":"Ernst Gethmann",
    "wof:placetype":"venue"
},
  "geometry": {"coordinates":[8.0186815262,50.8762741089],"type":"Point"}
}