{
  "type": "Feature",
  "properties": {
    "iso:country":"DE",
    "sg:address":"Hauptstr. 30",
    "sg:city":"Perl",
    "sg:phone":"+49 6866/821",
    "sg:postcode":"66706",
    "sg:province":"Saarland",
    "wof:name":"Alfons Gerardy",
    "wof:placetype":"venue"
},
  "geometry": {"coordinates":[6.4334778786,49.5327301025],"type":"Point"}
}