{
  "type": "Feature",
  "properties": {
    "iso:country":"DE",
    "sg:address":"Langgasse 30",
    "sg:city":"Idstein",
    "sg:phone":"+49 6126/91417",
    "sg:postcode":"65510",
    "sg:province":"Hessen",
    "wof:name":"Albrecht Gantzer Dachdeckermeister Gmbh",
    "wof:placetype":"venue"
},
  "geometry": {"coordinates":[8.332067,50.221397],"type":"Point"}
}