{
  "type": "Feature",
  "properties": {
    "iso:country":"DE",
    "sg:address":"Steindamm 45",
    "sg:city":"Norderstedt",
    "sg:phone":"+49 40/5222569",
    "sg:postcode":"22844",
    "sg:province":"Schleswig-Holstein",
    "wof:name":"A. Liermann-maus",
    "wof:placetype":"venue"
},
  "geometry": {"coordinates":[10.006299,53.719845],"type":"Point"}
}