{
  "type": "Feature",
  "properties": {
    "iso:country":"DE",
    "sg:address":"Springer Str. 1",
    "sg:city":"Hannover",
    "sg:phone":"+49 511/426765",
    "sg:postcode":"30459",
    "sg:province":"Niedersachsen",
    "wof:name":"Dr. Harald Lauth Tierarzt",
    "wof:placetype":"venue"
},
  "geometry": {"coordinates":[9.7027711868,52.341583252],"type":"Point"}
}