{
  "type": "Feature",
  "properties": {
    "iso:country":"DE",
    "sg:address":"Wolftalstr. 28",
    "sg:city":"Oberwolfach",
    "sg:phone":"+49 7834/260",
    "sg:postcode":"77709",
    "sg:province":"Baden-W\u00fcrttemberg",
    "wof:name":"Drei K\u00f6nige",
    "wof:placetype":"venue"
},
  "geometry": {"coordinates":[8.2156438828,48.3185691833],"type":"Point"}
}