{
  "type": "Feature",
  "properties": {
    "iso:country":"DE",
    "sg:address":"Wohlenbergstr. 8",
    "sg:city":"Hannover",
    "sg:phone":"+49 4951/163970",
    "sg:postcode":"30179",
    "sg:province":"Niedersachsen",
    "wof:name":"Wohlenberg Schneidesysteme Gmbh",
    "wof:placetype":"venue"
},
  "geometry": {"coordinates":[9.724744,52.4175],"type":"Point"}
}