{
  "type": "Feature",
  "properties": {
    "iso:country":"DE",
    "sg:address":"Am Paasberg 12",
    "sg:city":"Isselburg",
    "sg:phone":"+49 2874/2139",
    "sg:postcode":"46419",
    "sg:province":"Nordrhein-Westfalen",
    "wof:name":"Meyer Und Neitzel Architekten",
    "wof:placetype":"venue"
},
  "geometry": {"coordinates":[6.422533,51.850842],"type":"Point"}
}