{
  "type": "Feature",
  "properties": {
    "iso:country":"DE",
    "sg:address":"Ernst-Th\u00e4lmann-Str. 40",
    "sg:city":"Wustrau",
    "sg:phone":"+49 33925/71233",
    "sg:postcode":"16818",
    "sg:province":"Brandenburg",
    "wof:name":"Gutsmilch Rinderhaltung Gmbh",
    "wof:placetype":"venue"
},
  "geometry": {"coordinates":[12.8573036194,52.8456535339],"type":"Point"}
}