{
  "type": "Feature",
  "properties": {
    "iso:country":"DE",
    "sg:address":"Langenhainer Str. 97",
    "sg:city":"Fr\u00f6ttst\u00e4dt",
    "sg:phone":"+49 3622/902971",
    "sg:postcode":"99880",
    "sg:province":"Th\u00fcringen",
    "wof:name":"Franke Brennstoffhandels Gmbh",
    "wof:placetype":"venue"
},
  "geometry": {"coordinates":[10.5718812943,50.9319381714],"type":"Point"}
}