{
  "type": "Feature",
  "properties": {
    "iso:country":"DE",
    "sg:address":"August-Heine-Weg 5",
    "sg:city":"Halberstadt",
    "sg:phone":"+49 3941/24074",
    "sg:postcode":"38820",
    "sg:province":"Sachsen-Anhalt",
    "wof:name":"Halberst\u00e4dter Wertstoffhandel Und Containderdienst",
    "wof:placetype":"venue"
},
  "geometry": {"coordinates":[11.037976265,51.8960418701],"type":"Point"}
}