{
  "type": "Feature",
  "properties": {
    "iso:country":"DE",
    "sg:address":"Calauer Str. 1",
    "sg:city":"Senftenberg",
    "sg:postcode":"01968",
    "sg:province":"Brandenburg",
    "wof:name":"Katholisches Pfarramt Senftenberg",
    "wof:placetype":"venue"
},
  "geometry": {"coordinates":[14.0017127991,51.5284156799],"type":"Point"}
}