{
  "type": "Feature",
  "properties": {
    "iso:country":"DE",
    "sg:address":"Am Elbufer",
    "sg:city":"K\u00f6nigstein",
    "sg:phone":"+49 35021/224",
    "sg:postcode":"01824",
    "sg:province":"Sachsen",
    "wof:name":"Campingplatz K\u00f6nigstein",
    "wof:placetype":"venue"
},
  "geometry": {"coordinates":[14.07936,50.888939],"type":"Point"}
}