{
  "type": "Feature",
  "properties": {
    "iso:country":"DE",
    "sg:address":"Balmerstr. 10",
    "sg:city":"Dornhan",
    "sg:phone":"+49 7455/9310",
    "sg:postcode":"72175",
    "sg:province":"Baden-W\u00fcrttemberg",
    "wof:name":"Maschinenfabrik Dornhan Gmbh",
    "wof:placetype":"venue"
},
  "geometry": {"coordinates":[8.5092735291,48.3519248962],"type":"Point"}
}