{
  "type": "Feature",
  "properties": {
    "iso:country":"DE",
    "sg:address":"Bruchweg 4",
    "sg:city":"Pennigsehl",
    "sg:postcode":"31621",
    "sg:province":"Niedersachsen",
    "wof:name":"Malerbetrieb Bergholz Gmbh",
    "wof:placetype":"venue"
},
  "geometry": {"coordinates":[9.026179,52.647369],"type":"Point"}
}