{
  "type": "Feature",
  "properties": {
    "iso:country":"DE",
    "sg:address":"Haderslebener Str 7",
    "sg:city":"Pinneberg",
    "sg:phone":"+49 4101/58550",
    "sg:postcode":"25421",
    "sg:province":"Schleswig-Holstein",
    "wof:name":"Br\u00fcckner Aktuelle B\u00fcrosysteme Gmbh",
    "wof:placetype":"venue"
},
  "geometry": {"coordinates":[9.8035240173,53.6757164001],"type":"Point"}
}