{
  "type": "Feature",
  "properties": {
    "iso:country":"DE",
    "sg:address":"Lindenstr. 46",
    "sg:city":"Aichwald",
    "sg:phone":"+49 711/362187",
    "sg:postcode":"73773",
    "sg:province":"Baden-W\u00fcrttemberg",
    "wof:name":"R. Gl\u00e4ser Steuerbevollm\u00e4chtigte",
    "wof:placetype":"venue"
},
  "geometry": {"coordinates":[9.4001369476,48.7637443542],"type":"Point"}
}