{
  "type": "Feature",
  "properties": {
    "iso:country":"DE",
    "sg:address":"Weidener Str. 4",
    "sg:city":"Regensburg",
    "sg:phone":"+49 941/40807",
    "sg:postcode":"93057",
    "sg:province":"Bayern",
    "wof:name":"Seiler-schaumstoff Gmbh",
    "wof:placetype":"venue"
},
  "geometry": {"coordinates":[12.133844,49.0625],"type":"Point"}
}