{
  "type": "Feature",
  "properties": {
    "iso:country":"DE",
    "sg:city":"Eslohe",
    "sg:postcode":"59889",
    "sg:province":"Nordrhein-Westfalen",
    "wof:name":"Erdenklang Label",
    "wof:placetype":"venue"
},
  "geometry": {"coordinates":[8.18112,51.2449],"type":"Point"}
}