{
  "type": "Feature",
  "properties": {
    "iso:country":"DE",
    "sg:address":"Untermarkt 3",
    "sg:city":"Wolfratshausen",
    "sg:phone":"+49 8171/72241",
    "sg:postcode":"82515",
    "sg:province":"Bayern",
    "wof:name":"Erich Ritter Ingenieur",
    "wof:placetype":"venue"
},
  "geometry": {"coordinates":[11.4179849625,47.9143180847],"type":"Point"}
}