{
  "type": "Feature",
  "properties": {
    "iso:country":"DE",
    "sg:address":"Amselweg 1",
    "sg:city":"Bad F\u00fcssing",
    "sg:phone":"+49 8531/29241",
    "sg:postcode":"94072",
    "sg:province":"Bayern",
    "wof:name":"Kurhaus Weidinger",
    "wof:placetype":"venue"
},
  "geometry": {"coordinates":[13.3245639801,48.3448104858],"type":"Point"}
}