{
  "type": "Feature",
  "properties": {
    "iso:country":"DE",
    "sg:address":"Mittelweg 5",
    "sg:city":"Sylt-Ost",
    "sg:phone":"+49 4651/33454",
    "sg:postcode":"25980",
    "sg:province":"Schleswig-Holstein",
    "wof:name":"Long-horn",
    "wof:placetype":"venue"
},
  "geometry": {"coordinates":[8.3395586014,54.8999519348],"type":"Point"}
}