{
  "type": "Feature",
  "properties": {
    "iso:country":"DE",
    "sg:address":"Detmolder Str. 136",
    "sg:city":"Bad Lippspringe",
    "sg:phone":"+49 5252/50314",
    "sg:postcode":"33175",
    "sg:province":"Nordrhein-Westfalen",
    "wof:name":"Gerhard Heinemann",
    "wof:placetype":"venue"
},
  "geometry": {"coordinates":[8.8176221848,51.7818565369],"type":"Point"}
}