{
  "type": "Feature",
  "properties": {
    "iso:country":"DE",
    "sg:address":"Weiherstr 46",
    "sg:city":"Puchheim",
    "sg:phone":"+49 89/89020510",
    "sg:postcode":"82178",
    "sg:province":"Bayern",
    "wof:name":"8sense",
    "wof:placetype":"venue"
},
  "geometry": {"coordinates":[11.365846,48.175083],"type":"Point"}
}