{
  "type": "Feature",
  "properties": {
    "iso:country":"DE",
    "sg:address":"Einsteinstr. 60",
    "sg:city":"Ulm",
    "sg:phone":"+49 731/935280",
    "sg:postcode":"89077",
    "sg:province":"Baden-W\u00fcrttemberg",
    "wof:name":"Ulma Technische Produkte Gmbh & Co.",
    "wof:placetype":"venue"
},
  "geometry": {"coordinates":[9.96022,48.39706],"type":"Point"}
}