{
  "type": "Feature",
  "properties": {
    "iso:country":"DE",
    "sg:address":"Pestalozzistr. 1",
    "sg:city":"Pinneberg",
    "sg:phone":"+49 4101/850340",
    "sg:postcode":"25421",
    "sg:province":"Schleswig-Holstein",
    "wof:name":"Kurt Markussen",
    "wof:placetype":"venue"
},
  "geometry": {"coordinates":[9.81482,53.642666],"type":"Point"}
}