{
  "type": "Feature",
  "properties": {
    "iso:country":"DE",
    "sg:address":"Regensburger Str. 39",
    "sg:city":"Schrobenhausen",
    "sg:phone":"+49 8252/7805",
    "sg:postcode":"86529",
    "sg:province":"Bayern",
    "wof:name":"M. Euba",
    "wof:placetype":"venue"
},
  "geometry": {"coordinates":[11.263377,48.567257],"type":"Point"}
}