{
  "type": "Feature",
  "properties": {
    "iso:country":"DE",
    "sg:city":"Greifswald",
    "sg:postcode":"17487",
    "sg:province":"Mecklenburg-Vorpommern",
    "wof:name":"Institut F\u00fcr Sportwissenschaft Greifswald",
    "wof:placetype":"venue"
},
  "geometry": {"coordinates":[13.384235,54.097317],"type":"Point"}
}