{
  "type": "Feature",
  "properties": {
    "iso:country":"DE",
    "sg:address":"Kreuzgang 2",
    "sg:city":"Neubrandenburg",
    "sg:phone":"+49 395/5443232",
    "sg:postcode":"17033",
    "sg:province":"Mecklenburg-Vorpommern",
    "wof:name":"Dachdeckerei Suhr Gmbh",
    "wof:placetype":"venue"
},
  "geometry": {"coordinates":[13.233103,53.555035],"type":"Point"}
}