{
  "type": "Feature",
  "properties": {
    "iso:country":"DE",
    "sg:address":"Zietenstr. 123",
    "sg:city":"Chemnitz",
    "sg:phone":"+49 371/428598",
    "sg:postcode":"09130",
    "sg:province":"Sachsen",
    "wof:name":"Car Stop Service Shop",
    "wof:placetype":"venue"
},
  "geometry": {"coordinates":[12.943497,50.843498],"type":"Point"}
}