{
  "type": "Feature",
  "properties": {
    "iso:country":"DE",
    "sg:address":"Havelch. 157",
    "sg:city":"Berlin",
    "sg:phone":"+49 4930/3055084",
    "sg:postcode":"14055",
    "sg:province":"Berlin",
    "wof:name":"Mette Wasserbau Gmbh & Co. Kg",
    "wof:placetype":"venue"
},
  "geometry": {"coordinates":[13.24357,52.501549],"type":"Point"}
}