{
  "type": "Feature",
  "properties": {
    "iso:country":"DE",
    "sg:address":"Siemensdamm 50",
    "sg:city":"Berlin",
    "sg:phone":"+49 30/50576131",
    "sg:postcode":"13629",
    "sg:province":"Berlin",
    "wof:name":"Siemens Geb\u00e4udetechnik Ost Gmbh & Co. Ohg",
    "wof:placetype":"venue"
},
  "geometry": {"coordinates":[13.274394,52.535736],"type":"Point"}
}