{
  "type": "Feature",
  "properties": {
    "iso:country":"DE",
    "sg:address":"Zur Werner Heide 34",
    "sg:city":"Bochum",
    "sg:phone":"+49 234/926010",
    "sg:postcode":"44894",
    "sg:province":"Nordrhein-Westfalen",
    "wof:name":"Druckerei Bringmann Gmbh",
    "wof:placetype":"venue"
},
  "geometry": {"coordinates":[7.306578,51.489136],"type":"Point"}
}