{
  "type": "Feature",
  "properties": {
    "iso:country":"DE",
    "sg:address":"M\u00fcnstersche Str. 1",
    "sg:city":"Brandenburg",
    "sg:phone":"+49 3381",
    "sg:postcode":"14772",
    "sg:province":"Brandenburg",
    "wof:name":"Autohaus Chlupka, Brandenburg - Partner Von Faircar",
    "wof:placetype":"venue"
},
  "geometry": {"coordinates":[12.5265235901,52.4399833679],"type":"Point"}
}