{
  "type": "Feature",
  "properties": {
    "iso:country":"DE",
    "sg:address":"St.-Georg-Ring 9",
    "sg:city":"Schwarzenberg",
    "sg:phone":"+49 3774/25292",
    "sg:postcode":"08340",
    "sg:province":"Sachsen",
    "wof:name":"A. S\u00e4ndig",
    "wof:placetype":"venue"
},
  "geometry": {"coordinates":[12.780979,50.541973],"type":"Point"}
}