{
  "type": "Feature",
  "properties": {
    "iso:country":"DE",
    "sg:address":"Riemenschneiderweg 51",
    "sg:city":"Gerolzhofen",
    "sg:phone":"+49 9382/8319",
    "sg:postcode":"97447",
    "sg:province":"Bayern",
    "wof:name":"Pension Robert Und Renate Groha",
    "wof:placetype":"venue"
},
  "geometry": {"coordinates":[10.3469352722,49.8941078186],"type":"Point"}
}