{
  "type": "Feature",
  "properties": {
    "iso:country":"DE",
    "sg:address":"Contrescarpe 45",
    "sg:city":"Bremen",
    "sg:phone":"+49 421/324210",
    "sg:postcode":"28195",
    "sg:province":"Bremen",
    "wof:name":"City Gmbh",
    "wof:placetype":"venue"
},
  "geometry": {"coordinates":[8.8150348663,53.0773353577],"type":"Point"}
}