{
  "type": "Feature",
  "properties": {
    "iso:country":"DE",
    "sg:address":"Kanalstr. 75",
    "sg:city":"Hamburg",
    "sg:phone":"+49 40/222761",
    "sg:postcode":"22085",
    "sg:province":"Hamburg",
    "wof:name":"Paul Herrmann",
    "wof:placetype":"venue"
},
  "geometry": {"coordinates":[10.022592,53.573463],"type":"Point"}
}