{
  "type": "Feature",
  "properties": {
    "iso:country":"DE",
    "sg:address":"Georg-Wrede-Str. 13",
    "sg:city":"Freilassing",
    "sg:phone":"+49 8654/9076",
    "sg:postcode":"83395",
    "sg:province":"Bayern",
    "wof:name":"Isn International Sports Network Vertriebs Gmbh",
    "wof:placetype":"venue"
},
  "geometry": {"coordinates":[12.972743988,47.8368911743],"type":"Point"}
}