{
  "type": "Feature",
  "properties": {
    "iso:country":"DE",
    "sg:address":"Hoher Weg 2",
    "sg:city":"Ludwigshafen",
    "sg:phone":"+49 621/549690",
    "sg:postcode":"67067",
    "sg:province":"Rheinland-Pfalz",
    "wof:name":"Deflize & Partner Gmbh",
    "wof:placetype":"venue"
},
  "geometry": {"coordinates":[8.4175224304,49.4443817139],"type":"Point"}
}