{
  "type": "Feature",
  "properties": {
    "iso:country":"DE",
    "sg:address":"Pelzerstr. 5",
    "sg:city":"Bremen",
    "sg:phone":"+49 421/171771",
    "sg:postcode":"28195",
    "sg:province":"Bremen",
    "wof:name":"September Gmbh",
    "wof:placetype":"venue"
},
  "geometry": {"coordinates":[8.8070297241,53.0779380798],"type":"Point"}
}