{
  "type": "Feature",
  "properties": {
    "iso:country":"DE",
    "sg:address":"Stehlings",
    "sg:city":"Eggenthal",
    "sg:phone":"+49 8347/7015",
    "sg:postcode":"87653",
    "sg:province":"Bayern",
    "wof:name":"F. Huber",
    "wof:placetype":"venue"
},
  "geometry": {"coordinates":[10.464565,47.904156],"type":"Point"}
}