{
  "type": "Feature",
  "properties": {
    "iso:country":"DE",
    "sg:address":"Naglerstr. 4",
    "sg:city":"Pforzheim",
    "sg:phone":"+49 7231/955173",
    "sg:postcode":"75175",
    "sg:province":"Baden-W\u00fcrttemberg",
    "wof:name":"Wilhelm Sch\u00e4fer Gmbh & Co.",
    "wof:placetype":"venue"
},
  "geometry": {"coordinates":[8.7231760025,48.8977279663],"type":"Point"}
}