{
  "type": "Feature",
  "properties": {
    "iso:country":"DE",
    "sg:address":"Hauptstr. 107",
    "sg:city":"Lunzenau",
    "sg:phone":"+49 37383/6515",
    "sg:postcode":"09328",
    "sg:province":"Sachsen",
    "wof:name":"Siegfried Lindner",
    "wof:placetype":"venue"
},
  "geometry": {"coordinates":[12.7059698105,50.970741272],"type":"Point"}
}