{
  "type": "Feature",
  "properties": {
    "iso:country":"DE",
    "sg:address":"Amtmannstr. 1",
    "sg:city":"Lichtenau",
    "sg:postcode":"09244",
    "sg:province":"Sachsen",
    "wof:name":"Gemotec Gmbh & Co. Kg",
    "wof:placetype":"venue"
},
  "geometry": {"coordinates":[12.9581298828,50.9083595276],"type":"Point"}
}