{
  "type": "Feature",
  "properties": {
    "iso:country":"DE",
    "sg:address":"Gotenstr. 13",
    "sg:city":"Hamburg",
    "sg:phone":"+49 40/2388280",
    "sg:postcode":"20097",
    "sg:province":"Hamburg",
    "wof:name":"Meier Und Meinecke Rechtsanw\u00e4lte",
    "wof:placetype":"venue"
},
  "geometry": {"coordinates":[10.0242052078,53.5493812561],"type":"Point"}
}