{
  "type": "Feature",
  "properties": {
    "iso:country":"DE",
    "sg:address":"Am Erlen 2",
    "sg:city":"Allendorf",
    "sg:phone":"+49 6407/6416",
    "sg:postcode":"35469",
    "sg:province":"Hessen",
    "wof:name":"Heinz Schnell",
    "wof:placetype":"venue"
},
  "geometry": {"coordinates":[8.823044,50.671124],"type":"Point"}
}