{
  "type": "Feature",
  "properties": {
    "iso:country":"DE",
    "sg:address":"Bahnhofstr. 28",
    "sg:city":"Ortrand",
    "sg:phone":"+49 35755/50232",
    "sg:postcode":"01990",
    "sg:province":"Brandenburg",
    "wof:name":"H. Grafe",
    "wof:placetype":"venue"
},
  "geometry": {"coordinates":[13.760745,51.374538],"type":"Point"}
}