{
  "type": "Feature",
  "properties": {
    "iso:country":"DE",
    "sg:address":"Weckinghauser Weg 27",
    "sg:city":"Erwitte",
    "sg:postcode":"59597",
    "sg:province":"Nordrhein-Westfalen",
    "wof:name":"Logo Massivhaus Gmbh",
    "wof:placetype":"venue"
},
  "geometry": {"coordinates":[8.3314027786,51.6191215515],"type":"Point"}
}