{
  "type": "Feature",
  "properties": {
    "iso:country":"DE",
    "sg:address":"Rossmarkt 12",
    "sg:city":"Frankfurt am Main",
    "sg:phone":"+49 30/203080",
    "sg:postcode":"60311",
    "sg:province":"Hessen",
    "wof:name":"Association Of German Chambers Of Commerce And Industry",
    "wof:placetype":"venue"
},
  "geometry": {"coordinates":[13.405571,52.514523],"type":"Point"}
}