{
  "type": "Feature",
  "properties": {
    "iso:country":"DE",
    "sg:address":"Roemerstr. 1",
    "sg:city":"Trierweiler",
    "sg:phone":"+49 651",
    "sg:postcode":"54311",
    "sg:province":"Rheinland-Pfalz",
    "wof:name":"Autohaus Buschmann Gmbh & Co Kg",
    "wof:placetype":"venue"
},
  "geometry": {"coordinates":[6.5906939507,49.7699356079],"type":"Point"}
}