{
  "type": "Feature",
  "properties": {
    "iso:country":"DE",
    "sg:address":"Winkelstr. 32",
    "sg:city":"B\u00fcnde",
    "sg:phone":"+49 5223/574444",
    "sg:postcode":"32257",
    "sg:province":"Nordrhein-Westfalen",
    "wof:name":"Plum & Partner Werkzeugmaschinen Gmbh",
    "wof:placetype":"venue"
},
  "geometry": {"coordinates":[8.582233,52.192612],"type":"Point"}
}