{
  "type": "Feature",
  "properties": {
    "iso:country":"DE",
    "sg:address":"Oppenweher Str. 27",
    "sg:city":"Stemwede",
    "sg:postcode":"32351",
    "sg:province":"Nordrhein-Westfalen",
    "wof:name":"Bis Bauingenieurb\u00fcro Stemwede Gmbh",
    "wof:placetype":"venue"
},
  "geometry": {"coordinates":[8.5096702576,52.4636993408],"type":"Point"}
}