{
  "type": "Feature",
  "properties": {
    "iso:country":"DE",
    "sg:address":"Peulendorfer Str. 1 A",
    "sg:city":"Sche\u00dflitz",
    "sg:phone":"+49 9542/1666",
    "sg:postcode":"96110",
    "sg:province":"Bayern",
    "wof:name":"Praxis Dr. Med. Lebert Und Dr. Med. Schumm",
    "wof:placetype":"venue"
},
  "geometry": {"coordinates":[11.0325546265,49.9742622375],"type":"Point"}
}