{
  "type": "Feature",
  "properties": {
    "iso:country":"DE",
    "sg:address":"Uhlandstr. 151",
    "sg:city":"Berlin",
    "sg:phone":"+49 30/8850855",
    "sg:postcode":"10719",
    "sg:province":"Berlin",
    "wof:name":"Andreas Czerwinka Immobilienmakler",
    "wof:placetype":"venue"
},
  "geometry": {"coordinates":[13.3245172501,52.4973068237],"type":"Point"}
}