{
  "type": "Feature",
  "properties": {
    "iso:country":"DE",
    "sg:address":"Industriestr 10",
    "sg:city":"Erzhausen",
    "sg:phone":"+49 6150/85290",
    "sg:postcode":"64390",
    "sg:province":"Hessen",
    "wof:name":"Theodor Schaeben",
    "wof:placetype":"venue"
},
  "geometry": {"coordinates":[8.6497850418,49.9480857849],"type":"Point"}
}