{
  "type": "Feature",
  "properties": {
    "iso:country":"DE",
    "sg:address":"Schleusenstr. 28",
    "sg:city":"Kleinwallstadt",
    "sg:phone":"+49 6022/2914",
    "sg:postcode":"63839",
    "sg:province":"Bayern",
    "wof:name":"Hans Stegmann Binnenschiffahrtsunternehmen",
    "wof:placetype":"venue"
},
  "geometry": {"coordinates":[9.16201,49.866714],"type":"Point"}
}