{
  "type": "Feature",
  "properties": {
    "iso:country":"DE",
    "sg:address":"Curiestr. 15",
    "sg:city":"Lippstadt",
    "sg:phone":"+49 2941/12836",
    "sg:postcode":"59557",
    "sg:province":"Nordrhein-Westfalen",
    "wof:name":"F.w. Sommer Gmbh",
    "wof:placetype":"venue"
},
  "geometry": {"coordinates":[8.329295,51.657593],"type":"Point"}
}