{
  "type": "Feature",
  "properties": {
    "iso:country":"DE",
    "sg:address":"Kreuzstr. 59",
    "sg:city":"Kaarst",
    "sg:phone":"+49 2131/602373",
    "sg:postcode":"41564",
    "sg:province":"Nordrhein-Westfalen",
    "wof:name":"Friedrich P\u00f6tt",
    "wof:placetype":"venue"
},
  "geometry": {"coordinates":[6.625334,51.213699],"type":"Point"}
}