{
  "type": "Feature",
  "properties": {
    "iso:country":"DE",
    "sg:address":"Osdorfer Weg 27",
    "sg:city":"Hamburg",
    "sg:phone":"+49 40/8992931",
    "sg:postcode":"22607",
    "sg:province":"Hamburg",
    "wof:name":"Lothar Brusdeilins Ingenieur",
    "wof:placetype":"venue"
},
  "geometry": {"coordinates":[9.8951654434,53.565864563],"type":"Point"}
}