{
  "type": "Feature",
  "properties": {
    "iso:country":"DE",
    "sg:address":"Benseb\u00fclter Weg 8",
    "sg:city":"Varrel",
    "sg:phone":"+49 4274/673",
    "sg:postcode":"27259",
    "sg:province":"Niedersachsen",
    "wof:name":"G\u00fcnter Kemmann",
    "wof:placetype":"venue"
},
  "geometry": {"coordinates":[8.729436,52.608135],"type":"Point"}
}