{
  "type": "Feature",
  "properties": {
    "iso:country":"DE",
    "sg:address":"Gau\u00dfstr. 7",
    "sg:city":"Peine",
    "sg:phone":"+49 4951/7117061",
    "sg:postcode":"31224",
    "sg:province":"Niedersachsen",
    "wof:name":"Goy & Balke Maschinenbau Gmbh",
    "wof:placetype":"venue"
},
  "geometry": {"coordinates":[10.263648,52.316189],"type":"Point"}
}