{
  "type": "Feature",
  "properties": {
    "iso:country":"DE",
    "sg:address":"Treptower Str. 115",
    "sg:city":"Berlin",
    "sg:postcode":"12043",
    "sg:province":"Berlin",
    "wof:name":"Aldi Gmbh & Co. Kg",
    "wof:placetype":"venue"
},
  "geometry": {"coordinates":[13.4355745316,52.4806632996],"type":"Point"}
}