{
  "type": "Feature",
  "properties": {
    "iso:country":"DE",
    "sg:address":"Mitteltorstr. 28",
    "sg:city":"Marktheidenfeld",
    "sg:phone":"+49 9391/916532",
    "sg:postcode":"97828",
    "sg:province":"Bayern",
    "wof:name":"Treppchen",
    "wof:placetype":"venue"
},
  "geometry": {"coordinates":[9.6020488739,49.8434410095],"type":"Point"}
}