{
  "type": "Feature",
  "properties": {
    "iso:country":"DE",
    "sg:address":"Merianstr. 36-38",
    "sg:city":"N\u00fcrnberg",
    "sg:postcode":"90409",
    "sg:province":"Bayern",
    "wof:name":"Albert G\u00fcnther Schreinerei Und Innenausbau Gmbh",
    "wof:placetype":"venue"
},
  "geometry": {"coordinates":[11.101762,49.472729],"type":"Point"}
}