{
  "type": "Feature",
  "properties": {
    "iso:country":"DE",
    "sg:address":"Dorfstr. 18",
    "sg:city":"Piskaborn",
    "sg:phone":"+49 34782/20631",
    "sg:postcode":"06343",
    "sg:province":"Sachsen-Anhalt",
    "wof:name":"W. Ulrich",
    "wof:placetype":"venue"
},
  "geometry": {"coordinates":[11.368274,51.584663],"type":"Point"}
}