{
  "type": "Feature",
  "properties": {
    "iso:country":"DE",
    "sg:address":"Dr.-Fritz-Wiede-Str. 9",
    "sg:city":"Naila",
    "sg:phone":"+49 9282/982311",
    "sg:postcode":"95119",
    "sg:province":"Bayern",
    "wof:name":"Richard Ultsch Heizungsbau Gmbh",
    "wof:placetype":"venue"
},
  "geometry": {"coordinates":[11.689119339,50.3622207642],"type":"Point"}
}