{
  "type": "Feature",
  "properties": {
    "iso:country":"DE",
    "sg:address":"Am M\u00fchlbach 10",
    "sg:city":"Altshausen",
    "sg:phone":"+49 7584/811",
    "sg:postcode":"88361",
    "sg:province":"Baden-W\u00fcrttemberg",
    "wof:name":"Barth Gmbh",
    "wof:placetype":"venue"
},
  "geometry": {"coordinates":[9.5570163727,47.913684845],"type":"Point"}
}