{
  "type": "Feature",
  "properties": {
    "iso:country":"DE",
    "sg:address":"Theodor-Dierlamm-Str. 19",
    "sg:city":"Calw",
    "sg:phone":"+49 7051/50727",
    "sg:postcode":"75365",
    "sg:province":"Baden-W\u00fcrttemberg",
    "wof:name":"Siegfried Rentschler",
    "wof:placetype":"venue"
},
  "geometry": {"coordinates":[8.7000684738,48.7256584167],"type":"Point"}
}