{
  "type": "Feature",
  "properties": {
    "iso:country":"DE",
    "sg:address":"Kirschweg 32",
    "sg:city":"K\u00f6ln",
    "sg:phone":"+49 2203/81089",
    "sg:postcode":"51143",
    "sg:province":"Nordrhein-Westfalen",
    "wof:name":"Heinz Heyermann",
    "wof:placetype":"venue"
},
  "geometry": {"coordinates":[7.054857,50.86623],"type":"Point"}
}