{
  "type": "Feature",
  "properties": {
    "iso:country":"DE",
    "sg:address":"Feilitzschstr. 15",
    "sg:city":"M\u00fcnchen",
    "sg:postcode":"80802",
    "sg:province":"Bayern",
    "wof:name":"4con & Gesellschaft F\u00fcr Marketing- Und Software-",
    "wof:placetype":"venue"
},
  "geometry": {"coordinates":[11.5893802643,48.1612663269],"type":"Point"}
}