{
  "type": "Feature",
  "properties": {
    "iso:country":"DE",
    "sg:address":"97355",
    "sg:city":"Abtswind",
    "sg:phone":"+49 9383/300",
    "sg:postcode":"97355",
    "sg:province":"Bayern",
    "wof:name":"Haus Des Gastes",
    "wof:placetype":"venue"
},
  "geometry": {"coordinates":[10.3745613098,49.7707138062],"type":"Point"}
}