{
  "type": "Feature",
  "properties": {
    "iso:country":"DE",
    "sg:address":"Derentaler Str. 6",
    "sg:city":"F\u00fcrstenberg",
    "sg:phone":"+49 5271/4174",
    "sg:postcode":"37699",
    "sg:province":"Niedersachsen",
    "wof:name":"Gudrun Schulze",
    "wof:placetype":"venue"
},
  "geometry": {"coordinates":[9.4011793137,51.7290382385],"type":"Point"}
}