{
  "type": "Feature",
  "properties": {
    "iso:country":"DE",
    "sg:address":"Werrestr. 117",
    "sg:city":"Herford",
    "sg:phone":"+49 5221/61010",
    "sg:postcode":"32049",
    "sg:province":"Nordrhein-Westfalen",
    "wof:name":"Meyer_feuerl\u00f6schger\u00e4te Dieter Niestrath Gmbh",
    "wof:placetype":"venue"
},
  "geometry": {"coordinates":[8.6752796173,52.1312484741],"type":"Point"}
}