{
  "type": "Feature",
  "properties": {
    "iso:country":"DE",
    "sg:address":"D\u00fcsseldorfer Str. 126",
    "sg:city":"Viersen",
    "sg:phone":"+49 2162/80794",
    "sg:postcode":"41749",
    "sg:province":"Nordrhein-Westfalen",
    "wof:name":"Rwr Natur- Und Betonwerkstein Gmbh",
    "wof:placetype":"venue"
},
  "geometry": {"coordinates":[6.37542,51.2752],"type":"Point"}
}