{
  "type": "Feature",
  "properties": {
    "iso:country":"DE",
    "sg:address":"Jennerstr. 32",
    "sg:city":"M\u00fcnchen",
    "sg:phone":"+49 89/8128144",
    "sg:postcode":"80999",
    "sg:province":"Bayern",
    "wof:name":"Natrisana Gmbh Vertrieb Von Naturprodukten",
    "wof:placetype":"venue"
},
  "geometry": {"coordinates":[11.4437932968,48.1810913086],"type":"Point"}
}