{
  "type": "Feature",
  "properties": {
    "iso:country":"DE",
    "sg:address":"Kramerstr 12::",
    "sg:city":"Hanau",
    "sg:postcode":"63450",
    "sg:province":"Hessen",
    "wof:name":"Volksbank-raiffeisenbank Hanau Eg",
    "wof:placetype":"venue"
},
  "geometry": {"coordinates":[8.915061,50.133259],"type":"Point"}
}