{
  "type": "Feature",
  "properties": {
    "iso:country":"DE",
    "sg:address":"Reuschstr. 34",
    "sg:city":"Heiningen",
    "sg:phone":"+49 7161/948850",
    "sg:postcode":"73092",
    "sg:province":"Baden-W\u00fcrttemberg",
    "wof:name":"Horst Mohring",
    "wof:placetype":"venue"
},
  "geometry": {"coordinates":[9.6480426788,48.6565361023],"type":"Point"}
}