{
  "type": "Feature",
  "properties": {
    "iso:country":"DE",
    "sg:address":"m\u00fchlenstr. 51",
    "sg:city":"Melle",
    "sg:postcode":"49324",
    "sg:province":"Niedersachsen",
    "wof:name":"Else-lichtspiele",
    "wof:placetype":"venue"
},
  "geometry": {"coordinates":[8.341319,52.205711],"type":"Point"}
}