{
  "type": "Feature",
  "properties": {
    "iso:country":"DE",
    "sg:address":"Bachstr. 3",
    "sg:city":"Weilm\u00fcnster",
    "sg:phone":"+49 6475/8072",
    "sg:postcode":"35789",
    "sg:province":"Hessen",
    "wof:name":"Alfred Jung Gmbh",
    "wof:placetype":"venue"
},
  "geometry": {"coordinates":[8.3378791809,50.3995132446],"type":"Point"}
}