{
  "type": "Feature",
  "properties": {
    "iso:country":"DE",
    "sg:address":"Albert-Einstein-Str. 6",
    "sg:city":"Naumburg",
    "sg:phone":"+49 3445/702700",
    "sg:postcode":"06618",
    "sg:province":"Sachsen-Anhalt",
    "wof:name":"Taxi-unternehmen Boost",
    "wof:placetype":"venue"
},
  "geometry": {"coordinates":[11.8147392273,51.1599693298],"type":"Point"}
}