{
  "type": "Feature",
  "properties": {
    "iso:country":"DE",
    "sg:address":"Wilhelmstr. 27",
    "sg:city":"Weinheim",
    "sg:phone":"+49 6201/63708",
    "sg:postcode":"69469",
    "sg:province":"Baden-W\u00fcrttemberg",
    "wof:name":"G. Noe",
    "wof:placetype":"venue"
},
  "geometry": {"coordinates":[8.672853,49.556641],"type":"Point"}
}