{
  "type": "Feature",
  "properties": {
    "iso:country":"DE",
    "sg:address":"Achterweg 43",
    "sg:city":"Pr\u00fcm",
    "sg:phone":"+49 6551/2600",
    "sg:postcode":"54595",
    "sg:province":"Rheinland-Pfalz",
    "wof:name":"Gerhard Linke Masseur",
    "wof:placetype":"venue"
},
  "geometry": {"coordinates":[6.414491,50.206261],"type":"Point"}
}