{
  "type": "Feature",
  "properties": {
    "iso:country":"DE",
    "sg:address":"Sudenburger Wuhne 486",
    "sg:city":"Magdeburg",
    "sg:postcode":"39116",
    "sg:province":"Sachsen-Anhalt",
    "wof:name":"Amitec Automatisierungs- Und Maschineninstandsetzungs-gmbh",
    "wof:placetype":"venue"
},
  "geometry": {"coordinates":[11.5837402344,52.1177978516],"type":"Point"}
}