{
  "type": "Feature",
  "properties": {
    "iso:country":"DE",
    "sg:address":"Neustr. 166",
    "sg:city":"Senheim",
    "sg:phone":"+49 2673/4533",
    "sg:postcode":"56820",
    "sg:province":"Rheinland-Pfalz",
    "wof:name":"Hans Berhard",
    "wof:placetype":"venue"
},
  "geometry": {"coordinates":[7.2114400864,50.0844306946],"type":"Point"}
}