{
  "type": "Feature",
  "properties": {
    "iso:country":"DE",
    "sg:address":"Humboldtstr. 44",
    "sg:city":"Cottbus",
    "sg:postcode":"03050",
    "sg:province":"Brandenburg",
    "wof:name":"Dr. Med. Hans-peter Braun",
    "wof:placetype":"venue"
},
  "geometry": {"coordinates":[14.338477,51.742104],"type":"Point"}
}