{
  "type": "Feature",
  "properties": {
    "iso:country":"DE",
    "sg:address":"Moselstr. 23",
    "sg:city":"R\u00fcsselsheim",
    "sg:phone":"+49 6142/91010",
    "sg:postcode":"65428",
    "sg:province":"Hessen",
    "wof:name":"Weiss Verwaltungsges. Mbh",
    "wof:placetype":"venue"
},
  "geometry": {"coordinates":[8.416093,49.990929],"type":"Point"}
}