{
  "type": "Feature",
  "properties": {
    "iso:country":"DE",
    "sg:address":"Burgstr. 29",
    "sg:city":"L\u00f6bej\u00fcn",
    "sg:phone":"+49 34603/78271",
    "sg:postcode":"06193",
    "sg:province":"Sachsen-Anhalt",
    "wof:name":"Ristorante Pizzeria Crispianello",
    "wof:placetype":"venue"
},
  "geometry": {"coordinates":[11.9033403397,51.6357727051],"type":"Point"}
}