{
  "type": "Feature",
  "properties": {
    "iso:country":"DE",
    "sg:address":"Bornwiesenweg 12",
    "sg:city":"Frankfurt",
    "sg:phone":"+49 69/599659",
    "sg:postcode":"60322",
    "sg:province":"Hessen",
    "wof:name":"B. Hahn",
    "wof:placetype":"venue"
},
  "geometry": {"coordinates":[8.6790876389,50.1220359802],"type":"Point"}
}