{
  "type": "Feature",
  "properties": {
    "iso:country":"DE",
    "sg:address":"Gartenstr. 15",
    "sg:city":"Reutlingen",
    "sg:phone":"+49 7121/334522",
    "sg:postcode":"72764",
    "sg:province":"Baden-W\u00fcrttemberg",
    "wof:name":"Renate Quast Rechtsanw\u00e4ltin",
    "wof:placetype":"venue"
},
  "geometry": {"coordinates":[9.2124214172,48.4939537048],"type":"Point"}
}