{
  "type": "Feature",
  "properties": {
    "iso:country":"DE",
    "sg:address":"Humboldtstr. 51",
    "sg:city":"Hamburg",
    "sg:phone":"+49 40/2201353",
    "sg:postcode":"22083",
    "sg:province":"Hamburg",
    "wof:name":"Inv Industrien\u00e4hmaschinen Vertriebs Gmbh",
    "wof:placetype":"venue"
},
  "geometry": {"coordinates":[10.025220871,53.5739097595],"type":"Point"}
}