{
  "type": "Feature",
  "properties": {
    "iso:country":"DE",
    "sg:address":"Graf-P\u00fcckler-Str. 6",
    "sg:city":"Gaildorf",
    "sg:phone":"+49 7971/8987",
    "sg:postcode":"74405",
    "sg:province":"Baden-W\u00fcrttemberg",
    "wof:name":"\u00cav. Sozialstation",
    "wof:placetype":"venue"
},
  "geometry": {"coordinates":[9.767145,49.00053],"type":"Point"}
}