{
  "type": "Feature",
  "properties": {
    "iso:country":"DE",
    "sg:address":"Sontheimer Str. 12",
    "sg:city":"Sontheim",
    "sg:postcode":"89567",
    "sg:province":"Baden-W\u00fcrttemberg",
    "wof:name":"Raiffeisenbank Niedertaufkirchen Eg",
    "wof:placetype":"venue"
},
  "geometry": {"coordinates":[12.55103,48.330296],"type":"Point"}
}