{
  "type": "Feature",
  "properties": {
    "iso:country":"DE",
    "sg:address":"Clayallee 337",
    "sg:city":"Berlin",
    "sg:phone":"+49 30/8011202",
    "sg:postcode":"14169",
    "sg:province":"Berlin",
    "wof:name":"Eberhard Hilliges Glas- Und Porzellanwaren",
    "wof:placetype":"venue"
},
  "geometry": {"coordinates":[13.2613515854,52.437210083],"type":"Point"}
}