{
  "type": "Feature",
  "properties": {
    "iso:country":"DE",
    "sg:address":"G-F-Steinmeyer-Str 3",
    "sg:city":"Oettingen",
    "sg:phone":"+49 9082/2011",
    "sg:postcode":"86732",
    "sg:province":"Bayern",
    "wof:name":"G. F. Steinmeyer Gmbh & Co. Kg",
    "wof:placetype":"venue"
},
  "geometry": {"coordinates":[10.5764112473,48.9453849792],"type":"Point"}
}