{
  "type": "Feature",
  "properties": {
    "iso:country":"DE",
    "sg:address":"Flothender Str. 59",
    "sg:city":"Nettetal",
    "sg:phone":"+49 2153/6430",
    "sg:postcode":"41334",
    "sg:province":"Nordrhein-Westfalen",
    "wof:name":"Hans Christians",
    "wof:placetype":"venue"
},
  "geometry": {"coordinates":[6.267402,51.301865],"type":"Point"}
}