{
  "type": "Feature",
  "properties": {
    "iso:country":"DE",
    "sg:address":"Altinger Str. 46",
    "sg:city":"Schliengen",
    "sg:phone":"+49 7635/1227",
    "sg:postcode":"79418",
    "sg:province":"Baden-W\u00fcrttemberg",
    "wof:name":"R\u00f6cker Zimmerei Kg",
    "wof:placetype":"venue"
},
  "geometry": {"coordinates":[7.5838589668,47.7532234192],"type":"Point"}
}