{
  "type": "Feature",
  "properties": {
    "iso:country":"DE",
    "sg:address":"Deutschenbaurstr. 20",
    "sg:city":"Augsburg",
    "sg:phone":"+49 821/526666",
    "sg:postcode":"86157",
    "sg:province":"Bayern",
    "wof:name":"Bar Und Diskothek Jazz House",
    "wof:placetype":"venue"
},
  "geometry": {"coordinates":[10.866282,48.367088],"type":"Point"}
}