{
  "type": "Feature",
  "properties": {
    "iso:country":"DE",
    "sg:address":"Osterende 19",
    "sg:city":"Husum",
    "sg:postcode":"25813",
    "sg:province":"Schleswig-Holstein",
    "wof:name":"Ehsa Handels Gmbh",
    "wof:placetype":"venue"
},
  "geometry": {"coordinates":[9.058071,54.478699],"type":"Point"}
}