{
  "type": "Feature",
  "properties": {
    "iso:country":"DE",
    "sg:address":"Hauptstr. 41",
    "sg:city":"Birkenwerder",
    "sg:postcode":"16547",
    "sg:province":"Brandenburg",
    "wof:name":"Eisenwaren Werkzeuge",
    "wof:placetype":"venue"
},
  "geometry": {"coordinates":[13.2809200287,52.689201355],"type":"Point"}
}