{
  "type": "Feature",
  "properties": {
    "iso:country":"DE",
    "sg:address":"Memminger Str. 69",
    "sg:city":"Altenstadt",
    "sg:phone":"+49 8337/235",
    "sg:postcode":"89281",
    "sg:province":"Bayern",
    "wof:name":"Mangold",
    "wof:placetype":"venue"
},
  "geometry": {"coordinates":[10.1134567261,48.1611061096],"type":"Point"}
}