{
  "type": "Feature",
  "properties": {
    "iso:country":"DE",
    "sg:address":"Hauptstr. 20",
    "sg:city":"Stadtsteinach",
    "sg:phone":"+49 9225/216",
    "sg:postcode":"95346",
    "sg:province":"Bayern",
    "wof:name":"B. Riemer",
    "wof:placetype":"venue"
},
  "geometry": {"coordinates":[11.503665,50.162899],"type":"Point"}
}