{
  "type": "Feature",
  "properties": {
    "iso:country":"DE",
    "sg:address":"Beethovenstr. 14",
    "sg:city":"Beilstein",
    "sg:phone":"+49 7062/5255",
    "sg:postcode":"71717",
    "sg:province":"Baden-W\u00fcrttemberg",
    "wof:name":"Dr. Med. B\u00e4rbel Epperlein \u00c4rztin F\u00fcr Allgemeinmedizin",
    "wof:placetype":"venue"
},
  "geometry": {"coordinates":[9.3081111908,49.0420646667],"type":"Point"}
}