{
  "type": "Feature",
  "properties": {
    "iso:country":"DE",
    "sg:address":"Beerenbrouckstr. 62b",
    "sg:city":"Geldern",
    "sg:phone":"+49 2831/3685",
    "sg:postcode":"47608",
    "sg:province":"Nordrhein-Westfalen",
    "wof:name":"Theo Devers",
    "wof:placetype":"venue"
},
  "geometry": {"coordinates":[6.376554,51.548672],"type":"Point"}
}