{
  "type": "Feature",
  "properties": {
    "iso:country":"DE",
    "sg:address":"Langenbochumer Str. 174",
    "sg:city":"Herten",
    "sg:phone":"+49 2366/53402",
    "sg:postcode":"45701",
    "sg:province":"Nordrhein-Westfalen",
    "wof:name":"Pflanzencenter Gottschling E. Kfm.",
    "wof:placetype":"venue"
},
  "geometry": {"coordinates":[7.121729,51.613052],"type":"Point"}
}