{
  "type": "Feature",
  "properties": {
    "iso:country":"DE",
    "sg:address":"Birkenstr. 13",
    "sg:city":"Grasbrunn",
    "sg:phone":"+49 89/4604619",
    "sg:postcode":"85630",
    "sg:province":"Bayern",
    "wof:name":"Werner Seibold",
    "wof:placetype":"venue"
},
  "geometry": {"coordinates":[11.760071,48.093952],"type":"Point"}
}