{
  "type": "Feature",
  "properties": {
    "iso:country":"DE",
    "sg:address":"Natinger Weg 4",
    "sg:city":"Borgentreich",
    "sg:phone":"+49 5645/74525",
    "sg:postcode":"34434",
    "sg:province":"Nordrhein-Westfalen",
    "wof:name":"Karl-heinz Pauls",
    "wof:placetype":"venue"
},
  "geometry": {"coordinates":[9.254491806,51.6223258972],"type":"Point"}
}