{
  "type": "Feature",
  "properties": {
    "iso:country":"DE",
    "sg:address":"Glei\u00dfende Marter 15",
    "sg:city":"Bad Windsheim",
    "sg:phone":"+49 9841/4609",
    "sg:postcode":"91438",
    "sg:province":"Bayern",
    "wof:name":"Gefl\u00fcgelzuchtverein Klaus Billenstein",
    "wof:placetype":"venue"
},
  "geometry": {"coordinates":[10.406247139,49.5049095154],"type":"Point"}
}