{
  "type": "Feature",
  "properties": {
    "iso:country":"DE",
    "sg:address":"Beim Retteich 14",
    "sg:city":"L\u00fcbeck",
    "sg:phone":"+49 451/8714660",
    "sg:postcode":"23558",
    "sg:province":"Schleswig-Holstein",
    "wof:name":"Restaurant Endstation",
    "wof:placetype":"venue"
},
  "geometry": {"coordinates":[10.6687707901,53.8661384583],"type":"Point"}
}