{
  "type": "Feature",
  "properties": {
    "iso:country":"DE",
    "sg:address":"Stebbacher Str. 3",
    "sg:city":"Eppingen",
    "sg:phone":"+49 7262/5907",
    "sg:postcode":"75031",
    "sg:province":"Baden-W\u00fcrttemberg",
    "wof:name":"Rose Steffen",
    "wof:placetype":"venue"
},
  "geometry": {"coordinates":[8.942617,49.168896],"type":"Point"}
}