{
  "type": "Feature",
  "properties": {
    "iso:country":"DE",
    "sg:address":"Im Stecket 8",
    "sg:city":"Achern",
    "sg:phone":"+49 7841/1863",
    "sg:postcode":"77855",
    "sg:province":"Baden-W\u00fcrttemberg",
    "wof:name":"W. Schneider",
    "wof:placetype":"venue"
},
  "geometry": {"coordinates":[8.044276,48.650013],"type":"Point"}
}