{
  "type": "Feature",
  "properties": {
    "iso:country":"DE",
    "sg:address":"Quellenstr. 51",
    "sg:city":"Remagen",
    "sg:phone":"+49 2642/44596",
    "sg:postcode":"53424",
    "sg:province":"Rheinland-Pfalz",
    "wof:name":"Rolf Etscheid",
    "wof:placetype":"venue"
},
  "geometry": {"coordinates":[7.27111,50.560112],"type":"Point"}
}