{
  "type": "Feature",
  "properties": {
    "iso:country":"DE",
    "sg:address":"H\u00fclser Str. 437",
    "sg:city":"Krefeld",
    "sg:phone":"+49 2151/755569",
    "sg:postcode":"47803",
    "sg:province":"Nordrhein-Westfalen",
    "wof:name":"Theo Kleinkauertz Gmbh",
    "wof:placetype":"venue"
},
  "geometry": {"coordinates":[6.538196,51.351555],"type":"Point"}
}