{
  "type": "Feature",
  "properties": {
    "iso:country":"DE",
    "sg:address":"Wiedenseil 1",
    "sg:city":"Singen",
    "sg:phone":"+49 7731/66528",
    "sg:postcode":"78224",
    "sg:province":"Baden-W\u00fcrttemberg",
    "wof:name":"Schneider & Anghel Gmbh",
    "wof:placetype":"venue"
},
  "geometry": {"coordinates":[8.8676204681,47.7571105957],"type":"Point"}
}