{
  "type": "Feature",
  "properties": {
    "iso:country":"DE",
    "sg:address":"Schr\u00f6tteringksweg 19",
    "sg:city":"Hamburg",
    "sg:phone":"+49 40/7211061",
    "sg:postcode":"22085",
    "sg:province":"Hamburg",
    "wof:name":"Royal-pr\u00e4sente Verkaufs Gmbh",
    "wof:placetype":"venue"
},
  "geometry": {"coordinates":[10.0232257843,53.5703926086],"type":"Point"}
}