{
  "type": "Feature",
  "properties": {
    "iso:country":"DE",
    "sg:address":"Fluplatzstrasse 39",
    "sg:city":"Nordhorn/Klausheide",
    "sg:phone":"+49 5921/971110",
    "sg:postcode":"48531",
    "sg:province":"Niedersachsen",
    "wof:name":"Nordhorn Karting",
    "wof:placetype":"venue"
},
  "geometry": {"coordinates":[7.1675629616,52.4577598572],"type":"Point"}
}