{
  "type": "Feature",
  "properties": {
    "iso:country":"DE",
    "sg:address":"88605",
    "sg:city":"Sauldorf",
    "sg:phone":"+49 7578/562",
    "sg:postcode":"88605",
    "sg:province":"Baden-W\u00fcrttemberg",
    "wof:name":"Krone",
    "wof:placetype":"venue"
},
  "geometry": {"coordinates":[9.1072101593,47.9434356689],"type":"Point"}
}