{
  "type": "Feature",
  "properties": {
    "iso:country":"DE",
    "sg:address":"Stiftsbogen 142",
    "sg:city":"M\u00fcnchen",
    "sg:phone":"+49 89/7409621",
    "sg:postcode":"81375",
    "sg:province":"Bayern",
    "wof:name":"Yan Reisen Inh. Yan Frenkel E. K.",
    "wof:placetype":"venue"
},
  "geometry": {"coordinates":[11.4854898453,48.120464325],"type":"Point"}
}