{
  "type": "Feature",
  "properties": {
    "iso:country":"DE",
    "sg:address":"Bahnhofstr. 20",
    "sg:city":"Neu Wulmstorf",
    "sg:phone":"+49 40/7006133",
    "sg:postcode":"21629",
    "sg:province":"Niedersachsen",
    "wof:name":"Wolfgang Otten",
    "wof:placetype":"venue"
},
  "geometry": {"coordinates":[9.793841362,53.465839386],"type":"Point"}
}