{
  "type": "Feature",
  "properties": {
    "iso:country":"DE",
    "sg:address":"Bremer Str. 5",
    "sg:city":"S\u00fcstedt",
    "sg:phone":"+49 4252/4428",
    "sg:postcode":"27305",
    "sg:province":"Niedersachsen",
    "wof:name":"Gasthaus Puvogel Inh. Karin Wichmann",
    "wof:placetype":"venue"
},
  "geometry": {"coordinates":[8.9176607132,52.8340415955],"type":"Point"}
}