{
  "type": "Feature",
  "properties": {
    "iso:country":"DE",
    "sg:address":"Ludwigstr. 26",
    "sg:city":"Augsburg",
    "sg:phone":"+49 821/155099",
    "sg:postcode":"86152",
    "sg:province":"Bayern",
    "wof:name":"Oswald Silberhorn Ingenieur",
    "wof:placetype":"venue"
},
  "geometry": {"coordinates":[10.8935937881,48.3707695007],"type":"Point"}
}