{
  "type": "Feature",
  "properties": {
    "iso:country":"DE",
    "sg:address":"Vor der Reihe 18",
    "sg:city":"Petershagen",
    "sg:phone":"+49 5702/2122",
    "sg:postcode":"32469",
    "sg:province":"Nordrhein-Westfalen",
    "wof:name":"Manfred Rohs",
    "wof:placetype":"venue"
},
  "geometry": {"coordinates":[8.9882469177,52.3704833984],"type":"Point"}
}