{
  "type": "Feature",
  "properties": {
    "iso:country":"DE",
    "sg:address":"Kolpingstr. 23",
    "sg:city":"Kerken",
    "sg:phone":"+49 2833/6909",
    "sg:postcode":"47647",
    "sg:province":"Nordrhein-Westfalen",
    "wof:name":"Volksf\u00fcrsorge Versicherung Bernhard Post",
    "wof:placetype":"venue"
},
  "geometry": {"coordinates":[6.423459053,51.4434700012],"type":"Point"}
}