{
  "type": "Feature",
  "properties": {
    "iso:country":"DE",
    "sg:address":"Oberdorf 127",
    "sg:city":"Gro\u00dfr\u00fcckerswalde",
    "sg:phone":"+49 3735/22541",
    "sg:postcode":"09518",
    "sg:province":"Sachsen",
    "wof:name":"Windkraft Stephan & Partner Ohg",
    "wof:placetype":"venue"
},
  "geometry": {"coordinates":[13.135483,50.625286],"type":"Point"}
}