{
  "type": "Feature",
  "properties": {
    "iso:country":"DE",
    "sg:address":"Bertolt-Brecht-Str. 60",
    "sg:city":"N\u00fcrnberg",
    "sg:phone":"+49 911/8147021",
    "sg:postcode":"90471",
    "sg:province":"Bayern",
    "wof:name":"A. Und M. Carl Ing.-b\u00fcro",
    "wof:placetype":"venue"
},
  "geometry": {"coordinates":[11.122979,49.414379],"type":"Point"}
}