{
  "type": "Feature",
  "properties": {
    "iso:country":"DE",
    "sg:address":"Thomas-M\u00fcntzer-Str. 2",
    "sg:city":"Reichenbach",
    "sg:phone":"+49 35828/70331",
    "sg:postcode":"02894",
    "sg:province":"Sachsen",
    "wof:name":"Elke Kindler",
    "wof:placetype":"venue"
},
  "geometry": {"coordinates":[14.795572,51.142441],"type":"Point"}
}