{
  "type": "Feature",
  "properties": {
    "iso:country":"DE",
    "sg:address":"Ahrfeldstr. 72",
    "sg:city":"Essen",
    "sg:phone":"+49 201/261141",
    "sg:postcode":"45136",
    "sg:province":"Nordrhein-Westfalen",
    "wof:name":"Possinke Und Quarg",
    "wof:placetype":"venue"
},
  "geometry": {"coordinates":[7.042015,51.438465],"type":"Point"}
}