{
  "type": "Feature",
  "properties": {
    "iso:country":"DE",
    "sg:address":"Am Sonnenweg 33",
    "sg:city":"Stuttgart",
    "sg:phone":"+49 711/446645",
    "sg:postcode":"70619",
    "sg:province":"Baden-W\u00fcrttemberg",
    "wof:name":"Ec-werbung E. Clement",
    "wof:placetype":"venue"
},
  "geometry": {"coordinates":[9.2390527725,48.7494773865],"type":"Point"}
}