{
  "type": "Feature",
  "properties": {
    "iso:country":"DE",
    "sg:address":"Heidm\u00fchlenweg 53b",
    "sg:city":"Elmshorn",
    "sg:phone":"+49 4121/94688",
    "sg:postcode":"25336",
    "sg:province":"Schleswig-Holstein",
    "wof:name":"Renate Rudek",
    "wof:placetype":"venue"
},
  "geometry": {"coordinates":[9.652776,53.737316],"type":"Point"}
}