{
  "type": "Feature",
  "properties": {
    "iso:country":"DE",
    "sg:address":"Wilhelmstr. 5",
    "sg:city":"Hohenlockstedt",
    "sg:phone":"+49 4826/900",
    "sg:postcode":"25551",
    "sg:province":"Schleswig-Holstein",
    "wof:name":"Verena Reimers Masseurin",
    "wof:placetype":"venue"
},
  "geometry": {"coordinates":[9.618716,53.963196],"type":"Point"}
}