{
  "type": "Feature",
  "properties": {
    "iso:country":"DE",
    "sg:address":"Hauptstr. 24",
    "sg:city":"Weinsberg",
    "sg:phone":"+49 7134/8881",
    "sg:postcode":"74189",
    "sg:province":"Baden-W\u00fcrttemberg",
    "wof:name":"Pro Marketing Werbeagentur Gmbh",
    "wof:placetype":"venue"
},
  "geometry": {"coordinates":[9.286751,49.151356],"type":"Point"}
}