{
  "type": "Feature",
  "properties": {
    "iso:country":"DE",
    "sg:address":"Ringstr. 10",
    "sg:city":"Lauscha",
    "sg:phone":"+49 36702/20205",
    "sg:postcode":"98724",
    "sg:province":"Th\u00fcringen",
    "wof:name":"Falk Br\u00fcckner",
    "wof:placetype":"venue"
},
  "geometry": {"coordinates":[11.159548,50.482998],"type":"Point"}
}