{
  "type": "Feature",
  "properties": {
    "iso:country":"DE",
    "sg:address":"H\u00f6pfertsteig 12",
    "sg:city":"Berlin",
    "sg:phone":"+49 30/4028998",
    "sg:postcode":"13469",
    "sg:province":"Berlin",
    "wof:name":"Dr. L. Pahl",
    "wof:placetype":"venue"
},
  "geometry": {"coordinates":[13.355545,52.615814],"type":"Point"}
}