{
  "type": "Feature",
  "properties": {
    "iso:country":"DE",
    "sg:address":"Hammerschmiede 2",
    "sg:city":"Oberstaufen",
    "sg:phone":"+49 8386/2094",
    "sg:postcode":"87534",
    "sg:province":"Bayern",
    "wof:name":"Erwin J\u00f6rg",
    "wof:placetype":"venue"
},
  "geometry": {"coordinates":[10.0170459747,47.5424957275],"type":"Point"}
}