{
  "type": "Feature",
  "properties": {
    "iso:country":"DE",
    "sg:address":"Pennricher Str. 20",
    "sg:city":"Freital",
    "sg:phone":"+49 351/6502507",
    "sg:postcode":"01705",
    "sg:province":"Sachsen",
    "wof:name":"Mathias Schulz",
    "wof:placetype":"venue"
},
  "geometry": {"coordinates":[13.6345863342,51.0299377441],"type":"Point"}
}