{
  "type": "Feature",
  "properties": {
    "iso:country":"DE",
    "sg:address":"Schillerstr. 42",
    "sg:city":"D\u00fcsseldorf",
    "sg:phone":"+49 211/675435",
    "sg:postcode":"40237",
    "sg:province":"Nordrhein-Westfalen",
    "wof:name":"Dr. W. Miese Steuerberater",
    "wof:placetype":"venue"
},
  "geometry": {"coordinates":[6.8022651672,51.2358665466],"type":"Point"}
}