{
  "type": "Feature",
  "properties": {
    "iso:country":"DE",
    "sg:address":"Schwarzer Weg 95",
    "sg:city":"Inden",
    "sg:phone":"+49 4924/6599000",
    "sg:postcode":"52459",
    "sg:province":"Nordrhein-Westfalen",
    "wof:name":"Wellpappenwerk Lamersdorf Pb Marx Gmbh & Co Kg",
    "wof:placetype":"venue"
},
  "geometry": {"coordinates":[6.3541679382,50.8517951965],"type":"Point"}
}