{
  "type": "Feature",
  "properties": {
    "iso:country":"DE",
    "sg:address":"Merlerstr. 3",
    "sg:city":"Zell/Mosel",
    "sg:phone":"+49 6542/4391",
    "sg:postcode":"56851",
    "wof:name":"Jugend- Und Erwachsenenbildungswerk Zell/mosel",
    "wof:placetype":"venue"
},
  "geometry": {"coordinates":[7.17606,50.037121],"type":"Point"}
}