{
  "type": "Feature",
  "properties": {
    "iso:country":"DE",
    "sg:address":"Gro\u00dfe Str. 39",
    "sg:city":"Bodenwerder",
    "sg:phone":"+49 5533/1828",
    "sg:postcode":"37619",
    "sg:province":"Niedersachsen",
    "wof:name":"Erwin Framke Heilpraktiker",
    "wof:placetype":"venue"
},
  "geometry": {"coordinates":[9.5163383484,51.9783401489],"type":"Point"}
}