{
  "type": "Feature",
  "properties": {
    "iso:country":"DE",
    "sg:address":"Horstweg 2",
    "sg:city":"Elsterwerda",
    "sg:phone":"+49 3533",
    "sg:postcode":"04910",
    "sg:province":"Brandenburg",
    "wof:name":"Preisagentur,werbeagentur",
    "wof:placetype":"venue"
},
  "geometry": {"coordinates":[13.523691,51.444386],"type":"Point"}
}