{
  "type": "Feature",
  "properties": {
    "iso:country":"DE",
    "sg:address":"Gr\u00f6perstr. 14",
    "sg:city":"Magdeburg",
    "sg:phone":"+49 391/25623",
    "sg:postcode":"39124",
    "sg:province":"Sachsen-Anhalt",
    "wof:name":"Gebr. Garloff Gmbh",
    "wof:placetype":"venue"
},
  "geometry": {"coordinates":[11.643474,52.151291],"type":"Point"}
}