{
  "type": "Feature",
  "properties": {
    "iso:country":"DE",
    "sg:address":"Blumenstrasse 22",
    "sg:city":"Mannheim",
    "sg:phone":"+49 621/8414204",
    "sg:postcode":"68199",
    "sg:province":"Baden-W\u00fcrttemberg",
    "wof:name":"781 Siebenhunderteinundachtzig",
    "wof:placetype":"venue"
},
  "geometry": {"coordinates":[8.4925079346,49.4520874023],"type":"Point"}
}