{
  "type": "Feature",
  "properties": {
    "iso:country":"DE",
    "sg:address":"Bayreuther Str. 22",
    "sg:city":"Forchheim",
    "sg:phone":"+49 9191/727720",
    "sg:postcode":"91301",
    "sg:province":"Bayern",
    "wof:name":"Dea Tankstelle",
    "wof:placetype":"venue"
},
  "geometry": {"coordinates":[11.0808029175,49.7151641846],"type":"Point"}
}