{
  "type": "Feature",
  "properties": {
    "iso:country":"DE",
    "sg:address":"Pr\u00e4sidentenstr. 8",
    "sg:city":"Wildberg",
    "sg:phone":"+49 33928/327",
    "sg:postcode":"16845",
    "sg:province":"Brandenburg",
    "wof:name":"G. Pfannenberg",
    "wof:placetype":"venue"
},
  "geometry": {"coordinates":[12.629676,52.878246],"type":"Point"}
}