{
  "type": "Feature",
  "properties": {
    "iso:country":"DE",
    "sg:address":"Friedl\u00e4nder Str. 3",
    "sg:city":"Brunn",
    "sg:postcode":"17039",
    "sg:province":"Mecklenburg-Vorpommern",
    "wof:name":"Rinderland Gmbh & Co. Kg",
    "wof:placetype":"venue"
},
  "geometry": {"coordinates":[13.369389534,53.6677627563],"type":"Point"}
}