{
  "type": "Feature",
  "properties": {
    "iso:country":"DE",
    "sg:address":"Breitscheidstr. 105 c",
    "sg:city":"Rudolstadt",
    "sg:postcode":"07407",
    "sg:province":"Th\u00fcringen",
    "wof:name":"Sotech-sondermaschinen Und Technologie Gmbh",
    "wof:placetype":"venue"
},
  "geometry": {"coordinates":[11.328235,50.702152],"type":"Point"}
}