{
  "type": "Feature",
  "properties": {
    "iso:country":"DE",
    "sg:address":"Falkenberger Str. 9",
    "sg:city":"Wabern",
    "sg:phone":"+49 5681/2894",
    "sg:postcode":"34590",
    "sg:province":"Hessen",
    "wof:name":"Karl Thiel",
    "wof:placetype":"venue"
},
  "geometry": {"coordinates":[9.3815641403,51.0690612793],"type":"Point"}
}