{
  "type": "Feature",
  "properties": {
    "iso:country":"DE",
    "sg:address":"Im Biengarten 33",
    "sg:city":"Neustadt",
    "sg:phone":"+49 6321/68386",
    "sg:postcode":"67435",
    "sg:province":"Rheinland-Pfalz",
    "wof:name":"Karin Stump Steuerberaterin",
    "wof:placetype":"venue"
},
  "geometry": {"coordinates":[8.1541004181,49.3830947876],"type":"Point"}
}