{
  "type": "Feature",
  "properties": {
    "iso:country":"DE",
    "sg:address":"Friedrich-Bergius-Ring 44",
    "sg:city":"W\u00fcrzburg",
    "sg:phone":"+49 931/279810",
    "sg:postcode":"97076",
    "sg:province":"Bayern",
    "wof:name":"W\u00f6rle Druck- Und Verlags Gmbh",
    "wof:placetype":"venue"
},
  "geometry": {"coordinates":[10.001681,49.798832],"type":"Point"}
}