{
  "type": "Feature",
  "properties": {
    "iso:country":"DE",
    "sg:address":"S\u00fcdallee 34",
    "sg:city":"Trier",
    "sg:phone":"+49 651/970800",
    "sg:postcode":"54290",
    "sg:province":"Rheinland-Pfalz",
    "wof:name":"Karl-heinz Serwe Patenanwalt",
    "wof:placetype":"venue"
},
  "geometry": {"coordinates":[6.6347851753,49.750038147],"type":"Point"}
}