{
  "type": "Feature",
  "properties": {
    "iso:country":"DE",
    "sg:address":"Bischof-Ketteler-Str. 48",
    "sg:city":"M\u00fchlheim",
    "sg:phone":"+49 6108/66418",
    "sg:postcode":"63165",
    "sg:province":"Hessen",
    "wof:name":"Ketteler-apotheke",
    "wof:placetype":"venue"
},
  "geometry": {"coordinates":[8.856985,50.096176],"type":"Point"}
}