{
  "type": "Feature",
  "properties": {
    "iso:country":"DE",
    "sg:address":"Industriestr. 5-9",
    "sg:city":"Ettlingen",
    "sg:phone":"+49 8247/30070",
    "sg:postcode":"76275",
    "sg:province":"Baden-W\u00fcrttemberg",
    "wof:name":"Krafthand Verlag Walter Schulz Gmbh",
    "wof:placetype":"venue"
},
  "geometry": {"coordinates":[10.5980701447,48.0241508484],"type":"Point"}
}