{
  "type": "Feature",
  "properties": {
    "iso:country":"DE",
    "sg:address":"Zerbster Str. 7",
    "sg:city":"Lindau",
    "sg:phone":"+49 39246/9242",
    "sg:postcode":"39264",
    "sg:province":"Sachsen-Anhalt",
    "wof:name":"I. Sinast",
    "wof:placetype":"venue"
},
  "geometry": {"coordinates":[12.104486,52.035126],"type":"Point"}
}