{
  "type": "Feature",
  "properties": {
    "iso:country":"DE",
    "sg:address":"Ziegelstr. 64",
    "sg:city":"Vogt",
    "sg:phone":"+49 7529/2814",
    "sg:postcode":"88267",
    "sg:province":"Baden-W\u00fcrttemberg",
    "wof:name":"H. Und I. H\u00e4usle",
    "wof:placetype":"venue"
},
  "geometry": {"coordinates":[9.767512,47.768311],"type":"Point"}
}