{
  "type": "Feature",
  "properties": {
    "iso:country":"DE",
    "sg:address":"Promenade 6",
    "sg:city":"M\u00fcncheberg",
    "sg:phone":"+49 33432/73110",
    "sg:postcode":"15374",
    "sg:province":"Brandenburg",
    "wof:name":"Menze & Koch Ohg",
    "wof:placetype":"venue"
},
  "geometry": {"coordinates":[14.140734,52.501972],"type":"Point"}
}