{
  "type": "Feature",
  "properties": {
    "iso:country":"DE",
    "sg:address":"Pr\u00fcfeninger Str. 70",
    "sg:city":"Regensburg",
    "sg:phone":"+49 941/22190",
    "sg:postcode":"93049",
    "sg:province":"Bayern",
    "wof:name":"Blumen Speth Gmbh",
    "wof:placetype":"venue"
},
  "geometry": {"coordinates":[12.068623,49.016273],"type":"Point"}
}