{
  "type": "Feature",
  "properties": {
    "iso:country":"DE",
    "sg:address":"Hausner Str. 61",
    "sg:city":"Kirchheim",
    "sg:phone":"+49 89/9044570",
    "sg:postcode":"85551",
    "sg:province":"Bayern",
    "wof:name":"Joachim J\u00e4schke",
    "wof:placetype":"venue"
},
  "geometry": {"coordinates":[11.7480764389,48.1766281128],"type":"Point"}
}