{
  "type": "Feature",
  "properties": {
    "iso:country":"DE",
    "sg:address":"Breslauer Str. 41",
    "sg:city":"Kempten",
    "sg:phone":"+49 831/67552",
    "sg:postcode":"87437",
    "sg:province":"Bayern",
    "wof:name":"M. Und P. Schreiner",
    "wof:placetype":"venue"
},
  "geometry": {"coordinates":[10.3376159668,47.7157325745],"type":"Point"}
}