{
  "type": "Feature",
  "properties": {
    "iso:country":"DE",
    "sg:address":"Viehweg 2 a",
    "sg:city":"Lichtenfels",
    "sg:phone":"+49 5636/237",
    "sg:postcode":"35104",
    "sg:province":"Hessen",
    "wof:name":"Kamm Gmbh",
    "wof:placetype":"venue"
},
  "geometry": {"coordinates":[8.8098249435,51.1981277466],"type":"Point"}
}