{
  "type": "Feature",
  "properties": {
    "iso:country":"DE",
    "sg:address":"Mercedesstr. 3",
    "sg:city":"Stuttgart",
    "sg:phone":"+49 711/562019",
    "sg:postcode":"70372",
    "sg:province":"Baden-W\u00fcrttemberg",
    "wof:name":"S. Dembitzer Optische Erzeugnisse",
    "wof:placetype":"venue"
},
  "geometry": {"coordinates":[9.2140436172,48.8003463745],"type":"Point"}
}