{
  "type": "Feature",
  "properties": {
    "iso:country":"DE",
    "sg:address":"In der R\u00f6merstadt 172",
    "sg:city":"Frankfurt",
    "sg:phone":"+49 69/575059",
    "sg:postcode":"60439",
    "sg:province":"Hessen",
    "wof:name":"Hans Unnold",
    "wof:placetype":"venue"
},
  "geometry": {"coordinates":[8.627869,50.152168],"type":"Point"}
}