{
  "type": "Feature",
  "properties": {
    "iso:country":"DE",
    "sg:address":"N\u00fcrnberger Str. 14",
    "sg:city":"Karlsruhe",
    "sg:phone":"+49 721/892656",
    "sg:postcode":"76199",
    "sg:province":"Baden-W\u00fcrttemberg",
    "wof:name":"Bimbambino",
    "wof:placetype":"venue"
},
  "geometry": {"coordinates":[8.398065567,48.9844512939],"type":"Point"}
}