{
  "type": "Feature",
  "properties": {
    "iso:country":"DE",
    "sg:address":"Fischer\u00e4cker 2",
    "sg:city":"Flein",
    "sg:postcode":"74223",
    "sg:province":"Baden-W\u00fcrttemberg",
    "wof:name":"Fs-bau Konzeptions- Und Bautr\u00e4gerges. Mbh",
    "wof:placetype":"venue"
},
  "geometry": {"coordinates":[9.189908,49.102547],"type":"Point"}
}