{
  "type": "Feature",
  "properties": {
    "iso:country":"DE",
    "sg:address":"Taunusweg 1",
    "sg:city":"Illingen",
    "sg:phone":"+49 6825/3907",
    "sg:postcode":"66557",
    "sg:province":"Saarland",
    "wof:name":"Manfred Klein Krankengymnast",
    "wof:placetype":"venue"
},
  "geometry": {"coordinates":[7.068207,49.374352],"type":"Point"}
}