{
  "type": "Feature",
  "properties": {
    "iso:country":"DE",
    "sg:address":"Im Schlehert 14",
    "sg:city":"Karlsruhe",
    "sg:phone":"+49 721/5310477",
    "sg:postcode":"76187",
    "sg:province":"Baden-W\u00fcrttemberg",
    "wof:name":"Striegel-bau-gesellschaft Mbh",
    "wof:placetype":"venue"
},
  "geometry": {"coordinates":[8.3241014481,49.0181007385],"type":"Point"}
}