{
  "type": "Feature",
  "properties": {
    "iso:country":"DE",
    "sg:address":"Dickichtweg 3",
    "sg:city":"Hamburg",
    "sg:phone":"+49 40/60911998",
    "sg:postcode":"22359",
    "sg:province":"Hamburg",
    "wof:name":"Ads Textil Handel Gmbh",
    "wof:placetype":"venue"
},
  "geometry": {"coordinates":[10.153509,53.643955],"type":"Point"}
}