{
  "type": "Feature",
  "properties": {
    "iso:country":"DE",
    "sg:address":"Vennekenweg 60",
    "sg:city":"Raesfeld",
    "sg:phone":"+49 2865/10666",
    "sg:postcode":"46348",
    "sg:province":"Nordrhein-Westfalen",
    "wof:name":"F. Nagel Landwirtschaftl. Lohnbetrieb",
    "wof:placetype":"venue"
},
  "geometry": {"coordinates":[6.83303,51.795704],"type":"Point"}
}