{
  "type": "Feature",
  "properties": {
    "iso:country":"DE",
    "sg:address":"Goethestr. 12",
    "sg:city":"Germering",
    "sg:phone":"+49 89/8411102",
    "sg:postcode":"82110",
    "sg:province":"Bayern",
    "wof:name":"F. Sch\u00f6nhuber",
    "wof:placetype":"venue"
},
  "geometry": {"coordinates":[11.3620195389,48.1328811646],"type":"Point"}
}