{
  "type": "Feature",
  "properties": {
    "iso:country":"DE",
    "sg:address":"Siedlung K\u00f6nigshufen 50",
    "sg:city":"G\u00f6rlitz",
    "sg:postcode":"02828",
    "sg:province":"Sachsen",
    "wof:name":"Mechtild Gerntke",
    "wof:placetype":"venue"
},
  "geometry": {"coordinates":[14.9735116959,51.1744041443],"type":"Point"}
}