{
  "type": "Feature",
  "properties": {
    "iso:country":"DE",
    "sg:address":"Schillerstr. 211",
    "sg:city":"Waiblingen",
    "sg:phone":"+49 7146/4984",
    "sg:postcode":"71336",
    "sg:province":"Baden-W\u00fcrttemberg",
    "wof:name":"Schw\u00e4mmle",
    "wof:placetype":"venue"
},
  "geometry": {"coordinates":[9.32851,48.89093],"type":"Point"}
}