{
  "type": "Feature",
  "properties": {
    "iso:country":"DE",
    "sg:address":"Hauptstr. 5",
    "sg:city":"Hedersleben",
    "sg:phone":"+49 34773/20481",
    "sg:postcode":"06295",
    "sg:province":"Sachsen-Anhalt",
    "wof:name":"Dorfgastst\u00e4tte",
    "wof:placetype":"venue"
},
  "geometry": {"coordinates":[11.6459989548,51.547794342],"type":"Point"}
}