{
  "type": "Feature",
  "properties": {
    "iso:country":"DE",
    "sg:address":"Andernacher Str. 240",
    "sg:city":"Koblenz",
    "sg:phone":"+49 261/804960",
    "sg:postcode":"56070",
    "sg:province":"Rheinland-Pfalz",
    "wof:name":"P. M. Kugler",
    "wof:placetype":"venue"
},
  "geometry": {"coordinates":[7.580242,50.381126],"type":"Point"}
}