{
  "type": "Feature",
  "properties": {
    "iso:country":"DE",
    "sg:address":"Bahnhofstr. 9",
    "sg:city":"Asbach-B\u00e4umenheim",
    "sg:phone":"+49 906/9443",
    "sg:postcode":"86663",
    "sg:province":"Bayern",
    "wof:name":"Mayr Druck Gmbh B\u00e4umenheim",
    "wof:placetype":"venue"
},
  "geometry": {"coordinates":[10.808957,48.681019],"type":"Point"}
}