{
  "type": "Feature",
  "properties": {
    "iso:country":"DE",
    "sg:address":"Pacellistr. 14",
    "sg:city":"M\u00fcnchen",
    "sg:postcode":"80333",
    "sg:province":"Bayern",
    "wof:name":"Kn\u00fcrr-holding Gmbh",
    "wof:placetype":"venue"
},
  "geometry": {"coordinates":[11.570284,48.14082],"type":"Point"}
}