{
  "type": "Feature",
  "properties": {
    "iso:country":"DE",
    "sg:address":"St.-Kilians-Platz 8",
    "sg:city":"M\u00fcnnerstadt",
    "sg:phone":"+49 9766/340",
    "sg:postcode":"97702",
    "sg:province":"Bayern",
    "wof:name":"Engelbert Schneider",
    "wof:placetype":"venue"
},
  "geometry": {"coordinates":[10.326485,50.22929],"type":"Point"}
}