{
  "type": "Feature",
  "properties": {
    "iso:country":"DE",
    "sg:address":"Waldstr. 61",
    "sg:city":"Herford",
    "sg:phone":"+49 5221/73501",
    "sg:postcode":"32052",
    "sg:province":"Nordrhein-Westfalen",
    "wof:name":"Walter Kr\u00e4mer",
    "wof:placetype":"venue"
},
  "geometry": {"coordinates":[8.637615,52.071308],"type":"Point"}
}