{
  "type": "Feature",
  "properties": {
    "iso:country":"DE",
    "sg:address":"Bamberger Str. 53",
    "sg:city":"Berlin",
    "sg:phone":"+49 30/2183579",
    "sg:postcode":"10777",
    "sg:province":"Berlin",
    "wof:name":"Noack Otto Inh. Dietrich Strauch",
    "wof:placetype":"venue"
},
  "geometry": {"coordinates":[13.3374481201,52.4954986572],"type":"Point"}
}