{
  "type": "Feature",
  "properties": {
    "iso:country":"DE",
    "sg:address":"Billwerder Steindamm 26",
    "sg:city":"Hamburg",
    "sg:phone":"+49 40/255171",
    "sg:postcode":"20537",
    "sg:province":"Hamburg",
    "wof:name":"Omnibusboerse.de",
    "wof:placetype":"venue"
},
  "geometry": {"coordinates":[10.040011,53.544033],"type":"Point"}
}