{
  "type": "Feature",
  "properties": {
    "iso:country":"DE",
    "sg:address":"Neumarktstr. 9",
    "sg:city":"Halle",
    "sg:phone":"+49 345/2941497",
    "sg:postcode":"06108",
    "sg:province":"Sachsen-Anhalt",
    "wof:name":"Kirchner & Hedicke Dienstleistungen F\u00fcr",
    "wof:placetype":"venue"
},
  "geometry": {"coordinates":[11.9667873383,51.4881706238],"type":"Point"}
}