{
  "type": "Feature",
  "properties": {
    "iso:country":"DE",
    "sg:address":"Feldstr. 3",
    "sg:city":"Gr\u00fcndau",
    "sg:phone":"+49 6051/12528",
    "sg:postcode":"63584",
    "sg:province":"Hessen",
    "wof:name":"D. K\u00f6hler",
    "wof:placetype":"venue"
},
  "geometry": {"coordinates":[9.1116743088,50.2003974915],"type":"Point"}
}