{
  "type": "Feature",
  "properties": {
    "iso:country":"DE",
    "sg:address":"Pfarrer-Nagel-Str. 11",
    "sg:city":"M\u00fcnchsm\u00fcnster",
    "sg:phone":"+49 8402/556",
    "sg:postcode":"85126",
    "sg:province":"Bayern",
    "wof:name":"G. Kovacs",
    "wof:placetype":"venue"
},
  "geometry": {"coordinates":[11.6961011887,48.7615737915],"type":"Point"}
}