{
  "type": "Feature",
  "properties": {
    "iso:country":"DE",
    "sg:address":"Max-Eyth-Weg 1",
    "sg:city":"Kohlberg",
    "sg:phone":"+49 7025/2565",
    "sg:postcode":"72664",
    "sg:province":"Baden-W\u00fcrttemberg",
    "wof:name":"Friedrich Sigmund Gmbh Drahtwarenfabrik",
    "wof:placetype":"venue"
},
  "geometry": {"coordinates":[9.3432016373,48.5604782104],"type":"Point"}
}