{
  "type": "Feature",
  "properties": {
    "iso:country":"DE",
    "sg:address":"Peter-Swyn-Str. 23",
    "sg:city":"Lehe",
    "sg:phone":"+49 4882/322",
    "sg:postcode":"25774",
    "sg:province":"Schleswig-Holstein",
    "wof:name":"Traute Malta",
    "wof:placetype":"venue"
},
  "geometry": {"coordinates":[9.02287,54.337597],"type":"Point"}
}