{
  "type": "Feature",
  "properties": {
    "iso:country":"DE",
    "sg:address":"Kreuzerweg 77",
    "sg:city":"Gr\u00fcnstadt",
    "sg:phone":"+49 6359/84128",
    "sg:postcode":"67269",
    "sg:province":"Rheinland-Pfalz",
    "wof:name":"Werner Schneider",
    "wof:placetype":"venue"
},
  "geometry": {"coordinates":[8.167131424,49.5570220947],"type":"Point"}
}