{
  "type": "Feature",
  "properties": {
    "iso:country":"DE",
    "sg:address":"Hoffeldstr. 89",
    "sg:city":"D\u00fcsseldorf",
    "sg:phone":"+49 211/686822",
    "sg:postcode":"40235",
    "sg:province":"Nordrhein-Westfalen",
    "wof:name":"Michel & Demmer Reliefdruck Gmbh",
    "wof:placetype":"venue"
},
  "geometry": {"coordinates":[6.814545,51.227322],"type":"Point"}
}