{
  "type": "Feature",
  "properties": {
    "iso:country":"DE",
    "sg:address":"Limesstr. 91",
    "sg:city":"M\u00fcnchen",
    "sg:phone":"+49 89/870576",
    "sg:postcode":"81243",
    "sg:province":"Bayern",
    "wof:name":"Monika Bock",
    "wof:placetype":"venue"
},
  "geometry": {"coordinates":[11.422863,48.145245],"type":"Point"}
}