{
  "type": "Feature",
  "properties": {
    "iso:country":"DE",
    "sg:address":"Maarstr. 10",
    "sg:city":"Landscheid",
    "sg:phone":"+49 6575/4338",
    "sg:postcode":"54526",
    "sg:province":"Rheinland-Pfalz",
    "wof:name":"R. Weinsberg Haus- Und K\u00fcchenger\u00e4te",
    "wof:placetype":"venue"
},
  "geometry": {"coordinates":[6.7707071304,49.9854621887],"type":"Point"}
}