{
  "type": "Feature",
  "properties": {
    "iso:country":"DE",
    "sg:address":"Hauptstr. 26",
    "sg:city":"Fluorn Winzeln",
    "sg:postcode":"78737",
    "sg:province":"Baden-W\u00fcrttemberg",
    "wof:name":"Raiffeisenbank Fl\u00f6ha Ag",
    "wof:placetype":"venue"
},
  "geometry": {"coordinates":[13.167667,50.86211],"type":"Point"}
}