{
  "type": "Feature",
  "properties": {
    "iso:country":"DE",
    "sg:address":"R\u00f6delheimer Str. 5-9",
    "sg:city":"Frankfurt",
    "sg:postcode":"60487",
    "sg:province":"Hessen",
    "wof:name":"Sinitec Service F\u00fcr Infortmationssysteme Gmbh",
    "wof:placetype":"venue"
},
  "geometry": {"coordinates":[8.6379928589,50.125164032],"type":"Point"}
}