{
  "type": "Feature",
  "properties": {
    "iso:country":"DE",
    "sg:address":"Hindenburgplatz 3",
    "sg:city":"Hildesheim",
    "sg:phone":"+49 5121/12097",
    "sg:postcode":"31134",
    "sg:province":"Niedersachsen",
    "wof:name":"Landesversicherungsanstalt Hannover",
    "wof:placetype":"venue"
},
  "geometry": {"coordinates":[9.9534826279,52.1493606567],"type":"Point"}
}