{
  "type": "Feature",
  "properties": {
    "iso:country":"DE",
    "sg:address":"B\u00fcchener Weg 53",
    "sg:city":"Lauenburg",
    "sg:phone":"+49 4153/4199",
    "sg:postcode":"21481",
    "sg:province":"Schleswig-Holstein",
    "wof:name":"Dieter Schloer",
    "wof:placetype":"venue"
},
  "geometry": {"coordinates":[10.5546503067,53.3796348572],"type":"Point"}
}