{
  "type": "Feature",
  "properties": {
    "iso:country":"DE",
    "sg:address":"Trauner Str. 12",
    "sg:city":"Obing",
    "sg:phone":"+49 8624/4484",
    "sg:postcode":"83119",
    "sg:province":"Bayern",
    "wof:name":"Gebr. Hochberger",
    "wof:placetype":"venue"
},
  "geometry": {"coordinates":[12.411759,47.995747],"type":"Point"}
}