{
  "type": "Feature",
  "properties": {
    "iso:country":"DE",
    "sg:address":"Marienstr 5",
    "sg:city":"Stuttgart",
    "sg:phone":"+49 711/2270386",
    "sg:postcode":"70178",
    "sg:province":"Baden-W\u00fcrttemberg",
    "wof:name":"Sch\u00fcta",
    "wof:placetype":"venue"
},
  "geometry": {"coordinates":[9.173009,48.772949],"type":"Point"}
}