{
  "type": "Feature",
  "properties": {
    "iso:country":"DE",
    "sg:address":"Schlo\u00df\u00e4cker 32",
    "sg:city":"Laupheim",
    "sg:phone":"+49 7392/2729",
    "sg:postcode":"88471",
    "sg:province":"Baden-W\u00fcrttemberg",
    "wof:name":"Bernd-mich. Rother Immobilienmakler",
    "wof:placetype":"venue"
},
  "geometry": {"coordinates":[9.8935832977,48.2290916443],"type":"Point"}
}