{
  "type": "Feature",
  "properties": {
    "iso:country":"DE",
    "sg:address":"Hauptstr. 44",
    "sg:city":"Langenberg",
    "sg:phone":"+49 5248/1001",
    "sg:postcode":"33449",
    "sg:province":"Nordrhein-Westfalen",
    "wof:name":"Elvira Kruse",
    "wof:placetype":"venue"
},
  "geometry": {"coordinates":[8.3165235519,51.7757530212],"type":"Point"}
}