{
  "type": "Feature",
  "properties": {
    "iso:country":"DE",
    "sg:address":"M\u00fchlenstr. 50 b",
    "sg:city":"Jever",
    "sg:phone":"+49 4461/93340",
    "sg:postcode":"26441",
    "sg:province":"Niedersachsen",
    "wof:name":"Flemming Dental Gmbh",
    "wof:placetype":"venue"
},
  "geometry": {"coordinates":[7.9106340408,53.567237854],"type":"Point"}
}