{
  "type": "Feature",
  "properties": {
    "iso:country":"DE",
    "sg:address":"Anton-F\u00fchrer-Str. 5d",
    "sg:city":"Rheine",
    "sg:phone":"+49 5971/92200",
    "sg:postcode":"48431",
    "sg:province":"Nordrhein-Westfalen",
    "wof:name":"Hartmann & Associates Euregio Gmbh",
    "wof:placetype":"venue"
},
  "geometry": {"coordinates":[7.4328479767,52.2820281982],"type":"Point"}
}