{
  "type": "Feature",
  "properties": {
    "iso:country":"DE",
    "sg:address":"Fritz-Henkel-Str. 6",
    "sg:city":"Biedenkopf",
    "sg:phone":"+49 6461/8474",
    "sg:postcode":"35216",
    "sg:province":"Hessen",
    "wof:name":"Dieter Donges",
    "wof:placetype":"venue"
},
  "geometry": {"coordinates":[8.4729528427,50.9275779724],"type":"Point"}
}