{
  "type": "Feature",
  "properties": {
    "iso:country":"DE",
    "sg:address":"Kiestr. 9",
    "sg:city":"Erftstadt",
    "sg:phone":"+49 2235",
    "sg:postcode":"50374",
    "sg:province":"Nordrhein-Westfalen",
    "wof:name":"Allfinanzconsulting Dipl.-kauffrau Ute Santander",
    "wof:placetype":"venue"
},
  "geometry": {"coordinates":[6.7649641037,50.825012207],"type":"Point"}
}