{
  "type": "Feature",
  "properties": {
    "iso:country":"DE",
    "sg:address":"In den Birken 21 b",
    "sg:city":"Hinterweidenthal",
    "sg:phone":"+49 6396/92110",
    "sg:postcode":"66999",
    "sg:province":"Rheinland-Pfalz",
    "wof:name":"M\u00e4rdian Werkzeug- Und Maschinenbau Gmbh",
    "wof:placetype":"venue"
},
  "geometry": {"coordinates":[7.7530617714,49.1902656555],"type":"Point"}
}