{
  "type": "Feature",
  "properties": {
    "iso:country":"DE",
    "sg:address":"Berliner Str. 76",
    "sg:city":"Herzberg",
    "sg:phone":"+49 3535/20931",
    "sg:postcode":"04916",
    "sg:province":"Brandenburg",
    "wof:name":"H. Frank",
    "wof:placetype":"venue"
},
  "geometry": {"coordinates":[13.2407102585,51.7053565979],"type":"Point"}
}