{
  "type": "Feature",
  "properties": {
    "iso:country":"DE",
    "sg:address":"Langer Rain 5",
    "sg:city":"R\u00f6dental",
    "sg:postcode":"96472",
    "sg:province":"Bayern",
    "wof:name":"Firma Willy Gerlicher Maler- Und Putzgesch\u00e4ft",
    "wof:placetype":"venue"
},
  "geometry": {"coordinates":[11.032312,50.291092],"type":"Point"}
}