{
  "type": "Feature",
  "properties": {
    "iso:country":"DE",
    "sg:address":"Hannah-Vogt-Str. 1",
    "sg:city":"G\u00f6ttingen",
    "sg:phone":"+49 551/3700020",
    "sg:postcode":"37085",
    "sg:province":"Niedersachsen",
    "wof:name":"Trinos Vakuum Systeme",
    "wof:placetype":"venue"
},
  "geometry": {"coordinates":[9.9720935822,51.5206871033],"type":"Point"}
}