{
  "type": "Feature",
  "properties": {
    "iso:country":"DE",
    "sg:address":"Im Neudeck 22",
    "sg:city":"Speyer",
    "sg:phone":"+49 6232/33431",
    "sg:postcode":"67346",
    "sg:province":"Rheinland-Pfalz",
    "wof:name":"K\u00e4ltetechnik Wegerich",
    "wof:placetype":"venue"
},
  "geometry": {"coordinates":[8.430978,49.337608],"type":"Point"}
}