{
  "type": "Feature",
  "properties": {
    "iso:country":"DE",
    "sg:address":"Lange Str. 79",
    "sg:city":"Hessisch Oldendorf",
    "sg:phone":"+49 5152/2626",
    "sg:postcode":"31840",
    "sg:province":"Niedersachsen",
    "wof:name":"Sanit\u00e4tshaus Gisela Staudigel Inh. Hans-j\u00fcrgen Leitzmann",
    "wof:placetype":"venue"
},
  "geometry": {"coordinates":[9.2503728867,52.1685943604],"type":"Point"}
}