{
  "type": "Feature",
  "properties": {
    "iso:country":"DE",
    "sg:address":"Alte Landstr. 17",
    "sg:city":"Sigmarszell",
    "sg:phone":"+49 8382/975906",
    "sg:postcode":"88138",
    "sg:province":"Bayern",
    "wof:name":"Elco Unternehmensberatung Gmbh",
    "wof:placetype":"venue"
},
  "geometry": {"coordinates":[9.7540998459,47.5877304077],"type":"Point"}
}