{
  "type": "Feature",
  "properties": {
    "iso:country":"DE",
    "sg:address":"Bornberg 33",
    "sg:city":"Wuppertal",
    "sg:phone":"+49 202/751632",
    "sg:postcode":"42109",
    "sg:province":"Nordrhein-Westfalen",
    "wof:name":"Rainer Westenberg Finanzberater",
    "wof:placetype":"venue"
},
  "geometry": {"coordinates":[7.152859211,51.2737808228],"type":"Point"}
}