{
  "type": "Feature",
  "properties": {
    "iso:country":"DE",
    "sg:address":"Jakobstr. 14",
    "sg:city":"K\u00f6then",
    "sg:phone":"+49 3496/553865",
    "sg:postcode":"06366",
    "sg:province":"Sachsen-Anhalt",
    "wof:name":"O. St\u00e4hr Anlageberater",
    "wof:placetype":"venue"
},
  "geometry": {"coordinates":[11.9682893753,51.7393951416],"type":"Point"}
}