{
  "type": "Feature",
  "properties": {
    "iso:country":"DE",
    "sg:address":"Hof\u00e4cker 5",
    "sg:city":"Mengerskirchen",
    "sg:phone":"+49 6476/8121",
    "sg:postcode":"35794",
    "sg:province":"Hessen",
    "wof:name":"Karl-heinz Becker",
    "wof:placetype":"venue"
},
  "geometry": {"coordinates":[8.181247,50.547966],"type":"Point"}
}