{
  "type": "Feature",
  "properties": {
    "iso:country":"DE",
    "sg:address":"Buchenwinkel 2",
    "sg:city":"Hohenfels",
    "sg:postcode":"78355",
    "sg:province":"Baden-W\u00fcrttemberg",
    "wof:name":"Institut F. Bienenkunde D. Universit\u00e4t Frankfurt",
    "wof:placetype":"venue"
},
  "geometry": {"coordinates":[9.0728282928,47.8946800232],"type":"Point"}
}