{
  "type": "Feature",
  "properties": {
    "iso:country":"DE",
    "sg:address":"Harkortstr. 51 a",
    "sg:city":"Dortmund",
    "sg:phone":"+49 231/712169",
    "sg:postcode":"44225",
    "sg:province":"Nordrhein-Westfalen",
    "wof:name":"L\u00f6wen-apotheke",
    "wof:placetype":"venue"
},
  "geometry": {"coordinates":[7.440623,51.475853],"type":"Point"}
}