{
  "type": "Feature",
  "properties": {
    "iso:country":"DE",
    "sg:address":"Fliednerstr. 2",
    "sg:city":"Wiesbaden",
    "sg:phone":"+49 611/503907",
    "sg:postcode":"65191",
    "sg:province":"Hessen",
    "wof:name":"Volksbildungswerk Bierstadt E. V.",
    "wof:placetype":"venue"
},
  "geometry": {"coordinates":[8.2802371979,50.0800514221],"type":"Point"}
}