{
  "type": "Feature",
  "properties": {
    "iso:country":"DE",
    "sg:address":"Hubstr. 56",
    "sg:city":"Walldorf",
    "sg:phone":"+49 6227/821110",
    "sg:postcode":"69190",
    "sg:province":"Baden-W\u00fcrttemberg",
    "wof:name":"Klaus Steidle Steuerberater",
    "wof:placetype":"venue"
},
  "geometry": {"coordinates":[8.6478271484,49.3144645691],"type":"Point"}
}