{
  "type": "Feature",
  "properties": {
    "iso:country":"DE",
    "sg:address":"Von-Ossietzky-Str. 32",
    "sg:city":"Gera",
    "sg:postcode":"07552",
    "sg:province":"Th\u00fcringen",
    "wof:name":"Th\u00fcringer Antiquit\u00e4ten Gmbh",
    "wof:placetype":"venue"
},
  "geometry": {"coordinates":[12.0587940216,50.9194526672],"type":"Point"}
}