{
  "type": "Feature",
  "properties": {
    "iso:country":"DE",
    "sg:address":"Hauptstr. 6",
    "sg:city":"Lauterecken",
    "sg:phone":"+49 6382/922115",
    "sg:postcode":"67742",
    "sg:province":"Rheinland-Pfalz",
    "wof:name":"E. R. B. Wohnungsbau- Gmbh",
    "wof:placetype":"venue"
},
  "geometry": {"coordinates":[7.589425,49.651493],"type":"Point"}
}