{
  "type": "Feature",
  "properties": {
    "iso:country":"DE",
    "sg:address":"W\u00f6hrden 74",
    "sg:city":"Hollern-Twielenfleth",
    "sg:phone":"+49 4141/2893",
    "sg:postcode":"21723",
    "sg:province":"Niedersachsen",
    "wof:name":"Gastst\u00e4tte Zur Symphonie",
    "wof:placetype":"venue"
},
  "geometry": {"coordinates":[9.5164203644,53.6093101501],"type":"Point"}
}