{
  "type": "Feature",
  "properties": {
    "iso:country":"DE",
    "sg:address":"Nollstr. 30",
    "sg:city":"Elsdorf",
    "sg:postcode":"50189",
    "sg:province":"Nordrhein-Westfalen",
    "wof:name":"Kfz-werkstattausr\u00fcstung R. Guba Gmbh",
    "wof:placetype":"venue"
},
  "geometry": {"coordinates":[6.560542,50.935883],"type":"Point"}
}