{
  "type": "Feature",
  "properties": {
    "iso:country":"DE",
    "sg:address":"Darmst\u00e4dter Str. 70",
    "sg:city":"Ober-Ramstadt",
    "sg:phone":"+49 6154/2323",
    "sg:postcode":"64372",
    "sg:province":"Hessen",
    "wof:name":"Sport Und Freizeit Georg Heleine E. K.",
    "wof:placetype":"venue"
},
  "geometry": {"coordinates":[8.74826,49.826241],"type":"Point"}
}