{
  "type": "Feature",
  "properties": {
    "iso:country":"DE",
    "sg:address":"Wendelsteinweg 14",
    "sg:city":"Maisach",
    "sg:phone":"+49 8142/41202",
    "sg:postcode":"82216",
    "sg:province":"Bayern",
    "wof:name":"Stephan Birkner Rechtsanwalt",
    "wof:placetype":"venue"
},
  "geometry": {"coordinates":[11.2940292358,48.2184753418],"type":"Point"}
}