{
  "type": "Feature",
  "properties": {
    "iso:country":"DE",
    "sg:address":"Marktplatz 12",
    "sg:city":"Furtwangen",
    "sg:phone":"+49 7723/7261",
    "sg:postcode":"78120",
    "sg:province":"Baden-W\u00fcrttemberg",
    "wof:name":"Tabak-gl\u00fcck",
    "wof:placetype":"venue"
},
  "geometry": {"coordinates":[8.2059984207,48.052028656],"type":"Point"}
}