{
  "type": "Feature",
  "properties": {
    "iso:country":"DE",
    "sg:address":"Dorfstr. 11",
    "sg:city":"Drebber",
    "sg:phone":"+49 5445/516",
    "sg:postcode":"49457",
    "sg:province":"Niedersachsen",
    "wof:name":"Gastst\u00e4tte Gustav Schr\u00f6der",
    "wof:placetype":"venue"
},
  "geometry": {"coordinates":[8.4240732193,52.6503753662],"type":"Point"}
}