{
  "type": "Feature",
  "properties": {
    "iso:country":"DE",
    "sg:address":"Hauptstr. 81",
    "sg:city":"M\u00fchlhausen",
    "sg:phone":"+49 6222/62724",
    "sg:postcode":"69242",
    "sg:province":"Baden-W\u00fcrttemberg",
    "wof:name":"Alois Breitner",
    "wof:placetype":"venue"
},
  "geometry": {"coordinates":[8.727027,49.248341],"type":"Point"}
}