{
  "type": "Feature",
  "properties": {
    "iso:country":"DE",
    "sg:address":"Lennestr. 8",
    "sg:city":"Magdeburg",
    "sg:phone":"+49 391/6219607",
    "sg:postcode":"39112",
    "sg:province":"Sachsen-Anhalt",
    "wof:name":"Kristina Scheithauer",
    "wof:placetype":"venue"
},
  "geometry": {"coordinates":[11.620223999,52.1151695251],"type":"Point"}
}