{
  "type": "Feature",
  "properties": {
    "iso:country":"DE",
    "sg:address":"Harvestehuder Weg 24",
    "sg:city":"Hamburg",
    "sg:postcode":"20149",
    "sg:province":"Hamburg",
    "wof:name":"Popular Leader Gmbh",
    "wof:placetype":"venue"
},
  "geometry": {"coordinates":[9.999025,53.573917],"type":"Point"}
}