{
  "type": "Feature",
  "properties": {
    "iso:country":"DE",
    "sg:address":"Hochstr. 1",
    "sg:city":"Geldern",
    "sg:phone":"+49 2831/5729",
    "sg:postcode":"47608",
    "sg:province":"Nordrhein-Westfalen",
    "wof:name":"Johannes Brauwers",
    "wof:placetype":"venue"
},
  "geometry": {"coordinates":[6.2435479164,51.4981575012],"type":"Point"}
}