{
  "type": "Feature",
  "properties": {
    "iso:country":"DE",
    "sg:address":"Schulstr. 1",
    "sg:city":"Untereisesheim",
    "sg:phone":"+49 7132/41423",
    "sg:postcode":"74257",
    "sg:province":"Baden-W\u00fcrttemberg",
    "wof:name":"Gastst\u00e4tte Hummel",
    "wof:placetype":"venue"
},
  "geometry": {"coordinates":[9.2019538879,49.2119102478],"type":"Point"}
}