{
  "type": "Feature",
  "properties": {
    "iso:country":"DE",
    "sg:address":"Bernauer Str. 8",
    "sg:city":"Altlandsberg",
    "sg:phone":"+49 33438/60415",
    "sg:postcode":"15345",
    "sg:province":"Brandenburg",
    "wof:name":"Hans-j\u00fcrgen Tornow",
    "wof:placetype":"venue"
},
  "geometry": {"coordinates":[13.727918,52.566139],"type":"Point"}
}