{
  "type": "Feature",
  "properties": {
    "iso:country":"DE",
    "sg:address":"Herterichstr. 63",
    "sg:city":"M\u00fcnchen",
    "sg:phone":"+49 89/7498290",
    "sg:postcode":"81479",
    "sg:province":"Bayern",
    "wof:name":"Hotel Sollner Hof",
    "wof:placetype":"venue"
},
  "geometry": {"coordinates":[11.5142755508,48.0760002136],"type":"Point"}
}