{
  "type": "Feature",
  "properties": {
    "iso:country":"DE",
    "sg:address":"Rissener Ufer 15",
    "sg:city":"Hamburg",
    "sg:postcode":"22559",
    "sg:province":"Hamburg",
    "wof:name":"Haus Wittenbergen",
    "wof:placetype":"venue"
},
  "geometry": {"coordinates":[9.757976,53.565388],"type":"Point"}
}