{
  "type": "Feature",
  "properties": {
    "iso:country":"DE",
    "sg:address":"Bergkirchener Str. 14",
    "sg:city":"Hille",
    "sg:phone":"+49 5734/7700",
    "sg:postcode":"32479",
    "sg:province":"Nordrhein-Westfalen",
    "wof:name":"Friedr. W. B\u00f6hne",
    "wof:placetype":"venue"
},
  "geometry": {"coordinates":[8.79407,52.287933],"type":"Point"}
}