{
  "type": "Feature",
  "properties": {
    "iso:country":"DE",
    "sg:address":"Bahnhofstr. 48",
    "sg:city":"Tostedt",
    "sg:phone":"+49 4182/1385",
    "sg:postcode":"21255",
    "sg:province":"Niedersachsen",
    "wof:name":"E. Kitta",
    "wof:placetype":"venue"
},
  "geometry": {"coordinates":[9.7190008163,53.2742385864],"type":"Point"}
}