{
  "type": "Feature",
  "properties": {
    "iso:country":"DE",
    "sg:address":"Eisenacher Str. 48",
    "sg:city":"Berlin",
    "sg:phone":"+49 30/8536679",
    "sg:postcode":"10823",
    "sg:province":"Berlin",
    "wof:name":"Hathor Gitta Bergemann",
    "wof:placetype":"venue"
},
  "geometry": {"coordinates":[13.3492927551,52.4877815247],"type":"Point"}
}