{
  "type": "Feature",
  "properties": {
    "iso:country":"DE",
    "sg:address":"Mozartstr. 12",
    "sg:city":"Mering",
    "sg:phone":"+49 8233/9789",
    "sg:postcode":"86415",
    "sg:province":"Bayern",
    "wof:name":"C. B. Radio-club Mering Franz Heinrich",
    "wof:placetype":"venue"
},
  "geometry": {"coordinates":[10.975894928,48.2610054016],"type":"Point"}
}