{
  "type": "Feature",
  "properties": {
    "iso:country":"DE",
    "sg:address":"Rathausstr. 1",
    "sg:city":"Halle",
    "sg:phone":"+49 345/5544710",
    "sg:postcode":"06108",
    "sg:province":"Sachsen-Anhalt",
    "wof:name":"Stadtarchiv",
    "wof:placetype":"venue"
},
  "geometry": {"coordinates":[11.971546,51.482849],"type":"Point"}
}