{
  "type": "Feature",
  "properties": {
    "iso:country":"DE",
    "sg:address":"Schubertstr. 13",
    "sg:city":"Baumholder",
    "sg:phone":"+49 6783/2123",
    "sg:postcode":"55774",
    "sg:province":"Rheinland-Pfalz",
    "wof:name":"Taxen-dienst E. V.",
    "wof:placetype":"venue"
},
  "geometry": {"coordinates":[7.3312969208,49.6125717163],"type":"Point"}
}