{
  "type": "Feature",
  "properties": {
    "iso:country":"DE",
    "sg:address":"Schwarzwaldstr 3",
    "sg:city":"Todtnau",
    "sg:phone":"+49 4531/16101",
    "sg:postcode":"79674",
    "sg:province":"Baden-W\u00fcrttemberg",
    "wof:name":"Deutsche Aerosol-ventil Gmbh",
    "wof:placetype":"venue"
},
  "geometry": {"coordinates":[10.389978,53.801601],"type":"Point"}
}