{
  "type": "Feature",
  "properties": {
    "iso:country":"DE",
    "sg:address":"Borsigstr. 26",
    "sg:city":"Rodgau",
    "sg:phone":"+49 6106/75400",
    "sg:postcode":"63110",
    "sg:province":"Hessen",
    "wof:name":"H. D\u00fcrr",
    "wof:placetype":"venue"
},
  "geometry": {"coordinates":[8.865066,49.990662],"type":"Point"}
}