{
  "type": "Feature",
  "properties": {
    "iso:country":"DE",
    "sg:address":"Am Soll 1",
    "sg:city":"Gro\u00dfensee",
    "sg:phone":"+49 4154/6141",
    "sg:postcode":"22946",
    "sg:province":"Schleswig-Holstein",
    "wof:name":"Dirk Eylmann",
    "wof:placetype":"venue"
},
  "geometry": {"coordinates":[10.34171,53.616066],"type":"Point"}
}