{
  "type": "Feature",
  "properties": {
    "iso:country":"DE",
    "sg:address":"Ottensener Weg 89a",
    "sg:city":"Buxtehude",
    "sg:phone":"+49 4161/713526",
    "sg:postcode":"21614",
    "sg:province":"Niedersachsen",
    "wof:name":"Die Offizielle Homepage Des Buxtehuder Schwimmclub",
    "wof:placetype":"venue"
},
  "geometry": {"coordinates":[9.67323,53.459743],"type":"Point"}
}