{
  "type": "Feature",
  "properties": {
    "iso:country":"DE",
    "sg:address":"Gamlener Str. 15",
    "sg:city":"Kaifenheim",
    "sg:phone":"+49 2653/3285",
    "sg:postcode":"56761",
    "sg:province":"Rheinland-Pfalz",
    "wof:name":"Gabriele Hoffmann",
    "wof:placetype":"venue"
},
  "geometry": {"coordinates":[7.224165,50.245384],"type":"Point"}
}