{
  "type": "Feature",
  "properties": {
    "iso:country":"DE",
    "sg:address":"Am Starzenbach 21",
    "sg:city":"Wolnzach",
    "sg:phone":"+49 8442/92590",
    "sg:postcode":"85283",
    "sg:province":"Bayern",
    "wof:name":"Johann Schels Steuerberater",
    "wof:placetype":"venue"
},
  "geometry": {"coordinates":[11.6269197464,48.6015014648],"type":"Point"}
}