{
  "type": "Feature",
  "properties": {
    "iso:country":"DE",
    "sg:address":"Dietrich-He\u00dfmer-Platz 29",
    "sg:city":"Lauchhammer",
    "sg:phone":"+49 3574/121759",
    "sg:postcode":"01979",
    "sg:province":"Brandenburg",
    "wof:name":"Heike Donath",
    "wof:placetype":"venue"
},
  "geometry": {"coordinates":[13.761875,51.494701],"type":"Point"}
}