{
  "type": "Feature",
  "properties": {
    "iso:country":"DE",
    "sg:address":"Markt 10",
    "sg:city":"Meppen",
    "sg:phone":"+49 5931/89080",
    "sg:postcode":"49716",
    "sg:province":"Niedersachsen",
    "wof:name":"Dreier Gmbh",
    "wof:placetype":"venue"
},
  "geometry": {"coordinates":[7.291627,52.69146],"type":"Point"}
}