{
  "type": "Feature",
  "properties": {
    "iso:country":"DE",
    "sg:address":"Strandweg 1 b",
    "sg:city":"Bellin",
    "sg:phone":"+49 39771/22460",
    "sg:postcode":"17375",
    "sg:province":"Mecklenburg-Vorpommern",
    "wof:name":"K.-e. Gerhard Ingenieur",
    "wof:placetype":"venue"
},
  "geometry": {"coordinates":[-122.33190917970001,48.7150688171],"type":"Point"}
}