{
  "type": "Feature",
  "properties": {
    "iso:country":"DE",
    "sg:address":"Sch\u00fctzeberger Str. 73",
    "sg:city":"Wolfhagen",
    "sg:phone":"+49 5692/8805",
    "sg:postcode":"34466",
    "sg:province":"Hessen",
    "wof:name":"Chinarestaurant Bambusgarten",
    "wof:placetype":"venue"
},
  "geometry": {"coordinates":[9.172410965,51.3278045654],"type":"Point"}
}