{
  "type": "Feature",
  "properties": {
    "iso:country":"DE",
    "sg:address":"Lingener Str. 106",
    "sg:city":"Nordhorn",
    "sg:phone":"+49 5921/36361",
    "sg:postcode":"48531",
    "sg:province":"Niedersachsen",
    "wof:name":"Westfalen-tankstelle",
    "wof:placetype":"venue"
},
  "geometry": {"coordinates":[7.0872840881,52.4405326843],"type":"Point"}
}