{
  "type": "Feature",
  "properties": {
    "iso:country":"DE",
    "sg:address":"Hasselborn 8",
    "sg:city":"Brilon",
    "sg:phone":"+49 2961/8961",
    "sg:postcode":"59929",
    "sg:province":"Nordrhein-Westfalen",
    "wof:name":"Robert Hovestadt",
    "wof:placetype":"venue"
},
  "geometry": {"coordinates":[8.569439888,51.3999214172],"type":"Point"}
}