{
  "type": "Feature",
  "properties": {
    "iso:country":"DE",
    "sg:address":"Gewerbegebiet",
    "sg:city":"Retzow",
    "sg:phone":"+49 39888/3252",
    "sg:postcode":"17279",
    "sg:province":"Brandenburg",
    "wof:name":"Havel-heizungsbau Gmbh",
    "wof:placetype":"venue"
},
  "geometry": {"coordinates":[13.3152351379,53.2103767395],"type":"Point"}
}