{
  "type": "Feature",
  "properties": {
    "iso:country":"DE",
    "sg:address":"Strandstr. 2",
    "sg:city":"Waren",
    "sg:postcode":"17192",
    "sg:province":"Mecklenburg-Vorpommern",
    "wof:name":"Wolfgang Dreier",
    "wof:placetype":"venue"
},
  "geometry": {"coordinates":[12.7829904556,53.5109405518],"type":"Point"}
}