{
  "type": "Feature",
  "properties": {
    "iso:country":"DE",
    "sg:address":"Carl-Benz-Str. 18",
    "sg:city":"Gilching",
    "sg:phone":"+49 8105/5066",
    "sg:postcode":"82205",
    "sg:province":"Bayern",
    "wof:name":"Kufe-kunststoff-fenster -herstellung-gmbh & Co. Kg",
    "wof:placetype":"venue"
},
  "geometry": {"coordinates":[11.287404,48.107265],"type":"Point"}
}