{
  "type": "Feature",
  "properties": {
    "iso:country":"DE",
    "sg:address":"Am Dittwarer Bahnhof 20",
    "sg:city":"Tauberbischofsheim",
    "sg:phone":"+49 9341/4507",
    "sg:postcode":"97941",
    "sg:province":"Baden-W\u00fcrttemberg",
    "wof:name":"Movie-point",
    "wof:placetype":"venue"
},
  "geometry": {"coordinates":[9.6401014328,49.6037597656],"type":"Point"}
}