{
  "type": "Feature",
  "properties": {
    "iso:country":"DE",
    "sg:address":"Zingelpfad 29",
    "sg:city":"Essen",
    "sg:phone":"+49 201/291504",
    "sg:postcode":"45309",
    "sg:province":"Nordrhein-Westfalen",
    "wof:name":"Dieter Herche",
    "wof:placetype":"venue"
},
  "geometry": {"coordinates":[7.066824913,51.4710578918],"type":"Point"}
}