{
  "type": "Feature",
  "properties": {
    "iso:country":"DE",
    "sg:address":"Holzhofallee 15 a",
    "sg:city":"Darmstadt",
    "sg:phone":"+49 6151/300980",
    "sg:postcode":"64295",
    "sg:province":"Hessen",
    "wof:name":"Netuschil Breunig Und Kollegen Rechtsanw\u00e4lte Und Notare",
    "wof:placetype":"venue"
},
  "geometry": {"coordinates":[8.6421604156,49.8651504517],"type":"Point"}
}