{
  "type": "Feature",
  "properties": {
    "iso:country":"DE",
    "sg:address":"Adalbertsteinweg 67-69",
    "sg:city":"Aachen",
    "sg:phone":"+49 241/4007790",
    "sg:postcode":"52070",
    "sg:province":"Nordrhein-Westfalen",
    "wof:name":"J\u00f6rg Kropp Rechtsanwalt",
    "wof:placetype":"venue"
},
  "geometry": {"coordinates":[6.1010408401,50.7746315002],"type":"Point"}
}