{
  "type": "Feature",
  "properties": {
    "iso:country":"DE",
    "sg:address":"Lange Str. 20",
    "sg:city":"Seesen",
    "sg:phone":"+49 5381/2362",
    "sg:postcode":"38723",
    "sg:province":"Niedersachsen",
    "wof:name":"Karl Heinzel",
    "wof:placetype":"venue"
},
  "geometry": {"coordinates":[10.1720066071,51.8898124695],"type":"Point"}
}