{
  "type": "Feature",
  "properties": {
    "iso:country":"DE",
    "sg:address":"Oedenberger Str. 159",
    "sg:city":"N\u00fcrnberg",
    "sg:phone":"+49 911/919720",
    "sg:postcode":"90491",
    "sg:province":"Bayern",
    "wof:name":"Messer Stadelmeyer Und Wurm Rechtsanw\u00e4lte",
    "wof:placetype":"venue"
},
  "geometry": {"coordinates":[11.1189689636,49.4739685059],"type":"Point"}
}