{
  "type": "Feature",
  "properties": {
    "iso:country":"DE",
    "sg:address":"Breslauer Str. 16",
    "sg:city":"Neu-Ulm",
    "sg:phone":"+49 731/81871",
    "sg:postcode":"89231",
    "sg:province":"Bayern",
    "wof:name":"Gisela Von Albedyhll Tanzschule",
    "wof:placetype":"venue"
},
  "geometry": {"coordinates":[10.0149908066,48.3694801331],"type":"Point"}
}