{
  "type": "Feature",
  "properties": {
    "iso:country":"DE",
    "sg:address":"Landstr. 2",
    "sg:city":"Gro\u00dfweitzschen",
    "sg:phone":"+49 3431/613470",
    "sg:postcode":"04720",
    "sg:province":"Sachsen",
    "wof:name":"B. Bertelsmeier & A. Kunze Gbr",
    "wof:placetype":"venue"
},
  "geometry": {"coordinates":[13.059239,51.155842],"type":"Point"}
}