{
  "type": "Feature",
  "properties": {
    "iso:country":"DE",
    "sg:address":"Breitenfelder Str. 42",
    "sg:city":"Gevelsberg",
    "sg:phone":"+49 2332/2993",
    "sg:postcode":"58285",
    "sg:province":"Nordrhein-Westfalen",
    "wof:name":"Sabine Heinrich",
    "wof:placetype":"venue"
},
  "geometry": {"coordinates":[7.3183369637,51.3170204163],"type":"Point"}
}