{
  "type": "Feature",
  "properties": {
    "iso:country":"DE",
    "sg:address":"Balthasar-Neumann-Str. 92a",
    "sg:city":"N\u00fcrnberg",
    "sg:phone":"+49 911/546362",
    "sg:postcode":"90480",
    "sg:province":"Bayern",
    "wof:name":"Ch. Buko",
    "wof:placetype":"venue"
},
  "geometry": {"coordinates":[11.1406030655,49.4586868286],"type":"Point"}
}