{
  "type": "Feature",
  "properties": {
    "iso:country":"DE",
    "sg:address":"Am Buschfeld 6",
    "sg:city":"Schneverdingen",
    "sg:phone":"+49 5193/982404",
    "sg:postcode":"29640",
    "sg:province":"Niedersachsen",
    "wof:name":"Debeka Versicherung Michael Kautz",
    "wof:placetype":"venue"
},
  "geometry": {"coordinates":[9.7949104309,53.108001709],"type":"Point"}
}