{
  "type": "Feature",
  "properties": {
    "iso:country":"DE",
    "sg:address":"Rathausstr. 15",
    "sg:city":"Aachen",
    "sg:phone":"+49 241/13224",
    "sg:postcode":"52072",
    "sg:province":"Nordrhein-Westfalen",
    "wof:name":"Siegfried Reitz Architekt",
    "wof:placetype":"venue"
},
  "geometry": {"coordinates":[6.056796,50.798416],"type":"Point"}
}