{
  "type": "Feature",
  "properties": {
    "iso:country":"DE",
    "sg:address":"Humboldtstr. 164",
    "sg:city":"Bremen",
    "sg:phone":"+49 421/7947550",
    "sg:postcode":"28203",
    "sg:province":"Bremen",
    "wof:name":"M. Leeuwarden",
    "wof:placetype":"venue"
},
  "geometry": {"coordinates":[8.8337526321,53.0741615295],"type":"Point"}
}