{
  "type": "Feature",
  "properties": {
    "iso:country":"DE",
    "sg:address":"Peter-Sengl-Str 22 1/2",
    "sg:city":"Aindling",
    "sg:phone":"+49 8237/5560",
    "sg:postcode":"86447",
    "sg:province":"Bayern",
    "wof:name":"Erwin Witzenberger",
    "wof:placetype":"venue"
},
  "geometry": {"coordinates":[10.9563102722,48.5133247375],"type":"Point"}
}