{
  "type": "Feature",
  "properties": {
    "iso:country":"DE",
    "sg:address":"Fischerstr. 7",
    "sg:city":"Duisburg",
    "sg:phone":"+49 203/773383",
    "sg:postcode":"47055",
    "sg:province":"Nordrhein-Westfalen",
    "wof:name":"Noy",
    "wof:placetype":"venue"
},
  "geometry": {"coordinates":[6.7518501282,51.4027671814],"type":"Point"}
}