{
  "type": "Feature",
  "properties": {
    "iso:country":"DE",
    "sg:address":"Neust\u00e4dter Str. 4",
    "sg:city":"Windischeschenbach",
    "sg:phone":"+49 9681/1371",
    "sg:postcode":"92670",
    "sg:province":"Bayern",
    "wof:name":"Emmeram Bauer",
    "wof:placetype":"venue"
},
  "geometry": {"coordinates":[12.153968,49.802738],"type":"Point"}
}