{
  "type": "Feature",
  "properties": {
    "iso:country":"DE",
    "sg:address":"Silvester-Herzog-Str. 11",
    "sg:city":"Mosbach",
    "sg:postcode":"74821",
    "sg:province":"Baden-W\u00fcrttemberg",
    "wof:name":"Ullrich & Tipold Ohg",
    "wof:placetype":"venue"
},
  "geometry": {"coordinates":[9.10199,49.33963],"type":"Point"}
}