{
  "type": "Feature",
  "properties": {
    "iso:country":"DE",
    "sg:address":"Bahnhofstr. 30",
    "sg:city":"M\u00f6ckm\u00fchl",
    "sg:phone":"+49 6298/1208",
    "sg:postcode":"74219",
    "sg:province":"Baden-W\u00fcrttemberg",
    "wof:name":"Deutsche Bahn Ag",
    "wof:placetype":"venue"
},
  "geometry": {"coordinates":[9.358089447,49.3222618103],"type":"Point"}
}