{
  "type": "Feature",
  "properties": {
    "iso:country":"DE",
    "sg:address":"Conrad-R\u00f6ntgen-Str. 14 a",
    "sg:city":"Sondershausen",
    "sg:phone":"+49 3632/602491",
    "sg:postcode":"99706",
    "sg:province":"Th\u00fcringen",
    "wof:name":"Jaro Kubicka",
    "wof:placetype":"venue"
},
  "geometry": {"coordinates":[10.8643093109,51.3702735901],"type":"Point"}
}