{
  "type": "Feature",
  "properties": {
    "iso:country":"DE",
    "sg:address":"Papenburger Str. 1",
    "sg:city":"Leer",
    "sg:phone":"+49 491/71717",
    "sg:postcode":"26789",
    "sg:province":"Niedersachsen",
    "wof:name":"Mc Donalds",
    "wof:placetype":"venue"
},
  "geometry": {"coordinates":[7.4758877754,53.2346916199],"type":"Point"}
}