{
  "type": "Feature",
  "properties": {
    "iso:country":"DE",
    "sg:address":"Liebigstr. 6",
    "sg:city":"M\u00fcnchen",
    "sg:phone":"+49 89/29164160",
    "sg:postcode":"80538",
    "sg:province":"Bayern",
    "wof:name":"Park And Ride Sportartikel Und Warenvertriebs Gmbh",
    "wof:placetype":"venue"
},
  "geometry": {"coordinates":[11.5867996216,48.1412963867],"type":"Point"}
}