{
  "type": "Feature",
  "properties": {
    "iso:country":"DE",
    "sg:address":"Emscherweg 11",
    "sg:city":"Holzwickede",
    "sg:phone":"+49 2301/12571",
    "sg:postcode":"59439",
    "sg:province":"Nordrhein-Westfalen",
    "wof:name":"Heinrich Spiekermann",
    "wof:placetype":"venue"
},
  "geometry": {"coordinates":[7.614129,51.49773],"type":"Point"}
}