{
  "type": "Feature",
  "properties": {
    "iso:country":"DE",
    "sg:address":"Beutlingsallee 10",
    "sg:city":"Melle",
    "sg:phone":"+49 5429/419",
    "sg:postcode":"49326",
    "sg:province":"Niedersachsen",
    "wof:name":"Unnerstall Holz- Verarbeitung Gmbh",
    "wof:placetype":"venue"
},
  "geometry": {"coordinates":[8.26702,52.152023],"type":"Point"}
}