{
  "type": "Feature",
  "properties": {
    "iso:country":"DE",
    "sg:address":"Tente 64",
    "sg:city":"Wermelskirchen",
    "sg:phone":"+49 2196/2005",
    "sg:postcode":"42929",
    "sg:province":"Nordrhein-Westfalen",
    "wof:name":"Kurt Radig",
    "wof:placetype":"venue"
},
  "geometry": {"coordinates":[7.1941170692,51.1247062683],"type":"Point"}
}