{
  "type": "Feature",
  "properties": {
    "iso:country":"DE",
    "sg:address":"Konstanzer Str. 2a",
    "sg:city":"Bielefeld",
    "sg:phone":"+49 521/9594999",
    "sg:postcode":"33659",
    "sg:province":"Nordrhein-Westfalen",
    "wof:name":"Handelsunternehmen Stadtlander Inh. Mark Stadtlander",
    "wof:placetype":"venue"
},
  "geometry": {"coordinates":[8.5566501617,51.9632530212],"type":"Point"}
}