{
  "type": "Feature",
  "properties": {
    "iso:country":"DE",
    "sg:address":"Schwarzbacherstrasse 2",
    "sg:city":"Wasungen",
    "sg:phone":"+49 4936/9417860",
    "sg:postcode":"98634",
    "sg:province":"Th\u00fcringen",
    "wof:name":"Aqua Bau Gmbh",
    "wof:placetype":"venue"
},
  "geometry": {"coordinates":[10.35557,50.664516],"type":"Point"}
}