{
  "type": "Feature",
  "properties": {
    "iso:country":"DE",
    "sg:address":"Markt 1",
    "sg:city":"St. Goar",
    "sg:phone":"+49 6741/1689",
    "sg:postcode":"56329",
    "sg:province":"Rheinland-Pfalz",
    "wof:name":"Hotel Am Markt",
    "wof:placetype":"venue"
},
  "geometry": {"coordinates":[7.7149481773,50.1506843567],"type":"Point"}
}