{
  "type": "Feature",
  "properties": {
    "iso:country":"DE",
    "sg:address":"Steindamm 38",
    "sg:city":"Bremen",
    "sg:phone":"+49 421/69330",
    "sg:postcode":"28719",
    "sg:province":"Bremen",
    "wof:name":"Trasco Export Gmbh",
    "wof:placetype":"venue"
},
  "geometry": {"coordinates":[8.7071790695,53.1610565186],"type":"Point"}
}