{
  "type": "Feature",
  "properties": {
    "iso:country":"DE",
    "sg:address":"Spielbruch 79",
    "sg:city":"Solingen",
    "sg:phone":"+49 212/3833200",
    "sg:postcode":"42659",
    "sg:province":"Nordrhein-Westfalen",
    "wof:name":"Proxxis Gmbh",
    "wof:placetype":"venue"
},
  "geometry": {"coordinates":[7.104628,51.157219],"type":"Point"}
}