{
  "type": "Feature",
  "properties": {
    "iso:country":"DE",
    "sg:address":"Schadewachten 46",
    "sg:city":"Stendal",
    "sg:phone":"+49 3931/212547",
    "sg:postcode":"39576",
    "sg:province":"Sachsen-Anhalt",
    "wof:name":"Otto Amtage",
    "wof:placetype":"venue"
},
  "geometry": {"coordinates":[11.8634748459,52.6015853882],"type":"Point"}
}