{
  "type": "Feature",
  "properties": {
    "iso:country":"DE",
    "sg:address":"Moorhof 4",
    "sg:city":"Liebenau",
    "sg:phone":"+49 5023/2179",
    "sg:postcode":"31618",
    "sg:province":"Niedersachsen",
    "wof:name":"Silvia Heise",
    "wof:placetype":"venue"
},
  "geometry": {"coordinates":[9.0956783295,52.60679245],"type":"Point"}
}