{
  "type": "Feature",
  "properties": {
    "iso:country":"DE",
    "sg:address":"Stummstr. 51",
    "sg:city":"Dillingen",
    "sg:phone":"+49 6831/703894",
    "sg:postcode":"66763",
    "sg:province":"Saarland",
    "wof:name":"Rudis Reste Rampe",
    "wof:placetype":"venue"
},
  "geometry": {"coordinates":[6.728407,49.35437],"type":"Point"}
}