{
  "type": "Feature",
  "properties": {
    "iso:country":"DE",
    "sg:address":"Pfeifferstr. 10",
    "sg:city":"Magdeburg",
    "sg:phone":"+49 391/8505140",
    "sg:postcode":"39114",
    "sg:province":"Sachsen-Anhalt",
    "wof:name":"Versorgungskasse F\u00fcr Die Schwesternschaft Des",
    "wof:placetype":"venue"
},
  "geometry": {"coordinates":[11.6644983292,52.1164169312],"type":"Point"}
}