{
  "type": "Feature",
  "properties": {
    "iso:country":"DE",
    "sg:address":"Bahnhofstr. 55",
    "sg:city":"Langenau",
    "sg:phone":"+49 7345/7639",
    "sg:postcode":"89129",
    "sg:province":"Baden-W\u00fcrttemberg",
    "wof:name":"H. Bischoff",
    "wof:placetype":"venue"
},
  "geometry": {"coordinates":[10.125314,48.494343],"type":"Point"}
}