{
  "type": "Feature",
  "properties": {
    "iso:country":"DE",
    "sg:address":"Kr\u00fcllsdyk",
    "sg:city":"Krefeld",
    "sg:phone":"+49 2151/758898",
    "sg:postcode":"47803",
    "sg:province":"Nordrhein-Westfalen",
    "wof:name":"Reiner Sagolla",
    "wof:placetype":"venue"
},
  "geometry": {"coordinates":[6.5628399849,51.3498954773],"type":"Point"}
}