{
  "type": "Feature",
  "properties": {
    "iso:country":"DE",
    "sg:address":"Ringstr. 25",
    "sg:city":"Bad Sooden-Allendorf",
    "sg:phone":"+49 5652/4904",
    "sg:postcode":"37242",
    "sg:province":"Hessen",
    "wof:name":"A. Lewetz",
    "wof:placetype":"venue"
},
  "geometry": {"coordinates":[9.9822130203,51.2666358948],"type":"Point"}
}