{
  "type": "Feature",
  "properties": {
    "iso:country":"DE",
    "sg:address":"Kaiserstr. 40",
    "sg:city":"W\u00fcrselen",
    "sg:phone":"+49 2405/2840",
    "sg:postcode":"52146",
    "sg:province":"Nordrhein-Westfalen",
    "wof:name":"Reiner Bahs Rechtsanwalt",
    "wof:placetype":"venue"
},
  "geometry": {"coordinates":[6.1313610077,50.820438385],"type":"Point"}
}