{
  "type": "Feature",
  "properties": {
    "iso:country":"DE",
    "sg:address":"Hochbergweg 11",
    "sg:city":"Heidenheim",
    "sg:phone":"+49 7321/45014",
    "sg:postcode":"89518",
    "sg:province":"Baden-W\u00fcrttemberg",
    "wof:name":"Hermann Junginger Ingenieur",
    "wof:placetype":"venue"
},
  "geometry": {"coordinates":[10.1329936981,48.6789703369],"type":"Point"}
}