{
  "type": "Feature",
  "properties": {
    "iso:country":"DE",
    "sg:address":"Rennbahnstr. 175",
    "sg:city":"Hamburg",
    "sg:phone":"+49 40/6522994",
    "sg:postcode":"22043",
    "sg:province":"Hamburg",
    "wof:name":"Peter Schipke",
    "wof:placetype":"venue"
},
  "geometry": {"coordinates":[10.0766334534,53.5662536621],"type":"Point"}
}