{
  "type": "Feature",
  "properties": {
    "iso:country":"DE",
    "sg:address":"Waldemarstr. 29",
    "sg:city":"Rathenow",
    "sg:phone":"+49 3385/503503",
    "sg:postcode":"14712",
    "sg:province":"Brandenburg",
    "wof:name":"T. Rohrlack Immobilienmakler",
    "wof:placetype":"venue"
},
  "geometry": {"coordinates":[12.3430843353,52.6075973511],"type":"Point"}
}