{
  "type": "Feature",
  "properties": {
    "iso:country":"DE",
    "sg:address":"Gasthauskanal 6",
    "sg:city":"Papenburg",
    "sg:phone":"+49 4961/2126",
    "sg:postcode":"26871",
    "sg:province":"Niedersachsen",
    "wof:name":"Restaurant Hilde Doeden",
    "wof:placetype":"venue"
},
  "geometry": {"coordinates":[7.4057788849,53.0758934021],"type":"Point"}
}