{
  "type": "Feature",
  "properties": {
    "iso:country":"DE",
    "sg:address":"J\u00e4gerstr. 36b",
    "sg:city":"L\u00fcnen",
    "sg:phone":"+49 2306/40225",
    "sg:postcode":"44532",
    "sg:province":"Nordrhein-Westfalen",
    "wof:name":"Fischer",
    "wof:placetype":"venue"
},
  "geometry": {"coordinates":[7.52027,51.584049],"type":"Point"}
}