{
  "type": "Feature",
  "properties": {
    "iso:country":"DE",
    "sg:address":"Ehrenbergstr 57",
    "sg:city":"Hamburg",
    "sg:phone":"+49 40/85374654",
    "sg:postcode":"22767",
    "sg:province":"Hamburg",
    "wof:name":"Dieckmann & Str\u00fcbing Inh. Albrecht Laue",
    "wof:placetype":"venue"
},
  "geometry": {"coordinates":[9.937726,53.549988],"type":"Point"}
}