{
  "type": "Feature",
  "properties": {
    "iso:country":"DE",
    "sg:address":"Gerichtstr. 8",
    "sg:city":"Meinerzhagen",
    "sg:phone":"+49 2354/2411",
    "sg:postcode":"58540",
    "sg:province":"Nordrhein-Westfalen",
    "wof:name":"Ernst Hassler Mech. Werkstatt",
    "wof:placetype":"venue"
},
  "geometry": {"coordinates":[7.643736,51.10527],"type":"Point"}
}