{
  "type": "Feature",
  "properties": {
    "iso:country":"DE",
    "sg:address":"Charles-H.-King-Str. 12",
    "sg:city":"Berlin",
    "sg:phone":"+49 30",
    "sg:postcode":"14163",
    "sg:province":"Berlin",
    "wof:name":"Idt-edelstahl",
    "wof:placetype":"venue"
},
  "geometry": {"coordinates":[13.2272119522,52.4295921326],"type":"Point"}
}