{
  "type": "Feature",
  "properties": {
    "iso:country":"DE",
    "sg:address":"Am Sch\u00f6nberg 8",
    "sg:city":"Merzhausen",
    "sg:phone":"+49 761/402648",
    "sg:postcode":"79249",
    "sg:province":"Baden-W\u00fcrttemberg",
    "wof:name":"Dr. Med. Ursula Schwertner",
    "wof:placetype":"venue"
},
  "geometry": {"coordinates":[7.8219327927,47.9638366699],"type":"Point"}
}