{
  "type": "Feature",
  "properties": {
    "iso:country":"DE",
    "sg:address":"Lindenring 14",
    "sg:city":"Pei\u00dfen",
    "sg:phone":"+49 345/7700243",
    "sg:postcode":"06188",
    "sg:province":"Sachsen-Anhalt",
    "wof:name":"Alfred Wardetzki",
    "wof:placetype":"venue"
},
  "geometry": {"coordinates":[12.0577421188,51.5015411377],"type":"Point"}
}