{
  "type": "Feature",
  "properties": {
    "iso:country":"DE",
    "sg:address":"Philippistr. 8",
    "sg:city":"Berlin",
    "sg:postcode":"14059",
    "sg:province":"Berlin",
    "wof:name":"H & P Consilium Et Auxilium Gesellschaft F\u00fcr Unternehmens-",
    "wof:placetype":"venue"
},
  "geometry": {"coordinates":[13.2867832184,52.5111618042],"type":"Point"}
}