{
  "type": "Feature",
  "properties": {
    "iso:country":"DE",
    "sg:address":"Siemensstr. 1",
    "sg:city":"Asperg",
    "sg:phone":"+49 7141/681160",
    "sg:postcode":"71679",
    "sg:province":"Baden-W\u00fcrttemberg",
    "wof:name":"Cleanpart Gmbh",
    "wof:placetype":"venue"
},
  "geometry": {"coordinates":[9.156177,48.8979],"type":"Point"}
}