{
  "type": "Feature",
  "properties": {
    "iso:country":"DE",
    "sg:address":"J\u00e4gerpfad",
    "sg:city":"Morschen",
    "sg:postcode":"34326",
    "sg:province":"Hessen",
    "wof:name":"Mehrzweckhalle Altmorschen",
    "wof:placetype":"venue"
},
  "geometry": {"coordinates":[9.617614,51.069843],"type":"Point"}
}