{
  "type": "Feature",
  "properties": {
    "iso:country":"DE",
    "sg:address":"Frankenstra\u00dfe 7",
    "sg:city":"Hamburg",
    "sg:phone":"+49 40/23890111",
    "sg:postcode":"20097",
    "sg:province":"Hamburg",
    "wof:name":"Rms Radio Marketing Service",
    "wof:placetype":"venue"
},
  "geometry": {"coordinates":[10.023571,53.548321],"type":"Point"}
}