{
  "type": "Feature",
  "properties": {
    "iso:country":"DE",
    "sg:address":"Oststr. 5",
    "sg:city":"Leipzig",
    "sg:postcode":"04317",
    "sg:province":"Sachsen",
    "wof:name":"Gfip Gesellschaft F\u00fcr Immobilien-management",
    "wof:placetype":"venue"
},
  "geometry": {"coordinates":[12.396847,51.332314],"type":"Point"}
}