{
  "type": "Feature",
  "properties": {
    "iso:country":"DE",
    "sg:address":"Zaucheweg 4",
    "sg:city":"Leipzig",
    "sg:phone":"+49 341/6517781",
    "sg:postcode":"04316",
    "sg:province":"Sachsen",
    "wof:name":"Krause Rollst\u00fchle Gmbh & Co. Kg",
    "wof:placetype":"venue"
},
  "geometry": {"coordinates":[12.490434,51.322449],"type":"Point"}
}