{
  "type": "Feature",
  "properties": {
    "iso:country":"DE",
    "sg:address":"Austr. 4",
    "sg:city":"St Georgen",
    "sg:phone":"+49 8669/2355",
    "sg:postcode":"83368",
    "sg:province":"Bayern",
    "wof:name":"Johann Magg",
    "wof:placetype":"venue"
},
  "geometry": {"coordinates":[12.565597,47.969597],"type":"Point"}
}