{
  "type": "Feature",
  "properties": {
    "iso:country":"DE",
    "sg:address":"Uracher Str. 7",
    "sg:city":"H\u00fclben",
    "sg:phone":"+49 7125/5733",
    "sg:postcode":"72584",
    "sg:province":"Baden-W\u00fcrttemberg",
    "wof:name":"Christof Beck Spielwaren Gmbh",
    "wof:placetype":"venue"
},
  "geometry": {"coordinates":[9.4074754715,48.5180664062],"type":"Point"}
}