{
  "type": "Feature",
  "properties": {
    "iso:country":"DE",
    "sg:address":"Breitendieler Str. 43",
    "sg:city":"Miltenberg",
    "sg:phone":"+49 9371/5152",
    "sg:postcode":"63897",
    "sg:province":"Bayern",
    "wof:name":"Br\u00e4utigam-baumarkt",
    "wof:placetype":"venue"
},
  "geometry": {"coordinates":[9.2264556885,49.7021560669],"type":"Point"}
}