{
  "type": "Feature",
  "properties": {
    "iso:country":"DE",
    "sg:address":"Meerkircher Str. 13",
    "sg:city":"Ovelg\u00f6nne",
    "sg:phone":"+49 4483/255",
    "sg:postcode":"26939",
    "sg:province":"Niedersachsen",
    "wof:name":"Gerhard Meins",
    "wof:placetype":"venue"
},
  "geometry": {"coordinates":[8.3100728989,53.2631568909],"type":"Point"}
}