{
  "type": "Feature",
  "properties": {
    "iso:country":"DE",
    "sg:address":"Oberstr. 25",
    "sg:city":"R\u00fcdesheim am Rhein",
    "sg:phone":"+49 6722/4635",
    "sg:postcode":"65385",
    "sg:province":"Hessen",
    "wof:name":"Engelbert Hess Weinanbau",
    "wof:placetype":"venue"
},
  "geometry": {"coordinates":[7.919298172,49.9790153503],"type":"Point"}
}