{
  "type": "Feature",
  "properties": {
    "iso:country":"DE",
    "sg:address":"Am Steinbruch",
    "sg:city":"Kulmbach",
    "sg:phone":"+49 9261/3421",
    "sg:postcode":"95326",
    "sg:province":"Bayern",
    "wof:name":"Karl Heublein Gmbh",
    "wof:placetype":"venue"
},
  "geometry": {"coordinates":[11.4835577011,50.1206741333],"type":"Point"}
}