{
  "type": "Feature",
  "properties": {
    "iso:country":"DE",
    "sg:address":"Hinrich-Fehrs-Str. 12",
    "sg:city":"Quickborn",
    "sg:phone":"+49 4106/72570",
    "sg:postcode":"25451",
    "sg:province":"Schleswig-Holstein",
    "wof:name":"Eroticats Dieter Lohmann",
    "wof:placetype":"venue"
},
  "geometry": {"coordinates":[9.956628,53.751995],"type":"Point"}
}