{
  "type": "Feature",
  "properties": {
    "iso:country":"DE",
    "sg:address":"Fuldatalstra\u00dfe 12",
    "sg:city":"Kassel",
    "sg:phone":"+49 561",
    "sg:postcode":"34125",
    "sg:province":"Hessen",
    "wof:name":"Ines Energie Systeme Gmbh, Kassel",
    "wof:placetype":"venue"
},
  "geometry": {"coordinates":[9.517976,51.325619],"type":"Point"}
}