{
  "type": "Feature",
  "properties": {
    "iso:country":"DE",
    "sg:address":"Baurenfeldstr. 4",
    "sg:city":"St\u00f6dtlen",
    "sg:phone":"+49 7964/2141",
    "sg:postcode":"73495",
    "sg:province":"Baden-W\u00fcrttemberg",
    "wof:name":"K. Bach",
    "wof:placetype":"venue"
},
  "geometry": {"coordinates":[10.3277740479,49.0178031921],"type":"Point"}
}