{
  "type": "Feature",
  "properties": {
    "iso:country":"DE",
    "sg:address":"Harburger Rathauspassage",
    "sg:city":"Hamburg",
    "sg:phone":"+49 40/773190",
    "sg:postcode":"21073",
    "sg:province":"Hamburg",
    "wof:name":"Pehm\u00f6ller Bauelemente Gmbh",
    "wof:placetype":"venue"
},
  "geometry": {"coordinates":[9.979725,53.458729],"type":"Point"}
}