{
  "type": "Feature",
  "properties": {
    "iso:country":"DE",
    "sg:address":"Fabrikstr. 28",
    "sg:city":"Bissingen",
    "sg:phone":"+49 7023/6282",
    "sg:postcode":"73266",
    "sg:province":"Baden-W\u00fcrttemberg",
    "wof:name":"R. W. Reichel Ingenieur",
    "wof:placetype":"venue"
},
  "geometry": {"coordinates":[9.4933023453,48.6053924561],"type":"Point"}
}