{
  "type": "Feature",
  "properties": {
    "iso:country":"DE",
    "sg:address":"Knappstr. 27",
    "sg:city":"Dortmund",
    "sg:phone":"+49 2304/80323",
    "sg:postcode":"44267",
    "sg:province":"Nordrhein-Westfalen",
    "wof:name":"J\u00e4ger Gmbh & Co. Kg Fernmeldeanlagenbau",
    "wof:placetype":"venue"
},
  "geometry": {"coordinates":[7.530687809,51.4582328796],"type":"Point"}
}