{
  "type": "Feature",
  "properties": {
    "iso:country":"DE",
    "sg:address":"Siempelkampstr. 50",
    "sg:city":"Krefeld",
    "sg:postcode":"47803",
    "sg:province":"Nordrhein-Westfalen",
    "wof:name":"Bws Fensterbau Gmbh",
    "wof:placetype":"venue"
},
  "geometry": {"coordinates":[6.531116,51.351475],"type":"Point"}
}