{
  "type": "Feature",
  "properties": {
    "iso:country":"DE",
    "sg:address":"Sandstr. 13",
    "sg:city":"D\u00fclmen",
    "sg:phone":"+49 2594/82123",
    "sg:postcode":"48249",
    "sg:province":"Nordrhein-Westfalen",
    "wof:name":"Sportsch\u00e4nke",
    "wof:placetype":"venue"
},
  "geometry": {"coordinates":[7.2469210625,51.8074836731],"type":"Point"}
}