{
  "type": "Feature",
  "properties": {
    "iso:country":"DE",
    "sg:address":"St\u00fcttekofener Str. 77",
    "sg:city":"Leverkusen",
    "sg:phone":"+49 214/505072",
    "sg:postcode":"51375",
    "sg:province":"Nordrhein-Westfalen",
    "wof:name":"Thadd\u00e4us Mykita",
    "wof:placetype":"venue"
},
  "geometry": {"coordinates":[7.0412268639,51.0403862],"type":"Point"}
}