{
  "type": "Feature",
  "properties": {
    "iso:country":"DE",
    "sg:address":"Rottweiler Str. 29",
    "sg:city":"Villingendorf",
    "sg:phone":"+49 741/31197",
    "sg:postcode":"78667",
    "sg:province":"Baden-W\u00fcrttemberg",
    "wof:name":"Hubertushof",
    "wof:placetype":"venue"
},
  "geometry": {"coordinates":[8.5936946869,48.1980895996],"type":"Point"}
}