{
  "type": "Feature",
  "properties": {
    "iso:country":"DE",
    "sg:address":"Murrstr. 17",
    "sg:city":"Kornwestheim",
    "sg:phone":"+49 7154/7720",
    "sg:postcode":"70806",
    "sg:province":"Baden-W\u00fcrttemberg",
    "wof:name":"Rudolf Gaulrapp",
    "wof:placetype":"venue"
},
  "geometry": {"coordinates":[9.208516,48.863014],"type":"Point"}
}