{
  "type": "Feature",
  "properties": {
    "iso:country":"DE",
    "sg:city":"Berlin",
    "sg:postcode":"13088",
    "sg:province":"Berlin",
    "wof:name":"Norbert Metzger",
    "wof:placetype":"venue"
},
  "geometry": {"coordinates":[13.467727,52.561069],"type":"Point"}
}