{
  "type": "Feature",
  "properties": {
    "iso:country":"DE",
    "sg:address":"Hauptstr. 50",
    "sg:city":"Ostramondra",
    "sg:phone":"+49 36378/5957",
    "sg:postcode":"99636",
    "sg:province":"Th\u00fcringen",
    "wof:name":"Bernd Nauhardt",
    "wof:placetype":"venue"
},
  "geometry": {"coordinates":[11.327104,51.198486],"type":"Point"}
}