{
  "type": "Feature",
  "properties": {
    "iso:country":"DE",
    "sg:address":"Rothgerberbach 5",
    "sg:city":"K\u00f6ln",
    "sg:phone":"+49 221/252045",
    "sg:postcode":"50676",
    "sg:province":"Nordrhein-Westfalen",
    "wof:name":"Westdeutsche Zucker- Vertriebs Gmbh",
    "wof:placetype":"venue"
},
  "geometry": {"coordinates":[6.9506487846,50.930355072],"type":"Point"}
}