{
  "type": "Feature",
  "properties": {
    "iso:country":"DE",
    "sg:address":"Wilhelmstr. 17",
    "sg:city":"Bad Kreuznach",
    "sg:phone":"+49 671/35223",
    "sg:postcode":"55543",
    "sg:province":"Rheinland-Pfalz",
    "wof:name":"Haubrich & Partner",
    "wof:placetype":"venue"
},
  "geometry": {"coordinates":[7.8620219231,49.8445167542],"type":"Point"}
}