{
  "type": "Feature",
  "properties": {
    "iso:country":"DE",
    "sg:address":"Bismarckstr. 122",
    "sg:city":"V\u00f6lklingen",
    "sg:phone":"+49 6898/26500",
    "sg:postcode":"66333",
    "sg:province":"Saarland",
    "wof:name":"H\u00fcttensch\u00e4nke",
    "wof:placetype":"venue"
},
  "geometry": {"coordinates":[6.8484759331,49.2550354004],"type":"Point"}
}