{
  "type": "Feature",
  "properties": {
    "iso:country":"DE",
    "sg:address":"Goethestr. 12",
    "sg:city":"M\u00fccke",
    "sg:phone":"+49 6400/5357",
    "sg:postcode":"35325",
    "sg:province":"Hessen",
    "wof:name":"Bernd Richter",
    "wof:placetype":"venue"
},
  "geometry": {"coordinates":[9.11366,50.616253],"type":"Point"}
}