{
  "type": "Feature",
  "properties": {
    "iso:country":"DE",
    "sg:address":"Am Holtkamp 36",
    "sg:city":"Bochum",
    "sg:phone":"+49 234/471728",
    "sg:postcode":"44795",
    "sg:province":"Nordrhein-Westfalen",
    "wof:name":"Holtkampsch\u00e4nke",
    "wof:placetype":"venue"
},
  "geometry": {"coordinates":[7.1990599632,51.4390068054],"type":"Point"}
}