{
  "type": "Feature",
  "properties": {
    "iso:country":"DE",
    "sg:address":"R\u00fcstringer Str. 22",
    "sg:city":"Bremen",
    "sg:phone":"+49 421/3807540",
    "sg:postcode":"28219",
    "sg:province":"Bremen",
    "wof:name":"Ingeborg V\u00f6ge-boelen",
    "wof:placetype":"venue"
},
  "geometry": {"coordinates":[8.780168,53.100948],"type":"Point"}
}