{
  "type": "Feature",
  "properties": {
    "iso:country":"DE",
    "sg:address":"Liedbachstr. 33",
    "sg:city":"Unna",
    "sg:postcode":"59427",
    "sg:province":"Nordrhein-Westfalen",
    "wof:name":"Le Four Industriel Belge Deutschland Gmbh",
    "wof:placetype":"venue"
},
  "geometry": {"coordinates":[7.669213,51.502224],"type":"Point"}
}