{
  "type": "Feature",
  "properties": {
    "iso:country":"DE",
    "sg:address":"G\u00e4rtnereiweg 7",
    "sg:city":"Glauchau",
    "sg:phone":"+49 3763/5674",
    "sg:postcode":"08371",
    "sg:province":"Sachsen",
    "wof:name":"H. Schmidt",
    "wof:placetype":"venue"
},
  "geometry": {"coordinates":[12.5435819626,50.8113555908],"type":"Point"}
}