{
  "type": "Feature",
  "properties": {
    "iso:country":"DE",
    "sg:address":"Am Flutgraben 9",
    "sg:city":"K\u00f6ln",
    "sg:postcode":"51067",
    "sg:province":"Nordrhein-Westfalen",
    "wof:name":"Nbs Dienstleistungen Gmbh",
    "wof:placetype":"venue"
},
  "geometry": {"coordinates":[7.036909,50.964573],"type":"Point"}
}