{
  "type": "Feature",
  "properties": {
    "iso:country":"DE",
    "sg:address":"Theaterstr. 5",
    "sg:city":"D\u00f6beln",
    "sg:phone":"+49 3431/716020",
    "sg:postcode":"04720",
    "sg:province":"Sachsen",
    "wof:name":"Kowa Handelsgenossenschaft D\u00f6beln Eg",
    "wof:placetype":"venue"
},
  "geometry": {"coordinates":[13.1173849106,51.1206169128],"type":"Point"}
}