{
  "type": "Feature",
  "properties": {
    "iso:country":"DE",
    "sg:address":"Am Kesselbergweg 2 d",
    "sg:city":"Eystrup",
    "sg:phone":"+49 4254/723",
    "sg:postcode":"27324",
    "sg:province":"Niedersachsen",
    "wof:name":"Wilhelm Alhusen",
    "wof:placetype":"venue"
},
  "geometry": {"coordinates":[9.205943,52.780342],"type":"Point"}
}