{
  "type": "Feature",
  "properties": {
    "iso:country":"DE",
    "sg:address":"Hohenzollerndamm 105",
    "sg:city":"Berlin",
    "sg:postcode":"14199",
    "sg:province":"Berlin",
    "wof:name":"Provaluta Verm\u00f6gens- Verwaltung Gmbh",
    "wof:placetype":"venue"
},
  "geometry": {"coordinates":[13.281605,52.477009],"type":"Point"}
}