{
  "type": "Feature",
  "properties": {
    "iso:country":"DE",
    "sg:address":"Kurmainzer Ring 43",
    "sg:city":"Sulzbach",
    "sg:phone":"+49 6028/1532",
    "sg:postcode":"63834",
    "sg:province":"Bayern",
    "wof:name":"Manfred Gessner E. K.",
    "wof:placetype":"venue"
},
  "geometry": {"coordinates":[9.1626253128,49.9074440002],"type":"Point"}
}