{
  "type": "Feature",
  "properties": {
    "iso:country":"DE",
    "sg:address":"Neckarstr. 37",
    "sg:city":"Bad Rappenau",
    "sg:phone":"+49 7264/5207",
    "sg:postcode":"74906",
    "sg:province":"Baden-W\u00fcrttemberg",
    "wof:name":"Rein Gmbh",
    "wof:placetype":"venue"
},
  "geometry": {"coordinates":[9.148323,49.262119],"type":"Point"}
}