{
  "type": "Feature",
  "properties": {
    "iso:country":"DE",
    "sg:address":"Kleiststr. 10",
    "sg:city":"K\u00f6ln",
    "sg:phone":"+49 221/552514",
    "sg:postcode":"50825",
    "sg:province":"Nordrhein-Westfalen",
    "wof:name":"Heinz Schallenberg",
    "wof:placetype":"venue"
},
  "geometry": {"coordinates":[6.916327,50.956455],"type":"Point"}
}