{
  "type": "Feature",
  "properties": {
    "iso:country":"DE",
    "sg:address":"Wesekerweg 38",
    "sg:city":"S\u00fcdlohn",
    "sg:phone":"+49 4966/2150400",
    "sg:postcode":"46354",
    "sg:province":"Nordrhein-Westfalen",
    "wof:name":"Schmelz U Webert",
    "wof:placetype":"venue"
},
  "geometry": {"coordinates":[9.717,50.861752],"type":"Point"}
}