{
  "type": "Feature",
  "properties": {
    "iso:country":"DE",
    "sg:address":"D\u00fcsseldorfer Str. 87",
    "sg:city":"Meerbusch",
    "sg:postcode":"40667",
    "sg:province":"Nordrhein-Westfalen",
    "wof:name":"Van Helden Gmbh",
    "wof:placetype":"venue"
},
  "geometry": {"coordinates":[6.698324,51.243618],"type":"Point"}
}