{
  "type": "Feature",
  "properties": {
    "iso:country":"DE",
    "sg:address":"Bierlingweg 14",
    "sg:city":"Landshut",
    "sg:phone":"+49 871/42227",
    "sg:postcode":"84036",
    "sg:province":"Bayern",
    "wof:name":"A. Hartl Hebamme",
    "wof:placetype":"venue"
},
  "geometry": {"coordinates":[12.143121,48.522503],"type":"Point"}
}