{
  "type": "Feature",
  "properties": {
    "iso:country":"DE",
    "sg:address":"Am H\u00e4ngelbach 2",
    "sg:city":"Bendorf",
    "sg:postcode":"56170",
    "sg:province":"Rheinland-Pfalz",
    "wof:name":"K\u00f6rber & Sacher Inh. Bernd Sacher E. K.",
    "wof:placetype":"venue"
},
  "geometry": {"coordinates":[7.5616559982,50.4261627197],"type":"Point"}
}