{
  "type": "Feature",
  "properties": {
    "iso:country":"DE",
    "sg:address":"Renatastr. 69",
    "sg:city":"M\u00fcnchen",
    "sg:phone":"+49 89/1688011",
    "sg:postcode":"80639",
    "sg:province":"Bayern",
    "wof:name":"Intelligenz Sys. Transfer Gmbh",
    "wof:placetype":"venue"
},
  "geometry": {"coordinates":[11.5265035629,48.1561546326],"type":"Point"}
}