{
  "type": "Feature",
  "properties": {
    "iso:country":"DE",
    "sg:address":"Laizer Str. 3",
    "sg:city":"Sigmaringen",
    "sg:postcode":"72488",
    "sg:province":"Baden-W\u00fcrttemberg",
    "wof:name":"Aralcenter Karl Stenzel",
    "wof:placetype":"venue"
},
  "geometry": {"coordinates":[9.212515831,48.0865898132],"type":"Point"}
}