{
  "type": "Feature",
  "properties": {
    "iso:country":"DE",
    "sg:address":"Bahnhofstr. 17",
    "sg:city":"Gr\u00fcnhain",
    "sg:phone":"+49 4937/74520",
    "sg:postcode":"08358",
    "wof:name":"Elektromotorenwerk Gr\u00dcnhain Gmbh & Co Kg",
    "wof:placetype":"venue"
},
  "geometry": {"coordinates":[12.808052,50.580841],"type":"Point"}
}