{
  "type": "Feature",
  "properties": {
    "iso:country":"DE",
    "sg:address":"Industriestr. 18",
    "sg:city":"Hauzenberg",
    "sg:phone":"+49 8586/96110",
    "sg:postcode":"94051",
    "sg:province":"Bayern",
    "wof:name":"Penninger Gmbh",
    "wof:placetype":"venue"
},
  "geometry": {"coordinates":[13.6360712051,48.626991272],"type":"Point"}
}