{
  "type": "Feature",
  "properties": {
    "iso:country":"DE",
    "sg:address":"Zum Stadion 1",
    "sg:city":"Mosbach",
    "sg:phone":"+49 6261/7406",
    "sg:postcode":"74821",
    "sg:province":"Baden-W\u00fcrttemberg",
    "wof:name":"Gastst\u00e4tte Elzstadion",
    "wof:placetype":"venue"
},
  "geometry": {"coordinates":[9.1144075394,49.3447380066],"type":"Point"}
}