{
  "type": "Feature",
  "properties": {
    "iso:country":"DE",
    "sg:address":"Windscheidstr. 2",
    "sg:city":"Leipzig",
    "sg:phone":"+49 341/30310",
    "sg:postcode":"04277",
    "sg:province":"Sachsen",
    "wof:name":"Skorrupa Altmann Zimmermann Und Partner Gbr",
    "wof:placetype":"venue"
},
  "geometry": {"coordinates":[12.3682022095,51.3142127991],"type":"Point"}
}