{
  "type": "Feature",
  "properties": {
    "iso:country":"DE",
    "sg:address":"Holzbachtalstr. 326",
    "sg:city":"Straubenhardt",
    "sg:phone":"+49 7248/932593",
    "sg:postcode":"75334",
    "sg:province":"Baden-W\u00fcrttemberg",
    "wof:name":"Brodbeck Verwaltungs- Gmbh",
    "wof:placetype":"venue"
},
  "geometry": {"coordinates":[8.5075483322,48.8185920715],"type":"Point"}
}