{
  "type": "Feature",
  "properties": {
    "iso:country":"DE",
    "sg:address":"Kl\u00f6nnestr. 90",
    "sg:city":"Dortmund",
    "sg:phone":"+49 231/551339",
    "sg:postcode":"44143",
    "sg:province":"Nordrhein-Westfalen",
    "wof:name":"Jet-tankstelle",
    "wof:placetype":"venue"
},
  "geometry": {"coordinates":[7.4880337715,51.5193710327],"type":"Point"}
}