{
  "type": "Feature",
  "properties": {
    "iso:country":"DE",
    "sg:address":"Stra\u00dfe 621 Nr.31",
    "sg:city":"Berlin",
    "sg:phone":"+49 30/74374701",
    "sg:postcode":"12349",
    "sg:province":"Berlin",
    "wof:name":"Berlin-ballons - Ihr Fachmann F\u00fcr Ballondekoration",
    "wof:placetype":"venue"
},
  "geometry": {"coordinates":[13.429461,52.421322],"type":"Point"}
}