{
  "type": "Feature",
  "properties": {
    "iso:country":"DE",
    "sg:address":"Genh\u00fclsen 210",
    "sg:city":"M\u00f6nchengladbach",
    "sg:postcode":"41179",
    "sg:province":"Nordrhein-Westfalen",
    "wof:name":"Hammerschmidt Malerbetrieb Verwaltungs Gmbh",
    "wof:placetype":"venue"
},
  "geometry": {"coordinates":[6.401112,51.154339],"type":"Point"}
}