{
  "type": "Feature",
  "properties": {
    "iso:country":"DE",
    "sg:address":"Mathildenstr. 34",
    "sg:city":"Saarbr\u00fccken",
    "sg:phone":"+49 681/54437",
    "sg:postcode":"66128",
    "sg:province":"Saarland",
    "wof:name":"Heinrich Bandel Architekt",
    "wof:placetype":"venue"
},
  "geometry": {"coordinates":[6.903523,49.238834],"type":"Point"}
}