{
  "type": "Feature",
  "properties": {
    "iso:country":"DE",
    "sg:address":"Karl-Liebknecht-Str. 17",
    "sg:city":"Deuben",
    "sg:phone":"+49 34441/4290",
    "sg:postcode":"06682",
    "sg:province":"Sachsen-Anhalt",
    "wof:name":"Ifw Ingenieurgesellschaft F\u00fcr W\u00e4rmetechnik Mbh",
    "wof:placetype":"venue"
},
  "geometry": {"coordinates":[12.0725603104,51.1145744324],"type":"Point"}
}