{
  "type": "Feature",
  "properties": {
    "iso:country":"DE",
    "sg:address":"Nesselrodeweg 45",
    "sg:city":"Gelsenkirchen",
    "sg:phone":"+49 209/9772316",
    "sg:postcode":"45891",
    "sg:province":"Nordrhein-Westfalen",
    "wof:name":"Aco",
    "wof:placetype":"venue"
},
  "geometry": {"coordinates":[7.092502,51.566147],"type":"Point"}
}