{
  "type": "Feature",
  "properties": {
    "iso:country":"DE",
    "sg:address":"Hopfelder Str. 14",
    "sg:city":"Hessisch Lichtenau",
    "sg:phone":"+49 5602/4808",
    "sg:postcode":"37235",
    "sg:province":"Hessen",
    "wof:name":"Dieter Eisel Elektroinstallation",
    "wof:placetype":"venue"
},
  "geometry": {"coordinates":[9.72196,51.19437],"type":"Point"}
}