{
  "type": "Feature",
  "properties": {
    "iso:country":"DE",
    "sg:address":"Dr.-Wilhelm-K\u00fclz-Str 10",
    "sg:city":"M\u00fccheln",
    "sg:phone":"+49 5427/921080",
    "sg:postcode":"06249",
    "sg:province":"Sachsen-Anhalt",
    "wof:name":"Spedition Georg Dankmeyer",
    "wof:placetype":"venue"
},
  "geometry": {"coordinates":[8.4167852402,52.2896347046],"type":"Point"}
}