{
  "type": "Feature",
  "properties": {
    "iso:country":"DE",
    "sg:address":"Am Hinterweg 26",
    "sg:city":"Herxheim",
    "sg:phone":"+49 7276/7297",
    "sg:postcode":"76863",
    "sg:province":"Rheinland-Pfalz",
    "wof:name":"Arnulf Ohmer & Boxheimer Architekten",
    "wof:placetype":"venue"
},
  "geometry": {"coordinates":[8.225445,49.150864],"type":"Point"}
}