{
  "type": "Feature",
  "properties": {
    "iso:country":"DE",
    "sg:address":"Hauptstr. 50",
    "sg:city":"Holzwickede",
    "sg:phone":"+49 4902/3013056",
    "sg:postcode":"59439",
    "sg:province":"Nordrhein-Westfalen",
    "wof:name":"Optik Und Akustik Mosbach",
    "wof:placetype":"venue"
},
  "geometry": {"coordinates":[7.615686,51.50021],"type":"Point"}
}