{
  "type": "Feature",
  "properties": {
    "iso:country":"DE",
    "sg:address":"Zur Dicken Linde 62",
    "sg:city":"Oelde",
    "sg:phone":"+49 2522/4173",
    "sg:postcode":"59302",
    "sg:province":"Nordrhein-Westfalen",
    "wof:name":"Hermann Feldmeier",
    "wof:placetype":"venue"
},
  "geometry": {"coordinates":[8.1541175842,51.8221092224],"type":"Point"}
}