{
  "type": "Feature",
  "properties": {
    "iso:country":"DE",
    "sg:address":"Hauptstr. 53",
    "sg:city":"Gro\u00dfbothen",
    "sg:phone":"+49 34384/71313",
    "sg:postcode":"04668",
    "sg:province":"Sachsen",
    "wof:name":"Verwaltungsges. Gro\u00dfbothener",
    "wof:placetype":"venue"
},
  "geometry": {"coordinates":[12.742843,51.187477],"type":"Point"}
}