{
  "type": "Feature",
  "properties": {
    "iso:country":"DE",
    "sg:address":"Syker Str. 118",
    "sg:city":"Delmenhorst",
    "sg:phone":"+49 4221/70408",
    "sg:postcode":"27751",
    "sg:province":"Niedersachsen",
    "wof:name":"Pizzeria Sardegna",
    "wof:placetype":"venue"
},
  "geometry": {"coordinates":[8.657740593,53.0491790771],"type":"Point"}
}