{
  "type": "Feature",
  "properties": {
    "iso:country":"DE",
    "sg:address":"Schlo\u00dfplatz 3",
    "sg:city":"Ballenstedt",
    "sg:phone":"+49 39483/82412",
    "sg:postcode":"06493",
    "sg:province":"Sachsen-Anhalt",
    "wof:name":"Restaurant Im Schlo\u00df",
    "wof:placetype":"venue"
},
  "geometry": {"coordinates":[11.2369832993,51.7208862305],"type":"Point"}
}