{
  "type": "Feature",
  "properties": {
    "iso:country":"DE",
    "sg:address":"Hauptstr.",
    "sg:city":"Neugersdorf",
    "sg:phone":"+49 3586/32123",
    "sg:postcode":"02727",
    "sg:province":"Sachsen",
    "wof:name":"Margit Klenert",
    "wof:placetype":"venue"
},
  "geometry": {"coordinates":[14.6122512817,50.9821739197],"type":"Point"}
}