{
  "type": "Feature",
  "properties": {
    "iso:country":"DE",
    "sg:address":"Bremhof 2 A",
    "sg:city":"Michelstadt",
    "sg:phone":"+49 6066/682",
    "sg:postcode":"64720",
    "sg:province":"Hessen",
    "wof:name":"Einkehr Bremhof",
    "wof:placetype":"venue"
},
  "geometry": {"coordinates":[9.1125669479,49.7312812805],"type":"Point"}
}