{
  "type": "Feature",
  "properties": {
    "iso:country":"DE",
    "sg:address":"Im L\u00e4nderrain 41",
    "sg:city":"Tamm",
    "sg:phone":"+49 7141/604188",
    "sg:postcode":"71732",
    "sg:province":"Baden-W\u00fcrttemberg",
    "wof:name":"Schreinerei Und Innenausbau Zezelj Gmbh",
    "wof:placetype":"venue"
},
  "geometry": {"coordinates":[9.125758,48.916664],"type":"Point"}
}