{
  "type": "Feature",
  "properties": {
    "iso:country":"DE",
    "sg:address":"Kantstrasse 36",
    "sg:city":"Heusenstamm",
    "sg:phone":"+49 6104/101177",
    "sg:postcode":"63150",
    "sg:province":"Hessen",
    "wof:name":"Medienberatung Torsten Jaschek",
    "wof:placetype":"venue"
},
  "geometry": {"coordinates":[8.795782,50.054897],"type":"Point"}
}