{
  "type": "Feature",
  "properties": {
    "iso:country":"DE",
    "sg:address":"Kornstr. 309",
    "sg:city":"Bremen",
    "sg:phone":"+49 421/536475",
    "sg:postcode":"28201",
    "sg:province":"Bremen",
    "wof:name":"Schmidt Gmbh & Co. Kg",
    "wof:placetype":"venue"
},
  "geometry": {"coordinates":[8.814382,53.054932],"type":"Point"}
}