{
  "type": "Feature",
  "properties": {
    "iso:country":"DE",
    "sg:address":"Norbertuskirchplatz 6",
    "sg:city":"Duisburg",
    "sg:phone":"+49 203/580648",
    "sg:postcode":"47166",
    "sg:province":"Nordrhein-Westfalen",
    "wof:name":"Kath. Pfarramt St. Norbert",
    "wof:placetype":"venue"
},
  "geometry": {"coordinates":[6.7837982178,51.4985733032],"type":"Point"}
}