{
  "type": "Feature",
  "properties": {
    "iso:country":"DE",
    "sg:address":"Bitterfelder Str. 63",
    "sg:city":"Delitzsch",
    "sg:phone":"+49 34202/63953",
    "sg:postcode":"04509",
    "sg:province":"Sachsen",
    "wof:name":"J\u00fcrgen Haynitzsch",
    "wof:placetype":"venue"
},
  "geometry": {"coordinates":[12.33585,51.533058],"type":"Point"}
}