{
  "type": "Feature",
  "properties": {
    "iso:country":"DE",
    "sg:address":"Zum Seegrund 2",
    "sg:city":"Bad Driburg",
    "sg:phone":"+49 5259/1030",
    "sg:postcode":"33014",
    "sg:province":"Nordrhein-Westfalen",
    "wof:name":"Rodemeyer-klee Immobilien Rdm",
    "wof:placetype":"venue"
},
  "geometry": {"coordinates":[9.0552625656,51.6731109619],"type":"Point"}
}