{
  "type": "Feature",
  "properties": {
    "iso:country":"DE",
    "sg:address":"Butzbacher Str. 16",
    "sg:city":"Lich",
    "sg:phone":"+49 6004/507",
    "sg:postcode":"35423",
    "sg:province":"Hessen",
    "wof:name":"Gerd Wedemann",
    "wof:placetype":"venue"
},
  "geometry": {"coordinates":[8.7591104507,50.4761886597],"type":"Point"}
}