{
  "type": "Feature",
  "properties": {
    "iso:country":"DE",
    "sg:address":"Hauptstr. 35",
    "sg:city":"Schmalenberg",
    "sg:phone":"+49 4963/076059",
    "sg:postcode":"67718",
    "sg:province":"Rheinland-Pfalz",
    "wof:name":"Raiffeisenbank Waldfischbach Eg",
    "wof:placetype":"venue"
},
  "geometry": {"coordinates":[7.730032,49.331429],"type":"Point"}
}