{
  "type": "Feature",
  "properties": {
    "iso:country":"DE",
    "sg:address":"Hauptstr. 29",
    "sg:city":"Busenberg",
    "sg:phone":"+49 6391/993217",
    "sg:postcode":"76891",
    "sg:province":"Rheinland-Pfalz",
    "wof:name":"Frank Weis Justus W\u00e4rmetechnik Gmbh",
    "wof:placetype":"venue"
},
  "geometry": {"coordinates":[7.8302698135,49.1303405762],"type":"Point"}
}