{
  "type": "Feature",
  "properties": {
    "iso:country":"DE",
    "sg:address":"W\u00fcrzburger Str. 8a",
    "sg:city":"Rimpar",
    "sg:phone":"+49 9365/9769",
    "sg:postcode":"97222",
    "sg:province":"Bayern",
    "wof:name":"Hilmar Senger",
    "wof:placetype":"venue"
},
  "geometry": {"coordinates":[9.97307,49.845654],"type":"Point"}
}