{
  "type": "Feature",
  "properties": {
    "iso:country":"DE",
    "sg:address":"Wilhelm-Busch-Str. 12",
    "sg:city":"Braunschweig",
    "sg:phone":"+49 531/78127",
    "sg:postcode":"38104",
    "sg:province":"Niedersachsen",
    "wof:name":"Volker Kuhnen Architekt",
    "wof:placetype":"venue"
},
  "geometry": {"coordinates":[10.556332,52.260307],"type":"Point"}
}