{
  "type": "Feature",
  "properties": {
    "iso:country":"DE",
    "sg:address":"B\u00e4ckerstr. 16",
    "sg:city":"Clausthal-Zellerfeld",
    "sg:phone":"+49 5323/82207",
    "sg:postcode":"38678",
    "sg:province":"Niedersachsen",
    "wof:name":"Gerhard Koch",
    "wof:placetype":"venue"
},
  "geometry": {"coordinates":[10.33512,51.818672],"type":"Point"}
}