{
  "type": "Feature",
  "properties": {
    "iso:country":"DE",
    "sg:address":"Waldstr. 23",
    "sg:city":"Triftern",
    "sg:phone":"+49 8562/1280",
    "sg:postcode":"84371",
    "sg:province":"Bayern",
    "wof:name":"Franz Allgeier",
    "wof:placetype":"venue"
},
  "geometry": {"coordinates":[13.027273,48.432972],"type":"Point"}
}