{
  "type": "Feature",
  "properties": {
    "iso:country":"DE",
    "sg:address":"Steinfeldweg 6",
    "sg:city":"Cham",
    "sg:postcode":"93413",
    "sg:province":"Bayern",
    "wof:name":"Spittler Andreas Handelsvertretung E. K.",
    "wof:placetype":"venue"
},
  "geometry": {"coordinates":[12.675487,49.178947],"type":"Point"}
}