{
  "type": "Feature",
  "properties": {
    "iso:country":"DE",
    "sg:address":"Otto-Hahn-Str. 14",
    "sg:city":"Rodgau",
    "sg:phone":"+49 6106/15155",
    "sg:postcode":"63110",
    "sg:province":"Hessen",
    "wof:name":"B\u00fcttner Gmbh",
    "wof:placetype":"venue"
},
  "geometry": {"coordinates":[8.8998146057,50.0241775513],"type":"Point"}
}