{
  "type": "Feature",
  "properties": {
    "iso:country":"DE",
    "sg:address":"Bahrenfelder Marktplatz 18",
    "sg:city":"Hamburg",
    "sg:phone":"+49 40/8100306",
    "sg:postcode":"22761",
    "sg:province":"Hamburg",
    "wof:name":"Tandberg Unterrichtstechnik-vertrieb Gmbh",
    "wof:placetype":"venue"
},
  "geometry": {"coordinates":[9.9011917114,53.5650100708],"type":"Point"}
}