{
  "type": "Feature",
  "properties": {
    "iso:country":"DE",
    "sg:address":"Theodor-Storm-Weg 5",
    "sg:city":"Ganderkesee",
    "sg:phone":"+49 4222/4000060",
    "sg:postcode":"27777",
    "sg:province":"Niedersachsen",
    "wof:name":"44u Marketing Und Internet Promotion",
    "wof:placetype":"venue"
},
  "geometry": {"coordinates":[8.5433998108,53.0450439453],"type":"Point"}
}