{
  "type": "Feature",
  "properties": {
    "iso:country":"DE",
    "sg:address":"Liptinger Str 10",
    "sg:city":"Eigeltingen",
    "sg:phone":"+49 7774/92200",
    "sg:postcode":"78253",
    "sg:province":"Baden-W\u00fcrttemberg",
    "wof:name":"W. Schmidt",
    "wof:placetype":"venue"
},
  "geometry": {"coordinates":[8.883884,47.896179],"type":"Point"}
}