{
  "type": "Feature",
  "properties": {
    "iso:country":"DE",
    "sg:address":"Kaiserstr. 17",
    "sg:city":"Lampertheim",
    "sg:phone":"+49 6206/912351",
    "sg:postcode":"68623",
    "sg:province":"Hessen",
    "wof:name":"Andreas D\u00f6rsam Rechtsanwalt",
    "wof:placetype":"venue"
},
  "geometry": {"coordinates":[8.4693145752,49.5952110291],"type":"Point"}
}