{
  "type": "Feature",
  "properties": {
    "iso:country":"DE",
    "sg:address":"Blankestr. 4",
    "sg:city":"Berlin",
    "sg:phone":"+49 30/4952018",
    "sg:postcode":"13403",
    "sg:province":"Berlin",
    "wof:name":"Kusian Wohnen Und Galerie Inh. Reinhard Kusian",
    "wof:placetype":"venue"
},
  "geometry": {"coordinates":[13.3300657272,52.5637512207],"type":"Point"}
}