{
  "type": "Feature",
  "properties": {
    "iso:country":"DE",
    "sg:address":"Waldstr. 25",
    "sg:city":"Uchte",
    "sg:phone":"+49 5763/2275",
    "sg:postcode":"31600",
    "sg:province":"Niedersachsen",
    "wof:name":"Horst-heinrich Winsel",
    "wof:placetype":"venue"
},
  "geometry": {"coordinates":[8.9050092697,52.4962272644],"type":"Point"}
}