{
  "type": "Feature",
  "properties": {
    "iso:country":"DE",
    "sg:address":"Langenforther Platz 1",
    "sg:city":"Langenhagen",
    "sg:phone":"+49 511/732026",
    "sg:postcode":"30853",
    "sg:province":"Niedersachsen",
    "wof:name":"Cafe Monopol",
    "wof:placetype":"venue"
},
  "geometry": {"coordinates":[9.7398300171,52.4406051636],"type":"Point"}
}