{
  "type": "Feature",
  "properties": {
    "iso:country":"DE",
    "sg:address":"Am Markt 6",
    "sg:city":"Gr\u00f6mitz",
    "sg:phone":"+49 4562/22760",
    "sg:postcode":"23743",
    "sg:province":"Schleswig-Holstein",
    "wof:name":"Hotel Restaurant Gosch",
    "wof:placetype":"venue"
},
  "geometry": {"coordinates":[10.9563455582,54.1509971619],"type":"Point"}
}