{
  "type": "Feature",
  "properties": {
    "iso:country":"DE",
    "sg:address":"Ranischbergstr. 2",
    "sg:city":"Isen",
    "sg:phone":"+49 8083/627",
    "sg:postcode":"84424",
    "sg:province":"Bayern",
    "wof:name":"Erwin Kirmeier",
    "wof:placetype":"venue"
},
  "geometry": {"coordinates":[12.060945,48.213642],"type":"Point"}
}