{
  "type": "Feature",
  "properties": {
    "iso:country":"DE",
    "sg:address":"Atzumer Weg 10",
    "sg:city":"Wolfenb\u00fcttel",
    "sg:phone":"+49 5331/72723",
    "sg:postcode":"38302",
    "sg:province":"Niedersachsen",
    "wof:name":"Rudi Geffers",
    "wof:placetype":"venue"
},
  "geometry": {"coordinates":[10.595891,52.175434],"type":"Point"}
}