{
  "type": "Feature",
  "properties": {
    "iso:country":"DE",
    "sg:address":"Schreckerstr. 16",
    "sg:city":"Duisburg",
    "sg:postcode":"47166",
    "sg:province":"Nordrhein-Westfalen",
    "wof:name":"Psg Parenteral Service Gmbh",
    "wof:placetype":"venue"
},
  "geometry": {"coordinates":[6.773001,51.491848],"type":"Point"}
}