{
  "type": "Feature",
  "properties": {
    "iso:country":"DE",
    "sg:address":"R\u00f6merstr. 8 a",
    "sg:city":"Haltern",
    "sg:phone":"+49 2364/7566",
    "sg:postcode":"45721",
    "sg:province":"Nordrhein-Westfalen",
    "wof:name":"R\u00f6mer-apotheke",
    "wof:placetype":"venue"
},
  "geometry": {"coordinates":[7.188589,51.726761],"type":"Point"}
}