{
  "type": "Feature",
  "properties": {
    "iso:country":"DE",
    "sg:address":"Rudolf-Breitscheid-Str. 1",
    "sg:city":"K\u00fchlungsborn",
    "sg:phone":"+49 38293/16408",
    "sg:postcode":"18225",
    "sg:province":"Mecklenburg-Vorpommern",
    "wof:name":"Bahnhofsgastst\u00e4tte Ost",
    "wof:placetype":"venue"
},
  "geometry": {"coordinates":[11.76030159,54.1492576599],"type":"Point"}
}