{
  "type": "Feature",
  "properties": {
    "iso:country":"DE",
    "sg:address":"Oderlandstra\u00dfe 12",
    "sg:city":"Eisenh\u00fcttenstadt",
    "sg:phone":"+49 3364",
    "sg:postcode":"15890",
    "sg:province":"Brandenburg",
    "wof:name":"East Side Records",
    "wof:placetype":"venue"
},
  "geometry": {"coordinates":[14.654299,52.154083],"type":"Point"}
}