{
  "type": "Feature",
  "properties": {
    "iso:country":"DE",
    "sg:address":"Eben\u00f6der Weg 6",
    "sg:city":"Vlotho",
    "sg:postcode":"32602",
    "sg:province":"Nordrhein-Westfalen",
    "wof:name":"Cnf - Feinmechanik",
    "wof:placetype":"venue"
},
  "geometry": {"coordinates":[8.8435611725,52.1718215942],"type":"Point"}
}