{
  "type": "Feature",
  "properties": {
    "iso:country":"DE",
    "sg:address":"Steinf\u00f6rder Str. 38",
    "sg:city":"Wietze",
    "sg:phone":"+49 5146/361",
    "sg:postcode":"29323",
    "sg:province":"Niedersachsen",
    "wof:name":"Nieders\u00e4chsische Waldsamen- Und Forstpflanzen Gmbh",
    "wof:placetype":"venue"
},
  "geometry": {"coordinates":[9.845583,52.650761],"type":"Point"}
}