{
  "type": "Feature",
  "properties": {
    "iso:country":"DE",
    "sg:address":"Akazienweg 9",
    "sg:city":"Pinnow",
    "sg:phone":"+49 33335/2832",
    "sg:postcode":"16278",
    "sg:province":"Brandenburg",
    "wof:name":"Christel D\u00f6ring",
    "wof:placetype":"venue"
},
  "geometry": {"coordinates":[14.1006574631,53.0610923767],"type":"Point"}
}