{
  "type": "Feature",
  "properties": {
    "iso:country":"DE",
    "sg:address":"Orleansplatz 9",
    "sg:city":"M\u00fcnchen",
    "sg:phone":"+49 89/1281",
    "sg:postcode":"81667",
    "sg:province":"Bayern",
    "wof:name":"Deutsche Bahn Ag",
    "wof:placetype":"venue"
},
  "geometry": {"coordinates":[11.6045246124,48.1280136108],"type":"Point"}
}