{
  "type": "Feature",
  "properties": {
    "iso:country":"DE",
    "sg:address":"B\u00fcrgermeister-Keim-Str. 16",
    "sg:city":"Mainz",
    "sg:postcode":"55129",
    "sg:province":"Rheinland-Pfalz",
    "wof:name":"Bms Immobilien Gmbh",
    "wof:placetype":"venue"
},
  "geometry": {"coordinates":[8.281983,49.960564],"type":"Point"}
}