{
  "type": "Feature",
  "properties": {
    "iso:country":"DE",
    "sg:address":"Otto-Hahn-Str. 5",
    "sg:city":"Dietzenbach",
    "sg:phone":"+49 6074/49400",
    "sg:postcode":"63128",
    "sg:province":"Hessen",
    "wof:name":"Schindler Gmbh",
    "wof:placetype":"venue"
},
  "geometry": {"coordinates":[8.7769756317,50.0092964172],"type":"Point"}
}