{
  "type": "Feature",
  "properties": {
    "iso:country":"DE",
    "sg:address":"Schlupfener Str. 2",
    "sg:city":"Ebenweiler",
    "sg:phone":"+49 7584/2327",
    "sg:postcode":"88370",
    "sg:province":"Baden-W\u00fcrttemberg",
    "wof:name":"Siegfried Arnold",
    "wof:placetype":"venue"
},
  "geometry": {"coordinates":[9.514216423,47.8985862732],"type":"Point"}
}