{
  "type": "Feature",
  "properties": {
    "iso:country":"DE",
    "sg:address":"Bahnhofstr. 11",
    "sg:city":"Bad Bevensen",
    "sg:phone":"+49 5821/2420",
    "sg:postcode":"29549",
    "sg:province":"Niedersachsen",
    "wof:name":"Keusens Kaffeest\u00fcbchen",
    "wof:placetype":"venue"
},
  "geometry": {"coordinates":[10.576451,53.078991],"type":"Point"}
}