{
  "type": "Feature",
  "properties": {
    "iso:country":"DE",
    "sg:address":"Markt 5",
    "sg:city":"Dortmund",
    "sg:phone":"+49 231/527243",
    "sg:postcode":"44137",
    "sg:province":"Nordrhein-Westfalen",
    "wof:name":"Trebag Treuhand Und Beratung Ag",
    "wof:placetype":"venue"
},
  "geometry": {"coordinates":[7.4662652016,51.5139274597],"type":"Point"}
}