{
  "type": "Feature",
  "properties": {
    "iso:country":"DE",
    "sg:address":"Schulstr. 20",
    "sg:city":"Ohorn",
    "sg:phone":"+49 35955/73693",
    "sg:postcode":"01896",
    "sg:province":"Sachsen",
    "wof:name":"Erik Sommer",
    "wof:placetype":"venue"
},
  "geometry": {"coordinates":[14.044719696,51.1762924194],"type":"Point"}
}