{
  "type": "Feature",
  "properties": {
    "iso:country":"DE",
    "sg:address":"Amalie-Hofer-Str. 4",
    "sg:city":"Offenburg",
    "sg:phone":"+49 781/924170",
    "sg:postcode":"77656",
    "sg:province":"Baden-W\u00fcrttemberg",
    "wof:name":"F & S Gesellschaft F\u00fcr",
    "wof:placetype":"venue"
},
  "geometry": {"coordinates":[7.917746067,48.4596214294],"type":"Point"}
}