{
  "type": "Feature",
  "properties": {
    "iso:country":"DE",
    "sg:address":"Hintergasse 1",
    "sg:city":"M\u00fcnster",
    "sg:phone":"+49 6071/22135",
    "sg:postcode":"64839",
    "sg:province":"Hessen",
    "wof:name":"Antikform Oscar Schubert",
    "wof:placetype":"venue"
},
  "geometry": {"coordinates":[8.858915329,49.9258537292],"type":"Point"}
}