{
  "type": "Feature",
  "properties": {
    "iso:country":"DE",
    "sg:address":"Sonnenstr. 3",
    "sg:city":"Eisingen",
    "sg:phone":"+49 9306/99220",
    "sg:postcode":"97249",
    "sg:province":"Bayern",
    "wof:name":"Verband Bildung Und Erziehung Vbe",
    "wof:placetype":"venue"
},
  "geometry": {"coordinates":[9.8316774368,49.7586097717],"type":"Point"}
}