{
  "type": "Feature",
  "properties": {
    "iso:country":"DE",
    "sg:address":"Hauptstr. 35",
    "sg:city":"Schifferstadt",
    "sg:phone":"+49 6235/3825",
    "sg:postcode":"67105",
    "sg:province":"Rheinland-Pfalz",
    "wof:name":"Engel-apotheke",
    "wof:placetype":"venue"
},
  "geometry": {"coordinates":[8.374501,49.382935],"type":"Point"}
}