{
  "type": "Feature",
  "properties": {
    "iso:country":"DE",
    "sg:address":"Friesenstr. 13",
    "sg:city":"Worms",
    "sg:phone":"+49 6241/44600",
    "sg:postcode":"67547",
    "sg:province":"Rheinland-Pfalz",
    "wof:name":"Merkur Stube",
    "wof:placetype":"venue"
},
  "geometry": {"coordinates":[8.3694391251,49.6347770691],"type":"Point"}
}