{
  "type": "Feature",
  "properties": {
    "iso:country":"DE",
    "sg:address":"Schalksburgstr. 4",
    "sg:city":"Porta Westfalica",
    "sg:postcode":"32457",
    "sg:province":"Nordrhein-Westfalen",
    "wof:name":"Schalksburg Gastronomie Gmbh",
    "wof:placetype":"venue"
},
  "geometry": {"coordinates":[8.9212398529,52.2394714355],"type":"Point"}
}