{
  "type": "Feature",
  "properties": {
    "iso:country":"DE",
    "sg:address":"Bahnhofstr. 78",
    "sg:city":"Staffelstein",
    "sg:phone":"+49 9573/7455",
    "sg:postcode":"96231",
    "sg:province":"Bayern",
    "wof:name":"Pizzeria Patrizierquelle",
    "wof:placetype":"venue"
},
  "geometry": {"coordinates":[10.995557785,50.1081581116],"type":"Point"}
}