{
  "type": "Feature",
  "properties": {
    "iso:country":"DE",
    "sg:address":"Wotzmannsreut 58",
    "sg:city":"Waldkirchen",
    "sg:phone":"+49 8581/1271",
    "sg:postcode":"94065",
    "sg:province":"Bayern",
    "wof:name":"Baier Gmbh",
    "wof:placetype":"venue"
},
  "geometry": {"coordinates":[13.59057,48.751888],"type":"Point"}
}