{
  "type": "Feature",
  "properties": {
    "iso:country":"DE",
    "sg:address":"Am Lechtinger Berg 5",
    "sg:city":"Wallenhorst",
    "sg:phone":"+49 5407/1213",
    "sg:postcode":"49134",
    "sg:province":"Niedersachsen",
    "wof:name":"Albert Vosgr\u00f6ne",
    "wof:placetype":"venue"
},
  "geometry": {"coordinates":[8.041529,52.326202],"type":"Point"}
}