{
  "type": "Feature",
  "properties": {
    "iso:country":"DE",
    "sg:address":"Wilhelmstr. 50-52",
    "sg:city":"Aachen",
    "sg:postcode":"52070",
    "sg:province":"Nordrhein-Westfalen",
    "wof:name":"Berke Gmbh",
    "wof:placetype":"venue"
},
  "geometry": {"coordinates":[6.0954670906,50.7718238831],"type":"Point"}
}