{
  "type": "Feature",
  "properties": {
    "iso:country":"DE",
    "sg:address":"Birrekoven 36",
    "sg:city":"Alfter",
    "sg:postcode":"53347",
    "sg:province":"Nordrhein-Westfalen",
    "wof:name":"Mind-focus Gmbh",
    "wof:placetype":"venue"
},
  "geometry": {"coordinates":[7.010855,50.730957],"type":"Point"}
}