{
  "type": "Feature",
  "properties": {
    "iso:country":"DE",
    "sg:address":"Am Jungst\u00fcck 45",
    "sg:city":"Mainz",
    "sg:postcode":"55130",
    "sg:province":"Rheinland-Pfalz",
    "wof:name":"49dm.de ...einfach Besser Schenken E. K.",
    "wof:placetype":"venue"
},
  "geometry": {"coordinates":[8.307947,49.953476],"type":"Point"}
}