{
  "type": "Feature",
  "properties": {
    "iso:country":"DE",
    "sg:address":"Friedrichstr. 2",
    "sg:city":"Treuchtlingen",
    "sg:phone":"+49 9142/200754",
    "sg:postcode":"91757",
    "sg:province":"Bayern",
    "wof:name":"Gr\u00fcner Baum",
    "wof:placetype":"venue"
},
  "geometry": {"coordinates":[10.9084339142,48.9534606934],"type":"Point"}
}