{
  "type": "Feature",
  "properties": {
    "iso:country":"DE",
    "sg:address":"B\u00e4ckerstr. 7",
    "sg:city":"Torgau",
    "sg:postcode":"04860",
    "sg:province":"Sachsen",
    "wof:name":"B\u00fcro- Und Copyshop",
    "wof:placetype":"venue"
},
  "geometry": {"coordinates":[13.00411,51.559441],"type":"Point"}
}