{
  "type": "Feature",
  "properties": {
    "iso:country":"DE",
    "sg:address":"Zeppelinstr. 8",
    "sg:city":"Dessau",
    "sg:postcode":"06847",
    "sg:province":"Sachsen-Anhalt",
    "wof:name":"Thyrolf & Uhle Stahl- Und Komponentenbau Gmbh",
    "wof:placetype":"venue"
},
  "geometry": {"coordinates":[12.2214536667,51.8303070068],"type":"Point"}
}