{
  "type": "Feature",
  "properties": {
    "iso:country":"DE",
    "sg:address":"Max-Liebermann-Str. 11",
    "sg:city":"Weimar",
    "sg:phone":"+49 3643/903254",
    "sg:postcode":"99425",
    "sg:province":"Th\u00fcringen",
    "wof:name":"Dr. Med. Wolfgang Wackwitz",
    "wof:placetype":"venue"
},
  "geometry": {"coordinates":[11.331525,50.966328],"type":"Point"}
}