{
  "type": "Feature",
  "properties": {
    "iso:country":"DE",
    "sg:address":"Horbach 7",
    "sg:city":"Dachsberg",
    "sg:phone":"+49 7672/4571",
    "sg:postcode":"79875",
    "sg:province":"Baden-W\u00fcrttemberg",
    "wof:name":"Klaus Malzacher",
    "wof:placetype":"venue"
},
  "geometry": {"coordinates":[8.10083,47.728458],"type":"Point"}
}