{
  "type": "Feature",
  "properties": {
    "iso:country":"DE",
    "sg:address":"Zw\u00e4tzengasse 14",
    "sg:city":"Jena",
    "sg:phone":"+49 3641/441144",
    "sg:postcode":"07743",
    "sg:province":"Th\u00fcringen",
    "wof:name":"Anke T\u00f6pfer",
    "wof:placetype":"venue"
},
  "geometry": {"coordinates":[11.58979702,50.9315910339],"type":"Point"}
}