{
  "type": "Feature",
  "properties": {
    "iso:country":"DE",
    "sg:address":"Stra\u00dfe des Friedens 65",
    "sg:city":"Gera",
    "sg:phone":"+49 365/82380",
    "sg:postcode":"07548",
    "sg:province":"Th\u00fcringen",
    "wof:name":"Dres. F\u00fcrst & Partner Gmbh",
    "wof:placetype":"venue"
},
  "geometry": {"coordinates":[12.0641260147,50.8669471741],"type":"Point"}
}