{
  "type": "Feature",
  "properties": {
    "iso:country":"DE",
    "sg:address":"Schlosserstra\u00dfe 3",
    "sg:city":"Herbrechtingen-Bolheim",
    "sg:phone":"+49 7324/41425",
    "sg:postcode":"89542",
    "sg:province":"Baden-W\u00fcrttemberg",
    "wof:name":"Gr\u00f6ner Gmbh",
    "wof:placetype":"venue"
},
  "geometry": {"coordinates":[10.16362,48.629681],"type":"Point"}
}