{
  "type": "Feature",
  "properties": {
    "iso:country":"DE",
    "sg:address":"Burgstr. 27",
    "sg:city":"Berlin",
    "sg:postcode":"10178",
    "sg:province":"Berlin",
    "wof:name":"United Energy Entertainment Bild- Und Tontr\u00e4ger Vertriebs-",
    "wof:placetype":"venue"
},
  "geometry": {"coordinates":[13.4241552353,52.5212135315],"type":"Point"}
}