{
  "type": "Feature",
  "properties": {
    "iso:country":"DE",
    "sg:address":"Lembergweg 17",
    "sg:city":"N\u00fcrtingen",
    "sg:phone":"+49 7022/51323",
    "sg:postcode":"72622",
    "sg:province":"Baden-W\u00fcrttemberg",
    "wof:name":"Dr. Marcus Dorfschmid",
    "wof:placetype":"venue"
},
  "geometry": {"coordinates":[9.3044347763,48.619972229],"type":"Point"}
}