{
  "type": "Feature",
  "properties": {
    "iso:country":"DE",
    "sg:address":"Heegweg 2",
    "sg:city":"Ranstadt",
    "sg:phone":"+49 6041/6633",
    "sg:postcode":"63691",
    "sg:province":"Hessen",
    "wof:name":"Karl Rumbler",
    "wof:placetype":"venue"
},
  "geometry": {"coordinates":[8.9847135544,50.3573417664],"type":"Point"}
}