{
  "type": "Feature",
  "properties": {
    "iso:country":"DE",
    "sg:address":"D\u00fcmmerstr. 22",
    "sg:city":"Damme",
    "sg:phone":"+49 5491/7681",
    "sg:postcode":"49401",
    "sg:province":"Niedersachsen",
    "wof:name":"Schmutte Eierverpackungsvertriebs Gmbh",
    "wof:placetype":"venue"
},
  "geometry": {"coordinates":[8.28894,52.529182],"type":"Point"}
}