{
  "type": "Feature",
  "properties": {
    "iso:country":"DE",
    "sg:address":"Marienstr. 50",
    "sg:city":"H\u00fcckelhoven",
    "sg:phone":"+49 2433/42802",
    "sg:postcode":"41836",
    "sg:province":"Nordrhein-Westfalen",
    "wof:name":"Josef Sieberichs",
    "wof:placetype":"venue"
},
  "geometry": {"coordinates":[6.221062,51.039513],"type":"Point"}
}