{
  "type": "Feature",
  "properties": {
    "iso:country":"DE",
    "sg:address":"Immerather Bahnhof 1",
    "sg:city":"Erkelenz",
    "sg:phone":"+49 2164/4365",
    "sg:postcode":"41812",
    "sg:province":"Nordrhein-Westfalen",
    "wof:name":"Elfriede Withaar",
    "wof:placetype":"venue"
},
  "geometry": {"coordinates":[6.4475507736,51.0417442322],"type":"Point"}
}