{
  "type": "Feature",
  "properties": {
    "iso:country":"DE",
    "sg:address":"Im Hohen Felde 10",
    "sg:city":"H\u00f6xter",
    "sg:phone":"+49 5271/37314",
    "sg:postcode":"37671",
    "sg:province":"Nordrhein-Westfalen",
    "wof:name":"J. Potthast",
    "wof:placetype":"venue"
},
  "geometry": {"coordinates":[9.3744077682,51.7679672241],"type":"Point"}
}