{
  "type": "Feature",
  "properties": {
    "iso:country":"DE",
    "sg:address":"Kappelner Str. 14",
    "sg:city":"S\u00f6rup",
    "sg:postcode":"24966",
    "sg:province":"Schleswig-Holstein",
    "wof:name":"Peter M\u00f6ller Fliesenarbeiten Inhaber Gustav Lorenzen E. K.",
    "wof:placetype":"venue"
},
  "geometry": {"coordinates":[9.6603755951,54.7479400635],"type":"Point"}
}