{
  "type": "Feature",
  "properties": {
    "iso:country":"DE",
    "sg:address":"Schwarzenbergstr. 32",
    "sg:city":"Hamburg",
    "sg:phone":"+49 40/7673050",
    "sg:postcode":"21073",
    "sg:province":"Hamburg",
    "wof:name":"Altenschmidt Immobilien E. Kfm.",
    "wof:placetype":"venue"
},
  "geometry": {"coordinates":[9.9760513306,53.4618721008],"type":"Point"}
}