{
  "type": "Feature",
  "properties": {
    "iso:country":"DE",
    "sg:address":"Clemensstr. 13",
    "sg:city":"Koblenz",
    "sg:phone":"+49 261/12288",
    "sg:postcode":"56068",
    "sg:province":"Rheinland-Pfalz",
    "wof:name":"Wema Gesellschaft F\u00fcr Immobilienvermittlung Mbh",
    "wof:placetype":"venue"
},
  "geometry": {"coordinates":[7.598091,50.358624],"type":"Point"}
}