{
  "type": "Feature",
  "properties": {
    "iso:country":"DE",
    "sg:address":"Hans-Bunte-Str. 45",
    "sg:city":"N\u00fcrnberg",
    "sg:phone":"+49 911/324420",
    "sg:postcode":"90431",
    "sg:province":"Bayern",
    "wof:name":"Sch\u00d6nberger & Weiss Gmbh",
    "wof:placetype":"venue"
},
  "geometry": {"coordinates":[11.04267,49.448582],"type":"Point"}
}