{
  "type": "Feature",
  "properties": {
    "iso:country":"DE",
    "sg:address":"Z\u00e4hringerstr. 29",
    "sg:city":"Berlin",
    "sg:phone":"+49 30/8813194",
    "sg:postcode":"10707",
    "sg:province":"Berlin",
    "wof:name":"Heinz-bernd L\u00fcttke",
    "wof:placetype":"venue"
},
  "geometry": {"coordinates":[13.3118658066,52.4958686829],"type":"Point"}
}