{
  "type": "Feature",
  "properties": {
    "iso:country":"DE",
    "sg:address":"Salzstr. 21",
    "sg:city":"M\u00fcnster",
    "sg:phone":"+49 251/47746",
    "sg:postcode":"48143",
    "sg:province":"Nordrhein-Westfalen",
    "wof:name":"Runners Point Warenhandelsgesellschaft Mbh",
    "wof:placetype":"venue"
},
  "geometry": {"coordinates":[7.632048,51.961479],"type":"Point"}
}