{
  "type": "Feature",
  "properties": {
    "iso:country":"DE",
    "sg:address":"Brahmsstr. 11",
    "sg:city":"S\u00f6mmerda",
    "sg:phone":"+49 3634/602097",
    "sg:postcode":"99610",
    "sg:province":"Th\u00fcringen",
    "wof:name":"R. Haupt Immobilienmakler",
    "wof:placetype":"venue"
},
  "geometry": {"coordinates":[11.1364774704,51.1598548889],"type":"Point"}
}