{
  "type": "Feature",
  "properties": {
    "iso:country":"DE",
    "sg:address":"Wiesental 1",
    "sg:city":"Rockenberg",
    "sg:phone":"+49 6033/72178",
    "sg:postcode":"35519",
    "sg:province":"Hessen",
    "wof:name":"W. Raab",
    "wof:placetype":"venue"
},
  "geometry": {"coordinates":[8.739182,50.418678],"type":"Point"}
}