{
  "type": "Feature",
  "properties": {
    "iso:country":"DE",
    "sg:address":"Eckenheimer Landstr. 345",
    "sg:city":"Frankfurt",
    "sg:phone":"+49 69/562960",
    "sg:postcode":"60435",
    "sg:province":"Hessen",
    "wof:name":"Maria R. B\u00f6hm",
    "wof:placetype":"venue"
},
  "geometry": {"coordinates":[8.68306,50.142509],"type":"Point"}
}