{
  "type": "Feature",
  "properties": {
    "iso:country":"DE",
    "sg:address":"Godramsteiner Hauptstr. 167",
    "sg:city":"Landau",
    "sg:phone":"+49 4963/4196560",
    "sg:postcode":"76829",
    "sg:province":"Rheinland-Pfalz",
    "wof:name":"Watts Industries Deutschland Gmbh",
    "wof:placetype":"venue"
},
  "geometry": {"coordinates":[8.0888385773,49.209777832],"type":"Point"}
}