{
  "type": "Feature",
  "properties": {
    "iso:country":"DE",
    "sg:address":"Mittelbachstr. 29",
    "sg:city":"Aalen",
    "sg:phone":"+49 7361/6721",
    "sg:postcode":"73430",
    "sg:province":"Baden-W\u00fcrttemberg",
    "wof:name":"Richard Horn Architekturb\u00fcro",
    "wof:placetype":"venue"
},
  "geometry": {"coordinates":[10.092657,48.839478],"type":"Point"}
}