{
  "type": "Feature",
  "properties": {
    "iso:country":"DE",
    "sg:address":"Poststr. 2",
    "sg:city":"Kirchheim",
    "sg:phone":"+49 8266/1687",
    "sg:postcode":"87757",
    "sg:province":"Bayern",
    "wof:name":"Briefmarkenversand",
    "wof:placetype":"venue"
},
  "geometry": {"coordinates":[10.4770441055,48.1726875305],"type":"Point"}
}