{
  "type": "Feature",
  "properties": {
    "iso:country":"DE",
    "sg:address":"Holstener Weg 46",
    "sg:city":"Salzbergen",
    "sg:phone":"+49 5976/1208",
    "sg:postcode":"48499",
    "sg:province":"Niedersachsen",
    "wof:name":"Ihr Raumausstatter Kreimer Inh. Frank Kreimer E. K.",
    "wof:placetype":"venue"
},
  "geometry": {"coordinates":[7.3815407753,52.3278160095],"type":"Point"}
}