{
  "type": "Feature",
  "properties": {
    "iso:country":"DE",
    "sg:address":"Stephanienstr. 19",
    "sg:city":"D\u00fcsseldorf",
    "sg:phone":"+49 211/359632",
    "sg:postcode":"40211",
    "sg:province":"Nordrhein-Westfalen",
    "wof:name":"Helmut Friedrichs",
    "wof:placetype":"venue"
},
  "geometry": {"coordinates":[6.7914848328,51.225189209],"type":"Point"}
}