{
  "type": "Feature",
  "properties": {
    "iso:country":"DE",
    "sg:address":"Nordring 72",
    "sg:city":"Offenbach",
    "sg:postcode":"63067",
    "sg:province":"Hessen",
    "wof:name":"Ibke- Gmbh",
    "wof:placetype":"venue"
},
  "geometry": {"coordinates":[8.7494535446,50.1120681763],"type":"Point"}
}