{
  "type": "Feature",
  "properties": {
    "iso:country":"DE",
    "sg:address":"Hofkamp 131",
    "sg:city":"Wuppertal",
    "sg:phone":"+49 202/443918",
    "sg:postcode":"42103",
    "sg:province":"Nordrhein-Westfalen",
    "wof:name":"Wolfgang Scholz Steuerberater",
    "wof:placetype":"venue"
},
  "geometry": {"coordinates":[7.1577267647,51.2576522827],"type":"Point"}
}