{
  "type": "Feature",
  "properties": {
    "iso:country":"DE",
    "sg:address":"Boschstr. 8",
    "sg:city":"Neustadt",
    "sg:phone":"+49 5032/953580",
    "sg:postcode":"31535",
    "sg:province":"Niedersachsen",
    "wof:name":"Neutronic System Technik Gmbh",
    "wof:placetype":"venue"
},
  "geometry": {"coordinates":[9.328224,48.857578],"type":"Point"}
}