{
  "type": "Feature",
  "properties": {
    "iso:country":"DE",
    "sg:address":"Schweizerthaler Str. 1",
    "sg:city":"Taura",
    "sg:phone":"+49 3724/3272",
    "sg:postcode":"09249",
    "sg:province":"Sachsen",
    "wof:name":"Chemnitztal-apotheke",
    "wof:placetype":"venue"
},
  "geometry": {"coordinates":[12.851936,50.924603],"type":"Point"}
}