{
  "type": "Feature",
  "properties": {
    "iso:country":"DE",
    "sg:address":"Humboldtstr. 9",
    "sg:city":"Simmerath",
    "sg:phone":"+49 2473/7434",
    "sg:postcode":"52152",
    "sg:province":"Nordrhein-Westfalen",
    "wof:name":"Wolfgang M\u00fcller",
    "wof:placetype":"venue"
},
  "geometry": {"coordinates":[6.306853,50.606483],"type":"Point"}
}