{
  "type": "Feature",
  "properties": {
    "iso:country":"DE",
    "sg:address":"Marktplatz 6 OT Beeck",
    "sg:city":"Duisburg",
    "sg:phone":"+49 203/460389",
    "sg:postcode":"47139",
    "sg:province":"Nordrhein-Westfalen",
    "wof:name":"Adler-apotheke Hans Hassel Inh. Manfred Kr\u00e4mer",
    "wof:placetype":"venue"
},
  "geometry": {"coordinates":[6.733575,51.47805],"type":"Point"}
}