{
  "type": "Feature",
  "properties": {
    "iso:country":"DE",
    "sg:address":"Schapenbruch 10",
    "sg:city":"Braunschweig",
    "sg:phone":"+49 531/360096",
    "sg:postcode":"38104",
    "sg:province":"Niedersachsen",
    "wof:name":"Gerhard Bode Immobilienmakler",
    "wof:placetype":"venue"
},
  "geometry": {"coordinates":[10.6027612686,52.2801742554],"type":"Point"}
}