{
  "type": "Feature",
  "properties": {
    "iso:country":"DE",
    "sg:address":"Dorfstr. 9a",
    "sg:city":"Niendorf",
    "sg:postcode":"15936",
    "sg:province":"Brandenburg",
    "wof:name":"Beverlac Beschichtungs- Gmbh",
    "wof:placetype":"venue"
},
  "geometry": {"coordinates":[13.380399704,51.8595733643],"type":"Point"}
}