{
  "type": "Feature",
  "properties": {
    "iso:country":"DE",
    "sg:address":"B\u00e4ckerstr. 11",
    "sg:city":"Zeven",
    "sg:phone":"+49 4281/8576",
    "sg:postcode":"27404",
    "sg:province":"Niedersachsen",
    "wof:name":"China Restaurant Chien Fu Low",
    "wof:placetype":"venue"
},
  "geometry": {"coordinates":[9.2943935394,53.2996482849],"type":"Point"}
}