{
  "type": "Feature",
  "properties": {
    "iso:country":"DE",
    "sg:address":"Brettener Str. 51",
    "sg:city":"Eppingen",
    "sg:postcode":"75031",
    "sg:province":"Baden-W\u00fcrttemberg",
    "wof:name":"Amalie Kepner Gmbh",
    "wof:placetype":"venue"
},
  "geometry": {"coordinates":[8.906943,49.135654],"type":"Point"}
}