{
  "type": "Feature",
  "properties": {
    "iso:country":"DE",
    "sg:address":"Hauptstr. 8",
    "sg:city":"Grafenau",
    "sg:postcode":"94481",
    "sg:province":"Bayern",
    "wof:name":"Pas Gmbh",
    "wof:placetype":"venue"
},
  "geometry": {"coordinates":[13.3974647522,48.8571472168],"type":"Point"}
}