{
  "type": "Feature",
  "properties": {
    "iso:country":"DE",
    "sg:address":"Berggasse 8",
    "sg:city":"Bodenmais",
    "sg:phone":"+49 9924/348",
    "sg:postcode":"94249",
    "sg:province":"Bayern",
    "wof:name":"Pension Ruth Huber",
    "wof:placetype":"venue"
},
  "geometry": {"coordinates":[13.1057691574,49.0728111267],"type":"Point"}
}