{
  "type": "Feature",
  "properties": {
    "iso:country":"DE",
    "sg:address":"Kemnader Str. 245",
    "sg:city":"Bochum",
    "sg:phone":"+49 234/799626",
    "sg:postcode":"44797",
    "sg:province":"Nordrhein-Westfalen",
    "wof:name":"K. H. Treutner Garten- Und",
    "wof:placetype":"venue"
},
  "geometry": {"coordinates":[7.234991,51.431015],"type":"Point"}
}