{
  "type": "Feature",
  "properties": {
    "iso:country":"DE",
    "sg:address":"Langeooger Str. 15",
    "sg:city":"Moormerland",
    "sg:phone":"+49 4954/89116",
    "sg:postcode":"26802",
    "sg:province":"Niedersachsen",
    "wof:name":"Jonetat Immobilienmakler",
    "wof:placetype":"venue"
},
  "geometry": {"coordinates":[7.4860048294,53.3009033203],"type":"Point"}
}