{
  "type": "Feature",
  "properties": {
    "iso:country":"DE",
    "sg:address":"Erlenweg 18",
    "sg:city":"Eberhardzell",
    "sg:phone":"+49 7355/7046",
    "sg:postcode":"88436",
    "sg:province":"Baden-W\u00fcrttemberg",
    "wof:name":"Gretzbach Wohnbau Gmbh",
    "wof:placetype":"venue"
},
  "geometry": {"coordinates":[9.8200960159,48.0026054382],"type":"Point"}
}