{
  "type": "Feature",
  "properties": {
    "iso:country":"DE",
    "sg:address":"K\u00fcchelbachstr. 1",
    "sg:city":"Abenberg",
    "sg:phone":"+49 9178/1693",
    "sg:postcode":"91183",
    "sg:province":"Bayern",
    "wof:name":"Manfred Friedrich",
    "wof:placetype":"venue"
},
  "geometry": {"coordinates":[10.959652,49.238384],"type":"Point"}
}