{
  "type": "Feature",
  "properties": {
    "iso:country":"DE",
    "sg:address":"Am Knick 28",
    "sg:city":"Oststeinbek",
    "sg:postcode":"22113",
    "sg:province":"Schleswig-Holstein",
    "wof:name":"Miller Beteiligungs Gmbh",
    "wof:placetype":"venue"
},
  "geometry": {"coordinates":[10.1603088379,53.5525016785],"type":"Point"}
}