{
  "type": "Feature",
  "properties": {
    "iso:country":"DE",
    "sg:address":"Danneckerstr 15",
    "sg:city":"Stuttgart",
    "sg:phone":"+49 711/262491",
    "sg:postcode":"70182",
    "sg:province":"Baden-W\u00fcrttemberg",
    "wof:name":"Ce Cimpoaca Elektronik Gmbh",
    "wof:placetype":"venue"
},
  "geometry": {"coordinates":[9.185564,48.771721],"type":"Point"}
}