{
  "type": "Feature",
  "properties": {
    "iso:country":"DE",
    "sg:address":"Lise-Meitner-Str. 5",
    "sg:city":"Nordstemmen",
    "sg:phone":"+49 5069/965053",
    "sg:postcode":"31171",
    "sg:province":"Niedersachsen",
    "wof:name":"J. Feretti Gmbh",
    "wof:placetype":"venue"
},
  "geometry": {"coordinates":[9.7852668762,52.1696357727],"type":"Point"}
}