{
  "type": "Feature",
  "properties": {
    "iso:country":"DE",
    "sg:address":"K\u00f6nigsbr\u00fccker Landstr. 24",
    "sg:city":"Dresden",
    "sg:postcode":"01109",
    "sg:province":"Sachsen",
    "wof:name":"Industrietechnik Frenzel Gmbh",
    "wof:placetype":"venue"
},
  "geometry": {"coordinates":[13.778253,51.111561],"type":"Point"}
}