{
  "type": "Feature",
  "properties": {
    "iso:country":"DE",
    "sg:address":"Bahnhofstr. 8",
    "sg:city":"Crimmitschau",
    "sg:phone":"+49 3762/42675",
    "sg:postcode":"08451",
    "sg:province":"Sachsen",
    "wof:name":"Praxis F\u00fcr Physiotherapie Und Massagen",
    "wof:placetype":"venue"
},
  "geometry": {"coordinates":[12.39234,50.814709],"type":"Point"}
}