{
  "type": "Feature",
  "properties": {
    "iso:country":"DE",
    "sg:address":"Donaustr. 21",
    "sg:city":"Vohburg",
    "sg:phone":"+49 8457/302",
    "sg:postcode":"85088",
    "sg:province":"Bayern",
    "wof:name":"J. M\u00fcller",
    "wof:placetype":"venue"
},
  "geometry": {"coordinates":[11.6176843643,48.7709007263],"type":"Point"}
}