{
  "type": "Feature",
  "properties": {
    "iso:country":"DE",
    "sg:address":"Moselwei\u00dfer Str. 34",
    "sg:city":"Koblenz",
    "sg:phone":"+49 261/44444",
    "sg:postcode":"56073",
    "sg:province":"Rheinland-Pfalz",
    "wof:name":"Ingo Patzke Masseur",
    "wof:placetype":"venue"
},
  "geometry": {"coordinates":[7.582437,50.360817],"type":"Point"}
}