{
  "type": "Feature",
  "properties": {
    "iso:country":"DE",
    "sg:address":"Nu\u00dfbaumallee 7",
    "sg:city":"Kerpen",
    "sg:postcode":"50169",
    "sg:province":"Nordrhein-Westfalen",
    "wof:name":"Datarent B\u00fcroverfahrenstechnik Und Handel Gmbh",
    "wof:placetype":"venue"
},
  "geometry": {"coordinates":[6.7413129807,50.8663215637],"type":"Point"}
}