{
  "type": "Feature",
  "properties": {
    "iso:country":"DE",
    "sg:address":"Altst\u00e4dter Kirchplatz 3",
    "sg:city":"Bielefeld",
    "sg:phone":"+49 8324/2081",
    "sg:postcode":"33602",
    "sg:province":"Nordrhein-Westfalen",
    "wof:name":"Leder-eberhart Gmbh",
    "wof:placetype":"venue"
},
  "geometry": {"coordinates":[10.378208,47.504478],"type":"Point"}
}