{
  "type": "Feature",
  "properties": {
    "iso:country":"DE",
    "sg:address":"Hauptstr. 100",
    "sg:city":"Berlin",
    "sg:postcode":"10827",
    "sg:province":"Berlin",
    "wof:name":"Efirom Spielhallen Gmbh",
    "wof:placetype":"venue"
},
  "geometry": {"coordinates":[13.3458242416,52.4795951843],"type":"Point"}
}