{
  "type": "Feature",
  "properties": {
    "iso:country":"DE",
    "sg:address":"W\u00f6rmlitzer Str. 24",
    "sg:city":"Halle",
    "sg:postcode":"06110",
    "sg:province":"Sachsen-Anhalt",
    "wof:name":"Procon R\u00fchlemann & Heckes Gmbh",
    "wof:placetype":"venue"
},
  "geometry": {"coordinates":[11.964924,51.469528],"type":"Point"}
}