{
  "type": "Feature",
  "properties": {
    "iso:country":"DE",
    "sg:address":"Kapellenstr. 11",
    "sg:city":"Medebach",
    "sg:phone":"+49 2982/8455",
    "sg:postcode":"59964",
    "sg:province":"Nordrhein-Westfalen",
    "wof:name":"Brieden Verwaltungs- Und Beteiligungs Gmbh",
    "wof:placetype":"venue"
},
  "geometry": {"coordinates":[8.7075748444,51.1979866028],"type":"Point"}
}