{
  "type": "Feature",
  "properties": {
    "iso:country":"DE",
    "sg:address":"Hamburger Str. 144",
    "sg:city":"Hamburg",
    "sg:phone":"+49 40/29883997",
    "sg:postcode":"22083",
    "sg:province":"Hamburg",
    "wof:name":"Haller-stiftung",
    "wof:placetype":"venue"
},
  "geometry": {"coordinates":[10.037358284,53.5759735107],"type":"Point"}
}