{
  "type": "Feature",
  "properties": {
    "iso:country":"DE",
    "sg:address":"Carl-Severing-Str. 116",
    "sg:city":"Bielefeld",
    "sg:phone":"+49 521/946460",
    "sg:postcode":"33649",
    "sg:province":"Nordrhein-Westfalen",
    "wof:name":"Autohaus Neumann Beteiligungs Gmbh",
    "wof:placetype":"venue"
},
  "geometry": {"coordinates":[8.478118,51.996929],"type":"Point"}
}