{
  "type": "Feature",
  "properties": {
    "iso:country":"DE",
    "sg:address":"Hans-Sachs-Str. 3",
    "sg:city":"D\u00fcsseldorf",
    "sg:phone":"+49 211/680470",
    "sg:postcode":"40237",
    "sg:province":"Nordrhein-Westfalen",
    "wof:name":"Klaus Malenke Und Partner",
    "wof:placetype":"venue"
},
  "geometry": {"coordinates":[6.8117451668,51.2333068848],"type":"Point"}
}