{
  "type": "Feature",
  "properties": {
    "iso:country":"DE",
    "sg:address":"Alt-Haarener Str. 13",
    "sg:city":"Aachen",
    "sg:phone":"+49 241/161715",
    "sg:postcode":"52080",
    "sg:province":"Nordrhein-Westfalen",
    "wof:name":"Bernhard Knauf",
    "wof:placetype":"venue"
},
  "geometry": {"coordinates":[6.1227798462,50.7941207886],"type":"Point"}
}