{
  "type": "Feature",
  "properties": {
    "iso:country":"DE",
    "sg:address":"Blumenstr. 3",
    "sg:city":"Thaden",
    "sg:phone":"+49 4872/942955",
    "sg:postcode":"25557",
    "sg:province":"Schleswig-Holstein",
    "wof:name":"Zimmerei Tank & Thun Gmbh",
    "wof:placetype":"venue"
},
  "geometry": {"coordinates":[9.4256620407,54.1023025513],"type":"Point"}
}