{
  "type": "Feature",
  "properties": {
    "iso:country":"DE",
    "sg:address":"K\u00f6nigswinterer Str 11-21",
    "sg:city":"Bonn",
    "sg:phone":"+49 228/400000",
    "sg:postcode":"53227",
    "sg:province":"Nordrhein-Westfalen",
    "wof:name":"Kessler & Comp. Gmbh & Co Kg",
    "wof:placetype":"venue"
},
  "geometry": {"coordinates":[7.15554,50.721062],"type":"Point"}
}