{
  "type": "Feature",
  "properties": {
    "iso:country":"DE",
    "sg:address":"Heimhuder Str. 5",
    "sg:city":"Hamburg",
    "sg:phone":"+49 40/41170727",
    "sg:postcode":"20148",
    "sg:province":"Hamburg",
    "wof:name":"Gesellschaft Zur Verwertung Von Leistungsschutzrechten Mbh",
    "wof:placetype":"venue"
},
  "geometry": {"coordinates":[9.9924459457,53.5644607544],"type":"Point"}
}