{
  "type": "Feature",
  "properties": {
    "iso:country":"DE",
    "sg:address":"Trogemannstr. 4",
    "sg:city":"Marl",
    "sg:phone":"+49 2365/42001",
    "sg:postcode":"45772",
    "sg:province":"Nordrhein-Westfalen",
    "wof:name":"G. Holub",
    "wof:placetype":"venue"
},
  "geometry": {"coordinates":[7.1315178871,51.6633872986],"type":"Point"}
}