{
  "type": "Feature",
  "properties": {
    "iso:country":"DE",
    "sg:address":"Stemberg 61",
    "sg:city":"Horn-Bad Meinberg",
    "sg:phone":"+49 5234/2296",
    "sg:postcode":"32805",
    "sg:province":"Nordrhein-Westfalen",
    "wof:name":"Dieter Stoll",
    "wof:placetype":"venue"
},
  "geometry": {"coordinates":[8.8955984116,51.8807029724],"type":"Point"}
}