{
  "type": "Feature",
  "properties": {
    "iso:country":"DE",
    "sg:address":"Heinrich-Zille-Str. 6",
    "sg:city":"Dassel",
    "sg:postcode":"37586",
    "sg:province":"Niedersachsen",
    "wof:name":"Katholische M\u00e4nnergemeinschaft Wolfgang Henniges",
    "wof:placetype":"venue"
},
  "geometry": {"coordinates":[9.6935787201,51.7990036011],"type":"Point"}
}