{
  "type": "Feature",
  "properties": {
    "iso:country":"DE",
    "sg:address":"Max-Eyth-Str. 50",
    "sg:city":"Hannover",
    "sg:phone":"+49 511/855206",
    "sg:postcode":"30173",
    "sg:province":"Niedersachsen",
    "wof:name":"Prof. Dr. Rainer Hobigk Architekt",
    "wof:placetype":"venue"
},
  "geometry": {"coordinates":[9.770572,52.360901],"type":"Point"}
}