{
  "type": "Feature",
  "properties": {
    "iso:country":"DE",
    "sg:address":"Bahnhofstr. 15",
    "sg:city":"Dingolfing",
    "sg:phone":"+49 8731/75850",
    "sg:postcode":"84130",
    "sg:province":"Bayern",
    "wof:name":"Automobile Dorfner",
    "wof:placetype":"venue"
},
  "geometry": {"coordinates":[12.4434146881,48.6333732605],"type":"Point"}
}