{
  "type": "Feature",
  "properties": {
    "iso:country":"DE",
    "sg:address":"Am Deichfleet 13",
    "sg:city":"Bremen",
    "sg:phone":"+49 421/2769746",
    "sg:postcode":"28357",
    "sg:province":"Bremen",
    "wof:name":"Gebr\u00fcder Sierig Verwaltungs Gmbh",
    "wof:placetype":"venue"
},
  "geometry": {"coordinates":[8.8942565918,53.1184158325],"type":"Point"}
}