{
  "type": "Feature",
  "properties": {
    "iso:country":"DE",
    "sg:address":"D\u00fcrerring 59",
    "sg:city":"Lehrte",
    "sg:phone":"+49 5132/4675",
    "sg:postcode":"31275",
    "sg:province":"Niedersachsen",
    "wof:name":"R. Miller Immobilienmakler",
    "wof:placetype":"venue"
},
  "geometry": {"coordinates":[9.9692678452,52.3617935181],"type":"Point"}
}