{
  "type": "Feature",
  "properties": {
    "iso:country":"DE",
    "sg:address":"In den Fischermatten 2",
    "sg:city":"Emmendingen",
    "sg:phone":"+49 7641/919470",
    "sg:postcode":"79312",
    "sg:province":"Baden-W\u00fcrttemberg",
    "wof:name":"Grossm\u00fcller Gmbh",
    "wof:placetype":"venue"
},
  "geometry": {"coordinates":[7.8463139534,48.1149978638],"type":"Point"}
}