{
  "type": "Feature",
  "properties": {
    "iso:country":"DE",
    "sg:address":"Torgauer Str. 53",
    "sg:city":"Herzberg",
    "sg:phone":"+49 3535/3830",
    "sg:postcode":"04916",
    "sg:province":"Brandenburg",
    "wof:name":"Otto Franz",
    "wof:placetype":"venue"
},
  "geometry": {"coordinates":[13.2302246094,51.690952301],"type":"Point"}
}