{
  "type": "Feature",
  "properties": {
    "iso:country":"DE",
    "sg:address":"Pappelallee 10",
    "sg:city":"Sch\u00f6now",
    "sg:phone":"+49 3338/38444",
    "sg:postcode":"16321",
    "sg:province":"Brandenburg",
    "wof:name":"Frank Pinske",
    "wof:placetype":"venue"
},
  "geometry": {"coordinates":[13.582827,52.680218],"type":"Point"}
}