{
  "type": "Feature",
  "properties": {
    "iso:country":"DE",
    "sg:address":"Rottenbucher Str. 19",
    "sg:city":"M\u00fcnchen",
    "sg:phone":"+49 89/7193814",
    "sg:postcode":"81377",
    "sg:province":"Bayern",
    "wof:name":"Vvr Verkehrs-verlag Gmbh",
    "wof:placetype":"venue"
},
  "geometry": {"coordinates":[11.5110282898,48.1151885986],"type":"Point"}
}