{
  "type": "Feature",
  "properties": {
    "iso:country":"DE",
    "sg:address":"Br\u00fccknerstr. 7",
    "sg:city":"W\u00fcrzburg",
    "sg:phone":"+49 931/285450",
    "sg:postcode":"97080",
    "sg:province":"Bayern",
    "wof:name":"Radsport Gerhard Back",
    "wof:placetype":"venue"
},
  "geometry": {"coordinates":[9.943867,49.802399],"type":"Point"}
}