{
  "type": "Feature",
  "properties": {
    "iso:country":"DE",
    "sg:address":"Falkenkorso 32",
    "sg:city":"Falkensee",
    "sg:phone":"+49 3322/203114",
    "sg:postcode":"14612",
    "sg:province":"Brandenburg",
    "wof:name":"Birgit Br\u00fcckner",
    "wof:placetype":"venue"
},
  "geometry": {"coordinates":[13.082188,52.571087],"type":"Point"}
}