{
  "type": "Feature",
  "properties": {
    "iso:country":"DE",
    "sg:address":"Volkacher Str. 38",
    "sg:city":"Volkach",
    "sg:phone":"+49 9381/6737",
    "sg:postcode":"97332",
    "sg:province":"Bayern",
    "wof:name":"Gerhard Steiner",
    "wof:placetype":"venue"
},
  "geometry": {"coordinates":[10.297421,49.844288],"type":"Point"}
}