{
  "type": "Feature",
  "properties": {
    "iso:country":"DE",
    "sg:address":"Ostertorsteinweg 25",
    "sg:city":"Bremen",
    "sg:phone":"+49 421/701699",
    "sg:postcode":"28203",
    "sg:province":"Bremen",
    "wof:name":"Kosmetik-bazar",
    "wof:placetype":"venue"
},
  "geometry": {"coordinates":[8.820083,53.072769],"type":"Point"}
}