{
  "type": "Feature",
  "properties": {
    "iso:country":"DE",
    "sg:address":"Sprottaer Landstr.",
    "sg:city":"Eilenburg",
    "sg:phone":"+49 3423/3971",
    "sg:postcode":"04838",
    "sg:province":"Sachsen",
    "wof:name":"Leist Kies Gmbh",
    "wof:placetype":"venue"
},
  "geometry": {"coordinates":[12.6718397141,51.4740257263],"type":"Point"}
}