{
  "type": "Feature",
  "properties": {
    "iso:country":"DE",
    "sg:address":"Parkallee 25",
    "sg:city":"Reinbek",
    "sg:phone":"+49 40/7224546",
    "sg:postcode":"21465",
    "sg:province":"Schleswig-Holstein",
    "wof:name":"Carl Manzel",
    "wof:placetype":"venue"
},
  "geometry": {"coordinates":[10.2534456253,53.512588501],"type":"Point"}
}