{
  "type": "Feature",
  "properties": {
    "iso:country":"DE",
    "sg:address":"Hasselrott 41",
    "sg:city":"Gettorf",
    "sg:phone":"+49 4943/464380",
    "sg:postcode":"24214",
    "sg:province":"Schleswig-Holstein",
    "wof:name":"Johann Wiese & Sohn Ohg",
    "wof:placetype":"venue"
},
  "geometry": {"coordinates":[9.964569,54.404423],"type":"Point"}
}