{
  "type": "Feature",
  "properties": {
    "iso:country":"DE",
    "sg:address":"Industriestr.",
    "sg:city":"Beverungen",
    "sg:phone":"+49 5273/4948",
    "sg:postcode":"37688",
    "sg:province":"Nordrhein-Westfalen",
    "wof:name":"Josef V\u00f6ssing & Sohn Gmbh",
    "wof:placetype":"venue"
},
  "geometry": {"coordinates":[9.379246,51.676006],"type":"Point"}
}