{
  "type": "Feature",
  "properties": {
    "iso:country":"DE",
    "sg:address":"Werner-For\u00dfmann-Str. 12",
    "sg:city":"Winsen",
    "sg:postcode":"21423",
    "sg:province":"Niedersachsen",
    "wof:name":"Koch Gewerbe-r\u00e4ume Gmbh",
    "wof:placetype":"venue"
},
  "geometry": {"coordinates":[10.2313995361,53.3389587402],"type":"Point"}
}