{
  "type": "Feature",
  "properties": {
    "iso:country":"DE",
    "sg:address":"Putzbrunner Str. 252",
    "sg:city":"M\u00fcnchen",
    "sg:phone":"+49 89/6011572",
    "sg:postcode":"81739",
    "sg:province":"Bayern",
    "wof:name":"R. D\u00fch Sen.",
    "wof:placetype":"venue"
},
  "geometry": {"coordinates":[11.673697,48.08596],"type":"Point"}
}