{
  "type": "Feature",
  "properties": {
    "iso:country":"DE",
    "sg:address":"Waldstr. 4",
    "sg:city":"Steimbke",
    "sg:phone":"+49 5026/1247",
    "sg:postcode":"31634",
    "sg:province":"Niedersachsen",
    "wof:name":"Angelika Buhmann Krankengymnastin",
    "wof:placetype":"venue"
},
  "geometry": {"coordinates":[9.376955,52.660217],"type":"Point"}
}