{
  "type": "Feature",
  "properties": {
    "iso:country":"DE",
    "sg:address":"G\u00f6rlitzer Str. 4",
    "sg:city":"Bernstadt",
    "sg:phone":"+49 35874/24242",
    "sg:postcode":"02748",
    "sg:province":"Sachsen",
    "wof:name":"Apotheke Bernstadt",
    "wof:placetype":"venue"
},
  "geometry": {"coordinates":[14.827731,51.047272],"type":"Point"}
}