{
  "type": "Feature",
  "properties": {
    "iso:country":"DE",
    "sg:address":"Am Alten Galgen 14",
    "sg:city":"Montabaur",
    "sg:phone":"+49 4926/0292160",
    "sg:postcode":"56410",
    "sg:province":"Rheinland-Pfalz",
    "wof:name":"Ursa-chemie Gmbh",
    "wof:placetype":"venue"
},
  "geometry": {"coordinates":[7.840988,50.450588],"type":"Point"}
}