{
  "type": "Feature",
  "properties": {
    "iso:country":"DE",
    "sg:address":"Forststr. 71",
    "sg:city":"Stuttgart",
    "sg:postcode":"70176",
    "sg:province":"Baden-W\u00fcrttemberg",
    "wof:name":"Aci Gesellschaft Zur Aufbereitung Und Conception",
    "wof:placetype":"venue"
},
  "geometry": {"coordinates":[9.159189,48.778362],"type":"Point"}
}