{
  "type": "Feature",
  "properties": {
    "iso:country":"DE",
    "sg:address":"Kapuzinerstr. 7",
    "sg:city":"M\u00fcnchen",
    "sg:postcode":"80337",
    "sg:province":"Bayern",
    "wof:name":"Christthaller Verm\u00f6gensmanagement E. K.",
    "wof:placetype":"venue"
},
  "geometry": {"coordinates":[11.556916,48.12775],"type":"Point"}
}