{
  "type": "Feature",
  "properties": {
    "iso:country":"DE",
    "sg:address":"Il\u00e4nderh\u00f6he 19",
    "sg:city":"Essen",
    "sg:phone":"+49 201/409589",
    "sg:postcode":"45239",
    "sg:province":"Nordrhein-Westfalen",
    "wof:name":"T. Tittel Garten- Und",
    "wof:placetype":"venue"
},
  "geometry": {"coordinates":[7.027436,51.378311],"type":"Point"}
}