{
  "type": "Feature",
  "properties": {
    "iso:country":"DE",
    "sg:address":"Matthiasstr. 16",
    "sg:city":"Leiwen",
    "sg:phone":"+49 6507/3202",
    "sg:postcode":"54340",
    "sg:province":"Rheinland-Pfalz",
    "wof:name":"Johann Lex-ambre",
    "wof:placetype":"venue"
},
  "geometry": {"coordinates":[6.878455162,49.8195075989],"type":"Point"}
}