{
  "type": "Feature",
  "properties": {
    "iso:country":"DE",
    "sg:address":"Am Glockenstein 19 a",
    "sg:city":"Bremen",
    "sg:postcode":"28197",
    "sg:province":"Bremen",
    "wof:name":"Hagens Kietz-speicher- Domizil Beteiligungs Gmbh",
    "wof:placetype":"venue"
},
  "geometry": {"coordinates":[8.695721,53.117207],"type":"Point"}
}