{
  "type": "Feature",
  "properties": {
    "iso:country":"DE",
    "sg:address":"Neumattring 8",
    "sg:city":"Baden-Baden",
    "sg:phone":"+49 7221/63690",
    "sg:postcode":"76532",
    "sg:province":"Baden-W\u00fcrttemberg",
    "wof:name":"Rainer Weber",
    "wof:placetype":"venue"
},
  "geometry": {"coordinates":[8.21194,48.814339],"type":"Point"}
}