{
  "type": "Feature",
  "properties": {
    "iso:country":"DE",
    "sg:address":"K\u00f6lner Str. 1",
    "sg:city":"Kerpen",
    "sg:phone":"+49 2237/51482",
    "sg:postcode":"50171",
    "sg:province":"Nordrhein-Westfalen",
    "wof:name":"Atlas Reiseb\u00fcro Gmbh",
    "wof:placetype":"venue"
},
  "geometry": {"coordinates":[6.6951851845,50.8702049255],"type":"Point"}
}