{
  "type": "Feature",
  "properties": {
    "iso:country":"DE",
    "sg:address":"Schellingstr. 5",
    "sg:city":"Hamburg",
    "sg:phone":"+49 40/2005242",
    "sg:postcode":"22089",
    "sg:province":"Hamburg",
    "wof:name":"Non Plus Ultra Events Frank Kottysch",
    "wof:placetype":"venue"
},
  "geometry": {"coordinates":[10.0461978912,53.5690956116],"type":"Point"}
}