{
  "type": "Feature",
  "properties": {
    "iso:country":"DE",
    "sg:address":"Gemeindehausstr. 8",
    "sg:city":"Welzheim",
    "sg:phone":"+49 7182/6065",
    "sg:postcode":"73642",
    "sg:province":"Baden-W\u00fcrttemberg",
    "wof:name":"Friedrich Bauer",
    "wof:placetype":"venue"
},
  "geometry": {"coordinates":[9.636053,48.874516],"type":"Point"}
}