{
  "type": "Feature",
  "properties": {
    "iso:country":"DE",
    "sg:address":"Adolf-K\u00f6hne-Str. 6",
    "sg:city":"Osnabr\u00fcck",
    "sg:phone":"+49 541/5600903",
    "sg:postcode":"49090",
    "sg:province":"Niedersachsen",
    "wof:name":"G\u00dcnter Sauer Kg",
    "wof:placetype":"venue"
},
  "geometry": {"coordinates":[8.003869,52.306011],"type":"Point"}
}