{
  "type": "Feature",
  "properties": {
    "iso:country":"DE",
    "sg:address":"Neubeuerer Str. 2",
    "sg:city":"Nu\u00dfdorf",
    "sg:phone":"+49 8034/309520",
    "sg:postcode":"83131",
    "sg:province":"Bayern",
    "wof:name":"Heimservice Pizza-flizza",
    "wof:placetype":"venue"
},
  "geometry": {"coordinates":[12.156579,47.743782],"type":"Point"}
}