{
  "type": "Feature",
  "properties": {
    "iso:country":"DE",
    "sg:address":"Rudolf-Virchow-Str. 9",
    "sg:city":"Weil am Rhein",
    "sg:phone":"+49 7621/73237",
    "sg:postcode":"79576",
    "sg:province":"Baden-W\u00fcrttemberg",
    "wof:name":"G. A. Neubauer Ingenieur",
    "wof:placetype":"venue"
},
  "geometry": {"coordinates":[7.6188158989,47.5944099426],"type":"Point"}
}