{
  "type": "Feature",
  "properties": {
    "iso:country":"DE",
    "sg:address":"Huderstr. 25",
    "sg:city":"Bardowick",
    "sg:phone":"+49 4131/12686",
    "sg:postcode":"21357",
    "sg:province":"Niedersachsen",
    "wof:name":"Hermann Bardowicks",
    "wof:placetype":"venue"
},
  "geometry": {"coordinates":[10.391216,53.302532],"type":"Point"}
}