{
  "type": "Feature",
  "properties": {
    "iso:country":"DE",
    "sg:address":"Schulstr. 16",
    "sg:city":"Hehlen",
    "sg:phone":"+49 4955/332181",
    "sg:postcode":"37619",
    "sg:province":"Niedersachsen",
    "wof:name":"Stadtsparkasse Bodenwerder",
    "wof:placetype":"venue"
},
  "geometry": {"coordinates":[9.472911,51.98444],"type":"Point"}
}