{
  "type": "Feature",
  "properties": {
    "iso:country":"DE",
    "sg:address":"Grossmoorbg. 7a",
    "sg:city":"Hamburg",
    "sg:phone":"+49 89/9038433",
    "sg:postcode":"21079",
    "sg:province":"Hamburg",
    "wof:name":"Back-tech Maschinenbau- U. Handelsges. Mbh",
    "wof:placetype":"venue"
},
  "geometry": {"coordinates":[11.7528133392,48.1559371948],"type":"Point"}
}