{
  "type": "Feature",
  "properties": {
    "iso:country":"DE",
    "sg:address":"Mescheder Str. 22",
    "sg:city":"Sundern",
    "sg:phone":"+49 2933/6979",
    "sg:postcode":"59846",
    "sg:province":"Nordrhein-Westfalen",
    "wof:name":"Haus Der Wohnkultur M\u00f6belhandel-verwaltungs-gmbh",
    "wof:placetype":"venue"
},
  "geometry": {"coordinates":[8.008491,51.330021],"type":"Point"}
}