{
  "type": "Feature",
  "properties": {
    "iso:country":"DE",
    "sg:address":"Schwarzwaldstr. 21",
    "sg:city":"H\u00fcgelsheim",
    "sg:phone":"+49 7229/4529",
    "sg:postcode":"76549",
    "sg:province":"Baden-W\u00fcrttemberg",
    "wof:name":"Hartmut R\u00f6singer",
    "wof:placetype":"venue"
},
  "geometry": {"coordinates":[8.110828,48.794884],"type":"Point"}
}