{
  "type": "Feature",
  "properties": {
    "iso:country":"DE",
    "sg:address":"Wefelshohler Str. 50",
    "sg:city":"L\u00fcdenscheid",
    "sg:phone":"+49 2351/938750",
    "sg:postcode":"58511",
    "sg:province":"Nordrhein-Westfalen",
    "wof:name":"Grafe Druck Gmbh",
    "wof:placetype":"venue"
},
  "geometry": {"coordinates":[7.654265,51.215694],"type":"Point"}
}