{
  "type": "Feature",
  "properties": {
    "iso:country":"DE",
    "sg:address":"Ratzelstr. 210",
    "sg:city":"Leipzig",
    "sg:phone":"+49 341",
    "sg:postcode":"04207",
    "sg:province":"Sachsen",
    "wof:name":"Funkfachhandel Lemp - Ihr Mobilfunkspezialist",
    "wof:placetype":"venue"
},
  "geometry": {"coordinates":[12.272549,51.309525],"type":"Point"}
}