{
  "type": "Feature",
  "properties": {
    "iso:country":"DE",
    "sg:address":"Klausstr. B 242",
    "sg:city":"Friesdorf",
    "sg:postcode":"06543",
    "sg:province":"Sachsen-Anhalt",
    "wof:name":"Mansfelder Land-gastronomie Gesch\u00e4ftsf\u00fchrungs- Gmbh",
    "wof:placetype":"venue"
},
  "geometry": {"coordinates":[11.305296,51.621693],"type":"Point"}
}