{
  "type": "Feature",
  "properties": {
    "iso:country":"DE",
    "sg:address":"Sonnenstr. 1a",
    "sg:city":"Holzg\u00fcnz",
    "sg:phone":"+49 8393/7031",
    "sg:postcode":"87752",
    "sg:province":"Bayern",
    "wof:name":"M. A. S. Schuster Handels-gmbh",
    "wof:placetype":"venue"
},
  "geometry": {"coordinates":[10.2451601028,48.0164871216],"type":"Point"}
}