{
  "type": "Feature",
  "properties": {
    "iso:country":"DE",
    "sg:address":"Sendlinger-Tor-Platz",
    "sg:city":"Muenchen",
    "sg:phone":"+49 89/54838100",
    "sg:postcode":"80336",
    "sg:province":"Bayern",
    "wof:name":"Hengstenberg Und Partner Gmbh Versicherungsmakler Seit 1983",
    "wof:placetype":"venue"
},
  "geometry": {"coordinates":[11.565505,48.133686],"type":"Point"}
}