{
  "type": "Feature",
  "properties": {
    "iso:country":"DE",
    "sg:address":"Petersberg 25",
    "sg:city":"Petersberg",
    "sg:phone":"+49 34325/20351",
    "sg:postcode":"04720",
    "sg:province":"Sachsen",
    "wof:name":"Rainer Fickenwirth",
    "wof:placetype":"venue"
},
  "geometry": {"coordinates":[13.2219085693,51.1247673035],"type":"Point"}
}