{
  "type": "Feature",
  "properties": {
    "iso:country":"DE",
    "sg:address":"Bundesstr. 15",
    "sg:city":"Hamburg",
    "sg:phone":"+49 40/4107585",
    "sg:postcode":"20146",
    "sg:province":"Hamburg",
    "wof:name":"La Mirabelle",
    "wof:placetype":"venue"
},
  "geometry": {"coordinates":[9.9805603027,53.5650177002],"type":"Point"}
}