{
  "type": "Feature",
  "properties": {
    "iso:country":"DE",
    "sg:address":"Volmerswerther Str 41",
    "sg:city":"D\u00fcsseldorf",
    "sg:phone":"+49 211/390060",
    "sg:postcode":"40221",
    "sg:province":"Nordrhein-Westfalen",
    "wof:name":"Esser, Franke & Partner Gmbh",
    "wof:placetype":"venue"
},
  "geometry": {"coordinates":[6.761086,51.208843],"type":"Point"}
}