{
  "type": "Feature",
  "properties": {
    "iso:country":"DE",
    "sg:address":"Kolpingstr. 22",
    "sg:city":"Menden",
    "sg:phone":"+49 2373/14466",
    "sg:postcode":"58706",
    "sg:province":"Nordrhein-Westfalen",
    "wof:name":"Dr. Med. Peter Koch Arzt F\u00fcr Gyn\u00e4kologie",
    "wof:placetype":"venue"
},
  "geometry": {"coordinates":[7.1619391441,50.7925262451],"type":"Point"}
}