{
  "type": "Feature",
  "properties": {
    "iso:country":"DE",
    "sg:address":"Burgbergstr. 72",
    "sg:city":"Erlangen",
    "sg:phone":"+49 9131/29848",
    "sg:postcode":"91054",
    "sg:province":"Bayern",
    "wof:name":"Rolf Hartmann Rechtsanwalt",
    "wof:placetype":"venue"
},
  "geometry": {"coordinates":[11.0082044601,49.6085700989],"type":"Point"}
}