{
  "type": "Feature",
  "properties": {
    "iso:country":"DE",
    "sg:address":"Rudolf-Breitscheid-Str. 12",
    "sg:city":"Schweina",
    "sg:postcode":"36448",
    "sg:province":"Th\u00fcringen",
    "wof:name":"Cranio-dental Verwaltungsges. Mbh",
    "wof:placetype":"venue"
},
  "geometry": {"coordinates":[10.3356513977,50.8239212036],"type":"Point"}
}