{
  "type": "Feature",
  "properties": {
    "iso:country":"DE",
    "sg:address":"Kosselstr. 13",
    "sg:city":"Braunschweig",
    "sg:phone":"+49 531/511831",
    "sg:postcode":"38116",
    "sg:province":"Niedersachsen",
    "wof:name":"Schulverein Oswald Berkhan- Schule E. V.",
    "wof:placetype":"venue"
},
  "geometry": {"coordinates":[10.4622497559,52.2864303589],"type":"Point"}
}