{
  "type": "Feature",
  "properties": {
    "iso:country":"DE",
    "sg:address":"Goethestr. 18",
    "sg:city":"Zeil",
    "sg:phone":"+49 9524/1208",
    "sg:postcode":"97475",
    "sg:province":"Bayern",
    "wof:name":"Tino Hirt",
    "wof:placetype":"venue"
},
  "geometry": {"coordinates":[10.5961990356,50.0144996643],"type":"Point"}
}