{
  "type": "Feature",
  "properties": {
    "iso:country":"DE",
    "sg:address":"Augsburger Str. 42",
    "sg:city":"Dresden",
    "sg:phone":"+49 351/3109920",
    "sg:postcode":"01309",
    "sg:province":"Sachsen",
    "wof:name":"Gerd K\u00fcchenmeister Hdl. Vertreter Schl\u00fcsseldienst",
    "wof:placetype":"venue"
},
  "geometry": {"coordinates":[13.789115,51.049046],"type":"Point"}
}