{
  "type": "Feature",
  "properties": {
    "iso:country":"DE",
    "sg:address":"Saalburgstr. 18 a",
    "sg:city":"Friedrichsdorf",
    "sg:phone":"+49 6172/77577",
    "sg:postcode":"61381",
    "sg:province":"Hessen",
    "wof:name":"Gisela Zimmermann Architektin",
    "wof:placetype":"venue"
},
  "geometry": {"coordinates":[8.632448,50.2551],"type":"Point"}
}