{
  "type": "Feature",
  "properties": {
    "iso:country":"DE",
    "sg:address":"Nordbahnhofstr. 2",
    "sg:city":"Husum",
    "sg:phone":"+49 4841/83520",
    "sg:postcode":"25813",
    "sg:province":"Schleswig-Holstein",
    "wof:name":"Redaktion Husum Husum Druck- Und Verlagsges.",
    "wof:placetype":"venue"
},
  "geometry": {"coordinates":[9.0433702469,54.4771003723],"type":"Point"}
}