{
  "type": "Feature",
  "properties": {
    "iso:country":"DE",
    "sg:address":"Von-Ketteler-Str. 36",
    "sg:city":"Hildesheim",
    "sg:phone":"+49 5121/27701",
    "sg:postcode":"31137",
    "sg:province":"Niedersachsen",
    "wof:name":"Dagmar Kickler-meyer Krankengymnastin",
    "wof:placetype":"venue"
},
  "geometry": {"coordinates":[9.912546,52.168076],"type":"Point"}
}