{
  "type": "Feature",
  "properties": {
    "iso:country":"DE",
    "sg:address":"Westf\u00e4lische Str. 4",
    "sg:city":"Olpe",
    "sg:phone":"+49 2761/400281",
    "sg:postcode":"57462",
    "sg:province":"Nordrhein-Westfalen",
    "wof:name":"Dr. Peter R\u00f6mer Heilpraktiker",
    "wof:placetype":"venue"
},
  "geometry": {"coordinates":[7.8440089226,51.02967453],"type":"Point"}
}