{
  "type": "Feature",
  "properties": {
    "iso:country":"DE",
    "sg:address":"Bachstr. 20",
    "sg:city":"Gro\u00dfhabersdorf",
    "sg:phone":"+49 9105/230",
    "sg:postcode":"90613",
    "sg:province":"Bayern",
    "wof:name":"Andreas Boas Lagerhaus",
    "wof:placetype":"venue"
},
  "geometry": {"coordinates":[10.7874,49.405479],"type":"Point"}
}