{
  "type": "Feature",
  "properties": {
    "iso:country":"DE",
    "sg:address":"Am Flachmoor 16",
    "sg:city":"N\u00fcrnberg",
    "sg:phone":"+49 911/442344",
    "sg:postcode":"90475",
    "sg:province":"Bayern",
    "wof:name":"Hiltner Gmbh",
    "wof:placetype":"venue"
},
  "geometry": {"coordinates":[11.1800985336,49.386100769],"type":"Point"}
}