{
  "type": "Feature",
  "properties": {
    "iso:country":"DE",
    "sg:address":"Eremitagestr. 30",
    "sg:city":"Bayreuth",
    "sg:phone":"+49 921/92496",
    "sg:postcode":"95448",
    "sg:province":"Bayern",
    "wof:name":"M. Wilczek",
    "wof:placetype":"venue"
},
  "geometry": {"coordinates":[11.6165533066,49.9471855164],"type":"Point"}
}