{
  "type": "Feature",
  "properties": {
    "iso:country":"DE",
    "sg:address":"Bergische Landstr. 88",
    "sg:city":"R\u00f6srath",
    "sg:phone":"+49 2205/84753",
    "sg:postcode":"51503",
    "sg:province":"Nordrhein-Westfalen",
    "wof:name":"Rainer Sekulla",
    "wof:placetype":"venue"
},
  "geometry": {"coordinates":[7.197332859,50.9295463562],"type":"Point"}
}