{
  "type": "Feature",
  "properties": {
    "iso:country":"DE",
    "sg:address":"Hungener Weg 24",
    "sg:city":"W\u00f6lfersheim",
    "sg:phone":"+49 6036/418",
    "sg:postcode":"61200",
    "sg:province":"Hessen",
    "wof:name":"M\u00f6rschel Heiz\u00f6l Gmbh",
    "wof:placetype":"venue"
},
  "geometry": {"coordinates":[8.8090524673,50.3834266663],"type":"Point"}
}