{
  "type": "Feature",
  "properties": {
    "iso:country":"DE",
    "sg:address":"Mohrenstr. 11",
    "sg:city":"Coburg",
    "sg:phone":"+49 9561/74044",
    "sg:postcode":"96450",
    "sg:province":"Bayern",
    "wof:name":"Eckart Staritz Rechtsanwalt",
    "wof:placetype":"venue"
},
  "geometry": {"coordinates":[10.9616708755,50.2619552612],"type":"Point"}
}