{
  "type": "Feature",
  "properties": {
    "iso:country":"DE",
    "sg:address":"Sonnenstr. 3",
    "sg:city":"Lengede",
    "sg:phone":"+49 5174/1805",
    "sg:postcode":"38268",
    "sg:province":"Niedersachsen",
    "wof:name":"Walter Popke",
    "wof:placetype":"venue"
},
  "geometry": {"coordinates":[10.2954463959,52.2206611633],"type":"Point"}
}