{
  "type": "Feature",
  "properties": {
    "iso:country":"DE",
    "sg:address":"Freie Str. 8",
    "sg:city":"Rosdorf",
    "sg:phone":"+49 5509/365",
    "sg:postcode":"37124",
    "sg:province":"Niedersachsen",
    "wof:name":"Heiko K\u00fcck",
    "wof:placetype":"venue"
},
  "geometry": {"coordinates":[9.8954372406,51.5038757324],"type":"Point"}
}