{
  "type": "Feature",
  "properties": {
    "iso:country":"DE",
    "sg:address":"Hans-B\u00f6ckler-Str. 8",
    "sg:city":"G\u00f6ttingen",
    "sg:phone":"+49 4955/1505180",
    "sg:postcode":"37079",
    "sg:province":"Niedersachsen",
    "wof:name":"Die Signmaker Gmbh",
    "wof:placetype":"venue"
},
  "geometry": {"coordinates":[9.882594,51.550034],"type":"Point"}
}