{
  "type": "Feature",
  "properties": {
    "iso:country":"DE",
    "sg:address":"Haagstr. 36",
    "sg:city":"M\u00f6mbris",
    "sg:phone":"+49 6029/5504",
    "sg:postcode":"63776",
    "sg:province":"Bayern",
    "wof:name":"Stefan Hellwig",
    "wof:placetype":"venue"
},
  "geometry": {"coordinates":[9.112374,50.05238],"type":"Point"}
}