{
  "type": "Feature",
  "properties": {
    "iso:country":"DE",
    "sg:address":"Saseler Chaussee 111",
    "sg:city":"Hamburg",
    "sg:phone":"+49 40/6003505",
    "sg:postcode":"22393",
    "sg:province":"Hamburg",
    "wof:name":"Bernd Bernhard Behr Steuerberater",
    "wof:placetype":"venue"
},
  "geometry": {"coordinates":[10.0997457504,53.644367218],"type":"Point"}
}