{
  "type": "Feature",
  "properties": {
    "iso:country":"DE",
    "sg:address":"Otto-Bayer-Str. 10::",
    "sg:city":"Esslingen",
    "sg:phone":"+49 4966/21810",
    "sg:postcode":"73730",
    "sg:province":"Baden-W\u00fcrttemberg",
    "wof:name":"Grenzebach Bsh Gmbh",
    "wof:placetype":"venue"
},
  "geometry": {"coordinates":[9.707366,50.871754],"type":"Point"}
}