{
  "type": "Feature",
  "properties": {
    "iso:country":"DE",
    "sg:address":"Im Dombach 4",
    "sg:city":"Eschenburg",
    "sg:phone":"+49 2774/6033",
    "sg:postcode":"35713",
    "sg:province":"Hessen",
    "wof:name":"Bauunternehmung Fritz M\u00fcller Gmbh",
    "wof:placetype":"venue"
},
  "geometry": {"coordinates":[8.342215538,50.8175468445],"type":"Point"}
}