{
  "type": "Feature",
  "properties": {
    "iso:country":"DE",
    "sg:address":"Feldstr. 12",
    "sg:city":"Katzenelnbogen",
    "sg:phone":"+49 6486/8411",
    "sg:postcode":"56368",
    "sg:province":"Rheinland-Pfalz",
    "wof:name":"Fiebig Gmbh",
    "wof:placetype":"venue"
},
  "geometry": {"coordinates":[7.980833,50.265495],"type":"Point"}
}