{
  "type": "Feature",
  "properties": {
    "iso:country":"DE",
    "sg:address":"Ludwigstr. 59",
    "sg:city":"Wald-Michelbach",
    "sg:phone":"+49 6207/2666",
    "sg:postcode":"69483",
    "sg:province":"Hessen",
    "wof:name":"Sch\u00e4fer Textilhaus Gmbh",
    "wof:placetype":"venue"
},
  "geometry": {"coordinates":[8.8267068863,49.5712623596],"type":"Point"}
}