{
  "type": "Feature",
  "properties": {
    "iso:country":"DE",
    "sg:address":"Glockenklanger Str. 1",
    "sg:city":"Johanngeorgenstadt",
    "sg:phone":"+49 3773/882079",
    "sg:postcode":"08349",
    "sg:province":"Sachsen",
    "wof:name":"J\u00fcrgen Kr\u00e4tzschmar",
    "wof:placetype":"venue"
},
  "geometry": {"coordinates":[12.723057,50.429764],"type":"Point"}
}