{
  "type": "Feature",
  "properties": {
    "iso:country":"DE",
    "sg:address":"M\u00fchlhagener Str. 5",
    "sg:city":"Riegsee",
    "sg:postcode":"82418",
    "sg:province":"Bayern",
    "wof:name":"Margarethe Goebels Gmbh",
    "wof:placetype":"venue"
},
  "geometry": {"coordinates":[11.2301111221,47.6746139526],"type":"Point"}
}