{
  "type": "Feature",
  "properties": {
    "iso:country":"DE",
    "sg:address":"Wellinghofer Str. 1",
    "sg:city":"Dortmund",
    "sg:phone":"+49 231/415173",
    "sg:postcode":"44263",
    "sg:province":"Nordrhein-Westfalen",
    "wof:name":"Kunze-olms",
    "wof:placetype":"venue"
},
  "geometry": {"coordinates":[7.49875,51.486469],"type":"Point"}
}