{
  "type": "Feature",
  "properties": {
    "iso:country":"DE",
    "sg:address":"Bahnhofstr. 86",
    "sg:city":"Zwenkau",
    "sg:phone":"+49 34203/52912",
    "sg:postcode":"04442",
    "sg:province":"Sachsen",
    "wof:name":"Manfred Jope",
    "wof:placetype":"venue"
},
  "geometry": {"coordinates":[12.339451,51.216137],"type":"Point"}
}