{
  "type": "Feature",
  "properties": {
    "iso:country":"DE",
    "sg:address":"Solinger Str. 29",
    "sg:city":"Langenfeld",
    "sg:phone":"+49 2173/22673",
    "sg:postcode":"40764",
    "sg:province":"Nordrhein-Westfalen",
    "wof:name":"Angelika Straatman Automaten Service Gmbh",
    "wof:placetype":"venue"
},
  "geometry": {"coordinates":[6.951731,51.111542],"type":"Point"}
}