{
  "type": "Feature",
  "properties": {
    "iso:country":"DE",
    "sg:address":"Steinbruchweg 3",
    "sg:city":"Neckarbischofsheim",
    "sg:postcode":"74924",
    "sg:province":"Baden-W\u00fcrttemberg",
    "wof:name":"Aig Gmbh",
    "wof:placetype":"venue"
},
  "geometry": {"coordinates":[9.014109,49.270653],"type":"Point"}
}