{
  "type": "Feature",
  "properties": {
    "iso:country":"DE",
    "sg:address":"Brunnenstr. 31",
    "sg:city":"Fronhausen",
    "sg:phone":"+49 6426/92340",
    "sg:postcode":"35112",
    "sg:province":"Hessen",
    "wof:name":"Etzelm\u00fcller Reisen Gmbh & Co. Busbetriebs Kg",
    "wof:placetype":"venue"
},
  "geometry": {"coordinates":[8.6662473679,50.7076759338],"type":"Point"}
}