{
  "type": "Feature",
  "properties": {
    "iso:country":"DE",
    "sg:address":"Bahnhofstr. 38",
    "sg:city":"Staudach-Egerndach",
    "sg:phone":"+49 8641/2443",
    "sg:postcode":"83224",
    "sg:province":"Bayern",
    "wof:name":"K. Guggenbichler",
    "wof:placetype":"venue"
},
  "geometry": {"coordinates":[12.4809923172,47.7798347473],"type":"Point"}
}