{
  "type": "Feature",
  "properties": {
    "iso:country":"DE",
    "sg:address":"Lemper Str. 38",
    "sg:city":"Sprockh\u00f6vel",
    "sg:phone":"+49 2339/2869",
    "sg:postcode":"45549",
    "sg:province":"Nordrhein-Westfalen",
    "wof:name":"Erich B\u00fchren Jun.",
    "wof:placetype":"venue"
},
  "geometry": {"coordinates":[7.2765860558,51.3272514343],"type":"Point"}
}