{
  "type": "Feature",
  "properties": {
    "iso:country":"DE",
    "sg:address":"Dammstr. 8",
    "sg:city":"Waiblingen",
    "sg:phone":"+49 7151/959040",
    "sg:postcode":"71332",
    "sg:province":"Baden-W\u00fcrttemberg",
    "wof:name":"Ernst Pfleiderer",
    "wof:placetype":"venue"
},
  "geometry": {"coordinates":[9.3026485443,48.8272590637],"type":"Point"}
}