{
  "type": "Feature",
  "properties": {
    "iso:country":"DE",
    "sg:address":"Aktienstr. 161b",
    "sg:city":"M\u00fclheim",
    "sg:phone":"+49 208/479236",
    "sg:postcode":"45473",
    "sg:province":"Nordrhein-Westfalen",
    "wof:name":"Peco Greenline Sportartikel Vertriebs Gmbh",
    "wof:placetype":"venue"
},
  "geometry": {"coordinates":[6.8972330093,51.4419822693],"type":"Point"}
}