{
  "type": "Feature",
  "properties": {
    "iso:country":"DE",
    "sg:address":"G\u00fcstener Str. 12",
    "sg:city":"J\u00fclich",
    "sg:phone":"+49 2463/3749",
    "sg:postcode":"52428",
    "sg:province":"Nordrhein-Westfalen",
    "wof:name":"Franz Johnen & Jakob Hecker",
    "wof:placetype":"venue"
},
  "geometry": {"coordinates":[6.419208,50.950409],"type":"Point"}
}