{
  "type": "Feature",
  "properties": {
    "iso:country":"DE",
    "sg:address":"D\u00fcnner Str. 31",
    "sg:city":"M\u00f6nchengladbach",
    "sg:phone":"+49 2161/633076",
    "sg:postcode":"41066",
    "sg:province":"Nordrhein-Westfalen",
    "wof:name":"E. Sch\u00fcrkens",
    "wof:placetype":"venue"
},
  "geometry": {"coordinates":[6.457930088,51.2238731384],"type":"Point"}
}