{
  "type": "Feature",
  "properties": {
    "iso:country":"DE",
    "sg:address":"Warwischer Hinterdeich 82",
    "sg:city":"Hamburg",
    "sg:phone":"+49 40/7372182",
    "sg:postcode":"21037",
    "sg:province":"Hamburg",
    "wof:name":"Vbu Vierl\u00e4nder Bestattungs- Unternehmen Elfriede Frey Gmbh",
    "wof:placetype":"venue"
},
  "geometry": {"coordinates":[10.117004,53.433228],"type":"Point"}
}