{
  "type": "Feature",
  "properties": {
    "iso:country":"DE",
    "sg:address":"Bl\u00fccherstr. 1",
    "sg:city":"Wesel",
    "sg:phone":"+49 281/52723",
    "sg:postcode":"46485",
    "sg:province":"Nordrhein-Westfalen",
    "wof:name":"H. Stahl",
    "wof:placetype":"venue"
},
  "geometry": {"coordinates":[6.6306009293,51.664730072],"type":"Point"}
}