{
  "type": "Feature",
  "properties": {
    "iso:country":"DE",
    "sg:address":"Mannhardtweg 11",
    "sg:city":"Berlin",
    "sg:phone":"+49 30/36801325",
    "sg:postcode":"14089",
    "sg:province":"Berlin",
    "wof:name":"Mussotter Immobilien",
    "wof:placetype":"venue"
},
  "geometry": {"coordinates":[13.1212596893,52.4548568726],"type":"Point"}
}