{
  "type": "Feature",
  "properties": {
    "iso:country":"DE",
    "sg:address":"Kranstr. 25",
    "sg:city":"Hamm",
    "sg:postcode":"59071",
    "sg:province":"Nordrhein-Westfalen",
    "wof:name":"Charite Cosmetic Vertriebs Gmbh",
    "wof:placetype":"venue"
},
  "geometry": {"coordinates":[7.945829,51.686825],"type":"Point"}
}