{
  "type": "Feature",
  "properties": {
    "iso:country":"DE",
    "sg:address":"Unckelstr. 14",
    "sg:city":"M\u00fcnster",
    "sg:phone":"+49 2501/27770",
    "sg:postcode":"48165",
    "sg:province":"Nordrhein-Westfalen",
    "wof:name":"Dreymann & Schulte Consulting Gmbh",
    "wof:placetype":"venue"
},
  "geometry": {"coordinates":[7.6475682259,51.906288147],"type":"Point"}
}