{
  "type": "Feature",
  "properties": {
    "iso:country":"DE",
    "sg:address":"Herbergsweg 1",
    "sg:city":"Finnentrop",
    "sg:phone":"+49 2721/7293",
    "sg:postcode":"57413",
    "sg:province":"Nordrhein-Westfalen",
    "wof:name":"Jupp-sch\u00f6ttler-jugendherberge",
    "wof:placetype":"venue"
},
  "geometry": {"coordinates":[7.9773368835,51.1722488403],"type":"Point"}
}