{
  "type": "Feature",
  "properties": {
    "iso:country":"DE",
    "sg:address":"Dorfstr. 8",
    "sg:city":"Kammerstein",
    "sg:phone":"+49 9122/4175",
    "sg:postcode":"91126",
    "sg:province":"Bayern",
    "wof:name":"Leonhard Schwab",
    "wof:placetype":"venue"
},
  "geometry": {"coordinates":[10.970078,49.292698],"type":"Point"}
}