{
  "type": "Feature",
  "properties": {
    "iso:country":"DE",
    "sg:address":"Duisburger Str. 149",
    "sg:city":"Duisburg",
    "sg:phone":"+49 203/559631",
    "sg:postcode":"47166",
    "sg:province":"Nordrhein-Westfalen",
    "wof:name":"Krinn",
    "wof:placetype":"venue"
},
  "geometry": {"coordinates":[6.7802929878,51.4905281067],"type":"Point"}
}