{
  "type": "Feature",
  "properties": {
    "iso:country":"DE",
    "sg:address":"Kernriedstr. 8",
    "sg:city":"Augsburg",
    "sg:phone":"+49 821/401177",
    "sg:postcode":"86156",
    "sg:province":"Bayern",
    "wof:name":"Kurt Prestel",
    "wof:placetype":"venue"
},
  "geometry": {"coordinates":[10.8640069962,48.3821182251],"type":"Point"}
}