{
  "type": "Feature",
  "properties": {
    "iso:country":"DE",
    "sg:address":"Heuberger Str. 28",
    "sg:city":"H\u00f6chstadt",
    "sg:postcode":"91315",
    "sg:province":"Bayern",
    "wof:name":"Paulus Innenausbau Gmbh",
    "wof:placetype":"venue"
},
  "geometry": {"coordinates":[10.8136978149,49.7075004578],"type":"Point"}
}