{
  "type": "Feature",
  "properties": {
    "iso:country":"DE",
    "sg:address":"St.-Josef-Str. 17",
    "sg:city":"Holzkirchen",
    "sg:phone":"+49 8024/7268",
    "sg:postcode":"83607",
    "sg:province":"Bayern",
    "wof:name":"J. Eschbaumer",
    "wof:placetype":"venue"
},
  "geometry": {"coordinates":[11.694986,47.880772],"type":"Point"}
}