{
  "type": "Feature",
  "properties": {
    "iso:country":"DE",
    "sg:address":"Kleingem\u00fcnder Str. 111",
    "sg:city":"Heidelberg",
    "sg:phone":"+49 6221/808256",
    "sg:postcode":"69118",
    "sg:province":"Baden-W\u00fcrttemberg",
    "wof:name":"H. Kowatsch",
    "wof:placetype":"venue"
},
  "geometry": {"coordinates":[8.7742843628,49.4147644043],"type":"Point"}
}