{
  "type": "Feature",
  "properties": {
    "iso:country":"DE",
    "sg:address":"Hoheluftchaussee 125",
    "sg:city":"Hamburg",
    "sg:phone":"+49 40/4203055",
    "sg:postcode":"20253",
    "sg:province":"Hamburg",
    "wof:name":"Smileys Graetz Kg",
    "wof:placetype":"venue"
},
  "geometry": {"coordinates":[9.970263,53.583111],"type":"Point"}
}