{
  "type": "Feature",
  "properties": {
    "iso:country":"DE",
    "sg:address":"Gretenbachstr. 15",
    "sg:city":"Bad Orb",
    "sg:phone":"+49 6052/6266",
    "sg:postcode":"63619",
    "sg:province":"Hessen",
    "wof:name":"Restaurant Salzgrafenkeller",
    "wof:placetype":"venue"
},
  "geometry": {"coordinates":[9.3490247726,50.2264823914],"type":"Point"}
}