{
  "type": "Feature",
  "properties": {
    "iso:country":"DE",
    "sg:address":"Gerresheimer Str 2",
    "sg:city":"Amberg",
    "sg:phone":"+49 9621/82030",
    "sg:postcode":"92224",
    "sg:province":"Bayern",
    "wof:name":"Kunststoff Birner",
    "wof:placetype":"venue"
},
  "geometry": {"coordinates":[11.881142,49.429672],"type":"Point"}
}