{
  "type": "Feature",
  "properties": {
    "iso:country":"DE",
    "sg:address":"Zwickauer Str. 336",
    "sg:city":"Chemnitz",
    "sg:phone":"+49 371/852562",
    "sg:postcode":"09116",
    "sg:province":"Sachsen",
    "wof:name":"Rudolf Wetzel",
    "wof:placetype":"venue"
},
  "geometry": {"coordinates":[12.862764,50.819584],"type":"Point"}
}