{
  "type": "Feature",
  "properties": {
    "iso:country":"DE",
    "sg:address":"Rathausstr. 60",
    "sg:city":"Wiesbaden",
    "sg:phone":"+49 611/602390",
    "sg:postcode":"65203",
    "sg:province":"Hessen",
    "wof:name":"Peter Deutschmann Masseur",
    "wof:placetype":"venue"
},
  "geometry": {"coordinates":[8.239546,50.041824],"type":"Point"}
}