{
  "type": "Feature",
  "properties": {
    "iso:country":"DE",
    "sg:address":"Beethovenweg 22",
    "sg:city":"Herbrechtingen",
    "sg:phone":"+49 7324/6254",
    "sg:postcode":"89542",
    "sg:province":"Baden-W\u00fcrttemberg",
    "wof:name":"Ipe Produktionsges. F\u00fcr Entsorgungssysteme Mbh",
    "wof:placetype":"venue"
},
  "geometry": {"coordinates":[10.17858,48.633839],"type":"Point"}
}