{
  "type": "Feature",
  "properties": {
    "iso:country":"DE",
    "sg:address":"Belgradstr. 47/2",
    "sg:city":"M\u00fcnchen",
    "sg:phone":"+49 89/394085",
    "sg:postcode":"80796",
    "sg:province":"Bayern",
    "wof:name":"Dr. K\u00f6rner Und Partner Steuerberatungs Gmbh",
    "wof:placetype":"venue"
},
  "geometry": {"coordinates":[11.5739688873,48.1651039124],"type":"Point"}
}