{
  "type": "Feature",
  "properties": {
    "iso:country":"DE",
    "sg:address":"Rossinistr. 24",
    "sg:city":"N\u00fcrnberg",
    "sg:phone":"+49 9122/98960",
    "sg:postcode":"90455",
    "sg:province":"Bayern",
    "wof:name":"Transport-kontor Mittel- Franken Gmbh & Co. Verm.",
    "wof:placetype":"venue"
},
  "geometry": {"coordinates":[11.0565567017,49.3546562195],"type":"Point"}
}