{
  "type": "Feature",
  "properties": {
    "iso:country":"DE",
    "sg:address":"Kleine Falterstr. 27",
    "sg:city":"Stuttgart",
    "sg:phone":"+49 711/7654222",
    "sg:postcode":"70597",
    "sg:province":"Baden-W\u00fcrttemberg",
    "wof:name":"Hartmut Fuchs Architekt",
    "wof:placetype":"venue"
},
  "geometry": {"coordinates":[9.173722,48.744789],"type":"Point"}
}