{
  "type": "Feature",
  "properties": {
    "iso:country":"DE",
    "sg:address":"Bahnhofstr. 79",
    "sg:city":"Pfungstadt",
    "sg:phone":"+49 6157/4155",
    "sg:postcode":"64319",
    "sg:province":"Hessen",
    "wof:name":"Blumen Schulz",
    "wof:placetype":"venue"
},
  "geometry": {"coordinates":[8.602873,49.808842],"type":"Point"}
}