{
  "type": "Feature",
  "properties": {
    "iso:country":"DE",
    "sg:address":"Hogendiek 4",
    "sg:city":"Ganderkesee",
    "sg:phone":"+49 4221/43770",
    "sg:postcode":"27777",
    "sg:province":"Niedersachsen",
    "wof:name":"Gisela Glasow",
    "wof:placetype":"venue"
},
  "geometry": {"coordinates":[8.605363,53.074062],"type":"Point"}
}