{
  "type": "Feature",
  "properties": {
    "iso:country":"DE",
    "sg:address":"Kurhofer Str. 26",
    "sg:city":"Heusweiler",
    "sg:phone":"+49 6806/78470",
    "sg:postcode":"66265",
    "sg:province":"Saarland",
    "wof:name":"Edmund Croon",
    "wof:placetype":"venue"
},
  "geometry": {"coordinates":[6.92892,49.337753],"type":"Point"}
}