{
  "type": "Feature",
  "properties": {
    "iso:country":"DE",
    "sg:address":"Sch\u00f6nebecker Str. 1",
    "sg:city":"Joachimsthal",
    "sg:phone":"+49 33361/555",
    "sg:postcode":"16247",
    "sg:province":"Brandenburg",
    "wof:name":"Lutz Folgmann",
    "wof:placetype":"venue"
},
  "geometry": {"coordinates":[13.7413816452,52.9768638611],"type":"Point"}
}