{
  "type": "Feature",
  "properties": {
    "iso:country":"DE",
    "sg:address":"Hauptstr. 165",
    "sg:city":"Hemer",
    "sg:phone":"+49 2372/2931",
    "sg:postcode":"58675",
    "sg:province":"Nordrhein-Westfalen",
    "wof:name":"Vogt",
    "wof:placetype":"venue"
},
  "geometry": {"coordinates":[7.766995,51.38303],"type":"Point"}
}