{
  "type": "Feature",
  "properties": {
    "iso:country":"DE",
    "sg:address":"K\u00f6nigstr. 73",
    "sg:city":"Landau",
    "sg:phone":"+49 6341/87058",
    "sg:postcode":"76829",
    "sg:province":"Rheinland-Pfalz",
    "wof:name":"Dvr Recherchen- Und Info-dienst Gmbh",
    "wof:placetype":"venue"
},
  "geometry": {"coordinates":[8.1156759262,49.1956138611],"type":"Point"}
}