{
  "type": "Feature",
  "properties": {
    "iso:country":"DE",
    "sg:address":"Anderlwies 7",
    "sg:city":"Haarbach",
    "sg:phone":"+49 8535/91031",
    "sg:postcode":"94542",
    "sg:province":"Bayern",
    "wof:name":"Ivg Internationale Vertiebs Gmbh",
    "wof:placetype":"venue"
},
  "geometry": {"coordinates":[13.1444616318,48.5052871704],"type":"Point"}
}