{
  "type": "Feature",
  "properties": {
    "iso:country":"DE",
    "sg:address":"Kieler Str. 278",
    "sg:city":"Hamburg",
    "sg:postcode":"22525",
    "sg:province":"Hamburg",
    "wof:name":"Tunescoot Oliver Kubbe E. K.",
    "wof:placetype":"venue"
},
  "geometry": {"coordinates":[9.9304246902,53.5907211304],"type":"Point"}
}