{
  "type": "Feature",
  "properties": {
    "iso:country":"DE",
    "sg:address":"Weststr. 6",
    "sg:city":"Schm\u00f6lln",
    "sg:postcode":"04626",
    "sg:province":"Th\u00fcringen",
    "wof:name":"Gpg Cyclamen Schm\u00f6lln",
    "wof:placetype":"venue"
},
  "geometry": {"coordinates":[12.3466596603,50.8948745728],"type":"Point"}
}