{
  "type": "Feature",
  "properties": {
    "iso:country":"DE",
    "sg:address":"Fischerstr. 9",
    "sg:city":"Bochum",
    "sg:phone":"+49 234/862680",
    "sg:postcode":"44805",
    "sg:province":"Nordrhein-Westfalen",
    "wof:name":"Kurt Borgwardt Gmbh",
    "wof:placetype":"venue"
},
  "geometry": {"coordinates":[7.285643,51.521526],"type":"Point"}
}