{
  "type": "Feature",
  "properties": {
    "iso:country":"DE",
    "sg:address":"Spiekersh\u00e4user Str. 3",
    "sg:city":"Kassel",
    "sg:phone":"+49 561/872161",
    "sg:postcode":"34125",
    "sg:province":"Hessen",
    "wof:name":"G. Buschek",
    "wof:placetype":"venue"
},
  "geometry": {"coordinates":[9.5340223312,51.3296279907],"type":"Point"}
}