{
  "type": "Feature",
  "properties": {
    "iso:country":"DE",
    "sg:address":"Rheinfeld 8",
    "sg:city":"Rheinberg",
    "sg:phone":"+49 2843/990016",
    "sg:postcode":"47495",
    "sg:province":"Nordrhein-Westfalen",
    "wof:name":"Metallbau Schlosserei Andre Jan\u00dfen Gmbh",
    "wof:placetype":"venue"
},
  "geometry": {"coordinates":[6.580855,51.554825],"type":"Point"}
}