{
  "type": "Feature",
  "properties": {
    "iso:country":"DE",
    "sg:address":"Thankirchen 17",
    "sg:city":"Dietramszell",
    "sg:phone":"+49 8027/508",
    "sg:postcode":"83623",
    "sg:province":"Bayern",
    "wof:name":"Hans Ra\u00dfhofer Ingenieur",
    "wof:placetype":"venue"
},
  "geometry": {"coordinates":[11.5663232803,47.8543014526],"type":"Point"}
}