{
  "type": "Feature",
  "properties": {
    "iso:country":"DE",
    "sg:address":"Carl-Netter-Str. 9",
    "sg:city":"B\u00fchl",
    "sg:phone":"+49 7223/902320",
    "sg:postcode":"77815",
    "sg:province":"Baden-W\u00fcrttemberg",
    "wof:name":"Bau Und Grund Immobilien-vermittlung Gmbh",
    "wof:placetype":"venue"
},
  "geometry": {"coordinates":[8.141612,48.698139],"type":"Point"}
}