{
  "type": "Feature",
  "properties": {
    "iso:country":"DE",
    "sg:address":"Werftstr. 46",
    "sg:city":"Andernach",
    "sg:phone":"+49 2632/1355",
    "sg:postcode":"56626",
    "sg:province":"Rheinland-Pfalz",
    "wof:name":"Anja Schneider-kohl Ergotherapeutsche Praxis",
    "wof:placetype":"venue"
},
  "geometry": {"coordinates":[7.411851,50.436268],"type":"Point"}
}