{
  "type": "Feature",
  "properties": {
    "iso:country":"DE",
    "sg:address":"Niddastr. 57",
    "sg:city":"Frankfurt",
    "sg:phone":"+49 69/233766",
    "sg:postcode":"60329",
    "sg:province":"Hessen",
    "wof:name":"Fl Fashion Rauchwarenhandels-gmbh",
    "wof:placetype":"venue"
},
  "geometry": {"coordinates":[8.66367,50.109306],"type":"Point"}
}