{
  "type": "Feature",
  "properties": {
    "iso:country":"DE",
    "sg:address":"Zum Auetal 23",
    "sg:city":"Garrel",
    "sg:phone":"+49 4474/930111",
    "sg:postcode":"49681",
    "sg:province":"Niedersachsen",
    "wof:name":"A. Thienel",
    "wof:placetype":"venue"
},
  "geometry": {"coordinates":[8.0270013809,52.9633865356],"type":"Point"}
}