{
  "type": "Feature",
  "properties": {
    "iso:country":"DE",
    "sg:address":"Marktplatz 50",
    "sg:city":"Lauf",
    "sg:phone":"+49 9123/82080",
    "sg:postcode":"91207",
    "sg:province":"Bayern",
    "wof:name":"Rats-apotheke",
    "wof:placetype":"venue"
},
  "geometry": {"coordinates":[11.280779,49.51141],"type":"Point"}
}