{
  "type": "Feature",
  "properties": {
    "iso:country":"DE",
    "sg:address":"Schwarzwaldstr. 105",
    "sg:city":"Stuttgart",
    "sg:phone":"+49 711/6871622",
    "sg:postcode":"70569",
    "sg:province":"Baden-W\u00fcrttemberg",
    "wof:name":"Beatrix Blessing Rechtsanw\u00e4ltin",
    "wof:placetype":"venue"
},
  "geometry": {"coordinates":[9.1214094162,48.7406616211],"type":"Point"}
}