{
  "type": "Feature",
  "properties": {
    "iso:country":"DE",
    "sg:address":"Bernhardstr. 40",
    "sg:city":"Apolda",
    "sg:phone":"+49 3644/2013",
    "sg:postcode":"99510",
    "sg:province":"Th\u00fcringen",
    "wof:name":"Simon H & T Gmbh",
    "wof:placetype":"venue"
},
  "geometry": {"coordinates":[11.5182323456,51.0280838013],"type":"Point"}
}