{
  "type": "Feature",
  "properties": {
    "iso:country":"DE",
    "sg:address":"Rudolf-Breitscheid-Str. 27",
    "sg:city":"Eberswalde",
    "sg:phone":"+49 3334/22298",
    "sg:postcode":"16225",
    "sg:province":"Brandenburg",
    "wof:name":"Schmidt Und Partner Gmbh",
    "wof:placetype":"venue"
},
  "geometry": {"coordinates":[13.807220459,52.8301849365],"type":"Point"}
}