{
  "type": "Feature",
  "properties": {
    "iso:country":"DE",
    "sg:address":"Heidst\u00fcckenkehre 71",
    "sg:city":"Hamburg",
    "sg:phone":"+49 40/6429777",
    "sg:postcode":"22179",
    "sg:province":"Hamburg",
    "wof:name":"Joachim Peters Ingenieur",
    "wof:placetype":"venue"
},
  "geometry": {"coordinates":[10.0939712524,53.6170196533],"type":"Point"}
}