{
  "type": "Feature",
  "properties": {
    "iso:country":"DE",
    "sg:address":"Krohnstr. 2",
    "sg:city":"Detmold",
    "sg:phone":"+49 5231/25731",
    "sg:postcode":"32756",
    "sg:province":"Nordrhein-Westfalen",
    "wof:name":"Praxis Dr. Med. Philippi Und Dr. Med. Rastetter-gutmann",
    "wof:placetype":"venue"
},
  "geometry": {"coordinates":[8.8830900192,51.9301109314],"type":"Point"}
}