{
  "type": "Feature",
  "properties": {
    "iso:country":"DE",
    "sg:address":"Neuer Weg 4",
    "sg:city":"Bad Krozingen",
    "sg:phone":"+49 7633/9334690",
    "sg:postcode":"79189",
    "sg:province":"Baden-W\u00fcrttemberg",
    "wof:name":"A. Eckert Steinmetz",
    "wof:placetype":"venue"
},
  "geometry": {"coordinates":[7.665763855,47.9050216675],"type":"Point"}
}