{
  "type": "Feature",
  "properties": {
    "iso:country":"DE",
    "sg:address":"Kappelstr. 1",
    "sg:city":"Nehren",
    "sg:phone":"+49 7473/7420",
    "sg:postcode":"72147",
    "sg:province":"Baden-W\u00fcrttemberg",
    "wof:name":"K. Nill",
    "wof:placetype":"venue"
},
  "geometry": {"coordinates":[9.0699119568,48.4312858582],"type":"Point"}
}