{
  "type": "Feature",
  "properties": {
    "iso:country":"DE",
    "sg:address":"Gohliser Stra\u00dfe 7",
    "sg:city":"Leipzig",
    "sg:phone":"+49 341/5647372",
    "sg:postcode":"04105",
    "sg:province":"Sachsen",
    "wof:name":"Werbeagentur Pi",
    "wof:placetype":"venue"
},
  "geometry": {"coordinates":[12.371154,51.35466],"type":"Point"}
}