{
  "type": "Feature",
  "properties": {
    "iso:country":"DE",
    "sg:address":"Kirchgasse 6",
    "sg:city":"Niederstetten",
    "sg:phone":"+49 7932/358",
    "sg:postcode":"97996",
    "sg:province":"Baden-W\u00fcrttemberg",
    "wof:name":"Evangelisches Pfarramt",
    "wof:placetype":"venue"
},
  "geometry": {"coordinates":[9.9197254181,49.4006500244],"type":"Point"}
}