{
  "type": "Feature",
  "properties": {
    "iso:country":"DE",
    "sg:address":"Bahnhofstr. 10-12",
    "sg:city":"Wiesbaden",
    "sg:phone":"+49 611/9016607",
    "sg:postcode":"65185",
    "sg:province":"Hessen",
    "wof:name":"Thomas Broadcasting Gmbh",
    "wof:placetype":"venue"
},
  "geometry": {"coordinates":[8.2425174713,50.0787086487],"type":"Point"}
}