{
  "type": "Feature",
  "properties": {
    "iso:country":"DE",
    "sg:address":"Kehrbeeke 5 a",
    "sg:city":"Braunschweig",
    "sg:phone":"+49 531/353111",
    "sg:postcode":"38108",
    "sg:province":"Niedersachsen",
    "wof:name":"Rudolf Steinke Architekt",
    "wof:placetype":"venue"
},
  "geometry": {"coordinates":[10.549699,52.300102],"type":"Point"}
}