{
  "type": "Feature",
  "properties": {
    "iso:country":"DE",
    "sg:address":"Amalienstr. 24",
    "sg:city":"Ettlingen",
    "sg:phone":"+49 7243/90265",
    "sg:postcode":"76275",
    "sg:province":"Baden-W\u00fcrttemberg",
    "wof:name":"Jaroslav Kosar Gmbh",
    "wof:placetype":"venue"
},
  "geometry": {"coordinates":[8.3723087311,48.9283180237],"type":"Point"}
}