{
  "type": "Feature",
  "properties": {
    "iso:country":"DE",
    "sg:address":"Klammstr. 21",
    "sg:city":"Mittenwald",
    "sg:phone":"+49 8823/2906",
    "sg:postcode":"82481",
    "sg:province":"Bayern",
    "wof:name":"Hans Knilling",
    "wof:placetype":"venue"
},
  "geometry": {"coordinates":[11.258808136,47.438659668],"type":"Point"}
}