{
  "type": "Feature",
  "properties": {
    "iso:country":"DE",
    "sg:address":"Schillerplatz 11",
    "sg:city":"Bamberg",
    "sg:phone":"+49 951/22876",
    "sg:postcode":"96047",
    "sg:province":"Bayern",
    "wof:name":"Restaurant Olympia",
    "wof:placetype":"venue"
},
  "geometry": {"coordinates":[10.8915510178,49.8897171021],"type":"Point"}
}