{
  "type": "Feature",
  "properties": {
    "iso:country":"DE",
    "sg:address":"Holstenplatz 6",
    "sg:city":"Elmshorn",
    "sg:phone":"+49 4121/25606",
    "sg:postcode":"25335",
    "sg:province":"Schleswig-Holstein",
    "wof:name":"Lederwaren Liedtke",
    "wof:placetype":"venue"
},
  "geometry": {"coordinates":[9.657747,53.755276],"type":"Point"}
}