{
  "type": "Feature",
  "properties": {
    "iso:country":"DE",
    "sg:address":"Kleine Reihe 3",
    "sg:city":"Seesen",
    "sg:phone":"+49 5381/5471",
    "sg:postcode":"38723",
    "sg:province":"Niedersachsen",
    "wof:name":"H. Knackstedt Alt- Und Abfallstoffe",
    "wof:placetype":"venue"
},
  "geometry": {"coordinates":[10.176502,51.891346],"type":"Point"}
}