{
  "type": "Feature",
  "properties": {
    "iso:country":"DE",
    "sg:address":"Gro\u00dfe Elbstr. 40",
    "sg:city":"Hamburg",
    "sg:phone":"+49 40/69794377",
    "sg:postcode":"22767",
    "sg:province":"Hamburg",
    "wof:name":"Boogi M\u00f6bel-licht-accessoires Burkhardt Zipperich E. Kfm.",
    "wof:placetype":"venue"
},
  "geometry": {"coordinates":[9.950593,53.54501],"type":"Point"}
}