{
  "type": "Feature",
  "properties": {
    "iso:country":"DE",
    "sg:address":"Br\u00fcckenstr. 2",
    "sg:city":"Leverkusen",
    "sg:phone":"+49 2171/72450",
    "sg:postcode":"51379",
    "sg:province":"Nordrhein-Westfalen",
    "wof:name":"Micronik Multimedia Manfred Kotulla E. K.",
    "wof:placetype":"venue"
},
  "geometry": {"coordinates":[6.996836,51.071587],"type":"Point"}
}