{
  "type": "Feature",
  "properties": {
    "iso:country":"DE",
    "sg:address":"Frankenring 16",
    "sg:city":"Langenhagen",
    "sg:phone":"+49 511/9784970",
    "sg:postcode":"30855",
    "sg:province":"Niedersachsen",
    "wof:name":"Ascom Deutschland Gmbh",
    "wof:placetype":"venue"
},
  "geometry": {"coordinates":[9.6853780746,52.4419898987],"type":"Point"}
}