{
  "type": "Feature",
  "properties": {
    "iso:country":"DE",
    "sg:address":"Auguststr. 57",
    "sg:city":"Bremen",
    "sg:phone":"+49 421/3964506",
    "sg:postcode":"28219",
    "sg:province":"Bremen",
    "wof:name":"R. Schlafka",
    "wof:placetype":"venue"
},
  "geometry": {"coordinates":[8.7924776077,53.1019973755],"type":"Point"}
}