{
  "type": "Feature",
  "properties": {
    "iso:country":"DE",
    "sg:address":"Hubertusstr. 4",
    "sg:city":"Herzberg",
    "sg:phone":"+49 5521/5001",
    "sg:postcode":"37412",
    "sg:province":"Niedersachsen",
    "wof:name":"G\u00fcnter Geile Architekt",
    "wof:placetype":"venue"
},
  "geometry": {"coordinates":[10.351653,51.658615],"type":"Point"}
}