{
  "type": "Feature",
  "properties": {
    "iso:country":"DE",
    "sg:address":"Frankfurter Str. 26",
    "sg:city":"Lutter",
    "sg:phone":"+49 5383/8606",
    "sg:postcode":"38729",
    "sg:province":"Niedersachsen",
    "wof:name":"Bistro 2000",
    "wof:placetype":"venue"
},
  "geometry": {"coordinates":[10.2688426971,51.988948822],"type":"Point"}
}