{
  "type": "Feature",
  "properties": {
    "iso:country":"DE",
    "sg:address":"Emmersdorfer Str. 1",
    "sg:city":"Johanniskirchen",
    "sg:phone":"+49 8564/332",
    "sg:postcode":"84381",
    "sg:province":"Bayern",
    "wof:name":"Karl Dobler",
    "wof:placetype":"venue"
},
  "geometry": {"coordinates":[12.9853258133,48.5561256409],"type":"Point"}
}