{
  "type": "Feature",
  "properties": {
    "iso:country":"DE",
    "sg:address":"H\u00f6ppnerweg 5-7",
    "sg:city":"Timmendorfer Strand",
    "sg:phone":"+49 4503/6262",
    "sg:postcode":"23669",
    "sg:province":"Schleswig-Holstein",
    "wof:name":"Famila",
    "wof:placetype":"venue"
},
  "geometry": {"coordinates":[10.7828731537,53.9955368042],"type":"Point"}
}