{
  "type": "Feature",
  "properties": {
    "iso:country":"DE",
    "sg:address":"RWE-Str. 77",
    "sg:city":"Wesel",
    "sg:phone":"+49 281/8519711",
    "sg:postcode":"46485",
    "sg:province":"Nordrhein-Westfalen",
    "wof:name":"Bl Wohnungsbau Gmbh",
    "wof:placetype":"venue"
},
  "geometry": {"coordinates":[6.675849,51.648926],"type":"Point"}
}