{
  "type": "Feature",
  "properties": {
    "iso:country":"DE",
    "sg:address":"Bismarckstr. 76",
    "sg:city":"Bad Harzburg",
    "sg:phone":"+49 5322/2821",
    "sg:postcode":"38667",
    "sg:province":"Niedersachsen",
    "wof:name":"Dr. Bruns Rechtsanwalt Und Notar",
    "wof:placetype":"venue"
},
  "geometry": {"coordinates":[10.5566854477,51.8796386719],"type":"Point"}
}