{
  "type": "Feature",
  "properties": {
    "iso:country":"DE",
    "sg:address":"\u00d6sterreicher Str. 7",
    "sg:city":"Zirndorf",
    "sg:phone":"+49 911/607096",
    "sg:postcode":"90513",
    "sg:province":"Bayern",
    "wof:name":"Lucom Gmbh",
    "wof:placetype":"venue"
},
  "geometry": {"coordinates":[10.95996,49.435322],"type":"Point"}
}