{
  "type": "Feature",
  "properties": {
    "iso:country":"DE",
    "sg:address":"Gewerbepark 13",
    "sg:city":"Bruckm\u00fchl",
    "sg:phone":"+49 8062",
    "sg:postcode":"83052",
    "sg:province":"Bayern",
    "wof:name":"Willkommen Bei Urotech",
    "wof:placetype":"venue"
},
  "geometry": {"coordinates":[11.933863,47.876537],"type":"Point"}
}