{
  "type": "Feature",
  "properties": {
    "iso:country":"DE",
    "sg:address":"Bennoweg 9",
    "sg:city":"Mei\u00dfen",
    "sg:phone":"+49 3521/435533",
    "sg:postcode":"01662",
    "sg:province":"Sachsen",
    "wof:name":"Weinprobierstube",
    "wof:placetype":"venue"
},
  "geometry": {"coordinates":[13.4920568466,51.1692848206],"type":"Point"}
}