{
  "type": "Feature",
  "properties": {
    "iso:country":"DE",
    "sg:address":"Postfach 2657:: 92616 Weiden:: Germany.^^W\u00f6rthstr 14::",
    "sg:city":"Weiden",
    "sg:phone":"+49 961/840",
    "sg:postcode":"92637",
    "sg:province":"Bayern",
    "wof:name":"Volksbank Nordoberpfalz Eg",
    "wof:placetype":"venue"
},
  "geometry": {"coordinates":[12.156355,49.674026],"type":"Point"}
}