{
  "type": "Feature",
  "properties": {
    "iso:country":"DE",
    "sg:address":"Grabenstr. 9",
    "sg:city":"Backnang",
    "sg:phone":"+49 7191/83911",
    "sg:postcode":"71522",
    "sg:province":"Baden-W\u00fcrttemberg",
    "wof:name":"P. Kotsoglou",
    "wof:placetype":"venue"
},
  "geometry": {"coordinates":[9.4285402298,48.9465713501],"type":"Point"}
}