{
  "type": "Feature",
  "properties": {
    "iso:country":"DE",
    "sg:address":"Moltkestr. 23",
    "sg:city":"Heidelberg",
    "sg:phone":"+49 6221/452322",
    "sg:postcode":"69120",
    "sg:province":"Baden-W\u00fcrttemberg",
    "wof:name":"Pro-presse-agentur Rieger & Oster Gmbh",
    "wof:placetype":"venue"
},
  "geometry": {"coordinates":[8.6861209869,49.4192504883],"type":"Point"}
}