{
  "type": "Feature",
  "properties": {
    "iso:country":"DE",
    "sg:address":"Kreuzauer Str. 55",
    "sg:city":"D\u00fcren",
    "sg:phone":"+49 2421/53632",
    "sg:postcode":"52355",
    "sg:province":"Nordrhein-Westfalen",
    "wof:name":"Pizzeria Hellas",
    "wof:placetype":"venue"
},
  "geometry": {"coordinates":[6.4918289185,50.7747612],"type":"Point"}
}