{
  "type": "Feature",
  "properties": {
    "iso:country":"DE",
    "sg:address":"Otto-Ge\u00dfler-Str. 9",
    "sg:city":"Ludwigsburg",
    "sg:phone":"+49 7141/28550",
    "sg:postcode":"71638",
    "sg:province":"Baden-W\u00fcrttemberg",
    "wof:name":"Kujacinski Und Veigel Steuerberater Und",
    "wof:placetype":"venue"
},
  "geometry": {"coordinates":[9.2071266174,48.8917655945],"type":"Point"}
}