{
  "type": "Feature",
  "properties": {
    "iso:country":"DE",
    "sg:address":"Hermann-L\u00f6ns-Str. 8",
    "sg:city":"Marktredwitz",
    "sg:phone":"+49 9231/8306",
    "sg:postcode":"95615",
    "sg:province":"Bayern",
    "wof:name":"Ev. Luth. Pfarramt",
    "wof:placetype":"venue"
},
  "geometry": {"coordinates":[12.0720043182,50.0009803772],"type":"Point"}
}