{
  "type": "Feature",
  "properties": {
    "iso:country":"DE",
    "sg:address":"Kapellenweg 7",
    "sg:city":"Hille",
    "sg:phone":"+49 5734/7839",
    "sg:postcode":"32479",
    "sg:province":"Nordrhein-Westfalen",
    "wof:name":"Heinrich Eickmeier",
    "wof:placetype":"venue"
},
  "geometry": {"coordinates":[8.798855,52.283295],"type":"Point"}
}