{
  "type": "Feature",
  "properties": {
    "iso:country":"DE",
    "sg:address":"Kirchstr. 35",
    "sg:city":"Rhede",
    "sg:phone":"+49 4964/285",
    "sg:postcode":"26899",
    "sg:province":"Niedersachsen",
    "wof:name":"Paul Puls",
    "wof:placetype":"venue"
},
  "geometry": {"coordinates":[7.267267,53.060207],"type":"Point"}
}