{
  "type": "Feature",
  "properties": {
    "iso:country":"DE",
    "sg:address":"Garbestr. 4",
    "sg:city":"Hamburg",
    "sg:phone":"+49 40/412018",
    "sg:postcode":"20144",
    "sg:province":"Hamburg",
    "wof:name":"Heike Lesmeister Rechtsanw\u00e4ltin",
    "wof:placetype":"venue"
},
  "geometry": {"coordinates":[9.9697780609,53.5705032349],"type":"Point"}
}