{
  "type": "Feature",
  "properties": {
    "iso:country":"DE",
    "sg:address":"Provinzialstr. 273",
    "sg:city":"Dortmund",
    "sg:phone":"+49 231/6900854",
    "sg:postcode":"44388",
    "sg:province":"Nordrhein-Westfalen",
    "wof:name":"Haus Niederhoff",
    "wof:placetype":"venue"
},
  "geometry": {"coordinates":[7.3222160339,51.5114517212],"type":"Point"}
}