{
  "type": "Feature",
  "properties": {
    "iso:country":"DE",
    "sg:address":"Nordendstr. 15",
    "sg:city":"M\u00fcnchen",
    "sg:phone":"+49 89/27399711",
    "sg:postcode":"80799",
    "sg:province":"Bayern",
    "wof:name":"Christian M\u00fcller",
    "wof:placetype":"venue"
},
  "geometry": {"coordinates":[11.57525,48.154613],"type":"Point"}
}