{
  "type": "Feature",
  "properties": {
    "iso:country":"DE",
    "sg:address":"Tischlerstr. 8",
    "sg:city":"Isernhagen",
    "sg:phone":"+49 5136/84394",
    "sg:postcode":"30916",
    "sg:province":"Niedersachsen",
    "wof:name":"J. C. Fr\u00f6hling",
    "wof:placetype":"venue"
},
  "geometry": {"coordinates":[9.880317688,52.4405975342],"type":"Point"}
}