{
  "type": "Feature",
  "properties": {
    "iso:country":"DE",
    "sg:address":"F\u00fcrst-P\u00fcckler-Str. 8",
    "sg:city":"K\u00f6ln",
    "sg:phone":"+49 221/9126380",
    "sg:postcode":"50935",
    "sg:province":"Nordrhein-Westfalen",
    "wof:name":"Carl Britt Gmbh",
    "wof:placetype":"venue"
},
  "geometry": {"coordinates":[6.9080581665,50.9283370972],"type":"Point"}
}