{
  "type": "Feature",
  "properties": {
    "iso:country":"DE",
    "sg:address":"Taubenstr. 24",
    "sg:city":"Bielefeld",
    "sg:phone":"+49 521/287740",
    "sg:postcode":"33607",
    "sg:province":"Nordrhein-Westfalen",
    "wof:name":"Web Projects Internet Service E. K.",
    "wof:placetype":"venue"
},
  "geometry": {"coordinates":[8.563461,52.014072],"type":"Point"}
}