{
  "type": "Feature",
  "properties": {
    "iso:country":"DE",
    "sg:address":"Tramplerstr. 45a",
    "sg:city":"Lahr",
    "sg:phone":"+49 7821/22132",
    "sg:postcode":"77933",
    "sg:province":"Baden-W\u00fcrttemberg",
    "wof:name":"O Fix Artur Von Manger",
    "wof:placetype":"venue"
},
  "geometry": {"coordinates":[7.8588080406,48.3346939087],"type":"Point"}
}