{
  "type": "Feature",
  "properties": {
    "iso:country":"DE",
    "sg:address":"Im Goldenen Horn 1",
    "sg:city":"Espenau",
    "sg:phone":"+49 5673/5879",
    "sg:postcode":"34314",
    "sg:province":"Hessen",
    "wof:name":"Peter Hille Ingenieur",
    "wof:placetype":"venue"
},
  "geometry": {"coordinates":[9.4731216431,51.4011230469],"type":"Point"}
}