{
  "type": "Feature",
  "properties": {
    "iso:country":"DE",
    "sg:address":"Calwer Str. 37",
    "sg:city":"Stuttgart",
    "sg:phone":"+49 711/2255066",
    "sg:postcode":"70173",
    "sg:province":"Baden-W\u00fcrttemberg",
    "wof:name":"Vs-verlagshaus Stuttgart Gmbh",
    "wof:placetype":"venue"
},
  "geometry": {"coordinates":[9.173324585,48.7753448486],"type":"Point"}
}