{
  "type": "Feature",
  "properties": {
    "iso:country":"DE",
    "sg:address":"Viernheimer Str. 51",
    "sg:city":"Weinheim",
    "sg:postcode":"69469",
    "sg:province":"Baden-W\u00fcrttemberg",
    "wof:name":"Reiseb\u00fcro Schumacher Gmbh",
    "wof:placetype":"venue"
},
  "geometry": {"coordinates":[8.6558361053,49.5560493469],"type":"Point"}
}