{
  "type": "Feature",
  "properties": {
    "iso:country":"DE",
    "sg:address":"Klusstr. 79",
    "sg:city":"B\u00fcnde",
    "sg:phone":"+49 5223/41565",
    "sg:postcode":"32257",
    "sg:province":"Nordrhein-Westfalen",
    "wof:name":"Wilhelm Kemner",
    "wof:placetype":"venue"
},
  "geometry": {"coordinates":[8.5858354568,52.223739624],"type":"Point"}
}