{
  "type": "Feature",
  "properties": {
    "iso:country":"DE",
    "sg:address":"Mundsburger Damm 36",
    "sg:city":"Hamburg",
    "sg:phone":"+49 40/2209855",
    "sg:postcode":"22087",
    "sg:province":"Hamburg",
    "wof:name":"Johann Velden Gmbh",
    "wof:placetype":"venue"
},
  "geometry": {"coordinates":[10.0228185654,53.5673904419],"type":"Point"}
}