{
  "type": "Feature",
  "properties": {
    "iso:country":"DE",
    "sg:address":"Adelbylund 11",
    "sg:city":"Flensburg",
    "sg:postcode":"24943",
    "sg:province":"Schleswig-Holstein",
    "wof:name":"Ghg-grundst\u00fcckshandels- Gesellschaft L\u00fctzner Str. Mbh",
    "wof:placetype":"venue"
},
  "geometry": {"coordinates":[9.451927,54.781815],"type":"Point"}
}