{
  "type": "Feature",
  "properties": {
    "iso:country":"DE",
    "sg:address":"Liebigstr. 9",
    "sg:city":"Pattensen",
    "sg:phone":"+49 5101/13452",
    "sg:postcode":"30982",
    "sg:province":"Niedersachsen",
    "wof:name":"Manfred Minack Masseur",
    "wof:placetype":"venue"
},
  "geometry": {"coordinates":[9.761926,52.269287],"type":"Point"}
}