{
  "type": "Feature",
  "properties": {
    "iso:country":"DE",
    "sg:address":"Dr.-Kiefl-Str. 4",
    "sg:city":"Plattling",
    "sg:phone":"+49 9931/8520",
    "sg:postcode":"94447",
    "sg:province":"Bayern",
    "wof:name":"B. Wallner",
    "wof:placetype":"venue"
},
  "geometry": {"coordinates":[12.870178,48.781456],"type":"Point"}
}