{
  "type": "Feature",
  "properties": {
    "iso:country":"DE",
    "sg:address":"Testorf 1",
    "sg:city":"Weste",
    "sg:postcode":"29599",
    "sg:province":"Niedersachsen",
    "wof:name":"Wester Windparkbetriebsges. Mbh",
    "wof:placetype":"venue"
},
  "geometry": {"coordinates":[10.716085,53.046066],"type":"Point"}
}