{
  "type": "Feature",
  "properties": {
    "iso:country":"DE",
    "sg:address":"Rambower Weg",
    "sg:city":"Dorf Mecklenburg",
    "sg:postcode":"23972",
    "sg:province":"Mecklenburg-Vorpommern",
    "wof:name":"Oskar Bedne Gmbh",
    "wof:placetype":"venue"
},
  "geometry": {"coordinates":[11.455421,53.84248],"type":"Point"}
}