{
  "type": "Feature",
  "properties": {
    "iso:country":"DE",
    "sg:address":"K\u00e4rntenstr. 7",
    "sg:city":"Bamberg",
    "sg:postcode":"96052",
    "sg:province":"Bayern",
    "wof:name":"Sml Sabrina Mode In Leder Gmbh & Co. Kg",
    "wof:placetype":"venue"
},
  "geometry": {"coordinates":[10.899985,49.913334],"type":"Point"}
}