{
  "type": "Feature",
  "properties": {
    "iso:country":"DE",
    "sg:address":"Kaiserbleek 4",
    "sg:city":"Goslar",
    "sg:phone":"+49 5321/22921",
    "sg:postcode":"38640",
    "sg:province":"Niedersachsen",
    "wof:name":"Ev. Pfarramt Marktkirchengem.",
    "wof:placetype":"venue"
},
  "geometry": {"coordinates":[10.4263286591,51.9034156799],"type":"Point"}
}