{
  "type": "Feature",
  "properties": {
    "iso:country":"DE",
    "sg:address":"Walter-Kollo-Str. 56",
    "sg:city":"Bad Soden",
    "sg:phone":"+49 6196/24532",
    "sg:postcode":"65812",
    "sg:province":"Hessen",
    "wof:name":"Oskar Schmidt Architekt",
    "wof:placetype":"venue"
},
  "geometry": {"coordinates":[8.502771,50.135796],"type":"Point"}
}