{
  "type": "Feature",
  "properties": {
    "iso:country":"DE",
    "sg:address":"Kr\u00fctzpoort 21",
    "sg:city":"Krefeld",
    "sg:phone":"+49 2151/978757",
    "sg:postcode":"47804",
    "sg:province":"Nordrhein-Westfalen",
    "wof:name":"Reiner Diehl Industrie- Service Gmbh & Co. Kg",
    "wof:placetype":"venue"
},
  "geometry": {"coordinates":[6.525739193,51.3260574341],"type":"Point"}
}