{
  "type": "Feature",
  "properties": {
    "iso:country":"DE",
    "sg:address":"Schulstr. 14 a",
    "sg:city":"Wollin",
    "sg:phone":"+49 33833/70206",
    "sg:postcode":"14778",
    "sg:province":"Brandenburg",
    "wof:name":"Krauses Restaurant",
    "wof:placetype":"venue"
},
  "geometry": {"coordinates":[12.4730911255,52.2785491943],"type":"Point"}
}