{
  "type": "Feature",
  "properties": {
    "iso:country":"DE",
    "sg:address":"Scharfensteinstr. 26",
    "sg:city":"Eltville",
    "sg:phone":"+49 6123/2862",
    "sg:postcode":"65343",
    "sg:province":"Hessen",
    "wof:name":"Fritz Sch\u00e4fermeier",
    "wof:placetype":"venue"
},
  "geometry": {"coordinates":[8.1127052307,50.0315055847],"type":"Point"}
}