{
  "type": "Feature",
  "properties": {
    "iso:country":"DE",
    "sg:address":"Torstenssonstr. 2",
    "sg:city":"Hannover",
    "sg:phone":"+49 511/425105",
    "sg:postcode":"30459",
    "sg:province":"Niedersachsen",
    "wof:name":"Elli Krause",
    "wof:placetype":"venue"
},
  "geometry": {"coordinates":[9.7125787735,52.3419685364],"type":"Point"}
}