{
  "type": "Feature",
  "properties": {
    "iso:country":"DE",
    "sg:address":"Denzerhammer 2",
    "sg:city":"Winterberg",
    "sg:phone":"+49 2981/2602",
    "sg:postcode":"59955",
    "sg:province":"Nordrhein-Westfalen",
    "wof:name":"Maria Braun Hebamme",
    "wof:placetype":"venue"
},
  "geometry": {"coordinates":[8.555113,51.166832],"type":"Point"}
}