{
  "type": "Feature",
  "properties": {
    "iso:country":"DE",
    "sg:address":"Im Rosengarten 8",
    "sg:city":"Stutensee",
    "sg:phone":"+49 7244/945845",
    "sg:postcode":"76297",
    "sg:province":"Baden-W\u00fcrttemberg",
    "wof:name":"Adelheid Mack Krankengymnastin",
    "wof:placetype":"venue"
},
  "geometry": {"coordinates":[8.465217,49.06456],"type":"Point"}
}