{
  "type": "Feature",
  "properties": {
    "iso:country":"DE",
    "sg:address":"Schwabstr. 179",
    "sg:city":"Stuttgart",
    "sg:phone":"+49 711/294967",
    "sg:postcode":"70193",
    "sg:province":"Baden-W\u00fcrttemberg",
    "wof:name":"Gerd O. Freitag",
    "wof:placetype":"venue"
},
  "geometry": {"coordinates":[9.156822,48.781113],"type":"Point"}
}