{
  "type": "Feature",
  "properties": {
    "iso:country":"DE",
    "sg:address":"Am Aukopf 29",
    "sg:city":"Heidelberg",
    "sg:phone":"+49 6221/800485",
    "sg:postcode":"69118",
    "sg:province":"Baden-W\u00fcrttemberg",
    "wof:name":"Ifm Heidelberg Klaus Kretz",
    "wof:placetype":"venue"
},
  "geometry": {"coordinates":[8.753371,49.414593],"type":"Point"}
}