{
  "type": "Feature",
  "properties": {
    "iso:country":"DE",
    "sg:address":"Reichsstr. 24",
    "sg:city":"Donauw\u00f6rth",
    "sg:phone":"+49 906/28081",
    "sg:postcode":"86609",
    "sg:province":"Bayern",
    "wof:name":"Imofinanz Immobilien- Und Versicherungsvermittlungs Gmbh",
    "wof:placetype":"venue"
},
  "geometry": {"coordinates":[10.7796020508,48.7187309265],"type":"Point"}
}