{
  "type": "Feature",
  "properties": {
    "iso:country":"DE",
    "sg:address":"Harvestehuder Weg 25",
    "sg:city":"Hamburg",
    "sg:phone":"+49 40/441990",
    "sg:postcode":"20149",
    "sg:province":"Hamburg",
    "wof:name":"Gerling Industrie-service Gmbh",
    "wof:placetype":"venue"
},
  "geometry": {"coordinates":[9.999049,53.574474],"type":"Point"}
}