{
  "type": "Feature",
  "properties": {
    "iso:country":"DE",
    "sg:address":"Vossworth 7",
    "sg:city":"Visselh\u00f6vede",
    "sg:phone":"+49 4262/94176",
    "sg:postcode":"27374",
    "sg:province":"Niedersachsen",
    "wof:name":"Dehnke Und Lippke Architekten",
    "wof:placetype":"venue"
},
  "geometry": {"coordinates":[9.618237,53.004002],"type":"Point"}
}