{
  "type": "Feature",
  "properties": {
    "iso:country":"DE",
    "sg:address":"Ro\u00dfkampffstr 13",
    "sg:city":"Heilbronn",
    "sg:phone":"+49 7131/991220",
    "sg:postcode":"74072",
    "sg:province":"Baden-W\u00fcrttemberg",
    "wof:name":"Handelsdruckerei Georg Hohmann Gmbh",
    "wof:placetype":"venue"
},
  "geometry": {"coordinates":[9.2100954056,49.1415596008],"type":"Point"}
}