{
  "type": "Feature",
  "properties": {
    "iso:country":"DE",
    "sg:address":"Schwertfegerstr. 33",
    "sg:city":"L\u00fcbeck",
    "sg:phone":"+49 451/873840",
    "sg:postcode":"23556",
    "sg:province":"Schleswig-Holstein",
    "wof:name":"Theodor Schr\u00f6der Gmbh",
    "wof:placetype":"venue"
},
  "geometry": {"coordinates":[10.6295890808,53.8605575562],"type":"Point"}
}