{
  "type": "Feature",
  "properties": {
    "iso:country":"DE",
    "sg:address":"Ulmenweg 3",
    "sg:city":"Lauenau",
    "sg:phone":"+49 5043/2358",
    "sg:postcode":"31867",
    "sg:province":"Niedersachsen",
    "wof:name":"Walter O. V. Wieprecht",
    "wof:placetype":"venue"
},
  "geometry": {"coordinates":[9.3939371109,52.2837371826],"type":"Point"}
}