{
  "type": "Feature",
  "properties": {
    "iso:country":"DE",
    "sg:address":"Thyratal 9 b",
    "sg:city":"Stolberg",
    "sg:phone":"+49 34654/368",
    "sg:postcode":"06547",
    "sg:province":"Sachsen-Anhalt",
    "wof:name":"Wasserversorgung Und Abwasserbehandlung Halle Gmbh",
    "wof:placetype":"venue"
},
  "geometry": {"coordinates":[10.9567518234,51.5619888306],"type":"Point"}
}