{
  "type": "Feature",
  "properties": {
    "iso:country":"DE",
    "sg:address":"Marktstr. 3",
    "sg:city":"Horn-Bad Meinberg",
    "sg:phone":"+49 5234/1407",
    "sg:postcode":"32805",
    "sg:province":"Nordrhein-Westfalen",
    "wof:name":"Kerstin Fliegner",
    "wof:placetype":"venue"
},
  "geometry": {"coordinates":[8.9802246094,51.8946380615],"type":"Point"}
}