{
  "type": "Feature",
  "properties": {
    "iso:country":"DE",
    "sg:address":"Westendorf 16",
    "sg:city":"Eilenstedt",
    "sg:phone":"+49 39425/2647",
    "sg:postcode":"38838",
    "sg:province":"Sachsen-Anhalt",
    "wof:name":"Eberhard Esche",
    "wof:placetype":"venue"
},
  "geometry": {"coordinates":[11.041416,51.98431],"type":"Point"}
}