{
  "type": "Feature",
  "properties": {
    "iso:country":"DE",
    "sg:address":"Wellingsb\u00fcttler Weg 121",
    "sg:city":"Hamburg",
    "sg:phone":"+49 40/5362875",
    "sg:postcode":"22391",
    "sg:province":"Hamburg",
    "wof:name":"Klaus-dieter Drews",
    "wof:placetype":"venue"
},
  "geometry": {"coordinates":[10.080953598,53.6418418884],"type":"Point"}
}