{
  "type": "Feature",
  "properties": {
    "iso:country":"DE",
    "sg:address":"Weyerstr. 88",
    "sg:city":"K\u00f6ln",
    "sg:phone":"+49 221/235933",
    "sg:postcode":"50676",
    "sg:province":"Nordrhein-Westfalen",
    "wof:name":"Tagtraum Film- Und Videoproduktion Gmbh",
    "wof:placetype":"venue"
},
  "geometry": {"coordinates":[6.94309,50.930447],"type":"Point"}
}