{
  "type": "Feature",
  "properties": {
    "iso:country":"DE",
    "sg:address":"Traminerweg 20",
    "sg:city":"Saulheim",
    "sg:phone":"+49 6732/62997",
    "sg:postcode":"55291",
    "sg:province":"Rheinland-Pfalz",
    "wof:name":"Wolfgang Graf",
    "wof:placetype":"venue"
},
  "geometry": {"coordinates":[8.1436166763,49.8720092773],"type":"Point"}
}