{
  "type": "Feature",
  "properties": {
    "iso:country":"DE",
    "sg:address":"Raubersrieder Hauptstr. 7",
    "sg:city":"Wendelstein",
    "sg:phone":"+49 9129/26450",
    "sg:postcode":"90530",
    "sg:province":"Bayern",
    "wof:name":"Ulrich Pfann",
    "wof:placetype":"venue"
},
  "geometry": {"coordinates":[11.1465053558,49.3438110352],"type":"Point"}
}