{
  "type": "Feature",
  "properties": {
    "iso:country":"DE",
    "sg:address":"Fuggerstr. 15",
    "sg:city":"N\u00fcrnberg",
    "sg:phone":"+49 911/412233",
    "sg:postcode":"90439",
    "sg:province":"Bayern",
    "wof:name":"Rs Karosseriebau Kg",
    "wof:placetype":"venue"
},
  "geometry": {"coordinates":[11.0507440567,49.4438018799],"type":"Point"}
}