{
  "type": "Feature",
  "properties": {
    "iso:country":"DE",
    "sg:address":"Gudvanger Str. 28",
    "sg:city":"Berlin",
    "sg:postcode":"10439",
    "sg:province":"Berlin",
    "wof:name":"Armin Kr\u00fcgel",
    "wof:placetype":"venue"
},
  "geometry": {"coordinates":[13.425174,52.55024],"type":"Point"}
}