{
  "type": "Feature",
  "properties": {
    "iso:country":"DE",
    "sg:address":"Burgsiedlung",
    "sg:city":"Friedberg",
    "sg:phone":"+49 4950/635284",
    "sg:postcode":"61169",
    "sg:province":"Hessen",
    "wof:name":"Sempter Schlauchleitungen Gmbh",
    "wof:placetype":"venue"
},
  "geometry": {"coordinates":[10.0032539368,52.0582847595],"type":"Point"}
}