{
  "type": "Feature",
  "properties": {
    "iso:country":"DE",
    "sg:address":"Badstr. 15",
    "sg:city":"Bad Bellingen",
    "sg:phone":"+49 7635/8650",
    "sg:postcode":"79415",
    "sg:province":"Baden-W\u00fcrttemberg",
    "wof:name":"Bio-bar",
    "wof:placetype":"venue"
},
  "geometry": {"coordinates":[7.551923,47.729683],"type":"Point"}
}