{
  "type": "Feature",
  "properties": {
    "iso:country":"DE",
    "sg:address":"Fritz-Hofmann-Weg 43",
    "sg:city":"Merseburg",
    "sg:phone":"+49 3461/721635",
    "sg:postcode":"06217",
    "sg:province":"Sachsen-Anhalt",
    "wof:name":"Bernd Staude",
    "wof:placetype":"venue"
},
  "geometry": {"coordinates":[11.974591,51.380501],"type":"Point"}
}