{
  "type": "Feature",
  "properties": {
    "iso:country":"DE",
    "sg:address":"Karl-Marx-Str. 10",
    "sg:city":"L\u00fcnen",
    "sg:phone":"+49 231/871521",
    "sg:postcode":"44536",
    "sg:province":"Nordrhein-Westfalen",
    "wof:name":"Heinz D\u00fcrholt",
    "wof:placetype":"venue"
},
  "geometry": {"coordinates":[7.4397168159,51.5993309021],"type":"Point"}
}