{
  "type": "Feature",
  "properties": {
    "iso:country":"DE",
    "sg:address":"Bernsburger Str. 14",
    "sg:city":"Willingshausen",
    "sg:phone":"+49 6697/275",
    "sg:postcode":"34628",
    "sg:province":"Hessen",
    "wof:name":"Wilhelm Faust",
    "wof:placetype":"venue"
},
  "geometry": {"coordinates":[9.192406,50.847176],"type":"Point"}
}