{
  "type": "Feature",
  "properties": {
    "iso:country":"DE",
    "sg:address":"H\u00f6henstr. 10",
    "sg:city":"Elsenfeld",
    "sg:phone":"+49 9374/1507",
    "sg:postcode":"63820",
    "sg:province":"Bayern",
    "wof:name":"Pension Kolb",
    "wof:placetype":"venue"
},
  "geometry": {"coordinates":[9.2341365814,49.8476333618],"type":"Point"}
}