{
  "type": "Feature",
  "properties": {
    "iso:country":"DE",
    "sg:address":"Max-Hueber-Str. 4",
    "sg:city":"Ismaning",
    "sg:phone":"+49 89/96020",
    "sg:postcode":"85737",
    "sg:province":"Bayern",
    "wof:name":"Redaktion Jahrbuch-deutsch Als Fremdsprache",
    "wof:placetype":"venue"
},
  "geometry": {"coordinates":[11.6660041809,48.2181243896],"type":"Point"}
}