{
  "type": "Feature",
  "properties": {
    "iso:country":"DE",
    "sg:address":"Degerndorfer Str. 5",
    "sg:city":"Brannenburg",
    "sg:phone":"+49 8034/307887",
    "sg:postcode":"83098",
    "sg:province":"Bayern",
    "wof:name":"T. Schauer",
    "wof:placetype":"venue"
},
  "geometry": {"coordinates":[12.1034021378,47.73777771],"type":"Point"}
}