{
  "type": "Feature",
  "properties": {
    "iso:country":"DE",
    "sg:address":"Kortenstr. 17",
    "sg:city":"Sprockh\u00f6vel",
    "sg:phone":"+49 2339/3481",
    "sg:postcode":"45549",
    "sg:province":"Nordrhein-Westfalen",
    "wof:name":"Alfons Fuchs Rechtsanwalt",
    "wof:placetype":"venue"
},
  "geometry": {"coordinates":[7.2870111465,51.335735321],"type":"Point"}
}