{
  "type": "Feature",
  "properties": {
    "iso:country":"DE",
    "sg:address":"Sonnenhalde 4",
    "sg:city":"Ostfildern",
    "sg:phone":"+49 7158/2033",
    "sg:postcode":"73760",
    "sg:province":"Baden-W\u00fcrttemberg",
    "wof:name":"Lore Strobel",
    "wof:placetype":"venue"
},
  "geometry": {"coordinates":[9.2719507217,48.708530426],"type":"Point"}
}