{
  "type": "Feature",
  "properties": {
    "iso:country":"DE",
    "sg:address":"Auf dem Hohen Ufer 86",
    "sg:city":"Bremen",
    "sg:phone":"+49 421/627570",
    "sg:postcode":"28759",
    "sg:province":"Bremen",
    "wof:name":"Rabbit Bmx Bremen",
    "wof:placetype":"venue"
},
  "geometry": {"coordinates":[8.66885,53.164452],"type":"Point"}
}