{
  "type": "Feature",
  "properties": {
    "iso:country":"DE",
    "sg:address":"Waldstr. 10",
    "sg:city":"Aachen",
    "sg:postcode":"52080",
    "sg:province":"Nordrhein-Westfalen",
    "wof:name":"St. Christophorus Apotheke E. K.",
    "wof:placetype":"venue"
},
  "geometry": {"coordinates":[6.157106,50.795551],"type":"Point"}
}