{
  "type": "Feature",
  "properties": {
    "iso:country":"DE",
    "sg:address":"Liebigstr. 17",
    "sg:city":"Aachen",
    "sg:postcode":"52070",
    "sg:province":"Nordrhein-Westfalen",
    "wof:name":"Top Job Gastronomiedienstleistung Gmbh",
    "wof:placetype":"venue"
},
  "geometry": {"coordinates":[6.110289,50.79105],"type":"Point"}
}