{
  "type": "Feature",
  "properties": {
    "iso:country":"DE",
    "sg:address":"Vogelsangstr. 17",
    "sg:city":"Brackenheim",
    "sg:phone":"+49 7135/6185",
    "sg:postcode":"74336",
    "sg:province":"Baden-W\u00fcrttemberg",
    "wof:name":"Effenberger Gmbh",
    "wof:placetype":"venue"
},
  "geometry": {"coordinates":[9.0589990616,49.0786476135],"type":"Point"}
}