{
  "type": "Feature",
  "properties": {
    "iso:country":"DE",
    "sg:address":"Hauptstr. 23",
    "sg:city":"Cremlingen",
    "sg:phone":"+49 5306/7089",
    "sg:postcode":"38162",
    "sg:province":"Niedersachsen",
    "wof:name":"Marlies Anders",
    "wof:placetype":"venue"
},
  "geometry": {"coordinates":[10.652316,52.248795],"type":"Point"}
}