{
  "type": "Feature",
  "properties": {
    "iso:country":"DE",
    "sg:address":"Sch\u00fcttenberg 20",
    "sg:city":"Bar\u00dfel",
    "sg:phone":"+49 4497/203",
    "sg:postcode":"26676",
    "sg:province":"Niedersachsen",
    "wof:name":"Gottfried L\u00fcken",
    "wof:placetype":"venue"
},
  "geometry": {"coordinates":[7.827974,53.11491],"type":"Point"}
}