{
  "type": "Feature",
  "properties": {
    "iso:country":"DE",
    "sg:address":"Peter-Henlein-Str. 24",
    "sg:city":"Augsburg",
    "sg:phone":"+49 821/96719",
    "sg:postcode":"86199",
    "sg:province":"Bayern",
    "wof:name":"W. Schenk \u00dcbersetzungsb\u00fcro",
    "wof:placetype":"venue"
},
  "geometry": {"coordinates":[10.874525,48.340279],"type":"Point"}
}