{
  "type": "Feature",
  "properties": {
    "iso:country":"DE",
    "sg:address":"Dorfstr. 60",
    "sg:city":"Grammentin",
    "sg:phone":"+49 39952/2207",
    "sg:postcode":"17153",
    "sg:province":"Mecklenburg-Vorpommern",
    "wof:name":"Dorfgastst\u00e4tte",
    "wof:placetype":"venue"
},
  "geometry": {"coordinates":[12.8935289383,53.7554550171],"type":"Point"}
}