{
  "type": "Feature",
  "properties": {
    "iso:country":"DE",
    "sg:address":"Am Dorfbach 12",
    "sg:city":"Freiburg",
    "sg:phone":"+49 761/43708",
    "sg:postcode":"79111",
    "sg:province":"Baden-W\u00fcrttemberg",
    "wof:name":"Elektro Ehret Gmbh",
    "wof:placetype":"venue"
},
  "geometry": {"coordinates":[7.7949,47.976669],"type":"Point"}
}