{
  "type": "Feature",
  "properties": {
    "iso:country":"DE",
    "sg:address":"Schm\u00f6lestr. 12",
    "sg:city":"Iserlohn",
    "sg:postcode":"58640",
    "sg:province":"Nordrhein-Westfalen",
    "wof:name":"Kdi Kalk- Und D\u00fcngerhandel Gmbh",
    "wof:placetype":"venue"
},
  "geometry": {"coordinates":[7.693884,51.402451],"type":"Point"}
}