{
  "type": "Feature",
  "properties": {
    "iso:country":"DE",
    "sg:address":"Bergheimer Str. 11",
    "sg:city":"Z\u00fclpich",
    "sg:phone":"+49 2252/2091",
    "sg:postcode":"53909",
    "sg:province":"Nordrhein-Westfalen",
    "wof:name":"Werner Thelen Ohg",
    "wof:placetype":"venue"
},
  "geometry": {"coordinates":[6.6589689255,50.701499939],"type":"Point"}
}