{
  "type": "Feature",
  "properties": {
    "iso:country":"DE",
    "sg:address":"Lorenzlust 28",
    "sg:city":"Magdeburg",
    "sg:phone":"+49 391/4018250",
    "sg:postcode":"39128",
    "sg:province":"Sachsen-Anhalt",
    "wof:name":"Bmt-baumaschinentechnik Gmbh",
    "wof:placetype":"venue"
},
  "geometry": {"coordinates":[11.621969,52.14854],"type":"Point"}
}