{
  "type": "Feature",
  "properties": {
    "iso:country":"DE",
    "sg:address":"Alt-Tempelhof 17",
    "sg:city":"Berlin",
    "sg:phone":"+49 30/7517366",
    "sg:postcode":"12099",
    "sg:province":"Berlin",
    "wof:name":"Cartoon",
    "wof:placetype":"venue"
},
  "geometry": {"coordinates":[13.38651371,52.4655914307],"type":"Point"}
}