{
  "type": "Feature",
  "properties": {
    "iso:country":"DE",
    "sg:address":"Petrikirchstr. 16",
    "sg:city":"Stendal",
    "sg:phone":"+49 3931/714598",
    "sg:postcode":"39576",
    "sg:province":"Sachsen-Anhalt",
    "wof:name":"Dr. Gabriele Breitling Tier\u00e4rtzin",
    "wof:placetype":"venue"
},
  "geometry": {"coordinates":[11.8529109955,52.6058197021],"type":"Point"}
}