{
  "type": "Feature",
  "properties": {
    "iso:country":"DE",
    "sg:address":"Siedlungsstr. 10",
    "sg:city":"Berbisdorf",
    "sg:phone":"+49 35208/4503",
    "sg:postcode":"01471",
    "sg:province":"Sachsen",
    "wof:name":"H. Wagner",
    "wof:placetype":"venue"
},
  "geometry": {"coordinates":[13.719522,51.185658],"type":"Point"}
}