{
  "type": "Feature",
  "properties": {
    "iso:country":"DE",
    "sg:address":"Altstr. 1",
    "sg:city":"Weiden",
    "sg:phone":"+49 961/25879",
    "sg:postcode":"92637",
    "sg:province":"Bayern",
    "wof:name":"L. Spranger",
    "wof:placetype":"venue"
},
  "geometry": {"coordinates":[12.149214,49.673367],"type":"Point"}
}