{
  "type": "Feature",
  "properties": {
    "iso:country":"DE",
    "sg:address":"Albrechtstr 93",
    "sg:city":"Berlin",
    "sg:phone":"+49 30/7953082",
    "sg:postcode":"12167",
    "sg:province":"Berlin",
    "wof:name":"Lufthig Gesellschaft F\u00fcr Klima- Und L\u00fcftungstechnik In Haus, Industrie, Gewerbe Gmbh",
    "wof:placetype":"venue"
},
  "geometry": {"coordinates":[13.333849,52.452282],"type":"Point"}
}