{
  "type": "Feature",
  "properties": {
    "iso:country":"DE",
    "sg:address":"Putzbrunner Str. 127",
    "sg:city":"M\u00fcnchen",
    "sg:phone":"+49 89/6352383",
    "sg:postcode":"81739",
    "sg:province":"Bayern",
    "wof:name":"Hans Brunsch",
    "wof:placetype":"venue"
},
  "geometry": {"coordinates":[11.652701,48.094662],"type":"Point"}
}