{
  "type": "Feature",
  "properties": {
    "iso:country":"DE",
    "sg:address":"Stra\u00dfe der Einheit 40",
    "sg:city":"Ausleben",
    "sg:phone":"+49 39404/50756",
    "sg:postcode":"39393",
    "sg:province":"Sachsen-Anhalt",
    "wof:name":"Richard Sch\u00f6nborn",
    "wof:placetype":"venue"
},
  "geometry": {"coordinates":[11.112295,52.090511],"type":"Point"}
}