{
  "type": "Feature",
  "properties": {
    "iso:country":"DE",
    "sg:address":"Ohmstr. 19",
    "sg:city":"Fellbach",
    "sg:phone":"+49 711/581464",
    "sg:postcode":"70736",
    "sg:province":"Baden-W\u00fcrttemberg",
    "wof:name":"August Seibold Hoch- Und Tiebau",
    "wof:placetype":"venue"
},
  "geometry": {"coordinates":[9.284559,48.821659],"type":"Point"}
}