{
  "type": "Feature",
  "properties": {
    "iso:country":"DE",
    "sg:address":"Friedhofsweg 7",
    "sg:city":"Eitelborn",
    "sg:phone":"+49 2620/8694",
    "sg:postcode":"56337",
    "sg:province":"Rheinland-Pfalz",
    "wof:name":"Heinrich Klaue",
    "wof:placetype":"venue"
},
  "geometry": {"coordinates":[7.722838,50.373295],"type":"Point"}
}