{
  "type": "Feature",
  "properties": {
    "iso:country":"DE",
    "sg:address":"Am Weinberg 4",
    "sg:city":"Oberammergau",
    "sg:phone":"+49 8822/4765",
    "sg:postcode":"82487",
    "sg:province":"Bayern",
    "wof:name":"Xaver Seem\u00fcller",
    "wof:placetype":"venue"
},
  "geometry": {"coordinates":[11.056952,47.602955],"type":"Point"}
}