{
  "type": "Feature",
  "properties": {
    "iso:country":"DE",
    "sg:address":"Boschstr. 12",
    "sg:city":"Herford",
    "sg:phone":"+49 5221/93300",
    "sg:postcode":"32051",
    "sg:province":"Nordrhein-Westfalen",
    "wof:name":"Weihe Systems Verwaltungsgesellschaft Mbh",
    "wof:placetype":"venue"
},
  "geometry": {"coordinates":[8.6239185333,52.1009788513],"type":"Point"}
}