{
  "type": "Feature",
  "properties": {
    "iso:country":"DE",
    "sg:address":"Hafenstr. 20",
    "sg:city":"Stralsund",
    "sg:phone":"+49 3831/278460",
    "sg:postcode":"18439",
    "sg:province":"Mecklenburg-Vorpommern",
    "wof:name":"Schornsteintechnik Gmbh",
    "wof:placetype":"venue"
},
  "geometry": {"coordinates":[13.0995969772,54.3126831055],"type":"Point"}
}