{
  "type": "Feature",
  "properties": {
    "iso:country":"DE",
    "sg:address":"Premenreuther Str.",
    "sg:city":"Reuth",
    "sg:phone":"+49 9681/661",
    "sg:postcode":"92717",
    "sg:province":"Bayern",
    "wof:name":"O. Reichenberger B\u00e4ckerei",
    "wof:placetype":"venue"
},
  "geometry": {"coordinates":[12.124535,49.84248],"type":"Point"}
}