{
  "type": "Feature",
  "properties": {
    "iso:country":"DE",
    "sg:address":"Freiburger Str. 12",
    "sg:city":"Kenzingen",
    "sg:phone":"+49 7644/8333",
    "sg:postcode":"79341",
    "sg:province":"Baden-W\u00fcrttemberg",
    "wof:name":"Willi Kreutner",
    "wof:placetype":"venue"
},
  "geometry": {"coordinates":[7.7655930519,48.188621521],"type":"Point"}
}