{
  "type": "Feature",
  "properties": {
    "iso:country":"DE",
    "sg:address":"Baptist-Kraus-Str. 1",
    "sg:city":"Altenstadt",
    "sg:phone":"+49 9602/6996",
    "sg:postcode":"92665",
    "sg:province":"Bayern",
    "wof:name":"Renate Schiller",
    "wof:placetype":"venue"
},
  "geometry": {"coordinates":[12.093077,49.777115],"type":"Point"}
}