{
  "type": "Feature",
  "properties": {
    "iso:country":"DE",
    "sg:address":"Reitwallstr. 5",
    "sg:city":"Hannover",
    "sg:phone":"+49 511/466698",
    "sg:postcode":"30159",
    "sg:province":"Niedersachsen",
    "wof:name":"Kino Erwin Aschenbach",
    "wof:placetype":"venue"
},
  "geometry": {"coordinates":[9.7329473495,52.3753700256],"type":"Point"}
}