{
  "type": "Feature",
  "properties": {
    "iso:country":"DE",
    "sg:address":"Hornbacher Landstr. 19",
    "sg:city":"Walld\u00fcrn",
    "sg:phone":"+49 6286/1474",
    "sg:postcode":"74731",
    "sg:province":"Baden-W\u00fcrttemberg",
    "wof:name":"S. Kern",
    "wof:placetype":"venue"
},
  "geometry": {"coordinates":[9.359998,49.583317],"type":"Point"}
}