{
  "type": "Feature",
  "properties": {
    "iso:country":"DE",
    "sg:address":"Osterseenstr. 21",
    "sg:city":"Iffeldorf",
    "sg:phone":"+49 8856/933515",
    "sg:postcode":"82393",
    "sg:province":"Bayern",
    "wof:name":"Welzm\u00fcller Gmbh",
    "wof:placetype":"venue"
},
  "geometry": {"coordinates":[11.320358,47.774109],"type":"Point"}
}