{
  "type": "Feature",
  "properties": {
    "iso:country":"DE",
    "sg:address":"Domplatz 8",
    "sg:city":"Naumburg",
    "sg:phone":"+49 3445/205382",
    "sg:postcode":"06618",
    "sg:province":"Sachsen-Anhalt",
    "wof:name":"Dr. Ettl Dr. Sattler Dr. Schuh Und Dr. Sobott Geologen",
    "wof:placetype":"venue"
},
  "geometry": {"coordinates":[11.8027858734,51.1553039551],"type":"Point"}
}