{
  "type": "Feature",
  "properties": {
    "iso:country":"DE",
    "sg:address":"Horstweg 16",
    "sg:city":"Elsterwerda",
    "sg:phone":"+49 3533/163366",
    "sg:postcode":"04910",
    "sg:province":"Brandenburg",
    "wof:name":"Hofmann",
    "wof:placetype":"venue"
},
  "geometry": {"coordinates":[13.525136,51.445091],"type":"Point"}
}