{
  "type": "Feature",
  "properties": {
    "iso:country":"DE",
    "sg:address":"Dr.-Karl-Meister-Str. 12",
    "sg:city":"Bruchsal",
    "sg:phone":"+49 7251/97040",
    "sg:postcode":"76646",
    "sg:province":"Baden-W\u00fcrttemberg",
    "wof:name":"Badische Anzeigen Verlags Gmbh",
    "wof:placetype":"venue"
},
  "geometry": {"coordinates":[8.6010227203,49.1237716675],"type":"Point"}
}