{
  "type": "Feature",
  "properties": {
    "iso:country":"DE",
    "sg:address":"Rotherstr. 22",
    "sg:city":"Berlin",
    "sg:postcode":"10245",
    "sg:province":"Berlin",
    "wof:name":"Berlin.de New Media Gmbh & Co. Kg",
    "wof:placetype":"venue"
},
  "geometry": {"coordinates":[13.4512424469,52.5035972595],"type":"Point"}
}