{
  "type": "Feature",
  "properties": {
    "iso:country":"DE",
    "sg:address":"Haus-Berge-Str. 229",
    "sg:city":"Essen",
    "sg:phone":"+49 201/8669071",
    "sg:postcode":"45356",
    "sg:province":"Nordrhein-Westfalen",
    "wof:name":"Holger Kapela",
    "wof:placetype":"venue"
},
  "geometry": {"coordinates":[6.9764947891,51.4788970947],"type":"Point"}
}