{
  "type": "Feature",
  "properties": {
    "iso:country":"DE",
    "sg:address":"Louise-Dumont-Str. 7",
    "sg:city":"D\u00fcsseldorf",
    "sg:phone":"+49 211/9357620",
    "sg:postcode":"40211",
    "sg:province":"Nordrhein-Westfalen",
    "wof:name":"Vatan Flugreisen Gmbh",
    "wof:placetype":"venue"
},
  "geometry": {"coordinates":[6.7883758545,51.2285461426],"type":"Point"}
}