{
  "type": "Feature",
  "properties": {
    "iso:country":"DE",
    "sg:address":"Yburgstr. 75a",
    "sg:city":"Baden-Baden",
    "sg:phone":"+49 7223/60529",
    "sg:postcode":"76534",
    "sg:province":"Baden-W\u00fcrttemberg",
    "wof:name":"Stefan Kopp",
    "wof:placetype":"venue"
},
  "geometry": {"coordinates":[8.16637,48.727745],"type":"Point"}
}