{
  "type": "Feature",
  "properties": {
    "iso:country":"DE",
    "sg:address":"Schlitzer Str. 56 a",
    "sg:city":"Berlin",
    "sg:phone":"+49 30/4028149",
    "sg:postcode":"13435",
    "sg:province":"Berlin",
    "wof:name":"Joachim Nicoleit",
    "wof:placetype":"venue"
},
  "geometry": {"coordinates":[13.340591,52.601784],"type":"Point"}
}