{
  "type": "Feature",
  "properties": {
    "iso:country":"DE",
    "sg:address":"Buchrainweg 9",
    "sg:city":"Kiefersfelden",
    "sg:phone":"+49 8033/7580",
    "sg:postcode":"83088",
    "sg:province":"Bayern",
    "wof:name":"Tsh Thermo Schuhhandels Gmbh",
    "wof:placetype":"venue"
},
  "geometry": {"coordinates":[12.1904649734,47.6192474365],"type":"Point"}
}