{
  "type": "Feature",
  "properties": {
    "iso:country":"DE",
    "sg:address":"Am Anger 1a",
    "sg:city":"Langenmosen",
    "sg:phone":"+49 8433/1514",
    "sg:postcode":"86571",
    "sg:province":"Bayern",
    "wof:name":"Josef Bachhuber",
    "wof:placetype":"venue"
},
  "geometry": {"coordinates":[11.217666,48.607613],"type":"Point"}
}