{
  "type": "Feature",
  "properties": {
    "iso:country":"DE",
    "sg:address":"Finkenstr. 2",
    "sg:city":"Grasbrunn",
    "sg:phone":"+49 89/467369",
    "sg:postcode":"85630",
    "sg:province":"Bayern",
    "wof:name":"Peter Strasser Rechtsanwalt",
    "wof:placetype":"venue"
},
  "geometry": {"coordinates":[11.7598724365,48.0982475281],"type":"Point"}
}