{
  "type": "Feature",
  "properties": {
    "iso:country":"DE",
    "sg:address":"Untere Hauptstr. 24",
    "sg:city":"Burkhardtsdorf",
    "sg:phone":"+49 3721/22710",
    "sg:postcode":"09235",
    "sg:province":"Sachsen",
    "wof:name":"A. Nestler",
    "wof:placetype":"venue"
},
  "geometry": {"coordinates":[12.9277906418,50.733089447],"type":"Point"}
}