{
  "type": "Feature",
  "properties": {
    "iso:country":"DE",
    "sg:address":"Lichte",
    "sg:city":"Empfertshausen",
    "sg:phone":"+49 36964/93043",
    "sg:postcode":"36452",
    "sg:province":"Th\u00fcringen",
    "wof:name":"F\u00e4rsenaufzucht Rh\u00f6nperle Gmbh",
    "wof:placetype":"venue"
},
  "geometry": {"coordinates":[10.0956096649,50.665473938],"type":"Point"}
}