{
  "type": "Feature",
  "properties": {
    "iso:country":"DE",
    "sg:address":"Pr\u00fcfeninger Str. 77",
    "sg:city":"Regensburg",
    "sg:phone":"+49 941/29370",
    "sg:postcode":"93049",
    "sg:province":"Bayern",
    "wof:name":"Bauers Backstube Inh. J\u00fcrgen Bauer",
    "wof:placetype":"venue"
},
  "geometry": {"coordinates":[12.069158,49.015972],"type":"Point"}
}