{
  "type": "Feature",
  "properties": {
    "iso:country":"DE",
    "sg:address":"Buddestr. 21",
    "sg:city":"Berlin",
    "sg:phone":"+49 30/41926276",
    "sg:postcode":"13507",
    "sg:province":"Berlin",
    "wof:name":"Kunstamt Reinickendorf",
    "wof:placetype":"venue"
},
  "geometry": {"coordinates":[13.2870969772,52.5902557373],"type":"Point"}
}