{
  "type": "Feature",
  "properties": {
    "iso:country":"DE",
    "sg:address":"Max-Lieber-Str. 26",
    "sg:city":"Wriezen",
    "sg:phone":"+49 33456/71543",
    "sg:postcode":"16269",
    "sg:province":"Brandenburg",
    "wof:name":"Bail Bauhof Gmbh",
    "wof:placetype":"venue"
},
  "geometry": {"coordinates":[14.1201095581,52.7288208008],"type":"Point"}
}