{
  "type": "Feature",
  "properties": {
    "iso:country":"DE",
    "sg:address":"Achalmstr. 25",
    "sg:city":"Pfullingen",
    "sg:phone":"+49 7121/71223",
    "sg:postcode":"72793",
    "sg:province":"Baden-W\u00fcrttemberg",
    "wof:name":"Wolfram Sch\u00fcler Gmbh",
    "wof:placetype":"venue"
},
  "geometry": {"coordinates":[9.231461525,48.4677085876],"type":"Point"}
}