{
  "type": "Feature",
  "properties": {
    "iso:country":"DE",
    "sg:address":"Drostenstr. 9",
    "sg:city":"Varel",
    "sg:phone":"+49 4451/91180",
    "sg:postcode":"26316",
    "sg:province":"Niedersachsen",
    "wof:name":"Drosten-apotheke Inh. E. Onken",
    "wof:placetype":"venue"
},
  "geometry": {"coordinates":[8.138851,53.396835],"type":"Point"}
}