{
  "type": "Feature",
  "properties": {
    "iso:country":"DE",
    "sg:address":"Kaiserstr. 46",
    "sg:city":"Lahr",
    "sg:phone":"+49 7821/985358",
    "sg:postcode":"77933",
    "sg:province":"Baden-W\u00fcrttemberg",
    "wof:name":"Vahap Arabaci",
    "wof:placetype":"venue"
},
  "geometry": {"coordinates":[7.8692641258,48.3414154053],"type":"Point"}
}