{
  "type": "Feature",
  "properties": {
    "iso:country":"DE",
    "sg:address":"Obere Grabenstr. 25",
    "sg:city":"Gundersheim",
    "sg:phone":"+49 6244/231",
    "sg:postcode":"67598",
    "sg:province":"Rheinland-Pfalz",
    "wof:name":"Philipp Huppert",
    "wof:placetype":"venue"
},
  "geometry": {"coordinates":[8.2039518356,49.6929931641],"type":"Point"}
}