{
  "type": "Feature",
  "properties": {
    "iso:country":"DE",
    "sg:address":"Brunnenstr. 15",
    "sg:city":"Sinzig",
    "sg:phone":"+49 2642/41656",
    "sg:postcode":"53489",
    "sg:province":"Rheinland-Pfalz",
    "wof:name":"M. Sonntag Heissmangel",
    "wof:placetype":"venue"
},
  "geometry": {"coordinates":[7.2267460823,50.5378723145],"type":"Point"}
}