{
  "type": "Feature",
  "properties": {
    "iso:country":"DE",
    "sg:address":"Brandstr. 35",
    "sg:city":"Beeskow",
    "sg:postcode":"15848",
    "sg:province":"Brandenburg",
    "wof:name":"Evangelisches Pfarramt",
    "wof:placetype":"venue"
},
  "geometry": {"coordinates":[14.2489881516,52.1707878113],"type":"Point"}
}