{
  "type": "Feature",
  "properties": {
    "iso:country":"DE",
    "sg:address":"Marienstr. 37",
    "sg:city":"Stuttgart",
    "sg:phone":"+49 711/60174848",
    "sg:postcode":"70178",
    "sg:province":"Baden-W\u00fcrttemberg",
    "wof:name":"Enarplan Ingenieurgesellschaft F\u00fcr Internationale Bau-",
    "wof:placetype":"venue"
},
  "geometry": {"coordinates":[9.1702651978,48.7706031799],"type":"Point"}
}