{
  "type": "Feature",
  "properties": {
    "iso:country":"DE",
    "sg:address":"Lange Str. 115",
    "sg:city":"N\u00f6rten-Hardenberg",
    "sg:phone":"+49 5503/749",
    "sg:postcode":"37176",
    "sg:province":"Niedersachsen",
    "wof:name":"Erich Kannengiesser",
    "wof:placetype":"venue"
},
  "geometry": {"coordinates":[9.9375247955,51.6332740784],"type":"Point"}
}