{
  "type": "Feature",
  "properties": {
    "iso:country":"DE",
    "sg:address":"Wildbacher Str.",
    "sg:city":"Schneeberg",
    "sg:phone":"+49 3772/23045",
    "sg:postcode":"08289",
    "sg:province":"Sachsen",
    "wof:name":"Bernd Kornatz Metallhandel Ohg",
    "wof:placetype":"venue"
},
  "geometry": {"coordinates":[12.640245,50.607323],"type":"Point"}
}