{
  "type": "Feature",
  "properties": {
    "iso:country":"DE",
    "sg:address":"Horb",
    "sg:city":"Horb",
    "sg:phone":"+49 7486/376",
    "sg:postcode":"72160",
    "sg:province":"Baden-W\u00fcrttemberg",
    "wof:name":"Volksbank Horb Eg",
    "wof:placetype":"venue"
},
  "geometry": {"coordinates":[8.66144,48.452332],"type":"Point"}
}