{
  "type": "Feature",
  "properties": {
    "iso:country":"DE",
    "sg:address":"Vulkanstr. 52",
    "sg:city":"Berlin",
    "sg:postcode":"10367",
    "sg:province":"Berlin",
    "wof:name":"Kostenlose Onlinespiele",
    "wof:placetype":"venue"
},
  "geometry": {"coordinates":[13.485081,52.525272],"type":"Point"}
}