{
  "type": "Feature",
  "properties": {
    "iso:country":"DE",
    "sg:address":"Kommerner Str. 204",
    "sg:city":"Euskirchen",
    "sg:phone":"+49 2251/58770",
    "sg:postcode":"53879",
    "sg:province":"Nordrhein-Westfalen",
    "wof:name":"J. Niehsen Ingenieur",
    "wof:placetype":"venue"
},
  "geometry": {"coordinates":[6.7701539993,50.6572036743],"type":"Point"}
}