{
  "type": "Feature",
  "properties": {
    "iso:country":"DE",
    "sg:address":"Bahnhofstrasse 4",
    "sg:city":"Henstedt-Ulzburg",
    "sg:postcode":"24558",
    "sg:province":"Schleswig-Holstein",
    "wof:name":"Manu Bauunternehmung Gmbh & Co",
    "wof:placetype":"venue"
},
  "geometry": {"coordinates":[9.9812383652,53.7947845459],"type":"Point"}
}