{
  "type": "Feature",
  "properties": {
    "iso:country":"DE",
    "sg:address":"Vordergasse 5",
    "sg:city":"Lautertal",
    "sg:phone":"+49 6643/8166",
    "sg:postcode":"36369",
    "sg:province":"Hessen",
    "wof:name":"Uwe Philipp",
    "wof:placetype":"venue"
},
  "geometry": {"coordinates":[9.3013563156,50.6060218811],"type":"Point"}
}