{
  "type": "Feature",
  "properties": {
    "iso:country":"DE",
    "sg:address":"Oberlindau 80/82",
    "sg:city":"Frankfurt",
    "sg:postcode":"60322",
    "sg:province":"Hessen",
    "wof:name":"Fcf Finanz Consult Frankfurt Gmbh",
    "wof:placetype":"venue"
},
  "geometry": {"coordinates":[8.6682424545,50.1220817566],"type":"Point"}
}