{
  "type": "Feature",
  "properties": {
    "iso:country":"DE",
    "sg:address":"Innere Schneeberger Str. 2",
    "sg:city":"Zwickau",
    "sg:phone":"+49 375/390340",
    "sg:postcode":"08056",
    "sg:province":"Sachsen",
    "wof:name":"Gutenberg-buchhandlung Ohg Kozok & Unger",
    "wof:placetype":"venue"
},
  "geometry": {"coordinates":[12.496837616,50.7173194885],"type":"Point"}
}