{
  "type": "Feature",
  "properties": {
    "iso:country":"DE",
    "sg:address":"Steppacher Str. 32",
    "sg:city":"Diedorf",
    "sg:phone":"+49 821/4863431",
    "sg:postcode":"86420",
    "sg:province":"Bayern",
    "wof:name":"Rolf Pfister Beteiligungs Gmbh",
    "wof:placetype":"venue"
},
  "geometry": {"coordinates":[10.7934484482,48.364200592],"type":"Point"}
}