{
  "type": "Feature",
  "properties": {
    "iso:country":"DE",
    "sg:address":"Voigtei 68",
    "sg:city":"Steyerberg",
    "sg:phone":"+49 5769/262",
    "sg:postcode":"31595",
    "sg:province":"Niedersachsen",
    "wof:name":"Gastst\u00e4tte Willi Schr\u00f6der",
    "wof:placetype":"venue"
},
  "geometry": {"coordinates":[8.9396314621,52.6113510132],"type":"Point"}
}