{
  "type": "Feature",
  "properties": {
    "iso:country":"DE",
    "sg:address":"Z\u00e4hringer Str. 373",
    "sg:city":"Freiburg",
    "sg:phone":"+49 761",
    "sg:postcode":"79108",
    "sg:province":"Baden-W\u00fcrttemberg",
    "wof:name":"Deutsche Schutzvereinigung Auslandsimmobilien E.v.",
    "wof:placetype":"venue"
},
  "geometry": {"coordinates":[7.860457,48.02483],"type":"Point"}
}