{
  "type": "Feature",
  "properties": {
    "iso:country":"DE",
    "sg:address":"Bredowstr. 33",
    "sg:city":"Hamburg",
    "sg:postcode":"22113",
    "sg:province":"Schleswig-Holstein",
    "wof:name":"Hahnemann Kartonagenvertrieb E. K.",
    "wof:placetype":"venue"
},
  "geometry": {"coordinates":[10.095694,53.519783],"type":"Point"}
}