{
  "type": "Feature",
  "properties": {
    "iso:country":"DE",
    "sg:address":"Alte Eppel Heimer Str. 8",
    "sg:city":"Heidelberg",
    "sg:phone":"+49 4962/2145020",
    "sg:postcode":"69115",
    "sg:province":"Baden-W\u00fcrttemberg",
    "wof:name":"Novasoft Ag",
    "wof:placetype":"venue"
},
  "geometry": {"coordinates":[8.683317,49.407097],"type":"Point"}
}