{
  "type": "Feature",
  "properties": {
    "iso:country":"DE",
    "sg:address":"Buchbindergasse 12",
    "sg:city":"Kulmbach",
    "sg:phone":"+49 9221/4491",
    "sg:postcode":"95326",
    "sg:province":"Bayern",
    "wof:name":"Pizzeria Allarustica",
    "wof:placetype":"venue"
},
  "geometry": {"coordinates":[11.4575119019,50.1078681946],"type":"Point"}
}