{
  "type": "Feature",
  "properties": {
    "iso:country":"DE",
    "sg:address":"An der Bleiche 9",
    "sg:city":"Dinklage",
    "sg:phone":"+49 4443/1528",
    "sg:postcode":"49413",
    "sg:province":"Niedersachsen",
    "wof:name":"Lfb Kunstdarm Handelsgesellschaft Mbh",
    "wof:placetype":"venue"
},
  "geometry": {"coordinates":[8.116786,52.662647],"type":"Point"}
}