{
  "type": "Feature",
  "properties": {
    "iso:country":"DE",
    "sg:address":"Arnold-Kock-Str. 4",
    "sg:city":"Steinfurt",
    "sg:phone":"+49 2552/3368",
    "sg:postcode":"48565",
    "sg:province":"Nordrhein-Westfalen",
    "wof:name":"Hotel Sch\u00fctzenhof",
    "wof:placetype":"venue"
},
  "geometry": {"coordinates":[7.3985638618,52.1287727356],"type":"Point"}
}