{
  "type": "Feature",
  "properties": {
    "iso:country":"DE",
    "sg:address":"Herrenheeg 1",
    "sg:city":"Herschbach",
    "sg:phone":"+49 2626/140940",
    "sg:postcode":"56249",
    "sg:province":"Rheinland-Pfalz",
    "wof:name":"Amusa Arbeitsmedizin Gmbh",
    "wof:placetype":"venue"
},
  "geometry": {"coordinates":[7.7421460152,50.5736923218],"type":"Point"}
}