{
  "type": "Feature",
  "properties": {
    "iso:country":"DE",
    "sg:address":"Vor dem Stodt 18",
    "sg:city":"Meschede",
    "sg:phone":"+49 291/51501",
    "sg:postcode":"59872",
    "sg:province":"Nordrhein-Westfalen",
    "wof:name":"Dr. Raymund Fitzer Tierarzt",
    "wof:placetype":"venue"
},
  "geometry": {"coordinates":[8.3382806778,51.3737831116],"type":"Point"}
}