{
  "type": "Feature",
  "properties": {
    "iso:country":"DE",
    "sg:address":"Lisztweg 24",
    "sg:city":"Geretsried",
    "sg:phone":"+49 8171/31989",
    "sg:postcode":"82538",
    "sg:province":"Bayern",
    "wof:name":"Abs Zimmerei Gmbh",
    "wof:placetype":"venue"
},
  "geometry": {"coordinates":[11.4777345657,47.8541870117],"type":"Point"}
}