{
  "type": "Feature",
  "properties": {
    "iso:country":"DE",
    "sg:address":"Rohrlochstr. 10",
    "sg:city":"Balingen",
    "sg:phone":"+49 7433/903131",
    "sg:postcode":"72336",
    "sg:province":"Baden-W\u00fcrttemberg",
    "wof:name":"At-stautz Technik Gmbh",
    "wof:placetype":"venue"
},
  "geometry": {"coordinates":[8.83911,48.282597],"type":"Point"}
}