{
  "type": "Feature",
  "properties": {
    "iso:country":"DE",
    "sg:address":"Karlsruher Str. 76",
    "sg:city":"Heidelberg",
    "sg:phone":"+49 6221/373943",
    "sg:postcode":"69126",
    "sg:province":"Baden-W\u00fcrttemberg",
    "wof:name":"Franz J. Riedel",
    "wof:placetype":"venue"
},
  "geometry": {"coordinates":[8.6893005371,49.3812522888],"type":"Point"}
}