{
  "type": "Feature",
  "properties": {
    "iso:country":"DE",
    "sg:address":"Adolfstr. 19",
    "sg:city":"Braunschweig",
    "sg:phone":"+49 531/73224",
    "sg:postcode":"38102",
    "sg:province":"Niedersachsen",
    "wof:name":"Schr\u00f6ter Bauwerks- Erhaltung Gmbh",
    "wof:placetype":"venue"
},
  "geometry": {"coordinates":[10.534104,52.259392],"type":"Point"}
}