{
  "type": "Feature",
  "properties": {
    "iso:country":"DE",
    "sg:address":"Westerende 11",
    "sg:city":"Zetel",
    "sg:phone":"+49 4453/3115",
    "sg:postcode":"26340",
    "sg:province":"Niedersachsen",
    "wof:name":"Gerd Ahlers Baustoffe Gmbh",
    "wof:placetype":"venue"
},
  "geometry": {"coordinates":[7.9692487717,53.4217414856],"type":"Point"}
}