{
  "type": "Feature",
  "properties": {
    "iso:country":"DE",
    "sg:address":"Weidacher Hauptstr. 27",
    "sg:city":"Wolfratshausen",
    "sg:phone":"+49 8171/20539",
    "sg:postcode":"82515",
    "sg:province":"Bayern",
    "wof:name":"Michael Baindl",
    "wof:placetype":"venue"
},
  "geometry": {"coordinates":[11.42818,47.919834],"type":"Point"}
}