{
  "type": "Feature",
  "properties": {
    "iso:country":"DE",
    "sg:address":"Markt 21",
    "sg:city":"D\u00fcren",
    "sg:phone":"+49 2421/10184",
    "sg:postcode":"52349",
    "sg:province":"Nordrhein-Westfalen",
    "wof:name":"Piano",
    "wof:placetype":"venue"
},
  "geometry": {"coordinates":[6.483738,50.802479],"type":"Point"}
}