{
  "type": "Feature",
  "properties": {
    "iso:country":"DE",
    "sg:city":"Duesseldorf",
    "sg:phone":"+49 211",
    "sg:postcode":"40549",
    "sg:province":"Nordrhein-Westfalen",
    "wof:name":"Eichhorn Und Ody - Steuerberatungsgesellschaft Mbh",
    "wof:placetype":"venue"
},
  "geometry": {"coordinates":[6.718873,51.233208],"type":"Point"}
}