{
  "type": "Feature",
  "properties": {
    "iso:country":"DE",
    "sg:address":"Krugenofen 49",
    "sg:city":"Aachen",
    "sg:phone":"+49 241/62369",
    "sg:postcode":"52066",
    "sg:province":"Nordrhein-Westfalen",
    "wof:name":"Dieter Zimmermann",
    "wof:placetype":"venue"
},
  "geometry": {"coordinates":[6.0880088806,50.7628250122],"type":"Point"}
}