{
  "type": "Feature",
  "properties": {
    "iso:country":"DE",
    "sg:address":"Sandforther Str. 8",
    "sg:city":"Steinhagen",
    "sg:phone":"+49 5204/3781",
    "sg:postcode":"33803",
    "sg:province":"Nordrhein-Westfalen",
    "wof:name":"H. A. Rieke",
    "wof:placetype":"venue"
},
  "geometry": {"coordinates":[8.3461494446,51.9922904968],"type":"Point"}
}