{
  "type": "Feature",
  "properties": {
    "iso:country":"DE",
    "sg:address":"Am Stadtgraben 4",
    "sg:city":"Kitzingen",
    "sg:phone":"+49 9321/8047",
    "sg:postcode":"97318",
    "sg:province":"Bayern",
    "wof:name":"Redaktion Volksblatt",
    "wof:placetype":"venue"
},
  "geometry": {"coordinates":[10.1610832214,49.7364578247],"type":"Point"}
}