{
  "type": "Feature",
  "properties": {
    "iso:country":"DE",
    "sg:address":"Wiesenweg 22",
    "sg:city":"Landau",
    "sg:phone":"+49 9951/9420",
    "sg:postcode":"94405",
    "sg:province":"Bayern",
    "wof:name":"Hans Einhell Ag",
    "wof:placetype":"venue"
},
  "geometry": {"coordinates":[12.7007541656,48.686870575],"type":"Point"}
}