{
  "type": "Feature",
  "properties": {
    "iso:country":"DE",
    "sg:address":"Windener Weg 24",
    "sg:city":"Kreuzau",
    "sg:postcode":"52372",
    "sg:province":"Nordrhein-Westfalen",
    "wof:name":"Festhalle",
    "wof:placetype":"venue"
},
  "geometry": {"coordinates":[6.484901,50.743851],"type":"Point"}
}