{
  "type": "Feature",
  "properties": {
    "iso:country":"DE",
    "sg:address":"Martinstr. 25",
    "sg:city":"Aachen",
    "sg:phone":"+49 241/36087",
    "sg:postcode":"52062",
    "sg:province":"Nordrhein-Westfalen",
    "wof:name":"Bernhard May",
    "wof:placetype":"venue"
},
  "geometry": {"coordinates":[6.085999,50.779617],"type":"Point"}
}