{
  "type": "Feature",
  "properties": {
    "iso:country":"DE",
    "sg:address":"Mittelweg 141",
    "sg:city":"Hamburg",
    "sg:postcode":"20148",
    "sg:province":"Hamburg",
    "wof:name":"Konrad-adenauer-stiftung E. V. Hermann-ehlers-bildungswerk",
    "wof:placetype":"venue"
},
  "geometry": {"coordinates":[9.9954214096,53.5702171326],"type":"Point"}
}