{
  "type": "Feature",
  "properties": {
    "iso:country":"DE",
    "sg:address":"Altenberger Str. 38",
    "sg:city":"Nordwalde",
    "sg:postcode":"48356",
    "sg:province":"Nordrhein-Westfalen",
    "wof:name":"M. B\u00fcning Kg",
    "wof:placetype":"venue"
},
  "geometry": {"coordinates":[7.478323,52.077915],"type":"Point"}
}