{
  "type": "Feature",
  "properties": {
    "iso:country":"DE",
    "sg:address":"Flotowstr. 7",
    "sg:city":"Fredersdorf",
    "sg:phone":"+49 33439/76590",
    "sg:postcode":"15370",
    "sg:province":"Brandenburg",
    "wof:name":"Herbert Nevyhosteny Elektro",
    "wof:placetype":"venue"
},
  "geometry": {"coordinates":[13.754613,52.547649],"type":"Point"}
}