{
  "type": "Feature",
  "properties": {
    "iso:country":"DE",
    "sg:address":"Niedergasse 45",
    "sg:city":"Stolberg",
    "sg:phone":"+49 34654/10300",
    "sg:postcode":"06547",
    "sg:province":"Sachsen-Anhalt",
    "wof:name":"Altes Kino",
    "wof:placetype":"venue"
},
  "geometry": {"coordinates":[10.9570837021,51.5704956055],"type":"Point"}
}