{
  "type": "Feature",
  "properties": {
    "iso:country":"DE",
    "sg:address":"Comeniusstr.",
    "sg:city":"Kempen",
    "sg:phone":"+49 2152/20950",
    "sg:postcode":"47906",
    "sg:province":"Nordrhein-Westfalen",
    "wof:name":"New Tech Videokomponenten Vertriebs Gmbh",
    "wof:placetype":"venue"
},
  "geometry": {"coordinates":[6.4150018692,51.3687438965],"type":"Point"}
}