{
  "type": "Feature",
  "properties": {
    "iso:country":"DE",
    "sg:address":"Helschen 10",
    "sg:city":"Emsb\u00fcren",
    "sg:postcode":"48488",
    "sg:province":"Niedersachsen",
    "wof:name":"Lohnbetrieb Rothk\u00f6tter Inh. Helmut Berning E. K.",
    "wof:placetype":"venue"
},
  "geometry": {"coordinates":[7.3409771919,52.4061126709],"type":"Point"}
}