{
  "type": "Feature",
  "properties": {
    "iso:country":"DE",
    "sg:address":"Kleinseebacher Str. 61",
    "sg:city":"M\u00f6hrendorf",
    "sg:phone":"+49 9133/1612",
    "sg:postcode":"91096",
    "sg:province":"Bayern",
    "wof:name":"Regierungsbaumeister Schlegel Gmbh & Co. Kg",
    "wof:placetype":"venue"
},
  "geometry": {"coordinates":[11.0054931641,49.6505813599],"type":"Point"}
}