{
  "type": "Feature",
  "properties": {
    "iso:country":"DE",
    "sg:address":"Waldenburger Str. 16",
    "sg:city":"Hohenstein-Ernstthal",
    "sg:phone":"+49 3723/711933",
    "sg:postcode":"09337",
    "sg:province":"Sachsen",
    "wof:name":"W. Decker",
    "wof:placetype":"venue"
},
  "geometry": {"coordinates":[12.738511,50.815372],"type":"Point"}
}