{
  "type": "Feature",
  "properties": {
    "iso:country":"DE",
    "sg:address":"Windm\u00fchlenweg 4",
    "sg:city":"Bakum",
    "sg:phone":"+49 4446/1768",
    "sg:postcode":"49456",
    "sg:province":"Niedersachsen",
    "wof:name":"Gregor Marquering",
    "wof:placetype":"venue"
},
  "geometry": {"coordinates":[8.127886,52.744061],"type":"Point"}
}