{
  "type": "Feature",
  "properties": {
    "iso:country":"DE",
    "sg:address":"Sandweg 32",
    "sg:city":"Marburg",
    "sg:phone":"+49 6421/36915",
    "sg:postcode":"35037",
    "sg:province":"Hessen",
    "wof:name":"K.-l. Leiter",
    "wof:placetype":"venue"
},
  "geometry": {"coordinates":[8.75409,50.807053],"type":"Point"}
}