{
  "type": "Feature",
  "properties": {
    "iso:country":"DE",
    "sg:address":"Jauerstr. 21",
    "sg:city":"N\u00fcrnberg",
    "sg:phone":"+49 911/805440",
    "sg:postcode":"90473",
    "sg:province":"Bayern",
    "wof:name":"Gernot Schulz",
    "wof:placetype":"venue"
},
  "geometry": {"coordinates":[11.1495399475,49.405796051],"type":"Point"}
}