{
  "type": "Feature",
  "properties": {
    "iso:country":"DE",
    "sg:address":"Auf dem Esch 71",
    "sg:city":"Diepholz",
    "sg:phone":"+49 5441/3518",
    "sg:postcode":"49356",
    "sg:province":"Niedersachsen",
    "wof:name":"Insider",
    "wof:placetype":"venue"
},
  "geometry": {"coordinates":[8.3759593964,52.6146659851],"type":"Point"}
}