{
  "type": "Feature",
  "properties": {
    "iso:country":"DE",
    "sg:address":"K\u00f6nigsberger Str. 12-18",
    "sg:city":"Kaarst",
    "sg:phone":"+49 2131/60070",
    "sg:postcode":"41564",
    "sg:province":"Nordrhein-Westfalen",
    "wof:name":"Kr\u00fcll Gmbh",
    "wof:placetype":"venue"
},
  "geometry": {"coordinates":[6.637547,51.219116],"type":"Point"}
}