{
  "type": "Feature",
  "properties": {
    "iso:country":"DE",
    "sg:address":"Burgstr. 56",
    "sg:city":"Mertloch",
    "sg:phone":"+49 2654/7321",
    "sg:postcode":"56753",
    "sg:province":"Rheinland-Pfalz",
    "wof:name":"Leo Krechel",
    "wof:placetype":"venue"
},
  "geometry": {"coordinates":[7.30404,50.267281],"type":"Point"}
}