{
  "type": "Feature",
  "properties": {
    "iso:country":"DE",
    "sg:address":"Beethovenstr. 69",
    "sg:city":"Regenstauf",
    "sg:phone":"+49 9402/70446",
    "sg:postcode":"93128",
    "sg:province":"Bayern",
    "wof:name":"Warnold Marketing Gmbh",
    "wof:placetype":"venue"
},
  "geometry": {"coordinates":[12.129548,49.131149],"type":"Point"}
}