{
  "type": "Feature",
  "properties": {
    "iso:country":"DE",
    "sg:address":"Schie\u00dfhausstr. 1",
    "sg:city":"Altdorf",
    "sg:phone":"+49 9187/3422",
    "sg:postcode":"90518",
    "sg:province":"Bayern",
    "wof:name":"Sss Schnelzer Gmbh",
    "wof:placetype":"venue"
},
  "geometry": {"coordinates":[11.3606834412,49.3854370117],"type":"Point"}
}