{
  "type": "Feature",
  "properties": {
    "iso:country":"DE",
    "sg:address":"Leininger Str. 55 a",
    "sg:city":"Enkenbach-Alsenborn",
    "sg:phone":"+49 6303/7709",
    "sg:postcode":"67677",
    "sg:province":"Rheinland-Pfalz",
    "wof:name":"R. Brendel",
    "wof:placetype":"venue"
},
  "geometry": {"coordinates":[7.928356,49.490055],"type":"Point"}
}