{
  "type": "Feature",
  "properties": {
    "iso:country":"DE",
    "sg:address":"R\u00fcskenkampstr. 1",
    "sg:city":"Westerkappeln",
    "sg:phone":"+49 5404/1530",
    "sg:postcode":"49492",
    "sg:province":"Nordrhein-Westfalen",
    "wof:name":"F. Mertsching",
    "wof:placetype":"venue"
},
  "geometry": {"coordinates":[7.8824558258,52.316608429],"type":"Point"}
}