{
  "type": "Feature",
  "properties": {
    "iso:country":"DE",
    "sg:address":"Auf der Ennest 34",
    "sg:city":"Lennestadt",
    "sg:phone":"+49 2723/6334",
    "sg:postcode":"57368",
    "sg:province":"Nordrhein-Westfalen",
    "wof:name":"Sexy Und Geil - Die Besten Shows Im Web!",
    "wof:placetype":"venue"
},
  "geometry": {"coordinates":[8.067463,51.108158],"type":"Point"}
}