{
  "type": "Feature",
  "properties": {
    "iso:country":"DE",
    "sg:address":"Mohrenstr. 7",
    "sg:city":"Ettlingen",
    "sg:phone":"+49 7243/14517",
    "sg:postcode":"76275",
    "sg:province":"Baden-W\u00fcrttemberg",
    "wof:name":"Rob-hydraulikger\u00e4te Gmbh",
    "wof:placetype":"venue"
},
  "geometry": {"coordinates":[8.404299736,48.942615509],"type":"Point"}
}