{
  "type": "Feature",
  "properties": {
    "iso:country":"DE",
    "sg:address":"Klintweg 7a",
    "sg:city":"Bargenstedt",
    "sg:phone":"+49 4832/2974",
    "sg:postcode":"25704",
    "sg:province":"Schleswig-Holstein",
    "wof:name":"K. Kornau",
    "wof:placetype":"venue"
},
  "geometry": {"coordinates":[9.152796,54.095882],"type":"Point"}
}