{
  "type": "Feature",
  "properties": {
    "iso:country":"DE",
    "sg:address":"Torgauer Str.",
    "sg:city":"Eilenburg",
    "sg:phone":"+49 3423/602379",
    "sg:postcode":"04838",
    "sg:province":"Sachsen",
    "wof:name":"Krane Optik- Und Akustik Gmbh & Co. Betriebs Kg",
    "wof:placetype":"venue"
},
  "geometry": {"coordinates":[12.6376152039,51.4609260559],"type":"Point"}
}