{
  "type": "Feature",
  "properties": {
    "iso:country":"DE",
    "sg:address":"Fritzlarerstrasse 25",
    "sg:city":"Schwalmstadt",
    "sg:phone":"+49 6691/96170",
    "sg:postcode":"34613",
    "sg:province":"Hessen",
    "wof:name":"Tieman Gmbh",
    "wof:placetype":"venue"
},
  "geometry": {"coordinates":[9.19376,50.922951],"type":"Point"}
}