{
  "type": "Feature",
  "properties": {
    "iso:country":"DE",
    "sg:address":"Richtstr. 30",
    "sg:city":"Schweich",
    "sg:phone":"+49 6502/1081",
    "sg:postcode":"54338",
    "sg:province":"Rheinland-Pfalz",
    "wof:name":"Zahnhausen Und Wahlen Rechtsanw\u00e4lte",
    "wof:placetype":"venue"
},
  "geometry": {"coordinates":[6.7530851364,49.8229522705],"type":"Point"}
}