{
  "type": "Feature",
  "properties": {
    "iso:country":"DE",
    "sg:address":"L\u00fcneburger Str. 13",
    "sg:city":"Winsen",
    "sg:phone":"+49 4171/71041",
    "sg:postcode":"21423",
    "sg:province":"Niedersachsen",
    "wof:name":"G\u00fcnther H\u00e4rtel",
    "wof:placetype":"venue"
},
  "geometry": {"coordinates":[10.2078418732,53.3558502197],"type":"Point"}
}