{
  "type": "Feature",
  "properties": {
    "iso:country":"DE",
    "sg:address":"K\u00f6nigstr. 16",
    "sg:city":"Haigerloch",
    "sg:phone":"+49 7474/51136",
    "sg:postcode":"72401",
    "sg:province":"Baden-W\u00fcrttemberg",
    "wof:name":"E. Henne",
    "wof:placetype":"venue"
},
  "geometry": {"coordinates":[8.827009,48.337215],"type":"Point"}
}