{
  "type": "Feature",
  "properties": {
    "iso:country":"DE",
    "sg:address":"Bergstr. 3",
    "sg:city":"Kolkwitz",
    "sg:phone":"+49 355/287160",
    "sg:postcode":"03099",
    "sg:province":"Brandenburg",
    "wof:name":"Horst Kr\u00fcger",
    "wof:placetype":"venue"
},
  "geometry": {"coordinates":[14.2927188873,51.7153015137],"type":"Point"}
}