{
  "type": "Feature",
  "properties": {
    "iso:country":"DE",
    "sg:address":"Vilsecker Str. 24",
    "sg:city":"Grafenw\u00f6hr",
    "sg:phone":"+49 9641/3605",
    "sg:postcode":"92655",
    "sg:province":"Bayern",
    "wof:name":"Raimund R\u00f6ttenbacher Architekt",
    "wof:placetype":"venue"
},
  "geometry": {"coordinates":[11.896925,49.714535],"type":"Point"}
}