{
  "type": "Feature",
  "properties": {
    "iso:country":"DE",
    "sg:address":"Hirschberger Str. 16",
    "sg:city":"G\u00fctersloh",
    "sg:phone":"+49 5241/73163",
    "sg:postcode":"33335",
    "sg:province":"Nordrhein-Westfalen",
    "wof:name":"R. Und S. Stefan",
    "wof:placetype":"venue"
},
  "geometry": {"coordinates":[8.438953,51.938786],"type":"Point"}
}