{
  "type": "Feature",
  "properties": {
    "iso:country":"DE",
    "sg:address":"Schulstr. 5",
    "sg:city":"Rastatt",
    "sg:phone":"+49 7222/25423",
    "sg:postcode":"76437",
    "sg:province":"Baden-W\u00fcrttemberg",
    "wof:name":"K. H. Haas",
    "wof:placetype":"venue"
},
  "geometry": {"coordinates":[8.1544094086,48.8843841553],"type":"Point"}
}