{
  "type": "Feature",
  "properties": {
    "iso:country":"DE",
    "sg:city":"Uhingen",
    "sg:postcode":"73066",
    "sg:province":"Baden-W\u00fcrttemberg",
    "wof:name":"Malerei",
    "wof:placetype":"venue"
},
  "geometry": {"coordinates":[9.584786,48.705826],"type":"Point"}
}