{
  "type": "Feature",
  "properties": {
    "iso:country":"DE",
    "sg:address":"Am Kronenberg 2",
    "sg:city":"Walkenried",
    "sg:phone":"+49 5525/1881",
    "sg:postcode":"37445",
    "sg:province":"Niedersachsen",
    "wof:name":"Manfred Hanke",
    "wof:placetype":"venue"
},
  "geometry": {"coordinates":[10.622394,51.58987],"type":"Point"}
}