{
  "type": "Feature",
  "properties": {
    "iso:country":"DE",
    "sg:address":"Entenbachstr. 29",
    "sg:city":"M\u00fcnchen",
    "sg:phone":"+49 89/62220",
    "sg:postcode":"81541",
    "sg:province":"Bayern",
    "wof:name":"Wohnstift Am Entenbach",
    "wof:placetype":"venue"
},
  "geometry": {"coordinates":[11.57811,48.122665],"type":"Point"}
}