{
  "type": "Feature",
  "properties": {
    "iso:country":"DE",
    "sg:address":"Gartenstr. 7",
    "sg:city":"Eckental",
    "sg:phone":"+49 9126/7941",
    "sg:postcode":"90542",
    "sg:province":"Bayern",
    "wof:name":"Jaroslav Cervinka",
    "wof:placetype":"venue"
},
  "geometry": {"coordinates":[11.214381,49.577011],"type":"Point"}
}