{
  "type": "Feature",
  "properties": {
    "iso:country":"DE",
    "sg:address":"Bismarckplatz 16a",
    "sg:city":"Aken",
    "sg:phone":"+49 34909/82714",
    "sg:postcode":"06385",
    "sg:province":"Sachsen-Anhalt",
    "wof:name":"Abis Zeuner Mechanik Gmbh",
    "wof:placetype":"venue"
},
  "geometry": {"coordinates":[12.0382289886,51.8563232422],"type":"Point"}
}