{
  "type": "Feature",
  "properties": {
    "iso:country":"DE",
    "sg:address":"Enzmannstr. 17",
    "sg:city":"Chemnitz",
    "sg:phone":"+49 371/300433",
    "sg:postcode":"09112",
    "sg:province":"Sachsen",
    "wof:name":"J. Kirsch",
    "wof:placetype":"venue"
},
  "geometry": {"coordinates":[12.9073591232,50.8299598694],"type":"Point"}
}