{
  "type": "Feature",
  "properties": {
    "iso:country":"DE",
    "sg:address":"K\u00fcsterkamp 2",
    "sg:city":"Barmstedt",
    "sg:postcode":"25355",
    "sg:province":"Schleswig-Holstein",
    "wof:name":"Aldi Gmbh & Co. Kg",
    "wof:placetype":"venue"
},
  "geometry": {"coordinates":[9.77069664,53.7884635925],"type":"Point"}
}