{
  "type": "Feature",
  "properties": {
    "iso:country":"DE",
    "sg:address":"Dornacher Str. 3c",
    "sg:city":"Feldkirchen",
    "sg:postcode":"85622",
    "sg:province":"Bayern",
    "wof:name":"Digital Equipment Gmbh Gesch\u00e4ftsbereich Pc",
    "wof:placetype":"venue"
},
  "geometry": {"coordinates":[11.7224769592,48.1508407593],"type":"Point"}
}