{
  "type": "Feature",
  "properties": {
    "iso:country":"DE",
    "sg:address":"Waldweg 6",
    "sg:city":"Erkelenz",
    "sg:phone":"+49 2431/2065",
    "sg:postcode":"41812",
    "sg:province":"Nordrhein-Westfalen",
    "wof:name":"De-co Leder Vertriebs Gmbh",
    "wof:placetype":"venue"
},
  "geometry": {"coordinates":[6.3458309174,51.0591316223],"type":"Point"}
}