{
  "type": "Feature",
  "properties": {
    "iso:country":"DE",
    "sg:address":"Industriestr 2",
    "sg:city":"Deilingen",
    "sg:phone":"+49 7426/519730",
    "sg:postcode":"78586",
    "sg:province":"Baden-W\u00fcrttemberg",
    "wof:name":"Geschwentner",
    "wof:placetype":"venue"
},
  "geometry": {"coordinates":[8.7800540924,48.1685066223],"type":"Point"}
}