{
  "type": "Feature",
  "properties": {
    "iso:country":"DE",
    "sg:address":"Lange St\u00fccken 5",
    "sg:city":"Berlin",
    "sg:phone":"+49 30/8052565",
    "sg:postcode":"14109",
    "sg:province":"Berlin",
    "wof:name":"Kurt H. Stirm Architekt",
    "wof:placetype":"venue"
},
  "geometry": {"coordinates":[13.144965,52.41671],"type":"Point"}
}