{
  "type": "Feature",
  "properties": {
    "iso:country":"DE",
    "sg:address":"Harkortstr. 140",
    "sg:city":"Hamburg",
    "sg:postcode":"22765",
    "sg:province":"Hamburg",
    "wof:name":"Tanzschule Zorbas",
    "wof:placetype":"venue"
},
  "geometry": {"coordinates":[9.9408445358,53.561416626],"type":"Point"}
}