{
  "type": "Feature",
  "properties": {
    "iso:country":"DE",
    "sg:address":"Hauptstr. 116",
    "sg:city":"Wei\u00dfenborn",
    "sg:postcode":"09600",
    "sg:province":"Sachsen",
    "wof:name":"B & B Projektges. 116 Mbh",
    "wof:placetype":"venue"
},
  "geometry": {"coordinates":[13.3815460205,50.8685264587],"type":"Point"}
}