{
  "type": "Feature",
  "properties": {
    "iso:country":"DE",
    "sg:address":"Crumbacher Str. 25",
    "sg:city":"Reichelsheim",
    "sg:phone":"+49 6164/54603",
    "sg:postcode":"64385",
    "sg:province":"Hessen",
    "wof:name":"Georg Kahles",
    "wof:placetype":"venue"
},
  "geometry": {"coordinates":[8.8659696579,49.7238082886],"type":"Point"}
}