{
  "type": "Feature",
  "properties": {
    "iso:country":"DE",
    "sg:address":"Kirchwerder Elbdeich 238",
    "sg:city":"Hamburg",
    "sg:phone":"+49 40/7230553",
    "sg:postcode":"21037",
    "sg:province":"Hamburg",
    "wof:name":"Werner Timmann",
    "wof:placetype":"venue"
},
  "geometry": {"coordinates":[10.198298,53.430012],"type":"Point"}
}