{
  "type": "Feature",
  "properties": {
    "iso:country":"DE",
    "sg:address":"Alte Schulstr. 3",
    "sg:city":"Estorf",
    "sg:phone":"+49 5025/1628",
    "sg:postcode":"31629",
    "sg:province":"Niedersachsen",
    "wof:name":"G\u00fcnther R\u00f6ttger",
    "wof:placetype":"venue"
},
  "geometry": {"coordinates":[9.140615,52.588554],"type":"Point"}
}