{
  "type": "Feature",
  "properties": {
    "iso:country":"DE",
    "sg:address":"Marktstr. 65",
    "sg:city":"Wilhelmshaven",
    "sg:phone":"+49 4421/21315",
    "sg:postcode":"26382",
    "sg:province":"Niedersachsen",
    "wof:name":"Wilhelm Johde Gmbh & Co. Kg",
    "wof:placetype":"venue"
},
  "geometry": {"coordinates":[8.110652,53.520279],"type":"Point"}
}