{
  "type": "Feature",
  "properties": {
    "iso:country":"DE",
    "sg:address":"R\u00f6merweg 2 a",
    "sg:city":"Sigmaringen",
    "sg:phone":"+49 7571/3408",
    "sg:postcode":"72488",
    "sg:province":"Baden-W\u00fcrttemberg",
    "wof:name":"Otto Grom",
    "wof:placetype":"venue"
},
  "geometry": {"coordinates":[9.221989,48.080498],"type":"Point"}
}