{
  "type": "Feature",
  "properties": {
    "iso:country":"DE",
    "sg:address":"Kumpfm\u00fchler Str. 51",
    "sg:city":"Regensburg",
    "sg:phone":"+49 941/98861",
    "sg:postcode":"93051",
    "sg:province":"Bayern",
    "wof:name":"Kopier-eck Fotokopien",
    "wof:placetype":"venue"
},
  "geometry": {"coordinates":[12.0872001648,49.0074424744],"type":"Point"}
}