{
  "type": "Feature",
  "properties": {
    "iso:country":"DE",
    "sg:address":"Keesburgstr. 11",
    "sg:city":"W\u00fcrzburg",
    "sg:phone":"+49 931/797563",
    "sg:postcode":"97074",
    "sg:province":"Bayern",
    "wof:name":"Rapid Biomedizinische Ger\u00e4te Rapid Biomedical Gmbh",
    "wof:placetype":"venue"
},
  "geometry": {"coordinates":[9.9426164627,49.782043457],"type":"Point"}
}