{
  "type": "Feature",
  "properties": {
    "iso:country":"DE",
    "sg:address":"Am Friedhof 1",
    "sg:city":"Lippstadt",
    "sg:phone":"+49 2941/60260",
    "sg:postcode":"59555",
    "sg:province":"Nordrhein-Westfalen",
    "wof:name":"Hans Klingler",
    "wof:placetype":"venue"
},
  "geometry": {"coordinates":[8.354217,51.681065],"type":"Point"}
}