{
  "type": "Feature",
  "properties": {
    "iso:country":"DE",
    "sg:address":"Hauptstr. 56",
    "sg:city":"M\u00fcnsingen",
    "sg:phone":"+49 7381/6333",
    "sg:postcode":"72525",
    "sg:province":"Baden-W\u00fcrttemberg",
    "wof:name":"C. Kuhnle",
    "wof:placetype":"venue"
},
  "geometry": {"coordinates":[9.498986,48.410248],"type":"Point"}
}