{
  "type": "Feature",
  "properties": {
    "iso:country":"DE",
    "sg:address":"Buxacher Str. 10",
    "sg:city":"Memmingen",
    "sg:phone":"+49 8331/71045",
    "sg:postcode":"87700",
    "sg:province":"Bayern",
    "wof:name":"R. Geiger Immobilienmakler",
    "wof:placetype":"venue"
},
  "geometry": {"coordinates":[10.1746587753,47.9858818054],"type":"Point"}
}