{
  "type": "Feature",
  "properties": {
    "iso:country":"DE",
    "sg:address":"M\u00fcggelwerderweg 58",
    "sg:city":"Berlin",
    "sg:phone":"+49 30/6485852",
    "sg:postcode":"12589",
    "sg:province":"Berlin",
    "wof:name":"Torsten Kr\u00e4mer",
    "wof:placetype":"venue"
},
  "geometry": {"coordinates":[13.681703,52.437168],"type":"Point"}
}