{
  "type": "Feature",
  "properties": {
    "iso:country":"DE",
    "sg:address":"Am Behnckenhof 60",
    "sg:city":"L\u00fcbeck",
    "sg:phone":"+49 451/40226",
    "sg:postcode":"23554",
    "sg:province":"Schleswig-Holstein",
    "wof:name":"Alten- Und Pflegeheim Behnckenhof",
    "wof:placetype":"venue"
},
  "geometry": {"coordinates":[10.675975,53.894066],"type":"Point"}
}