{
  "type": "Feature",
  "properties": {
    "iso:country":"DE",
    "sg:address":"Zippelhaus 2",
    "sg:city":"Hamburg",
    "sg:phone":"+49 40/32540250",
    "sg:postcode":"20457",
    "sg:province":"Hamburg",
    "wof:name":"Beteiligungsgesellschaft Ms Scan Oceanic Mbh & Co. Kg",
    "wof:placetype":"venue"
},
  "geometry": {"coordinates":[9.995774,53.546131],"type":"Point"}
}