{
  "type": "Feature",
  "properties": {
    "iso:country":"DE",
    "sg:address":"Bubesheimer Str. 5",
    "sg:city":"Leipheim",
    "sg:postcode":"89340",
    "sg:province":"Bayern",
    "wof:name":"Guntia Air-charter Gmbh",
    "wof:placetype":"venue"
},
  "geometry": {"coordinates":[10.213805,48.445274],"type":"Point"}
}