{
  "type": "Feature",
  "properties": {
    "iso:country":"DE",
    "sg:address":"Prinz-von-Homburg-Str. 19",
    "sg:city":"Neustadt",
    "sg:phone":"+49 33970/13309",
    "sg:postcode":"16845",
    "sg:province":"Brandenburg",
    "wof:name":"F. Leidig",
    "wof:placetype":"venue"
},
  "geometry": {"coordinates":[12.4317245483,52.8606071472],"type":"Point"}
}