{
  "type": "Feature",
  "properties": {
    "iso:country":"DE",
    "sg:address":"Karl-Br\u00fcckner-Str. 1",
    "sg:city":"G\u00f6\u00dfweinstein",
    "sg:phone":"+49 9242/1412",
    "sg:postcode":"91327",
    "sg:province":"Bayern",
    "wof:name":"G. Und H. Zweck",
    "wof:placetype":"venue"
},
  "geometry": {"coordinates":[11.3360834122,49.7696990967],"type":"Point"}
}