{
  "type": "Feature",
  "properties": {
    "iso:country":"DE",
    "sg:address":"Limbecker Platz 4",
    "sg:city":"Essen",
    "sg:postcode":"45127",
    "sg:province":"Nordrhein-Westfalen",
    "wof:name":"Dr. Joseph Sch\u00e4fer Nachf.",
    "wof:placetype":"venue"
},
  "geometry": {"coordinates":[7.007084,51.457886],"type":"Point"}
}