{
  "type": "Feature",
  "properties": {
    "iso:country":"DE",
    "sg:address":"Brunnfeld 2-6",
    "sg:city":"Burglengenfeld",
    "sg:postcode":"93133",
    "sg:province":"Bayern",
    "wof:name":"Activision Beteiligungs Gmbh",
    "wof:placetype":"venue"
},
  "geometry": {"coordinates":[12.022034,49.210991],"type":"Point"}
}