{
  "type": "Feature",
  "properties": {
    "iso:country":"DE",
    "sg:address":"D\u00fcnenweg 3",
    "sg:city":"L\u00fcbeck",
    "sg:phone":"+49 4502/2835",
    "sg:postcode":"23570",
    "sg:province":"Schleswig-Holstein",
    "wof:name":"Strandcamping",
    "wof:placetype":"venue"
},
  "geometry": {"coordinates":[10.88321,53.958511],"type":"Point"}
}