{
  "type": "Feature",
  "properties": {
    "iso:country":"DE",
    "sg:address":"Gr\u00fcnheider Str. 5",
    "sg:city":"Warnitz",
    "sg:phone":"+49 39863/7334",
    "sg:postcode":"17291",
    "sg:province":"Brandenburg",
    "wof:name":"Gastst\u00e4tte Damitz",
    "wof:placetype":"venue"
},
  "geometry": {"coordinates":[13.9239311218,53.1510429382],"type":"Point"}
}