{
  "type": "Feature",
  "properties": {
    "iso:country":"DE",
    "sg:address":"Hanauer Str. 12",
    "sg:city":"Sch\u00f6neck",
    "sg:phone":"+49 6187/910935",
    "sg:postcode":"61137",
    "sg:province":"Hessen",
    "wof:name":"Fritz M\u00fcller",
    "wof:placetype":"venue"
},
  "geometry": {"coordinates":[8.856771,50.199333],"type":"Point"}
}