{
  "type": "Feature",
  "properties": {
    "iso:country":"DE",
    "sg:address":"Barbarastr. 69",
    "sg:city":"K\u00f6ln",
    "sg:phone":"+49 221/7607329",
    "sg:postcode":"50735",
    "sg:province":"Nordrhein-Westfalen",
    "wof:name":"B. Fa\u00dfbender",
    "wof:placetype":"venue"
},
  "geometry": {"coordinates":[6.976742,50.969269],"type":"Point"}
}