{
  "type": "Feature",
  "properties": {
    "iso:country":"DE",
    "sg:address":"Brohltalstr. 152",
    "sg:city":"Burgbrohl",
    "sg:phone":"+49 2636/941220",
    "sg:postcode":"56659",
    "sg:province":"Rheinland-Pfalz",
    "wof:name":"Bilerrahmenkunst Marcus Diede",
    "wof:placetype":"venue"
},
  "geometry": {"coordinates":[7.270232,50.458603],"type":"Point"}
}