{
  "type": "Feature",
  "properties": {
    "iso:country":"DE",
    "sg:address":"B\u00fcrenbrucher Weg 17",
    "sg:city":"Schwerte",
    "sg:phone":"+49 2304/78264",
    "sg:postcode":"58239",
    "sg:province":"Nordrhein-Westfalen",
    "wof:name":"Edeltraud Schwake Heilpraktikerin",
    "wof:placetype":"venue"
},
  "geometry": {"coordinates":[7.5996661186,51.4078063965],"type":"Point"}
}