{
  "type": "Feature",
  "properties": {
    "iso:country":"DE",
    "sg:address":"Lothringer Str. 51",
    "sg:city":"Duisburg",
    "sg:phone":"+49 2066/501717",
    "sg:postcode":"47198",
    "sg:province":"Nordrhein-Westfalen",
    "wof:name":"Wilhelm Kuhlen",
    "wof:placetype":"venue"
},
  "geometry": {"coordinates":[6.70181,51.458046],"type":"Point"}
}