{
  "type": "Feature",
  "properties": {
    "iso:country":"DE",
    "sg:address":"Lindenweg 10",
    "sg:city":"Obermichelbach",
    "sg:postcode":"90587",
    "sg:province":"Bayern",
    "wof:name":"Rangau Wind Verwaltungs Gmbh",
    "wof:placetype":"venue"
},
  "geometry": {"coordinates":[10.9081268311,49.5263252258],"type":"Point"}
}