{
  "type": "Feature",
  "properties": {
    "iso:country":"DE",
    "sg:address":"L\u00f6btauer Str. 67",
    "sg:city":"Dresden",
    "sg:phone":"+49 351/4729959",
    "sg:postcode":"01159",
    "sg:province":"Sachsen",
    "wof:name":"Schwabe & M\u00fcller Gbr",
    "wof:placetype":"venue"
},
  "geometry": {"coordinates":[13.7070407867,51.0457267761],"type":"Point"}
}