{
  "type": "Feature",
  "properties": {
    "iso:country":"DE",
    "sg:address":"Florenz-Maisch-Str. 6",
    "sg:city":"Gaggenau",
    "sg:postcode":"76571",
    "sg:province":"Baden-W\u00fcrttemberg",
    "wof:name":"Dmedia",
    "wof:placetype":"venue"
},
  "geometry": {"coordinates":[8.318487,48.813499],"type":"Point"}
}