{
  "type": "Feature",
  "properties": {
    "iso:country":"DE",
    "sg:address":"Pfitznerstr. 80",
    "sg:city":"Hamburg",
    "sg:postcode":"22761",
    "sg:province":"Hamburg",
    "wof:name":"Clobal Verwaltungs Gmbh",
    "wof:placetype":"venue"
},
  "geometry": {"coordinates":[9.9020347595,53.5647506714],"type":"Point"}
}