{
  "type": "Feature",
  "properties": {
    "iso:country":"DE",
    "sg:address":"Maximilianstr. 35",
    "sg:city":"Muenchen",
    "sg:postcode":"80539",
    "sg:province":"Bayern",
    "wof:name":"Berzconsult.com",
    "wof:placetype":"venue"
},
  "geometry": {"coordinates":[11.58429,48.13842],"type":"Point"}
}