{
  "type": "Feature",
  "properties": {
    "iso:country":"DE",
    "sg:address":"Wilhelm-R\u00f6ntgen-Str.",
    "sg:city":"Offenburg",
    "sg:phone":"+49 781/57341",
    "sg:postcode":"77656",
    "sg:province":"Baden-W\u00fcrttemberg",
    "wof:name":"Hammer Gmbh",
    "wof:placetype":"venue"
},
  "geometry": {"coordinates":[7.9266109467,48.4711380005],"type":"Point"}
}