{
  "type": "Feature",
  "properties": {
    "iso:country":"DE",
    "sg:address":"Industriestr. 3",
    "sg:city":"M\u00fcllheim",
    "sg:phone":"+49 7631/36850",
    "sg:postcode":"79379",
    "sg:province":"Baden-W\u00fcrttemberg",
    "wof:name":"Schott Glaskontor Gmbh",
    "wof:placetype":"venue"
},
  "geometry": {"coordinates":[7.6184220314,47.8321647644],"type":"Point"}
}