{
  "type": "Feature",
  "properties": {
    "iso:country":"DE",
    "sg:address":"Po\u00dfmoorweg 5",
    "sg:city":"Hamburg",
    "sg:phone":"+49 40/27170",
    "sg:postcode":"22301",
    "sg:province":"Hamburg",
    "wof:name":"Archiv Der Jahreszeiten-verlag Gmbh",
    "wof:placetype":"venue"
},
  "geometry": {"coordinates":[10.007276,53.585613],"type":"Point"}
}