{
  "type": "Feature",
  "properties": {
    "iso:country":"DE",
    "sg:address":"Bismarckstr. 18",
    "sg:city":"Marburg",
    "sg:phone":"+49 6421/171717",
    "sg:postcode":"35037",
    "sg:province":"Hessen",
    "wof:name":"Telos Herstellung Und Vertrieb Medizinisch-technischer",
    "wof:placetype":"venue"
},
  "geometry": {"coordinates":[8.763457,50.804379],"type":"Point"}
}