{
  "type": "Feature",
  "properties": {
    "iso:country":"DE",
    "sg:address":"R\u00fchler Dorfstr.",
    "sg:city":"Meppen",
    "sg:phone":"+49 5931/12248",
    "sg:postcode":"49716",
    "sg:province":"Niedersachsen",
    "wof:name":"Gefl\u00fcgel-erzeuger-gemeinschaft R\u00fchle Gmbh & Co. Kg",
    "wof:placetype":"venue"
},
  "geometry": {"coordinates":[7.23056,52.668301],"type":"Point"}
}