{
  "type": "Feature",
  "properties": {
    "iso:country":"DE",
    "sg:address":"Schlappm\u00fchler Pfad 42",
    "sg:city":"Usingen",
    "sg:phone":"+49 4960/8114942",
    "sg:postcode":"61250",
    "sg:province":"Hessen",
    "wof:name":"Sommer Pr\u00c4zisionstechnik",
    "wof:placetype":"venue"
},
  "geometry": {"coordinates":[8.5477256775,50.3372840881],"type":"Point"}
}