{
  "type": "Feature",
  "properties": {
    "iso:country":"DE",
    "sg:address":"Lentersheim 94",
    "sg:city":"Ehingen",
    "sg:phone":"+49 9835/254",
    "sg:postcode":"91725",
    "sg:province":"Bayern",
    "wof:name":"F. Nehmeyer",
    "wof:placetype":"venue"
},
  "geometry": {"coordinates":[10.5851039886,49.0796318054],"type":"Point"}
}