{
  "type": "Feature",
  "properties": {
    "iso:country":"DE",
    "sg:address":"Vilshofener Str. 2",
    "sg:city":"Windorf",
    "sg:phone":"+49 8541/8349",
    "sg:postcode":"94575",
    "sg:province":"Bayern",
    "wof:name":"J. Schober",
    "wof:placetype":"venue"
},
  "geometry": {"coordinates":[13.217754364,48.6269073486],"type":"Point"}
}