{
  "type": "Feature",
  "properties": {
    "iso:country":"DE",
    "sg:address":"Roteb\u00fchlstr. 88",
    "sg:city":"Stuttgart",
    "sg:phone":"+49 711/621313",
    "sg:postcode":"70178",
    "sg:province":"Baden-W\u00fcrttemberg",
    "wof:name":"Dieter Wagner",
    "wof:placetype":"venue"
},
  "geometry": {"coordinates":[9.160117,48.771263],"type":"Point"}
}