{
  "type": "Feature",
  "properties": {
    "iso:country":"DE",
    "sg:address":"Waidhauser Str. 3",
    "sg:city":"Eslarn",
    "sg:phone":"+49 9653/1501",
    "sg:postcode":"92693",
    "sg:province":"Bayern",
    "wof:name":"A. Salomon",
    "wof:placetype":"venue"
},
  "geometry": {"coordinates":[12.52025,49.583187],"type":"Point"}
}