{
  "type": "Feature",
  "properties": {
    "iso:country":"DE",
    "sg:address":"Hauptstr. 11",
    "sg:city":"Seeg",
    "sg:phone":"+49 8364/287",
    "sg:postcode":"87637",
    "sg:province":"Bayern",
    "wof:name":"Caritas Alten-pflegeheim",
    "wof:placetype":"venue"
},
  "geometry": {"coordinates":[10.608957,47.656307],"type":"Point"}
}