{
  "type": "Feature",
  "properties": {
    "iso:country":"DE",
    "sg:address":"Alleestr. 4",
    "sg:city":"Spalt",
    "sg:phone":"+49 9175/224",
    "sg:postcode":"91174",
    "sg:province":"Bayern",
    "wof:name":"Maria Restaurant Caf\u00e8",
    "wof:placetype":"venue"
},
  "geometry": {"coordinates":[10.926295,49.179569],"type":"Point"}
}