{
  "type": "Feature",
  "properties": {
    "iso:country":"DE",
    "sg:address":"Eichenstr. 15",
    "sg:city":"Trebur",
    "sg:phone":"+49 6147/919930",
    "sg:postcode":"65468",
    "sg:province":"Hessen",
    "wof:name":"Sparkassenversicherung L. Sohn",
    "wof:placetype":"venue"
},
  "geometry": {"coordinates":[8.4147291183,49.9259643555],"type":"Point"}
}