{
  "type": "Feature",
  "properties": {
    "iso:country":"DE",
    "sg:address":"Waldemar-Bonsels-Weg 170",
    "sg:city":"Ahrensburg",
    "sg:phone":"+49 4102/55471",
    "sg:postcode":"22926",
    "sg:province":"Schleswig-Holstein",
    "wof:name":"Lefo-institut F\u00fcr Lebensmittel Und Umweltforschung Gmbh",
    "wof:placetype":"venue"
},
  "geometry": {"coordinates":[10.2203531265,53.663936615],"type":"Point"}
}