{
  "type": "Feature",
  "properties": {
    "iso:country":"DE",
    "sg:address":"Bergheim",
    "sg:city":"M\u00f6dingen",
    "sg:phone":"+49 9076/1269",
    "sg:postcode":"89426",
    "sg:province":"Bayern",
    "wof:name":"Gastst\u00e4tte Andreas Hummel",
    "wof:placetype":"venue"
},
  "geometry": {"coordinates":[10.4152193069,48.6192398071],"type":"Point"}
}