{
  "type": "Feature",
  "properties": {
    "iso:country":"DE",
    "sg:address":"Franzstr. 7",
    "sg:city":"Leinefelde",
    "sg:phone":"+49 3605/519950",
    "sg:postcode":"37327",
    "sg:province":"Th\u00fcringen",
    "wof:name":"Heinemann Reinigungstechnik",
    "wof:placetype":"venue"
},
  "geometry": {"coordinates":[10.314416,51.38694],"type":"Point"}
}