{
  "type": "Feature",
  "properties": {
    "iso:country":"DE",
    "sg:address":"Brauerstr. 1",
    "sg:city":"Dortmund",
    "sg:phone":"+49 231/435961",
    "sg:postcode":"44263",
    "sg:province":"Nordrhein-Westfalen",
    "wof:name":"Dipl. Ing. Andreas Schl\u00f6sser",
    "wof:placetype":"venue"
},
  "geometry": {"coordinates":[7.502396,51.490215],"type":"Point"}
}