{
  "type": "Feature",
  "properties": {
    "iso:country":"DE",
    "sg:address":"Kurf\u00fcrstenstr. 214",
    "sg:city":"Berlin",
    "sg:phone":"+49 30/8834900",
    "sg:postcode":"10785",
    "sg:province":"Berlin",
    "wof:name":"Restaurant Churrasco",
    "wof:placetype":"venue"
},
  "geometry": {"coordinates":[13.3582754135,52.5009040833],"type":"Point"}
}