{
  "type": "Feature",
  "properties": {
    "iso:country":"DE",
    "sg:address":"Sprendlinger Landstra\u00dfe 166",
    "sg:city":"Offenbach",
    "sg:phone":"+49 69",
    "sg:postcode":"63069",
    "sg:province":"Hessen",
    "wof:name":"Honda Deutschland Gmbh",
    "wof:placetype":"venue"
},
  "geometry": {"coordinates":[8.7470884323,50.0860671997],"type":"Point"}
}