{
  "type": "Feature",
  "properties": {
    "iso:country":"DE",
    "sg:address":"Hermann-Kussek-Str. 3",
    "sg:city":"Halle",
    "sg:phone":"+49 345/7759165",
    "sg:postcode":"06132",
    "sg:province":"Sachsen-Anhalt",
    "wof:name":"Vereinslokal",
    "wof:placetype":"venue"
},
  "geometry": {"coordinates":[11.9914674759,51.4308815002],"type":"Point"}
}