{
  "type": "Feature",
  "properties": {
    "iso:country":"DE",
    "sg:address":"Bokeler Str. 39",
    "sg:city":"Aschendorf",
    "sg:phone":"+49 4962/214",
    "sg:postcode":"26871",
    "sg:province":"Niedersachsen",
    "wof:name":"Engelbert Kruse Binnenschiffahrtsunternehmen",
    "wof:placetype":"venue"
},
  "geometry": {"coordinates":[7.335564,53.057419],"type":"Point"}
}