{
  "type": "Feature",
  "properties": {
    "iso:country":"DE",
    "sg:address":"Eberhardstr. 49",
    "sg:city":"Remscheid",
    "sg:phone":"+49 2191/49650",
    "sg:postcode":"42853",
    "sg:province":"Nordrhein-Westfalen",
    "wof:name":"Hotel Kerkhoff",
    "wof:placetype":"venue"
},
  "geometry": {"coordinates":[7.1779761314,51.188999176],"type":"Point"}
}