{
  "type": "Feature",
  "properties": {
    "iso:country":"DE",
    "sg:address":"Kirschgarten 6",
    "sg:city":"Hamburg",
    "sg:phone":"+49 40/7302832",
    "sg:postcode":"21031",
    "sg:province":"Hamburg",
    "wof:name":"Dieter Stenner",
    "wof:placetype":"venue"
},
  "geometry": {"coordinates":[10.1970319748,53.5027770996],"type":"Point"}
}