{
  "type": "Feature",
  "properties": {
    "iso:country":"DE",
    "sg:address":"K\u00fcsterstr. 59",
    "sg:city":"Berlin",
    "sg:phone":"+49 30/3342159",
    "sg:postcode":"13599",
    "sg:province":"Berlin",
    "wof:name":"Rudolf Stengert",
    "wof:placetype":"venue"
},
  "geometry": {"coordinates":[13.242839,52.546711],"type":"Point"}
}