{
  "type": "Feature",
  "properties": {
    "iso:country":"DE",
    "sg:address":"Ulmenstr 30",
    "sg:city":"Frankfurt",
    "sg:phone":"+49 69/58990",
    "sg:postcode":"60325",
    "sg:province":"Hessen",
    "wof:name":"Merrill Lynch Investment Managers Kapitalanlagegesellschaft Mbh",
    "wof:placetype":"venue"
},
  "geometry": {"coordinates":[8.68342,50.112041],"type":"Point"}
}