{
  "type": "Feature",
  "properties": {
    "iso:country":"DE",
    "sg:address":"Winkeler Str. 74",
    "sg:city":"Geisenheim",
    "sg:phone":"+49 6722/64922",
    "sg:postcode":"65366",
    "sg:province":"Hessen",
    "wof:name":"Kroos Wickeltechnik Gmbh",
    "wof:placetype":"venue"
},
  "geometry": {"coordinates":[7.9707508087,49.985874176],"type":"Point"}
}