{
  "type": "Feature",
  "properties": {
    "iso:country":"DE",
    "sg:address":"B\u00f6lschestr. 63",
    "sg:city":"Berlin",
    "sg:postcode":"12587",
    "sg:province":"Berlin",
    "wof:name":"Lsr Finanzanalyse Und Verm\u00f6gensverwaltung Gmbh",
    "wof:placetype":"venue"
},
  "geometry": {"coordinates":[13.6254653931,52.4551811218],"type":"Point"}
}