{
  "type": "Feature",
  "properties": {
    "iso:country":"DE",
    "sg:address":"Umgehungsstr. 78b",
    "sg:city":"Mellingen",
    "sg:phone":"+49 36453/8760",
    "sg:postcode":"99441",
    "sg:province":"Th\u00fcringen",
    "wof:name":"Readymix Blank Beton Gmbh & Co. Kg",
    "wof:placetype":"venue"
},
  "geometry": {"coordinates":[11.3993234634,50.9431762695],"type":"Point"}
}