{
  "type": "Feature",
  "properties": {
    "iso:country":"DE",
    "sg:address":"Hintere Gasse 2",
    "sg:city":"Braunsbach",
    "sg:phone":"+49 7906/521",
    "sg:postcode":"74542",
    "sg:province":"Baden-W\u00fcrttemberg",
    "wof:name":"Adler",
    "wof:placetype":"venue"
},
  "geometry": {"coordinates":[9.7867383957,49.169883728],"type":"Point"}
}