{
  "type": "Feature",
  "properties": {
    "iso:country":"DE",
    "sg:address":"Gewerbepark 6",
    "sg:city":"Biessenhofen",
    "sg:phone":"+49 8342/898600",
    "sg:postcode":"87640",
    "sg:province":"Bayern",
    "wof:name":"Bioplasma Vertriebs- Und Verlags- Gmbh",
    "wof:placetype":"venue"
},
  "geometry": {"coordinates":[10.642647,47.809502],"type":"Point"}
}