{
  "type": "Feature",
  "properties": {
    "iso:country":"DE",
    "sg:address":"Landsberger Str. 28",
    "sg:city":"Buchloe",
    "sg:phone":"+49 8241/4520",
    "sg:postcode":"86807",
    "sg:province":"Bayern",
    "wof:name":"Hans Freudling",
    "wof:placetype":"venue"
},
  "geometry": {"coordinates":[10.7340402603,48.0358734131],"type":"Point"}
}