{
  "type": "Feature",
  "properties": {
    "iso:country":"DE",
    "sg:address":"Schwiftinger Str. 2-4",
    "sg:city":"Landsberg",
    "sg:phone":"+49 8191/921316",
    "sg:postcode":"86899",
    "sg:province":"Bayern",
    "wof:name":"Immobilien Neumair Gmbh",
    "wof:placetype":"venue"
},
  "geometry": {"coordinates":[10.8906965256,48.0502967834],"type":"Point"}
}