{
  "type": "Feature",
  "properties": {
    "iso:country":"DE",
    "sg:address":"Carl-Zei\u00df-Str. 49",
    "sg:city":"Erfurt",
    "sg:postcode":"99097",
    "sg:province":"Th\u00fcringen",
    "wof:name":"Steven J\u00e4ger",
    "wof:placetype":"venue"
},
  "geometry": {"coordinates":[11.079555,50.945625],"type":"Point"}
}