{
  "type": "Feature",
  "properties": {
    "iso:country":"DE",
    "sg:address":"Tannenstr. 9",
    "sg:city":"Herforst",
    "sg:phone":"+49 6562/8198",
    "sg:postcode":"54662",
    "sg:province":"Rheinland-Pfalz",
    "wof:name":"Klaus Pitsch",
    "wof:placetype":"venue"
},
  "geometry": {"coordinates":[6.7037291527,49.9445762634],"type":"Point"}
}