{
  "type": "Feature",
  "properties": {
    "iso:country":"DE",
    "sg:address":"Rosenstr. 1",
    "sg:city":"Bad Rappenau",
    "sg:phone":"+49 7264/4911",
    "sg:postcode":"74906",
    "sg:province":"Baden-W\u00fcrttemberg",
    "wof:name":"Adolf H.g. Schaaf Ingenieur",
    "wof:placetype":"venue"
},
  "geometry": {"coordinates":[9.1031589508,49.2361679077],"type":"Point"}
}