{
  "type": "Feature",
  "properties": {
    "iso:country":"DE",
    "sg:address":"Kl\u00fctstr. 8",
    "sg:city":"Hameln",
    "sg:phone":"+49 5151/65040",
    "sg:postcode":"31787",
    "sg:province":"Niedersachsen",
    "wof:name":"Peter E. Hoffmann Heilpraktiker",
    "wof:placetype":"venue"
},
  "geometry": {"coordinates":[9.3467235565,52.1005897522],"type":"Point"}
}