{
  "type": "Feature",
  "properties": {
    "iso:country":"DE",
    "sg:address":"Kellereistr. 1",
    "sg:city":"Neustadt",
    "sg:phone":"+49 6321/2493",
    "sg:postcode":"67433",
    "sg:province":"Rheinland-Pfalz",
    "wof:name":"Dr. Med. Robert Eder",
    "wof:placetype":"venue"
},
  "geometry": {"coordinates":[8.1371011734,49.3536071777],"type":"Point"}
}