{
  "type": "Feature",
  "properties": {
    "iso:country":"DE",
    "sg:address":"Distelstr. 4",
    "sg:city":"Gem\u00fcnden",
    "sg:phone":"+49 9351/3853",
    "sg:postcode":"97737",
    "sg:province":"Bayern",
    "wof:name":"Armin Stichel Versicherungsb\u00fcro Gmbh",
    "wof:placetype":"venue"
},
  "geometry": {"coordinates":[9.6669454575,50.061290741],"type":"Point"}
}