{
  "type": "Feature",
  "properties": {
    "iso:country":"DE",
    "sg:address":"Andergasse 59",
    "sg:city":"Neustadt",
    "sg:phone":"+49 6321/86457",
    "sg:postcode":"67434",
    "sg:province":"Rheinland-Pfalz",
    "wof:name":"Klaus M\u00fcller Weinanbau",
    "wof:placetype":"venue"
},
  "geometry": {"coordinates":[8.1270580292,49.3228416443],"type":"Point"}
}