{
  "type": "Feature",
  "properties": {
    "iso:country":"DE",
    "sg:address":"Bergstr. 3",
    "sg:city":"Feldberg",
    "sg:phone":"+49 39831/20088",
    "sg:postcode":"17258",
    "sg:province":"Mecklenburg-Vorpommern",
    "wof:name":"Monika Niemann",
    "wof:placetype":"venue"
},
  "geometry": {"coordinates":[13.4383249283,53.335231781],"type":"Point"}
}