{
  "type": "Feature",
  "properties": {
    "iso:country":"DE",
    "sg:address":"Birnenallee 4",
    "sg:city":"Lebus",
    "sg:phone":"+49 33604/301",
    "sg:postcode":"15326",
    "sg:province":"Brandenburg",
    "wof:name":"Uwe Gielisch",
    "wof:placetype":"venue"
},
  "geometry": {"coordinates":[14.5356788635,52.4342308044],"type":"Point"}
}