{
  "type": "Feature",
  "properties": {
    "iso:country":"DE",
    "sg:address":"G\u00fcterbahnhofstr. 16-17",
    "sg:city":"Northeim",
    "sg:phone":"+49 5551/62882",
    "sg:postcode":"37154",
    "sg:province":"Niedersachsen",
    "wof:name":"Fitness Club High Energy",
    "wof:placetype":"venue"
},
  "geometry": {"coordinates":[9.9886341095,51.7011184692],"type":"Point"}
}