{
  "type": "Feature",
  "properties": {
    "iso:country":"DE",
    "sg:address":"Reesenberg 35",
    "sg:city":"Kiel",
    "sg:phone":"+49 431/711103",
    "sg:postcode":"24145",
    "sg:province":"Schleswig-Holstein",
    "wof:name":"Hermann Outzen",
    "wof:placetype":"venue"
},
  "geometry": {"coordinates":[10.1396875381,54.2841796875],"type":"Point"}
}