{
  "type": "Feature",
  "properties": {
    "iso:country":"DE",
    "sg:address":"Illerberger Str. 23",
    "sg:city":"Senden",
    "sg:phone":"+49 7309/3546",
    "sg:postcode":"89250",
    "sg:province":"Bayern",
    "wof:name":"E. Kuhn",
    "wof:placetype":"venue"
},
  "geometry": {"coordinates":[10.1005392075,48.3143005371],"type":"Point"}
}