{
  "type": "Feature",
  "properties": {
    "iso:country":"DE",
    "sg:address":"Gewerbestr. 4",
    "sg:city":"Zaisenhausen",
    "sg:postcode":"75059",
    "sg:province":"Baden-W\u00fcrttemberg",
    "wof:name":"Ssw Stainless Steel Ware E. K.",
    "wof:placetype":"venue"
},
  "geometry": {"coordinates":[8.808417,49.103062],"type":"Point"}
}