{
  "type": "Feature",
  "properties": {
    "iso:country":"DE",
    "sg:address":"Woort 3",
    "sg:city":"Halberstadt",
    "sg:phone":"+49 3941/446597",
    "sg:postcode":"38820",
    "sg:province":"Sachsen-Anhalt",
    "wof:name":"Hans-j\u00fcrgen Hilbert",
    "wof:placetype":"venue"
},
  "geometry": {"coordinates":[11.051861,51.899143],"type":"Point"}
}