{
  "type": "Feature",
  "properties": {
    "iso:country":"DE",
    "sg:address":"Rohrbacher Str. 95",
    "sg:city":"Leimen",
    "sg:phone":"+49 6224/7030",
    "sg:postcode":"69181",
    "sg:province":"Baden-W\u00fcrttemberg",
    "wof:name":"Heidelberger Zement Ag",
    "wof:placetype":"venue"
},
  "geometry": {"coordinates":[8.6890907288,49.3574104309],"type":"Point"}
}