{
  "type": "Feature",
  "properties": {
    "iso:country":"DE",
    "sg:address":"Angerweg 2",
    "sg:city":"Stephanskirchen",
    "sg:phone":"+49 8031/71957",
    "sg:postcode":"83071",
    "sg:province":"Bayern",
    "wof:name":"Karl Mair Gmbh & Co. Bautr\u00e4ger Kg",
    "wof:placetype":"venue"
},
  "geometry": {"coordinates":[12.145947,47.856861],"type":"Point"}
}