{
  "type": "Feature",
  "properties": {
    "iso:country":"DE",
    "sg:address":"Kirchenstr. 2",
    "sg:city":"Homburg",
    "sg:phone":"+49 6841/4717",
    "sg:postcode":"66424",
    "sg:province":"Saarland",
    "wof:name":"Akropolis",
    "wof:placetype":"venue"
},
  "geometry": {"coordinates":[7.3389439583,49.321685791],"type":"Point"}
}