{
  "type": "Feature",
  "properties": {
    "iso:country":"DE",
    "sg:address":"Frontenhausener Str. 53",
    "sg:city":"Gangkofen",
    "sg:phone":"+49 8722/8927",
    "sg:postcode":"84140",
    "sg:province":"Bayern",
    "wof:name":"Rudolf Brunnmeier",
    "wof:placetype":"venue"
},
  "geometry": {"coordinates":[12.56042099,48.4408149719],"type":"Point"}
}