{
  "type": "Feature",
  "properties": {
    "iso:country":"DE",
    "sg:address":"Von-Suttner-Str. 10",
    "sg:city":"Wedel",
    "sg:postcode":"22880",
    "sg:province":"Schleswig-Holstein",
    "wof:name":"Pd Pflegeheim- Dienstleistungsges. Mbh",
    "wof:placetype":"venue"
},
  "geometry": {"coordinates":[9.724816,53.592609],"type":"Point"}
}