{
  "type": "Feature",
  "properties": {
    "iso:country":"DE",
    "sg:address":"Scheibe Alsbach Hauptstr.",
    "sg:city":"Steinheid",
    "sg:phone":"+49 36704/722",
    "sg:postcode":"98749",
    "sg:province":"Th\u00fcringen",
    "wof:name":"Volksbank Im Kreis Neuhaus Am, Rennweg E. G.",
    "wof:placetype":"venue"
},
  "geometry": {"coordinates":[11.061973,50.488949],"type":"Point"}
}