{
  "type": "Feature",
  "properties": {
    "iso:country":"DE",
    "sg:address":"Hutstr 15",
    "sg:city":"Lauf",
    "sg:phone":"+49 9123/82632",
    "sg:postcode":"91207",
    "sg:province":"Bayern",
    "wof:name":"Montageteam Eisen",
    "wof:placetype":"venue"
},
  "geometry": {"coordinates":[11.265492,49.548061],"type":"Point"}
}