{
  "type": "Feature",
  "properties": {
    "iso:country":"DE",
    "sg:address":"K\u00f6nigstor 30",
    "sg:city":"Kassel",
    "sg:phone":"+49 561/103950",
    "sg:postcode":"34117",
    "sg:province":"Hessen",
    "wof:name":"Galenus-apotheke",
    "wof:placetype":"venue"
},
  "geometry": {"coordinates":[9.484234,51.313175],"type":"Point"}
}