{
  "type": "Feature",
  "properties": {
    "iso:country":"DE",
    "sg:address":"Golfstr. 25",
    "sg:city":"Frankfurt",
    "sg:phone":"+49 69/6611246",
    "sg:postcode":"60528",
    "sg:province":"Hessen",
    "wof:name":"Object & Parkette Gmbh",
    "wof:placetype":"venue"
},
  "geometry": {"coordinates":[8.6437540054,50.0742340088],"type":"Point"}
}