{
  "type": "Feature",
  "properties": {
    "iso:country":"DE",
    "sg:address":"Lixstr. 13",
    "sg:city":"Heilbronn",
    "sg:phone":"+49 7131/82671",
    "sg:postcode":"74072",
    "sg:province":"Baden-W\u00fcrttemberg",
    "wof:name":"Rolf B\u00f6hner Architekt",
    "wof:placetype":"venue"
},
  "geometry": {"coordinates":[9.224428,49.138123],"type":"Point"}
}