{
  "type": "Feature",
  "properties": {
    "iso:country":"DE",
    "sg:address":"Bismarckstr. 19",
    "sg:city":"Dettenhausen",
    "sg:phone":"+49 7157/65482",
    "sg:postcode":"72135",
    "sg:province":"Baden-W\u00fcrttemberg",
    "wof:name":"K.-h. R\u00f6hm",
    "wof:placetype":"venue"
},
  "geometry": {"coordinates":[9.0962438583,48.6076927185],"type":"Point"}
}