{
  "type": "Feature",
  "properties": {
    "iso:country":"DE",
    "sg:address":"Rudolf-Breitscheid-Str. 24",
    "sg:city":"L\u00fcbtheen",
    "sg:phone":"+49 38855/51361",
    "sg:postcode":"19249",
    "sg:province":"Mecklenburg-Vorpommern",
    "wof:name":"B\u00e4ckerei Stra\u00dfer Gmbh",
    "wof:placetype":"venue"
},
  "geometry": {"coordinates":[11.081183,53.306335],"type":"Point"}
}