{
  "type": "Feature",
  "properties": {
    "iso:country":"DE",
    "sg:address":"Allgau 2",
    "sg:city":"Reichersbeuern",
    "sg:phone":"+49 8041/70514",
    "sg:postcode":"83677",
    "sg:province":"Bayern",
    "wof:name":"Chemcontrol W. Schnitzenbauer Gmbh",
    "wof:placetype":"venue"
},
  "geometry": {"coordinates":[11.6253328323,47.7854347229],"type":"Point"}
}