{
  "type": "Feature",
  "properties": {
    "iso:country":"DE",
    "sg:address":"Wolfenb\u00fctteler Str. 23",
    "sg:city":"Hannover",
    "sg:phone":"+49 511/8483750",
    "sg:postcode":"30519",
    "sg:province":"Niedersachsen",
    "wof:name":"Ergotherapiepraxis Stenzel",
    "wof:placetype":"venue"
},
  "geometry": {"coordinates":[9.768983,52.339844],"type":"Point"}
}