{
  "type": "Feature",
  "properties": {
    "iso:country":"DE",
    "sg:address":"Rathausstr. 13",
    "sg:city":"Arzberg",
    "sg:phone":"+49 9233/1567",
    "sg:postcode":"95659",
    "sg:province":"Bayern",
    "wof:name":"August Neidhardt",
    "wof:placetype":"venue"
},
  "geometry": {"coordinates":[12.1873540878,50.0558395386],"type":"Point"}
}