{
  "type": "Feature",
  "properties": {
    "iso:country":"DE",
    "sg:address":"Wasserstr. 10",
    "sg:city":"Steinfurt",
    "sg:phone":"+49 2551/4094",
    "sg:postcode":"48565",
    "sg:province":"Nordrhein-Westfalen",
    "wof:name":"Vinothek Weingut Johanneshof",
    "wof:placetype":"venue"
},
  "geometry": {"coordinates":[7.3397359848,52.1484985352],"type":"Point"}
}