{
  "type": "Feature",
  "properties": {
    "iso:country":"DE",
    "sg:address":"Kleiner Schlo\u00dfplatz 4",
    "sg:city":"Stuttgart",
    "sg:phone":"+49 711/2265191",
    "sg:postcode":"70173",
    "sg:province":"Baden-W\u00fcrttemberg",
    "wof:name":"Restaurant Ochs-n Willi",
    "wof:placetype":"venue"
},
  "geometry": {"coordinates":[9.17719841,48.7779312134],"type":"Point"}
}