{
  "type": "Feature",
  "properties": {
    "iso:country":"DE",
    "sg:address":"Steinstr. 55",
    "sg:city":"M\u00fcnchen",
    "sg:phone":"+49 89/487789",
    "sg:postcode":"81667",
    "sg:province":"Bayern",
    "wof:name":"Herbert Verweyen",
    "wof:placetype":"venue"
},
  "geometry": {"coordinates":[11.5963039398,48.1312980652],"type":"Point"}
}