{
  "type": "Feature",
  "properties": {
    "iso:country":"DE",
    "sg:address":"Daimlerstr. 55",
    "sg:city":"Leingarten",
    "sg:phone":"+49 7131/90920",
    "sg:postcode":"74211",
    "sg:province":"Baden-W\u00fcrttemberg",
    "wof:name":"Rudolf Rieker Gmbh",
    "wof:placetype":"venue"
},
  "geometry": {"coordinates":[9.132743,49.150288],"type":"Point"}
}