{
  "type": "Feature",
  "properties": {
    "iso:country":"DE",
    "sg:address":"Richard-Wagner-Str. 14",
    "sg:city":"Geiselh\u00f6ring",
    "sg:phone":"+49 9423/421",
    "sg:postcode":"94333",
    "sg:province":"Bayern",
    "wof:name":"Helmut Lederer Architekt",
    "wof:placetype":"venue"
},
  "geometry": {"coordinates":[12.400984,48.82793],"type":"Point"}
}