{
  "type": "Feature",
  "properties": {
    "iso:country":"DE",
    "sg:address":"Hauptstr. 57",
    "sg:city":"Eppstein",
    "sg:phone":"+49 6198/8142",
    "sg:postcode":"65817",
    "sg:province":"Hessen",
    "wof:name":"Biedermann Und Karwarth-klein Ergotherapeutische Praxis",
    "wof:placetype":"venue"
},
  "geometry": {"coordinates":[8.37571,50.153622],"type":"Point"}
}