{
  "type": "Feature",
  "properties": {
    "iso:country":"DE",
    "sg:address":"Schwalbenstr. 7",
    "sg:city":"Haiterbach",
    "sg:phone":"+49 7456/438",
    "sg:postcode":"72221",
    "sg:province":"Baden-W\u00fcrttemberg",
    "wof:name":"Wilhelm Krau\u00df",
    "wof:placetype":"venue"
},
  "geometry": {"coordinates":[8.662437,48.550289],"type":"Point"}
}