{
  "type": "Feature",
  "properties": {
    "iso:country":"DE",
    "sg:address":"Kreuzstr. 91",
    "sg:city":"Weiterstadt",
    "sg:phone":"+49 6150/12347",
    "sg:postcode":"64331",
    "sg:province":"Hessen",
    "wof:name":"Ehmig-fliesen Gmbh",
    "wof:placetype":"venue"
},
  "geometry": {"coordinates":[8.5925312042,49.9072303772],"type":"Point"}
}