{
  "type": "Feature",
  "properties": {
    "iso:country":"DE",
    "sg:address":"Ludwig-Hermann-Str 100",
    "sg:city":"Gersthofen",
    "sg:phone":"+49 821/4790",
    "sg:postcode":"86368",
    "sg:province":"Bayern",
    "wof:name":"Igs Industriepark Gersthofen Service Gmbh & Co Kg",
    "wof:placetype":"venue"
},
  "geometry": {"coordinates":[10.879296,48.444237],"type":"Point"}
}