{
  "type": "Feature",
  "properties": {
    "iso:country":"DE",
    "sg:address":"Meckelfelder Weg 2a",
    "sg:city":"Hamburg",
    "sg:phone":"+49 40/7698210",
    "sg:postcode":"21079",
    "sg:province":"Hamburg",
    "wof:name":"Spang Sonnenschutz Und Bauelemente Gmbh",
    "wof:placetype":"venue"
},
  "geometry": {"coordinates":[9.993259,53.425316],"type":"Point"}
}