{
  "type": "Feature",
  "properties": {
    "iso:country":"DE",
    "sg:address":"M\u00fchlenstr. 17",
    "sg:city":"Steffenberg",
    "sg:phone":"+49 6465/7196",
    "sg:postcode":"35239",
    "sg:province":"Hessen",
    "wof:name":"Johann Beck",
    "wof:placetype":"venue"
},
  "geometry": {"coordinates":[8.4711046219,50.8529167175],"type":"Point"}
}