{
  "type": "Feature",
  "properties": {
    "iso:country":"DE",
    "sg:address":"Auf der Fohrt 1",
    "sg:city":"Olpe",
    "sg:phone":"+49 2761/65570",
    "sg:postcode":"57462",
    "sg:province":"Nordrhein-Westfalen",
    "wof:name":"Koch & Holderberg Ohg",
    "wof:placetype":"venue"
},
  "geometry": {"coordinates":[7.852451,51.02964],"type":"Point"}
}