{
  "type": "Feature",
  "properties": {
    "iso:country":"DE",
    "sg:address":"Siedlerstr. 9",
    "sg:city":"Offenberg",
    "sg:phone":"+49 9906/347",
    "sg:postcode":"94560",
    "sg:province":"Bayern",
    "wof:name":"Josef Lipp",
    "wof:placetype":"venue"
},
  "geometry": {"coordinates":[12.867999,48.861485],"type":"Point"}
}