{
  "type": "Feature",
  "properties": {
    "iso:country":"DE",
    "sg:address":"Moerser Str. 268",
    "sg:city":"Kamp-Lintfort",
    "sg:phone":"+49 2842/13086",
    "sg:postcode":"47475",
    "sg:province":"Nordrhein-Westfalen",
    "wof:name":"Brillen-wiesner Augenoptiker",
    "wof:placetype":"venue"
},
  "geometry": {"coordinates":[6.548999,51.501053],"type":"Point"}
}