{
  "type": "Feature",
  "properties": {
    "iso:country":"DE",
    "sg:city":"K\u00f6ln",
    "sg:phone":"+49 221/2976495",
    "sg:postcode":"51107",
    "sg:province":"Nordrhein-Westfalen",
    "wof:name":"Zacher Umwelt- Und Ingenieurgeophysik, Sondierung Mit Rmt",
    "wof:placetype":"venue"
},
  "geometry": {"coordinates":[7.081296,50.92165],"type":"Point"}
}