{
  "type": "Feature",
  "properties": {
    "iso:country":"DE",
    "sg:address":"Alte Dorfstr. 26",
    "sg:city":"Husum",
    "sg:phone":"+49 5027/671",
    "sg:postcode":"31632",
    "sg:province":"Niedersachsen",
    "wof:name":"Fritz Schm\u00e4deke",
    "wof:placetype":"venue"
},
  "geometry": {"coordinates":[9.2932,52.561932],"type":"Point"}
}