{
  "type": "Feature",
  "properties": {
    "iso:country":"DE",
    "sg:address":"Cottbuser Str. 18",
    "sg:city":"Calau",
    "sg:phone":"+49 3541/801852",
    "sg:postcode":"03205",
    "sg:province":"Brandenburg",
    "wof:name":"Schulze Und Manthey Ingenieure",
    "wof:placetype":"venue"
},
  "geometry": {"coordinates":[13.9511222839,51.7471237183],"type":"Point"}
}