{
  "type": "Feature",
  "properties": {
    "iso:country":"DE",
    "sg:address":"Bahnhofstr. 24",
    "sg:city":"Bad Sobernheim",
    "sg:phone":"+49 6751/3360",
    "sg:postcode":"55566",
    "sg:province":"Rheinland-Pfalz",
    "wof:name":"Friedhelm Haag",
    "wof:placetype":"venue"
},
  "geometry": {"coordinates":[7.6482920647,49.7844390869],"type":"Point"}
}