{
  "type": "Feature",
  "properties": {
    "iso:country":"DE",
    "sg:address":"W\u00fcrzburger Str. 14",
    "sg:city":"Aschaffenburg",
    "sg:phone":"+49 6021/219133",
    "sg:postcode":"63739",
    "sg:province":"Bayern",
    "wof:name":"Eins A Computertechnik Gmbh",
    "wof:placetype":"venue"
},
  "geometry": {"coordinates":[9.1524772644,49.9740104675],"type":"Point"}
}