{
  "type": "Feature",
  "properties": {
    "iso:country":"DE",
    "sg:address":"Friedenstr. 127",
    "sg:city":"Pforzheim",
    "sg:phone":"+49 7231/102883",
    "sg:postcode":"75173",
    "sg:province":"Baden-W\u00fcrttemberg",
    "wof:name":"Rudolf Schupp Inh. Heinz Schupp",
    "wof:placetype":"venue"
},
  "geometry": {"coordinates":[8.68542099,48.8767738342],"type":"Point"}
}