{
  "type": "Feature",
  "properties": {
    "iso:country":"DE",
    "sg:address":"Am Notteflie\u00df 2",
    "sg:city":"K\u00f6nigs Wusterhausen",
    "sg:phone":"+49 3375/292168",
    "sg:postcode":"15711",
    "sg:province":"Brandenburg",
    "wof:name":"Caf\u00e8-restaurant Nr. 2",
    "wof:placetype":"venue"
},
  "geometry": {"coordinates":[13.605418,52.294682],"type":"Point"}
}