{
  "type": "Feature",
  "properties": {
    "iso:country":"DE",
    "sg:address":"G\u00fcterstr. 8",
    "sg:city":"Wilhelmshaven",
    "sg:phone":"+49 4421/74400",
    "sg:postcode":"26389",
    "sg:province":"Niedersachsen",
    "wof:name":"Avcp Parsch Autovermietung",
    "wof:placetype":"venue"
},
  "geometry": {"coordinates":[8.08457,53.52029],"type":"Point"}
}