{
  "type": "Feature",
  "properties": {
    "iso:country":"DE",
    "sg:address":"Sachsenstr. 26",
    "sg:city":"Nattheim",
    "sg:postcode":"89564",
    "sg:province":"Baden-W\u00fcrttemberg",
    "wof:name":"G. Unterer",
    "wof:placetype":"venue"
},
  "geometry": {"coordinates":[10.2532863617,48.7005577087],"type":"Point"}
}