{
  "type": "Feature",
  "properties": {
    "iso:country":"DE",
    "sg:address":"Hauptstr. 60",
    "sg:city":"Markt Erlbach",
    "sg:phone":"+49 9106/891",
    "sg:postcode":"91459",
    "sg:province":"Bayern",
    "wof:name":"J\u00fcrgen Kn\u00f6rr",
    "wof:placetype":"venue"
},
  "geometry": {"coordinates":[10.6492547989,49.4931221008],"type":"Point"}
}