{
  "type": "Feature",
  "properties": {
    "iso:country":"DE",
    "sg:address":"Schwarzwaldstr. 4",
    "sg:city":"Wertheim",
    "sg:phone":"+49 9342/5896",
    "sg:postcode":"97877",
    "sg:province":"Baden-W\u00fcrttemberg",
    "wof:name":"Rolf Weih Mechanische Werkst\u00e4tten",
    "wof:placetype":"venue"
},
  "geometry": {"coordinates":[9.494275,49.785233],"type":"Point"}
}