{
  "type": "Feature",
  "properties": {
    "iso:country":"DE",
    "sg:address":"Gebhardtstr. 13",
    "sg:city":"Solingen",
    "sg:phone":"+49 212/317600",
    "sg:postcode":"42719",
    "sg:province":"Nordrhein-Westfalen",
    "wof:name":"Gerhard Hillebrand",
    "wof:placetype":"venue"
},
  "geometry": {"coordinates":[7.0486578941,51.1844482422],"type":"Point"}
}