{
  "type": "Feature",
  "properties": {
    "iso:country":"DE",
    "sg:address":"Lindenstr 64-66",
    "sg:city":"Ennepetal",
    "sg:phone":"+49 2333/97970",
    "sg:postcode":"58256",
    "sg:province":"Nordrhein-Westfalen",
    "wof:name":"Franz Fahl Gmbh Westf\u00e4lische Metall-locherei",
    "wof:placetype":"venue"
},
  "geometry": {"coordinates":[7.389815,51.303703],"type":"Point"}
}