{
  "type": "Feature",
  "properties": {
    "iso:country":"DE",
    "sg:address":"Wenceslaigasse 30",
    "sg:city":"Wurzen",
    "sg:phone":"+49 3425/817202",
    "sg:postcode":"04808",
    "sg:province":"Sachsen",
    "wof:name":"Gebr. Rogel Gbr",
    "wof:placetype":"venue"
},
  "geometry": {"coordinates":[12.7344350815,51.3676261902],"type":"Point"}
}