{
  "type": "Feature",
  "properties": {
    "iso:country":"DE",
    "sg:address":"Aloysianastr. 30",
    "sg:city":"Bocholt",
    "sg:phone":"+49 2871/43340",
    "sg:postcode":"46399",
    "sg:province":"Nordrhein-Westfalen",
    "wof:name":"H. Reygers & E. Booms",
    "wof:placetype":"venue"
},
  "geometry": {"coordinates":[6.583881,51.857147],"type":"Point"}
}