{
  "type": "Feature",
  "properties": {
    "iso:country":"DE",
    "sg:address":"Berliner Allee 51-53",
    "sg:city":"Langenhagen",
    "sg:phone":"+49 511/786760",
    "sg:postcode":"30855",
    "sg:province":"Niedersachsen",
    "wof:name":"Seidensticker Spedition Gmbh",
    "wof:placetype":"venue"
},
  "geometry": {"coordinates":[9.6890735626,52.4337921143],"type":"Point"}
}