{
  "type": "Feature",
  "properties": {
    "iso:country":"DE",
    "sg:address":"Kagrastr. 1",
    "sg:city":"Abensberg",
    "sg:phone":"+49 9443/2973",
    "sg:postcode":"93326",
    "sg:province":"Bayern",
    "wof:name":"Heigl Vertriebs- Gmbh",
    "wof:placetype":"venue"
},
  "geometry": {"coordinates":[11.8573331833,48.8192901611],"type":"Point"}
}