{
  "type": "Feature",
  "properties": {
    "iso:country":"DE",
    "sg:address":"Sieboldstr. 8",
    "sg:city":"W\u00fcrzburg",
    "sg:phone":"+49 931/77626",
    "sg:postcode":"97072",
    "sg:province":"Bayern",
    "wof:name":"D. Schwind",
    "wof:placetype":"venue"
},
  "geometry": {"coordinates":[9.940408,49.787613],"type":"Point"}
}