{
  "type": "Feature",
  "properties": {
    "iso:country":"DE",
    "sg:address":"Bayerstr. 4",
    "sg:city":"Duisburg",
    "sg:phone":"+49 2151/409452",
    "sg:postcode":"47239",
    "sg:province":"Nordrhein-Westfalen",
    "wof:name":"Paul Hedwig",
    "wof:placetype":"venue"
},
  "geometry": {"coordinates":[6.6527647972,51.3863983154],"type":"Point"}
}