{
  "type": "Feature",
  "properties": {
    "iso:country":"DE",
    "sg:address":"We\u00dflinger Str. 32",
    "sg:city":"Gilching",
    "sg:phone":"+49 8105/9024",
    "sg:postcode":"82205",
    "sg:province":"Bayern",
    "wof:name":"Eisenhandel Gilching Gmbh",
    "wof:placetype":"venue"
},
  "geometry": {"coordinates":[11.283475,48.112499],"type":"Point"}
}