{
  "type": "Feature",
  "properties": {
    "iso:country":"DE",
    "sg:address":"Niddagaustr. 43",
    "sg:city":"Frankfurt",
    "sg:phone":"+49 69/78800108",
    "sg:postcode":"60489",
    "sg:province":"Hessen",
    "wof:name":"E. Jarschel",
    "wof:placetype":"venue"
},
  "geometry": {"coordinates":[8.6134414673,50.1290855408],"type":"Point"}
}