{
  "type": "Feature",
  "properties": {
    "iso:country":"DE",
    "sg:address":"Finkenburg 6",
    "sg:city":"Gerterode",
    "sg:phone":"+49 36076/51416",
    "sg:postcode":"37355",
    "sg:province":"Th\u00fcringen",
    "wof:name":"M. Gunkel",
    "wof:placetype":"venue"
},
  "geometry": {"coordinates":[10.4915237427,51.3799591064],"type":"Point"}
}