{
  "type": "Feature",
  "properties": {
    "iso:country":"DE",
    "sg:address":"Dorotheenstr. 35",
    "sg:city":"Essen",
    "sg:phone":"+49 201/776893",
    "sg:postcode":"45130",
    "sg:province":"Nordrhein-Westfalen",
    "wof:name":"Adolf R\u00f6ser Ingenieur",
    "wof:placetype":"venue"
},
  "geometry": {"coordinates":[7.0089440346,51.4362297058],"type":"Point"}
}