{
  "type": "Feature",
  "properties": {
    "iso:country":"DE",
    "sg:address":"Lange Str. 41",
    "sg:city":"Moringen",
    "sg:phone":"+49 5554/2230",
    "sg:postcode":"37186",
    "sg:province":"Niedersachsen",
    "wof:name":"Rudolf Hilke",
    "wof:placetype":"venue"
},
  "geometry": {"coordinates":[9.871296,51.701797],"type":"Point"}
}