{
  "type": "Feature",
  "properties": {
    "iso:country":"DE",
    "sg:address":"Kirchstr. 8",
    "sg:city":"Stiege",
    "sg:phone":"+49 39459/71444",
    "sg:postcode":"38899",
    "sg:province":"Sachsen-Anhalt",
    "wof:name":"Helmuth Hoppe",
    "wof:placetype":"venue"
},
  "geometry": {"coordinates":[10.892138,51.665813],"type":"Point"}
}