{
  "type": "Feature",
  "properties": {
    "iso:country":"DE",
    "sg:address":"Kastler Str. 13",
    "sg:city":"Amberg",
    "sg:phone":"+49 9621/15252",
    "sg:postcode":"92224",
    "sg:province":"Bayern",
    "wof:name":"Kummert-keller",
    "wof:placetype":"venue"
},
  "geometry": {"coordinates":[11.8463878632,49.4430198669],"type":"Point"}
}