{
  "type": "Feature",
  "properties": {
    "iso:country":"DE",
    "sg:address":"Christoph-von-Gluck-Platz 16",
    "sg:city":"M\u00fcnchen",
    "sg:phone":"+49 89/3594775",
    "sg:postcode":"80807",
    "sg:province":"Bayern",
    "wof:name":"Broadcast Productions Kameramann",
    "wof:placetype":"venue"
},
  "geometry": {"coordinates":[11.5758008957,48.1813163757],"type":"Point"}
}