{
  "type": "Feature",
  "properties": {
    "iso:country":"DE",
    "sg:address":"Blankensteinstr. 66",
    "sg:city":"Stuttgart",
    "sg:phone":"+49 711/843485",
    "sg:postcode":"70437",
    "sg:province":"Baden-W\u00fcrttemberg",
    "wof:name":"Hetzl",
    "wof:placetype":"venue"
},
  "geometry": {"coordinates":[9.196954,48.840065],"type":"Point"}
}