{
  "type": "Feature",
  "properties": {
    "iso:country":"DE",
    "sg:address":"Segelfalterstr. 27",
    "sg:city":"Stuttgart",
    "sg:phone":"+49 711/802957",
    "sg:postcode":"70439",
    "sg:province":"Baden-W\u00fcrttemberg",
    "wof:name":"Karl Scheck Bauunternehmung Gmbh",
    "wof:placetype":"venue"
},
  "geometry": {"coordinates":[9.17034,48.846661],"type":"Point"}
}