{
  "type": "Feature",
  "properties": {
    "iso:country":"DE",
    "sg:address":"In den Folgen 5",
    "sg:city":"Langewiesen",
    "sg:phone":"+49 3677/80400",
    "sg:postcode":"98704",
    "sg:province":"Th\u00fcringen",
    "wof:name":"Idc Ger\u00e4teentwicklungs Gmbh",
    "wof:placetype":"venue"
},
  "geometry": {"coordinates":[10.971422,50.675297],"type":"Point"}
}