{
  "type": "Feature",
  "properties": {
    "iso:country":"DE",
    "sg:address":"Sinntalstra\u00dfe 9-11",
    "sg:city":"Sinntal-Oberzell",
    "sg:postcode":"36391",
    "sg:province":"Hessen",
    "wof:name":"Getraenke Heil",
    "wof:placetype":"venue"
},
  "geometry": {"coordinates":[9.6775922775,50.2992897034],"type":"Point"}
}