{
  "type": "Feature",
  "properties": {
    "iso:country":"DE",
    "sg:address":"Dammstr. 25",
    "sg:city":"Hildesheim",
    "sg:phone":"+49 5121/32839",
    "sg:postcode":"31134",
    "sg:province":"Niedersachsen",
    "wof:name":"Erika Bettin",
    "wof:placetype":"venue"
},
  "geometry": {"coordinates":[9.94127,52.149284],"type":"Point"}
}