{
  "type": "Feature",
  "properties": {
    "iso:country":"DE",
    "sg:address":"Fetscherplatz 2",
    "sg:city":"Dresden",
    "sg:phone":"+49 351/4425603",
    "sg:postcode":"01307",
    "sg:province":"Sachsen",
    "wof:name":"Fetscher-apotheke",
    "wof:placetype":"venue"
},
  "geometry": {"coordinates":[13.770677,51.046795],"type":"Point"}
}