{
  "type": "Feature",
  "properties": {
    "iso:country":"DE",
    "sg:address":"Im Steinb\u00fchl 3",
    "sg:city":"Alth\u00fctte",
    "sg:phone":"+49 7183/41546",
    "sg:postcode":"71566",
    "sg:province":"Baden-W\u00fcrttemberg",
    "wof:name":"Jakob Reining",
    "wof:placetype":"venue"
},
  "geometry": {"coordinates":[9.5692071915,48.9147491455],"type":"Point"}
}