{
  "type": "Feature",
  "properties": {
    "iso:country":"DE",
    "sg:address":"O7",
    "sg:city":"Mannheim",
    "sg:phone":"+49 180 4 262231",
    "sg:postcode":"68161",
    "sg:province":"Baden-W\u00fcrttemberg",
    "wof:name":"Russian-contact",
    "wof:placetype":"venue"
},
  "geometry": {"coordinates":[8.472794,49.484978],"type":"Point"}
}