{
  "type": "Feature",
  "properties": {
    "iso:country":"DE",
    "sg:address":"Oeseder Str. 79",
    "sg:city":"Georgsmarienh\u00fctte",
    "sg:phone":"+49 5401/43931",
    "sg:postcode":"49124",
    "sg:province":"Niedersachsen",
    "wof:name":"Peter Sarrazin",
    "wof:placetype":"venue"
},
  "geometry": {"coordinates":[8.0657348633,52.2056617737],"type":"Point"}
}