{
  "type": "Feature",
  "properties": {
    "iso:country":"DE",
    "sg:address":"Rupertsbergweg 2",
    "sg:city":"St. Georgen",
    "sg:phone":"+49 7724/6207",
    "sg:postcode":"78112",
    "sg:province":"Baden-W\u00fcrttemberg",
    "wof:name":"Stadt Frankfurt",
    "wof:placetype":"venue"
},
  "geometry": {"coordinates":[8.3344087601,48.1317672729],"type":"Point"}
}