{
  "type": "Feature",
  "properties": {
    "iso:country":"DE",
    "sg:address":"M\u00fclheimer Str. 15",
    "sg:city":"Ratingen",
    "sg:phone":"+49 2102/844828",
    "sg:postcode":"40878",
    "sg:province":"Nordrhein-Westfalen",
    "wof:name":"Ratinger Fu\u00df-studio",
    "wof:placetype":"venue"
},
  "geometry": {"coordinates":[6.853652,51.29966],"type":"Point"}
}