{
  "type": "Feature",
  "properties": {
    "iso:country":"DE",
    "sg:address":"Rigaer Str. 57",
    "sg:city":"Berlin",
    "sg:phone":"+49 30/4279223",
    "sg:postcode":"10247",
    "sg:province":"Berlin",
    "wof:name":"Peters Bier-bar",
    "wof:placetype":"venue"
},
  "geometry": {"coordinates":[13.471445,52.515419],"type":"Point"}
}