{
  "type": "Feature",
  "properties": {
    "iso:country":"DE",
    "sg:address":"Auf der Donn 8",
    "sg:city":"Neunkirchen-Seelscheid",
    "sg:phone":"+49 2247/4889",
    "sg:postcode":"53819",
    "sg:province":"Nordrhein-Westfalen",
    "wof:name":"Heim & Haus Gmbh Hans Heck",
    "wof:placetype":"venue"
},
  "geometry": {"coordinates":[7.327458,50.824024],"type":"Point"}
}