{
  "type": "Feature",
  "properties": {
    "iso:country":"DE",
    "sg:address":"Dekan-Schindler-Str. 10",
    "sg:city":"Gersheim",
    "sg:postcode":"66453",
    "sg:province":"Saarland",
    "wof:name":"Kath. \u00d6ffentliche Bibliothek",
    "wof:placetype":"venue"
},
  "geometry": {"coordinates":[7.205547,49.149776],"type":"Point"}
}