{
  "type": "Feature",
  "properties": {
    "iso:country":"DE",
    "sg:address":"Pallaswiesenstr 206",
    "sg:city":"Darmstadt",
    "sg:phone":"+49 6151/860762",
    "sg:postcode":"64293",
    "sg:province":"Hessen",
    "wof:name":"Heckmann & Assmuth Gmbh & Co Kg",
    "wof:placetype":"venue"
},
  "geometry": {"coordinates":[8.6295681,49.8845748901],"type":"Point"}
}