{
  "type": "Feature",
  "properties": {
    "iso:country":"DE",
    "sg:address":"Goethestr. 4",
    "sg:city":"Waldkirch",
    "sg:phone":"+49 7681/40760",
    "sg:postcode":"79183",
    "sg:province":"Baden-W\u00fcrttemberg",
    "wof:name":"Kr\u00e4ter Gmbh",
    "wof:placetype":"venue"
},
  "geometry": {"coordinates":[7.9595332146,48.0915565491],"type":"Point"}
}