{
  "type": "Feature",
  "properties": {
    "iso:country":"DE",
    "sg:address":"Essenweinstrasse 9",
    "sg:city":"Karlsruhe",
    "sg:postcode":"76131",
    "sg:province":"Baden-W\u00fcrttemberg",
    "wof:name":"Night Of The Stormrider - True Metal In Karlsruhe",
    "wof:placetype":"venue"
},
  "geometry": {"coordinates":[8.424667,49.010265],"type":"Point"}
}