{
  "type": "Feature",
  "properties": {
    "iso:country":"DE",
    "sg:address":"Meyenkrebs",
    "sg:city":"Demmin",
    "sg:phone":"+49 3998/362311",
    "sg:postcode":"17109",
    "sg:province":"Mecklenburg-Vorpommern",
    "wof:name":"Baustoffrecycling Demmin Gmbh",
    "wof:placetype":"venue"
},
  "geometry": {"coordinates":[13.041595459,53.9225616455],"type":"Point"}
}