{
  "type": "Feature",
  "properties": {
    "iso:country":"DE",
    "sg:address":"Behringstra\u00dfe 42 - 44",
    "sg:city":"Hamburg",
    "sg:phone":"+49 40/39903603",
    "sg:postcode":"22763",
    "sg:province":"Hamburg",
    "wof:name":"Stadtcafe Ottensen",
    "wof:placetype":"venue"
},
  "geometry": {"coordinates":[9.9198379517,53.5540657043],"type":"Point"}
}