{
  "type": "Feature",
  "properties": {
    "iso:country":"DE",
    "sg:address":"Vaaker Weg 1",
    "sg:city":"Reinhardshagen",
    "sg:phone":"+49 5544/1340",
    "sg:postcode":"34359",
    "sg:province":"Hessen",
    "wof:name":"Willi Gerth",
    "wof:placetype":"venue"
},
  "geometry": {"coordinates":[9.604976,51.491009],"type":"Point"}
}