{
  "type": "Feature",
  "properties": {
    "iso:country":"DE",
    "sg:address":"Neue Str. 4",
    "sg:city":"Dahlenwarsleben",
    "sg:phone":"+49 39202/61852",
    "sg:postcode":"39326",
    "sg:province":"Sachsen-Anhalt",
    "wof:name":"Ronge Trapezblech- Montagen Gmbh",
    "wof:placetype":"venue"
},
  "geometry": {"coordinates":[11.5406017303,52.1951637268],"type":"Point"}
}