{
  "type": "Feature",
  "properties": {
    "iso:country":"DE",
    "sg:address":"Unterer Bongert 10",
    "sg:city":"Nassau",
    "sg:phone":"+49 2604/950196",
    "sg:postcode":"56377",
    "sg:province":"Rheinland-Pfalz",
    "wof:name":"Naturheilpraxis M. Herkert",
    "wof:placetype":"venue"
},
  "geometry": {"coordinates":[7.8002901077,50.3152580261],"type":"Point"}
}