{
  "type": "Feature",
  "properties": {
    "iso:country":"DE",
    "sg:address":"Oelsnitzer Str.",
    "sg:city":"Leipzig",
    "sg:postcode":"04349",
    "sg:province":"Sachsen",
    "wof:name":"Feierabend- Und Pflegeheim",
    "wof:placetype":"venue"
},
  "geometry": {"coordinates":[12.435127,51.37487],"type":"Point"}
}