{
  "type": "Feature",
  "properties": {
    "iso:country":"DE",
    "sg:address":"G\u00fcntherstr. 51",
    "sg:city":"Hamburg",
    "sg:phone":"+49 40/2542802",
    "sg:postcode":"22087",
    "sg:province":"Hamburg",
    "wof:name":"A. Meyer",
    "wof:placetype":"venue"
},
  "geometry": {"coordinates":[10.0300607681,53.564163208],"type":"Point"}
}