{
  "type": "Feature",
  "properties": {
    "iso:country":"DE",
    "sg:address":"Am Kapellenberg 8",
    "sg:city":"Oberwesel",
    "sg:phone":"+49 6744/8365",
    "sg:postcode":"55430",
    "sg:province":"Rheinland-Pfalz",
    "wof:name":"H.-e. Mehren",
    "wof:placetype":"venue"
},
  "geometry": {"coordinates":[7.7121782303,50.0957374573],"type":"Point"}
}