{
  "type": "Feature",
  "properties": {
    "iso:country":"DE",
    "sg:address":"Arzheimer Str. 24",
    "sg:city":"Ilbesheim",
    "sg:postcode":"76831",
    "sg:province":"Rheinland-Pfalz",
    "wof:name":"Weingut Reinhard Schmitt",
    "wof:placetype":"venue"
},
  "geometry": {"coordinates":[8.0543031693,49.1843986511],"type":"Point"}
}