{
  "type": "Feature",
  "properties": {
    "iso:country":"DE",
    "sg:address":"Linzer Str. 17",
    "sg:city":"Bad Honnef",
    "sg:phone":"+49 2224/93760",
    "sg:postcode":"53604",
    "sg:province":"Nordrhein-Westfalen",
    "wof:name":"Schwager Und Kromik Rechtsanw\u00e4lte",
    "wof:placetype":"venue"
},
  "geometry": {"coordinates":[7.2283430099,50.6427879333],"type":"Point"}
}