{
  "type": "Feature",
  "properties": {
    "iso:country":"DE",
    "sg:address":"R\u00f6merweg 7",
    "sg:city":"Inzell",
    "sg:phone":"+49 8665/7348",
    "sg:postcode":"83334",
    "sg:province":"Bayern",
    "wof:name":"K. Lindner",
    "wof:placetype":"venue"
},
  "geometry": {"coordinates":[12.7514896393,47.7564620972],"type":"Point"}
}