{
  "type": "Feature",
  "properties": {
    "iso:country":"DE",
    "sg:address":"Johannes-Albers-Str. 45",
    "sg:city":"K\u00f6ln",
    "sg:phone":"+49 221/798601",
    "sg:postcode":"50767",
    "sg:province":"Nordrhein-Westfalen",
    "wof:name":"Matthias Fischer",
    "wof:placetype":"venue"
},
  "geometry": {"coordinates":[6.8940138817,51.0081863403],"type":"Point"}
}