{
  "type": "Feature",
  "properties": {
    "iso:country":"DE",
    "sg:address":"Grillparzerweg 24",
    "sg:city":"Lutherstadt Wittenberg",
    "sg:phone":"+49 3491/883254",
    "sg:postcode":"06886",
    "sg:province":"Sachsen-Anhalt",
    "wof:name":"J\u00fcrgen Wondrak",
    "wof:placetype":"venue"
},
  "geometry": {"coordinates":[12.6644792557,51.8858451843],"type":"Point"}
}