{
  "type": "Feature",
  "properties": {
    "iso:country":"DE",
    "sg:address":"Eichh\u00f6rnchensteg 23",
    "sg:city":"Hannover",
    "sg:phone":"+49 511/65484",
    "sg:postcode":"30657",
    "sg:province":"Niedersachsen",
    "wof:name":"J\u00fcrgen Nedde Immobilienmakler",
    "wof:placetype":"venue"
},
  "geometry": {"coordinates":[9.7982206345,52.4272537231],"type":"Point"}
}