{
  "type": "Feature",
  "properties": {
    "iso:country":"DE",
    "sg:address":"Emmelner Str. 96",
    "sg:city":"Haren",
    "sg:phone":"+49 5932/2719",
    "sg:postcode":"49733",
    "sg:province":"Niedersachsen",
    "wof:name":"Karl Ricke",
    "wof:placetype":"venue"
},
  "geometry": {"coordinates":[7.2449297905,52.7900390625],"type":"Point"}
}