{
  "type": "Feature",
  "properties": {
    "iso:country":"DE",
    "sg:address":"Dammkarstr. 5",
    "sg:city":"Mittenwald",
    "sg:phone":"+49 8823/8247",
    "sg:postcode":"82481",
    "sg:province":"Bayern",
    "wof:name":"G\u00e4stehaus Sonnenheim",
    "wof:placetype":"venue"
},
  "geometry": {"coordinates":[11.2637662888,47.4418754578],"type":"Point"}
}