{
  "type": "Feature",
  "properties": {
    "iso:country":"DE",
    "sg:address":"Knivsbergring 25",
    "sg:city":"Pl\u00f6n",
    "sg:phone":"+49 4522/2052",
    "sg:postcode":"24306",
    "sg:province":"Schleswig-Holstein",
    "wof:name":"Ingrid Willutzki",
    "wof:placetype":"venue"
},
  "geometry": {"coordinates":[10.4061851501,54.16456604],"type":"Point"}
}