{
  "type": "Feature",
  "properties": {
    "iso:country":"DE",
    "sg:address":"Langenhorner Chaussee 42",
    "sg:city":"Hamburg",
    "sg:postcode":"22335",
    "sg:province":"Hamburg",
    "wof:name":"Hsmc Hanseatische System Und Management Consulting Gmbh",
    "wof:placetype":"venue"
},
  "geometry": {"coordinates":[10.0165100098,53.6345214844],"type":"Point"}
}