{
  "type": "Feature",
  "properties": {
    "iso:country":"DE",
    "sg:address":"Burgsdorfer Weg 1",
    "sg:city":"Dederstedt",
    "sg:phone":"+49 34773/20396",
    "sg:postcode":"06295",
    "sg:province":"Sachsen-Anhalt",
    "wof:name":"Helmut G\u00e4bler",
    "wof:placetype":"venue"
},
  "geometry": {"coordinates":[11.6856422424,51.5453414917],"type":"Point"}
}