{
  "type": "Feature",
  "properties": {
    "iso:country":"DE",
    "sg:address":"Lingscheiderweg 10",
    "sg:city":"Meschede",
    "sg:phone":"+49 291/51577",
    "sg:postcode":"59872",
    "sg:province":"Nordrhein-Westfalen",
    "wof:name":"Schr\u00f6der-hedwig Gmbh",
    "wof:placetype":"venue"
},
  "geometry": {"coordinates":[8.3282232285,51.3663444519],"type":"Point"}
}