{
  "type": "Feature",
  "properties": {
    "iso:country":"DE",
    "sg:city":"Ahaus",
    "sg:phone":"+49 4925/613026",
    "sg:postcode":"48683",
    "sg:province":"Nordrhein-Westfalen",
    "wof:name":"Westdeutsche Landesbank",
    "wof:placetype":"venue"
},
  "geometry": {"coordinates":[7.007952,52.072693],"type":"Point"}
}