{
  "type": "Feature",
  "properties": {
    "iso:country":"DE",
    "sg:address":"M\u00fchlenredder 43",
    "sg:city":"Reinbek",
    "sg:phone":"+49 40/7223251",
    "sg:postcode":"21465",
    "sg:province":"Schleswig-Holstein",
    "wof:name":"Tennissportanlage",
    "wof:placetype":"venue"
},
  "geometry": {"coordinates":[10.2434206009,53.5178375244],"type":"Point"}
}