{
  "type": "Feature",
  "properties": {
    "iso:country":"DE",
    "sg:address":"Karlstr. 26",
    "sg:city":"Wuppertal",
    "sg:phone":"+49 202/4938472",
    "sg:postcode":"42105",
    "sg:province":"Nordrhein-Westfalen",
    "wof:name":"F. Arik",
    "wof:placetype":"venue"
},
  "geometry": {"coordinates":[7.1454510689,51.2610664368],"type":"Point"}
}