{
  "type": "Feature",
  "properties": {
    "iso:country":"DE",
    "sg:address":"Breitscheidstr. 3C",
    "sg:city":"Beeskow",
    "sg:phone":"+49 3366/23826",
    "sg:postcode":"15848",
    "sg:province":"Brandenburg",
    "wof:name":"J. Rathke Architekt",
    "wof:placetype":"venue"
},
  "geometry": {"coordinates":[14.243413,52.168919],"type":"Point"}
}