{
  "type": "Feature",
  "properties": {
    "iso:country":"DE",
    "sg:address":"Auf dem Zetel 18",
    "sg:city":"Bar\u00dfel",
    "sg:phone":"+49 4499/7393",
    "sg:postcode":"26676",
    "sg:province":"Niedersachsen",
    "wof:name":"Pizzeria Chateau",
    "wof:placetype":"venue"
},
  "geometry": {"coordinates":[7.7411170006,53.1699066162],"type":"Point"}
}