{
  "type": "Feature",
  "properties": {
    "iso:country":"DE",
    "sg:address":"Brunnengasse 4",
    "sg:city":"G\u00f6ttingen",
    "sg:postcode":"37077",
    "sg:province":"Niedersachsen",
    "wof:name":"Fair Prax Abrechnungsges. F\u00fcr Leistungserbringer Im",
    "wof:placetype":"venue"
},
  "geometry": {"coordinates":[9.9327726364,51.5606803894],"type":"Point"}
}