{
  "type": "Feature",
  "properties": {
    "iso:country":"DE",
    "sg:address":"Zur Polterkuhle 25",
    "sg:city":"Oelde",
    "sg:phone":"+49 2522/4427",
    "sg:postcode":"59302",
    "sg:province":"Nordrhein-Westfalen",
    "wof:name":"Konrad B\u00e4nisch",
    "wof:placetype":"venue"
},
  "geometry": {"coordinates":[8.1347293854,51.815952301],"type":"Point"}
}