{
  "type": "Feature",
  "properties": {
    "iso:country":"DE",
    "sg:address":"Schk\u00f6lener Weg 31",
    "sg:city":"L\u00fctzen",
    "sg:phone":"+49 34444/20335",
    "sg:postcode":"06686",
    "sg:province":"Sachsen-Anhalt",
    "wof:name":"Dr. Horst Kannenberg Tierarzt",
    "wof:placetype":"venue"
},
  "geometry": {"coordinates":[12.149394989,51.2593002319],"type":"Point"}
}