{
  "type": "Feature",
  "properties": {
    "iso:country":"DE",
    "sg:address":"Deutschenbaurstr. 2",
    "sg:city":"Augsburg",
    "sg:phone":"+49 821/523522",
    "sg:postcode":"86157",
    "sg:province":"Bayern",
    "wof:name":"Juke Box",
    "wof:placetype":"venue"
},
  "geometry": {"coordinates":[10.8642034531,48.3651428223],"type":"Point"}
}