{
  "type": "Feature",
  "properties": {
    "iso:country":"DE",
    "sg:address":"Siemensstr. 5 PF 001150",
    "sg:city":"Hainburg",
    "sg:phone":"+49 6182/9532600",
    "sg:postcode":"63512",
    "sg:province":"Hessen",
    "wof:name":"Pharma Test Apparatebau Gmbh",
    "wof:placetype":"venue"
},
  "geometry": {"coordinates":[8.9410400391,50.0825653076],"type":"Point"}
}