{
  "type": "Feature",
  "properties": {
    "iso:country":"DE",
    "sg:address":"Hauptstr. 27",
    "sg:city":"Oberpleichfeld",
    "sg:phone":"+49 9367/2790",
    "sg:postcode":"97241",
    "sg:province":"Bayern",
    "wof:name":"Alfred Keller",
    "wof:placetype":"venue"
},
  "geometry": {"coordinates":[10.086182,49.879192],"type":"Point"}
}