{
  "type": "Feature",
  "properties": {
    "iso:country":"DE",
    "sg:address":"Stra\u00dfe der Einheit 142-148",
    "sg:city":"Falkensee",
    "sg:postcode":"14612",
    "sg:province":"Brandenburg",
    "wof:name":"Herlitz Papierverarbeitungs Gmbh",
    "wof:placetype":"venue"
},
  "geometry": {"coordinates":[13.1124095917,52.5523147583],"type":"Point"}
}