{
  "type": "Feature",
  "properties": {
    "iso:country":"DE",
    "sg:address":"Ludwig-Schriever-Str. 1",
    "sg:city":"L\u00fcnne",
    "sg:phone":"+49 5906/564",
    "sg:postcode":"48480",
    "sg:province":"Niedersachsen",
    "wof:name":"Josef Unkenholz",
    "wof:placetype":"venue"
},
  "geometry": {"coordinates":[7.42415,52.431122],"type":"Point"}
}