{
  "type": "Feature",
  "properties": {
    "iso:country":"DE",
    "sg:address":"Germaniastr. 134",
    "sg:city":"Berlin",
    "sg:phone":"+49 30/7510016",
    "sg:postcode":"12099",
    "sg:province":"Berlin",
    "wof:name":"China Restaurant Lai Lai",
    "wof:placetype":"venue"
},
  "geometry": {"coordinates":[13.3998403549,52.4644775391],"type":"Point"}
}