{
  "type": "Feature",
  "properties": {
    "iso:country":"DE",
    "sg:address":"Arthur-Hoffmann-Strasse 87",
    "sg:city":"Leipzig",
    "sg:phone":"+49 341/3067669",
    "sg:postcode":"04275",
    "sg:province":"Sachsen",
    "wof:name":"Swen Quosdorf",
    "wof:placetype":"venue"
},
  "geometry": {"coordinates":[12.378749,51.322269],"type":"Point"}
}