{
  "type": "Feature",
  "properties": {
    "iso:country":"DE",
    "sg:address":"Hindenburgstr. 7",
    "sg:city":"Siegen",
    "sg:phone":"+49 271/20872",
    "sg:postcode":"57072",
    "sg:province":"Nordrhein-Westfalen",
    "wof:name":"K\u00f6nig-city",
    "wof:placetype":"venue"
},
  "geometry": {"coordinates":[8.0192899704,50.8765182495],"type":"Point"}
}