{
  "type": "Feature",
  "properties": {
    "iso:country":"DE",
    "sg:address":"Marktstr. 40",
    "sg:city":"Kaiserslautern",
    "sg:phone":"+49 631/63471",
    "sg:postcode":"67655",
    "sg:province":"Rheinland-Pfalz",
    "wof:name":"Heinz Kakuk Und Wolf-dieter Schierstein",
    "wof:placetype":"venue"
},
  "geometry": {"coordinates":[7.7698287964,49.4439086914],"type":"Point"}
}