{
  "type": "Feature",
  "properties": {
    "iso:country":"DE",
    "sg:address":"Borker Str. 68",
    "sg:city":"L\u00fcnen",
    "sg:phone":"+49 2306/50477",
    "sg:postcode":"44534",
    "sg:province":"Nordrhein-Westfalen",
    "wof:name":"Flegel Bauunternehmung Gmbh",
    "wof:placetype":"venue"
},
  "geometry": {"coordinates":[7.516573,51.621662],"type":"Point"}
}