{
  "type": "Feature",
  "properties": {
    "iso:country":"DE",
    "sg:address":"Im Br\u00fcckenfeld 7",
    "sg:city":"Oftersheim",
    "sg:phone":"+49 6202/52116",
    "sg:postcode":"68723",
    "sg:province":"Baden-W\u00fcrttemberg",
    "wof:name":"Ev. Pfarramt Ii",
    "wof:placetype":"venue"
},
  "geometry": {"coordinates":[8.5890798569,49.3721046448],"type":"Point"}
}