{
  "type": "Feature",
  "properties": {
    "iso:country":"DE",
    "sg:address":"Okenstr. 35",
    "sg:city":"N\u00fcrnberg",
    "sg:phone":"+49 911/427193",
    "sg:postcode":"90443",
    "sg:province":"Bayern",
    "wof:name":"Comet-markt",
    "wof:placetype":"venue"
},
  "geometry": {"coordinates":[11.0705862045,49.4379730225],"type":"Point"}
}