{
  "type": "Feature",
  "properties": {
    "iso:country":"DE",
    "sg:address":"Kin\u00dffeldstr. 36",
    "sg:city":"Essen",
    "sg:postcode":"45326",
    "sg:province":"Nordrhein-Westfalen",
    "wof:name":"Uh Softwarevertrieb Gmbh",
    "wof:placetype":"venue"
},
  "geometry": {"coordinates":[7.016161,51.491684],"type":"Point"}
}