{
  "type": "Feature",
  "properties": {
    "iso:country":"DE",
    "sg:address":"Ringstr. 11",
    "sg:city":"Ellingen",
    "sg:phone":"+49 9141/3051",
    "sg:postcode":"91792",
    "sg:province":"Bayern",
    "wof:name":"G\u00d6hs Gmbh",
    "wof:placetype":"venue"
},
  "geometry": {"coordinates":[10.961999,49.062599],"type":"Point"}
}