{
  "type": "Feature",
  "properties": {
    "iso:country":"DE",
    "sg:address":"Schlossallee 3",
    "sg:city":"Northeim",
    "sg:phone":"+49 4955/5199110",
    "sg:postcode":"37154",
    "sg:province":"Niedersachsen",
    "wof:name":"Rebel Kunststoffe Gmbh",
    "wof:placetype":"venue"
},
  "geometry": {"coordinates":[10.0067996979,51.7066497803],"type":"Point"}
}