{
  "type": "Feature",
  "properties": {
    "iso:country":"DE",
    "sg:address":"Killingerstr. 37",
    "sg:city":"Obersulm",
    "sg:phone":"+49 7130/453303",
    "sg:postcode":"74182",
    "sg:province":"Baden-W\u00fcrttemberg",
    "wof:name":"Sammet",
    "wof:placetype":"venue"
},
  "geometry": {"coordinates":[9.4104232788,49.1387786865],"type":"Point"}
}