{
  "type": "Feature",
  "properties": {
    "iso:country":"DE",
    "sg:address":"Miesweg 1",
    "sg:city":"Oberaula",
    "sg:phone":"+49 6628/8661",
    "sg:postcode":"36280",
    "sg:province":"Hessen",
    "wof:name":"Fritz Ziegler",
    "wof:placetype":"venue"
},
  "geometry": {"coordinates":[9.47831,50.85981],"type":"Point"}
}