{
  "type": "Feature",
  "properties": {
    "iso:country":"DE",
    "sg:address":"Fichtenstr. 3",
    "sg:city":"Deisenhofen",
    "sg:phone":"+49 89/7472250",
    "sg:postcode":"82041",
    "sg:province":"Bayern",
    "wof:name":"Zur\u00fcck Zur Natur Gmbh & Co. Kg",
    "wof:placetype":"venue"
},
  "geometry": {"coordinates":[11.5889425278,48.01404953],"type":"Point"}
}