{
  "type": "Feature",
  "properties": {
    "iso:country":"DE",
    "sg:address":"Kruppstr. 105",
    "sg:city":"Frankfurt",
    "sg:postcode":"60388",
    "sg:province":"Hessen",
    "wof:name":"Max Kammerer Gmbh",
    "wof:placetype":"venue"
},
  "geometry": {"coordinates":[8.7438840866,50.1395149231],"type":"Point"}
}