{
  "type": "Feature",
  "properties": {
    "iso:country":"DE",
    "sg:address":"Paffrather Str. 318",
    "sg:city":"Bergisch Gladbach",
    "sg:phone":"+49 2202/54181",
    "sg:postcode":"51469",
    "sg:province":"Nordrhein-Westfalen",
    "wof:name":"Grill Firuze Ii",
    "wof:placetype":"venue"
},
  "geometry": {"coordinates":[7.1014199257,50.9986915588],"type":"Point"}
}