{
  "type": "Feature",
  "properties": {
    "iso:country":"DE",
    "sg:address":"Schumannstr. 21",
    "sg:city":"Meckenheim",
    "sg:phone":"+49 2225/14493",
    "sg:postcode":"53340",
    "sg:province":"Nordrhein-Westfalen",
    "wof:name":"Fritsche Augenoptik",
    "wof:placetype":"venue"
},
  "geometry": {"coordinates":[7.042591095,50.6262207031],"type":"Point"}
}