{
  "type": "Feature",
  "properties": {
    "iso:country":"DE",
    "sg:address":"Bussardweg 28b",
    "sg:city":"Ihlow",
    "sg:phone":"+49 4928/915770",
    "sg:postcode":"26632",
    "sg:province":"Niedersachsen",
    "wof:name":"Thoyan-world",
    "wof:placetype":"venue"
},
  "geometry": {"coordinates":[7.371901,53.412113],"type":"Point"}
}