{
  "type": "Feature",
  "properties": {
    "iso:country":"DE",
    "sg:address":"Batteriestr. 14",
    "sg:city":"Flensburg",
    "sg:phone":"+49 4946/1493030",
    "sg:postcode":"24939",
    "sg:province":"Schleswig-Holstein",
    "wof:name":"Flensburger Fleisch-kontor Gmbh & Co. Kg",
    "wof:placetype":"venue"
},
  "geometry": {"coordinates":[9.4270124435,54.8033905029],"type":"Point"}
}