{
  "type": "Feature",
  "properties": {
    "iso:country":"DE",
    "sg:address":"Grundstr. 5",
    "sg:city":"Karlsruhe",
    "sg:phone":"+49 721/491424",
    "sg:postcode":"76228",
    "sg:province":"Baden-W\u00fcrttemberg",
    "wof:name":"G\u00fcnter Huber Hausbau Gmbh & Co. Kg",
    "wof:placetype":"venue"
},
  "geometry": {"coordinates":[8.4504451752,48.9742736816],"type":"Point"}
}