{
  "type": "Feature",
  "properties": {
    "iso:country":"DE",
    "sg:address":"Bernhard-Winter-Str. 42",
    "sg:city":"Oldenburg",
    "sg:phone":"+49 441/41153",
    "sg:postcode":"26133",
    "sg:province":"Niedersachsen",
    "wof:name":"Prof. U. Reuss Tierarzt",
    "wof:placetype":"venue"
},
  "geometry": {"coordinates":[8.2269001007,53.0966911316],"type":"Point"}
}