{
  "type": "Feature",
  "properties": {
    "iso:country":"DE",
    "sg:address":"Stuttgarter Str. 146",
    "sg:city":"B\u00f6blingen",
    "sg:postcode":"71032",
    "sg:province":"Baden-W\u00fcrttemberg",
    "wof:name":"K & N Handels Gmbh",
    "wof:placetype":"venue"
},
  "geometry": {"coordinates":[9.026762,48.69305],"type":"Point"}
}