{
  "type": "Feature",
  "properties": {
    "iso:country":"DE",
    "sg:address":"Alleestr. 56",
    "sg:city":"Hamm",
    "sg:phone":"+49 2381/950440",
    "sg:postcode":"59065",
    "sg:province":"Nordrhein-Westfalen",
    "wof:name":"F. Fischer",
    "wof:placetype":"venue"
},
  "geometry": {"coordinates":[7.81808,51.672081],"type":"Point"}
}