{
  "type": "Feature",
  "properties": {
    "iso:country":"DE",
    "sg:address":"Gro\u00dfe Johannisgasse 3",
    "sg:city":"Coburg",
    "sg:phone":"+49 9561/90415",
    "sg:postcode":"96450",
    "sg:province":"Bayern",
    "wof:name":"Carola Burkhardt",
    "wof:placetype":"venue"
},
  "geometry": {"coordinates":[10.965971,50.259254],"type":"Point"}
}