{
  "type": "Feature",
  "properties": {
    "iso:country":"DE",
    "sg:address":"M\u00fcnsterstr. 9",
    "sg:city":"Versmold",
    "sg:phone":"+49 5423/42525",
    "sg:postcode":"33775",
    "sg:province":"Nordrhein-Westfalen",
    "wof:name":"Bettina S.",
    "wof:placetype":"venue"
},
  "geometry": {"coordinates":[8.154315,52.039734],"type":"Point"}
}