{
  "type": "Feature",
  "properties": {
    "iso:country":"DE",
    "sg:address":"Ratskellerstr. 7",
    "sg:city":"Achern",
    "sg:phone":"+49 7841/290990",
    "sg:postcode":"77855",
    "sg:province":"Baden-W\u00fcrttemberg",
    "wof:name":"Acrobat Technische Personalleasing Gmbh",
    "wof:placetype":"venue"
},
  "geometry": {"coordinates":[8.0725402832,48.6280212402],"type":"Point"}
}