{
  "type": "Feature",
  "properties": {
    "iso:country":"DE",
    "sg:address":"Herzbergstr 33-34",
    "sg:city":"Berlin",
    "sg:phone":"+49 30/5577330",
    "sg:postcode":"10365",
    "sg:province":"Berlin",
    "wof:name":"Otto W\u00f6ltinger Tief- U. Rohrleitungsbau Gmbh & Co Kg",
    "wof:placetype":"venue"
},
  "geometry": {"coordinates":[13.4904556274,52.5263977051],"type":"Point"}
}