{
  "type": "Feature",
  "properties": {
    "iso:country":"DE",
    "sg:address":"Stra\u00dfe der Jugend 4",
    "sg:city":"Delitzsch",
    "sg:phone":"+49 34202/58598",
    "sg:postcode":"04509",
    "sg:province":"Sachsen",
    "wof:name":"Extra",
    "wof:placetype":"venue"
},
  "geometry": {"coordinates":[12.3275279999,51.5368156433],"type":"Point"}
}