{
  "type": "Feature",
  "properties": {
    "iso:country":"DE",
    "sg:address":"Gerhardstr. 11",
    "sg:city":"Elmshorn",
    "sg:phone":"+49 4121/3853",
    "sg:postcode":"25335",
    "sg:province":"Schleswig-Holstein",
    "wof:name":"Peter Mehl",
    "wof:placetype":"venue"
},
  "geometry": {"coordinates":[9.651982,53.758705],"type":"Point"}
}