{
  "type": "Feature",
  "properties": {
    "iso:country":"DE",
    "sg:address":"Mittelweg 115 b",
    "sg:city":"Hamburg",
    "sg:phone":"+49 40/2385300",
    "sg:postcode":"20149",
    "sg:province":"Hamburg",
    "wof:name":"Promotions Unlimited Gmbh",
    "wof:placetype":"venue"
},
  "geometry": {"coordinates":[9.993803,53.57349],"type":"Point"}
}