{
  "type": "Feature",
  "properties": {
    "iso:country":"DE",
    "sg:address":"Schulstr. 12",
    "sg:city":"Stammham",
    "sg:phone":"+49 8405/461",
    "sg:postcode":"85134",
    "sg:province":"Bayern",
    "wof:name":"Anton Haas",
    "wof:placetype":"venue"
},
  "geometry": {"coordinates":[11.4532899857,48.8588905334],"type":"Point"}
}