{
  "type": "Feature",
  "properties": {
    "iso:country":"DE",
    "sg:address":"K\u00f6lner Str. 57",
    "sg:city":"Bergheim",
    "sg:phone":"+49 2271/41149",
    "sg:postcode":"50126",
    "sg:province":"Nordrhein-Westfalen",
    "wof:name":"Engelbert Bodewig",
    "wof:placetype":"venue"
},
  "geometry": {"coordinates":[6.64899683,50.951751709],"type":"Point"}
}