{
  "type": "Feature",
  "properties": {
    "iso:country":"DE",
    "sg:address":"Gelnh\u00e4user Str. 1a",
    "sg:city":"Langenselbold",
    "sg:phone":"+49 6184/3323",
    "sg:postcode":"63505",
    "sg:province":"Hessen",
    "wof:name":"Idea Die Gr\u00fcne Drogerie Gmbh",
    "wof:placetype":"venue"
},
  "geometry": {"coordinates":[9.040952,50.175926],"type":"Point"}
}