{
  "type": "Feature",
  "properties": {
    "iso:country":"DE",
    "sg:address":"Am Setzen 12",
    "sg:city":"Gochsheim",
    "sg:phone":"+49 9721/61446",
    "sg:postcode":"97469",
    "sg:province":"Bayern",
    "wof:name":"Gerd Reichert",
    "wof:placetype":"venue"
},
  "geometry": {"coordinates":[10.2872371674,50.0253562927],"type":"Point"}
}