{
  "type": "Feature",
  "properties": {
    "iso:country":"DE",
    "sg:address":"Gonsenheimer Str. 6",
    "sg:city":"Mainz",
    "sg:phone":"+49 6131/477034",
    "sg:postcode":"55126",
    "sg:province":"Rheinland-Pfalz",
    "wof:name":"K. Wolff",
    "wof:placetype":"venue"
},
  "geometry": {"coordinates":[8.184934,49.99453],"type":"Point"}
}