{
  "type": "Feature",
  "properties": {
    "iso:country":"DE",
    "sg:address":"Wellmersdorfer Str. 50",
    "sg:city":"Neustadt",
    "sg:phone":"+49 9568/2155",
    "sg:postcode":"96465",
    "sg:province":"Bayern",
    "wof:name":"Hotel Heidehof Gmbh",
    "wof:placetype":"venue"
},
  "geometry": {"coordinates":[11.1140890121,50.2896003723],"type":"Point"}
}