{
  "type": "Feature",
  "properties": {
    "iso:country":"DE",
    "sg:address":"Bebenh\u00e4user Str. 11",
    "sg:city":"Ludwigsburg",
    "sg:phone":"+49 7141/81430",
    "sg:postcode":"71638",
    "sg:province":"Baden-W\u00fcrttemberg",
    "wof:name":"Los Alhama",
    "wof:placetype":"venue"
},
  "geometry": {"coordinates":[9.207942009,48.8922195435],"type":"Point"}
}