{
  "type": "Feature",
  "properties": {
    "iso:country":"DE",
    "sg:address":"Lindenweg 2",
    "sg:city":"Haste",
    "sg:phone":"+49 5723/82431",
    "sg:postcode":"31559",
    "sg:province":"Niedersachsen",
    "wof:name":"Iduna",
    "wof:placetype":"venue"
},
  "geometry": {"coordinates":[9.401594162,52.3844070435],"type":"Point"}
}