{
  "type": "Feature",
  "properties": {
    "iso:country":"DE",
    "sg:address":"Ro\u00dfm\u00e4\u00dflerstr. 20",
    "sg:city":"Berlin",
    "sg:phone":"+49 30/5082062",
    "sg:postcode":"10318",
    "sg:province":"Berlin",
    "wof:name":"Joachim Elster",
    "wof:placetype":"venue"
},
  "geometry": {"coordinates":[13.5373010635,52.4963302612],"type":"Point"}
}