{
  "type": "Feature",
  "properties": {
    "iso:country":"DE",
    "sg:address":"Im Ort 2",
    "sg:city":"Scharnebeck",
    "sg:phone":"+49 4136/287",
    "sg:postcode":"21379",
    "sg:province":"Niedersachsen",
    "wof:name":"J\u00fcrgen Blume",
    "wof:placetype":"venue"
},
  "geometry": {"coordinates":[10.504909,53.287945],"type":"Point"}
}