{
  "type": "Feature",
  "properties": {
    "iso:country":"DE",
    "sg:address":"Am Hagedorn 3",
    "sg:city":"Dortmund",
    "sg:phone":"+49 231/216676",
    "sg:postcode":"44319",
    "sg:province":"Nordrhein-Westfalen",
    "wof:name":"Club Nr. 3",
    "wof:placetype":"venue"
},
  "geometry": {"coordinates":[7.5884141922,51.5287322998],"type":"Point"}
}