{
  "type": "Feature",
  "properties": {
    "iso:country":"DE",
    "sg:address":"Rudolf-Diesel-Ring 4-6",
    "sg:city":"Neustadt",
    "sg:phone":"+49 5032/949440",
    "sg:postcode":"31535",
    "sg:province":"Niedersachsen",
    "wof:name":"Ncs Holzkontor",
    "wof:placetype":"venue"
},
  "geometry": {"coordinates":[9.479391,52.506664],"type":"Point"}
}