{
  "type": "Feature",
  "properties": {
    "iso:country":"DE",
    "sg:address":"Ebertstr. 30",
    "sg:city":"Herzogenrath",
    "sg:phone":"+49 2407/917127",
    "sg:postcode":"52134",
    "sg:province":"Nordrhein-Westfalen",
    "wof:name":"Aetas Alten- Und Krankenpflegedienst Gmbh",
    "wof:placetype":"venue"
},
  "geometry": {"coordinates":[6.093577,50.8675],"type":"Point"}
}