{
  "type": "Feature",
  "properties": {
    "iso:country":"DE",
    "sg:address":"Wagnerstr. 28 1/2",
    "sg:city":"Memmingen",
    "sg:phone":"+49 8331/62709",
    "sg:postcode":"87700",
    "sg:province":"Bayern",
    "wof:name":"West-apotheke Apotheker Georg Thanner E. K.",
    "wof:placetype":"venue"
},
  "geometry": {"coordinates":[10.180405,47.98634],"type":"Point"}
}