{
  "type": "Feature",
  "properties": {
    "iso:country":"DE",
    "sg:address":"Schulstr. 2",
    "sg:city":"Kemberg",
    "sg:phone":"+49 34921/20735",
    "sg:postcode":"06901",
    "sg:province":"Sachsen-Anhalt",
    "wof:name":"Petite Fleur Gmbh",
    "wof:placetype":"venue"
},
  "geometry": {"coordinates":[12.635138,51.77359],"type":"Point"}
}