{
  "type": "Feature",
  "properties": {
    "iso:country":"DE",
    "sg:address":"Lauter 44",
    "sg:city":"Suhl",
    "sg:phone":"+49 3681/422200",
    "sg:postcode":"98528",
    "sg:province":"Th\u00fcringen",
    "wof:name":"A. Steittmann",
    "wof:placetype":"venue"
},
  "geometry": {"coordinates":[10.7476100922,50.6266517639],"type":"Point"}
}