{
  "type": "Feature",
  "properties": {
    "iso:country":"DE",
    "sg:address":"Bauerlandstr. 29",
    "sg:city":"Flensburg",
    "sg:postcode":"24939",
    "sg:province":"Schleswig-Holstein",
    "wof:name":"Exite.de.vu",
    "wof:placetype":"venue"
},
  "geometry": {"coordinates":[9.421033,54.801846],"type":"Point"}
}