{
  "type": "Feature",
  "properties": {
    "iso:country":"DE",
    "sg:address":"Karlstadter Str. 43",
    "sg:city":"Gem\u00fcnden",
    "sg:phone":"+49 9351/8796",
    "sg:postcode":"97737",
    "sg:province":"Bayern",
    "wof:name":"Edgar Ebert",
    "wof:placetype":"venue"
},
  "geometry": {"coordinates":[9.7272119522,50.0250473022],"type":"Point"}
}