{
  "type": "Feature",
  "properties": {
    "iso:country":"DE",
    "sg:address":"Achenbachstr. 55",
    "sg:city":"D\u00fcsseldorf",
    "sg:phone":"+49 211/4201201",
    "sg:postcode":"40237",
    "sg:province":"Nordrhein-Westfalen",
    "wof:name":"Wedeco Gesellschaft F\u00fcr Umwelttechnologie Mbh",
    "wof:placetype":"venue"
},
  "geometry": {"coordinates":[6.804964,51.2341],"type":"Point"}
}