{
  "type": "Feature",
  "properties": {
    "iso:country":"DE",
    "sg:address":"Amtsseite-Steiler Aufstieg 7",
    "sg:city":"Pobershau",
    "sg:phone":"+49 3735/22838",
    "sg:postcode":"09496",
    "sg:province":"Sachsen",
    "wof:name":"Steffen Reichel",
    "wof:placetype":"venue"
},
  "geometry": {"coordinates":[13.217053,50.634945],"type":"Point"}
}