{
  "type": "Feature",
  "properties": {
    "iso:country":"DE",
    "sg:address":"Hauptstr. 28",
    "sg:city":"Erlenbach",
    "sg:phone":"+49 6398/449",
    "sg:postcode":"76891",
    "sg:province":"Rheinland-Pfalz",
    "wof:name":"Agnes Schwarzmueller Hebamme",
    "wof:placetype":"venue"
},
  "geometry": {"coordinates":[7.859351,49.111401],"type":"Point"}
}