{
  "type": "Feature",
  "properties": {
    "iso:country":"DE",
    "sg:address":"August-Bebel-Str 35",
    "sg:city":"Gerwisch",
    "sg:phone":"+49 39292/26166",
    "sg:postcode":"39175",
    "sg:province":"Sachsen-Anhalt",
    "wof:name":"Recycling Und Umweltschutz Gmbh",
    "wof:placetype":"venue"
},
  "geometry": {"coordinates":[11.7144184113,52.154094696],"type":"Point"}
}