{
  "type": "Feature",
  "properties": {
    "iso:country":"DE",
    "sg:address":"Eulenbogen 85",
    "sg:city":"Brandenburg",
    "sg:phone":"+49 3381/669977",
    "sg:postcode":"14776",
    "sg:province":"Brandenburg",
    "wof:name":"Montanhandel Brandenburg A. D. Havel Gmbh",
    "wof:placetype":"venue"
},
  "geometry": {"coordinates":[12.516696,52.374264],"type":"Point"}
}