{
  "type": "Feature",
  "properties": {
    "iso:country":"DE",
    "sg:address":"Rot-Kreuz-Str. 3",
    "sg:city":"Gunzenhausen",
    "sg:phone":"+49 9831/611975",
    "sg:postcode":"91710",
    "sg:province":"Bayern",
    "wof:name":"Ludwig Beil Steinmetz",
    "wof:placetype":"venue"
},
  "geometry": {"coordinates":[10.7570161819,49.1146087646],"type":"Point"}
}