{
  "type": "Feature",
  "properties": {
    "iso:country":"DE",
    "sg:address":"M\u00fchlenweg 2",
    "sg:city":"Ritzerau",
    "sg:phone":"+49 4543/230",
    "sg:postcode":"23896",
    "sg:province":"Schleswig-Holstein",
    "wof:name":"Hermann Groth",
    "wof:placetype":"venue"
},
  "geometry": {"coordinates":[10.568,53.663162],"type":"Point"}
}