{
  "type": "Feature",
  "properties": {
    "iso:country":"DE",
    "sg:address":"Junkerstr. 8",
    "sg:city":"Wittingen",
    "sg:phone":"+49 5831/1224",
    "sg:postcode":"29378",
    "sg:province":"Niedersachsen",
    "wof:name":"Dieckmanns Apotheke Inh. Martina Baumann",
    "wof:placetype":"venue"
},
  "geometry": {"coordinates":[10.736984,52.728951],"type":"Point"}
}