{
  "type": "Feature",
  "properties": {
    "iso:country":"DE",
    "sg:address":"Jean-Paul-Str. 65",
    "sg:city":"Bayreuth",
    "sg:phone":"+49 921/53552",
    "sg:postcode":"95444",
    "sg:province":"Bayern",
    "wof:name":"B\u00fcrgerbr\u00e4u Gmbh",
    "wof:placetype":"venue"
},
  "geometry": {"coordinates":[11.582308,49.936947],"type":"Point"}
}