{
  "type": "Feature",
  "properties": {
    "iso:country":"DE",
    "sg:address":"Falkensteiner Str. 2-4",
    "sg:city":"Auerbach",
    "sg:phone":"+49 3744/212619",
    "sg:postcode":"08209",
    "sg:province":"Sachsen",
    "wof:name":"Hal Securi Gmbh",
    "wof:placetype":"venue"
},
  "geometry": {"coordinates":[12.398793,50.504089],"type":"Point"}
}