{
  "type": "Feature",
  "properties": {
    "iso:country":"DE",
    "sg:address":"West-H\u00f6chster Str. 72",
    "sg:city":"Frankfurt",
    "sg:phone":"+49 69/3089047",
    "sg:postcode":"65931",
    "sg:province":"Hessen",
    "wof:name":"Bistro Im Park",
    "wof:placetype":"venue"
},
  "geometry": {"coordinates":[8.5005121231,50.0928840637],"type":"Point"}
}