{
  "type": "Feature",
  "properties": {
    "iso:country":"DE",
    "sg:address":"Justinaweg 5",
    "sg:city":"Wildpoldsried",
    "sg:phone":"+49 8304/5288",
    "sg:postcode":"87499",
    "sg:province":"Bayern",
    "wof:name":"Bernhard Schumacher",
    "wof:placetype":"venue"
},
  "geometry": {"coordinates":[10.401255,47.762737],"type":"Point"}
}