{
  "type": "Feature",
  "properties": {
    "iso:country":"DE",
    "sg:address":"Gewerbestr. 5",
    "sg:city":"Ebringen",
    "sg:phone":"+49 7664/97040",
    "sg:postcode":"79285",
    "sg:province":"Baden-W\u00fcrttemberg",
    "wof:name":"Hans Orth Ingenieur",
    "wof:placetype":"venue"
},
  "geometry": {"coordinates":[7.7689561844,47.9556808472],"type":"Point"}
}