{
  "type": "Feature",
  "properties": {
    "iso:country":"DE",
    "sg:address":"St\u00fcrsholz 10",
    "sg:city":"Steinberg",
    "sg:phone":"+49 4632/7266",
    "sg:postcode":"24972",
    "sg:province":"Schleswig-Holstein",
    "wof:name":"Christian Steib Architekt",
    "wof:placetype":"venue"
},
  "geometry": {"coordinates":[9.78617,54.769566],"type":"Point"}
}