{
  "type": "Feature",
  "properties": {
    "iso:country":"DE",
    "sg:address":"Spittwitz 23",
    "sg:city":"G\u00f6da",
    "sg:phone":"+49 35930/50223",
    "sg:postcode":"02633",
    "sg:province":"Sachsen",
    "wof:name":"Slb Betonwerk Spittwitz Gmbh",
    "wof:placetype":"venue"
},
  "geometry": {"coordinates":[14.2811279297,51.170375824],"type":"Point"}
}