{
  "type": "Feature",
  "properties": {
    "iso:country":"DE",
    "sg:address":"Schlo\u00dfberg 1 B",
    "sg:city":"Harrislee",
    "sg:postcode":"24955",
    "sg:province":"Schleswig-Holstein",
    "wof:name":"Frager Gmbh",
    "wof:placetype":"venue"
},
  "geometry": {"coordinates":[9.387549,54.825481],"type":"Point"}
}