{
  "type": "Feature",
  "properties": {
    "iso:country":"DE",
    "sg:address":"Lange Str. 14",
    "sg:city":"Wittingen",
    "sg:phone":"+49 5831/8770",
    "sg:postcode":"29378",
    "sg:province":"Niedersachsen",
    "wof:name":"L\u00f6wenzahn",
    "wof:placetype":"venue"
},
  "geometry": {"coordinates":[10.738363,52.728409],"type":"Point"}
}