{
  "type": "Feature",
  "properties": {
    "iso:country":"DE",
    "sg:address":"Espenweg 42",
    "sg:city":"Nordhorn",
    "sg:phone":"+49 5921/35303",
    "sg:postcode":"48531",
    "sg:province":"Niedersachsen",
    "wof:name":"Peter Welling",
    "wof:placetype":"venue"
},
  "geometry": {"coordinates":[7.147066,52.458603],"type":"Point"}
}