{
  "type": "Feature",
  "properties": {
    "iso:country":"DE",
    "sg:address":"Siegburgstr. 23",
    "sg:city":"Dortmund",
    "sg:phone":"+49 231/332321",
    "sg:postcode":"44359",
    "sg:province":"Nordrhein-Westfalen",
    "wof:name":"Siegburggrill",
    "wof:placetype":"venue"
},
  "geometry": {"coordinates":[7.3833651543,51.5695838928],"type":"Point"}
}