{
  "type": "Feature",
  "properties": {
    "iso:country":"DE",
    "sg:address":"Eisenstr. 10",
    "sg:city":"R\u00fcsselsheim",
    "sg:phone":"+49 6142/168290",
    "sg:postcode":"65428",
    "sg:province":"Hessen",
    "wof:name":"Vsg Verkehrs-sich.-ger\u00c4te Gmbh",
    "wof:placetype":"venue"
},
  "geometry": {"coordinates":[8.4209260941,49.9764251709],"type":"Point"}
}