{
  "type": "Feature",
  "properties": {
    "iso:country":"DE",
    "sg:address":"Hauptstr. 86",
    "sg:city":"Hafenlohr",
    "sg:phone":"+49 9391/3971",
    "sg:postcode":"97840",
    "sg:province":"Bayern",
    "wof:name":"G\u00c4rtnerei Fischer",
    "wof:placetype":"venue"
},
  "geometry": {"coordinates":[9.603438,49.872845],"type":"Point"}
}