{
  "type": "Feature",
  "properties": {
    "iso:country":"DE",
    "sg:address":"Hans-Sachs-Str. 17",
    "sg:city":"Hilden",
    "sg:phone":"+49 2103/31232",
    "sg:postcode":"40721",
    "sg:province":"Nordrhein-Westfalen",
    "wof:name":"D. Gillert",
    "wof:placetype":"venue"
},
  "geometry": {"coordinates":[6.9175162315,51.1744308472],"type":"Point"}
}