{
  "type": "Feature",
  "properties": {
    "iso:country":"DE",
    "sg:address":"Beim Rathaus 14",
    "sg:city":"Metzingen",
    "sg:phone":"+49 7123/2512",
    "sg:postcode":"72555",
    "sg:province":"Baden-W\u00fcrttemberg",
    "wof:name":"Hauber Kaufhaus Gmbh & Co. Kg",
    "wof:placetype":"venue"
},
  "geometry": {"coordinates":[9.283943,48.540146],"type":"Point"}
}