{
  "type": "Feature",
  "properties": {
    "iso:country":"DE",
    "sg:address":"Schillweg 11",
    "sg:city":"Calw",
    "sg:postcode":"75365",
    "sg:province":"Baden-W\u00fcrttemberg",
    "wof:name":"Steinwald Edv Handels & Service Gmbh",
    "wof:placetype":"venue"
},
  "geometry": {"coordinates":[8.7650814056,48.7106323242],"type":"Point"}
}