{
  "type": "Feature",
  "properties": {
    "iso:country":"DE",
    "sg:address":"Bergstr. 5",
    "sg:city":"Soyen",
    "sg:phone":"+49 8071/3657",
    "sg:postcode":"83564",
    "sg:province":"Bayern",
    "wof:name":"Anneliese Eiglstorfer",
    "wof:placetype":"venue"
},
  "geometry": {"coordinates":[12.2115688324,48.1107215881],"type":"Point"}
}