{
  "type": "Feature",
  "properties": {
    "iso:country":"DE",
    "sg:address":"Waldowstr. 29",
    "sg:city":"Berlin",
    "sg:phone":"+49 4930/4767438",
    "sg:postcode":"13156",
    "sg:province":"Berlin",
    "wof:name":"Gr\u00dcnblick Gmbh & Co. Service Kg",
    "wof:placetype":"venue"
},
  "geometry": {"coordinates":[13.406988,52.586147],"type":"Point"}
}