{
  "type": "Feature",
  "properties": {
    "iso:country":"DE",
    "sg:address":"Fischerh\u00fcttenstr. 38",
    "sg:city":"Berlin",
    "sg:phone":"+49 30/8014099",
    "sg:postcode":"14163",
    "sg:province":"Berlin",
    "wof:name":"Rolf B\u00e4hr Rechtsanwalt",
    "wof:placetype":"venue"
},
  "geometry": {"coordinates":[13.2480630875,52.4388694763],"type":"Point"}
}