{
  "type": "Feature",
  "properties": {
    "iso:country":"DE",
    "sg:address":"Thomas-Mann-Str 57",
    "sg:city":"Maintal",
    "sg:phone":"+49 6109/771948",
    "sg:postcode":"63477",
    "sg:province":"Hessen",
    "wof:name":"Gregor Pischzan Pischzan Technologies",
    "wof:placetype":"venue"
},
  "geometry": {"coordinates":[8.809659,50.1464],"type":"Point"}
}