{
  "type": "Feature",
  "properties": {
    "iso:country":"DE",
    "sg:address":"Tannenstr. 6",
    "sg:city":"Lahr",
    "sg:phone":"+49 7821/955976",
    "sg:postcode":"77933",
    "sg:province":"Baden-W\u00fcrttemberg",
    "wof:name":"J. Spinner",
    "wof:placetype":"venue"
},
  "geometry": {"coordinates":[7.820912838,48.3315963745],"type":"Point"}
}