{
  "type": "Feature",
  "properties": {
    "iso:country":"DE",
    "sg:address":"Ostfreesenstraat 12",
    "sg:city":"Dornumersiel",
    "sg:phone":"+49 4933",
    "sg:postcode":"26553",
    "sg:province":"Niedersachsen",
    "wof:name":"Erholsamer Urlaub An Der Ostfriesischen Nord",
    "wof:placetype":"venue"
},
  "geometry": {"coordinates":[7.473902,53.674889],"type":"Point"}
}