{
  "type": "Feature",
  "properties": {
    "iso:country":"DE",
    "sg:address":"Haselsteiner Str.",
    "sg:city":"N\u00fcsttal",
    "sg:postcode":"36167",
    "sg:province":"Hessen",
    "wof:name":"Behindertenwerkstatt",
    "wof:placetype":"venue"
},
  "geometry": {"coordinates":[9.85704,50.644638],"type":"Point"}
}