{
  "type": "Feature",
  "properties": {
    "iso:country":"DE",
    "sg:address":"Graf-Zeppelin-Str. 20",
    "sg:city":"Mayen",
    "sg:phone":"+49 2651/490333",
    "sg:postcode":"56727",
    "sg:province":"Rheinland-Pfalz",
    "wof:name":"Gilles & Wagner Verwaltungs Gmbh",
    "wof:placetype":"venue"
},
  "geometry": {"coordinates":[7.2536950111,50.3322486877],"type":"Point"}
}