{
  "type": "Feature",
  "properties": {
    "iso:country":"DE",
    "sg:address":"Rumpenheimer Str. 9",
    "sg:city":"Offenbach",
    "sg:phone":"+49 69/863923",
    "sg:postcode":"63075",
    "sg:province":"Hessen",
    "wof:name":"Ernst Hildenbrand",
    "wof:placetype":"venue"
},
  "geometry": {"coordinates":[8.7844791412,50.1186141968],"type":"Point"}
}