{
  "type": "Feature",
  "properties": {
    "iso:country":"DE",
    "sg:address":"Friedrich-Engels-Str. 18-22",
    "sg:city":"Schwedt",
    "sg:phone":"+49 3332/33168",
    "sg:postcode":"16303",
    "sg:province":"Brandenburg",
    "wof:name":"Kerstin Tr\u00fcbenbach",
    "wof:placetype":"venue"
},
  "geometry": {"coordinates":[14.2499341965,53.0681877136],"type":"Point"}
}