{
  "type": "Feature",
  "properties": {
    "iso:country":"DE",
    "sg:address":"Robert-Franke-Str. 52",
    "sg:city":"Porta Westfalica",
    "sg:phone":"+49 5706/558",
    "sg:postcode":"32457",
    "sg:province":"Nordrhein-Westfalen",
    "wof:name":"Friedrich Temme",
    "wof:placetype":"venue"
},
  "geometry": {"coordinates":[8.969952,52.193428],"type":"Point"}
}