{
  "type": "Feature",
  "properties": {
    "iso:country":"DE",
    "sg:address":"L\u00f6rracher Str. 41",
    "sg:city":"Freiburg",
    "sg:phone":"+49 4976/1452320",
    "sg:postcode":"79115",
    "sg:province":"Baden-W\u00fcrttemberg",
    "wof:name":"Eckert Sicherheitstechnik Gmbh",
    "wof:placetype":"venue"
},
  "geometry": {"coordinates":[7.8217301369,47.9800376892],"type":"Point"}
}