{
  "type": "Feature",
  "properties": {
    "iso:country":"DE",
    "sg:address":"Schweinstal 1",
    "sg:city":"Krickenbach",
    "sg:phone":"+49 6307/337",
    "sg:postcode":"67706",
    "sg:province":"Rheinland-Pfalz",
    "wof:name":"Carl Picard",
    "wof:placetype":"venue"
},
  "geometry": {"coordinates":[7.6871571541,49.3711891174],"type":"Point"}
}