{
  "type": "Feature",
  "properties": {
    "iso:country":"DE",
    "sg:address":"Luisenstr. 13",
    "sg:city":"Muggensturm",
    "sg:phone":"+49 7222/53592",
    "sg:postcode":"76461",
    "sg:province":"Baden-W\u00fcrttemberg",
    "wof:name":"Bertold Raub",
    "wof:placetype":"venue"
},
  "geometry": {"coordinates":[8.281156,48.86956],"type":"Point"}
}