{
  "type": "Feature",
  "properties": {
    "iso:country":"DE",
    "sg:address":"In der Schank 30",
    "sg:city":"Merzig",
    "sg:phone":"+49 6861/4175",
    "sg:postcode":"66663",
    "sg:province":"Saarland",
    "wof:name":"Gerhard Martin Innenarchitekt",
    "wof:placetype":"venue"
},
  "geometry": {"coordinates":[6.58811,49.47052],"type":"Point"}
}