{
  "type": "Feature",
  "properties": {
    "iso:country":"DE",
    "sg:address":"Gro\u00dfe Str. 64",
    "sg:city":"Oyten",
    "sg:phone":"+49 4207/7050",
    "sg:postcode":"28876",
    "sg:province":"Niedersachsen",
    "wof:name":"Heidis Imbi\u00df",
    "wof:placetype":"venue"
},
  "geometry": {"coordinates":[9.0849819183,53.0631446838],"type":"Point"}
}