{
  "type": "Feature",
  "properties": {
    "iso:country":"DE",
    "sg:address":"Waldstr. 2",
    "sg:city":"Sitzendorf",
    "sg:phone":"+49 36730/22286",
    "sg:postcode":"07429",
    "sg:province":"Th\u00fcringen",
    "wof:name":"Restaurant F. H\u00f6rcher",
    "wof:placetype":"venue"
},
  "geometry": {"coordinates":[11.1594905853,50.6260299683],"type":"Point"}
}