{
  "type": "Feature",
  "properties": {
    "iso:country":"DE",
    "sg:address":"Sebastian-Bach-Str. 8",
    "sg:city":"Fellbach",
    "sg:phone":"+49 711/582904",
    "sg:postcode":"70734",
    "sg:province":"Baden-W\u00fcrttemberg",
    "wof:name":"M. Ho\u00df",
    "wof:placetype":"venue"
},
  "geometry": {"coordinates":[9.277057,48.813816],"type":"Point"}
}