{
  "type": "Feature",
  "properties": {
    "iso:country":"DE",
    "sg:address":"Lindenstr. 3",
    "sg:city":"Saarbr\u00fccken",
    "sg:phone":"+49 6805/3330",
    "sg:postcode":"66129",
    "sg:province":"Saarland",
    "wof:name":"Werner Steuer",
    "wof:placetype":"venue"
},
  "geometry": {"coordinates":[7.0430932045,49.1775588989],"type":"Point"}
}