{
  "type": "Feature",
  "properties": {
    "iso:country":"DE",
    "sg:address":"Waldstr.",
    "sg:city":"Essen",
    "sg:phone":"+49 5434/850",
    "sg:postcode":"49632",
    "sg:province":"Niedersachsen",
    "wof:name":"Fleisch-krone-feinkost Gmbh",
    "wof:placetype":"venue"
},
  "geometry": {"coordinates":[7.1014699936,51.4476356506],"type":"Point"}
}