{
  "type": "Feature",
  "properties": {
    "iso:country":"DE",
    "sg:address":"Ke\u00dflerstr. 18",
    "sg:city":"Bamberg",
    "sg:phone":"+49 951/22062",
    "sg:postcode":"96047",
    "sg:province":"Bayern",
    "wof:name":"Le\u00dfner Fleischwaren Gmbh",
    "wof:placetype":"venue"
},
  "geometry": {"coordinates":[10.8895797729,49.8927764893],"type":"Point"}
}