{
  "type": "Feature",
  "properties": {
    "iso:country":"DE",
    "sg:address":"Markt 1",
    "sg:city":"Frauenstein",
    "sg:postcode":"09623",
    "sg:province":"Sachsen",
    "wof:name":"Heinz Ebert",
    "wof:placetype":"venue"
},
  "geometry": {"coordinates":[13.5388374329,50.8026618958],"type":"Point"}
}