{
  "type": "Feature",
  "properties": {
    "iso:country":"DE",
    "sg:address":"Neumeyerstr. 48",
    "sg:city":"N\u00fcrnberg",
    "sg:postcode":"90411",
    "sg:province":"Bayern",
    "wof:name":"Bpw Nordbayern-businessplan- Wettbewerb Nordbayern Gmbh",
    "wof:placetype":"venue"
},
  "geometry": {"coordinates":[11.1210250854,49.4813117981],"type":"Point"}
}