{
  "type": "Feature",
  "properties": {
    "iso:country":"DE",
    "sg:address":"M\u00fchlenstr. 17",
    "sg:city":"M\u00f6nchweiler",
    "sg:phone":"+49 7721/71955",
    "sg:postcode":"78087",
    "sg:province":"Baden-W\u00fcrttemberg",
    "wof:name":"E. H. Lehmann",
    "wof:placetype":"venue"
},
  "geometry": {"coordinates":[8.4229726791,48.1028404236],"type":"Point"}
}