{
  "type": "Feature",
  "properties": {
    "iso:country":"DE",
    "sg:address":"Hauptstr. 113 POSTFACH 122112",
    "sg:city":"Idar-Oberstein",
    "sg:phone":"+49 4967/8142039",
    "sg:postcode":"55713",
    "sg:province":"Rheinland-Pfalz",
    "wof:name":"Walter Bohrer Ohg",
    "wof:placetype":"venue"
},
  "geometry": {"coordinates":[7.3040747643,49.7187385559],"type":"Point"}
}