{
  "type": "Feature",
  "properties": {
    "iso:country":"DE",
    "sg:address":"Altenoyther Str. 44",
    "sg:city":"Friesoythe",
    "sg:phone":"+49 4491/3341",
    "sg:postcode":"26169",
    "sg:province":"Niedersachsen",
    "wof:name":"Theo Kemper",
    "wof:placetype":"venue"
},
  "geometry": {"coordinates":[7.902458,53.046398],"type":"Point"}
}