{
  "type": "Feature",
  "properties": {
    "iso:country":"DE",
    "sg:address":"Oberstr. 17",
    "sg:city":"M\u00fclheim",
    "sg:phone":"+49 208/32761",
    "sg:postcode":"45468",
    "sg:province":"Nordrhein-Westfalen",
    "wof:name":"K. Rosskothen",
    "wof:placetype":"venue"
},
  "geometry": {"coordinates":[6.8883328438,51.4251480103],"type":"Point"}
}