{
  "type": "Feature",
  "properties": {
    "iso:country":"DE",
    "sg:address":"Bretonischer Ring 3",
    "sg:city":"Grasbrunn",
    "sg:postcode":"85630",
    "sg:province":"Bayern",
    "wof:name":"Cpays Ag",
    "wof:placetype":"venue"
},
  "geometry": {"coordinates":[11.761957,48.100231],"type":"Point"}
}