{
  "type": "Feature",
  "properties": {
    "iso:country":"DE",
    "sg:address":"Immenhofer Str. 42",
    "sg:city":"Stuttgart",
    "sg:phone":"+49 711/6403506",
    "sg:postcode":"70180",
    "sg:province":"Baden-W\u00fcrttemberg",
    "wof:name":"L\u00f6we & Thalheimer",
    "wof:placetype":"venue"
},
  "geometry": {"coordinates":[9.176441,48.76355],"type":"Point"}
}