{
  "type": "Feature",
  "properties": {
    "iso:country":"DE",
    "sg:address":"Auguststr. 4",
    "sg:city":"Bad Schwartau",
    "sg:phone":"+49 451/24345",
    "sg:postcode":"23611",
    "sg:province":"Schleswig-Holstein",
    "wof:name":"H\u00e4hncheneck Drews",
    "wof:placetype":"venue"
},
  "geometry": {"coordinates":[10.6966943741,53.9172782898],"type":"Point"}
}