{
  "type": "Feature",
  "properties": {
    "iso:country":"DE",
    "sg:address":"Austr. 42",
    "sg:city":"Lenningen",
    "sg:phone":"+49 7026/2074",
    "sg:postcode":"73252",
    "sg:province":"Baden-W\u00fcrttemberg",
    "wof:name":"Cbf Controlling Buchungs Und Finanzdienstleistungs",
    "wof:placetype":"venue"
},
  "geometry": {"coordinates":[9.46172,48.559078],"type":"Point"}
}