{
  "type": "Feature",
  "properties": {
    "iso:country":"DE",
    "sg:address":"Kilianstr. 2",
    "sg:city":"Paderborn",
    "sg:phone":"+49 5251/26892",
    "sg:postcode":"33098",
    "sg:province":"Nordrhein-Westfalen",
    "wof:name":"Hesterstuben",
    "wof:placetype":"venue"
},
  "geometry": {"coordinates":[8.7519311905,51.7143783569],"type":"Point"}
}