{
  "type": "Feature",
  "properties": {
    "iso:country":"DE",
    "sg:address":"Carl-Mannich-Str 26",
    "sg:city":"Eschborn",
    "sg:phone":"+49 6196/928401",
    "sg:postcode":"65760",
    "sg:province":"Hessen",
    "wof:name":"Werbe- Und Vertriebsgesellschaft Deutscher Apotheker Mbh",
    "wof:placetype":"venue"
},
  "geometry": {"coordinates":[8.5796108246,50.1434516907],"type":"Point"}
}