{
  "type": "Feature",
  "properties": {
    "iso:country":"DE",
    "sg:address":"Neutor 19-21",
    "sg:city":"Borken",
    "sg:phone":"+49 2861/94030",
    "sg:postcode":"46325",
    "sg:province":"Nordrhein-Westfalen",
    "wof:name":"M\u00f6bel Siebelt",
    "wof:placetype":"venue"
},
  "geometry": {"coordinates":[6.8572611809,51.8428192139],"type":"Point"}
}