{
  "type": "Feature",
  "properties": {
    "iso:country":"DE",
    "sg:address":"Im Weinfurth 4",
    "sg:city":"Nidda",
    "sg:phone":"+49 6043/3122",
    "sg:postcode":"63667",
    "sg:province":"Hessen",
    "wof:name":"Oswald Weber Masseur",
    "wof:placetype":"venue"
},
  "geometry": {"coordinates":[9.011828,50.421883],"type":"Point"}
}