{
  "type": "Feature",
  "properties": {
    "iso:country":"DE",
    "sg:address":"Bismarckplatz 37",
    "sg:city":"Krefeld",
    "sg:phone":"+49 2151/596568",
    "sg:postcode":"47799",
    "sg:province":"Nordrhein-Westfalen",
    "wof:name":"Klaus P. Noever",
    "wof:placetype":"venue"
},
  "geometry": {"coordinates":[6.576717,51.339863],"type":"Point"}
}