{
  "type": "Feature",
  "properties": {
    "iso:country":"DE",
    "sg:address":"Steindamm 9",
    "sg:city":"Gro\u00df Sch\u00f6nebeck",
    "sg:phone":"+49 33393/584",
    "sg:postcode":"16348",
    "sg:province":"Brandenburg",
    "wof:name":"Rudolf Lenuweit",
    "wof:placetype":"venue"
},
  "geometry": {"coordinates":[13.472614,52.755035],"type":"Point"}
}