{
  "type": "Feature",
  "properties": {
    "iso:country":"DE",
    "sg:address":"Bolander Str. 2",
    "sg:city":"Weitersweiler",
    "sg:phone":"+49 6357/287",
    "sg:postcode":"67808",
    "sg:province":"Rheinland-Pfalz",
    "wof:name":"A Kirschner",
    "wof:placetype":"venue"
},
  "geometry": {"coordinates":[7.9961848259,49.6150436401],"type":"Point"}
}