{
  "type": "Feature",
  "properties": {
    "iso:country":"DE",
    "sg:address":"Banzhaldenstr. 44",
    "sg:city":"Stuttgart",
    "sg:phone":"+49 711/858262",
    "sg:postcode":"70469",
    "sg:province":"Baden-W\u00fcrttemberg",
    "wof:name":"Dietrich Schreiweis",
    "wof:placetype":"venue"
},
  "geometry": {"coordinates":[9.143672,48.806721],"type":"Point"}
}