{
  "type": "Feature",
  "properties": {
    "iso:country":"DE",
    "sg:address":"Silberne Bergstr. 7",
    "sg:city":"Heiligkreuzsteinach",
    "sg:phone":"+49 6220/205",
    "sg:postcode":"69253",
    "sg:province":"Baden-W\u00fcrttemberg",
    "wof:name":"Katholisches Pfarramt Hl. Kreuz",
    "wof:placetype":"venue"
},
  "geometry": {"coordinates":[8.7952280045,49.4840965271],"type":"Point"}
}