{
  "type": "Feature",
  "properties": {
    "iso:country":"DE",
    "sg:address":"Amesberg 1",
    "sg:city":"Viechtach",
    "sg:phone":"+49 9942/8973",
    "sg:postcode":"94234",
    "sg:province":"Bayern",
    "wof:name":"Penzkofer Gmbh",
    "wof:placetype":"venue"
},
  "geometry": {"coordinates":[12.9378461838,49.1160621643],"type":"Point"}
}