{
  "type": "Feature",
  "properties": {
    "iso:country":"DE",
    "sg:address":"Philippistr. 8",
    "sg:city":"Haltern",
    "sg:phone":"+49 2364/4626",
    "sg:postcode":"45721",
    "sg:province":"Nordrhein-Westfalen",
    "wof:name":"Roman Brombach",
    "wof:placetype":"venue"
},
  "geometry": {"coordinates":[7.180147171,51.7374076843],"type":"Point"}
}