{
  "type": "Feature",
  "properties": {
    "iso:country":"DE",
    "sg:address":"C\u00e4mmerswalder Str. 17",
    "sg:city":"Dresden",
    "sg:phone":"+49 351/4033815",
    "sg:postcode":"01189",
    "sg:province":"Sachsen",
    "wof:name":"J\u00fcrgen Winkler Immobilienmakler",
    "wof:placetype":"venue"
},
  "geometry": {"coordinates":[13.7176809311,51.0209732056],"type":"Point"}
}