{
  "type": "Feature",
  "properties": {
    "iso:country":"DE",
    "sg:address":"Br\u00fchlstr. 16",
    "sg:city":"Burladingen",
    "sg:phone":"+49 7477/508",
    "sg:postcode":"72393",
    "sg:province":"Baden-W\u00fcrttemberg",
    "wof:name":"Erwin Hofer",
    "wof:placetype":"venue"
},
  "geometry": {"coordinates":[9.0649414062,48.3028755188],"type":"Point"}
}