{
  "type": "Feature",
  "properties": {
    "iso:country":"DE",
    "sg:address":"Hinterm Gallberg 14",
    "sg:city":"Brilon",
    "sg:phone":"+49 2961/8066",
    "sg:postcode":"59929",
    "sg:province":"Nordrhein-Westfalen",
    "wof:name":"Bwi Isenberg Gmbh",
    "wof:placetype":"venue"
},
  "geometry": {"coordinates":[8.5936279297,51.4079170227],"type":"Point"}
}