{
  "type": "Feature",
  "properties": {
    "iso:country":"DE",
    "sg:address":"Z\u00f6beritzer Str. 12",
    "sg:city":"Halle",
    "sg:phone":"+49 345/5227297",
    "sg:postcode":"06118",
    "sg:province":"Sachsen-Anhalt",
    "wof:name":"Johanna Schwendler",
    "wof:placetype":"venue"
},
  "geometry": {"coordinates":[12.008988,51.515182],"type":"Point"}
}