{
  "type": "Feature",
  "properties": {
    "iso:country":"DE",
    "sg:address":"Schillerstr. 4",
    "sg:city":"Ladenburg",
    "sg:phone":"+49 6203/3487",
    "sg:postcode":"68526",
    "sg:province":"Baden-W\u00fcrttemberg",
    "wof:name":"N. Y\u00fcr\u00fctken",
    "wof:placetype":"venue"
},
  "geometry": {"coordinates":[8.602850914,49.4725189209],"type":"Point"}
}