{
  "type": "Feature",
  "properties": {
    "iso:country":"DE",
    "sg:address":"Hauptstr. 37",
    "sg:city":"Leuthen",
    "sg:phone":"+49 35602/729",
    "sg:postcode":"03058",
    "sg:province":"Brandenburg",
    "wof:name":"Hans-joachim Staritz",
    "wof:placetype":"venue"
},
  "geometry": {"coordinates":[14.24185,51.698738],"type":"Point"}
}