{
  "type": "Feature",
  "properties": {
    "iso:country":"DE",
    "sg:address":"Weinbergstr. 8",
    "sg:city":"Wittenberge",
    "sg:phone":"+49 3877/60450",
    "sg:postcode":"19322",
    "sg:province":"Brandenburg",
    "wof:name":"Harry Wolke",
    "wof:placetype":"venue"
},
  "geometry": {"coordinates":[11.748689,52.994053],"type":"Point"}
}