{
  "type": "Feature",
  "properties": {
    "iso:country":"DE",
    "sg:address":"Rudolf-Breitscheid-Str. 36",
    "sg:city":"Luckenwalde",
    "sg:phone":"+49 3371/615986",
    "sg:postcode":"14943",
    "sg:province":"Brandenburg",
    "wof:name":"Asia-restaurant",
    "wof:placetype":"venue"
},
  "geometry": {"coordinates":[13.1649208069,52.0858383179],"type":"Point"}
}