{
  "type": "Feature",
  "properties": {
    "iso:country":"DE",
    "sg:address":"Alte Steige 4",
    "sg:city":"Esslingen",
    "sg:phone":"+49 711/378616",
    "sg:postcode":"73732",
    "sg:province":"Baden-W\u00fcrttemberg",
    "wof:name":"Hans-j\u00f6rg Kottmus Architekt",
    "wof:placetype":"venue"
},
  "geometry": {"coordinates":[9.337687,48.747597],"type":"Point"}
}