{
  "type": "Feature",
  "properties": {
    "iso:country":"DE",
    "sg:address":"Friedrich-Breuer-Str. 90",
    "sg:city":"Bonn",
    "sg:phone":"+49 228/475692",
    "sg:postcode":"53225",
    "sg:province":"Nordrhein-Westfalen",
    "wof:name":"Armin Sch\u00fcnemann",
    "wof:placetype":"venue"
},
  "geometry": {"coordinates":[7.122487,50.739738],"type":"Point"}
}