{
  "type": "Feature",
  "properties": {
    "iso:country":"DE",
    "sg:address":"Baudirektor-Hahn-Str. 95",
    "sg:city":"Cuxhaven",
    "sg:postcode":"27472",
    "sg:province":"Niedersachsen",
    "wof:name":"Elbe Immobilien Gmbh & Co. Kg",
    "wof:placetype":"venue"
},
  "geometry": {"coordinates":[8.6978178024,53.8583068848],"type":"Point"}
}