{
  "type": "Feature",
  "properties": {
    "iso:country":"DE",
    "sg:address":"Kirchstr. 24",
    "sg:city":"Altenberge",
    "sg:phone":"+49 2505/1241",
    "sg:postcode":"48341",
    "sg:province":"Nordrhein-Westfalen",
    "wof:name":"Pizzeria Etcetera",
    "wof:placetype":"venue"
},
  "geometry": {"coordinates":[7.4680418968,52.0461883545],"type":"Point"}
}