{
  "type": "Feature",
  "properties": {
    "iso:country":"DE",
    "sg:address":"Br\u00fcderweg 150",
    "sg:city":"Siegen",
    "sg:phone":"+49 271/62579",
    "sg:postcode":"57074",
    "sg:province":"Nordrhein-Westfalen",
    "wof:name":"Antonio Pucci",
    "wof:placetype":"venue"
},
  "geometry": {"coordinates":[8.0423879623,50.8789672852],"type":"Point"}
}