{
  "type": "Feature",
  "properties": {
    "iso:country":"DE",
    "sg:address":"Bahnhofstr. 18",
    "sg:city":"Penzberg",
    "sg:phone":"+49 8856/4626",
    "sg:postcode":"82377",
    "sg:province":"Bayern",
    "wof:name":"Wilhelm Tichelkamp",
    "wof:placetype":"venue"
},
  "geometry": {"coordinates":[11.37413,47.750061],"type":"Point"}
}