{
  "type": "Feature",
  "properties": {
    "iso:country":"DE",
    "sg:address":"Am Sagle 2",
    "sg:city":"Mittenwald",
    "sg:phone":"+49 8823/8426",
    "sg:postcode":"82481",
    "sg:province":"Bayern",
    "wof:name":"Bernhard Habusta",
    "wof:placetype":"venue"
},
  "geometry": {"coordinates":[11.2696228027,47.4411811829],"type":"Point"}
}