{
  "type": "Feature",
  "properties": {
    "iso:country":"DE",
    "sg:address":"Sudetendeutsche Str. 1 B",
    "sg:city":"Regensburg",
    "sg:phone":"+49 941/4662990",
    "sg:postcode":"93057",
    "sg:province":"Bayern",
    "wof:name":"Volksbank Regensburg Eg",
    "wof:placetype":"venue"
},
  "geometry": {"coordinates":[12.1168022156,49.0355758667],"type":"Point"}
}