{
  "type": "Feature",
  "properties": {
    "iso:country":"DE",
    "sg:address":"Marktstr. 57",
    "sg:city":"Ravensburg",
    "sg:phone":"+49 751/22826",
    "sg:postcode":"88212",
    "sg:province":"Baden-W\u00fcrttemberg",
    "wof:name":"J. Joos",
    "wof:placetype":"venue"
},
  "geometry": {"coordinates":[9.6162843704,47.7800140381],"type":"Point"}
}