{
  "type": "Feature",
  "properties": {
    "iso:country":"DE",
    "sg:address":"Hauptstr. 7",
    "sg:city":"Gro\u00dfmehring",
    "sg:phone":"+49 8456/8371",
    "sg:postcode":"85098",
    "sg:province":"Bayern",
    "wof:name":"Blasius K\u00fcrzinger",
    "wof:placetype":"venue"
},
  "geometry": {"coordinates":[11.543442,48.798172],"type":"Point"}
}