{
  "type": "Feature",
  "properties": {
    "iso:country":"DE",
    "sg:address":"Neuhauser Str. 7",
    "sg:city":"M\u00fcnchen",
    "sg:phone":"+49 89/264192",
    "sg:postcode":"80331",
    "sg:province":"Bayern",
    "wof:name":"Thalaysia Orthop\u00e4die- Salon Hans-friedrich Von",
    "wof:placetype":"venue"
},
  "geometry": {"coordinates":[11.570566,48.138302],"type":"Point"}
}