{
  "type": "Feature",
  "properties": {
    "iso:country":"DE",
    "sg:address":"Dreieichstr. 19",
    "sg:city":"Dietzenbach",
    "sg:phone":"+49 6074/27797",
    "sg:postcode":"63128",
    "sg:province":"Hessen",
    "wof:name":"Waltraud Charlotte Maurer Antiquariat",
    "wof:placetype":"venue"
},
  "geometry": {"coordinates":[8.7755184174,50.0167274475],"type":"Point"}
}