{
  "type": "Feature",
  "properties": {
    "iso:country":"DE",
    "sg:address":"Massener Str. 9",
    "sg:city":"Unna",
    "sg:phone":"+49 2303/15172",
    "sg:postcode":"59423",
    "sg:province":"Nordrhein-Westfalen",
    "wof:name":"Heinrich Br\u00e4ckelmann Architekt",
    "wof:placetype":"venue"
},
  "geometry": {"coordinates":[7.688986,51.534557],"type":"Point"}
}