{
  "type": "Feature",
  "properties": {
    "iso:country":"DE",
    "sg:address":"Hauptstr. 47 A",
    "sg:city":"Uetze",
    "sg:phone":"+49 5147/617",
    "sg:postcode":"31311",
    "sg:province":"Niedersachsen",
    "wof:name":"Werner H\u00fcbner",
    "wof:placetype":"venue"
},
  "geometry": {"coordinates":[10.058635,52.497475],"type":"Point"}
}