{
  "type": "Feature",
  "properties": {
    "iso:country":"DE",
    "sg:address":"Buchenweg 14",
    "sg:city":"Treia",
    "sg:phone":"+49 4626/187725",
    "sg:postcode":"24896",
    "sg:province":"Schleswig-Holstein",
    "wof:name":"Haye Und Partner",
    "wof:placetype":"venue"
},
  "geometry": {"coordinates":[9.311879158,54.5153388977],"type":"Point"}
}