{
  "type": "Feature",
  "properties": {
    "iso:country":"DE",
    "sg:address":"Dorfstr. 52",
    "sg:city":"Bad Segeberg",
    "sg:postcode":"23795",
    "sg:province":"Schleswig-Holstein",
    "wof:name":"Enzmann Bau Gmbh",
    "wof:placetype":"venue"
},
  "geometry": {"coordinates":[10.300195,53.949402],"type":"Point"}
}