{
  "type": "Feature",
  "properties": {
    "iso:country":"DE",
    "sg:address":"Wallstra\u00dfe 14",
    "sg:city":"M\u00fclheim Ruhr",
    "sg:phone":"+49 4920/8459459",
    "sg:postcode":"45468",
    "sg:province":"Nordrhein-Westfalen",
    "wof:name":"Call-cars Kraftdroschkenverein M\u00fclheim An Der Ruhr",
    "wof:placetype":"venue"
},
  "geometry": {"coordinates":[6.880817,51.428768],"type":"Point"}
}