{
  "type": "Feature",
  "properties": {
    "iso:country":"DE",
    "sg:address":"Erlengarten 5",
    "sg:city":"Boll",
    "sg:phone":"+49 7164/912140",
    "sg:postcode":"73087",
    "sg:province":"Baden-W\u00fcrttemberg",
    "wof:name":"Sch\u00f6ne",
    "wof:placetype":"venue"
},
  "geometry": {"coordinates":[9.6126461029,48.6420402527],"type":"Point"}
}