{
  "type": "Feature",
  "properties": {
    "iso:country":"DE",
    "sg:address":"In der Neckarhelle 70",
    "sg:city":"Heidelberg",
    "sg:phone":"+49 6221/802654",
    "sg:postcode":"69118",
    "sg:province":"Baden-W\u00fcrttemberg",
    "wof:name":"Gerhard Krumm Architekt",
    "wof:placetype":"venue"
},
  "geometry": {"coordinates":[8.749377,49.41748],"type":"Point"}
}