{
  "type": "Feature",
  "properties": {
    "iso:country":"DE",
    "sg:address":"Diamantweg 7",
    "sg:city":"Neubrandenburg",
    "sg:phone":"+49 395/7780231",
    "sg:postcode":"17036",
    "sg:province":"Mecklenburg-Vorpommern",
    "wof:name":"Neubrandenburger Immobilien Markt",
    "wof:placetype":"venue"
},
  "geometry": {"coordinates":[13.3063144684,53.5493278503],"type":"Point"}
}