{
  "type": "Feature",
  "properties": {
    "iso:country":"DE",
    "sg:address":"St\u00f6tteritzer Landstr. 33",
    "sg:city":"Leipzig",
    "sg:phone":"+49 34297/48513",
    "sg:postcode":"04288",
    "sg:province":"Sachsen",
    "wof:name":"Helmut M\u00fcller",
    "wof:placetype":"venue"
},
  "geometry": {"coordinates":[12.461930275,51.3063430786],"type":"Point"}
}