{
  "type": "Feature",
  "properties": {
    "iso:country":"DE",
    "sg:address":"Osterstr. 47",
    "sg:city":"Hamburg",
    "sg:phone":"+49 40/493095",
    "sg:postcode":"20259",
    "sg:province":"Hamburg",
    "wof:name":"Tornow Verm\u00f6gens Gmbh",
    "wof:placetype":"venue"
},
  "geometry": {"coordinates":[9.957503,53.574821],"type":"Point"}
}