{
  "type": "Feature",
  "properties": {
    "iso:country":"DE",
    "sg:address":"Ruppertshofer Str. 40",
    "sg:city":"T\u00e4ferrot",
    "sg:phone":"+49 7176/1748",
    "sg:postcode":"73527",
    "sg:province":"Baden-W\u00fcrttemberg",
    "wof:name":"U. Nuding",
    "wof:placetype":"venue"
},
  "geometry": {"coordinates":[9.817854,48.86367],"type":"Point"}
}