{
  "type": "Feature",
  "properties": {
    "iso:country":"DE",
    "sg:address":"Marlener Str. 3a",
    "sg:city":"Offenburg",
    "sg:postcode":"77656",
    "sg:province":"Baden-W\u00fcrttemberg",
    "wof:name":"Aldi Gmbh & Co. Kg",
    "wof:placetype":"venue"
},
  "geometry": {"coordinates":[7.9322180748,48.4684066772],"type":"Point"}
}