{
  "type": "Feature",
  "properties": {
    "iso:country":"DE",
    "sg:address":"Marktplatz 13",
    "sg:city":"Bad Neuenahr-Ahrweiler",
    "sg:phone":"+49 2641/34737",
    "sg:postcode":"53474",
    "sg:province":"Rheinland-Pfalz",
    "wof:name":"Kath. Pfarramt St. Lauritius",
    "wof:placetype":"venue"
},
  "geometry": {"coordinates":[7.0936760902,50.5425109863],"type":"Point"}
}