{
  "type": "Feature",
  "properties": {
    "iso:country":"DE",
    "sg:address":"Hermann-Muth-Str. 4",
    "sg:city":"Fulda",
    "sg:phone":"+49 4966/1160",
    "sg:postcode":"36039",
    "sg:province":"Hessen",
    "wof:name":"Friedrich Zufall Gmbh & Co. Kg",
    "wof:placetype":"venue"
},
  "geometry": {"coordinates":[9.6784143448,50.5684547424],"type":"Point"}
}