{
  "type": "Feature",
  "properties": {
    "iso:country":"DE",
    "sg:address":"Steinlestr. 4",
    "sg:city":"Frankfurt",
    "sg:phone":"+49 69/635014",
    "sg:postcode":"60596",
    "sg:province":"Hessen",
    "wof:name":"Pbg Gesellschaft F\u00fcr Projektmanagement Und Baulei-",
    "wof:placetype":"venue"
},
  "geometry": {"coordinates":[8.67324,50.102295],"type":"Point"}
}