{
  "type": "Feature",
  "properties": {
    "iso:country":"DE",
    "sg:address":"Pirnaer Landstr. 227",
    "sg:city":"Dresden",
    "sg:phone":"+49 351/2024748",
    "sg:postcode":"01259",
    "sg:province":"Sachsen",
    "wof:name":"M\u00fcller Arbeitsb\u00fchnen Gmbh",
    "wof:placetype":"venue"
},
  "geometry": {"coordinates":[13.840883,51.004406],"type":"Point"}
}