{
  "type": "Feature",
  "properties": {
    "iso:country":"DE",
    "sg:address":"Schloenbachstr. 28",
    "sg:city":"Salzgitter",
    "sg:phone":"+49 5341/35055",
    "sg:postcode":"38259",
    "sg:province":"Niedersachsen",
    "wof:name":"Arz-ambulantes Rehazentrum F\u00fcr Pr\u00e4vention Und Rehabilation",
    "wof:placetype":"venue"
},
  "geometry": {"coordinates":[10.3750352859,52.0411148071],"type":"Point"}
}