{
  "type": "Feature",
  "properties": {
    "iso:country":"DE",
    "sg:address":"Klostergasse 1",
    "sg:city":"Rohr",
    "sg:postcode":"93352",
    "sg:province":"Bayern",
    "wof:name":"B\u00e4ckerei Buchner Gmbh",
    "wof:placetype":"venue"
},
  "geometry": {"coordinates":[11.967085,48.768375],"type":"Point"}
}