{
  "type": "Feature",
  "properties": {
    "iso:country":"DE",
    "sg:address":"Hermann-Kirchhoff-Str. 5",
    "sg:city":"Paderborn",
    "sg:phone":"+49 5251/32938",
    "sg:postcode":"33102",
    "sg:province":"Nordrhein-Westfalen",
    "wof:name":"F. A. Hesse-pawlak",
    "wof:placetype":"venue"
},
  "geometry": {"coordinates":[8.748855,51.733562],"type":"Point"}
}