{
  "type": "Feature",
  "properties": {
    "iso:country":"DE",
    "sg:address":"Poisentalstr. 45b",
    "sg:city":"Freital",
    "sg:phone":"+49 351/6491898",
    "sg:postcode":"01705",
    "sg:province":"Sachsen",
    "wof:name":"G\u00dcnter & Thomas Richter Gbr",
    "wof:placetype":"venue"
},
  "geometry": {"coordinates":[13.6577825546,50.9920310974],"type":"Point"}
}