{
  "type": "Feature",
  "properties": {
    "iso:country":"DE",
    "sg:address":"Petersburg 15",
    "sg:city":"Gladenbach",
    "sg:phone":"+49 6462/5393",
    "sg:postcode":"35075",
    "sg:province":"Hessen",
    "wof:name":"Matthias Schneider",
    "wof:placetype":"venue"
},
  "geometry": {"coordinates":[8.5436658859,50.7535324097],"type":"Point"}
}