{
  "type": "Feature",
  "properties": {
    "iso:country":"DE",
    "sg:address":"Von-der-Goltz-Allee 93",
    "sg:city":"Kiel",
    "sg:phone":"+49 431/648930",
    "sg:postcode":"24113",
    "sg:province":"Schleswig-Holstein",
    "wof:name":"Kieler R\u00fcck- Versicherungsverein Ag",
    "wof:placetype":"venue"
},
  "geometry": {"coordinates":[10.1254081726,54.3004112244],"type":"Point"}
}