{
  "type": "Feature",
  "properties": {
    "iso:country":"DE",
    "sg:address":"Schwaighofstr. 78",
    "sg:city":"Tegernsee",
    "sg:phone":"+49 8022/67251",
    "sg:postcode":"83684",
    "sg:province":"Bayern",
    "wof:name":"Richard Eberwein",
    "wof:placetype":"venue"
},
  "geometry": {"coordinates":[11.772218,47.694511],"type":"Point"}
}