{
  "type": "Feature",
  "properties": {
    "iso:country":"DE",
    "sg:address":"Oskar-Messter-Str 22",
    "sg:city":"Ismaning",
    "sg:phone":"+49 89/2060310",
    "sg:postcode":"85737",
    "sg:province":"Bayern",
    "wof:name":"Loral Cyberstar Gmbh",
    "wof:placetype":"venue"
},
  "geometry": {"coordinates":[11.6807479858,48.2342567444],"type":"Point"}
}