{
  "type": "Feature",
  "properties": {
    "iso:country":"DE",
    "sg:address":"Widumstr. 29",
    "sg:city":"Hamm",
    "sg:phone":"+49 2381/90130",
    "sg:postcode":"59065",
    "sg:province":"Nordrhein-Westfalen",
    "wof:name":"Busch",
    "wof:placetype":"venue"
},
  "geometry": {"coordinates":[7.8226752281,51.681854248],"type":"Point"}
}