{
  "type": "Feature",
  "properties": {
    "iso:country":"DE",
    "sg:address":"Wandsbeker Zollstr. 141-143",
    "sg:city":"Hamburg-Wandsbek",
    "sg:phone":"+49 40/65681070",
    "sg:postcode":"22041",
    "sg:province":"Hamburg",
    "wof:name":"Zahnarztpraxis Dres.k\u00fcnzle",
    "wof:placetype":"venue"
},
  "geometry": {"coordinates":[10.084848,53.577381],"type":"Point"}
}