{
  "type": "Feature",
  "properties": {
    "iso:country":"DE",
    "sg:address":"Am Hauptbahnhof 8",
    "sg:city":"Weinheim",
    "sg:phone":"+49 6201/69100",
    "sg:postcode":"69469",
    "sg:province":"Baden-W\u00fcrttemberg",
    "wof:name":"Las Vegas",
    "wof:placetype":"venue"
},
  "geometry": {"coordinates":[8.6665086746,49.5539207458],"type":"Point"}
}