{
  "type": "Feature",
  "properties": {
    "iso:country":"DE",
    "sg:address":"J\u00e4gerstr. 41",
    "sg:city":"Duisburg",
    "sg:phone":"+49 203/559968",
    "sg:postcode":"47166",
    "sg:province":"Nordrhein-Westfalen",
    "wof:name":"P. Leutl",
    "wof:placetype":"venue"
},
  "geometry": {"coordinates":[6.768074,51.490059],"type":"Point"}
}