{
  "type": "Feature",
  "properties": {
    "iso:country":"DE",
    "sg:address":"Bockgasse 29",
    "sg:city":"Ulm",
    "sg:phone":"+49 731/9217311",
    "sg:postcode":"89073",
    "sg:province":"Baden-W\u00fcrttemberg",
    "wof:name":"G. Kayrak",
    "wof:placetype":"venue"
},
  "geometry": {"coordinates":[9.999021,48.399651],"type":"Point"}
}