{
  "type": "Feature",
  "properties": {
    "iso:country":"DE",
    "sg:address":"Grevener Str. 16",
    "sg:city":"Telgte",
    "sg:phone":"+49 2504/88406",
    "sg:postcode":"48291",
    "sg:province":"Nordrhein-Westfalen",
    "wof:name":"Antonio Vale De Gato Heilpraktiker",
    "wof:placetype":"venue"
},
  "geometry": {"coordinates":[7.780960083,52.0216293335],"type":"Point"}
}