{
  "type": "Feature",
  "properties": {
    "iso:country":"DE",
    "sg:address":"Gest\u00fctstr. 22",
    "sg:city":"Neuburg",
    "sg:phone":"+49 8431/9836",
    "sg:postcode":"86633",
    "sg:province":"Bayern",
    "wof:name":"Gastst\u00e4tte Georg Eder",
    "wof:placetype":"venue"
},
  "geometry": {"coordinates":[11.2614526749,48.7189674377],"type":"Point"}
}