{
  "type": "Feature",
  "properties": {
    "iso:country":"DE",
    "sg:address":"Burgweg 16",
    "sg:city":"Iserlohn",
    "sg:phone":"+49 2371/25248",
    "sg:postcode":"58638",
    "sg:province":"Nordrhein-Westfalen",
    "wof:name":"Wolfgang Helmholz Architekt",
    "wof:placetype":"venue"
},
  "geometry": {"coordinates":[7.69506,51.380714],"type":"Point"}
}