{
  "type": "Feature",
  "properties": {
    "iso:country":"DE",
    "sg:address":"Pappelstr. 99-101",
    "sg:city":"Bremen",
    "sg:phone":"+49 421/501431",
    "sg:postcode":"28199",
    "sg:province":"Bremen",
    "wof:name":"Delme Tee Contor",
    "wof:placetype":"venue"
},
  "geometry": {"coordinates":[8.7920732498,53.0671272278],"type":"Point"}
}