{
  "type": "Feature",
  "properties": {
    "iso:country":"DE",
    "sg:address":"Birlenbacher Str. 134",
    "sg:city":"Siegen",
    "sg:phone":"+49 271/83949",
    "sg:postcode":"57078",
    "sg:province":"Nordrhein-Westfalen",
    "wof:name":"Walfried Utsch",
    "wof:placetype":"venue"
},
  "geometry": {"coordinates":[7.9911379814,50.9052963257],"type":"Point"}
}