{
  "type": "Feature",
  "properties": {
    "iso:country":"DE",
    "sg:address":"Columbiadamm 111",
    "sg:city":"Berlin",
    "sg:phone":"+49 30/6916061",
    "sg:postcode":"10965",
    "sg:province":"Berlin",
    "wof:name":"Restaurant Lilienthals",
    "wof:placetype":"venue"
},
  "geometry": {"coordinates":[13.407782,52.482456],"type":"Point"}
}