{
  "type": "Feature",
  "properties": {
    "iso:country":"DE",
    "sg:address":"Hauptstr. 34",
    "sg:city":"Frankenthal",
    "sg:phone":"+49 35954/53481",
    "sg:postcode":"01909",
    "sg:province":"Sachsen",
    "wof:name":"G\u00fcnther Haufe",
    "wof:placetype":"venue"
},
  "geometry": {"coordinates":[14.105558,51.131897],"type":"Point"}
}