{
  "type": "Feature",
  "properties": {
    "iso:country":"DE",
    "sg:address":"Borglingstr. 1",
    "sg:city":"Hannover",
    "sg:phone":"+49 511/791001",
    "sg:postcode":"30419",
    "sg:province":"Niedersachsen",
    "wof:name":"Praxis Dr. Med. Duderstadt Und Trzeba",
    "wof:placetype":"venue"
},
  "geometry": {"coordinates":[9.6773900986,52.4124679565],"type":"Point"}
}