{
  "type": "Feature",
  "properties": {
    "iso:country":"DE",
    "sg:address":"Westrg. 15",
    "sg:city":"Pforzheim",
    "sg:phone":"+49 4972/3173107",
    "sg:postcode":"75180",
    "sg:province":"Baden-W\u00fcrttemberg",
    "wof:name":"Berwinkel & Eitel Gmbh",
    "wof:placetype":"venue"
},
  "geometry": {"coordinates":[8.6575,48.858738],"type":"Point"}
}