{
  "type": "Feature",
  "properties": {
    "iso:country":"DE",
    "sg:address":"Heckenstr. 10",
    "sg:city":"Salzgitter",
    "sg:phone":"+49 5341/84820",
    "sg:postcode":"38226",
    "sg:province":"Niedersachsen",
    "wof:name":"Apotheke Am Kreisel",
    "wof:placetype":"venue"
},
  "geometry": {"coordinates":[10.323832,52.149719],"type":"Point"}
}