{
  "type": "Feature",
  "properties": {
    "iso:country":"DE",
    "sg:address":"Obere L\u00e4nge 22",
    "sg:city":"Sand",
    "sg:phone":"+49 9524/5473",
    "sg:postcode":"97522",
    "sg:province":"Bayern",
    "wof:name":"Theo Mahr Gmbh",
    "wof:placetype":"venue"
},
  "geometry": {"coordinates":[10.5812292099,49.9868965149],"type":"Point"}
}