{
  "type": "Feature",
  "properties": {
    "iso:country":"DE",
    "sg:address":"Amselweg 1",
    "sg:city":"Burgstetten",
    "sg:phone":"+49 7191/899066",
    "sg:postcode":"71576",
    "sg:province":"Baden-W\u00fcrttemberg",
    "wof:name":"Netz-baustelle - Web-design Und Mehr",
    "wof:placetype":"venue"
},
  "geometry": {"coordinates":[9.368209,48.927086],"type":"Point"}
}