{
  "type": "Feature",
  "properties": {
    "iso:country":"DE",
    "sg:address":"Kolben",
    "sg:city":"Wiggensbach",
    "sg:phone":"+49 8370/595",
    "sg:postcode":"87487",
    "sg:province":"Bayern",
    "wof:name":"A. Thannheimer Steuerberater",
    "wof:placetype":"venue"
},
  "geometry": {"coordinates":[10.2085895538,47.7472038269],"type":"Point"}
}