{
  "type": "Feature",
  "properties": {
    "iso:country":"DE",
    "sg:address":"Thomas-Mann-Str. 1",
    "sg:city":"Neuss",
    "sg:phone":"+49 2137/2160",
    "sg:postcode":"41469",
    "sg:province":"Nordrhein-Westfalen",
    "wof:name":"Roland Edelmann Masseur",
    "wof:placetype":"venue"
},
  "geometry": {"coordinates":[6.736204,51.151539],"type":"Point"}
}