{
  "type": "Feature",
  "properties": {
    "iso:country":"DE",
    "sg:address":"Am Deich 6",
    "sg:city":"Rhinow",
    "sg:phone":"+49 33875/30734",
    "sg:postcode":"14728",
    "sg:province":"Brandenburg",
    "wof:name":"Rosis Kleine Gaststube",
    "wof:placetype":"venue"
},
  "geometry": {"coordinates":[12.3391590118,52.7524681091],"type":"Point"}
}