{
  "type": "Feature",
  "properties": {
    "iso:country":"DE",
    "sg:address":"Oberer Graben 17",
    "sg:city":"Leutkirch",
    "sg:phone":"+49 7561/87133",
    "sg:postcode":"88299",
    "sg:province":"Baden-W\u00fcrttemberg",
    "wof:name":"Lehrschwimmbecken",
    "wof:placetype":"venue"
},
  "geometry": {"coordinates":[10.0254459381,47.8266868591],"type":"Point"}
}