{
  "type": "Feature",
  "properties": {
    "iso:country":"DE",
    "sg:address":"M\u00fchlwehrstr 28",
    "sg:city":"Sch\u00f6ntal",
    "sg:phone":"+49 6294/42140",
    "sg:postcode":"74214",
    "sg:province":"Baden-W\u00fcrttemberg",
    "wof:name":"M\u00fchlenbeck Gmbh",
    "wof:placetype":"venue"
},
  "geometry": {"coordinates":[9.610698,49.347424],"type":"Point"}
}