{
  "type": "Feature",
  "properties": {
    "iso:country":"DE",
    "sg:address":"Rechnerstr. 4 d",
    "sg:city":"Haar",
    "sg:postcode":"85540",
    "sg:province":"Bayern",
    "wof:name":"Guido Opfergeld Malereibetrieb Gmbh",
    "wof:placetype":"venue"
},
  "geometry": {"coordinates":[11.738065,48.106762],"type":"Point"}
}