{
  "type": "Feature",
  "properties": {
    "iso:country":"DE",
    "sg:address":"Meller Str. 33",
    "sg:city":"Melle",
    "sg:phone":"+49 5226/309",
    "sg:postcode":"49328",
    "sg:province":"Niedersachsen",
    "wof:name":"Gastst\u00e4tte Lohse",
    "wof:placetype":"venue"
},
  "geometry": {"coordinates":[8.4512910843,52.2023086548],"type":"Point"}
}