{
  "type": "Feature",
  "properties": {
    "iso:country":"DE",
    "sg:address":"Untere Heide 4",
    "sg:city":"Schwebheim",
    "sg:postcode":"97525",
    "sg:province":"Bayern",
    "wof:name":"World Advanced Packaging Technology Gmbh",
    "wof:placetype":"venue"
},
  "geometry": {"coordinates":[10.241945,50.001602],"type":"Point"}
}