{
  "type": "Feature",
  "properties": {
    "iso:country":"DE",
    "sg:address":"D\u00f6bbricker Dorfstr. 35",
    "sg:city":"Cottbus",
    "sg:phone":"+49 355/873911",
    "sg:postcode":"03054",
    "sg:province":"Brandenburg",
    "wof:name":"Widmar Gerth Architekt",
    "wof:placetype":"venue"
},
  "geometry": {"coordinates":[14.345962,51.825539],"type":"Point"}
}