{
  "type": "Feature",
  "properties": {
    "iso:country":"DE",
    "sg:address":"Vogl\u00f6d 19",
    "sg:city":"Bad F\u00fcssing",
    "sg:phone":"+49 8538/473",
    "sg:postcode":"94072",
    "sg:province":"Bayern",
    "wof:name":"Robert Halsch Masseur",
    "wof:placetype":"venue"
},
  "geometry": {"coordinates":[13.373104,48.378941],"type":"Point"}
}