{
  "type": "Feature",
  "properties": {
    "iso:country":"DE",
    "sg:address":"Knaackstr. 5",
    "sg:city":"Berlin",
    "sg:phone":"+49 30/4428014",
    "sg:postcode":"10405",
    "sg:province":"Berlin",
    "wof:name":"Petra Tack & Band Co Falk-hendrik D\u00f6rffel",
    "wof:placetype":"venue"
},
  "geometry": {"coordinates":[13.4199924469,52.5338516235],"type":"Point"}
}