{
  "type": "Feature",
  "properties": {
    "iso:country":"DE",
    "sg:address":"Priggenhagener Str. 1",
    "sg:city":"Bersenbr\u00fcck",
    "sg:phone":"+49 5439/1787",
    "sg:postcode":"49593",
    "sg:province":"Niedersachsen",
    "wof:name":"Vege-markt Vinzenz Deichsel",
    "wof:placetype":"venue"
},
  "geometry": {"coordinates":[7.9353780746,52.5492668152],"type":"Point"}
}