{
  "type": "Feature",
  "properties": {
    "iso:country":"DE",
    "sg:address":"Freudenthalstr. 29",
    "sg:city":"Tostedt",
    "sg:phone":"+49 4182/1286",
    "sg:postcode":"21255",
    "sg:province":"Niedersachsen",
    "wof:name":"Hans-j. L\u00fcdtke",
    "wof:placetype":"venue"
},
  "geometry": {"coordinates":[9.713489,53.274479],"type":"Point"}
}