{
  "type": "Feature",
  "properties": {
    "iso:country":"DE",
    "sg:address":"Rumbecker Holz 37",
    "sg:city":"Arnsberg",
    "sg:phone":"+49 2932/33767",
    "sg:postcode":"59759",
    "sg:province":"Nordrhein-Westfalen",
    "wof:name":"Rudolf M\u00fcller Innenarchitekt",
    "wof:placetype":"venue"
},
  "geometry": {"coordinates":[7.961155,51.437641],"type":"Point"}
}