{
  "type": "Feature",
  "properties": {
    "iso:country":"DE",
    "sg:address":"Hauptstr. 120",
    "sg:city":"Dederstedt",
    "sg:phone":"+49 34773/20289",
    "sg:postcode":"06295",
    "sg:province":"Sachsen-Anhalt",
    "wof:name":"H. Halle",
    "wof:placetype":"venue"
},
  "geometry": {"coordinates":[11.6874198914,51.5466308594],"type":"Point"}
}