{
  "type": "Feature",
  "properties": {
    "iso:country":"DE",
    "sg:address":"Lessingstr. 6",
    "sg:city":"Frankfurt",
    "sg:phone":"+49 335/537561",
    "sg:postcode":"15230",
    "sg:province":"Brandenburg",
    "wof:name":"L. Lingorow Immobilienmakler",
    "wof:placetype":"venue"
},
  "geometry": {"coordinates":[14.5343513489,52.3439865112],"type":"Point"}
}