{
  "type": "Feature",
  "properties": {
    "iso:country":"DE",
    "sg:address":"Breite Gasse 72",
    "sg:city":"N\u00fcrnberg",
    "sg:phone":"+49 911/206750",
    "sg:postcode":"90402",
    "sg:province":"Bayern",
    "wof:name":"Atlas Reisen Gmbh",
    "wof:placetype":"venue"
},
  "geometry": {"coordinates":[11.0733070374,49.4502754211],"type":"Point"}
}