{
  "type": "Feature",
  "properties": {
    "iso:country":"DE",
    "sg:address":"Tassiloplatz 7",
    "sg:city":"M\u00fcnchen",
    "sg:phone":"+49 89/6886775",
    "sg:postcode":"81541",
    "sg:province":"Bayern",
    "wof:name":"Peter Naumann",
    "wof:placetype":"venue"
},
  "geometry": {"coordinates":[11.59528,48.123211],"type":"Point"}
}