{
  "type": "Feature",
  "properties": {
    "iso:country":"DE",
    "sg:address":"Mindener Str. 205",
    "sg:city":"Osnabr\u00fcck",
    "sg:phone":"+49 541/7102201",
    "sg:postcode":"49084",
    "sg:province":"Niedersachsen",
    "wof:name":"Hahm Planungsb\u00fcro Gmbh",
    "wof:placetype":"venue"
},
  "geometry": {"coordinates":[8.097589,52.269039],"type":"Point"}
}