{
  "type": "Feature",
  "properties": {
    "iso:country":"DE",
    "sg:address":"Adlerstr. 18",
    "sg:city":"N\u00fcrnberg",
    "sg:phone":"+49 911/227003",
    "sg:postcode":"90403",
    "sg:province":"Bayern",
    "wof:name":"Zur Baumwolle",
    "wof:placetype":"venue"
},
  "geometry": {"coordinates":[11.0760221481,49.4519844055],"type":"Point"}
}