{
  "type": "Feature",
  "properties": {
    "iso:country":"DE",
    "sg:address":"An der St. Marienkirche 1",
    "sg:city":"Uelzen",
    "sg:phone":"+49 581/800127",
    "sg:postcode":"29525",
    "sg:province":"Niedersachsen",
    "wof:name":"Stadtarchiv",
    "wof:placetype":"venue"
},
  "geometry": {"coordinates":[10.558983,52.964371],"type":"Point"}
}