{
  "type": "Feature",
  "properties": {
    "iso:country":"DE",
    "sg:address":"Info-Zentrum 3",
    "sg:city":"Zwiesel",
    "sg:phone":"+49 9922/802480",
    "sg:postcode":"94227",
    "sg:province":"Bayern",
    "wof:name":"Naturpark Bayerischer Wald",
    "wof:placetype":"venue"
},
  "geometry": {"coordinates":[13.2331895828,49.0147514343],"type":"Point"}
}