{
  "type": "Feature",
  "properties": {
    "iso:country":"DE",
    "sg:address":"Helmut-Just-Str. 2",
    "sg:city":"Pirna",
    "sg:phone":"+49 3501/773729",
    "sg:postcode":"01796",
    "sg:province":"Sachsen",
    "wof:name":"Jutta Wenzel",
    "wof:placetype":"venue"
},
  "geometry": {"coordinates":[13.950953,50.95575],"type":"Point"}
}