{
  "type": "Feature",
  "properties": {
    "iso:country":"DE",
    "sg:address":"Bahnhofstr. 72",
    "sg:city":"Eisenh\u00fcttenstadt",
    "sg:phone":"+49 3364/750675",
    "sg:postcode":"15890",
    "sg:province":"Brandenburg",
    "wof:name":"H. Beige",
    "wof:placetype":"venue"
},
  "geometry": {"coordinates":[14.662585,52.147175],"type":"Point"}
}