{
  "type": "Feature",
  "properties": {
    "iso:country":"DE",
    "sg:address":"Dr.-Enders-Str. 55::",
    "sg:city":"Hof",
    "sg:phone":"+49 9281/6070",
    "sg:postcode":"95030",
    "sg:province":"Bayern",
    "wof:name":"Dr Bernd Roedl & Parnter Gmbh Wirtschaftspruefungsges",
    "wof:placetype":"venue"
},
  "geometry": {"coordinates":[11.897847,50.319656],"type":"Point"}
}