{
  "type": "Feature",
  "properties": {
    "iso:country":"DE",
    "sg:address":"Hiening 8",
    "sg:city":"Haibach",
    "sg:phone":"+49 9963/910026",
    "sg:postcode":"94353",
    "sg:province":"Bayern",
    "wof:name":"Ludwig Macht Gmbh",
    "wof:placetype":"venue"
},
  "geometry": {"coordinates":[12.7409152985,49.0443344116],"type":"Point"}
}