{
  "type": "Feature",
  "properties": {
    "iso:country":"DE",
    "sg:address":"Dr.-Georg-Sch\u00e4fer-Str. 11",
    "sg:city":"Furth im Wald",
    "sg:phone":"+49 9973/2058",
    "sg:postcode":"93437",
    "sg:province":"Bayern",
    "wof:name":"Romsped Spedition Gmbh",
    "wof:placetype":"venue"
},
  "geometry": {"coordinates":[12.8520383835,49.3199920654],"type":"Point"}
}