{
  "type": "Feature",
  "properties": {
    "iso:country":"DE",
    "sg:address":"Ehrenfried-Jopp-Str. 55",
    "sg:city":"F\u00fcrstenwalde",
    "sg:phone":"+49 3361/341048",
    "sg:postcode":"15517",
    "sg:province":"Brandenburg",
    "wof:name":"L. Wendlandt",
    "wof:placetype":"venue"
},
  "geometry": {"coordinates":[14.071875,52.365738],"type":"Point"}
}