{
  "type": "Feature",
  "properties": {
    "iso:country":"DE",
    "sg:address":"Kurt-Schumacher-Allee 1",
    "sg:city":"Recklinghausen",
    "sg:postcode":"45657",
    "sg:province":"Nordrhein-Westfalen",
    "wof:name":"Seegesellschaft Haltern Mbh",
    "wof:placetype":"venue"
},
  "geometry": {"coordinates":[7.204043,51.608517],"type":"Point"}
}