{
  "type": "Feature",
  "properties": {
    "iso:country":"DE",
    "sg:address":"Kellerstr. 19",
    "sg:city":"M\u00fcnchen",
    "sg:phone":"+49 89/4802786",
    "sg:postcode":"81667",
    "sg:province":"Bayern",
    "wof:name":"Sophie Sibille U. F. Holfelder",
    "wof:placetype":"venue"
},
  "geometry": {"coordinates":[11.5940065384,48.131061554],"type":"Point"}
}