{
  "type": "Feature",
  "properties": {
    "iso:country":"DE",
    "sg:address":"Holunderweg 4",
    "sg:city":"Schwetzingen",
    "sg:phone":"+49 6202/22785",
    "sg:postcode":"68723",
    "sg:province":"Baden-W\u00fcrttemberg",
    "wof:name":"Dr. E. Meiringer Rechtsanwalt",
    "wof:placetype":"venue"
},
  "geometry": {"coordinates":[8.55098629,49.4058380127],"type":"Point"}
}