{
  "type": "Feature",
  "properties": {
    "iso:country":"DE",
    "sg:address":"Westender Weg 89",
    "sg:city":"Herdecke",
    "sg:phone":"+49 2330/73105",
    "sg:postcode":"58313",
    "sg:province":"Nordrhein-Westfalen",
    "wof:name":"Hans Spiekmann",
    "wof:placetype":"venue"
},
  "geometry": {"coordinates":[7.404532,51.412552],"type":"Point"}
}