{
  "type": "Feature",
  "properties": {
    "iso:country":"DE",
    "sg:address":"Maihaldenstr. 10",
    "sg:city":"Heilbronn",
    "sg:phone":"+49 7131/43259",
    "sg:postcode":"74078",
    "sg:province":"Baden-W\u00fcrttemberg",
    "wof:name":"Alfred Wagner Ingenieur",
    "wof:placetype":"venue"
},
  "geometry": {"coordinates":[9.1668205261,49.1636276245],"type":"Point"}
}