{
  "type": "Feature",
  "properties": {
    "iso:country":"DE",
    "sg:address":"Lenabergweg 4",
    "sg:city":"Schopfloch",
    "sg:phone":"+49 9857/681",
    "sg:postcode":"91626",
    "sg:province":"Bayern",
    "wof:name":"Johannes Meist Kg",
    "wof:placetype":"venue"
},
  "geometry": {"coordinates":[10.304356575,49.118057251],"type":"Point"}
}