{
  "type": "Feature",
  "properties": {
    "iso:country":"DE",
    "sg:address":"Schwanenweg 33",
    "sg:city":"M\u00fcnchen",
    "sg:phone":"+49 89/4302089",
    "sg:postcode":"81827",
    "sg:province":"Bayern",
    "wof:name":"Ifha Int. Fracht- Und Handels-",
    "wof:placetype":"venue"
},
  "geometry": {"coordinates":[11.7091665268,48.1124572754],"type":"Point"}
}