{
  "type": "Feature",
  "properties": {
    "iso:country":"DE",
    "sg:address":"Luisenstr. 8-10",
    "sg:city":"Baden-Baden",
    "sg:phone":"+49 7221/38081",
    "sg:postcode":"76530",
    "sg:province":"Baden-W\u00fcrttemberg",
    "wof:name":"Leo\u00b4s : Restaurant : Cafe : Bar : Baden-baden",
    "wof:placetype":"venue"
},
  "geometry": {"coordinates":[8.238886,48.761635],"type":"Point"}
}