{
  "type": "Feature",
  "properties": {
    "iso:country":"DE",
    "sg:address":"Graffeln 22",
    "sg:city":"B\u00fcren",
    "sg:phone":"+49 2955/1526",
    "sg:postcode":"33142",
    "sg:province":"Nordrhein-Westfalen",
    "wof:name":"Johannes Grote Architekt",
    "wof:placetype":"venue"
},
  "geometry": {"coordinates":[8.646685,51.613602],"type":"Point"}
}