{
  "type": "Feature",
  "properties": {
    "iso:country":"DE",
    "sg:address":"Luisental 10",
    "sg:city":"Bremen",
    "sg:phone":"+49 421/233236",
    "sg:postcode":"28359",
    "sg:province":"Bremen",
    "wof:name":"Magischer Zirkel Bremen E. V. Ulrich Hornbogen",
    "wof:placetype":"venue"
},
  "geometry": {"coordinates":[8.8755054474,53.0981369019],"type":"Point"}
}