{
  "type": "Feature",
  "properties": {
    "iso:country":"DE",
    "sg:address":"Am Holzfeld 38",
    "sg:city":"Schneverdingen",
    "sg:phone":"+49 5193/7800",
    "sg:postcode":"29640",
    "sg:province":"Niedersachsen",
    "wof:name":"Schr\u00f6der",
    "wof:placetype":"venue"
},
  "geometry": {"coordinates":[9.801134,53.124027],"type":"Point"}
}