{
  "type": "Feature",
  "properties": {
    "iso:country":"DE",
    "sg:address":"Neumarktstr. 21",
    "sg:city":"Obernkirchen",
    "sg:phone":"+49 5724/2581",
    "sg:postcode":"31683",
    "sg:province":"Niedersachsen",
    "wof:name":"Brigitte Mestwarp Krankengymnastin",
    "wof:placetype":"venue"
},
  "geometry": {"coordinates":[9.130706,52.272072],"type":"Point"}
}