{
  "type": "Feature",
  "properties": {
    "iso:country":"DE",
    "sg:address":"Stephan-Heise-Str. 17",
    "sg:city":"Frankfurt",
    "sg:phone":"+49 69/763567",
    "sg:postcode":"60488",
    "sg:province":"Hessen",
    "wof:name":"G\u00fcnther Berger Bildhauer",
    "wof:placetype":"venue"
},
  "geometry": {"coordinates":[8.613983,50.134422],"type":"Point"}
}