{
  "type": "Feature",
  "properties": {
    "iso:country":"DE",
    "sg:address":"Saalburgring 11",
    "sg:city":"Bruchk\u00f6bel",
    "sg:phone":"+49 6181/76939",
    "sg:postcode":"63486",
    "sg:province":"Hessen",
    "wof:name":"Paul Makolla",
    "wof:placetype":"venue"
},
  "geometry": {"coordinates":[8.9125413895,50.1858253479],"type":"Point"}
}