{
  "type": "Feature",
  "properties": {
    "iso:country":"DE",
    "sg:address":"Auestr. 45",
    "sg:city":"Frankenberg",
    "sg:phone":"+49 6451/5040",
    "sg:postcode":"35066",
    "sg:province":"Hessen",
    "wof:name":"Finger Gmbh",
    "wof:placetype":"venue"
},
  "geometry": {"coordinates":[8.776144,51.051723],"type":"Point"}
}