{
  "type": "Feature",
  "properties": {
    "iso:country":"DE",
    "sg:address":"Wielandstr. 1",
    "sg:city":"Frickenhausen",
    "sg:phone":"+49 7022/45700",
    "sg:postcode":"72636",
    "sg:province":"Baden-W\u00fcrttemberg",
    "wof:name":"Weinkeller Schneckenhaus",
    "wof:placetype":"venue"
},
  "geometry": {"coordinates":[9.3555250168,48.5932693481],"type":"Point"}
}