{
  "type": "Feature",
  "properties": {
    "iso:country":"DE",
    "sg:address":"Poppenlauerer Str. 13",
    "sg:city":"Ma\u00dfbach",
    "sg:phone":"+49 9735/200",
    "sg:postcode":"97711",
    "sg:province":"Bayern",
    "wof:name":"Luise Endriss",
    "wof:placetype":"venue"
},
  "geometry": {"coordinates":[10.274538,50.184933],"type":"Point"}
}