{
  "type": "Feature",
  "properties": {
    "iso:country":"DE",
    "sg:address":"Mecklenburger Str. 9",
    "sg:city":"Bonn",
    "sg:phone":"+49 228/379739",
    "sg:postcode":"53175",
    "sg:province":"Nordrhein-Westfalen",
    "wof:name":"Ncg",
    "wof:placetype":"venue"
},
  "geometry": {"coordinates":[7.147412,50.702682],"type":"Point"}
}