{
  "type": "Feature",
  "properties": {
    "iso:country":"DE",
    "sg:address":"Schneeberger Str. 13a",
    "sg:city":"Eibenstock",
    "sg:phone":"+49 37752/2250",
    "sg:postcode":"08309",
    "sg:province":"Sachsen",
    "wof:name":"W. Dotzauer",
    "wof:placetype":"venue"
},
  "geometry": {"coordinates":[12.603015,50.502174],"type":"Point"}
}