{
  "type": "Feature",
  "properties": {
    "iso:country":"DE",
    "sg:address":"Milanweg 17 a",
    "sg:city":"Paderborn",
    "sg:postcode":"33100",
    "sg:province":"Nordrhein-Westfalen",
    "wof:name":"Wurzelholzversand Mitte Gmbh",
    "wof:placetype":"venue"
},
  "geometry": {"coordinates":[8.80629,51.719368],"type":"Point"}
}