{
  "type": "Feature",
  "properties": {
    "iso:country":"DE",
    "sg:address":"Okenstr. 101",
    "sg:city":"Offenburg",
    "sg:phone":"+49 4978/1939960",
    "sg:postcode":"77652",
    "sg:province":"Baden-W\u00fcrttemberg",
    "wof:name":"Keller Beleuchtungsk\u00d6rper Gmbh & Co. Kg",
    "wof:placetype":"venue"
},
  "geometry": {"coordinates":[7.947165,48.483643],"type":"Point"}
}