{
  "type": "Feature",
  "properties": {
    "iso:country":"DE",
    "sg:address":"Ulmenallee 2 a",
    "sg:city":"Sieverstedt",
    "sg:postcode":"24885",
    "sg:province":"Schleswig-Holstein",
    "wof:name":"Gerhard Ripke Verwaltungs Gmbh",
    "wof:placetype":"venue"
},
  "geometry": {"coordinates":[9.4746255875,54.6433982849],"type":"Point"}
}