{
  "type": "Feature",
  "properties": {
    "iso:country":"DE",
    "sg:address":"Christus-K\u00f6nig-Weg 14",
    "sg:city":"Duderstadt",
    "sg:phone":"+49 5527/5549",
    "sg:postcode":"37115",
    "sg:province":"Niedersachsen",
    "wof:name":"Ewald Diedrich",
    "wof:placetype":"venue"
},
  "geometry": {"coordinates":[10.227517128,51.5172767639],"type":"Point"}
}