{
  "type": "Feature",
  "properties": {
    "iso:country":"DE",
    "sg:address":"Frankenstr. 3",
    "sg:city":"Hamburg",
    "sg:postcode":"20097",
    "sg:province":"Hamburg",
    "wof:name":"Antares Bau Gmbh & Co. Kg",
    "wof:placetype":"venue"
},
  "geometry": {"coordinates":[10.022857,53.548016],"type":"Point"}
}