{
  "type": "Feature",
  "properties": {
    "iso:country":"DE",
    "sg:address":"Rathenaustr. 5",
    "sg:city":"Leipzig",
    "sg:phone":"+49 341/4511360",
    "sg:postcode":"04179",
    "sg:province":"Sachsen",
    "wof:name":"Preisring Warenhandelsges. Mbh",
    "wof:placetype":"venue"
},
  "geometry": {"coordinates":[12.3149623871,51.349899292],"type":"Point"}
}