{
  "type": "Feature",
  "properties": {
    "iso:country":"DE",
    "sg:address":"Industriestr. 19",
    "sg:city":"Freigericht",
    "sg:phone":"+49 6055/880363",
    "sg:postcode":"63579",
    "sg:province":"Hessen",
    "wof:name":"Dtp Deutsche Thermo Plast Gmbh",
    "wof:placetype":"venue"
},
  "geometry": {"coordinates":[9.137336731,50.1422271729],"type":"Point"}
}