{
  "type": "Feature",
  "properties": {
    "iso:country":"DE",
    "sg:address":"Bismarckstr. 171",
    "sg:city":"Offenbach",
    "sg:postcode":"63067",
    "sg:province":"Hessen",
    "wof:name":"Hant",
    "wof:placetype":"venue"
},
  "geometry": {"coordinates":[8.757835,50.09935],"type":"Point"}
}