{
  "type": "Feature",
  "properties": {
    "iso:country":"DE",
    "sg:address":"Wibbeltstr. 45",
    "sg:city":"Oelde",
    "sg:phone":"+49 2522/62798",
    "sg:postcode":"59302",
    "sg:province":"Nordrhein-Westfalen",
    "wof:name":"Christa Siebert",
    "wof:placetype":"venue"
},
  "geometry": {"coordinates":[8.1529865265,51.8366661072],"type":"Point"}
}