{
  "type": "Feature",
  "properties": {
    "iso:country":"DE",
    "sg:address":"Am Freizeit-Zentrum",
    "sg:city":"Parsberg",
    "sg:phone":"+49 9492/94030",
    "sg:postcode":"92331",
    "sg:province":"Bayern",
    "wof:name":"Moebelhof Parsberg Gmbh",
    "wof:placetype":"venue"
},
  "geometry": {"coordinates":[11.71621418,49.1620140076],"type":"Point"}
}