{
  "type": "Feature",
  "properties": {
    "iso:country":"DE",
    "sg:address":"Querbacher Str. 18",
    "sg:city":"Kehl",
    "sg:phone":"+49 7853/233",
    "sg:postcode":"77694",
    "sg:province":"Baden-W\u00fcrttemberg",
    "wof:name":"Karl Lauck",
    "wof:placetype":"venue"
},
  "geometry": {"coordinates":[7.870146,48.597431],"type":"Point"}
}