{
  "type": "Feature",
  "properties": {
    "iso:country":"DE",
    "sg:address":"Industriestr. 1",
    "sg:city":"Waldkirch",
    "sg:phone":"+49 7681/4778760",
    "sg:postcode":"79183",
    "sg:province":"Baden-W\u00fcrttemberg",
    "wof:name":"Tencate Plasticum Ilkenhans Gmbh",
    "wof:placetype":"venue"
},
  "geometry": {"coordinates":[7.9457092285,48.0867462158],"type":"Point"}
}