{
  "type": "Feature",
  "properties": {
    "iso:country":"DE",
    "sg:address":"Bahnhofstra\u00dfe 27",
    "sg:city":"Stuttgart",
    "sg:phone":"+49 711/550410",
    "sg:postcode":"70372",
    "sg:province":"Baden-W\u00fcrttemberg",
    "wof:name":"Pro Reha Handelsgesellschaft Mbh & Co.kg",
    "wof:placetype":"venue"
},
  "geometry": {"coordinates":[9.218248,48.802052],"type":"Point"}
}