{
  "type": "Feature",
  "properties": {
    "iso:country":"DE",
    "sg:address":"Bederkesaer Str. 52",
    "sg:city":"Langen",
    "sg:phone":"+49 4707/1204",
    "sg:postcode":"27607",
    "sg:province":"Niedersachsen",
    "wof:name":"Waltraud Hiller",
    "wof:placetype":"venue"
},
  "geometry": {"coordinates":[8.704678,53.67416],"type":"Point"}
}