{
  "type": "Feature",
  "properties": {
    "iso:country":"DE",
    "sg:address":"Friedrich-Intorf-Str. 9",
    "sg:city":"Betheln",
    "sg:phone":"+49 5182/1714",
    "sg:postcode":"31032",
    "sg:province":"Niedersachsen",
    "wof:name":"L. Hoffmann",
    "wof:placetype":"venue"
},
  "geometry": {"coordinates":[9.7896442413,52.1092262268],"type":"Point"}
}