{
  "type": "Feature",
  "properties": {
    "iso:country":"DE",
    "sg:address":"Krainh\u00e4ger Weg 50",
    "sg:city":"Obernkirchen",
    "sg:phone":"+49 5724/7722",
    "sg:postcode":"31683",
    "sg:province":"Niedersachsen",
    "wof:name":"Adolf Gehrig",
    "wof:placetype":"venue"
},
  "geometry": {"coordinates":[9.131309,52.255161],"type":"Point"}
}