{
  "type": "Feature",
  "properties": {
    "iso:country":"DE",
    "sg:address":"Darmst\u00e4dter Str. 8",
    "sg:city":"Langen",
    "sg:phone":"+49 6103/21028",
    "sg:postcode":"63225",
    "sg:province":"Hessen",
    "wof:name":"Sabine Frommann Rechsanw\u00e4ltin Und Notarin",
    "wof:placetype":"venue"
},
  "geometry": {"coordinates":[8.6790246964,49.986415863],"type":"Point"}
}