{
  "type": "Feature",
  "properties": {
    "iso:country":"DE",
    "sg:address":"K\u00f6nigstr. 58",
    "sg:city":"Hof",
    "sg:phone":"+49 9281/15973",
    "sg:postcode":"95028",
    "sg:province":"Bayern",
    "wof:name":"Dentatech Gmbh",
    "wof:placetype":"venue"
},
  "geometry": {"coordinates":[11.9200305939,50.3130187988],"type":"Point"}
}