{
  "type": "Feature",
  "properties": {
    "iso:country":"DE",
    "sg:address":"Hainsche Str. 13",
    "sg:city":"Bad Liebenwerda",
    "sg:phone":"+49 35341/10413",
    "sg:postcode":"04924",
    "sg:province":"Brandenburg",
    "wof:name":"Alfred Zehmisch",
    "wof:placetype":"venue"
},
  "geometry": {"coordinates":[13.3967456818,51.5148506165],"type":"Point"}
}