{
  "type": "Feature",
  "properties": {
    "iso:country":"DE",
    "sg:address":"Bahnhofstr. 107",
    "sg:city":"Gr\u00e4fenroda",
    "sg:phone":"+49 36205/77167",
    "sg:postcode":"99330",
    "sg:province":"Th\u00fcringen",
    "wof:name":"Fantasia 2000 Imbiss",
    "wof:placetype":"venue"
},
  "geometry": {"coordinates":[10.8272562027,50.7579307556],"type":"Point"}
}