{
  "type": "Feature",
  "properties": {
    "iso:country":"DE",
    "sg:address":"Schierke 6",
    "sg:city":"Salzgitter",
    "sg:phone":"+49 5341/58849",
    "sg:postcode":"38228",
    "sg:province":"Niedersachsen",
    "wof:name":"B. Treuheit",
    "wof:placetype":"venue"
},
  "geometry": {"coordinates":[10.295659,52.132195],"type":"Point"}
}