{
  "type": "Feature",
  "properties": {
    "iso:country":"DE",
    "sg:address":"Mainzer Str. 98-102",
    "sg:city":"Wiesbaden",
    "sg:phone":"+49 611",
    "sg:postcode":"65189",
    "sg:province":"Hessen",
    "wof:name":"Hessenenergie",
    "wof:placetype":"venue"
},
  "geometry": {"coordinates":[8.249804,50.067547],"type":"Point"}
}