{
  "type": "Feature",
  "properties": {
    "iso:country":"DE",
    "sg:address":"Beguinenstr. 15",
    "sg:city":"Coesfeld",
    "sg:postcode":"48653",
    "sg:province":"Nordrhein-Westfalen",
    "wof:name":"Radiologie-coesfeld: Diagnostik",
    "wof:placetype":"venue"
},
  "geometry": {"coordinates":[7.169891,51.943909],"type":"Point"}
}