{
  "type": "Feature",
  "properties": {
    "iso:country":"DE",
    "sg:address":"Sebastian-Kneipp-Str. 4",
    "sg:city":"Hindelang",
    "sg:phone":"+49 8324/642",
    "sg:postcode":"87541",
    "sg:province":"Bayern",
    "wof:name":"Cafe-fremdenheim Sonja",
    "wof:placetype":"venue"
},
  "geometry": {"coordinates":[10.3738241196,47.5044784546],"type":"Point"}
}