{
  "type": "Feature",
  "properties": {
    "iso:country":"DE",
    "sg:address":"Breite Str. 18",
    "sg:city":"Mainz",
    "sg:phone":"+49 6131/44753",
    "sg:postcode":"55124",
    "sg:province":"Rheinland-Pfalz",
    "wof:name":"Walter Lenert",
    "wof:placetype":"venue"
},
  "geometry": {"coordinates":[8.2098445892,50.0025253296],"type":"Point"}
}