{
  "type": "Feature",
  "properties": {
    "iso:country":"DE",
    "sg:address":"Am Dobben 65",
    "sg:city":"Bremen",
    "sg:phone":"+49 421/705375",
    "sg:postcode":"28203",
    "sg:province":"Bremen",
    "wof:name":"Esra-reisen Inh. Leyla Celik",
    "wof:placetype":"venue"
},
  "geometry": {"coordinates":[8.8227024078,53.0738334656],"type":"Point"}
}