{
  "type": "Feature",
  "properties": {
    "iso:country":"DE",
    "sg:address":"Schubertstr. 17",
    "sg:city":"Schwetzingen",
    "sg:phone":"+49 6202/23100",
    "sg:postcode":"68723",
    "sg:province":"Baden-W\u00fcrttemberg",
    "wof:name":"Aldi Gmbh & Co. Kg",
    "wof:placetype":"venue"
},
  "geometry": {"coordinates":[8.5794296265,49.3887290955],"type":"Point"}
}