{
  "type": "Feature",
  "properties": {
    "iso:country":"DE",
    "sg:address":"Sponackerweg 56",
    "sg:city":"Haibach",
    "sg:phone":"+49 6021/61927",
    "sg:postcode":"63808",
    "sg:province":"Bayern",
    "wof:name":"Ibb Engineering",
    "wof:placetype":"venue"
},
  "geometry": {"coordinates":[9.1884975433,49.9643249512],"type":"Point"}
}