{
  "type": "Feature",
  "properties": {
    "iso:country":"DE",
    "sg:address":"Langemattstr. 30",
    "sg:city":"Neuried",
    "sg:phone":"+49 7807/30612",
    "sg:postcode":"77743",
    "sg:province":"Baden-W\u00fcrttemberg",
    "wof:name":"Hans Niekamp Architekt",
    "wof:placetype":"venue"
},
  "geometry": {"coordinates":[7.826528,48.453449],"type":"Point"}
}