{
  "type": "Feature",
  "properties": {
    "iso:country":"DE",
    "sg:address":"Haus der Mode 4",
    "sg:city":"Eschborn",
    "sg:phone":"+49 6196/48851",
    "sg:postcode":"65760",
    "sg:province":"Hessen",
    "wof:name":"Ver Tex Vertriebsges. F\u00fcr Textil-einrichtungsbedarf Mbh",
    "wof:placetype":"venue"
},
  "geometry": {"coordinates":[8.5721111298,50.1404151917],"type":"Point"}
}