{
  "type": "Feature",
  "properties": {
    "iso:country":"DE",
    "sg:address":"Elbgaustr. 80",
    "sg:city":"Hamburg",
    "sg:phone":"+49 40/5709186",
    "sg:postcode":"22523",
    "sg:province":"Hamburg",
    "wof:name":"Paul Schilling",
    "wof:placetype":"venue"
},
  "geometry": {"coordinates":[9.897181,53.605133],"type":"Point"}
}