{
  "type": "Feature",
  "properties": {
    "iso:country":"DE",
    "sg:address":"Eulespring 5",
    "sg:city":"Magdeburg",
    "sg:phone":"+49 391/6313499",
    "sg:postcode":"39116",
    "sg:province":"Sachsen-Anhalt",
    "wof:name":"Bernd Wolter Bauunternehmung Gmbh",
    "wof:placetype":"venue"
},
  "geometry": {"coordinates":[11.5686416626,52.0876197815],"type":"Point"}
}