{
  "type": "Feature",
  "properties": {
    "iso:country":"DE",
    "sg:address":"Ludwigsplatz 17",
    "sg:city":"Rosenheim",
    "sg:phone":"+49 8031/37836",
    "sg:postcode":"83022",
    "sg:province":"Bayern",
    "wof:name":"Georg Stelle",
    "wof:placetype":"venue"
},
  "geometry": {"coordinates":[12.128977,47.856586],"type":"Point"}
}