{
  "type": "Feature",
  "properties": {
    "iso:country":"DE",
    "sg:address":"Herrngartenstr. 40",
    "sg:city":"Fischbachtal",
    "sg:phone":"+49 6166/60156",
    "sg:postcode":"64405",
    "sg:province":"Hessen",
    "wof:name":"Horst Und Karl-heinz Greschner Haustechnik Gmbh",
    "wof:placetype":"venue"
},
  "geometry": {"coordinates":[8.810819,49.767639],"type":"Point"}
}