{
  "type": "Feature",
  "properties": {
    "iso:country":"DE",
    "sg:address":"Industriestr. 14",
    "sg:city":"Adelsdorf",
    "sg:phone":"+49 9195/94550",
    "sg:postcode":"91325",
    "sg:province":"Bayern",
    "wof:name":"Frankonia-elektronik Gmbh",
    "wof:placetype":"venue"
},
  "geometry": {"coordinates":[10.880281,49.707577],"type":"Point"}
}