{
  "type": "Feature",
  "properties": {
    "iso:country":"DE",
    "sg:address":"In der Olpke 4",
    "sg:city":"Werl",
    "sg:phone":"+49 2922/5031",
    "sg:postcode":"59457",
    "sg:province":"Nordrhein-Westfalen",
    "wof:name":"Prinz & Co. Gmbh",
    "wof:placetype":"venue"
},
  "geometry": {"coordinates":[7.9580879211,51.55701828],"type":"Point"}
}