{
  "type": "Feature",
  "properties": {
    "iso:country":"DE",
    "sg:address":"Pastorenkamp 1",
    "sg:city":"H\u00f6rstel",
    "sg:phone":"+49 5459/9530",
    "sg:postcode":"48477",
    "sg:province":"Nordrhein-Westfalen",
    "wof:name":"Norbert Liedmeyer Diplom-bauingenieur",
    "wof:placetype":"venue"
},
  "geometry": {"coordinates":[7.5869469643,52.3043251038],"type":"Point"}
}