{
  "type": "Feature",
  "properties": {
    "iso:country":"DE",
    "sg:address":"Paulstr. 3",
    "sg:city":"Hamburg",
    "sg:phone":"+49 40/448735",
    "sg:postcode":"20095",
    "sg:province":"Hamburg",
    "wof:name":"React Christian Rating",
    "wof:placetype":"venue"
},
  "geometry": {"coordinates":[9.9969377518,53.550868988],"type":"Point"}
}