{
  "type": "Feature",
  "properties": {
    "iso:country":"DE",
    "sg:address":"Altener Str. 43",
    "sg:city":"Dessau",
    "sg:phone":"+49 340/618544",
    "sg:postcode":"06847",
    "sg:province":"Sachsen-Anhalt",
    "wof:name":"Wolf Toner Recycling Systeme",
    "wof:placetype":"venue"
},
  "geometry": {"coordinates":[12.2046766281,51.8124275208],"type":"Point"}
}