{
  "type": "Feature",
  "properties": {
    "iso:country":"DE",
    "sg:address":"Ringstr. 28",
    "sg:city":"Kiel",
    "sg:phone":"+49 431/671115",
    "sg:postcode":"24103",
    "sg:province":"Schleswig-Holstein",
    "wof:name":"Nuppenau",
    "wof:placetype":"venue"
},
  "geometry": {"coordinates":[10.1276540756,54.3157119751],"type":"Point"}
}