{
  "type": "Feature",
  "properties": {
    "iso:country":"DE",
    "sg:address":"Am G\u00fcterbahnhof 9",
    "sg:city":"Biberach",
    "sg:phone":"+49 7835/5648",
    "sg:postcode":"77781",
    "sg:province":"Baden-W\u00fcrttemberg",
    "wof:name":"Raiffeisen-warengenossenschaft Biberach Zell Eg",
    "wof:placetype":"venue"
},
  "geometry": {"coordinates":[8.033083,48.337826],"type":"Point"}
}