{
  "type": "Feature",
  "properties": {
    "iso:country":"DE",
    "sg:address":"Kuckucksblumenstr. 10",
    "sg:city":"M\u00fcnchen",
    "sg:phone":"+49 89/1505124",
    "sg:postcode":"80995",
    "sg:province":"Bayern",
    "wof:name":"Erich Schneider",
    "wof:placetype":"venue"
},
  "geometry": {"coordinates":[11.522238,48.198402],"type":"Point"}
}