{
  "type": "Feature",
  "properties": {
    "iso:country":"DE",
    "sg:address":"Ruhesteinstr. 479",
    "sg:city":"Baiersbronn",
    "sg:phone":"+49 7449/330",
    "sg:postcode":"72270",
    "sg:province":"Baden-W\u00fcrttemberg",
    "wof:name":"Gotthilf G\u00fcnter",
    "wof:placetype":"venue"
},
  "geometry": {"coordinates":[8.2981290817,48.5324440002],"type":"Point"}
}