{
  "type": "Feature",
  "properties": {
    "iso:country":"DE",
    "sg:address":"Grenzstr. 14",
    "sg:city":"L\u00fctzkampen",
    "sg:phone":"+49 6559/287",
    "sg:postcode":"54617",
    "sg:province":"Rheinland-Pfalz",
    "wof:name":"Josef Reinartz Elektroinstallation",
    "wof:placetype":"venue"
},
  "geometry": {"coordinates":[6.18774,50.149094],"type":"Point"}
}