{
  "type": "Feature",
  "properties": {
    "iso:country":"DE",
    "sg:address":"Am Hohen Weg 20",
    "sg:city":"Kottgeisering",
    "sg:phone":"+49 8144/7216",
    "sg:postcode":"82288",
    "sg:province":"Bayern",
    "wof:name":"Lichem",
    "wof:placetype":"venue"
},
  "geometry": {"coordinates":[11.1376457214,48.1244392395],"type":"Point"}
}