{
  "type": "Feature",
  "properties": {
    "iso:country":"DE",
    "sg:address":"Kurze Str. 11",
    "sg:city":"Bockhorn",
    "sg:phone":"+49 4453/72965",
    "sg:postcode":"26345",
    "sg:province":"Niedersachsen",
    "wof:name":"Wsa Werkzeugmaschinen- Handels Gmbh",
    "wof:placetype":"venue"
},
  "geometry": {"coordinates":[8.0220832825,53.3927154541],"type":"Point"}
}