{
  "type": "Feature",
  "properties": {
    "iso:country":"DE",
    "sg:address":"Alleestr. 5",
    "sg:city":"Solingen",
    "sg:phone":"+49 4921/256474",
    "sg:postcode":"42653",
    "sg:province":"Nordrhein-Westfalen",
    "wof:name":"Richter & Kattwinkel",
    "wof:placetype":"venue"
},
  "geometry": {"coordinates":[7.0792541504,51.1883430481],"type":"Point"}
}