{
  "type": "Feature",
  "properties": {
    "iso:country":"DE",
    "sg:address":"Am Hahnenschnabel 26",
    "sg:city":"Heidenheim",
    "sg:phone":"+49 7321/41346",
    "sg:postcode":"89520",
    "sg:province":"Baden-W\u00fcrttemberg",
    "wof:name":"Kurt Gr\u00fcner Steuerberater",
    "wof:placetype":"venue"
},
  "geometry": {"coordinates":[10.1543216705,48.6929931641],"type":"Point"}
}