{
  "type": "Feature",
  "properties": {
    "iso:country":"DE",
    "sg:address":"Oelsen 22",
    "sg:city":"Gro\u00df Briesen",
    "sg:postcode":"15848",
    "sg:province":"Brandenburg",
    "wof:name":"Karras Diamant - Technik Gmbh",
    "wof:placetype":"venue"
},
  "geometry": {"coordinates":[14.1746101379,52.2288208008],"type":"Point"}
}