{
  "type": "Feature",
  "properties": {
    "iso:country":"DE",
    "sg:address":"Stresemannstr. 90",
    "sg:city":"Berlin",
    "sg:phone":"+49 30/2308220",
    "sg:postcode":"10963",
    "sg:province":"Berlin",
    "wof:name":"Institut F\u00fcr St\u00e4dtebau",
    "wof:placetype":"venue"
},
  "geometry": {"coordinates":[13.3821592331,52.5049591064],"type":"Point"}
}