{
  "type": "Feature",
  "properties": {
    "iso:country":"DE",
    "sg:address":"Gottlieb-Daimler-Str. 41",
    "sg:city":"Murr",
    "sg:phone":"+49 7144/22900",
    "sg:postcode":"71711",
    "sg:province":"Baden-W\u00fcrttemberg",
    "wof:name":"Gasthof Holzwurm",
    "wof:placetype":"venue"
},
  "geometry": {"coordinates":[9.2450790405,48.956161499],"type":"Point"}
}