{
  "type": "Feature",
  "properties": {
    "iso:country":"DE",
    "sg:address":"Landstr. 6",
    "sg:city":"Bad Lausick",
    "sg:phone":"+49 34345/22055",
    "sg:postcode":"04651",
    "sg:province":"Sachsen",
    "wof:name":"R. K\u00fchn",
    "wof:placetype":"venue"
},
  "geometry": {"coordinates":[12.659257,51.160213],"type":"Point"}
}