{
  "type": "Feature",
  "properties": {
    "iso:country":"DE",
    "sg:address":"Wattenbergstr. 12",
    "sg:city":"Schauenburg",
    "sg:phone":"+49 5601/5711",
    "sg:postcode":"34270",
    "sg:province":"Hessen",
    "wof:name":"Treffpunkt",
    "wof:placetype":"venue"
},
  "geometry": {"coordinates":[9.2865056992,51.2874336243],"type":"Point"}
}