{
  "type": "Feature",
  "properties": {
    "iso:country":"DE",
    "sg:address":"Widenmayerstr. 36",
    "sg:city":"M\u00fcnchen",
    "sg:phone":"+49 89/2289476",
    "sg:postcode":"80538",
    "sg:province":"Bayern",
    "wof:name":"Hovis Gmbh Co Stever & Beiten",
    "wof:placetype":"venue"
},
  "geometry": {"coordinates":[11.5952577591,48.1450958252],"type":"Point"}
}