{
  "type": "Feature",
  "properties": {
    "iso:country":"DE",
    "sg:address":"Mittelstr. 18",
    "sg:city":"Gera",
    "sg:phone":"+49 365/52286",
    "sg:postcode":"07546",
    "sg:province":"Th\u00fcringen",
    "wof:name":"K. Meyer",
    "wof:placetype":"venue"
},
  "geometry": {"coordinates":[12.092198,50.880688],"type":"Point"}
}