{
  "type": "Feature",
  "properties": {
    "iso:country":"DE",
    "sg:address":"Marktplatz 5",
    "sg:city":"Weiler",
    "sg:phone":"+49 6754/1843",
    "sg:postcode":"55627",
    "sg:province":"Rheinland-Pfalz",
    "wof:name":"Karl Heinrich",
    "wof:placetype":"venue"
},
  "geometry": {"coordinates":[7.560974,49.808807],"type":"Point"}
}