{
  "type": "Feature",
  "properties": {
    "iso:country":"DE",
    "sg:address":"Lichtenbergplatz 3",
    "sg:city":"Hannover",
    "sg:phone":"+49 511/457263",
    "sg:postcode":"30449",
    "sg:province":"Niedersachsen",
    "wof:name":"Heide Bahner",
    "wof:placetype":"venue"
},
  "geometry": {"coordinates":[9.7128562927,52.3689880371],"type":"Point"}
}