{
  "type": "Feature",
  "properties": {
    "iso:country":"DE",
    "sg:address":"Lerchenstr. 3",
    "sg:city":"Norden",
    "sg:phone":"+49 4931/4501",
    "sg:postcode":"26506",
    "sg:province":"Niedersachsen",
    "wof:name":"G. Hasbargen",
    "wof:placetype":"venue"
},
  "geometry": {"coordinates":[7.1904611588,53.5995941162],"type":"Point"}
}