{
  "type": "Feature",
  "properties": {
    "iso:country":"DE",
    "sg:address":"Mittelweg 10",
    "sg:city":"Prohn",
    "sg:phone":"+49 38323/81408",
    "sg:postcode":"18445",
    "sg:province":"Mecklenburg-Vorpommern",
    "wof:name":"Eckhard Reinke",
    "wof:placetype":"venue"
},
  "geometry": {"coordinates":[13.0265283585,54.3768959045],"type":"Point"}
}