{
  "type": "Feature",
  "properties": {
    "iso:country":"DE",
    "sg:address":"Marktplatz 6",
    "sg:city":"Weissenburg",
    "sg:phone":"+49 9141/997207",
    "sg:postcode":"91781",
    "sg:province":"Bayern",
    "wof:name":"Kurtzweylig Reisen",
    "wof:placetype":"venue"
},
  "geometry": {"coordinates":[10.971665,49.03067],"type":"Point"}
}