{
  "type": "Feature",
  "properties": {
    "iso:country":"DE",
    "sg:address":"Patriotischer Weg 12 a",
    "sg:city":"Rostock",
    "sg:phone":"+49 381/203000",
    "sg:postcode":"18057",
    "sg:province":"Mecklenburg-Vorpommern",
    "wof:name":"Hardt Und R\u00f6mmling Rechtsanw\u00e4lte",
    "wof:placetype":"venue"
},
  "geometry": {"coordinates":[12.1239748001,54.0904541016],"type":"Point"}
}