{
  "type": "Feature",
  "properties": {
    "iso:country":"DE",
    "sg:address":"Helle Schlah 6",
    "sg:city":"Attendorn",
    "sg:postcode":"57439",
    "sg:province":"Nordrhein-Westfalen",
    "wof:name":"Niekamp Und Looks Verwaltungs Gmbh",
    "wof:placetype":"venue"
},
  "geometry": {"coordinates":[7.842446804,51.1488342285],"type":"Point"}
}