{
  "type": "Feature",
  "properties": {
    "iso:country":"DE",
    "sg:address":"Wollgasse 11",
    "sg:city":"Andernach",
    "sg:phone":"+49 2632/45971",
    "sg:postcode":"56626",
    "sg:province":"Rheinland-Pfalz",
    "wof:name":"Sch\u00f6nes Wohnen",
    "wof:placetype":"venue"
},
  "geometry": {"coordinates":[7.40172,50.438759],"type":"Point"}
}