{
  "type": "Feature",
  "properties": {
    "iso:country":"DE",
    "sg:address":"Benroder Str. 2",
    "sg:city":"Uetze",
    "sg:phone":"+49 5173/922015",
    "sg:postcode":"31311",
    "sg:province":"Niedersachsen",
    "wof:name":"Hartmut Gerloff Architekt",
    "wof:placetype":"venue"
},
  "geometry": {"coordinates":[10.215318,52.47102],"type":"Point"}
}