{
  "type": "Feature",
  "properties": {
    "iso:country":"DE",
    "sg:address":"Veener Weg 24 a",
    "sg:city":"Xanten",
    "sg:phone":"+49 2801/2487",
    "sg:postcode":"46509",
    "sg:province":"Nordrhein-Westfalen",
    "wof:name":"Johannes H\u00fclsmann",
    "wof:placetype":"venue"
},
  "geometry": {"coordinates":[6.456738,51.648808],"type":"Point"}
}