{
  "type": "Feature",
  "properties": {
    "iso:country":"DE",
    "sg:address":"Treitschkestr. 6",
    "sg:city":"M\u00fcnchen",
    "sg:postcode":"80992",
    "sg:province":"Bayern",
    "wof:name":"Mada Fix Gmbh",
    "wof:placetype":"venue"
},
  "geometry": {"coordinates":[11.5227527618,48.1770896912],"type":"Point"}
}