{
  "type": "Feature",
  "properties": {
    "iso:country":"DE",
    "sg:address":"K\u00fchlenfels 67",
    "sg:city":"Pottenstein",
    "sg:phone":"+49 9243/382",
    "sg:postcode":"91278",
    "sg:province":"Bayern",
    "wof:name":"Friedrich Neuner",
    "wof:placetype":"venue"
},
  "geometry": {"coordinates":[11.4250898361,49.7356109619],"type":"Point"}
}