{
  "type": "Feature",
  "properties": {
    "iso:country":"DE",
    "sg:address":"H\u00fcnerbergweg 26",
    "sg:city":"L\u00f6rrach",
    "sg:phone":"+49 7621/2066",
    "sg:postcode":"79539",
    "sg:province":"Baden-W\u00fcrttemberg",
    "wof:name":"Hotel Villa Elben",
    "wof:placetype":"venue"
},
  "geometry": {"coordinates":[7.6677050591,47.6120872498],"type":"Point"}
}