{
  "type": "Feature",
  "properties": {
    "iso:country":"DE",
    "sg:address":"Breiteweg 144",
    "sg:city":"Barleben",
    "sg:phone":"+49 39203/7516",
    "sg:postcode":"39179",
    "sg:province":"Sachsen-Anhalt",
    "wof:name":"Busa Brandschutz Und Sicherheitsanlagen Gmbh",
    "wof:placetype":"venue"
},
  "geometry": {"coordinates":[11.6184158325,52.2022590637],"type":"Point"}
}