{
  "type": "Feature",
  "properties": {
    "iso:country":"DE",
    "sg:address":"Im Berg 16",
    "sg:city":"Wei\u00dfenthurm",
    "sg:phone":"+49 2637/8790",
    "sg:postcode":"56575",
    "sg:province":"Rheinland-Pfalz",
    "wof:name":"H. Korth",
    "wof:placetype":"venue"
},
  "geometry": {"coordinates":[7.46083498,50.4067382812],"type":"Point"}
}