{
  "type": "Feature",
  "properties": {
    "iso:country":"DE",
    "sg:address":"\u00d6sterblick 1",
    "sg:city":"Meldorf",
    "sg:phone":"+49 4832/4218",
    "sg:postcode":"25704",
    "sg:province":"Schleswig-Holstein",
    "wof:name":"Taverna Ellena",
    "wof:placetype":"venue"
},
  "geometry": {"coordinates":[9.0891103745,54.0888137817],"type":"Point"}
}