{
  "type": "Feature",
  "properties": {
    "iso:country":"DE",
    "sg:address":"Bahnhofstr. 8",
    "sg:city":"S\u00fcnching",
    "sg:phone":"+49 9480/1480",
    "sg:postcode":"93104",
    "sg:province":"Bayern",
    "wof:name":"Karl Scheid",
    "wof:placetype":"venue"
},
  "geometry": {"coordinates":[12.354382,48.880909],"type":"Point"}
}