{
  "type": "Feature",
  "properties": {
    "iso:country":"DE",
    "sg:address":"Adolph-Kolping-Str. 11",
    "sg:city":"R\u00f6tz",
    "sg:phone":"+49 9976/792",
    "sg:postcode":"92444",
    "sg:province":"Bayern",
    "wof:name":"J. Und J. Ruhland",
    "wof:placetype":"venue"
},
  "geometry": {"coordinates":[12.5271053314,49.3441009521],"type":"Point"}
}