{
  "type": "Feature",
  "properties": {
    "iso:country":"DE",
    "sg:address":"Friedrichstr. 8",
    "sg:city":"L\u00fcdenscheid",
    "sg:postcode":"58507",
    "sg:province":"Nordrhein-Westfalen",
    "wof:name":"Villa Kunterbunt E. V.",
    "wof:placetype":"venue"
},
  "geometry": {"coordinates":[7.6278009415,51.2179298401],"type":"Point"}
}