{
  "type": "Feature",
  "properties": {
    "iso:country":"DE",
    "sg:address":"Am Sieberdamm 3",
    "sg:city":"Herzberg",
    "sg:phone":"+49 5521/3336",
    "sg:postcode":"37412",
    "sg:province":"Niedersachsen",
    "wof:name":"Walter Henze E. K.",
    "wof:placetype":"venue"
},
  "geometry": {"coordinates":[10.2875213623,51.6688423157],"type":"Point"}
}