{
  "type": "Feature",
  "properties": {
    "iso:country":"DE",
    "sg:address":"Sonnenwald",
    "sg:city":"Sch\u00f6fweg",
    "sg:phone":"+49 9908/317",
    "sg:postcode":"94572",
    "sg:province":"Bayern",
    "wof:name":"B\u00fccherei Sporthotel Sonnenwald",
    "wof:placetype":"venue"
},
  "geometry": {"coordinates":[13.2331047058,48.8399200439],"type":"Point"}
}