{
  "type": "Feature",
  "properties": {
    "iso:country":"DE",
    "sg:address":"Brauhausstr. 32",
    "sg:city":"Lauter",
    "sg:phone":"+49 3771/51777",
    "sg:postcode":"08312",
    "sg:province":"Sachsen",
    "wof:name":"Lutz Reichel",
    "wof:placetype":"venue"
},
  "geometry": {"coordinates":[12.7428569794,50.5637054443],"type":"Point"}
}