{
  "type": "Feature",
  "properties": {
    "iso:country":"DE",
    "sg:address":"Juri-Gagarin-Str. 19",
    "sg:city":"Halberstadt",
    "sg:phone":"+49 3941/68950",
    "sg:postcode":"38820",
    "sg:province":"Sachsen-Anhalt",
    "wof:name":"Veranstaltungskalender Harz",
    "wof:placetype":"venue"
},
  "geometry": {"coordinates":[11.06935,51.895649],"type":"Point"}
}