{
  "type": "Feature",
  "properties": {
    "iso:country":"DE",
    "sg:address":"Hauptstr. 37",
    "sg:city":"Birkenau",
    "sg:phone":"+49 6201/33337",
    "sg:postcode":"69488",
    "sg:province":"Hessen",
    "wof:name":"Mbb Marketing Beratung Gmbh Birkenau",
    "wof:placetype":"venue"
},
  "geometry": {"coordinates":[8.7003517151,49.5616798401],"type":"Point"}
}