{
  "type": "Feature",
  "properties": {
    "iso:country":"DE",
    "sg:address":"Schlo\u00dfstr. 21",
    "sg:city":"Waldheim",
    "sg:phone":"+49 34327/93187",
    "sg:postcode":"04736",
    "sg:province":"Sachsen",
    "wof:name":"Matthias M\u00f6ller",
    "wof:placetype":"venue"
},
  "geometry": {"coordinates":[13.0252609253,51.0731697083],"type":"Point"}
}