{
  "type": "Feature",
  "properties": {
    "iso:country":"DE",
    "sg:address":"Herrenwiesenweg 5",
    "sg:city":"Dreieich",
    "sg:phone":"+49 6074/861313",
    "sg:postcode":"63303",
    "sg:province":"Hessen",
    "wof:name":"Reisestudio Offenthal Thomas Stelzer",
    "wof:placetype":"venue"
},
  "geometry": {"coordinates":[8.7430496216,49.9808998108],"type":"Point"}
}