{
  "type": "Feature",
  "properties": {
    "iso:country":"DE",
    "sg:address":"Zittauer Str. 2",
    "sg:city":"Leipzig",
    "sg:phone":"+49 341/2330226",
    "sg:postcode":"04347",
    "sg:province":"Sachsen",
    "wof:name":"Fischfachgesch\u00e4ft Eichler Gmbh",
    "wof:placetype":"venue"
},
  "geometry": {"coordinates":[12.4140777588,51.3557701111],"type":"Point"}
}