{
  "type": "Feature",
  "properties": {
    "iso:country":"DE",
    "sg:address":"Birkenstra\u00dfe 24",
    "sg:city":"Ahlerstedt",
    "sg:phone":"+49 4166/848377",
    "sg:postcode":"21702",
    "sg:province":"Niedersachsen",
    "wof:name":"Professionelles Konfliktmanagement",
    "wof:placetype":"venue"
},
  "geometry": {"coordinates":[9.431775,53.362701],"type":"Point"}
}