{
  "type": "Feature",
  "properties": {
    "iso:country":"DE",
    "sg:address":"Massiefen 1-5",
    "sg:city":"Burscheid",
    "sg:phone":"+49 2174/780577",
    "sg:postcode":"51399",
    "sg:province":"Nordrhein-Westfalen",
    "wof:name":"Jeuken & Di Monaco Oberfl\u00e4chentechnik",
    "wof:placetype":"venue"
},
  "geometry": {"coordinates":[7.09593,51.086571],"type":"Point"}
}