{
  "type": "Feature",
  "properties": {
    "iso:country":"DE",
    "sg:address":"Timm-Kr\u00f6ger-Str. 2",
    "sg:city":"Elmshorn",
    "sg:phone":"+49 4121/65956",
    "sg:postcode":"25336",
    "sg:province":"Schleswig-Holstein",
    "wof:name":"Michels Eck",
    "wof:placetype":"venue"
},
  "geometry": {"coordinates":[9.6578741074,53.7394256592],"type":"Point"}
}