{
  "type": "Feature",
  "properties": {
    "iso:country":"DE",
    "sg:address":"Schlei\u00dfheimer Str. 46 c",
    "sg:city":"M\u00fcnchen",
    "sg:phone":"+49 89/52388099",
    "sg:postcode":"80333",
    "sg:province":"Bayern",
    "wof:name":"Martin Falk Rechtsanwalt",
    "wof:placetype":"venue"
},
  "geometry": {"coordinates":[11.5602035522,48.1509170532],"type":"Point"}
}