{
  "type": "Feature",
  "properties": {
    "iso:country":"DE",
    "sg:address":"Goethestr. 1",
    "sg:city":"Ilmenau",
    "sg:phone":"+49 3677/62044",
    "sg:postcode":"98693",
    "sg:province":"Th\u00fcringen",
    "wof:name":"Sauna Atoll",
    "wof:placetype":"venue"
},
  "geometry": {"coordinates":[10.90741,50.680248],"type":"Point"}
}