{
  "type": "Feature",
  "properties": {
    "iso:country":"DE",
    "sg:address":"Fridericusstr. 2",
    "sg:city":"M\u00fcnster",
    "sg:phone":"+49 2533/525",
    "sg:postcode":"48161",
    "sg:province":"Nordrhein-Westfalen",
    "wof:name":"Ms Gesch\u00e4ftshaus Halle Verwaltungs-gmbh",
    "wof:placetype":"venue"
},
  "geometry": {"coordinates":[7.5481362343,51.9964561462],"type":"Point"}
}