{
  "type": "Feature",
  "properties": {
    "iso:country":"DE",
    "sg:address":"Kopernikusstr. 1",
    "sg:city":"Rodgau",
    "sg:phone":"+49 6106/8240",
    "sg:postcode":"63110",
    "sg:province":"Hessen",
    "wof:name":"Semikon Gmbh & Co. Management Kg",
    "wof:placetype":"venue"
},
  "geometry": {"coordinates":[8.8835792542,49.9985313416],"type":"Point"}
}