{
  "type": "Feature",
  "properties": {
    "iso:country":"DE",
    "sg:city":"Hilgermissen",
    "sg:phone":"+49 4942/51409",
    "sg:postcode":"27318",
    "sg:province":"Niedersachsen",
    "wof:name":"Volksbank Grafschaft Hoya Eg",
    "wof:placetype":"venue"
},
  "geometry": {"coordinates":[9.148241,52.84557],"type":"Point"}
}