{
  "type": "Feature",
  "properties": {
    "iso:country":"DE",
    "sg:address":"Bahnhofstr. 3",
    "sg:city":"Waiblingen",
    "sg:phone":"+49 4971/5117110",
    "sg:postcode":"71334",
    "sg:province":"Baden-W\u00fcrttemberg",
    "wof:name":"Dresdner Bank Ag",
    "wof:placetype":"venue"
},
  "geometry": {"coordinates":[9.314195,48.829605],"type":"Point"}
}