{
  "type": "Feature",
  "properties": {
    "iso:country":"DE",
    "sg:address":"Steinweg 19",
    "sg:city":"Wetter",
    "sg:phone":"+49 6423/6527",
    "sg:postcode":"35083",
    "sg:province":"Hessen",
    "wof:name":"Ludwig G\u00f6bel",
    "wof:placetype":"venue"
},
  "geometry": {"coordinates":[8.6463975906,50.8892860413],"type":"Point"}
}