{
  "type": "Feature",
  "properties": {
    "iso:country":"DE",
    "sg:address":"Griesener Str. 13",
    "sg:city":"Grainau",
    "sg:phone":"+49 8821/51655",
    "sg:postcode":"82491",
    "sg:province":"Bayern",
    "wof:name":"Xaver Erhard",
    "wof:placetype":"venue"
},
  "geometry": {"coordinates":[11.0529937744,47.4792671204],"type":"Point"}
}