{
  "type": "Feature",
  "properties": {
    "iso:country":"DE",
    "sg:address":"Hintere Gasse 2",
    "sg:city":"Buchloe",
    "sg:phone":"+49 8241/5999",
    "sg:postcode":"86807",
    "sg:province":"Bayern",
    "wof:name":"D. Und F. Hank",
    "wof:placetype":"venue"
},
  "geometry": {"coordinates":[10.722492218,48.0366516113],"type":"Point"}
}