{
  "type": "Feature",
  "properties": {
    "iso:country":"DE",
    "sg:address":"Katharinenstr. 1",
    "sg:city":"H\u00fcckelhoven",
    "sg:phone":"+49 2433/90700",
    "sg:postcode":"41836",
    "sg:province":"Nordrhein-Westfalen",
    "wof:name":"Renate Darius-franzen Steuerberaterin",
    "wof:placetype":"venue"
},
  "geometry": {"coordinates":[6.2306461334,51.0496673584],"type":"Point"}
}