{
  "type": "Feature",
  "properties": {
    "iso:country":"DE",
    "sg:address":"Hauptstr. 44",
    "sg:city":"Bad Saulgau",
    "sg:phone":"+49 7581/8703",
    "sg:postcode":"88348",
    "sg:province":"Baden-W\u00fcrttemberg",
    "wof:name":"C. Royer",
    "wof:placetype":"venue"
},
  "geometry": {"coordinates":[9.4985589981,48.0178565979],"type":"Point"}
}