{
  "type": "Feature",
  "properties": {
    "iso:country":"DE",
    "sg:address":"Hammerweg 9",
    "sg:city":"Arzberg",
    "sg:phone":"+49 9233/8837",
    "sg:postcode":"95659",
    "sg:province":"Bayern",
    "wof:name":"Rudolf Raithel",
    "wof:placetype":"venue"
},
  "geometry": {"coordinates":[12.189146,50.05645],"type":"Point"}
}