{
  "type": "Feature",
  "properties": {
    "iso:country":"DE",
    "sg:address":"Schwandorfer Str. 6",
    "sg:city":"Teublitz",
    "sg:phone":"+49 9471/90398",
    "sg:postcode":"93158",
    "sg:province":"Bayern",
    "wof:name":"I. Spichtinger",
    "wof:placetype":"venue"
},
  "geometry": {"coordinates":[12.100797,49.246536],"type":"Point"}
}