{
  "type": "Feature",
  "properties": {
    "iso:country":"DE",
    "sg:address":"Eichenweg 11",
    "sg:city":"Lichtenfels",
    "sg:phone":"+49 9571/70014",
    "sg:postcode":"96215",
    "sg:province":"Bayern",
    "wof:name":"Vogel & Heppner Gmbh",
    "wof:placetype":"venue"
},
  "geometry": {"coordinates":[11.086312,50.147865],"type":"Point"}
}