{
  "type": "Feature",
  "properties": {
    "iso:country":"DE",
    "sg:address":"Ruhlsdorfer Str. 3",
    "sg:city":"Teltow",
    "sg:phone":"+49 3328/41332",
    "sg:postcode":"14513",
    "sg:province":"Brandenburg",
    "wof:name":"Stadt-apotheke Inh. Edeltraud Schulz",
    "wof:placetype":"venue"
},
  "geometry": {"coordinates":[13.268214,52.400059],"type":"Point"}
}