{
  "type": "Feature",
  "properties": {
    "iso:country":"DE",
    "sg:address":"Schulstr. 12",
    "sg:city":"Bayreuth",
    "sg:phone":"+49 921/22505",
    "sg:postcode":"95444",
    "sg:province":"Bayern",
    "wof:name":"Triltsch Moden",
    "wof:placetype":"venue"
},
  "geometry": {"coordinates":[11.575363,49.948082],"type":"Point"}
}