{
  "type": "Feature",
  "properties": {
    "iso:country":"DE",
    "sg:address":"L\u00fcdemannsweg 6",
    "sg:city":"Gelsenkirchen",
    "sg:phone":"+49 209/379666",
    "sg:postcode":"45894",
    "sg:province":"Nordrhein-Westfalen",
    "wof:name":"Dr. Gregor Mattheis Rechtsanwalt",
    "wof:placetype":"venue"
},
  "geometry": {"coordinates":[7.0370540619,51.580532074],"type":"Point"}
}