{
  "type": "Feature",
  "properties": {
    "iso:country":"DE",
    "sg:city":"Diez",
    "sg:postcode":"65582",
    "sg:province":"Rheinland-Pfalz",
    "wof:name":"Asp Mefatech Ag",
    "wof:placetype":"venue"
},
  "geometry": {"coordinates":[8.009341,50.370358],"type":"Point"}
}