{
  "type": "Feature",
  "properties": {
    "iso:country":"DE",
    "sg:address":"Hoffmannstr. 12",
    "sg:city":"Reutlingen",
    "sg:phone":"+49 7121/918773",
    "sg:postcode":"72770",
    "sg:province":"Baden-W\u00fcrttemberg",
    "wof:name":"Das Syndikat Zimmerei Ag",
    "wof:placetype":"venue"
},
  "geometry": {"coordinates":[9.1799497604,48.5007400513],"type":"Point"}
}