{
  "type": "Feature",
  "properties": {
    "iso:country":"DE",
    "sg:address":"Schie\u00dfgartenweg 8 a",
    "sg:city":"Frankenthal",
    "sg:phone":"+49 6233/66032",
    "sg:postcode":"67227",
    "sg:province":"Rheinland-Pfalz",
    "wof:name":"Gta Ges. F\u00fcr Technik Im Anlagenbau Mbh",
    "wof:placetype":"venue"
},
  "geometry": {"coordinates":[8.363433,49.536476],"type":"Point"}
}