{
  "type": "Feature",
  "properties": {
    "iso:country":"DE",
    "sg:address":"Spieroweg 1",
    "sg:city":"Berlin",
    "sg:phone":"+49 30/3662857",
    "sg:postcode":"13591",
    "sg:province":"Berlin",
    "wof:name":"Albert T\u00f6pper",
    "wof:placetype":"venue"
},
  "geometry": {"coordinates":[13.154363,52.527447],"type":"Point"}
}