{
  "type": "Feature",
  "properties": {
    "iso:country":"DE",
    "sg:address":"Ranzenstr. 8",
    "sg:city":"Forchheim",
    "sg:phone":"+49 7642/922045",
    "sg:postcode":"79362",
    "sg:province":"Baden-W\u00fcrttemberg",
    "wof:name":"Christel L\u00f6sch Steuerberater",
    "wof:placetype":"venue"
},
  "geometry": {"coordinates":[7.7009401321,48.1651992798],"type":"Point"}
}