{
  "type": "Feature",
  "properties": {
    "iso:country":"DE",
    "sg:address":"Einsiedler Str. 42",
    "sg:city":"R\u00fcbenau",
    "sg:phone":"+49 37366/6410",
    "sg:postcode":"09526",
    "sg:province":"Sachsen",
    "wof:name":"O. Seifert",
    "wof:placetype":"venue"
},
  "geometry": {"coordinates":[-94.2087402344,47.3429832458],"type":"Point"}
}