{
  "type": "Feature",
  "properties": {
    "iso:country":"DE",
    "sg:address":"Heidekamp 4",
    "sg:city":"Dassendorf",
    "sg:phone":"+49 4104/6764",
    "sg:postcode":"21521",
    "sg:province":"Schleswig-Holstein",
    "wof:name":"Wolfgang Choinka",
    "wof:placetype":"venue"
},
  "geometry": {"coordinates":[10.357559,53.504395],"type":"Point"}
}