{
  "type": "Feature",
  "properties": {
    "iso:country":"DE",
    "sg:address":"Augustinerstr. 24",
    "sg:city":"Mainz",
    "sg:phone":"+49 6131/222763",
    "sg:postcode":"55116",
    "sg:province":"Rheinland-Pfalz",
    "wof:name":"Dreamworld Wohnstudio Gmbh",
    "wof:placetype":"venue"
},
  "geometry": {"coordinates":[8.2753801346,49.9965820312],"type":"Point"}
}