{
  "type": "Feature",
  "properties": {
    "iso:country":"DE",
    "sg:address":"Arloffer Str. 7",
    "sg:city":"Euskirchen",
    "sg:phone":"+49 2255/1595",
    "sg:postcode":"53881",
    "sg:province":"Nordrhein-Westfalen",
    "wof:name":"Helmut N\u00f6then",
    "wof:placetype":"venue"
},
  "geometry": {"coordinates":[6.835808,50.612835],"type":"Point"}
}