{
  "type": "Feature",
  "properties": {
    "iso:country":"DE",
    "sg:address":"Wentorfer Str. 7",
    "sg:city":"Hamburg",
    "sg:phone":"+49 40/7213201",
    "sg:postcode":"21029",
    "sg:province":"Hamburg",
    "wof:name":"Fu\u00dforthop\u00e4die Paul Hast Gmbh",
    "wof:placetype":"venue"
},
  "geometry": {"coordinates":[10.2170991898,53.4869537354],"type":"Point"}
}