{
  "type": "Feature",
  "properties": {
    "iso:country":"DE",
    "sg:address":"Auf der Paint 31",
    "sg:city":"N\u00fcrnberg",
    "sg:phone":"+49 911/883626",
    "sg:postcode":"90455",
    "sg:province":"Bayern",
    "wof:name":"Bernd Klos",
    "wof:placetype":"venue"
},
  "geometry": {"coordinates":[11.073974,49.37273],"type":"Point"}
}