{
  "type": "Feature",
  "properties": {
    "iso:country":"DE",
    "sg:address":"Dieselstr. 4",
    "sg:city":"Reinbek",
    "sg:phone":"+49 40/7277030",
    "sg:postcode":"21465",
    "sg:province":"Schleswig-Holstein",
    "wof:name":"V. H\u00f6veling Yachtfarben E. K.",
    "wof:placetype":"venue"
},
  "geometry": {"coordinates":[10.234852,53.525105],"type":"Point"}
}