{
  "type": "Feature",
  "properties": {
    "iso:country":"DE",
    "sg:address":"Augustenstr. 15",
    "sg:city":"M\u00fcnchen",
    "sg:phone":"+49 89/595094",
    "sg:postcode":"80333",
    "sg:province":"Bayern",
    "wof:name":"H. Kellner",
    "wof:placetype":"venue"
},
  "geometry": {"coordinates":[11.5608282089,48.146232605],"type":"Point"}
}