{
  "type": "Feature",
  "properties": {
    "iso:country":"DE",
    "sg:address":"Taklerring",
    "sg:city":"Rostock",
    "sg:phone":"+49 381/1200287",
    "sg:postcode":"18109",
    "sg:province":"Mecklenburg-Vorpommern",
    "wof:name":"Der Norddeutsche Anzeigenmarkt",
    "wof:placetype":"venue"
},
  "geometry": {"coordinates":[12.073181,54.152569],"type":"Point"}
}