{
  "type": "Feature",
  "properties": {
    "iso:country":"DE",
    "sg:address":"Untere Langgasse 6",
    "sg:city":"Speyer",
    "sg:phone":"+49 6232/60660",
    "sg:postcode":"67346",
    "sg:province":"Rheinland-Pfalz",
    "wof:name":"Kuhnlein Und Kuhnlein Rechtsanw\u00e4lte",
    "wof:placetype":"venue"
},
  "geometry": {"coordinates":[8.4300737381,49.3186645508],"type":"Point"}
}