{
  "type": "Feature",
  "properties": {
    "iso:country":"DE",
    "sg:address":"Dorfplatz 6",
    "sg:city":"Rippien",
    "sg:phone":"+49 351/4720709",
    "sg:postcode":"01728",
    "sg:province":"Sachsen",
    "wof:name":"Rippien",
    "wof:placetype":"venue"
},
  "geometry": {"coordinates":[13.7336807251,50.9820251465],"type":"Point"}
}