{
  "type": "Feature",
  "properties": {
    "iso:country":"DE",
    "sg:address":"Wei\u00dfenburgstr. 12",
    "sg:city":"Pforzheim",
    "sg:phone":"+49 7231/351535",
    "sg:postcode":"75173",
    "sg:province":"Baden-W\u00fcrttemberg",
    "wof:name":"W. Und Brigitte Zachmann",
    "wof:placetype":"venue"
},
  "geometry": {"coordinates":[8.692825,48.878822],"type":"Point"}
}