{
  "type": "Feature",
  "properties": {
    "iso:country":"DE",
    "sg:address":"Richard-Wagner-Str 4",
    "sg:city":"Bamberg",
    "sg:phone":"+49 951/9844240",
    "sg:postcode":"96047",
    "sg:province":"Bayern",
    "wof:name":"Landeszentralbank",
    "wof:placetype":"venue"
},
  "geometry": {"coordinates":[10.892816,49.890015],"type":"Point"}
}