{
  "type": "Feature",
  "properties": {
    "iso:country":"DE",
    "sg:address":"K\u00f6nigstr. 22",
    "sg:city":"Stuttgart",
    "sg:phone":"+49 711/2237288",
    "sg:postcode":"70173",
    "sg:province":"Baden-W\u00fcrttemberg",
    "wof:name":"Heilbronner Stimme",
    "wof:placetype":"venue"
},
  "geometry": {"coordinates":[9.1792287827,48.7798042297],"type":"Point"}
}