{
  "type": "Feature",
  "properties": {
    "iso:country":"DE",
    "sg:address":"Am Ballbruchgraben 17",
    "sg:city":"Duisburg",
    "sg:phone":"+49 2065/80253",
    "sg:postcode":"47228",
    "sg:province":"Nordrhein-Westfalen",
    "wof:name":"Lorenz Gr\u00fctter Architekt",
    "wof:placetype":"venue"
},
  "geometry": {"coordinates":[6.675196,51.422218],"type":"Point"}
}