{
  "type": "Feature",
  "properties": {
    "iso:country":"DE",
    "sg:address":"Hauptstr. 45",
    "sg:city":"Gerolstein",
    "sg:phone":"+49 6591/3451",
    "sg:postcode":"54568",
    "sg:province":"Rheinland-Pfalz",
    "wof:name":"Pfaff",
    "wof:placetype":"venue"
},
  "geometry": {"coordinates":[6.6666088104,50.2220611572],"type":"Point"}
}