{
  "type": "Feature",
  "properties": {
    "iso:country":"DE",
    "sg:address":"Maienplatz 2",
    "sg:city":"Rheinfelden",
    "sg:phone":"+49 7623/72150",
    "sg:postcode":"79618",
    "sg:province":"Baden-W\u00fcrttemberg",
    "wof:name":"Hotel-restaurant Maien",
    "wof:placetype":"venue"
},
  "geometry": {"coordinates":[7.7570438385,47.5997390747],"type":"Point"}
}