{
  "type": "Feature",
  "properties": {
    "iso:country":"DE",
    "sg:address":"Kissinger Str. 13",
    "sg:city":"Hammelburg",
    "sg:phone":"+49 9732/2178",
    "sg:postcode":"97762",
    "sg:province":"Bayern",
    "wof:name":"R. Struensee Inh. Rita Schmitt",
    "wof:placetype":"venue"
},
  "geometry": {"coordinates":[9.891417,50.115631],"type":"Point"}
}