{
  "type": "Feature",
  "properties": {
    "iso:country":"DE",
    "sg:address":"Gro\u00dfenhainer Str. 137",
    "sg:city":"Mei\u00dfen",
    "sg:phone":"+49 3521/733781",
    "sg:postcode":"01662",
    "sg:province":"Sachsen",
    "wof:name":"Armin Zabe",
    "wof:placetype":"venue"
},
  "geometry": {"coordinates":[13.494966,51.176842],"type":"Point"}
}