{
  "type": "Feature",
  "properties": {
    "iso:country":"DE",
    "sg:address":"Am Landhaag 16",
    "sg:city":"Appenweier",
    "sg:phone":"+49 7805/2585",
    "sg:postcode":"77767",
    "sg:province":"Baden-W\u00fcrttemberg",
    "wof:name":"Matthias Lutterer Anlageberater",
    "wof:placetype":"venue"
},
  "geometry": {"coordinates":[7.9820289612,48.5444526672],"type":"Point"}
}