{
  "type": "Feature",
  "properties": {
    "iso:country":"DE",
    "sg:address":"Werrenwiesenstr. 75-79",
    "sg:city":"Schw\u00e4bisch Gm\u00fcnd",
    "sg:postcode":"73525",
    "sg:province":"Baden-W\u00fcrttemberg",
    "wof:name":"Motothek Warehouse Warenhandelsges. Mbh",
    "wof:placetype":"venue"
},
  "geometry": {"coordinates":[9.8257102966,48.7993545532],"type":"Point"}
}