{
  "type": "Feature",
  "properties": {
    "iso:country":"DE",
    "sg:address":"Ringstr. 27",
    "sg:city":"Freudenstadt",
    "sg:phone":"+49 7441/84565",
    "sg:postcode":"72250",
    "sg:province":"Baden-W\u00fcrttemberg",
    "wof:name":"Atlantis Automaten- Betriebs Gmbh",
    "wof:placetype":"venue"
},
  "geometry": {"coordinates":[8.4116096497,48.466709137],"type":"Point"}
}