{
  "type": "Feature",
  "properties": {
    "iso:country":"DE",
    "sg:address":"Catharinenstr. 40",
    "sg:city":"Cuxhaven",
    "sg:phone":"+49 4721/35618",
    "sg:postcode":"27472",
    "sg:province":"Niedersachsen",
    "wof:name":"R. Butt Heissmangel",
    "wof:placetype":"venue"
},
  "geometry": {"coordinates":[8.6939620972,53.8693695068],"type":"Point"}
}