{
  "type": "Feature",
  "properties": {
    "iso:country":"DE",
    "sg:address":"Paradiesweg 2",
    "sg:city":"Klosterfelde",
    "sg:phone":"+49 33396/607",
    "sg:postcode":"16348",
    "sg:province":"Brandenburg",
    "wof:name":"Handelshaus Massi",
    "wof:placetype":"venue"
},
  "geometry": {"coordinates":[13.4726142883,52.7550354004],"type":"Point"}
}