{
  "type": "Feature",
  "properties": {
    "iso:country":"DE",
    "sg:address":"Dazendorf",
    "sg:city":"Gremersdorf",
    "sg:phone":"+49 4362/6510",
    "sg:postcode":"23758",
    "sg:province":"Schleswig-Holstein",
    "wof:name":"H. Radke",
    "wof:placetype":"venue"
},
  "geometry": {"coordinates":[10.92782,54.354374],"type":"Point"}
}