{
  "type": "Feature",
  "properties": {
    "iso:country":"DE",
    "sg:address":"M\u00fchlstr. 11",
    "sg:city":"Sch\u00f6neck",
    "sg:phone":"+49 6187/5436",
    "sg:postcode":"61137",
    "sg:province":"Hessen",
    "wof:name":"Ev. Pfarramt B\u00fcdesheim",
    "wof:placetype":"venue"
},
  "geometry": {"coordinates":[8.8379392624,50.2171020508],"type":"Point"}
}