{
  "type": "Feature",
  "properties": {
    "iso:country":"DE",
    "sg:address":"Langenend 4",
    "sg:city":"Hambergen",
    "sg:phone":"+49 4793/1343",
    "sg:postcode":"27729",
    "sg:province":"Niedersachsen",
    "wof:name":"Bierverlag Fritz Prigge",
    "wof:placetype":"venue"
},
  "geometry": {"coordinates":[8.825005,53.311092],"type":"Point"}
}