{
  "type": "Feature",
  "properties": {
    "iso:country":"DE",
    "sg:address":"Azaleenweg 5",
    "sg:city":"Enger",
    "sg:phone":"+49 5224/79342",
    "sg:postcode":"32130",
    "sg:province":"Nordrhein-Westfalen",
    "wof:name":"Horst Schnellb\u00e4cher Rechtsanwalt",
    "wof:placetype":"venue"
},
  "geometry": {"coordinates":[8.5806760788,52.1496505737],"type":"Point"}
}