{
  "type": "Feature",
  "properties": {
    "iso:country":"DE",
    "sg:address":"Bahnhofstr. 2",
    "sg:city":"Waiblingen",
    "sg:phone":"+49 4971/515060",
    "sg:postcode":"71332",
    "sg:province":"Baden-W\u00fcrttemberg",
    "wof:name":"Volksbank Waiblingen Eg",
    "wof:placetype":"venue"
},
  "geometry": {"coordinates":[9.314104,48.829868],"type":"Point"}
}