{
  "type": "Feature",
  "properties": {
    "iso:country":"DE",
    "sg:address":"Ahornallee 7",
    "sg:city":"Werder",
    "sg:postcode":"16818",
    "sg:province":"Brandenburg",
    "wof:name":"Bullinger Verwaltungs Gmbh",
    "wof:placetype":"venue"
},
  "geometry": {"coordinates":[12.705075,52.919529],"type":"Point"}
}