{
  "type": "Feature",
  "properties": {
    "iso:country":"DE",
    "sg:address":"K\u00f6lner Str. 136",
    "sg:city":"Bergneustadt",
    "sg:phone":"+49 2261/41743",
    "sg:postcode":"51702",
    "sg:province":"Nordrhein-Westfalen",
    "wof:name":"Heinz Wingendorf",
    "wof:placetype":"venue"
},
  "geometry": {"coordinates":[7.640052,51.017426],"type":"Point"}
}