{
  "type": "Feature",
  "properties": {
    "iso:country":"DE",
    "sg:address":"Ludwigshafener Str. 69a",
    "sg:city":"Dessau",
    "sg:phone":"+49 340/8504855",
    "sg:postcode":"06842",
    "sg:province":"Sachsen-Anhalt",
    "wof:name":"Tannenheger",
    "wof:placetype":"venue"
},
  "geometry": {"coordinates":[12.2507534027,51.8218612671],"type":"Point"}
}