{
  "type": "Feature",
  "properties": {
    "iso:country":"DE",
    "sg:address":"Birkenhof 2",
    "sg:city":"Willst\u00e4tt",
    "sg:phone":"+49 7852/7140",
    "sg:postcode":"77731",
    "sg:province":"Baden-W\u00fcrttemberg",
    "wof:name":"Walter Arndt",
    "wof:placetype":"venue"
},
  "geometry": {"coordinates":[7.91332,48.585239],"type":"Point"}
}