{
  "type": "Feature",
  "properties": {
    "iso:country":"DE",
    "sg:address":"Theodor-Heuss-Str. 21",
    "sg:city":"Schwerte",
    "sg:phone":"+49 2304/990407",
    "sg:postcode":"58239",
    "sg:province":"Nordrhein-Westfalen",
    "wof:name":"Joachim Fehring",
    "wof:placetype":"venue"
},
  "geometry": {"coordinates":[7.6116700172,51.4569129944],"type":"Point"}
}