{
  "type": "Feature",
  "properties": {
    "iso:country":"DE",
    "sg:address":"Wiewelhook 25",
    "sg:city":"Telgte",
    "sg:phone":"+49 2504/8545",
    "sg:postcode":"48291",
    "sg:province":"Nordrhein-Westfalen",
    "wof:name":"Josef Lembeck-leusing",
    "wof:placetype":"venue"
},
  "geometry": {"coordinates":[7.745733,52.042023],"type":"Point"}
}