{
  "type": "Feature",
  "properties": {
    "iso:country":"DE",
    "sg:address":"L\u00f6\u00dfnitzstr. 8",
    "sg:city":"Dresden",
    "sg:phone":"+49 351/8496709",
    "sg:postcode":"01097",
    "sg:province":"Sachsen",
    "wof:name":"Drekon Wohnbau Gmbh",
    "wof:placetype":"venue"
},
  "geometry": {"coordinates":[13.7459440231,51.0683631897],"type":"Point"}
}