{
  "type": "Feature",
  "properties": {
    "iso:country":"DE",
    "sg:address":"Dobrudschastr. 43",
    "sg:city":"Heilbronn",
    "sg:phone":"+49 7131/572091",
    "sg:postcode":"74081",
    "sg:province":"Baden-W\u00fcrttemberg",
    "wof:name":"U. Und A. Bellersheim",
    "wof:placetype":"venue"
},
  "geometry": {"coordinates":[9.1829004288,49.1164894104],"type":"Point"}
}