{
  "type": "Feature",
  "properties": {
    "iso:country":"DE",
    "sg:address":"Enge Str. 9",
    "sg:city":"Lichtenstein",
    "sg:phone":"+49 7129/2492",
    "sg:postcode":"72805",
    "sg:province":"Baden-W\u00fcrttemberg",
    "wof:name":"Ulrich Staiger",
    "wof:placetype":"venue"
},
  "geometry": {"coordinates":[9.2536239624,48.4260444641],"type":"Point"}
}