{
  "type": "Feature",
  "properties": {
    "iso:country":"DE",
    "sg:address":"F-Wilh-Raiffeisen-Str 6",
    "sg:city":"Reutlingen",
    "sg:postcode":"72770",
    "sg:province":"Baden-W\u00fcrttemberg",
    "wof:name":"Erfa Organisations- Und Dienstleistungs-verwaltungs-",
    "wof:placetype":"venue"
},
  "geometry": {"coordinates":[9.1772432327,48.499786377],"type":"Point"}
}