{
  "type": "Feature",
  "properties": {
    "iso:country":"DE",
    "sg:address":"Kirchwerder Hausdeich 72",
    "sg:city":"Hamburg",
    "sg:phone":"+49 40/7232218",
    "sg:postcode":"21037",
    "sg:province":"Hamburg",
    "wof:name":"Heinz Jan\u00dfen",
    "wof:placetype":"venue"
},
  "geometry": {"coordinates":[10.184429,53.439644],"type":"Point"}
}