{
  "type": "Feature",
  "properties": {
    "iso:country":"DE",
    "sg:address":"Lise-Meitner-Str. 21",
    "sg:city":"Nordhorn",
    "sg:postcode":"48529",
    "sg:province":"Niedersachsen",
    "wof:name":"N & L Metallbau Gmbh",
    "wof:placetype":"venue"
},
  "geometry": {"coordinates":[7.083944,52.410683],"type":"Point"}
}