{
  "type": "Feature",
  "properties": {
    "iso:country":"DE",
    "sg:address":"Kreuzstr. 72",
    "sg:city":"Krefeld",
    "sg:phone":"+49 2151/973250",
    "sg:postcode":"47839",
    "sg:province":"Nordrhein-Westfalen",
    "wof:name":"J\u00f6bkes Bautr\u00e4ger Und Immobilien Gmbh",
    "wof:placetype":"venue"
},
  "geometry": {"coordinates":[6.513906,51.369461],"type":"Point"}
}