{
  "type": "Feature",
  "properties": {
    "iso:country":"DE",
    "sg:address":"Am Radeberg 1",
    "sg:city":"Bremen",
    "sg:phone":"+49 421/693890",
    "sg:postcode":"28717",
    "sg:province":"Bremen",
    "wof:name":"H. Beiderbeck Rechtsanwalt Und Notar",
    "wof:placetype":"venue"
},
  "geometry": {"coordinates":[8.6864690781,53.1710357666],"type":"Point"}
}