{
  "type": "Feature",
  "properties": {
    "iso:country":"DE",
    "sg:address":"Horner Kamp 3",
    "sg:city":"Geesthacht",
    "sg:phone":"+49 4152/71274",
    "sg:postcode":"21502",
    "sg:province":"Schleswig-Holstein",
    "wof:name":"Sens & M\u00f6ller Ingenieurges. F\u00fcr Arbeitss. Sicherheitst.",
    "wof:placetype":"venue"
},
  "geometry": {"coordinates":[10.4029140472,53.4445533752],"type":"Point"}
}