{
  "type": "Feature",
  "properties": {
    "iso:country":"DE",
    "sg:city":"Marburg",
    "sg:phone":"+49 641/2176650",
    "sg:postcode":"35037",
    "sg:province":"Hessen",
    "wof:name":"Mediasyn",
    "wof:placetype":"venue"
},
  "geometry": {"coordinates":[8.772526,50.808426],"type":"Point"}
}