{
  "type": "Feature",
  "properties": {
    "iso:country":"DE",
    "sg:address":"M\u00fchlmatt 47",
    "sg:city":"Gengenbach",
    "sg:phone":"+49 7803/980390",
    "sg:postcode":"77723",
    "sg:province":"Baden-W\u00fcrttemberg",
    "wof:name":"Heinz Harter Gmbh",
    "wof:placetype":"venue"
},
  "geometry": {"coordinates":[8.0222387314,48.4287719727],"type":"Point"}
}