{
  "type": "Feature",
  "properties": {
    "iso:country":"DE",
    "sg:address":"Hauptstr. 18",
    "sg:city":"Jestetten",
    "sg:phone":"+49 7745/7268",
    "sg:postcode":"79798",
    "sg:province":"Baden-W\u00fcrttemberg",
    "wof:name":"Georg Hosp Elekroinstallation",
    "wof:placetype":"venue"
},
  "geometry": {"coordinates":[8.569103,47.650993],"type":"Point"}
}