{
  "type": "Feature",
  "properties": {
    "iso:country":"DE",
    "sg:address":"Bahnstr. 40",
    "sg:city":"D\u00fcsseldorf",
    "sg:phone":"+49 211/323598",
    "sg:postcode":"40210",
    "sg:province":"Nordrhein-Westfalen",
    "wof:name":"High Und Mighty Outsize Manshops Gmbh",
    "wof:placetype":"venue"
},
  "geometry": {"coordinates":[6.7825808525,51.219871521],"type":"Point"}
}