{
  "type": "Feature",
  "properties": {
    "iso:country":"DE",
    "sg:address":"In der Konde 54",
    "sg:city":"K\u00f6ln",
    "sg:phone":"+49 221/861564",
    "sg:postcode":"51107",
    "sg:province":"Nordrhein-Westfalen",
    "wof:name":"Josef Krein",
    "wof:placetype":"venue"
},
  "geometry": {"coordinates":[7.079174,50.920033],"type":"Point"}
}