{
  "type": "Feature",
  "properties": {
    "iso:country":"DE",
    "sg:address":"dorfstra\u00dfe 36",
    "sg:city":"trent/r\u00fcgen",
    "sg:phone":"+49 38309/20022",
    "sg:postcode":"18569",
    "sg:province":"Mecklenburg-Vorpommern",
    "wof:name":"Feller Funk Fernsehen",
    "wof:placetype":"venue"
},
  "geometry": {"coordinates":[13.256401,54.521088],"type":"Point"}
}