{
  "type": "Feature",
  "properties": {
    "iso:country":"DE",
    "sg:address":"Hauptstr. 91",
    "sg:city":"Lebach",
    "sg:phone":"+49 6888/1056",
    "sg:postcode":"66822",
    "sg:province":"Saarland",
    "wof:name":"Peter Scherer",
    "wof:placetype":"venue"
},
  "geometry": {"coordinates":[6.9627151489,49.4559364319],"type":"Point"}
}