{
  "type": "Feature",
  "properties": {
    "iso:country":"DE",
    "sg:address":"Neue Str. 17",
    "sg:city":"Wendeburg",
    "sg:phone":"+49 5303/910677",
    "sg:postcode":"38176",
    "sg:province":"Niedersachsen",
    "wof:name":"Idee-fix Peters Majer",
    "wof:placetype":"venue"
},
  "geometry": {"coordinates":[10.392603,52.32032],"type":"Point"}
}