{
  "type": "Feature",
  "properties": {
    "iso:country":"DE",
    "sg:address":"Danziger Str. 136",
    "sg:city":"Berlin",
    "sg:phone":"+49 30/4257294",
    "sg:postcode":"10407",
    "sg:province":"Berlin",
    "wof:name":"Gerhard Blankenburg",
    "wof:placetype":"venue"
},
  "geometry": {"coordinates":[13.435131,52.534897],"type":"Point"}
}