{
  "type": "Feature",
  "properties": {
    "iso:country":"DE",
    "sg:address":"Neuer Weyerstra\u00dferweg 135",
    "sg:city":"K\u00f6ln",
    "sg:postcode":"50969",
    "sg:province":"Nordrhein-Westfalen",
    "wof:name":"Sudden Industries Multimedia Gmbh",
    "wof:placetype":"venue"
},
  "geometry": {"coordinates":[6.9318041801,50.9044876099],"type":"Point"}
}