{
  "type": "Feature",
  "properties": {
    "iso:country":"DE",
    "sg:address":"Am Rotberg 58",
    "sg:city":"Wutha-Farnroda",
    "sg:phone":"+49 36921/92012",
    "sg:postcode":"99848",
    "sg:province":"Th\u00fcringen",
    "wof:name":"Helmut Thiel Automaten Gmbh",
    "wof:placetype":"venue"
},
  "geometry": {"coordinates":[10.3965396881,50.9510307312],"type":"Point"}
}