{
  "type": "Feature",
  "properties": {
    "iso:country":"DE",
    "sg:address":"Adelheidstr. 2",
    "sg:city":"Walluf",
    "sg:phone":"+49 6123/71312",
    "sg:postcode":"65396",
    "sg:province":"Hessen",
    "wof:name":"Wilhelm Sch\u00f6ndaube",
    "wof:placetype":"venue"
},
  "geometry": {"coordinates":[8.159892,50.036049],"type":"Point"}
}