{
  "type": "Feature",
  "properties": {
    "iso:country":"DE",
    "sg:address":"Wiesenweg 8",
    "sg:city":"Bad Neuenahr-Ahrweiler",
    "sg:phone":"+49 2641/26007",
    "sg:postcode":"53474",
    "sg:province":"Rheinland-Pfalz",
    "wof:name":"Arevital Sport- Und Gesundheits Center Ag",
    "wof:placetype":"venue"
},
  "geometry": {"coordinates":[7.1710500717,50.546421051],"type":"Point"}
}