{
  "type": "Feature",
  "properties": {
    "iso:country":"DE",
    "sg:address":"Meinekestr. 13",
    "sg:city":"Berlin",
    "sg:phone":"+49 30/8842000",
    "sg:postcode":"10719",
    "sg:province":"Berlin",
    "wof:name":"Joachim Schmelzer Steuerberater",
    "wof:placetype":"venue"
},
  "geometry": {"coordinates":[13.328868866,52.4998092651],"type":"Point"}
}