{
  "type": "Feature",
  "properties": {
    "iso:country":"DE",
    "sg:address":"Hindenburgstr. 38",
    "sg:city":"Bondorf",
    "sg:phone":"+49 7457/8475",
    "sg:postcode":"71149",
    "sg:province":"Baden-W\u00fcrttemberg",
    "wof:name":"Eberhard Wei\u00df",
    "wof:placetype":"venue"
},
  "geometry": {"coordinates":[8.831916,48.521015],"type":"Point"}
}