{
  "type": "Feature",
  "properties": {
    "iso:country":"DE",
    "sg:address":"Am K\u00f6hlw\u00e4ldchen",
    "sg:city":"Landstuhl",
    "sg:phone":"+49 6371/912010",
    "sg:postcode":"66849",
    "sg:province":"Rheinland-Pfalz",
    "wof:name":"Mc Donalds",
    "wof:placetype":"venue"
},
  "geometry": {"coordinates":[7.5721797943,49.4117660522],"type":"Point"}
}