{
  "type": "Feature",
  "properties": {
    "iso:country":"DE",
    "sg:address":"Im Vogelsang 6a",
    "sg:city":"Kettig",
    "sg:phone":"+49 2637/2489",
    "sg:postcode":"56220",
    "sg:province":"Rheinland-Pfalz",
    "wof:name":"Marie-luise Engel Steuerberaterin",
    "wof:placetype":"venue"
},
  "geometry": {"coordinates":[7.463493824,50.3943786621],"type":"Point"}
}