{
  "type": "Feature",
  "properties": {
    "iso:country":"DE",
    "sg:address":"Hansastr. 8",
    "sg:city":"Leopoldsh\u00f6he",
    "sg:phone":"+49 5202/98380",
    "sg:postcode":"33818",
    "sg:province":"Nordrhein-Westfalen",
    "wof:name":"Ernst Kleinebenne Fahrzeugbau Gmbh & Co.",
    "wof:placetype":"venue"
},
  "geometry": {"coordinates":[8.6664686203,51.9776153564],"type":"Point"}
}