{
  "type": "Feature",
  "properties": {
    "iso:country":"DE",
    "sg:address":"Dietrichstr. 112",
    "sg:city":"Bonn",
    "sg:phone":"+49 4922/8951390",
    "sg:postcode":"53175",
    "sg:province":"Nordrhein-Westfalen",
    "wof:name":"Kft Kunststoff- Form-technik Gmbh",
    "wof:placetype":"venue"
},
  "geometry": {"coordinates":[7.1391448975,50.6894073486],"type":"Point"}
}