{
  "type": "Feature",
  "properties": {
    "iso:country":"DE",
    "sg:address":"Merzbacherstr. 22",
    "sg:city":"M\u00fcnchen",
    "sg:postcode":"80637",
    "sg:province":"Bayern",
    "wof:name":"Birgitta L\u00fcbbering",
    "wof:placetype":"venue"
},
  "geometry": {"coordinates":[11.536503,48.164455],"type":"Point"}
}