{
  "type": "Feature",
  "properties": {
    "iso:country":"DE",
    "sg:address":"Schulgasse 3",
    "sg:city":"L\u00f6bau",
    "sg:phone":"+49 3585/402192",
    "sg:postcode":"02708",
    "sg:province":"Sachsen",
    "wof:name":"Maik Andreas Zoo Hdl.",
    "wof:placetype":"venue"
},
  "geometry": {"coordinates":[14.667229,51.095528],"type":"Point"}
}