{
  "type": "Feature",
  "properties": {
    "iso:country":"DE",
    "sg:address":"Obere Gasse 5",
    "sg:city":"Rottenburg",
    "sg:phone":"+49 7472/1461",
    "sg:postcode":"72108",
    "sg:province":"Baden-W\u00fcrttemberg",
    "wof:name":"Hermann Bolz",
    "wof:placetype":"venue"
},
  "geometry": {"coordinates":[8.934277,48.478119],"type":"Point"}
}