{
  "type": "Feature",
  "properties": {
    "iso:country":"DE",
    "sg:address":"Hauptstr. 24",
    "sg:city":"Battenberg",
    "sg:phone":"+49 6452/3379",
    "sg:postcode":"35088",
    "sg:province":"Hessen",
    "wof:name":"Helmut Wack",
    "wof:placetype":"venue"
},
  "geometry": {"coordinates":[8.643669,51.0168],"type":"Point"}
}