{
  "type": "Feature",
  "properties": {
    "iso:country":"DE",
    "sg:address":"Gro\u00dfe Hamheide 11",
    "sg:city":"Oldenburg",
    "sg:phone":"+49 441/55266",
    "sg:postcode":"26125",
    "sg:province":"Niedersachsen",
    "wof:name":"Peter B\u00f6geholz",
    "wof:placetype":"venue"
},
  "geometry": {"coordinates":[8.262714,53.176979],"type":"Point"}
}