{
  "type": "Feature",
  "properties": {
    "iso:country":"DE",
    "sg:address":"Hirtenstr. 20 - 22",
    "sg:city":"M\u00fcnchen",
    "sg:phone":"+49 89/5459530",
    "sg:postcode":"80335",
    "sg:province":"Bayern",
    "wof:name":"Alfa-hotel",
    "wof:placetype":"venue"
},
  "geometry": {"coordinates":[11.5575523376,48.1424980164],"type":"Point"}
}