{
  "type": "Feature",
  "properties": {
    "iso:country":"DE",
    "sg:address":"Im Schlenk 26",
    "sg:city":"Duisburg",
    "sg:phone":"+49 203/730055",
    "sg:postcode":"47055",
    "sg:province":"Nordrhein-Westfalen",
    "wof:name":"B. Weiss",
    "wof:placetype":"venue"
},
  "geometry": {"coordinates":[6.765031,51.401039],"type":"Point"}
}