{
  "type": "Feature",
  "properties": {
    "iso:country":"DE",
    "sg:address":"Eyersheimer M\u00fchle",
    "sg:city":"Weisenheim am Sand",
    "sg:phone":"+49 6353/6333",
    "sg:postcode":"67256",
    "sg:province":"Rheinland-Pfalz",
    "wof:name":"P. Laloire Dolmetscherb\u00fcro",
    "wof:placetype":"venue"
},
  "geometry": {"coordinates":[8.253124,49.494751],"type":"Point"}
}