{
  "type": "Feature",
  "properties": {
    "iso:country":"DE",
    "sg:address":"Am Schl\u00f6\u00dfle 1",
    "sg:city":"Zell",
    "sg:phone":"+49 7625/1663",
    "sg:postcode":"79669",
    "sg:province":"Baden-W\u00fcrttemberg",
    "wof:name":"Hausverwaltungen Mond Gmbh",
    "wof:placetype":"venue"
},
  "geometry": {"coordinates":[7.8691649437,47.713848114],"type":"Point"}
}