{
  "type": "Feature",
  "properties": {
    "iso:country":"DE",
    "sg:city":"Wildsteig",
    "sg:phone":"+49 8867/369",
    "sg:postcode":"82409",
    "sg:province":"Bayern",
    "wof:name":"Cafe Schlo\u00dfberg",
    "wof:placetype":"venue"
},
  "geometry": {"coordinates":[10.938052,47.704124],"type":"Point"}
}