{
  "type": "Feature",
  "properties": {
    "iso:country":"DE",
    "sg:address":"Schleestr. 7",
    "sg:city":"Reutlingen",
    "sg:phone":"+49 7121/44221",
    "sg:postcode":"72766",
    "sg:province":"Baden-W\u00fcrttemberg",
    "wof:name":"Werner Kehrer Ingenieur",
    "wof:placetype":"venue"
},
  "geometry": {"coordinates":[9.2308769226,48.5168609619],"type":"Point"}
}