{
  "type": "Feature",
  "properties": {
    "iso:country":"DE",
    "sg:address":"Magdalenenweg 30",
    "sg:city":"Kirchheim",
    "sg:postcode":"85551",
    "sg:province":"Bayern",
    "wof:name":"Dr. Detlef Ro\u00df Bevsh Gmbh",
    "wof:placetype":"venue"
},
  "geometry": {"coordinates":[11.7603139877,48.1735076904],"type":"Point"}
}