{
  "type": "Feature",
  "properties": {
    "iso:country":"DE",
    "sg:address":"Frankfurter Str. 17",
    "sg:city":"Michelstadt",
    "sg:phone":"+49 6061/5999",
    "sg:postcode":"64720",
    "sg:province":"Hessen",
    "wof:name":"H. Wolf",
    "wof:placetype":"venue"
},
  "geometry": {"coordinates":[9.003276,49.684563],"type":"Point"}
}