{
  "type": "Feature",
  "properties": {
    "iso:country":"DE",
    "sg:address":"In den Leppsteinswiesen 8",
    "sg:city":"Ro\u00dfdorf",
    "sg:phone":"+49 6154/83319",
    "sg:postcode":"64380",
    "sg:province":"Hessen",
    "wof:name":"Volker K\u00fchsel",
    "wof:placetype":"venue"
},
  "geometry": {"coordinates":[8.7445249557,49.8648338318],"type":"Point"}
}