{
  "type": "Feature",
  "properties": {
    "iso:country":"DE",
    "sg:address":"Bahnhofstr. 23",
    "sg:city":"Preu\u00dfisch Oldendorf",
    "sg:phone":"+49 5742/3118",
    "sg:postcode":"32361",
    "sg:province":"Nordrhein-Westfalen",
    "wof:name":"Karl Siebe Gmbh",
    "wof:placetype":"venue"
},
  "geometry": {"coordinates":[8.5379447937,52.2885704041],"type":"Point"}
}