{
  "type": "Feature",
  "properties": {
    "iso:country":"DE",
    "sg:address":"Isselstr. 7",
    "sg:city":"Neuss",
    "sg:phone":"+49 2137/4402",
    "sg:postcode":"41469",
    "sg:province":"Nordrhein-Westfalen",
    "wof:name":"H. Und Grete Bunse",
    "wof:placetype":"venue"
},
  "geometry": {"coordinates":[6.731354,51.161953],"type":"Point"}
}