{
  "type": "Feature",
  "properties": {
    "iso:country":"DE",
    "sg:address":"Hauptstr. 30",
    "sg:city":"Morsbach",
    "sg:phone":"+49 2294/1588",
    "sg:postcode":"51597",
    "sg:province":"Nordrhein-Westfalen",
    "wof:name":"Heinz Dietermann",
    "wof:placetype":"venue"
},
  "geometry": {"coordinates":[7.681591,50.842281],"type":"Point"}
}