{
  "type": "Feature",
  "properties": {
    "iso:country":"DE",
    "sg:address":"Rudolf-Diener-Str. 12",
    "sg:city":"Gera",
    "sg:phone":"+49 365/881760",
    "sg:postcode":"07545",
    "sg:province":"Th\u00fcringen",
    "wof:name":"Peter Lenk Rechtsanwalt",
    "wof:placetype":"venue"
},
  "geometry": {"coordinates":[12.0828533173,50.8790512085],"type":"Point"}
}