{
  "type": "Feature",
  "properties": {
    "iso:country":"DE",
    "sg:address":"Sch\u00f6nflie\u00dfer Str.",
    "sg:city":"Berlin",
    "sg:phone":"+49 30/4476609",
    "sg:postcode":"10439",
    "sg:province":"Berlin",
    "wof:name":"F\u00f6rderverein-odense-grundschule",
    "wof:placetype":"venue"
},
  "geometry": {"coordinates":[13.4086,52.553589],"type":"Point"}
}