{
  "type": "Feature",
  "properties": {
    "iso:country":"DE",
    "sg:address":"Heidkaten",
    "sg:city":"Hamweddel",
    "sg:phone":"+49 4875/96060",
    "sg:postcode":"24816",
    "sg:province":"Schleswig-Holstein",
    "wof:name":"Grand Pa Beschallungs- Und Lichttechnik Verwaltungs Gmbh",
    "wof:placetype":"venue"
},
  "geometry": {"coordinates":[9.6356315613,54.1861763],"type":"Point"}
}