{
  "type": "Feature",
  "properties": {
    "iso:country":"DE",
    "sg:address":"Hammerau",
    "sg:city":"Sinsheim",
    "sg:phone":"+49 7261/1896",
    "sg:postcode":"74889",
    "sg:province":"Baden-W\u00fcrttemberg",
    "wof:name":"K. Hammer & Partner Gmbh",
    "wof:placetype":"venue"
},
  "geometry": {"coordinates":[8.8527402878,49.2146682739],"type":"Point"}
}