{
  "type": "Feature",
  "properties": {
    "iso:country":"DE",
    "sg:address":"Apothekergasse 3",
    "sg:city":"Ellwangen",
    "sg:phone":"+49 7961/7488",
    "sg:postcode":"73479",
    "sg:province":"Baden-W\u00fcrttemberg",
    "wof:name":"R. Kleeberger",
    "wof:placetype":"venue"
},
  "geometry": {"coordinates":[10.1332702637,48.9612426758],"type":"Point"}
}