{
  "type": "Feature",
  "properties": {
    "iso:country":"DE",
    "sg:address":"Salinenstr. 39/1",
    "sg:city":"Kirchardt",
    "sg:phone":"+49 7266/911134",
    "sg:postcode":"74912",
    "sg:province":"Baden-W\u00fcrttemberg",
    "wof:name":"M. Sch\u00e4fer",
    "wof:placetype":"venue"
},
  "geometry": {"coordinates":[8.9797487259,49.1818580627],"type":"Point"}
}