{
  "type": "Feature",
  "properties": {
    "iso:country":"DE",
    "sg:address":"Landhausstr. 13",
    "sg:city":"Berlin",
    "sg:phone":"+49 30/875564",
    "sg:postcode":"10717",
    "sg:province":"Berlin",
    "wof:name":"Prof. Heinz Tr\u00f6kes Kunstmaler",
    "wof:placetype":"venue"
},
  "geometry": {"coordinates":[13.328502,52.489037],"type":"Point"}
}