{
  "type": "Feature",
  "properties": {
    "iso:country":"DE",
    "sg:address":"Steenkoppel 31",
    "sg:city":"Boostedt",
    "sg:phone":"+49 4393/3402",
    "sg:postcode":"24598",
    "sg:province":"Schleswig-Holstein",
    "wof:name":"Ingo Boldt Architekt",
    "wof:placetype":"venue"
},
  "geometry": {"coordinates":[10.017388,54.005543],"type":"Point"}
}