{
  "type": "Feature",
  "properties": {
    "iso:country":"DE",
    "sg:address":"Hugo-Wolf-Str. 10",
    "sg:city":"Offenbach",
    "sg:phone":"+49 69/844058",
    "sg:postcode":"63069",
    "sg:province":"Hessen",
    "wof:name":"Wiener Feinb\u00e4ckerei Heberer Gmbh",
    "wof:placetype":"venue"
},
  "geometry": {"coordinates":[8.753226,50.085529],"type":"Point"}
}