{
  "type": "Feature",
  "properties": {
    "iso:country":"DE",
    "sg:address":"August-L\u00fctgenau-Str. 1",
    "sg:city":"H\u00fcckeswagen",
    "sg:phone":"+49 2192/92420",
    "sg:postcode":"42499",
    "sg:province":"Nordrhein-Westfalen",
    "wof:name":"Haberstroh Sappelt Und Biesenbach",
    "wof:placetype":"venue"
},
  "geometry": {"coordinates":[7.3348312378,51.1487236023],"type":"Point"}
}