{
  "type": "Feature",
  "properties": {
    "iso:country":"DE",
    "sg:address":"Markt 2::",
    "sg:city":"Altenburg",
    "sg:phone":"+49 4934/475960",
    "sg:postcode":"04600",
    "sg:province":"Th\u00fcringen",
    "wof:name":"Sparkasse Altenburg - Schmoelln",
    "wof:placetype":"venue"
},
  "geometry": {"coordinates":[12.433195,50.985111],"type":"Point"}
}