{
  "type": "Feature",
  "properties": {
    "iso:country":"DE",
    "sg:address":"Zum Kleinen Feld 7",
    "sg:city":"Uslar",
    "sg:phone":"+49 5571/2426",
    "sg:postcode":"37170",
    "sg:province":"Niedersachsen",
    "wof:name":"Katholisches Pfarramt St. Konrad V. Parzham",
    "wof:placetype":"venue"
},
  "geometry": {"coordinates":[9.6359643936,51.6621055603],"type":"Point"}
}