{
  "type": "Feature",
  "properties": {
    "iso:country":"DE",
    "sg:address":"Talstr. 32",
    "sg:city":"St Gangloff",
    "sg:phone":"+49 36606/86000",
    "sg:postcode":"07629",
    "sg:province":"Th\u00fcringen",
    "wof:name":"Carsten Staps",
    "wof:placetype":"venue"
},
  "geometry": {"coordinates":[11.903553009,50.8528556824],"type":"Point"}
}