{
  "type": "Feature",
  "properties": {
    "iso:country":"DE",
    "sg:address":"Am H\u00f6llberg 22",
    "sg:city":"Hebertshausen",
    "sg:postcode":"85241",
    "sg:province":"Bayern",
    "wof:name":"Carls Equipment Gmbh",
    "wof:placetype":"venue"
},
  "geometry": {"coordinates":[11.4607439041,48.2904396057],"type":"Point"}
}