{
  "type": "Feature",
  "properties": {
    "iso:country":"DE",
    "sg:address":"Am Zwinger 14",
    "sg:city":"Bielefeld",
    "sg:phone":"+49 521/179233",
    "sg:postcode":"33602",
    "sg:province":"Nordrhein-Westfalen",
    "wof:name":"Galerie",
    "wof:placetype":"venue"
},
  "geometry": {"coordinates":[8.527998,52.023445],"type":"Point"}
}