{
  "type": "Feature",
  "properties": {
    "iso:country":"DE",
    "sg:address":"Hauptstr. 5",
    "sg:city":"D\u00f6hlau",
    "sg:phone":"+49 9281/41970",
    "sg:postcode":"95182",
    "sg:province":"Bayern",
    "wof:name":"Dieter Wanjelik Bauelemente",
    "wof:placetype":"venue"
},
  "geometry": {"coordinates":[11.981741,50.278748],"type":"Point"}
}