{
  "type": "Feature",
  "properties": {
    "iso:country":"DE",
    "sg:address":"Am Reuterweg 15",
    "sg:city":"Sundern",
    "sg:phone":"+49 2393/501",
    "sg:postcode":"59846",
    "sg:province":"Nordrhein-Westfalen",
    "wof:name":"Gerhard M\u00fcller Ingenieur",
    "wof:placetype":"venue"
},
  "geometry": {"coordinates":[7.9501957893,51.2855262756],"type":"Point"}
}