{
  "type": "Feature",
  "properties": {
    "iso:country":"DE",
    "sg:address":"K\u00f6ln-Aachener-Str. 141-144",
    "sg:city":"Elsdorf",
    "sg:phone":"+49 2274/3250",
    "sg:postcode":"50189",
    "sg:province":"Nordrhein-Westfalen",
    "wof:name":"Textil Peters Gmbh",
    "wof:placetype":"venue"
},
  "geometry": {"coordinates":[6.5670962334,50.9340362549],"type":"Point"}
}