{
  "type": "Feature",
  "properties": {
    "iso:country":"DE",
    "sg:address":"Krokusstr. 27",
    "sg:city":"Germering",
    "sg:phone":"+49 89/846031",
    "sg:postcode":"82110",
    "sg:province":"Bayern",
    "wof:name":"Siegfried Hailer",
    "wof:placetype":"venue"
},
  "geometry": {"coordinates":[11.3831796646,48.1344451904],"type":"Point"}
}