{
  "type": "Feature",
  "properties": {
    "iso:country":"DE",
    "sg:address":"Kirchgasse 2a",
    "sg:city":"Nidderau",
    "sg:phone":"+49 6187/1497",
    "sg:postcode":"61130",
    "sg:province":"Hessen",
    "wof:name":"Ev. Pfarramt Ostheim",
    "wof:placetype":"venue"
},
  "geometry": {"coordinates":[8.9107408524,50.2249908447],"type":"Point"}
}