{
  "type": "Feature",
  "properties": {
    "iso:country":"DE",
    "sg:address":"Friedrich-Ebert-Str. 69-71",
    "sg:city":"Emden",
    "sg:phone":"+49 4921/89970",
    "sg:postcode":"26725",
    "sg:province":"Niedersachsen",
    "wof:name":"Upstalsboom Hotel & Freizeit Gmbh",
    "wof:placetype":"venue"
},
  "geometry": {"coordinates":[7.2137851715,53.36378479],"type":"Point"}
}