{
  "type": "Feature",
  "properties": {
    "iso:country":"DE",
    "sg:address":"Ostseestr. 111",
    "sg:city":"Berlin",
    "sg:phone":"+49 30/4429073",
    "sg:postcode":"10409",
    "sg:province":"Berlin",
    "wof:name":"W\u00f6rlitz Tourist Gmbh",
    "wof:placetype":"venue"
},
  "geometry": {"coordinates":[13.4430761337,52.5464286804],"type":"Point"}
}