{
  "type": "Feature",
  "properties": {
    "iso:country":"DE",
    "sg:address":"Goethestr. 7",
    "sg:city":"Hameln",
    "sg:phone":"+49 5151/95140",
    "sg:postcode":"31785",
    "sg:province":"Niedersachsen",
    "wof:name":"Alfred Reinhold Stiftung",
    "wof:placetype":"venue"
},
  "geometry": {"coordinates":[9.3564462662,52.111530304],"type":"Point"}
}