{
  "type": "Feature",
  "properties": {
    "iso:country":"DE",
    "sg:address":"Hindenburgstr. 3",
    "sg:city":"Fallingbostel",
    "sg:phone":"+49 5162/91222",
    "sg:postcode":"29683",
    "sg:province":"Niedersachsen",
    "wof:name":"Dr. Med. Wilfried J\u00e4rschke",
    "wof:placetype":"venue"
},
  "geometry": {"coordinates":[9.6981191635,52.864982605],"type":"Point"}
}