{
  "type": "Feature",
  "properties": {
    "iso:country":"DE",
    "sg:address":"Weingartenstr. 3",
    "sg:city":"Graach",
    "sg:phone":"+49 6531/2592",
    "sg:postcode":"54470",
    "sg:province":"Rheinland-Pfalz",
    "wof:name":"Heinrich Eckstein-kieren",
    "wof:placetype":"venue"
},
  "geometry": {"coordinates":[7.064704895,49.9342193604],"type":"Point"}
}