{
  "type": "Feature",
  "properties": {
    "iso:country":"DE",
    "sg:address":"Frankfurter Str. 108",
    "sg:city":"Bad Vilbel",
    "sg:phone":"+49 6101/88051",
    "sg:postcode":"61118",
    "sg:province":"Hessen",
    "wof:name":"Reiseb\u00fcro Flug Und Reisekontor Gmbh",
    "wof:placetype":"venue"
},
  "geometry": {"coordinates":[8.7370157242,50.1796340942],"type":"Point"}
}