{
  "type": "Feature",
  "properties": {
    "iso:country":"DE",
    "sg:address":"Eiserfelder Str. 432",
    "sg:city":"Siegen",
    "sg:phone":"+49 271/382066",
    "sg:postcode":"57080",
    "sg:province":"Nordrhein-Westfalen",
    "wof:name":"D. Kas\u00fcske & G. Knipp",
    "wof:placetype":"venue"
},
  "geometry": {"coordinates":[7.9877848625,50.8370933533],"type":"Point"}
}