{
  "type": "Feature",
  "properties": {
    "iso:country":"DE",
    "sg:address":"Oberdreeser Str. 13",
    "sg:city":"Rheinbach",
    "sg:phone":"+49 2226/912083",
    "sg:postcode":"53359",
    "sg:province":"Nordrhein-Westfalen",
    "wof:name":"T. Ohm Rechtsanwalt",
    "wof:placetype":"venue"
},
  "geometry": {"coordinates":[6.9194140434,50.6414108276],"type":"Point"}
}