{
  "type": "Feature",
  "properties": {
    "iso:country":"DE",
    "sg:address":"Zu den Moorteilen 97",
    "sg:city":"Quernheim",
    "sg:phone":"+49 5443/1533",
    "sg:postcode":"49448",
    "sg:province":"Niedersachsen",
    "wof:name":"Henning Stummeyer Rechtsanwalt",
    "wof:placetype":"venue"
},
  "geometry": {"coordinates":[8.3942623138,52.4655532837],"type":"Point"}
}