{
  "type": "Feature",
  "properties": {
    "iso:country":"DE",
    "sg:address":"K\u00f6lner Str. 106",
    "sg:city":"Remscheid",
    "sg:phone":"+49 2191/963456",
    "sg:postcode":"42897",
    "sg:province":"Nordrhein-Westfalen",
    "wof:name":"Musikhaus Andre Louis Gmbh",
    "wof:placetype":"venue"
},
  "geometry": {"coordinates":[7.2546682358,51.1844940186],"type":"Point"}
}