{
  "type": "Feature",
  "properties": {
    "iso:country":"DE",
    "sg:address":"Lautenthaler Str. 56",
    "sg:city":"Seesen",
    "sg:postcode":"38723",
    "sg:province":"Niedersachsen",
    "wof:name":"Fischer Silotechnologie Gmbh",
    "wof:placetype":"venue"
},
  "geometry": {"coordinates":[10.19328,51.886536],"type":"Point"}
}