{
  "type": "Feature",
  "properties": {
    "iso:country":"DE",
    "sg:address":"Zum Silberling 18",
    "sg:city":"Hennef",
    "sg:postcode":"53773",
    "sg:province":"Nordrhein-Westfalen",
    "wof:name":"P. Neimann",
    "wof:placetype":"venue"
},
  "geometry": {"coordinates":[7.339137,50.77953],"type":"Point"}
}