{
  "type": "Feature",
  "properties": {
    "iso:country":"DE",
    "sg:address":"Wildbader Str. 45-1",
    "sg:city":"Dobel",
    "sg:phone":"+49 7083/8758",
    "sg:postcode":"75335",
    "sg:province":"Baden-W\u00fcrttemberg",
    "wof:name":"Hotel-restaurant Wagnerst\u00fcble Inh. R. Kieferle",
    "wof:placetype":"venue"
},
  "geometry": {"coordinates":[8.4984474182,48.7947883606],"type":"Point"}
}