{
  "type": "Feature",
  "properties": {
    "iso:country":"DE",
    "sg:address":"Gewerbepark 11",
    "sg:city":"Rauenstein",
    "sg:phone":"+49 36766/8800",
    "sg:postcode":"96528",
    "sg:province":"Th\u00fcringen",
    "wof:name":"Fct Hartbearbeitungs Gmbh",
    "wof:placetype":"venue"
},
  "geometry": {"coordinates":[11.0427103043,50.4106025696],"type":"Point"}
}