{
  "type": "Feature",
  "properties": {
    "iso:country":"DE",
    "sg:address":"Kirchstr. 5",
    "sg:city":"Bad W\u00fcnnenberg",
    "sg:phone":"+49 2953/8344",
    "sg:postcode":"33181",
    "sg:province":"Nordrhein-Westfalen",
    "wof:name":"Weber Architekt",
    "wof:placetype":"venue"
},
  "geometry": {"coordinates":[8.740903,51.515881],"type":"Point"}
}