{
  "type": "Feature",
  "properties": {
    "iso:country":"DE",
    "sg:address":"Leimengrubenstr. 8",
    "sg:city":"Gerlingen",
    "sg:phone":"+49 7156/28741",
    "sg:postcode":"70839",
    "sg:province":"Baden-W\u00fcrttemberg",
    "wof:name":"Stockinger Gmbh",
    "wof:placetype":"venue"
},
  "geometry": {"coordinates":[9.0567274094,48.7971572876],"type":"Point"}
}