{
  "type": "Feature",
  "properties": {
    "iso:country":"DE",
    "sg:address":"Starkertshofen 12",
    "sg:city":"Reichertshofen",
    "sg:phone":"+49 8446/439",
    "sg:postcode":"85084",
    "sg:province":"Bayern",
    "wof:name":"Silvia Schmid",
    "wof:placetype":"venue"
},
  "geometry": {"coordinates":[11.464996,48.655891],"type":"Point"}
}