{
  "type": "Feature",
  "properties": {
    "iso:country":"DE",
    "sg:address":"Kirchstr. 11",
    "sg:city":"Lengerich",
    "sg:phone":"+49 5904/885",
    "sg:postcode":"49838",
    "sg:province":"Niedersachsen",
    "wof:name":"Wilhelm Stassen Elektrountern.",
    "wof:placetype":"venue"
},
  "geometry": {"coordinates":[7.5316271782,52.5544929504],"type":"Point"}
}