{
  "type": "Feature",
  "properties": {
    "iso:country":"DE",
    "sg:address":"Le-Croisic-Str. 21",
    "sg:city":"Laufenburg",
    "sg:postcode":"79725",
    "sg:province":"Baden-W\u00fcrttemberg",
    "wof:name":"Hydroq Gmbh",
    "wof:placetype":"venue"
},
  "geometry": {"coordinates":[8.0570354462,47.56690979],"type":"Point"}
}