{
  "type": "Feature",
  "properties": {
    "iso:country":"DE",
    "sg:address":"Am M\u00fchlanger 8",
    "sg:city":"Ismaning",
    "sg:phone":"+49 89/963070",
    "sg:postcode":"85737",
    "sg:province":"Bayern",
    "wof:name":"Immobilien Irmgard Mielczarek",
    "wof:placetype":"venue"
},
  "geometry": {"coordinates":[11.6778478622,48.2235527039],"type":"Point"}
}