{
  "type": "Feature",
  "properties": {
    "iso:country":"DE",
    "sg:address":"Hemberger Str. 63",
    "sg:city":"Bornheim",
    "sg:phone":"+49 2227/1384",
    "sg:postcode":"53332",
    "sg:province":"Nordrhein-Westfalen",
    "wof:name":"Inau Automatik",
    "wof:placetype":"venue"
},
  "geometry": {"coordinates":[6.996895,50.760811],"type":"Point"}
}