{
  "type": "Feature",
  "properties": {
    "iso:country":"DE",
    "sg:address":"Waldpfad 61",
    "sg:city":"Plankstadt",
    "sg:phone":"+49 6202/26743",
    "sg:postcode":"68723",
    "sg:province":"Baden-W\u00fcrttemberg",
    "wof:name":"Meisel Consulting Gmbh",
    "wof:placetype":"venue"
},
  "geometry": {"coordinates":[8.5913963318,49.3917274475],"type":"Point"}
}