{
  "type": "Feature",
  "properties": {
    "iso:country":"DE",
    "sg:address":"Breslauer Str. 18",
    "sg:city":"L\u00f6rrach",
    "sg:phone":"+49 7621/2976",
    "sg:postcode":"79539",
    "sg:province":"Baden-W\u00fcrttemberg",
    "wof:name":"Dr. Harry Ende Dipl.-chem.",
    "wof:placetype":"venue"
},
  "geometry": {"coordinates":[7.6752171516,47.6142654419],"type":"Point"}
}