{
  "type": "Feature",
  "properties": {
    "iso:country":"DE",
    "sg:address":"Wiesenstr. 39",
    "sg:city":"Staudt",
    "sg:phone":"+49 2602/60053",
    "sg:postcode":"56424",
    "sg:province":"Rheinland-Pfalz",
    "wof:name":"Korbach Speditions- Und Transporte Gmbh",
    "wof:placetype":"venue"
},
  "geometry": {"coordinates":[7.8319158554,50.4681587219],"type":"Point"}
}