{
  "type": "Feature",
  "properties": {
    "iso:country":"DE",
    "sg:address":"Heidenheimer Str. 21",
    "sg:city":"Neresheim",
    "sg:phone":"+49 7326/919931",
    "sg:postcode":"73450",
    "sg:province":"Baden-W\u00fcrttemberg",
    "wof:name":"Lux Cnc Fr\u00e4s- Und Drehteile",
    "wof:placetype":"venue"
},
  "geometry": {"coordinates":[10.327385,48.755028],"type":"Point"}
}