{
  "type": "Feature",
  "properties": {
    "iso:country":"DE",
    "sg:address":"Saalkamp 38",
    "sg:city":"Hamburg",
    "sg:postcode":"22397",
    "sg:province":"Hamburg",
    "wof:name":"Ilm-institut",
    "wof:placetype":"venue"
},
  "geometry": {"coordinates":[10.1063451767,53.7029075623],"type":"Point"}
}