{
  "type": "Feature",
  "properties": {
    "iso:country":"DE",
    "sg:address":"Falkenried 7",
    "sg:city":"Hamburg",
    "sg:postcode":"20251",
    "sg:province":"Hamburg",
    "wof:name":"Michael-balint-institut Institut F\u00fcr Psychoanalyse",
    "wof:placetype":"venue"
},
  "geometry": {"coordinates":[9.9786729813,53.5814933777],"type":"Point"}
}