{
  "type": "Feature",
  "properties": {
    "iso:country":"DE",
    "sg:address":"G\u00f6dinghover Weg 80",
    "sg:city":"D\u00fcsseldorf",
    "sg:phone":"+49 211/273989",
    "sg:postcode":"40627",
    "sg:province":"Nordrhein-Westfalen",
    "wof:name":"Galerie Wohnart Gmbh",
    "wof:placetype":"venue"
},
  "geometry": {"coordinates":[6.8724961281,51.2178077698],"type":"Point"}
}