{
  "type": "Feature",
  "properties": {
    "iso:country":"DE",
    "sg:address":"Bremen",
    "sg:city":"Hohentengen",
    "sg:phone":"+49 7572/78511",
    "sg:postcode":"88367",
    "sg:province":"Baden-W\u00fcrttemberg",
    "wof:name":"Gasthaus Zur Br\u00fccke",
    "wof:placetype":"venue"
},
  "geometry": {"coordinates":[9.3629703522,48.0282859802],"type":"Point"}
}