{
  "type": "Feature",
  "properties": {
    "iso:country":"DE",
    "sg:address":"Tournelystr. 18",
    "sg:city":"Stadtbergen",
    "sg:phone":"+49 821/435512",
    "sg:postcode":"86391",
    "sg:province":"Bayern",
    "wof:name":"Gustav Fischbach Ingenieur",
    "wof:placetype":"venue"
},
  "geometry": {"coordinates":[10.833706,48.353119],"type":"Point"}
}