{
  "type": "Feature",
  "properties": {
    "iso:country":"DE",
    "sg:address":"Kurze Str. 15",
    "sg:city":"Uslar",
    "sg:phone":"+49 5571/7942",
    "sg:postcode":"37170",
    "sg:province":"Niedersachsen",
    "wof:name":"L\u00fccke",
    "wof:placetype":"venue"
},
  "geometry": {"coordinates":[9.6347751617,51.6600341797],"type":"Point"}
}