{
  "type": "Feature",
  "properties": {
    "iso:country":"DE",
    "sg:address":"Leonhardiweg 1",
    "sg:city":"Zusmarshausen",
    "sg:phone":"+49 8291/383",
    "sg:postcode":"86441",
    "sg:province":"Bayern",
    "wof:name":"H. Huber",
    "wof:placetype":"venue"
},
  "geometry": {"coordinates":[10.599088,48.433334],"type":"Point"}
}