{
  "type": "Feature",
  "properties": {
    "iso:country":"DE",
    "sg:address":"Im Kreuztal 82",
    "sg:city":"Wissen",
    "sg:phone":"+49 2742/2631",
    "sg:postcode":"57537",
    "sg:province":"Rheinland-Pfalz",
    "wof:name":"Gert P\u00fctter",
    "wof:placetype":"venue"
},
  "geometry": {"coordinates":[7.732627,50.780224],"type":"Point"}
}