{
  "type": "Feature",
  "properties": {
    "iso:country":"DE",
    "sg:address":"Tschaikowskistr. 29",
    "sg:city":"Leipzig",
    "sg:phone":"+49 341/9806785",
    "sg:postcode":"04105",
    "sg:province":"Sachsen",
    "wof:name":"Ursula Weitzd\u00f6rfer \u00c4rztin F\u00fcr Allgemeinmedizin",
    "wof:placetype":"venue"
},
  "geometry": {"coordinates":[12.3600893021,51.3458633423],"type":"Point"}
}