{
  "type": "Feature",
  "properties": {
    "iso:country":"DE",
    "sg:address":"Mutter-Ey-Str. 5",
    "sg:city":"D\u00fcsseldorf",
    "sg:postcode":"40213",
    "sg:province":"Nordrhein-Westfalen",
    "wof:name":"Innofact Ag",
    "wof:placetype":"venue"
},
  "geometry": {"coordinates":[6.775668,51.22715],"type":"Point"}
}