{
  "type": "Feature",
  "properties": {
    "iso:country":"DE",
    "sg:address":"\u00d6stliche Zwingergasse 17",
    "sg:city":"Deggendorf",
    "sg:phone":"+49 991/340421",
    "sg:postcode":"94469",
    "sg:province":"Bayern",
    "wof:name":"Christian Altmann",
    "wof:placetype":"venue"
},
  "geometry": {"coordinates":[12.9646244049,48.8330688477],"type":"Point"}
}