{
  "type": "Feature",
  "properties": {
    "iso:country":"DE",
    "sg:address":"Taubenweg 71",
    "sg:city":"Leverkusen",
    "sg:phone":"+49 2171/51118",
    "sg:postcode":"51381",
    "sg:province":"Nordrhein-Westfalen",
    "wof:name":"Egon Kaschta",
    "wof:placetype":"venue"
},
  "geometry": {"coordinates":[7.046371,51.058094],"type":"Point"}
}