{
  "type": "Feature",
  "properties": {
    "iso:country":"DE",
    "sg:address":"B\u00fcltestr. 70",
    "sg:city":"L\u00f6hne",
    "sg:phone":"+49 5731/81669",
    "sg:postcode":"32584",
    "sg:province":"Nordrhein-Westfalen",
    "wof:name":"Tannenhof",
    "wof:placetype":"venue"
},
  "geometry": {"coordinates":[8.7824296951,52.1907806396],"type":"Point"}
}