{
  "type": "Feature",
  "properties": {
    "iso:country":"DE",
    "sg:address":"Hauptstra\u00dfe48",
    "sg:city":"Didderse",
    "sg:phone":"+49 5373",
    "sg:postcode":"38530",
    "sg:province":"Niedersachsen",
    "wof:name":"Mesa Messen & Abrechnen Eckhard Meier Gmbh",
    "wof:placetype":"venue"
},
  "geometry": {"coordinates":[10.4030237198,52.3805809021],"type":"Point"}
}