{
  "type": "Feature",
  "properties": {
    "iso:country":"DE",
    "sg:address":"Riedstr. 38",
    "sg:city":"Konstanz",
    "sg:phone":"+49 7531/73033",
    "sg:postcode":"78467",
    "sg:province":"Baden-W\u00fcrttemberg",
    "wof:name":"E. Buchholz",
    "wof:placetype":"venue"
},
  "geometry": {"coordinates":[9.147111,47.683681],"type":"Point"}
}