{
  "type": "Feature",
  "properties": {
    "iso:country":"DE",
    "sg:address":"Petershof 22b",
    "sg:city":"Thurnau",
    "sg:postcode":"95349",
    "sg:province":"Bayern",
    "wof:name":"Hofmann Immobilien E. K.",
    "wof:placetype":"venue"
},
  "geometry": {"coordinates":[11.3861312866,50.0271110535],"type":"Point"}
}