{
  "type": "Feature",
  "properties": {
    "iso:country":"DE",
    "sg:address":"Wallstr. 1",
    "sg:city":"Blankenburg",
    "sg:phone":"+49 3944/2081",
    "sg:postcode":"38889",
    "sg:province":"Sachsen-Anhalt",
    "wof:name":"Karl-heinz Lamade Makler",
    "wof:placetype":"venue"
},
  "geometry": {"coordinates":[10.9510135651,51.7891311646],"type":"Point"}
}