{
  "type": "Feature",
  "properties": {
    "iso:country":"DE",
    "sg:address":"Steindamm 55",
    "sg:city":"Bremen",
    "sg:phone":"+49 421/642386",
    "sg:postcode":"28719",
    "sg:province":"Bremen",
    "wof:name":"Draht Dressel",
    "wof:placetype":"venue"
},
  "geometry": {"coordinates":[8.707576,53.16029],"type":"Point"}
}