{
  "type": "Feature",
  "properties": {
    "iso:country":"DE",
    "sg:address":"Ernst-Rein-Str. 21",
    "sg:city":"Bielefeld",
    "sg:phone":"+49 521/967230",
    "sg:postcode":"33613",
    "sg:province":"Nordrhein-Westfalen",
    "wof:name":"Perthes-haus Alten- Und Pflegeheim",
    "wof:placetype":"venue"
},
  "geometry": {"coordinates":[8.53392,52.03418],"type":"Point"}
}