{
  "type": "Feature",
  "properties": {
    "iso:country":"DE",
    "sg:address":"Dorfstr. 44",
    "sg:city":"Mildenau",
    "sg:phone":"+49 3733/555100",
    "sg:postcode":"09456",
    "sg:province":"Sachsen",
    "wof:name":"Bekleidungshaus J\u00e4ckel Inh. Marion Gentzen",
    "wof:placetype":"venue"
},
  "geometry": {"coordinates":[13.069637,50.595261],"type":"Point"}
}