{
  "type": "Feature",
  "properties": {
    "iso:country":"DE",
    "sg:address":"Beuditzstr. 32",
    "sg:city":"Wei\u00dfenfels",
    "sg:phone":"+49 3443/305448",
    "sg:postcode":"06667",
    "sg:province":"Sachsen-Anhalt",
    "wof:name":"Bobolowski & Wihan",
    "wof:placetype":"venue"
},
  "geometry": {"coordinates":[11.960735,51.199615],"type":"Point"}
}