{
  "type": "Feature",
  "properties": {
    "iso:country":"DE",
    "sg:address":"Pirmasenser Weg 40",
    "sg:city":"Pirmasens",
    "sg:phone":"+49 6331/64027",
    "sg:postcode":"66954",
    "sg:province":"Rheinland-Pfalz",
    "wof:name":"Philipps Reisen Inh. Philipp Mayer",
    "wof:placetype":"venue"
},
  "geometry": {"coordinates":[7.5891990662,49.2244644165],"type":"Point"}
}