{
  "type": "Feature",
  "properties": {
    "iso:country":"DE",
    "sg:address":"Holstenstr. 48",
    "sg:city":"Schenefeld",
    "sg:phone":"+49 4892/346",
    "sg:postcode":"25560",
    "sg:province":"Schleswig-Holstein",
    "wof:name":"Berg-apotheke",
    "wof:placetype":"venue"
},
  "geometry": {"coordinates":[9.481104,54.045734],"type":"Point"}
}