{
  "type": "Feature",
  "properties": {
    "iso:country":"DE",
    "sg:address":"Kurhessenstr. 25",
    "sg:city":"Neukirchen",
    "sg:phone":"+49 6694/366",
    "sg:postcode":"34626",
    "sg:province":"Hessen",
    "wof:name":"Karl Knoll Papier- Und Schreibwaren",
    "wof:placetype":"venue"
},
  "geometry": {"coordinates":[9.34431,50.868191],"type":"Point"}
}