{
  "type": "Feature",
  "properties": {
    "iso:country":"DE",
    "sg:address":"Gewerbegebiet Kuhleich",
    "sg:city":"Tann",
    "sg:phone":"+49 6682/1899",
    "sg:postcode":"36142",
    "sg:province":"Hessen",
    "wof:name":"H. Drott",
    "wof:placetype":"venue"
},
  "geometry": {"coordinates":[10.01533,50.62664],"type":"Point"}
}