{
  "type": "Feature",
  "properties": {
    "iso:country":"DE",
    "sg:address":"Auf dem Boden 22",
    "sg:city":"Netphen",
    "sg:phone":"+49 2738/1769",
    "sg:postcode":"57250",
    "sg:province":"Nordrhein-Westfalen",
    "wof:name":"Fl\u00fcga Fl\u00fcssiggasvertrieb Verwaltungs- Und",
    "wof:placetype":"venue"
},
  "geometry": {"coordinates":[8.1326,50.918568],"type":"Point"}
}