{
  "type": "Feature",
  "properties": {
    "iso:country":"DE",
    "sg:address":"Zum Espen 3",
    "sg:city":"Singen",
    "sg:phone":"+49 7731/29307",
    "sg:postcode":"78224",
    "sg:province":"Baden-W\u00fcrttemberg",
    "wof:name":"Palummo & Schneider Friseurtechnik Gmbh",
    "wof:placetype":"venue"
},
  "geometry": {"coordinates":[8.8954343796,47.7218322754],"type":"Point"}
}