{
  "type": "Feature",
  "properties": {
    "iso:country":"DE",
    "sg:address":"Wiesendamm 126",
    "sg:city":"Hamburg",
    "sg:phone":"+49 40/273437",
    "sg:postcode":"22303",
    "sg:province":"Hamburg",
    "wof:name":"K & W Karin Wurst",
    "wof:placetype":"venue"
},
  "geometry": {"coordinates":[10.0195856094,53.589679718],"type":"Point"}
}