{
  "type": "Feature",
  "properties": {
    "iso:country":"DE",
    "sg:address":"An der R\u00f6te 24",
    "sg:city":"Sinsheim",
    "sg:phone":"+49 7265/7092",
    "sg:postcode":"74889",
    "sg:province":"Baden-W\u00fcrttemberg",
    "wof:name":"Ges. Zur F\u00f6rderung Des Reitsports Neckargem. Mbh",
    "wof:placetype":"venue"
},
  "geometry": {"coordinates":[8.780620575,49.2543792725],"type":"Point"}
}