{
  "type": "Feature",
  "properties": {
    "iso:country":"DE",
    "sg:address":"Berndesallee 71-73",
    "sg:city":"Heidesheim",
    "sg:phone":"+49 6132/58848",
    "sg:postcode":"55262",
    "sg:province":"Rheinland-Pfalz",
    "wof:name":"Heidesheimmaschinen Hagen W. Dieter",
    "wof:placetype":"venue"
},
  "geometry": {"coordinates":[8.103278,49.992294],"type":"Point"}
}