{
  "type": "Feature",
  "properties": {
    "iso:country":"DE",
    "sg:address":"An der Kirche 21",
    "sg:city":"Steinau",
    "sg:phone":"+49 6667/558",
    "sg:postcode":"36396",
    "sg:province":"Hessen",
    "wof:name":"Klaus Dorn",
    "wof:placetype":"venue"
},
  "geometry": {"coordinates":[9.418244,50.373341],"type":"Point"}
}