{
  "type": "Feature",
  "properties": {
    "iso:country":"DE",
    "sg:address":"Weinbergstr. 28",
    "sg:city":"Zornheim",
    "sg:phone":"+49 6136/43770",
    "sg:postcode":"55270",
    "sg:province":"Rheinland-Pfalz",
    "wof:name":"Reinhold Mend",
    "wof:placetype":"venue"
},
  "geometry": {"coordinates":[8.233938,49.89518],"type":"Point"}
}