{
  "type": "Feature",
  "properties": {
    "iso:country":"DE",
    "sg:city":"Ingolstadt",
    "sg:phone":"+49 8450",
    "sg:postcode":"85051",
    "sg:province":"Bayern",
    "wof:name":"Feng Shui Beratungen",
    "wof:placetype":"venue"
},
  "geometry": {"coordinates":[11.40555,48.71241],"type":"Point"}
}