{
  "type": "Feature",
  "properties": {
    "iso:country":"DE",
    "sg:address":"Hermannstr. 22",
    "sg:city":"Rostock",
    "sg:phone":"+49 381/27903",
    "sg:postcode":"18055",
    "sg:province":"Mecklenburg-Vorpommern",
    "wof:name":"Dr. V. Schr\u00f6der Ingenieur",
    "wof:placetype":"venue"
},
  "geometry": {"coordinates":[12.1354951859,54.0811691284],"type":"Point"}
}