{
  "type": "Feature",
  "properties": {
    "iso:country":"DE",
    "sg:address":"Hermann-L\u00f6ns-Str. 19",
    "sg:city":"Ense",
    "sg:phone":"+49 2938/2345",
    "sg:postcode":"59469",
    "sg:province":"Nordrhein-Westfalen",
    "wof:name":"Hustadt & Hansen M\u00f6belagentur-gmbh",
    "wof:placetype":"venue"
},
  "geometry": {"coordinates":[7.944065094,51.4861221313],"type":"Point"}
}