{
  "type": "Feature",
  "properties": {
    "iso:country":"DE",
    "sg:address":"Oberasberg 2",
    "sg:city":"Rinchnach",
    "sg:phone":"+49 9922/3063",
    "sg:postcode":"94269",
    "sg:province":"Bayern",
    "wof:name":"Hotel Haus Am Berg",
    "wof:placetype":"venue"
},
  "geometry": {"coordinates":[13.2170200348,48.9675102234],"type":"Point"}
}