{
  "type": "Feature",
  "properties": {
    "iso:country":"DE",
    "sg:address":"Kirchstr. 3",
    "sg:city":"Wuppertal",
    "sg:phone":"+49 202/2989719",
    "sg:postcode":"42103",
    "sg:province":"Nordrhein-Westfalen",
    "wof:name":"Casa Bellezza",
    "wof:placetype":"venue"
},
  "geometry": {"coordinates":[7.1474971771,51.2566223145],"type":"Point"}
}