{
  "type": "Feature",
  "properties": {
    "iso:country":"DE",
    "sg:address":"Alte Poststr. 119",
    "sg:city":"Schermbeck",
    "sg:postcode":"46514",
    "sg:province":"Nordrhein-Westfalen",
    "wof:name":"Hess Gmbh",
    "wof:placetype":"venue"
},
  "geometry": {"coordinates":[6.8681511879,51.6805496216],"type":"Point"}
}