{
  "type": "Feature",
  "properties": {
    "iso:country":"DE",
    "sg:address":"Industriestr 2",
    "sg:city":"Schillingsf\u00fcrst",
    "sg:phone":"+49 9868/989490",
    "sg:postcode":"91583",
    "sg:province":"Bayern",
    "wof:name":"Styro Gmbh",
    "wof:placetype":"venue"
},
  "geometry": {"coordinates":[10.246889,49.277966],"type":"Point"}
}