{
  "type": "Feature",
  "properties": {
    "iso:country":"DE",
    "sg:address":"Br\u00e4uhausstr. 6",
    "sg:city":"Immenstadt",
    "sg:phone":"+49 8323/987280",
    "sg:postcode":"87509",
    "sg:province":"Bayern",
    "wof:name":"Fritz Rehrnbeck Heilpraktiker",
    "wof:placetype":"venue"
},
  "geometry": {"coordinates":[10.2174530029,47.559551239],"type":"Point"}
}