{
  "type": "Feature",
  "properties": {
    "iso:country":"DE",
    "sg:address":"Platanenstr.",
    "sg:city":"Lorsch",
    "sg:phone":"+49 6251/57711",
    "sg:postcode":"64653",
    "sg:province":"Hessen",
    "wof:name":"Friedel Dray\u00df",
    "wof:placetype":"venue"
},
  "geometry": {"coordinates":[8.56793,49.642059],"type":"Point"}
}