{
  "type": "Feature",
  "properties": {
    "iso:country":"DE",
    "sg:address":"Lothforster Str. 36-40",
    "sg:city":"Wassenberg",
    "sg:phone":"+49 2432/96660",
    "sg:postcode":"41849",
    "sg:province":"Nordrhein-Westfalen",
    "wof:name":"Bdl Maschinenbau Gmbh",
    "wof:placetype":"venue"
},
  "geometry": {"coordinates":[6.135801,51.102242],"type":"Point"}
}