{
  "type": "Feature",
  "properties": {
    "iso:country":"DE",
    "sg:address":"Sebastianstr. 67",
    "sg:city":"Bad Neuenahr-Ahrweiler",
    "sg:phone":"+49 2641/6327",
    "sg:postcode":"53474",
    "sg:province":"Rheinland-Pfalz",
    "wof:name":"Joachim Brinkmann",
    "wof:placetype":"venue"
},
  "geometry": {"coordinates":[7.1249451637,50.5448303223],"type":"Point"}
}