{
  "type": "Feature",
  "properties": {
    "iso:country":"DE",
    "sg:address":"Waitzinger Wiese 2",
    "sg:city":"Landsberg",
    "sg:phone":"+49 8191/1359",
    "sg:postcode":"86899",
    "sg:province":"Bayern",
    "wof:name":"Br\u00e4ust\u00fcberl",
    "wof:placetype":"venue"
},
  "geometry": {"coordinates":[10.8711242676,48.0568580627],"type":"Point"}
}