{
  "type": "Feature",
  "properties": {
    "iso:country":"DE",
    "sg:address":"Hattinger Str. 900 a",
    "sg:city":"Bochum",
    "sg:phone":"+49 234/9409091",
    "sg:postcode":"44879",
    "sg:province":"Nordrhein-Westfalen",
    "wof:name":"Immobilien H.-w. Zolc Gmbh",
    "wof:placetype":"venue"
},
  "geometry": {"coordinates":[7.165314,51.420582],"type":"Point"}
}