{
  "type": "Feature",
  "properties": {
    "iso:country":"DE",
    "sg:address":"Weidmattenstr. 11",
    "sg:city":"B\u00fchl",
    "sg:phone":"+49 7223/24145",
    "sg:postcode":"77815",
    "sg:province":"Baden-W\u00fcrttemberg",
    "wof:name":"Rolf Teichmann Komponist",
    "wof:placetype":"venue"
},
  "geometry": {"coordinates":[8.110408783,48.7220993042],"type":"Point"}
}