{
  "type": "Feature",
  "properties": {
    "iso:country":"DE",
    "sg:address":"Eichendorffstr. 72",
    "sg:city":"Kirchheim",
    "sg:phone":"+49 7021/54530",
    "sg:postcode":"73230",
    "sg:province":"Baden-W\u00fcrttemberg",
    "wof:name":"Cb-radio-club Teck E. V. Rolf Schmidt",
    "wof:placetype":"venue"
},
  "geometry": {"coordinates":[9.4582014084,48.6403198242],"type":"Point"}
}