{
  "type": "Feature",
  "properties": {
    "iso:country":"DE",
    "sg:address":"Pelikanstra\u00dfe 4",
    "sg:city":"Hannover",
    "sg:phone":"+49 511",
    "sg:postcode":"30167",
    "sg:province":"Niedersachsen",
    "wof:name":"Zahn\u00e4rztliche Gemeinschaftspraxis Pelikanstra\u00dfe",
    "wof:placetype":"venue"
},
  "geometry": {"coordinates":[9.77161,52.398727],"type":"Point"}
}