{
  "type": "Feature",
  "properties": {
    "iso:country":"DE",
    "sg:address":"Leuschnerstr. 58",
    "sg:city":"Stuttgart",
    "sg:phone":"+49 711/6158994",
    "sg:postcode":"70176",
    "sg:province":"Baden-W\u00fcrttemberg",
    "wof:name":"Susanne Baur",
    "wof:placetype":"venue"
},
  "geometry": {"coordinates":[9.1620063782,48.7756004333],"type":"Point"}
}