{
  "type": "Feature",
  "properties": {
    "iso:country":"DE",
    "sg:address":"Gustebiner Wende 1b",
    "sg:city":"Greifswald",
    "sg:postcode":"17491",
    "sg:province":"Mecklenburg-Vorpommern",
    "wof:name":"Cziotec Industrie-umform-und Werkzeugbautechnik Gmbh",
    "wof:placetype":"venue"
},
  "geometry": {"coordinates":[13.4036970139,54.0771102905],"type":"Point"}
}