{
  "type": "Feature",
  "properties": {
    "iso:country":"DE",
    "sg:address":"Antoniusweg 2",
    "sg:city":"Bad F\u00fcssing",
    "sg:phone":"+49 8531/21440",
    "sg:postcode":"94072",
    "sg:province":"Bayern",
    "wof:name":"Martin Resch Masseur",
    "wof:placetype":"venue"
},
  "geometry": {"coordinates":[13.338337,48.350334],"type":"Point"}
}