{
  "type": "Feature",
  "properties": {
    "iso:country":"DE",
    "sg:address":"Auf Hart 80",
    "sg:city":"Markgr\u00f6ningen",
    "sg:phone":"+49 7145/3739",
    "sg:postcode":"71706",
    "sg:province":"Baden-W\u00fcrttemberg",
    "wof:name":"M\u00fcller Immobilienmakler",
    "wof:placetype":"venue"
},
  "geometry": {"coordinates":[9.0689401627,48.9062423706],"type":"Point"}
}