{
  "type": "Feature",
  "properties": {
    "iso:country":"DE",
    "sg:city":"Wiesenbach",
    "sg:phone":"+49 6223/4362",
    "sg:postcode":"69257",
    "sg:province":"Baden-W\u00fcrttemberg",
    "wof:name":"C. Hartmann",
    "wof:placetype":"venue"
},
  "geometry": {"coordinates":[8.803548,49.361038],"type":"Point"}
}