{
  "type": "Feature",
  "properties": {
    "iso:country":"DE",
    "sg:address":"Kirchhellener Str. 23",
    "sg:city":"Gladbeck",
    "sg:phone":"+49 2043/42412",
    "sg:postcode":"45966",
    "sg:province":"Nordrhein-Westfalen",
    "wof:name":"H. Stezaly",
    "wof:placetype":"venue"
},
  "geometry": {"coordinates":[6.9472999573,51.5838508606],"type":"Point"}
}