{
  "type": "Feature",
  "properties": {
    "iso:country":"DE",
    "sg:address":"Holzplatz 1",
    "sg:city":"Borken",
    "sg:phone":"+49 2861/3065",
    "sg:postcode":"46325",
    "sg:province":"Nordrhein-Westfalen",
    "wof:name":"Johann Stewering",
    "wof:placetype":"venue"
},
  "geometry": {"coordinates":[6.8645868301,51.8608131409],"type":"Point"}
}