{
  "type": "Feature",
  "properties": {
    "iso:country":"DE",
    "sg:address":"Lindengasse 44",
    "sg:city":"Blaufelden",
    "sg:phone":"+49 7936/242",
    "sg:postcode":"74572",
    "sg:province":"Baden-W\u00fcrttemberg",
    "wof:name":"Andreas Gebhart Finanzberater",
    "wof:placetype":"venue"
},
  "geometry": {"coordinates":[9.8886404037,49.3254508972],"type":"Point"}
}