{
  "type": "Feature",
  "properties": {
    "iso:country":"DE",
    "sg:address":"Neckarstr. 41",
    "sg:city":"Bensheim",
    "sg:phone":"+49 6251/2836",
    "sg:postcode":"64625",
    "sg:province":"Hessen",
    "wof:name":"Starkenburger Milchleifervereinigung",
    "wof:placetype":"venue"
},
  "geometry": {"coordinates":[8.6187982559,49.6784744263],"type":"Point"}
}