{
  "type": "Feature",
  "properties": {
    "iso:country":"DE",
    "sg:address":"Stegemannstr. 16",
    "sg:city":"Koblenz",
    "sg:postcode":"56068",
    "sg:province":"Rheinland-Pfalz",
    "wof:name":"Gig-concerts Gmbh",
    "wof:placetype":"venue"
},
  "geometry": {"coordinates":[7.5957660675,50.3560791016],"type":"Point"}
}