{
  "type": "Feature",
  "properties": {
    "iso:country":"DE",
    "sg:address":"Dompfaffstr. 42",
    "sg:city":"Erlangen",
    "sg:phone":"+49 9131/43735",
    "sg:postcode":"91056",
    "sg:province":"Bayern",
    "wof:name":"E. Rudolph",
    "wof:placetype":"venue"
},
  "geometry": {"coordinates":[10.976103,49.604286],"type":"Point"}
}