{
  "type": "Feature",
  "properties": {
    "iso:country":"DE",
    "sg:address":"Behringstr. 120",
    "sg:city":"Hamburg",
    "sg:phone":"+49 40/8818010",
    "sg:postcode":"22763",
    "sg:province":"Hamburg",
    "wof:name":"Hfm Hamburger Facility Management Ag",
    "wof:placetype":"venue"
},
  "geometry": {"coordinates":[9.9084949493,53.5547103882],"type":"Point"}
}