{
  "type": "Feature",
  "properties": {
    "iso:country":"DE",
    "sg:address":"Joseph-M\u00e4urer-Str. 12",
    "sg:city":"Wipperf\u00fcrth",
    "sg:phone":"+49 2267/9160",
    "sg:postcode":"51688",
    "sg:province":"Nordrhein-Westfalen",
    "wof:name":"Garant Grundst\u00fccksverwertungs- Gmbh",
    "wof:placetype":"venue"
},
  "geometry": {"coordinates":[7.3802018166,51.1240158081],"type":"Point"}
}