{
  "type": "Feature",
  "properties": {
    "iso:country":"DE",
    "sg:address":"Tolkmittstr. 18",
    "sg:city":"Berlin",
    "sg:phone":"+49 30/5645792",
    "sg:postcode":"12621",
    "sg:province":"Berlin",
    "wof:name":"Manfred Streich",
    "wof:placetype":"venue"
},
  "geometry": {"coordinates":[13.609199,52.522812],"type":"Point"}
}