{
  "type": "Feature",
  "properties": {
    "iso:country":"DE",
    "sg:address":"Bahnstr. 86",
    "sg:city":"Grevenbroich",
    "sg:phone":"+49 2181/5491",
    "sg:postcode":"41515",
    "sg:province":"Nordrhein-Westfalen",
    "wof:name":"Okcuoglu",
    "wof:placetype":"venue"
},
  "geometry": {"coordinates":[6.5817117691,51.0920677185],"type":"Point"}
}