{
  "type": "Feature",
  "properties": {
    "iso:country":"DE",
    "sg:address":"Unterd\u00f6rnen 71",
    "sg:city":"Wuppertal",
    "sg:phone":"+49 202/2547218",
    "sg:postcode":"42283",
    "sg:province":"Nordrhein-Westfalen",
    "wof:name":"Rolf Kohlstock",
    "wof:placetype":"venue"
},
  "geometry": {"coordinates":[7.1910672188,51.2683792114],"type":"Point"}
}