{
  "type": "Feature",
  "properties": {
    "iso:country":"DE",
    "sg:address":"Alter Waidweg 18",
    "sg:city":"Gro\u00dfenhain",
    "sg:phone":"+49 3522/62171",
    "sg:postcode":"01558",
    "sg:province":"Sachsen",
    "wof:name":"Andreas Krysztofiak",
    "wof:placetype":"venue"
},
  "geometry": {"coordinates":[13.541676,51.295979],"type":"Point"}
}