{
  "type": "Feature",
  "properties": {
    "iso:country":"DE",
    "sg:address":"Wilhelmstr. 101",
    "sg:city":"B\u00fcnde",
    "sg:phone":"+49 5223/60860",
    "sg:postcode":"32257",
    "sg:province":"Nordrhein-Westfalen",
    "wof:name":"Bernhard Holtwick",
    "wof:placetype":"venue"
},
  "geometry": {"coordinates":[8.5618934631,52.1974716187],"type":"Point"}
}