{
  "type": "Feature",
  "properties": {
    "iso:country":"DE",
    "sg:address":"Ensheimer Str. 127",
    "sg:city":"St. Ingbert",
    "sg:postcode":"66386",
    "sg:province":"Saarland",
    "wof:name":"B\u00e4ckerei - Konditorei Werner Kayser",
    "wof:placetype":"venue"
},
  "geometry": {"coordinates":[7.105566,49.267643],"type":"Point"}
}