{
  "type": "Feature",
  "properties": {
    "iso:country":"DE",
    "sg:address":"Hof G\u00fcldenwerth 40",
    "sg:city":"Remscheid",
    "sg:phone":"+49 2191/790274",
    "sg:postcode":"42857",
    "sg:province":"Nordrhein-Westfalen",
    "wof:name":"Johann-ludwig Heim",
    "wof:placetype":"venue"
},
  "geometry": {"coordinates":[7.1593408585,51.1680755615],"type":"Point"}
}