{
  "type": "Feature",
  "properties": {
    "iso:country":"DE",
    "sg:address":"Hauptstr. 20",
    "sg:city":"Bernstadt",
    "sg:phone":"+49 35874/29180",
    "sg:postcode":"02748",
    "sg:province":"Sachsen",
    "wof:name":"Heidrun Knothe",
    "wof:placetype":"venue"
},
  "geometry": {"coordinates":[14.781288,51.068481],"type":"Point"}
}