{
  "type": "Feature",
  "properties": {
    "iso:country":"DE",
    "sg:address":"Sch\u00f6nbrunner Str. 16",
    "sg:city":"Aglasterhausen",
    "sg:phone":"+49 6262/95285",
    "sg:postcode":"74858",
    "sg:province":"Baden-W\u00fcrttemberg",
    "wof:name":"Heinz Ernst Ingenieur",
    "wof:placetype":"venue"
},
  "geometry": {"coordinates":[8.9604091644,49.3780288696],"type":"Point"}
}