{
  "type": "Feature",
  "properties": {
    "iso:country":"DE",
    "sg:address":"Mainzer Str. 3",
    "sg:city":"Alsheim",
    "sg:phone":"+49 6249/5253",
    "sg:postcode":"67577",
    "sg:province":"Rheinland-Pfalz",
    "wof:name":"Christian Reinhard",
    "wof:placetype":"venue"
},
  "geometry": {"coordinates":[8.341885,49.768173],"type":"Point"}
}