{
  "type": "Feature",
  "properties": {
    "iso:country":"DE",
    "sg:address":"Ahornallee 7",
    "sg:city":"Berlin",
    "sg:phone":"+49 30/3655584",
    "sg:postcode":"14089",
    "sg:province":"Berlin",
    "wof:name":"Paul L\u00f6chel Steuerberater",
    "wof:placetype":"venue"
},
  "geometry": {"coordinates":[13.1232318878,52.4694290161],"type":"Point"}
}