{
  "type": "Feature",
  "properties": {
    "iso:country":"DE",
    "sg:address":"Niewaldstr. 82",
    "sg:city":"Detmold",
    "sg:phone":"+49 5232/65444",
    "sg:postcode":"32758",
    "sg:province":"Nordrhein-Westfalen",
    "wof:name":"Meierherm Gmbh",
    "wof:placetype":"venue"
},
  "geometry": {"coordinates":[8.84853,51.97538],"type":"Point"}
}