{
  "type": "Feature",
  "properties": {
    "iso:country":"DE",
    "sg:address":"L\u00e4rchenweg 4",
    "sg:city":"Werdau",
    "sg:phone":"+49 3761/885646",
    "sg:postcode":"08412",
    "sg:province":"Sachsen",
    "wof:name":"N. G\u00f6pel",
    "wof:placetype":"venue"
},
  "geometry": {"coordinates":[12.3218898773,50.7280311584],"type":"Point"}
}