{
  "type": "Feature",
  "properties": {
    "iso:country":"DE",
    "sg:address":"Johann-Sebastian-Bach-Platz 20",
    "sg:city":"Ansbach",
    "sg:phone":"+49 981/969600",
    "sg:postcode":"91522",
    "sg:province":"Bayern",
    "wof:name":"Wilhelm Jotz",
    "wof:placetype":"venue"
},
  "geometry": {"coordinates":[10.5746421814,49.3023719788],"type":"Point"}
}