{
  "type": "Feature",
  "properties": {
    "iso:country":"DE",
    "sg:address":"Nibelungenstr. 57",
    "sg:city":"Miltenberg",
    "sg:phone":"+49 9371/2516",
    "sg:postcode":"63897",
    "sg:province":"Bayern",
    "wof:name":"Wolf Gmbh Grabmal- Und Steinmetzbetrieb",
    "wof:placetype":"venue"
},
  "geometry": {"coordinates":[9.2201166153,49.6882171631],"type":"Point"}
}