{
  "type": "Feature",
  "properties": {
    "iso:country":"DE",
    "sg:address":"Ziegeleiweg 7",
    "sg:city":"Aichhalden",
    "sg:phone":"+49 7444/2071",
    "sg:postcode":"78733",
    "sg:province":"Baden-W\u00fcrttemberg",
    "wof:name":"Pension Armbruster",
    "wof:placetype":"venue"
},
  "geometry": {"coordinates":[8.4243602753,48.2980194092],"type":"Point"}
}