{
  "type": "Feature",
  "properties": {
    "iso:country":"DE",
    "sg:address":"Lippst\u00e4dter Str. 2",
    "sg:city":"Erwitte",
    "sg:phone":"+49 2943/2414",
    "sg:postcode":"59597",
    "sg:province":"Nordrhein-Westfalen",
    "wof:name":"Dransfeld",
    "wof:placetype":"venue"
},
  "geometry": {"coordinates":[8.3360090256,51.6120376587],"type":"Point"}
}