{
  "type": "Feature",
  "properties": {
    "iso:country":"DE",
    "sg:address":"Scheunebergstr. 41",
    "sg:city":"Delmenhorst",
    "sg:phone":"+49 4221/14055",
    "sg:postcode":"27749",
    "sg:province":"Niedersachsen",
    "wof:name":"Anonyme Drogenberatung Arbeiterwohlfahrt",
    "wof:placetype":"venue"
},
  "geometry": {"coordinates":[8.634219,53.045486],"type":"Point"}
}