{
  "type": "Feature",
  "properties": {
    "iso:country":"DE",
    "sg:address":"Zur M\u00fchle 5",
    "sg:city":"Langelsheim",
    "sg:phone":"+49 5326/3279",
    "sg:postcode":"38685",
    "sg:province":"Niedersachsen",
    "wof:name":"Bodo Prange Steuerberater",
    "wof:placetype":"venue"
},
  "geometry": {"coordinates":[10.3605270386,51.9247741699],"type":"Point"}
}