{
  "type": "Feature",
  "properties": {
    "iso:country":"DE",
    "sg:address":"Hintere Rottach 7",
    "sg:city":"Kempten",
    "sg:phone":"+49 831/93222",
    "sg:postcode":"87439",
    "sg:province":"Bayern",
    "wof:name":"Karl Ziegler",
    "wof:placetype":"venue"
},
  "geometry": {"coordinates":[10.299109,47.734196],"type":"Point"}
}