{
  "type": "Feature",
  "properties": {
    "iso:country":"DE",
    "sg:address":"Max-Planck-Str. 7",
    "sg:city":"Altshausen",
    "sg:postcode":"88361",
    "sg:province":"Baden-W\u00fcrttemberg",
    "wof:name":"Gersa Ger\u00e4tebau Gmbh",
    "wof:placetype":"venue"
},
  "geometry": {"coordinates":[9.5360641479,47.9238510132],"type":"Point"}
}