{
  "type": "Feature",
  "properties": {
    "iso:country":"DE",
    "sg:address":"Im Hag 5",
    "sg:city":"Sulzbach-Rosenberg",
    "sg:phone":"+49 9661/4598",
    "sg:postcode":"92237",
    "sg:province":"Bayern",
    "wof:name":"Paul Hudeczek",
    "wof:placetype":"venue"
},
  "geometry": {"coordinates":[11.7362804413,49.5060272217],"type":"Point"}
}