{
  "type": "Feature",
  "properties": {
    "iso:country":"DE",
    "sg:address":"Inzenham 4",
    "sg:city":"Prutting",
    "sg:phone":"+49 8036/30830",
    "sg:postcode":"83134",
    "sg:province":"Bayern",
    "wof:name":"Bbw Lasertechnik Gmbh",
    "wof:placetype":"venue"
},
  "geometry": {"coordinates":[12.2292070389,47.8801956177],"type":"Point"}
}