{
  "type": "Feature",
  "properties": {
    "iso:country":"DE",
    "sg:address":"Mainzer Landstr. 292",
    "sg:city":"Frankfurt",
    "sg:phone":"+49 69/733284",
    "sg:postcode":"60326",
    "sg:province":"Hessen",
    "wof:name":"Radio Sauerwein Nachf. Horst Fraud",
    "wof:placetype":"venue"
},
  "geometry": {"coordinates":[8.6374835968,50.1025543213],"type":"Point"}
}