{
  "type": "Feature",
  "properties": {
    "iso:country":"DE",
    "sg:address":"Martin-Behaim-Str. 3",
    "sg:city":"M\u00fcnchen",
    "sg:postcode":"81373",
    "sg:province":"Bayern",
    "wof:name":"Trans World Music Verlag Und Produktion Gmbh",
    "wof:placetype":"venue"
},
  "geometry": {"coordinates":[11.537314415,48.1245574951],"type":"Point"}
}