{
  "type": "Feature",
  "properties": {
    "iso:country":"DE",
    "sg:address":"M\u00fchlsteige 1",
    "sg:city":"M\u00fcnsingen",
    "sg:phone":"+49 4973/83395",
    "sg:postcode":"72525",
    "sg:province":"Baden-W\u00fcrttemberg",
    "wof:name":"Kreissparkasse Reutlingen",
    "wof:placetype":"venue"
},
  "geometry": {"coordinates":[9.494393,48.41116],"type":"Point"}
}