{
  "type": "Feature",
  "properties": {
    "iso:country":"DE",
    "sg:address":"Am Markt 11",
    "sg:city":"Sternberg",
    "sg:phone":"+49 3847/312234",
    "sg:postcode":"19406",
    "sg:province":"Mecklenburg-Vorpommern",
    "wof:name":"Horst Funke",
    "wof:placetype":"venue"
},
  "geometry": {"coordinates":[11.828199,53.712009],"type":"Point"}
}