{
  "type": "Feature",
  "properties": {
    "iso:country":"DE",
    "sg:address":"Wolf-Hirth-Str. 33",
    "sg:city":"B\u00f6blingen",
    "sg:phone":"+49 7031/71121",
    "sg:postcode":"71034",
    "sg:province":"Baden-W\u00fcrttemberg",
    "wof:name":"Stadtanzeiger Immobilien Gmbh & Co. Kg",
    "wof:placetype":"venue"
},
  "geometry": {"coordinates":[8.979138,48.681339],"type":"Point"}
}