{
  "type": "Feature",
  "properties": {
    "iso:country":"DE",
    "sg:address":"Br\u00fchlstr. 12",
    "sg:city":"Hilzingen",
    "sg:phone":"+49 7731/61026",
    "sg:postcode":"78247",
    "sg:province":"Baden-W\u00fcrttemberg",
    "wof:name":"Mauch Gmbh",
    "wof:placetype":"venue"
},
  "geometry": {"coordinates":[8.78191,47.757778],"type":"Point"}
}