{
  "type": "Feature",
  "properties": {
    "iso:country":"DE",
    "sg:address":"Realschulweg 20",
    "sg:city":"Wuppertal",
    "sg:phone":"+49 202/4781992",
    "sg:postcode":"42349",
    "sg:province":"Nordrhein-Westfalen",
    "wof:name":"Biom Umwelt- Und Biotechnik E. K.",
    "wof:placetype":"venue"
},
  "geometry": {"coordinates":[7.1331381798,51.198348999],"type":"Point"}
}