{
  "type": "Feature",
  "properties": {
    "iso:country":"DE",
    "sg:address":"Siemensstr. 20",
    "sg:city":"Ostfildern",
    "sg:phone":"+49 7158/4063",
    "sg:postcode":"73760",
    "sg:province":"Baden-W\u00fcrttemberg",
    "wof:name":"Filder-wohnbau Scharnhausen Gmbh & Co. Kg",
    "wof:placetype":"venue"
},
  "geometry": {"coordinates":[9.249662,48.707104],"type":"Point"}
}