{
  "type": "Feature",
  "properties": {
    "iso:country":"DE",
    "sg:address":"Turnerh\u00f6lzlstr. 25",
    "sg:city":"Siegenburg",
    "sg:phone":"+49 9444/427",
    "sg:postcode":"93354",
    "sg:province":"Bayern",
    "wof:name":"Karl Aschinger",
    "wof:placetype":"venue"
},
  "geometry": {"coordinates":[11.85239,48.751141],"type":"Point"}
}