{
  "type": "Feature",
  "properties": {
    "iso:country":"DE",
    "sg:address":"Aquinostr. 7 - 11",
    "sg:city":"K\u00f6ln",
    "sg:phone":"+49 221/211555",
    "sg:postcode":"50670",
    "sg:province":"Nordrhein-Westfalen",
    "wof:name":"Soz Zeit Verlags Gmbh",
    "wof:placetype":"venue"
},
  "geometry": {"coordinates":[6.9535732269,50.9514884949],"type":"Point"}
}