{
  "type": "Feature",
  "properties": {
    "iso:country":"DE",
    "sg:address":"Josef-Haubrich-Hof 1",
    "sg:city":"K\u00f6ln",
    "sg:phone":"+49 221/2213779",
    "sg:postcode":"50676",
    "sg:province":"Nordrhein-Westfalen",
    "wof:name":"Archiv Des International Stereoscopic Library And Isu",
    "wof:placetype":"venue"
},
  "geometry": {"coordinates":[6.949695,50.934963],"type":"Point"}
}