{
  "type": "Feature",
  "properties": {
    "iso:country":"DE",
    "sg:address":"Moosangerweg 12",
    "sg:city":"F\u00fcssen",
    "sg:phone":"+49 8362/91360",
    "sg:postcode":"87629",
    "sg:province":"Bayern",
    "wof:name":"Hans Baur Baustoffe Gro\u00df- Und Fachhandel",
    "wof:placetype":"venue"
},
  "geometry": {"coordinates":[10.701618,47.581169],"type":"Point"}
}