{
  "type": "Feature",
  "properties": {
    "iso:country":"DE",
    "sg:address":"Gotenstr. 86",
    "sg:city":"Bielefeld",
    "sg:postcode":"33647",
    "sg:province":"Nordrhein-Westfalen",
    "wof:name":"Bechler Tournee- Service E. Kfr.",
    "wof:placetype":"venue"
},
  "geometry": {"coordinates":[8.50242,51.995659],"type":"Point"}
}