{
  "type": "Feature",
  "properties": {
    "iso:country":"DE",
    "sg:address":"Gottlieb-Daimler-Str 1",
    "sg:city":"Rheinfelden",
    "sg:phone":"+49 7623/4177",
    "sg:postcode":"79618",
    "sg:province":"Baden-W\u00fcrttemberg",
    "wof:name":"Gutmann Zerspanungstechnik Gmbh",
    "wof:placetype":"venue"
},
  "geometry": {"coordinates":[7.7409,47.548462],"type":"Point"}
}