{
  "type": "Feature",
  "properties": {
    "iso:country":"DE",
    "sg:address":"Am Oberen Tor 17",
    "sg:city":"Waldeck",
    "sg:phone":"+49 5634/834",
    "sg:postcode":"34513",
    "sg:province":"Hessen",
    "wof:name":"Schreinerei D. Isenberg E. K.",
    "wof:placetype":"venue"
},
  "geometry": {"coordinates":[9.002288,51.250111],"type":"Point"}
}