{
  "type": "Feature",
  "properties": {
    "iso:country":"DE",
    "sg:address":"Am Vogelgesang 12",
    "sg:city":"Magdeburg",
    "sg:phone":"+49 391/224466",
    "sg:postcode":"39124",
    "sg:province":"Sachsen-Anhalt",
    "wof:name":"Vogelgesang",
    "wof:placetype":"venue"
},
  "geometry": {"coordinates":[11.6453733444,52.1664657593],"type":"Point"}
}