{
  "type": "Feature",
  "properties": {
    "iso:country":"DE",
    "sg:address":"Fischteichweg 15",
    "sg:city":"Aurich",
    "sg:phone":"+49 4941/63273",
    "sg:postcode":"26603",
    "sg:province":"Niedersachsen",
    "wof:name":"L\u00f6wen Play",
    "wof:placetype":"venue"
},
  "geometry": {"coordinates":[7.4823431969,53.46717453],"type":"Point"}
}