{
  "type": "Feature",
  "properties": {
    "iso:country":"DE",
    "sg:address":"Sigmaringer Str. 39",
    "sg:city":"Stuttgart",
    "sg:phone":"+49 711/717757",
    "sg:postcode":"70567",
    "sg:province":"Baden-W\u00fcrttemberg",
    "wof:name":"Ew Einrichten Und Wohnen Gmbh",
    "wof:placetype":"venue"
},
  "geometry": {"coordinates":[9.1570653915,48.731842041],"type":"Point"}
}