{
  "type": "Feature",
  "properties": {
    "iso:country":"DE",
    "sg:address":"Gl\u00e4ndstr. 14",
    "sg:city":"Mengen",
    "sg:phone":"+49 7576/2555",
    "sg:postcode":"88512",
    "sg:province":"Baden-W\u00fcrttemberg",
    "wof:name":"Michael Hepp",
    "wof:placetype":"venue"
},
  "geometry": {"coordinates":[9.2964782715,48.0240631104],"type":"Point"}
}