{
  "type": "Feature",
  "properties": {
    "iso:country":"DE",
    "sg:address":"Berner Str. 103",
    "sg:city":"Frankfurt",
    "sg:phone":"+49 69/9855730",
    "sg:postcode":"60437",
    "sg:province":"Hessen",
    "wof:name":"Konami Of Europe Gmbh",
    "wof:placetype":"venue"
},
  "geometry": {"coordinates":[8.655751,50.192894],"type":"Point"}
}