{
  "type": "Feature",
  "properties": {
    "iso:country":"DE",
    "sg:address":"Ostallee 39",
    "sg:city":"Trier",
    "sg:phone":"+49 651/72299",
    "sg:postcode":"54290",
    "sg:province":"Rheinland-Pfalz",
    "wof:name":"G\u00fcnter Felgenhauer",
    "wof:placetype":"venue"
},
  "geometry": {"coordinates":[6.6467838287,49.7537384033],"type":"Point"}
}