{
  "type": "Feature",
  "properties": {
    "iso:country":"DE",
    "sg:address":"Nebengasse 1",
    "sg:city":"Grolsheim",
    "sg:phone":"+49 6727/8665",
    "sg:postcode":"55459",
    "sg:province":"Rheinland-Pfalz",
    "wof:name":"Friedel Engel",
    "wof:placetype":"venue"
},
  "geometry": {"coordinates":[7.91413,49.909039],"type":"Point"}
}