{
  "type": "Feature",
  "properties": {
    "iso:country":"DE",
    "sg:address":"Grefrather Str. 52",
    "sg:city":"Wachtendonk",
    "sg:phone":"+49 2836/339",
    "sg:postcode":"47669",
    "sg:province":"Nordrhein-Westfalen",
    "wof:name":"Helmut Hermsen",
    "wof:placetype":"venue"
},
  "geometry": {"coordinates":[6.3088002205,51.3876991272],"type":"Point"}
}