{
  "type": "Feature",
  "properties": {
    "iso:country":"DE",
    "sg:address":"Sch\u00fctzenstr. 103",
    "sg:city":"Solingen",
    "sg:phone":"+49 212/2441711",
    "sg:postcode":"42659",
    "sg:province":"Nordrhein-Westfalen",
    "wof:name":"Christoph Bieker Rechtsanwalt",
    "wof:placetype":"venue"
},
  "geometry": {"coordinates":[7.0976009369,51.1625061035],"type":"Point"}
}