{
  "type": "Feature",
  "properties": {
    "iso:country":"DE",
    "sg:address":"Wittener Str. 35",
    "sg:city":"Castrop-Rauxel",
    "sg:phone":"+49 2305/29041",
    "sg:postcode":"44575",
    "sg:province":"Nordrhein-Westfalen",
    "wof:name":"K. Figge Garten- Und",
    "wof:placetype":"venue"
},
  "geometry": {"coordinates":[7.313626,51.547668],"type":"Point"}
}