{
  "type": "Feature",
  "properties": {
    "iso:country":"DE",
    "sg:address":"Helmholtzstr. 45",
    "sg:city":"Chemnitz",
    "sg:phone":"+49 371/300291",
    "sg:postcode":"09131",
    "sg:province":"Sachsen",
    "wof:name":"S. Uhle",
    "wof:placetype":"venue"
},
  "geometry": {"coordinates":[12.945309,50.854874],"type":"Point"}
}