{
  "type": "Feature",
  "properties": {
    "iso:country":"DE",
    "sg:address":"Friedrich-Ebert-Str. 26",
    "sg:city":"Roth",
    "sg:phone":"+49 9171/5950",
    "sg:postcode":"91154",
    "sg:province":"Bayern",
    "wof:name":"Ludwig Kaiser Rechtsanwalt",
    "wof:placetype":"venue"
},
  "geometry": {"coordinates":[11.1000328064,49.2507362366],"type":"Point"}
}