{
  "type": "Feature",
  "properties": {
    "iso:country":"DE",
    "sg:address":"Mittlere Str. 29",
    "sg:city":"Weil am Rhein",
    "sg:phone":"+49 7621/799555",
    "sg:postcode":"79576",
    "sg:province":"Baden-W\u00fcrttemberg",
    "wof:name":"Friedemann Ulbrich Rechtsanwalt",
    "wof:placetype":"venue"
},
  "geometry": {"coordinates":[7.6312627792,47.5922584534],"type":"Point"}
}