{
  "type": "Feature",
  "properties": {
    "iso:country":"DE",
    "sg:address":"Gablenzer Str. 20",
    "sg:city":"Chemnitz",
    "sg:postcode":"09127",
    "sg:province":"Sachsen",
    "wof:name":"Ge\u00dfler & Schaltonat Gmbh",
    "wof:placetype":"venue"
},
  "geometry": {"coordinates":[12.95781,50.829159],"type":"Point"}
}