{
  "type": "Feature",
  "properties": {
    "iso:country":"DE",
    "sg:address":"Burgleitenstr. 1",
    "sg:city":"Windach",
    "sg:phone":"+49 8193/6691",
    "sg:postcode":"86949",
    "sg:province":"Bayern",
    "wof:name":"Hannelore Hofbauer",
    "wof:placetype":"venue"
},
  "geometry": {"coordinates":[11.0330619812,48.0672454834],"type":"Point"}
}