{
  "type": "Feature",
  "properties": {
    "iso:country":"DE",
    "sg:address":"Martin-Luther-Str. 38",
    "sg:city":"Eckental",
    "sg:phone":"+49 9126/287150",
    "sg:postcode":"90542",
    "sg:province":"Bayern",
    "wof:name":"K\u00fcchen-weigert",
    "wof:placetype":"venue"
},
  "geometry": {"coordinates":[11.2178726196,49.5934371948],"type":"Point"}
}