{
  "type": "Feature",
  "properties": {
    "iso:country":"DE",
    "sg:address":"Ludwig-Lutz-Str. 9",
    "sg:city":"Ellwangen",
    "sg:phone":"+49 7961/54047",
    "sg:postcode":"73479",
    "sg:province":"Baden-W\u00fcrttemberg",
    "wof:name":"Bo Frost Vertriebs- Verwaltungs Vxii Gmbh",
    "wof:placetype":"venue"
},
  "geometry": {"coordinates":[10.176984787,48.9526824951],"type":"Point"}
}