{
  "type": "Feature",
  "properties": {
    "iso:country":"DE",
    "sg:address":"Burger Str. 58",
    "sg:city":"Wermelskirchen",
    "sg:phone":"+49 2196/72760",
    "sg:postcode":"42929",
    "sg:province":"Nordrhein-Westfalen",
    "wof:name":"Bauzentrum Louis Wiesdorf Verwaltungs Gmbh",
    "wof:placetype":"venue"
},
  "geometry": {"coordinates":[7.199413,51.136833],"type":"Point"}
}