{
  "type": "Feature",
  "properties": {
    "iso:country":"DE",
    "sg:address":"Hauptstr. 37",
    "sg:city":"Abtweiler",
    "sg:phone":"+49 6753/2337",
    "sg:postcode":"55568",
    "sg:province":"Rheinland-Pfalz",
    "wof:name":"Adolf Und Peter Michel",
    "wof:placetype":"venue"
},
  "geometry": {"coordinates":[7.655554,49.743488],"type":"Point"}
}