{
  "type": "Feature",
  "properties": {
    "iso:country":"DE",
    "sg:address":"Am Schelmengraben 19",
    "sg:city":"Meiningen",
    "sg:postcode":"98617",
    "sg:province":"Th\u00fcringen",
    "wof:name":"Dr. Med. Klaus Heuer",
    "wof:placetype":"venue"
},
  "geometry": {"coordinates":[10.427959,50.570435],"type":"Point"}
}