{
  "type": "Feature",
  "properties": {
    "iso:country":"DE",
    "sg:address":"Poetenweg 52 a",
    "sg:city":"Falkensee",
    "sg:phone":"+49 3322/235682",
    "sg:postcode":"14612",
    "sg:province":"Brandenburg",
    "wof:name":"Planungs Und Ingenieurb\u00fcro H. Weber",
    "wof:placetype":"venue"
},
  "geometry": {"coordinates":[13.056401,52.555798],"type":"Point"}
}