{
  "type": "Feature",
  "properties": {
    "iso:country":"DE",
    "sg:address":"Akazienweg 17",
    "sg:city":"Wachtberg",
    "sg:phone":"+49 2225/14460",
    "sg:postcode":"53343",
    "sg:province":"Nordrhein-Westfalen",
    "wof:name":"H. Hinzmann",
    "wof:placetype":"venue"
},
  "geometry": {"coordinates":[7.0649971962,50.6158905029],"type":"Point"}
}