{
  "type": "Feature",
  "properties": {
    "iso:country":"DE",
    "sg:address":"Bahnhofstr. 27",
    "sg:city":"Ro\u00dfwein",
    "sg:phone":"+49 34322/42863",
    "sg:postcode":"04741",
    "sg:province":"Sachsen",
    "wof:name":"Annelies Laube",
    "wof:placetype":"venue"
},
  "geometry": {"coordinates":[13.183023,51.060749],"type":"Point"}
}