{
  "type": "Feature",
  "properties": {
    "iso:country":"DE",
    "sg:address":"An der Osternohe 2",
    "sg:city":"Schnaittach",
    "sg:phone":"+49 9153/7586",
    "sg:postcode":"91220",
    "sg:province":"Bayern",
    "wof:name":"Gasthof Goldener Stern",
    "wof:placetype":"venue"
},
  "geometry": {"coordinates":[11.3695850372,49.5876731873],"type":"Point"}
}