{
  "type": "Feature",
  "properties": {
    "iso:country":"DE",
    "sg:address":"Jakobikirchhof 9",
    "sg:city":"Hamburg",
    "sg:postcode":"20095",
    "sg:province":"Hamburg",
    "wof:name":"Projektentwicklungs - Verwaltungsgesellschaft",
    "wof:placetype":"venue"
},
  "geometry": {"coordinates":[10.0018596649,53.5502471924],"type":"Point"}
}