{
  "type": "Feature",
  "properties": {
    "iso:country":"DE",
    "sg:address":"Sennereistr. 4",
    "sg:city":"Bodolz",
    "sg:phone":"+49 8382/25946",
    "sg:postcode":"88131",
    "sg:province":"Bayern",
    "wof:name":"Anton Witzigmann",
    "wof:placetype":"venue"
},
  "geometry": {"coordinates":[9.661112,47.570644],"type":"Point"}
}