{
  "type": "Feature",
  "properties": {
    "iso:country":"DE",
    "sg:address":"Lindenstr. 1",
    "sg:city":"Coesfeld",
    "sg:phone":"+49 2546/1049",
    "sg:postcode":"48653",
    "sg:province":"Nordrhein-Westfalen",
    "wof:name":"Kath. Pfarramt St. Johannes D. T\u00e4ufer",
    "wof:placetype":"venue"
},
  "geometry": {"coordinates":[7.1927909851,51.8961143494],"type":"Point"}
}