{
  "type": "Feature",
  "properties": {
    "iso:country":"DE",
    "sg:address":"Insterburger Str. 15",
    "sg:city":"Bruchk\u00f6bel",
    "sg:phone":"+49 6181/76135",
    "sg:postcode":"63486",
    "sg:province":"Hessen",
    "wof:name":"Dieter Guse",
    "wof:placetype":"venue"
},
  "geometry": {"coordinates":[8.9192724228,50.1683616638],"type":"Point"}
}