{
  "type": "Feature",
  "properties": {
    "iso:country":"DE",
    "sg:address":"Bahnhofstr. 5",
    "sg:city":"L\u00f6hne",
    "sg:phone":"+49 5732/1792",
    "sg:postcode":"32584",
    "sg:province":"Nordrhein-Westfalen",
    "wof:name":"Kath. Pfarramt St. Laurentius",
    "wof:placetype":"venue"
},
  "geometry": {"coordinates":[8.7129735947,52.2004165649],"type":"Point"}
}