{
  "type": "Feature",
  "properties": {
    "iso:country":"DE",
    "sg:address":"Carmerstr. 41",
    "sg:city":"Essen",
    "sg:phone":"+49 201/708085",
    "sg:postcode":"45147",
    "sg:province":"Nordrhein-Westfalen",
    "wof:name":"R. E. Goelst Gmbh",
    "wof:placetype":"venue"
},
  "geometry": {"coordinates":[6.992076,51.442078],"type":"Point"}
}