{
  "type": "Feature",
  "properties": {
    "iso:country":"DE",
    "sg:address":"Gesmolder Str. 189",
    "sg:city":"Melle",
    "sg:phone":"+49 5422/930186",
    "sg:postcode":"49326",
    "sg:province":"Niedersachsen",
    "wof:name":"E. Wortmann-klockenbrink",
    "wof:placetype":"venue"
},
  "geometry": {"coordinates":[8.2744216919,52.2098731995],"type":"Point"}
}