{
  "type": "Feature",
  "properties": {
    "iso:country":"DE",
    "sg:address":"Ludwig-Thoma-Str. 7",
    "sg:city":"Stockdorf",
    "sg:phone":"+49 89/8573205",
    "sg:postcode":"82131",
    "sg:province":"Bayern",
    "wof:name":"Reinhold Urban",
    "wof:placetype":"venue"
},
  "geometry": {"coordinates":[11.4046583176,48.0850372314],"type":"Point"}
}