{
  "type": "Feature",
  "properties": {
    "iso:country":"DE",
    "sg:address":"Hohe Str. 23",
    "sg:city":"Datteln",
    "sg:phone":"+49 2363/52488",
    "sg:postcode":"45711",
    "sg:province":"Nordrhein-Westfalen",
    "wof:name":"R. Hagemann",
    "wof:placetype":"venue"
},
  "geometry": {"coordinates":[7.3413939476,51.6528434753],"type":"Point"}
}