{
  "type": "Feature",
  "properties": {
    "iso:country":"DE",
    "sg:address":"Papenberg 21",
    "sg:city":"Helmstedt",
    "sg:phone":"+49 5351/40700",
    "sg:postcode":"38350",
    "sg:province":"Niedersachsen",
    "wof:name":"Knigge",
    "wof:placetype":"venue"
},
  "geometry": {"coordinates":[11.0126342773,52.2269973755],"type":"Point"}
}