{
  "type": "Feature",
  "properties": {
    "iso:country":"DE",
    "sg:address":"Oberndorfer Str. 19",
    "sg:city":"Feldkirchen",
    "sg:phone":"+49 89/9032507",
    "sg:postcode":"85622",
    "sg:province":"Bayern",
    "wof:name":"Fritz Bischoff",
    "wof:placetype":"venue"
},
  "geometry": {"coordinates":[11.731647,48.144775],"type":"Point"}
}