{
  "type": "Feature",
  "properties": {
    "iso:country":"DE",
    "sg:address":"B\u00f6rster Weg 38 a",
    "sg:city":"Recklinghausen",
    "sg:phone":"+49 2361/29119",
    "sg:postcode":"45657",
    "sg:province":"Nordrhein-Westfalen",
    "wof:name":"Pedale",
    "wof:placetype":"venue"
},
  "geometry": {"coordinates":[7.2009191513,51.6213951111],"type":"Point"}
}