{
  "type": "Feature",
  "properties": {
    "iso:country":"DE",
    "sg:address":"Wallstr. 9",
    "sg:city":"Freiburg",
    "sg:phone":"+49 761/31251",
    "sg:postcode":"79098",
    "sg:province":"Baden-W\u00fcrttemberg",
    "wof:name":"Schmidt-hofner Und Meister Rechtsanw\u00e4lte",
    "wof:placetype":"venue"
},
  "geometry": {"coordinates":[7.8524208069,47.9922027588],"type":"Point"}
}