{
  "type": "Feature",
  "properties": {
    "iso:country":"DE",
    "sg:address":"Amselweg 6",
    "sg:city":"Dietfurt",
    "sg:phone":"+49 8464/8142",
    "sg:postcode":"92345",
    "sg:province":"Bayern",
    "wof:name":"Franz Ast",
    "wof:placetype":"venue"
},
  "geometry": {"coordinates":[11.578099,49.039165],"type":"Point"}
}