{
  "type": "Feature",
  "properties": {
    "iso:country":"DE",
    "sg:address":"Laygasse 25",
    "sg:city":"Neuwied",
    "sg:phone":"+49 2631/73707",
    "sg:postcode":"56567",
    "sg:province":"Rheinland-Pfalz",
    "wof:name":"E. Neitzert",
    "wof:placetype":"venue"
},
  "geometry": {"coordinates":[7.4150791168,50.4492225647],"type":"Point"}
}