{
  "type": "Feature",
  "properties": {
    "iso:country":"DE",
    "sg:address":"Lilienweg 1",
    "sg:city":"St. Wendel",
    "sg:phone":"+49 6854/8526",
    "sg:postcode":"66606",
    "sg:province":"Saarland",
    "wof:name":"Edwin Senges Elektroinstallation",
    "wof:placetype":"venue"
},
  "geometry": {"coordinates":[7.104481,49.499367],"type":"Point"}
}