{
  "type": "Feature",
  "properties": {
    "iso:country":"DE",
    "sg:address":"Stettiner Str.",
    "sg:city":"Birkenau",
    "sg:phone":"+49 6201/873108",
    "sg:postcode":"69488",
    "sg:province":"Hessen",
    "wof:name":"Vertriebsmanagement",
    "wof:placetype":"venue"
},
  "geometry": {"coordinates":[8.7075634003,49.5706596375],"type":"Point"}
}