{
  "type": "Feature",
  "properties": {
    "iso:country":"DE",
    "sg:address":"Z\u00f6rbiger Str.",
    "sg:city":"Bitterfeld",
    "sg:phone":"+49 3493/42200",
    "sg:postcode":"06749",
    "sg:province":"Sachsen-Anhalt",
    "wof:name":"Preussag Anlagenbau Produkte Wasser Und",
    "wof:placetype":"venue"
},
  "geometry": {"coordinates":[12.297565,51.623779],"type":"Point"}
}