{
  "type": "Feature",
  "properties": {
    "iso:country":"DE",
    "sg:address":"millratherweg 122",
    "sg:city":"Erkrath",
    "sg:phone":"+49 177 3461338",
    "sg:postcode":"40699",
    "sg:province":"Nordrhein-Westfalen",
    "wof:name":"Dessous/internetshop Fachgesch\u00e4ft F\u00fcr Dessous -",
    "wof:placetype":"venue"
},
  "geometry": {"coordinates":[6.925924,51.196896],"type":"Point"}
}