{
  "type": "Feature",
  "properties": {
    "iso:country":"DE",
    "sg:address":"Zimmerstr. 4",
    "sg:city":"Darmstadt",
    "sg:phone":"+49 6151/97610",
    "sg:postcode":"64283",
    "sg:province":"Hessen",
    "wof:name":"Verlag F\u00fcr Wirtschafts- F\u00f6rderung G\u00f6hde Gmbh & Co.",
    "wof:placetype":"venue"
},
  "geometry": {"coordinates":[8.6498765945,49.8696861267],"type":"Point"}
}