{
  "type": "Feature",
  "properties": {
    "iso:country":"DE",
    "sg:address":"Pattweg 25",
    "sg:city":"Herford",
    "sg:phone":"+49 5221/31176",
    "sg:postcode":"32051",
    "sg:province":"Nordrhein-Westfalen",
    "wof:name":"Klaus Altemeier Ingenieur",
    "wof:placetype":"venue"
},
  "geometry": {"coordinates":[8.6174049377,52.1280403137],"type":"Point"}
}