{
  "type": "Feature",
  "properties": {
    "iso:country":"DE",
    "sg:address":"Salzufler Str. 143",
    "sg:city":"Herford",
    "sg:phone":"+49 5221/85827",
    "sg:postcode":"32052",
    "sg:province":"Nordrhein-Westfalen",
    "wof:name":"Ralf Opitz Rechtsanwalt",
    "wof:placetype":"venue"
},
  "geometry": {"coordinates":[8.6935558319,52.1046981812],"type":"Point"}
}