{
  "type": "Feature",
  "properties": {
    "iso:country":"DE",
    "sg:address":"Mannesmannstr. 18 B",
    "sg:city":"Wermelskirchen",
    "sg:phone":"+49 2196/92982",
    "sg:postcode":"42929",
    "sg:province":"Nordrhein-Westfalen",
    "wof:name":"Kurt Steinmann Steinmetzbetrieb",
    "wof:placetype":"venue"
},
  "geometry": {"coordinates":[7.2115621567,51.1439857483],"type":"Point"}
}