{
  "type": "Feature",
  "properties": {
    "iso:country":"DE",
    "sg:address":"Hardtstr. 42",
    "sg:city":"M\u00fcnsingen",
    "sg:phone":"+49 7381/2530",
    "sg:postcode":"72525",
    "sg:province":"Baden-W\u00fcrttemberg",
    "wof:name":"K.h. Volk Mech.werkstatt",
    "wof:placetype":"venue"
},
  "geometry": {"coordinates":[9.547633,48.41325],"type":"Point"}
}