{
  "type": "Feature",
  "properties": {
    "iso:country":"DE",
    "sg:address":"Speyerer Str. 50",
    "sg:city":"M\u00fchlhausen",
    "sg:phone":"+49 6222/61051",
    "sg:postcode":"69242",
    "sg:province":"Baden-W\u00fcrttemberg",
    "wof:name":"Ingenieurb\u00fcro Schneider Elektrotechnik Gmbh",
    "wof:placetype":"venue"
},
  "geometry": {"coordinates":[8.7149848938,49.2498703003],"type":"Point"}
}