{
  "type": "Feature",
  "properties": {
    "iso:country":"DE",
    "sg:address":"Oberndorfer Str. 38-40",
    "sg:city":"Griesheim",
    "sg:phone":"+49 6155/4418",
    "sg:postcode":"64347",
    "sg:province":"Hessen",
    "wof:name":"Wk Vorrichtungs- U. Proto- Typenbau Feinmechanische",
    "wof:placetype":"venue"
},
  "geometry": {"coordinates":[8.5552387238,49.856590271],"type":"Point"}
}