{
  "type": "Feature",
  "properties": {
    "iso:country":"DE",
    "sg:address":"Philipp von Zabern Platz 1-3",
    "sg:city":"Mainz",
    "sg:phone":"+49 6131",
    "sg:postcode":"55116",
    "sg:province":"Rheinland-Pfalz",
    "wof:name":"Verlag Philipp Von Zabern",
    "wof:placetype":"venue"
},
  "geometry": {"coordinates":[8.267644,50.000881],"type":"Point"}
}