{
  "type": "Feature",
  "properties": {
    "iso:country":"DE",
    "sg:address":"Brunnenstr. 28 b",
    "sg:city":"Herford",
    "sg:postcode":"32052",
    "sg:province":"Nordrhein-Westfalen",
    "wof:name":"Schnatmeyer Metallbau Verwaltungs- Gmbh",
    "wof:placetype":"venue"
},
  "geometry": {"coordinates":[8.6950120926,52.1010322571],"type":"Point"}
}