{
  "type": "Feature",
  "properties": {
    "iso:country":"DE",
    "sg:address":"Friedrichstr. 58",
    "sg:city":"Erkner",
    "sg:phone":"+49 3362/25082",
    "sg:postcode":"15537",
    "sg:province":"Brandenburg",
    "wof:name":"Rossmann Drogeriemarkt",
    "wof:placetype":"venue"
},
  "geometry": {"coordinates":[13.753654,52.421818],"type":"Point"}
}