{
  "type": "Feature",
  "properties": {
    "iso:country":"DE",
    "sg:address":"Baiersbronner Str. 35",
    "sg:city":"Baiersbronn",
    "sg:phone":"+49 7442/3361",
    "sg:postcode":"72270",
    "sg:province":"Baden-W\u00fcrttemberg",
    "wof:name":"Walter Gey Ingenieur",
    "wof:placetype":"venue"
},
  "geometry": {"coordinates":[8.3951787949,48.5204696655],"type":"Point"}
}