{
  "type": "Feature",
  "properties": {
    "iso:country":"DE",
    "sg:address":"Industriestr. 1",
    "sg:city":"Wietze",
    "sg:phone":"+49 5146/988260",
    "sg:postcode":"29323",
    "sg:province":"Niedersachsen",
    "wof:name":"Weitec Fahrwerktechnik Gmbh",
    "wof:placetype":"venue"
},
  "geometry": {"coordinates":[9.8279438019,52.6566467285],"type":"Point"}
}