{
  "type": "Feature",
  "properties": {
    "iso:country":"DE",
    "sg:address":"Hirschstr 3",
    "sg:city":"Laichingen",
    "sg:phone":"+49 7333/5387",
    "sg:postcode":"89150",
    "sg:province":"Baden-W\u00fcrttemberg",
    "wof:name":"Jakob Hermann Leinenweberei Und W\u00e4schefabrikation Kg",
    "wof:placetype":"venue"
},
  "geometry": {"coordinates":[9.687086,48.492859],"type":"Point"}
}