{
  "type": "Feature",
  "properties": {
    "iso:country":"DE",
    "sg:address":"Osterstr. 16",
    "sg:city":"Hildesheim",
    "sg:postcode":"31134",
    "sg:province":"Niedersachsen",
    "wof:name":"The Wild Geese Irish Pub Hildesheim Gmbh",
    "wof:placetype":"venue"
},
  "geometry": {"coordinates":[9.9547338486,52.1549186707],"type":"Point"}
}