{
  "type": "Feature",
  "properties": {
    "iso:country":"DE",
    "sg:address":"Ostcharweg 92",
    "sg:city":"Recklinghausen",
    "sg:phone":"+49 2361/498020",
    "sg:postcode":"45665",
    "sg:province":"Nordrhein-Westfalen",
    "wof:name":"Josef Vierhaus E. K.",
    "wof:placetype":"venue"
},
  "geometry": {"coordinates":[7.227288,51.621983],"type":"Point"}
}