{
  "type": "Feature",
  "properties": {
    "iso:country":"DE",
    "sg:address":"Dainbacher Weg 1",
    "sg:city":"Bad Mergentheim",
    "sg:phone":"+49 7931/7829",
    "sg:postcode":"97980",
    "sg:province":"Baden-W\u00fcrttemberg",
    "wof:name":"Siegfried Kreissl",
    "wof:placetype":"venue"
},
  "geometry": {"coordinates":[9.756135,49.493935],"type":"Point"}
}