{
  "type": "Feature",
  "properties": {
    "iso:country":"DE",
    "sg:address":"Am Raffelnberg 1-3",
    "sg:city":"Luedenscheid",
    "sg:phone":"+49 4923/5197590",
    "sg:postcode":"58515",
    "sg:province":"Nordrhein-Westfalen",
    "wof:name":"E U W Gloerfeld Gmbh",
    "wof:placetype":"venue"
},
  "geometry": {"coordinates":[7.56589,51.205891],"type":"Point"}
}