{
  "type": "Feature",
  "properties": {
    "iso:country":"DE",
    "sg:address":"Bergisch Gladbacher Str. 634",
    "sg:city":"K\u00f6ln",
    "sg:phone":"+49 221/638940",
    "sg:postcode":"51067",
    "sg:province":"Nordrhein-Westfalen",
    "wof:name":"Jakob Schlimbach Verwaltungsges. Mbh",
    "wof:placetype":"venue"
},
  "geometry": {"coordinates":[7.050196,50.971249],"type":"Point"}
}