{
  "type": "Feature",
  "properties": {
    "iso:country":"DE",
    "sg:address":"Siemensstr. 16",
    "sg:city":"Kleve",
    "sg:phone":"+49 2821/971304",
    "sg:postcode":"47533",
    "sg:province":"Nordrhein-Westfalen",
    "wof:name":"Rl Versorgungstechnik Gmbh",
    "wof:placetype":"venue"
},
  "geometry": {"coordinates":[6.139373,51.813244],"type":"Point"}
}