{
  "type": "Feature",
  "properties": {
    "iso:country":"DE",
    "sg:address":"Robert-Bosch-Str. 1",
    "sg:city":"V\u00f6hringen",
    "sg:phone":"+49 7306/96400",
    "sg:postcode":"89269",
    "sg:province":"Bayern",
    "wof:name":"Robert Harder Spedition",
    "wof:placetype":"venue"
},
  "geometry": {"coordinates":[10.0697746277,48.296913147],"type":"Point"}
}