{
  "type": "Feature",
  "properties": {
    "iso:country":"DE",
    "sg:address":"Kirchberger Str. 37 a",
    "sg:city":"Dickenschied",
    "sg:phone":"+49 6763/2276",
    "sg:postcode":"55483",
    "sg:province":"Rheinland-Pfalz",
    "wof:name":"Schreinerei Christ Gmbh",
    "wof:placetype":"venue"
},
  "geometry": {"coordinates":[7.419009,49.900284],"type":"Point"}
}