{
  "type": "Feature",
  "properties": {
    "iso:country":"DE",
    "sg:address":"Saseler Str. 186",
    "sg:city":"Hamburg",
    "sg:phone":"+49 40/6444748",
    "sg:postcode":"22159",
    "sg:province":"Hamburg",
    "wof:name":"Prof. Nils Sustrate",
    "wof:placetype":"venue"
},
  "geometry": {"coordinates":[10.1432628632,53.6342086792],"type":"Point"}
}