{
  "type": "Feature",
  "properties": {
    "iso:country":"DE",
    "sg:address":"Passauer Str. 2",
    "sg:city":"Neuhaus",
    "sg:phone":"+49 8503/8444",
    "sg:postcode":"94152",
    "sg:province":"Bayern",
    "wof:name":"Hotel-restaurant Haus Des Gastes",
    "wof:placetype":"venue"
},
  "geometry": {"coordinates":[13.4196243286,48.45703125],"type":"Point"}
}