{
  "type": "Feature",
  "properties": {
    "iso:country":"DE",
    "sg:address":"Starks\u00e4ckerweg 7",
    "sg:city":"Hemsbach",
    "sg:postcode":"69502",
    "sg:province":"Baden-W\u00fcrttemberg",
    "wof:name":"Deutsche Bahn Ag",
    "wof:placetype":"venue"
},
  "geometry": {"coordinates":[8.6500892639,49.5882759094],"type":"Point"}
}