{
  "type": "Feature",
  "properties": {
    "iso:country":"DE",
    "sg:address":"Fedderwarderdeich 10",
    "sg:city":"Butjadingen",
    "sg:phone":"+49 4733/920030",
    "sg:postcode":"26969",
    "sg:province":"Niedersachsen",
    "wof:name":"Adolf Wefer",
    "wof:placetype":"venue"
},
  "geometry": {"coordinates":[8.3456821442,53.6024131775],"type":"Point"}
}