{
  "type": "Feature",
  "properties": {
    "iso:country":"DE",
    "sg:address":"Kirchzartener Str. 21",
    "sg:city":"Freiburg",
    "sg:phone":"+49 761/67164",
    "sg:postcode":"79117",
    "sg:province":"Baden-W\u00fcrttemberg",
    "wof:name":"Hermann Thoma Kg",
    "wof:placetype":"venue"
},
  "geometry": {"coordinates":[7.9186429977,47.9745445251],"type":"Point"}
}