{
  "type": "Feature",
  "properties": {
    "iso:country":"DE",
    "sg:address":"Schaumburgstr. 21",
    "sg:city":"M\u00fcnster",
    "sg:phone":"+49 251/64102",
    "sg:postcode":"48145",
    "sg:province":"Nordrhein-Westfalen",
    "wof:name":"Bleckmann Gmbh",
    "wof:placetype":"venue"
},
  "geometry": {"coordinates":[7.6392278671,51.959980011],"type":"Point"}
}