{
  "type": "Feature",
  "properties": {
    "iso:country":"DE",
    "sg:address":"Wendenstr. 331",
    "sg:city":"Hamburg",
    "sg:phone":"+49 40/2502349",
    "sg:postcode":"20537",
    "sg:province":"Hamburg",
    "wof:name":"Herbert Meier Immobilienmakler",
    "wof:placetype":"venue"
},
  "geometry": {"coordinates":[10.0440168381,53.5510826111],"type":"Point"}
}