{
  "type": "Feature",
  "properties": {
    "iso:country":"DE",
    "sg:address":"Vor den Siebenburgen 2",
    "sg:city":"K\u00f6ln",
    "sg:phone":"+49 221/9312400",
    "sg:postcode":"50676",
    "sg:province":"Nordrhein-Westfalen",
    "wof:name":"Helvetia Versicherungen",
    "wof:placetype":"venue"
},
  "geometry": {"coordinates":[6.9536218643,50.9261741638],"type":"Point"}
}