{
  "type": "Feature",
  "properties": {
    "iso:country":"DE",
    "sg:address":"Hindenburgstr. 25",
    "sg:city":"Hannover",
    "sg:postcode":"30175",
    "sg:province":"Niedersachsen",
    "wof:name":"Internationale \u00c4rztegesell- Schaft F. Sauerstoff-immun-",
    "wof:placetype":"venue"
},
  "geometry": {"coordinates":[9.7596988678,52.3788528442],"type":"Point"}
}