{
  "type": "Feature",
  "properties": {
    "iso:country":"DE",
    "sg:address":"Reichsapfelstr. 20",
    "sg:city":"Wiesbaden",
    "sg:phone":"+49 611/29157",
    "sg:postcode":"65201",
    "sg:province":"Hessen",
    "wof:name":"Zum Adler",
    "wof:placetype":"venue"
},
  "geometry": {"coordinates":[8.1968383789,50.0444831848],"type":"Point"}
}