{
  "type": "Feature",
  "properties": {
    "iso:country":"DE",
    "sg:address":"Bramfelder Str. 90",
    "sg:city":"Hamburg",
    "sg:phone":"+49 40/6914844",
    "sg:postcode":"22305",
    "sg:province":"Hamburg",
    "wof:name":"P. Schweitzer",
    "wof:placetype":"venue"
},
  "geometry": {"coordinates":[10.052925,53.588276],"type":"Point"}
}