{
  "type": "Feature",
  "properties": {
    "iso:country":"DE",
    "sg:address":"Lousbergstr. 4",
    "sg:city":"Aachen",
    "sg:phone":"+49 241/156370",
    "sg:postcode":"52072",
    "sg:province":"Nordrhein-Westfalen",
    "wof:name":"Theodor Kind",
    "wof:placetype":"venue"
},
  "geometry": {"coordinates":[6.0797,50.782917],"type":"Point"}
}