{
  "type": "Feature",
  "properties": {
    "iso:country":"DE",
    "sg:address":"Steinstr. 30",
    "sg:city":"Wilhelmshaven",
    "sg:phone":"+49 4421/995155",
    "sg:postcode":"26388",
    "sg:province":"Niedersachsen",
    "wof:name":"Michael Huischen",
    "wof:placetype":"venue"
},
  "geometry": {"coordinates":[8.0890703201,53.567276001],"type":"Point"}
}