{
  "type": "Feature",
  "properties": {
    "iso:country":"DE",
    "sg:address":"Hahnrodsweg 1",
    "sg:city":"Biedenkopf",
    "sg:phone":"+49 6461/89008",
    "sg:postcode":"35216",
    "sg:province":"Hessen",
    "wof:name":"Wilhelm M\u00fcller Gmbh & Co. Kg",
    "wof:placetype":"venue"
},
  "geometry": {"coordinates":[8.471337,50.927765],"type":"Point"}
}