{
  "type": "Feature",
  "properties": {
    "iso:country":"DE",
    "sg:address":"Lindenweg 6",
    "sg:city":"Uffing",
    "sg:phone":"+49 8846/232",
    "sg:postcode":"82449",
    "sg:province":"Bayern",
    "wof:name":"Hellmut Kollmann",
    "wof:placetype":"venue"
},
  "geometry": {"coordinates":[11.1471042633,47.7157173157],"type":"Point"}
}