{
  "type": "Feature",
  "properties": {
    "iso:country":"DE",
    "sg:address":"Kirchstr. 84",
    "sg:city":"Kunitz",
    "sg:phone":"+49 3641/425304",
    "sg:postcode":"07751",
    "sg:province":"Th\u00fcringen",
    "wof:name":"E. H\u00fcttich",
    "wof:placetype":"venue"
},
  "geometry": {"coordinates":[11.636697,50.955223],"type":"Point"}
}