{
  "type": "Feature",
  "properties": {
    "iso:country":"DE",
    "sg:address":"Hauptstra\u00dfe 18-20",
    "sg:city":"Frechen",
    "sg:phone":"+49 2234/954510",
    "sg:postcode":"50226",
    "sg:province":"Nordrhein-Westfalen",
    "wof:name":"Unitell Gmbh",
    "wof:placetype":"venue"
},
  "geometry": {"coordinates":[6.813651,50.909782],"type":"Point"}
}