{
  "type": "Feature",
  "properties": {
    "iso:country":"DE",
    "sg:address":"Breslauer Str. 2",
    "sg:city":"Extertal",
    "sg:phone":"+49 4952/6294640",
    "sg:postcode":"32699",
    "sg:province":"Nordrhein-Westfalen",
    "wof:name":"Rauchfuss Knopf Gmbh",
    "wof:placetype":"venue"
},
  "geometry": {"coordinates":[9.106886,52.069286],"type":"Point"}
}