{
  "type": "Feature",
  "properties": {
    "iso:country":"DE",
    "sg:address":"Zum Stillen Tal 12",
    "sg:city":"Bernhardswald",
    "sg:phone":"+49 9407/2248",
    "sg:postcode":"93170",
    "sg:province":"Bayern",
    "wof:name":"Josef Gassner",
    "wof:placetype":"venue"
},
  "geometry": {"coordinates":[12.2509870529,49.1166534424],"type":"Point"}
}