{
  "type": "Feature",
  "properties": {
    "iso:country":"DE",
    "sg:address":"Mittelstr. 30",
    "sg:city":"Annaburg",
    "sg:phone":"+49 35385/21922",
    "sg:postcode":"06925",
    "sg:province":"Sachsen-Anhalt",
    "wof:name":"Klein",
    "wof:placetype":"venue"
},
  "geometry": {"coordinates":[13.0496425629,51.7327461243],"type":"Point"}
}