{
  "type": "Feature",
  "properties": {
    "iso:country":"DE",
    "sg:address":"Opferfeldstr 39",
    "sg:city":"Enger",
    "sg:phone":"+49 5224/99070",
    "sg:postcode":"32130",
    "sg:province":"Nordrhein-Westfalen",
    "wof:name":"Dieckmann",
    "wof:placetype":"venue"
},
  "geometry": {"coordinates":[8.561587,52.146095],"type":"Point"}
}