{
  "type": "Feature",
  "properties": {
    "iso:country":"DE",
    "sg:address":"Liselotte-Herrmann-Str. 6",
    "sg:city":"Bergholz-Rehbr\u00fccke",
    "sg:postcode":"14558",
    "sg:province":"Brandenburg",
    "wof:name":"Dr. Med. Alois Kreisl",
    "wof:placetype":"venue"
},
  "geometry": {"coordinates":[13.108528,52.345261],"type":"Point"}
}