{
  "type": "Feature",
  "properties": {
    "iso:country":"DE",
    "sg:address":"R\u00fcdesheimer Str. 82",
    "sg:city":"Hofheim",
    "sg:phone":"+49 6122/13757",
    "sg:postcode":"65719",
    "sg:province":"Hessen",
    "wof:name":"Dietmar Haschke Architekt",
    "wof:placetype":"venue"
},
  "geometry": {"coordinates":[8.362066,50.063126],"type":"Point"}
}