{
  "type": "Feature",
  "properties": {
    "iso:country":"DE",
    "sg:address":"Im Silberloch 3",
    "sg:city":"Lauf",
    "sg:phone":"+49 7841/1257",
    "sg:postcode":"77886",
    "sg:province":"Baden-W\u00fcrttemberg",
    "wof:name":"Renate Weiler Handarbeitsgesch\u00e4ft",
    "wof:placetype":"venue"
},
  "geometry": {"coordinates":[8.14224,48.648849],"type":"Point"}
}