{
  "type": "Feature",
  "properties": {
    "iso:country":"DE",
    "sg:address":"Goethestr. 20",
    "sg:city":"Linkenheim-Hochstetten",
    "sg:phone":"+49 7247/7474",
    "sg:postcode":"76351",
    "sg:province":"Baden-W\u00fcrttemberg",
    "wof:name":"W. Holland-cunz Ingenieur",
    "wof:placetype":"venue"
},
  "geometry": {"coordinates":[8.4205608368,49.1346931458],"type":"Point"}
}