{
  "type": "Feature",
  "properties": {
    "iso:country":"DE",
    "sg:address":"Hauptstr. 29",
    "sg:city":"Karlstadt",
    "sg:postcode":"97753",
    "sg:province":"Bayern",
    "wof:name":"Investoxx-beratungsges. Mbh",
    "wof:placetype":"venue"
},
  "geometry": {"coordinates":[9.7642498016,49.9622192383],"type":"Point"}
}