{
  "type": "Feature",
  "properties": {
    "iso:country":"DE",
    "sg:address":"Osnabr\u00fccker Str. 346",
    "sg:city":"Rheine",
    "sg:phone":"+49 5971/71125",
    "sg:postcode":"48429",
    "sg:province":"Nordrhein-Westfalen",
    "wof:name":"A. Und H. Brinker Eisenwaren",
    "wof:placetype":"venue"
},
  "geometry": {"coordinates":[7.477298,52.286724],"type":"Point"}
}