{
  "type": "Feature",
  "properties": {
    "iso:country":"DE",
    "sg:address":"Fl\u00f6thwiesen 13",
    "sg:city":"Hannover",
    "sg:postcode":"30657",
    "sg:province":"Niedersachsen",
    "wof:name":"Mct Mitsu Chemical Trading Gmbh",
    "wof:placetype":"venue"
},
  "geometry": {"coordinates":[9.7944173813,52.4390487671],"type":"Point"}
}