{
  "type": "Feature",
  "properties": {
    "iso:country":"DE",
    "sg:address":"Zell",
    "sg:city":"Bad Aibling",
    "sg:phone":"+49 8061/7547",
    "sg:postcode":"83043",
    "sg:province":"Bayern",
    "wof:name":"Cafe Heiss",
    "wof:placetype":"venue"
},
  "geometry": {"coordinates":[12.02498,47.869904],"type":"Point"}
}