{
  "type": "Feature",
  "properties": {
    "iso:country":"DE",
    "sg:address":"Haidkamp 1",
    "sg:city":"Legden",
    "sg:phone":"+49 2566/2080",
    "sg:postcode":"48739",
    "sg:province":"Nordrhein-Westfalen",
    "wof:name":"Hotel Und Freizeitpark Dorf M\u00fcnsterland Betriebs- Gmbh",
    "wof:placetype":"venue"
},
  "geometry": {"coordinates":[7.1069078445,52.0386581421],"type":"Point"}
}