{
  "type": "Feature",
  "properties": {
    "iso:country":"DE",
    "sg:address":"Mariabrunnweg 50",
    "sg:city":"Benediktbeuern",
    "sg:phone":"+49 8857/691931",
    "sg:postcode":"83671",
    "sg:province":"Bayern",
    "wof:name":"Reiner Kg",
    "wof:placetype":"venue"
},
  "geometry": {"coordinates":[11.42070961,47.7011604309],"type":"Point"}
}