{
  "type": "Feature",
  "properties": {
    "iso:country":"DE",
    "sg:address":"Provisstr. 1",
    "sg:city":"Edesheim",
    "sg:phone":"+49 6323/5443",
    "sg:postcode":"67483",
    "sg:province":"Rheinland-Pfalz",
    "wof:name":"Harald Platz",
    "wof:placetype":"venue"
},
  "geometry": {"coordinates":[8.127608,49.261086],"type":"Point"}
}