{
  "type": "Feature",
  "properties": {
    "iso:country":"DE",
    "sg:address":"Quettinger Str. 173",
    "sg:city":"Leverkusen",
    "sg:phone":"+49 2171/80538",
    "sg:postcode":"51381",
    "sg:province":"Nordrhein-Westfalen",
    "wof:name":"Quettinger-grill",
    "wof:placetype":"venue"
},
  "geometry": {"coordinates":[7.0282931328,51.0610122681],"type":"Point"}
}