{
  "type": "Feature",
  "properties": {
    "iso:country":"DE",
    "sg:address":"Anger 10",
    "sg:city":"Ramerberg",
    "sg:postcode":"83561",
    "sg:province":"Bayern",
    "wof:name":"Romanoff Parf\u00fcms Ag",
    "wof:placetype":"venue"
},
  "geometry": {"coordinates":[12.147118,48.021927],"type":"Point"}
}