{
  "type": "Feature",
  "properties": {
    "iso:country":"DE",
    "sg:address":"Salinenstr. 8",
    "sg:city":"Bad Reichenhall",
    "sg:phone":"+49 8651/3219",
    "sg:postcode":"83435",
    "sg:province":"Bayern",
    "wof:name":"Edition Raphaele",
    "wof:placetype":"venue"
},
  "geometry": {"coordinates":[12.8764848709,47.7215309143],"type":"Point"}
}