{
  "type": "Feature",
  "properties": {
    "iso:country":"DE",
    "sg:address":"Rethelstr. 9",
    "sg:city":"Berlin",
    "sg:phone":"+49 30/5337430",
    "sg:postcode":"12435",
    "sg:province":"Berlin",
    "wof:name":"J\u00fcrgen Gustavus",
    "wof:placetype":"venue"
},
  "geometry": {"coordinates":[13.4667863846,52.4849090576],"type":"Point"}
}