{
  "type": "Feature",
  "properties": {
    "iso:country":"DE",
    "sg:address":"Zu den Hofstellen 9",
    "sg:city":"Gemmingen",
    "sg:phone":"+49 7267/8560",
    "sg:postcode":"75050",
    "sg:province":"Baden-W\u00fcrttemberg",
    "wof:name":"Harald Krepp",
    "wof:placetype":"venue"
},
  "geometry": {"coordinates":[8.983585,49.15633],"type":"Point"}
}