{
  "type": "Feature",
  "properties": {
    "iso:country":"DE",
    "sg:address":"Derfflingerstr. 17",
    "sg:city":"Berlin",
    "sg:postcode":"10785",
    "sg:province":"Berlin",
    "wof:name":"Drei-m\u00f6nche Kultur- Und Bildungsbr\u00fccke Gmbh",
    "wof:placetype":"venue"
},
  "geometry": {"coordinates":[13.3562040329,52.50258255],"type":"Point"}
}