{
  "type": "Feature",
  "properties": {
    "iso:country":"DE",
    "sg:address":"Alpenstr. 2",
    "sg:city":"Puchheim",
    "sg:phone":"+49 89/806622",
    "sg:postcode":"82178",
    "sg:province":"Bayern",
    "wof:name":"H. Tschenscher",
    "wof:placetype":"venue"
},
  "geometry": {"coordinates":[11.360927,48.179642],"type":"Point"}
}