{
  "type": "Feature",
  "properties": {
    "iso:country":"DE",
    "sg:address":"Herner Str. 57",
    "sg:city":"Recklinghausen",
    "sg:phone":"+49 2361/21481",
    "sg:postcode":"45657",
    "sg:province":"Nordrhein-Westfalen",
    "wof:name":"Volker Stratmann Ingenieur",
    "wof:placetype":"venue"
},
  "geometry": {"coordinates":[7.2000479698,51.6060218811],"type":"Point"}
}