{
  "type": "Feature",
  "properties": {
    "iso:country":"DE",
    "sg:address":"Gr\u00fcner Heideberg 2",
    "sg:city":"Kleve",
    "sg:phone":"+49 2821/26265",
    "sg:postcode":"47533",
    "sg:province":"Nordrhein-Westfalen",
    "wof:name":"Frido Gerrits",
    "wof:placetype":"venue"
},
  "geometry": {"coordinates":[6.1361641884,51.7877883911],"type":"Point"}
}