{
  "type": "Feature",
  "properties": {
    "iso:country":"DE",
    "sg:address":"Ernst-August-Str. 16",
    "sg:city":"Holzminden",
    "sg:phone":"+49 5531/60255",
    "sg:postcode":"37603",
    "sg:province":"Niedersachsen",
    "wof:name":"Leclair's M\u00fchle",
    "wof:placetype":"venue"
},
  "geometry": {"coordinates":[9.4551515579,51.82629776],"type":"Point"}
}