{
  "type": "Feature",
  "properties": {
    "iso:country":"DE",
    "sg:address":"Stengelstr. 6a",
    "sg:city":"M\u00fcnchen",
    "sg:postcode":"80805",
    "sg:province":"Bayern",
    "wof:name":"Dr. Roland U. Dr. Hildeg Jung Tier\u00e4rztin",
    "wof:placetype":"venue"
},
  "geometry": {"coordinates":[11.594956398,48.1694374084],"type":"Point"}
}