{
  "type": "Feature",
  "properties": {
    "iso:country":"DE",
    "sg:address":"Ludwig-Thoma-Str. 49",
    "sg:city":"Rottach-Egern",
    "sg:phone":"+49 8022/26182",
    "sg:postcode":"83700",
    "sg:province":"Bayern",
    "wof:name":"Klaus Stillner",
    "wof:placetype":"venue"
},
  "geometry": {"coordinates":[11.779045,47.688412],"type":"Point"}
}