{
  "type": "Feature",
  "properties": {
    "iso:country":"DE",
    "sg:address":"M\u00fchlenstr. 10",
    "sg:city":"Freital",
    "sg:phone":"+49 351/640490",
    "sg:postcode":"01705",
    "sg:province":"Sachsen",
    "wof:name":"M\u00fcnzer Und Collegen Rechtsanwaltsgesellschaft Mbh",
    "wof:placetype":"venue"
},
  "geometry": {"coordinates":[13.6496334076,50.9935264587],"type":"Point"}
}