{
  "type": "Feature",
  "properties": {
    "iso:country":"DE",
    "sg:address":"Benzhauser Str. 18",
    "sg:city":"March",
    "sg:phone":"+49 7665/400350",
    "sg:postcode":"79232",
    "sg:province":"Baden-W\u00fcrttemberg",
    "wof:name":"K. Ziegler",
    "wof:placetype":"venue"
},
  "geometry": {"coordinates":[7.79935,48.068039],"type":"Point"}
}