{
  "type": "Feature",
  "properties": {
    "iso:country":"DE",
    "sg:address":"Gro\u00dfmoor 2",
    "sg:city":"Schmalstede",
    "sg:phone":"+49 4322/3905",
    "sg:postcode":"24241",
    "sg:province":"Schleswig-Holstein",
    "wof:name":"Eichstedt",
    "wof:placetype":"venue"
},
  "geometry": {"coordinates":[10.030620575,54.2011222839],"type":"Point"}
}