{
  "type": "Feature",
  "properties": {
    "iso:country":"DE",
    "sg:address":"Emanuel-Geibel-Str. 9",
    "sg:city":"B\u00fcdelsdorf",
    "sg:phone":"+49 4331/37211",
    "sg:postcode":"24782",
    "sg:province":"Schleswig-Holstein",
    "wof:name":"A. Jegsen Heilpraktiker",
    "wof:placetype":"venue"
},
  "geometry": {"coordinates":[9.6837282181,54.3226966858],"type":"Point"}
}