{
  "type": "Feature",
  "properties": {
    "iso:country":"DE",
    "sg:address":"Stadtplatz 1",
    "sg:city":"Hemau",
    "sg:phone":"+49 9491/410",
    "sg:postcode":"93155",
    "sg:province":"Bayern",
    "wof:name":"Stadt-apotheke",
    "wof:placetype":"venue"
},
  "geometry": {"coordinates":[11.782575,49.051975],"type":"Point"}
}