{
  "type": "Feature",
  "properties": {
    "iso:country":"DE",
    "sg:address":"Benzstr. 2",
    "sg:city":"H\u00f6sbach",
    "sg:phone":"+49 6021/588390",
    "sg:postcode":"63768",
    "sg:province":"Bayern",
    "wof:name":"Sfc Software For Companies Gmbh",
    "wof:placetype":"venue"
},
  "geometry": {"coordinates":[9.2191591263,50.0089378357],"type":"Point"}
}