{
  "type": "Feature",
  "properties": {
    "iso:country":"DE",
    "sg:address":"Albstr. 14",
    "sg:city":"Spaichingen",
    "sg:phone":"+49 7424/2886",
    "sg:postcode":"78549",
    "sg:province":"Baden-W\u00fcrttemberg",
    "wof:name":"Klaus Dieter M\u00e4hnert",
    "wof:placetype":"venue"
},
  "geometry": {"coordinates":[8.7247781754,48.0830993652],"type":"Point"}
}