{
  "type": "Feature",
  "properties": {
    "iso:country":"DE",
    "sg:address":"Dittersbacher Str. 2",
    "sg:city":"Ostritz",
    "sg:phone":"+49 35823/86321",
    "sg:postcode":"02899",
    "sg:province":"Sachsen",
    "wof:name":"S\u00e4gewerk Marienthal Gmbh",
    "wof:placetype":"venue"
},
  "geometry": {"coordinates":[14.9125652313,51.0005569458],"type":"Point"}
}