{
  "type": "Feature",
  "properties": {
    "iso:country":"DE",
    "sg:address":"K\u00f6nigstor 43",
    "sg:city":"Kassel",
    "sg:phone":"+49 561/719539",
    "sg:postcode":"34117",
    "sg:province":"Hessen",
    "wof:name":"Ramex Bilderhandels Gmbh",
    "wof:placetype":"venue"
},
  "geometry": {"coordinates":[9.480736,51.313408],"type":"Point"}
}