{
  "type": "Feature",
  "properties": {
    "iso:country":"DE",
    "sg:address":"Gra\u00dfdorfer Str. 15",
    "sg:city":"Taucha",
    "sg:phone":"+49 34298/30242",
    "sg:postcode":"04425",
    "sg:province":"Sachsen",
    "wof:name":"Siba Gmbh",
    "wof:placetype":"venue"
},
  "geometry": {"coordinates":[12.493564,51.382145],"type":"Point"}
}