{
  "type": "Feature",
  "properties": {
    "iso:country":"DE",
    "sg:address":"K\u00f6lner Str. 7",
    "sg:city":"Blankenheim",
    "sg:phone":"+49 2449/1388",
    "sg:postcode":"53945",
    "sg:province":"Nordrhein-Westfalen",
    "wof:name":"Hotel Violet",
    "wof:placetype":"venue"
},
  "geometry": {"coordinates":[6.6529760361,50.4376449585],"type":"Point"}
}