{
  "type": "Feature",
  "properties": {
    "iso:country":"DE",
    "sg:address":"Altenberger Str. 11",
    "sg:city":"M\u00fcnster",
    "sg:phone":"+49 2533/919474",
    "sg:postcode":"48161",
    "sg:province":"Nordrhein-Westfalen",
    "wof:name":"Planet Groove Productions",
    "wof:placetype":"venue"
},
  "geometry": {"coordinates":[7.561834,51.998016],"type":"Point"}
}