{
  "type": "Feature",
  "properties": {
    "iso:country":"DE",
    "sg:address":"G\u00fcnterstalstr. 37",
    "sg:city":"Freiburg",
    "sg:phone":"+49 761/701733",
    "sg:postcode":"79102",
    "sg:province":"Baden-W\u00fcrttemberg",
    "wof:name":"Dr. Med. A. Stuttmann-balke",
    "wof:placetype":"venue"
},
  "geometry": {"coordinates":[7.8476881981,47.9864730835],"type":"Point"}
}