{
  "type": "Feature",
  "properties": {
    "iso:country":"DE",
    "sg:address":"Geiersbergweg 7d",
    "sg:city":"Regensburg",
    "sg:postcode":"93059",
    "sg:province":"Bayern",
    "wof:name":"Atw-ges. F\u00fcr Alternative Technologien Und",
    "wof:placetype":"venue"
},
  "geometry": {"coordinates":[12.097244,49.032818],"type":"Point"}
}