{
  "type": "Feature",
  "properties": {
    "iso:country":"DE",
    "sg:address":"Irlbacher Str. 13",
    "sg:city":"Stra\u00dfkirchen",
    "sg:phone":"+49 9424/1448",
    "sg:postcode":"94342",
    "sg:province":"Bayern",
    "wof:name":"Josef Hilmer",
    "wof:placetype":"venue"
},
  "geometry": {"coordinates":[12.725908,48.831516],"type":"Point"}
}