{
  "type": "Feature",
  "properties": {
    "iso:country":"DE",
    "sg:address":"Eichenstr. 2",
    "sg:city":"Kroppenstedt",
    "sg:phone":"+49 4939/264226",
    "sg:postcode":"39397",
    "sg:province":"Sachsen-Anhalt",
    "wof:name":"Moldenhauer Tankanlagenbau Und Service Gmbh",
    "wof:placetype":"venue"
},
  "geometry": {"coordinates":[11.302355,51.942795],"type":"Point"}
}