{
  "type": "Feature",
  "properties": {
    "iso:country":"DE",
    "sg:address":"F\u00fcrther Str. 65",
    "sg:city":"N\u00fcrnberg",
    "sg:phone":"+49 911/263025",
    "sg:postcode":"90429",
    "sg:province":"Bayern",
    "wof:name":"Alpha-modelle",
    "wof:placetype":"venue"
},
  "geometry": {"coordinates":[11.055246,49.450897],"type":"Point"}
}