{
  "type": "Feature",
  "properties": {
    "iso:country":"DE",
    "sg:address":"St.-Petersburger-Str. 5",
    "sg:city":"Ribnitz-Damgarten",
    "sg:phone":"+49 3821/812341",
    "sg:postcode":"18311",
    "sg:province":"Mecklenburg-Vorpommern",
    "wof:name":"W. Hartmann Anlageberater",
    "wof:placetype":"venue"
},
  "geometry": {"coordinates":[12.4116487503,54.2416114807],"type":"Point"}
}