{
  "type": "Feature",
  "properties": {
    "iso:country":"DE",
    "sg:address":"Mittelstr. 36-38",
    "sg:city":"Hilden",
    "sg:phone":"+49 2103/62956",
    "sg:postcode":"40721",
    "sg:province":"Nordrhein-Westfalen",
    "wof:name":"Intra-ferrum Gmbh",
    "wof:placetype":"venue"
},
  "geometry": {"coordinates":[6.936473,51.169144],"type":"Point"}
}