{
  "type": "Feature",
  "properties": {
    "iso:country":"DE",
    "sg:address":"Bergheimer Str. 17",
    "sg:city":"Grevenbroich",
    "sg:phone":"+49 2181/62422",
    "sg:postcode":"41515",
    "sg:province":"Nordrhein-Westfalen",
    "wof:name":"Walter Geuer",
    "wof:placetype":"venue"
},
  "geometry": {"coordinates":[6.581809,51.089191],"type":"Point"}
}