{
  "type": "Feature",
  "properties": {
    "iso:country":"DE",
    "sg:address":"Langebr\u00fcckstr. 16",
    "sg:city":"Eckernf\u00f6rde",
    "sg:phone":"+49 4351/71700",
    "sg:postcode":"24340",
    "sg:province":"Schleswig-Holstein",
    "wof:name":"Nicolai-apotheke",
    "wof:placetype":"venue"
},
  "geometry": {"coordinates":[9.83496,54.472599],"type":"Point"}
}