{
  "type": "Feature",
  "properties": {
    "iso:country":"DE",
    "sg:address":"Forstweg 28",
    "sg:city":"Brieselang",
    "sg:phone":"+49 33232/41501",
    "sg:postcode":"14656",
    "sg:province":"Brandenburg",
    "wof:name":"El-hei-sa-bau Gmbh",
    "wof:placetype":"venue"
},
  "geometry": {"coordinates":[12.988967,52.583397],"type":"Point"}
}