{
  "type": "Feature",
  "properties": {
    "iso:country":"DE",
    "sg:address":"Herrenstr. 36a",
    "sg:city":"Simmertal",
    "sg:phone":"+49 6754/8142",
    "sg:postcode":"55618",
    "sg:province":"Rheinland-Pfalz",
    "wof:name":"Willi Fr\u00f6tschl",
    "wof:placetype":"venue"
},
  "geometry": {"coordinates":[7.5198497772,49.8095703125],"type":"Point"}
}