{
  "type": "Feature",
  "properties": {
    "iso:country":"DE",
    "sg:address":"Carl-Zeiss-Str. 1",
    "sg:city":"Waldshut-Tiengen",
    "sg:phone":"+49 7741/3536",
    "sg:postcode":"79761",
    "sg:province":"Baden-W\u00fcrttemberg",
    "wof:name":"K. Liar",
    "wof:placetype":"venue"
},
  "geometry": {"coordinates":[8.2642211914,47.6281852722],"type":"Point"}
}