{
  "type": "Feature",
  "properties": {
    "iso:country":"DE",
    "sg:address":"B\u00fcchel 43",
    "sg:city":"Neuss",
    "sg:phone":"+49 2131/277061",
    "sg:postcode":"41460",
    "sg:province":"Nordrhein-Westfalen",
    "wof:name":"Atlas Reiseb\u00fcro Gmbh",
    "wof:placetype":"venue"
},
  "geometry": {"coordinates":[6.6907072067,51.1992454529],"type":"Point"}
}