{
  "type": "Feature",
  "properties": {
    "iso:country":"DE",
    "sg:address":"Bergstr. 33",
    "sg:city":"Neulingen",
    "sg:phone":"+49 7237/9530",
    "sg:postcode":"75245",
    "sg:province":"Baden-W\u00fcrttemberg",
    "wof:name":"U. Gwinner",
    "wof:placetype":"venue"
},
  "geometry": {"coordinates":[8.6941013336,48.9875831604],"type":"Point"}
}