{
  "type": "Feature",
  "properties": {
    "iso:country":"DE",
    "sg:address":"Heideweg 19",
    "sg:city":"Bremerhaven",
    "sg:phone":"+49 471/81024",
    "sg:postcode":"27578",
    "sg:province":"Bremen",
    "wof:name":"Br\u00fcggemann Gmbh",
    "wof:placetype":"venue"
},
  "geometry": {"coordinates":[8.6007633209,53.5872917175],"type":"Point"}
}