{
  "type": "Feature",
  "properties": {
    "iso:country":"DE",
    "sg:address":"Gerbergasse 4",
    "sg:city":"Mei\u00dfen",
    "sg:phone":"+49 3521/454449",
    "sg:postcode":"01662",
    "sg:province":"Sachsen",
    "wof:name":"Dr. Med. Hansj\u00f6rg Weber",
    "wof:placetype":"venue"
},
  "geometry": {"coordinates":[13.473838,51.163509],"type":"Point"}
}