{
  "type": "Feature",
  "properties": {
    "iso:country":"DE",
    "sg:address":"Freiherr-vom-Stein-Str. 1",
    "sg:city":"Regensburg",
    "sg:phone":"+49 941/3995090",
    "sg:postcode":"93049",
    "sg:province":"Bayern",
    "wof:name":"Berthold Aumeier Immobilien Gmbh",
    "wof:placetype":"venue"
},
  "geometry": {"coordinates":[12.06183815,49.0159492493],"type":"Point"}
}