{
  "type": "Feature",
  "properties": {
    "iso:country":"DE",
    "sg:address":"Eberhardshofstr. 18",
    "sg:city":"N\u00fcrnberg",
    "sg:phone":"+49 911/2878412",
    "sg:postcode":"90429",
    "sg:province":"Bayern",
    "wof:name":"Sidhu",
    "wof:placetype":"venue"
},
  "geometry": {"coordinates":[11.0543804169,49.449962616],"type":"Point"}
}