{
  "type": "Feature",
  "properties": {
    "iso:country":"DE",
    "sg:address":"Zur Alten Hege 21",
    "sg:city":"Schwalmstadt",
    "sg:phone":"+49 6692/1438",
    "sg:postcode":"34613",
    "sg:province":"Hessen",
    "wof:name":"G. Pech",
    "wof:placetype":"venue"
},
  "geometry": {"coordinates":[9.144958,50.882214],"type":"Point"}
}