{
  "type": "Feature",
  "properties": {
    "iso:country":"DE",
    "sg:address":"Brunnengasse 16",
    "sg:city":"Hohenroth",
    "sg:phone":"+49 9771/5600",
    "sg:postcode":"97618",
    "sg:province":"Bayern",
    "wof:name":"Weigand",
    "wof:placetype":"venue"
},
  "geometry": {"coordinates":[10.141212,50.337673],"type":"Point"}
}