{
  "type": "Feature",
  "properties": {
    "iso:country":"DE",
    "sg:address":"Esslinger Str. 6",
    "sg:city":"Pforzheim",
    "sg:phone":"+49 7231/102902",
    "sg:postcode":"75179",
    "sg:province":"Baden-W\u00fcrttemberg",
    "wof:name":"Sigrist Metallveredelung Gmbh",
    "wof:placetype":"venue"
},
  "geometry": {"coordinates":[8.6533298492,48.9027671814],"type":"Point"}
}