{
  "type": "Feature",
  "properties": {
    "iso:country":"DE",
    "sg:address":"Angerstr. 2",
    "sg:city":"Karlskron",
    "sg:phone":"+49 8454/99010",
    "sg:postcode":"85123",
    "sg:province":"Bayern",
    "wof:name":"Kreil Kunststofftechnik Gmbh",
    "wof:placetype":"venue"
},
  "geometry": {"coordinates":[11.379653,48.663464],"type":"Point"}
}