{
  "type": "Feature",
  "properties": {
    "iso:country":"DE",
    "sg:address":"Vo\u00dfkuhlen",
    "sg:city":"Elmshorn",
    "sg:postcode":"25335",
    "sg:province":"Schleswig-Holstein",
    "wof:name":"U. Skerswetat Immobilienmakler",
    "wof:placetype":"venue"
},
  "geometry": {"coordinates":[9.6832704544,53.7686843872],"type":"Point"}
}