{
  "type": "Feature",
  "properties": {
    "iso:country":"DE",
    "sg:address":"Alpirsbacher Str. 69",
    "sg:city":"Aichhalden",
    "sg:phone":"+49 7444/51500",
    "sg:postcode":"78733",
    "sg:province":"Baden-W\u00fcrttemberg",
    "wof:name":"Karl Fuchs",
    "wof:placetype":"venue"
},
  "geometry": {"coordinates":[8.424385,48.307968],"type":"Point"}
}