{
  "type": "Feature",
  "properties": {
    "iso:country":"DE",
    "sg:address":"Simonsh\u00f6fchen 28",
    "sg:city":"Wuppertal",
    "sg:phone":"+49 202/730026",
    "sg:postcode":"42327",
    "sg:province":"Nordrhein-Westfalen",
    "wof:name":"Axel Halt Auf Der Heide",
    "wof:placetype":"venue"
},
  "geometry": {"coordinates":[7.0480899811,51.2264518738],"type":"Point"}
}