{
  "type": "Feature",
  "properties": {
    "iso:country":"DE",
    "sg:address":"F\u00fcrther Str. 343",
    "sg:city":"N\u00fcrnberg",
    "sg:phone":"+49 911/320836",
    "sg:postcode":"90429",
    "sg:province":"Bayern",
    "wof:name":"Raab + Metz Pelze Gmbh",
    "wof:placetype":"venue"
},
  "geometry": {"coordinates":[11.020168,49.46233],"type":"Point"}
}