{
  "type": "Feature",
  "properties": {
    "iso:country":"DE",
    "sg:address":"Hochfellnstr. 53",
    "sg:city":"Bergen",
    "sg:phone":"+49 8662/8614",
    "sg:postcode":"83346",
    "sg:province":"Bayern",
    "wof:name":"G\u00e4stehaus Johann Dangl",
    "wof:placetype":"venue"
},
  "geometry": {"coordinates":[12.5901594162,47.7999305725],"type":"Point"}
}