{
  "type": "Feature",
  "properties": {
    "iso:country":"DE",
    "sg:address":"Braunetsriether Weg 48",
    "sg:city":"Vohenstrau\u00df",
    "sg:phone":"+49 9651/91214",
    "sg:postcode":"92648",
    "sg:province":"Bayern",
    "wof:name":"F. Forstner",
    "wof:placetype":"venue"
},
  "geometry": {"coordinates":[12.3519248962,49.6196784973],"type":"Point"}
}