{
  "type": "Feature",
  "properties": {
    "iso:country":"DE",
    "sg:address":"Crailsheimer Str. 67",
    "sg:city":"Schw\u00e4bisch Hall",
    "sg:postcode":"74523",
    "sg:province":"Baden-W\u00fcrttemberg",
    "wof:name":"Eurospar",
    "wof:placetype":"venue"
},
  "geometry": {"coordinates":[9.7500801086,49.1188659668],"type":"Point"}
}