{
  "type": "Feature",
  "properties": {
    "iso:country":"DE",
    "sg:address":"Helenenhof",
    "sg:city":"\u00dcbach-Palenberg",
    "sg:phone":"+49 2451/43676",
    "sg:postcode":"52531",
    "sg:province":"Nordrhein-Westfalen",
    "wof:name":"Anh\u00e4ngerspezialist Radermacher  Da L\u00e4uft Was!",
    "wof:placetype":"venue"
},
  "geometry": {"coordinates":[6.1475100517,50.9219665527],"type":"Point"}
}