{
  "type": "Feature",
  "properties": {
    "iso:country":"DE",
    "sg:address":"Siebenb\u00fcrgenweg 1",
    "sg:city":"Osterode",
    "sg:phone":"+49 5522/90120",
    "sg:postcode":"37520",
    "sg:province":"Niedersachsen",
    "wof:name":"Seniorenheim Siebenb\u00fcrgen",
    "wof:placetype":"venue"
},
  "geometry": {"coordinates":[10.251443,51.719769],"type":"Point"}
}