{
  "type": "Feature",
  "properties": {
    "iso:country":"DE",
    "sg:address":"Burgstr. 18",
    "sg:city":"Freigericht",
    "sg:postcode":"63579",
    "sg:province":"Hessen",
    "wof:name":"Service Und Trade Gmbh",
    "wof:placetype":"venue"
},
  "geometry": {"coordinates":[9.14454,50.141201],"type":"Point"}
}