{
  "type": "Feature",
  "properties": {
    "iso:country":"DE",
    "sg:address":"Frauenstr. 9 /11",
    "sg:city":"Niederwiesa",
    "sg:phone":"+49 3726/6176",
    "sg:postcode":"09577",
    "sg:province":"Sachsen",
    "wof:name":"Bau-berger Gmbh",
    "wof:placetype":"venue"
},
  "geometry": {"coordinates":[13.022373,50.861813],"type":"Point"}
}