{
  "type": "Feature",
  "properties": {
    "iso:country":"DE",
    "sg:address":"Annastr. 4",
    "sg:city":"Iserlohn",
    "sg:phone":"+49 2371/23375",
    "sg:postcode":"58636",
    "sg:province":"Nordrhein-Westfalen",
    "wof:name":"I. Konstantinidis",
    "wof:placetype":"venue"
},
  "geometry": {"coordinates":[7.709458828,51.3774528503],"type":"Point"}
}