{
  "type": "Feature",
  "properties": {
    "iso:country":"DE",
    "sg:address":"Pagenstecherstr. 15",
    "sg:city":"Osnabr\u00fcck",
    "sg:phone":"+49 541/963963",
    "sg:postcode":"49090",
    "sg:province":"Niedersachsen",
    "wof:name":"Siegfried Sander Gmbh & Co. Kg",
    "wof:placetype":"venue"
},
  "geometry": {"coordinates":[8.0339422226,52.2860145569],"type":"Point"}
}