{
  "type": "Feature",
  "properties": {
    "iso:country":"DE",
    "sg:address":"Neue Gasse 3",
    "sg:city":"Kleinschmalkalden",
    "sg:phone":"+49 36849/1312",
    "sg:postcode":"98593",
    "sg:province":"Th\u00fcringen",
    "wof:name":"Howaton Musikvermittlung",
    "wof:placetype":"venue"
},
  "geometry": {"coordinates":[10.4761924744,50.7971687317],"type":"Point"}
}