{
  "type": "Feature",
  "properties": {
    "iso:country":"DE",
    "sg:address":"Fourtgasse 168",
    "sg:city":"Mellingen",
    "sg:phone":"+49 36453/80606",
    "sg:postcode":"99441",
    "sg:province":"Th\u00fcringen",
    "wof:name":"Hotel-landgasthaus Birkenhof",
    "wof:placetype":"venue"
},
  "geometry": {"coordinates":[11.3925151825,50.9394035339],"type":"Point"}
}