{
  "type": "Feature",
  "properties": {
    "iso:country":"DE",
    "sg:address":"Barther Str. 8",
    "sg:city":"Berlin",
    "sg:phone":"+49 30/9276015",
    "sg:postcode":"13051",
    "sg:province":"Berlin",
    "wof:name":"Heinz Kulpe Architekt",
    "wof:placetype":"venue"
},
  "geometry": {"coordinates":[13.500493,52.565159],"type":"Point"}
}