{
  "type": "Feature",
  "properties": {
    "iso:country":"DE",
    "sg:address":"Domplatz 36",
    "sg:city":"Halberstadt",
    "sg:phone":"+49 3941/607570",
    "sg:postcode":"38820",
    "sg:province":"Sachsen-Anhalt",
    "wof:name":"Museumscafe",
    "wof:placetype":"venue"
},
  "geometry": {"coordinates":[11.048014,51.8965],"type":"Point"}
}