{
  "type": "Feature",
  "properties": {
    "iso:country":"DE",
    "sg:address":"Mozartstr. 31",
    "sg:city":"Heiden",
    "sg:phone":"+49 2867/8566",
    "sg:postcode":"46359",
    "sg:province":"Nordrhein-Westfalen",
    "wof:name":"Paul Galle",
    "wof:placetype":"venue"
},
  "geometry": {"coordinates":[6.926345,51.828281],"type":"Point"}
}