{
  "type": "Feature",
  "properties": {
    "iso:country":"DE",
    "sg:address":"Sonnenallee 62",
    "sg:city":"Berlin",
    "sg:phone":"+49 30/6231854",
    "sg:postcode":"12045",
    "sg:province":"Berlin",
    "wof:name":"Gatec Gesellschaft F\u00fcr Gasanlagen-installation Mbh",
    "wof:placetype":"venue"
},
  "geometry": {"coordinates":[13.4340324402,52.4843902588],"type":"Point"}
}