{
  "type": "Feature",
  "properties": {
    "iso:country":"DE",
    "sg:address":"Hauptstr. 33",
    "sg:city":"Aerzen",
    "sg:phone":"+49 5154/96191",
    "sg:postcode":"31855",
    "sg:province":"Niedersachsen",
    "wof:name":"Martin Karzenburg Architekt",
    "wof:placetype":"venue"
},
  "geometry": {"coordinates":[9.236523,52.030235],"type":"Point"}
}