{
  "type": "Feature",
  "properties": {
    "iso:country":"DE",
    "sg:address":"Ettlinger Str. 22",
    "sg:city":"Waldbronn",
    "sg:phone":"+49 7243/572793",
    "sg:postcode":"76337",
    "sg:province":"Baden-W\u00fcrttemberg",
    "wof:name":"Gerhard Jungwirth",
    "wof:placetype":"venue"
},
  "geometry": {"coordinates":[8.4604988098,48.9310760498],"type":"Point"}
}