{
  "type": "Feature",
  "properties": {
    "iso:country":"DE",
    "sg:address":"Hainstr. 110",
    "sg:city":"Chemnitz",
    "sg:phone":"+49 371/410109",
    "sg:postcode":"09130",
    "sg:province":"Sachsen",
    "wof:name":"Ryczek",
    "wof:placetype":"venue"
},
  "geometry": {"coordinates":[12.9376277924,50.8425559998],"type":"Point"}
}