{
  "type": "Feature",
  "properties": {
    "iso:country":"DE",
    "sg:address":"Dresdener Str 19",
    "sg:city":"Wilthen",
    "sg:phone":"+49 6172/80900",
    "sg:postcode":"02681",
    "sg:province":"Sachsen",
    "wof:name":"Kilb & Co Kg",
    "wof:placetype":"venue"
},
  "geometry": {"coordinates":[8.609567,50.236938],"type":"Point"}
}