{
  "type": "Feature",
  "properties": {
    "iso:country":"DE",
    "sg:address":"Postfach 840:: 40708 Hilden:: Germany.^^Mittelstr 44::",
    "sg:city":"Hilden",
    "sg:phone":"+49 2173/9090",
    "sg:postcode":"40721",
    "sg:province":"Nordrhein-Westfalen",
    "wof:name":"Stadt-sparkasse Langenfeld",
    "wof:placetype":"venue"
},
  "geometry": {"coordinates":[6.95112,51.113384],"type":"Point"}
}