{
  "type": "Feature",
  "properties": {
    "iso:country":"DE",
    "sg:address":"Poststr. 70",
    "sg:city":"Velbert",
    "sg:phone":"+49 2051/63801",
    "sg:postcode":"42549",
    "sg:province":"Nordrhein-Westfalen",
    "wof:name":"Waldschl\u00f6sschen",
    "wof:placetype":"venue"
},
  "geometry": {"coordinates":[7.0349030495,51.3368759155],"type":"Point"}
}