{
  "type": "Feature",
  "properties": {
    "iso:country":"DE",
    "sg:address":"Drosselweg 21",
    "sg:city":"M\u00fcnchen",
    "sg:phone":"+49 89/453120",
    "sg:postcode":"81827",
    "sg:province":"Bayern",
    "wof:name":"Ford Autohaus Kuttendreier",
    "wof:placetype":"venue"
},
  "geometry": {"coordinates":[11.6945037842,48.1184310913],"type":"Point"}
}