{
  "type": "Feature",
  "properties": {
    "iso:country":"DE",
    "sg:address":"Steimelstr. 10",
    "sg:city":"K\u00f6nigswinter",
    "sg:phone":"+49 2244/470330",
    "sg:postcode":"53639",
    "sg:province":"Nordrhein-Westfalen",
    "wof:name":"S. Eitel Ingenieur",
    "wof:placetype":"venue"
},
  "geometry": {"coordinates":[7.2922620773,50.723903656],"type":"Point"}
}