{
  "type": "Feature",
  "properties": {
    "iso:country":"DE",
    "sg:address":"Hofackerweg 9",
    "sg:city":"Wetter",
    "sg:postcode":"35083",
    "sg:province":"Hessen",
    "wof:name":"Adeis Hinterl\u00e4nder- Nudelspezialit\u00e4ten- Gmbh",
    "wof:placetype":"venue"
},
  "geometry": {"coordinates":[8.6454753876,50.9135627747],"type":"Point"}
}