{
  "type": "Feature",
  "properties": {
    "iso:country":"DE",
    "sg:address":"Bahnhofstr. 3",
    "sg:city":"Lebach",
    "sg:phone":"+49 6881/53567",
    "sg:postcode":"66822",
    "sg:province":"Saarland",
    "wof:name":"Side Grill",
    "wof:placetype":"venue"
},
  "geometry": {"coordinates":[6.9112849236,49.4108161926],"type":"Point"}
}