{
  "type": "Feature",
  "properties": {
    "iso:country":"DE",
    "sg:address":"Parkallee 35",
    "sg:city":"Bremen",
    "sg:phone":"+49 421/346000",
    "sg:postcode":"28209",
    "sg:province":"Bremen",
    "wof:name":"Anna-maria Weide Baustoffe E. K.",
    "wof:placetype":"venue"
},
  "geometry": {"coordinates":[8.822661,53.082485],"type":"Point"}
}