{
  "type": "Feature",
  "properties": {
    "iso:country":"DE",
    "sg:address":"Poetenweg 23a",
    "sg:city":"Lutherstadt Wittenberg",
    "sg:postcode":"06886",
    "sg:province":"Sachsen-Anhalt",
    "wof:name":"Branchenservice Mit Kompletten Suchdienst",
    "wof:placetype":"venue"
},
  "geometry": {"coordinates":[12.631203,51.873985],"type":"Point"}
}