{
  "type": "Feature",
  "properties": {
    "iso:country":"DE",
    "sg:address":"Credenstr. 32",
    "sg:city":"Herford",
    "sg:phone":"+49 5221/55966",
    "sg:postcode":"32052",
    "sg:province":"Nordrhein-Westfalen",
    "wof:name":"E. Koch",
    "wof:placetype":"venue"
},
  "geometry": {"coordinates":[8.6760215759,52.115978241],"type":"Point"}
}