{
  "type": "Feature",
  "properties": {
    "iso:country":"DE",
    "sg:address":"Gagarinstra\u00dfe",
    "sg:city":"Potsdam",
    "sg:phone":"+49 331/6004622",
    "sg:postcode":"14480",
    "sg:province":"Brandenburg",
    "wof:name":"Ihr Rewe Markt Sch\u00f6nborn Ohg",
    "wof:placetype":"venue"
},
  "geometry": {"coordinates":[13.125826,52.3801],"type":"Point"}
}