{
  "type": "Feature",
  "properties": {
    "iso:country":"DE",
    "sg:address":"Marie-Luise-Kaschnitz-Str. 18",
    "sg:city":"Karlsruhe",
    "sg:phone":"+49 721/888388",
    "sg:postcode":"76199",
    "sg:province":"Baden-W\u00fcrttemberg",
    "wof:name":"Rolf Egle Ingenieur",
    "wof:placetype":"venue"
},
  "geometry": {"coordinates":[8.416601181,48.9654006958],"type":"Point"}
}