{
  "type": "Feature",
  "properties": {
    "iso:country":"DE",
    "sg:address":"Grafenhof 1",
    "sg:city":"Northeim",
    "sg:phone":"+49 5551/7682",
    "sg:postcode":"37154",
    "sg:province":"Niedersachsen",
    "wof:name":"B. Scherzberg",
    "wof:placetype":"venue"
},
  "geometry": {"coordinates":[9.997721,51.705265],"type":"Point"}
}