{
  "type": "Feature",
  "properties": {
    "iso:country":"DE",
    "sg:address":"Marktplatz 14",
    "sg:city":"N\u00f6rdlingen",
    "sg:phone":"+49 9081/86091",
    "sg:postcode":"86720",
    "sg:province":"Bayern",
    "wof:name":"Deutsche Bank Ag",
    "wof:placetype":"venue"
},
  "geometry": {"coordinates":[10.487879,48.850727],"type":"Point"}
}