{
  "type": "Feature",
  "properties": {
    "iso:country":"DE",
    "sg:address":"Sch\u00e4ferstr 5",
    "sg:city":"Gelsenkirchen",
    "sg:phone":"+49 209/581021",
    "sg:postcode":"45897",
    "sg:province":"Nordrhein-Westfalen",
    "wof:name":"Rio Artur Scheck Ballfabrik Ek",
    "wof:placetype":"venue"
},
  "geometry": {"coordinates":[7.062691,51.542778],"type":"Point"}
}