{
  "type": "Feature",
  "properties": {
    "iso:country":"DE",
    "sg:address":"Ernst-Haeckel-Str. 5",
    "sg:city":"Zella-Mehlis",
    "sg:phone":"+49 3682/482694",
    "sg:postcode":"98544",
    "sg:province":"Th\u00fcringen",
    "wof:name":"Werner Gerloff",
    "wof:placetype":"venue"
},
  "geometry": {"coordinates":[10.6674766541,50.658000946],"type":"Point"}
}