{
  "type": "Feature",
  "properties": {
    "iso:country":"DE",
    "sg:address":"Inselbergstr. 11",
    "sg:city":"Brotterode",
    "sg:phone":"+49 36840/32269",
    "sg:postcode":"98599",
    "sg:province":"Th\u00fcringen",
    "wof:name":"E. Scheffler",
    "wof:placetype":"venue"
},
  "geometry": {"coordinates":[10.4423475266,50.8246307373],"type":"Point"}
}