{
  "type": "Feature",
  "properties": {
    "iso:country":"DE",
    "sg:address":"Dorfstr. 64",
    "sg:city":"Trockenborn-Wolfersdorf",
    "sg:phone":"+49 36428/40925",
    "sg:postcode":"07646",
    "sg:province":"Th\u00fcringen",
    "wof:name":"Th\u00fcmmel Gmbh",
    "wof:placetype":"venue"
},
  "geometry": {"coordinates":[11.697724,50.787704],"type":"Point"}
}