{
  "type": "Feature",
  "properties": {
    "iso:country":"DE",
    "sg:address":"B\u00e4ckerstr. 23",
    "sg:city":"Marne",
    "sg:phone":"+49 4851/589",
    "sg:postcode":"25709",
    "sg:province":"Schleswig-Holstein",
    "wof:name":"Leszirkel Volquarts Inh. Jan Volquarts",
    "wof:placetype":"venue"
},
  "geometry": {"coordinates":[9.009805,53.95118],"type":"Point"}
}