{
  "type": "Feature",
  "properties": {
    "iso:country":"DE",
    "sg:address":"Mitterweg 6",
    "sg:city":"Bernau",
    "sg:phone":"+49 8051/7560",
    "sg:postcode":"83233",
    "sg:province":"Bayern",
    "wof:name":"Fremdenheim Max Herrmann",
    "wof:placetype":"venue"
},
  "geometry": {"coordinates":[12.3733615875,47.8103713989],"type":"Point"}
}