{
  "type": "Feature",
  "properties": {
    "iso:country":"DE",
    "sg:address":"Karlstr. 6",
    "sg:city":"B\u00fchl",
    "sg:phone":"+49 7227/3085",
    "sg:postcode":"77815",
    "sg:province":"Baden-W\u00fcrttemberg",
    "wof:name":"Peter D\u00f6rr",
    "wof:placetype":"venue"
},
  "geometry": {"coordinates":[8.0651683807,48.7166252136],"type":"Point"}
}