{
  "type": "Feature",
  "properties": {
    "iso:country":"DE",
    "sg:address":"Gro\u00dfbeerenstr 146 Tor 4",
    "sg:city":"Berlin",
    "sg:phone":"+49 30/6125454",
    "sg:postcode":"12277",
    "sg:province":"Berlin",
    "wof:name":"Michael Busse Metalldr\u00fcckerei U. Umformtechnik",
    "wof:placetype":"venue"
},
  "geometry": {"coordinates":[13.3680267334,52.4124145508],"type":"Point"}
}