{
  "type": "Feature",
  "properties": {
    "iso:country":"DE",
    "sg:address":"Herrenstr. 1",
    "sg:city":"Gettorf",
    "sg:phone":"+49 4346/3287",
    "sg:postcode":"24214",
    "sg:province":"Schleswig-Holstein",
    "wof:name":"Mi\u00dffeldt Tischlerei Und Bestattungen",
    "wof:placetype":"venue"
},
  "geometry": {"coordinates":[9.975081,54.409523],"type":"Point"}
}