{
  "type": "Feature",
  "properties": {
    "iso:country":"DE",
    "sg:address":"Sch\u00fcrholz 38",
    "sg:city":"Wermelskirchen",
    "sg:phone":"+49 2193/944",
    "sg:postcode":"42929",
    "sg:province":"Nordrhein-Westfalen",
    "wof:name":"Wasserversorgungsverband Rhein-wupper",
    "wof:placetype":"venue"
},
  "geometry": {"coordinates":[7.2058057785,51.099445343],"type":"Point"}
}