{
  "type": "Feature",
  "properties": {
    "iso:country":"DE",
    "sg:address":"Gerhart-Hauptmann-Str. 3",
    "sg:city":"Eberdingen",
    "sg:phone":"+49 7042/98440",
    "sg:postcode":"71735",
    "sg:province":"Baden-W\u00fcrttemberg",
    "wof:name":"Horst Wagner Ingenieur",
    "wof:placetype":"venue"
},
  "geometry": {"coordinates":[8.937541008,48.8982543945],"type":"Point"}
}