{
  "type": "Feature",
  "properties": {
    "iso:country":"DE",
    "sg:address":"Kirchstr. 75",
    "sg:city":"Budenheim",
    "sg:phone":"+49 4961/39450",
    "sg:postcode":"55257",
    "sg:province":"Rheinland-Pfalz",
    "wof:name":"Mobile Tischlerei U. Treppenbau Gmbh",
    "wof:placetype":"venue"
},
  "geometry": {"coordinates":[8.1829833984,50.0288467407],"type":"Point"}
}