{
  "type": "Feature",
  "properties": {
    "iso:country":"DE",
    "sg:address":"Weilerweg 12",
    "sg:city":"K\u00f6nigsbronn",
    "sg:phone":"+49 7328/6600",
    "sg:postcode":"89551",
    "sg:province":"Baden-W\u00fcrttemberg",
    "wof:name":"Jugendherberge K\u00f6nigsbronn",
    "wof:placetype":"venue"
},
  "geometry": {"coordinates":[10.1424026489,48.7438735962],"type":"Point"}
}