{
  "type": "Feature",
  "properties": {
    "iso:country":"DE",
    "sg:address":"Hanauer Str. 1",
    "sg:city":"Maintal",
    "sg:phone":"+49 6181/45366",
    "sg:postcode":"63477",
    "sg:province":"Hessen",
    "wof:name":"Pulino Inneneinrichtungen",
    "wof:placetype":"venue"
},
  "geometry": {"coordinates":[8.837815,50.153984],"type":"Point"}
}