{
  "type": "Feature",
  "properties": {
    "iso:country":"DE",
    "sg:address":"Rieper Str. 4",
    "sg:city":"Bomlitz",
    "sg:postcode":"29699",
    "sg:province":"Niedersachsen",
    "wof:name":"Tischlerei Eitzmann Gmbh",
    "wof:placetype":"venue"
},
  "geometry": {"coordinates":[9.692053,52.942707],"type":"Point"}
}