{
  "type": "Feature",
  "properties": {
    "iso:country":"DE",
    "sg:address":"Bauerland 14",
    "sg:city":"Bremen",
    "sg:phone":"+49 4942/1571004",
    "sg:postcode":"28259",
    "sg:province":"Bremen",
    "wof:name":"Volker Eblinger & Paolo Immerini Gbr",
    "wof:placetype":"venue"
},
  "geometry": {"coordinates":[8.725356102,53.0597381592],"type":"Point"}
}