{
  "type": "Feature",
  "properties": {
    "iso:country":"DE",
    "sg:address":"Lindenweg 18",
    "sg:city":"Siggelkow",
    "sg:phone":"+49 38724/20447",
    "sg:postcode":"19376",
    "sg:province":"Mecklenburg-Vorpommern",
    "wof:name":"Wiesenkrug",
    "wof:placetype":"venue"
},
  "geometry": {"coordinates":[12.0333852768,53.375831604],"type":"Point"}
}