{
  "type": "Feature",
  "properties": {
    "iso:country":"DE",
    "sg:address":"Gervinusstr. 40",
    "sg:city":"N\u00fcrnberg",
    "sg:phone":"+49 911/595037",
    "sg:postcode":"90491",
    "sg:province":"Bayern",
    "wof:name":"Michel Wolf Rechtsanwalt",
    "wof:placetype":"venue"
},
  "geometry": {"coordinates":[11.1268587112,49.4730834961],"type":"Point"}
}