{
  "type": "Feature",
  "properties": {
    "iso:country":"DE",
    "sg:address":"Gartenstr. 19",
    "sg:city":"Berg",
    "sg:phone":"+49 9189/40074",
    "sg:postcode":"92348",
    "sg:province":"Bayern",
    "wof:name":"K\u00f6lbl Bau Gmbh",
    "wof:placetype":"venue"
},
  "geometry": {"coordinates":[11.4394931793,49.3269500732],"type":"Point"}
}