{
  "type": "Feature",
  "properties": {
    "iso:country":"DE",
    "sg:address":"Kurt-Schumacher-Str. 49",
    "sg:city":"Leipzig",
    "sg:phone":"+49 341/209541",
    "sg:postcode":"04105",
    "sg:province":"Sachsen",
    "wof:name":"H\u00f6ft Wessel & Dr. Dre\u00dfler Gmbh",
    "wof:placetype":"venue"
},
  "geometry": {"coordinates":[12.3774585724,51.3490486145],"type":"Point"}
}