{
  "type": "Feature",
  "properties": {
    "iso:country":"DE",
    "sg:address":"Raimundstr. 104",
    "sg:city":"Frankfurt",
    "sg:phone":"+49 69/564098",
    "sg:postcode":"60320",
    "sg:province":"Hessen",
    "wof:name":"Draganescu",
    "wof:placetype":"venue"
},
  "geometry": {"coordinates":[8.662813,50.139626],"type":"Point"}
}