{
  "type": "Feature",
  "properties": {
    "iso:country":"DE",
    "sg:address":"Dorfstr. 43",
    "sg:city":"Schwante",
    "sg:phone":"+49 33055/70948",
    "sg:postcode":"16727",
    "sg:province":"Brandenburg",
    "wof:name":"Karl-dietmar Plentz",
    "wof:placetype":"venue"
},
  "geometry": {"coordinates":[13.085397,52.736107],"type":"Point"}
}