{
  "type": "Feature",
  "properties": {
    "iso:country":"DE",
    "sg:address":"An der Bundesautobahn A 5",
    "sg:city":"Mahlberg",
    "sg:phone":"+49 7825/1057",
    "sg:postcode":"77972",
    "sg:province":"Baden-W\u00fcrttemberg",
    "wof:name":"Tank- Und Rastanlage Mahlberg Ost Gmbh",
    "wof:placetype":"venue"
},
  "geometry": {"coordinates":[7.8132300377,48.2870788574],"type":"Point"}
}