{
  "type": "Feature",
  "properties": {
    "iso:country":"DE",
    "sg:address":"Dirschelweg 5",
    "sg:city":"Berlin",
    "sg:phone":"+49 30/7038905",
    "sg:postcode":"12109",
    "sg:province":"Berlin",
    "wof:name":"Alexandra Jaroni Heilpraktikerin",
    "wof:placetype":"venue"
},
  "geometry": {"coordinates":[13.3994188309,52.4448280334],"type":"Point"}
}