{
  "type": "Feature",
  "properties": {
    "iso:country":"DE",
    "sg:address":"Kirchweg 13",
    "sg:city":"Lichtenberg",
    "sg:postcode":"09638",
    "sg:province":"Sachsen",
    "wof:name":"Ev.-luth. Kirche Lichtenberg",
    "wof:placetype":"venue"
},
  "geometry": {"coordinates":[13.4092006683,50.8427619934],"type":"Point"}
}