{
  "type": "Feature",
  "properties": {
    "iso:country":"DE",
    "sg:address":"Peter-Henlein-Str. 27",
    "sg:city":"Eckental",
    "sg:phone":"+49 9126/7512",
    "sg:postcode":"90542",
    "sg:province":"Bayern",
    "wof:name":"Micom B\u00fcro- Und Informations- Systeme Gmbh",
    "wof:placetype":"venue"
},
  "geometry": {"coordinates":[11.2105827332,49.5909233093],"type":"Point"}
}