{
  "type": "Feature",
  "properties": {
    "iso:country":"DE",
    "sg:address":"Weiherstr. 19",
    "sg:city":"Traben-Trarbach",
    "sg:phone":"+49 6541/6737",
    "sg:postcode":"56841",
    "sg:province":"Rheinland-Pfalz",
    "wof:name":"Karl Caspari",
    "wof:placetype":"venue"
},
  "geometry": {"coordinates":[7.1110711098,49.9465332031],"type":"Point"}
}