{
  "type": "Feature",
  "properties": {
    "iso:country":"DE",
    "sg:city":"Isny",
    "sg:phone":"+49 7562/4786",
    "sg:postcode":"88316",
    "sg:province":"Baden-W\u00fcrttemberg",
    "wof:name":"R. Prohmann",
    "wof:placetype":"venue"
},
  "geometry": {"coordinates":[10.039095,47.691719],"type":"Point"}
}