{
  "type": "Feature",
  "properties": {
    "iso:country":"DE",
    "sg:address":"Rudolf-Diesel-Str. 11",
    "sg:city":"Odelzhausen",
    "sg:phone":"+49 8134/93430",
    "sg:postcode":"85235",
    "sg:province":"Bayern",
    "wof:name":"Heinrich Schaub Stahlhandel Gmbh",
    "wof:placetype":"venue"
},
  "geometry": {"coordinates":[11.207095,48.30267],"type":"Point"}
}