{
  "type": "Feature",
  "properties": {
    "iso:country":"DE",
    "sg:address":"Buchholzer Str.",
    "sg:city":"Steinh\u00f6fel",
    "sg:phone":"+49 33636/5018",
    "sg:postcode":"15518",
    "sg:province":"Brandenburg",
    "wof:name":"M & G Metall- Und Gestellbau Gmbh",
    "wof:placetype":"venue"
},
  "geometry": {"coordinates":[14.153535,52.449306],"type":"Point"}
}