{
  "type": "Feature",
  "properties": {
    "iso:country":"DE",
    "sg:address":"Oppspring 62",
    "sg:city":"M\u00fclheim",
    "sg:phone":"+49 208/374425",
    "sg:postcode":"45470",
    "sg:province":"Nordrhein-Westfalen",
    "wof:name":"Pps & Partner Gmbh",
    "wof:placetype":"venue"
},
  "geometry": {"coordinates":[6.9086589813,51.4199829102],"type":"Point"}
}