{
  "type": "Feature",
  "properties": {
    "iso:country":"DE",
    "sg:address":"Schlo\u00dfgartenweg 12",
    "sg:city":"Herxheim",
    "sg:phone":"+49 7276/919901",
    "sg:postcode":"76863",
    "sg:province":"Rheinland-Pfalz",
    "wof:name":"Idee Wohnbau Gmbh",
    "wof:placetype":"venue"
},
  "geometry": {"coordinates":[8.214346,49.147198],"type":"Point"}
}