{
  "type": "Feature",
  "properties": {
    "iso:country":"DE",
    "sg:address":"Bergstr. 1",
    "sg:city":"Freystadt",
    "sg:phone":"+49 9179/94244",
    "sg:postcode":"92342",
    "sg:province":"Bayern",
    "wof:name":"Xaver Brandl Gmbh",
    "wof:placetype":"venue"
},
  "geometry": {"coordinates":[11.331025,49.239681],"type":"Point"}
}