{
  "type": "Feature",
  "properties": {
    "iso:country":"DE",
    "sg:address":"Brunnenstr.35a",
    "sg:city":"Singen",
    "sg:phone":"+49 7731/51449",
    "sg:postcode":"78224",
    "sg:province":"Baden-W\u00fcrttemberg",
    "wof:name":"Chance Zum Erfolg.",
    "wof:placetype":"venue"
},
  "geometry": {"coordinates":[8.898495,47.737038],"type":"Point"}
}