{
  "type": "Feature",
  "properties": {
    "iso:country":"DE",
    "sg:address":"Oststr. 61",
    "sg:city":"Meerbusch",
    "sg:phone":"+49 2132/72858",
    "sg:postcode":"40667",
    "sg:province":"Nordrhein-Westfalen",
    "wof:name":"Heinrich Parlings",
    "wof:placetype":"venue"
},
  "geometry": {"coordinates":[6.7028150558,51.2445335388],"type":"Point"}
}