{
  "type": "Feature",
  "properties": {
    "iso:country":"DE",
    "sg:address":"Kellinghusenstr. 14",
    "sg:city":"Hamburg",
    "sg:postcode":"20249",
    "sg:province":"Hamburg",
    "wof:name":"Versus Vertrieb Jens-dieter Ahrens",
    "wof:placetype":"venue"
},
  "geometry": {"coordinates":[9.9924430847,53.5911331177],"type":"Point"}
}