{
  "type": "Feature",
  "properties": {
    "iso:country":"DE",
    "sg:address":"Sophienstr. 17",
    "sg:city":"W\u00fcrzburg",
    "sg:phone":"+49 931/885726",
    "sg:postcode":"97072",
    "sg:province":"Bayern",
    "wof:name":"Winfried Kohlhepp Bauschlosserei",
    "wof:placetype":"venue"
},
  "geometry": {"coordinates":[9.9386882782,49.7861175537],"type":"Point"}
}