{
  "type": "Feature",
  "properties": {
    "iso:country":"DE",
    "sg:address":"Am Vogelherd 8b",
    "sg:city":"Roding",
    "sg:phone":"+49 9469/460",
    "sg:postcode":"93426",
    "sg:province":"Bayern",
    "wof:name":"Hans-dieter Schlotter",
    "wof:placetype":"venue"
},
  "geometry": {"coordinates":[12.4959621429,49.2443580627],"type":"Point"}
}