{
  "type": "Feature",
  "properties": {
    "iso:country":"DE",
    "sg:address":"Stuttgarter Str. 38",
    "sg:city":"Walddorfh\u00e4slach",
    "sg:phone":"+49 7127/31005",
    "sg:postcode":"72141",
    "sg:province":"Baden-W\u00fcrttemberg",
    "wof:name":"Schneider Gmbh",
    "wof:placetype":"venue"
},
  "geometry": {"coordinates":[9.1848478317,48.5862541199],"type":"Point"}
}