{
  "type": "Feature",
  "properties": {
    "iso:country":"DE",
    "sg:address":"Hauptstr. 65",
    "sg:city":"Bammental",
    "sg:phone":"+49 6223/5607",
    "sg:postcode":"69245",
    "sg:province":"Baden-W\u00fcrttemberg",
    "wof:name":"Sch\u00fctzenhof",
    "wof:placetype":"venue"
},
  "geometry": {"coordinates":[8.7768220901,49.3561401367],"type":"Point"}
}