{
  "type": "Feature",
  "properties": {
    "iso:country":"DE",
    "sg:address":"Rothenburger Str. 165",
    "sg:city":"N\u00fcrnberg",
    "sg:phone":"+49 911/612870",
    "sg:postcode":"90439",
    "sg:province":"Bayern",
    "wof:name":"Gustav Flachenecker",
    "wof:placetype":"venue"
},
  "geometry": {"coordinates":[11.0484666824,49.4420852661],"type":"Point"}
}