{
  "type": "Feature",
  "properties": {
    "iso:country":"DE",
    "sg:address":"Siegener Str. 99",
    "sg:city":"Wenden",
    "sg:phone":"+49 2762/6354",
    "sg:postcode":"57482",
    "sg:province":"Nordrhein-Westfalen",
    "wof:name":"Annette Wurm",
    "wof:placetype":"venue"
},
  "geometry": {"coordinates":[7.9017529488,50.9354171753],"type":"Point"}
}