{
  "type": "Feature",
  "properties": {
    "iso:country":"DE",
    "sg:address":"Sielower Str. 55",
    "sg:city":"Cottbus",
    "sg:phone":"+49 355/701118",
    "sg:postcode":"03044",
    "sg:province":"Brandenburg",
    "wof:name":"Restaurante Pizzeria Italia",
    "wof:placetype":"venue"
},
  "geometry": {"coordinates":[14.3323011398,51.7657012939],"type":"Point"}
}