{
  "type": "Feature",
  "properties": {
    "iso:country":"DE",
    "sg:address":"F\u00fcrstenrieder Str. 44",
    "sg:city":"M\u00fcnchen",
    "sg:phone":"+49 89/54674111",
    "sg:postcode":"80686",
    "sg:province":"Bayern",
    "wof:name":"Buchhandlung Siegfried Hacker Inh. Ulrich Schiefer",
    "wof:placetype":"venue"
},
  "geometry": {"coordinates":[11.502743721,48.1375579834],"type":"Point"}
}