{
  "type": "Feature",
  "properties": {
    "iso:country":"DE",
    "sg:address":"Am Marienberg 65",
    "sg:city":"Strausberg",
    "sg:phone":"+49 3341/421943",
    "sg:postcode":"15344",
    "sg:province":"Brandenburg",
    "wof:name":"Sanit\u00e4tshaus Seeger Inh. Andre Peste",
    "wof:placetype":"venue"
},
  "geometry": {"coordinates":[13.8665914536,52.5537567139],"type":"Point"}
}