{
  "type": "Feature",
  "properties": {
    "iso:country":"DE",
    "sg:address":"Wellesbach 2",
    "sg:city":"Wallenfels",
    "sg:phone":"+49 9262/286",
    "sg:postcode":"96346",
    "sg:province":"Bayern",
    "wof:name":"R. Und J. Ring Forsthaus",
    "wof:placetype":"venue"
},
  "geometry": {"coordinates":[11.5183763504,50.2777137756],"type":"Point"}
}