{
  "type": "Feature",
  "properties": {
    "iso:country":"DE",
    "sg:address":"Lembergstr. 3",
    "sg:city":"Gosheim",
    "sg:phone":"+49 4974/267925",
    "sg:postcode":"78559",
    "sg:province":"Baden-W\u00fcrttemberg",
    "wof:name":"Volksbank Spaichingen Eg",
    "wof:placetype":"venue"
},
  "geometry": {"coordinates":[8.752596,48.135681],"type":"Point"}
}