{
  "type": "Feature",
  "properties": {
    "iso:country":"DE",
    "sg:address":"Bahnhofstr. 92",
    "sg:city":"Biesenthal",
    "sg:postcode":"16359",
    "sg:province":"Brandenburg",
    "wof:name":"Drogerie",
    "wof:placetype":"venue"
},
  "geometry": {"coordinates":[13.668606,52.75687],"type":"Point"}
}