{
  "type": "Feature",
  "properties": {
    "iso:country":"DE",
    "sg:address":"Jahnstr. 92",
    "sg:city":"D\u00fcsseldorf",
    "sg:phone":"+49 211/934040",
    "sg:postcode":"40215",
    "sg:province":"Nordrhein-Westfalen",
    "wof:name":"Friedrich Jacobs Gmbh & Co.",
    "wof:placetype":"venue"
},
  "geometry": {"coordinates":[6.780912,51.211964],"type":"Point"}
}