{
  "type": "Feature",
  "properties": {
    "iso:country":"DE",
    "sg:address":"Windausstr. 39",
    "sg:city":"Braunschweig",
    "sg:phone":"+49 531/513635",
    "sg:postcode":"38116",
    "sg:province":"Niedersachsen",
    "wof:name":"Prof. Dr. W. Clau\u00dfnitzer Ingenieur",
    "wof:placetype":"venue"
},
  "geometry": {"coordinates":[10.461689949,52.290019989],"type":"Point"}
}