{
  "type": "Feature",
  "properties": {
    "iso:country":"DE",
    "sg:address":"Kr\u00f6pelweg 2",
    "sg:city":"Wangerland",
    "sg:phone":"+49 4461/2927",
    "sg:postcode":"26434",
    "sg:province":"Niedersachsen",
    "wof:name":"Hans Freese",
    "wof:placetype":"venue"
},
  "geometry": {"coordinates":[7.95743,53.609539],"type":"Point"}
}