{
  "type": "Feature",
  "properties": {
    "iso:country":"DE",
    "sg:address":"Lessingplatz 9",
    "sg:city":"Lauta",
    "sg:phone":"+49 35722/3680",
    "sg:postcode":"02991",
    "sg:province":"Sachsen",
    "wof:name":"M\u00f6bel-kasper E. Kfm.",
    "wof:placetype":"venue"
},
  "geometry": {"coordinates":[14.1046380997,51.4483070374],"type":"Point"}
}