{
  "type": "Feature",
  "properties": {
    "iso:country":"DE",
    "sg:address":"Breedenweg 2",
    "sg:city":"Hamburg",
    "sg:phone":"+49 40/7132150",
    "sg:postcode":"22117",
    "sg:province":"Hamburg",
    "wof:name":"J\u00fcrgen Feil Elektro Installation Gmbh",
    "wof:placetype":"venue"
},
  "geometry": {"coordinates":[10.141074,53.543987],"type":"Point"}
}