{
  "type": "Feature",
  "properties": {
    "iso:country":"DE",
    "sg:address":"Wedeler Landstr 16",
    "sg:city":"Hamburg",
    "sg:phone":"+49 40/81960634",
    "sg:postcode":"22559",
    "sg:province":"Hamburg",
    "wof:name":"Stapelfeldt Electronic Gmbh",
    "wof:placetype":"venue"
},
  "geometry": {"coordinates":[9.759739,53.581661],"type":"Point"}
}