{
  "type": "Feature",
  "properties": {
    "iso:country":"DE",
    "sg:address":"Mohlenhofstr. 8",
    "sg:city":"Hamburg",
    "sg:phone":"+49 40/330687",
    "sg:postcode":"20095",
    "sg:province":"Hamburg",
    "wof:name":"Gebr. Haupt",
    "wof:placetype":"venue"
},
  "geometry": {"coordinates":[10.001271,53.549431],"type":"Point"}
}