{
  "type": "Feature",
  "properties": {
    "iso:country":"DE",
    "sg:address":"Metzinger Str. 20",
    "sg:city":"Kohlberg",
    "sg:phone":"+49 7025/5215",
    "sg:postcode":"72664",
    "sg:province":"Baden-W\u00fcrttemberg",
    "wof:name":"A. Greiner",
    "wof:placetype":"venue"
},
  "geometry": {"coordinates":[9.3331680298,48.5595550537],"type":"Point"}
}