{
  "type": "Feature",
  "properties": {
    "iso:country":"DE",
    "sg:address":"Rudolf-Diesel-Str. 8",
    "sg:city":"Illertissen",
    "sg:phone":"+49 7303/1790",
    "sg:postcode":"89257",
    "sg:province":"Bayern",
    "wof:name":"Lanwehr Gmbh",
    "wof:placetype":"venue"
},
  "geometry": {"coordinates":[10.0962400436,48.2298164368],"type":"Point"}
}