{
  "type": "Feature",
  "properties": {
    "iso:country":"DE",
    "sg:address":"Uterm\u00f6hlestr. 20",
    "sg:city":"Hildesheim",
    "sg:postcode":"31135",
    "sg:province":"Niedersachsen",
    "wof:name":"Clean House Gmbh",
    "wof:placetype":"venue"
},
  "geometry": {"coordinates":[9.9903173447,52.1676483154],"type":"Point"}
}