{
  "type": "Feature",
  "properties": {
    "iso:country":"DE",
    "sg:address":"W\u00fcrselener Str. 3",
    "sg:city":"K\u00f6ln",
    "sg:phone":"+49 221/541886",
    "sg:postcode":"50933",
    "sg:province":"Nordrhein-Westfalen",
    "wof:name":"N. Meyer Architekt",
    "wof:placetype":"venue"
},
  "geometry": {"coordinates":[6.901207,50.940697],"type":"Point"}
}