{
  "type": "Feature",
  "properties": {
    "iso:country":"DE",
    "sg:address":"Pr\u00fcfeninger Str. 35",
    "sg:city":"Regensburg",
    "sg:phone":"+49 941/297270",
    "sg:postcode":"93049",
    "sg:province":"Bayern",
    "wof:name":"Alfons Eisenreich Steuerberater",
    "wof:placetype":"venue"
},
  "geometry": {"coordinates":[12.0775718689,49.0171203613],"type":"Point"}
}