{
  "type": "Feature",
  "properties": {
    "iso:country":"DE",
    "sg:address":"Schellingstr. 9",
    "sg:city":"Wilhelmshaven",
    "sg:phone":"+49 4421/304171",
    "sg:postcode":"26384",
    "sg:province":"Niedersachsen",
    "wof:name":"Gerhard Lemke",
    "wof:placetype":"venue"
},
  "geometry": {"coordinates":[8.1295318604,53.5341377258],"type":"Point"}
}