{
  "type": "Feature",
  "properties": {
    "iso:country":"DE",
    "sg:address":"Hauptstr. 149",
    "sg:city":"Adelheidsdorf",
    "sg:phone":"+49 5085/347",
    "sg:postcode":"29352",
    "sg:province":"Niedersachsen",
    "wof:name":"Hans-j\u00fcrgen Boldt",
    "wof:placetype":"venue"
},
  "geometry": {"coordinates":[10.04014,52.55352],"type":"Point"}
}