{
  "type": "Feature",
  "properties": {
    "iso:country":"DE",
    "sg:address":"Br\u00f6nnerstr. 17b",
    "sg:city":"Frankfurt",
    "sg:phone":"+49 69/2193570",
    "sg:postcode":"60313",
    "sg:province":"Hessen",
    "wof:name":"I.t.a.s. Impianti Termotecnici Applicazioni Speciali S.p.a.",
    "wof:placetype":"venue"
},
  "geometry": {"coordinates":[8.6830215454,50.1162796021],"type":"Point"}
}