{
  "type": "Feature",
  "properties": {
    "iso:country":"DE",
    "sg:address":"Dietr-Bonhoeffer-Str 12",
    "sg:city":"Rheine",
    "sg:postcode":"48429",
    "sg:province":"Nordrhein-Westfalen",
    "wof:name":"B\u00f6nninghoff Gmbh",
    "wof:placetype":"venue"
},
  "geometry": {"coordinates":[7.44171381,52.3000488281],"type":"Point"}
}