{
  "type": "Feature",
  "properties": {
    "iso:country":"DE",
    "sg:address":"Bronnwiesenstr. 9",
    "sg:city":"Berglen",
    "sg:phone":"+49 7195/74596",
    "sg:postcode":"73663",
    "sg:province":"Baden-W\u00fcrttemberg",
    "wof:name":"B. Stemmler Heilpraktiker",
    "wof:placetype":"venue"
},
  "geometry": {"coordinates":[9.4688329697,48.8726959229],"type":"Point"}
}