{
  "type": "Feature",
  "properties": {
    "iso:country":"DE",
    "sg:address":"Walliser Str. 76",
    "sg:city":"Bremen",
    "sg:phone":"+49 421/422338",
    "sg:postcode":"28325",
    "sg:province":"Bremen",
    "wof:name":"Ewald U. K\u00e4the St\u00e4ubner Textilien",
    "wof:placetype":"venue"
},
  "geometry": {"coordinates":[8.951816,53.068317],"type":"Point"}
}