{
  "type": "Feature",
  "properties": {
    "iso:country":"DE",
    "sg:address":"Hermann-L\u00f6ns-Weg 4",
    "sg:city":"Bad Orb",
    "sg:phone":"+49 6052/4520",
    "sg:postcode":"63619",
    "sg:province":"Hessen",
    "wof:name":"Herbert Reinhard",
    "wof:placetype":"venue"
},
  "geometry": {"coordinates":[9.3550882339,50.2284507751],"type":"Point"}
}