{
  "type": "Feature",
  "properties": {
    "iso:country":"DE",
    "sg:address":"Weseler Str. 34",
    "sg:city":"Duisburg",
    "sg:phone":"+49 203/400205",
    "sg:postcode":"47169",
    "sg:province":"Nordrhein-Westfalen",
    "wof:name":"Grillstube Ilse Arndt",
    "wof:placetype":"venue"
},
  "geometry": {"coordinates":[6.7565522194,51.5026321411],"type":"Point"}
}