{
  "type": "Feature",
  "properties": {
    "iso:country":"DE",
    "sg:address":"Am Dammacker 27",
    "sg:city":"Bremen",
    "sg:phone":"+49 421/555400",
    "sg:postcode":"28201",
    "sg:province":"Bremen",
    "wof:name":"Werder Transport Kg",
    "wof:placetype":"venue"
},
  "geometry": {"coordinates":[8.8150434494,53.058795929],"type":"Point"}
}