{
  "type": "Feature",
  "properties": {
    "iso:country":"DE",
    "sg:address":"Wiesendamm 22 a",
    "sg:city":"Hamburg",
    "sg:postcode":"22305",
    "sg:province":"Hamburg",
    "wof:name":"Adispa Verlagsgesellschaft Mbh",
    "wof:placetype":"venue"
},
  "geometry": {"coordinates":[10.0395336151,53.5875587463],"type":"Point"}
}