{
  "type": "Feature",
  "properties": {
    "iso:country":"DE",
    "sg:address":"Sonnentaustr. 21",
    "sg:city":"Potsdam",
    "sg:phone":"+49 331/860785",
    "sg:postcode":"14478",
    "sg:province":"Brandenburg",
    "wof:name":"Matthias Richter Anlageberater",
    "wof:placetype":"venue"
},
  "geometry": {"coordinates":[13.0879306793,52.3636360168],"type":"Point"}
}