{
  "type": "Feature",
  "properties": {
    "iso:country":"DE",
    "sg:address":"Broner Platz 2",
    "sg:city":"Weingarten",
    "sg:phone":"+49 751/47264",
    "sg:postcode":"88250",
    "sg:province":"Baden-W\u00fcrttemberg",
    "wof:name":"Stern-apotheke",
    "wof:placetype":"venue"
},
  "geometry": {"coordinates":[9.642452,47.807632],"type":"Point"}
}