{
  "type": "Feature",
  "properties": {
    "iso:country":"DE",
    "sg:address":"Damenpfad 14",
    "sg:city":"Wangerooge",
    "sg:phone":"+49 4469/340",
    "sg:postcode":"26486",
    "sg:province":"Niedersachsen",
    "wof:name":"Ingeborg Bruncken Hebamme",
    "wof:placetype":"venue"
},
  "geometry": {"coordinates":[7.901972,53.790131],"type":"Point"}
}