{
  "type": "Feature",
  "properties": {
    "iso:country":"DE",
    "sg:address":"Albstr. 80",
    "sg:city":"Stuttgart",
    "sg:postcode":"70597",
    "sg:province":"Baden-W\u00fcrttemberg",
    "wof:name":"Gemeinschaft Der Freunde Des Wilhelms-gymnasiums",
    "wof:placetype":"venue"
},
  "geometry": {"coordinates":[9.1656227112,48.7419166565],"type":"Point"}
}