{
  "type": "Feature",
  "properties": {
    "iso:country":"DE",
    "sg:address":"Hamburger Str. 5",
    "sg:city":"Berge",
    "sg:phone":"+49 3321/47006",
    "sg:postcode":"14641",
    "sg:province":"Brandenburg",
    "wof:name":"Christa Starke",
    "wof:placetype":"venue"
},
  "geometry": {"coordinates":[12.8012247086,52.6200065613],"type":"Point"}
}