{
  "type": "Feature",
  "properties": {
    "iso:country":"DE",
    "sg:address":"M\u00fchlenweg 8",
    "sg:city":"Aurich",
    "sg:phone":"+49 4941/65080",
    "sg:postcode":"26603",
    "sg:province":"Niedersachsen",
    "wof:name":"Helmut Redmers Heissmangel",
    "wof:placetype":"venue"
},
  "geometry": {"coordinates":[7.495677948,53.4663467407],"type":"Point"}
}