{
  "type": "Feature",
  "properties": {
    "iso:country":"DE",
    "sg:address":"Mockauer Str. 99",
    "sg:city":"Leipzig",
    "sg:phone":"+49 341/6021780",
    "sg:postcode":"04357",
    "sg:province":"Sachsen",
    "wof:name":"E. Kunath",
    "wof:placetype":"venue"
},
  "geometry": {"coordinates":[12.4096193314,51.3722114563],"type":"Point"}
}