{
  "type": "Feature",
  "properties": {
    "iso:country":"DE",
    "sg:address":"Hornstr. 23",
    "sg:city":"Berlin",
    "sg:phone":"+49 30/2158056",
    "sg:postcode":"10963",
    "sg:province":"Berlin",
    "wof:name":"Gastst\u00e4tte Blumberg",
    "wof:placetype":"venue"
},
  "geometry": {"coordinates":[13.3827419281,52.4937553406],"type":"Point"}
}