{
  "type": "Feature",
  "properties": {
    "iso:country":"DE",
    "sg:address":"Glattalstr. 23",
    "sg:city":"Sulz",
    "sg:phone":"+49 7454/3044",
    "sg:postcode":"72172",
    "sg:province":"Baden-W\u00fcrttemberg",
    "wof:name":"Ev. Pfarramt Hopfau",
    "wof:placetype":"venue"
},
  "geometry": {"coordinates":[8.5769844055,48.3720245361],"type":"Point"}
}