{
  "type": "Feature",
  "properties": {
    "iso:country":"DE",
    "sg:address":"Kimbacher Str. 8",
    "sg:city":"Michelstadt",
    "sg:phone":"+49 6066/216",
    "sg:postcode":"64720",
    "sg:province":"Hessen",
    "wof:name":"Raymund Fabry Architekt",
    "wof:placetype":"venue"
},
  "geometry": {"coordinates":[9.090935,49.713852],"type":"Point"}
}