{
  "type": "Feature",
  "properties": {
    "iso:country":"DE",
    "sg:address":"In den K\u00e4mpen 13",
    "sg:city":"Willingen",
    "sg:phone":"+49 5632/6865",
    "sg:postcode":"34508",
    "sg:province":"Hessen",
    "wof:name":"Snowmakers + Seilbahntechnik Peter Vekens",
    "wof:placetype":"venue"
},
  "geometry": {"coordinates":[8.6039199829,51.295135498],"type":"Point"}
}