{
  "type": "Feature",
  "properties": {
    "iso:country":"DE",
    "sg:address":"Paul-Robeson-Str.33",
    "sg:city":"Berlin",
    "sg:phone":"+49 30/50159515",
    "sg:postcode":"10439",
    "sg:province":"Berlin",
    "wof:name":"Mediatel-berlin",
    "wof:placetype":"venue"
},
  "geometry": {"coordinates":[13.406644,52.552593],"type":"Point"}
}