{
  "type": "Feature",
  "properties": {
    "iso:country":"DE",
    "sg:address":"Ulmer Hof",
    "sg:city":"W\u00fcrzburg",
    "sg:phone":"+49 931/53621",
    "sg:postcode":"97070",
    "sg:province":"Bayern",
    "wof:name":"B. Ritter",
    "wof:placetype":"venue"
},
  "geometry": {"coordinates":[9.9289302826,49.795955658],"type":"Point"}
}