{
  "type": "Feature",
  "properties": {
    "iso:country":"DE",
    "sg:address":"Klammstr. 31",
    "sg:city":"Garmisch-Partenkirchen",
    "sg:phone":"+49 8821/58066",
    "sg:postcode":"82467",
    "sg:province":"Bayern",
    "wof:name":"Hotel Garni Brunnthaler",
    "wof:placetype":"venue"
},
  "geometry": {"coordinates":[11.0921611786,47.4904975891],"type":"Point"}
}