{
  "type": "Feature",
  "properties": {
    "iso:country":"DE",
    "sg:address":"Kopperpahler Allee 26",
    "sg:city":"Kronshagen",
    "sg:phone":"+49 431/589161",
    "sg:postcode":"24119",
    "sg:province":"Schleswig-Holstein",
    "wof:name":"O. Und R. Liedl",
    "wof:placetype":"venue"
},
  "geometry": {"coordinates":[10.086315,54.334381],"type":"Point"}
}