{
  "type": "Feature",
  "properties": {
    "iso:country":"DE",
    "sg:address":"Bohlstr. 6",
    "sg:city":"Kohlberg",
    "sg:phone":"+49 7025/2676",
    "sg:postcode":"72664",
    "sg:province":"Baden-W\u00fcrttemberg",
    "wof:name":"Kurt Geiger",
    "wof:placetype":"venue"
},
  "geometry": {"coordinates":[9.3393745422,48.5586624146],"type":"Point"}
}