{
  "type": "Feature",
  "properties": {
    "iso:country":"DE",
    "sg:address":"Alte Landstr. 7",
    "sg:city":"Erbach",
    "sg:phone":"+49 7305/7555",
    "sg:postcode":"89155",
    "sg:province":"Baden-W\u00fcrttemberg",
    "wof:name":"Schreinerei T. Hollstegge Gmbh",
    "wof:placetype":"venue"
},
  "geometry": {"coordinates":[9.9069747925,48.3006248474],"type":"Point"}
}