{
  "type": "Feature",
  "properties": {
    "iso:country":"DE",
    "sg:address":"Krehtalweg 10",
    "sg:city":"Schwangau",
    "sg:phone":"+49 8362/987044",
    "sg:postcode":"87645",
    "sg:province":"Bayern",
    "wof:name":"Franz Mair",
    "wof:placetype":"venue"
},
  "geometry": {"coordinates":[10.7388811111,47.5816688538],"type":"Point"}
}