{
  "type": "Feature",
  "properties": {
    "iso:country":"DE",
    "sg:address":"Landgrabenstr. 121",
    "sg:city":"N\u00fcrnberg",
    "sg:phone":"+49 911/443454",
    "sg:postcode":"90459",
    "sg:province":"Bayern",
    "wof:name":"Nikar Gro\u00df- Und Einzelhandel F\u00fcr Schulbedarf Gmbh",
    "wof:placetype":"venue"
},
  "geometry": {"coordinates":[11.076986,49.439903],"type":"Point"}
}