{
  "type": "Feature",
  "properties": {
    "iso:country":"DE",
    "sg:address":"Zeppelinstr.43",
    "sg:city":"Bodelshausen",
    "sg:phone":"+49 7471",
    "sg:postcode":"72411",
    "sg:province":"Baden-W\u00fcrttemberg",
    "wof:name":"Www.pemak.de Der Onlineshop",
    "wof:placetype":"venue"
},
  "geometry": {"coordinates":[8.981424,48.38385],"type":"Point"}
}