{
  "type": "Feature",
  "properties": {
    "iso:country":"DE",
    "sg:address":"Dietrich-Bonhoeffer-Str. 88",
    "sg:city":"Eckernf\u00f6rde",
    "sg:phone":"+49 4351/86867",
    "sg:postcode":"24340",
    "sg:province":"Schleswig-Holstein",
    "wof:name":"Horst Pudlas",
    "wof:placetype":"venue"
},
  "geometry": {"coordinates":[9.8412103653,54.485710144],"type":"Point"}
}