{
  "type": "Feature",
  "properties": {
    "iso:country":"DE",
    "sg:address":"Albrechtstra\u00dfe 10",
    "sg:city":"Berlin",
    "sg:phone":"+49 30",
    "sg:postcode":"10117",
    "sg:province":"Berlin",
    "wof:name":"Netzeitung - Die Schnellste Tageszeitung Im Web",
    "wof:placetype":"venue"
},
  "geometry": {"coordinates":[13.384662,52.521538],"type":"Point"}
}