{
  "type": "Feature",
  "properties": {
    "iso:country":"DE",
    "sg:address":"Scheerenberger Str. 100",
    "sg:city":"Osterode",
    "sg:phone":"+49 5522/74544",
    "sg:postcode":"37520",
    "sg:province":"Niedersachsen",
    "wof:name":"Kiefer-scheune",
    "wof:placetype":"venue"
},
  "geometry": {"coordinates":[10.30898,51.676579],"type":"Point"}
}