{
  "type": "Feature",
  "properties": {
    "iso:country":"DE",
    "sg:address":"Am Marktplatz 15",
    "sg:city":"K\u00f6nigswartha",
    "sg:phone":"+49 35931/20496",
    "sg:postcode":"02699",
    "sg:province":"Sachsen",
    "wof:name":"Helmut Schreiber",
    "wof:placetype":"venue"
},
  "geometry": {"coordinates":[14.326828,51.310734],"type":"Point"}
}