{
  "type": "Feature",
  "properties": {
    "iso:country":"DE",
    "sg:address":"88457",
    "sg:city":"Kirchdorf",
    "sg:postcode":"88457",
    "sg:province":"Baden-W\u00fcrttemberg",
    "wof:name":"Raiffeisenbank Kirchdorf A D Iller Eg",
    "wof:placetype":"venue"
},
  "geometry": {"coordinates":[10.12324,48.077789],"type":"Point"}
}