{
  "type": "Feature",
  "properties": {
    "iso:country":"DE",
    "sg:address":"Hauptstr. 22",
    "sg:city":"Bad Soden",
    "sg:phone":"+49 6196/28131",
    "sg:postcode":"65812",
    "sg:province":"Hessen",
    "wof:name":"Teresas Pilsstube",
    "wof:placetype":"venue"
},
  "geometry": {"coordinates":[8.4931097031,50.1567192078],"type":"Point"}
}