{
  "type": "Feature",
  "properties": {
    "iso:country":"DE",
    "sg:address":"B\u00f6cklinstr. 27",
    "sg:city":"Essen",
    "sg:phone":"+49 201/701678",
    "sg:postcode":"45147",
    "sg:province":"Nordrhein-Westfalen",
    "wof:name":"Stadt Essen Bezirksbibliothek Holsterhaus.",
    "wof:placetype":"venue"
},
  "geometry": {"coordinates":[6.988213,51.439617],"type":"Point"}
}