{
  "type": "Feature",
  "properties": {
    "iso:country":"DE",
    "sg:address":"Franz-Geiger-Str. 12",
    "sg:city":"Wolfratshausen",
    "sg:phone":"+49 8171/18525",
    "sg:postcode":"82515",
    "sg:province":"Bayern",
    "wof:name":"Hauptenbuchner Gmbh",
    "wof:placetype":"venue"
},
  "geometry": {"coordinates":[11.43196,47.918644],"type":"Point"}
}