{
  "type": "Feature",
  "properties": {
    "iso:country":"DE",
    "sg:address":"Am Katzenturm 3",
    "sg:city":"Oberwesel",
    "sg:phone":"+49 6744/281",
    "sg:postcode":"55430",
    "sg:province":"Rheinland-Pfalz",
    "wof:name":"Hubert Silbernagel Und Sohn Gmbh",
    "wof:placetype":"venue"
},
  "geometry": {"coordinates":[7.721927,50.111988],"type":"Point"}
}