{
  "type": "Feature",
  "properties": {
    "iso:country":"DE",
    "sg:address":"Weiherstr. 6",
    "sg:city":"Bernhardswald",
    "sg:phone":"+49 9407/444",
    "sg:postcode":"93170",
    "sg:province":"Bayern",
    "wof:name":"Dr. Marianne Wrobel Tier\u00e4rztin",
    "wof:placetype":"venue"
},
  "geometry": {"coordinates":[12.2458848953,49.0929946899],"type":"Point"}
}