{
  "type": "Feature",
  "properties": {
    "iso:country":"DE",
    "sg:address":"Schulstr. 7",
    "sg:city":"Burgen",
    "sg:phone":"+49 6534/18349",
    "sg:postcode":"54472",
    "sg:province":"Rheinland-Pfalz",
    "wof:name":"Norbert Licht-klemm",
    "wof:placetype":"venue"
},
  "geometry": {"coordinates":[6.9997830391,49.879283905],"type":"Point"}
}