{
  "type": "Feature",
  "properties": {
    "iso:country":"DE",
    "sg:address":"Olgastr. 12",
    "sg:city":"Heidenheim",
    "sg:postcode":"89518",
    "sg:province":"Baden-W\u00fcrttemberg",
    "wof:name":"Public Print Werbeverlag Und Reiseb\u00fcro Gmbh & Co. Kg",
    "wof:placetype":"venue"
},
  "geometry": {"coordinates":[10.1533613205,48.6789970398],"type":"Point"}
}