{
  "type": "Feature",
  "properties": {
    "iso:country":"DE",
    "sg:address":"Oranienstr. 38",
    "sg:city":"Burbach",
    "sg:phone":"+49 2736/2213",
    "sg:postcode":"57299",
    "sg:province":"Nordrhein-Westfalen",
    "wof:name":"A. Theis",
    "wof:placetype":"venue"
},
  "geometry": {"coordinates":[8.105340004,50.7220954895],"type":"Point"}
}