{
  "type": "Feature",
  "properties": {
    "iso:country":"DE",
    "sg:address":"Deutschhofstr. 6",
    "sg:city":"Heilbronn",
    "sg:phone":"+49 7131/562295",
    "sg:postcode":"74072",
    "sg:province":"Baden-W\u00fcrttemberg",
    "wof:name":"St\u00e4dtische Museen Heilbronn",
    "wof:placetype":"venue"
},
  "geometry": {"coordinates":[9.217389,49.140556],"type":"Point"}
}