{
  "type": "Feature",
  "properties": {
    "iso:country":"DE",
    "sg:address":"Drususallee 13",
    "sg:city":"Neuss",
    "sg:phone":"+49 2131/276405",
    "sg:postcode":"41460",
    "sg:province":"Nordrhein-Westfalen",
    "wof:name":"Jochen Usinger Architekt Und Innenarchitekt",
    "wof:placetype":"venue"
},
  "geometry": {"coordinates":[6.687139,51.197727],"type":"Point"}
}