{
  "type": "Feature",
  "properties": {
    "iso:country":"DE",
    "sg:address":"Westrup 44",
    "sg:city":"Stemwede",
    "sg:phone":"+49 5773/1897",
    "sg:postcode":"32351",
    "sg:province":"Nordrhein-Westfalen",
    "wof:name":"Sander K\u00fcchenkultur",
    "wof:placetype":"venue"
},
  "geometry": {"coordinates":[8.4333276749,52.4179229736],"type":"Point"}
}