{
  "type": "Feature",
  "properties": {
    "iso:country":"DE",
    "sg:address":"Am Industriegel\u00e4nde 8",
    "sg:city":"Brandenburg",
    "sg:phone":"+49 3381/72800",
    "sg:postcode":"14772",
    "sg:province":"Brandenburg",
    "wof:name":"Brandenburger Montage- Und Kranservice Gmbh",
    "wof:placetype":"venue"
},
  "geometry": {"coordinates":[12.548795,52.429024],"type":"Point"}
}