{
  "type": "Feature",
  "properties": {
    "iso:country":"DE",
    "sg:address":"Am Brink 1",
    "sg:city":"Undeloh",
    "sg:phone":"+49 4189/592",
    "sg:postcode":"21274",
    "sg:province":"Niedersachsen",
    "wof:name":"Nfs Nordheide Forst Service Gmbh",
    "wof:placetype":"venue"
},
  "geometry": {"coordinates":[9.9732704163,53.1956100464],"type":"Point"}
}