{
  "type": "Feature",
  "properties": {
    "iso:country":"DE",
    "sg:address":"Helle 5",
    "sg:city":"B\u00fcren",
    "sg:phone":"+49 2951/2573",
    "sg:postcode":"33142",
    "sg:province":"Nordrhein-Westfalen",
    "wof:name":"Heinrich Hardes",
    "wof:placetype":"venue"
},
  "geometry": {"coordinates":[8.5902757645,51.5839195251],"type":"Point"}
}