{
  "type": "Feature",
  "properties": {
    "iso:country":"DE",
    "sg:address":"Hauptstr. 47",
    "sg:city":"Otterberg",
    "sg:phone":"+49 6301/793414",
    "sg:postcode":"67697",
    "sg:province":"Rheinland-Pfalz",
    "wof:name":"Hauer",
    "wof:placetype":"venue"
},
  "geometry": {"coordinates":[7.772515,49.502193],"type":"Point"}
}