{
  "type": "Feature",
  "properties": {
    "iso:country":"DE",
    "sg:address":"An Bracht 24",
    "sg:city":"Siegbach",
    "sg:phone":"+49 2778/2968",
    "sg:postcode":"35768",
    "sg:province":"Hessen",
    "wof:name":"Erich Schulewski",
    "wof:placetype":"venue"
},
  "geometry": {"coordinates":[8.412332,50.738094],"type":"Point"}
}