{
  "type": "Feature",
  "properties": {
    "iso:country":"DE",
    "sg:address":"Weseler Str. 991",
    "sg:city":"M\u00fcnster",
    "sg:phone":"+49 2536/1078",
    "sg:postcode":"48163",
    "sg:province":"Nordrhein-Westfalen",
    "wof:name":"Paul Storp",
    "wof:placetype":"venue"
},
  "geometry": {"coordinates":[7.527381,51.92448],"type":"Point"}
}