{
  "type": "Feature",
  "properties": {
    "iso:country":"DE",
    "sg:address":"Walther-Rathenau-Str. 11",
    "sg:city":"Teltow",
    "sg:phone":"+49 3328/41334",
    "sg:postcode":"14513",
    "sg:province":"Brandenburg",
    "wof:name":"Peter Larsen",
    "wof:placetype":"venue"
},
  "geometry": {"coordinates":[13.2558870316,52.397769928],"type":"Point"}
}