{
  "type": "Feature",
  "properties": {
    "iso:country":"DE",
    "sg:address":"Schwabenstr. 9",
    "sg:city":"Marktheidenfeld",
    "sg:phone":"+49 9391/2316",
    "sg:postcode":"97828",
    "sg:province":"Bayern",
    "wof:name":"Siegfried Rausch",
    "wof:placetype":"venue"
},
  "geometry": {"coordinates":[9.603738,49.854679],"type":"Point"}
}