{
  "type": "Feature",
  "properties": {
    "iso:country":"DE",
    "sg:address":"Alte Bahnhofstr. 21",
    "sg:city":"Roding",
    "sg:postcode":"93426",
    "sg:province":"Bayern",
    "wof:name":"Ls Metallhandels Gmbh",
    "wof:placetype":"venue"
},
  "geometry": {"coordinates":[12.51032,49.203571],"type":"Point"}
}