{
  "type": "Feature",
  "properties": {
    "iso:country":"DE",
    "sg:address":"Lindenthaler Hauptstr. 42",
    "sg:city":"Leipzig",
    "sg:postcode":"04158",
    "sg:province":"Sachsen",
    "wof:name":"Ramona Weigel",
    "wof:placetype":"venue"
},
  "geometry": {"coordinates":[12.330479,51.39344],"type":"Point"}
}