{
  "type": "Feature",
  "properties": {
    "iso:country":"DE",
    "sg:address":"Horster Str. 123",
    "sg:city":"Hamm",
    "sg:phone":"+49 2381/71498",
    "sg:postcode":"59075",
    "sg:province":"Nordrhein-Westfalen",
    "wof:name":"Johannes Schulze Everding",
    "wof:placetype":"venue"
},
  "geometry": {"coordinates":[7.74115,51.699726],"type":"Point"}
}