{
  "type": "Feature",
  "properties": {
    "iso:country":"DE",
    "sg:address":"Ulrich-Hofmaier-Str. 1",
    "sg:city":"Augsburg",
    "sg:phone":"+49 821/573601",
    "sg:postcode":"86159",
    "sg:province":"Bayern",
    "wof:name":"Reinhold Wolff Steuerberater",
    "wof:placetype":"venue"
},
  "geometry": {"coordinates":[10.8847398758,48.355381012],"type":"Point"}
}