{
  "type": "Feature",
  "properties": {
    "iso:country":"DE",
    "sg:address":"Kellinghusenstr. 27",
    "sg:city":"Hamburg",
    "sg:phone":"+49 40/474198",
    "sg:postcode":"20249",
    "sg:province":"Hamburg",
    "wof:name":"Michael Galweit",
    "wof:placetype":"venue"
},
  "geometry": {"coordinates":[9.992559433,53.5922279358],"type":"Point"}
}