{
  "type": "Feature",
  "properties": {
    "iso:country":"DE",
    "sg:address":"Zimmermannstr. 8",
    "sg:city":"Zwickau",
    "sg:phone":"+49 375/572114",
    "sg:postcode":"08060",
    "sg:province":"Sachsen",
    "wof:name":"J. Wei\u00df",
    "wof:placetype":"venue"
},
  "geometry": {"coordinates":[12.4602022171,50.7195739746],"type":"Point"}
}