{
  "type": "Feature",
  "properties": {
    "iso:country":"DE",
    "sg:address":"Kurallee 2",
    "sg:city":"Nidda",
    "sg:phone":"+49 6043/4369",
    "sg:postcode":"63667",
    "sg:province":"Hessen",
    "wof:name":"G. Wiehl",
    "wof:placetype":"venue"
},
  "geometry": {"coordinates":[8.977145,50.412266],"type":"Point"}
}