{
  "type": "Feature",
  "properties": {
    "iso:country":"DE",
    "sg:address":"Leipziger Ring 138",
    "sg:city":"Rodgau",
    "sg:phone":"+49 6106/74260",
    "sg:postcode":"63110",
    "sg:province":"Hessen",
    "wof:name":"Michael Fischer",
    "wof:placetype":"venue"
},
  "geometry": {"coordinates":[8.875264,50.003963],"type":"Point"}
}