{
  "type": "Feature",
  "properties": {
    "iso:country":"DE",
    "sg:address":"Rudolf-Steiner-Str. 2",
    "sg:city":"Braunschweig",
    "sg:phone":"+49 531/286030",
    "sg:postcode":"38120",
    "sg:province":"Niedersachsen",
    "wof:name":"Freundeskreis F\u00fcr Waldorf- P\u00e4dagogik In Braun-",
    "wof:placetype":"venue"
},
  "geometry": {"coordinates":[10.493016243,52.2500457764],"type":"Point"}
}