{
  "type": "Feature",
  "properties": {
    "iso:country":"DE",
    "sg:address":"Im Appensee 10",
    "sg:city":"Darmstadt",
    "sg:phone":"+49 6150/6286",
    "sg:postcode":"64291",
    "sg:province":"Hessen",
    "wof:name":"Werner Damm",
    "wof:placetype":"venue"
},
  "geometry": {"coordinates":[8.6500864029,49.9331474304],"type":"Point"}
}