{
  "type": "Feature",
  "properties": {
    "iso:country":"DE",
    "sg:address":"Waldstr. 22",
    "sg:city":"Frankfurt",
    "sg:phone":"+49 69/6708873",
    "sg:postcode":"60528",
    "sg:province":"Hessen",
    "wof:name":"Sch\u00e4ffer & Weid",
    "wof:placetype":"venue"
},
  "geometry": {"coordinates":[8.650697,50.080898],"type":"Point"}
}