{
  "type": "Feature",
  "properties": {
    "iso:country":"DE",
    "sg:address":"Rheinstr. 27",
    "sg:city":"Frankfurt",
    "sg:postcode":"60325",
    "sg:province":"Hessen",
    "wof:name":"M & A Dentaltechnik Gmbh",
    "wof:placetype":"venue"
},
  "geometry": {"coordinates":[8.658129,50.111958],"type":"Point"}
}