{
  "type": "Feature",
  "properties": {
    "iso:country":"DE",
    "sg:address":"Birkenweg 4",
    "sg:city":"Sch\u00f6nberg",
    "sg:phone":"+49 8554/941401",
    "sg:postcode":"94513",
    "sg:province":"Bayern",
    "wof:name":"Christian Lustinger Versicherungsmakler Concept",
    "wof:placetype":"venue"
},
  "geometry": {"coordinates":[13.3618574142,48.8178825378],"type":"Point"}
}