{
  "type": "Feature",
  "properties": {
    "iso:country":"DE",
    "sg:address":"Wasserburg 37",
    "sg:city":"Olfen",
    "sg:phone":"+49 2595/5169",
    "sg:postcode":"59399",
    "sg:province":"Nordrhein-Westfalen",
    "wof:name":"Harry Fr\u00f6hlich",
    "wof:placetype":"venue"
},
  "geometry": {"coordinates":[7.378246,51.703773],"type":"Point"}
}