{
  "type": "Feature",
  "properties": {
    "iso:country":"DE",
    "sg:address":"Feldstr. 30",
    "sg:city":"D\u00fcsseldorf",
    "sg:phone":"+49 211/4930816",
    "sg:postcode":"40479",
    "sg:province":"Nordrhein-Westfalen",
    "wof:name":"C. B\u00fcsen",
    "wof:placetype":"venue"
},
  "geometry": {"coordinates":[6.7815651894,51.2333488464],"type":"Point"}
}