{
  "type": "Feature",
  "properties": {
    "iso:country":"DE",
    "sg:address":"August-Bebel-Str. 9",
    "sg:city":"Hainichen",
    "sg:phone":"+49 37207/3774",
    "sg:postcode":"09661",
    "sg:province":"Sachsen",
    "wof:name":"Hartmut Winkler",
    "wof:placetype":"venue"
},
  "geometry": {"coordinates":[13.119605,50.964333],"type":"Point"}
}