{
  "type": "Feature",
  "properties": {
    "iso:country":"DE",
    "sg:address":"Sandwigstr. 17",
    "sg:city":"Gl\u00fccksburg",
    "sg:phone":"+49 4631/2489",
    "sg:postcode":"24960",
    "sg:province":"Schleswig-Holstein",
    "wof:name":"Hotel R. Reich",
    "wof:placetype":"venue"
},
  "geometry": {"coordinates":[9.5361413956,54.8424339294],"type":"Point"}
}