{
  "type": "Feature",
  "properties": {
    "iso:country":"DE",
    "sg:address":"Am Odenberg 21",
    "sg:city":"Niederkirchen",
    "sg:phone":"+49 6363/993026",
    "sg:postcode":"67700",
    "sg:province":"Rheinland-Pfalz",
    "wof:name":"R. Dolibois",
    "wof:placetype":"venue"
},
  "geometry": {"coordinates":[7.6973438263,49.5772323608],"type":"Point"}
}