{
  "type": "Feature",
  "properties": {
    "iso:country":"DE",
    "sg:address":"Poststr. 31",
    "sg:city":"Velbert",
    "sg:phone":"+49 2051/55718",
    "sg:postcode":"42549",
    "sg:province":"Nordrhein-Westfalen",
    "wof:name":"China-restaurant Yang Zhou",
    "wof:placetype":"venue"
},
  "geometry": {"coordinates":[7.0409460068,51.3394241333],"type":"Point"}
}