{
  "type": "Feature",
  "properties": {
    "iso:country":"DE",
    "sg:address":"Alte Landstr. 10",
    "sg:city":"Lauterach",
    "sg:postcode":"89584",
    "sg:province":"Baden-W\u00fcrttemberg",
    "wof:name":"Hermann Pfanner Getr\u00e4nke Ges.m.b.h.",
    "wof:placetype":"venue"
},
  "geometry": {"coordinates":[9.7267847061,48.2823867798],"type":"Point"}
}