{
  "type": "Feature",
  "properties": {
    "iso:country":"DE",
    "sg:address":"Wiesenstr. 15",
    "sg:city":"Bad Bentheim",
    "sg:phone":"+49 5922/2662",
    "sg:postcode":"48455",
    "sg:province":"Niedersachsen",
    "wof:name":"Gefl\u00fcgelzuchtverein Bentheim Lambert Timmer",
    "wof:placetype":"venue"
},
  "geometry": {"coordinates":[7.1482319832,52.3066978455],"type":"Point"}
}