{
  "type": "Feature",
  "properties": {
    "iso:country":"DE",
    "sg:address":"Am Farrnbach 6-8",
    "sg:city":"Cadolzburg",
    "sg:postcode":"90556",
    "sg:province":"Bayern",
    "wof:name":"Los-de Gmbh",
    "wof:placetype":"venue"
},
  "geometry": {"coordinates":[10.8661766052,49.4763641357],"type":"Point"}
}