{
  "type": "Feature",
  "properties": {
    "iso:country":"DE",
    "sg:address":"Altzirkendorf",
    "sg:city":"Kirchenthumbach",
    "sg:phone":"+49 9647/457",
    "sg:postcode":"91281",
    "sg:province":"Bayern",
    "wof:name":"Gastst\u00e4tte Oswald Kohl",
    "wof:placetype":"venue"
},
  "geometry": {"coordinates":[11.6702508926,49.7361602783],"type":"Point"}
}