{
  "type": "Feature",
  "properties": {
    "iso:country":"DE",
    "sg:address":"Ro\u00dfstr. 13",
    "sg:city":"D\u00fcsseldorf",
    "sg:phone":"+49 211/4846150",
    "sg:postcode":"40476",
    "sg:province":"Nordrhein-Westfalen",
    "wof:name":"Askor Industrievertretungen Gmbh",
    "wof:placetype":"venue"
},
  "geometry": {"coordinates":[6.7815308571,51.2431678772],"type":"Point"}
}