{
  "type": "Feature",
  "properties": {
    "iso:country":"DE",
    "sg:address":"Lichterfelder Str. 24",
    "sg:city":"Blomberg",
    "sg:phone":"+49 5235/7368",
    "sg:postcode":"32825",
    "sg:province":"Nordrhein-Westfalen",
    "wof:name":"Wedeking Gmbh",
    "wof:placetype":"venue"
},
  "geometry": {"coordinates":[9.1091346741,51.9394836426],"type":"Point"}
}