{
  "type": "Feature",
  "properties": {
    "iso:country":"DE",
    "sg:address":"Am Pappelgraben 41",
    "sg:city":"Osnabr\u00fcck",
    "sg:phone":"+49 541/89094",
    "sg:postcode":"49080",
    "sg:province":"Niedersachsen",
    "wof:name":"M. Radosavijevic",
    "wof:placetype":"venue"
},
  "geometry": {"coordinates":[8.0296049118,52.2657699585],"type":"Point"}
}