{
  "type": "Feature",
  "properties": {
    "iso:country":"DE",
    "sg:address":"Bahnhofstr. 38",
    "sg:city":"Lengerich",
    "sg:phone":"+49 5481/5051",
    "sg:postcode":"49525",
    "sg:province":"Nordrhein-Westfalen",
    "wof:name":"C.-g. David Rechtsanwalt",
    "wof:placetype":"venue"
},
  "geometry": {"coordinates":[7.8563342094,52.187286377],"type":"Point"}
}