{
  "type": "Feature",
  "properties": {
    "iso:country":"DE",
    "sg:address":"Lyhrener Dorfstr. 8",
    "sg:city":"Apelern",
    "sg:phone":"+49 5043/2345",
    "sg:postcode":"31552",
    "sg:province":"Niedersachsen",
    "wof:name":"Cc-holzhandels Gmbh",
    "wof:placetype":"venue"
},
  "geometry": {"coordinates":[9.314798,52.300659],"type":"Point"}
}