{
  "type": "Feature",
  "properties": {
    "iso:country":"DE",
    "sg:address":"M\u00f6rkenstra\u00dfe 8",
    "sg:city":"Hamburg",
    "sg:phone":"+49 40/3800292",
    "sg:postcode":"22767",
    "sg:province":"Hamburg",
    "wof:name":"G. K. H. Eismann Nautiquit\u00e4ten Und Geod\u00e4tische Instrumente",
    "wof:placetype":"venue"
},
  "geometry": {"coordinates":[9.9473848343,53.5494117737],"type":"Point"}
}