{
  "type": "Feature",
  "properties": {
    "iso:country":"DE",
    "sg:address":"Augsburger Str. 73",
    "sg:city":"Friedberg",
    "sg:phone":"+49 821/62715",
    "sg:postcode":"86316",
    "sg:province":"Bayern",
    "wof:name":"Ludwig Pest Versandgesch\u00e4ft",
    "wof:placetype":"venue"
},
  "geometry": {"coordinates":[10.95801,48.355576],"type":"Point"}
}