{
  "type": "Feature",
  "properties": {
    "iso:country":"DE",
    "sg:address":"H\u00e4gerstr. 283",
    "sg:city":"M\u00fcnster",
    "sg:phone":"+49 2533/1008",
    "sg:postcode":"48161",
    "sg:province":"Nordrhein-Westfalen",
    "wof:name":"R. Fehmer",
    "wof:placetype":"venue"
},
  "geometry": {"coordinates":[7.5566601753,52.0072097778],"type":"Point"}
}