{
  "type": "Feature",
  "properties": {
    "iso:country":"DE",
    "sg:address":"Hirtenweg 2",
    "sg:city":"Gallmersgarten",
    "sg:phone":"+49 9843/493",
    "sg:postcode":"91605",
    "sg:province":"Bayern",
    "wof:name":"Rudolf Ringler",
    "wof:placetype":"venue"
},
  "geometry": {"coordinates":[10.262154,49.451469],"type":"Point"}
}