{
  "type": "Feature",
  "properties": {
    "iso:country":"DE",
    "sg:address":"Hechtstr. 23",
    "sg:city":"Dresden",
    "sg:phone":"+49 351/8011722",
    "sg:postcode":"01097",
    "sg:province":"Sachsen",
    "wof:name":"Heiko-therm Dresden Gmbh",
    "wof:placetype":"venue"
},
  "geometry": {"coordinates":[13.7465791702,51.0740013123],"type":"Point"}
}