{
  "type": "Feature",
  "properties": {
    "iso:country":"DE",
    "sg:address":"Kronenstr. 30",
    "sg:city":"Solingen",
    "sg:phone":"+49 212/330774",
    "sg:postcode":"42697",
    "sg:province":"Nordrhein-Westfalen",
    "wof:name":"Rolf Bergmeister Betriebswirt",
    "wof:placetype":"venue"
},
  "geometry": {"coordinates":[7.0123372078,51.1628646851],"type":"Point"}
}