{
  "type": "Feature",
  "properties": {
    "iso:country":"DE",
    "sg:address":"Weststr. 32",
    "sg:city":"Bochum",
    "sg:phone":"+49 2327/82946",
    "sg:postcode":"44866",
    "sg:province":"Nordrhein-Westfalen",
    "wof:name":"Aps Advanced Personal Software Gmbh",
    "wof:placetype":"venue"
},
  "geometry": {"coordinates":[7.1302390099,51.4812889099],"type":"Point"}
}