{
  "type": "Feature",
  "properties": {
    "iso:country":"DE",
    "sg:address":"Am W\u00e4ldchen 12",
    "sg:city":"Essen",
    "sg:phone":"+49 201/54905",
    "sg:postcode":"45279",
    "sg:province":"Nordrhein-Westfalen",
    "wof:name":"Rudolph Stahlhandel Gmbh",
    "wof:placetype":"venue"
},
  "geometry": {"coordinates":[7.116274,51.438782],"type":"Point"}
}