{
  "type": "Feature",
  "properties": {
    "iso:country":"DE",
    "sg:address":"Amselweg 4",
    "sg:city":"Mantel",
    "sg:phone":"+49 9605/2725",
    "sg:postcode":"92708",
    "sg:province":"Bayern",
    "wof:name":"G\u00e4bl",
    "wof:placetype":"venue"
},
  "geometry": {"coordinates":[12.0498533249,49.6473083496],"type":"Point"}
}