{
  "type": "Feature",
  "properties": {
    "iso:country":"DE",
    "sg:address":"H\u00f6nningen 16",
    "sg:city":"Hellenthal",
    "sg:phone":"+49 2482/2176",
    "sg:postcode":"53940",
    "sg:province":"Nordrhein-Westfalen",
    "wof:name":"Robert Pelzer Rechtsanwalt",
    "wof:placetype":"venue"
},
  "geometry": {"coordinates":[6.4536190033,50.4815559387],"type":"Point"}
}