{
  "type": "Feature",
  "properties": {
    "iso:country":"DE",
    "sg:address":"Hauptstr. 32",
    "sg:city":"Elzach",
    "sg:phone":"+49 7682/235",
    "sg:postcode":"79215",
    "sg:province":"Baden-W\u00fcrttemberg",
    "wof:name":"Drogerie Richard Fischer",
    "wof:placetype":"venue"
},
  "geometry": {"coordinates":[8.071321,48.173611],"type":"Point"}
}