{
  "type": "Feature",
  "properties": {
    "iso:country":"DE",
    "sg:address":"Gottlieb-Daimler-Str. 12",
    "sg:city":"Kaltenkirchen",
    "sg:phone":"+49 4191/93770",
    "sg:postcode":"24568",
    "sg:province":"Schleswig-Holstein",
    "wof:name":"Carl Sch\u00f6nfeldts Buchdruckerei Kg",
    "wof:placetype":"venue"
},
  "geometry": {"coordinates":[9.966114,53.826305],"type":"Point"}
}