{
  "type": "Feature",
  "properties": {
    "iso:country":"DE",
    "sg:address":"Im Loffenkamp 2",
    "sg:city":"Springe",
    "sg:phone":"+49 5044/9700",
    "sg:postcode":"31832",
    "sg:province":"Niedersachsen",
    "wof:name":"Sabine Schneider",
    "wof:placetype":"venue"
},
  "geometry": {"coordinates":[9.6719169617,52.170917511],"type":"Point"}
}