{
  "type": "Feature",
  "properties": {
    "iso:country":"DE",
    "sg:address":"Am Spratzer 31",
    "sg:city":"H\u00f6chstadt",
    "sg:phone":"+49 9193/3589",
    "sg:postcode":"91315",
    "sg:province":"Bayern",
    "wof:name":"Max Heuschmid Heilpraktiker",
    "wof:placetype":"venue"
},
  "geometry": {"coordinates":[10.8080682755,49.713092804],"type":"Point"}
}