{
  "type": "Feature",
  "properties": {
    "iso:country":"DE",
    "sg:address":"Mohrenstr. 24",
    "sg:city":"Coburg",
    "sg:phone":"+49 9561/87260",
    "sg:postcode":"96450",
    "sg:province":"Bayern",
    "wof:name":"Dannecker Und Heil Notare",
    "wof:placetype":"venue"
},
  "geometry": {"coordinates":[10.9631795883,50.260799408],"type":"Point"}
}