{
  "type": "Feature",
  "properties": {
    "iso:country":"DE",
    "sg:address":"M\u00f6nterstr. 57",
    "sg:city":"Osnabr\u00fcck",
    "sg:phone":"+49 541/73648",
    "sg:postcode":"49084",
    "sg:province":"Niedersachsen",
    "wof:name":"Horst Baumeier",
    "wof:placetype":"venue"
},
  "geometry": {"coordinates":[8.1031980515,52.2799034119],"type":"Point"}
}