{
  "type": "Feature",
  "properties": {
    "iso:country":"DE",
    "sg:address":"Wiedenkamper Str. 15",
    "sg:city":"Solingen",
    "sg:phone":"+49 212/314055",
    "sg:postcode":"42719",
    "sg:province":"Nordrhein-Westfalen",
    "wof:name":"Justus Brenger & Co.",
    "wof:placetype":"venue"
},
  "geometry": {"coordinates":[7.043364,51.181469],"type":"Point"}
}