{
  "type": "Feature",
  "properties": {
    "iso:country":"DE",
    "sg:address":"Tor 4",
    "sg:city":"Rodenberg",
    "sg:phone":"+49 5723/916983",
    "sg:postcode":"31552",
    "sg:province":"Niedersachsen",
    "wof:name":"Vgh Versicherungen D. J\u00e4ger",
    "wof:placetype":"venue"
},
  "geometry": {"coordinates":[9.3513631821,52.3108787537],"type":"Point"}
}