{
  "type": "Feature",
  "properties": {
    "iso:country":"DE",
    "sg:address":"Grochlitzer Str.2-3",
    "sg:city":"Naumburg",
    "sg:phone":"+49 3445/201538",
    "sg:postcode":"06618",
    "sg:province":"Sachsen-Anhalt",
    "wof:name":"Prasser Immobilien",
    "wof:placetype":"venue"
},
  "geometry": {"coordinates":[11.8153085709,51.1523132324],"type":"Point"}
}