{
  "type": "Feature",
  "properties": {
    "iso:country":"DE",
    "sg:address":"Langhausstr. 15",
    "sg:city":"Saal",
    "sg:phone":"+49 4945/1200980",
    "sg:postcode":"93342",
    "sg:province":"Bayern",
    "wof:name":"Karl Hauff Gmbh",
    "wof:placetype":"venue"
},
  "geometry": {"coordinates":[10.6956672668,53.919960022],"type":"Point"}
}