{
  "type": "Feature",
  "properties": {
    "iso:country":"DE",
    "sg:address":"Osterholzstr. 21",
    "sg:city":"Asperg",
    "sg:phone":"+49 7141/63348",
    "sg:postcode":"71679",
    "sg:province":"Baden-W\u00fcrttemberg",
    "wof:name":"Vereinsheim",
    "wof:placetype":"venue"
},
  "geometry": {"coordinates":[9.1440286636,48.9031295776],"type":"Point"}
}