{
  "type": "Feature",
  "properties": {
    "iso:country":"DE",
    "sg:address":"Am G\u00fcterbahnhof 10",
    "sg:city":"Hameln",
    "sg:phone":"+49 5151/14005",
    "sg:postcode":"31785",
    "sg:province":"Niedersachsen",
    "wof:name":"Erich Wortmann Transporte Und Lagerei Gmbh",
    "wof:placetype":"venue"
},
  "geometry": {"coordinates":[9.3822479248,52.1034584045],"type":"Point"}
}