{
  "type": "Feature",
  "properties": {
    "iso:country":"DE",
    "sg:address":"Buchenweg 7",
    "sg:city":"Mosbach",
    "sg:phone":"+49 6261/2657",
    "sg:postcode":"74821",
    "sg:province":"Baden-W\u00fcrttemberg",
    "wof:name":"Klaus Wiersing Steuerbevollm\u00e4chtigter",
    "wof:placetype":"venue"
},
  "geometry": {"coordinates":[9.127120018,49.3401489258],"type":"Point"}
}