{
  "type": "Feature",
  "properties": {
    "iso:country":"DE",
    "sg:address":"Anspacher Str. 15",
    "sg:city":"Frankfurt",
    "sg:phone":"+49 69/7392343",
    "sg:postcode":"60326",
    "sg:province":"Hessen",
    "wof:name":"Baran Bau- Gmbh",
    "wof:placetype":"venue"
},
  "geometry": {"coordinates":[8.62044,50.105347],"type":"Point"}
}