{
  "type": "Feature",
  "properties": {
    "iso:country":"DE",
    "sg:address":"Hauptstr. 7",
    "sg:city":"Hirschberg",
    "sg:phone":"+49 6201/51266",
    "sg:postcode":"69493",
    "sg:province":"Baden-W\u00fcrttemberg",
    "wof:name":"Rose",
    "wof:placetype":"venue"
},
  "geometry": {"coordinates":[8.6626377106,49.500164032],"type":"Point"}
}