{
  "type": "Feature",
  "properties": {
    "iso:country":"DE",
    "sg:address":"B\u00fcttnerstr. 22",
    "sg:city":"Hannover",
    "sg:phone":"+49 511/672081",
    "sg:postcode":"30165",
    "sg:province":"Niedersachsen",
    "wof:name":"Erich Kretschmar Gmbh & Co. Kunststoffverarb.u.vertrieb Kg",
    "wof:placetype":"venue"
},
  "geometry": {"coordinates":[9.731243,52.407505],"type":"Point"}
}