{
  "type": "Feature",
  "properties": {
    "iso:country":"DE",
    "sg:address":"Im Thorgarten 2",
    "sg:city":"Ortenberg",
    "sg:phone":"+49 6049/950839",
    "sg:postcode":"63683",
    "sg:province":"Hessen",
    "wof:name":"Magdalena Niederhausen Vereinigte Krankenversicherung",
    "wof:placetype":"venue"
},
  "geometry": {"coordinates":[9.1415319443,50.3605728149],"type":"Point"}
}