{
  "type": "Feature",
  "properties": {
    "iso:country":"DE",
    "sg:address":"Johann-Christoph-Hilf-Str. 2",
    "sg:city":"Bad Elster",
    "sg:phone":"+49 37437/46371",
    "sg:postcode":"08645",
    "sg:province":"Sachsen",
    "wof:name":"Architektenb\u00fcro K. Kiener",
    "wof:placetype":"venue"
},
  "geometry": {"coordinates":[12.237792,50.279629],"type":"Point"}
}