{
  "type": "Feature",
  "properties": {
    "iso:country":"DE",
    "sg:address":"Magdeburger Str 5-7",
    "sg:city":"Hamburg",
    "sg:phone":"+49 40/7224029",
    "sg:postcode":"20457",
    "sg:province":"Hamburg",
    "wof:name":"Stromme Its Germany Gmbh",
    "wof:placetype":"venue"
},
  "geometry": {"coordinates":[10.0001821518,53.5433044434],"type":"Point"}
}