{
  "type": "Feature",
  "properties": {
    "iso:country":"DE",
    "sg:address":"Pastoriusstr. 72",
    "sg:city":"Krefeld",
    "sg:postcode":"47809",
    "sg:province":"Nordrhein-Westfalen",
    "wof:name":"Mb - Airtech Gmbh",
    "wof:placetype":"venue"
},
  "geometry": {"coordinates":[6.651845,51.337311],"type":"Point"}
}