{
  "type": "Feature",
  "properties": {
    "iso:country":"DE",
    "sg:address":"Hauptstr. 34",
    "sg:city":"Ilvesheim",
    "sg:phone":"+49 621/4962067",
    "sg:postcode":"68549",
    "sg:province":"Baden-W\u00fcrttemberg",
    "wof:name":"Proclient Versicherungsmakler E. Kfm.",
    "wof:placetype":"venue"
},
  "geometry": {"coordinates":[8.5642795563,49.4719200134],"type":"Point"}
}