{
  "type": "Feature",
  "properties": {
    "iso:country":"DE",
    "sg:address":"Josef-Schregel-Str. 29",
    "sg:city":"D\u00fcren",
    "sg:phone":"+49 2421/42183",
    "sg:postcode":"52349",
    "sg:province":"Nordrhein-Westfalen",
    "wof:name":"Plus",
    "wof:placetype":"venue"
},
  "geometry": {"coordinates":[6.480219841,50.8082084656],"type":"Point"}
}