{
  "type": "Feature",
  "properties": {
    "iso:country":"DE",
    "sg:address":"Harpener Str. 14",
    "sg:city":"Bochum",
    "sg:phone":"+49 234/591520",
    "sg:postcode":"44791",
    "sg:province":"Nordrhein-Westfalen",
    "wof:name":"Reinhold Neugebauer",
    "wof:placetype":"venue"
},
  "geometry": {"coordinates":[7.2455887794,51.4841918945],"type":"Point"}
}