{
  "type": "Feature",
  "properties": {
    "iso:country":"DE",
    "sg:city":"N\u00fcrnberg",
    "sg:phone":"+49 911/428822",
    "sg:postcode":"90402",
    "sg:province":"Bayern",
    "wof:name":"Fun And Jump",
    "wof:placetype":"venue"
},
  "geometry": {"coordinates":[11.07395,49.454315],"type":"Point"}
}