{
  "type": "Feature",
  "properties": {
    "iso:country":"DE",
    "sg:address":"Von-der-Tann-Str. 22",
    "sg:city":"Regensburg",
    "sg:postcode":"93047",
    "sg:province":"Bayern",
    "wof:name":"Lmvo Gmbh",
    "wof:placetype":"venue"
},
  "geometry": {"coordinates":[12.1050720215,49.0162124634],"type":"Point"}
}