{
  "type": "Feature",
  "properties": {
    "iso:country":"DE",
    "sg:address":"Forster Str. 8",
    "sg:city":"Niederkirchen",
    "sg:phone":"+49 6326/1606",
    "sg:postcode":"67150",
    "sg:province":"Rheinland-Pfalz",
    "wof:name":"F. Und St. Becker Weinanbau",
    "wof:placetype":"venue"
},
  "geometry": {"coordinates":[8.2208595276,49.4169311523],"type":"Point"}
}