{
  "type": "Feature",
  "properties": {
    "iso:country":"DE",
    "sg:address":"Franziskanerstr. 1",
    "sg:city":"Mainz",
    "sg:phone":"+49 6131/236571",
    "sg:postcode":"55116",
    "sg:province":"Rheinland-Pfalz",
    "wof:name":"Siegfried Pawlowski Rechtsanwalt",
    "wof:placetype":"venue"
},
  "geometry": {"coordinates":[8.2694320679,50.000213623],"type":"Point"}
}