{
  "type": "Feature",
  "properties": {
    "iso:country":"DE",
    "sg:address":"Am Hardtwald 6-8",
    "sg:city":"Ettlingen",
    "sg:phone":"+49 7243/94970",
    "sg:postcode":"76275",
    "sg:province":"Baden-W\u00fcrttemberg",
    "wof:name":"Sss Siedle Ausstellungs- Und",
    "wof:placetype":"venue"
},
  "geometry": {"coordinates":[8.377943,48.95594],"type":"Point"}
}