{
  "type": "Feature",
  "properties": {
    "iso:country":"DE",
    "sg:address":"Carl-Hellermann-Str. 37",
    "sg:city":"Meisenheim",
    "sg:phone":"+49 6753/2706",
    "sg:postcode":"55590",
    "sg:province":"Rheinland-Pfalz",
    "wof:name":"H. M. Nesselberger",
    "wof:placetype":"venue"
},
  "geometry": {"coordinates":[7.662189,49.708984],"type":"Point"}
}