{
  "type": "Feature",
  "properties": {
    "iso:country":"DE",
    "sg:address":"Hinter der Neustadt 76",
    "sg:city":"Husum",
    "sg:phone":"+49 4841/65744",
    "sg:postcode":"25813",
    "sg:province":"Schleswig-Holstein",
    "wof:name":"Dental Stolle Husum Verwaltungs Gmbh",
    "wof:placetype":"venue"
},
  "geometry": {"coordinates":[9.0450344086,54.481967926],"type":"Point"}
}