{
  "type": "Feature",
  "properties": {
    "iso:country":"DE",
    "sg:address":"Am Zimmerplatz 28",
    "sg:city":"Ehringshausen",
    "sg:phone":"+49 6443/2447",
    "sg:postcode":"35630",
    "sg:province":"Hessen",
    "wof:name":"A. Althaus-sattler",
    "wof:placetype":"venue"
},
  "geometry": {"coordinates":[8.3473024368,50.6070213318],"type":"Point"}
}