{
  "type": "Feature",
  "properties": {
    "iso:country":"DE",
    "sg:address":"Pontwall 18",
    "sg:city":"Aachen",
    "sg:phone":"+49 241/402949",
    "sg:postcode":"52062",
    "sg:province":"Nordrhein-Westfalen",
    "wof:name":"Georg Karapanagiotidis",
    "wof:placetype":"venue"
},
  "geometry": {"coordinates":[6.0774230957,50.7812767029],"type":"Point"}
}