{
  "type": "Feature",
  "properties": {
    "iso:country":"DE",
    "sg:address":"Karmeliterstr. 6",
    "sg:city":"Worms",
    "sg:phone":"+49 6241/925593",
    "sg:postcode":"67547",
    "sg:province":"Rheinland-Pfalz",
    "wof:name":"Tresor Gastst\u00e4tten Gmbh",
    "wof:placetype":"venue"
},
  "geometry": {"coordinates":[8.360478,49.633698],"type":"Point"}
}