{
  "type": "Feature",
  "properties": {
    "iso:country":"DE",
    "sg:address":"Dellbr\u00fccker Hauptstr. 130",
    "sg:city":"K\u00f6ln",
    "sg:phone":"+49 221/686766",
    "sg:postcode":"51069",
    "sg:province":"Nordrhein-Westfalen",
    "wof:name":"Sandy",
    "wof:placetype":"venue"
},
  "geometry": {"coordinates":[7.071191,50.978245],"type":"Point"}
}