{
  "type": "Feature",
  "properties": {
    "iso:country":"DE",
    "sg:address":"Prinz-Eugen-Str. 5",
    "sg:city":"Blaustein",
    "sg:phone":"+49 7304/5789",
    "sg:postcode":"89134",
    "sg:province":"Baden-W\u00fcrttemberg",
    "wof:name":"Pizzeria Engel",
    "wof:placetype":"venue"
},
  "geometry": {"coordinates":[9.8631896973,48.427482605],"type":"Point"}
}