{
  "type": "Feature",
  "properties": {
    "iso:country":"DE",
    "sg:address":"Tonwerkstr. 1",
    "sg:city":"Emmering",
    "sg:phone":"+49 8141/92028",
    "sg:postcode":"82275",
    "sg:province":"Bayern",
    "wof:name":"Silvester Dellinger",
    "wof:placetype":"venue"
},
  "geometry": {"coordinates":[11.277564,48.178696],"type":"Point"}
}