{
  "type": "Feature",
  "properties": {
    "iso:country":"DE",
    "sg:address":"Unterl\u00e4nder Str. 39",
    "sg:city":"Stuttgart",
    "sg:phone":"+49 711/8790087",
    "sg:postcode":"70435",
    "sg:province":"Baden-W\u00fcrttemberg",
    "wof:name":"Heinrich Freihofer Heilpraktiker",
    "wof:placetype":"venue"
},
  "geometry": {"coordinates":[9.1713380814,48.8320274353],"type":"Point"}
}