{
  "type": "Feature",
  "properties": {
    "iso:country":"DE",
    "sg:address":"Am Steinchen 7",
    "sg:city":"Neu-Anspach",
    "sg:phone":"+49 6081/41825",
    "sg:postcode":"61267",
    "sg:province":"Hessen",
    "wof:name":"L. Hottenrott Steuerberater",
    "wof:placetype":"venue"
},
  "geometry": {"coordinates":[8.5049676895,50.2859458923],"type":"Point"}
}