{
  "type": "Feature",
  "properties": {
    "iso:country":"DE",
    "sg:address":"W\u00f6rg\u00f6tterplatz 4",
    "sg:city":"Bad Reichenhall",
    "sg:phone":"+49 8651/2746",
    "sg:postcode":"83435",
    "sg:province":"Bayern",
    "wof:name":"Josef Hofm\u00fcller",
    "wof:placetype":"venue"
},
  "geometry": {"coordinates":[12.8751001358,47.7230491638],"type":"Point"}
}