{
  "type": "Feature",
  "properties": {
    "iso:country":"DE",
    "sg:address":"Zinkh\u00fcttenstr. 37-39",
    "sg:city":"M\u00fclheim",
    "sg:phone":"+49 208/3899029",
    "sg:postcode":"45473",
    "sg:province":"Nordrhein-Westfalen",
    "wof:name":"Management-baugesellschaft Mbh & Co. Kg",
    "wof:placetype":"venue"
},
  "geometry": {"coordinates":[6.8808050156,51.4378890991],"type":"Point"}
}