{
  "type": "Feature",
  "properties": {
    "iso:country":"DE",
    "sg:address":"Niederste Str. 14",
    "sg:city":"Attendorn",
    "sg:phone":"+49 2722/2436",
    "sg:postcode":"57439",
    "sg:province":"Nordrhein-Westfalen",
    "wof:name":"Agnes W\u00f6renk\u00e4mper Inh. Horst W\u00f6renk\u00e4mper",
    "wof:placetype":"venue"
},
  "geometry": {"coordinates":[7.9055871964,51.1260719299],"type":"Point"}
}