{
  "type": "Feature",
  "properties": {
    "iso:country":"DE",
    "sg:address":"M\u00fchlweg 19",
    "sg:city":"Hardheim",
    "sg:phone":"+49 6283/50844",
    "sg:postcode":"74736",
    "sg:province":"Baden-W\u00fcrttemberg",
    "wof:name":"Pension Agnes Baumeister",
    "wof:placetype":"venue"
},
  "geometry": {"coordinates":[9.4770097733,49.6055412292],"type":"Point"}
}