{
  "type": "Feature",
  "properties": {
    "iso:country":"DE",
    "sg:address":"Sch\u00e4ferstege 5/15",
    "sg:city":"Berlin",
    "sg:postcode":"13129",
    "sg:province":"Berlin",
    "wof:name":"Soliman Transport Und Logistik Gmbh",
    "wof:placetype":"venue"
},
  "geometry": {"coordinates":[13.4496583939,52.5929069519],"type":"Point"}
}