{
  "type": "Feature",
  "properties": {
    "iso:country":"DE",
    "sg:address":"Bruchweg 1",
    "sg:city":"Prenzlau",
    "sg:postcode":"17291",
    "sg:province":"Brandenburg",
    "wof:name":"Dhd Kompaktbau Gmbh",
    "wof:placetype":"venue"
},
  "geometry": {"coordinates":[13.844557,53.313629],"type":"Point"}
}