{
  "type": "Feature",
  "properties": {
    "iso:country":"DE",
    "sg:address":"Classenstieg 5",
    "sg:city":"Hamburg",
    "sg:phone":"+49 40/5360091",
    "sg:postcode":"22391",
    "sg:province":"Hamburg",
    "wof:name":"Hess Massiv-bau Gmbh",
    "wof:placetype":"venue"
},
  "geometry": {"coordinates":[10.091629982,53.6370506287],"type":"Point"}
}