{
  "type": "Feature",
  "properties": {
    "iso:country":"DE",
    "sg:address":"Landgrabenstr. 40",
    "sg:city":"N\u00fcrnberg",
    "sg:phone":"+49 911/416145",
    "sg:postcode":"90443",
    "sg:province":"Bayern",
    "wof:name":"Franz Schell",
    "wof:placetype":"venue"
},
  "geometry": {"coordinates":[11.0668830872,49.4394607544],"type":"Point"}
}