{
  "type": "Feature",
  "properties": {
    "iso:country":"DE",
    "sg:address":"Goerdelerstr. 26",
    "sg:city":"Rostock",
    "sg:phone":"+49 381/82352",
    "sg:postcode":"18069",
    "sg:province":"Mecklenburg-Vorpommern",
    "wof:name":"Nord-dach Eg",
    "wof:placetype":"venue"
},
  "geometry": {"coordinates":[12.07354,54.096039],"type":"Point"}
}