{
  "type": "Feature",
  "properties": {
    "iso:country":"DE",
    "sg:address":"Herzog-Tassilo-Ring 64",
    "sg:city":"Zorneding",
    "sg:phone":"+49 8106/20502",
    "sg:postcode":"85604",
    "sg:province":"Bayern",
    "wof:name":"Wolfgang Kronschnabl Architekt",
    "wof:placetype":"venue"
},
  "geometry": {"coordinates":[11.841277,48.085487],"type":"Point"}
}