{
  "type": "Feature",
  "properties": {
    "iso:country":"DE",
    "sg:address":"P\u00f6ttmeser Str. 25",
    "sg:city":"Inchenhofen",
    "sg:phone":"+49 8257/1205",
    "sg:postcode":"86570",
    "sg:province":"Bayern",
    "wof:name":"Autohaus Stahl Verwaltungs-gmbh",
    "wof:placetype":"venue"
},
  "geometry": {"coordinates":[11.11167,48.514561],"type":"Point"}
}