{
  "type": "Feature",
  "properties": {
    "iso:country":"DE",
    "sg:address":"Industriestrasse 161 c",
    "sg:city":"K\u00f6ln",
    "sg:phone":"+49 180",
    "sg:postcode":"50999",
    "sg:province":"Nordrhein-Westfalen",
    "wof:name":"Aairline-direct",
    "wof:placetype":"venue"
},
  "geometry": {"coordinates":[6.998469,50.873009],"type":"Point"}
}