{
  "type": "Feature",
  "properties": {
    "iso:country":"DE",
    "sg:address":"Alleeweg 9",
    "sg:city":"Roggenburg",
    "sg:phone":"+49 7300/200",
    "sg:postcode":"89297",
    "sg:province":"Bayern",
    "wof:name":"J. Bergert",
    "wof:placetype":"venue"
},
  "geometry": {"coordinates":[10.2324552536,48.2770957947],"type":"Point"}
}