{
  "type": "Feature",
  "properties": {
    "iso:country":"DE",
    "sg:address":"Von-M\u00f6ller-Str. 48",
    "sg:city":"Bielefeld",
    "sg:phone":"+49 521/442480",
    "sg:postcode":"33649",
    "sg:province":"Nordrhein-Westfalen",
    "wof:name":"Bauerk\u00e4mper Wettannahme",
    "wof:placetype":"venue"
},
  "geometry": {"coordinates":[8.487681,51.983963],"type":"Point"}
}