{
  "type": "Feature",
  "properties": {
    "iso:country":"DE",
    "sg:address":"Eisenbahnstr. 52",
    "sg:city":"Homburg",
    "sg:phone":"+49 6841/67942",
    "sg:postcode":"66424",
    "sg:province":"Saarland",
    "wof:name":"Billard-cafe Insel",
    "wof:placetype":"venue"
},
  "geometry": {"coordinates":[7.3391251564,49.3262138367],"type":"Point"}
}