{
  "type": "Feature",
  "properties": {
    "iso:country":"DE",
    "sg:address":"Hauptstr. 5",
    "sg:city":"Langeoog",
    "sg:phone":"+49 4972/990310",
    "sg:postcode":"26465",
    "sg:province":"Niedersachsen",
    "wof:name":"Pizzeria Piccolo",
    "wof:placetype":"venue"
},
  "geometry": {"coordinates":[7.4851760864,53.7457809448],"type":"Point"}
}