{
  "type": "Feature",
  "properties": {
    "iso:country":"DE",
    "sg:address":"G\u00fcldene Kammer 6",
    "sg:city":"Bad Hersfeld",
    "sg:phone":"+49 6621/74749",
    "sg:postcode":"36251",
    "sg:province":"Hessen",
    "wof:name":"Kte Gesellschaft F\u00fcr Kranken- Haus Und Therapieeinrichtungen",
    "wof:placetype":"venue"
},
  "geometry": {"coordinates":[9.705057,50.874626],"type":"Point"}
}