{
  "type": "Feature",
  "properties": {
    "iso:country":"DE",
    "sg:address":"Ostseestr. 8",
    "sg:city":"Sch\u00f6nberg",
    "sg:phone":"+49 4344/3174",
    "sg:postcode":"24217",
    "sg:province":"Schleswig-Holstein",
    "wof:name":"Probsteier Heimatmuseum",
    "wof:placetype":"venue"
},
  "geometry": {"coordinates":[10.372864,54.39537],"type":"Point"}
}