{
  "type": "Feature",
  "properties": {
    "iso:country":"DE",
    "sg:address":"Bornimer Str. 4",
    "sg:city":"Berlin",
    "sg:phone":"+49 30/89093480",
    "sg:postcode":"10711",
    "sg:province":"Berlin",
    "wof:name":"Itb Gmbh",
    "wof:placetype":"venue"
},
  "geometry": {"coordinates":[13.2857074738,52.4961776733],"type":"Point"}
}