{
  "type": "Feature",
  "properties": {
    "iso:country":"DE",
    "sg:address":"Op de Schonz 12",
    "sg:city":"Br\u00fcggen",
    "sg:phone":"+49 2157/871850",
    "sg:postcode":"41379",
    "sg:province":"Nordrhein-Westfalen",
    "wof:name":"R. Schoeps",
    "wof:placetype":"venue"
},
  "geometry": {"coordinates":[6.197903,51.28656],"type":"Point"}
}