{
  "type": "Feature",
  "properties": {
    "iso:country":"DE",
    "sg:address":"Jesuitengasse 9",
    "sg:city":"Augsburg",
    "sg:phone":"+49 821/3493216",
    "sg:postcode":"86152",
    "sg:province":"Bayern",
    "wof:name":"Elysee Gmbh",
    "wof:placetype":"venue"
},
  "geometry": {"coordinates":[10.894977,48.373798],"type":"Point"}
}