{
  "type": "Feature",
  "properties": {
    "iso:country":"DE",
    "sg:address":"Stedener Str. 3",
    "sg:city":"Holste",
    "sg:phone":"+49 4748/651",
    "sg:postcode":"27729",
    "sg:province":"Niedersachsen",
    "wof:name":"Gasth. Bodenstab Stedener Hof",
    "wof:placetype":"venue"
},
  "geometry": {"coordinates":[8.8555955887,53.3589096069],"type":"Point"}
}