{
  "type": "Feature",
  "properties": {
    "iso:country":"DE",
    "sg:address":"Weinberge 16a",
    "sg:city":"Elsterwerda",
    "sg:phone":"+49 3533/2470",
    "sg:postcode":"04910",
    "sg:province":"Brandenburg",
    "wof:name":"Baustoffhandel Hoffmann Gmbh",
    "wof:placetype":"venue"
},
  "geometry": {"coordinates":[13.5430269241,51.4701118469],"type":"Point"}
}