{
  "type": "Feature",
  "properties": {
    "iso:country":"DE",
    "sg:address":"Gebhardstr. 7",
    "sg:city":"Friedrichshafen",
    "sg:phone":"+49 7541/21062",
    "sg:postcode":"88046",
    "sg:province":"Baden-W\u00fcrttemberg",
    "wof:name":"Karl Abele",
    "wof:placetype":"venue"
},
  "geometry": {"coordinates":[9.4898071289,47.6531600952],"type":"Point"}
}