{
  "type": "Feature",
  "properties": {
    "iso:country":"DE",
    "sg:address":"Aarstr. 53",
    "sg:city":"Wiesbaden",
    "sg:phone":"+49 611/47018",
    "sg:postcode":"65195",
    "sg:province":"Hessen",
    "wof:name":"P & S Rohr- Und Stahlbau Gmbh",
    "wof:placetype":"venue"
},
  "geometry": {"coordinates":[8.218321,50.089397],"type":"Point"}
}