{
  "type": "Feature",
  "properties": {
    "iso:country":"DE",
    "sg:address":"Liebfrauenstr. 44",
    "sg:city":"Oberwesel",
    "sg:phone":"+49 6744/369",
    "sg:postcode":"55430",
    "sg:province":"Rheinland-Pfalz",
    "wof:name":"Hans Steinhauser",
    "wof:placetype":"venue"
},
  "geometry": {"coordinates":[7.7278499603,50.1067886353],"type":"Point"}
}