{
  "type": "Feature",
  "properties": {
    "iso:country":"DE",
    "sg:address":"Obernstr. 5",
    "sg:city":"Stadthagen",
    "sg:phone":"+49 5721/923723",
    "sg:postcode":"31655",
    "sg:province":"Niedersachsen",
    "wof:name":"Mobil Com Shop",
    "wof:placetype":"venue"
},
  "geometry": {"coordinates":[9.2054290771,52.3228988647],"type":"Point"}
}