{
  "type": "Feature",
  "properties": {
    "iso:country":"DE",
    "sg:address":"Am Elsterbach 6",
    "sg:city":"Oestrich-Winkel",
    "sg:phone":"+49 6723/5576",
    "sg:postcode":"65375",
    "sg:province":"Hessen",
    "wof:name":"Adolf Freimuth",
    "wof:placetype":"venue"
},
  "geometry": {"coordinates":[7.9994258881,49.9925994873],"type":"Point"}
}