{
  "type": "Feature",
  "properties": {
    "iso:country":"DE",
    "sg:address":"Damgartener Chaussee 14",
    "sg:city":"Ribnitz-Damgarten",
    "sg:phone":"+49 3821/2593",
    "sg:postcode":"18311",
    "sg:province":"Mecklenburg-Vorpommern",
    "wof:name":"M. Weck",
    "wof:placetype":"venue"
},
  "geometry": {"coordinates":[12.439166069,54.2429389954],"type":"Point"}
}