{
  "type": "Feature",
  "properties": {
    "iso:country":"DE",
    "sg:address":"Walter-Gropius-Ring 13",
    "sg:city":"Alfeld",
    "sg:phone":"+49 5181/1315",
    "sg:postcode":"31061",
    "sg:province":"Niedersachsen",
    "wof:name":"Rolf Nietmann",
    "wof:placetype":"venue"
},
  "geometry": {"coordinates":[9.8325881958,51.9899711609],"type":"Point"}
}