{
  "type": "Feature",
  "properties": {
    "iso:country":"DE",
    "sg:address":"B\u00fchlmattstr. 20",
    "sg:city":"Murg",
    "sg:phone":"+49 7763/1634",
    "sg:postcode":"79730",
    "sg:province":"Baden-W\u00fcrttemberg",
    "wof:name":"M. Krause",
    "wof:placetype":"venue"
},
  "geometry": {"coordinates":[8.02594,47.583019],"type":"Point"}
}