{
  "type": "Feature",
  "properties": {
    "iso:country":"DE",
    "sg:address":"Kurf\u00fcrstenstr. 24",
    "sg:city":"Wintrich",
    "sg:phone":"+49 6534/8894",
    "sg:postcode":"54487",
    "sg:province":"Rheinland-Pfalz",
    "wof:name":"E. Gorges-marx",
    "wof:placetype":"venue"
},
  "geometry": {"coordinates":[6.9553489685,49.8909606934],"type":"Point"}
}