{
  "type": "Feature",
  "properties": {
    "iso:country":"DE",
    "sg:address":"Gutenbergstr. 18",
    "sg:city":"Weiterstadt",
    "sg:postcode":"64331",
    "sg:province":"Hessen",
    "wof:name":"Ab-sprint Gmbh",
    "wof:placetype":"venue"
},
  "geometry": {"coordinates":[8.60719,49.889671],"type":"Point"}
}