{
  "type": "Feature",
  "properties": {
    "iso:country":"DE",
    "sg:address":"Eutighofer Str. 135",
    "sg:city":"Schw\u00e4bisch Gm\u00fcnd",
    "sg:phone":"+49 7171/30804",
    "sg:postcode":"73525",
    "sg:province":"Baden-W\u00fcrttemberg",
    "wof:name":"T\u00dcv S\u00fcdwest",
    "wof:placetype":"venue"
},
  "geometry": {"coordinates":[9.7665147781,48.786567688],"type":"Point"}
}