{
  "type": "Feature",
  "properties": {
    "iso:country":"DE",
    "sg:address":"Dr.-Hofmann-Str. 14",
    "sg:city":"Bad Mergentheim",
    "sg:phone":"+49 7931/45065",
    "sg:postcode":"97980",
    "sg:province":"Baden-W\u00fcrttemberg",
    "wof:name":"Dr. Dietmar V\u00f6tisch",
    "wof:placetype":"venue"
},
  "geometry": {"coordinates":[9.8385419846,49.4726676941],"type":"Point"}
}