{
  "type": "Feature",
  "properties": {
    "iso:country":"DE",
    "sg:address":"Hohe Egge 46",
    "sg:city":"Witten",
    "sg:phone":"+49 2302/72634",
    "sg:postcode":"58456",
    "sg:province":"Nordrhein-Westfalen",
    "wof:name":"M. Und H. Kr\u00fcger Steuerberater",
    "wof:placetype":"venue"
},
  "geometry": {"coordinates":[7.2819838524,51.3829956055],"type":"Point"}
}