{
  "type": "Feature",
  "properties": {
    "iso:country":"DE",
    "sg:address":"Deichstr. 45",
    "sg:city":"Hamburg",
    "sg:postcode":"20459",
    "sg:province":"Hamburg",
    "wof:name":"Siegrid Harbach Marine-decoder Und Computer Kg",
    "wof:placetype":"venue"
},
  "geometry": {"coordinates":[9.9869318008,53.5452232361],"type":"Point"}
}