{
  "type": "Feature",
  "properties": {
    "iso:country":"DE",
    "sg:address":"Pulverm\u00fchlenweg 31",
    "sg:city":"Seevetal",
    "sg:phone":"+49 40/7685081",
    "sg:postcode":"21217",
    "sg:province":"Niedersachsen",
    "wof:name":"Mondevino Internationale Weine Schaumweine Spirituosen",
    "wof:placetype":"venue"
},
  "geometry": {"coordinates":[10.0331754684,53.4200515747],"type":"Point"}
}