{
  "type": "Feature",
  "properties": {
    "iso:country":"DE",
    "sg:address":"Marktplatz 11",
    "sg:city":"Gerolzhofen",
    "sg:phone":"+49 9382/5094",
    "sg:postcode":"97447",
    "sg:province":"Bayern",
    "wof:name":"Siegfried Gerner-vogt Rechtsanwalt",
    "wof:placetype":"venue"
},
  "geometry": {"coordinates":[10.3497877121,49.901058197],"type":"Point"}
}