{
  "type": "Feature",
  "properties": {
    "iso:country":"DE",
    "sg:address":"Lichtenberger Str. 22",
    "sg:city":"Rheinau",
    "sg:phone":"+49 7844/98902",
    "sg:postcode":"77866",
    "sg:province":"Baden-W\u00fcrttemberg",
    "wof:name":"Norbert Fuchs Anlageberater",
    "wof:placetype":"venue"
},
  "geometry": {"coordinates":[7.9365448952,48.6524887085],"type":"Point"}
}