{
  "type": "Feature",
  "properties": {
    "iso:country":"DE",
    "sg:address":"Sandforter Str. 2",
    "sg:city":"Olfen",
    "sg:phone":"+49 2595/96200",
    "sg:postcode":"59399",
    "sg:province":"Nordrhein-Westfalen",
    "wof:name":"Planaid E. K.",
    "wof:placetype":"venue"
},
  "geometry": {"coordinates":[7.415664,51.695732],"type":"Point"}
}