{
  "type": "Feature",
  "properties": {
    "iso:country":"DE",
    "sg:address":"Augsburger Str. 1c",
    "sg:city":"T\u00fcrkheim",
    "sg:phone":"+49 8245/90682",
    "sg:postcode":"86842",
    "sg:province":"Bayern",
    "wof:name":"Flying Pizza",
    "wof:placetype":"venue"
},
  "geometry": {"coordinates":[10.6401567459,48.0633430481],"type":"Point"}
}