{
  "type": "Feature",
  "properties": {
    "iso:country":"DE",
    "sg:address":"Gerichtstr. 2",
    "sg:city":"Kalbe",
    "sg:phone":"+49 39080/3017",
    "sg:postcode":"39624",
    "sg:province":"Sachsen-Anhalt",
    "wof:name":"Jens Franke",
    "wof:placetype":"venue"
},
  "geometry": {"coordinates":[11.3898429871,52.6524353027],"type":"Point"}
}