{
  "type": "Feature",
  "properties": {
    "iso:country":"DE",
    "sg:address":"Vereinsstr. 29",
    "sg:city":"Gotha",
    "sg:phone":"+49 3621/36540",
    "sg:postcode":"99867",
    "sg:province":"Th\u00fcringen",
    "wof:name":"P. Kaiser Immobilienmakler",
    "wof:placetype":"venue"
},
  "geometry": {"coordinates":[10.7134046555,50.9585456848],"type":"Point"}
}