{
  "type": "Feature",
  "properties": {
    "iso:country":"DE",
    "sg:address":"Viehreihe 53",
    "sg:city":"Lilienthal",
    "sg:phone":"+49 4298/30850",
    "sg:postcode":"28865",
    "sg:province":"Niedersachsen",
    "wof:name":"Kev K\u00fcchen- Und Elektro- Vertriebsgesellschaft In",
    "wof:placetype":"venue"
},
  "geometry": {"coordinates":[8.9350910187,53.1605987549],"type":"Point"}
}