{
  "type": "Feature",
  "properties": {
    "iso:country":"DE",
    "sg:address":"Perlingerstr. 10",
    "sg:city":"Grafenwiesen",
    "sg:phone":"+49 9941/1761",
    "sg:postcode":"93479",
    "sg:province":"Bayern",
    "wof:name":"Josef M\u00fchlbauer",
    "wof:placetype":"venue"
},
  "geometry": {"coordinates":[12.8766450882,49.200553894],"type":"Point"}
}