{
  "type": "Feature",
  "properties": {
    "iso:country":"DE",
    "sg:address":"Eichenstr. 3",
    "sg:city":"Puderbach",
    "sg:phone":"+49 2684/3070",
    "sg:postcode":"56305",
    "sg:province":"Rheinland-Pfalz",
    "wof:name":"Dr. Heinz Henn Tierarzt",
    "wof:placetype":"venue"
},
  "geometry": {"coordinates":[7.6145129204,50.6045227051],"type":"Point"}
}