{
  "type": "Feature",
  "properties": {
    "iso:country":"DE",
    "sg:address":"Burgplatz 21-22",
    "sg:city":"D\u00fcsseldorf",
    "sg:phone":"+49 211/84183",
    "sg:postcode":"40213",
    "sg:province":"Nordrhein-Westfalen",
    "wof:name":"Dr. Klaus Neumayer Steuerberater",
    "wof:placetype":"venue"
},
  "geometry": {"coordinates":[6.7716159821,51.2270393372],"type":"Point"}
}