{
  "type": "Feature",
  "properties": {
    "iso:country":"DE",
    "sg:address":"Hans-Eidig-Str. 12",
    "sg:city":"Rosengarten",
    "sg:phone":"+49 4105/76493",
    "sg:postcode":"21224",
    "sg:province":"Niedersachsen",
    "wof:name":"Handelskontor Susanne Siebert",
    "wof:placetype":"venue"
},
  "geometry": {"coordinates":[9.9362154007,53.3722114563],"type":"Point"}
}