{
  "type": "Feature",
  "properties": {
    "iso:country":"DE",
    "sg:address":"Baumberger Str 55",
    "sg:city":"Rosendahl",
    "sg:phone":"+49 2547/93070",
    "sg:postcode":"48720",
    "sg:province":"Nordrhein-Westfalen",
    "wof:name":"Anton H\u00fclsken Gmbh & Co Kg",
    "wof:placetype":"venue"
},
  "geometry": {"coordinates":[7.229589,51.998211],"type":"Point"}
}