{
  "type": "Feature",
  "properties": {
    "iso:country":"DE",
    "sg:address":"Mundatstr. 1",
    "sg:city":"Kapsweyer",
    "sg:phone":"+49 6340/8607",
    "sg:postcode":"76889",
    "sg:province":"Rheinland-Pfalz",
    "wof:name":"Block",
    "wof:placetype":"venue"
},
  "geometry": {"coordinates":[8.021167,49.042725],"type":"Point"}
}