{
  "type": "Feature",
  "properties": {
    "iso:country":"DE",
    "sg:address":"Lindenstr. 5-7",
    "sg:city":"Solms",
    "sg:phone":"+49 6441/679010",
    "sg:postcode":"35606",
    "sg:province":"Hessen",
    "wof:name":"Kpa-immobilien Verwaltungsgesellschaft Mbh",
    "wof:placetype":"venue"
},
  "geometry": {"coordinates":[8.4064655304,50.5391921997],"type":"Point"}
}