{
  "type": "Feature",
  "properties": {
    "iso:country":"DE",
    "sg:address":"Elisabethstr. 26",
    "sg:city":"Wesseling",
    "sg:phone":"+49 2232/51646",
    "sg:postcode":"50389",
    "sg:province":"Nordrhein-Westfalen",
    "wof:name":"Wilfried Schwarzer Steuerberater",
    "wof:placetype":"venue"
},
  "geometry": {"coordinates":[6.9446182251,50.8316764832],"type":"Point"}
}