{
  "type": "Feature",
  "properties": {
    "iso:country":"DE",
    "sg:address":"L\u00fcllauer Str. 2",
    "sg:city":"Jesteburg",
    "sg:phone":"+49 4183/4909",
    "sg:postcode":"21266",
    "sg:province":"Niedersachsen",
    "wof:name":"Klaus E. Waje Architekt",
    "wof:placetype":"venue"
},
  "geometry": {"coordinates":[9.952547,53.306538],"type":"Point"}
}