{
  "type": "Feature",
  "properties": {
    "iso:country":"DE",
    "sg:address":"Hirschstr. 16",
    "sg:city":"Lindenberg",
    "sg:phone":"+49 8381/1693",
    "sg:postcode":"88161",
    "sg:province":"Bayern",
    "wof:name":"Restaurant Br\u00e4uhaus",
    "wof:placetype":"venue"
},
  "geometry": {"coordinates":[9.8867530823,47.5985183716],"type":"Point"}
}