{
  "type": "Feature",
  "properties": {
    "iso:country":"DE",
    "sg:address":"Bussenblick 10",
    "sg:city":"Emerkingen",
    "sg:phone":"+49 7393/95190",
    "sg:postcode":"89607",
    "sg:province":"Baden-W\u00fcrttemberg",
    "wof:name":"Bartholomaeus Industrievertretungen Gmbh",
    "wof:placetype":"venue"
},
  "geometry": {"coordinates":[9.653046608,48.2092895508],"type":"Point"}
}