{
  "type": "Feature",
  "properties": {
    "iso:country":"DE",
    "sg:address":"Kreuzbuschstr. 4",
    "sg:city":"Wassenberg",
    "sg:phone":"+49 2432/3885",
    "sg:postcode":"41849",
    "sg:province":"Nordrhein-Westfalen",
    "wof:name":"E. Stabenow",
    "wof:placetype":"venue"
},
  "geometry": {"coordinates":[6.148825,51.119087],"type":"Point"}
}