{
  "type": "Feature",
  "properties": {
    "iso:country":"DE",
    "sg:address":"Kurgartenstr. 5",
    "sg:city":"Bad D\u00fcrkheim",
    "sg:phone":"+49 6322/989482",
    "sg:postcode":"67098",
    "sg:province":"Rheinland-Pfalz",
    "wof:name":"J. Sanzen Inh. R. Kinscher",
    "wof:placetype":"venue"
},
  "geometry": {"coordinates":[8.1679925919,49.4618186951],"type":"Point"}
}