{
  "type": "Feature",
  "properties": {
    "iso:country":"DE",
    "sg:address":"Lange Str. 22",
    "sg:city":"Gleichen",
    "sg:phone":"+49 551/791086",
    "sg:postcode":"37130",
    "sg:province":"Niedersachsen",
    "wof:name":"Lks L\u00fcftungs- Und Klima-service Gmbh",
    "wof:placetype":"venue"
},
  "geometry": {"coordinates":[10.0420198441,51.448841095],"type":"Point"}
}