{
  "type": "Feature",
  "properties": {
    "iso:country":"DE",
    "sg:address":"Pfarrwiese 2",
    "sg:city":"Sailauf",
    "sg:phone":"+49 6093/2424",
    "sg:postcode":"63877",
    "sg:province":"Bayern",
    "wof:name":"Rosanna",
    "wof:placetype":"venue"
},
  "geometry": {"coordinates":[9.25508,50.022961],"type":"Point"}
}