{
  "type": "Feature",
  "properties": {
    "iso:country":"DE",
    "sg:address":"Tonwerkstr. 13",
    "sg:city":"L\u00f6hne",
    "sg:phone":"+49 5732/2157",
    "sg:postcode":"32584",
    "sg:province":"Nordrhein-Westfalen",
    "wof:name":"Hermann Beckervordersandfort Steuerberater",
    "wof:placetype":"venue"
},
  "geometry": {"coordinates":[8.7015190125,52.2008399963],"type":"Point"}
}