{
  "type": "Feature",
  "properties": {
    "iso:country":"DE",
    "sg:address":"Herzog-Max-Str. 2",
    "sg:city":"Bamberg",
    "sg:phone":"+49 951/981340",
    "sg:postcode":"96047",
    "sg:province":"Bayern",
    "wof:name":"Bamberger M\u00fctzen- Industrie Gmbh & Co. Kg",
    "wof:placetype":"venue"
},
  "geometry": {"coordinates":[10.8950338364,49.8912239075],"type":"Point"}
}