{
  "type": "Feature",
  "properties": {
    "iso:country":"DE",
    "sg:address":"Burgangerweg 8",
    "sg:city":"Oberstaufen",
    "sg:phone":"+49 8325/733",
    "sg:postcode":"87534",
    "sg:province":"Bayern",
    "wof:name":"Mechatronic Gmbh",
    "wof:placetype":"venue"
},
  "geometry": {"coordinates":[10.091867,47.559532],"type":"Point"}
}