{
  "type": "Feature",
  "properties": {
    "iso:country":"DE",
    "sg:address":"Hagedornstr. 1",
    "sg:city":"Friedland",
    "sg:postcode":"17098",
    "sg:province":"Mecklenburg-Vorpommern",
    "wof:name":"Wasserversorgung Und Abwasserbehandlung",
    "wof:placetype":"venue"
},
  "geometry": {"coordinates":[13.5608158112,53.6712303162],"type":"Point"}
}