{
  "type": "Feature",
  "properties": {
    "iso:country":"DE",
    "sg:address":"Hornberger Str. 70",
    "sg:city":"Lauterbach",
    "sg:phone":"+49 7422/245419",
    "sg:postcode":"78730",
    "sg:province":"Baden-W\u00fcrttemberg",
    "wof:name":"Karl Binder",
    "wof:placetype":"venue"
},
  "geometry": {"coordinates":[8.335113,48.228798],"type":"Point"}
}