{
  "type": "Feature",
  "properties": {
    "iso:country":"DE",
    "sg:address":"M\u00f6rgener Str. 13",
    "sg:city":"Tussenhausen",
    "sg:phone":"+49 8268/904900",
    "sg:postcode":"86874",
    "sg:province":"Bayern",
    "wof:name":"Ronge Gmbh",
    "wof:placetype":"venue"
},
  "geometry": {"coordinates":[10.5396509171,48.1212768555],"type":"Point"}
}