{
  "type": "Feature",
  "properties": {
    "iso:country":"DE",
    "sg:address":"Hedwigstr. 4",
    "sg:city":"Chemnitz",
    "sg:phone":"+49 371/54971",
    "sg:postcode":"09125",
    "sg:province":"Sachsen",
    "wof:name":"Rank",
    "wof:placetype":"venue"
},
  "geometry": {"coordinates":[12.920783,50.773277],"type":"Point"}
}