{
  "type": "Feature",
  "properties": {
    "iso:country":"DE",
    "sg:address":"Emanuel-Leutze-Str. 17",
    "sg:city":"D\u00fcsseldorf",
    "sg:phone":"+49 211/523970",
    "sg:postcode":"40547",
    "sg:province":"Nordrhein-Westfalen",
    "wof:name":"Ik Immobilienkontor Gmbh",
    "wof:placetype":"venue"
},
  "geometry": {"coordinates":[6.7390608788,51.2445640564],"type":"Point"}
}