{
  "type": "Feature",
  "properties": {
    "iso:country":"DE",
    "sg:address":"Heusenstammer Str. 48",
    "sg:city":"Obertshausen",
    "sg:phone":"+49 6104/41953",
    "sg:postcode":"63179",
    "sg:province":"Hessen",
    "wof:name":"H.hans Opitz",
    "wof:placetype":"venue"
},
  "geometry": {"coordinates":[8.8469009399,50.0685310364],"type":"Point"}
}