{
  "type": "Feature",
  "properties": {
    "iso:country":"DE",
    "sg:address":"Basler Str. 12",
    "sg:city":"Breisach",
    "sg:phone":"+49 7667/6988",
    "sg:postcode":"79206",
    "sg:province":"Baden-W\u00fcrttemberg",
    "wof:name":"Ingeborg Eichstetter Steuerberaterin",
    "wof:placetype":"venue"
},
  "geometry": {"coordinates":[7.5873222351,48.0388336182],"type":"Point"}
}