{
  "type": "Feature",
  "properties": {
    "iso:country":"DE",
    "sg:address":"Renchener Str. 3",
    "sg:city":"Oberkirch",
    "sg:phone":"+49 7802/982565",
    "sg:postcode":"77704",
    "sg:province":"Baden-W\u00fcrttemberg",
    "wof:name":"Restaurant Samos",
    "wof:placetype":"venue"
},
  "geometry": {"coordinates":[8.0781002045,48.5322990417],"type":"Point"}
}