{
  "type": "Feature",
  "properties": {
    "iso:country":"DE",
    "sg:address":"Oldenburger Str. 258",
    "sg:city":"Rastede",
    "sg:phone":"+49 4402/4141",
    "sg:postcode":"26180",
    "sg:province":"Niedersachsen",
    "wof:name":"Bernd Hoffmann Rechtsanwalt Und Notar",
    "wof:placetype":"venue"
},
  "geometry": {"coordinates":[8.1983680725,53.2486495972],"type":"Point"}
}