{
  "type": "Feature",
  "properties": {
    "iso:country":"DE",
    "sg:address":"Bahnhofstr. 71",
    "sg:city":"Zepernick",
    "sg:postcode":"16341",
    "sg:province":"Brandenburg",
    "wof:name":"Ursula Weigel",
    "wof:placetype":"venue"
},
  "geometry": {"coordinates":[13.519783,52.648075],"type":"Point"}
}