{
  "type": "Feature",
  "properties": {
    "iso:country":"DE",
    "sg:address":"Neuwarendorf",
    "sg:city":"Warendorf",
    "sg:phone":"+49 2581/2309",
    "sg:postcode":"48231",
    "sg:province":"Nordrhein-Westfalen",
    "wof:name":"B. H\u00f6llmann",
    "wof:placetype":"venue"
},
  "geometry": {"coordinates":[7.92793,51.958988],"type":"Point"}
}