{
  "type": "Feature",
  "properties": {
    "iso:country":"DE",
    "sg:address":"Balgerbr\u00fcck 2",
    "sg:city":"Melle",
    "sg:phone":"+49 5225/3661",
    "sg:postcode":"49328",
    "sg:province":"Niedersachsen",
    "wof:name":"P. H. Gr\u00f6negress Verwaltungs-gmbh",
    "wof:placetype":"venue"
},
  "geometry": {"coordinates":[8.491686,52.168068],"type":"Point"}
}