{
  "type": "Feature",
  "properties": {
    "iso:country":"DE",
    "sg:address":"Kleiner Kuhberg 4",
    "sg:city":"Kiel",
    "sg:postcode":"24103",
    "sg:province":"Schleswig-Holstein",
    "wof:name":"Thomas Bischoff Immobilien Gmbh",
    "wof:placetype":"venue"
},
  "geometry": {"coordinates":[10.1330165863,54.3208198547],"type":"Point"}
}