{
  "type": "Feature",
  "properties": {
    "iso:country":"DE",
    "sg:address":"Mittelstr. 22",
    "sg:city":"Leipzig",
    "sg:phone":"+49 341/9411455",
    "sg:postcode":"04205",
    "sg:province":"Sachsen",
    "wof:name":"Jens Marquardt-bau-gmbh",
    "wof:placetype":"venue"
},
  "geometry": {"coordinates":[12.2572822571,51.3212547302],"type":"Point"}
}