{
  "type": "Feature",
  "properties": {
    "iso:country":"DE",
    "sg:address":"Alexanderstr. 303",
    "sg:city":"Oldenburg",
    "sg:phone":"+49 441/63904",
    "sg:postcode":"26127",
    "sg:province":"Niedersachsen",
    "wof:name":"Adler-apotheke",
    "wof:placetype":"venue"
},
  "geometry": {"coordinates":[8.198852,53.167461],"type":"Point"}
}