{
  "type": "Feature",
  "properties": {
    "iso:country":"DE",
    "sg:address":"Stra\u00dfe des Friedens 16",
    "sg:city":"Ellefeld",
    "sg:phone":"+49 3745/72918",
    "sg:postcode":"08236",
    "sg:province":"Sachsen",
    "wof:name":"A. Angermann",
    "wof:placetype":"venue"
},
  "geometry": {"coordinates":[12.381077,50.482212],"type":"Point"}
}