{
  "type": "Feature",
  "properties": {
    "iso:country":"DE",
    "sg:address":"Kirchhofallee 46",
    "sg:city":"Kiel",
    "sg:phone":"+49 431/677673",
    "sg:postcode":"24114",
    "sg:province":"Schleswig-Holstein",
    "wof:name":"Uwe Und J\u00fcrgen Peter",
    "wof:placetype":"venue"
},
  "geometry": {"coordinates":[10.1222982407,54.3169631958],"type":"Point"}
}