{
  "type": "Feature",
  "properties": {
    "iso:country":"DE",
    "sg:address":"Brucknerstr. 8a",
    "sg:city":"Hattingen",
    "sg:phone":"+49 2324/82020",
    "sg:postcode":"45529",
    "sg:province":"Nordrhein-Westfalen",
    "wof:name":"R\u00fcgensche Kleinbahn Verwaltungs Gmbh",
    "wof:placetype":"venue"
},
  "geometry": {"coordinates":[7.1680898666,51.4121513367],"type":"Point"}
}