{
  "type": "Feature",
  "properties": {
    "iso:country":"DE",
    "sg:address":"An der Steige 12",
    "sg:city":"Gutenstetten",
    "sg:phone":"+49 9163/8062",
    "sg:postcode":"91468",
    "sg:province":"Bayern",
    "wof:name":"Fritz Gei\u00dfd\u00f6rfer",
    "wof:placetype":"venue"
},
  "geometry": {"coordinates":[10.6506385803,49.6247558594],"type":"Point"}
}