{
  "type": "Feature",
  "properties": {
    "iso:country":"DE",
    "sg:address":"Aechterhoek 22",
    "sg:city":"Emsdetten",
    "sg:phone":"+49 2572/7629",
    "sg:postcode":"48282",
    "sg:province":"Nordrhein-Westfalen",
    "wof:name":"Werner Rinno",
    "wof:placetype":"venue"
},
  "geometry": {"coordinates":[7.51223,52.188751],"type":"Point"}
}