{
  "type": "Feature",
  "properties": {
    "iso:country":"DE",
    "sg:address":"Dinst\u00fchlerstr. 86",
    "sg:city":"H\u00fcckelhoven",
    "sg:phone":"+49 2433/84512",
    "sg:postcode":"41836",
    "sg:province":"Nordrhein-Westfalen",
    "wof:name":"F. Mahr & U. Mertsch",
    "wof:placetype":"venue"
},
  "geometry": {"coordinates":[6.2268590927,51.0525131226],"type":"Point"}
}