{
  "type": "Feature",
  "properties": {
    "iso:country":"DE",
    "sg:address":"Ulzburger Str. 360",
    "sg:city":"Norderstedt",
    "sg:phone":"+49 40/5221753",
    "sg:postcode":"22846",
    "sg:province":"Schleswig-Holstein",
    "wof:name":"Ralf Goldschmidt",
    "wof:placetype":"venue"
},
  "geometry": {"coordinates":[9.998684,53.719521],"type":"Point"}
}