{
  "type": "Feature",
  "properties": {
    "iso:country":"DE",
    "sg:address":"Edwin-Reis-Str. 10",
    "sg:city":"Mannheim",
    "sg:phone":"+49 621/473117",
    "sg:postcode":"68229",
    "sg:province":"Baden-W\u00fcrttemberg",
    "wof:name":"C. Von Nagel",
    "wof:placetype":"venue"
},
  "geometry": {"coordinates":[8.573217392,49.441532135],"type":"Point"}
}