{
  "type": "Feature",
  "properties": {
    "iso:country":"DE",
    "sg:address":"Pfeuferstr. 37",
    "sg:city":"M\u00fcnchen",
    "sg:phone":"+49 89/74791700",
    "sg:postcode":"81373",
    "sg:province":"Bayern",
    "wof:name":"Wilhelm Erfurt",
    "wof:placetype":"venue"
},
  "geometry": {"coordinates":[11.54152,48.123898],"type":"Point"}
}