{
  "type": "Feature",
  "properties": {
    "iso:country":"DE",
    "sg:address":"Brockenstra\u00dfe",
    "sg:city":"Schierke",
    "sg:phone":"+49 39455",
    "sg:postcode":"38879",
    "sg:province":"Sachsen-Anhalt",
    "wof:name":"Der Harzer Blaumachersuchdienst",
    "wof:placetype":"venue"
},
  "geometry": {"coordinates":[10.650099,51.770325],"type":"Point"}
}