{
  "type": "Feature",
  "properties": {
    "iso:country":"DE",
    "sg:address":"M\u00fchlenkamp 39",
    "sg:city":"Hamburg",
    "sg:phone":"+49 40/2791818",
    "sg:postcode":"22303",
    "sg:province":"Hamburg",
    "wof:name":"Dirk Becker",
    "wof:placetype":"venue"
},
  "geometry": {"coordinates":[10.0109233856,53.5819740295],"type":"Point"}
}