{
  "type": "Feature",
  "properties": {
    "iso:country":"DE",
    "sg:address":"Eichenstra\u00dfe 15",
    "sg:city":"M\u00fcnchen",
    "sg:phone":"+49 89/7592252",
    "sg:postcode":"82061",
    "sg:province":"Bayern",
    "wof:name":"Quintenz",
    "wof:placetype":"venue"
},
  "geometry": {"coordinates":[11.4769258499,48.1185035706],"type":"Point"}
}