{
  "type": "Feature",
  "properties": {
    "iso:country":"DE",
    "sg:address":"Schwalbenweg 3",
    "sg:city":"Aichwald",
    "sg:phone":"+49 711/361112",
    "sg:postcode":"73773",
    "sg:province":"Baden-W\u00fcrttemberg",
    "wof:name":"Gerhard Veigele Elektroinstallation",
    "wof:placetype":"venue"
},
  "geometry": {"coordinates":[9.371455,48.761444],"type":"Point"}
}