{
  "type": "Feature",
  "properties": {
    "iso:country":"DE",
    "sg:address":"Hauptstr. 35",
    "sg:city":"Nufringen",
    "sg:phone":"+49 4970/328063",
    "sg:postcode":"71154",
    "sg:province":"Baden-W\u00fcrttemberg",
    "wof:name":"Nufringer Bank -raiffeisen Eg",
    "wof:placetype":"venue"
},
  "geometry": {"coordinates":[8.891113,48.623199],"type":"Point"}
}