{
  "type": "Feature",
  "properties": {
    "iso:country":"DE",
    "sg:address":"Am Hasselt 20c",
    "sg:city":"Bad Bramstedt",
    "sg:phone":"+49 4192/899661",
    "sg:postcode":"24576",
    "sg:province":"Schleswig-Holstein",
    "wof:name":"Walter Kruse",
    "wof:placetype":"venue"
},
  "geometry": {"coordinates":[9.9016370773,53.9295120239],"type":"Point"}
}