{
  "type": "Feature",
  "properties": {
    "iso:country":"DE",
    "sg:address":"R\u00f6thaer Str. 22",
    "sg:city":"Borna",
    "sg:postcode":"04552",
    "sg:province":"Sachsen",
    "wof:name":"Mitteldeutsche Braunkohle Strukturf\u00f6rderungsges. Mbh Mbs",
    "wof:placetype":"venue"
},
  "geometry": {"coordinates":[12.49976,51.130775],"type":"Point"}
}