{
  "type": "Feature",
  "properties": {
    "iso:country":"DE",
    "sg:address":"Herderstr. 27",
    "sg:city":"Greifswald",
    "sg:phone":"+49 3834/501600",
    "sg:postcode":"17489",
    "sg:province":"Mecklenburg-Vorpommern",
    "wof:name":"Wolfgang Schult",
    "wof:placetype":"venue"
},
  "geometry": {"coordinates":[13.367463,54.081493],"type":"Point"}
}