{
  "type": "Feature",
  "properties": {
    "iso:country":"DE",
    "sg:address":"Stockumer Str. 136",
    "sg:city":"Dortmund",
    "sg:phone":"+49 231/7920300",
    "sg:postcode":"44225",
    "sg:province":"Nordrhein-Westfalen",
    "wof:name":"Ves Planungsgesellschaft F\u00fcr Transport- U. Lagersysteme Mbh",
    "wof:placetype":"venue"
},
  "geometry": {"coordinates":[7.444231987,51.4799079895],"type":"Point"}
}