{
  "type": "Feature",
  "properties": {
    "iso:country":"DE",
    "sg:address":"Klosterstra\u00dfe 1a",
    "sg:city":"Dachau",
    "sg:phone":"+49 8131/81375",
    "sg:postcode":"85221",
    "sg:province":"Bayern",
    "wof:name":"Walter Baedeker",
    "wof:placetype":"venue"
},
  "geometry": {"coordinates":[11.4334220886,48.2593955994],"type":"Point"}
}