{
  "type": "Feature",
  "properties": {
    "iso:country":"DE",
    "sg:address":"Wilhelmstr. 34",
    "sg:city":"L\u00fcdenscheid",
    "sg:phone":"+49 2351/21581",
    "sg:postcode":"58511",
    "sg:province":"Nordrhein-Westfalen",
    "wof:name":"Carl Heinz Hohage Inh. Thomas Niederges\u00e4\u00df E.kfm.",
    "wof:placetype":"venue"
},
  "geometry": {"coordinates":[7.632205,51.215714],"type":"Point"}
}