{
  "type": "Feature",
  "properties": {
    "iso:country":"DE",
    "sg:address":"Zum Panrepel 24",
    "sg:city":"Bremen",
    "sg:phone":"+49 4942/1871640",
    "sg:postcode":"28307",
    "sg:province":"Bremen",
    "wof:name":"Aquametro Messtechnik Gmbh",
    "wof:placetype":"venue"
},
  "geometry": {"coordinates":[8.964818,53.045403],"type":"Point"}
}