{
  "type": "Feature",
  "properties": {
    "iso:country":"DE",
    "sg:address":"Hauptstr. 10",
    "sg:city":"Mannebach",
    "sg:phone":"+49 6581/4341",
    "sg:postcode":"54441",
    "sg:province":"Rheinland-Pfalz",
    "wof:name":"J. Und M. Strupp",
    "wof:placetype":"venue"
},
  "geometry": {"coordinates":[6.5100111961,49.6338348389],"type":"Point"}
}