{
  "type": "Feature",
  "properties": {
    "iso:country":"DE",
    "sg:address":"Ringstr. 4",
    "sg:city":"Emden",
    "sg:phone":"+49 4921/89010",
    "sg:postcode":"26721",
    "sg:province":"Niedersachsen",
    "wof:name":"Industrie-leasing Leokadia Beninga",
    "wof:placetype":"venue"
},
  "geometry": {"coordinates":[7.2023148537,53.3638916016],"type":"Point"}
}