{
  "type": "Feature",
  "properties": {
    "iso:country":"DE",
    "sg:address":"Am Brink 3",
    "sg:city":"Neustadt",
    "sg:phone":"+49 4950/361560",
    "sg:postcode":"31535",
    "sg:province":"Niedersachsen",
    "wof:name":"Kreissparkasse Hannover",
    "wof:placetype":"venue"
},
  "geometry": {"coordinates":[9.330998,52.53252],"type":"Point"}
}