{
  "type": "Feature",
  "properties": {
    "iso:country":"DE",
    "sg:address":"Alleestr. 40",
    "sg:city":"Duisburg",
    "sg:phone":"+49 203/550921",
    "sg:postcode":"47166",
    "sg:province":"Nordrhein-Westfalen",
    "wof:name":"Pizzeria N. Vergadoro",
    "wof:placetype":"venue"
},
  "geometry": {"coordinates":[6.7742772102,51.4896202087],"type":"Point"}
}