{
  "type": "Feature",
  "properties": {
    "iso:country":"DE",
    "sg:address":"Georgstr. 5",
    "sg:city":"Friedrichshafen",
    "sg:phone":"+49 7541/92240",
    "sg:postcode":"88046",
    "sg:province":"Baden-W\u00fcrttemberg",
    "wof:name":"Terminus Steuerberatungs Gmbh",
    "wof:placetype":"venue"
},
  "geometry": {"coordinates":[9.491638,47.652809],"type":"Point"}
}