{
  "type": "Feature",
  "properties": {
    "iso:country":"DE",
    "sg:address":"Birker Weg 5",
    "sg:city":"Remscheid",
    "sg:phone":"+49 2191/55553",
    "sg:postcode":"42899",
    "sg:province":"Nordrhein-Westfalen",
    "wof:name":"Erich Rauch Ohg",
    "wof:placetype":"venue"
},
  "geometry": {"coordinates":[7.2291297913,51.2086715698],"type":"Point"}
}