{
  "type": "Feature",
  "properties": {
    "iso:country":"DE",
    "sg:address":"Lindenweg 16",
    "sg:city":"Wichtshausen",
    "sg:phone":"+49 36846/60169",
    "sg:postcode":"98530",
    "sg:province":"Th\u00fcringen",
    "wof:name":"Voigt & Voigt Vertriebs Gmbh",
    "wof:placetype":"venue"
},
  "geometry": {"coordinates":[10.5738801956,50.5999221802],"type":"Point"}
}