{
  "type": "Feature",
  "properties": {
    "iso:country":"DE",
    "sg:address":"Am Teich 9",
    "sg:city":"Neum\u00fcnster",
    "sg:phone":"+49 4321/46600",
    "sg:postcode":"24534",
    "sg:province":"Schleswig-Holstein",
    "wof:name":"L\u00f6wen Kosmetik Studio",
    "wof:placetype":"venue"
},
  "geometry": {"coordinates":[9.982794,54.072987],"type":"Point"}
}