{
  "type": "Feature",
  "properties": {
    "iso:country":"DE",
    "sg:address":"Baumwall 7",
    "sg:city":"Hamburg",
    "sg:postcode":"20459",
    "sg:province":"Hamburg",
    "wof:name":"Sharco Sechzigste Verm\u00f6gens- Verwaltungsgesellschaft Mbh",
    "wof:placetype":"venue"
},
  "geometry": {"coordinates":[9.98188591,53.5445594788],"type":"Point"}
}