{
  "type": "Feature",
  "properties": {
    "iso:country":"DE",
    "sg:address":"Am Neuen Werk 4",
    "sg:city":"Rheda-Wiedenbr\u00fcck",
    "sg:phone":"+49 5242/92590",
    "sg:postcode":"33378",
    "sg:province":"Nordrhein-Westfalen",
    "wof:name":"Kreisheimst\u00e4tte Wiedenbr\u00fcck Gmbh",
    "wof:placetype":"venue"
},
  "geometry": {"coordinates":[8.3145904541,51.8332595825],"type":"Point"}
}