{
  "type": "Feature",
  "properties": {
    "iso:country":"DE",
    "sg:address":"Gro\u00dfe Str. 23",
    "sg:city":"Bad Iburg",
    "sg:phone":"+49 5403/332",
    "sg:postcode":"49186",
    "sg:province":"Niedersachsen",
    "wof:name":"Karl-heinz Hannibal",
    "wof:placetype":"venue"
},
  "geometry": {"coordinates":[8.0452919006,52.1563339233],"type":"Point"}
}