{
  "type": "Feature",
  "properties": {
    "iso:country":"DE",
    "sg:address":"Markt 8",
    "sg:city":"Saalfeld",
    "sg:phone":"+49 3671/33788",
    "sg:postcode":"07318",
    "sg:province":"Th\u00fcringen",
    "wof:name":"Eiscafe Venezia",
    "wof:placetype":"venue"
},
  "geometry": {"coordinates":[11.360082,50.647766],"type":"Point"}
}