{
  "type": "Feature",
  "properties": {
    "iso:country":"DE",
    "sg:address":"Hauptstr. 7",
    "sg:city":"M\u00fcden",
    "sg:phone":"+49 5375/498",
    "sg:postcode":"38539",
    "sg:province":"Niedersachsen",
    "wof:name":"Zimmermann",
    "wof:placetype":"venue"
},
  "geometry": {"coordinates":[10.3561382294,52.5277671814],"type":"Point"}
}