{
  "type": "Feature",
  "properties": {
    "iso:country":"DE",
    "sg:address":"Am Kirchfeld 10",
    "sg:city":"Calberlah",
    "sg:phone":"+49 5374/5056",
    "sg:postcode":"38547",
    "sg:province":"Niedersachsen",
    "wof:name":"U. Leist",
    "wof:placetype":"venue"
},
  "geometry": {"coordinates":[10.6429166794,52.4206848145],"type":"Point"}
}