{
  "type": "Feature",
  "properties": {
    "iso:country":"DE",
    "sg:address":"In den Hof\u00e4ckern 3",
    "sg:city":"Amorbach",
    "sg:postcode":"63916",
    "sg:province":"Bayern",
    "wof:name":"E-b-tec Gesellschaft F\u00fcr Energie- Und",
    "wof:placetype":"venue"
},
  "geometry": {"coordinates":[9.2232999802,49.6393623352],"type":"Point"}
}