{
  "type": "Feature",
  "properties": {
    "iso:country":"DE",
    "sg:address":"Seestr. 20",
    "sg:city":"Winterbach",
    "sg:phone":"+49 7181/73200",
    "sg:postcode":"73650",
    "sg:province":"Baden-W\u00fcrttemberg",
    "wof:name":"Walter Reiniger Gmbh",
    "wof:placetype":"venue"
},
  "geometry": {"coordinates":[9.481016,48.80135],"type":"Point"}
}