{
  "type": "Feature",
  "properties": {
    "iso:country":"DE",
    "sg:address":"Nymphenburger Stra\u00dfe 58",
    "sg:city":"M\u00fcnchen",
    "sg:postcode":"80335",
    "sg:province":"Bayern",
    "wof:name":"Classics International Models",
    "wof:placetype":"venue"
},
  "geometry": {"coordinates":[11.549374,48.149426],"type":"Point"}
}