{
  "type": "Feature",
  "properties": {
    "iso:country":"DE",
    "sg:address":"Carl-Zeiss-Str. 1",
    "sg:city":"Kaltenkirchen",
    "sg:phone":"+49 4191/4844",
    "sg:postcode":"24568",
    "sg:province":"Schleswig-Holstein",
    "wof:name":"B\u00fcro & Kopie Gmbh",
    "wof:placetype":"venue"
},
  "geometry": {"coordinates":[9.9766397476,53.8181686401],"type":"Point"}
}