{
  "type": "Feature",
  "properties": {
    "iso:country":"DE",
    "sg:address":"Perlenweg 2",
    "sg:city":"Overath",
    "sg:postcode":"51491",
    "sg:province":"Nordrhein-Westfalen",
    "wof:name":"Christiane Fanger Gmbh",
    "wof:placetype":"venue"
},
  "geometry": {"coordinates":[7.2597231865,50.9769973755],"type":"Point"}
}