{
  "type": "Feature",
  "properties": {
    "iso:country":"DE",
    "sg:address":"Thom\u00e4str. 79",
    "sg:city":"Soest",
    "sg:phone":"+49 2921/36250",
    "sg:postcode":"59494",
    "sg:province":"Nordrhein-Westfalen",
    "wof:name":"M. Treitschke",
    "wof:placetype":"venue"
},
  "geometry": {"coordinates":[8.1157512665,51.5699691772],"type":"Point"}
}