{
  "type": "Feature",
  "properties": {
    "iso:country":"DE",
    "sg:address":"K\u00f6tnerstr. 12",
    "sg:city":"Tostedt",
    "sg:postcode":"21255",
    "sg:province":"Niedersachsen",
    "wof:name":"R & V Bauplan Gmbh",
    "wof:placetype":"venue"
},
  "geometry": {"coordinates":[9.704669,53.281826],"type":"Point"}
}