{
  "type": "Feature",
  "properties": {
    "iso:country":"DE",
    "sg:address":"Gerberstr. 10",
    "sg:city":"Philippsburg",
    "sg:phone":"+49 7256/4270",
    "sg:postcode":"76661",
    "sg:province":"Baden-W\u00fcrttemberg",
    "wof:name":"Waldemar Grill",
    "wof:placetype":"venue"
},
  "geometry": {"coordinates":[8.45252,49.233593],"type":"Point"}
}