{
  "type": "Feature",
  "properties": {
    "iso:country":"DE",
    "sg:address":"Ittling 1",
    "sg:city":"Simmelsdorf",
    "sg:phone":"+49 9155/425",
    "sg:postcode":"91245",
    "sg:province":"Bayern",
    "wof:name":"Elfriede Schubert",
    "wof:placetype":"venue"
},
  "geometry": {"coordinates":[11.378985405,49.6350784302],"type":"Point"}
}