{
  "type": "Feature",
  "properties": {
    "iso:country":"DE",
    "sg:address":"Otto-D\u00fcrr-Str. 15-17",
    "sg:city":"Stuttgart",
    "sg:phone":"+49 711/8262054",
    "sg:postcode":"70435",
    "sg:province":"Baden-W\u00fcrttemberg",
    "wof:name":"Fedor Schoen Gmbh & Co.",
    "wof:placetype":"venue"
},
  "geometry": {"coordinates":[9.1431283951,48.8331756592],"type":"Point"}
}