{
  "type": "Feature",
  "properties": {
    "iso:country":"DE",
    "sg:address":"Stellenfelde 27",
    "sg:city":"Ottersberg",
    "sg:phone":"+49 4297/817000",
    "sg:postcode":"28870",
    "sg:province":"Niedersachsen",
    "wof:name":"Drucklufttechnik Heinz Linge",
    "wof:placetype":"venue"
},
  "geometry": {"coordinates":[9.176583,53.049961],"type":"Point"}
}