{
  "type": "Feature",
  "properties": {
    "iso:country":"DE",
    "sg:address":"Wolfshalde 81/1",
    "sg:city":"Ebersbach",
    "sg:postcode":"01561",
    "sg:province":"Sachsen",
    "wof:name":"Cc 203 Verwaltungsgesellschaft Mbh",
    "wof:placetype":"venue"
},
  "geometry": {"coordinates":[13.6318826675,51.2896308899],"type":"Point"}
}