{
  "type": "Feature",
  "properties": {
    "iso:country":"DE",
    "sg:address":"Germanenstr. 45",
    "sg:city":"Wuppertal",
    "sg:phone":"+49 202/500037",
    "sg:postcode":"42277",
    "sg:province":"Nordrhein-Westfalen",
    "wof:name":"Konzertdirektion Wylach Kg",
    "wof:placetype":"venue"
},
  "geometry": {"coordinates":[7.2084321976,51.2798538208],"type":"Point"}
}