{
  "type": "Feature",
  "properties": {
    "iso:country":"DE",
    "sg:address":"Ferdinandstr. 41",
    "sg:city":"Hamburg",
    "sg:phone":"+49 40/30081",
    "sg:postcode":"20095",
    "sg:province":"Hamburg",
    "wof:name":"Psn Pflanzenschutzhandel Nord Gmbh & Co. Kg",
    "wof:placetype":"venue"
},
  "geometry": {"coordinates":[9.9994707108,53.5535926819],"type":"Point"}
}