{
  "type": "Feature",
  "properties": {
    "iso:country":"DE",
    "sg:address":"Schopshofer Weg 8a",
    "sg:city":"Heiligenhaus",
    "sg:phone":"+49 2056/21106",
    "sg:postcode":"42579",
    "sg:province":"Nordrhein-Westfalen",
    "wof:name":"Lilli Daemen",
    "wof:placetype":"venue"
},
  "geometry": {"coordinates":[6.953185,51.328342],"type":"Point"}
}