{
  "type": "Feature",
  "properties": {
    "iso:country":"DE",
    "sg:address":"Esmarchstr. 3",
    "sg:city":"Bad Segeberg",
    "sg:phone":"+49 4551/82582",
    "sg:postcode":"23795",
    "sg:province":"Schleswig-Holstein",
    "wof:name":"Helmut Cziesla",
    "wof:placetype":"venue"
},
  "geometry": {"coordinates":[10.307897,53.948021],"type":"Point"}
}