{
  "type": "Feature",
  "properties": {
    "iso:country":"DE",
    "sg:address":"Bochumer Str. 66",
    "sg:city":"Recklinghausen",
    "sg:phone":"+49 2361/7654",
    "sg:postcode":"45661",
    "sg:province":"Nordrhein-Westfalen",
    "wof:name":"Helmut D\u00f6veling",
    "wof:placetype":"venue"
},
  "geometry": {"coordinates":[7.2131590843,51.5781745911],"type":"Point"}
}