{
  "type": "Feature",
  "properties": {
    "iso:country":"DE",
    "sg:address":"Elsener Str 20",
    "sg:city":"Paderborn",
    "sg:phone":"+49 5251/13400",
    "sg:postcode":"33102",
    "sg:province":"Nordrhein-Westfalen",
    "wof:name":"A. L\u00fccking Gmbh & Co Kg",
    "wof:placetype":"venue"
},
  "geometry": {"coordinates":[8.733234,51.725609],"type":"Point"}
}