{
  "type": "Feature",
  "properties": {
    "iso:country":"DE",
    "sg:address":"Hauffstr. 13",
    "sg:city":"Balingen",
    "sg:phone":"+49 7433/5861",
    "sg:postcode":"72336",
    "sg:province":"Baden-W\u00fcrttemberg",
    "wof:name":"B\u00e4ckerei Karahan Gmbh",
    "wof:placetype":"venue"
},
  "geometry": {"coordinates":[8.86126,48.277431],"type":"Point"}
}