{
  "type": "Feature",
  "properties": {
    "iso:country":"DE",
    "sg:address":"Bahnhofstr. 4",
    "sg:city":"Kirchzarten",
    "sg:phone":"+49 7661/4030",
    "sg:postcode":"79199",
    "sg:province":"Baden-W\u00fcrttemberg",
    "wof:name":"Dieter Meihofer",
    "wof:placetype":"venue"
},
  "geometry": {"coordinates":[7.9557051659,47.9658088684],"type":"Point"}
}