{
  "type": "Feature",
  "properties": {
    "iso:country":"DE",
    "sg:address":"Reimsbacher Str. 46",
    "sg:city":"Schmelz",
    "sg:phone":"+49 6887/92213",
    "sg:postcode":"66839",
    "sg:province":"Saarland",
    "wof:name":"G. Truar",
    "wof:placetype":"venue"
},
  "geometry": {"coordinates":[6.8369779587,49.4465255737],"type":"Point"}
}