{
  "type": "Feature",
  "properties": {
    "iso:country":"DE",
    "sg:address":"Hohenzollernstra\u00dfe 17",
    "sg:city":"D\u00fcsseldorf",
    "sg:phone":"+49 211/1793070",
    "sg:postcode":"40211",
    "sg:province":"Nordrhein-Westfalen",
    "wof:name":"\u00dcbersetzungsdienst D\u00fcchting Inh. J. Nobelen",
    "wof:placetype":"venue"
},
  "geometry": {"coordinates":[6.790199,51.225071],"type":"Point"}
}