{
  "type": "Feature",
  "properties": {
    "iso:country":"DE",
    "sg:address":"Helene-Huber-Str. 27",
    "sg:city":"Bad Wildbad",
    "sg:phone":"+49 7081/2337",
    "sg:postcode":"75323",
    "sg:province":"Baden-W\u00fcrttemberg",
    "wof:name":"E. Schill",
    "wof:placetype":"venue"
},
  "geometry": {"coordinates":[8.5483226776,48.7561302185],"type":"Point"}
}