{
  "type": "Feature",
  "properties": {
    "iso:country":"DE",
    "sg:address":"Bochumer Str. 136",
    "sg:city":"Bochum",
    "sg:phone":"+49 2327/82273",
    "sg:postcode":"44866",
    "sg:province":"Nordrhein-Westfalen",
    "wof:name":"Zeki Turhal",
    "wof:placetype":"venue"
},
  "geometry": {"coordinates":[7.1641402245,51.4804420471],"type":"Point"}
}