{
  "type": "Feature",
  "properties": {
    "iso:country":"DE",
    "sg:address":"Hofmarkstr.21",
    "sg:city":"Furth b. Landshut",
    "sg:phone":"+49 8704",
    "sg:postcode":"84095",
    "sg:province":"Bayern",
    "wof:name":"Der Hit --- Die Seilbahn-gondel Auf R\u00e4dern",
    "wof:placetype":"venue"
},
  "geometry": {"coordinates":[12.017107,48.595036],"type":"Point"}
}