{
  "type": "Feature",
  "properties": {
    "iso:country":"DE",
    "sg:address":"Bettina-von-Arnim-Str. 9",
    "sg:city":"Elmshorn",
    "sg:postcode":"25337",
    "sg:province":"Schleswig-Holstein",
    "wof:name":"Blue Bio Tech Gmbh",
    "wof:placetype":"venue"
},
  "geometry": {"coordinates":[9.6766738892,53.7516517639],"type":"Point"}
}