{
  "type": "Feature",
  "properties": {
    "iso:country":"DE",
    "sg:address":"Johann-Firlbeck-Str. 20",
    "sg:city":"Atting",
    "sg:phone":"+49 9421/22019",
    "sg:postcode":"94348",
    "sg:province":"Bayern",
    "wof:name":"Saatzucht Firlbeck Gmbh & Co. Kg",
    "wof:placetype":"venue"
},
  "geometry": {"coordinates":[12.486106,48.895733],"type":"Point"}
}