{
  "type": "Feature",
  "properties": {
    "iso:country":"DE",
    "sg:address":"An der Schlamme 36",
    "sg:city":"Werl",
    "sg:phone":"+49 2922/3398",
    "sg:postcode":"59457",
    "sg:province":"Nordrhein-Westfalen",
    "wof:name":"Josef Hanowski",
    "wof:placetype":"venue"
},
  "geometry": {"coordinates":[7.8831119537,51.5474205017],"type":"Point"}
}