{
  "type": "Feature",
  "properties": {
    "iso:country":"DE",
    "sg:address":"Hunnenstr. 17",
    "sg:city":"\u00d6hringen",
    "sg:phone":"+49 7941/98102",
    "sg:postcode":"74613",
    "sg:province":"Baden-W\u00fcrttemberg",
    "wof:name":"E. Petzel",
    "wof:placetype":"venue"
},
  "geometry": {"coordinates":[9.505746,49.199951],"type":"Point"}
}