{
  "type": "Feature",
  "properties": {
    "iso:country":"DE",
    "sg:address":"St.-Urban-Str. 14",
    "sg:city":"Oberkirch",
    "sg:phone":"+49 7802/3350",
    "sg:postcode":"77704",
    "sg:province":"Baden-W\u00fcrttemberg",
    "wof:name":"L. Maier",
    "wof:placetype":"venue"
},
  "geometry": {"coordinates":[8.0652170181,48.5573310852],"type":"Point"}
}