{
  "type": "Feature",
  "properties": {
    "iso:country":"DE",
    "sg:address":"Richard-Wagner-Str. 21",
    "sg:city":"Groitzsch",
    "sg:phone":"+49 34296/42091",
    "sg:postcode":"04539",
    "sg:province":"Sachsen",
    "wof:name":"Groitzscher Umweltservice Und Holzbau Gmbh",
    "wof:placetype":"venue"
},
  "geometry": {"coordinates":[12.277909,51.154877],"type":"Point"}
}