{
  "type": "Feature",
  "properties": {
    "iso:country":"DE",
    "sg:address":"Im Grund 12",
    "sg:city":"Aach",
    "sg:postcode":"78267",
    "sg:province":"Baden-W\u00fcrttemberg",
    "wof:name":"B\u00fcroprofil",
    "wof:placetype":"venue"
},
  "geometry": {"coordinates":[8.8502159119,47.8393821716],"type":"Point"}
}