{
  "type": "Feature",
  "properties": {
    "iso:country":"DE",
    "sg:address":"D\u00fcrerstr. 41",
    "sg:city":"Iserlohn",
    "sg:phone":"+49 2371/770603",
    "sg:postcode":"58636",
    "sg:province":"Nordrhein-Westfalen",
    "wof:name":"Media Consult Gmbh",
    "wof:placetype":"venue"
},
  "geometry": {"coordinates":[7.699983,51.385181],"type":"Point"}
}