{
  "type": "Feature",
  "properties": {
    "iso:country":"DE",
    "sg:address":"Friedrichstr. 4",
    "sg:city":"Waldshut-Tiengen",
    "sg:phone":"+49 7751/83090",
    "sg:postcode":"79761",
    "sg:province":"Baden-W\u00fcrttemberg",
    "wof:name":"Beckmann Fehrenbach Eckert Und Welz",
    "wof:placetype":"venue"
},
  "geometry": {"coordinates":[8.2179260254,47.6239776611],"type":"Point"}
}