{
  "type": "Feature",
  "properties": {
    "iso:country":"DE",
    "sg:address":"Am Klostergrund 19",
    "sg:city":"Sinzing",
    "sg:phone":"+49 941/31995",
    "sg:postcode":"93161",
    "sg:province":"Bayern",
    "wof:name":"Stefan Hanke",
    "wof:placetype":"venue"
},
  "geometry": {"coordinates":[12.0372562408,48.9882850647],"type":"Point"}
}