{
  "type": "Feature",
  "properties": {
    "iso:country":"DE",
    "sg:address":"Tannh\u00e4userring 87",
    "sg:city":"Mannheim",
    "sg:phone":"+49 621/813625",
    "sg:postcode":"68199",
    "sg:province":"Baden-W\u00fcrttemberg",
    "wof:name":"Gerhard Rappenecker Finanzberater",
    "wof:placetype":"venue"
},
  "geometry": {"coordinates":[8.473400116,49.4540367126],"type":"Point"}
}