{
  "type": "Feature",
  "properties": {
    "iso:country":"DE",
    "sg:address":"Luitpoldstr. 14",
    "sg:city":"Lauf",
    "sg:phone":"+49 9123/2135",
    "sg:postcode":"91207",
    "sg:province":"Bayern",
    "wof:name":"Klaus-j\u00fcrgen Ryba",
    "wof:placetype":"venue"
},
  "geometry": {"coordinates":[11.2803106308,49.5077438354],"type":"Point"}
}