{
  "type": "Feature",
  "properties": {
    "iso:country":"DE",
    "sg:address":"H\u00f6hnweg 8",
    "sg:city":"R\u00f6dental",
    "sg:phone":"+49 9563/3218",
    "sg:postcode":"96472",
    "sg:province":"Bayern",
    "wof:name":"Arno B\u00e4tz",
    "wof:placetype":"venue"
},
  "geometry": {"coordinates":[11.031159,50.276718],"type":"Point"}
}