{
  "type": "Feature",
  "properties": {
    "iso:country":"DE",
    "sg:address":"Erlengrundstr. 37",
    "sg:city":"\u00d6hringen",
    "sg:phone":"+49 7948/518",
    "sg:postcode":"74613",
    "sg:province":"Baden-W\u00fcrttemberg",
    "wof:name":"Hermann Sch\u00e4fter Schotter Und Mahlwerk Verwaltungs Gmbh",
    "wof:placetype":"venue"
},
  "geometry": {"coordinates":[9.436291,49.241009],"type":"Point"}
}