{
  "type": "Feature",
  "properties": {
    "iso:country":"DE",
    "sg:address":"Vor dem Hohen Tor 14",
    "sg:city":"Wanzleben",
    "sg:phone":"+49 39209/2725",
    "sg:postcode":"39164",
    "sg:province":"Sachsen-Anhalt",
    "wof:name":"B\u00fcro- Und Informationssysteme Meinecke & Oeltze Gmbh",
    "wof:placetype":"venue"
},
  "geometry": {"coordinates":[11.4486207962,52.056728363],"type":"Point"}
}