{
  "type": "Feature",
  "properties": {
    "iso:country":"DE",
    "sg:address":"Bornheimer Landstr. 48",
    "sg:city":"Frankfurt",
    "sg:phone":"+49 69/448088",
    "sg:postcode":"60316",
    "sg:province":"Hessen",
    "wof:name":"A. Drissler Gmbh",
    "wof:placetype":"venue"
},
  "geometry": {"coordinates":[8.6944618225,50.122833252],"type":"Point"}
}