{
  "type": "Feature",
  "properties": {
    "iso:country":"DE",
    "sg:address":"In den Fahrg\u00e4rten 10",
    "sg:city":"Waldsee",
    "sg:phone":"+49 6236/54910",
    "sg:postcode":"67165",
    "sg:province":"Rheinland-Pfalz",
    "wof:name":"E. Kamb",
    "wof:placetype":"venue"
},
  "geometry": {"coordinates":[8.4411153793,49.3938789368],"type":"Point"}
}