{
  "type": "Feature",
  "properties": {
    "iso:country":"DE",
    "sg:address":"R\u00fcckersdorfer Str. 13",
    "sg:city":"R\u00f6thenbach",
    "sg:phone":"+49 911/5709440",
    "sg:postcode":"90552",
    "sg:province":"Bayern",
    "wof:name":"Georgios Vrakas",
    "wof:placetype":"venue"
},
  "geometry": {"coordinates":[11.2398509979,49.483455658],"type":"Point"}
}