{
  "type": "Feature",
  "properties": {
    "iso:country":"DE",
    "sg:address":"Rischkampweg 21",
    "sg:city":"Hessisch Oldendorf",
    "sg:phone":"+49 5152/3122",
    "sg:postcode":"31840",
    "sg:province":"Niedersachsen",
    "wof:name":"Hermann Stock",
    "wof:placetype":"venue"
},
  "geometry": {"coordinates":[9.213429,52.146622],"type":"Point"}
}