{
  "type": "Feature",
  "properties": {
    "iso:country":"DE",
    "sg:address":"Fortunastr. 12",
    "sg:city":"W\u00fclfrath",
    "sg:phone":"+49 2058/7860",
    "sg:postcode":"42489",
    "sg:province":"Nordrhein-Westfalen",
    "wof:name":"Breyer Gmbh",
    "wof:placetype":"venue"
},
  "geometry": {"coordinates":[7.014735,51.277473],"type":"Point"}
}