{
  "type": "Feature",
  "properties": {
    "iso:country":"DE",
    "sg:address":"Elsterweg 10",
    "sg:city":"Wolfsburg",
    "sg:phone":"+49 4953/627397",
    "sg:postcode":"38442",
    "sg:province":"Niedersachsen",
    "wof:name":"Sparkasse Gifhorn-wolfsburg",
    "wof:placetype":"venue"
},
  "geometry": {"coordinates":[10.71601,52.418442],"type":"Point"}
}