{
  "type": "Feature",
  "properties": {
    "iso:country":"DE",
    "sg:address":"Alte Landstr. 22",
    "sg:city":"Bad Bentheim",
    "sg:phone":"+49 5924/271",
    "sg:postcode":"48455",
    "sg:province":"Niedersachsen",
    "wof:name":"Restaurant Niermann",
    "wof:placetype":"venue"
},
  "geometry": {"coordinates":[7.0741138458,52.3038024902],"type":"Point"}
}