{
  "type": "Feature",
  "properties": {
    "iso:country":"DE",
    "sg:address":"Castroper Hellweg 406",
    "sg:city":"Bochum",
    "sg:phone":"+49 234/85702",
    "sg:postcode":"44805",
    "sg:province":"Nordrhein-Westfalen",
    "wof:name":"Dresdner Bank",
    "wof:placetype":"venue"
},
  "geometry": {"coordinates":[7.2873,51.525478],"type":"Point"}
}