{
  "type": "Feature",
  "properties": {
    "iso:country":"DE",
    "sg:address":"Dillinger Str. 27",
    "sg:city":"Donauw\u00f6rth",
    "sg:phone":"+49 906/706810",
    "sg:postcode":"86609",
    "sg:province":"Bayern",
    "wof:name":"Mevlana Fleisch- Und Wurstwaren Gmbh",
    "wof:placetype":"venue"
},
  "geometry": {"coordinates":[10.7679548264,48.7164039612],"type":"Point"}
}