{
  "type": "Feature",
  "properties": {
    "iso:country":"DE",
    "sg:address":"Robert-Bosch-Str. 23",
    "sg:city":"Waldstetten",
    "sg:phone":"+49 7171/44060",
    "sg:postcode":"73550",
    "sg:province":"Baden-W\u00fcrttemberg",
    "wof:name":"Franz Maier Mechanische Werkst\u00e4tte Gmbh",
    "wof:placetype":"venue"
},
  "geometry": {"coordinates":[9.83348,48.769794],"type":"Point"}
}