{
  "type": "Feature",
  "properties": {
    "iso:country":"DE",
    "sg:address":"Naumburger Str. 19",
    "sg:city":"Kassel",
    "sg:phone":"+49 561/894430",
    "sg:postcode":"34127",
    "sg:province":"Hessen",
    "wof:name":"Frank Reinigungssysteme Gmbh",
    "wof:placetype":"venue"
},
  "geometry": {"coordinates":[9.476385,51.324486],"type":"Point"}
}