{
  "type": "Feature",
  "properties": {
    "iso:country":"DE",
    "sg:address":"Hauptstr. 104",
    "sg:city":"Offenburg",
    "sg:phone":"+49 781/25562",
    "sg:postcode":"77652",
    "sg:province":"Baden-W\u00fcrttemberg",
    "wof:name":"B\u00fcrgerstube",
    "wof:placetype":"venue"
},
  "geometry": {"coordinates":[7.9426460266,48.4683914185],"type":"Point"}
}