{
  "type": "Feature",
  "properties": {
    "iso:country":"DE",
    "sg:address":"Dreekamp 2",
    "sg:city":"Aurich",
    "sg:phone":"+49 4941/180810",
    "sg:postcode":"26605",
    "sg:province":"Niedersachsen",
    "wof:name":"Inline-center-sportlaufbahn Beteiligungs Gmbh",
    "wof:placetype":"venue"
},
  "geometry": {"coordinates":[7.461053,53.470627],"type":"Point"}
}