{
  "type": "Feature",
  "properties": {
    "iso:country":"DE",
    "sg:address":"Zeppelinstr. 4",
    "sg:city":"Buseck",
    "sg:phone":"+49 6408/90110",
    "sg:postcode":"35418",
    "sg:province":"Hessen",
    "wof:name":"Weber Schwei\u00dftechnik Gmbh",
    "wof:placetype":"venue"
},
  "geometry": {"coordinates":[8.7987909317,50.6003303528],"type":"Point"}
}