{
  "type": "Feature",
  "properties": {
    "iso:country":"DE",
    "sg:address":"Ingolst\u00e4dter Str. 27",
    "sg:city":"Pfaffenhofen",
    "sg:phone":"+49 8441/803454",
    "sg:postcode":"85276",
    "sg:province":"Bayern",
    "wof:name":"Jakob Ga\u00dfner",
    "wof:placetype":"venue"
},
  "geometry": {"coordinates":[11.5071344376,48.5315055847],"type":"Point"}
}