{
  "type": "Feature",
  "properties": {
    "iso:country":"DE",
    "sg:address":"Kelterstr. 32",
    "sg:city":"Markgr\u00f6ningen",
    "sg:phone":"+49 7147/3716",
    "sg:postcode":"71706",
    "sg:province":"Baden-W\u00fcrttemberg",
    "wof:name":"Kleintierzuchtverein Unterriexingen",
    "wof:placetype":"venue"
},
  "geometry": {"coordinates":[9.0632200241,48.9371757507],"type":"Point"}
}