{
  "type": "Feature",
  "properties": {
    "iso:country":"DE",
    "sg:address":"Monschauer Str. 219",
    "sg:city":"D\u00fcren",
    "sg:phone":"+49 2421/96700",
    "sg:postcode":"52355",
    "sg:province":"Nordrhein-Westfalen",
    "wof:name":"Hans-peter Peters Gmbh",
    "wof:placetype":"venue"
},
  "geometry": {"coordinates":[6.4657111168,50.7865486145],"type":"Point"}
}