{
  "type": "Feature",
  "properties": {
    "iso:country":"DE",
    "sg:address":"Heinrich-Pesch-Str. 59",
    "sg:city":"M\u00f6nchengladbach",
    "sg:phone":"+49 2166/42268",
    "sg:postcode":"41239",
    "sg:province":"Nordrhein-Westfalen",
    "wof:name":"Bodo Blume Rechtsanwalt",
    "wof:placetype":"venue"
},
  "geometry": {"coordinates":[6.4364299774,51.1729049683],"type":"Point"}
}