{
  "type": "Feature",
  "properties": {
    "iso:country":"DE",
    "sg:address":"Marktstr. 1",
    "sg:city":"Steinheim",
    "sg:phone":"+49 5233/5232",
    "sg:postcode":"32839",
    "sg:province":"Nordrhein-Westfalen",
    "wof:name":"Engel-apotheke",
    "wof:placetype":"venue"
},
  "geometry": {"coordinates":[9.09407,51.866138],"type":"Point"}
}