{
  "type": "Feature",
  "properties": {
    "iso:country":"DE",
    "sg:address":"Hammerm\u00fchle 22",
    "sg:city":"Overath",
    "sg:postcode":"51491",
    "sg:province":"Nordrhein-Westfalen",
    "wof:name":"S\u00fcdstern Hochbau Gmbh",
    "wof:placetype":"venue"
},
  "geometry": {"coordinates":[7.293724,50.939079],"type":"Point"}
}