{
  "type": "Feature",
  "properties": {
    "iso:country":"DE",
    "sg:address":"Hauptstr. 18",
    "sg:city":"Niederrieden",
    "sg:phone":"+49 8335/774",
    "sg:postcode":"87767",
    "sg:province":"Bayern",
    "wof:name":"Kath. Pfarramt St. Georg",
    "wof:placetype":"venue"
},
  "geometry": {"coordinates":[10.1852073669,48.0577507019],"type":"Point"}
}