{
  "type": "Feature",
  "properties": {
    "iso:country":"DE",
    "sg:address":"Steinhuder Str. 1a",
    "sg:city":"Wunstorf",
    "sg:phone":"+49 5031/16472",
    "sg:postcode":"31515",
    "sg:province":"Niedersachsen",
    "wof:name":"D. Kruppa Und H. Gollub",
    "wof:placetype":"venue"
},
  "geometry": {"coordinates":[9.3764095306,52.4172744751],"type":"Point"}
}