{
  "type": "Feature",
  "properties": {
    "iso:country":"DE",
    "sg:address":"Bundesstr. 1",
    "sg:city":"Gundelfingen",
    "sg:phone":"+49 761/5932039",
    "sg:postcode":"79194",
    "sg:province":"Baden-W\u00fcrttemberg",
    "wof:name":"Babyone Baby- Und Kinderbedarf Gmbh",
    "wof:placetype":"venue"
},
  "geometry": {"coordinates":[7.8642878532,48.0372123718],"type":"Point"}
}