{
  "type": "Feature",
  "properties": {
    "iso:country":"DE",
    "sg:address":"Am Alten Teich 11",
    "sg:city":"Meerbusch",
    "sg:phone":"+49 2150/700644",
    "sg:postcode":"40668",
    "sg:province":"Nordrhein-Westfalen",
    "wof:name":"Peter Kessels Architekt",
    "wof:placetype":"venue"
},
  "geometry": {"coordinates":[6.686334,51.304005],"type":"Point"}
}