{
  "type": "Feature",
  "properties": {
    "iso:country":"DE",
    "sg:address":"Luisenstr. 10",
    "sg:city":"Freiburg",
    "sg:phone":"+49 761/33251",
    "sg:postcode":"79098",
    "sg:province":"Baden-W\u00fcrttemberg",
    "wof:name":"Ortrud Einfeld Rechtsanw\u00e4ltin",
    "wof:placetype":"venue"
},
  "geometry": {"coordinates":[7.8498840332,47.9907341003],"type":"Point"}
}