{
  "type": "Feature",
  "properties": {
    "iso:country":"DE",
    "sg:address":"Egestorfer Str. 4",
    "sg:city":"Barsinghausen",
    "sg:postcode":"30890",
    "sg:province":"Niedersachsen",
    "wof:name":"Bibi Spielhallenbetriebs- Gesellschaft Mbh",
    "wof:placetype":"venue"
},
  "geometry": {"coordinates":[9.4816503525,52.2940292358],"type":"Point"}
}