{
  "type": "Feature",
  "properties": {
    "iso:country":"DE",
    "sg:address":"Massener Str. 26",
    "sg:city":"Unna",
    "sg:phone":"+49 2303/12063",
    "sg:postcode":"59423",
    "sg:province":"Nordrhein-Westfalen",
    "wof:name":"Joaquim Ribeiro",
    "wof:placetype":"venue"
},
  "geometry": {"coordinates":[7.6887450218,51.5343132019],"type":"Point"}
}