{
  "type": "Feature",
  "properties": {
    "iso:country":"DE",
    "sg:address":"Sulzbacher Str. 24",
    "sg:city":"N\u00fcrnberg",
    "sg:phone":"+49 911/5882711",
    "sg:postcode":"90489",
    "sg:province":"Bayern",
    "wof:name":"Aral Ag",
    "wof:placetype":"venue"
},
  "geometry": {"coordinates":[11.0930166245,49.4578819275],"type":"Point"}
}