{
  "type": "Feature",
  "properties": {
    "iso:country":"DE",
    "sg:address":"Bergederweg 36",
    "sg:city":"Soest",
    "sg:phone":"+49 700386544533",
    "sg:postcode":"59494",
    "sg:province":"Nordrhein-Westfalen",
    "wof:name":"Funkhilfe Kreis Soest",
    "wof:placetype":"venue"
},
  "geometry": {"coordinates":[8.12188,51.556408],"type":"Point"}
}