{
  "type": "Feature",
  "properties": {
    "iso:country":"DE",
    "sg:address":"Gartenweg 10",
    "sg:city":"Marburg",
    "sg:phone":"+49 6421/46705",
    "sg:postcode":"35043",
    "sg:province":"Hessen",
    "wof:name":"Willi Linne",
    "wof:placetype":"venue"
},
  "geometry": {"coordinates":[8.7712316513,50.7755355835],"type":"Point"}
}