{
  "type": "Feature",
  "properties": {
    "iso:country":"DE",
    "sg:address":"Ludwig-Thoma-Weg 7",
    "sg:city":"Baierbrunn",
    "sg:phone":"+49 89/1786550",
    "sg:postcode":"82065",
    "sg:province":"Bayern",
    "wof:name":"Seefelder",
    "wof:placetype":"venue"
},
  "geometry": {"coordinates":[11.4833469391,48.0283164978],"type":"Point"}
}