{
  "type": "Feature",
  "properties": {
    "iso:country":"DE",
    "sg:address":"Husener Eichwaldstr. 222",
    "sg:city":"Dortmund",
    "sg:phone":"+49 231/281225",
    "sg:postcode":"44319",
    "sg:province":"Nordrhein-Westfalen",
    "wof:name":"Theodor Keutken",
    "wof:placetype":"venue"
},
  "geometry": {"coordinates":[7.5929160118,51.5498733521],"type":"Point"}
}