{
  "type": "Feature",
  "properties": {
    "iso:country":"DE",
    "sg:address":"Schwabacher Str. 15",
    "sg:city":"F\u00fcrth",
    "sg:phone":"+49 911/771968",
    "sg:postcode":"90762",
    "sg:province":"Bayern",
    "wof:name":"Pfaff N\u00e4hzentrum B\u00e4r Gmbh",
    "wof:placetype":"venue"
},
  "geometry": {"coordinates":[10.9888944626,49.4742507935],"type":"Point"}
}