{
  "type": "Feature",
  "properties": {
    "iso:country":"DE",
    "sg:address":"Sulzbachstr. 2",
    "sg:city":"Saarbr\u00fccken",
    "sg:phone":"+49 681/34499",
    "sg:postcode":"66111",
    "sg:province":"Saarland",
    "wof:name":"Schubert",
    "wof:placetype":"venue"
},
  "geometry": {"coordinates":[6.9928078651,49.2367553711],"type":"Point"}
}