{
  "type": "Feature",
  "properties": {
    "iso:country":"DE",
    "sg:address":"Hauptstr. 12",
    "sg:city":"P\u00f6litz",
    "sg:phone":"+49 4531/81892",
    "sg:postcode":"23847",
    "sg:province":"Schleswig-Holstein",
    "wof:name":"M. Freitag",
    "wof:placetype":"venue"
},
  "geometry": {"coordinates":[10.37702,53.775299],"type":"Point"}
}