{
  "type": "Feature",
  "properties": {
    "iso:country":"DE",
    "sg:address":"Kaiserstr. 30",
    "sg:city":"Hungen",
    "sg:phone":"+49 6402/9537",
    "sg:postcode":"35410",
    "sg:province":"Hessen",
    "wof:name":"Werner Frutig",
    "wof:placetype":"venue"
},
  "geometry": {"coordinates":[8.894246,50.476173],"type":"Point"}
}