{
  "type": "Feature",
  "properties": {
    "iso:country":"DE",
    "sg:address":"Sudetenstr. 13",
    "sg:city":"Gro\u00df-Umstadt",
    "sg:phone":"+49 6078/6505",
    "sg:postcode":"64823",
    "sg:province":"Hessen",
    "wof:name":"Christel May",
    "wof:placetype":"venue"
},
  "geometry": {"coordinates":[8.9484796524,49.9009780884],"type":"Point"}
}