{
  "type": "Feature",
  "properties": {
    "iso:country":"DE",
    "sg:address":"Bahnhofstr 4",
    "sg:city":"Syke",
    "sg:phone":"+49 4242/66177",
    "sg:postcode":"28857",
    "sg:province":"Niedersachsen",
    "wof:name":"Kreissparkasse Syke",
    "wof:placetype":"venue"
},
  "geometry": {"coordinates":[8.815509,52.915005],"type":"Point"}
}