{
  "type": "Feature",
  "properties": {
    "iso:country":"DE",
    "sg:address":"Koppelstr. 8",
    "sg:city":"F\u00fcrstenau",
    "sg:phone":"+49 5901/2208",
    "sg:postcode":"49584",
    "sg:province":"Niedersachsen",
    "wof:name":"G. Elfring Bestattungen Inh. Kurt Theilmann",
    "wof:placetype":"venue"
},
  "geometry": {"coordinates":[7.67648,52.514858],"type":"Point"}
}