{
  "type": "Feature",
  "properties": {
    "iso:country":"DE",
    "sg:address":"Ringstr 28",
    "sg:city":"Fellbach",
    "sg:phone":"+49 711/5719571",
    "sg:postcode":"70736",
    "sg:province":"Baden-W\u00fcrttemberg",
    "wof:name":"Hts Hydraulische Transportsysteme Gmbh",
    "wof:placetype":"venue"
},
  "geometry": {"coordinates":[9.277651,48.820724],"type":"Point"}
}