{
  "type": "Feature",
  "properties": {
    "iso:country":"DE",
    "sg:address":"Hauptstr. 87",
    "sg:city":"Donzdorf",
    "sg:postcode":"73072",
    "sg:province":"Baden-W\u00fcrttemberg",
    "wof:name":"D\u00f6bel & Kaya Gmbh",
    "wof:placetype":"venue"
},
  "geometry": {"coordinates":[9.811509,48.687809],"type":"Point"}
}