{
  "type": "Feature",
  "properties": {
    "iso:country":"DE",
    "sg:address":"Riedstr. 31",
    "sg:city":"Freiberg",
    "sg:phone":"+49 7141/71738",
    "sg:postcode":"71691",
    "sg:province":"Baden-W\u00fcrttemberg",
    "wof:name":"Gerhard Dworschak Mech. Werkstatt",
    "wof:placetype":"venue"
},
  "geometry": {"coordinates":[9.180355,48.932331],"type":"Point"}
}