{
  "type": "Feature",
  "properties": {
    "iso:country":"DE",
    "sg:address":"Lange Str. 12",
    "sg:city":"Hardegsen",
    "sg:phone":"+49 5505/5874",
    "sg:postcode":"37181",
    "sg:province":"Niedersachsen",
    "wof:name":"Michael Hahn Praxis F\u00fcr Krankengymnastik",
    "wof:placetype":"venue"
},
  "geometry": {"coordinates":[9.829986,51.650719],"type":"Point"}
}