{
  "type": "Feature",
  "properties": {
    "iso:country":"DE",
    "sg:address":"Friedrich-Ebert-Str. 51",
    "sg:city":"Schwandorf",
    "sg:phone":"+49 9431/1614",
    "sg:postcode":"92421",
    "sg:province":"Bayern",
    "wof:name":"Uwe Joller",
    "wof:placetype":"venue"
},
  "geometry": {"coordinates":[12.108789444,49.3267822266],"type":"Point"}
}