{
  "type": "Feature",
  "properties": {
    "iso:country":"DE",
    "sg:address":"Rotdornschleife 29",
    "sg:city":"Hamm",
    "sg:phone":"+49 2381/13339",
    "sg:postcode":"59063",
    "sg:province":"Nordrhein-Westfalen",
    "wof:name":"Heinz Kambeck Rechtsanwalt",
    "wof:placetype":"venue"
},
  "geometry": {"coordinates":[7.8378520012,51.6776733398],"type":"Point"}
}