{
  "type": "Feature",
  "properties": {
    "iso:country":"DE",
    "sg:address":"Alte Dorfstr. 70",
    "sg:city":"Probsteierhagen",
    "sg:phone":"+49 4348/912715",
    "sg:postcode":"24253",
    "sg:province":"Schleswig-Holstein",
    "wof:name":"Elektro Rethwisch Inh. H.-h. Rethwisch",
    "wof:placetype":"venue"
},
  "geometry": {"coordinates":[10.2917699814,54.3633804321],"type":"Point"}
}