{
  "type": "Feature",
  "properties": {
    "iso:country":"DE",
    "sg:address":"Auf dem H\u00fcls 16",
    "sg:city":"Mettmann",
    "sg:phone":"+49 2104/75561",
    "sg:postcode":"40822",
    "sg:province":"Nordrhein-Westfalen",
    "wof:name":"Gather Equity Gmbh",
    "wof:placetype":"venue"
},
  "geometry": {"coordinates":[6.954788,51.254116],"type":"Point"}
}