{
  "type": "Feature",
  "properties": {
    "iso:country":"DE",
    "sg:city":"Langen",
    "sg:phone":"+49 6103/921229",
    "sg:postcode":"63225",
    "sg:province":"Hessen",
    "wof:name":"Secon Gmbh",
    "wof:placetype":"venue"
},
  "geometry": {"coordinates":[8.66357,49.990059],"type":"Point"}
}