{
  "type": "Feature",
  "properties": {
    "iso:country":"DE",
    "sg:address":"Gutenbergstr. 53",
    "sg:city":"Dortmund",
    "sg:phone":"+49 231/525387",
    "sg:postcode":"44139",
    "sg:province":"Nordrhein-Westfalen",
    "wof:name":"Hartmut Ellend",
    "wof:placetype":"venue"
},
  "geometry": {"coordinates":[7.4639940262,51.5083503723],"type":"Point"}
}