{
  "type": "Feature",
  "properties": {
    "iso:country":"DE",
    "sg:address":"Mannheimer Str. 13",
    "sg:city":"Hockenheim",
    "sg:phone":"+49 6205/20290",
    "sg:postcode":"68766",
    "sg:province":"Baden-W\u00fcrttemberg",
    "wof:name":"Reifen-sessler Verwaltungs Gmbh",
    "wof:placetype":"venue"
},
  "geometry": {"coordinates":[8.5361785889,49.3306350708],"type":"Point"}
}