{
  "type": "Feature",
  "properties": {
    "iso:country":"DE",
    "sg:address":"Grillenburger Str. 8",
    "sg:city":"Dresden",
    "sg:postcode":"01159",
    "sg:province":"Sachsen",
    "wof:name":"Dresden Mobil-communication",
    "wof:placetype":"venue"
},
  "geometry": {"coordinates":[13.687984,51.040886],"type":"Point"}
}