{
  "type": "Feature",
  "properties": {
    "iso:country":"DE",
    "sg:address":"Hollich 142",
    "sg:city":"Steinfurt",
    "sg:phone":"+49 2551/5689",
    "sg:postcode":"48565",
    "sg:province":"Nordrhein-Westfalen",
    "wof:name":"G. Palstring Landwirtschaftl. Lohnbetrieb",
    "wof:placetype":"venue"
},
  "geometry": {"coordinates":[7.392903,52.149246],"type":"Point"}
}