{
  "type": "Feature",
  "properties": {
    "iso:country":"DE",
    "sg:address":"Weinstr. 147b",
    "sg:city":"Offenburg",
    "sg:phone":"+49 781/9489030",
    "sg:postcode":"77654",
    "sg:province":"Baden-W\u00fcrttemberg",
    "wof:name":"Hertwig Gmbh",
    "wof:placetype":"venue"
},
  "geometry": {"coordinates":[7.973134,48.480545],"type":"Point"}
}