{
  "type": "Feature",
  "properties": {
    "iso:country":"DE",
    "sg:address":"Ringstr. 4",
    "sg:city":"Magstadt",
    "sg:phone":"+49 7159/41305",
    "sg:postcode":"71106",
    "sg:province":"Baden-W\u00fcrttemberg",
    "wof:name":"Karl Fahrner",
    "wof:placetype":"venue"
},
  "geometry": {"coordinates":[8.9685506821,48.7469520569],"type":"Point"}
}