{
  "type": "Feature",
  "properties": {
    "iso:country":"DE",
    "sg:address":"Karl-Liebknecht-Str. 59",
    "sg:city":"Leipzig",
    "sg:phone":"+49 341/390040",
    "sg:postcode":"04275",
    "sg:province":"Sachsen",
    "wof:name":"Handorn Und Wagner Rechtsanw\u00e4lte",
    "wof:placetype":"venue"
},
  "geometry": {"coordinates":[12.3738336563,51.3252372742],"type":"Point"}
}