{
  "type": "Feature",
  "properties": {
    "iso:country":"DE",
    "sg:address":"Hauptstr. 1",
    "sg:city":"Heuchelheim",
    "sg:phone":"+49 6238/3171",
    "sg:postcode":"67259",
    "sg:province":"Rheinland-Pfalz",
    "wof:name":"Karl-heinz Schneider",
    "wof:placetype":"venue"
},
  "geometry": {"coordinates":[8.058692,49.144806],"type":"Point"}
}