{
  "type": "Feature",
  "properties": {
    "iso:country":"DE",
    "sg:address":"Am Steinberg 35",
    "sg:city":"M\u00f6nchengladbach",
    "sg:phone":"+49 4921/6189920",
    "sg:postcode":"41061",
    "sg:province":"Nordrhein-Westfalen",
    "wof:name":"Linssen Elektro-handels Gmbh",
    "wof:placetype":"venue"
},
  "geometry": {"coordinates":[6.422208,51.199455],"type":"Point"}
}