{
  "type": "Feature",
  "properties": {
    "iso:country":"DE",
    "sg:address":"Rheinstr. 60",
    "sg:city":"Wilhelmshaven",
    "sg:phone":"+49 4421/33691",
    "sg:postcode":"26382",
    "sg:province":"Niedersachsen",
    "wof:name":"Mathias Gerhards Leder- Und Schuhmacherbedarf",
    "wof:placetype":"venue"
},
  "geometry": {"coordinates":[8.1293458939,53.5162734985],"type":"Point"}
}