{
  "type": "Feature",
  "properties": {
    "iso:country":"DE",
    "sg:address":"Ringstr. 1",
    "sg:city":"H\u00f6sbach",
    "sg:phone":"+49 6024/9314",
    "sg:postcode":"63768",
    "sg:province":"Bayern",
    "wof:name":"Norbert M\u00fcller",
    "wof:placetype":"venue"
},
  "geometry": {"coordinates":[9.199108,50.005611],"type":"Point"}
}