{
  "type": "Feature",
  "properties": {
    "iso:country":"DE",
    "sg:address":"Oberer Markt 13",
    "sg:city":"Neunkirchen",
    "sg:phone":"+49 6821/22657",
    "sg:postcode":"66538",
    "sg:province":"Saarland",
    "wof:name":"L\u00f6wen-apotheke",
    "wof:placetype":"venue"
},
  "geometry": {"coordinates":[7.180371,49.34304],"type":"Point"}
}