{
  "type": "Feature",
  "properties": {
    "iso:country":"DE",
    "sg:address":"Winzerstr. 7",
    "sg:city":"Keltern",
    "sg:phone":"+49 7236/267",
    "sg:postcode":"75210",
    "sg:province":"Baden-W\u00fcrttemberg",
    "wof:name":"Weinbaugenossenschaft Ellmendingen Eg",
    "wof:placetype":"venue"
},
  "geometry": {"coordinates":[8.5816516876,48.9050483704],"type":"Point"}
}