{
  "type": "Feature",
  "properties": {
    "iso:country":"DE",
    "sg:address":"Lindenstr. 12-22",
    "sg:city":"H\u00f6hr-Grenzhausen",
    "sg:phone":"+49 2624/160",
    "sg:postcode":"56203",
    "sg:province":"Rheinland-Pfalz",
    "wof:name":"Rastal Verwaltungs-gmbh",
    "wof:placetype":"venue"
},
  "geometry": {"coordinates":[7.657955,50.443085],"type":"Point"}
}