{
  "type": "Feature",
  "properties": {
    "iso:country":"DE",
    "sg:address":"Zum Telegrafenberg 11",
    "sg:city":"Bleckede / Breetze",
    "sg:postcode":"21354",
    "sg:province":"Niedersachsen",
    "wof:name":"Bleckede.com Firmen / Jobb\u00f6rse / Bildergalerie",
    "wof:placetype":"venue"
},
  "geometry": {"coordinates":[10.702571,53.264683],"type":"Point"}
}