{
  "type": "Feature",
  "properties": {
    "iso:country":"DE",
    "sg:address":"Feuerbachstr.",
    "sg:city":"Berlin",
    "sg:phone":"+49 30/7912786",
    "sg:postcode":"12163",
    "sg:province":"Berlin",
    "wof:name":"Elzbieta Suchanek-orenczuk",
    "wof:placetype":"venue"
},
  "geometry": {"coordinates":[13.339495,52.464554],"type":"Point"}
}