{
  "type": "Feature",
  "properties": {
    "iso:country":"DE",
    "sg:address":"Hauptstr. 7",
    "sg:city":"Hohenlinden",
    "sg:phone":"+49 8124/9534",
    "sg:postcode":"85664",
    "sg:province":"Bayern",
    "wof:name":"Forst-apotheke Inh. Uwe Scheerschmidt",
    "wof:placetype":"venue"
},
  "geometry": {"coordinates":[11.995635,48.157822],"type":"Point"}
}