{
  "type": "Feature",
  "properties": {
    "iso:country":"DE",
    "sg:address":"Ohlsdorfer Str. 50",
    "sg:city":"Hamburg",
    "sg:postcode":"22999",
    "sg:province":"Hamburg",
    "wof:name":"International Trading Hamburg",
    "wof:placetype":"venue"
},
  "geometry": {"coordinates":[9.99244,53.553341],"type":"Point"}
}