{
  "type": "Feature",
  "properties": {
    "iso:country":"DE",
    "sg:address":"Hiddentruper Str. 15",
    "sg:city":"Lage",
    "sg:phone":"+49 5232/88141",
    "sg:postcode":"32791",
    "sg:province":"Nordrhein-Westfalen",
    "wof:name":"Friedrich Brokmann",
    "wof:placetype":"venue"
},
  "geometry": {"coordinates":[8.75825,51.946602],"type":"Point"}
}