{
  "type": "Feature",
  "properties": {
    "iso:country":"DE",
    "sg:address":"Diebacher Str 20",
    "sg:city":"Insingen",
    "sg:phone":"+49 9869/972244",
    "sg:postcode":"91610",
    "sg:province":"Bayern",
    "wof:name":"Transportbeton Insingen Gmbh",
    "wof:placetype":"venue"
},
  "geometry": {"coordinates":[10.1720161438,49.3046531677],"type":"Point"}
}