{
  "type": "Feature",
  "properties": {
    "iso:country":"DE",
    "sg:address":"Georgenstr. 47",
    "sg:city":"Augsburg",
    "sg:phone":"+49 821/30929",
    "sg:postcode":"86152",
    "sg:province":"Bayern",
    "wof:name":"Christina Perocco",
    "wof:placetype":"venue"
},
  "geometry": {"coordinates":[10.891002655,48.3757400513],"type":"Point"}
}