{
  "type": "Feature",
  "properties": {
    "iso:country":"DE",
    "sg:address":"Dorfm\u00fchlstr. 5",
    "sg:city":"Weihmichl",
    "sg:postcode":"84107",
    "sg:province":"Bayern",
    "wof:name":"S\u00e4gewerk Christl Ohg",
    "wof:placetype":"venue"
},
  "geometry": {"coordinates":[12.0463695526,48.5996551514],"type":"Point"}
}