{
  "type": "Feature",
  "properties": {
    "iso:country":"DE",
    "sg:address":"B\u00fcchel 33",
    "sg:city":"Neuss",
    "sg:phone":"+49 2131/222221",
    "sg:postcode":"41460",
    "sg:province":"Nordrhein-Westfalen",
    "wof:name":"Dauzer",
    "wof:placetype":"venue"
},
  "geometry": {"coordinates":[6.6910319328,51.1990699768],"type":"Point"}
}