{
  "type": "Feature",
  "properties": {
    "iso:country":"DE",
    "sg:address":"Theilheimer Weg 5",
    "sg:city":"Eibelstadt",
    "sg:phone":"+49 9303/980430",
    "sg:postcode":"97246",
    "sg:province":"Bayern",
    "wof:name":"Wulf Viola Rechtsanwalt",
    "wof:placetype":"venue"
},
  "geometry": {"coordinates":[9.9986057281,49.7267150879],"type":"Point"}
}