{
  "type": "Feature",
  "properties": {
    "iso:country":"DE",
    "sg:address":"Pacelliallee 38",
    "sg:city":"Fulda",
    "sg:phone":"+49 661/33066",
    "sg:postcode":"36043",
    "sg:province":"Hessen",
    "wof:name":"Bonn & Tatje Gmbh & Co. Kg",
    "wof:placetype":"venue"
},
  "geometry": {"coordinates":[9.7039165497,50.5471229553],"type":"Point"}
}