{
  "type": "Feature",
  "properties": {
    "iso:country":"DE",
    "sg:address":"Philosophenweg 49",
    "sg:city":"Duisburg",
    "sg:phone":"+49 203/2983690",
    "sg:postcode":"47051",
    "sg:province":"Nordrhein-Westfalen",
    "wof:name":"K\u00fcppersm\u00fchle",
    "wof:placetype":"venue"
},
  "geometry": {"coordinates":[6.7738242149,51.4409294128],"type":"Point"}
}