{
  "type": "Feature",
  "properties": {
    "iso:country":"DE",
    "sg:address":"St\u00f6rkamp 9",
    "sg:city":"Norderstedt",
    "sg:phone":"+49 40/5292053",
    "sg:postcode":"22851",
    "sg:province":"Schleswig-Holstein",
    "wof:name":"Heinz G\u00fcnter Meyer",
    "wof:placetype":"venue"
},
  "geometry": {"coordinates":[10.0275974274,53.6945075989],"type":"Point"}
}