{
  "type": "Feature",
  "properties": {
    "iso:country":"DE",
    "sg:address":"Am Waldstadion",
    "sg:city":"Tholey",
    "sg:phone":"+49 6853/6514",
    "sg:postcode":"66636",
    "sg:province":"Saarland",
    "wof:name":"G\u00fcnter Diefenthal",
    "wof:placetype":"venue"
},
  "geometry": {"coordinates":[6.976372,49.488144],"type":"Point"}
}