{
  "type": "Feature",
  "properties": {
    "iso:country":"DE",
    "sg:address":"Rebgartenweg 11",
    "sg:city":"Dirmstein",
    "sg:phone":"+49 6238/98310",
    "sg:postcode":"67246",
    "sg:province":"Rheinland-Pfalz",
    "wof:name":"Ecs Gmbh",
    "wof:placetype":"venue"
},
  "geometry": {"coordinates":[8.253113,49.566559],"type":"Point"}
}