{
  "type": "Feature",
  "properties": {
    "iso:country":"DE",
    "sg:address":"An Der Schwarza 9",
    "sg:city":"Meuselbach-Schwarzm\u00fchle",
    "sg:phone":"+49 36781/44711",
    "sg:postcode":"98746",
    "sg:province":"Th\u00fcringen",
    "wof:name":"Jens Voigt",
    "wof:placetype":"venue"
},
  "geometry": {"coordinates":[11.07793,50.58165],"type":"Point"}
}