{
  "type": "Feature",
  "properties": {
    "iso:country":"DE",
    "sg:address":"Dorfstr. 44",
    "sg:city":"Dietersdorf",
    "sg:phone":"+49 33747/60336",
    "sg:postcode":"14913",
    "sg:province":"Brandenburg",
    "wof:name":"Birk Holz Gmbh",
    "wof:placetype":"venue"
},
  "geometry": {"coordinates":[11.051133,51.529217],"type":"Point"}
}