{
  "type": "Feature",
  "properties": {
    "iso:country":"DE",
    "sg:address":"Bahnhofstr. 16",
    "sg:city":"Bad Bederkesa",
    "sg:phone":"+49 4745/7169",
    "sg:postcode":"27624",
    "sg:province":"Niedersachsen",
    "wof:name":"Museumsbahn Bremerhaven- Bederkesa E.v.",
    "wof:placetype":"venue"
},
  "geometry": {"coordinates":[8.8301420212,53.6302108765],"type":"Point"}
}