{
  "type": "Feature",
  "properties": {
    "iso:country":"DE",
    "sg:address":"Peterstr. 30",
    "sg:city":"H\u00fcckeswagen",
    "sg:phone":"+49 2192/2071",
    "sg:postcode":"42499",
    "sg:province":"Nordrhein-Westfalen",
    "wof:name":"Siegfried Berg Industrievertretungen",
    "wof:placetype":"venue"
},
  "geometry": {"coordinates":[7.3453879356,51.1487045288],"type":"Point"}
}