{
  "type": "Feature",
  "properties": {
    "iso:country":"DE",
    "sg:address":"Ermlinghofer Str. 8",
    "sg:city":"Dortmund",
    "sg:phone":"+49 231/412406",
    "sg:postcode":"44263",
    "sg:province":"Nordrhein-Westfalen",
    "wof:name":"Egon Pahl",
    "wof:placetype":"venue"
},
  "geometry": {"coordinates":[7.495895,51.484081],"type":"Point"}
}