{
  "type": "Feature",
  "properties": {
    "iso:country":"DE",
    "sg:address":"Dr.-Zinn-Weg 1",
    "sg:city":"Eberswalde",
    "sg:phone":"+49 3334/25380",
    "sg:postcode":"16225",
    "sg:province":"Brandenburg",
    "wof:name":"Cura Gmbh",
    "wof:placetype":"venue"
},
  "geometry": {"coordinates":[13.8315963745,52.853313446],"type":"Point"}
}