{
  "type": "Feature",
  "properties": {
    "iso:country":"DE",
    "sg:address":"Kieler Str. 51-53",
    "sg:city":"Kaltenkirchen",
    "sg:phone":"+49 4191/89603",
    "sg:postcode":"24568",
    "sg:province":"Schleswig-Holstein",
    "wof:name":"Bp-tankstelle",
    "wof:placetype":"venue"
},
  "geometry": {"coordinates":[9.948141098,53.8406524658],"type":"Point"}
}