{
  "type": "Feature",
  "properties": {
    "iso:country":"DE",
    "sg:address":"Erich-Weinert-Str. 15",
    "sg:city":"Neubrandenburg",
    "sg:phone":"+49 395/4224561",
    "sg:postcode":"17034",
    "sg:province":"Mecklenburg-Vorpommern",
    "wof:name":"Josef Jendrysczyk",
    "wof:placetype":"venue"
},
  "geometry": {"coordinates":[13.257385,53.565239],"type":"Point"}
}