{
  "type": "Feature",
  "properties": {
    "iso:country":"DE",
    "sg:address":"Hauptstr. 16",
    "sg:city":"Gro\u00dfkampenberg",
    "sg:phone":"+49 6559/284",
    "sg:postcode":"54619",
    "sg:province":"Rheinland-Pfalz",
    "wof:name":"Willi Darimont Autovermietung",
    "wof:placetype":"venue"
},
  "geometry": {"coordinates":[6.213675,50.158245],"type":"Point"}
}