{
  "type": "Feature",
  "properties": {
    "iso:country":"DE",
    "sg:address":"Von-Rost-Str. 40",
    "sg:city":"M\u00fchlhausen-Ehingen",
    "sg:phone":"+49 7733/5453",
    "sg:postcode":"78259",
    "sg:province":"Baden-W\u00fcrttemberg",
    "wof:name":"G. Czechowski",
    "wof:placetype":"venue"
},
  "geometry": {"coordinates":[8.8144140244,47.8113021851],"type":"Point"}
}