{
  "type": "Feature",
  "properties": {
    "iso:country":"DE",
    "sg:address":"Buerger 212",
    "sg:city":"Bremerhaven",
    "sg:phone":"+49 471",
    "sg:postcode":"27568",
    "sg:province":"Bremen",
    "wof:name":"Naturkost-gruenschnabel",
    "wof:placetype":"venue"
},
  "geometry": {"coordinates":[8.579829,53.542046],"type":"Point"}
}