{
  "type": "Feature",
  "properties": {
    "iso:country":"DE",
    "sg:address":"An der Kirche 6",
    "sg:city":"Lippstadt",
    "sg:phone":"+49 2948/228",
    "sg:postcode":"59558",
    "sg:province":"Nordrhein-Westfalen",
    "wof:name":"Katholisches Pfarramt St. Martin",
    "wof:placetype":"venue"
},
  "geometry": {"coordinates":[8.4339580536,51.6900062561],"type":"Point"}
}