{
  "type": "Feature",
  "properties": {
    "iso:country":"DE",
    "sg:address":"Friedrichstr. 169-170",
    "sg:city":"Berlin",
    "sg:postcode":"10117",
    "sg:province":"Berlin",
    "wof:name":"Imc Internet Media Communication Gmbh",
    "wof:placetype":"venue"
},
  "geometry": {"coordinates":[13.388924,52.515011],"type":"Point"}
}