{
  "type": "Feature",
  "properties": {
    "iso:country":"DE",
    "sg:address":"Langbruck 16",
    "sg:city":"Bischofsmais",
    "sg:phone":"+49 9920/1395",
    "sg:postcode":"94253",
    "sg:province":"Bayern",
    "wof:name":"Btp Fliesenbau Gmbh",
    "wof:placetype":"venue"
},
  "geometry": {"coordinates":[13.116264,48.925819],"type":"Point"}
}