{
  "type": "Feature",
  "properties": {
    "iso:country":"DE",
    "sg:address":"B\u00fcrgerstr. 17",
    "sg:city":"Bad Waldsee",
    "sg:phone":"+49 7524/6595",
    "sg:postcode":"88339",
    "sg:province":"Baden-W\u00fcrttemberg",
    "wof:name":"Robert Maucher",
    "wof:placetype":"venue"
},
  "geometry": {"coordinates":[9.7993879318,47.8821563721],"type":"Point"}
}