{
  "type": "Feature",
  "properties": {
    "iso:country":"DE",
    "sg:address":"Ballengasse 6",
    "sg:city":"Swisttal",
    "sg:phone":"+49 2254/1092",
    "sg:postcode":"53913",
    "sg:province":"Nordrhein-Westfalen",
    "wof:name":"Josef Reinartz",
    "wof:placetype":"venue"
},
  "geometry": {"coordinates":[6.913906,50.715202],"type":"Point"}
}