{
  "type": "Feature",
  "properties": {
    "iso:country":"DE",
    "sg:address":"Am Brink 8",
    "sg:city":"Wistedt",
    "sg:phone":"+49 4182/28050",
    "sg:postcode":"21255",
    "sg:province":"Niedersachsen",
    "wof:name":"Manfred Schwerk",
    "wof:placetype":"venue"
},
  "geometry": {"coordinates":[9.677653,53.270283],"type":"Point"}
}