{
  "type": "Feature",
  "properties": {
    "iso:country":"DE",
    "sg:address":"Lindenstr. 1",
    "sg:city":"Rieden",
    "sg:phone":"+49 9624/2727",
    "sg:postcode":"92286",
    "sg:province":"Bayern",
    "wof:name":"Vilstal Gym",
    "wof:placetype":"venue"
},
  "geometry": {"coordinates":[11.9424791336,49.321975708],"type":"Point"}
}