{
  "type": "Feature",
  "properties": {
    "iso:country":"DE",
    "sg:address":"Hohlweg 50",
    "sg:city":"Kerpen",
    "sg:postcode":"50170",
    "sg:province":"Nordrhein-Westfalen",
    "wof:name":"Railroad Tracks Gmbh",
    "wof:placetype":"venue"
},
  "geometry": {"coordinates":[6.585034,50.864548],"type":"Point"}
}