{
  "type": "Feature",
  "properties": {
    "iso:country":"DE",
    "sg:address":"Eibenstr. 1",
    "sg:city":"D\u00fcsseldorf",
    "sg:postcode":"40627",
    "sg:province":"Nordrhein-Westfalen",
    "wof:name":"K & M Bau Consulting Gmbh",
    "wof:placetype":"venue"
},
  "geometry": {"coordinates":[6.8994989395,51.1997451782],"type":"Point"}
}