{
  "type": "Feature",
  "properties": {
    "iso:country":"DE",
    "sg:address":"Dr.-Friedrichs-Str. 3",
    "sg:city":"Limbach",
    "sg:phone":"+49 3765/36678",
    "sg:postcode":"08491",
    "sg:province":"Sachsen",
    "wof:name":"A. Clau\u00df",
    "wof:placetype":"venue"
},
  "geometry": {"coordinates":[12.2451019287,50.5829277039],"type":"Point"}
}