{
  "type": "Feature",
  "properties": {
    "iso:country":"DE",
    "sg:address":"Karl-Benz-Str. 3",
    "sg:city":"Pliezhausen",
    "sg:phone":"+49 4971/2797900",
    "sg:postcode":"72124",
    "sg:province":"Baden-W\u00fcrttemberg",
    "wof:name":"Karl Grammlich Offsetdruckerei Gmbh",
    "wof:placetype":"venue"
},
  "geometry": {"coordinates":[9.2001953125,48.5670814514],"type":"Point"}
}