{
  "type": "Feature",
  "properties": {
    "iso:country":"DE",
    "sg:address":"Zehdenicker Str. 49",
    "sg:city":"Falkenthal",
    "sg:postcode":"16775",
    "sg:province":"Brandenburg",
    "wof:name":"K. V. E. Gmbh Elektronischer Gro\u00dfhandel",
    "wof:placetype":"venue"
},
  "geometry": {"coordinates":[13.3050842285,52.9100875854],"type":"Point"}
}