{
  "type": "Feature",
  "properties": {
    "iso:country":"DE",
    "sg:address":"Ostwall 26",
    "sg:city":"Krefeld",
    "sg:phone":"+49 2151/314087",
    "sg:postcode":"47798",
    "sg:province":"Nordrhein-Westfalen",
    "wof:name":"Ostwall-sch\u00e4nke",
    "wof:placetype":"venue"
},
  "geometry": {"coordinates":[6.5683960915,51.3272132874],"type":"Point"}
}