{
  "type": "Feature",
  "properties": {
    "iso:country":"DE",
    "sg:address":"Blumenstr. 8",
    "sg:city":"Deizisau",
    "sg:phone":"+49 7153/70180",
    "sg:postcode":"73779",
    "sg:province":"Baden-W\u00fcrttemberg",
    "wof:name":"Wilhelm E. H. Biesterfeld",
    "wof:placetype":"venue"
},
  "geometry": {"coordinates":[9.391453,48.71299],"type":"Point"}
}