{
  "type": "Feature",
  "properties": {
    "iso:country":"DE",
    "sg:address":"Mittelstr. 4",
    "sg:city":"Sassnitz",
    "sg:phone":"+49 38392/5150",
    "sg:postcode":"18546",
    "sg:province":"Mecklenburg-Vorpommern",
    "wof:name":"Villa Strandh\u00fcgel",
    "wof:placetype":"venue"
},
  "geometry": {"coordinates":[13.6449508667,54.516582489],"type":"Point"}
}