{
  "type": "Feature",
  "properties": {
    "iso:country":"DE",
    "sg:address":"Auf der Kratz 14",
    "sg:city":"Fr\u00fccht",
    "sg:phone":"+49 2603/4313",
    "sg:postcode":"56132",
    "sg:province":"Rheinland-Pfalz",
    "wof:name":"Malerbetrieb Neuhaus Gmbh",
    "wof:placetype":"venue"
},
  "geometry": {"coordinates":[7.677623,50.31398],"type":"Point"}
}