{
  "type": "Feature",
  "properties": {
    "iso:country":"DE",
    "sg:address":"Klosterstr. 10",
    "sg:city":"Pappenheim",
    "sg:phone":"+49 9143/511513",
    "sg:postcode":"91788",
    "sg:province":"Bayern",
    "wof:name":"Stadtwerke Pappenheim",
    "wof:placetype":"venue"
},
  "geometry": {"coordinates":[10.972492,48.934292],"type":"Point"}
}