{
  "type": "Feature",
  "properties": {
    "iso:country":"DE",
    "sg:address":"Memminger Str. 11",
    "sg:city":"Wei\u00dfenhorn",
    "sg:phone":"+49 7309/3051",
    "sg:postcode":"89264",
    "sg:province":"Bayern",
    "wof:name":"Rainer Wolf",
    "wof:placetype":"venue"
},
  "geometry": {"coordinates":[10.160421,48.302784],"type":"Point"}
}