{
  "type": "Feature",
  "properties": {
    "iso:country":"DE",
    "sg:address":"Herrenstr. 16",
    "sg:city":"Bad Wurzach",
    "sg:phone":"+49 7564/2845",
    "sg:postcode":"88410",
    "sg:province":"Baden-W\u00fcrttemberg",
    "wof:name":"Wilhelm Fleischer",
    "wof:placetype":"venue"
},
  "geometry": {"coordinates":[9.8947916031,47.9089126587],"type":"Point"}
}