{
  "type": "Feature",
  "properties": {
    "iso:country":"DE",
    "sg:address":"Adelsbergstr. 204",
    "sg:city":"Chemnitz",
    "sg:phone":"+49 371/729324",
    "sg:postcode":"09127",
    "sg:province":"Sachsen",
    "wof:name":"Roland Hartzendorf",
    "wof:placetype":"venue"
},
  "geometry": {"coordinates":[12.974188,50.823257],"type":"Point"}
}