{
  "type": "Feature",
  "properties": {
    "iso:country":"DE",
    "sg:address":"B\u00e4rental 26 / Hirsau",
    "sg:city":"Calw",
    "sg:phone":"+49 4970/5160010",
    "sg:postcode":"75365",
    "sg:province":"Baden-W\u00fcrttemberg",
    "wof:name":"Robert Seuffer Gmbh & Co. Kg",
    "wof:placetype":"venue"
},
  "geometry": {"coordinates":[8.740343,48.714355],"type":"Point"}
}