{
  "type": "Feature",
  "properties": {
    "iso:country":"DE",
    "sg:address":"Pferdemarkt 41",
    "sg:city":"G\u00fcstrow",
    "sg:phone":"+49 3843/686109",
    "sg:postcode":"18273",
    "sg:province":"Mecklenburg-Vorpommern",
    "wof:name":"Chinarestaurant",
    "wof:placetype":"venue"
},
  "geometry": {"coordinates":[12.1752977371,53.7947463989],"type":"Point"}
}