{
  "type": "Feature",
  "properties": {
    "iso:country":"DE",
    "sg:address":"Krumbacher Str. 6",
    "sg:city":"Ottendorf",
    "sg:phone":"+49 37208/2492",
    "sg:postcode":"09648",
    "sg:province":"Sachsen",
    "wof:name":"Edda Steinert",
    "wof:placetype":"venue"
},
  "geometry": {"coordinates":[12.980837822,50.9366989136],"type":"Point"}
}