{
  "type": "Feature",
  "properties": {
    "iso:country":"DE",
    "sg:address":"Dreihausen 31",
    "sg:city":"Petershagen",
    "sg:phone":"+49 5702/9507",
    "sg:postcode":"32469",
    "sg:province":"Nordrhein-Westfalen",
    "wof:name":"Hall Beteiligungs Und Verwaltungs-gmbh",
    "wof:placetype":"venue"
},
  "geometry": {"coordinates":[9.015483,52.385185],"type":"Point"}
}