{
  "type": "Feature",
  "properties": {
    "iso:country":"DE",
    "sg:address":"Ahrweiler Str. 54-58",
    "sg:city":"Bad M\u00fcnstereifel",
    "sg:phone":"+49 2253/92440",
    "sg:postcode":"53902",
    "sg:province":"Nordrhein-Westfalen",
    "wof:name":"Embewe Gmbh",
    "wof:placetype":"venue"
},
  "geometry": {"coordinates":[6.7764759064,50.5311775208],"type":"Point"}
}