{
  "type": "Feature",
  "properties": {
    "iso:country":"DE",
    "sg:address":"Buchtalstr. 91",
    "sg:city":"Albstadt",
    "sg:phone":"+49 7432/980240",
    "sg:postcode":"72461",
    "sg:province":"Baden-W\u00fcrttemberg",
    "wof:name":"Hermann Conzelmann Beteiligungs Und",
    "wof:placetype":"venue"
},
  "geometry": {"coordinates":[9.01859,48.267101],"type":"Point"}
}