{
  "type": "Feature",
  "properties": {
    "iso:country":"DE",
    "sg:address":"Lindenstr. 50",
    "sg:city":"Pfungstadt",
    "sg:phone":"+49 6157/930329",
    "sg:postcode":"64319",
    "sg:province":"Hessen",
    "wof:name":"Philipp Liebig",
    "wof:placetype":"venue"
},
  "geometry": {"coordinates":[8.597093,49.807049],"type":"Point"}
}