{
  "type": "Feature",
  "properties": {
    "iso:country":"DE",
    "sg:address":"Graben 6",
    "sg:city":"Kassel",
    "sg:phone":"+49 561/719299",
    "sg:postcode":"34117",
    "sg:province":"Hessen",
    "wof:name":"Frank Piske",
    "wof:placetype":"venue"
},
  "geometry": {"coordinates":[9.5020494461,51.3152008057],"type":"Point"}
}