{
  "type": "Feature",
  "properties": {
    "iso:country":"DE",
    "sg:address":"Oberstadtstr. 11",
    "sg:city":"Haigerloch",
    "sg:postcode":"72401",
    "sg:province":"Baden-W\u00fcrttemberg",
    "wof:name":"Wohnbau Haigerloch Gmbh",
    "wof:placetype":"venue"
},
  "geometry": {"coordinates":[8.805925,48.367039],"type":"Point"}
}