{
  "type": "Feature",
  "properties": {
    "iso:country":"DE",
    "sg:address":"Hochstr. 55",
    "sg:city":"Grefrath",
    "sg:phone":"+49 2158/5147",
    "sg:postcode":"47929",
    "sg:province":"Nordrhein-Westfalen",
    "wof:name":"Haus Stefes",
    "wof:placetype":"venue"
},
  "geometry": {"coordinates":[6.3808498383,51.3233604431],"type":"Point"}
}