{
  "type": "Feature",
  "properties": {
    "iso:country":"DE",
    "sg:address":"Am Steinufer",
    "sg:city":"Dingelst\u00e4dt",
    "sg:phone":"+49 36075/2898",
    "sg:postcode":"37351",
    "sg:province":"Th\u00fcringen",
    "wof:name":"Kreissparkasse",
    "wof:placetype":"venue"
},
  "geometry": {"coordinates":[10.31978,51.319004],"type":"Point"}
}