{
  "type": "Feature",
  "properties": {
    "iso:country":"DE",
    "sg:address":"Stockkamp 8",
    "sg:city":"Solingen",
    "sg:postcode":"42651",
    "sg:province":"Nordrhein-Westfalen",
    "wof:name":"Aldi Gmbh & Co. Kg",
    "wof:placetype":"venue"
},
  "geometry": {"coordinates":[7.1050891876,51.1616592407],"type":"Point"}
}