{
  "type": "Feature",
  "properties": {
    "iso:country":"DE",
    "sg:address":"Im Kleinen Feldchen 1",
    "sg:city":"Gr\u00fcndau",
    "sg:phone":"+49 6051/18471",
    "sg:postcode":"63584",
    "sg:province":"Hessen",
    "wof:name":"Frey Service- Gmbh",
    "wof:placetype":"venue"
},
  "geometry": {"coordinates":[9.105769,50.197811],"type":"Point"}
}