{
  "type": "Feature",
  "properties": {
    "iso:country":"DE",
    "sg:address":"Parkstr. 1",
    "sg:city":"Wrestedt",
    "sg:phone":"+49 5825/476",
    "sg:postcode":"29559",
    "sg:province":"Niedersachsen",
    "wof:name":"Ev. Luth. Pfarramt Gemeinde Lehmke",
    "wof:placetype":"venue"
},
  "geometry": {"coordinates":[10.640581131,52.9265594482],"type":"Point"}
}