{
  "type": "Feature",
  "properties": {
    "iso:country":"DE",
    "sg:address":"Bebra Iba",
    "sg:city":"Bebra",
    "sg:phone":"+49 4966/27180",
    "sg:postcode":"36179",
    "sg:province":"Hessen",
    "wof:name":"Drm Druckguss Gmbh",
    "wof:placetype":"venue"
},
  "geometry": {"coordinates":[9.799323,50.966339],"type":"Point"}
}