{
  "type": "Feature",
  "properties": {
    "iso:country":"DE",
    "sg:address":"Schwanenstr. 65",
    "sg:city":"Voerde",
    "sg:phone":"+49 281/60410",
    "sg:postcode":"46562",
    "sg:province":"Nordrhein-Westfalen",
    "wof:name":"Klaus Und S. Tietze",
    "wof:placetype":"venue"
},
  "geometry": {"coordinates":[6.702528,51.59343],"type":"Point"}
}