{
  "type": "Feature",
  "properties": {
    "iso:country":"DE",
    "sg:address":"Sandweg 3",
    "sg:city":"Georgsmarienh\u00fctte",
    "sg:phone":"+49 5401/5534",
    "sg:postcode":"49124",
    "sg:province":"Niedersachsen",
    "wof:name":"Hans Luttmann",
    "wof:placetype":"venue"
},
  "geometry": {"coordinates":[8.0664653778,52.2048034668],"type":"Point"}
}