{
  "type": "Feature",
  "properties": {
    "iso:country":"DE",
    "sg:address":"Weinb\u00f6hlaer Str. 64",
    "sg:city":"Coswig",
    "sg:phone":"+49 3523/701347",
    "sg:postcode":"01640",
    "sg:province":"Sachsen",
    "wof:name":"Hotel Forsthaus",
    "wof:placetype":"venue"
},
  "geometry": {"coordinates":[13.5755281448,51.1377944946],"type":"Point"}
}