{
  "type": "Feature",
  "properties": {
    "iso:country":"DE",
    "sg:address":"Frankfurter Str. 23",
    "sg:city":"R\u00fcsselsheim",
    "sg:phone":"+49 6142/16838",
    "sg:postcode":"65428",
    "sg:province":"Hessen",
    "wof:name":"Computertechnik Rainer Neuderth",
    "wof:placetype":"venue"
},
  "geometry": {"coordinates":[8.4154748917,49.9956512451],"type":"Point"}
}