{
  "type": "Feature",
  "properties": {
    "iso:country":"DE",
    "sg:address":"Tundinger Str. 1",
    "sg:city":"Moosthenning",
    "sg:phone":"+49 8731/9519",
    "sg:postcode":"84164",
    "sg:province":"Bayern",
    "wof:name":"Chinarestaurant",
    "wof:placetype":"venue"
},
  "geometry": {"coordinates":[12.4638290405,48.6729240417],"type":"Point"}
}