{
  "type": "Feature",
  "properties": {
    "iso:country":"DE",
    "sg:address":"Untergr\u00fcner Str. 8",
    "sg:city":"Iserlohn",
    "sg:phone":"+49 2374/850654",
    "sg:postcode":"58644",
    "sg:province":"Nordrhein-Westfalen",
    "wof:name":"Parkhalle Verwaltungs Gmbh",
    "wof:placetype":"venue"
},
  "geometry": {"coordinates":[7.63631,51.363209],"type":"Point"}
}