{
  "type": "Feature",
  "properties": {
    "iso:country":"DE",
    "sg:address":"Tangendorfer Str. 10",
    "sg:city":"Toppenstedt",
    "sg:phone":"+49 4173/8565",
    "sg:postcode":"21442",
    "sg:province":"Niedersachsen",
    "wof:name":"Ingrid Bartsch Masseurin",
    "wof:placetype":"venue"
},
  "geometry": {"coordinates":[10.111484,53.26564],"type":"Point"}
}