{
  "type": "Feature",
  "properties": {
    "iso:country":"DE",
    "sg:address":"Adalbertstr. 126",
    "sg:city":"Aachen",
    "sg:phone":"+49 241/39009",
    "sg:postcode":"52062",
    "sg:province":"Nordrhein-Westfalen",
    "wof:name":"G. Engelen",
    "wof:placetype":"venue"
},
  "geometry": {"coordinates":[6.0949487686,50.7745742798],"type":"Point"}
}