{
  "type": "Feature",
  "properties": {
    "iso:country":"DE",
    "sg:address":"Luisenstr. 25",
    "sg:city":"Pirmasens",
    "sg:phone":"+49 6331/42927",
    "sg:postcode":"66953",
    "sg:province":"Rheinland-Pfalz",
    "wof:name":"Monika Mayer",
    "wof:placetype":"venue"
},
  "geometry": {"coordinates":[7.609655,49.203362],"type":"Point"}
}