{
  "type": "Feature",
  "properties": {
    "iso:country":"DE",
    "sg:address":"Parlerstr. 56",
    "sg:city":"Stuttgart",
    "sg:phone":"+49 711/165570",
    "sg:postcode":"70192",
    "sg:province":"Baden-W\u00fcrttemberg",
    "wof:name":"Peter Sigwart Immobilienmakler",
    "wof:placetype":"venue"
},
  "geometry": {"coordinates":[9.1696548462,48.7926597595],"type":"Point"}
}