{
  "type": "Feature",
  "properties": {
    "iso:country":"DE",
    "sg:address":"L\u00e4rchenweg 1",
    "sg:city":"Haste",
    "sg:phone":"+49 5723/8481",
    "sg:postcode":"31559",
    "sg:province":"Niedersachsen",
    "wof:name":"F. Baule",
    "wof:placetype":"venue"
},
  "geometry": {"coordinates":[9.398144722,52.3861885071],"type":"Point"}
}