{
  "type": "Feature",
  "properties": {
    "iso:country":"DE",
    "sg:city":"Kirchen",
    "sg:phone":"+49 2741/61594",
    "sg:postcode":"57548",
    "sg:province":"Rheinland-Pfalz",
    "wof:name":"P. Sch\u00e4fer Altenheim",
    "wof:placetype":"venue"
},
  "geometry": {"coordinates":[7.878613,50.81028],"type":"Point"}
}