{
  "type": "Feature",
  "properties": {
    "iso:country":"DE",
    "sg:address":"Waisenhausstr. 9",
    "sg:city":"Freiberg",
    "sg:phone":"+49 3731/23020",
    "sg:postcode":"09599",
    "sg:province":"Sachsen",
    "wof:name":"Bbf Baub\u00fcro Freiburg Gmbh",
    "wof:placetype":"venue"
},
  "geometry": {"coordinates":[13.339898,50.916412],"type":"Point"}
}