{
  "type": "Feature",
  "properties": {
    "iso:country":"DE",
    "sg:address":"Friedensstr. 58",
    "sg:city":"Duderstadt",
    "sg:postcode":"37115",
    "sg:province":"Niedersachsen",
    "wof:name":"Daniela Blaschke Handarbeiten",
    "wof:placetype":"venue"
},
  "geometry": {"coordinates":[10.241991,51.506489],"type":"Point"}
}