{
  "type": "Feature",
  "properties": {
    "iso:country":"DE",
    "sg:address":"Moorweg 3",
    "sg:city":"Syke",
    "sg:phone":"+49 4240/1018",
    "sg:postcode":"28857",
    "sg:province":"Niedersachsen",
    "wof:name":"Kurt Helms",
    "wof:placetype":"venue"
},
  "geometry": {"coordinates":[8.917909,52.87347],"type":"Point"}
}