{
  "type": "Feature",
  "properties": {
    "iso:country":"DE",
    "sg:address":"Falkenstr. 33",
    "sg:city":"Neuenhaus",
    "sg:phone":"+49 5941/1259",
    "sg:postcode":"49828",
    "sg:province":"Niedersachsen",
    "wof:name":"Hindrik Heesmann",
    "wof:placetype":"venue"
},
  "geometry": {"coordinates":[6.98596,52.477951],"type":"Point"}
}