{
  "type": "Feature",
  "properties": {
    "iso:country":"DE",
    "sg:address":"Brunnenstr. 18",
    "sg:city":"Pfinztal",
    "sg:phone":"+49 721/460798",
    "sg:postcode":"76327",
    "sg:province":"Baden-W\u00fcrttemberg",
    "wof:name":"Dr. Schmitt & Co.",
    "wof:placetype":"venue"
},
  "geometry": {"coordinates":[8.5217103958,48.9929542542],"type":"Point"}
}