{
  "type": "Feature",
  "properties": {
    "iso:country":"DE",
    "sg:address":"Tiergartenstr. 122",
    "sg:city":"Hannover",
    "sg:phone":"+49 511/522624",
    "sg:postcode":"30559",
    "sg:province":"Niedersachsen",
    "wof:name":"Rolf K\u00fcker Beteiligungs Gmbh",
    "wof:placetype":"venue"
},
  "geometry": {"coordinates":[9.827628,52.361088],"type":"Point"}
}