{
  "type": "Feature",
  "properties": {
    "iso:country":"DE",
    "sg:address":"Postfach 13 09 47",
    "sg:city":"D\u00fcsseldorf",
    "sg:phone":"+49 190856989",
    "sg:postcode":"40559",
    "sg:province":"Nordrhein-Westfalen",
    "wof:name":"Alten Treff - Seniorentreff Und Mehr",
    "wof:placetype":"venue"
},
  "geometry": {"coordinates":[6.77568,51.22506],"type":"Point"}
}