{
  "type": "Feature",
  "properties": {
    "iso:country":"DE",
    "sg:address":"Bismarckstr. 6",
    "sg:city":"Westerland",
    "sg:phone":"+49 4651/27690",
    "sg:postcode":"25980",
    "sg:province":"Schleswig-Holstein",
    "wof:name":"H. Borges",
    "wof:placetype":"venue"
},
  "geometry": {"coordinates":[8.3026065826,54.9068107605],"type":"Point"}
}