{
  "type": "Feature",
  "properties": {
    "iso:country":"DE",
    "sg:address":"Hauptstr. 79",
    "sg:city":"Freigericht",
    "sg:phone":"+49 6055/2263",
    "sg:postcode":"63579",
    "sg:province":"Hessen",
    "wof:name":"G\u00fcnter Kramer",
    "wof:placetype":"venue"
},
  "geometry": {"coordinates":[9.1432180405,50.1409606934],"type":"Point"}
}