{
  "type": "Feature",
  "properties": {
    "iso:country":"DE",
    "sg:address":"Freiburger Str. 36",
    "sg:city":"Kehl",
    "sg:phone":"+49 7851/2151",
    "sg:postcode":"77694",
    "sg:province":"Baden-W\u00fcrttemberg",
    "wof:name":"Kurt Honauer",
    "wof:placetype":"venue"
},
  "geometry": {"coordinates":[7.83804,48.607613],"type":"Point"}
}