{
  "type": "Feature",
  "properties": {
    "iso:country":"DE",
    "sg:address":"Lange Str. 8",
    "sg:city":"Wolfsburg",
    "sg:phone":"+49 5363/73833",
    "sg:postcode":"38448",
    "sg:province":"Niedersachsen",
    "wof:name":"Restaurant Kartoffelhaus",
    "wof:placetype":"venue"
},
  "geometry": {"coordinates":[10.8370895386,52.4387245178],"type":"Point"}
}