{
  "type": "Feature",
  "properties": {
    "iso:country":"DE",
    "sg:address":"Nonnengasse 8",
    "sg:city":"Duisburg",
    "sg:phone":"+49 203/26859",
    "sg:postcode":"47051",
    "sg:province":"Nordrhein-Westfalen",
    "wof:name":"Dreigiebelhaus Restaurant",
    "wof:placetype":"venue"
},
  "geometry": {"coordinates":[6.7645168304,51.4368057251],"type":"Point"}
}