{
  "type": "Feature",
  "properties": {
    "iso:country":"DE",
    "sg:address":"Calauer Str. 28",
    "sg:city":"Luckau",
    "sg:phone":"+49 3544/3126",
    "sg:postcode":"15926",
    "sg:province":"Brandenburg",
    "wof:name":"Wilfried Quoos",
    "wof:placetype":"venue"
},
  "geometry": {"coordinates":[13.7230653763,51.851890564],"type":"Point"}
}