{
  "type": "Feature",
  "properties": {
    "iso:country":"DE",
    "sg:address":"Steinbeisstrasse 12",
    "sg:city":"G\u00f6ppingen",
    "sg:phone":"+49 7161",
    "sg:postcode":"73037",
    "sg:province":"Baden-W\u00fcrttemberg",
    "wof:name":"Coriphea Informatik",
    "wof:placetype":"venue"
},
  "geometry": {"coordinates":[9.6881170273,48.7156181335],"type":"Point"}
}