{
  "type": "Feature",
  "properties": {
    "iso:country":"DE",
    "sg:address":"Dernauer Str. 16 a",
    "sg:city":"Hamburg",
    "sg:phone":"+49 40",
    "sg:postcode":"22047",
    "sg:province":"Hamburg",
    "wof:name":"Autofit Kfz Werkstatt Autoservice Gaworski",
    "wof:placetype":"venue"
},
  "geometry": {"coordinates":[10.0856714249,53.5818710327],"type":"Point"}
}