{
  "type": "Feature",
  "properties": {
    "iso:country":"DE",
    "sg:address":"Uferstr. 5",
    "sg:city":"K\u00e4mpfelbach",
    "sg:phone":"+49 7232/6656",
    "sg:postcode":"75236",
    "sg:province":"Baden-W\u00fcrttemberg",
    "wof:name":"Werner Brenk",
    "wof:placetype":"venue"
},
  "geometry": {"coordinates":[8.622130394,48.9514961243],"type":"Point"}
}