{
  "type": "Feature",
  "properties": {
    "iso:country":"DE",
    "sg:address":"Olpener Str. 855",
    "sg:city":"K\u00f6ln",
    "sg:phone":"+49 221/843214",
    "sg:postcode":"51109",
    "sg:province":"Nordrhein-Westfalen",
    "wof:name":"Margareten-apotheke",
    "wof:placetype":"venue"
},
  "geometry": {"coordinates":[7.078878,50.945602],"type":"Point"}
}