{
  "type": "Feature",
  "properties": {
    "iso:country":"DE",
    "sg:address":"Richard-Wagner-Str. 6",
    "sg:city":"Herzogenaurach",
    "sg:phone":"+49 9132/797676",
    "sg:postcode":"91074",
    "sg:province":"Bayern",
    "wof:name":"Haus Und Hof Wohnbau Gmbh",
    "wof:placetype":"venue"
},
  "geometry": {"coordinates":[10.876204,49.567635],"type":"Point"}
}