{
  "type": "Feature",
  "properties": {
    "iso:country":"DE",
    "sg:address":"Schlo\u00df Monrepos",
    "sg:city":"Ludwigsburg",
    "sg:phone":"+49 7141/225525",
    "sg:postcode":"71634",
    "sg:province":"Baden-W\u00fcrttemberg",
    "wof:name":"W\u00fcrttembergische Hof- Kammerkellerei",
    "wof:placetype":"venue"
},
  "geometry": {"coordinates":[9.1674261093,48.921005249],"type":"Point"}
}