{
  "type": "Feature",
  "properties": {
    "iso:country":"DE",
    "sg:address":"Gumbertstr. 116",
    "sg:city":"D\u00fcsseldorf",
    "sg:phone":"+49 211/9216140",
    "sg:postcode":"40229",
    "sg:province":"Nordrhein-Westfalen",
    "wof:name":"Eller Weinhaus",
    "wof:placetype":"venue"
},
  "geometry": {"coordinates":[6.8371191025,51.2017326355],"type":"Point"}
}