{
  "type": "Feature",
  "properties": {
    "iso:country":"DE",
    "sg:address":"B\u00f6rsenplatz 7-11",
    "sg:city":"Frankfurt",
    "sg:postcode":"60313",
    "sg:province":"Hessen",
    "wof:name":"Eurex Clearing Ag",
    "wof:placetype":"venue"
},
  "geometry": {"coordinates":[8.6776008606,50.1148719788],"type":"Point"}
}