{
  "type": "Feature",
  "properties": {
    "iso:country":"DE",
    "sg:address":"Am Burghaus 11",
    "sg:city":"Reichshof",
    "sg:phone":"+49 2296/8799",
    "sg:postcode":"51580",
    "sg:province":"Nordrhein-Westfalen",
    "wof:name":"Dietmar Eisenacher",
    "wof:placetype":"venue"
},
  "geometry": {"coordinates":[7.632242,50.952312],"type":"Point"}
}