{
  "type": "Feature",
  "properties": {
    "iso:country":"DE",
    "sg:address":"Am Rhein 15",
    "sg:city":"Rheinfelden",
    "sg:phone":"+49 4976/234144",
    "sg:postcode":"79618",
    "sg:province":"Baden-W\u00fcrttemberg",
    "wof:name":"Maschinenfabrik Christian H\u00c4usler Gmbh",
    "wof:placetype":"venue"
},
  "geometry": {"coordinates":[7.733728,47.545055],"type":"Point"}
}