{
  "type": "Feature",
  "properties": {
    "iso:country":"DE",
    "sg:address":"Michaelisstr. 8",
    "sg:city":"Bad Salzungen",
    "sg:phone":"+49 3695/62244",
    "sg:postcode":"36433",
    "sg:province":"Th\u00fcringen",
    "wof:name":"Deutsches Haus",
    "wof:placetype":"venue"
},
  "geometry": {"coordinates":[10.2358360291,50.8137207031],"type":"Point"}
}