{
  "type": "Feature",
  "properties": {
    "iso:country":"DE",
    "sg:address":"Rennweg 53",
    "sg:city":"N\u00fcrnberg",
    "sg:phone":"+49 911/551050",
    "sg:postcode":"90489",
    "sg:province":"Bayern",
    "wof:name":"Troeger & B\u00fccking Emil Bach & Co.",
    "wof:placetype":"venue"
},
  "geometry": {"coordinates":[11.0976104736,49.46276474],"type":"Point"}
}