{
  "type": "Feature",
  "properties": {
    "iso:country":"DE",
    "sg:address":"Bodenackerstr. 1",
    "sg:city":"L\u00f6rrach",
    "sg:phone":"+49 7621/53834",
    "sg:postcode":"79541",
    "sg:province":"Baden-W\u00fcrttemberg",
    "wof:name":"Edeltraud Feigl",
    "wof:placetype":"venue"
},
  "geometry": {"coordinates":[7.6779508591,47.6377906799],"type":"Point"}
}