{
  "type": "Feature",
  "properties": {
    "iso:country":"DE",
    "sg:address":"Kirchfeldstr. 24",
    "sg:city":"Meckenheim",
    "sg:phone":"+49 2225/12489",
    "sg:postcode":"53340",
    "sg:province":"Nordrhein-Westfalen",
    "wof:name":"K. Zedlitz-neukirch Rechtsanw\u00e4ltin",
    "wof:placetype":"venue"
},
  "geometry": {"coordinates":[7.0184440613,50.6200485229],"type":"Point"}
}