{
  "type": "Feature",
  "properties": {
    "iso:country":"DE",
    "sg:address":"Wittenberger Str. 9",
    "sg:city":"Dresden",
    "sg:postcode":"01309",
    "sg:province":"Sachsen",
    "wof:name":"Lappkabel",
    "wof:placetype":"venue"
},
  "geometry": {"coordinates":[13.7823457718,51.0510215759],"type":"Point"}
}