{
  "type": "Feature",
  "properties": {
    "iso:country":"DE",
    "sg:address":"Wilhelmsaue 17",
    "sg:city":"Berlin",
    "sg:phone":"+49 30/8735509",
    "sg:postcode":"10715",
    "sg:province":"Berlin",
    "wof:name":"Manfred Pirschel Und Krauel Nachfolger",
    "wof:placetype":"venue"
},
  "geometry": {"coordinates":[13.324726,52.48568],"type":"Point"}
}