{
  "type": "Feature",
  "properties": {
    "iso:country":"DE",
    "sg:address":"Kirschgartenstr. 8",
    "sg:city":"Zornheim",
    "sg:phone":"+49 6136/45136",
    "sg:postcode":"55270",
    "sg:province":"Rheinland-Pfalz",
    "wof:name":"Anita Hanke",
    "wof:placetype":"venue"
},
  "geometry": {"coordinates":[8.2282447815,49.8876228333],"type":"Point"}
}