{
  "type": "Feature",
  "properties": {
    "iso:country":"DE",
    "sg:address":"Marktstr. 20",
    "sg:city":"Duderstadt",
    "sg:phone":"+49 5527/5157",
    "sg:postcode":"37115",
    "sg:province":"Niedersachsen",
    "wof:name":"Restaurant Elaton",
    "wof:placetype":"venue"
},
  "geometry": {"coordinates":[10.2578477859,51.512096405],"type":"Point"}
}