{
  "type": "Feature",
  "properties": {
    "iso:country":"DE",
    "sg:address":"Bernhardstr. 9 - 11",
    "sg:city":"Aschaffenburg",
    "sg:phone":"+49 6021/412020",
    "sg:postcode":"63741",
    "sg:province":"Bayern",
    "wof:name":"Auto Herzog Gmbh",
    "wof:placetype":"venue"
},
  "geometry": {"coordinates":[9.140932,49.983158],"type":"Point"}
}