{
  "type": "Feature",
  "properties": {
    "iso:country":"DE",
    "sg:address":"Josef-Frankl-Str. 45 a",
    "sg:city":"M\u00fcnchen",
    "sg:postcode":"80995",
    "sg:province":"Bayern",
    "wof:name":"Kanarya Fu\u00dfboden Gmbh",
    "wof:placetype":"venue"
},
  "geometry": {"coordinates":[11.5313978195,48.2149848938],"type":"Point"}
}