{
  "type": "Feature",
  "properties": {
    "iso:country":"DE",
    "sg:address":"Hauptstr. 4",
    "sg:city":"Mettenheim",
    "sg:phone":"+49 6242/1621",
    "sg:postcode":"67582",
    "sg:province":"Rheinland-Pfalz",
    "wof:name":"Rolf Wei\u00dfbach",
    "wof:placetype":"venue"
},
  "geometry": {"coordinates":[8.3262691498,49.7399520874],"type":"Point"}
}