{
  "type": "Feature",
  "properties": {
    "iso:country":"DE",
    "sg:address":"Hansering 12",
    "sg:city":"Halle",
    "sg:phone":"+49 345/2003852",
    "sg:postcode":"06108",
    "sg:province":"Sachsen-Anhalt",
    "wof:name":"Apotheke Am Hansering Inh. Ines Wenzel",
    "wof:placetype":"venue"
},
  "geometry": {"coordinates":[11.974816,51.482018],"type":"Point"}
}