{
  "type": "Feature",
  "properties": {
    "iso:country":"DE",
    "sg:address":"Adolf-Schmetzer-Str. 7",
    "sg:city":"Regensburg",
    "sg:phone":"+49 941/799940",
    "sg:postcode":"93055",
    "sg:province":"Bayern",
    "wof:name":"Lindner Ag",
    "wof:placetype":"venue"
},
  "geometry": {"coordinates":[12.110054,49.017666],"type":"Point"}
}