{
  "type": "Feature",
  "properties": {
    "iso:country":"DE",
    "sg:address":"Schottjer Str. 2",
    "sg:city":"Upgant-Schott",
    "sg:phone":"+49 4934/4118",
    "sg:postcode":"26529",
    "sg:province":"Niedersachsen",
    "wof:name":"Adena Gmbh",
    "wof:placetype":"venue"
},
  "geometry": {"coordinates":[7.2688188553,53.5121078491],"type":"Point"}
}