{
  "type": "Feature",
  "properties": {
    "iso:country":"DE",
    "sg:address":"Roscherstr. 13",
    "sg:city":"Hannover",
    "sg:postcode":"30161",
    "sg:province":"Niedersachsen",
    "wof:name":"Penta Tv Puppen F\u00fcr Film Werbung Und",
    "wof:placetype":"venue"
},
  "geometry": {"coordinates":[9.747289,52.37743],"type":"Point"}
}