{
  "type": "Feature",
  "properties": {
    "iso:country":"DE",
    "sg:address":"Stadtdeich 7",
    "sg:city":"Hamburg",
    "sg:phone":"+49 40/3256230",
    "sg:postcode":"20097",
    "sg:province":"Hamburg",
    "wof:name":"Hermes Datenservice Gmbh",
    "wof:placetype":"venue"
},
  "geometry": {"coordinates":[10.008246,53.545517],"type":"Point"}
}