{
  "type": "Feature",
  "properties": {
    "iso:country":"DE",
    "sg:address":"Bahnhofsring 30",
    "sg:city":"Leer",
    "sg:phone":"+49 491/5547",
    "sg:postcode":"26789",
    "sg:province":"Niedersachsen",
    "wof:name":"J. Seemann",
    "wof:placetype":"venue"
},
  "geometry": {"coordinates":[7.4624500275,53.2329406738],"type":"Point"}
}