{
  "type": "Feature",
  "properties": {
    "iso:country":"DE",
    "sg:address":"Am Haushof 3",
    "sg:city":"W\u00fcrselen",
    "sg:phone":"+49 2405/93502",
    "sg:postcode":"52146",
    "sg:province":"Nordrhein-Westfalen",
    "wof:name":"Andreas Weber",
    "wof:placetype":"venue"
},
  "geometry": {"coordinates":[6.135137,50.814541],"type":"Point"}
}