{
  "type": "Feature",
  "properties": {
    "iso:country":"DE",
    "sg:address":"Meinekestr. 3",
    "sg:city":"Nordhorn",
    "sg:phone":"+49 4959/2183890",
    "sg:postcode":"48531",
    "sg:province":"Niedersachsen",
    "wof:name":"K\u00d6hler Nutzfahrzeug-technik Gmbh",
    "wof:placetype":"venue"
},
  "geometry": {"coordinates":[7.153676033,52.4612121582],"type":"Point"}
}