{
  "type": "Feature",
  "properties": {
    "iso:country":"DE",
    "sg:address":"Schillerring 77",
    "sg:city":"Schwedt",
    "sg:phone":"+49 3332/32350",
    "sg:postcode":"16303",
    "sg:province":"Brandenburg",
    "wof:name":"Mocca Bar",
    "wof:placetype":"venue"
},
  "geometry": {"coordinates":[14.247452,53.072334],"type":"Point"}
}