{
  "type": "Feature",
  "properties": {
    "iso:country":"DE",
    "sg:address":"Schmidhub 3",
    "sg:city":"Pleiskirchen",
    "sg:postcode":"84568",
    "sg:province":"Bayern",
    "wof:name":"Pleiskirchen Golf Verwaltungs Gmbh",
    "wof:placetype":"venue"
},
  "geometry": {"coordinates":[12.6014318466,48.3110237122],"type":"Point"}
}