{
  "type": "Feature",
  "properties": {
    "iso:country":"DE",
    "sg:address":"Vor Dem Rostocker Tor 48",
    "sg:city":"B\u00fctzow",
    "sg:phone":"+49 4938/4612664",
    "sg:postcode":"18246",
    "sg:province":"Mecklenburg-Vorpommern",
    "wof:name":"Hans-georg Barmwoldt",
    "wof:placetype":"venue"
},
  "geometry": {"coordinates":[11.99136,53.853748],"type":"Point"}
}