{
  "type": "Feature",
  "properties": {
    "iso:country":"DE",
    "sg:address":"Bahnhofstr. 40",
    "sg:city":"Ochtrup",
    "sg:phone":"+49 2553/2664",
    "sg:postcode":"48607",
    "sg:province":"Nordrhein-Westfalen",
    "wof:name":"P. Ross",
    "wof:placetype":"venue"
},
  "geometry": {"coordinates":[7.1873321533,52.2053070068],"type":"Point"}
}