{
  "type": "Feature",
  "properties": {
    "iso:country":"DE",
    "sg:address":"Sonnenweg 21",
    "sg:city":"Todtmoos",
    "sg:phone":"+49 7674/8687",
    "sg:postcode":"79682",
    "sg:province":"Baden-W\u00fcrttemberg",
    "wof:name":"G\u00e4stehaus Moosyb\u00e4rh\u00fctte M\u00e4ttle",
    "wof:placetype":"venue"
},
  "geometry": {"coordinates":[7.9889268875,47.7466545105],"type":"Point"}
}