{
  "type": "Feature",
  "properties": {
    "iso:country":"DE",
    "sg:address":"Clara-Zetkin-Str. 37",
    "sg:city":"Holzwei\u00dfig",
    "sg:phone":"+49 3493/69617",
    "sg:postcode":"06808",
    "sg:province":"Sachsen-Anhalt",
    "wof:name":"Helgard Wawzyniak",
    "wof:placetype":"venue"
},
  "geometry": {"coordinates":[12.305748,51.598019],"type":"Point"}
}