{
  "type": "Feature",
  "properties": {
    "iso:country":"DE",
    "sg:address":"Brandenburger Str. 76",
    "sg:city":"Genthin",
    "sg:phone":"+49 3933/3685",
    "sg:postcode":"39307",
    "sg:province":"Sachsen-Anhalt",
    "wof:name":"Arthur Riegel Inh. Dagmar Fielecke",
    "wof:placetype":"venue"
},
  "geometry": {"coordinates":[12.1608133316,52.4056625366],"type":"Point"}
}