{
  "type": "Feature",
  "properties": {
    "iso:country":"DE",
    "sg:address":"Boxhagener Str. 28",
    "sg:city":"Berlin",
    "sg:phone":"+49 30/2910626",
    "sg:postcode":"10245",
    "sg:province":"Berlin",
    "wof:name":"Roland Jabs",
    "wof:placetype":"venue"
},
  "geometry": {"coordinates":[13.45854,52.512524],"type":"Point"}
}