{
  "type": "Feature",
  "properties": {
    "iso:country":"DE",
    "sg:address":"Keckstr. 1",
    "sg:city":"Endingen",
    "sg:phone":"+49 7642/3992",
    "sg:postcode":"79346",
    "sg:province":"Baden-W\u00fcrttemberg",
    "wof:name":"Fischer Kr\u00e4mer Orgelbau Ohg",
    "wof:placetype":"venue"
},
  "geometry": {"coordinates":[7.7052087784,48.1435317993],"type":"Point"}
}