{
  "type": "Feature",
  "properties": {
    "iso:country":"DE",
    "sg:address":"Hauptstr. 20",
    "sg:city":"Wiehl",
    "sg:phone":"+49 2262/91604",
    "sg:postcode":"51674",
    "sg:province":"Nordrhein-Westfalen",
    "wof:name":"R. Schauer",
    "wof:placetype":"venue"
},
  "geometry": {"coordinates":[7.547807,50.949306],"type":"Point"}
}