{
  "type": "Feature",
  "properties": {
    "iso:country":"DE",
    "sg:address":"Friedrichstr. 62-80",
    "sg:city":"D\u00fcsseldorf",
    "sg:phone":"+49 211/8263066",
    "sg:postcode":"40217",
    "sg:province":"Nordrhein-Westfalen",
    "wof:name":"West Lb Asset Management Kapitalanlagegesellschaft Mbh",
    "wof:placetype":"venue"
},
  "geometry": {"coordinates":[6.7770419121,51.2136497498],"type":"Point"}
}