{
  "type": "Feature",
  "properties": {
    "iso:country":"DE",
    "sg:address":"Bexterbreden 7",
    "sg:city":"Bad Salzuflen",
    "sg:phone":"+49 5222/977540",
    "sg:postcode":"32107",
    "sg:province":"Nordrhein-Westfalen",
    "wof:name":"Iso D\u00e4mmstoff Handels Gmbh",
    "wof:placetype":"venue"
},
  "geometry": {"coordinates":[8.707186,52.052998],"type":"Point"}
}