{
  "type": "Feature",
  "properties": {
    "iso:country":"DE",
    "sg:address":"Wildbader Str. 128",
    "sg:city":"Birkenfeld",
    "sg:phone":"+49 7231/472122",
    "sg:postcode":"75217",
    "sg:province":"Baden-W\u00fcrttemberg",
    "wof:name":"H. Ossira",
    "wof:placetype":"venue"
},
  "geometry": {"coordinates":[8.6401472092,48.8653106689],"type":"Point"}
}