{
  "type": "Feature",
  "properties": {
    "iso:country":"DE",
    "sg:address":"Bessemerstr. 2",
    "sg:city":"Stadtlohn",
    "sg:phone":"+49 2563/97483",
    "sg:postcode":"48703",
    "sg:province":"Nordrhein-Westfalen",
    "wof:name":"Kirschner Bedachungs- Gmbh",
    "wof:placetype":"venue"
},
  "geometry": {"coordinates":[6.914458,51.984417],"type":"Point"}
}