{
  "type": "Feature",
  "properties": {
    "iso:country":"DE",
    "sg:address":"Pettenkoferstr. 16",
    "sg:city":"Ludwigshafen",
    "sg:phone":"+49 621/5293954",
    "sg:postcode":"67063",
    "sg:province":"Rheinland-Pfalz",
    "wof:name":"Mayerbr\u00e4u Am Hallenbad",
    "wof:placetype":"venue"
},
  "geometry": {"coordinates":[8.424949646,49.4872779846],"type":"Point"}
}