{
  "type": "Feature",
  "properties": {
    "iso:country":"DE",
    "sg:address":"Gartenstr 1",
    "sg:city":"Heidenheim",
    "sg:phone":"+49 4973/677388",
    "sg:postcode":"89518",
    "sg:province":"Baden-W\u00fcrttemberg",
    "wof:name":"Heidenheimer Volksbank Eg",
    "wof:placetype":"venue"
},
  "geometry": {"coordinates":[10.13046,48.68504],"type":"Point"}
}