{
  "type": "Feature",
  "properties": {
    "iso:country":"DE",
    "sg:address":"Ulrich-von-Hassell-Str. 9a",
    "sg:city":"Ebenhausen",
    "sg:phone":"+49 8178/4607",
    "sg:postcode":"82067",
    "sg:province":"Bayern",
    "wof:name":"Elmar Dittmann Architekt",
    "wof:placetype":"venue"
},
  "geometry": {"coordinates":[11.45131,47.979618],"type":"Point"}
}