{
  "type": "Feature",
  "properties": {
    "iso:country":"DE",
    "sg:address":"J\u00f6rg-Ratgeb-Str. 43",
    "sg:city":"Pforzheim",
    "sg:phone":"+49 7231/26230",
    "sg:postcode":"75173",
    "sg:province":"Baden-W\u00fcrttemberg",
    "wof:name":"Ars Vivendi",
    "wof:placetype":"venue"
},
  "geometry": {"coordinates":[8.695306778,48.8895263672],"type":"Point"}
}