{
  "type": "Feature",
  "properties": {
    "iso:country":"DE",
    "sg:address":"Am Schlo\u00dfplatz 6",
    "sg:city":"Rastatt",
    "sg:phone":"+49 7222/938126",
    "sg:postcode":"76437",
    "sg:province":"Baden-W\u00fcrttemberg",
    "wof:name":"J\u00fcrgen Und Ute Schwab Anlageberater",
    "wof:placetype":"venue"
},
  "geometry": {"coordinates":[8.2079057693,48.8589744568],"type":"Point"}
}