{
  "type": "Feature",
  "properties": {
    "iso:country":"DE",
    "sg:address":"Leckingser Str. 201",
    "sg:city":"Iserlohn",
    "sg:phone":"+49 4923/7140081",
    "sg:postcode":"58640",
    "sg:province":"Nordrhein-Westfalen",
    "wof:name":"Kettenwerke Schlieper Gmbh",
    "wof:placetype":"venue"
},
  "geometry": {"coordinates":[7.6718578339,51.4239501953],"type":"Point"}
}