{
  "type": "Feature",
  "properties": {
    "iso:country":"DE",
    "sg:address":"Dammstr. 8",
    "sg:city":"Tuttlingen",
    "sg:phone":"+49 7461/2554",
    "sg:postcode":"78532",
    "sg:province":"Baden-W\u00fcrttemberg",
    "wof:name":"Wilhelm Koch",
    "wof:placetype":"venue"
},
  "geometry": {"coordinates":[8.8227062225,47.987159729],"type":"Point"}
}