{
  "type": "Feature",
  "properties": {
    "iso:country":"DE",
    "sg:address":"Lange Reihe 9",
    "sg:city":"Mewegen",
    "sg:phone":"+49 39744/203",
    "sg:postcode":"17322",
    "sg:province":"Mecklenburg-Vorpommern",
    "wof:name":"J\u00fcrgen Manthe",
    "wof:placetype":"venue"
},
  "geometry": {"coordinates":[14.334671,53.413372],"type":"Point"}
}