{
  "type": "Feature",
  "properties": {
    "iso:country":"DE",
    "sg:address":"Berliner Str. 16a",
    "sg:city":"Gransee",
    "sg:phone":"+49 3306/2277",
    "sg:postcode":"16775",
    "sg:province":"Brandenburg",
    "wof:name":"Bergmann Bau Gmbh",
    "wof:placetype":"venue"
},
  "geometry": {"coordinates":[13.153723,52.897305],"type":"Point"}
}