{
  "type": "Feature",
  "properties": {
    "iso:country":"DE",
    "sg:address":"Ruhrorter Str. 7",
    "sg:city":"Mannheim",
    "sg:phone":"+49 621/8042122",
    "sg:postcode":"68219",
    "sg:province":"Baden-W\u00fcrttemberg",
    "wof:name":"G\u00fcnter Pr\u00e4g Schrotthandel",
    "wof:placetype":"venue"
},
  "geometry": {"coordinates":[8.519026,49.422962],"type":"Point"}
}