{
  "type": "Feature",
  "properties": {
    "iso:country":"DE",
    "sg:address":"Trostfelder Weg 8",
    "sg:city":"Altentreptow",
    "sg:phone":"+49 3961/215001",
    "sg:postcode":"17087",
    "sg:province":"Mecklenburg-Vorpommern",
    "wof:name":"Nachrichtentechnik Bieck Ohg",
    "wof:placetype":"venue"
},
  "geometry": {"coordinates":[13.2387056351,53.6834640503],"type":"Point"}
}