{
  "type": "Feature",
  "properties": {
    "iso:country":"DE",
    "sg:address":"Blankenburger Str. 149 A",
    "sg:city":"Berlin",
    "sg:postcode":"13127",
    "sg:province":"Berlin",
    "wof:name":"Steinau Assekuranz- Vermittlung E. Kfr.",
    "wof:placetype":"venue"
},
  "geometry": {"coordinates":[13.427947998,52.5879859924],"type":"Point"}
}