{
  "type": "Feature",
  "properties": {
    "iso:country":"DE",
    "sg:address":"Rosenweg 26",
    "sg:city":"Geesthacht",
    "sg:phone":"+49 4152/843361",
    "sg:postcode":"21502",
    "sg:province":"Schleswig-Holstein",
    "wof:name":"Trading & Shipping Team Gmbh",
    "wof:placetype":"venue"
},
  "geometry": {"coordinates":[10.3536062241,53.4418449402],"type":"Point"}
}