{
  "type": "Feature",
  "properties": {
    "iso:country":"DE",
    "sg:address":"Gl\u00fcck-Auf-Siedlung 42",
    "sg:city":"Bernburg",
    "sg:phone":"+49 3471/311925",
    "sg:postcode":"06406",
    "sg:province":"Sachsen-Anhalt",
    "wof:name":"W. Schumann",
    "wof:placetype":"venue"
},
  "geometry": {"coordinates":[11.7322015762,51.7802886963],"type":"Point"}
}