{
  "type": "Feature",
  "properties": {
    "iso:country":"DE",
    "sg:address":"Bahnhofstr. 1",
    "sg:city":"Kastellaun",
    "sg:phone":"+49 6762/7213",
    "sg:postcode":"56288",
    "sg:province":"Rheinland-Pfalz",
    "wof:name":"Dieter Merg Heilpraktiker",
    "wof:placetype":"venue"
},
  "geometry": {"coordinates":[7.442358017,50.0695152283],"type":"Point"}
}