{
  "type": "Feature",
  "properties": {
    "iso:country":"DE",
    "sg:address":"Piusstr. 15",
    "sg:city":"Witten",
    "sg:phone":"+49 2302/80895",
    "sg:postcode":"58454",
    "sg:province":"Nordrhein-Westfalen",
    "wof:name":"Wilh. K\u00e4tker",
    "wof:placetype":"venue"
},
  "geometry": {"coordinates":[7.403653,51.450417],"type":"Point"}
}