{
  "type": "Feature",
  "properties": {
    "iso:country":"DE",
    "sg:address":"Auer Str. 50",
    "sg:city":"Karlsruhe",
    "sg:postcode":"76227",
    "sg:province":"Baden-W\u00fcrttemberg",
    "wof:name":"Kirschenmann Abg- Apparatebau E. K.",
    "wof:placetype":"venue"
},
  "geometry": {"coordinates":[8.4624862671,48.9956855774],"type":"Point"}
}