{
  "type": "Feature",
  "properties": {
    "iso:country":"DE",
    "sg:address":"Oberweg 4",
    "sg:city":"Langewiesen",
    "sg:phone":"+49 3677/812847",
    "sg:postcode":"98704",
    "sg:province":"Th\u00fcringen",
    "wof:name":"Hugo Eckstein",
    "wof:placetype":"venue"
},
  "geometry": {"coordinates":[10.9625864029,50.6750946045],"type":"Point"}
}