{
  "type": "Feature",
  "properties": {
    "iso:country":"DE",
    "sg:address":"Maarweg 9",
    "sg:city":"Weilerswist",
    "sg:phone":"+49 2254/5341",
    "sg:postcode":"53919",
    "sg:province":"Nordrhein-Westfalen",
    "wof:name":"Bruno Nowak",
    "wof:placetype":"venue"
},
  "geometry": {"coordinates":[6.845515,50.757992],"type":"Point"}
}