{
  "type": "Feature",
  "properties": {
    "iso:country":"DE",
    "sg:address":"Frohnhecken",
    "sg:city":"Laufach",
    "sg:phone":"+49 6093/8681",
    "sg:postcode":"63846",
    "sg:province":"Bayern",
    "wof:name":"Pizzeria Bei Ciccio",
    "wof:placetype":"venue"
},
  "geometry": {"coordinates":[9.2802152634,50.0083885193],"type":"Point"}
}