{
  "type": "Feature",
  "properties": {
    "iso:country":"DE",
    "sg:address":"Marktstr. 40",
    "sg:city":"B\u00f6blingen",
    "sg:phone":"+49 7031/225087",
    "sg:postcode":"71032",
    "sg:province":"Baden-W\u00fcrttemberg",
    "wof:name":"Hotel Garni Decker",
    "wof:placetype":"venue"
},
  "geometry": {"coordinates":[9.0131111145,48.6846084595],"type":"Point"}
}