{
  "type": "Feature",
  "properties": {
    "iso:country":"DE",
    "sg:address":"Bergesbirken 1",
    "sg:city":"Wipperf\u00fcrth",
    "sg:phone":"+49 2267/1076",
    "sg:postcode":"51688",
    "sg:province":"Nordrhein-Westfalen",
    "wof:name":"Heinz K\u00fcster",
    "wof:placetype":"venue"
},
  "geometry": {"coordinates":[7.386269,51.084785],"type":"Point"}
}