{
  "type": "Feature",
  "properties": {
    "iso:country":"DE",
    "sg:address":"Robert-Koch-Str. 5",
    "sg:city":"Potsdam",
    "sg:phone":"+49 331/707997",
    "sg:postcode":"14482",
    "sg:province":"Brandenburg",
    "wof:name":"Die Bratpfanne",
    "wof:placetype":"venue"
},
  "geometry": {"coordinates":[13.1149682999,52.3981704712],"type":"Point"}
}