{
  "type": "Feature",
  "properties": {
    "iso:country":"DE",
    "sg:address":"Bonner Talweg 344 B",
    "sg:city":"Bonn",
    "sg:phone":"+49 228/549155",
    "sg:postcode":"53129",
    "sg:province":"Nordrhein-Westfalen",
    "wof:name":"Frank Schneider Concepts",
    "wof:placetype":"venue"
},
  "geometry": {"coordinates":[7.105093,50.714088],"type":"Point"}
}