{
  "type": "Feature",
  "properties": {
    "iso:country":"DE",
    "sg:address":"Sternengasse 34",
    "sg:city":"Frechen",
    "sg:phone":"+49 2234/54487",
    "sg:postcode":"50226",
    "sg:province":"Nordrhein-Westfalen",
    "wof:name":"Peter Wolf",
    "wof:placetype":"venue"
},
  "geometry": {"coordinates":[6.8115267754,50.9088745117],"type":"Point"}
}