{
  "type": "Feature",
  "properties": {
    "iso:country":"DE",
    "sg:address":"Westernecke 8",
    "sg:city":"Borchen",
    "sg:phone":"+49 5292/1561",
    "sg:postcode":"33178",
    "sg:province":"Nordrhein-Westfalen",
    "wof:name":"Wilhelm R\u00f6ttger",
    "wof:placetype":"venue"
},
  "geometry": {"coordinates":[8.758362,51.630322],"type":"Point"}
}