{
  "type": "Feature",
  "properties": {
    "iso:country":"DE",
    "sg:address":"Iehweg",
    "sg:city":"Hemau",
    "sg:postcode":"93155",
    "sg:province":"Bayern",
    "wof:name":"Schrempf Bei Rohrmusik",
    "wof:placetype":"venue"
},
  "geometry": {"coordinates":[11.782335,49.052094],"type":"Point"}
}