{
  "type": "Feature",
  "properties": {
    "iso:country":"DE",
    "sg:address":"D\u00fcbener Landstr. 1",
    "sg:city":"Eilenburg",
    "sg:postcode":"04838",
    "sg:province":"Sachsen",
    "wof:name":"Zwischengenossenschaftliche Bauorganisation Landbau",
    "wof:placetype":"venue"
},
  "geometry": {"coordinates":[12.66487,51.474838],"type":"Point"}
}