{
  "type": "Feature",
  "properties": {
    "iso:country":"DE",
    "sg:address":"Duisburger Str. 301",
    "sg:city":"M\u00fclheim",
    "sg:phone":"+49 208/55007",
    "sg:postcode":"45478",
    "sg:province":"Nordrhein-Westfalen",
    "wof:name":"Wolfgang Hoyer Steuerberater",
    "wof:placetype":"venue"
},
  "geometry": {"coordinates":[6.8379268646,51.429523468],"type":"Point"}
}