{
  "type": "Feature",
  "properties": {
    "iso:country":"DE",
    "sg:address":"Riemannstr. 1",
    "sg:city":"Solms",
    "sg:postcode":"35606",
    "sg:province":"Hessen",
    "wof:name":"Beteiligungsges. Herhof- Trockenstabilat-anlage Gmbh",
    "wof:placetype":"venue"
},
  "geometry": {"coordinates":[8.392392,50.551334],"type":"Point"}
}