{
  "type": "Feature",
  "properties": {
    "iso:country":"DE",
    "sg:address":"Steingasse 46",
    "sg:city":"Schwalmstadt",
    "sg:phone":"+49 6691/21268",
    "sg:postcode":"34613",
    "sg:province":"Hessen",
    "wof:name":"Dieter Niemeyer",
    "wof:placetype":"venue"
},
  "geometry": {"coordinates":[9.1862001419,50.9149780273],"type":"Point"}
}