{
  "type": "Feature",
  "properties": {
    "iso:country":"DE",
    "sg:address":"Ottilienstr. 57a",
    "sg:city":"M\u00fcnchen",
    "sg:phone":"+49 89/4304261",
    "sg:postcode":"81827",
    "sg:province":"Bayern",
    "wof:name":"Wagner Gmbh",
    "wof:placetype":"venue"
},
  "geometry": {"coordinates":[11.681177,48.111427],"type":"Point"}
}