{
  "type": "Feature",
  "properties": {
    "iso:country":"DE",
    "sg:address":"Schulberg 4",
    "sg:city":"Krombach",
    "sg:postcode":"63829",
    "sg:province":"Bayern",
    "wof:name":"Gemeindeb\u00fccherei Krombach Rathaus",
    "wof:placetype":"venue"
},
  "geometry": {"coordinates":[9.207668,50.078766],"type":"Point"}
}