{
  "type": "Feature",
  "properties": {
    "iso:country":"DE",
    "sg:address":"Ulrich-Haberland-Str. 61",
    "sg:city":"Bonn",
    "sg:phone":"+49 228/735302",
    "sg:postcode":"53121",
    "sg:province":"Nordrhein-Westfalen",
    "wof:name":"Institut F\u00fcr Cytologie",
    "wof:placetype":"venue"
},
  "geometry": {"coordinates":[7.070827961,50.7319335938],"type":"Point"}
}