{
  "type": "Feature",
  "properties": {
    "iso:country":"DE",
    "sg:address":"Sudetenstr. 17",
    "sg:city":"Leipheim",
    "sg:postcode":"89340",
    "sg:province":"Bayern",
    "wof:name":"Oechsle Gmbh & Co. Kg",
    "wof:placetype":"venue"
},
  "geometry": {"coordinates":[10.2284517288,48.4533348083],"type":"Point"}
}