{
  "type": "Feature",
  "properties": {
    "iso:country":"DE",
    "sg:address":"Langstr. 7",
    "sg:city":"Erlensee",
    "sg:phone":"+49 6183/2366",
    "sg:postcode":"63526",
    "sg:province":"Hessen",
    "wof:name":"Karl Stumpp Architekt",
    "wof:placetype":"venue"
},
  "geometry": {"coordinates":[8.992823,50.160439],"type":"Point"}
}