{
  "type": "Feature",
  "properties": {
    "iso:country":"DE",
    "sg:address":"Gro\u00dfer Graben 23",
    "sg:city":"Walsrode",
    "sg:phone":"+49 5161",
    "sg:postcode":"29664",
    "sg:province":"Niedersachsen",
    "wof:name":"Chirurgische Gemeinschaftspraxis Walsrode",
    "wof:placetype":"venue"
},
  "geometry": {"coordinates":[9.590557,52.861961],"type":"Point"}
}