{
  "type": "Feature",
  "properties": {
    "iso:country":"DE",
    "sg:address":"Eichenstr. 15",
    "sg:city":"Ahorn",
    "sg:phone":"+49 9561/28739",
    "sg:postcode":"96482",
    "sg:province":"Bayern",
    "wof:name":"Reuter Gmbh",
    "wof:placetype":"venue"
},
  "geometry": {"coordinates":[10.912746,50.226521],"type":"Point"}
}