{
  "type": "Feature",
  "properties": {
    "iso:country":"DE",
    "sg:address":"Breitscheidstr. 28a",
    "sg:city":"Oschersleben",
    "sg:phone":"+49 4939/4994320",
    "sg:postcode":"39387",
    "sg:province":"Sachsen-Anhalt",
    "wof:name":"Dr. Ponsold Gmbh",
    "wof:placetype":"venue"
},
  "geometry": {"coordinates":[11.228547,52.036297],"type":"Point"}
}