{
  "type": "Feature",
  "properties": {
    "iso:country":"DE",
    "sg:address":"Mertensstr. 8",
    "sg:city":"H\u00fcckelhoven",
    "sg:phone":"+49 2462/906744",
    "sg:postcode":"41836",
    "sg:province":"Nordrhein-Westfalen",
    "wof:name":"Reinhard Gerl Cnc Service Team Gmbh",
    "wof:placetype":"venue"
},
  "geometry": {"coordinates":[6.2708587646,51.0152931213],"type":"Point"}
}