{
  "type": "Feature",
  "properties": {
    "iso:country":"DE",
    "sg:address":"Herbststr. 27",
    "sg:city":"Heilbronn",
    "sg:postcode":"74072",
    "sg:province":"Baden-W\u00fcrttemberg",
    "wof:name":"Griesinger Verwaltungs- Gmbh & Co. Kg",
    "wof:placetype":"venue"
},
  "geometry": {"coordinates":[9.2255029678,49.1378173828],"type":"Point"}
}