{
  "type": "Feature",
  "properties": {
    "iso:country":"DE",
    "sg:address":"Grunauer Str. 5",
    "sg:city":"Schee\u00dfel",
    "sg:phone":"+49 4263/2980",
    "sg:postcode":"27383",
    "sg:province":"Niedersachsen",
    "wof:name":"Otten",
    "wof:placetype":"venue"
},
  "geometry": {"coordinates":[9.489534,53.177608],"type":"Point"}
}