{
  "type": "Feature",
  "properties": {
    "iso:country":"DE",
    "sg:address":"Ruppertstr. 9",
    "sg:city":"M\u00fcnchen",
    "sg:phone":"+49 89/7252174",
    "sg:postcode":"80337",
    "sg:province":"Bayern",
    "wof:name":"Kaml Gmbh",
    "wof:placetype":"venue"
},
  "geometry": {"coordinates":[11.552136,48.123863],"type":"Point"}
}