{
  "type": "Feature",
  "properties": {
    "iso:country":"DE",
    "sg:address":"Berliner Str. 48",
    "sg:city":"A\u00dflar",
    "sg:phone":"+49 4964/4198410",
    "sg:postcode":"35614",
    "sg:province":"Hessen",
    "wof:name":"Suss Microtec Lithography Gmbh",
    "wof:placetype":"venue"
},
  "geometry": {"coordinates":[8.473405,50.582378],"type":"Point"}
}