{
  "type": "Feature",
  "properties": {
    "iso:country":"DE",
    "sg:address":"Coburger Str. 56",
    "sg:city":"Gr\u00e4fenthal",
    "sg:phone":"+49 36703/850",
    "sg:postcode":"98743",
    "sg:province":"Th\u00fcringen",
    "wof:name":"Gkt Gr\u00e4fenthaler Kunststofftechnik Gmbh",
    "wof:placetype":"venue"
},
  "geometry": {"coordinates":[11.309394,50.525707],"type":"Point"}
}