{
  "type": "Feature",
  "properties": {
    "iso:country":"DE",
    "sg:address":"Gesellenweg 7",
    "sg:city":"Minden",
    "sg:phone":"+49 571/504010",
    "sg:postcode":"32427",
    "sg:province":"Nordrhein-Westfalen",
    "wof:name":"I-center Elektrogro\u00dfhandel Gmbh & Co.",
    "wof:placetype":"venue"
},
  "geometry": {"coordinates":[8.8819503784,52.2918891907],"type":"Point"}
}