{
  "type": "Feature",
  "properties": {
    "iso:country":"DE",
    "sg:address":"Dorfstr. 32",
    "sg:city":"Gro\u00dfweitzschen",
    "sg:postcode":"04720",
    "sg:province":"Sachsen",
    "wof:name":"Fleischwarenverkaufs-und Gastst\u00e4ttenverwaltungsges. Mbh",
    "wof:placetype":"venue"
},
  "geometry": {"coordinates":[13.1196498871,51.1288414001],"type":"Point"}
}