{
  "type": "Feature",
  "properties": {
    "iso:country":"DE",
    "sg:address":"Schlo\u00dfstr. 8",
    "sg:city":"Tutzing",
    "sg:phone":"+49 8158/6766",
    "sg:postcode":"82327",
    "sg:province":"Bayern",
    "wof:name":"Dr. Albrecht Ulrich Rechtsanwalt",
    "wof:placetype":"venue"
},
  "geometry": {"coordinates":[11.2825870514,47.9097557068],"type":"Point"}
}