{
  "type": "Feature",
  "properties": {
    "iso:country":"DE",
    "sg:address":"Friedrich-Kirchhoff-Str. 4",
    "sg:city":"Iserlohn",
    "sg:postcode":"58640",
    "sg:province":"Nordrhein-Westfalen",
    "wof:name":"Manasse Gmbh",
    "wof:placetype":"venue"
},
  "geometry": {"coordinates":[7.6947088242,51.3998413086],"type":"Point"}
}