{
  "type": "Feature",
  "properties": {
    "iso:country":"DE",
    "sg:address":"Hasenrainweg 63",
    "sg:city":"Esslingen",
    "sg:phone":"+49 711/317305",
    "sg:postcode":"73730",
    "sg:province":"Baden-W\u00fcrttemberg",
    "wof:name":"Dr. Sommer Techn. Entwicklungen Gmbh",
    "wof:placetype":"venue"
},
  "geometry": {"coordinates":[9.329287529,48.7372207642],"type":"Point"}
}