{
  "type": "Feature",
  "properties": {
    "iso:country":"DE",
    "sg:address":"Kustrenaer Weg 70",
    "sg:city":"Bernburg",
    "sg:postcode":"06406",
    "sg:province":"Sachsen-Anhalt",
    "wof:name":"Normax Industriebedarf Gmbh",
    "wof:placetype":"venue"
},
  "geometry": {"coordinates":[11.73359,51.777077],"type":"Point"}
}