{
  "type": "Feature",
  "properties": {
    "iso:country":"DE",
    "sg:address":"Takelbasweg 1",
    "sg:city":"Bremen",
    "sg:phone":"+49 421/602269",
    "sg:postcode":"28777",
    "sg:province":"Bremen",
    "wof:name":"E. Nerger",
    "wof:placetype":"venue"
},
  "geometry": {"coordinates":[8.5444784164,53.1899299622],"type":"Point"}
}