{
  "type": "Feature",
  "properties": {
    "iso:country":"DE",
    "sg:address":"Isolde-Kurz-Str. 5",
    "sg:city":"Kirchheim",
    "sg:phone":"+49 7021/2178",
    "sg:postcode":"73230",
    "sg:province":"Baden-W\u00fcrttemberg",
    "wof:name":"Landmetzgerei Scheu & Weber Gmbh",
    "wof:placetype":"venue"
},
  "geometry": {"coordinates":[9.4222698212,48.6573600769],"type":"Point"}
}