{
  "type": "Feature",
  "properties": {
    "iso:country":"DE",
    "sg:address":"M\u00fchlenstr. 34",
    "sg:city":"Melle",
    "sg:phone":"+49 5422/41331",
    "sg:postcode":"49324",
    "sg:province":"Niedersachsen",
    "wof:name":"Diakonie-sozialstation",
    "wof:placetype":"venue"
},
  "geometry": {"coordinates":[8.341363,52.204956],"type":"Point"}
}