{
  "type": "Feature",
  "properties": {
    "iso:country":"DE",
    "sg:address":"Am B\u00fcchsensch\u00fctz 16",
    "sg:city":"Hattingen",
    "sg:phone":"+49 2324/21000",
    "sg:postcode":"45527",
    "sg:province":"Nordrhein-Westfalen",
    "wof:name":"Hitop",
    "wof:placetype":"venue"
},
  "geometry": {"coordinates":[7.200327,51.406742],"type":"Point"}
}