{
  "type": "Feature",
  "properties": {
    "iso:country":"DE",
    "sg:address":"Siegfriedstr. 2",
    "sg:city":"Xanten",
    "sg:phone":"+49 2801/853",
    "sg:postcode":"46509",
    "sg:province":"Nordrhein-Westfalen",
    "wof:name":"Hermann-josef Van Bebber",
    "wof:placetype":"venue"
},
  "geometry": {"coordinates":[6.45038,51.661022],"type":"Point"}
}