{
  "type": "Feature",
  "properties": {
    "iso:country":"DE",
    "sg:address":"Rosenstr. 11",
    "sg:city":"Lohne",
    "sg:phone":"+49 4442/4936",
    "sg:postcode":"49393",
    "sg:province":"Niedersachsen",
    "wof:name":"Heinz Kohl",
    "wof:placetype":"venue"
},
  "geometry": {"coordinates":[8.2271366119,52.6698646545],"type":"Point"}
}