{
  "type": "Feature",
  "properties": {
    "iso:country":"DE",
    "sg:address":"Schwetzinger Str. 36",
    "sg:city":"Heidelberg",
    "sg:phone":"+49 6221/785315",
    "sg:postcode":"69124",
    "sg:province":"Baden-W\u00fcrttemberg",
    "wof:name":"Werner J\u00e4ger",
    "wof:placetype":"venue"
},
  "geometry": {"coordinates":[8.667738,49.378208],"type":"Point"}
}