{
  "type": "Feature",
  "properties": {
    "iso:country":"DE",
    "sg:address":"Brigittastr. 26",
    "sg:city":"Essen",
    "sg:phone":"+49 201/774464",
    "sg:postcode":"45130",
    "sg:province":"Nordrhein-Westfalen",
    "wof:name":"B. Derichs",
    "wof:placetype":"venue"
},
  "geometry": {"coordinates":[7.0103549957,51.4395828247],"type":"Point"}
}