{
  "type": "Feature",
  "properties": {
    "iso:country":"DE",
    "sg:address":"St. Andre-Str. 5",
    "sg:city":"K\u00f6nigsbach-Stein",
    "sg:phone":"+49 7232/2952",
    "sg:postcode":"75203",
    "sg:province":"Baden-W\u00fcrttemberg",
    "wof:name":"Katz Gmbh",
    "wof:placetype":"venue"
},
  "geometry": {"coordinates":[8.612074852,48.9651565552],"type":"Point"}
}