{
  "type": "Feature",
  "properties": {
    "iso:country":"DE",
    "sg:address":"Bunsenstr. 27",
    "sg:city":"Kiel",
    "sg:postcode":"24145",
    "sg:province":"Schleswig-Holstein",
    "wof:name":"E. Meyer",
    "wof:placetype":"venue"
},
  "geometry": {"coordinates":[10.159571,54.27599],"type":"Point"}
}