{
  "type": "Feature",
  "properties": {
    "iso:country":"DE",
    "sg:address":"Rudolf-Hanauer-Str. 12a",
    "sg:city":"Herrsching",
    "sg:phone":"+49 8152/3255",
    "sg:postcode":"82211",
    "sg:province":"Bayern",
    "wof:name":"Rudolf Bachmann Steuerberater",
    "wof:placetype":"venue"
},
  "geometry": {"coordinates":[11.1693267822,47.9970359802],"type":"Point"}
}