{
  "type": "Feature",
  "properties": {
    "iso:country":"DE",
    "sg:address":"Schwelmer Str. 70",
    "sg:city":"Remscheid",
    "sg:phone":"+49 2191/61616",
    "sg:postcode":"42897",
    "sg:province":"Nordrhein-Westfalen",
    "wof:name":"Wei\u00df Gmbh",
    "wof:placetype":"venue"
},
  "geometry": {"coordinates":[7.26959,51.200321],"type":"Point"}
}