{
  "type": "Feature",
  "properties": {
    "iso:country":"DE",
    "sg:address":"Bohnhorst 21 a",
    "sg:city":"Warmsen",
    "sg:phone":"+49 5767/942006",
    "sg:postcode":"31606",
    "sg:province":"Niedersachsen",
    "wof:name":"Gasthaus Elsbeth Hannig",
    "wof:placetype":"venue"
},
  "geometry": {"coordinates":[8.8078699112,52.4287605286],"type":"Point"}
}