{
  "type": "Feature",
  "properties": {
    "iso:country":"DE",
    "sg:address":"Blumenweg 11",
    "sg:city":"Krombach",
    "sg:phone":"+49 6029/5501",
    "sg:postcode":"63829",
    "sg:province":"Bayern",
    "wof:name":"Ihge Fuchs Eletronik Gmbh",
    "wof:placetype":"venue"
},
  "geometry": {"coordinates":[9.190208,50.084702],"type":"Point"}
}