{
  "type": "Feature",
  "properties": {
    "iso:country":"DE",
    "sg:address":"Kieler Str. 66",
    "sg:city":"Wilhelmshaven",
    "sg:phone":"+49 4421/27523",
    "sg:postcode":"26382",
    "sg:province":"Niedersachsen",
    "wof:name":"Karin Rolle Masseurin",
    "wof:placetype":"venue"
},
  "geometry": {"coordinates":[8.113685,53.526176],"type":"Point"}
}