{
  "type": "Feature",
  "properties": {
    "iso:country":"DE",
    "sg:address":"Am Wasserbau 4",
    "sg:city":"L\u00fcbeck",
    "sg:phone":"+49 451/33184",
    "sg:postcode":"23568",
    "sg:province":"Schleswig-Holstein",
    "wof:name":"Tischlerei Klaus D\u00e4hn Vormals Tischlerei",
    "wof:placetype":"venue"
},
  "geometry": {"coordinates":[10.706027,53.894295],"type":"Point"}
}