{
  "type": "Feature",
  "properties": {
    "iso:country":"DE",
    "sg:address":"Alte Landstr. 14",
    "sg:city":"Neritz",
    "sg:phone":"+49 4531/880440",
    "sg:postcode":"23843",
    "sg:province":"Schleswig-Holstein",
    "wof:name":"Ramcke Datentechnik Gmbh",
    "wof:placetype":"venue"
},
  "geometry": {"coordinates":[10.2847852707,53.7858886719],"type":"Point"}
}