{
  "type": "Feature",
  "properties": {
    "iso:country":"DE",
    "sg:address":"Am Bahnhof 17",
    "sg:city":"Wolfsburg",
    "sg:phone":"+49 5363/1081",
    "sg:postcode":"38448",
    "sg:province":"Niedersachsen",
    "wof:name":"Kiebitzmarkt Kroll",
    "wof:placetype":"venue"
},
  "geometry": {"coordinates":[10.858116,52.431435],"type":"Point"}
}