{
  "type": "Feature",
  "properties": {
    "iso:country":"DE",
    "sg:address":"Am Pohl 37",
    "sg:city":"L\u00fcbeck",
    "sg:phone":"+49 451/601415",
    "sg:postcode":"23566",
    "sg:province":"Schleswig-Holstein",
    "wof:name":"Manfred Rohde",
    "wof:placetype":"venue"
},
  "geometry": {"coordinates":[10.73221,53.863354],"type":"Point"}
}