{
  "type": "Feature",
  "properties": {
    "iso:country":"DE",
    "sg:address":"Karmannstr. 13",
    "sg:city":"Osnabr\u00fcck",
    "sg:phone":"+49 4954/1957000",
    "sg:postcode":"49084",
    "sg:province":"Niedersachsen",
    "wof:name":"Ebm Elektro Bau Montage Gmbh & Co Kg",
    "wof:placetype":"venue"
},
  "geometry": {"coordinates":[8.082314,52.263809],"type":"Point"}
}