{
  "type": "Feature",
  "properties": {
    "iso:country":"DE",
    "sg:address":"Dortmunder Str. 51",
    "sg:city":"Witten",
    "sg:phone":"+49 2302/956550",
    "sg:postcode":"58455",
    "sg:province":"Nordrhein-Westfalen",
    "wof:name":"Hausemann-schluck Inh. A. Gra\u00dfhoff",
    "wof:placetype":"venue"
},
  "geometry": {"coordinates":[7.35327,51.442551],"type":"Point"}
}