{
  "type": "Feature",
  "properties": {
    "iso:country":"DE",
    "sg:address":"Benediktstr. 12",
    "sg:city":"Solnhofen",
    "sg:phone":"+49 9145/236",
    "sg:postcode":"91807",
    "sg:province":"Bayern",
    "wof:name":"Karl Ellinger Gmbh",
    "wof:placetype":"venue"
},
  "geometry": {"coordinates":[10.9920854568,48.8936576843],"type":"Point"}
}