{
  "type": "Feature",
  "properties": {
    "iso:country":"DE",
    "sg:address":"Nymphenburger Str. 126",
    "sg:city":"M\u00fcnchen",
    "sg:phone":"+49 89/12162462",
    "sg:postcode":"80636",
    "sg:province":"Bayern",
    "wof:name":"Marcels Weinhaus E. K.",
    "wof:placetype":"venue"
},
  "geometry": {"coordinates":[11.539191246,48.1514205933],"type":"Point"}
}