{
  "type": "Feature",
  "properties": {
    "iso:country":"DE",
    "sg:address":"Quellenstr 2",
    "sg:city":"Weida",
    "sg:phone":"+49 36603/7100",
    "sg:postcode":"07570",
    "sg:province":"Th\u00fcringen",
    "wof:name":"Breckle Matratzenwerk Weida Gmbh",
    "wof:placetype":"venue"
},
  "geometry": {"coordinates":[12.065097,50.763889],"type":"Point"}
}