{
  "type": "Feature",
  "properties": {
    "iso:country":"DE",
    "sg:address":"Langenstr. 12",
    "sg:city":"Twistringen",
    "sg:phone":"+49 4243/95495",
    "sg:postcode":"27239",
    "sg:province":"Niedersachsen",
    "wof:name":"Bernhard Buschmann",
    "wof:placetype":"venue"
},
  "geometry": {"coordinates":[8.638071,52.800659],"type":"Point"}
}