{
  "type": "Feature",
  "properties": {
    "iso:country":"DE",
    "sg:address":"Potsdamer Str. 74",
    "sg:city":"Gro\u00df Kreutz",
    "sg:phone":"+49 33207/32908",
    "sg:postcode":"14550",
    "sg:province":"Brandenburg",
    "wof:name":"Horst Winter",
    "wof:placetype":"venue"
},
  "geometry": {"coordinates":[12.7816591263,52.4026222229],"type":"Point"}
}