{
  "type": "Feature",
  "properties": {
    "iso:country":"DE",
    "sg:address":"Am Markt 3",
    "sg:city":"Bargteheide",
    "sg:phone":"+49 4532/8851",
    "sg:postcode":"22941",
    "sg:province":"Schleswig-Holstein",
    "wof:name":"V. Atik",
    "wof:placetype":"venue"
},
  "geometry": {"coordinates":[10.260052681,53.7291183472],"type":"Point"}
}