{
  "type": "Feature",
  "properties": {
    "iso:country":"DE",
    "sg:address":"Hauptstr. 15",
    "sg:city":"Br\u00fchl",
    "sg:phone":"+49 2232/922555",
    "sg:postcode":"50321",
    "sg:province":"Nordrhein-Westfalen",
    "wof:name":"Stifts-apotheke",
    "wof:placetype":"venue"
},
  "geometry": {"coordinates":[6.896978,50.843822],"type":"Point"}
}