{
  "type": "Feature",
  "properties": {
    "iso:country":"DE",
    "sg:address":"Flurstr. 83",
    "sg:city":"Hamburg",
    "sg:phone":"+49 40/836318",
    "sg:postcode":"22549",
    "sg:province":"Hamburg",
    "wof:name":"Roland Remmert",
    "wof:placetype":"venue"
},
  "geometry": {"coordinates":[9.8670015335,53.5861167908],"type":"Point"}
}