{
  "type": "Feature",
  "properties": {
    "iso:country":"DE",
    "sg:address":"Londorfer Str. 65",
    "sg:city":"Gr\u00fcnberg",
    "sg:phone":"+49 6401/8070",
    "sg:postcode":"35305",
    "sg:province":"Hessen",
    "wof:name":"C-print Schaltungstechnik Bender Gmbh & Co. Kg",
    "wof:placetype":"venue"
},
  "geometry": {"coordinates":[8.9570016861,50.5932769775],"type":"Point"}
}