{
  "type": "Feature",
  "properties": {
    "iso:country":"DE",
    "sg:address":"Br\u00fcckenstr. 22",
    "sg:city":"Schl\u00fcchtern",
    "sg:phone":"+49 6661/2527",
    "sg:postcode":"36381",
    "sg:province":"Hessen",
    "wof:name":"Heinrich Heilmann",
    "wof:placetype":"venue"
},
  "geometry": {"coordinates":[9.53178,50.348061],"type":"Point"}
}