{
  "type": "Feature",
  "properties": {
    "iso:country":"DE",
    "sg:address":"Geschwister-Scholl-Str. 15",
    "sg:city":"Wittstock",
    "sg:phone":"+49 3394/441125",
    "sg:postcode":"16909",
    "sg:province":"Brandenburg",
    "wof:name":"Dosse-men\u00fc",
    "wof:placetype":"venue"
},
  "geometry": {"coordinates":[12.496090889,53.1507530212],"type":"Point"}
}