{
  "type": "Feature",
  "properties": {
    "iso:country":"DE",
    "sg:address":"Karwendelstr. 150",
    "sg:city":"Ebersberg",
    "sg:phone":"+49 8092/22012",
    "sg:postcode":"85560",
    "sg:province":"Bayern",
    "wof:name":"Johann Brand",
    "wof:placetype":"venue"
},
  "geometry": {"coordinates":[11.955693,48.071968],"type":"Point"}
}