{
  "type": "Feature",
  "properties": {
    "iso:country":"DE",
    "sg:address":"Am Stadtweg 8",
    "sg:city":"Hohendodeleben",
    "sg:phone":"+49 39204/66460",
    "sg:postcode":"39167",
    "sg:province":"Sachsen-Anhalt",
    "wof:name":"B. A. A. K. E. Dach Gmbh",
    "wof:placetype":"venue"
},
  "geometry": {"coordinates":[11.517789,52.105633],"type":"Point"}
}