{
  "type": "Feature",
  "properties": {
    "iso:country":"DE",
    "sg:address":"Ruhrufer 20",
    "sg:city":"Olsberg",
    "sg:postcode":"59939",
    "sg:province":"Nordrhein-Westfalen",
    "wof:name":"Foto Strube Inh. J\u00f6rg Strube",
    "wof:placetype":"venue"
},
  "geometry": {"coordinates":[8.4864349365,51.3533744812],"type":"Point"}
}