{
  "type": "Feature",
  "properties": {
    "iso:country":"DE",
    "sg:address":"Sch\u00fctzenstr. 2",
    "sg:city":"Linsengericht",
    "sg:phone":"+49 6051/72525",
    "sg:postcode":"63589",
    "sg:province":"Hessen",
    "wof:name":"Manfred Hoffmann Steuerberater",
    "wof:placetype":"venue"
},
  "geometry": {"coordinates":[9.2190103531,50.1728668213],"type":"Point"}
}