{
  "type": "Feature",
  "properties": {
    "iso:country":"DE",
    "sg:address":"Donaustr. 29",
    "sg:city":"Vohburg",
    "sg:phone":"+49 8457/464",
    "sg:postcode":"85088",
    "sg:province":"Bayern",
    "wof:name":"Restaurant Seefelder Hof",
    "wof:placetype":"venue"
},
  "geometry": {"coordinates":[11.6178607941,48.7716674805],"type":"Point"}
}