{
  "type": "Feature",
  "properties": {
    "iso:country":"DE",
    "sg:address":"D\u00fcrener Str. 458",
    "sg:city":"K\u00f6ln",
    "sg:phone":"+49 2234/923175",
    "sg:postcode":"50858",
    "sg:province":"Nordrhein-Westfalen",
    "wof:name":"Apotheke Dr. Schreiber Im Kaufland",
    "wof:placetype":"venue"
},
  "geometry": {"coordinates":[6.851933,50.919193],"type":"Point"}
}