{
  "type": "Feature",
  "properties": {
    "iso:country":"DE",
    "sg:address":"Pfaffenm\u00fchlweg 74",
    "sg:city":"\u00d6hringen",
    "sg:phone":"+49 7941/7035",
    "sg:postcode":"74613",
    "sg:province":"Baden-W\u00fcrttemberg",
    "wof:name":"Walter Herbold Gmbh",
    "wof:placetype":"venue"
},
  "geometry": {"coordinates":[9.5148420334,49.1985702515],"type":"Point"}
}