{
  "type": "Feature",
  "properties": {
    "iso:country":"DE",
    "sg:address":"Am Vogelsberg 3",
    "sg:city":"Ratekau",
    "sg:phone":"+49 451/393970",
    "sg:postcode":"23626",
    "sg:province":"Schleswig-Holstein",
    "wof:name":"Gattinger Immobilien Inh. Horst Gattinger",
    "wof:placetype":"venue"
},
  "geometry": {"coordinates":[10.784122467,53.9339065552],"type":"Point"}
}