{
  "type": "Feature",
  "properties": {
    "iso:country":"DE",
    "sg:address":"Sportplatzweg 1",
    "sg:city":"Altlu\u00dfheim",
    "sg:phone":"+49 6205/31877",
    "sg:postcode":"68804",
    "sg:province":"Baden-W\u00fcrttemberg",
    "wof:name":"Oase Fitness Gmbh",
    "wof:placetype":"venue"
},
  "geometry": {"coordinates":[8.4944047928,49.3073005676],"type":"Point"}
}