{
  "type": "Feature",
  "properties": {
    "iso:country":"DE",
    "sg:address":"Oberb\u00f6hringer Str. 3",
    "sg:city":"Bad \u00dcberkingen",
    "sg:phone":"+49 7334/4376",
    "sg:postcode":"73337",
    "sg:province":"Baden-W\u00fcrttemberg",
    "wof:name":"Friedrich Bollet",
    "wof:placetype":"venue"
},
  "geometry": {"coordinates":[9.7615270615,48.6277313232],"type":"Point"}
}