{
  "type": "Feature",
  "properties": {
    "iso:country":"DE",
    "sg:address":"Tiroler Str. 26",
    "sg:city":"Stuttgart",
    "sg:phone":"+49 711/322436",
    "sg:postcode":"70329",
    "sg:province":"Baden-W\u00fcrttemberg",
    "wof:name":"Fahr & Klemm Verlagsvertreter",
    "wof:placetype":"venue"
},
  "geometry": {"coordinates":[9.283526,48.774494],"type":"Point"}
}