{
  "type": "Feature",
  "properties": {
    "iso:country":"DE",
    "sg:address":"Dahmengraben 22",
    "sg:city":"Aachen",
    "sg:postcode":"52062",
    "sg:province":"Nordrhein-Westfalen",
    "wof:name":"Bingo",
    "wof:placetype":"venue"
},
  "geometry": {"coordinates":[6.0885410309,50.7763595581],"type":"Point"}
}