{
  "type": "Feature",
  "properties": {
    "iso:country":"DE",
    "sg:address":"Zwergerstr. 2 b",
    "sg:city":"Neubiberg",
    "sg:postcode":"85579",
    "sg:province":"Bayern",
    "wof:name":"Zefatech Anlagen- Und Maschinenbau Gmbh",
    "wof:placetype":"venue"
},
  "geometry": {"coordinates":[11.6467199326,48.0818786621],"type":"Point"}
}