{
  "type": "Feature",
  "properties": {
    "iso:country":"DE",
    "sg:address":"Robert-R\u00f6ssle-Str. 10",
    "sg:city":"Berlin",
    "sg:postcode":"13125",
    "sg:province":"Berlin",
    "wof:name":"Psf Biotech Ag",
    "wof:placetype":"venue"
},
  "geometry": {"coordinates":[13.5008230209,52.6273155212],"type":"Point"}
}