{
  "type": "Feature",
  "properties": {
    "iso:country":"DE",
    "sg:address":"Schl\u00fcterstr. 9",
    "sg:city":"Erkrath",
    "sg:phone":"+49 211/2099490",
    "sg:postcode":"40699",
    "sg:province":"Nordrhein-Westfalen",
    "wof:name":"Wohnungsbaugenossen- Schaft Erkrath Eg",
    "wof:placetype":"venue"
},
  "geometry": {"coordinates":[6.9080929756,51.2176132202],"type":"Point"}
}