{
  "type": "Feature",
  "properties": {
    "iso:country":"DE",
    "sg:address":"Scheffelstra\u00dfe 7",
    "sg:city":"Wald-Michelbach",
    "sg:postcode":"69483",
    "sg:province":"Hessen",
    "wof:name":"Erdgas , Bald Freier Wettbewerb , Viele Anbieter",
    "wof:placetype":"venue"
},
  "geometry": {"coordinates":[8.82235,49.57592],"type":"Point"}
}