{
  "type": "Feature",
  "properties": {
    "iso:country":"DE",
    "sg:address":"Peter-D\u00f6rfler-Str. 66",
    "sg:city":"Lindenberg",
    "sg:phone":"+49 8381/6398",
    "sg:postcode":"88161",
    "sg:province":"Bayern",
    "wof:name":"Bautenschutz Otto Gmbh",
    "wof:placetype":"venue"
},
  "geometry": {"coordinates":[9.8734226227,47.597618103],"type":"Point"}
}