{
  "type": "Feature",
  "properties": {
    "iso:country":"DE",
    "sg:address":"Hauptstr. 5a",
    "sg:city":"Taunusstein",
    "sg:phone":"+49 6128/71413",
    "sg:postcode":"65232",
    "sg:province":"Hessen",
    "wof:name":"Albert Heilhecker",
    "wof:placetype":"venue"
},
  "geometry": {"coordinates":[8.172242,50.208591],"type":"Point"}
}