{
  "type": "Feature",
  "properties": {
    "iso:country":"DE",
    "sg:address":"Gro\u00dfe Str. 28",
    "sg:city":"Wallenhorst",
    "sg:phone":"+49 5407/859100",
    "sg:postcode":"49134",
    "sg:province":"Niedersachsen",
    "wof:name":"Meldefix Ohg",
    "wof:placetype":"venue"
},
  "geometry": {"coordinates":[8.014714,52.35099],"type":"Point"}
}