{
  "type": "Feature",
  "properties": {
    "iso:country":"DE",
    "sg:address":"Mittelstr. 20",
    "sg:city":"Gro\u00df-Gerau",
    "sg:phone":"+49 6152/40717",
    "sg:postcode":"64521",
    "sg:province":"Hessen",
    "wof:name":"G. Bauso",
    "wof:placetype":"venue"
},
  "geometry": {"coordinates":[8.4885187149,49.9196472168],"type":"Point"}
}