{
  "type": "Feature",
  "properties": {
    "iso:country":"DE",
    "sg:address":"Kleines Moor 6",
    "sg:city":"Verden",
    "sg:phone":"+49 4231/64867",
    "sg:postcode":"27283",
    "sg:province":"Niedersachsen",
    "wof:name":"Hans-heinr. B\u00f6meke",
    "wof:placetype":"venue"
},
  "geometry": {"coordinates":[9.269231,52.909962],"type":"Point"}
}