{
  "type": "Feature",
  "properties": {
    "iso:country":"DE",
    "sg:address":"Goethestr. 15",
    "sg:city":"Buttst\u00e4dt",
    "sg:phone":"+49 36373/40684",
    "sg:postcode":"99628",
    "sg:province":"Th\u00fcringen",
    "wof:name":"C. Schwartz",
    "wof:placetype":"venue"
},
  "geometry": {"coordinates":[11.413117,51.12439],"type":"Point"}
}