{
  "type": "Feature",
  "properties": {
    "iso:country":"DE",
    "sg:address":"Kirchplatz 3",
    "sg:city":"Havelberg",
    "sg:postcode":"39539",
    "sg:province":"Sachsen-Anhalt",
    "wof:name":"Evangelisches Pfarramt Stadtkirche",
    "wof:placetype":"venue"
},
  "geometry": {"coordinates":[12.0749149323,52.82472229],"type":"Point"}
}