{
  "type": "Feature",
  "properties": {
    "iso:country":"DE",
    "sg:address":"Anhaltstr. 13",
    "sg:city":"Magdeburg",
    "sg:phone":"+49 391/5414614",
    "sg:postcode":"39104",
    "sg:province":"Sachsen-Anhalt",
    "wof:name":"Sanit\u00e4tshaus Szameitat Gmbh",
    "wof:placetype":"venue"
},
  "geometry": {"coordinates":[11.6300163269,52.1243972778],"type":"Point"}
}