{
  "type": "Feature",
  "properties": {
    "iso:country":"DE",
    "sg:address":"Hoechster Str. 1",
    "sg:city":"Burgkirchen",
    "sg:phone":"+49 8679/2930",
    "sg:postcode":"84508",
    "sg:province":"Bayern",
    "wof:name":"C. Menzel",
    "wof:placetype":"venue"
},
  "geometry": {"coordinates":[12.7311668396,48.1670570374],"type":"Point"}
}