{
  "type": "Feature",
  "properties": {
    "iso:country":"DE",
    "sg:address":"Ottenh\u00e4user Str. 20",
    "sg:city":"Greu\u00dfen",
    "sg:phone":"+49 3636/703616",
    "sg:postcode":"99718",
    "sg:province":"Th\u00fcringen",
    "wof:name":"Heinrich Rudewig Bauunternehmungsgmbh",
    "wof:placetype":"venue"
},
  "geometry": {"coordinates":[10.953232,51.223812],"type":"Point"}
}