{
  "type": "Feature",
  "properties": {
    "iso:country":"DE",
    "sg:address":"Leeraner Str.",
    "sg:city":"Holtland",
    "sg:phone":"+49 4941/088061",
    "sg:postcode":"26835",
    "sg:province":"Niedersachsen",
    "wof:name":"Raiffeisen-warengenossenschaft Nordheide Nenndorf E.g.",
    "wof:placetype":"venue"
},
  "geometry": {"coordinates":[9.900682,53.383602],"type":"Point"}
}