{
  "type": "Feature",
  "properties": {
    "iso:country":"DE",
    "sg:address":"Am Vietberg 1",
    "sg:city":"Detmold",
    "sg:phone":"+49 5231/18661",
    "sg:postcode":"32758",
    "sg:province":"Nordrhein-Westfalen",
    "wof:name":"Johannes Stute",
    "wof:placetype":"venue"
},
  "geometry": {"coordinates":[8.841104,51.941715],"type":"Point"}
}