{
  "type": "Feature",
  "properties": {
    "iso:country":"DE",
    "sg:address":"Josef-Welte-Str. 2",
    "sg:city":"H\u00fcfingen",
    "sg:phone":"+49 7707/797",
    "sg:postcode":"78183",
    "sg:province":"Baden-W\u00fcrttemberg",
    "wof:name":"Manfred Stiebler",
    "wof:placetype":"venue"
},
  "geometry": {"coordinates":[8.464132309,47.8702659607],"type":"Point"}
}