{
  "type": "Feature",
  "properties": {
    "iso:country":"DE",
    "sg:address":"Geyener Str. 21",
    "sg:city":"Pulheim",
    "sg:phone":"+49 2238/7721",
    "sg:postcode":"50259",
    "sg:province":"Nordrhein-Westfalen",
    "wof:name":"Bernhard M\u00f6ller Ingenieur",
    "wof:placetype":"venue"
},
  "geometry": {"coordinates":[6.7971429825,50.9974021912],"type":"Point"}
}