{
  "type": "Feature",
  "properties": {
    "iso:country":"DE",
    "sg:address":"Bahnhofstr. 75",
    "sg:city":"Herten",
    "sg:phone":"+49 209/610887",
    "sg:postcode":"45701",
    "sg:province":"Nordrhein-Westfalen",
    "wof:name":"Reise-shop R\u00f6lver-hohmann Gmbh",
    "wof:placetype":"venue"
},
  "geometry": {"coordinates":[7.0861120224,51.6041564941],"type":"Point"}
}