{
  "type": "Feature",
  "properties": {
    "iso:country":"DE",
    "sg:address":"An der Halde 12",
    "sg:city":"Alpirsbach",
    "sg:phone":"+49 7444/2644",
    "sg:postcode":"72275",
    "sg:province":"Baden-W\u00fcrttemberg",
    "wof:name":"Single Shop Design Gmbh",
    "wof:placetype":"venue"
},
  "geometry": {"coordinates":[8.458517,48.325188],"type":"Point"}
}