{
  "type": "Feature",
  "properties": {
    "iso:country":"DE",
    "sg:address":"Setzweg 1",
    "sg:city":"Eichenb\u00fchl",
    "sg:phone":"+49 9371/406242",
    "sg:postcode":"63928",
    "sg:province":"Bayern",
    "wof:name":"Glaskunst Karlheinz Muth-von Tiffany Bis Iso Glas",
    "wof:placetype":"venue"
},
  "geometry": {"coordinates":[9.3335132599,49.7024307251],"type":"Point"}
}