{
  "type": "Feature",
  "properties": {
    "iso:country":"DE",
    "sg:address":"Pottbergsweg 14",
    "sg:city":"Garbsen",
    "sg:phone":"+49 5137/875447",
    "sg:postcode":"30823",
    "sg:province":"Niedersachsen",
    "wof:name":"Elke Salchow Rechtsanw\u00e4ltin",
    "wof:placetype":"venue"
},
  "geometry": {"coordinates":[9.5870199203,52.4185295105],"type":"Point"}
}