{
  "type": "Feature",
  "properties": {
    "iso:country":"DE",
    "sg:address":"Uhlbergstr. 16",
    "sg:city":"Leinfelden-Echterdingen",
    "sg:phone":"+49 711/757695",
    "sg:postcode":"70771",
    "sg:province":"Baden-W\u00fcrttemberg",
    "wof:name":"Karlheinz Grindler",
    "wof:placetype":"venue"
},
  "geometry": {"coordinates":[9.1439199448,48.6896362305],"type":"Point"}
}