{
  "type": "Feature",
  "properties": {
    "iso:country":"DE",
    "sg:address":"Hans-B\u00f6ckler-Str. 73",
    "sg:city":"Bremerhaven",
    "sg:phone":"+49 471/62547",
    "sg:postcode":"27578",
    "sg:province":"Bremen",
    "wof:name":"Helmuth Lehmann",
    "wof:placetype":"venue"
},
  "geometry": {"coordinates":[8.623467,53.591778],"type":"Point"}
}