{
  "type": "Feature",
  "properties": {
    "iso:country":"DE",
    "sg:address":"Rasenweg 1",
    "sg:city":"Jesberg",
    "sg:phone":"+49 6695/297",
    "sg:postcode":"34632",
    "sg:province":"Hessen",
    "wof:name":"Georg Range",
    "wof:placetype":"venue"
},
  "geometry": {"coordinates":[9.092549324,50.994884491],"type":"Point"}
}