{
  "type": "Feature",
  "properties": {
    "iso:country":"DE",
    "sg:address":"Schleiermacherstr. 2",
    "sg:city":"Witten",
    "sg:phone":"+49 2302/13796",
    "sg:postcode":"58453",
    "sg:province":"Nordrhein-Westfalen",
    "wof:name":"Willi Hasenkamp",
    "wof:placetype":"venue"
},
  "geometry": {"coordinates":[7.3611807823,51.4422264099],"type":"Point"}
}