{
  "type": "Feature",
  "properties": {
    "iso:country":"DE",
    "sg:address":"Weiherstr. 49",
    "sg:city":"Hochheim",
    "sg:phone":"+49 6146/5393",
    "sg:postcode":"65239",
    "sg:province":"Hessen",
    "wof:name":"Marianne Quink",
    "wof:placetype":"venue"
},
  "geometry": {"coordinates":[8.3528928757,50.0159683228],"type":"Point"}
}