{
  "type": "Feature",
  "properties": {
    "iso:country":"DE",
    "sg:address":"Kapit\u00e4n-Romer-Str. 9 b",
    "sg:city":"Konstanz",
    "sg:phone":"+49 7533/3033",
    "sg:postcode":"78465",
    "sg:province":"Baden-W\u00fcrttemberg",
    "wof:name":"Landhotel Traube",
    "wof:placetype":"venue"
},
  "geometry": {"coordinates":[9.1167602539,47.7383117676],"type":"Point"}
}