{
  "type": "Feature",
  "properties": {
    "iso:country":"DE",
    "sg:address":"Girardetstr. 4",
    "sg:city":"Essen",
    "sg:phone":"+49 201/785810",
    "sg:postcode":"45131",
    "sg:province":"Nordrhein-Westfalen",
    "wof:name":"China-restaurant Hong Kong Inn",
    "wof:placetype":"venue"
},
  "geometry": {"coordinates":[7.0069541931,51.4312324524],"type":"Point"}
}