{
  "type": "Feature",
  "properties": {
    "iso:country":"DE",
    "sg:address":"Mittelstr. 48",
    "sg:city":"Lemgo",
    "sg:phone":"+49 5261/15122",
    "sg:postcode":"32657",
    "sg:province":"Nordrhein-Westfalen",
    "wof:name":"Schmidts Drogerie-markt",
    "wof:placetype":"venue"
},
  "geometry": {"coordinates":[8.902027,52.028473],"type":"Point"}
}