{
  "type": "Feature",
  "properties": {
    "iso:country":"DE",
    "sg:address":"S\u00fcdliche Ringstr. 195",
    "sg:city":"Langen",
    "sg:phone":"+49 6103/29248",
    "sg:postcode":"63225",
    "sg:province":"Hessen",
    "wof:name":"J. Birken Immobilienmakler",
    "wof:placetype":"venue"
},
  "geometry": {"coordinates":[8.6803131104,49.9827651978],"type":"Point"}
}