{
  "type": "Feature",
  "properties": {
    "iso:country":"DE",
    "sg:address":"Hammer Str. 140",
    "sg:city":"M\u00fcnster",
    "sg:phone":"+49 251/714853",
    "sg:postcode":"48153",
    "sg:province":"Nordrhein-Westfalen",
    "wof:name":"L. Stilling",
    "wof:placetype":"venue"
},
  "geometry": {"coordinates":[7.6231451035,51.9438934326],"type":"Point"}
}