{
  "type": "Feature",
  "properties": {
    "iso:country":"DE",
    "sg:address":"Marspfortengasse 6",
    "sg:city":"K\u00f6ln",
    "sg:phone":"+49 221/2578905",
    "sg:postcode":"50667",
    "sg:province":"Nordrhein-Westfalen",
    "wof:name":"Bahi & Co.",
    "wof:placetype":"venue"
},
  "geometry": {"coordinates":[6.9570131302,50.9379272461],"type":"Point"}
}