{
  "type": "Feature",
  "properties": {
    "iso:country":"DE",
    "sg:address":"R\u00f6ntgenstr. 10",
    "sg:city":"Ehingen",
    "sg:phone":"+49 7391/58090",
    "sg:postcode":"89584",
    "sg:province":"Baden-W\u00fcrttemberg",
    "wof:name":"Tries Grundbesitzverwaltungs- Gmbh",
    "wof:placetype":"venue"
},
  "geometry": {"coordinates":[9.7194910049,48.2923088074],"type":"Point"}
}