{
  "type": "Feature",
  "properties": {
    "iso:country":"DE",
    "sg:address":"Im Oberland 4",
    "sg:city":"Breitenbach",
    "sg:phone":"+49 6675/226",
    "sg:postcode":"36287",
    "sg:province":"Hessen",
    "wof:name":"B\u00e4tz Gmbh",
    "wof:placetype":"venue"
},
  "geometry": {"coordinates":[9.4852962494,50.8033866882],"type":"Point"}
}