{
  "type": "Feature",
  "properties": {
    "iso:country":"DE",
    "sg:address":"Frankenthaler Str. 94",
    "sg:city":"Ludwigshafen",
    "sg:phone":"+49 621/516483",
    "sg:postcode":"67059",
    "sg:province":"Rheinland-Pfalz",
    "wof:name":"M\u00fcssig Gmbh",
    "wof:placetype":"venue"
},
  "geometry": {"coordinates":[8.4277038574,49.4835853577],"type":"Point"}
}