{
  "type": "Feature",
  "properties": {
    "iso:country":"DE",
    "sg:address":"Hauptstr. 4",
    "sg:city":"Ro\u00dfhaupten",
    "sg:phone":"+49 8367/308",
    "sg:postcode":"87672",
    "sg:province":"Bayern",
    "wof:name":"Post",
    "wof:placetype":"venue"
},
  "geometry": {"coordinates":[10.718621254,47.6544799805],"type":"Point"}
}