{
  "type": "Feature",
  "properties": {
    "iso:country":"DE",
    "sg:address":"Karl-Benz-Str. 3",
    "sg:city":"Dachau",
    "sg:phone":"+49 8131/334485",
    "sg:postcode":"85221",
    "sg:province":"Bayern",
    "wof:name":"R & W Gmbh",
    "wof:placetype":"venue"
},
  "geometry": {"coordinates":[11.4744052887,48.2656288147],"type":"Point"}
}