{
  "type": "Feature",
  "properties": {
    "iso:country":"DE",
    "sg:address":"Ahrensburger Str. 151",
    "sg:city":"Hamburg",
    "sg:postcode":"22045",
    "sg:province":"Hamburg",
    "wof:name":"Windsport G. Maass Gmbh",
    "wof:placetype":"venue"
},
  "geometry": {"coordinates":[10.10974,53.581802],"type":"Point"}
}