{
  "type": "Feature",
  "properties": {
    "iso:country":"DE",
    "sg:address":"Rosenheimer Str. 2",
    "sg:city":"Wasserburg",
    "sg:phone":"+49 8071/8050",
    "sg:postcode":"83512",
    "sg:province":"Bayern",
    "wof:name":"Wasserburger Bekleidungs Kg Lampersberger Gmbh & Co.",
    "wof:placetype":"venue"
},
  "geometry": {"coordinates":[12.2316217422,48.0584754944],"type":"Point"}
}