{
  "type": "Feature",
  "properties": {
    "iso:country":"DE",
    "sg:address":"Konrad-Zuse-Str 10",
    "sg:city":"Bochum",
    "sg:phone":"+49 6172/92680",
    "sg:postcode":"44801",
    "sg:province":"Nordrhein-Westfalen",
    "wof:name":"Csf Computersoftware F\u00fcr Fachanwendungen Gmbh",
    "wof:placetype":"venue"
},
  "geometry": {"coordinates":[8.652716,50.210896],"type":"Point"}
}