{
  "type": "Feature",
  "properties": {
    "iso:country":"DE",
    "sg:address":"Ulmer Str. 150",
    "sg:city":"Augsburg",
    "sg:phone":"+49 821/401351",
    "sg:postcode":"86156",
    "sg:province":"Bayern",
    "wof:name":"West-apotheke",
    "wof:placetype":"venue"
},
  "geometry": {"coordinates":[10.859081,48.380402],"type":"Point"}
}