{
  "type": "Feature",
  "properties": {
    "iso:country":"DE",
    "sg:address":"Erikastr. 66",
    "sg:city":"Hamburg",
    "sg:phone":"+49 40/4801031",
    "sg:postcode":"20251",
    "sg:province":"Hamburg",
    "wof:name":"Freund Gmbh",
    "wof:placetype":"venue"
},
  "geometry": {"coordinates":[9.98755,53.5938],"type":"Point"}
}