{
  "type": "Feature",
  "properties": {
    "iso:country":"DE",
    "sg:address":"Teutonenweg 15",
    "sg:city":"Rheine",
    "sg:phone":"+49 5971/72403",
    "sg:postcode":"48429",
    "sg:province":"Nordrhein-Westfalen",
    "wof:name":"Klaus Czelzinski",
    "wof:placetype":"venue"
},
  "geometry": {"coordinates":[7.4813351631,52.2833938599],"type":"Point"}
}