{
  "type": "Feature",
  "properties": {
    "iso:country":"DE",
    "sg:address":"Am Hafen 1",
    "sg:city":"Edewecht",
    "sg:phone":"+49 4486/8047",
    "sg:postcode":"26188",
    "sg:province":"Niedersachsen",
    "wof:name":"Leasingb\u00fcro Ro\u00dfmann Gesch\u00e4ftsf\u00fchrungs Gmbh",
    "wof:placetype":"venue"
},
  "geometry": {"coordinates":[8.0453023911,53.0883522034],"type":"Point"}
}