{
  "type": "Feature",
  "properties": {
    "iso:country":"DE",
    "sg:address":"Oberwiesbach 3",
    "sg:city":"Neumarkt-Sankt Veit",
    "sg:phone":"+49 8639/709797",
    "sg:postcode":"84494",
    "sg:province":"Bayern",
    "wof:name":"S. R. S. Obermeier & M\u00fcller Gmbh",
    "wof:placetype":"venue"
},
  "geometry": {"coordinates":[12.4960298538,48.4112014771],"type":"Point"}
}