{
  "type": "Feature",
  "properties": {
    "iso:country":"DE",
    "sg:address":"Untenende 28",
    "sg:city":"Rhauderfehn",
    "sg:phone":"+49 4952/2812",
    "sg:postcode":"26817",
    "sg:province":"Niedersachsen",
    "wof:name":"Bei Bruno",
    "wof:placetype":"venue"
},
  "geometry": {"coordinates":[7.5875000954,53.1371498108],"type":"Point"}
}