{
  "type": "Feature",
  "properties": {
    "iso:country":"DE",
    "sg:address":"Alter Kirchenweg 1",
    "sg:city":"Norderstedt",
    "sg:phone":"+49 40/5261582",
    "sg:postcode":"22844",
    "sg:province":"Schleswig-Holstein",
    "wof:name":"U. Semrau Zoologische Handlung",
    "wof:placetype":"venue"
},
  "geometry": {"coordinates":[9.997737,53.706181],"type":"Point"}
}