{
  "type": "Feature",
  "properties": {
    "iso:country":"DE",
    "sg:address":"Industriestr. 2a",
    "sg:city":"Schenefeld",
    "sg:phone":"+49 40/8003515",
    "sg:postcode":"22869",
    "sg:province":"Schleswig-Holstein",
    "wof:name":"I. Hamann Gmbh Ballondruckerei Werbemittel",
    "wof:placetype":"venue"
},
  "geometry": {"coordinates":[9.8384923935,53.6009483337],"type":"Point"}
}