{
  "type": "Feature",
  "properties": {
    "iso:country":"DE",
    "sg:address":"G\u00f6ttinger Str. 16",
    "sg:city":"N\u00f6rten-Hardenberg",
    "sg:phone":"+49 5503/2625",
    "sg:postcode":"37176",
    "sg:province":"Niedersachsen",
    "wof:name":"W. Mosmonder",
    "wof:placetype":"venue"
},
  "geometry": {"coordinates":[9.9363250732,51.6288566589],"type":"Point"}
}