{
  "type": "Feature",
  "properties": {
    "iso:country":"DE",
    "sg:address":"Carl-Maria-von-Weber-Allee",
    "sg:city":"Gro\u00dfenhain",
    "sg:phone":"+49 3522/502662",
    "sg:postcode":"01558",
    "sg:province":"Sachsen",
    "wof:name":"Strandbad",
    "wof:placetype":"venue"
},
  "geometry": {"coordinates":[13.534485817,51.2922210693],"type":"Point"}
}