{
  "type": "Feature",
  "properties": {
    "iso:country":"DE",
    "sg:address":"Alte Gasse 10",
    "sg:city":"Reichelsheim",
    "sg:phone":"+49 6035/5361",
    "sg:postcode":"61203",
    "sg:province":"Hessen",
    "wof:name":"Philipp Jung Iii. Inh. Hedwig Winkler",
    "wof:placetype":"venue"
},
  "geometry": {"coordinates":[8.8402290344,50.3393211365],"type":"Point"}
}