{
  "type": "Feature",
  "properties": {
    "iso:country":"DE",
    "sg:address":"Nideggener Str. 82",
    "sg:city":"Nideggen",
    "sg:phone":"+49 2474/225",
    "sg:postcode":"52385",
    "sg:province":"Nordrhein-Westfalen",
    "wof:name":"E. Stollenwerk",
    "wof:placetype":"venue"
},
  "geometry": {"coordinates":[6.419944,50.665928],"type":"Point"}
}