{
  "type": "Feature",
  "properties": {
    "iso:country":"DE",
    "sg:address":"Gewerbestr. 5 1/2",
    "sg:city":"Mettenheim",
    "sg:postcode":"84562",
    "sg:province":"Bayern",
    "wof:name":"Sukmo-iw E. K.",
    "wof:placetype":"venue"
},
  "geometry": {"coordinates":[12.4646072388,48.2662391663],"type":"Point"}
}