{
  "type": "Feature",
  "properties": {
    "iso:country":"DE",
    "sg:address":"Juri-Gagarin-Ring 101",
    "sg:city":"Erfurt",
    "sg:postcode":"99084",
    "sg:province":"Th\u00fcringen",
    "wof:name":"Tanka Grundst\u00fccks- Vermietungsges. Mbh",
    "wof:placetype":"venue"
},
  "geometry": {"coordinates":[11.0361375809,50.9745559692],"type":"Point"}
}