{
  "type": "Feature",
  "properties": {
    "iso:country":"DE",
    "sg:address":"Mittelstr. 4",
    "sg:city":"Stadthagen",
    "sg:phone":"+49 5721/2371",
    "sg:postcode":"31655",
    "sg:province":"Niedersachsen",
    "wof:name":"Walter T\u00f6lke",
    "wof:placetype":"venue"
},
  "geometry": {"coordinates":[9.1853227615,52.3332901001],"type":"Point"}
}