{
  "type": "Feature",
  "properties": {
    "iso:country":"DE",
    "sg:address":"R\u00f6mersiedlung 5",
    "sg:city":"Peiss/Aying",
    "sg:postcode":"85655",
    "wof:name":"Mineralienshop24",
    "wof:placetype":"venue"
},
  "geometry": {"coordinates":[11.7776498795,47.9613990784],"type":"Point"}
}