{
  "type": "Feature",
  "properties": {
    "iso:country":"DE",
    "sg:address":"Uhlandstr. 2",
    "sg:city":"Laichingen",
    "sg:phone":"+49 7333/5427",
    "sg:postcode":"89150",
    "sg:province":"Baden-W\u00fcrttemberg",
    "wof:name":"Gerhard Laichinger",
    "wof:placetype":"venue"
},
  "geometry": {"coordinates":[9.682592392,48.4895858765],"type":"Point"}
}