{
  "type": "Feature",
  "properties": {
    "iso:country":"DE",
    "sg:address":"Sudenhofer Damm",
    "sg:city":"Hagenow",
    "sg:postcode":"19230",
    "sg:province":"Mecklenburg-Vorpommern",
    "wof:name":"Hsd Verm\u00f6gensverwaltung Gmbh & Co. Kg",
    "wof:placetype":"venue"
},
  "geometry": {"coordinates":[11.2242650986,53.4425811768],"type":"Point"}
}