{
  "type": "Feature",
  "properties": {
    "iso:country":"DE",
    "sg:address":"Mozartstr. 5",
    "sg:city":"Albstadt",
    "sg:phone":"+49 7431/2193",
    "sg:postcode":"72458",
    "sg:province":"Baden-W\u00fcrttemberg",
    "wof:name":"Dr. Werner Bitzer Steuerberater",
    "wof:placetype":"venue"
},
  "geometry": {"coordinates":[9.0208282471,48.218585968],"type":"Point"}
}