{
  "type": "Feature",
  "properties": {
    "iso:country":"DE",
    "sg:address":"Jovestr. 23",
    "sg:city":"Wernsdorf",
    "sg:phone":"+49 3362/882088",
    "sg:postcode":"15537",
    "sg:province":"Brandenburg",
    "wof:name":"Prof. Heinicke & Co. Gmbh",
    "wof:placetype":"venue"
},
  "geometry": {"coordinates":[13.6927452087,52.3650398254],"type":"Point"}
}