{
  "type": "Feature",
  "properties": {
    "iso:country":"DE",
    "sg:address":"Grenzstr. 4",
    "sg:city":"Zirndorf",
    "sg:phone":"+49 911/606527",
    "sg:postcode":"90513",
    "sg:province":"Bayern",
    "wof:name":"Walther Bauer Kunstmaler",
    "wof:placetype":"venue"
},
  "geometry": {"coordinates":[10.970006,49.452133],"type":"Point"}
}