{
  "type": "Feature",
  "properties": {
    "iso:country":"DE",
    "sg:address":"Tiergartenstr. 69",
    "sg:city":"Jade",
    "sg:phone":"+49 4454/1515",
    "sg:postcode":"26349",
    "sg:province":"Niedersachsen",
    "wof:name":"Tierpark Jadeberg Gmbh",
    "wof:placetype":"venue"
},
  "geometry": {"coordinates":[8.18537,53.32143],"type":"Point"}
}