{
  "type": "Feature",
  "properties": {
    "iso:country":"DE",
    "sg:address":"Schlachthofstr. 3",
    "sg:city":"Weimar",
    "sg:phone":"+49 3643/59444",
    "sg:postcode":"99423",
    "sg:province":"Th\u00fcringen",
    "wof:name":"Restaurant Nudelhaus",
    "wof:placetype":"venue"
},
  "geometry": {"coordinates":[11.3339548111,50.9885902405],"type":"Point"}
}