{
  "type": "Feature",
  "properties": {
    "iso:country":"DE",
    "sg:address":"Up de Bookholt 48",
    "sg:city":"Vreden",
    "sg:phone":"+49 2564/93160",
    "sg:postcode":"48691",
    "sg:province":"Nordrhein-Westfalen",
    "wof:name":"Hotel Zum Stadpark Inh. Willi U. Marion Meyering",
    "wof:placetype":"venue"
},
  "geometry": {"coordinates":[6.8156700134,52.0338630676],"type":"Point"}
}