{
  "type": "Feature",
  "properties": {
    "iso:country":"DE",
    "sg:address":"Nissanstr. 1",
    "sg:city":"Neuss",
    "sg:phone":"+49 2131/3880",
    "sg:postcode":"41468",
    "sg:province":"Nordrhein-Westfalen",
    "wof:name":"Nissan Technical Centre Europe Brussels S. A.",
    "wof:placetype":"venue"
},
  "geometry": {"coordinates":[6.75571,51.169216],"type":"Point"}
}