{
  "type": "Feature",
  "properties": {
    "iso:country":"DE",
    "sg:address":"Siemensstr. 11",
    "sg:city":"Bremerhaven",
    "sg:phone":"+49 471/38758",
    "sg:postcode":"27574",
    "sg:province":"Bremen",
    "wof:name":"Erna Bastin Hebamme",
    "wof:placetype":"venue"
},
  "geometry": {"coordinates":[8.607057,53.514858],"type":"Point"}
}