{
  "type": "Feature",
  "properties": {
    "iso:country":"DE",
    "sg:address":"Maschener Sch\u00fctzenstr. 45",
    "sg:city":"Seevetal",
    "sg:phone":"+49 4105/82207",
    "sg:postcode":"21220",
    "sg:province":"Niedersachsen",
    "wof:name":"Kurt Von Bresler Schaufenstergestaltung",
    "wof:placetype":"venue"
},
  "geometry": {"coordinates":[10.0532979965,53.3948860168],"type":"Point"}
}