{
  "type": "Feature",
  "properties": {
    "iso:country":"DE",
    "sg:address":"Maudacher Str. 24",
    "sg:city":"Mannheim",
    "sg:phone":"+49 621/8710043",
    "sg:postcode":"68219",
    "sg:province":"Baden-W\u00fcrttemberg",
    "wof:name":"F. Schmitt Immobilienmakler",
    "wof:placetype":"venue"
},
  "geometry": {"coordinates":[8.5144996643,49.44140625],"type":"Point"}
}