{
  "type": "Feature",
  "properties": {
    "iso:country":"DE",
    "sg:address":"Leienbergstr. 35",
    "sg:city":"Eitorf",
    "sg:phone":"+49 2243/2891",
    "sg:postcode":"53783",
    "sg:province":"Nordrhein-Westfalen",
    "wof:name":"Hauptmann & Windscheif Gmbh",
    "wof:placetype":"venue"
},
  "geometry": {"coordinates":[7.450117,50.767635],"type":"Point"}
}