{
  "type": "Feature",
  "properties": {
    "iso:country":"DE",
    "sg:address":"Regensteinsweg 25",
    "sg:city":"Blankenburg",
    "sg:phone":"+49 3944/61450",
    "sg:postcode":"38889",
    "sg:province":"Sachsen-Anhalt",
    "wof:name":"Blb Land- Und Baustoff- Handel Gmbh",
    "wof:placetype":"venue"
},
  "geometry": {"coordinates":[10.953984,51.801403],"type":"Point"}
}