{
  "type": "Feature",
  "properties": {
    "iso:country":"DE",
    "sg:address":"Roggenkamp 25",
    "sg:city":"Vlotho",
    "sg:phone":"+49 5228/1078",
    "sg:postcode":"32602",
    "sg:province":"Nordrhein-Westfalen",
    "wof:name":"Siegfried M\u00fchlenweg",
    "wof:placetype":"venue"
},
  "geometry": {"coordinates":[8.7891769409,52.1356811523],"type":"Point"}
}