{
  "type": "Feature",
  "properties": {
    "iso:country":"DE",
    "sg:address":"S\u00fcdstr. 14",
    "sg:city":"Rehlingen-Siersburg",
    "sg:phone":"+49 6835/91930",
    "sg:postcode":"66780",
    "sg:province":"Saarland",
    "wof:name":"Altmayer Verwaltungs Gmbh",
    "wof:placetype":"venue"
},
  "geometry": {"coordinates":[6.6924710274,49.3667869568],"type":"Point"}
}