{
  "type": "Feature",
  "properties": {
    "iso:country":"DE",
    "sg:address":"Katharinenstr. 6",
    "sg:city":"Essen",
    "sg:phone":"+49 201/410707",
    "sg:postcode":"45131",
    "sg:province":"Nordrhein-Westfalen",
    "wof:name":"Eberhard Cziesla",
    "wof:placetype":"venue"
},
  "geometry": {"coordinates":[7.0030040741,51.4261283875],"type":"Point"}
}