{
  "type": "Feature",
  "properties": {
    "iso:country":"DE",
    "sg:address":"Im Granetal 4",
    "sg:city":"Langelsheim",
    "sg:phone":"+49 5326/85358",
    "sg:postcode":"38685",
    "sg:province":"Niedersachsen",
    "wof:name":"Neb Gmbh",
    "wof:placetype":"venue"
},
  "geometry": {"coordinates":[10.3840932846,51.9189338684],"type":"Point"}
}