{
  "type": "Feature",
  "properties": {
    "iso:country":"DE",
    "sg:address":"Watmarkt 6",
    "sg:city":"Regensburg",
    "sg:phone":"+49 941/54758",
    "sg:postcode":"93047",
    "sg:province":"Bayern",
    "wof:name":"K. Teresa",
    "wof:placetype":"venue"
},
  "geometry": {"coordinates":[12.096825,49.019756],"type":"Point"}
}