{
  "type": "Feature",
  "properties": {
    "iso:country":"DE",
    "sg:address":"Hainbuchenweg 8",
    "sg:city":"Mannheim",
    "sg:phone":"+49 621/755953",
    "sg:postcode":"68305",
    "sg:province":"Baden-W\u00fcrttemberg",
    "wof:name":"G\u00fcnther Drogatz",
    "wof:placetype":"venue"
},
  "geometry": {"coordinates":[8.495681,49.534046],"type":"Point"}
}