{
  "type": "Feature",
  "properties": {
    "iso:country":"DE",
    "sg:address":"Pirnaer Str. 3",
    "sg:city":"Heidenau",
    "sg:phone":"+49 3529/512414",
    "sg:postcode":"01809",
    "sg:province":"Sachsen",
    "wof:name":"Filmpalast",
    "wof:placetype":"venue"
},
  "geometry": {"coordinates":[13.872643,50.974411],"type":"Point"}
}