{
  "type": "Feature",
  "properties": {
    "iso:country":"DE",
    "sg:address":"Limburgstr. 137",
    "sg:city":"Dettingen",
    "sg:postcode":"73265",
    "sg:province":"Baden-W\u00fcrttemberg",
    "wof:name":"M-racing Motorsport Gmbh",
    "wof:placetype":"venue"
},
  "geometry": {"coordinates":[9.4654150009,48.6152153015],"type":"Point"}
}