{
  "type": "Feature",
  "properties": {
    "iso:country":"DE",
    "sg:address":"Rosenm\u00fchlenstr. 13",
    "sg:city":"Diesbar-Seu\u00dflitz",
    "sg:phone":"+49 35265/54100",
    "sg:postcode":"01612",
    "sg:province":"Sachsen",
    "wof:name":"G. Gr\u00fcnberg",
    "wof:placetype":"venue"
},
  "geometry": {"coordinates":[13.39539,51.2981],"type":"Point"}
}