{
  "type": "Feature",
  "properties": {
    "iso:country":"DE",
    "sg:address":"Aufhauser Str.",
    "sg:city":"Geislingen",
    "sg:phone":"+49 7334/5739",
    "sg:postcode":"73312",
    "sg:province":"Baden-W\u00fcrttemberg",
    "wof:name":"E. Luksch",
    "wof:placetype":"venue"
},
  "geometry": {"coordinates":[9.7913694382,48.5839653015],"type":"Point"}
}