{
  "type": "Feature",
  "properties": {
    "iso:country":"DE",
    "sg:address":"Pfarrer-Socher-Str. 39 c",
    "sg:city":"Oberhaching",
    "sg:phone":"+49 89/6133319",
    "sg:postcode":"82041",
    "sg:province":"Bayern",
    "wof:name":"Wolfgang Mair",
    "wof:placetype":"venue"
},
  "geometry": {"coordinates":[11.5961360931,48.0294723511],"type":"Point"}
}