{
  "type": "Feature",
  "properties": {
    "iso:country":"DE",
    "sg:address":"Landgraben 78",
    "sg:city":"Alfter",
    "sg:phone":"+49 2222/4673",
    "sg:postcode":"53347",
    "sg:province":"Nordrhein-Westfalen",
    "wof:name":"Thea Schwarz",
    "wof:placetype":"venue"
},
  "geometry": {"coordinates":[7.0159702301,50.7366828918],"type":"Point"}
}