{
  "type": "Feature",
  "properties": {
    "iso:country":"DE",
    "sg:address":"Im Hundel 19",
    "sg:city":"Haltern",
    "sg:phone":"+49 2360/1643",
    "sg:postcode":"45721",
    "sg:province":"Nordrhein-Westfalen",
    "wof:name":"Ev. Pfarramt Lippramsdorf",
    "wof:placetype":"venue"
},
  "geometry": {"coordinates":[7.100438118,51.7165603638],"type":"Point"}
}