{
  "type": "Feature",
  "properties": {
    "iso:country":"DE",
    "sg:address":"Ricklinger Str. 57",
    "sg:city":"Hannover",
    "sg:phone":"+49 511/442006",
    "sg:postcode":"30449",
    "sg:province":"Niedersachsen",
    "wof:name":"Vollmer Getr\u00e4nkefach- Gro\u00dfhandel Beteiligungs Gmbh",
    "wof:placetype":"venue"
},
  "geometry": {"coordinates":[9.719865799,52.3608093262],"type":"Point"}
}