{
  "type": "Feature",
  "properties": {
    "iso:country":"DE",
    "sg:address":"Hofgerichtsweg 7",
    "sg:city":"Dortmund",
    "sg:phone":"+49 231/202882",
    "sg:postcode":"44309",
    "sg:province":"Nordrhein-Westfalen",
    "wof:name":"A. Weber",
    "wof:placetype":"venue"
},
  "geometry": {"coordinates":[7.539566,51.524628],"type":"Point"}
}