{
  "type": "Feature",
  "properties": {
    "iso:country":"DE",
    "sg:address":"Hauffweg 14",
    "sg:city":"Weinsberg",
    "sg:phone":"+49 7134/14040",
    "sg:postcode":"74189",
    "sg:province":"Baden-W\u00fcrttemberg",
    "wof:name":"V. Leisterer Gmbh",
    "wof:placetype":"venue"
},
  "geometry": {"coordinates":[9.290583,49.14259],"type":"Point"}
}