{
  "type": "Feature",
  "properties": {
    "iso:country":"DE",
    "sg:address":"Maiergasse 1",
    "sg:city":"Munningen",
    "sg:phone":"+49 9082/96660",
    "sg:postcode":"86754",
    "sg:province":"Bayern",
    "wof:name":"Taglieber Internationale Spedition Gmbh",
    "wof:placetype":"venue"
},
  "geometry": {"coordinates":[10.6240797043,48.9108734131],"type":"Point"}
}