{
  "type": "Feature",
  "properties": {
    "iso:country":"DE",
    "sg:address":"Bremer Reihe 12-14",
    "sg:city":"Hamburg",
    "sg:phone":"+49 40/248720",
    "sg:postcode":"20099",
    "sg:province":"Hamburg",
    "wof:name":"Metro Merkur",
    "wof:placetype":"venue"
},
  "geometry": {"coordinates":[10.009969,53.553631],"type":"Point"}
}