{
  "type": "Feature",
  "properties": {
    "iso:country":"DE",
    "sg:address":"Am M\u00fchlenweiher 31",
    "sg:city":"Quierschied",
    "sg:phone":"+49 6897/966400",
    "sg:postcode":"66287",
    "sg:province":"Saarland",
    "wof:name":"Christian Klein",
    "wof:placetype":"venue"
},
  "geometry": {"coordinates":[7.050257206,49.3215103149],"type":"Point"}
}