{
  "type": "Feature",
  "properties": {
    "iso:country":"DE",
    "sg:address":"Reichenbacher Str. 67",
    "sg:city":"Zwickau",
    "sg:postcode":"08056",
    "sg:province":"Sachsen",
    "wof:name":"Job Personalservice Und Dienstleistungs Gmbh",
    "wof:placetype":"venue"
},
  "geometry": {"coordinates":[12.475768,50.711945],"type":"Point"}
}