{
  "type": "Feature",
  "properties": {
    "iso:country":"DE",
    "sg:address":"Oststr. 132-136",
    "sg:city":"Duisburg",
    "sg:phone":"+49 203/378860",
    "sg:postcode":"47057",
    "sg:province":"Nordrhein-Westfalen",
    "wof:name":"Kaufhalle Ag",
    "wof:placetype":"venue"
},
  "geometry": {"coordinates":[6.786886,51.427513],"type":"Point"}
}