{
  "type": "Feature",
  "properties": {
    "iso:country":"DE",
    "sg:address":"Um de Hook 17",
    "sg:city":"Quickborn",
    "sg:postcode":"25712",
    "sg:province":"Schleswig-Holstein",
    "wof:name":"Hvh Holz Von Hand Gmbh",
    "wof:placetype":"venue"
},
  "geometry": {"coordinates":[9.20699,54.008076],"type":"Point"}
}