{
  "type": "Feature",
  "properties": {
    "iso:country":"DE",
    "sg:address":"Mallinckrodtstr. 7",
    "sg:city":"Dortmund",
    "sg:phone":"+49 231/9812060",
    "sg:postcode":"44145",
    "sg:province":"Nordrhein-Westfalen",
    "wof:name":"Bee Baastrup Edv - Entwicklung Gmbh",
    "wof:placetype":"venue"
},
  "geometry": {"coordinates":[7.4711289406,51.5258560181],"type":"Point"}
}