{
  "type": "Feature",
  "properties": {
    "iso:country":"DE",
    "sg:address":"Achter\u00fcm 15",
    "sg:city":"Flintbek",
    "sg:phone":"+49 4347/2552",
    "sg:postcode":"24220",
    "sg:province":"Schleswig-Holstein",
    "wof:name":"Whk Wurst Handel Kontor Nord Gmbh",
    "wof:placetype":"venue"
},
  "geometry": {"coordinates":[10.0704879761,54.2381362915],"type":"Point"}
}