{
  "type": "Feature",
  "properties": {
    "iso:country":"DE",
    "sg:address":"Sch\u00fctzenstr. 5",
    "sg:city":"St. Andreasberg",
    "sg:phone":"+49 5582/8477",
    "sg:postcode":"37444",
    "sg:province":"Niedersachsen",
    "wof:name":"Aeromet Meteorologische Produkte Gmbh",
    "wof:placetype":"venue"
},
  "geometry": {"coordinates":[10.524064064,51.7140541077],"type":"Point"}
}