{
  "type": "Feature",
  "properties": {
    "iso:country":"DE",
    "sg:address":"Dreim\u00fchlenstr. 21",
    "sg:city":"M\u00fcnchen",
    "sg:phone":"+49 89/7259044",
    "sg:postcode":"80469",
    "sg:province":"Bayern",
    "wof:name":"Wagendienst Winkler Gmbh",
    "wof:placetype":"venue"
},
  "geometry": {"coordinates":[11.5599594116,48.1208572388],"type":"Point"}
}