{
  "type": "Feature",
  "properties": {
    "iso:country":"DE",
    "sg:address":"Unkel-Br\u00e4sig-Strat 23",
    "sg:city":"Malchin",
    "sg:postcode":"17139",
    "sg:province":"Mecklenburg-Vorpommern",
    "wof:name":"Landwirtschaft Nord Ost Gmbh",
    "wof:placetype":"venue"
},
  "geometry": {"coordinates":[12.758263588,53.7271537781],"type":"Point"}
}