{
  "type": "Feature",
  "properties": {
    "iso:country":"DE",
    "sg:address":"Neinstedter Str 7",
    "sg:city":"Magdeburg",
    "sg:phone":"+49 391/6201985",
    "sg:postcode":"39118",
    "sg:province":"Sachsen-Anhalt",
    "wof:name":"Bdl B\u00fcro- & Datenverarbeitungsservice Lemsdorf Gmbh",
    "wof:placetype":"venue"
},
  "geometry": {"coordinates":[11.5950717926,52.098903656],"type":"Point"}
}