{
  "type": "Feature",
  "properties": {
    "iso:country":"DE",
    "sg:address":"Dorfstr. 14",
    "sg:city":"Braak",
    "sg:phone":"+49 40/67593890",
    "sg:postcode":"22145",
    "sg:province":"Hamburg",
    "wof:name":"Verwaltungsgesellschaft Rehep Handelsges. Mbh",
    "wof:placetype":"venue"
},
  "geometry": {"coordinates":[-79.0160751343,38.9223251343],"type":"Point"}
}