{
  "type": "Feature",
  "properties": {
    "iso:country":"DE",
    "sg:address":"Am Wald",
    "sg:city":"Rossau",
    "sg:phone":"+49 4937/2794220",
    "sg:postcode":"09661",
    "sg:province":"Sachsen",
    "wof:name":"Seifersbacher Land Ag",
    "wof:placetype":"venue"
},
  "geometry": {"coordinates":[13.037199,50.972042],"type":"Point"}
}