{
  "type": "Feature",
  "properties": {
    "iso:country":"DE",
    "sg:address":"Rheinstr. 20",
    "sg:city":"Darmstadt",
    "sg:postcode":"64283",
    "sg:province":"Hessen",
    "wof:name":"Roset-m\u00f6bel Gmbh Zwndl. Darmstadt",
    "wof:placetype":"venue"
},
  "geometry": {"coordinates":[8.6476516724,49.8721656799],"type":"Point"}
}