{
  "type": "Feature",
  "properties": {
    "iso:country":"DE",
    "sg:address":"Lohner Str. 14",
    "sg:city":"S\u00fcdlohn",
    "sg:phone":"+49 2862/8585",
    "sg:postcode":"46354",
    "sg:province":"Nordrhein-Westfalen",
    "wof:name":"Dr. Ernst Sch\u00fcren Tierarzt",
    "wof:placetype":"venue"
},
  "geometry": {"coordinates":[6.8722310066,51.9463157654],"type":"Point"}
}