{
  "type": "Feature",
  "properties": {
    "iso:country":"DE",
    "sg:address":"Handwerkerring 5",
    "sg:city":"Wolmirstedt",
    "sg:postcode":"39326",
    "sg:province":"Sachsen-Anhalt",
    "wof:name":"Kr\u00fcger & Losensky Gmbh",
    "wof:placetype":"venue"
},
  "geometry": {"coordinates":[11.640676,52.253876],"type":"Point"}
}