{
  "type": "Feature",
  "properties": {
    "iso:country":"DE",
    "sg:address":"Osterdeich 5",
    "sg:city":"Nordstrand",
    "sg:phone":"+49 4842/352",
    "sg:postcode":"25845",
    "sg:province":"Schleswig-Holstein",
    "wof:name":"Elisabeth Petersen Hebamme",
    "wof:placetype":"venue"
},
  "geometry": {"coordinates":[8.856887,54.48547],"type":"Point"}
}