{
  "type": "Feature",
  "properties": {
    "iso:country":"DE",
    "sg:address":"Am P\u00e4ppelter W\u00e4ldchen 1",
    "sg:city":"Merzig",
    "sg:phone":"+49 6861/4619",
    "sg:postcode":"66663",
    "sg:province":"Saarland",
    "wof:name":"Rudolf Hoffmann Bauunternehmung Gmbh",
    "wof:placetype":"venue"
},
  "geometry": {"coordinates":[6.590773,49.472572],"type":"Point"}
}