{
  "type": "Feature",
  "properties": {
    "iso:country":"DE",
    "sg:address":"Innungstr. 43",
    "sg:city":"H\u00fcrth",
    "sg:phone":"+49 2233/34115",
    "sg:postcode":"50354",
    "sg:province":"Nordrhein-Westfalen",
    "wof:name":"Karin Zibler",
    "wof:placetype":"venue"
},
  "geometry": {"coordinates":[6.841756,50.889538],"type":"Point"}
}