{
  "type": "Feature",
  "properties": {
    "iso:country":"DE",
    "sg:address":"Drontheimer Str. 34 a",
    "sg:city":"Berlin",
    "sg:phone":"+49 30/4926356",
    "sg:postcode":"13359",
    "sg:province":"Berlin",
    "wof:name":"Erwin Niemke",
    "wof:placetype":"venue"
},
  "geometry": {"coordinates":[13.3767442703,52.558380127],"type":"Point"}
}