{
  "type": "Feature",
  "properties": {
    "iso:country":"DE",
    "sg:address":"Heinrich-Heine-Str. 1",
    "sg:city":"Auerbach",
    "sg:phone":"+49 3744/211889",
    "sg:postcode":"08209",
    "sg:province":"Sachsen",
    "wof:name":"Wolfgang K\u00fcmmerling Garten- Und",
    "wof:placetype":"venue"
},
  "geometry": {"coordinates":[12.395995,50.502644],"type":"Point"}
}