{
  "type": "Feature",
  "properties": {
    "iso:country":"DE",
    "sg:address":"Altenburger Str. 12",
    "sg:city":"Windischleuba",
    "sg:phone":"+49 3447/832813",
    "sg:postcode":"04603",
    "sg:province":"Th\u00fcringen",
    "wof:name":"Detlef Berkner",
    "wof:placetype":"venue"
},
  "geometry": {"coordinates":[12.46669,51.014198],"type":"Point"}
}