{
  "type": "Feature",
  "properties": {
    "iso:country":"DE",
    "sg:address":"Knooper Weg 144",
    "sg:city":"Kiel",
    "sg:phone":"+49 431/567002",
    "sg:postcode":"24105",
    "sg:province":"Schleswig-Holstein",
    "wof:name":"Ulf Heising E. K.",
    "wof:placetype":"venue"
},
  "geometry": {"coordinates":[10.129822731,54.334564209],"type":"Point"}
}