{
  "type": "Feature",
  "properties": {
    "iso:country":"DE",
    "sg:address":"Zschortauer Str. 83",
    "sg:city":"Leipzig",
    "sg:phone":"+49 341/9120850",
    "sg:postcode":"04129",
    "sg:province":"Sachsen",
    "wof:name":"Garagengemeinschaft Eutritzsch E. V.",
    "wof:placetype":"venue"
},
  "geometry": {"coordinates":[12.3928146362,51.3806762695],"type":"Point"}
}