{
  "type": "Feature",
  "properties": {
    "iso:country":"DE",
    "sg:address":"Am Hermesberg",
    "sg:city":"Hagen",
    "sg:phone":"+49 2337/2246",
    "sg:postcode":"58091",
    "sg:province":"Nordrhein-Westfalen",
    "wof:name":"Hans D\u00f6ring",
    "wof:placetype":"venue"
},
  "geometry": {"coordinates":[7.5307559967,51.3041954041],"type":"Point"}
}