{
  "type": "Feature",
  "properties": {
    "iso:country":"DE",
    "sg:address":"Warschauer Str. 11",
    "sg:city":"M\u00fcnchen",
    "sg:phone":"+49 89/1438740",
    "sg:postcode":"80992",
    "sg:province":"Bayern",
    "wof:name":"M & T Meisinger & Tauser Gmbh",
    "wof:placetype":"venue"
},
  "geometry": {"coordinates":[11.504817009,48.174243927],"type":"Point"}
}