{
  "type": "Feature",
  "properties": {
    "iso:country":"DE",
    "sg:address":"Dillinger Str. 68",
    "sg:city":"Friedrichsdorf",
    "sg:phone":"+49 6172/74133",
    "sg:postcode":"61381",
    "sg:province":"Hessen",
    "wof:name":"Kurt M\u00fcller",
    "wof:placetype":"venue"
},
  "geometry": {"coordinates":[8.6349658966,50.2653083801],"type":"Point"}
}