{
  "type": "Feature",
  "properties": {
    "iso:country":"DE",
    "sg:address":"Tiroler Str. 4-6",
    "sg:city":"Recklinghausen",
    "sg:phone":"+49 2361/374282",
    "sg:postcode":"45659",
    "sg:province":"Nordrhein-Westfalen",
    "wof:name":"Pharmdisan Verwaltungs Gmbh",
    "wof:placetype":"venue"
},
  "geometry": {"coordinates":[7.203222,51.586098],"type":"Point"}
}