{
  "type": "Feature",
  "properties": {
    "iso:country":"DE",
    "sg:address":"Schulstr. 7",
    "sg:city":"Neufarn",
    "sg:phone":"+49 89/99020094",
    "sg:postcode":"85646",
    "sg:province":"Bayern",
    "wof:name":"W Und P Textil Druck Und Vertriebs Gmbh",
    "wof:placetype":"venue"
},
  "geometry": {"coordinates":[11.8171606064,48.14635849],"type":"Point"}
}