{
  "type": "Feature",
  "properties": {
    "iso:country":"DE",
    "sg:address":"Hauptstr. 48",
    "sg:city":"Gro\u00dfsch\u00f6nau",
    "sg:phone":"+49 35841/37050",
    "sg:postcode":"02779",
    "sg:province":"Sachsen",
    "wof:name":"Praxis Dr. Med. Buhl \u00c4rzte F\u00fcr Allgemeinmedizin",
    "wof:placetype":"venue"
},
  "geometry": {"coordinates":[14.656085968,50.8974914551],"type":"Point"}
}