{
  "type": "Feature",
  "properties": {
    "iso:country":"DE",
    "sg:address":"Turnerstr. 4",
    "sg:city":"Bielefeld",
    "sg:phone":"+49 521/96190",
    "sg:postcode":"33602",
    "sg:province":"Nordrhein-Westfalen",
    "wof:name":"Beratungsstelle Des Caritasverbandes",
    "wof:placetype":"venue"
},
  "geometry": {"coordinates":[8.536637,52.023018],"type":"Point"}
}