{
  "type": "Feature",
  "properties": {
    "iso:country":"DE",
    "sg:address":"Sch\u00e4fflestr. 4",
    "sg:city":"Frankfurt",
    "sg:phone":"+49 69/418698",
    "sg:postcode":"60386",
    "sg:province":"Hessen",
    "wof:name":"Dietmar Fr\u00f6hlich",
    "wof:placetype":"venue"
},
  "geometry": {"coordinates":[8.7328472137,50.1308479309],"type":"Point"}
}