{
  "type": "Feature",
  "properties": {
    "iso:country":"DE",
    "sg:address":"Stuntzstr. 41",
    "sg:city":"M\u00fcnchen",
    "sg:phone":"+49 89/914280",
    "sg:postcode":"81677",
    "sg:province":"Bayern",
    "wof:name":"Georg K\u00fcrzinger Steuerberater",
    "wof:placetype":"venue"
},
  "geometry": {"coordinates":[11.6202802658,48.1418380737],"type":"Point"}
}