{
  "type": "Feature",
  "properties": {
    "iso:country":"DE",
    "sg:address":"Saseler Chaussee 49",
    "sg:city":"Hamburg",
    "sg:phone":"+49 40/5365804",
    "sg:postcode":"22391",
    "sg:province":"Hamburg",
    "wof:name":"Florida",
    "wof:placetype":"venue"
},
  "geometry": {"coordinates":[10.093187,53.637341],"type":"Point"}
}