{
  "type": "Feature",
  "properties": {
    "iso:country":"DE",
    "sg:address":"Ludwigsplatz 8",
    "sg:city":"Kelheim",
    "sg:phone":"+49 9441/10320",
    "sg:postcode":"93309",
    "sg:province":"Bayern",
    "wof:name":"J. Fischer Augenoptik",
    "wof:placetype":"venue"
},
  "geometry": {"coordinates":[11.8740053177,48.9181365967],"type":"Point"}
}