{
  "type": "Feature",
  "properties": {
    "iso:country":"DE",
    "sg:address":"Ortsstr. 28",
    "sg:city":"Sch\u00f6ndorf",
    "sg:postcode":"07924",
    "sg:province":"Th\u00fcringen",
    "wof:name":"Ev.-luth. Kirche Sch\u00f6ndorf",
    "wof:placetype":"venue"
},
  "geometry": {"coordinates":[11.6941242218,50.6184654236],"type":"Point"}
}