{
  "type": "Feature",
  "properties": {
    "iso:country":"DE",
    "sg:address":"Zei\u00dfelstr. 13",
    "sg:city":"Frankfurt",
    "sg:phone":"+49 69/5976448",
    "sg:postcode":"60318",
    "sg:province":"Hessen",
    "wof:name":"Ilse S. Grilz Heilpraktikerin",
    "wof:placetype":"venue"
},
  "geometry": {"coordinates":[8.6903686523,50.1240234375],"type":"Point"}
}