{
  "type": "Feature",
  "properties": {
    "iso:country":"DE",
    "sg:address":"B\u00fchlertalstr. 16",
    "sg:city":"B\u00fchl",
    "sg:phone":"+49 7223/23497",
    "sg:postcode":"77815",
    "sg:province":"Baden-W\u00fcrttemberg",
    "wof:name":"Deutscher Kaiser",
    "wof:placetype":"venue"
},
  "geometry": {"coordinates":[8.1371297836,48.6939659119],"type":"Point"}
}