{
  "type": "Feature",
  "properties": {
    "iso:country":"DE",
    "sg:address":"Schlierberger Str. 1",
    "sg:city":"Ehingen",
    "sg:phone":"+49 9835/251",
    "sg:postcode":"91725",
    "sg:province":"Bayern",
    "wof:name":"Gerda Voigt",
    "wof:placetype":"venue"
},
  "geometry": {"coordinates":[10.503099,49.112595],"type":"Point"}
}