{
  "type": "Feature",
  "properties": {
    "iso:country":"DE",
    "sg:address":"Bahnhofplatz 23",
    "sg:city":"Rudersberg",
    "sg:phone":"+49 7183/37585",
    "sg:postcode":"73635",
    "sg:province":"Baden-W\u00fcrttemberg",
    "wof:name":"P. U. R. Ehmann",
    "wof:placetype":"venue"
},
  "geometry": {"coordinates":[9.526795,48.872581],"type":"Point"}
}