{
  "type": "Feature",
  "properties": {
    "iso:country":"DE",
    "sg:address":"Heinkelstr. 8b",
    "sg:city":"Muggensturm",
    "sg:phone":"+49 7222/51091",
    "sg:postcode":"76461",
    "sg:province":"Baden-W\u00fcrttemberg",
    "wof:name":"Ape Elektronik Gmbh",
    "wof:placetype":"venue"
},
  "geometry": {"coordinates":[8.275244,48.878429],"type":"Point"}
}