{
  "type": "Feature",
  "properties": {
    "iso:country":"DE",
    "sg:address":"Borner Str. 48",
    "sg:city":"Br\u00fcggen",
    "sg:postcode":"41379",
    "sg:province":"Nordrhein-Westfalen",
    "wof:name":"Perkeo Kunstatelier Gmbh",
    "wof:placetype":"venue"
},
  "geometry": {"coordinates":[6.188852787,51.243560791],"type":"Point"}
}