{
  "type": "Feature",
  "properties": {
    "iso:country":"DE",
    "sg:address":"Schillerstr. 24",
    "sg:city":"Bremerhaven",
    "sg:phone":"+49 471/22142",
    "sg:postcode":"27570",
    "sg:province":"Bremen",
    "wof:name":"K. Schl\u00fcsing",
    "wof:placetype":"venue"
},
  "geometry": {"coordinates":[8.593442,53.533443],"type":"Point"}
}