{
  "type": "Feature",
  "properties": {
    "iso:country":"DE",
    "sg:address":"Hau\u00dfmannstr. 2",
    "sg:city":"Stuttgart",
    "sg:phone":"+49 711/235973",
    "sg:postcode":"70188",
    "sg:province":"Baden-W\u00fcrttemberg",
    "wof:name":"G. R. Oberer Rechtsanwalt",
    "wof:placetype":"venue"
},
  "geometry": {"coordinates":[9.1909379959,48.7785263062],"type":"Point"}
}