{
  "type": "Feature",
  "properties": {
    "iso:country":"DE",
    "sg:address":"Lange Str. 16",
    "sg:city":"Detmold",
    "sg:phone":"+49 4952/3122048",
    "sg:postcode":"32756",
    "sg:province":"Nordrhein-Westfalen",
    "wof:name":"Wmf W\u00dcrttembergischemetallwarenfabrik Ag",
    "wof:placetype":"venue"
},
  "geometry": {"coordinates":[8.878177,51.93375],"type":"Point"}
}