{
  "type": "Feature",
  "properties": {
    "iso:country":"DE",
    "sg:address":"Am Wettbach 2",
    "sg:city":"Balingen",
    "sg:phone":"+49 7433/36316",
    "sg:postcode":"72336",
    "sg:province":"Baden-W\u00fcrttemberg",
    "wof:name":"Br\u00fccke",
    "wof:placetype":"venue"
},
  "geometry": {"coordinates":[8.8393697739,48.2558288574],"type":"Point"}
}