{
  "type": "Feature",
  "properties": {
    "iso:country":"DE",
    "sg:address":"Marienstr. 30",
    "sg:city":"Zwickau",
    "sg:phone":"+49 375/215053",
    "sg:postcode":"08056",
    "sg:province":"Sachsen",
    "wof:name":"Dkv Deutsche Krankenversicherung Ag",
    "wof:placetype":"venue"
},
  "geometry": {"coordinates":[12.4955806732,50.7185058594],"type":"Point"}
}