{
  "type": "Feature",
  "properties": {
    "iso:country":"DE",
    "sg:address":"Martin-Luther-Str. 113",
    "sg:city":"Berlin",
    "sg:phone":"+49 30/78704291",
    "sg:postcode":"10825",
    "sg:province":"Berlin",
    "wof:name":"Ringservice - Deutscher Ring Generalagentur Urbigkeit",
    "wof:placetype":"venue"
},
  "geometry": {"coordinates":[13.3453960419,52.481754303],"type":"Point"}
}