{
  "type": "Feature",
  "properties": {
    "iso:country":"DE",
    "sg:address":"Richard-Kuckuck-Str. 26",
    "sg:city":"Bergholz-Rehbr\u00fccke",
    "sg:phone":"+49 33200/86020",
    "sg:postcode":"14558",
    "sg:province":"Brandenburg",
    "wof:name":"Video-bistro",
    "wof:placetype":"venue"
},
  "geometry": {"coordinates":[13.1098499298,52.3488006592],"type":"Point"}
}