{
  "type": "Feature",
  "properties": {
    "iso:country":"DE",
    "sg:address":"Sankt-Markus-Platz 2",
    "sg:city":"Recklinghausen",
    "sg:postcode":"45657",
    "sg:province":"Nordrhein-Westfalen",
    "wof:name":"Kath. \u00f6ffentliche Bibliothek St. Markus",
    "wof:placetype":"venue"
},
  "geometry": {"coordinates":[7.180614,51.616058],"type":"Point"}
}