{
  "type": "Feature",
  "properties": {
    "iso:country":"DE",
    "sg:address":"Fuhlsb\u00fcttler Str. 121",
    "sg:city":"Hamburg",
    "sg:phone":"+49 40/6913233",
    "sg:postcode":"22305",
    "sg:province":"Hamburg",
    "wof:name":"Neue Barmbeker Apotheke",
    "wof:placetype":"venue"
},
  "geometry": {"coordinates":[10.044773,53.590034],"type":"Point"}
}