{
  "type": "Feature",
  "properties": {
    "iso:country":"DE",
    "sg:address":"Roonstr. 52",
    "sg:city":"Duisburg",
    "sg:phone":"+49 203/405423",
    "sg:postcode":"47169",
    "sg:province":"Nordrhein-Westfalen",
    "wof:name":"Gerhard Zander",
    "wof:placetype":"venue"
},
  "geometry": {"coordinates":[6.7614560127,51.503200531],"type":"Point"}
}