{
  "type": "Feature",
  "properties": {
    "iso:country":"DE",
    "sg:address":"Im M\u00fchlenfeld 5",
    "sg:city":"Elze",
    "sg:phone":"+49 5068/9250",
    "sg:postcode":"31008",
    "sg:province":"Niedersachsen",
    "wof:name":"Iso-elektra Elektrochemische Fabrik Gmbh",
    "wof:placetype":"venue"
},
  "geometry": {"coordinates":[9.728331,52.114174],"type":"Point"}
}