{
  "type": "Feature",
  "properties": {
    "iso:country":"DE",
    "sg:address":"Karlsfelder Str. 11 D",
    "sg:city":"M\u00fcnchen",
    "sg:phone":"+49 89/3135281",
    "sg:postcode":"80995",
    "sg:province":"Bayern",
    "wof:name":"B. Hintermaier",
    "wof:placetype":"venue"
},
  "geometry": {"coordinates":[11.5257701874,48.2179832458],"type":"Point"}
}