{
  "type": "Feature",
  "properties": {
    "iso:country":"DE",
    "sg:address":"Nussh\u00fctterweg 1",
    "sg:city":"Falkenstein",
    "sg:phone":"+49 6302/1439",
    "sg:postcode":"67808",
    "sg:province":"Rheinland-Pfalz",
    "wof:name":"V. Blaum Bildhauer",
    "wof:placetype":"venue"
},
  "geometry": {"coordinates":[7.875318,49.612953],"type":"Point"}
}