{
  "type": "Feature",
  "properties": {
    "iso:country":"DE",
    "sg:address":"Freiligrathstr. 15",
    "sg:city":"Darmstadt",
    "sg:phone":"+49 6151/96820",
    "sg:postcode":"64285",
    "sg:province":"Hessen",
    "wof:name":"Horst Schreiber Rechtsanwalt",
    "wof:placetype":"venue"
},
  "geometry": {"coordinates":[8.6497001648,49.8520355225],"type":"Point"}
}