{
  "type": "Feature",
  "properties": {
    "iso:country":"DE",
    "sg:address":"Marienbergstr. 37",
    "sg:city":"Nordstemmen",
    "sg:phone":"+49 5069/2631",
    "sg:postcode":"31171",
    "sg:province":"Niedersachsen",
    "wof:name":"Ottokar Gosciejewicz",
    "wof:placetype":"venue"
},
  "geometry": {"coordinates":[9.780166626,52.1661338806],"type":"Point"}
}