{
  "type": "Feature",
  "properties": {
    "iso:country":"DE",
    "sg:address":"Potsdamer Str. 94",
    "sg:city":"Potsdam",
    "sg:phone":"+49 331/504050",
    "sg:postcode":"14469",
    "sg:province":"Brandenburg",
    "wof:name":"Klaus Broschke",
    "wof:placetype":"venue"
},
  "geometry": {"coordinates":[13.0012969971,52.4230308533],"type":"Point"}
}