{
  "type": "Feature",
  "properties": {
    "iso:country":"DE",
    "sg:address":"Boedikerweg 1",
    "sg:city":"Bad Breisig",
    "sg:phone":"+49 2633/95330",
    "sg:postcode":"53498",
    "sg:province":"Rheinland-Pfalz",
    "wof:name":"Mayflower",
    "wof:placetype":"venue"
},
  "geometry": {"coordinates":[7.3048348427,50.5048866272],"type":"Point"}
}