{
  "type": "Feature",
  "properties": {
    "iso:country":"DE",
    "sg:address":"Obere Str. 2",
    "sg:city":"Meerbusch",
    "sg:phone":"+49 2150/2315",
    "sg:postcode":"40668",
    "sg:province":"Nordrhein-Westfalen",
    "wof:name":"Wantikow",
    "wof:placetype":"venue"
},
  "geometry": {"coordinates":[6.682046,51.302895],"type":"Point"}
}