{
  "type": "Feature",
  "properties": {
    "iso:country":"DE",
    "sg:address":"Herzogstrasse 15::",
    "sg:city":"D\u00fcsseldorf",
    "sg:postcode":"40217",
    "sg:province":"Nordrhein-Westfalen",
    "wof:name":"Rw Finanzberatungs-und Beteiligungs Gmbh",
    "wof:placetype":"venue"
},
  "geometry": {"coordinates":[6.77676,51.21563],"type":"Point"}
}