{
  "type": "Feature",
  "properties": {
    "iso:country":"DE",
    "sg:address":"Otto-Hahn-Str. 10",
    "sg:city":"Gernsheim",
    "sg:phone":"+49 6258/4055",
    "sg:postcode":"64579",
    "sg:province":"Hessen",
    "wof:name":"Matthias Appelt",
    "wof:placetype":"venue"
},
  "geometry": {"coordinates":[8.490234375,49.7638092041],"type":"Point"}
}