{
  "type": "Feature",
  "properties": {
    "iso:country":"DE",
    "sg:address":"Segeberger Landstr. 91",
    "sg:city":"Kiel",
    "sg:phone":"+49 431/711935",
    "sg:postcode":"24145",
    "sg:province":"Schleswig-Holstein",
    "wof:name":"Uwe Schweim Architekt",
    "wof:placetype":"venue"
},
  "geometry": {"coordinates":[10.164521,54.29068],"type":"Point"}
}