{
  "type": "Feature",
  "properties": {
    "iso:country":"DE",
    "sg:address":"Friedrichstr. 5",
    "sg:city":"Erkrath",
    "sg:phone":"+49 211/242856",
    "sg:postcode":"40699",
    "sg:province":"Nordrhein-Westfalen",
    "wof:name":"Werner Fellenz Steuerberater Und Wirtschafts-",
    "wof:placetype":"venue"
},
  "geometry": {"coordinates":[6.9065079689,51.2252998352],"type":"Point"}
}