{
  "type": "Feature",
  "properties": {
    "iso:country":"DE",
    "sg:address":"R\u00fcdesheimer Str. 1",
    "sg:city":"Geisenheim",
    "sg:postcode":"65366",
    "sg:province":"Hessen",
    "wof:name":"Vinko Dujimovic Masseur",
    "wof:placetype":"venue"
},
  "geometry": {"coordinates":[7.946312,49.981579],"type":"Point"}
}