{
  "type": "Feature",
  "properties": {
    "iso:country":"DE",
    "sg:address":"Warrington-Platz 10",
    "sg:city":"Hilden",
    "sg:phone":"+49 2103/581095",
    "sg:postcode":"40721",
    "sg:province":"Nordrhein-Westfalen",
    "wof:name":"Dippels Bistro",
    "wof:placetype":"venue"
},
  "geometry": {"coordinates":[6.9345860481,51.1676979065],"type":"Point"}
}