{
  "type": "Feature",
  "properties": {
    "iso:country":"DE",
    "sg:address":"Am Hang 8",
    "sg:city":"Scharbeutz",
    "sg:phone":"+49 4503/8820",
    "sg:postcode":"23683",
    "sg:province":"Schleswig-Holstein",
    "wof:name":"Hotel G\u00f6ttsche",
    "wof:placetype":"venue"
},
  "geometry": {"coordinates":[10.7596607208,54.0227355957],"type":"Point"}
}