{
  "type": "Feature",
  "properties": {
    "iso:country":"DE",
    "sg:address":"Talstr. 15",
    "sg:city":"Herbrechtingen",
    "sg:phone":"+49 7324/7476",
    "sg:postcode":"89542",
    "sg:province":"Baden-W\u00fcrttemberg",
    "wof:name":"Talschenke",
    "wof:placetype":"venue"
},
  "geometry": {"coordinates":[10.1782169342,48.6012229919],"type":"Point"}
}