{
  "type": "Feature",
  "properties": {
    "iso:country":"DE",
    "sg:address":"G\u00fcnderodestr. 2c",
    "sg:city":"M\u00fcnchen",
    "sg:postcode":"81827",
    "sg:province":"Bayern",
    "wof:name":"Rsoft Gmbh",
    "wof:placetype":"venue"
},
  "geometry": {"coordinates":[11.6664123535,48.1030349731],"type":"Point"}
}