{
  "type": "Feature",
  "properties": {
    "iso:country":"DE",
    "sg:address":"Wiegenfeldring 9-11",
    "sg:city":"Markt Schwaben",
    "sg:postcode":"85570",
    "sg:province":"Bayern",
    "wof:name":"Domino",
    "wof:placetype":"venue"
},
  "geometry": {"coordinates":[11.8511943817,48.1893882751],"type":"Point"}
}