{
  "type": "Feature",
  "properties": {
    "iso:country":"DE",
    "sg:address":"M\u00fchlenbacher Str. 13",
    "sg:city":"Haslach",
    "sg:phone":"+49 7832/5107",
    "sg:postcode":"77716",
    "sg:province":"Baden-W\u00fcrttemberg",
    "wof:name":"H. Herrmann",
    "wof:placetype":"venue"
},
  "geometry": {"coordinates":[8.1109752655,48.287071228],"type":"Point"}
}