{
  "type": "Feature",
  "properties": {
    "iso:country":"DE",
    "sg:address":"Treppenstein 2",
    "sg:city":"M\u00e4hring",
    "sg:phone":"+49 9639/325",
    "sg:postcode":"95695",
    "sg:province":"Bayern",
    "wof:name":"Josef Vogl",
    "wof:placetype":"venue"
},
  "geometry": {"coordinates":[12.5386362076,49.8926277161],"type":"Point"}
}