{
  "type": "Feature",
  "properties": {
    "iso:country":"DE",
    "sg:address":"Goethestr. 11-13",
    "sg:city":"Prien",
    "sg:phone":"+49 8051/4443",
    "sg:postcode":"83209",
    "sg:province":"Bayern",
    "wof:name":"Effenberger Kunststoff- Verarbeitung Gmbh",
    "wof:placetype":"venue"
},
  "geometry": {"coordinates":[12.3534936905,47.8602752686],"type":"Point"}
}