{
  "type": "Feature",
  "properties": {
    "iso:country":"DE",
    "sg:address":"Ingolst\u00e4dter Str. 46",
    "sg:city":"Schrobenhausen",
    "sg:phone":"+49 8252/7214",
    "sg:postcode":"86529",
    "sg:province":"Bayern",
    "wof:name":"E. Wiedmann Steinmetz",
    "wof:placetype":"venue"
},
  "geometry": {"coordinates":[11.2646903992,48.5617637634],"type":"Point"}
}