{
  "type": "Feature",
  "properties": {
    "iso:country":"DE",
    "sg:address":"Schmechtingstr. 9",
    "sg:city":"Bochum",
    "sg:phone":"+49 234/513379",
    "sg:postcode":"44809",
    "sg:province":"Nordrhein-Westfalen",
    "wof:name":"Willi Vos",
    "wof:placetype":"venue"
},
  "geometry": {"coordinates":[7.2119288445,51.4937171936],"type":"Point"}
}