{
  "type": "Feature",
  "properties": {
    "iso:country":"DE",
    "sg:address":"Kiebitzreihe 67",
    "sg:city":"Norderstedt",
    "sg:phone":"+49 40/5218677",
    "sg:postcode":"22844",
    "sg:province":"Schleswig-Holstein",
    "wof:name":"Frank Kratschke Gmbh",
    "wof:placetype":"venue"
},
  "geometry": {"coordinates":[9.998565,53.706589],"type":"Point"}
}