{
  "type": "Feature",
  "properties": {
    "iso:country":"DE",
    "sg:address":"Krefelder Str 432",
    "sg:city":"M\u00f6nchengladbach",
    "sg:phone":"+49 2161/60786",
    "sg:postcode":"41066",
    "sg:province":"Nordrhein-Westfalen",
    "wof:name":"Mobilus Antriebselemente Gmbh",
    "wof:placetype":"venue"
},
  "geometry": {"coordinates":[6.475558,51.217049],"type":"Point"}
}