{
  "type": "Feature",
  "properties": {
    "iso:country":"DE",
    "sg:address":"Am Fleth 44",
    "sg:city":"Gl\u00fcckstadt",
    "sg:phone":"+49 4124/4848",
    "sg:postcode":"25348",
    "sg:province":"Schleswig-Holstein",
    "wof:name":"Apotheke Am Fleth",
    "wof:placetype":"venue"
},
  "geometry": {"coordinates":[9.422068,53.788914],"type":"Point"}
}