{
  "type": "Feature",
  "properties": {
    "iso:country":"DE",
    "sg:address":"Am Ersten Rasen 2",
    "sg:city":"Bleicherode",
    "sg:phone":"+49 36338/42295",
    "sg:postcode":"99752",
    "sg:province":"Th\u00fcringen",
    "wof:name":"B. M\u00fcller",
    "wof:placetype":"venue"
},
  "geometry": {"coordinates":[10.5638027191,51.4416465759],"type":"Point"}
}