{
  "type": "Feature",
  "properties": {
    "iso:country":"DE",
    "sg:address":"Weserstr. 28",
    "sg:city":"Berne",
    "sg:phone":"+49 4406/928994",
    "sg:postcode":"27804",
    "sg:province":"Niedersachsen",
    "wof:name":"Argonautic Gmbh",
    "wof:placetype":"venue"
},
  "geometry": {"coordinates":[8.484333992,53.1866836548],"type":"Point"}
}