{
  "type": "Feature",
  "properties": {
    "iso:country":"DE",
    "sg:address":"Schlo\u00dfpassage 29",
    "sg:city":"Braunschweig",
    "sg:phone":"+49 531/44144",
    "sg:postcode":"38100",
    "sg:province":"Niedersachsen",
    "wof:name":"Dieter Argenton Buchhandlung",
    "wof:placetype":"venue"
},
  "geometry": {"coordinates":[10.5247535706,52.2629241943],"type":"Point"}
}