{
  "type": "Feature",
  "properties": {
    "iso:country":"DE",
    "sg:address":"Wilhelm-Blos-Stra\u00dfe 13",
    "sg:city":"Ludwigsburg",
    "sg:phone":"+49 7141",
    "sg:postcode":"71636",
    "sg:province":"Baden-W\u00fcrttemberg",
    "wof:name":"Spuk",
    "wof:placetype":"venue"
},
  "geometry": {"coordinates":[9.1728019714,48.8957138062],"type":"Point"}
}