{
  "type": "Feature",
  "properties": {
    "iso:country":"DE",
    "sg:address":"Nahering 14",
    "sg:city":"Ingelheim",
    "sg:phone":"+49 6132/87908",
    "sg:postcode":"55218",
    "sg:province":"Rheinland-Pfalz",
    "wof:name":"Blumen-risse Gmbh & Co. Kg",
    "wof:placetype":"venue"
},
  "geometry": {"coordinates":[8.027617,49.982105],"type":"Point"}
}