{
  "type": "Feature",
  "properties": {
    "iso:country":"DE",
    "sg:address":"Lignitzerstr. 1",
    "sg:city":"W\u00fcllfrath",
    "sg:phone":"+49 202/2921656",
    "sg:postcode":"42489",
    "sg:province":"Nordrhein-Westfalen",
    "wof:name":"Quante Baulaser Gmbh",
    "wof:placetype":"venue"
},
  "geometry": {"coordinates":[7.0514450073,51.2853622437],"type":"Point"}
}