{
  "type": "Feature",
  "properties": {
    "iso:country":"DE",
    "sg:address":"Hiddestorfer Str.",
    "sg:city":"Pattensen",
    "sg:phone":"+49 5101/3454",
    "sg:postcode":"30982",
    "sg:province":"Niedersachsen",
    "wof:name":"Freibad Arnum",
    "wof:placetype":"venue"
},
  "geometry": {"coordinates":[9.7503757477,52.266834259],"type":"Point"}
}