{
  "type": "Feature",
  "properties": {
    "iso:country":"DE",
    "sg:address":"Lyzeumstr. 3",
    "sg:city":"Rastatt",
    "sg:phone":"+49 7222/33725",
    "sg:postcode":"76437",
    "sg:province":"Baden-W\u00fcrttemberg",
    "wof:name":"Alt Rastatt",
    "wof:placetype":"venue"
},
  "geometry": {"coordinates":[8.2003221512,48.8582725525],"type":"Point"}
}