{
  "type": "Feature",
  "properties": {
    "iso:country":"DE",
    "sg:address":"Fontanestr. 86",
    "sg:city":"Monheim",
    "sg:phone":"+49 2173/62574",
    "sg:postcode":"40789",
    "sg:province":"Nordrhein-Westfalen",
    "wof:name":"Heinz Heckers Architekt",
    "wof:placetype":"venue"
},
  "geometry": {"coordinates":[6.89039,51.122711],"type":"Point"}
}