{
  "type": "Feature",
  "properties": {
    "iso:country":"DE",
    "sg:address":"Barkenstr. 68",
    "sg:city":"Greven",
    "sg:phone":"+49 2571/2330",
    "sg:postcode":"48268",
    "sg:province":"Nordrhein-Westfalen",
    "wof:name":"Josef Verlage",
    "wof:placetype":"venue"
},
  "geometry": {"coordinates":[7.622441,52.096893],"type":"Point"}
}