{
  "type": "Feature",
  "properties": {
    "iso:country":"DE",
    "sg:address":"Ilsenburger Str. 70",
    "sg:city":"Wernigerode",
    "sg:postcode":"38855",
    "sg:province":"Sachsen-Anhalt",
    "wof:name":"Ahlsleben Tankstellen Gmbh",
    "wof:placetype":"venue"
},
  "geometry": {"coordinates":[10.76679039,51.8386154175],"type":"Point"}
}