{
  "type": "Feature",
  "properties": {
    "iso:country":"DE",
    "sg:address":"Lotzbeckstr. 19",
    "sg:city":"Lahr",
    "sg:phone":"+49 7821/37685",
    "sg:postcode":"77933",
    "sg:province":"Baden-W\u00fcrttemberg",
    "wof:name":"Repro-line Gmbh",
    "wof:placetype":"venue"
},
  "geometry": {"coordinates":[7.8685789108,48.3388557434],"type":"Point"}
}