{
  "type": "Feature",
  "properties": {
    "iso:country":"DE",
    "sg:address":"Forster Str. 1",
    "sg:city":"G\u00e4dheim",
    "sg:phone":"+49 9727/401",
    "sg:postcode":"97503",
    "sg:province":"Bayern",
    "wof:name":"G\u00fcnther Jost",
    "wof:placetype":"venue"
},
  "geometry": {"coordinates":[10.3425302505,50.0232810974],"type":"Point"}
}