{
  "type": "Feature",
  "properties": {
    "iso:country":"DE",
    "sg:address":"Stoltzestra\u00dfe 5-7",
    "sg:city":"Neu Isenburg",
    "sg:phone":"+49 6102/209610",
    "sg:postcode":"63263",
    "sg:province":"Hessen",
    "wof:name":"Willkommen Bei 3inone - Multimedia, Webdesign, App",
    "wof:placetype":"venue"
},
  "geometry": {"coordinates":[8.69107,50.056309],"type":"Point"}
}