{
  "type": "Feature",
  "properties": {
    "iso:country":"DE",
    "sg:address":"Bayerwaldring 8",
    "sg:city":"Dingolfing",
    "sg:phone":"+49 8731/370270",
    "sg:postcode":"84130",
    "sg:province":"Bayern",
    "wof:name":"Toni Wiesbeck Heilpraktiker",
    "wof:placetype":"venue"
},
  "geometry": {"coordinates":[12.5070648193,48.6379928589],"type":"Point"}
}