{
  "type": "Feature",
  "properties": {
    "iso:country":"DE",
    "sg:address":"Feldstr. 9",
    "sg:city":"Helbra",
    "sg:postcode":"06311",
    "sg:province":"Sachsen-Anhalt",
    "wof:name":"Hks Bauger\u00e4tevermietung Gmbh & Co. Kg",
    "wof:placetype":"venue"
},
  "geometry": {"coordinates":[11.4943799973,51.5605926514],"type":"Point"}
}