{
  "type": "Feature",
  "properties": {
    "iso:country":"DE",
    "sg:address":"Am Schmiedeh\u00f6fchen 12",
    "sg:city":"Taucha",
    "sg:phone":"+49 34298/38569",
    "sg:postcode":"04425",
    "sg:province":"Sachsen",
    "wof:name":"A. Brommer",
    "wof:placetype":"venue"
},
  "geometry": {"coordinates":[12.505048,51.377518],"type":"Point"}
}