{
  "type": "Feature",
  "properties": {
    "iso:country":"DE",
    "sg:address":"Im Grundsee 20",
    "sg:city":"R\u00fcsselsheim",
    "sg:phone":"+49 6142/72150",
    "sg:postcode":"65428",
    "sg:province":"Hessen",
    "wof:name":"Eginhard Diehl",
    "wof:placetype":"venue"
},
  "geometry": {"coordinates":[8.3847780228,49.961517334],"type":"Point"}
}