{
  "type": "Feature",
  "properties": {
    "iso:country":"DE",
    "sg:address":"Wallstadter Str. 8",
    "sg:city":"Ilvesheim",
    "sg:phone":"+49 621/494172",
    "sg:postcode":"68549",
    "sg:province":"Baden-W\u00fcrttemberg",
    "wof:name":"Johannes Biedermann",
    "wof:placetype":"venue"
},
  "geometry": {"coordinates":[8.5529050827,49.484375],"type":"Point"}
}