{
  "type": "Feature",
  "properties": {
    "iso:country":"DE",
    "sg:address":"Raiffeisenstr. 3",
    "sg:city":"R\u00fcthen",
    "sg:phone":"+49 2952/1506",
    "sg:postcode":"59602",
    "sg:province":"Nordrhein-Westfalen",
    "wof:name":"Katholisches Pfarramt St. Ursula",
    "wof:placetype":"venue"
},
  "geometry": {"coordinates":[8.4891529083,51.5120697021],"type":"Point"}
}