{
  "type": "Feature",
  "properties": {
    "iso:country":"DE",
    "sg:address":"Am Harthwald 6",
    "sg:city":"Chemnitz",
    "sg:phone":"+49 371/242131",
    "sg:postcode":"09123",
    "sg:province":"Sachsen",
    "wof:name":"S. Wachwitz",
    "wof:placetype":"venue"
},
  "geometry": {"coordinates":[12.9045991898,50.7875022888],"type":"Point"}
}