{
  "type": "Feature",
  "properties": {
    "iso:country":"DE",
    "sg:address":"Rungestr. 19",
    "sg:city":"Berlin",
    "sg:phone":"+49 30/27896860",
    "sg:postcode":"10179",
    "sg:province":"Berlin",
    "wof:name":"Interactive Technologies Gmbh",
    "wof:placetype":"venue"
},
  "geometry": {"coordinates":[13.4200086594,52.5123710632],"type":"Point"}
}