{
  "type": "Feature",
  "properties": {
    "iso:country":"DE",
    "sg:address":"Bismarckstr. 206",
    "sg:city":"Leverkusen",
    "sg:postcode":"51373",
    "sg:province":"Nordrhein-Westfalen",
    "wof:name":"D. Odenthal",
    "wof:placetype":"venue"
},
  "geometry": {"coordinates":[7.0056300163,51.0350494385],"type":"Point"}
}