{
  "type": "Feature",
  "properties": {
    "iso:country":"DE",
    "sg:address":"Ernst-Moritz-Arndt-Str. 20",
    "sg:city":"Bonn",
    "sg:phone":"+49 228/476974",
    "sg:postcode":"53225",
    "sg:province":"Nordrhein-Westfalen",
    "wof:name":"Pizzeria Pizza Avanti",
    "wof:placetype":"venue"
},
  "geometry": {"coordinates":[7.1222290993,50.7289237976],"type":"Point"}
}