{
  "type": "Feature",
  "properties": {
    "iso:country":"DE",
    "sg:address":"Birkenstr. 2",
    "sg:city":"Anhausen",
    "sg:phone":"+49 2639/960480",
    "sg:postcode":"56584",
    "sg:province":"Rheinland-Pfalz",
    "wof:name":"Hermes Transport Gmbh",
    "wof:placetype":"venue"
},
  "geometry": {"coordinates":[7.5653219223,50.5073661804],"type":"Point"}
}