{
  "type": "Feature",
  "properties": {
    "iso:country":"DE",
    "sg:address":"Rheinberger Str. 378",
    "sg:city":"Rheinberg",
    "sg:phone":"+49 2844/908136",
    "sg:postcode":"47495",
    "sg:province":"Nordrhein-Westfalen",
    "wof:name":"Dsq Dokumentationssicherung Und Qualit\u00e4tssicherung Gmbh",
    "wof:placetype":"venue"
},
  "geometry": {"coordinates":[6.6623601913,51.5260009766],"type":"Point"}
}