{
  "type": "Feature",
  "properties": {
    "iso:country":"DE",
    "sg:address":"Talstr. 7",
    "sg:city":"Cossebaude",
    "sg:phone":"+49 351/4537413",
    "sg:postcode":"01462",
    "wof:name":"Klaus Kahle Elbtal Druckerei Und",
    "wof:placetype":"venue"
},
  "geometry": {"coordinates":[13.6150045395,51.0790023804],"type":"Point"}
}