{
  "type": "Feature",
  "properties": {
    "iso:country":"DE",
    "sg:address":"Oberl\u00e4nder Ufer 190",
    "sg:city":"K\u00f6ln",
    "sg:phone":"+49 221/93729800",
    "sg:postcode":"50968",
    "sg:province":"Nordrhein-Westfalen",
    "wof:name":"Magirus-pur",
    "wof:placetype":"venue"
},
  "geometry": {"coordinates":[6.982363,50.902161],"type":"Point"}
}