{
  "type": "Feature",
  "properties": {
    "iso:country":"DE",
    "sg:address":"Thomasiusstr. 16",
    "sg:city":"Leipzig",
    "sg:postcode":"04109",
    "sg:province":"Sachsen",
    "wof:name":"K\u00e4te Heiseler",
    "wof:placetype":"venue"
},
  "geometry": {"coordinates":[12.3654298782,51.3409614563],"type":"Point"}
}