{
  "type": "Feature",
  "properties": {
    "iso:country":"DE",
    "sg:address":"Am Kai 2",
    "sg:city":"Gro\u00dfenbrode",
    "sg:postcode":"23775",
    "sg:province":"Schleswig-Holstein",
    "wof:name":"Yachthandel Gro\u00dfenbrode Gmbh",
    "wof:placetype":"venue"
},
  "geometry": {"coordinates":[11.0801849365,54.3548583984],"type":"Point"}
}