{
  "type": "Feature",
  "properties": {
    "iso:country":"DE",
    "sg:address":"Friedrichstr. 45",
    "sg:city":"Wiesbaden",
    "sg:phone":"+49 611/372062",
    "sg:postcode":"65185",
    "sg:province":"Hessen",
    "wof:name":"Rippon Boswell & Co. Ges. Zur Organisation",
    "wof:placetype":"venue"
},
  "geometry": {"coordinates":[8.2386627197,50.0804481506],"type":"Point"}
}