{
  "type": "Feature",
  "properties": {
    "iso:country":"DE",
    "sg:address":"Tr\u00fcbenbachstr. 12",
    "sg:city":"Suhl",
    "sg:phone":"+49 3681/305678",
    "sg:postcode":"98527",
    "sg:province":"Th\u00fcringen",
    "wof:name":"Der Fahrradkurier",
    "wof:placetype":"venue"
},
  "geometry": {"coordinates":[10.697541,50.60767],"type":"Point"}
}