{
  "type": "Feature",
  "properties": {
    "iso:country":"DE",
    "sg:address":"Georg - St\u00fctz - Str. 10",
    "sg:city":"Schw\u00e4bisch Gm\u00fcnd",
    "sg:phone":"+49 7171/38189",
    "sg:postcode":"73525",
    "sg:province":"Baden-W\u00fcrttemberg",
    "wof:name":"Brosien Verm\u00f6gensverwaltung",
    "wof:placetype":"venue"
},
  "geometry": {"coordinates":[9.7947502136,48.7939682007],"type":"Point"}
}