{
  "type": "Feature",
  "properties": {
    "iso:country":"DE",
    "sg:address":"Fritz-Reuter-Str. 5",
    "sg:city":"Camburg",
    "sg:phone":"+49 36421/22741",
    "sg:postcode":"07774",
    "sg:province":"Th\u00fcringen",
    "wof:name":"Paul Fischer",
    "wof:placetype":"venue"
},
  "geometry": {"coordinates":[11.70308,51.056309],"type":"Point"}
}