{
  "type": "Feature",
  "properties": {
    "iso:country":"DE",
    "sg:address":"Altk\u00f6nigstr. 2",
    "sg:city":"Fl\u00f6rsheim",
    "sg:phone":"+49 6145/4222",
    "sg:postcode":"65439",
    "sg:province":"Hessen",
    "wof:name":"Moll Und Eisenmann-kohl Rechtsanw\u00e4lte Und Notare",
    "wof:placetype":"venue"
},
  "geometry": {"coordinates":[8.4309034348,50.0156211853],"type":"Point"}
}