{
  "type": "Feature",
  "properties": {
    "iso:country":"DE",
    "sg:address":"Horst 6",
    "sg:city":"Peine",
    "sg:phone":"+49 5171/9560",
    "sg:postcode":"31226",
    "sg:province":"Niedersachsen",
    "wof:name":"Wasserverband Peine",
    "wof:placetype":"venue"
},
  "geometry": {"coordinates":[10.2141952515,52.317855835],"type":"Point"}
}