{
  "type": "Feature",
  "properties": {
    "iso:country":"DE",
    "sg:address":"K\u00f6lner Str. 58",
    "sg:city":"Gummersbach",
    "sg:phone":"+49 2261/5450",
    "sg:postcode":"51645",
    "sg:province":"Nordrhein-Westfalen",
    "wof:name":"Jobo Labortechnik Beteiligungs Gmbh",
    "wof:placetype":"venue"
},
  "geometry": {"coordinates":[7.619986,51.006325],"type":"Point"}
}