{
  "type": "Feature",
  "properties": {
    "iso:country":"DE",
    "sg:address":"Darmst\u00e4dter Str. 33 a",
    "sg:city":"Gro\u00df-Gerau",
    "sg:phone":"+49 6152/4317",
    "sg:postcode":"64521",
    "sg:province":"Hessen",
    "wof:name":"Linden-apotheke",
    "wof:placetype":"venue"
},
  "geometry": {"coordinates":[8.486366,49.919216],"type":"Point"}
}