{
  "type": "Feature",
  "properties": {
    "iso:country":"DE",
    "sg:address":"Buchweg 12",
    "sg:city":"Wangen im Allg\u00e4u",
    "sg:phone":"+49 7522",
    "sg:postcode":"88239",
    "sg:province":"Baden-W\u00fcrttemberg",
    "wof:name":"Mogema Gmbh",
    "wof:placetype":"venue"
},
  "geometry": {"coordinates":[9.8351984024,47.6886711121],"type":"Point"}
}