{
  "type": "Feature",
  "properties": {
    "iso:country":"DE",
    "sg:address":"Mundelsheimer Str. 2",
    "sg:city":"Heilbronn",
    "sg:phone":"+49 7131/52510",
    "sg:postcode":"74074",
    "sg:province":"Baden-W\u00fcrttemberg",
    "wof:name":"Ev. Pfarramt Kreuzkirche",
    "wof:placetype":"venue"
},
  "geometry": {"coordinates":[9.2082395554,49.1305923462],"type":"Point"}
}