{
  "type": "Feature",
  "properties": {
    "iso:country":"DE",
    "sg:address":"Weinstr. 7",
    "sg:city":"Bad D\u00fcrkheim",
    "sg:phone":"+49 6322/7057",
    "sg:postcode":"67098",
    "sg:province":"Rheinland-Pfalz",
    "wof:name":"E. Lerzer",
    "wof:placetype":"venue"
},
  "geometry": {"coordinates":[8.1757011414,49.4756507874],"type":"Point"}
}