{
  "type": "Feature",
  "properties": {
    "iso:country":"DE",
    "sg:address":"Am Osdorfer Born 30",
    "sg:city":"Hamburg",
    "sg:phone":"+49 40/80020411",
    "sg:postcode":"22549",
    "sg:province":"Hamburg",
    "wof:name":"Hans-r\u00fcdiger Fr\u00fchauf Ergotherapeutsche Praxis",
    "wof:placetype":"venue"
},
  "geometry": {"coordinates":[9.842338,53.576099],"type":"Point"}
}