{
  "type": "Feature",
  "properties": {
    "iso:country":"DE",
    "sg:address":"Masurenallee 5",
    "sg:city":"Bad Wildungen",
    "sg:phone":"+49 5621/72066",
    "sg:postcode":"34537",
    "sg:province":"Hessen",
    "wof:name":"Klaus Baronas",
    "wof:placetype":"venue"
},
  "geometry": {"coordinates":[9.078317,51.114761],"type":"Point"}
}