{
  "type": "Feature",
  "properties": {
    "iso:country":"DE",
    "sg:address":"Maschm\u00fchlenweg 8",
    "sg:city":"G\u00f6ttingen",
    "sg:phone":"+49 551/34039",
    "sg:postcode":"37073",
    "sg:province":"Niedersachsen",
    "wof:name":"Hallo Taxi Funkvermittlungs- Und",
    "wof:placetype":"venue"
},
  "geometry": {"coordinates":[9.9312019348,51.5396957397],"type":"Point"}
}