{
  "type": "Feature",
  "properties": {
    "iso:country":"DE",
    "sg:address":"Raiffeisenstr. 9-11",
    "sg:city":"Kassel",
    "sg:phone":"+49 561/209880",
    "sg:postcode":"34121",
    "sg:province":"Hessen",
    "wof:name":"Autolackiererei Karl Hucke Gmbh",
    "wof:placetype":"venue"
},
  "geometry": {"coordinates":[9.480302,51.293362],"type":"Point"}
}