{
  "type": "Feature",
  "properties": {
    "iso:country":"DE",
    "sg:address":"Wiesenstr. 2",
    "sg:city":"Eschweiler",
    "sg:phone":"+49 2403/52114",
    "sg:postcode":"52249",
    "sg:province":"Nordrhein-Westfalen",
    "wof:name":"Karl Grollmuhs",
    "wof:placetype":"venue"
},
  "geometry": {"coordinates":[6.291892,50.861698],"type":"Point"}
}