{
  "type": "Feature",
  "properties": {
    "iso:country":"DE",
    "sg:address":"Gerhart-Hauptmann-Str. 3",
    "sg:city":"Magdeburg",
    "sg:phone":"+49 391/737650",
    "sg:postcode":"39108",
    "sg:province":"Sachsen-Anhalt",
    "wof:name":"Gothaer Versicherung Chr. B\u00fctow",
    "wof:placetype":"venue"
},
  "geometry": {"coordinates":[11.616900444,52.1345710754],"type":"Point"}
}