{
  "type": "Feature",
  "properties": {
    "iso:country":"DE",
    "sg:address":"Christinastr. 46",
    "sg:city":"K\u00f6ln",
    "sg:phone":"+49 221/730270",
    "sg:postcode":"50733",
    "sg:province":"Nordrhein-Westfalen",
    "wof:name":"Ibrahim Altinova",
    "wof:placetype":"venue"
},
  "geometry": {"coordinates":[6.9529438019,50.9621963501],"type":"Point"}
}