{
  "type": "Feature",
  "properties": {
    "iso:country":"DE",
    "sg:address":"Alterlanger Str. 47",
    "sg:city":"Erlangen",
    "sg:phone":"+49 9131/45878",
    "sg:postcode":"91056",
    "sg:province":"Bayern",
    "wof:name":"Hilde St\u00fcmpel Fotografin",
    "wof:placetype":"venue"
},
  "geometry": {"coordinates":[10.9844293594,49.6005744934],"type":"Point"}
}