{
  "type": "Feature",
  "properties": {
    "iso:country":"DE",
    "sg:address":"Rader Heide 9",
    "sg:city":"Schwanewede",
    "sg:phone":"+49 421/6884366",
    "sg:postcode":"28790",
    "sg:province":"Niedersachsen",
    "wof:name":"Cme Kunststoff- Verarbeitungs Gmbh",
    "wof:placetype":"venue"
},
  "geometry": {"coordinates":[8.5395011902,53.2299346924],"type":"Point"}
}