{
  "type": "Feature",
  "properties": {
    "iso:country":"DE",
    "sg:address":"Bei den H\u00f6fen 82",
    "sg:city":"Hamburg",
    "sg:postcode":"22043",
    "sg:province":"Hamburg",
    "wof:name":"Eurospar",
    "wof:placetype":"venue"
},
  "geometry": {"coordinates":[10.1345691681,53.5718307495],"type":"Point"}
}