{
  "type": "Feature",
  "properties": {
    "iso:country":"DE",
    "sg:address":"Borsigstr. 22",
    "sg:city":"Reinbek",
    "sg:postcode":"21465",
    "sg:province":"Schleswig-Holstein",
    "wof:name":"Konietzky Erste Verm\u00f6gens- Verwaltungs Kg",
    "wof:placetype":"venue"
},
  "geometry": {"coordinates":[10.2405719757,53.5263710022],"type":"Point"}
}