{
  "type": "Feature",
  "properties": {
    "iso:country":"DE",
    "sg:address":"Filzenstr. 16 a",
    "sg:city":"Kolbermoor",
    "sg:phone":"+49 8031/96383",
    "sg:postcode":"83059",
    "sg:province":"Bayern",
    "wof:name":"Jr Beteiligungsges. Mbh",
    "wof:placetype":"venue"
},
  "geometry": {"coordinates":[12.071435,47.856766],"type":"Point"}
}