{
  "type": "Feature",
  "properties": {
    "iso:country":"DE",
    "sg:address":"Im Schwarzenbach 6",
    "sg:city":"Weil am Rhein",
    "sg:phone":"+49 7621/9409390",
    "sg:postcode":"79576",
    "sg:province":"Baden-W\u00fcrttemberg",
    "wof:name":"Bollinger Planungsges. Mbh",
    "wof:placetype":"venue"
},
  "geometry": {"coordinates":[7.599519,47.592148],"type":"Point"}
}