{
  "type": "Feature",
  "properties": {
    "iso:country":"DE",
    "sg:address":"Ostsee-Park-Str. 3",
    "sg:city":"Lambrechtshagen",
    "sg:phone":"+49 381/8002966",
    "sg:postcode":"18069",
    "sg:province":"Mecklenburg-Vorpommern",
    "wof:name":"Real",
    "wof:placetype":"venue"
},
  "geometry": {"coordinates":[12.0359172821,54.1057701111],"type":"Point"}
}