{
  "type": "Feature",
  "properties": {
    "iso:country":"DE",
    "sg:address":"Starkenburgring 30",
    "sg:city":"Alsbach-H\u00e4hnlein",
    "sg:phone":"+49 6257/903434",
    "sg:postcode":"64665",
    "sg:province":"Hessen",
    "wof:name":"Reinhard Hahn Rechtsanwalt",
    "wof:placetype":"venue"
},
  "geometry": {"coordinates":[8.6149892807,49.7379951477],"type":"Point"}
}