{
  "type": "Feature",
  "properties": {
    "iso:country":"DE",
    "sg:address":"Am Weendelsgraben 1",
    "sg:city":"G\u00f6ttingen",
    "sg:phone":"+49 551/380408",
    "sg:postcode":"37077",
    "sg:province":"Niedersachsen",
    "wof:name":"Biofiltronic Gmbh Labortechnik",
    "wof:placetype":"venue"
},
  "geometry": {"coordinates":[9.939557,51.564632],"type":"Point"}
}