{
  "type": "Feature",
  "properties": {
    "iso:country":"DE",
    "sg:address":"Dieselstr. 11",
    "sg:city":"Wadersloh",
    "sg:phone":"+49 2523/2043",
    "sg:postcode":"59329",
    "sg:province":"Nordrhein-Westfalen",
    "wof:name":"Heinrich Schniederjohann",
    "wof:placetype":"venue"
},
  "geometry": {"coordinates":[8.2583856583,51.734916687],"type":"Point"}
}