{
  "type": "Feature",
  "properties": {
    "iso:country":"DE",
    "sg:address":"Grauener Str. 6",
    "sg:city":"Neuenkirchen",
    "sg:phone":"+49 5195/392",
    "sg:postcode":"29643",
    "sg:province":"Niedersachsen",
    "wof:name":"Willi Bunke",
    "wof:placetype":"venue"
},
  "geometry": {"coordinates":[9.6672859192,53.0677032471],"type":"Point"}
}