{
  "type": "Feature",
  "properties": {
    "iso:country":"DE",
    "sg:address":"Vikarweg 10",
    "sg:city":"Stuttgart",
    "sg:phone":"+49 711/712870",
    "sg:postcode":"70567",
    "sg:province":"Baden-W\u00fcrttemberg",
    "wof:name":"Helmut Els\u00e4sser",
    "wof:placetype":"venue"
},
  "geometry": {"coordinates":[9.143716,48.724911],"type":"Point"}
}