{
  "type": "Feature",
  "properties": {
    "iso:country":"DE",
    "sg:address":"Moosweg 14-18",
    "sg:city":"Burgberg",
    "sg:phone":"+49 8321/66750",
    "sg:postcode":"87545",
    "sg:province":"Bayern",
    "wof:name":"Christian Wiegand",
    "wof:placetype":"venue"
},
  "geometry": {"coordinates":[10.277373,47.541859],"type":"Point"}
}