{
  "type": "Feature",
  "properties": {
    "iso:country":"DE",
    "sg:address":"Bredeneschredder 5",
    "sg:city":"Hamburg",
    "sg:phone":"+49 40/6040015",
    "sg:postcode":"22395",
    "sg:province":"Hamburg",
    "wof:name":"U Und H Beteiligungs-gmbh",
    "wof:placetype":"venue"
},
  "geometry": {"coordinates":[10.125636,53.668518],"type":"Point"}
}