{
  "type": "Feature",
  "properties": {
    "iso:country":"DE",
    "sg:address":"Gabelsbergerstr. 26",
    "sg:city":"M\u00f6nchengladbach",
    "sg:phone":"+49 2161/48903",
    "sg:postcode":"41065",
    "sg:province":"Nordrhein-Westfalen",
    "wof:name":"Selma Grewe",
    "wof:placetype":"venue"
},
  "geometry": {"coordinates":[6.4589757919,51.1895179749],"type":"Point"}
}