{
  "type": "Feature",
  "properties": {
    "iso:country":"DE",
    "sg:address":"Markt 6",
    "sg:city":"Crimmitschau",
    "sg:phone":"+49 3762/2274",
    "sg:postcode":"08451",
    "sg:province":"Sachsen",
    "wof:name":"L\u00f6wen-apotheke",
    "wof:placetype":"venue"
},
  "geometry": {"coordinates":[12.386253,50.816139],"type":"Point"}
}