{
  "type": "Feature",
  "properties": {
    "iso:country":"DE",
    "sg:address":"Feldstr. 11",
    "sg:city":"Langwedel",
    "sg:phone":"+49 4232/7672",
    "sg:postcode":"27299",
    "sg:province":"Niedersachsen",
    "wof:name":"Wilhelm Depke",
    "wof:placetype":"venue"
},
  "geometry": {"coordinates":[9.172726,52.979713],"type":"Point"}
}