{
  "type": "Feature",
  "properties": {
    "iso:country":"DE",
    "sg:address":"Grabenstr. 5",
    "sg:city":"Gerolzhofen",
    "sg:phone":"+49 9382/8325",
    "sg:postcode":"97447",
    "sg:province":"Bayern",
    "wof:name":"Arthur Schneider Gmbh & Co. Kg",
    "wof:placetype":"venue"
},
  "geometry": {"coordinates":[10.3502140045,49.8997497559],"type":"Point"}
}