{
  "type": "Feature",
  "properties": {
    "iso:country":"DE",
    "sg:address":"Marabustr. 35",
    "sg:city":"Stuttgart",
    "sg:phone":"+49 711/537242",
    "sg:postcode":"70378",
    "sg:province":"Baden-W\u00fcrttemberg",
    "wof:name":"Marktk\u00f6rble",
    "wof:placetype":"venue"
},
  "geometry": {"coordinates":[9.2320327759,48.8313407898],"type":"Point"}
}