{
  "type": "Feature",
  "properties": {
    "iso:country":"DE",
    "sg:address":"Ro\u00dfwette 2",
    "sg:city":"Villingen-Schwenningen",
    "sg:phone":"+49 7721/844810",
    "sg:postcode":"78048",
    "sg:province":"Baden-W\u00fcrttemberg",
    "wof:name":"Bernd Witz Gmbh",
    "wof:placetype":"venue"
},
  "geometry": {"coordinates":[8.462413,48.063198],"type":"Point"}
}