{
  "type": "Feature",
  "properties": {
    "iso:country":"DE",
    "sg:address":"Linkstr. 45",
    "sg:city":"Frankfurt",
    "sg:phone":"+49 69/381606",
    "sg:postcode":"65933",
    "sg:province":"Hessen",
    "wof:name":"Katholisches Pfarramt Mari\u00e4 Himmelfahrt",
    "wof:placetype":"venue"
},
  "geometry": {"coordinates":[8.6045818329,50.0922088623],"type":"Point"}
}