{
  "type": "Feature",
  "properties": {
    "iso:country":"DE",
    "sg:address":"Semmelweisstr. 12",
    "sg:city":"Jena",
    "sg:phone":"+49 3641/829683",
    "sg:postcode":"07743",
    "sg:province":"Th\u00fcringen",
    "wof:name":"Medizinisches Kaufhaus",
    "wof:placetype":"venue"
},
  "geometry": {"coordinates":[11.5764245987,50.9306640625],"type":"Point"}
}