{
  "type": "Feature",
  "properties": {
    "iso:country":"DE",
    "sg:address":"Bischof-Gerhard-Str. 6",
    "sg:city":"Schellerten",
    "sg:phone":"+49 5123/8419",
    "sg:postcode":"31174",
    "sg:province":"Niedersachsen",
    "wof:name":"Heinrich Bode",
    "wof:placetype":"venue"
},
  "geometry": {"coordinates":[10.067375,52.165146],"type":"Point"}
}