{
  "type": "Feature",
  "properties": {
    "iso:country":"DE",
    "sg:address":"Mainburger Str. 10",
    "sg:city":"Mauern",
    "sg:phone":"+49 8764/211",
    "sg:postcode":"85419",
    "sg:province":"Bayern",
    "wof:name":"A. Dausch",
    "wof:placetype":"venue"
},
  "geometry": {"coordinates":[11.89595,48.518448],"type":"Point"}
}