{
  "type": "Feature",
  "properties": {
    "iso:country":"DE",
    "sg:address":"Alt Nied 12",
    "sg:city":"Frankfurt",
    "sg:phone":"+49 69/397227",
    "sg:postcode":"65934",
    "sg:province":"Hessen",
    "wof:name":"Hasan Yenioglu",
    "wof:placetype":"venue"
},
  "geometry": {"coordinates":[8.565246582,50.0996856689],"type":"Point"}
}