{
  "type": "Feature",
  "properties": {
    "iso:country":"DE",
    "sg:address":"Bauernstr. 3",
    "sg:city":"Gablingen",
    "sg:phone":"+49 8230/7965",
    "sg:postcode":"86456",
    "sg:province":"Bayern",
    "wof:name":"Sebastian Meitinger",
    "wof:placetype":"venue"
},
  "geometry": {"coordinates":[10.826874,48.456711],"type":"Point"}
}