{
  "type": "Feature",
  "properties": {
    "iso:country":"DE",
    "sg:address":"Bahnhofsplatz 2",
    "sg:city":"Coburg",
    "sg:phone":"+49 9561/74093",
    "sg:postcode":"96450",
    "sg:province":"Bayern",
    "wof:name":"Thein Und Kollegen Rechtsanw\u00e4lte",
    "wof:placetype":"venue"
},
  "geometry": {"coordinates":[10.9586048126,50.2629547119],"type":"Point"}
}