{
  "type": "Feature",
  "properties": {
    "iso:country":"DE",
    "sg:address":"Clara-Zetkin-Str. 26a",
    "sg:city":"Tribsees",
    "sg:phone":"+49 38320/47196",
    "sg:postcode":"18465",
    "sg:province":"Mecklenburg-Vorpommern",
    "wof:name":"Martina Groth Masseurin",
    "wof:placetype":"venue"
},
  "geometry": {"coordinates":[12.763468,54.091961],"type":"Point"}
}