{
  "type": "Feature",
  "properties": {
    "iso:country":"DE",
    "sg:address":"Ahornstr. 9",
    "sg:city":"Thyrow",
    "sg:phone":"+49 33731/8290",
    "sg:postcode":"14974",
    "sg:province":"Brandenburg",
    "wof:name":"Der T\u00fcrenmann Bauelemente Vertriebs Beteiligungs Gmbh",
    "wof:placetype":"venue"
},
  "geometry": {"coordinates":[13.244794,52.253239],"type":"Point"}
}