{
  "type": "Feature",
  "properties": {
    "iso:country":"DE",
    "sg:address":"Schlo\u00dfstr. 4",
    "sg:city":"Oberstaufen",
    "sg:phone":"+49 8386/2075",
    "sg:postcode":"87534",
    "sg:province":"Bayern",
    "wof:name":"Raiffeisenbank Westallg\u00e4u Eg",
    "wof:placetype":"venue"
},
  "geometry": {"coordinates":[10.021342,47.553768],"type":"Point"}
}