{
  "type": "Feature",
  "properties": {
    "iso:country":"DE",
    "sg:address":"Auf der Leiten 8",
    "sg:city":"Penzberg",
    "sg:phone":"+49 8856/82227",
    "sg:postcode":"82377",
    "sg:province":"Bayern",
    "wof:name":"Henning Zahn-paulsen",
    "wof:placetype":"venue"
},
  "geometry": {"coordinates":[11.380941391,47.7629776001],"type":"Point"}
}