{
  "type": "Feature",
  "properties": {
    "iso:country":"DE",
    "sg:address":"Hildburghauser Str. 16b",
    "sg:city":"Berlin",
    "sg:phone":"+49 30/7214397",
    "sg:postcode":"12279",
    "sg:province":"Berlin",
    "wof:name":"Gerhard Thomas Wirtschaftspr\u00fcfer Und",
    "wof:placetype":"venue"
},
  "geometry": {"coordinates":[13.357003212,52.4133338928],"type":"Point"}
}