{
  "type": "Feature",
  "properties": {
    "iso:country":"DE",
    "sg:address":"Simrockstr. 64-66",
    "sg:city":"D\u00fcsseldorf",
    "sg:postcode":"40235",
    "sg:province":"Nordrhein-Westfalen",
    "wof:name":"Avp Arzt Gmbh",
    "wof:placetype":"venue"
},
  "geometry": {"coordinates":[6.8221721649,51.2417297363],"type":"Point"}
}