{
  "type": "Feature",
  "properties": {
    "iso:country":"DE",
    "sg:address":"Gewerbepark 8",
    "sg:city":"Gro\u00dfpostwitz",
    "sg:phone":"+49 3591/304800",
    "sg:postcode":"02692",
    "sg:province":"Sachsen",
    "wof:name":"D. Kothe",
    "wof:placetype":"venue"
},
  "geometry": {"coordinates":[14.4434261322,51.145198822],"type":"Point"}
}