{
  "type": "Feature",
  "properties": {
    "iso:country":"DE",
    "sg:address":"Hochstr. 26",
    "sg:city":"Gelsenkirchen",
    "sg:phone":"+49 209/39151",
    "sg:postcode":"45894",
    "sg:province":"Nordrhein-Westfalen",
    "wof:name":"Hollandfisch Van Den Berg Ohg",
    "wof:placetype":"venue"
},
  "geometry": {"coordinates":[7.0533018112,51.5788383484],"type":"Point"}
}