{
  "type": "Feature",
  "properties": {
    "iso:country":"DE",
    "sg:address":"Bergstr. 6",
    "sg:city":"Heidenheim",
    "sg:phone":"+49 9833/251",
    "sg:postcode":"91719",
    "sg:province":"Bayern",
    "wof:name":"Fritz Schmidt Hebamme",
    "wof:placetype":"venue"
},
  "geometry": {"coordinates":[10.699886,49.000767],"type":"Point"}
}