{
  "type": "Feature",
  "properties": {
    "iso:country":"DE",
    "sg:address":"Feldbergstr. 8",
    "sg:city":"Hilzingen",
    "sg:phone":"+49 7739/464",
    "sg:postcode":"78247",
    "sg:province":"Baden-W\u00fcrttemberg",
    "wof:name":"Helmut Post Kunst- Und Bauschlosserei",
    "wof:placetype":"venue"
},
  "geometry": {"coordinates":[8.7452325821,47.765663147],"type":"Point"}
}