{
  "type": "Feature",
  "properties": {
    "iso:country":"DE",
    "sg:address":"Wirtelstrasse 3",
    "sg:city":"D\u00fcren",
    "sg:phone":"+49 2421/959405",
    "sg:postcode":"52349",
    "sg:province":"Nordrhein-Westfalen",
    "wof:name":"Stellengesuche Im Internet",
    "wof:placetype":"venue"
},
  "geometry": {"coordinates":[6.48464,50.80304],"type":"Point"}
}