{
  "type": "Feature",
  "properties": {
    "iso:country":"DE",
    "sg:address":"B\u00fctzower Str. 3a",
    "sg:city":"Neukloster",
    "sg:phone":"+49 38422/25372",
    "sg:postcode":"23992",
    "sg:province":"Mecklenburg-Vorpommern",
    "wof:name":"M. Liesener",
    "wof:placetype":"venue"
},
  "geometry": {"coordinates":[11.687902,53.865189],"type":"Point"}
}