{
  "type": "Feature",
  "properties": {
    "iso:country":"DE",
    "sg:address":"Hauptstr. 43",
    "sg:city":"Werther",
    "sg:phone":"+49 3631/601217",
    "sg:postcode":"99735",
    "sg:province":"Th\u00fcringen",
    "wof:name":"Joachim Becker",
    "wof:placetype":"venue"
},
  "geometry": {"coordinates":[10.741887,51.473965],"type":"Point"}
}