{
  "type": "Feature",
  "properties": {
    "iso:country":"DE",
    "sg:address":"Nibelungenstr. 132",
    "sg:city":"Lorsch",
    "sg:phone":"+49 6251/52338",
    "sg:postcode":"64653",
    "sg:province":"Hessen",
    "wof:name":"W. Schneider Ohg",
    "wof:placetype":"venue"
},
  "geometry": {"coordinates":[8.5571641922,49.6529273987],"type":"Point"}
}