{
  "type": "Feature",
  "properties": {
    "iso:country":"DE",
    "sg:address":"Rosenplatz 16",
    "sg:city":"Baiersbronn",
    "sg:phone":"+49 7442/3544",
    "sg:postcode":"72270",
    "sg:province":"Baden-W\u00fcrttemberg",
    "wof:name":"E. Holz",
    "wof:placetype":"venue"
},
  "geometry": {"coordinates":[8.368896,48.50771],"type":"Point"}
}