{
  "type": "Feature",
  "properties": {
    "iso:country":"DE",
    "sg:address":"Rosenstr. 1",
    "sg:city":"Marienhafe",
    "sg:phone":"+49 4934/914025",
    "sg:postcode":"26529",
    "sg:province":"Niedersachsen",
    "wof:name":"Adler-apotheke",
    "wof:placetype":"venue"
},
  "geometry": {"coordinates":[7.27331,53.522308],"type":"Point"}
}