{
  "type": "Feature",
  "properties": {
    "iso:country":"DE",
    "sg:address":"Germaniaplatz 3",
    "sg:city":"Essen",
    "sg:phone":"+49 201/681520",
    "sg:postcode":"45355",
    "sg:province":"Nordrhein-Westfalen",
    "wof:name":"Caitas-essen Pflegedienste",
    "wof:placetype":"venue"
},
  "geometry": {"coordinates":[6.950947,51.475079],"type":"Point"}
}