{
  "type": "Feature",
  "properties": {
    "iso:country":"DE",
    "sg:address":"He\u00dfheimer Weg 2",
    "sg:city":"Karlstadt",
    "sg:phone":"+49 9353/3729",
    "sg:postcode":"97753",
    "sg:province":"Bayern",
    "wof:name":"Ehrenfels Spenglerei Bedachungen Gmbh",
    "wof:placetype":"venue"
},
  "geometry": {"coordinates":[9.751047,49.984463],"type":"Point"}
}