{
  "type": "Feature",
  "properties": {
    "iso:country":"DE",
    "sg:address":"Hauptstr. 125",
    "sg:city":"Birkenwerder",
    "sg:phone":"+49 3303/53420",
    "sg:postcode":"16547",
    "sg:province":"Brandenburg",
    "wof:name":"Fundamenta Baupartner Gmbh",
    "wof:placetype":"venue"
},
  "geometry": {"coordinates":[13.275556,52.696182],"type":"Point"}
}