{
  "type": "Feature",
  "properties": {
    "iso:country":"DE",
    "sg:address":"H\u00fcnxer Str. 347",
    "sg:city":"Dinslaken",
    "sg:phone":"+49 2064/36333",
    "sg:postcode":"46537",
    "sg:province":"Nordrhein-Westfalen",
    "wof:name":"Am Schacht",
    "wof:placetype":"venue"
},
  "geometry": {"coordinates":[6.7601900101,51.5797157288],"type":"Point"}
}