{
  "type": "Feature",
  "properties": {
    "iso:country":"DE",
    "sg:address":"An der Bach 2",
    "sg:city":"St. Goar",
    "sg:phone":"+49 6741/7011",
    "sg:postcode":"56329",
    "sg:province":"Rheinland-Pfalz",
    "wof:name":"R. Pabst",
    "wof:placetype":"venue"
},
  "geometry": {"coordinates":[7.7075791359,50.1474914551],"type":"Point"}
}