{
  "type": "Feature",
  "properties": {
    "iso:country":"DE",
    "sg:address":"Am Markt 26",
    "sg:city":"Schleiden",
    "sg:phone":"+49 2445/5351",
    "sg:postcode":"53937",
    "sg:province":"Nordrhein-Westfalen",
    "wof:name":"E. H\u00f6rnchen",
    "wof:placetype":"venue"
},
  "geometry": {"coordinates":[6.4756369591,50.5287895203],"type":"Point"}
}