{
  "type": "Feature",
  "properties": {
    "iso:country":"DE",
    "sg:address":"H\u00f6hstr. 7",
    "sg:city":"Merzalben",
    "sg:phone":"+49 6395/1703",
    "sg:postcode":"66978",
    "sg:province":"Rheinland-Pfalz",
    "wof:name":"Heidi Walter Masseurin",
    "wof:placetype":"venue"
},
  "geometry": {"coordinates":[7.722029,49.243469],"type":"Point"}
}