{
  "type": "Feature",
  "properties": {
    "iso:country":"DE",
    "sg:address":"Obere B\u00e4renloher Str. 11",
    "sg:city":"Bad Elster",
    "sg:phone":"+49 37437/2725",
    "sg:postcode":"08645",
    "sg:province":"Sachsen",
    "wof:name":"G. Katzmann",
    "wof:placetype":"venue"
},
  "geometry": {"coordinates":[12.2221651077,50.2874603271],"type":"Point"}
}