{
  "type": "Feature",
  "properties": {
    "iso:country":"DE",
    "sg:address":"Keplerweg 3",
    "sg:city":"Geretsried",
    "sg:phone":"+49 8171/909370",
    "sg:postcode":"82538",
    "sg:province":"Bayern",
    "wof:name":"Feine M\u00f6bel Inh. W. Berger",
    "wof:placetype":"venue"
},
  "geometry": {"coordinates":[11.496031,47.850079],"type":"Point"}
}