{
  "type": "Feature",
  "properties": {
    "iso:country":"DE",
    "sg:address":"Wartburgstr. 32",
    "sg:city":"Chemnitz",
    "sg:phone":"+49 371/585523",
    "sg:postcode":"09126",
    "sg:province":"Sachsen",
    "wof:name":"Fritzsch Und Mendrala",
    "wof:placetype":"venue"
},
  "geometry": {"coordinates":[12.937304,50.816799],"type":"Point"}
}