{
  "type": "Feature",
  "properties": {
    "iso:country":"DE",
    "sg:address":"Am Neuender Busch 46",
    "sg:city":"Wilhelmshaven",
    "sg:phone":"+49 4421/82664",
    "sg:postcode":"26386",
    "sg:province":"Niedersachsen",
    "wof:name":"Henze",
    "wof:placetype":"venue"
},
  "geometry": {"coordinates":[8.091181,53.550392],"type":"Point"}
}