{
  "type": "Feature",
  "properties": {
    "iso:country":"DE",
    "sg:address":"Halterner Str. 19",
    "sg:city":"Dorsten",
    "sg:phone":"+49 2362/208383",
    "sg:postcode":"46284",
    "sg:province":"Nordrhein-Westfalen",
    "wof:name":"D. Schulte-repel Augenoptiker",
    "wof:placetype":"venue"
},
  "geometry": {"coordinates":[6.9719800949,51.6700134277],"type":"Point"}
}