{
  "type": "Feature",
  "properties": {
    "iso:country":"DE",
    "sg:address":"Kochenbacher Str. 16",
    "sg:city":"K\u00f6nigswinter",
    "sg:phone":"+49 2244/7016",
    "sg:postcode":"53639",
    "sg:province":"Nordrhein-Westfalen",
    "wof:name":"Helmut Pinnen Finanzberater",
    "wof:placetype":"venue"
},
  "geometry": {"coordinates":[7.3174037933,50.6815681458],"type":"Point"}
}