{
  "type": "Feature",
  "properties": {
    "iso:country":"DE",
    "sg:address":"Am Drostenst\u00fcck 36",
    "sg:city":"L\u00fcdenscheid",
    "sg:phone":"+49 4961/0198580",
    "sg:postcode":"58507",
    "sg:province":"Nordrhein-Westfalen",
    "wof:name":"Frabona Gmbh",
    "wof:placetype":"venue"
},
  "geometry": {"coordinates":[8.752257,50.210354],"type":"Point"}
}