{
  "type": "Feature",
  "properties": {
    "iso:country":"DE",
    "sg:address":"Speerweg 25",
    "sg:city":"Berlin",
    "sg:postcode":"13465",
    "sg:province":"Berlin",
    "wof:name":"Obras Bautr\u00e4ger Gmbh",
    "wof:placetype":"venue"
},
  "geometry": {"coordinates":[13.268015,52.633884],"type":"Point"}
}