{
  "type": "Feature",
  "properties": {
    "iso:country":"DE",
    "sg:address":"Vorderettenberg 9",
    "sg:city":"Marktschellenberg",
    "sg:phone":"+49 8650/245",
    "sg:postcode":"83487",
    "sg:province":"Bayern",
    "wof:name":"Mesnerwirt Gastst\u00e4tten Gmbh",
    "wof:placetype":"venue"
},
  "geometry": {"coordinates":[13.0273418427,47.6833267212],"type":"Point"}
}