{
  "type": "Feature",
  "properties": {
    "iso:country":"DE",
    "sg:address":"Untermarkt 1",
    "sg:city":"Ortenburg",
    "sg:phone":"+49 8542/7575",
    "sg:postcode":"94496",
    "sg:province":"Bayern",
    "wof:name":"R. L\u00f6\u00dfl",
    "wof:placetype":"venue"
},
  "geometry": {"coordinates":[13.2241859436,48.5452003479],"type":"Point"}
}