{
  "type": "Feature",
  "properties": {
    "iso:country":"DE",
    "sg:address":"Domnauer Str. 2",
    "sg:city":"Berlin",
    "sg:phone":"+49 30/7535802",
    "sg:postcode":"12105",
    "sg:province":"Berlin",
    "wof:name":"Bernd Hennig",
    "wof:placetype":"venue"
},
  "geometry": {"coordinates":[13.36423,52.459423],"type":"Point"}
}