{
  "type": "Feature",
  "properties": {
    "iso:country":"DE",
    "sg:address":"Reichenbacher Str. 75",
    "sg:city":"G\u00f6rlitz",
    "sg:phone":"+49 3581/79064",
    "sg:postcode":"02827",
    "sg:province":"Sachsen",
    "wof:name":"P. Jutzi",
    "wof:placetype":"venue"
},
  "geometry": {"coordinates":[14.9458236694,51.14793396],"type":"Point"}
}