{
  "type": "Feature",
  "properties": {
    "iso:country":"DE",
    "sg:address":"Bernecker Str. 19-21",
    "sg:city":"Bayreuth",
    "sg:phone":"+49 921/83256",
    "sg:postcode":"95448",
    "sg:province":"Bayern",
    "wof:name":"\u00d6kometric Gmbh Bayreuther Institut F\u00fcr Umwelt-",
    "wof:placetype":"venue"
},
  "geometry": {"coordinates":[11.5939826965,49.9547920227],"type":"Point"}
}