{
  "type": "Feature",
  "properties": {
    "iso:country":"DE",
    "sg:address":"Freumericher Weg 14",
    "sg:city":"Engelskirchen",
    "sg:phone":"+49 2263/951376",
    "sg:postcode":"51766",
    "sg:province":"Nordrhein-Westfalen",
    "wof:name":"Berghaus Projekt Gesellschaft F\u00fcr E-technik",
    "wof:placetype":"venue"
},
  "geometry": {"coordinates":[7.461513,51.008476],"type":"Point"}
}