{
  "type": "Feature",
  "properties": {
    "iso:country":"DE",
    "sg:address":"Maxim-Gorki-Str. 20",
    "sg:city":"Magdeburg",
    "sg:phone":"+49 391/7316700",
    "sg:postcode":"39108",
    "sg:province":"Sachsen-Anhalt",
    "wof:name":"J. Pschak Steuerberater",
    "wof:placetype":"venue"
},
  "geometry": {"coordinates":[11.6174058914,52.131816864],"type":"Point"}
}