{
  "type": "Feature",
  "properties": {
    "iso:country":"DE",
    "sg:address":"Am Waymannshof 6",
    "sg:city":"Xanten",
    "sg:phone":"+49 2801/4821",
    "sg:postcode":"46509",
    "sg:province":"Nordrhein-Westfalen",
    "wof:name":"Heinz Kl\u00f6ckner",
    "wof:placetype":"venue"
},
  "geometry": {"coordinates":[6.4386410713,51.6495437622],"type":"Point"}
}