{
  "type": "Feature",
  "properties": {
    "iso:country":"DE",
    "sg:address":"Belvederer Allee 24",
    "sg:city":"Weimar",
    "sg:phone":"+49 3643/53211",
    "sg:postcode":"99425",
    "sg:province":"Th\u00fcringen",
    "wof:name":"C. Stengel",
    "wof:placetype":"venue"
},
  "geometry": {"coordinates":[11.3364686966,50.9678001404],"type":"Point"}
}