{
  "type": "Feature",
  "properties": {
    "iso:country":"DE",
    "sg:address":"Kleidorf 6",
    "sg:city":"Mauern",
    "sg:phone":"+49 8764/629",
    "sg:postcode":"85419",
    "sg:province":"Bayern",
    "wof:name":"L. Graf",
    "wof:placetype":"venue"
},
  "geometry": {"coordinates":[11.8974046707,48.5156745911],"type":"Point"}
}