{
  "type": "Feature",
  "properties": {
    "iso:country":"DE",
    "sg:address":"Bruchweg 26",
    "sg:city":"Krefeld",
    "sg:phone":"+49 2151/540206",
    "sg:postcode":"47829",
    "sg:province":"Nordrhein-Westfalen",
    "wof:name":"H. Eschig",
    "wof:placetype":"venue"
},
  "geometry": {"coordinates":[6.62886,51.378979],"type":"Point"}
}