{
  "type": "Feature",
  "properties": {
    "iso:country":"DE",
    "sg:address":"Friedrich-Ebert-Str. 6",
    "sg:city":"Leuna",
    "sg:phone":"+49 3461/813765",
    "sg:postcode":"06237",
    "sg:province":"Sachsen-Anhalt",
    "wof:name":"Allbau Gmbh",
    "wof:placetype":"venue"
},
  "geometry": {"coordinates":[12.017203,51.330524],"type":"Point"}
}