{
  "type": "Feature",
  "properties": {
    "iso:country":"DE",
    "sg:address":"Hauptstr. 18",
    "sg:city":"Garmisch-Partenkirchen",
    "sg:phone":"+49 8821/2843",
    "sg:postcode":"82467",
    "sg:province":"Bayern",
    "wof:name":"Markus Hagl Massage",
    "wof:placetype":"venue"
},
  "geometry": {"coordinates":[11.101454,47.500542],"type":"Point"}
}