{
  "type": "Feature",
  "properties": {
    "iso:country":"DE",
    "sg:address":"Weserm\u00fcnder Str.",
    "sg:city":"Otterndorf",
    "sg:phone":"+49 4751/3375",
    "sg:postcode":"21762",
    "sg:province":"Niedersachsen",
    "wof:name":"Ralph Matzner Gmbh",
    "wof:placetype":"venue"
},
  "geometry": {"coordinates":[8.89512,53.804523],"type":"Point"}
}