{
  "type": "Feature",
  "properties": {
    "iso:country":"DE",
    "sg:address":"Raerener Str. 2/1",
    "sg:city":"Aachen",
    "sg:phone":"+49 2408/930093",
    "sg:postcode":"52076",
    "sg:province":"Nordrhein-Westfalen",
    "wof:name":"Sml Licht- Und Therapiesysteme",
    "wof:placetype":"venue"
},
  "geometry": {"coordinates":[6.12358,50.718021],"type":"Point"}
}