{
  "type": "Feature",
  "properties": {
    "iso:country":"DE",
    "sg:address":"Wetterkreuz 23",
    "sg:city":"Erlangen",
    "sg:phone":"+49 9131/77370",
    "sg:postcode":"91058",
    "sg:province":"Bayern",
    "wof:name":"Thermo King",
    "wof:placetype":"venue"
},
  "geometry": {"coordinates":[11.022023201,49.5444450378],"type":"Point"}
}