{
  "type": "Feature",
  "properties": {
    "iso:country":"DE",
    "sg:address":"Bahnhofstr. 24",
    "sg:city":"H\u00f6henkirchen-Siegertbrn",
    "sg:phone":"+49 89/6019975",
    "sg:postcode":"85635",
    "sg:province":"Bayern",
    "wof:name":"Prandl Sport Inh. Harald Prandl",
    "wof:placetype":"venue"
},
  "geometry": {"coordinates":[11.721125,48.019707],"type":"Point"}
}