{
  "type": "Feature",
  "properties": {
    "iso:country":"DE",
    "sg:address":"Neubergstr. 19",
    "sg:city":"Schw\u00e4bisch Hall",
    "sg:phone":"+49 791/930000",
    "sg:postcode":"74523",
    "sg:province":"Baden-W\u00fcrttemberg",
    "wof:name":"Spedition K\u00fcbler Gmbh",
    "wof:placetype":"venue"
},
  "geometry": {"coordinates":[9.7405500412,49.1317214966],"type":"Point"}
}