{
  "type": "Feature",
  "properties": {
    "iso:country":"DE",
    "sg:address":"Eggstedter Holz",
    "sg:city":"Eggstedt",
    "sg:phone":"+49 4805/616",
    "sg:postcode":"25726",
    "sg:province":"Schleswig-Holstein",
    "wof:name":"Ferienhof Staben In Eggstedt",
    "wof:placetype":"venue"
},
  "geometry": {"coordinates":[-82.445374,38.41975],"type":"Point"}
}