{
  "type": "Feature",
  "properties": {
    "iso:country":"DE",
    "sg:address":"Ulmer Str 16/2",
    "sg:city":"Leonberg",
    "sg:phone":"+49 7152/979490",
    "sg:postcode":"71229",
    "sg:province":"Baden-W\u00fcrttemberg",
    "wof:name":"Robert Hoening Spezialfahrzeuge Gmbh",
    "wof:placetype":"venue"
},
  "geometry": {"coordinates":[9.0271587372,48.7873802185],"type":"Point"}
}