{
  "type": "Feature",
  "properties": {
    "iso:country":"DE",
    "sg:address":"Poststr. 35",
    "sg:city":"G\u00f6ppingen",
    "sg:phone":"+49 7161/969015",
    "sg:postcode":"73033",
    "sg:province":"Baden-W\u00fcrttemberg",
    "wof:name":"Johann Habla Rechtsanw\u00e4lte",
    "wof:placetype":"venue"
},
  "geometry": {"coordinates":[9.6562232971,48.7027816772],"type":"Point"}
}