{
  "type": "Feature",
  "properties": {
    "iso:country":"DE",
    "sg:address":"Friedlander Str. 5",
    "sg:city":"Karlsruhe",
    "sg:phone":"+49 7041/44047",
    "sg:postcode":"76139",
    "sg:province":"Baden-W\u00fcrttemberg",
    "wof:name":"Heinzpeter Schmieg Architekt",
    "wof:placetype":"venue"
},
  "geometry": {"coordinates":[8.438685,49.039715],"type":"Point"}
}