{
  "type": "Feature",
  "properties": {
    "iso:country":"DE",
    "sg:address":"Ringstr. 71",
    "sg:city":"Schweix",
    "sg:phone":"+49 6335/859165",
    "sg:postcode":"66957",
    "sg:province":"Rheinland-Pfalz",
    "wof:name":"Aloga Gmbh",
    "wof:placetype":"venue"
},
  "geometry": {"coordinates":[7.51161623,49.128704071],"type":"Point"}
}