{
  "type": "Feature",
  "properties": {
    "iso:country":"DE",
    "sg:city":"Wiggensbach",
    "sg:phone":"+49 8370/1231",
    "sg:postcode":"87487",
    "sg:province":"Bayern",
    "wof:name":"Raiffeisenbank Kempten Eg",
    "wof:placetype":"venue"
},
  "geometry": {"coordinates":[10.23114,47.745331],"type":"Point"}
}