{
  "type": "Feature",
  "properties": {
    "iso:country":"DE",
    "sg:address":"Schulstr. 14",
    "sg:city":"Gevelsberg",
    "sg:phone":"+49 4923/324370",
    "sg:postcode":"58285",
    "sg:province":"Nordrhein-Westfalen",
    "wof:name":"M. & B. Armbrecht Gmbh",
    "wof:placetype":"venue"
},
  "geometry": {"coordinates":[7.3436851501,51.3190917969],"type":"Point"}
}