{
  "type": "Feature",
  "properties": {
    "iso:country":"DE",
    "sg:address":"Grie 3 A",
    "sg:city":"Hildesheim",
    "sg:phone":"+49 5064/252",
    "sg:postcode":"31141",
    "sg:province":"Niedersachsen",
    "wof:name":"Heinrich Kaune",
    "wof:placetype":"venue"
},
  "geometry": {"coordinates":[9.995223,52.113594],"type":"Point"}
}