{
  "type": "Feature",
  "properties": {
    "iso:country":"DE",
    "sg:address":"Bommelser Str. 6",
    "sg:city":"Bomlitz",
    "sg:phone":"+49 5197/1237",
    "sg:postcode":"29699",
    "sg:province":"Niedersachsen",
    "wof:name":"Becker & H\u00e4nisch Gmbh",
    "wof:placetype":"venue"
},
  "geometry": {"coordinates":[9.692431,52.95013],"type":"Point"}
}