{
  "type": "Feature",
  "properties": {
    "iso:country":"DE",
    "sg:address":"Detlevstr 12",
    "sg:city":"Berlin",
    "sg:phone":"+49 30/9864123",
    "sg:postcode":"13053",
    "sg:province":"Berlin",
    "wof:name":"Ropo Rohrreinigungs-service Gmbh",
    "wof:placetype":"venue"
},
  "geometry": {"coordinates":[13.5232200623,52.5520019531],"type":"Point"}
}