{
  "type": "Feature",
  "properties": {
    "iso:country":"DE",
    "sg:address":"Mainzer Landstr. 351-367b",
    "sg:city":"Frankfurt",
    "sg:phone":"+49 69/97390357",
    "sg:postcode":"60326",
    "sg:province":"Hessen",
    "wof:name":"Sindtex Import-export Gmbh",
    "wof:placetype":"venue"
},
  "geometry": {"coordinates":[8.6350030899,50.102016449],"type":"Point"}
}