{
  "type": "Feature",
  "properties": {
    "iso:country":"DE",
    "sg:address":"In de Bost 27",
    "sg:city":"Hamburg",
    "sg:phone":"+49 40/865856",
    "sg:postcode":"22587",
    "sg:province":"Hamburg",
    "wof:name":"Rolf Kirsch Architekt",
    "wof:placetype":"venue"
},
  "geometry": {"coordinates":[9.828989,53.553196],"type":"Point"}
}