{
  "type": "Feature",
  "properties": {
    "iso:country":"DE",
    "sg:address":"Baumh\u00f6lzlweg 3",
    "sg:city":"Viechtach",
    "sg:phone":"+49 9942/5901",
    "sg:postcode":"94234",
    "sg:province":"Bayern",
    "wof:name":"W. Heintges Und H. Gl\u00e4\u00dfl Ingenieurb\u00fcro",
    "wof:placetype":"venue"
},
  "geometry": {"coordinates":[12.8842716217,49.0852661133],"type":"Point"}
}