{
  "type": "Feature",
  "properties": {
    "iso:country":"DE",
    "sg:address":"Hopfengartenstr. 14",
    "sg:city":"Ammerthal",
    "sg:phone":"+49 9628/1594",
    "sg:postcode":"92260",
    "sg:province":"Bayern",
    "wof:name":"Johann Fick Holzbildhauer",
    "wof:placetype":"venue"
},
  "geometry": {"coordinates":[11.763455,49.440399],"type":"Point"}
}