{
  "type": "Feature",
  "properties": {
    "iso:country":"DE",
    "sg:address":"Karl-Hoffmann-Str. 7",
    "sg:city":"Karlsruhe",
    "sg:postcode":"76137",
    "sg:province":"Baden-W\u00fcrttemberg",
    "wof:name":"Ip 5-ingenieurpartnerschaft Knapp Rohloffs Selig Wagner",
    "wof:placetype":"venue"
},
  "geometry": {"coordinates":[8.403581,48.995556],"type":"Point"}
}