{
  "type": "Feature",
  "properties": {
    "iso:country":"DE",
    "sg:address":"Leipziger Str. 26",
    "sg:city":"Gr\u00fcndau",
    "sg:phone":"+49 6051/5555",
    "sg:postcode":"63584",
    "sg:province":"Hessen",
    "wof:name":"Blumenhaus Fischer Heinrich Fischer",
    "wof:placetype":"venue"
},
  "geometry": {"coordinates":[9.137351,50.206463],"type":"Point"}
}