{
  "type": "Feature",
  "properties": {
    "iso:country":"DE",
    "sg:address":"Kamener Str. 73",
    "sg:city":"Hamm",
    "sg:phone":"+49 2381/450385",
    "sg:postcode":"59077",
    "sg:province":"Nordrhein-Westfalen",
    "wof:name":"L. Moser Esso Tankstelle",
    "wof:placetype":"venue"
},
  "geometry": {"coordinates":[7.7324881554,51.6315727234],"type":"Point"}
}