{
  "type": "Feature",
  "properties": {
    "iso:country":"DE",
    "sg:address":"Fr\u00fchaufstr. 29",
    "sg:city":"Idar-Oberstein",
    "sg:phone":"+49 6781/43246",
    "sg:postcode":"55743",
    "sg:province":"Rheinland-Pfalz",
    "wof:name":"E. Schmidt",
    "wof:placetype":"venue"
},
  "geometry": {"coordinates":[7.302457,49.724762],"type":"Point"}
}