{
  "type": "Feature",
  "properties": {
    "iso:country":"DE",
    "sg:address":"Hoenbergstr. 2 a",
    "sg:city":"Limburg",
    "sg:postcode":"65555",
    "sg:province":"Hessen",
    "wof:name":"P. O. S. Marketing Deutschland Gmbh",
    "wof:placetype":"venue"
},
  "geometry": {"coordinates":[8.0718755722,50.4035148621],"type":"Point"}
}