{
  "type": "Feature",
  "properties": {
    "iso:country":"DE",
    "sg:address":"R\u00f6thenbacher Str. 24",
    "sg:city":"Lauf",
    "sg:phone":"+49 9123/1710",
    "sg:postcode":"91207",
    "sg:province":"Bayern",
    "wof:name":"Georg Merkel Gmbh",
    "wof:placetype":"venue"
},
  "geometry": {"coordinates":[11.274283,49.501831],"type":"Point"}
}