{
  "type": "Feature",
  "properties": {
    "iso:country":"DE",
    "sg:address":"Breitenwieswg. 38",
    "sg:city":"Waldm\u00fcnchen",
    "sg:phone":"+49 9972/902063",
    "sg:postcode":"93449",
    "sg:province":"Bayern",
    "wof:name":"Eduard Deml Gmbh",
    "wof:placetype":"venue"
},
  "geometry": {"coordinates":[12.70264,49.381836],"type":"Point"}
}