{
  "type": "Feature",
  "properties": {
    "iso:country":"DE",
    "sg:address":"Ilbenstr. 39",
    "sg:city":"Furtwangen",
    "sg:phone":"+49 7723/1009",
    "sg:postcode":"78120",
    "sg:province":"Baden-W\u00fcrttemberg",
    "wof:name":"D. Sauter",
    "wof:placetype":"venue"
},
  "geometry": {"coordinates":[8.193342,48.051331],"type":"Point"}
}