{
  "type": "Feature",
  "properties": {
    "iso:country":"DE",
    "sg:address":"Kapellenstr. 51",
    "sg:city":"Kriftel",
    "sg:phone":"+49 6192/6082",
    "sg:postcode":"65830",
    "sg:province":"Hessen",
    "wof:name":"Edelholz Gmbh",
    "wof:placetype":"venue"
},
  "geometry": {"coordinates":[8.4568901062,50.0812797546],"type":"Point"}
}