{
  "type": "Feature",
  "properties": {
    "iso:country":"DE",
    "sg:address":"Hebelstr. 10",
    "sg:city":"Seelbach",
    "sg:phone":"+49 7823/96580",
    "sg:postcode":"77960",
    "sg:province":"Baden-W\u00fcrttemberg",
    "wof:name":"Franz Haag",
    "wof:placetype":"venue"
},
  "geometry": {"coordinates":[7.9406199455,48.314239502],"type":"Point"}
}