{
  "type": "Feature",
  "properties": {
    "iso:country":"DE",
    "sg:address":"Oesinghausener Str.",
    "sg:city":"Engelskirchen",
    "sg:phone":"+49 2261/73004",
    "sg:postcode":"51766",
    "sg:province":"Nordrhein-Westfalen",
    "wof:name":"Oberbergische Schraubenfabrik Gmbh & Co. Kg",
    "wof:placetype":"venue"
},
  "geometry": {"coordinates":[7.4968400002,50.9958724976],"type":"Point"}
}