{
  "type": "Feature",
  "properties": {
    "iso:country":"DE",
    "sg:address":"Grillparzerstr. 13",
    "sg:city":"Wiesbaden",
    "sg:phone":"+49 611/843021",
    "sg:postcode":"65187",
    "sg:province":"Hessen",
    "wof:name":"G\u00fcteschutz Beton- Und Fertig- Teilwerke Hessen E. V.",
    "wof:placetype":"venue"
},
  "geometry": {"coordinates":[8.2385196686,50.0678901672],"type":"Point"}
}