{
  "type": "Feature",
  "properties": {
    "iso:country":"DE",
    "sg:address":"Reichsstr. 20",
    "sg:city":"Kehl",
    "sg:phone":"+49 7851/5280",
    "sg:postcode":"77694",
    "sg:province":"Baden-W\u00fcrttemberg",
    "wof:name":"Christls Bierstube",
    "wof:placetype":"venue"
},
  "geometry": {"coordinates":[7.8424329758,48.5737037659],"type":"Point"}
}