{
  "type": "Feature",
  "properties": {
    "iso:country":"DE",
    "sg:address":"Tsingtauer Str. 71",
    "sg:city":"M\u00fcnchen",
    "sg:phone":"+49 89/4391880",
    "sg:postcode":"81827",
    "sg:province":"Bayern",
    "wof:name":"La Donna",
    "wof:placetype":"venue"
},
  "geometry": {"coordinates":[11.696396,48.104141],"type":"Point"}
}