{
  "type": "Feature",
  "properties": {
    "iso:country":"DE",
    "sg:address":"Eckenerstr. 18",
    "sg:city":"Hagen",
    "sg:phone":"+49 2331/52811",
    "sg:postcode":"58093",
    "sg:province":"Nordrhein-Westfalen",
    "wof:name":"Gottfried Krause",
    "wof:placetype":"venue"
},
  "geometry": {"coordinates":[7.512057,51.35376],"type":"Point"}
}