{
  "type": "Feature",
  "properties": {
    "iso:country":"DE",
    "sg:address":"Hastedter Osterdeich 241",
    "sg:city":"Bremen",
    "sg:postcode":"28207",
    "sg:province":"Bremen",
    "wof:name":"Lwl Com Gmbh",
    "wof:placetype":"venue"
},
  "geometry": {"coordinates":[8.87151,53.061481],"type":"Point"}
}