{
  "type": "Feature",
  "properties": {
    "iso:country":"DE",
    "sg:address":"Sch\u00fctzheide 26",
    "sg:city":"Stolberg",
    "sg:phone":"+49 2402/30431",
    "sg:postcode":"52223",
    "sg:province":"Nordrhein-Westfalen",
    "wof:name":"Anne Horbach Kunststopferei",
    "wof:placetype":"venue"
},
  "geometry": {"coordinates":[6.2192788124,50.7364044189],"type":"Point"}
}