{
  "type": "Feature",
  "properties": {
    "iso:country":"DE",
    "sg:address":"Karlstra\u00dfe 20",
    "sg:city":"D\u00fcsseldorf",
    "sg:phone":"+49 211/1792700",
    "sg:postcode":"40210",
    "sg:province":"Nordrhein-Westfalen",
    "wof:name":"Deutsches Ern\u00e4hrungsforum",
    "wof:placetype":"venue"
},
  "geometry": {"coordinates":[6.7894639969,51.2206382751],"type":"Point"}
}