{
  "type": "Feature",
  "properties": {
    "iso:country":"DE",
    "sg:address":"Dickte 4",
    "sg:city":"Hofgeismar",
    "sg:phone":"+49 5675/6119",
    "sg:postcode":"34369",
    "sg:province":"Hessen",
    "wof:name":"Volker Trupke",
    "wof:placetype":"venue"
},
  "geometry": {"coordinates":[9.42767,51.536221],"type":"Point"}
}