{
  "type": "Feature",
  "properties": {
    "iso:country":"DE",
    "sg:address":"Forststr. 35",
    "sg:city":"Plauen",
    "sg:phone":"+49 3741/226934",
    "sg:postcode":"08523",
    "sg:province":"Sachsen",
    "wof:name":"Karin K\u00e4stner Gmbh",
    "wof:placetype":"venue"
},
  "geometry": {"coordinates":[12.13787,50.499691],"type":"Point"}
}