{
  "type": "Feature",
  "properties": {
    "iso:country":"DE",
    "sg:address":"Theodor-Heuss-Str. 26",
    "sg:city":"Duisburg",
    "sg:phone":"+49 203/581058",
    "sg:postcode":"47167",
    "sg:province":"Nordrhein-Westfalen",
    "wof:name":"Bacharach Kg",
    "wof:placetype":"venue"
},
  "geometry": {"coordinates":[6.796911,51.486347],"type":"Point"}
}