{
  "type": "Feature",
  "properties": {
    "iso:country":"DE",
    "sg:address":"Hauptstr. 19",
    "sg:city":"Ladenburg",
    "sg:phone":"+49 6203/5210",
    "sg:postcode":"68526",
    "sg:province":"Baden-W\u00fcrttemberg",
    "wof:name":"Landesbausparkasse Beratungsstelle",
    "wof:placetype":"venue"
},
  "geometry": {"coordinates":[8.608854,49.471985],"type":"Point"}
}