{
  "type": "Feature",
  "properties": {
    "iso:country":"DE",
    "sg:address":"Schulzenweg 32",
    "sg:city":"Erfurt",
    "sg:phone":"+49 361",
    "sg:postcode":"99097",
    "sg:province":"Th\u00fcringen",
    "wof:name":"Virtual Erfurt, Antiqut\u00e4ten & Internet",
    "wof:placetype":"venue"
},
  "geometry": {"coordinates":[11.07173,50.951302],"type":"Point"}
}