{
  "type": "Feature",
  "properties": {
    "iso:country":"DE",
    "sg:address":"Postfach 50",
    "sg:city":"Kehl",
    "sg:phone":"+49 7851/76364",
    "sg:postcode":"77686",
    "sg:province":"Baden-W\u00fcrttemberg",
    "wof:name":"Forimpex Gmbh",
    "wof:placetype":"venue"
},
  "geometry": {"coordinates":[7.81324,48.572479],"type":"Point"}
}