{
  "type": "Feature",
  "properties": {
    "iso:country":"DE",
    "sg:address":"Oranienburger Str. 35",
    "sg:city":"Gransee",
    "sg:phone":"+49 3306/2301",
    "sg:postcode":"16775",
    "sg:province":"Brandenburg",
    "wof:name":"Werner Liese",
    "wof:placetype":"venue"
},
  "geometry": {"coordinates":[13.1543207169,53.0006637573],"type":"Point"}
}