{
  "type": "Feature",
  "properties": {
    "iso:country":"DE",
    "sg:address":"Am Laach 8",
    "sg:city":"Treis-Karden",
    "sg:phone":"+49 2672/9310",
    "sg:postcode":"56253",
    "sg:province":"Rheinland-Pfalz",
    "wof:name":"Mosellandwerkst\u00e4tten Ebernach-k\u00fchr Gemeinn. Gmbh",
    "wof:placetype":"venue"
},
  "geometry": {"coordinates":[7.294977,50.169708],"type":"Point"}
}