{
  "type": "Feature",
  "properties": {
    "iso:country":"DE",
    "sg:address":"Zedernstr. 31",
    "sg:city":"Grevenbroich",
    "sg:phone":"+49 2181/659320",
    "sg:postcode":"41515",
    "sg:province":"Nordrhein-Westfalen",
    "wof:name":"Paul R\u00fctten Zahntechnik Gmbh",
    "wof:placetype":"venue"
},
  "geometry": {"coordinates":[6.6004829407,51.0850028992],"type":"Point"}
}