{
  "type": "Feature",
  "properties": {
    "iso:country":"DE",
    "sg:address":"Gernr\u00f6der Weg 4c",
    "sg:city":"Quedlinburg",
    "sg:phone":"+49 3946/702211",
    "sg:postcode":"06484",
    "sg:province":"Sachsen-Anhalt",
    "wof:name":"Rohstoffrecycling Und Containerdienst Sch\u00fctze Gmbh",
    "wof:placetype":"venue"
},
  "geometry": {"coordinates":[11.142914772,51.7786712646],"type":"Point"}
}