{
  "type": "Feature",
  "properties": {
    "iso:country":"DE",
    "sg:address":"Hauptstr. 4",
    "sg:city":"Petersberg",
    "sg:phone":"+49 661/64100",
    "sg:postcode":"36100",
    "sg:province":"Hessen",
    "wof:name":"A. M\u00f6ller",
    "wof:placetype":"venue"
},
  "geometry": {"coordinates":[9.7335691452,50.5907897949],"type":"Point"}
}