{
  "type": "Feature",
  "properties": {
    "iso:country":"DE",
    "sg:address":"Berkaer Str. 6",
    "sg:city":"Berlin",
    "sg:phone":"+49 30/8263341",
    "sg:postcode":"14199",
    "sg:province":"Berlin",
    "wof:name":"G\u00fcnter Wehde Architekt",
    "wof:placetype":"venue"
},
  "geometry": {"coordinates":[13.288638,52.477028],"type":"Point"}
}