{
  "type": "Feature",
  "properties": {
    "iso:country":"DE",
    "sg:address":"Nideggener Str. 114",
    "sg:city":"D\u00fcren",
    "sg:phone":"+49 2421/57561",
    "sg:postcode":"52349",
    "sg:province":"Nordrhein-Westfalen",
    "wof:name":"B. Bellschan Von Mildenburg",
    "wof:placetype":"venue"
},
  "geometry": {"coordinates":[6.489684,50.791187],"type":"Point"}
}