{
  "type": "Feature",
  "properties": {
    "iso:country":"DE",
    "sg:address":"Kronskamp 2",
    "sg:city":"Barsinghausen",
    "sg:phone":"+49 5105/5270",
    "sg:postcode":"30890",
    "sg:province":"Niedersachsen",
    "wof:name":"Hotel Echo",
    "wof:placetype":"venue"
},
  "geometry": {"coordinates":[9.4152183533,52.3335418701],"type":"Point"}
}