{
  "type": "Feature",
  "properties": {
    "iso:country":"DE",
    "sg:address":"Moselring 2-4",
    "sg:city":"Koblenz",
    "sg:phone":"+49 261/404030",
    "sg:postcode":"56068",
    "sg:province":"Rheinland-Pfalz",
    "wof:name":"Evangelische Kirchengemeinde Koblenz-l\u00fctzel",
    "wof:placetype":"venue"
},
  "geometry": {"coordinates":[7.5887098312,50.3583450317],"type":"Point"}
}