{
  "type": "Feature",
  "properties": {
    "iso:country":"DE",
    "sg:address":"Am Sande 3",
    "sg:city":"L\u00fcneburg",
    "sg:phone":"+49 4131/732881",
    "sg:postcode":"21335",
    "sg:province":"Niedersachsen",
    "wof:name":"Mc Donalds",
    "wof:placetype":"venue"
},
  "geometry": {"coordinates":[10.4086580276,53.2473258972],"type":"Point"}
}