{
  "type": "Feature",
  "properties": {
    "iso:country":"DE",
    "sg:address":"Adenauerallee 6",
    "sg:city":"Hannover",
    "sg:phone":"+49 511/671020",
    "sg:postcode":"30175",
    "sg:province":"Niedersachsen",
    "wof:name":"B\u00fcro Becker",
    "wof:placetype":"venue"
},
  "geometry": {"coordinates":[9.7664909363,52.3810691833],"type":"Point"}
}