{
  "type": "Feature",
  "properties": {
    "iso:country":"DE",
    "sg:address":"B\u00e4rbroich 40",
    "sg:city":"Bergisch Gladbach",
    "sg:phone":"+49 2207/96930",
    "sg:postcode":"51429",
    "sg:province":"Nordrhein-Westfalen",
    "wof:name":"Dr. Joachim Urban",
    "wof:placetype":"venue"
},
  "geometry": {"coordinates":[7.222569,50.98243],"type":"Point"}
}