{
  "type": "Feature",
  "properties": {
    "iso:country":"DE",
    "sg:address":"Hildesheimer Str. 73",
    "sg:city":"Hannover",
    "sg:phone":"+49 511/885230",
    "sg:postcode":"30169",
    "sg:province":"Niedersachsen",
    "wof:name":"Restaurant Tai-pai",
    "wof:placetype":"venue"
},
  "geometry": {"coordinates":[9.7497692108,52.3613739014],"type":"Point"}
}