{
  "type": "Feature",
  "properties": {
    "iso:country":"DE",
    "sg:address":"Emser Landstr. 24",
    "sg:city":"Lahnstein",
    "sg:phone":"+49 2621/7054",
    "sg:postcode":"56112",
    "sg:province":"Rheinland-Pfalz",
    "wof:name":"Steinbruch Grauwacke Gmbh",
    "wof:placetype":"venue"
},
  "geometry": {"coordinates":[7.6413149834,50.3094863892],"type":"Point"}
}