{
  "type": "Feature",
  "properties": {
    "iso:country":"DE",
    "sg:address":"Theodor-Heuss-Str. 87",
    "sg:city":"Leimen",
    "sg:phone":"+49 6224/83708",
    "sg:postcode":"69181",
    "sg:province":"Baden-W\u00fcrttemberg",
    "wof:name":"Archisecur Sicherheitskonzepte Gmbh",
    "wof:placetype":"venue"
},
  "geometry": {"coordinates":[8.66881,49.333096],"type":"Point"}
}