{
  "type": "Feature",
  "properties": {
    "iso:country":"DE",
    "sg:address":"Inselweg 4",
    "sg:city":"Regnitzlosau",
    "sg:phone":"+49 9294/94111",
    "sg:postcode":"95194",
    "sg:province":"Bayern",
    "wof:name":"Apotheke Am Dreil\u00e4ndereck",
    "wof:placetype":"venue"
},
  "geometry": {"coordinates":[12.04545,50.298046],"type":"Point"}
}