{
  "type": "Feature",
  "properties": {
    "iso:country":"DE",
    "sg:address":"Schleiermacherstr. 15",
    "sg:city":"Leonberg",
    "sg:phone":"+49 7152/6732",
    "sg:postcode":"71229",
    "sg:province":"Baden-W\u00fcrttemberg",
    "wof:name":"Brigitte Brutscher Verlagsvertreter",
    "wof:placetype":"venue"
},
  "geometry": {"coordinates":[9.020438,48.796223],"type":"Point"}
}