{
  "type": "Feature",
  "properties": {
    "iso:country":"DE",
    "sg:address":"Raiffeisenstr. 9",
    "sg:city":"Prosselsheim",
    "sg:postcode":"97279",
    "sg:province":"Bayern",
    "wof:name":"B\u00f6ttcher Systembau Gmbh",
    "wof:placetype":"venue"
},
  "geometry": {"coordinates":[10.126833,49.865608],"type":"Point"}
}