{
  "type": "Feature",
  "properties": {
    "iso:country":"DE",
    "sg:address":"Leipziger Str. 40",
    "sg:city":"Frankfurt",
    "sg:phone":"+49 69/702355",
    "sg:postcode":"60487",
    "sg:province":"Hessen",
    "wof:name":"Eis-cafe Cortina",
    "wof:placetype":"venue"
},
  "geometry": {"coordinates":[8.647313,50.122044],"type":"Point"}
}