{
  "type": "Feature",
  "properties": {
    "iso:country":"DE",
    "sg:address":"Allacher Str. 98",
    "sg:city":"M\u00fcnchen",
    "sg:phone":"+49 89/142112",
    "sg:postcode":"80997",
    "sg:province":"Bayern",
    "wof:name":"Praxis Dr. Von Hummel - Muenchen",
    "wof:placetype":"venue"
},
  "geometry": {"coordinates":[11.493386,48.178867],"type":"Point"}
}