{
  "type": "Feature",
  "properties": {
    "iso:country":"DE",
    "sg:address":"Pfarrer-H\u00f6fflinger-Str. 6",
    "sg:city":"Ulm",
    "sg:phone":"+49 7305/4222",
    "sg:postcode":"89079",
    "sg:province":"Baden-W\u00fcrttemberg",
    "wof:name":"Antonie Hanselmann",
    "wof:placetype":"venue"
},
  "geometry": {"coordinates":[9.9323949814,48.3291511536],"type":"Point"}
}