{
  "type": "Feature",
  "properties": {
    "iso:country":"DE",
    "sg:address":"Zum Hornbruch 25",
    "sg:city":"Bergneustadt",
    "sg:phone":"+49 2261/40089",
    "sg:postcode":"51702",
    "sg:province":"Nordrhein-Westfalen",
    "wof:name":"Papierverarbeitung Peters Verwaltungs Gmbh",
    "wof:placetype":"venue"
},
  "geometry": {"coordinates":[7.6946821213,51.0337295532],"type":"Point"}
}