{
  "type": "Feature",
  "properties": {
    "iso:country":"DE",
    "sg:address":"Johannisthaler Chaussee 329",
    "sg:city":"Berlin",
    "sg:phone":"+49 30/60258952",
    "sg:postcode":"12351",
    "sg:province":"Berlin",
    "wof:name":"Diakonie-station Neuk\u00f6lln Gmbh",
    "wof:placetype":"venue"
},
  "geometry": {"coordinates":[13.453311,52.429146],"type":"Point"}
}