{
  "type": "Feature",
  "properties": {
    "iso:country":"DE",
    "sg:address":"Kornmarkt 14",
    "sg:city":"Biersdorf am See",
    "sg:phone":"+49 6569/513",
    "sg:postcode":"54636",
    "sg:province":"Rheinland-Pfalz",
    "wof:name":"Franziska Schreiber",
    "wof:placetype":"venue"
},
  "geometry": {"coordinates":[6.4489850998,50.0177612305],"type":"Point"}
}