{
  "type": "Feature",
  "properties": {
    "iso:country":"DE",
    "sg:address":"Nassachstr. 22",
    "sg:city":"Breiteng\u00fc\u00dfbach",
    "sg:phone":"+49 9544/980282",
    "sg:postcode":"96149",
    "sg:province":"Bayern",
    "wof:name":"Albert Krapf",
    "wof:placetype":"venue"
},
  "geometry": {"coordinates":[10.887049675,49.974609375],"type":"Point"}
}