{
  "type": "Feature",
  "properties": {
    "iso:country":"DE",
    "sg:address":"Ulmenstr. 29",
    "sg:city":"Essenbach",
    "sg:phone":"+49 8703/2641",
    "sg:postcode":"84051",
    "sg:province":"Bayern",
    "wof:name":"P.u.b. Gei\u00dfner",
    "wof:placetype":"venue"
},
  "geometry": {"coordinates":[12.224256,48.615341],"type":"Point"}
}