{
  "type": "Feature",
  "properties": {
    "iso:country":"DE",
    "sg:address":"Allmisried 1",
    "sg:city":"Isny",
    "sg:phone":"+49 7567/1026",
    "sg:postcode":"88316",
    "sg:province":"Baden-W\u00fcrttemberg",
    "wof:name":"Gebhard Und Elsa Wagner Campingplatz Beuren",
    "wof:placetype":"venue"
},
  "geometry": {"coordinates":[10.005433,47.753822],"type":"Point"}
}