{
  "type": "Feature",
  "properties": {
    "iso:country":"DE",
    "sg:address":"Hohenzollernstr. 46",
    "sg:city":"Essen",
    "sg:phone":"+49 201/773068",
    "sg:postcode":"45128",
    "sg:province":"Nordrhein-Westfalen",
    "wof:name":"Info-service Gmbh",
    "wof:placetype":"venue"
},
  "geometry": {"coordinates":[7.0127878189,51.4432830811],"type":"Point"}
}