{
  "type": "Feature",
  "properties": {
    "iso:country":"DE",
    "sg:address":"Hamburger Str. 205",
    "sg:city":"Elmshorn",
    "sg:phone":"+49 4121/71150",
    "sg:postcode":"25337",
    "sg:province":"Schleswig-Holstein",
    "wof:name":"Tennis Squash Und Fitnesspark Elmshorn",
    "wof:placetype":"venue"
},
  "geometry": {"coordinates":[9.6912994385,53.748500824],"type":"Point"}
}