{
  "type": "Feature",
  "properties": {
    "iso:country":"DE",
    "sg:address":"Gubener Str. 14",
    "sg:city":"Cottbus",
    "sg:phone":"+49 355/7390",
    "sg:postcode":"03042",
    "sg:province":"Brandenburg",
    "wof:name":"Finessa Fleisch- Und Wurstspezialit\u00e4ten",
    "wof:placetype":"venue"
},
  "geometry": {"coordinates":[14.3693056107,51.7642593384],"type":"Point"}
}