{
  "type": "Feature",
  "properties": {
    "iso:country":"DE",
    "sg:address":"Bredenscheider Str. 30 b",
    "sg:city":"Hattingen",
    "sg:phone":"+49 2324/202164",
    "sg:postcode":"45525",
    "sg:province":"Nordrhein-Westfalen",
    "wof:name":"Wald-apotheke",
    "wof:placetype":"venue"
},
  "geometry": {"coordinates":[7.192433,51.395172],"type":"Point"}
}