{
  "type": "Feature",
  "properties": {
    "iso:country":"DE",
    "sg:address":"Gleismuthhausen 18 h",
    "sg:city":"Se\u00dflach",
    "sg:phone":"+49 9567/232",
    "sg:postcode":"96145",
    "sg:province":"Bayern",
    "wof:name":"G. Fick",
    "wof:placetype":"venue"
},
  "geometry": {"coordinates":[10.8410129547,50.1890983582],"type":"Point"}
}