{
  "type": "Feature",
  "properties": {
    "iso:country":"DE",
    "sg:address":"Marktplatz 6",
    "sg:city":"Kastellaun",
    "sg:phone":"+49 6762/6630",
    "sg:postcode":"56288",
    "sg:province":"Rheinland-Pfalz",
    "wof:name":"M. Wilkening",
    "wof:placetype":"venue"
},
  "geometry": {"coordinates":[7.4413328171,50.0711975098],"type":"Point"}
}