{
  "type": "Feature",
  "properties": {
    "iso:country":"DE",
    "sg:address":"Pfaffenh\u00e4ule 50",
    "sg:city":"Singen",
    "sg:phone":"+49 4977/3168771",
    "sg:postcode":"78224",
    "sg:province":"Baden-W\u00fcrttemberg",
    "wof:name":"Daniel Hornung",
    "wof:placetype":"venue"
},
  "geometry": {"coordinates":[8.872026,47.758949],"type":"Point"}
}