{
  "type": "Feature",
  "properties": {
    "iso:country":"DE",
    "sg:address":"Th\u00fcringer Str. 7",
    "sg:city":"Hessisch Lichtenau",
    "sg:phone":"+49 5602/2343",
    "sg:postcode":"37235",
    "sg:province":"Hessen",
    "wof:name":"K. H. T\u00f6nsmann Steuerbevollm\u00e4chtigter",
    "wof:placetype":"venue"
},
  "geometry": {"coordinates":[9.7172679901,51.1919593811],"type":"Point"}
}