{
  "type": "Feature",
  "properties": {
    "iso:country":"DE",
    "sg:address":"Quagliostr. 6",
    "sg:city":"M\u00fcnchen",
    "sg:postcode":"81543",
    "sg:province":"Bayern",
    "wof:name":"Vedra Verlag Bernd Dost E. K.",
    "wof:placetype":"venue"
},
  "geometry": {"coordinates":[11.560891,48.10519],"type":"Point"}
}