{
  "type": "Feature",
  "properties": {
    "iso:country":"DE",
    "sg:address":"Kirchhellener Allee 92",
    "sg:city":"Dorsten",
    "sg:phone":"+49 2362/22531",
    "sg:postcode":"46282",
    "sg:province":"Nordrhein-Westfalen",
    "wof:name":"E. Krietemeyer Gmbh",
    "wof:placetype":"venue"
},
  "geometry": {"coordinates":[6.960053,51.652115],"type":"Point"}
}