{
  "type": "Feature",
  "properties": {
    "iso:country":"DE",
    "sg:address":"Industriestr. 12",
    "sg:city":"Holzkirchen",
    "sg:postcode":"83607",
    "sg:province":"Bayern",
    "wof:name":"Ratschiller's Konditorei Gmbh & Co. Kg",
    "wof:placetype":"venue"
},
  "geometry": {"coordinates":[11.7134599686,47.8800086975],"type":"Point"}
}