{
  "type": "Feature",
  "properties": {
    "iso:country":"DE",
    "sg:address":"Annenstr 9",
    "sg:city":"Kiel",
    "sg:phone":"+49 431/579890",
    "sg:postcode":"24105",
    "sg:province":"Schleswig-Holstein",
    "wof:name":"Heyne, Lippert & Team Werbeagentur Und Verlagsgesellschaft Mbh",
    "wof:placetype":"venue"
},
  "geometry": {"coordinates":[10.130638,54.330566],"type":"Point"}
}