{
  "type": "Feature",
  "properties": {
    "iso:country":"DE",
    "sg:address":"Taubenheimstr. 35",
    "sg:city":"Stuttgart",
    "sg:phone":"+49 711/569812",
    "sg:postcode":"70372",
    "sg:province":"Baden-W\u00fcrttemberg",
    "wof:name":"Gastst\u00e4tte K. J\u00e4ger",
    "wof:placetype":"venue"
},
  "geometry": {"coordinates":[9.2272844315,48.8047981262],"type":"Point"}
}