{
  "type": "Feature",
  "properties": {
    "iso:country":"DE",
    "sg:address":"Boeler Str. 3",
    "sg:city":"Hagen",
    "sg:phone":"+49 2331/882424",
    "sg:postcode":"58097",
    "sg:province":"Nordrhein-Westfalen",
    "wof:name":"Huk-coburg Kundendienstb\u00fcro",
    "wof:placetype":"venue"
},
  "geometry": {"coordinates":[7.4633398056,51.3720588684],"type":"Point"}
}