{
  "type": "Feature",
  "properties": {
    "iso:country":"DE",
    "sg:address":"Ritterstr. 11",
    "sg:city":"Neugersdorf",
    "sg:phone":"+49 3586/702435",
    "sg:postcode":"02727",
    "sg:province":"Sachsen",
    "wof:name":"Maler Und Ger\u00fcstbau Gmbh",
    "wof:placetype":"venue"
},
  "geometry": {"coordinates":[14.6103401184,50.9846916199],"type":"Point"}
}