{
  "type": "Feature",
  "properties": {
    "iso:country":"DE",
    "sg:address":"Kirchstr. 16",
    "sg:city":"Lauf",
    "sg:phone":"+49 7841/21438",
    "sg:postcode":"77886",
    "sg:province":"Baden-W\u00fcrttemberg",
    "wof:name":"Helmut B\u00e4uerle",
    "wof:placetype":"venue"
},
  "geometry": {"coordinates":[8.129409,48.6465],"type":"Point"}
}