{
  "type": "Feature",
  "properties": {
    "iso:country":"DE",
    "sg:address":"Rimparer Steig 1",
    "sg:city":"W\u00fcrzburg",
    "sg:phone":"+49 931/22777",
    "sg:postcode":"97080",
    "sg:province":"Bayern",
    "wof:name":"Werner Z\u00fcrn",
    "wof:placetype":"venue"
},
  "geometry": {"coordinates":[9.9407634735,49.8043060303],"type":"Point"}
}