{
  "type": "Feature",
  "properties": {
    "iso:country":"DE",
    "sg:address":"Lebacher Str. 102",
    "sg:city":"Heusweiler",
    "sg:phone":"+49 6806/8781",
    "sg:postcode":"66265",
    "sg:province":"Saarland",
    "wof:name":"Nuba - Handelsgesellschaft Mbh",
    "wof:placetype":"venue"
},
  "geometry": {"coordinates":[6.9322490692,49.3686790466],"type":"Point"}
}