{
  "type": "Feature",
  "properties": {
    "iso:country":"DE",
    "sg:address":"Berliner Str. 53",
    "sg:city":"Hennigsdorf",
    "sg:phone":"+49 3302/802032",
    "sg:postcode":"16761",
    "sg:province":"Brandenburg",
    "wof:name":"M. Herzog",
    "wof:placetype":"venue"
},
  "geometry": {"coordinates":[13.20803,52.639919],"type":"Point"}
}