{
  "type": "Feature",
  "properties": {
    "iso:country":"DE",
    "sg:address":"Fl\u00fcggenstr.",
    "sg:city":"M\u00fcnchen",
    "sg:postcode":"80639",
    "sg:province":"Bayern",
    "wof:name":"Helios Immobilien Service Gmbh",
    "wof:placetype":"venue"
},
  "geometry": {"coordinates":[11.5222702026,48.1551895142],"type":"Point"}
}