{
  "type": "Feature",
  "properties": {
    "iso:country":"DE",
    "sg:address":"Gewerbegebiet",
    "sg:city":"Niederau",
    "sg:phone":"+49 3521/74630",
    "sg:postcode":"01689",
    "sg:province":"Sachsen",
    "wof:name":"Der Schaff Gro\u00dfhandels Gmbh",
    "wof:placetype":"venue"
},
  "geometry": {"coordinates":[13.5059280396,51.1900634766],"type":"Point"}
}