{
  "type": "Feature",
  "properties": {
    "iso:country":"DE",
    "sg:address":"Kornblumenstr. 2",
    "sg:city":"Rheinstetten",
    "sg:phone":"+49 7242/952466",
    "sg:postcode":"76287",
    "sg:province":"Baden-W\u00fcrttemberg",
    "wof:name":"Willi Tritsch",
    "wof:placetype":"venue"
},
  "geometry": {"coordinates":[8.30202,48.961983],"type":"Point"}
}