{
  "type": "Feature",
  "properties": {
    "iso:country":"DE",
    "sg:address":"Colmantstr. 47",
    "sg:city":"Bonn",
    "sg:phone":"+49 228/983800",
    "sg:postcode":"53115",
    "sg:province":"Nordrhein-Westfalen",
    "wof:name":"Hotel Esplanade",
    "wof:placetype":"venue"
},
  "geometry": {"coordinates":[7.0915250778,50.7311630249],"type":"Point"}
}