{
  "type": "Feature",
  "properties": {
    "iso:country":"DE",
    "sg:address":"Rochlitzer Str. 17",
    "sg:city":"Mittweida",
    "sg:phone":"+49 3727/2573",
    "sg:postcode":"09648",
    "sg:province":"Sachsen",
    "wof:name":"Rossmann Drogeriemarkt",
    "wof:placetype":"venue"
},
  "geometry": {"coordinates":[12.978906,50.985912],"type":"Point"}
}