{
  "type": "Feature",
  "properties": {
    "iso:country":"DE",
    "sg:address":"Lindenstr. 2",
    "sg:city":"Thammenhain",
    "sg:phone":"+49 34262/61356",
    "sg:postcode":"04808",
    "sg:province":"Sachsen",
    "wof:name":"Lindengasthof Tammenhain",
    "wof:placetype":"venue"
},
  "geometry": {"coordinates":[12.8617696762,51.4208564758],"type":"Point"}
}