{
  "type": "Feature",
  "properties": {
    "iso:country":"DE",
    "sg:address":"Am Taschinger Berg 11",
    "sg:city":"Cham",
    "sg:phone":"+49 9971/89160",
    "sg:postcode":"93413",
    "sg:province":"Bayern",
    "wof:name":"Ostbayern Furnier Gmbh",
    "wof:placetype":"venue"
},
  "geometry": {"coordinates":[12.661497,49.198071],"type":"Point"}
}