{
  "type": "Feature",
  "properties": {
    "iso:country":"DE",
    "sg:address":"Linker Kreuthweg 9",
    "sg:city":"Affing",
    "sg:phone":"+49 8207/96110",
    "sg:postcode":"86444",
    "sg:province":"Bayern",
    "wof:name":"Ibexnet Ag",
    "wof:placetype":"venue"
},
  "geometry": {"coordinates":[10.9266109467,48.4380455017],"type":"Point"}
}