{
  "type": "Feature",
  "properties": {
    "iso:country":"DE",
    "sg:address":"Friedhofstr. 4",
    "sg:city":"Goldbach",
    "sg:phone":"+49 36255/80505",
    "sg:postcode":"99869",
    "sg:province":"Th\u00fcringen",
    "wof:name":"H. Kreibe",
    "wof:placetype":"venue"
},
  "geometry": {"coordinates":[10.6565999985,50.9911384583],"type":"Point"}
}