{
  "type": "Feature",
  "properties": {
    "iso:country":"DE",
    "sg:address":"Klosterweg 3",
    "sg:city":"Rosendahl",
    "sg:phone":"+49 2547/7105",
    "sg:postcode":"48720",
    "sg:province":"Nordrhein-Westfalen",
    "wof:name":"Hermann Merschformann",
    "wof:placetype":"venue"
},
  "geometry": {"coordinates":[7.231764,52.021061],"type":"Point"}
}