{
  "type": "Feature",
  "properties": {
    "iso:country":"DE",
    "sg:address":"Eiselenweg 11",
    "sg:city":"Langenhagen",
    "sg:postcode":"30851",
    "sg:province":"Niedersachsen",
    "wof:name":"Frobel Beteiligungs- Gmbh",
    "wof:placetype":"venue"
},
  "geometry": {"coordinates":[9.7339229584,52.4299697876],"type":"Point"}
}