{
  "type": "Feature",
  "properties": {
    "iso:country":"DE",
    "sg:address":"Neubertstr. 21",
    "sg:city":"Dresden",
    "sg:phone":"+49 351/440860",
    "sg:postcode":"01307",
    "sg:province":"Sachsen",
    "wof:name":"Ingenieurb\u00fcro M\u00fcller-marl Gmbh",
    "wof:placetype":"venue"
},
  "geometry": {"coordinates":[13.7741031647,51.0587005615],"type":"Point"}
}