{
  "type": "Feature",
  "properties": {
    "iso:country":"DE",
    "sg:address":"M\u00fchldorfer Str. 14 a",
    "sg:city":"Alt\u00f6tting",
    "sg:postcode":"84503",
    "sg:province":"Bayern",
    "wof:name":"Z. S. Zukunft Und Sicherheit Finanz Gmbh",
    "wof:placetype":"venue"
},
  "geometry": {"coordinates":[12.6726989746,48.2268486023],"type":"Point"}
}