{
  "type": "Feature",
  "properties": {
    "iso:country":"DE",
    "sg:address":"Kaiserstr. 13",
    "sg:city":"Vienenburg",
    "sg:phone":"+49 5324/2241",
    "sg:postcode":"38690",
    "sg:province":"Niedersachsen",
    "wof:name":"Alte Apotheke Wolfgang Jaeger",
    "wof:placetype":"venue"
},
  "geometry": {"coordinates":[10.564103,51.952679],"type":"Point"}
}