{
  "type": "Feature",
  "properties": {
    "iso:country":"DE",
    "sg:address":"Hugo-von-K\u00f6nigsegg-Str. 16",
    "sg:city":"Oberstaufen",
    "sg:phone":"+49 8386/7262",
    "sg:postcode":"87534",
    "sg:province":"Bayern",
    "wof:name":"Cafe Venezia",
    "wof:placetype":"venue"
},
  "geometry": {"coordinates":[10.019538,47.554321],"type":"Point"}
}