{
  "type": "Feature",
  "properties": {
    "iso:country":"DE",
    "sg:address":"Rudolf-Breitscheid-Str. 14 a",
    "sg:city":"Wedel",
    "sg:phone":"+49 4103/918531",
    "sg:postcode":"22880",
    "sg:province":"Schleswig-Holstein",
    "wof:name":"Eigenheim Wohnungsgenossenschaft Eg",
    "wof:placetype":"venue"
},
  "geometry": {"coordinates":[9.7126197815,53.5800590515],"type":"Point"}
}