{
  "type": "Feature",
  "properties": {
    "iso:country":"DE",
    "sg:address":"Guntersdorfer Str. 21",
    "sg:city":"Herborn",
    "sg:phone":"+49 2772/55226",
    "sg:postcode":"35745",
    "sg:province":"Hessen",
    "wof:name":"Albert Ihrig",
    "wof:placetype":"venue"
},
  "geometry": {"coordinates":[8.2670249939,50.6654510498],"type":"Point"}
}