{
  "type": "Feature",
  "properties": {
    "iso:country":"DE",
    "sg:address":"Am B\u00f6delein 16",
    "sg:city":"N\u00fcdlingen",
    "sg:phone":"+49 971/63816",
    "sg:postcode":"97720",
    "sg:province":"Bayern",
    "wof:name":"Alexander Hofmann",
    "wof:placetype":"venue"
},
  "geometry": {"coordinates":[10.12733078,50.2258300781],"type":"Point"}
}