{
  "type": "Feature",
  "properties": {
    "iso:country":"DE",
    "sg:address":"Waldweg 3",
    "sg:city":"Ludwigslust",
    "sg:phone":"+49 3874/23349",
    "sg:postcode":"19288",
    "sg:province":"Mecklenburg-Vorpommern",
    "wof:name":"Kluth Transport Gmbh & Co. Kg",
    "wof:placetype":"venue"
},
  "geometry": {"coordinates":[11.4994802475,53.3131103516],"type":"Point"}
}