{
  "type": "Feature",
  "properties": {
    "iso:country":"DE",
    "sg:address":"Schweinfurter Str. 31",
    "sg:city":"Schwarzach",
    "sg:phone":"+49 9324/99798",
    "sg:postcode":"97359",
    "sg:province":"Bayern",
    "wof:name":"Zum Benediktiner Hotel-restaurant",
    "wof:placetype":"venue"
},
  "geometry": {"coordinates":[10.2295284271,49.8051643372],"type":"Point"}
}