{
  "type": "Feature",
  "properties": {
    "iso:country":"DE",
    "sg:address":"Wilhelm-Busch-Str. 7",
    "sg:city":"Eschborn",
    "sg:phone":"+49 6196/42626",
    "sg:postcode":"65760",
    "sg:province":"Hessen",
    "wof:name":"Heinrich Ilkenhans",
    "wof:placetype":"venue"
},
  "geometry": {"coordinates":[8.5671443939,50.1467285156],"type":"Point"}
}