{
  "type": "Feature",
  "properties": {
    "iso:country":"DE",
    "sg:address":"Kamper Weg 149",
    "sg:city":"D\u00fcsseldorf",
    "sg:phone":"+49 211/279969",
    "sg:postcode":"40627",
    "sg:province":"Nordrhein-Westfalen",
    "wof:name":"Anne Silke Busche",
    "wof:placetype":"venue"
},
  "geometry": {"coordinates":[6.8578910828,51.2098655701],"type":"Point"}
}