{
  "type": "Feature",
  "properties": {
    "iso:country":"DE",
    "sg:address":"Britzer Damm 110",
    "sg:city":"Berlin",
    "sg:phone":"+49 30/6066877",
    "sg:postcode":"12347",
    "sg:province":"Berlin",
    "wof:name":"Eisen-d\u00f6ring",
    "wof:placetype":"venue"
},
  "geometry": {"coordinates":[13.4381380081,52.4532966614],"type":"Point"}
}