{
  "type": "Feature",
  "properties": {
    "iso:country":"DE",
    "sg:address":"Schulstr. 6a",
    "sg:city":"Pfaffen-Schwabenheim",
    "sg:phone":"+49 6701/2918",
    "sg:postcode":"55546",
    "sg:province":"Rheinland-Pfalz",
    "wof:name":"R. Mayer",
    "wof:placetype":"venue"
},
  "geometry": {"coordinates":[7.9534778595,49.8483657837],"type":"Point"}
}