{
  "type": "Feature",
  "properties": {
    "iso:country":"DE",
    "sg:address":"Mardorfer Str. 5",
    "sg:city":"Neustadt",
    "sg:phone":"+49 5036/438",
    "sg:postcode":"31535",
    "sg:province":"Niedersachsen",
    "wof:name":"B. Lohrer",
    "wof:placetype":"venue"
},
  "geometry": {"coordinates":[9.289412,52.489498],"type":"Point"}
}