{
  "type": "Feature",
  "properties": {
    "iso:country":"DE",
    "sg:address":"Murkenbachweg 48",
    "sg:city":"B\u00f6blingen",
    "sg:phone":"+49 7031/272463",
    "sg:postcode":"71032",
    "sg:province":"Baden-W\u00fcrttemberg",
    "wof:name":"Walz",
    "wof:placetype":"venue"
},
  "geometry": {"coordinates":[9.032125,48.676548],"type":"Point"}
}