{
  "type": "Feature",
  "properties": {
    "iso:country":"DE",
    "sg:address":"Industriestr. 6",
    "sg:city":"Kissing",
    "sg:phone":"+49 8233/8075",
    "sg:postcode":"86438",
    "sg:province":"Bayern",
    "wof:name":"Franz V\u00f6tter",
    "wof:placetype":"venue"
},
  "geometry": {"coordinates":[10.963653,48.298996],"type":"Point"}
}