{
  "type": "Feature",
  "properties": {
    "iso:country":"DE",
    "sg:address":"Vogt-Bornkast-Weg 12a",
    "sg:city":"Hamburg",
    "sg:postcode":"22457",
    "sg:province":"Hamburg",
    "wof:name":"Edcori Ag",
    "wof:placetype":"venue"
},
  "geometry": {"coordinates":[9.8917808533,53.6275978088],"type":"Point"}
}