{
  "type": "Feature",
  "properties": {
    "iso:country":"DE",
    "sg:address":"Kirchplatz 22e",
    "sg:city":"Belzig",
    "sg:postcode":"14806",
    "sg:province":"Brandenburg",
    "wof:name":"Fashion Pool Gmbh",
    "wof:placetype":"venue"
},
  "geometry": {"coordinates":[12.5881996155,52.1417198181],"type":"Point"}
}