{
  "type": "Feature",
  "properties": {
    "iso:country":"DE",
    "sg:address":"H\u00fcttweg 3",
    "sg:city":"Gelsenkirchen",
    "sg:phone":"+49 209/83320",
    "sg:postcode":"45881",
    "sg:province":"Nordrhein-Westfalen",
    "wof:name":"Richard Krause",
    "wof:placetype":"venue"
},
  "geometry": {"coordinates":[7.102621,51.523174],"type":"Point"}
}