{
  "type": "Feature",
  "properties": {
    "iso:country":"DE",
    "sg:address":"Altonaer Str. 28",
    "sg:city":"Erfurt",
    "sg:phone":"+49 361/5623159",
    "sg:postcode":"99085",
    "sg:province":"Th\u00fcringen",
    "wof:name":"Erfurter Maler Und Service Gmbh",
    "wof:placetype":"venue"
},
  "geometry": {"coordinates":[11.042655,50.98354],"type":"Point"}
}