{
  "type": "Feature",
  "properties": {
    "iso:country":"DE",
    "sg:address":"L\u00e4rchenstr. 2",
    "sg:city":"Hannover",
    "sg:phone":"+49 511/344837",
    "sg:postcode":"30161",
    "sg:province":"Niedersachsen",
    "wof:name":"Au Camenbert Alberts Weinbistro",
    "wof:placetype":"venue"
},
  "geometry": {"coordinates":[9.7543201447,52.3804664612],"type":"Point"}
}