{
  "type": "Feature",
  "properties": {
    "iso:country":"DE",
    "sg:address":"Robert-Koch-Str. 87 /1",
    "sg:city":"Ostfildern",
    "sg:phone":"+49 711/3430023",
    "sg:postcode":"73760",
    "sg:province":"Baden-W\u00fcrttemberg",
    "wof:name":"Ergotherapiepraxis Hammer",
    "wof:placetype":"venue"
},
  "geometry": {"coordinates":[9.272212,48.726227],"type":"Point"}
}