{
  "type": "Feature",
  "properties": {
    "iso:country":"DE",
    "sg:address":"Lindenwiese 10",
    "sg:city":"Hirzenhain",
    "sg:phone":"+49 6045/7796",
    "sg:postcode":"63697",
    "sg:province":"Hessen",
    "wof:name":"S. Sever",
    "wof:placetype":"venue"
},
  "geometry": {"coordinates":[9.159168,50.399445],"type":"Point"}
}