{
  "type": "Feature",
  "properties": {
    "iso:country":"DE",
    "sg:address":"Nikolausdorfer Str. 34",
    "sg:city":"Garrel",
    "sg:phone":"+49 4474/8524",
    "sg:postcode":"49681",
    "sg:province":"Niedersachsen",
    "wof:name":"D. Otten Hochbau Gmbh",
    "wof:placetype":"venue"
},
  "geometry": {"coordinates":[8.0557594299,52.9728736877],"type":"Point"}
}