{
  "type": "Feature",
  "properties": {
    "iso:country":"DE",
    "sg:address":"An der Unterm\u00fchle 5",
    "sg:city":"Grevenbroich",
    "sg:phone":"+49 2181/74372",
    "sg:postcode":"41516",
    "sg:province":"Nordrhein-Westfalen",
    "wof:name":"Baumax",
    "wof:placetype":"venue"
},
  "geometry": {"coordinates":[6.6258969307,51.112613678],"type":"Point"}
}