{
  "type": "Feature",
  "properties": {
    "iso:country":"DE",
    "sg:address":"Am Hintzenb\u00f6hl 46",
    "sg:city":"Bad Kreuznach",
    "sg:phone":"+49 671/76663",
    "sg:postcode":"55545",
    "sg:province":"Rheinland-Pfalz",
    "wof:name":"Berni Immig",
    "wof:placetype":"venue"
},
  "geometry": {"coordinates":[7.9081411362,49.8572654724],"type":"Point"}
}