{
  "type": "Feature",
  "properties": {
    "iso:country":"DE",
    "sg:address":"Hegerm\u00fchlenstr. 2",
    "sg:city":"Strausberg",
    "sg:phone":"+49 3341/311876",
    "sg:postcode":"15344",
    "sg:province":"Brandenburg",
    "wof:name":"R\u00fcdiger Naehring",
    "wof:placetype":"venue"
},
  "geometry": {"coordinates":[13.883121,52.575413],"type":"Point"}
}