{
  "type": "Feature",
  "properties": {
    "iso:country":"DE",
    "sg:address":"Gehlenbrink 54",
    "sg:city":"Spenge",
    "sg:phone":"+49 5225/2057",
    "sg:postcode":"32139",
    "sg:province":"Nordrhein-Westfalen",
    "wof:name":"H. Diekmann",
    "wof:placetype":"venue"
},
  "geometry": {"coordinates":[8.510989,52.16441],"type":"Point"}
}