{
  "type": "Feature",
  "properties": {
    "iso:country":"DE",
    "sg:address":"Grabenweg 1",
    "sg:city":"Wadern",
    "sg:phone":"+49 6871/1017",
    "sg:postcode":"66687",
    "sg:province":"Saarland",
    "wof:name":"Franz-josef Wagner",
    "wof:placetype":"venue"
},
  "geometry": {"coordinates":[6.8708977699,49.5088195801],"type":"Point"}
}