{
  "type": "Feature",
  "properties": {
    "iso:country":"DE",
    "sg:address":"Am Weinberg 12",
    "sg:city":"Bergen",
    "sg:phone":"+49 5051/3901",
    "sg:postcode":"29303",
    "sg:province":"Niedersachsen",
    "wof:name":"Chinarestaurant Peking",
    "wof:placetype":"venue"
},
  "geometry": {"coordinates":[9.9621667862,52.8117713928],"type":"Point"}
}