{
  "type": "Feature",
  "properties": {
    "iso:country":"DE",
    "sg:address":"Hamfehrer Weg 6",
    "sg:city":"Bremen",
    "sg:postcode":"28779",
    "sg:province":"Bremen",
    "wof:name":"Mbb B\u00fcy\u00fckbudak Baugesch\u00e4ft Gmbh",
    "wof:placetype":"venue"
},
  "geometry": {"coordinates":[8.5678853989,53.1967926025],"type":"Point"}
}