{
  "type": "Feature",
  "properties": {
    "iso:country":"DE",
    "sg:address":"G\u00e4ldrichweg 26",
    "sg:city":"Ravensburg",
    "sg:phone":"+49 751/32432",
    "sg:postcode":"88214",
    "sg:province":"Baden-W\u00fcrttemberg",
    "wof:name":"W. M\u00fcller",
    "wof:placetype":"venue"
},
  "geometry": {"coordinates":[9.6063623428,47.7662620544],"type":"Point"}
}