{
  "type": "Feature",
  "properties": {
    "iso:country":"DE",
    "sg:address":"Oststr. 11",
    "sg:city":"Oberstdorf",
    "sg:phone":"+49 8322/4661",
    "sg:postcode":"87561",
    "sg:province":"Bayern",
    "wof:name":"Ernst Kluger Modehaus Kg",
    "wof:placetype":"venue"
},
  "geometry": {"coordinates":[10.2805833817,47.406337738],"type":"Point"}
}