{
  "type": "Feature",
  "properties": {
    "iso:country":"DE",
    "sg:address":"Erich-Weinert-Str. 17 b",
    "sg:city":"F\u00fcrstenwalde",
    "sg:postcode":"15517",
    "sg:province":"Brandenburg",
    "wof:name":"Michael Uhlmann",
    "wof:placetype":"venue"
},
  "geometry": {"coordinates":[14.0543651581,52.355266571],"type":"Point"}
}