{
  "type": "Feature",
  "properties": {
    "iso:country":"DE",
    "sg:address":"Mittelstr. 10",
    "sg:city":"H\u00f6hr-Grenzhausen",
    "sg:phone":"+49 2624/6852",
    "sg:postcode":"56203",
    "sg:province":"Rheinland-Pfalz",
    "wof:name":"Hoffmann",
    "wof:placetype":"venue"
},
  "geometry": {"coordinates":[7.6729698181,50.4327507019],"type":"Point"}
}