{
  "type": "Feature",
  "properties": {
    "iso:country":"DE",
    "sg:address":"Berliner Str. 74",
    "sg:city":"Potsdam",
    "sg:phone":"+49 331/23060",
    "sg:postcode":"14467",
    "sg:province":"Brandenburg",
    "wof:name":"Rs Reengineering Softwaredesign Ag",
    "wof:placetype":"venue"
},
  "geometry": {"coordinates":[13.0854091644,52.412071228],"type":"Point"}
}