{
  "type": "Feature",
  "properties": {
    "iso:country":"DE",
    "sg:address":"Brienner Str. 7",
    "sg:city":"M\u00fcnchen",
    "sg:phone":"+49 89/294766",
    "sg:postcode":"80333",
    "sg:province":"Bayern",
    "wof:name":"Informationszentrale Der Bayerischen Wirtschaft",
    "wof:placetype":"venue"
},
  "geometry": {"coordinates":[11.5757379532,48.1428794861],"type":"Point"}
}