{
  "type": "Feature",
  "properties": {
    "iso:country":"DE",
    "sg:address":"Clemensstr. 77",
    "sg:city":"M\u00fcnchen",
    "sg:phone":"+49 89/304867",
    "sg:postcode":"80796",
    "sg:province":"Bayern",
    "wof:name":"Hermann Fauser",
    "wof:placetype":"venue"
},
  "geometry": {"coordinates":[11.572526,48.163586],"type":"Point"}
}