{
  "type": "Feature",
  "properties": {
    "iso:country":"DE",
    "sg:address":"Friedrich-Verleger-Str. 15",
    "sg:city":"Bielefeld",
    "sg:phone":"+49 521/170757",
    "sg:postcode":"33602",
    "sg:province":"Nordrhein-Westfalen",
    "wof:name":"Schulze",
    "wof:placetype":"venue"
},
  "geometry": {"coordinates":[8.53835392,52.0235595703],"type":"Point"}
}