{
  "type": "Feature",
  "properties": {
    "iso:country":"DE",
    "sg:address":"Heiligenseestr. 55",
    "sg:city":"Berlin",
    "sg:postcode":"13503",
    "sg:province":"Berlin",
    "wof:name":"Amolago Immobilien Gmbh",
    "wof:placetype":"venue"
},
  "geometry": {"coordinates":[13.238997,52.602383],"type":"Point"}
}