{
  "type": "Feature",
  "properties": {
    "iso:country":"DE",
    "sg:address":"Rotterter\u00f6der Str. 9",
    "sg:city":"Kirchheim",
    "sg:phone":"+49 6625/5611",
    "sg:postcode":"36275",
    "sg:province":"Hessen",
    "wof:name":"Otto Dostler Bau- Und Sanierungsarbeiten",
    "wof:placetype":"venue"
},
  "geometry": {"coordinates":[9.575173378,50.837688446],"type":"Point"}
}