{
  "type": "Feature",
  "properties": {
    "iso:country":"DE",
    "sg:address":"Gottschedstr.9",
    "sg:city":"Leipzig",
    "sg:phone":"+49 341/9602881",
    "sg:postcode":"04109",
    "sg:province":"Sachsen",
    "wof:name":"Disko-,deko-,spezial-,faserlichtdisko-wolf-leipzi",
    "wof:placetype":"venue"
},
  "geometry": {"coordinates":[12.369027,51.340263],"type":"Point"}
}