{
  "type": "Feature",
  "properties": {
    "iso:country":"DE",
    "sg:address":"Raiffeisenstr. 12",
    "sg:city":"Dormitz",
    "sg:phone":"+49 9134/1557",
    "sg:postcode":"91077",
    "sg:province":"Bayern",
    "wof:name":"Herbert Kreppel",
    "wof:placetype":"venue"
},
  "geometry": {"coordinates":[11.118117,49.595924],"type":"Point"}
}