{
  "type": "Feature",
  "properties": {
    "iso:country":"DE",
    "sg:address":"Straubinger Str. 17",
    "sg:city":"Laberweinting",
    "sg:phone":"+49 8772/473",
    "sg:postcode":"84082",
    "sg:province":"Bayern",
    "wof:name":"Gastst\u00e4tte Medard Zierer",
    "wof:placetype":"venue"
},
  "geometry": {"coordinates":[12.3217248917,48.7966384888],"type":"Point"}
}