{
  "type": "Feature",
  "properties": {
    "iso:country":"DE",
    "sg:address":"Starkholzbach 21",
    "sg:city":"Schw\u00e4bisch Hall",
    "sg:phone":"+49 791/89327",
    "sg:postcode":"74523",
    "sg:province":"Baden-W\u00fcrttemberg",
    "wof:name":"H.-j. Deck",
    "wof:placetype":"venue"
},
  "geometry": {"coordinates":[9.6641178131,49.0850715637],"type":"Point"}
}