{
  "type": "Feature",
  "properties": {
    "iso:country":"DE",
    "sg:address":"Schnutenhausstra\u00dfe 44",
    "sg:city":"Essen",
    "sg:postcode":"45136",
    "sg:province":"Nordrhein-Westfalen",
    "wof:name":"Institut Ranke-heinemann",
    "wof:placetype":"venue"
},
  "geometry": {"coordinates":[7.023775,51.440819],"type":"Point"}
}