{
  "type": "Feature",
  "properties": {
    "iso:country":"DE",
    "sg:address":"Scheffelstr. 5",
    "sg:city":"L\u00f6ffingen",
    "sg:phone":"+49 7654/585",
    "sg:postcode":"79843",
    "sg:province":"Baden-W\u00fcrttemberg",
    "wof:name":"C. Allinger",
    "wof:placetype":"venue"
},
  "geometry": {"coordinates":[8.342768,47.879711],"type":"Point"}
}