{
  "type": "Feature",
  "properties": {
    "iso:country":"DE",
    "sg:address":"Alt Hausen 25",
    "sg:city":"Frankfurt",
    "sg:phone":"+49 69/7894004",
    "sg:postcode":"60488",
    "sg:province":"Hessen",
    "wof:name":"Cts-color Transfer Service Gmbh",
    "wof:placetype":"venue"
},
  "geometry": {"coordinates":[8.625135,50.133308],"type":"Point"}
}