{
  "type": "Feature",
  "properties": {
    "iso:country":"DE",
    "sg:address":"Freitagsgasse 13",
    "sg:city":"Sinsheim",
    "sg:phone":"+49 7261/64902",
    "sg:postcode":"74889",
    "sg:province":"Baden-W\u00fcrttemberg",
    "wof:name":"Subita",
    "wof:placetype":"venue"
},
  "geometry": {"coordinates":[8.8794,49.251968],"type":"Point"}
}