{
  "type": "Feature",
  "properties": {
    "iso:country":"DE",
    "sg:address":"Glehner Weg 2",
    "sg:city":"Neuss",
    "sg:phone":"+49 2131/897365",
    "sg:postcode":"41464",
    "sg:province":"Nordrhein-Westfalen",
    "wof:name":"Shakespeare",
    "wof:placetype":"venue"
},
  "geometry": {"coordinates":[6.6735739708,51.1980400085],"type":"Point"}
}