{
  "type": "Feature",
  "properties": {
    "iso:country":"DE",
    "sg:address":"Hauptstr. 24",
    "sg:city":"Kassow",
    "sg:phone":"+49 38453/20431",
    "sg:postcode":"18258",
    "sg:province":"Mecklenburg-Vorpommern",
    "wof:name":"Gastst\u00e4tte Marions Gaststube",
    "wof:placetype":"venue"
},
  "geometry": {"coordinates":[12.0745916367,53.8789825439],"type":"Point"}
}