{
  "type": "Feature",
  "properties": {
    "iso:country":"DE",
    "sg:address":"Kaufbeurer Str. 32",
    "sg:city":"Pforzen",
    "sg:phone":"+49 8346/330",
    "sg:postcode":"87666",
    "sg:province":"Bayern",
    "wof:name":"Molkereigenossenschaft Georg Rampp",
    "wof:placetype":"venue"
},
  "geometry": {"coordinates":[10.6132211685,47.9261779785],"type":"Point"}
}