{
  "type": "Feature",
  "properties": {
    "iso:country":"DE",
    "sg:address":"Bodenburger Str. 55",
    "sg:city":"Bad Salzdetfurth",
    "sg:phone":"+49 5063/2573",
    "sg:postcode":"31162",
    "sg:province":"Niedersachsen",
    "wof:name":"Aral-tankstelle",
    "wof:placetype":"venue"
},
  "geometry": {"coordinates":[10.0023841858,52.0534858704],"type":"Point"}
}