{
  "type": "Feature",
  "properties": {
    "iso:country":"DE",
    "sg:address":"Engelbosteler Str. 23",
    "sg:city":"Garbsen",
    "sg:phone":"+49 5131/8024",
    "sg:postcode":"30827",
    "sg:province":"Niedersachsen",
    "wof:name":"Hartmut Uelschen",
    "wof:placetype":"venue"
},
  "geometry": {"coordinates":[9.627698,52.448357],"type":"Point"}
}