{
  "type": "Feature",
  "properties": {
    "iso:country":"DE",
    "sg:address":"Lahnhofstr. 14",
    "sg:city":"Netphen",
    "sg:phone":"+49 2737/91072",
    "sg:postcode":"57250",
    "sg:province":"Nordrhein-Westfalen",
    "wof:name":"Franz-josef Steiner",
    "wof:placetype":"venue"
},
  "geometry": {"coordinates":[8.2244234085,50.870475769],"type":"Point"}
}