{
  "type": "Feature",
  "properties": {
    "iso:country":"DE",
    "sg:address":"Postfach 20",
    "sg:city":"Neckartenzlingen",
    "sg:postcode":"72650",
    "sg:province":"Baden-W\u00fcrttemberg",
    "wof:name":"Melchior Festhalle Neckartenzlingen",
    "wof:placetype":"venue"
},
  "geometry": {"coordinates":[9.238285,48.589951],"type":"Point"}
}