{
  "type": "Feature",
  "properties": {
    "iso:country":"DE",
    "sg:address":"Neue Dorfstr. 9",
    "sg:city":"Gr\u00f6st",
    "sg:phone":"+49 34633/22878",
    "sg:postcode":"06632",
    "sg:province":"Sachsen-Anhalt",
    "wof:name":"B. Th\u00fcrkind",
    "wof:placetype":"venue"
},
  "geometry": {"coordinates":[11.8470067978,51.2597045898],"type":"Point"}
}