{
  "type": "Feature",
  "properties": {
    "iso:country":"DE",
    "sg:address":"Hirtenstr. 1",
    "sg:city":"Oberhausen",
    "sg:phone":"+49 208/632863",
    "sg:postcode":"46145",
    "sg:province":"Nordrhein-Westfalen",
    "wof:name":"Walter Straube",
    "wof:placetype":"venue"
},
  "geometry": {"coordinates":[6.859687,51.518143],"type":"Point"}
}