{
  "type": "Feature",
  "properties": {
    "iso:country":"DE",
    "sg:address":"Hallesche Str. 35",
    "sg:city":"Saarbr\u00fccken",
    "sg:phone":"+49 681/812744",
    "sg:postcode":"66121",
    "sg:province":"Saarland",
    "wof:name":"Ev. Pfarramt Eschberg",
    "wof:placetype":"venue"
},
  "geometry": {"coordinates":[7.0411877632,49.2349777222],"type":"Point"}
}