{
  "type": "Feature",
  "properties": {
    "iso:country":"DE",
    "sg:address":"Mittlere Bergstr.",
    "sg:city":"Radebeul",
    "sg:phone":"+49 351/8955140",
    "sg:postcode":"01445",
    "sg:province":"Sachsen",
    "wof:name":"S\u00c4chsisches Staatsweingut Gmbh",
    "wof:placetype":"venue"
},
  "geometry": {"coordinates":[13.602979,51.121868],"type":"Point"}
}