{
  "type": "Feature",
  "properties": {
    "iso:country":"DE",
    "sg:address":"Sch\u00f6nhagener Str. 10A",
    "sg:city":"Bredenbek",
    "sg:phone":"+49 4334/183707",
    "sg:postcode":"24796",
    "sg:province":"Schleswig-Holstein",
    "wof:name":"Birgit Schr\u00f6der Rechtsanw\u00e4ltin",
    "wof:placetype":"venue"
},
  "geometry": {"coordinates":[9.8597993851,54.3107032776],"type":"Point"}
}