{
  "type": "Feature",
  "properties": {
    "iso:country":"DE",
    "sg:address":"Jahnstr. 5",
    "sg:city":"Beckum",
    "sg:phone":"+49 2525/3780",
    "sg:postcode":"59269",
    "sg:province":"Nordrhein-Westfalen",
    "wof:name":"Hotel Rainer Kempe",
    "wof:placetype":"venue"
},
  "geometry": {"coordinates":[8.0268039703,51.7956314087],"type":"Point"}
}