{
  "type": "Feature",
  "properties": {
    "iso:country":"DE",
    "sg:address":"Waltersweierweg 3",
    "sg:city":"Offenburg",
    "sg:phone":"+49 781/22020",
    "sg:postcode":"77652",
    "sg:province":"Baden-W\u00fcrttemberg",
    "wof:name":"Link & Cie. Gmbh",
    "wof:placetype":"venue"
},
  "geometry": {"coordinates":[7.9334430695,48.4783363342],"type":"Point"}
}