{
  "type": "Feature",
  "properties": {
    "iso:country":"DE",
    "sg:address":"Sebastianusstr. 13",
    "sg:city":"Neuss",
    "sg:phone":"+49 2131/25500",
    "sg:postcode":"41460",
    "sg:province":"Nordrhein-Westfalen",
    "wof:name":"C. Pieper",
    "wof:placetype":"venue"
},
  "geometry": {"coordinates":[6.689135,51.198502],"type":"Point"}
}