{
  "type": "Feature",
  "properties": {
    "iso:country":"DE",
    "sg:address":"Welschstr. 43",
    "sg:city":"Waldfischbach-Burgalben",
    "sg:phone":"+49 6333/5746",
    "sg:postcode":"67714",
    "sg:province":"Rheinland-Pfalz",
    "wof:name":"G\u00fcnther Schmidt",
    "wof:placetype":"venue"
},
  "geometry": {"coordinates":[7.660795,49.286278],"type":"Point"}
}