{
  "type": "Feature",
  "properties": {
    "iso:country":"DE",
    "sg:address":"Werkstr. 4",
    "sg:city":"Schwerin",
    "sg:postcode":"19061",
    "sg:province":"Mecklenburg-Vorpommern",
    "wof:name":"L & M B\u00fcroinformations- Systeme Gmbh",
    "wof:placetype":"venue"
},
  "geometry": {"coordinates":[11.388049,53.571602],"type":"Point"}
}