{
  "type": "Feature",
  "properties": {
    "iso:country":"DE",
    "sg:city":"Gerolsbach",
    "sg:phone":"+49 8445/341",
    "sg:postcode":"85302",
    "sg:province":"Bayern",
    "wof:name":"Raiffeisenbank Schrobenhausen Eg",
    "wof:placetype":"venue"
},
  "geometry": {"coordinates":[11.360908,48.494263],"type":"Point"}
}