{
  "type": "Feature",
  "properties": {
    "iso:country":"DE",
    "sg:address":"Merkenicher Str 95",
    "sg:city":"K\u00f6ln",
    "sg:phone":"+49 8392/924240",
    "sg:postcode":"50735",
    "sg:province":"Nordrhein-Westfalen",
    "wof:name":"Notz Gmbh",
    "wof:placetype":"venue"
},
  "geometry": {"coordinates":[10.395265,47.946983],"type":"Point"}
}