{
  "type": "Feature",
  "properties": {
    "iso:country":"DE",
    "sg:address":"Hauptstr. 7",
    "sg:city":"Asbach-B\u00e4umenheim",
    "sg:phone":"+49 906/9810",
    "sg:postcode":"86663",
    "sg:province":"Bayern",
    "wof:name":"Xaver Fendt Gmbh & Co.",
    "wof:placetype":"venue"
},
  "geometry": {"coordinates":[10.812123,48.681538],"type":"Point"}
}