{
  "type": "Feature",
  "properties": {
    "iso:country":"DE",
    "sg:address":"Hannastr. 19",
    "sg:city":"Bremerhaven",
    "sg:phone":"+49 471/43155",
    "sg:postcode":"27568",
    "sg:province":"Bremen",
    "wof:name":"H. Und C. Maybauer",
    "wof:placetype":"venue"
},
  "geometry": {"coordinates":[8.576469,53.549545],"type":"Point"}
}