{
  "type": "Feature",
  "properties": {
    "iso:country":"DE",
    "sg:address":"Dorfstra\u00dfe 28",
    "sg:city":"Itzehoe",
    "sg:phone":"+49 4821/13530",
    "sg:postcode":"25524",
    "sg:province":"Schleswig-Holstein",
    "wof:name":"Borba",
    "wof:placetype":"venue"
},
  "geometry": {"coordinates":[9.4989728928,53.9280166626],"type":"Point"}
}