{
  "type": "Feature",
  "properties": {
    "iso:country":"DE",
    "sg:address":"Siemensstr. 46",
    "sg:city":"Ditzingen",
    "sg:phone":"+49 7156/95240",
    "sg:postcode":"71254",
    "sg:province":"Baden-W\u00fcrttemberg",
    "wof:name":"Intermetric Gesellschaft F\u00fcr Ingenieurmessung Und Raum-",
    "wof:placetype":"venue"
},
  "geometry": {"coordinates":[9.0647926331,48.8218193054],"type":"Point"}
}