{
  "type": "Feature",
  "properties": {
    "iso:country":"DE",
    "sg:address":"Pr\u00e4mienstr. 29",
    "sg:city":"Aachen",
    "sg:phone":"+49 2408/80141",
    "sg:postcode":"52076",
    "sg:province":"Nordrhein-Westfalen",
    "wof:name":"Wilms & Brenner Inh. Margot Brenner",
    "wof:placetype":"venue"
},
  "geometry": {"coordinates":[6.179669857,50.7055854797],"type":"Point"}
}