{
  "type": "Feature",
  "properties": {
    "iso:country":"DE",
    "sg:address":"Adenauerallee 75",
    "sg:city":"Bocholt",
    "sg:phone":"+49 2871/272420",
    "sg:postcode":"46399",
    "sg:province":"Nordrhein-Westfalen",
    "wof:name":"J. Arenhoevel Steuerberater",
    "wof:placetype":"venue"
},
  "geometry": {"coordinates":[6.6164741516,51.8489646912],"type":"Point"}
}