{
  "type": "Feature",
  "properties": {
    "iso:country":"DE",
    "sg:address":"Pallasstr. 82",
    "sg:city":"Castrop-Rauxel",
    "sg:phone":"+49 4923/0513417",
    "sg:postcode":"44575",
    "sg:province":"Nordrhein-Westfalen",
    "wof:name":"M\u00d6belspedition Hubert L\u00d6hr Zweigniederlassung M\u00d6belspedition",
    "wof:placetype":"venue"
},
  "geometry": {"coordinates":[7.311357975,51.5582885742],"type":"Point"}
}