{
  "type": "Feature",
  "properties": {
    "iso:country":"DE",
    "sg:address":"Feldstr. 18",
    "sg:city":"Hildesheim",
    "sg:phone":"+49 5121/809090",
    "sg:postcode":"31141",
    "sg:province":"Niedersachsen",
    "wof:name":"Thurau-beste Verwaltungs- Gmbh",
    "wof:placetype":"venue"
},
  "geometry": {"coordinates":[9.9633722305,52.1437683105],"type":"Point"}
}