{
  "type": "Feature",
  "properties": {
    "iso:country":"DE",
    "sg:address":"Handwerkerstr. 9",
    "sg:city":"Sennfeld",
    "sg:phone":"+49 9721/77200",
    "sg:postcode":"97526",
    "sg:province":"Bayern",
    "wof:name":"Rpm Recycling Plastic Materie Gmbh",
    "wof:placetype":"venue"
},
  "geometry": {"coordinates":[10.2585754395,50.0327758789],"type":"Point"}
}