{
  "type": "Feature",
  "properties": {
    "iso:country":"DE",
    "sg:address":"Hust\u00e4dter Str. 15",
    "sg:city":"Bad Essen",
    "sg:phone":"+49 5472/2094",
    "sg:postcode":"49152",
    "sg:province":"Niedersachsen",
    "wof:name":"Lothar We\u00dfler",
    "wof:placetype":"venue"
},
  "geometry": {"coordinates":[8.3679866791,52.3008995056],"type":"Point"}
}