{
  "type": "Feature",
  "properties": {
    "iso:country":"DE",
    "sg:address":"Brunnenstr. 32",
    "sg:city":"Schwerin",
    "sg:phone":"+49 385/660096",
    "sg:postcode":"19053",
    "sg:province":"Mecklenburg-Vorpommern",
    "wof:name":"Sbw Aus- Und Fortbildungsges. F\u00fcr Wirtschaft Und",
    "wof:placetype":"venue"
},
  "geometry": {"coordinates":[11.4013004303,53.6221694946],"type":"Point"}
}