{
  "type": "Feature",
  "properties": {
    "iso:country":"DE",
    "sg:address":"Ro\u00dfmarkt",
    "sg:city":"M\u00fcnchen",
    "sg:phone":"+49 89/7460855",
    "sg:postcode":"80331",
    "sg:province":"Bayern",
    "wof:name":"Fragiacomo & Co. Gmbh",
    "wof:placetype":"venue"
},
  "geometry": {"coordinates":[11.5691251755,48.13306427],"type":"Point"}
}