{
  "type": "Feature",
  "properties": {
    "iso:country":"DE",
    "sg:address":"Flottenstr. 7 -9",
    "sg:city":"Berlin",
    "sg:phone":"+49 30/351820",
    "sg:postcode":"13407",
    "sg:province":"Berlin",
    "wof:name":"Alba Holding Ag",
    "wof:placetype":"venue"
},
  "geometry": {"coordinates":[13.349947,52.578426],"type":"Point"}
}