{
  "type": "Feature",
  "properties": {
    "iso:country":"DE",
    "sg:address":"Torstr. 12",
    "sg:city":"Elbingerode",
    "sg:postcode":"38875",
    "sg:province":"Sachsen-Anhalt",
    "wof:name":"Ruth Schneider",
    "wof:placetype":"venue"
},
  "geometry": {"coordinates":[10.803096,51.767815],"type":"Point"}
}