{
  "type": "Feature",
  "properties": {
    "iso:country":"DE",
    "sg:address":"Ginsterstr. 9",
    "sg:city":"Molbergen",
    "sg:phone":"+49 4475/947780",
    "sg:postcode":"49696",
    "sg:province":"Niedersachsen",
    "wof:name":"Herbert Burke",
    "wof:placetype":"venue"
},
  "geometry": {"coordinates":[7.9291930199,52.8608016968],"type":"Point"}
}