{
  "type": "Feature",
  "properties": {
    "iso:country":"DE",
    "sg:address":"Lange Str. 14",
    "sg:city":"Wunstorf",
    "sg:phone":"+49 5031/12448",
    "sg:postcode":"31515",
    "sg:province":"Niedersachsen",
    "wof:name":"Lichthaus Rehkopf Inh. Michael Schaer",
    "wof:placetype":"venue"
},
  "geometry": {"coordinates":[9.427347,52.426041],"type":"Point"}
}