{
  "type": "Feature",
  "properties": {
    "iso:country":"DE",
    "sg:address":"B\u00fchlweg 69",
    "sg:city":"Waiblingen",
    "sg:phone":"+49 7151/81039",
    "sg:postcode":"71336",
    "sg:province":"Baden-W\u00fcrttemberg",
    "wof:name":"Blasenbrey Gmbh Reifenreinigungsger\u00e4te",
    "wof:placetype":"venue"
},
  "geometry": {"coordinates":[9.3293504715,48.8489723206],"type":"Point"}
}