{
  "type": "Feature",
  "properties": {
    "iso:country":"DE",
    "sg:address":"Hauptstr. 20A",
    "sg:city":"Plotitz",
    "sg:phone":"+49 35268/82254",
    "sg:postcode":"01594",
    "sg:province":"Sachsen",
    "wof:name":"Atomvet - Ta Georgi Gmbh",
    "wof:placetype":"venue"
},
  "geometry": {"coordinates":[13.243546,51.257912],"type":"Point"}
}