{
  "type": "Feature",
  "properties": {
    "iso:country":"DE",
    "sg:address":"Albert-Schweitzer-Str. 1",
    "sg:city":"H\u00f6chberg",
    "sg:phone":"+49 931/48899",
    "sg:postcode":"97204",
    "sg:province":"Bayern",
    "wof:name":"Tierklinik Krafzel Gmbh",
    "wof:placetype":"venue"
},
  "geometry": {"coordinates":[9.8847494125,49.788608551],"type":"Point"}
}