{
  "type": "Feature",
  "properties": {
    "iso:country":"DE",
    "sg:address":"Alt-Haarener Str. 249",
    "sg:city":"Aachen",
    "sg:phone":"+49 241/164506",
    "sg:postcode":"52080",
    "sg:province":"Nordrhein-Westfalen",
    "wof:name":"Bauernstube",
    "wof:placetype":"venue"
},
  "geometry": {"coordinates":[6.1304821968,50.800453186],"type":"Point"}
}