{
  "type": "Feature",
  "properties": {
    "iso:country":"DE",
    "sg:address":"Rahlstedter Str. 51d",
    "sg:city":"Hamburg",
    "sg:phone":"+49 40",
    "sg:postcode":"22149",
    "sg:province":"Hamburg",
    "wof:name":"Domaincrack Domains Zu Vermieten Verkaufen Suchen",
    "wof:placetype":"venue"
},
  "geometry": {"coordinates":[10.147316,53.595383],"type":"Point"}
}