{
  "type": "Feature",
  "properties": {
    "iso:country":"DE",
    "sg:address":"Karmeliterweg 9",
    "sg:city":"Berlin",
    "sg:phone":"+49 30/4017394",
    "sg:postcode":"13465",
    "sg:province":"Berlin",
    "wof:name":"Karin Engelhardt Steuerberaterin",
    "wof:placetype":"venue"
},
  "geometry": {"coordinates":[13.2879838943,52.6310119629],"type":"Point"}
}