{
  "type": "Feature",
  "properties": {
    "iso:country":"DE",
    "sg:address":"Bockenheimer Landstr. 101",
    "sg:city":"Frankfurt",
    "sg:phone":"+49 69/6000",
    "sg:postcode":"60325",
    "sg:province":"Hessen",
    "wof:name":"Ehg Elektroholding Gmbh",
    "wof:placetype":"venue"
},
  "geometry": {"coordinates":[8.6569957733,50.1195831299],"type":"Point"}
}