{
  "type": "Feature",
  "properties": {
    "iso:country":"DE",
    "sg:address":"Berliner Str. 157",
    "sg:city":"Gera",
    "sg:phone":"+49 365/4390046",
    "sg:postcode":"07546",
    "sg:province":"Th\u00fcringen",
    "wof:name":"Apfelbaum Gera",
    "wof:placetype":"venue"
},
  "geometry": {"coordinates":[12.0769309998,50.896156311],"type":"Point"}
}