{
  "type": "Feature",
  "properties": {
    "iso:country":"DE",
    "sg:address":"Mittelst\u00fcck 2",
    "sg:city":"Selbach",
    "sg:phone":"+49 2742/3201",
    "sg:postcode":"57537",
    "sg:province":"Rheinland-Pfalz",
    "wof:name":"Gregor Kl\u00f6ckner Gmbh",
    "wof:placetype":"venue"
},
  "geometry": {"coordinates":[7.768264,50.743183],"type":"Point"}
}