{
  "type": "Feature",
  "properties": {
    "iso:country":"DE",
    "sg:address":"Fischerhofstr. 1",
    "sg:city":"Uelzen",
    "sg:phone":"+49 581/5312",
    "sg:postcode":"29525",
    "sg:province":"Niedersachsen",
    "wof:name":"Jugendherberge Uelzen",
    "wof:placetype":"venue"
},
  "geometry": {"coordinates":[10.5469331741,52.9861221313],"type":"Point"}
}