{
  "type": "Feature",
  "properties": {
    "iso:country":"DE",
    "sg:address":"Konrad-Adenauer-Str. 11",
    "sg:city":"Ingelheim",
    "sg:phone":"+49 6132/43060",
    "sg:postcode":"55218",
    "sg:province":"Rheinland-Pfalz",
    "wof:name":"Weil Baumschulen Inh. Werner Weil",
    "wof:placetype":"venue"
},
  "geometry": {"coordinates":[8.054755,49.977516],"type":"Point"}
}