{
  "type": "Feature",
  "properties": {
    "iso:country":"DE",
    "sg:address":"M\u00fcnchener Str. 67",
    "sg:city":"Freilassing",
    "sg:phone":"+49 8654/608624",
    "sg:postcode":"83395",
    "sg:province":"Bayern",
    "wof:name":"Global-trade Handels Gmbh",
    "wof:placetype":"venue"
},
  "geometry": {"coordinates":[12.9694690704,47.8431777954],"type":"Point"}
}