{
  "type": "Feature",
  "properties": {
    "iso:country":"DE",
    "sg:address":"Wittlingstr. 16",
    "sg:city":"Bremerhaven",
    "sg:phone":"+49 4947/197370",
    "sg:postcode":"27572",
    "sg:province":"Bremen",
    "wof:name":"Bab Systems Gmbh & Co. Kg",
    "wof:placetype":"venue"
},
  "geometry": {"coordinates":[8.583155632,53.5158004761],"type":"Point"}
}