{
  "type": "Feature",
  "properties": {
    "iso:country":"DE",
    "sg:address":"Oberamteistr. 12",
    "sg:city":"K\u00fcnzelsau",
    "sg:phone":"+49 7940/6163",
    "sg:postcode":"74653",
    "sg:province":"Baden-W\u00fcrttemberg",
    "wof:name":"Karin M\u00f6ller Masseurin",
    "wof:placetype":"venue"
},
  "geometry": {"coordinates":[9.687737,49.278728],"type":"Point"}
}