{
  "type": "Feature",
  "properties": {
    "iso:country":"DE",
    "sg:address":"Neuffenstr. 84",
    "sg:city":"Wendlingen",
    "sg:phone":"+49 7024/923450",
    "sg:postcode":"73240",
    "sg:province":"Baden-W\u00fcrttemberg",
    "wof:name":"Bischoff Gmbh",
    "wof:placetype":"venue"
},
  "geometry": {"coordinates":[9.385641098,48.6695137024],"type":"Point"}
}