{
  "type": "Feature",
  "properties": {
    "iso:country":"DE",
    "sg:address":"Uhlandstr. 45",
    "sg:city":"M\u00fclheim",
    "sg:phone":"+49 208/479601",
    "sg:postcode":"45468",
    "sg:province":"Nordrhein-Westfalen",
    "wof:name":"Studio M.",
    "wof:placetype":"venue"
},
  "geometry": {"coordinates":[6.890661,51.433929],"type":"Point"}
}