{
  "type": "Feature",
  "properties": {
    "iso:country":"DE",
    "sg:address":"Dieselstr. 19b",
    "sg:city":"Dinslaken",
    "sg:phone":"+49 2064/49760",
    "sg:postcode":"46539",
    "sg:province":"Nordrhein-Westfalen",
    "wof:name":"Sako Maschinen-handels Gmbh",
    "wof:placetype":"venue"
},
  "geometry": {"coordinates":[6.797033,51.563805],"type":"Point"}
}