{
  "type": "Feature",
  "properties": {
    "iso:country":"DE",
    "sg:address":"Frosch\u00e4ckerweg 1",
    "sg:city":"Heidelberg",
    "sg:phone":"+49 6221/439347",
    "sg:postcode":"69121",
    "sg:province":"Baden-W\u00fcrttemberg",
    "wof:name":"H. Hohlwegler Ingenieur",
    "wof:placetype":"venue"
},
  "geometry": {"coordinates":[8.6835594177,49.4253959656],"type":"Point"}
}