{
  "type": "Feature",
  "properties": {
    "iso:country":"DE",
    "sg:address":"Brachvogelweg 27",
    "sg:city":"Oldenburg",
    "sg:phone":"+49 441/41084",
    "sg:postcode":"26133",
    "sg:province":"Niedersachsen",
    "wof:name":"Hotel Ingeborg",
    "wof:placetype":"venue"
},
  "geometry": {"coordinates":[8.234128952,53.119884491],"type":"Point"}
}