{
  "type": "Feature",
  "properties": {
    "iso:country":"DE",
    "sg:address":"Karl-Harre-Str. 1",
    "sg:city":"Bad Oeynhausen",
    "sg:phone":"+49 5731/4280",
    "sg:postcode":"32549",
    "sg:province":"Nordrhein-Westfalen",
    "wof:name":"W. Bastemeyer Radio Fernsehen",
    "wof:placetype":"venue"
},
  "geometry": {"coordinates":[8.7794809341,52.2146492004],"type":"Point"}
}