{
  "type": "Feature",
  "properties": {
    "iso:country":"DE",
    "sg:address":"Am Kurpark 26",
    "sg:city":"Bernau",
    "sg:phone":"+49 7675/365",
    "sg:postcode":"79872",
    "sg:province":"Baden-W\u00fcrttemberg",
    "wof:name":"Pension Schwarzwaldhaus",
    "wof:placetype":"venue"
},
  "geometry": {"coordinates":[8.0375642776,47.7998352051],"type":"Point"}
}