{
  "type": "Feature",
  "properties": {
    "iso:country":"DE",
    "sg:address":"Eilenburger Str. 57",
    "sg:city":"Delitzsch",
    "sg:phone":"+49 34202/53495",
    "sg:postcode":"04509",
    "sg:province":"Sachsen",
    "wof:name":"Siegismund Ryl",
    "wof:placetype":"venue"
},
  "geometry": {"coordinates":[12.342318,51.524643],"type":"Point"}
}