{
  "type": "Feature",
  "properties": {
    "iso:country":"DE",
    "sg:address":"Saarstr. 15",
    "sg:city":"Erlangen",
    "sg:phone":"+49 9131/32283",
    "sg:postcode":"91052",
    "sg:province":"Bayern",
    "wof:name":"Burkhart Eugen Rechtsanwalt",
    "wof:placetype":"venue"
},
  "geometry": {"coordinates":[11.0155315399,49.5852928162],"type":"Point"}
}