{
  "type": "Feature",
  "properties": {
    "iso:country":"DE",
    "sg:address":"Stellfelder Str. 1",
    "sg:city":"Wolfsburg",
    "sg:phone":"+49 5361/3010",
    "sg:postcode":"38442",
    "sg:province":"Niedersachsen",
    "wof:name":"Logis Ges. F\u00fcr Logistische Informationssysteme Mbh",
    "wof:placetype":"venue"
},
  "geometry": {"coordinates":[10.7574510574,52.4291801453],"type":"Point"}
}