{
  "type": "Feature",
  "properties": {
    "iso:country":"DE",
    "sg:address":"Am Altenhof 17",
    "sg:city":"Kaiserslautern",
    "sg:phone":"+49 631/696901",
    "sg:postcode":"67655",
    "sg:province":"Rheinland-Pfalz",
    "wof:name":"Otto Fenster Gmbh",
    "wof:placetype":"venue"
},
  "geometry": {"coordinates":[7.768142,49.443817],"type":"Point"}
}