{
  "type": "Feature",
  "properties": {
    "iso:country":"DE",
    "sg:address":"Bottroper Str. 28",
    "sg:city":"Gladbeck",
    "sg:phone":"+49 2043/68550",
    "sg:postcode":"45964",
    "sg:province":"Nordrhein-Westfalen",
    "wof:name":"Bhw Bausparkasse Ag",
    "wof:placetype":"venue"
},
  "geometry": {"coordinates":[6.985735,51.572655],"type":"Point"}
}