{
  "type": "Feature",
  "properties": {
    "iso:country":"DE",
    "sg:address":"Brabanter Str. 37-41",
    "sg:city":"K\u00f6ln",
    "sg:phone":"+49 221/9515190",
    "sg:postcode":"50672",
    "sg:province":"Nordrhein-Westfalen",
    "wof:name":"Tbs Ton- Und Bild- Service Gmbh",
    "wof:placetype":"venue"
},
  "geometry": {"coordinates":[6.9374279976,50.9391822815],"type":"Point"}
}