{
  "type": "Feature",
  "properties": {
    "iso:country":"DE",
    "sg:address":"Kellergasse 29",
    "sg:city":"Ebersdorf",
    "sg:phone":"+49 9562/1505",
    "sg:postcode":"96237",
    "sg:province":"Bayern",
    "wof:name":"Bernd Franzkowiak",
    "wof:placetype":"venue"
},
  "geometry": {"coordinates":[11.0886421204,50.213306427],"type":"Point"}
}