{
  "type": "Feature",
  "properties": {
    "iso:country":"DE",
    "sg:address":"Conradiplatz 7",
    "sg:city":"Je\u00dfnitz",
    "sg:phone":"+49 3494/27341",
    "sg:postcode":"06800",
    "sg:province":"Sachsen-Anhalt",
    "wof:name":"Je\u00dfnitzer Wohnungs Gmbh",
    "wof:placetype":"venue"
},
  "geometry": {"coordinates":[12.3027381897,51.6838722229],"type":"Point"}
}