{
  "type": "Feature",
  "properties": {
    "iso:country":"DE",
    "sg:address":"Fred-Joachim-Schoeps-Str 55",
    "sg:city":"Mannheim",
    "sg:phone":"+49 621/473107",
    "sg:postcode":"68229",
    "sg:province":"Baden-W\u00fcrttemberg",
    "wof:name":"Tb Portillo Gmbh",
    "wof:placetype":"venue"
},
  "geometry": {"coordinates":[8.575340271,49.4402618408],"type":"Point"}
}