{
  "type": "Feature",
  "properties": {
    "iso:country":"DE",
    "sg:address":"Lange Gasse 11",
    "sg:city":"Meinhard",
    "sg:phone":"+49 5651/3495",
    "sg:postcode":"37276",
    "sg:province":"Hessen",
    "wof:name":"Gr\u00fcner Baum",
    "wof:placetype":"venue"
},
  "geometry": {"coordinates":[10.1028051376,51.1950340271],"type":"Point"}
}