{
  "type": "Feature",
  "properties": {
    "iso:country":"DE",
    "sg:address":"Hauptstr. 51",
    "sg:city":"Osterspai",
    "sg:phone":"+49 2627/401",
    "sg:postcode":"56340",
    "sg:province":"Rheinland-Pfalz",
    "wof:name":"Kurt Gr\u00f6ger",
    "wof:placetype":"venue"
},
  "geometry": {"coordinates":[7.6146559715,50.2457466125],"type":"Point"}
}