{
  "type": "Feature",
  "properties": {
    "iso:country":"DE",
    "sg:address":"Hauptstr.",
    "sg:city":"Dallmin",
    "sg:postcode":"19357",
    "sg:province":"Brandenburg",
    "wof:name":"R. Stielow",
    "wof:placetype":"venue"
},
  "geometry": {"coordinates":[11.771,53.201359],"type":"Point"}
}