{
  "type": "Feature",
  "properties": {
    "iso:country":"DE",
    "sg:address":"Bockstalstr. 10 a",
    "sg:city":"Pfinztal",
    "sg:phone":"+49 7240/1502",
    "sg:postcode":"76327",
    "sg:province":"Baden-W\u00fcrttemberg",
    "wof:name":"Bockstal-apotheke",
    "wof:placetype":"venue"
},
  "geometry": {"coordinates":[8.552226,48.966419],"type":"Point"}
}