{
  "type": "Feature",
  "properties": {
    "iso:country":"DE",
    "sg:address":"Ludwig-Roselius-Allee 7",
    "sg:city":"Bremen",
    "sg:phone":"+49 421/464673",
    "sg:postcode":"28329",
    "sg:province":"Bremen",
    "wof:name":"S\u00f6rgel Sport Und Freizeit Gmbh",
    "wof:placetype":"venue"
},
  "geometry": {"coordinates":[8.89136,53.071491],"type":"Point"}
}