{
  "type": "Feature",
  "properties": {
    "iso:country":"DE",
    "sg:address":"Schulstr. 1",
    "sg:city":"Sch\u00f6nteichen",
    "sg:phone":"+49 35783/15595",
    "sg:postcode":"01920",
    "sg:province":"Sachsen",
    "wof:name":"Otto Trept",
    "wof:placetype":"venue"
},
  "geometry": {"coordinates":[14.132213,51.220978],"type":"Point"}
}