{
  "type": "Feature",
  "properties": {
    "iso:country":"DE",
    "sg:address":"Auf den K\u00f6ven 12",
    "sg:city":"Lamstedt",
    "sg:phone":"+49 4773/7444",
    "sg:postcode":"21769",
    "sg:province":"Niedersachsen",
    "wof:name":"G\u00fcnther Bergner Masseur",
    "wof:placetype":"venue"
},
  "geometry": {"coordinates":[9.09481,53.639702],"type":"Point"}
}