{
  "type": "Feature",
  "properties": {
    "iso:country":"DE",
    "sg:address":"Bahnhofstr. 25",
    "sg:city":"Mommenheim",
    "sg:phone":"+49 6138/1317",
    "sg:postcode":"55278",
    "sg:province":"Rheinland-Pfalz",
    "wof:name":"K. Kessel",
    "wof:placetype":"venue"
},
  "geometry": {"coordinates":[8.2741861343,49.8847503662],"type":"Point"}
}