{
  "type": "Feature",
  "properties": {
    "iso:country":"DE",
    "sg:address":"Steinstr. 11",
    "sg:city":"Idar-Oberstein",
    "sg:phone":"+49 6781/25239",
    "sg:postcode":"55743",
    "sg:province":"Rheinland-Pfalz",
    "wof:name":"Otto Lang",
    "wof:placetype":"venue"
},
  "geometry": {"coordinates":[7.326072216,49.6976165771],"type":"Point"}
}