{
  "type": "Feature",
  "properties": {
    "iso:country":"DE",
    "sg:address":"Zur Bockhorst 56",
    "sg:city":"Beckeln",
    "sg:phone":"+49 4244/7967",
    "sg:postcode":"27243",
    "sg:province":"Niedersachsen",
    "wof:name":"Asendorf Tiefbau Gmbh",
    "wof:placetype":"venue"
},
  "geometry": {"coordinates":[8.5701408386,52.8496665955],"type":"Point"}
}