{
  "type": "Feature",
  "properties": {
    "iso:country":"DE",
    "sg:address":"Am Umspannwerk",
    "sg:city":"Streumen",
    "sg:postcode":"01609",
    "sg:province":"Sachsen",
    "wof:name":"Wedel Transport Rohstoffhandels Kg",
    "wof:placetype":"venue"
},
  "geometry": {"coordinates":[13.4317684174,51.3949737549],"type":"Point"}
}