{
  "type": "Feature",
  "properties": {
    "iso:country":"DE",
    "sg:address":"Hauptstr. 87",
    "sg:city":"Nickenich",
    "sg:phone":"+49 2632/81558",
    "sg:postcode":"56645",
    "sg:province":"Rheinland-Pfalz",
    "wof:name":"Marion Betzing",
    "wof:placetype":"venue"
},
  "geometry": {"coordinates":[7.325574,50.413292],"type":"Point"}
}