{
  "type": "Feature",
  "properties": {
    "iso:country":"DE",
    "sg:address":"Querweingasse 2",
    "sg:city":"Rotenburg",
    "sg:phone":"+49 6623/2295",
    "sg:postcode":"36199",
    "sg:province":"Hessen",
    "wof:name":"Hans Metz Inh. Heinrich Metz",
    "wof:placetype":"venue"
},
  "geometry": {"coordinates":[9.725497,50.995823],"type":"Point"}
}