{
  "type": "Feature",
  "properties": {
    "iso:country":"DE",
    "sg:address":"Lockhofstr. 2b",
    "sg:city":"Gelsenkirchen",
    "sg:phone":"+49 209/48131",
    "sg:postcode":"45881",
    "sg:province":"Nordrhein-Westfalen",
    "wof:name":"E. Und F. J. L\u00fcke Gmbh",
    "wof:placetype":"venue"
},
  "geometry": {"coordinates":[7.072573185,51.5195999146],"type":"Point"}
}