{
  "type": "Feature",
  "properties": {
    "iso:country":"DE",
    "sg:address":"Am Verladebahnhof 4",
    "sg:city":"Mitterteich",
    "sg:postcode":"95666",
    "sg:province":"Bayern",
    "wof:name":"G. H. N. Gesch\u00e4fts- F\u00fchrungs Gmbh",
    "wof:placetype":"venue"
},
  "geometry": {"coordinates":[12.2488145828,49.9541168213],"type":"Point"}
}