{
  "type": "Feature",
  "properties": {
    "iso:country":"DE",
    "sg:address":"Igelbachstr. 7",
    "sg:city":"Gernsbach",
    "sg:phone":"+49 7224/50222",
    "sg:postcode":"76593",
    "sg:province":"Baden-W\u00fcrttemberg",
    "wof:name":"Lbs Baden-w\u00fcrttemberg Beratungsstelle",
    "wof:placetype":"venue"
},
  "geometry": {"coordinates":[8.337827,48.763062],"type":"Point"}
}