{
  "type": "Feature",
  "properties": {
    "iso:country":"DE",
    "sg:address":"Auf den Mehren 45",
    "sg:city":"Achim",
    "sg:phone":"+49 4202/2010",
    "sg:postcode":"28832",
    "sg:province":"Niedersachsen",
    "wof:name":"Achimer Funk-taxen",
    "wof:placetype":"venue"
},
  "geometry": {"coordinates":[9.003108,53.020775],"type":"Point"}
}