{
  "type": "Feature",
  "properties": {
    "iso:country":"DE",
    "sg:address":"Graseckstr. 41/2",
    "sg:city":"Kochel",
    "sg:phone":"+49 8851/5268",
    "sg:postcode":"82431",
    "sg:province":"Bayern",
    "wof:name":"Adolf Habla",
    "wof:placetype":"venue"
},
  "geometry": {"coordinates":[11.362578392,47.6511726379],"type":"Point"}
}