{
  "type": "Feature",
  "properties": {
    "iso:country":"DE",
    "sg:address":"Boelckestr. 144",
    "sg:city":"Mainz-Kastel",
    "sg:phone":"+49 6134/62104",
    "sg:postcode":"55252",
    "sg:province":"Hessen",
    "wof:name":"Heinrich Block Inh. Marg. Gehm",
    "wof:placetype":"venue"
},
  "geometry": {"coordinates":[8.291068,50.025459],"type":"Point"}
}