{
  "type": "Feature",
  "properties": {
    "iso:country":"DE",
    "sg:address":"Industriestr. 22",
    "sg:city":"G\u00f6ttingen",
    "sg:phone":"+49 551/631686",
    "sg:postcode":"37079",
    "sg:province":"Niedersachsen",
    "wof:name":"Dietlind Jeck",
    "wof:placetype":"venue"
},
  "geometry": {"coordinates":[9.9033298492,51.5415687561],"type":"Point"}
}