{
  "type": "Feature",
  "properties": {
    "iso:country":"DE",
    "sg:address":"Ringstr. 66",
    "sg:city":"Neuwied",
    "sg:phone":"+49 2631/22016",
    "sg:postcode":"56564",
    "sg:province":"Rheinland-Pfalz",
    "wof:name":"Kochh\u00e4user-immobilien Gmbh",
    "wof:placetype":"venue"
},
  "geometry": {"coordinates":[7.47303,50.435745],"type":"Point"}
}