{
  "type": "Feature",
  "properties": {
    "iso:country":"DE",
    "sg:address":"Friedrich-Naumann-Str. 37",
    "sg:city":"Zerbst",
    "sg:postcode":"39261",
    "sg:province":"Sachsen-Anhalt",
    "wof:name":"Katholisches Pfarramt Zerbst",
    "wof:placetype":"venue"
},
  "geometry": {"coordinates":[12.0935153961,51.9621887207],"type":"Point"}
}