{
  "type": "Feature",
  "properties": {
    "iso:country":"DE",
    "sg:address":"Lindenh\u00f6he 12",
    "sg:city":"Jena",
    "sg:phone":"+49 3641/331278",
    "sg:postcode":"07749",
    "sg:province":"Th\u00fcringen",
    "wof:name":"Dr. G\u00fcnter M\u00fcller Tierarzt",
    "wof:placetype":"venue"
},
  "geometry": {"coordinates":[11.5928277969,50.9194984436],"type":"Point"}
}