{
  "type": "Feature",
  "properties": {
    "iso:country":"DE",
    "sg:address":"Telbrake 15",
    "sg:city":"Vechta",
    "sg:phone":"+49 4441/3756",
    "sg:postcode":"49377",
    "sg:province":"Niedersachsen",
    "wof:name":"Franz Seelhorst",
    "wof:placetype":"venue"
},
  "geometry": {"coordinates":[8.314527,52.736721],"type":"Point"}
}