{
  "type": "Feature",
  "properties": {
    "iso:country":"DE",
    "sg:address":"Oststr. 5",
    "sg:city":"Oberstdorf",
    "sg:phone":"+49 8322/3158",
    "sg:postcode":"87561",
    "sg:province":"Bayern",
    "wof:name":"Bemeleit",
    "wof:placetype":"venue"
},
  "geometry": {"coordinates":[10.2796373367,47.4068641663],"type":"Point"}
}