{
  "type": "Feature",
  "properties": {
    "iso:country":"DE",
    "sg:address":"Goldstr. 15",
    "sg:city":"Quakenbr\u00fcck",
    "sg:phone":"+49 5431/3639",
    "sg:postcode":"49610",
    "sg:province":"Niedersachsen",
    "wof:name":"Gastst\u00e4tte Zum Rostigen Nagel",
    "wof:placetype":"venue"
},
  "geometry": {"coordinates":[7.9549322128,52.6766433716],"type":"Point"}
}