{
  "type": "Feature",
  "properties": {
    "iso:country":"DE",
    "sg:address":"B\u00e4rensprunger Str. 12",
    "sg:city":"Dannenwalde",
    "sg:phone":"+49 33975/50840",
    "sg:postcode":"16866",
    "sg:province":"Brandenburg",
    "wof:name":"Hans Wiese",
    "wof:placetype":"venue"
},
  "geometry": {"coordinates":[12.245085,53.020329],"type":"Point"}
}