{
  "type": "Feature",
  "properties": {
    "iso:country":"DE",
    "sg:address":"K\u00f6nigsteiner Str. 45",
    "sg:city":"Bad Soden",
    "sg:phone":"+49 172 6863374",
    "sg:postcode":"65812",
    "sg:province":"Hessen",
    "wof:name":"Georg Lauer Rechtsanwalt",
    "wof:placetype":"venue"
},
  "geometry": {"coordinates":[8.502913475,50.1424331665],"type":"Point"}
}