{
  "type": "Feature",
  "properties": {
    "iso:country":"DE",
    "sg:address":"Hallesche Str. 3",
    "sg:city":"Naumburg",
    "sg:postcode":"06618",
    "sg:province":"Sachsen-Anhalt",
    "wof:name":"Feierabendheim",
    "wof:placetype":"venue"
},
  "geometry": {"coordinates":[11.814499,51.156597],"type":"Point"}
}