{
  "type": "Feature",
  "properties": {
    "iso:country":"DE",
    "sg:address":"Robert-Koch-Str. 10",
    "sg:city":"Frechen",
    "sg:postcode":"50226",
    "sg:province":"Nordrhein-Westfalen",
    "wof:name":"Drokos Pharmazeutik Drogen-kosmetik Gmbh",
    "wof:placetype":"venue"
},
  "geometry": {"coordinates":[6.8093,50.910751],"type":"Point"}
}