{
  "type": "Feature",
  "properties": {
    "iso:country":"DE",
    "sg:address":"Am Solbad 7",
    "sg:city":"Herne",
    "sg:postcode":"44652",
    "sg:province":"Nordrhein-Westfalen",
    "wof:name":"Hallenbad",
    "wof:placetype":"venue"
},
  "geometry": {"coordinates":[7.1642417908,51.5244522095],"type":"Point"}
}