{
  "type": "Feature",
  "properties": {
    "iso:country":"DE",
    "sg:address":"Wei\u00dferlenstr. 13",
    "sg:city":"Freiburg",
    "sg:phone":"+49 761/152220",
    "sg:postcode":"79108",
    "sg:province":"Baden-W\u00fcrttemberg",
    "wof:name":"Hts Industrie Gmbh",
    "wof:placetype":"venue"
},
  "geometry": {"coordinates":[7.80996,48.040295],"type":"Point"}
}