{
  "type": "Feature",
  "properties": {
    "iso:country":"DE",
    "sg:address":"Fritz-Reuter-Str. 12",
    "sg:city":"Bad Oldesloe",
    "sg:phone":"+49 4531/82536",
    "sg:postcode":"23843",
    "sg:province":"Schleswig-Holstein",
    "wof:name":"Renate Struppek Masseurin",
    "wof:placetype":"venue"
},
  "geometry": {"coordinates":[10.358963,53.804798],"type":"Point"}
}