{
  "type": "Feature",
  "properties": {
    "iso:country":"DE",
    "sg:address":"Sonnenberger Str. 20",
    "sg:city":"Wiesbaden",
    "sg:phone":"+49 611/959720",
    "sg:postcode":"65193",
    "sg:province":"Hessen",
    "wof:name":"Samhall Rehab Gmbh",
    "wof:placetype":"venue"
},
  "geometry": {"coordinates":[8.248613,50.085609],"type":"Point"}
}