{
  "type": "Feature",
  "properties": {
    "iso:country":"DE",
    "sg:address":"Bergstr. 12",
    "sg:city":"Berlin",
    "sg:phone":"+49 30/7928981",
    "sg:postcode":"12169",
    "sg:province":"Berlin",
    "wof:name":"Janko Krickovic",
    "wof:placetype":"venue"
},
  "geometry": {"coordinates":[13.33091259,52.4580535889],"type":"Point"}
}