{
  "type": "Feature",
  "properties": {
    "iso:country":"DE",
    "sg:address":"Poststr. 6",
    "sg:city":"Krunkel",
    "sg:phone":"+49 2687/363",
    "sg:postcode":"56593",
    "sg:province":"Rheinland-Pfalz",
    "wof:name":"B. Leidig",
    "wof:placetype":"venue"
},
  "geometry": {"coordinates":[7.49355,50.579979],"type":"Point"}
}