{
  "type": "Feature",
  "properties": {
    "iso:country":"DE",
    "sg:address":"Johann-Wilhelm-Str. 51",
    "sg:city":"Wilhelmsfeld",
    "sg:phone":"+49 4968/945063",
    "sg:postcode":"69259",
    "sg:province":"Baden-W\u00fcrttemberg",
    "wof:name":"Obt Oberfl\u00c4chenbeschichtungstechnik Gmbh",
    "wof:placetype":"venue"
},
  "geometry": {"coordinates":[7.169968,49.285828],"type":"Point"}
}