{
  "type": "Feature",
  "properties": {
    "iso:country":"DE",
    "sg:address":"Osterholzer Landstr. 38",
    "sg:city":"Bremen",
    "sg:phone":"+49 421/420706",
    "sg:postcode":"28327",
    "sg:province":"Bremen",
    "wof:name":"Karl \u00d6streich",
    "wof:placetype":"venue"
},
  "geometry": {"coordinates":[8.9320316315,53.0638160706],"type":"Point"}
}