{
  "type": "Feature",
  "properties": {
    "iso:country":"DE",
    "sg:address":"Hahnenkammstr. 14",
    "sg:city":"Karlstein",
    "sg:phone":"+49 6188/5152",
    "sg:postcode":"63791",
    "sg:province":"Bayern",
    "wof:name":"Trageser Gmbh",
    "wof:placetype":"venue"
},
  "geometry": {"coordinates":[9.0364942551,50.040435791],"type":"Point"}
}