{
  "type": "Feature",
  "properties": {
    "iso:country":"DE",
    "sg:address":"Mohnweg 13",
    "sg:city":"Ehlscheid",
    "sg:phone":"+49 2634/1087",
    "sg:postcode":"56581",
    "sg:province":"Rheinland-Pfalz",
    "wof:name":"G\u00fcnter Sch\u00e4fer",
    "wof:placetype":"venue"
},
  "geometry": {"coordinates":[7.467897,50.517036],"type":"Point"}
}