{
  "type": "Feature",
  "properties": {
    "iso:country":"DE",
    "sg:address":"Hauptstr. 50",
    "sg:city":"K\u00f6nigsdorf",
    "sg:phone":"+49 8179/1887",
    "sg:postcode":"82549",
    "sg:province":"Bayern",
    "wof:name":"Markus Orterer",
    "wof:placetype":"venue"
},
  "geometry": {"coordinates":[11.4799079895,47.8147315979],"type":"Point"}
}