{
  "type": "Feature",
  "properties": {
    "iso:country":"DE",
    "sg:address":"Nienk\u00e4mpe 15",
    "sg:city":"Beckum",
    "sg:postcode":"59269",
    "sg:province":"Nordrhein-Westfalen",
    "wof:name":"Uwe D. Renner Architekt",
    "wof:placetype":"venue"
},
  "geometry": {"coordinates":[8.046078,51.80798],"type":"Point"}
}