{
  "type": "Feature",
  "properties": {
    "iso:country":"DE",
    "sg:address":"Hauptstr. 5",
    "sg:city":"Nohfelden",
    "sg:phone":"+49 6852/242",
    "sg:postcode":"66625",
    "sg:province":"Saarland",
    "wof:name":"Winfried Borgmann",
    "wof:placetype":"venue"
},
  "geometry": {"coordinates":[7.1428,49.587158],"type":"Point"}
}