{
  "type": "Feature",
  "properties": {
    "iso:country":"DE",
    "sg:address":"Friedrich-Ebert-Str. 14b",
    "sg:city":"Ebersbach",
    "sg:phone":"+49 3586/362652",
    "sg:postcode":"02730",
    "sg:province":"Sachsen",
    "wof:name":"R. Drei\u00dfig",
    "wof:placetype":"venue"
},
  "geometry": {"coordinates":[14.6086406708,50.9896278381],"type":"Point"}
}