{
  "type": "Feature",
  "properties": {
    "iso:country":"DE",
    "sg:address":"Franz-Mehring-Str. 5",
    "sg:city":"Potsdam",
    "sg:postcode":"14482",
    "sg:province":"Brandenburg",
    "wof:name":"Dr. Med. Doepner",
    "wof:placetype":"venue"
},
  "geometry": {"coordinates":[13.111802,52.39098],"type":"Point"}
}