{
  "type": "Feature",
  "properties": {
    "iso:country":"DE",
    "sg:address":"Breite Str. 15a",
    "sg:city":"Kl\u00f6tze",
    "sg:phone":"+49 3909/42525",
    "sg:postcode":"38486",
    "sg:province":"Sachsen-Anhalt",
    "wof:name":"D. Bode",
    "wof:placetype":"venue"
},
  "geometry": {"coordinates":[11.1654071808,52.6252441406],"type":"Point"}
}