{
  "type": "Feature",
  "properties": {
    "iso:country":"DE",
    "sg:address":"Hohentwielstr. 34",
    "sg:city":"Stuttgart",
    "sg:phone":"+49 711/6402578",
    "sg:postcode":"70199",
    "sg:province":"Baden-W\u00fcrttemberg",
    "wof:name":"Hans Heubeck Architekt",
    "wof:placetype":"venue"
},
  "geometry": {"coordinates":[9.154368,48.764004],"type":"Point"}
}