{
  "type": "Feature",
  "properties": {
    "iso:country":"DE",
    "sg:address":"Kappbergstr. 1",
    "sg:city":"Stadtbergen",
    "sg:postcode":"86391",
    "sg:province":"Bayern",
    "wof:name":"Ambiente Wohnbau Gmbh",
    "wof:placetype":"venue"
},
  "geometry": {"coordinates":[10.83392,48.356709],"type":"Point"}
}