{
  "type": "Feature",
  "properties": {
    "iso:country":"DE",
    "sg:address":"Tannenweg 10",
    "sg:city":"Dresden",
    "sg:postcode":"01257",
    "sg:province":"Sachsen",
    "wof:name":"Hwg Haus- Und Wohnungs- Bauges. Mbh",
    "wof:placetype":"venue"
},
  "geometry": {"coordinates":[13.806493,51.000683],"type":"Point"}
}