{
  "type": "Feature",
  "properties": {
    "iso:country":"DE",
    "sg:address":"Am Hain 10",
    "sg:city":"Neukirchen",
    "sg:phone":"+49 3762/3588",
    "sg:postcode":"08459",
    "sg:province":"Sachsen",
    "wof:name":"Brigitte K\u00fcchenreuther",
    "wof:placetype":"venue"
},
  "geometry": {"coordinates":[12.38667202,50.7888565063],"type":"Point"}
}