{
  "type": "Feature",
  "properties": {
    "iso:country":"DE",
    "sg:address":"Raiffeisenstr. 7",
    "sg:city":"Gernsheim",
    "sg:phone":"+49 4962/583433",
    "sg:postcode":"64579",
    "sg:province":"Hessen",
    "wof:name":"Raiffeisenbank Ried Eg",
    "wof:placetype":"venue"
},
  "geometry": {"coordinates":[8.52654,49.772213],"type":"Point"}
}