{
  "type": "Feature",
  "properties": {
    "iso:country":"DE",
    "sg:address":"Franziskusstr. 18",
    "sg:city":"H\u00f6sbach",
    "sg:phone":"+49 6021/66150",
    "sg:postcode":"63768",
    "sg:province":"Bayern",
    "wof:name":"Kraft-industriew\u00e4rmetechnik Dr. Ricke Gmbh",
    "wof:placetype":"venue"
},
  "geometry": {"coordinates":[9.2333450317,49.9863510132],"type":"Point"}
}