{
  "type": "Feature",
  "properties": {
    "iso:country":"DE",
    "sg:address":"Schlesienstr. 10",
    "sg:city":"Memmelsdorf",
    "sg:phone":"+49 951/44486",
    "sg:postcode":"96117",
    "sg:province":"Bayern",
    "wof:name":"Peter Reu\u00df Architekt",
    "wof:placetype":"venue"
},
  "geometry": {"coordinates":[10.925609,49.923885],"type":"Point"}
}