{
  "type": "Feature",
  "properties": {
    "iso:country":"DE",
    "sg:address":"Meyelheide 5",
    "sg:city":"Gro\u00dfenkneten",
    "sg:phone":"+49 4435/93010",
    "sg:postcode":"26197",
    "sg:province":"Niedersachsen",
    "wof:name":"G & K Montagen Gmbh",
    "wof:placetype":"venue"
},
  "geometry": {"coordinates":[8.2397356033,52.8835372925],"type":"Point"}
}