{
  "type": "Feature",
  "properties": {
    "iso:country":"DE",
    "sg:address":"Memminger Str. 10",
    "sg:city":"Giengen",
    "sg:phone":"+49 7322/5254",
    "sg:postcode":"89537",
    "sg:province":"Baden-W\u00fcrttemberg",
    "wof:name":"Wolfgang Schulz",
    "wof:placetype":"venue"
},
  "geometry": {"coordinates":[10.24544,48.616951],"type":"Point"}
}