{
  "type": "Feature",
  "properties": {
    "iso:country":"DE",
    "sg:address":"Ahornstr. 11",
    "sg:city":"Nordhorn",
    "sg:phone":"+49 5921/37118",
    "sg:postcode":"48531",
    "sg:province":"Niedersachsen",
    "wof:name":"Hermann H\u00f6lscher Elektro-mstr.",
    "wof:placetype":"venue"
},
  "geometry": {"coordinates":[7.094722,52.440804],"type":"Point"}
}