{
  "type": "Feature",
  "properties": {
    "iso:country":"DE",
    "sg:address":"Schmidtskamp 7",
    "sg:city":"Hamminkeln",
    "sg:phone":"+49 2856/98114",
    "sg:postcode":"46499",
    "sg:province":"Nordrhein-Westfalen",
    "wof:name":"D. Holsteg",
    "wof:placetype":"venue"
},
  "geometry": {"coordinates":[6.678634,51.726967],"type":"Point"}
}