{
  "type": "Feature",
  "properties": {
    "iso:country":"DE",
    "sg:address":"Rankbachstr. 49",
    "sg:city":"Renningen",
    "sg:phone":"+49 7159/18728",
    "sg:postcode":"71272",
    "sg:province":"Baden-W\u00fcrttemberg",
    "wof:name":"Svr-sportpark-restaurant",
    "wof:placetype":"venue"
},
  "geometry": {"coordinates":[8.9299898148,48.7708892822],"type":"Point"}
}