{
  "type": "Feature",
  "properties": {
    "iso:country":"DE",
    "sg:address":"Otto-Lindenmeyer-Str. 4",
    "sg:city":"Augsburg",
    "sg:phone":"+49 821/561079",
    "sg:postcode":"86153",
    "sg:province":"Bayern",
    "wof:name":"Hansj\u00f6rg Greineder Heilpraktiker",
    "wof:placetype":"venue"
},
  "geometry": {"coordinates":[10.914689064,48.3713226318],"type":"Point"}
}