{
  "type": "Feature",
  "properties": {
    "iso:country":"DE",
    "sg:address":"Fasanenstr. 66",
    "sg:city":"Unterhaching",
    "sg:phone":"+49 89/6650330",
    "sg:postcode":"82008",
    "sg:province":"Bayern",
    "wof:name":"Gries & Co. Kg",
    "wof:placetype":"venue"
},
  "geometry": {"coordinates":[11.609058,48.074726],"type":"Point"}
}