{
  "type": "Feature",
  "properties": {
    "iso:country":"DE",
    "sg:address":"Wildunger Str. 4 a",
    "sg:city":"Duderstadt",
    "sg:phone":"+49 5527/72001",
    "sg:postcode":"37115",
    "sg:province":"Niedersachsen",
    "wof:name":"Helmut Risse",
    "wof:placetype":"venue"
},
  "geometry": {"coordinates":[10.267523,51.507439],"type":"Point"}
}