{
  "type": "Feature",
  "properties": {
    "iso:country":"DE",
    "sg:address":"Parkstr. 1",
    "sg:city":"Willich",
    "sg:phone":"+49 2154/412910",
    "sg:postcode":"47877",
    "sg:province":"Nordrhein-Westfalen",
    "wof:name":"Nrm Neue Rhein Medien Gmbh",
    "wof:placetype":"venue"
},
  "geometry": {"coordinates":[6.5535497665,51.2664794922],"type":"Point"}
}