{
  "type": "Feature",
  "properties": {
    "iso:country":"DE",
    "sg:address":"Alte Hauptstr. 23",
    "sg:city":"Nuthe-Urstromtal",
    "sg:phone":"+49 3371/637216",
    "sg:postcode":"14947",
    "sg:province":"Brandenburg",
    "wof:name":"Arndt",
    "wof:placetype":"venue"
},
  "geometry": {"coordinates":[13.2275657654,52.0573654175],"type":"Point"}
}