{
  "type": "Feature",
  "properties": {
    "iso:country":"DE",
    "sg:address":"M\u00fchlenstr. 5",
    "sg:city":"Nalbach",
    "sg:postcode":"66809",
    "sg:province":"Saarland",
    "wof:name":"Arweiler Gmbh",
    "wof:placetype":"venue"
},
  "geometry": {"coordinates":[6.7894301414,49.3791236877],"type":"Point"}
}