{
  "type": "Feature",
  "properties": {
    "iso:country":"DE",
    "sg:address":"Aachener Str. 78",
    "sg:city":"D\u00fcren",
    "sg:phone":"+49 2421/941021",
    "sg:postcode":"52349",
    "sg:province":"Nordrhein-Westfalen",
    "wof:name":"A.c.o.",
    "wof:placetype":"venue"
},
  "geometry": {"coordinates":[6.4747900963,50.7960014343],"type":"Point"}
}