{
  "type": "Feature",
  "properties": {
    "iso:country":"DE",
    "sg:address":"Br\u00fcckenauer Str. 26",
    "sg:city":"Schl\u00fcchtern",
    "sg:phone":"+49 6661/2263",
    "sg:postcode":"36381",
    "sg:province":"Hessen",
    "wof:name":"Adolf Wolf Gmbh",
    "wof:placetype":"venue"
},
  "geometry": {"coordinates":[9.532374382,50.3483276367],"type":"Point"}
}