{
  "type": "Feature",
  "properties": {
    "iso:country":"DE",
    "sg:address":"Hauptstr. 45",
    "sg:city":"Ottersberg",
    "sg:phone":"+49 4205/2094",
    "sg:postcode":"28870",
    "sg:province":"Niedersachsen",
    "wof:name":"Hermann Holsten",
    "wof:placetype":"venue"
},
  "geometry": {"coordinates":[9.1473760605,53.146686554],"type":"Point"}
}