{
  "type": "Feature",
  "properties": {
    "iso:country":"DE",
    "sg:address":"Reichsstr. 2",
    "sg:city":"Gera",
    "sg:phone":"+49 365/8259990",
    "sg:postcode":"07545",
    "sg:province":"Th\u00fcringen",
    "wof:name":"Proplan Gesellschaft F\u00fcr Planung Und Entwicklung Mbh",
    "wof:placetype":"venue"
},
  "geometry": {"coordinates":[12.080818,50.875298],"type":"Point"}
}