{
  "type": "Feature",
  "properties": {
    "iso:country":"DE",
    "sg:address":"Urdenbacher Dorfstr. 26",
    "sg:city":"D\u00fcsseldorf",
    "sg:phone":"+49 211/713073",
    "sg:postcode":"40593",
    "sg:province":"Nordrhein-Westfalen",
    "wof:name":"B\u00fcnting Standdesign",
    "wof:placetype":"venue"
},
  "geometry": {"coordinates":[6.866824,51.148148],"type":"Point"}
}