{
  "type": "Feature",
  "properties": {
    "iso:country":"DE",
    "sg:address":"Trebuser Str.",
    "sg:city":"Niesky",
    "sg:phone":"+49 3588/25030",
    "sg:postcode":"02906",
    "sg:province":"Sachsen",
    "wof:name":"Neu & Reko Bau Glotz Gmbh",
    "wof:placetype":"venue"
},
  "geometry": {"coordinates":[14.834636,51.302208],"type":"Point"}
}