{
  "type": "Feature",
  "properties": {
    "iso:country":"DE",
    "sg:address":"M\u00fchlenweg",
    "sg:city":"Gusenburg",
    "sg:phone":"+49 6503/3965",
    "sg:postcode":"54413",
    "sg:province":"Rheinland-Pfalz",
    "wof:name":"Johannes Nickels",
    "wof:placetype":"venue"
},
  "geometry": {"coordinates":[6.905101,49.636219],"type":"Point"}
}