{
  "type": "Feature",
  "properties": {
    "iso:country":"DE",
    "sg:address":"Lugwaldstr 20",
    "sg:city":"M\u00fchlacker",
    "sg:phone":"+49 7041/95070",
    "sg:postcode":"75417",
    "sg:province":"Baden-W\u00fcrttemberg",
    "wof:name":"Idm Direktmarketing Gmbh",
    "wof:placetype":"venue"
},
  "geometry": {"coordinates":[8.873762,48.955173],"type":"Point"}
}