{
  "type": "Feature",
  "properties": {
    "iso:country":"DE",
    "sg:address":"Ruprechtstr. 20",
    "sg:city":"Edesheim",
    "sg:phone":"+49 6323/6284",
    "sg:postcode":"67483",
    "sg:province":"Rheinland-Pfalz",
    "wof:name":"H. Wolf",
    "wof:placetype":"venue"
},
  "geometry": {"coordinates":[8.1302537918,49.259967804],"type":"Point"}
}