{
  "type": "Feature",
  "properties": {
    "iso:country":"DE",
    "sg:address":"Hambrinker Heide 46",
    "sg:city":"Bielefeld",
    "sg:phone":"+49 5241/6587",
    "sg:postcode":"33649",
    "sg:province":"Nordrhein-Westfalen",
    "wof:name":"Eckhart Hammer",
    "wof:placetype":"venue"
},
  "geometry": {"coordinates":[8.417797,51.959576],"type":"Point"}
}