{
  "type": "Feature",
  "properties": {
    "iso:country":"DE",
    "sg:address":"Kolonnenweg 5",
    "sg:city":"Heikendorf",
    "sg:phone":"+49 431/242651",
    "sg:postcode":"24226",
    "sg:province":"Schleswig-Holstein",
    "wof:name":"Mathias Rolfs Architekt",
    "wof:placetype":"venue"
},
  "geometry": {"coordinates":[10.20353,54.382118],"type":"Point"}
}