{
  "type": "Feature",
  "properties": {
    "iso:country":"DE",
    "sg:address":"Friedensstr. 38",
    "sg:city":"Lorsch",
    "sg:phone":"+49 6251/59730",
    "sg:postcode":"64653",
    "sg:province":"Hessen",
    "wof:name":"Neubecker Gmbh Brandschutzservice",
    "wof:placetype":"venue"
},
  "geometry": {"coordinates":[8.569128,49.647717],"type":"Point"}
}