{
  "type": "Feature",
  "properties": {
    "iso:country":"DE",
    "sg:address":"Am Bahnhof",
    "sg:city":"Wittingen",
    "sg:phone":"+49 5831/1218",
    "sg:postcode":"29378",
    "sg:province":"Niedersachsen",
    "wof:name":"Deutsche Bahn Ag",
    "wof:placetype":"venue"
},
  "geometry": {"coordinates":[10.8080978394,52.6929855347],"type":"Point"}
}