{
  "type": "Feature",
  "properties": {
    "iso:country":"DE",
    "sg:address":"Markgrafenweg 14",
    "sg:city":"Altensteig",
    "sg:phone":"+49 7453/6616",
    "sg:postcode":"72213",
    "sg:province":"Baden-W\u00fcrttemberg",
    "wof:name":"Ev. Pfarramt Ii",
    "wof:placetype":"venue"
},
  "geometry": {"coordinates":[8.6086244583,48.589881897],"type":"Point"}
}