{
  "type": "Feature",
  "properties": {
    "iso:country":"DE",
    "sg:address":"Rathsberger Str. 10",
    "sg:city":"Erlangen",
    "sg:phone":"+49 9131/27058",
    "sg:postcode":"91054",
    "sg:province":"Bayern",
    "wof:name":"Carl-korth-institut E. V.",
    "wof:placetype":"venue"
},
  "geometry": {"coordinates":[11.0113582611,49.6065635681],"type":"Point"}
}