{
  "type": "Feature",
  "properties": {
    "iso:country":"DE",
    "sg:address":"Ringstr. 5",
    "sg:city":"Oberd\u00fcrenbach",
    "sg:postcode":"56651",
    "sg:province":"Rheinland-Pfalz",
    "wof:name":"Mehrzweckhalle Oberd\u00fcrenbach",
    "wof:placetype":"venue"
},
  "geometry": {"coordinates":[7.192298,50.452305],"type":"Point"}
}