{
  "type": "Feature",
  "properties": {
    "iso:country":"DE",
    "sg:address":"Bahnhofstr. 13",
    "sg:city":"Korbach",
    "sg:phone":"+49 5631/8599",
    "sg:postcode":"34497",
    "sg:province":"Hessen",
    "wof:name":"Reinhard Hein Buchhandlung",
    "wof:placetype":"venue"
},
  "geometry": {"coordinates":[8.8725118637,51.2775115967],"type":"Point"}
}