{
  "type": "Feature",
  "properties": {
    "iso:country":"DE",
    "sg:address":"Zum Ottersberg 9",
    "sg:city":"Wertheim",
    "sg:phone":"+49 9342/92400",
    "sg:postcode":"97877",
    "sg:province":"Baden-W\u00fcrttemberg",
    "wof:name":"Uebe Medical Gmbh",
    "wof:placetype":"venue"
},
  "geometry": {"coordinates":[9.5238409042,49.7303619385],"type":"Point"}
}