{
  "type": "Feature",
  "properties": {
    "iso:country":"DE",
    "sg:address":"Toracker 1",
    "sg:city":"Obertrubach",
    "sg:phone":"+49 9245/603",
    "sg:postcode":"91286",
    "sg:province":"Bayern",
    "wof:name":"A. Reichel",
    "wof:placetype":"venue"
},
  "geometry": {"coordinates":[11.3430976868,49.6956100464],"type":"Point"}
}