{
  "type": "Feature",
  "properties": {
    "iso:country":"DE",
    "sg:address":"Dr.-Mutterer-Str. 19",
    "sg:city":"Nassau",
    "sg:phone":"+49 2604/5009",
    "sg:postcode":"56377",
    "sg:province":"Rheinland-Pfalz",
    "wof:name":"Tasco Gmbh",
    "wof:placetype":"venue"
},
  "geometry": {"coordinates":[7.8002052307,50.3195266724],"type":"Point"}
}