{
  "type": "Feature",
  "properties": {
    "iso:country":"DE",
    "sg:address":"Carl-Coppius-Str. 10",
    "sg:city":"Grimmen",
    "sg:phone":"+49 38326/2614",
    "sg:postcode":"18507",
    "sg:province":"Mecklenburg-Vorpommern",
    "wof:name":"Horst Haase",
    "wof:placetype":"venue"
},
  "geometry": {"coordinates":[13.0409078598,54.1102027893],"type":"Point"}
}