{
  "type": "Feature",
  "properties": {
    "iso:country":"DE",
    "sg:address":"Rathausstr. 45",
    "sg:city":"Heidelberg",
    "sg:phone":"+49 6221/300282",
    "sg:postcode":"69126",
    "sg:province":"Baden-W\u00fcrttemberg",
    "wof:name":"Dorfsch\u00e4nke",
    "wof:placetype":"venue"
},
  "geometry": {"coordinates":[8.691945076,49.379032135],"type":"Point"}
}