{
  "type": "Feature",
  "properties": {
    "iso:country":"DE",
    "sg:address":"Lichtenstein 11",
    "sg:city":"Bad Gandersheim",
    "sg:phone":"+49 4953/823925",
    "sg:postcode":"37581",
    "sg:province":"Niedersachsen",
    "wof:name":"Raiffeisenbank Harriehausen-bornhau",
    "wof:placetype":"venue"
},
  "geometry": {"coordinates":[10.08998,51.84623],"type":"Point"}
}