{
  "type": "Feature",
  "properties": {
    "iso:country":"DE",
    "sg:address":"Rheinstr. 6",
    "sg:city":"Koblenz",
    "sg:phone":"+49 261/15068",
    "sg:postcode":"56068",
    "sg:province":"Rheinland-Pfalz",
    "wof:name":"Ingeborg Doll Immobilienmaklerin",
    "wof:placetype":"venue"
},
  "geometry": {"coordinates":[7.6035070419,50.3599662781],"type":"Point"}
}