{
  "type": "Feature",
  "properties": {
    "iso:country":"DE",
    "sg:address":"Werkzeugstr. 1",
    "sg:city":"Hagen",
    "sg:phone":"+49 2331/3550",
    "sg:postcode":"58093",
    "sg:province":"Nordrhein-Westfalen",
    "wof:name":"Logistik-zentrum In Halden Gmbh",
    "wof:placetype":"venue"
},
  "geometry": {"coordinates":[7.5104532242,51.3814430237],"type":"Point"}
}