{
  "type": "Feature",
  "properties": {
    "iso:country":"DE",
    "sg:address":"Schlo\u00dfbergstr. 17",
    "sg:city":"Scherstetten",
    "sg:phone":"+49 8262/698",
    "sg:postcode":"86872",
    "sg:province":"Bayern",
    "wof:name":"Karl H\u00f6\u00df",
    "wof:placetype":"venue"
},
  "geometry": {"coordinates":[10.641213,48.177029],"type":"Point"}
}