{
  "type": "Feature",
  "properties": {
    "iso:country":"DE",
    "sg:address":"Tassilostr. 17",
    "sg:city":"N\u00fcrnberg",
    "sg:phone":"+49 911/305594",
    "sg:postcode":"90429",
    "sg:province":"Bayern",
    "wof:name":"P. Risch",
    "wof:placetype":"venue"
},
  "geometry": {"coordinates":[11.020706,49.460545],"type":"Point"}
}