{
  "type": "Feature",
  "properties": {
    "iso:country":"DE",
    "sg:address":"Am Mosesbrunnen 9",
    "sg:city":"Gro\u00dfeibstadt",
    "sg:phone":"+49 9761/2461",
    "sg:postcode":"97633",
    "sg:province":"Bayern",
    "wof:name":"Schubert Krankenpflegedienst",
    "wof:placetype":"venue"
},
  "geometry": {"coordinates":[10.415008,50.300529],"type":"Point"}
}