{
  "type": "Feature",
  "properties": {
    "iso:country":"DE",
    "sg:address":"Frankenstr. 101",
    "sg:city":"Essen",
    "sg:postcode":"45134",
    "sg:province":"Nordrhein-Westfalen",
    "wof:name":"Ralph Steiner",
    "wof:placetype":"venue"
},
  "geometry": {"coordinates":[7.0439248085,51.4259986877],"type":"Point"}
}