{
  "type": "Feature",
  "properties": {
    "iso:country":"DE",
    "sg:address":"Altenberg 1",
    "sg:city":"Bad Mergentheim",
    "sg:phone":"+49 7931/6285",
    "sg:postcode":"97980",
    "sg:province":"Baden-W\u00fcrttemberg",
    "wof:name":"K.-h. Model",
    "wof:placetype":"venue"
},
  "geometry": {"coordinates":[9.742583,49.513851],"type":"Point"}
}