{
  "type": "Feature",
  "properties": {
    "iso:country":"DE",
    "sg:address":"Beethovenstr. 13",
    "sg:city":"Igersheim",
    "sg:phone":"+49 7931/2851",
    "sg:postcode":"97999",
    "sg:province":"Baden-W\u00fcrttemberg",
    "wof:name":"Kornelia Graf Steuerberater",
    "wof:placetype":"venue"
},
  "geometry": {"coordinates":[9.8144731522,49.4973449707],"type":"Point"}
}