{
  "type": "Feature",
  "properties": {
    "iso:country":"DE",
    "sg:address":"Haingasse 13-15",
    "sg:city":"Bad Homburg",
    "sg:phone":"+49 6172/92720",
    "sg:postcode":"61348",
    "sg:province":"Hessen",
    "wof:name":"B\u00fcro Gr\u00fcnzig Planungs- Gesellschaft Mbh",
    "wof:placetype":"venue"
},
  "geometry": {"coordinates":[8.613297,50.229397],"type":"Point"}
}