{
  "type": "Feature",
  "properties": {
    "iso:country":"DE",
    "sg:address":"Hanfriedenstr. 22",
    "sg:city":"Westerkappeln",
    "sg:phone":"+49 5404/3361",
    "sg:postcode":"49492",
    "sg:province":"Nordrhein-Westfalen",
    "wof:name":"Am Stadion",
    "wof:placetype":"venue"
},
  "geometry": {"coordinates":[7.8837018013,52.3164024353],"type":"Point"}
}