{
  "type": "Feature",
  "properties": {
    "iso:country":"DE",
    "sg:address":"Hohenzollernstr. 17",
    "sg:city":"M\u00fcnchen",
    "sg:phone":"+49 89/338434",
    "sg:postcode":"80801",
    "sg:province":"Bayern",
    "wof:name":"Carree Modehandel Gmbh",
    "wof:placetype":"venue"
},
  "geometry": {"coordinates":[11.581967,48.159691],"type":"Point"}
}