{
  "type": "Feature",
  "properties": {
    "iso:country":"DE",
    "sg:address":"Br\u00fcggemannhof 9",
    "sg:city":"Hannover",
    "sg:phone":"+49 511/701765",
    "sg:postcode":"30167",
    "sg:province":"Niedersachsen",
    "wof:name":"J\u00f6rg Nerbe",
    "wof:placetype":"venue"
},
  "geometry": {"coordinates":[9.723266,52.381172],"type":"Point"}
}