{
  "type": "Feature",
  "properties": {
    "iso:country":"DE",
    "sg:address":"Winzergasse 1",
    "sg:city":"Markdorf",
    "sg:phone":"+49 7544/72942",
    "sg:postcode":"88677",
    "sg:province":"Baden-W\u00fcrttemberg",
    "wof:name":"Wirkraum Parkettgestaltung Jeilig Und Kram Gbr",
    "wof:placetype":"venue"
},
  "geometry": {"coordinates":[9.3905105591,47.7208404541],"type":"Point"}
}