{
  "type": "Feature",
  "properties": {
    "iso:country":"DE",
    "sg:address":"Andersenring 19",
    "sg:city":"L\u00fcbeck",
    "sg:phone":"+49 451/805788",
    "sg:postcode":"23560",
    "sg:province":"Schleswig-Holstein",
    "wof:name":"Der Tabakladen Friedel Gyllensv\u00e4rd",
    "wof:placetype":"venue"
},
  "geometry": {"coordinates":[10.636097908,53.8429489136],"type":"Point"}
}