{
  "type": "Feature",
  "properties": {
    "iso:country":"DE",
    "sg:address":"Brooktorkai 3",
    "sg:city":"Hamburg",
    "sg:phone":"+49 40/322306",
    "sg:postcode":"20457",
    "sg:province":"Hamburg",
    "wof:name":"Habib Maschreghzamini",
    "wof:placetype":"venue"
},
  "geometry": {"coordinates":[10.0016317368,53.5455703735],"type":"Point"}
}