{
  "type": "Feature",
  "properties": {
    "iso:country":"DE",
    "sg:address":"Leipziger Str. 6",
    "sg:city":"Neuss",
    "sg:phone":"+49 2131/467394",
    "sg:postcode":"41472",
    "sg:province":"Nordrhein-Westfalen",
    "wof:name":"Hein Bau Gmbh",
    "wof:placetype":"venue"
},
  "geometry": {"coordinates":[6.6681389809,51.1640853882],"type":"Point"}
}