{
  "type": "Feature",
  "properties": {
    "iso:country":"DE",
    "sg:address":"Lessingstr. 10",
    "sg:city":"Saarbr\u00fccken",
    "sg:phone":"+49 681/967080",
    "sg:postcode":"66121",
    "sg:province":"Saarland",
    "wof:name":"Friedrich Naumann Stiftung",
    "wof:placetype":"venue"
},
  "geometry": {"coordinates":[7.0094208717,49.2269325256],"type":"Point"}
}