{
  "type": "Feature",
  "properties": {
    "iso:country":"DE",
    "sg:address":"Stettiner Str. 14",
    "sg:city":"Wiesbaden",
    "sg:phone":"+49 611/607783",
    "sg:postcode":"65203",
    "sg:province":"Hessen",
    "wof:name":"D. Reinhardt",
    "wof:placetype":"venue"
},
  "geometry": {"coordinates":[8.2397985458,50.0385742188],"type":"Point"}
}