{
  "type": "Feature",
  "properties": {
    "iso:country":"DE",
    "sg:address":"Burgstr. 4a",
    "sg:city":"Lahnstein",
    "sg:phone":"+49 2621/40665",
    "sg:postcode":"56112",
    "sg:province":"Rheinland-Pfalz",
    "wof:name":"E. Heilscher",
    "wof:placetype":"venue"
},
  "geometry": {"coordinates":[7.605649,50.299862],"type":"Point"}
}