{
  "type": "Feature",
  "properties": {
    "iso:country":"DE",
    "sg:address":"Sch\u00e4tzwaldweg 1",
    "sg:city":"Heiligenstadt",
    "sg:phone":"+49 9198/265",
    "sg:postcode":"91332",
    "sg:province":"Bayern",
    "wof:name":"Manfred Schmidt",
    "wof:placetype":"venue"
},
  "geometry": {"coordinates":[11.170149,49.863235],"type":"Point"}
}