{
  "type": "Feature",
  "properties": {
    "iso:country":"DE",
    "sg:address":"Untere Inntalstr. 44-46",
    "sg:city":"Bad F\u00fcssing",
    "sg:phone":"+49 8531/29261",
    "sg:postcode":"94072",
    "sg:province":"Bayern",
    "wof:name":"Agip-tankstelle",
    "wof:placetype":"venue"
},
  "geometry": {"coordinates":[13.3432483673,48.352432251],"type":"Point"}
}