{
  "type": "Feature",
  "properties": {
    "iso:country":"DE",
    "sg:address":"Grabenstr. 6 c",
    "sg:city":"Rheinbreitbach",
    "sg:phone":"+49 2224/5950",
    "sg:postcode":"53619",
    "sg:province":"Rheinland-Pfalz",
    "wof:name":"Erhard Richarts",
    "wof:placetype":"venue"
},
  "geometry": {"coordinates":[7.226352,50.616405],"type":"Point"}
}