{
  "type": "Feature",
  "properties": {
    "iso:country":"DE",
    "sg:address":"W\u00f6hrvorstadt 2 a",
    "sg:city":"Schwandorf",
    "sg:phone":"+49 9431/41812",
    "sg:postcode":"92421",
    "sg:province":"Bayern",
    "wof:name":"Karl Steiger Heilpraktiker",
    "wof:placetype":"venue"
},
  "geometry": {"coordinates":[12.106461525,49.3320159912],"type":"Point"}
}