{
  "type": "Feature",
  "properties": {
    "iso:country":"DE",
    "sg:address":"Regensburger Str. 23",
    "sg:city":"Gelsenkirchen",
    "sg:phone":"+49 209/204850",
    "sg:postcode":"45886",
    "sg:province":"Nordrhein-Westfalen",
    "wof:name":"G. Kwiedo",
    "wof:placetype":"venue"
},
  "geometry": {"coordinates":[7.114695,51.500839],"type":"Point"}
}