{
  "type": "Feature",
  "properties": {
    "iso:country":"DE",
    "sg:address":"Am Markt 9 a",
    "sg:city":"Warburg",
    "sg:phone":"+49 5641/1526",
    "sg:postcode":"34414",
    "sg:province":"Nordrhein-Westfalen",
    "wof:name":"Gr\u00fcnschnabel",
    "wof:placetype":"venue"
},
  "geometry": {"coordinates":[9.1470956802,51.4854049683],"type":"Point"}
}