{
  "type": "Feature",
  "properties": {
    "iso:country":"DE",
    "sg:address":"Prozessionsweg 1",
    "sg:city":"Werl",
    "sg:postcode":"59457",
    "sg:province":"Nordrhein-Westfalen",
    "wof:name":"Hellweg Transportbeton Werl Gmbh & Co. Kg",
    "wof:placetype":"venue"
},
  "geometry": {"coordinates":[7.8741540909,51.5520858765],"type":"Point"}
}