{
  "type": "Feature",
  "properties": {
    "iso:country":"DE",
    "sg:address":"Bernbacher Str. 83 a",
    "sg:city":"F\u00fcrth",
    "sg:phone":"+49 911/753747",
    "sg:postcode":"90768",
    "sg:province":"Bayern",
    "wof:name":"Georg G\u00f6tz Architekt",
    "wof:placetype":"venue"
},
  "geometry": {"coordinates":[10.91473,49.492359],"type":"Point"}
}