{
  "type": "Feature",
  "properties": {
    "iso:country":"DE",
    "sg:address":"Walsroder Str. 19",
    "sg:city":"Hannover",
    "sg:phone":"+49 511/573647",
    "sg:postcode":"30625",
    "sg:province":"Niedersachsen",
    "wof:name":"Dieter Krebs Architekt",
    "wof:placetype":"venue"
},
  "geometry": {"coordinates":[9.81545,52.37878],"type":"Point"}
}