{
  "type": "Feature",
  "properties": {
    "iso:country":"DE",
    "sg:address":"Barg Up 3",
    "sg:city":"Bremen",
    "sg:phone":"+49 421/635293",
    "sg:postcode":"28717",
    "sg:province":"Bremen",
    "wof:name":"Altes Packhaus Vegesack E. V. Hermann Krau\u00df",
    "wof:placetype":"venue"
},
  "geometry": {"coordinates":[8.6808576584,53.1656532288],"type":"Point"}
}