{
  "type": "Feature",
  "properties": {
    "iso:country":"DE",
    "sg:address":"Alt-Marienfelde 37",
    "sg:city":"Berlin",
    "sg:phone":"+49 30/7213037",
    "sg:postcode":"12277",
    "sg:province":"Berlin",
    "wof:name":"Lehmanns Bauernmarkt",
    "wof:placetype":"venue"
},
  "geometry": {"coordinates":[13.3667392731,52.4120826721],"type":"Point"}
}