{
  "type": "Feature",
  "properties": {
    "iso:country":"DE",
    "sg:address":"Oskar-Farny-Str. 16",
    "sg:city":"Ki\u00dflegg",
    "sg:phone":"+49 7563/915638",
    "sg:postcode":"88353",
    "sg:province":"Baden-W\u00fcrttemberg",
    "wof:name":"G. Dorn",
    "wof:placetype":"venue"
},
  "geometry": {"coordinates":[9.9191570282,47.7590484619],"type":"Point"}
}