{
  "type": "Feature",
  "properties": {
    "iso:country":"DE",
    "sg:address":"Herforder Str. 130 b",
    "sg:city":"Bielefeld",
    "sg:phone":"+49 521/34128",
    "sg:postcode":"33609",
    "sg:province":"Nordrhein-Westfalen",
    "wof:name":"E. Rahe",
    "wof:placetype":"venue"
},
  "geometry": {"coordinates":[8.5456256866,52.033706665],"type":"Point"}
}