{
  "type": "Feature",
  "properties": {
    "iso:country":"DE",
    "sg:address":"Neugasse 16",
    "sg:city":"Mainz",
    "sg:phone":"+49 6136/42372",
    "sg:postcode":"55129",
    "sg:province":"Rheinland-Pfalz",
    "wof:name":"H. J. Stuppert Gmbh",
    "wof:placetype":"venue"
},
  "geometry": {"coordinates":[8.246073,49.913044],"type":"Point"}
}