{
  "type": "Feature",
  "properties": {
    "iso:country":"DE",
    "sg:address":"Amperweg 44",
    "sg:city":"Dachau",
    "sg:phone":"+49 8131/13684",
    "sg:postcode":"85221",
    "sg:province":"Bayern",
    "wof:name":"Karl M\u00fchlstein",
    "wof:placetype":"venue"
},
  "geometry": {"coordinates":[11.447558403,48.2632522583],"type":"Point"}
}