{
  "type": "Feature",
  "properties": {
    "iso:country":"DE",
    "sg:address":"Alte Landstr. 67",
    "sg:city":"D\u00fcsseldorf",
    "sg:phone":"+49 211/940451",
    "sg:postcode":"40489",
    "sg:province":"Nordrhein-Westfalen",
    "wof:name":"Manfred Trinkhaus Steuerberater",
    "wof:placetype":"venue"
},
  "geometry": {"coordinates":[6.7401862144,51.2919502258],"type":"Point"}
}