{
  "type": "Feature",
  "properties": {
    "iso:country":"DE",
    "sg:address":"Werdestr. 2",
    "sg:city":"Hagen",
    "sg:phone":"+49 2331/26779",
    "sg:postcode":"58089",
    "sg:province":"Nordrhein-Westfalen",
    "wof:name":"Hotel B\u00fcrgerkrug",
    "wof:placetype":"venue"
},
  "geometry": {"coordinates":[7.4625210762,51.3638916016],"type":"Point"}
}