{
  "type": "Feature",
  "properties": {
    "iso:country":"DE",
    "sg:address":"Alte Schulstr. 1",
    "sg:city":"Steinfeld",
    "sg:phone":"+49 5492/2210",
    "sg:postcode":"49439",
    "sg:province":"Niedersachsen",
    "wof:name":"Dr. Bruns Bodenabbau Kg",
    "wof:placetype":"venue"
},
  "geometry": {"coordinates":[8.2707977295,52.5844841003],"type":"Point"}
}