{
  "type": "Feature",
  "properties": {
    "iso:country":"DE",
    "sg:address":"Uhlandstr. 22",
    "sg:city":"Karlsruhe",
    "sg:phone":"+49 721/849496",
    "sg:postcode":"76135",
    "sg:province":"Baden-W\u00fcrttemberg",
    "wof:name":"E. R\u00f6lz",
    "wof:placetype":"venue"
},
  "geometry": {"coordinates":[8.3749570847,49.009765625],"type":"Point"}
}