{
  "type": "Feature",
  "properties": {
    "iso:country":"DE",
    "sg:address":"Zeppelinstr. 6",
    "sg:city":"Bad Liebenzell",
    "sg:phone":"+49 7052/2611",
    "sg:postcode":"75378",
    "sg:province":"Baden-W\u00fcrttemberg",
    "wof:name":"Fremdenheim Burkhardt",
    "wof:placetype":"venue"
},
  "geometry": {"coordinates":[8.7286109924,48.7757301331],"type":"Point"}
}