{
  "type": "Feature",
  "properties": {
    "iso:country":"DE",
    "sg:address":"Adlerweg 3-5",
    "sg:city":"Detmold",
    "sg:phone":"+49 5231/47171",
    "sg:postcode":"32760",
    "sg:province":"Nordrhein-Westfalen",
    "wof:name":"Adlerwarte Berlebeck",
    "wof:placetype":"venue"
},
  "geometry": {"coordinates":[8.8728942871,51.8932952881],"type":"Point"}
}