{
  "type": "Feature",
  "properties": {
    "iso:country":"DE",
    "sg:address":"Herderweg 2",
    "sg:city":"Hanau",
    "sg:phone":"+49 6181/252125",
    "sg:postcode":"63454",
    "sg:province":"Hessen",
    "wof:name":"Ivan Baric Dolmetscher",
    "wof:placetype":"venue"
},
  "geometry": {"coordinates":[8.8847045898,50.1318397522],"type":"Point"}
}