{
  "type": "Feature",
  "properties": {
    "iso:country":"DE",
    "sg:address":"Maxstr. 53",
    "sg:city":"Ludwigshafen",
    "sg:phone":"+49 621/516991",
    "sg:postcode":"67059",
    "sg:province":"Rheinland-Pfalz",
    "wof:name":"Laterne",
    "wof:placetype":"venue"
},
  "geometry": {"coordinates":[8.4434709549,49.4827804565],"type":"Point"}
}