{
  "type": "Feature",
  "properties": {
    "iso:country":"DE",
    "sg:address":"Hesternstr. 55",
    "sg:city":"Bochum",
    "sg:phone":"+49 2327/79693",
    "sg:postcode":"44869",
    "sg:province":"Nordrhein-Westfalen",
    "wof:name":"Malerbetrieb Emmerich Gmbh",
    "wof:placetype":"venue"
},
  "geometry": {"coordinates":[7.167665,51.456112],"type":"Point"}
}