{
  "type": "Feature",
  "properties": {
    "iso:country":"DE",
    "sg:address":"Robert-Bosch-Str. 4",
    "sg:city":"Illerkirchberg",
    "sg:phone":"+49 7346/919491",
    "sg:postcode":"89171",
    "sg:province":"Baden-W\u00fcrttemberg",
    "wof:name":"Erika Straub Masseurin",
    "wof:placetype":"venue"
},
  "geometry": {"coordinates":[9.993422,48.33746],"type":"Point"}
}