{
  "type": "Feature",
  "properties": {
    "iso:country":"DE",
    "sg:address":"Helfer Str. 54",
    "sg:city":"Hagen",
    "sg:phone":"+49 2331/68274",
    "sg:postcode":"58099",
    "sg:province":"Nordrhein-Westfalen",
    "wof:name":"B. Dirks",
    "wof:placetype":"venue"
},
  "geometry": {"coordinates":[7.4833159447,51.3932952881],"type":"Point"}
}