{
  "type": "Feature",
  "properties": {
    "iso:country":"DE",
    "sg:address":"Hedelfinger Str 49",
    "sg:city":"Ostfildern",
    "sg:phone":"+49 711/412684",
    "sg:postcode":"73760",
    "sg:province":"Baden-W\u00fcrttemberg",
    "wof:name":"Binsch Gmbh",
    "wof:placetype":"venue"
},
  "geometry": {"coordinates":[9.2538204193,48.7366294861],"type":"Point"}
}