{
  "type": "Feature",
  "properties": {
    "iso:country":"DE",
    "sg:address":"St.-Anton-Str. 23",
    "sg:city":"Krefeld",
    "sg:phone":"+49 2151/961960",
    "sg:postcode":"47799",
    "sg:province":"Nordrhein-Westfalen",
    "wof:name":"Kormann Kormann-liebsch Rechtsanw\u00e4lte",
    "wof:placetype":"venue"
},
  "geometry": {"coordinates":[6.56620121,51.3347473145],"type":"Point"}
}