{
  "type": "Feature",
  "properties": {
    "iso:country":"DE",
    "sg:address":"Hoflacher Str. 87",
    "sg:city":"Eichenau",
    "sg:phone":"+49 8141/7497",
    "sg:postcode":"82223",
    "sg:province":"Bayern",
    "wof:name":"Rudolf K\u00fcrzl Steuerberater",
    "wof:placetype":"venue"
},
  "geometry": {"coordinates":[11.3140048981,48.1586036682],"type":"Point"}
}