{
  "type": "Feature",
  "properties": {
    "iso:country":"DE",
    "sg:address":"Frankfurter Str. 45",
    "sg:city":"Eisdorf",
    "sg:phone":"+49 5522/82742",
    "sg:postcode":"37534",
    "sg:province":"Niedersachsen",
    "wof:name":"Hans Hartung",
    "wof:placetype":"venue"
},
  "geometry": {"coordinates":[10.1796512604,51.7643165588],"type":"Point"}
}