{
  "type": "Feature",
  "properties": {
    "iso:country":"DE",
    "sg:address":"Lehmkaute 5",
    "sg:city":"Neuental",
    "sg:phone":"+49 6693/8675",
    "sg:postcode":"34599",
    "sg:province":"Hessen",
    "wof:name":"Sru Gesellschaft F\u00fcr Umwelttechnische Steuer-",
    "wof:placetype":"venue"
},
  "geometry": {"coordinates":[9.194214,50.963642],"type":"Point"}
}