{
  "type": "Feature",
  "properties": {
    "iso:country":"DE",
    "sg:address":"Waitzstr. 1",
    "sg:city":"Berlin",
    "sg:phone":"+49 30/3233957",
    "sg:postcode":"10629",
    "sg:province":"Berlin",
    "wof:name":"Estaminet",
    "wof:placetype":"venue"
},
  "geometry": {"coordinates":[13.3054847717,52.5032653809],"type":"Point"}
}