{
  "type": "Feature",
  "properties": {
    "iso:country":"DE",
    "sg:address":"Georgstr. 35a",
    "sg:city":"Lingen",
    "sg:phone":"+49 591/51933",
    "sg:postcode":"49809",
    "sg:province":"Niedersachsen",
    "wof:name":"G\u00fcnter Gewisler Masseur",
    "wof:placetype":"venue"
},
  "geometry": {"coordinates":[7.330072,52.521893],"type":"Point"}
}