{
  "type": "Feature",
  "properties": {
    "iso:country":"DE",
    "sg:address":"Richtarher Str.179",
    "sg:city":"Hilden",
    "sg:phone":"+49 2103/44358",
    "sg:postcode":"40723",
    "sg:province":"Nordrhein-Westfalen",
    "wof:name":"Sf Sw Hitdorf",
    "wof:placetype":"venue"
},
  "geometry": {"coordinates":[6.940295,51.154503],"type":"Point"}
}