{
  "type": "Feature",
  "properties": {
    "iso:country":"DE",
    "sg:address":"Amselschlag 5a",
    "sg:city":"Ro\u00dftal",
    "sg:phone":"+49 9127/7850",
    "sg:postcode":"90574",
    "sg:province":"Bayern",
    "wof:name":"Donald M. Fr\u00f6bel",
    "wof:placetype":"venue"
},
  "geometry": {"coordinates":[10.8980998993,49.3978385925],"type":"Point"}
}