{
  "type": "Feature",
  "properties": {
    "iso:country":"DE",
    "sg:address":"Schlichtweg 11",
    "sg:city":"M\u00fcnchen",
    "sg:phone":"+49 89/650743",
    "sg:postcode":"81543",
    "sg:province":"Bayern",
    "wof:name":"Tierpark",
    "wof:placetype":"venue"
},
  "geometry": {"coordinates":[11.5510959625,48.0945701599],"type":"Point"}
}