{
  "type": "Feature",
  "properties": {
    "iso:country":"DE",
    "sg:address":"Gotenstr. 7",
    "sg:city":"Bocholt",
    "sg:phone":"+49 2871/13784",
    "sg:postcode":"46395",
    "sg:province":"Nordrhein-Westfalen",
    "wof:name":"Johannes Willing",
    "wof:placetype":"venue"
},
  "geometry": {"coordinates":[6.607845,51.835205],"type":"Point"}
}