{
  "type": "Feature",
  "properties": {
    "iso:country":"DE",
    "sg:address":"Karl-Kegel-Str. 16 e",
    "sg:city":"Freiberg",
    "sg:phone":"+49 3731/73520",
    "sg:postcode":"09599",
    "sg:province":"Sachsen",
    "wof:name":"Marita Br\u00fchl",
    "wof:placetype":"venue"
},
  "geometry": {"coordinates":[13.339619,50.916958],"type":"Point"}
}