{
  "type": "Feature",
  "properties": {
    "iso:country":"DE",
    "sg:address":"Allerstr. 31",
    "sg:city":"Bornheim",
    "sg:phone":"+49 228/6024000",
    "sg:postcode":"53332",
    "sg:province":"Nordrhein-Westfalen",
    "wof:name":"M\u00d6ller Gmbh",
    "wof:placetype":"venue"
},
  "geometry": {"coordinates":[7.0434,50.7654],"type":"Point"}
}