{
  "type": "Feature",
  "properties": {
    "iso:country":"DE",
    "sg:address":"Hauptstr. 167",
    "sg:city":"Pockau",
    "sg:postcode":"09509",
    "sg:province":"Sachsen",
    "wof:name":"Ev.-luth. Kirche D\u00f6rnthal",
    "wof:placetype":"venue"
},
  "geometry": {"coordinates":[13.2714395523,50.7323112488],"type":"Point"}
}