{
  "type": "Feature",
  "properties": {
    "iso:country":"DE",
    "sg:address":"Gustedter Str. 201",
    "sg:city":"Salzgitter",
    "sg:phone":"+49 5341/871106",
    "sg:postcode":"38229",
    "sg:province":"Niedersachsen",
    "wof:name":"Cordes Gmbh",
    "wof:placetype":"venue"
},
  "geometry": {"coordinates":[10.3321781158,52.0954933167],"type":"Point"}
}