{
  "type": "Feature",
  "properties": {
    "iso:country":"DE",
    "sg:address":"Burgweg 15",
    "sg:city":"Emmendingen",
    "sg:phone":"+49 7641/8686",
    "sg:postcode":"79312",
    "sg:province":"Baden-W\u00fcrttemberg",
    "wof:name":"Hans Kunstmann Ingenieur",
    "wof:placetype":"venue"
},
  "geometry": {"coordinates":[7.8497138023,48.1249923706],"type":"Point"}
}