{
  "type": "Feature",
  "properties": {
    "iso:country":"DE",
    "sg:address":"\u00c4gidienstr. 9",
    "sg:city":"Amberg",
    "sg:phone":"+49 9621/14855",
    "sg:postcode":"92224",
    "sg:province":"Bayern",
    "wof:name":"G & M Allround Gmbh",
    "wof:placetype":"venue"
},
  "geometry": {"coordinates":[11.8875570297,49.4481430054],"type":"Point"}
}