{
  "type": "Feature",
  "properties": {
    "iso:country":"DE",
    "sg:address":"Oelder Str. 13",
    "sg:city":"Rheda-Wiedenbr\u00fcck",
    "sg:phone":"+49 5242/966160",
    "sg:postcode":"33378",
    "sg:province":"Nordrhein-Westfalen",
    "wof:name":"Gerhard Thome Architekt",
    "wof:placetype":"venue"
},
  "geometry": {"coordinates":[8.304553,51.834045],"type":"Point"}
}