{
  "type": "Feature",
  "properties": {
    "iso:country":"DE",
    "sg:address":"Sulzbacher Str. 7",
    "sg:city":"Kleinwallstadt",
    "sg:phone":"+49 6022/21696",
    "sg:postcode":"63839",
    "sg:province":"Bayern",
    "wof:name":"Wilhelm Ferstl Bau Ingenieur",
    "wof:placetype":"venue"
},
  "geometry": {"coordinates":[9.1667461395,49.878578186],"type":"Point"}
}