{
  "type": "Feature",
  "properties": {
    "iso:country":"DE",
    "sg:address":"M\u00fchlenweg 26",
    "sg:city":"Hahn",
    "sg:phone":"+49 2661/98580",
    "sg:postcode":"56472",
    "sg:province":"Rheinland-Pfalz",
    "wof:name":"H\u00f6rster B\u00fcroorganisation Gmbh",
    "wof:placetype":"venue"
},
  "geometry": {"coordinates":[7.9377617836,50.6318893433],"type":"Point"}
}