{
  "type": "Feature",
  "properties": {
    "iso:country":"DE",
    "sg:address":"Blombacher Bach 3",
    "sg:city":"Wuppertal",
    "sg:phone":"+49 202/600446",
    "sg:postcode":"42287",
    "sg:province":"Nordrhein-Westfalen",
    "wof:name":"K. Schmidt & W. Gelbrich Gbr",
    "wof:placetype":"venue"
},
  "geometry": {"coordinates":[7.232138,51.256344],"type":"Point"}
}