{
  "type": "Feature",
  "properties": {
    "iso:country":"DE",
    "sg:address":"Junkerstr. 4",
    "sg:city":"Wittingen",
    "sg:phone":"+49 5831/2068",
    "sg:postcode":"29378",
    "sg:province":"Niedersachsen",
    "wof:name":"A. Akpinar",
    "wof:placetype":"venue"
},
  "geometry": {"coordinates":[10.7361116409,52.728931427],"type":"Point"}
}