{
  "type": "Feature",
  "properties": {
    "iso:country":"DE",
    "sg:address":"Jarrestr. 80",
    "sg:city":"Hamburg",
    "sg:phone":"+49 40/2272290",
    "sg:postcode":"22303",
    "sg:province":"Hamburg",
    "wof:name":"Bpv- Architeken B\u00f6ge - Pilsinger - Veix",
    "wof:placetype":"venue"
},
  "geometry": {"coordinates":[10.030589,53.586384],"type":"Point"}
}