{
  "type": "Feature",
  "properties": {
    "iso:country":"DE",
    "sg:address":"Wachth\u00fcgelstr. 1",
    "sg:city":"Ha\u00dffurt",
    "sg:phone":"+49 9521/5985",
    "sg:postcode":"97437",
    "sg:province":"Bayern",
    "wof:name":"Willi Servatius",
    "wof:placetype":"venue"
},
  "geometry": {"coordinates":[10.5624818802,50.0528945923],"type":"Point"}
}