{
  "type": "Feature",
  "properties": {
    "iso:country":"DE",
    "sg:address":"Lindenhof",
    "sg:city":"Steinau",
    "sg:phone":"+49 6663/5008",
    "sg:postcode":"36396",
    "sg:province":"Hessen",
    "wof:name":"Pico Galvanik Und Metallwarenfabrik Gmbh",
    "wof:placetype":"venue"
},
  "geometry": {"coordinates":[9.428085,50.393116],"type":"Point"}
}