{
  "type": "Feature",
  "properties": {
    "iso:country":"DE",
    "sg:address":"Am Bahnhof",
    "sg:city":"Neustrelitz",
    "sg:phone":"+49 3981/205333",
    "sg:postcode":"17235",
    "sg:province":"Mecklenburg-Vorpommern",
    "wof:name":"W. Lipinski",
    "wof:placetype":"venue"
},
  "geometry": {"coordinates":[13.0885868073,53.3315963745],"type":"Point"}
}