{
  "type": "Feature",
  "properties": {
    "iso:country":"DE",
    "sg:address":"Kreuznacher Str. 4",
    "sg:city":"Rockenhausen",
    "sg:phone":"+49 6361/7935",
    "sg:postcode":"67806",
    "sg:province":"Rheinland-Pfalz",
    "wof:name":"H. Schmitt",
    "wof:placetype":"venue"
},
  "geometry": {"coordinates":[7.8216261864,49.6289558411],"type":"Point"}
}