{
  "type": "Feature",
  "properties": {
    "iso:country":"DE",
    "sg:address":"Am Rathaus 24",
    "sg:city":"Leutkirch",
    "sg:phone":"+49 7567/600",
    "sg:postcode":"88299",
    "sg:province":"Baden-W\u00fcrttemberg",
    "wof:name":"Dr. Med. Magdalena Schachtriek \u00c4rztin F\u00fcr Hom\u00f6opathie",
    "wof:placetype":"venue"
},
  "geometry": {"coordinates":[10.0965795517,47.7652397156],"type":"Point"}
}