{
  "type": "Feature",
  "properties": {
    "iso:country":"DE",
    "sg:address":"Humboldtallee 36",
    "sg:city":"G\u00f6ttingen",
    "sg:phone":"+49 551/399007",
    "sg:postcode":"37073",
    "sg:province":"Niedersachsen",
    "wof:name":"Universit\u00e4t G\u00f6ttingen Abt. Geschichte Der Medizin",
    "wof:placetype":"venue"
},
  "geometry": {"coordinates":[9.940687,51.544144],"type":"Point"}
}