{
  "type": "Feature",
  "properties": {
    "iso:country":"DE",
    "sg:city":"Ingolstadt",
    "sg:postcode":"85055",
    "sg:province":"Bayern",
    "wof:name":"Hotel Ammerland",
    "wof:placetype":"venue"
},
  "geometry": {"coordinates":[11.480437,48.772308],"type":"Point"}
}