{
  "type": "Feature",
  "properties": {
    "iso:country":"DE",
    "sg:address":"Wallster Weg 1",
    "sg:city":"Aurich",
    "sg:phone":"+49 4941/930010",
    "sg:postcode":"26603",
    "sg:province":"Niedersachsen",
    "wof:name":"Raiffeisen Warengenossenschaft Eg",
    "wof:placetype":"venue"
},
  "geometry": {"coordinates":[7.469514,53.471466],"type":"Point"}
}