{
  "type": "Feature",
  "properties": {
    "iso:country":"DE",
    "sg:address":"Am Blumenhof 1",
    "sg:city":"Aurich",
    "sg:phone":"+49 4947/489",
    "sg:postcode":"26607",
    "sg:province":"Niedersachsen",
    "wof:name":"Blumenhof Plaggenburg Epping & Walter",
    "wof:placetype":"venue"
},
  "geometry": {"coordinates":[7.555191,53.520508],"type":"Point"}
}