{
  "type": "Feature",
  "properties": {
    "iso:country":"DE",
    "sg:address":"Dritte Str. 19",
    "sg:city":"Neuenrade",
    "sg:phone":"+49 2392/61283",
    "sg:postcode":"58809",
    "sg:province":"Nordrhein-Westfalen",
    "wof:name":"Helmut Riecke",
    "wof:placetype":"venue"
},
  "geometry": {"coordinates":[7.780670166,51.2826423645],"type":"Point"}
}