{
  "type": "Feature",
  "properties": {
    "iso:country":"DE",
    "sg:address":"B\u00e4renweg 33",
    "sg:city":"Karlsruhe",
    "sg:phone":"+49 721/707160",
    "sg:postcode":"76149",
    "sg:province":"Baden-W\u00fcrttemberg",
    "wof:name":"Cc-gastst\u00e4tten- Betriebs Gmbh",
    "wof:placetype":"venue"
},
  "geometry": {"coordinates":[8.3813476562,49.0451698303],"type":"Point"}
}