{
  "type": "Feature",
  "properties": {
    "iso:country":"DE",
    "sg:address":"Dorfstr. 24",
    "sg:city":"\u00dcberlingen",
    "sg:phone":"+49 7551/7879",
    "sg:postcode":"88662",
    "sg:province":"Baden-W\u00fcrttemberg",
    "wof:name":"J. Schilffarth Und C. Wagner Architekten",
    "wof:placetype":"venue"
},
  "geometry": {"coordinates":[9.206061,47.793114],"type":"Point"}
}