{
  "type": "Feature",
  "properties": {
    "iso:country":"DE",
    "sg:address":"Treschklinger Str. 27-5",
    "sg:city":"Bad Rappenau",
    "sg:phone":"+49 7066/2155",
    "sg:postcode":"74906",
    "sg:province":"Baden-W\u00fcrttemberg",
    "wof:name":"Peter Terwen",
    "wof:placetype":"venue"
},
  "geometry": {"coordinates":[9.0908269882,49.2150840759],"type":"Point"}
}