{
  "type": "Feature",
  "properties": {
    "iso:country":"DE",
    "sg:address":"Plettenberger Str. 1",
    "sg:city":"Melle",
    "sg:phone":"+49 5422/5479",
    "sg:postcode":"49324",
    "sg:province":"Niedersachsen",
    "wof:name":"A. Beckmann",
    "wof:placetype":"venue"
},
  "geometry": {"coordinates":[8.3360834122,52.2016601562],"type":"Point"}
}