{
  "type": "Feature",
  "properties": {
    "iso:country":"DE",
    "sg:address":"Thyssenstr. 11",
    "sg:city":"Gersthofen",
    "sg:phone":"+49 821/473204",
    "sg:postcode":"86368",
    "sg:province":"Bayern",
    "wof:name":"Helga Schwarz Steuerberaterin",
    "wof:placetype":"venue"
},
  "geometry": {"coordinates":[10.8745212555,48.429851532],"type":"Point"}
}