{
  "type": "Feature",
  "properties": {
    "iso:country":"DE",
    "sg:address":"Diebrocker Str 315",
    "sg:city":"Herford",
    "sg:phone":"+49 5221/34080",
    "sg:postcode":"32051",
    "sg:province":"Nordrhein-Westfalen",
    "wof:name":"Strangh\u00f6ner Metalltechnik Gmbh",
    "wof:placetype":"venue"
},
  "geometry": {"coordinates":[8.61469,52.116322],"type":"Point"}
}