{
  "type": "Feature",
  "properties": {
    "iso:country":"DE",
    "sg:address":"Vogtstr. 8",
    "sg:city":"Lohne",
    "sg:phone":"+49 4442/5095",
    "sg:postcode":"49393",
    "sg:province":"Niedersachsen",
    "wof:name":"Die Zahnwerkstatt Gmbh & Co. Kg",
    "wof:placetype":"venue"
},
  "geometry": {"coordinates":[8.2349567413,52.6645240784],"type":"Point"}
}