{
  "type": "Feature",
  "properties": {
    "iso:country":"DE",
    "sg:address":"Am Elfenstein 12",
    "sg:city":"Bad Harzburg",
    "sg:phone":"+49 5322/1472",
    "sg:postcode":"38667",
    "sg:province":"Niedersachsen",
    "wof:name":"Karl-heinz M\u00fcller",
    "wof:placetype":"venue"
},
  "geometry": {"coordinates":[10.535531044,51.8788604736],"type":"Point"}
}