{
  "type": "Feature",
  "properties": {
    "iso:country":"DE",
    "sg:address":"Bellersheimerstra\u00dfe 43",
    "sg:city":"Hungen",
    "sg:phone":"+49 6402",
    "sg:postcode":"35410",
    "sg:province":"Hessen",
    "wof:name":"Karsten Hahn",
    "wof:placetype":"venue"
},
  "geometry": {"coordinates":[8.8952560425,50.447467804],"type":"Point"}
}