{
  "type": "Feature",
  "properties": {
    "iso:country":"DE",
    "sg:address":"Simon-von-Utrecht-Str. 65",
    "sg:city":"Hamburg",
    "sg:postcode":"20359",
    "sg:province":"Hamburg",
    "wof:name":"Ingenieurb\u00fcro Zieger Gmbh",
    "wof:placetype":"venue"
},
  "geometry": {"coordinates":[9.9665193558,53.5508804321],"type":"Point"}
}