{
  "type": "Feature",
  "properties": {
    "iso:country":"DE",
    "sg:address":"Rembrandtstr. 25",
    "sg:city":"Wuppertal",
    "sg:phone":"+49 202/735680",
    "sg:postcode":"42329",
    "sg:province":"Nordrhein-Westfalen",
    "wof:name":"Schirm Gmbh",
    "wof:placetype":"venue"
},
  "geometry": {"coordinates":[7.066069,51.22768],"type":"Point"}
}