{
  "type": "Feature",
  "properties": {
    "iso:country":"DE",
    "sg:address":"Timmendorfer Platz 16",
    "sg:city":"Timmendorfer Strand",
    "sg:phone":"+49 4503/2188",
    "sg:postcode":"23669",
    "sg:province":"Schleswig-Holstein",
    "wof:name":"Eis- U. Kebab-haus",
    "wof:placetype":"venue"
},
  "geometry": {"coordinates":[10.780873,53.997971],"type":"Point"}
}