{
  "type": "Feature",
  "properties": {
    "iso:country":"DE",
    "sg:address":"M\u00e4rkischer Weg 45",
    "sg:city":"Emsdetten",
    "sg:phone":"+49 2572/5951",
    "sg:postcode":"48282",
    "sg:province":"Nordrhein-Westfalen",
    "wof:name":"Egon Herbert Gmbh & Co. Kg",
    "wof:placetype":"venue"
},
  "geometry": {"coordinates":[7.549216,52.157257],"type":"Point"}
}