{
  "type": "Feature",
  "properties": {
    "iso:country":"DE",
    "sg:address":"Reitbrooker Westerdeich 70",
    "sg:city":"Hamburg",
    "sg:phone":"+49 40/7373576",
    "sg:postcode":"21037",
    "sg:province":"Hamburg",
    "wof:name":"G\u00fcnter Graf",
    "wof:placetype":"venue"
},
  "geometry": {"coordinates":[10.115546,53.471146],"type":"Point"}
}