{
  "type": "Feature",
  "properties": {
    "iso:country":"DE",
    "sg:address":"Hellerstr. 4",
    "sg:city":"Betzdorf",
    "sg:postcode":"57518",
    "sg:province":"Rheinland-Pfalz",
    "wof:name":"Behindertenwerkstatt",
    "wof:placetype":"venue"
},
  "geometry": {"coordinates":[7.874298,50.787464],"type":"Point"}
}