{
  "type": "Feature",
  "properties": {
    "iso:country":"DE",
    "sg:address":"Zechenstr. 69",
    "sg:city":"Unna",
    "sg:phone":"+49 2303/68386",
    "sg:postcode":"59425",
    "sg:province":"Nordrhein-Westfalen",
    "wof:name":"Gerd Solty",
    "wof:placetype":"venue"
},
  "geometry": {"coordinates":[7.6988329887,51.5556106567],"type":"Point"}
}