{
  "type": "Feature",
  "properties": {
    "iso:country":"DE",
    "sg:address":"Baiertaler Str 98",
    "sg:city":"Wiesloch",
    "sg:phone":"+49 6222/67990",
    "sg:postcode":"69168",
    "sg:province":"Baden-W\u00fcrttemberg",
    "wof:name":"Akb Gmbh Apparate- Und Kesselbau",
    "wof:placetype":"venue"
},
  "geometry": {"coordinates":[8.7211399078,49.2992362976],"type":"Point"}
}