{
  "type": "Feature",
  "properties": {
    "iso:country":"DE",
    "sg:address":"Albert-Schweitzer-Str. 6",
    "sg:city":"Bad Arolsen",
    "sg:phone":"+49 5691/50112",
    "sg:postcode":"34454",
    "sg:province":"Hessen",
    "wof:name":"Lydia Gerlach",
    "wof:placetype":"venue"
},
  "geometry": {"coordinates":[9.0073518753,51.3755645752],"type":"Point"}
}