{
  "type": "Feature",
  "properties": {
    "iso:country":"DE",
    "sg:address":"Waldweg",
    "sg:city":"Zeitz",
    "sg:phone":"+49 3441/221308",
    "sg:postcode":"06712",
    "sg:province":"Sachsen-Anhalt",
    "wof:name":"Rhodos Inh. Helga Wolf",
    "wof:placetype":"venue"
},
  "geometry": {"coordinates":[12.1206026077,51.0395507812],"type":"Point"}
}