{
  "type": "Feature",
  "properties": {
    "iso:country":"DE",
    "sg:address":"Lenaustr. 12",
    "sg:city":"Fellbach",
    "sg:postcode":"70736",
    "sg:province":"Baden-W\u00fcrttemberg",
    "wof:name":"Top Fit Naturkost",
    "wof:placetype":"venue"
},
  "geometry": {"coordinates":[9.2606830597,48.8438949585],"type":"Point"}
}