{
  "type": "Feature",
  "properties": {
    "iso:country":"DE",
    "sg:address":"Schl\u00e4gelstr. 68",
    "sg:city":"Oberhausen",
    "sg:phone":"+49 208/26698",
    "sg:postcode":"46045",
    "sg:province":"Nordrhein-Westfalen",
    "wof:name":"K.-h. Kr\u00fcger",
    "wof:placetype":"venue"
},
  "geometry": {"coordinates":[6.847192,51.464504],"type":"Point"}
}