{
  "type": "Feature",
  "properties": {
    "iso:country":"DE",
    "sg:address":"Schlesische Str. 3",
    "sg:city":"Gie\u00dfen",
    "sg:phone":"+49 641/491120",
    "sg:postcode":"35394",
    "sg:province":"Hessen",
    "wof:name":"Benno Koltermann Steuerberater",
    "wof:placetype":"venue"
},
  "geometry": {"coordinates":[8.6978912354,50.5801391602],"type":"Point"}
}