{
  "type": "Feature",
  "properties": {
    "iso:country":"DE",
    "sg:address":"Rochlitzer Str. 28",
    "sg:city":"Bad Lausick",
    "sg:phone":"+49 34345/3106",
    "sg:postcode":"04651",
    "sg:province":"Sachsen",
    "wof:name":"Tageskaffee Inh. T. Kohlmann",
    "wof:placetype":"venue"
},
  "geometry": {"coordinates":[12.646446,51.142132],"type":"Point"}
}