{
  "type": "Feature",
  "properties": {
    "iso:country":"DE",
    "sg:address":"Maubisstr. 42",
    "sg:city":"Kaarst",
    "sg:phone":"+49 2131/61980",
    "sg:postcode":"41564",
    "sg:province":"Nordrhein-Westfalen",
    "wof:name":"Dieter Christoph Architekt",
    "wof:placetype":"venue"
},
  "geometry": {"coordinates":[6.620276,51.227711],"type":"Point"}
}