{
  "type": "Feature",
  "properties": {
    "iso:country":"DE",
    "sg:address":"Rodendamm 3",
    "sg:city":"Stuhr",
    "sg:phone":"+49 421/809560",
    "sg:postcode":"28816",
    "sg:province":"Niedersachsen",
    "wof:name":"Aha Sportversand Handels-gmbh",
    "wof:placetype":"venue"
},
  "geometry": {"coordinates":[8.7894115448,53.0197181702],"type":"Point"}
}