{
  "type": "Feature",
  "properties": {
    "iso:country":"DE",
    "sg:address":"Liekweger Str. 42",
    "sg:city":"Nienst\u00e4dt",
    "sg:phone":"+49 5721/80150",
    "sg:postcode":"31688",
    "sg:province":"Niedersachsen",
    "wof:name":"R. Baue & J. Griffel",
    "wof:placetype":"venue"
},
  "geometry": {"coordinates":[9.1777858734,52.2866172791],"type":"Point"}
}