{
  "type": "Feature",
  "properties": {
    "iso:country":"DE",
    "sg:address":"Pfahlgraben 4",
    "sg:city":"Bad Ems",
    "sg:phone":"+49 2603/3150",
    "sg:postcode":"56130",
    "sg:province":"Rheinland-Pfalz",
    "wof:name":"Helmut Reinig",
    "wof:placetype":"venue"
},
  "geometry": {"coordinates":[7.730927,50.331104],"type":"Point"}
}