{
  "type": "Feature",
  "properties": {
    "iso:country":"DE",
    "sg:address":"Schwanenstr. 8",
    "sg:city":"Mannheim",
    "sg:postcode":"68259",
    "sg:province":"Baden-W\u00fcrttemberg",
    "wof:name":"Liebenzeller Gemeinde Mannheim Feudenheim",
    "wof:placetype":"venue"
},
  "geometry": {"coordinates":[8.526232,49.486794],"type":"Point"}
}