{
  "type": "Feature",
  "properties": {
    "iso:country":"DE",
    "sg:address":"Rotdornweg 8",
    "sg:city":"Walsrode",
    "sg:phone":"+49 5161/910410",
    "sg:postcode":"29664",
    "sg:province":"Niedersachsen",
    "wof:name":"Jozitech Medizinische Handelsgesellschaft Mbh",
    "wof:placetype":"venue"
},
  "geometry": {"coordinates":[9.579263,52.8536],"type":"Point"}
}