{
  "type": "Feature",
  "properties": {
    "iso:country":"DE",
    "sg:address":"Parkstr. 10B",
    "sg:city":"Zwickau",
    "sg:phone":"+49 375/2040979",
    "sg:postcode":"08056",
    "sg:province":"Sachsen",
    "wof:name":"Birgit Zierhold",
    "wof:placetype":"venue"
},
  "geometry": {"coordinates":[12.4864492416,50.7157554626],"type":"Point"}
}