{
  "type": "Feature",
  "properties": {
    "iso:country":"DE",
    "sg:address":"Uhlandstr. 27",
    "sg:city":"Berlin",
    "sg:phone":"+49 30/88551703",
    "sg:postcode":"10719",
    "sg:province":"Berlin",
    "wof:name":"Eckart Fleischmann Rechtsanwalt",
    "wof:placetype":"venue"
},
  "geometry": {"coordinates":[13.3249902725,52.5020904541],"type":"Point"}
}