{
  "type": "Feature",
  "properties": {
    "iso:country":"DE",
    "sg:address":"Meyerstr. 35",
    "sg:city":"Weimar",
    "sg:phone":"+49 3643/202804",
    "sg:postcode":"99423",
    "sg:province":"Th\u00fcringen",
    "wof:name":"Alubau R. Findeisen",
    "wof:placetype":"venue"
},
  "geometry": {"coordinates":[11.327988,50.98925],"type":"Point"}
}