{
  "type": "Feature",
  "properties": {
    "iso:country":"DE",
    "sg:address":"Kurhausstr. 24",
    "sg:city":"Bad Kissingen",
    "sg:phone":"+49 971/3115",
    "sg:postcode":"97688",
    "sg:province":"Bayern",
    "wof:name":"Kurheim Salfner",
    "wof:placetype":"venue"
},
  "geometry": {"coordinates":[10.0779495239,50.1917190552],"type":"Point"}
}