{
  "type": "Feature",
  "properties": {
    "iso:country":"DE",
    "sg:address":"Mainzer Str. 183",
    "sg:city":"Bonn",
    "sg:phone":"+49 228/347095",
    "sg:postcode":"53179",
    "sg:province":"Nordrhein-Westfalen",
    "wof:name":"Raili Ilves",
    "wof:placetype":"venue"
},
  "geometry": {"coordinates":[7.191884,50.661415],"type":"Point"}
}