{
  "type": "Feature",
  "properties": {
    "iso:country":"DE",
    "sg:address":"Ameisenbergstr. 26",
    "sg:city":"Stuttgart",
    "sg:phone":"+49 711/2623474",
    "sg:postcode":"70188",
    "sg:province":"Baden-W\u00fcrttemberg",
    "wof:name":"Therapeutikum Christophorus",
    "wof:placetype":"venue"
},
  "geometry": {"coordinates":[9.197534,48.784184],"type":"Point"}
}