{
  "type": "Feature",
  "properties": {
    "iso:country":"DE",
    "sg:address":"K\u00f6lner Str. 64",
    "sg:city":"Leverkusen",
    "sg:phone":"+49 2171/46418",
    "sg:postcode":"51379",
    "sg:province":"Nordrhein-Westfalen",
    "wof:name":"La Baguette",
    "wof:placetype":"venue"
},
  "geometry": {"coordinates":[7.0035099983,51.0634384155],"type":"Point"}
}