{
  "type": "Feature",
  "properties": {
    "iso:country":"DE",
    "sg:address":"Schmerlerstr. 35",
    "sg:city":"F\u00fcrth",
    "sg:phone":"+49 911/722099",
    "sg:postcode":"90768",
    "sg:province":"Bayern",
    "wof:name":"Gert Maih\u00f6fner",
    "wof:placetype":"venue"
},
  "geometry": {"coordinates":[10.953074,49.472572],"type":"Point"}
}