{
  "type": "Feature",
  "properties": {
    "iso:country":"DE",
    "sg:address":"P\u00fcttlachweg 10",
    "sg:city":"N\u00fcrnberg",
    "sg:phone":"+49 911/674221",
    "sg:postcode":"90449",
    "sg:province":"Bayern",
    "wof:name":"Karl Wittmann",
    "wof:placetype":"venue"
},
  "geometry": {"coordinates":[11.0107622147,49.4278526306],"type":"Point"}
}