{
  "type": "Feature",
  "properties": {
    "iso:country":"DE",
    "sg:address":"Am Ellernkamp 17",
    "sg:city":"Bielefeld",
    "sg:phone":"+49 521/23212",
    "sg:postcode":"33604",
    "sg:province":"Nordrhein-Westfalen",
    "wof:name":"Heinz St\u00f6rmer",
    "wof:placetype":"venue"
},
  "geometry": {"coordinates":[8.556738,52.005863],"type":"Point"}
}