{
  "type": "Feature",
  "properties": {
    "iso:country":"DE",
    "sg:address":"Hanauer Str. 8",
    "sg:city":"N\u00fcrnberg",
    "sg:phone":"+49 911/302693",
    "sg:postcode":"90427",
    "sg:province":"Bayern",
    "wof:name":"Henrik Verny Tennislehrer",
    "wof:placetype":"venue"
},
  "geometry": {"coordinates":[11.0072517395,49.5253372192],"type":"Point"}
}