{
  "type": "Feature",
  "properties": {
    "iso:country":"DE",
    "sg:address":"Erich-M\u00fchsam-Str. 2",
    "sg:city":"Chemnitz",
    "sg:phone":"+49 371/305431",
    "sg:postcode":"09112",
    "sg:province":"Sachsen",
    "wof:name":"Agnes Gremm",
    "wof:placetype":"venue"
},
  "geometry": {"coordinates":[12.8985729218,50.8340911865],"type":"Point"}
}