{
  "type": "Feature",
  "properties": {
    "iso:country":"DE",
    "sg:address":"Am Wirthemb\u00f6sch 18",
    "sg:city":"St. Wendel",
    "sg:phone":"+49 6851/81000",
    "sg:postcode":"66606",
    "sg:province":"Saarland",
    "wof:name":"Horst Hamburger Ingenieur",
    "wof:placetype":"venue"
},
  "geometry": {"coordinates":[7.1594929695,49.4645881653],"type":"Point"}
}