{
  "type": "Feature",
  "properties": {
    "iso:country":"DE",
    "sg:address":"Markt 45",
    "sg:city":"Lutherstadt Eisleben",
    "sg:phone":"+49 3475/696330",
    "sg:postcode":"06295",
    "sg:province":"Sachsen-Anhalt",
    "wof:name":"Video Aktuell Ohg",
    "wof:placetype":"venue"
},
  "geometry": {"coordinates":[11.5477466583,51.5280914307],"type":"Point"}
}