{
  "type": "Feature",
  "properties": {
    "iso:country":"DE",
    "sg:address":"Marienstr. 22",
    "sg:city":"Offenbach",
    "sg:phone":"+49 69/841532",
    "sg:postcode":"63069",
    "sg:province":"Hessen",
    "wof:name":"B. Fuchs",
    "wof:placetype":"venue"
},
  "geometry": {"coordinates":[8.7634143829,50.099067688],"type":"Point"}
}