{
  "type": "Feature",
  "properties": {
    "iso:country":"DE",
    "sg:address":"Fraunhoferstr. 12",
    "sg:city":"M\u00fchldorf",
    "sg:phone":"+49 8631/2205",
    "sg:postcode":"84453",
    "sg:province":"Bayern",
    "wof:name":"G. Sturm",
    "wof:placetype":"venue"
},
  "geometry": {"coordinates":[12.5311450958,48.2610435486],"type":"Point"}
}