{
  "type": "Feature",
  "properties": {
    "iso:country":"DE",
    "sg:address":"Kolbermoorer Str. 52 a",
    "sg:city":"Bad Aibling",
    "sg:phone":"+49 8061/2584",
    "sg:postcode":"83043",
    "sg:province":"Bayern",
    "wof:name":"Hansj\u00f6rg Derx Gmbh",
    "wof:placetype":"venue"
},
  "geometry": {"coordinates":[12.025220871,47.8594703674],"type":"Point"}
}