{
  "type": "Feature",
  "properties": {
    "iso:country":"DE",
    "sg:address":"Lettenfeld 2",
    "sg:city":"Bargstedt",
    "sg:phone":"+49 4164/1243",
    "sg:postcode":"21698",
    "sg:province":"Niedersachsen",
    "wof:name":"Lothar Neumann Gmbh",
    "wof:placetype":"venue"
},
  "geometry": {"coordinates":[9.428297,53.46133],"type":"Point"}
}