{
  "type": "Feature",
  "properties": {
    "iso:country":"DE",
    "sg:address":"Kirchplatz 2",
    "sg:city":"Hirschaid",
    "sg:phone":"+49 9543/277",
    "sg:postcode":"96114",
    "sg:province":"Bayern",
    "wof:name":"Kath. Pfarramt St. Vitus",
    "wof:placetype":"venue"
},
  "geometry": {"coordinates":[10.9887800217,49.8164520264],"type":"Point"}
}