{
  "type": "Feature",
  "properties": {
    "iso:country":"DE",
    "sg:address":"Friedrich-Ebert-Str. 19",
    "sg:city":"Nordenham",
    "sg:phone":"+49 4731/22712",
    "sg:postcode":"26954",
    "sg:province":"Niedersachsen",
    "wof:name":"Dorothee Sauerbaum Rechtsanw\u00e4ltin Und Notarin",
    "wof:placetype":"venue"
},
  "geometry": {"coordinates":[8.4837007523,53.5104751587],"type":"Point"}
}