{
  "type": "Feature",
  "properties": {
    "iso:country":"DE",
    "sg:address":"Spiegelsgasse 7",
    "sg:city":"Erding",
    "sg:phone":"+49 8122",
    "sg:postcode":"85435",
    "sg:province":"Bayern",
    "wof:name":"Ferienmarkt2000",
    "wof:placetype":"venue"
},
  "geometry": {"coordinates":[11.907616,48.305286],"type":"Point"}
}