{
  "type": "Feature",
  "properties": {
    "iso:country":"DE",
    "sg:address":"Hammfelddamm 6",
    "sg:city":"Neuss",
    "sg:phone":"+49 2131/1220",
    "sg:postcode":"41460",
    "sg:province":"Nordrhein-Westfalen",
    "wof:name":"Mercedes-benz Finanz Gmbh",
    "wof:placetype":"venue"
},
  "geometry": {"coordinates":[6.710556,51.193851],"type":"Point"}
}