{
  "type": "Feature",
  "properties": {
    "iso:country":"DE",
    "sg:address":"Grabenstr. 1",
    "sg:city":"Zell",
    "sg:phone":"+49 4978/358026",
    "sg:postcode":"77736",
    "sg:province":"Baden-W\u00fcrttemberg",
    "wof:name":"Volksbank Zell-oberharmersbach Eg",
    "wof:placetype":"venue"
},
  "geometry": {"coordinates":[8.063097,48.345928],"type":"Point"}
}