{
  "type": "Feature",
  "properties": {
    "iso:country":"DE",
    "sg:address":"Hofener Str. 40",
    "sg:city":"Fellbach",
    "sg:phone":"+49 711/512009",
    "sg:postcode":"70736",
    "sg:province":"Baden-W\u00fcrttemberg",
    "wof:name":"Venturi-vertrieb",
    "wof:placetype":"venue"
},
  "geometry": {"coordinates":[9.2572345734,48.8431663513],"type":"Point"}
}