{
  "type": "Feature",
  "properties": {
    "iso:country":"DE",
    "sg:address":"Dieselstr. 26-34",
    "sg:city":"Wolfsburg",
    "sg:phone":"+49 5361/53328",
    "sg:postcode":"38446",
    "sg:province":"Niedersachsen",
    "wof:name":"Stadt Wolfsburg",
    "wof:placetype":"venue"
},
  "geometry": {"coordinates":[10.8050413132,52.4269561768],"type":"Point"}
}