{
  "type": "Feature",
  "properties": {
    "iso:country":"DE",
    "sg:address":"Menzinger Str. 141a",
    "sg:city":"M\u00fcnchen",
    "sg:phone":"+49 89/8114604",
    "sg:postcode":"80997",
    "sg:province":"Bayern",
    "wof:name":"Dr. Thomas Kreppel Rechtsanwalt",
    "wof:placetype":"venue"
},
  "geometry": {"coordinates":[11.4774837494,48.1735038757],"type":"Point"}
}