{
  "type": "Feature",
  "properties": {
    "iso:country":"DE",
    "sg:address":"Willi-Zander-Str. 8",
    "sg:city":"Emden",
    "sg:postcode":"26723",
    "sg:province":"Niedersachsen",
    "wof:name":"Lwh Elektrotechnik Gmbh",
    "wof:placetype":"venue"
},
  "geometry": {"coordinates":[7.1884608269,53.3398704529],"type":"Point"}
}