{
  "type": "Feature",
  "properties": {
    "iso:country":"DE",
    "sg:address":"Detlev-Bremer-Str. 41",
    "sg:city":"Hamburg",
    "sg:phone":"+49 40/3194722",
    "sg:postcode":"20359",
    "sg:province":"Hamburg",
    "wof:name":"Posthorn",
    "wof:placetype":"venue"
},
  "geometry": {"coordinates":[9.9650888443,53.5506057739],"type":"Point"}
}