{
  "type": "Feature",
  "properties": {
    "iso:country":"DE",
    "sg:address":"Ro\u00dfmarkt 3",
    "sg:city":"Zeitz",
    "sg:phone":"+49 3441/713891",
    "sg:postcode":"06712",
    "sg:province":"Sachsen-Anhalt",
    "wof:name":"Apotheke Am Ro\u00dfmarkt",
    "wof:placetype":"venue"
},
  "geometry": {"coordinates":[12.132962,51.049843],"type":"Point"}
}