{
  "type": "Feature",
  "properties": {
    "iso:country":"DE",
    "sg:address":"Hauptstr. 142",
    "sg:city":"Schwegenheim",
    "sg:phone":"+49 6344/2471",
    "sg:postcode":"67365",
    "sg:province":"Rheinland-Pfalz",
    "wof:name":"Klaus Lehr Architekt",
    "wof:placetype":"venue"
},
  "geometry": {"coordinates":[8.321545,49.266354],"type":"Point"}
}