{
  "type": "Feature",
  "properties": {
    "iso:country":"DE",
    "sg:address":"Bergstr. 1",
    "sg:city":"Frankenhardt",
    "sg:phone":"+49 7959/925700",
    "sg:postcode":"74586",
    "sg:province":"Baden-W\u00fcrttemberg",
    "wof:name":"Werbeatelier Ziegler-naerum",
    "wof:placetype":"venue"
},
  "geometry": {"coordinates":[9.9818868637,49.0830497742],"type":"Point"}
}