{
  "type": "Feature",
  "properties": {
    "iso:country":"DE",
    "sg:address":"Demminer Str. 40d",
    "sg:city":"Anklam",
    "sg:phone":"+49 3971/210005",
    "sg:postcode":"17389",
    "sg:province":"Mecklenburg-Vorpommern",
    "wof:name":"Hartmut Rauchmann",
    "wof:placetype":"venue"
},
  "geometry": {"coordinates":[13.673858,53.852615],"type":"Point"}
}