{
  "type": "Feature",
  "properties": {
    "iso:country":"DE",
    "sg:address":"Halker Zeile 62",
    "sg:city":"Berlin",
    "sg:phone":"+49 30/7426002",
    "sg:postcode":"12305",
    "sg:province":"Berlin",
    "wof:name":"H\u00fcbner & Koch",
    "wof:placetype":"venue"
},
  "geometry": {"coordinates":[13.3965234756,52.4066467285],"type":"Point"}
}