{
  "type": "Feature",
  "properties": {
    "iso:country":"DE",
    "sg:address":"Darmst\u00e4dter Str. 62",
    "sg:city":"Ober-Ramstadt",
    "sg:phone":"+49 6154/2164",
    "sg:postcode":"64372",
    "sg:province":"Hessen",
    "wof:name":"Apotheke Am Markt Helmut Grewe E. K.",
    "wof:placetype":"venue"
},
  "geometry": {"coordinates":[8.748115,49.826813],"type":"Point"}
}