{
  "type": "Feature",
  "properties": {
    "iso:country":"DE",
    "sg:address":"Hauptstr. 26",
    "sg:city":"Jettingen-Scheppach",
    "sg:phone":"+49 8225/693",
    "sg:postcode":"89343",
    "sg:province":"Bayern",
    "wof:name":"Josef Wengenmayer",
    "wof:placetype":"venue"
},
  "geometry": {"coordinates":[10.44029,48.39864],"type":"Point"}
}