{
  "type": "Feature",
  "properties": {
    "iso:country":"DE",
    "sg:address":"Elsa-Brandstr\u00f6m-Str. 2",
    "sg:city":"Neugersdorf",
    "sg:postcode":"02727",
    "sg:province":"Sachsen",
    "wof:name":"Dachdeckerei Keil & Ziesche Gmbh",
    "wof:placetype":"venue"
},
  "geometry": {"coordinates":[14.6136236191,50.9852142334],"type":"Point"}
}