{
  "type": "Feature",
  "properties": {
    "iso:country":"DE",
    "sg:address":"Geschwister-Scholl-Str. 52",
    "sg:city":"Unterma\u00dffeld",
    "sg:postcode":"98617",
    "sg:province":"Th\u00fcringen",
    "wof:name":"Sabines Einkaufsland Teppich- Und Textilhandel",
    "wof:placetype":"venue"
},
  "geometry": {"coordinates":[10.4136228561,50.5312728882],"type":"Point"}
}