{
  "type": "Feature",
  "properties": {
    "iso:country":"DE",
    "sg:address":"M\u00fcnsterstr. 2 c",
    "sg:city":"Castrop-Rauxel",
    "sg:phone":"+49 2305/921210",
    "sg:postcode":"44575",
    "sg:province":"Nordrhein-Westfalen",
    "wof:name":"Wolfgang Enk Gmbh",
    "wof:placetype":"venue"
},
  "geometry": {"coordinates":[7.3103499413,51.5506706238],"type":"Point"}
}