{
  "type": "Feature",
  "properties": {
    "iso:country":"DE",
    "sg:address":"Dalbke 2",
    "sg:city":"Kalletal",
    "sg:phone":"+49 5264/8443",
    "sg:postcode":"32689",
    "sg:province":"Nordrhein-Westfalen",
    "wof:name":"Pension Erich Saak",
    "wof:placetype":"venue"
},
  "geometry": {"coordinates":[8.9441890717,52.1261024475],"type":"Point"}
}