{
  "type": "Feature",
  "properties": {
    "iso:country":"DE",
    "sg:address":"Nibelungenstr. 124 Sch\u00f6nberg",
    "sg:city":"Bensheim",
    "sg:phone":"+49 4962/511310",
    "sg:postcode":"64625",
    "sg:province":"Hessen",
    "wof:name":"Christoffel-blindenmission E.v.",
    "wof:placetype":"venue"
},
  "geometry": {"coordinates":[8.622493,49.682781],"type":"Point"}
}