{
  "type": "Feature",
  "properties": {
    "iso:country":"DE",
    "sg:address":"Am Schwarzenberg 16",
    "sg:city":"W\u00fcrzburg",
    "sg:phone":"+49 931/24186",
    "sg:postcode":"97078",
    "sg:province":"Bayern",
    "wof:name":"Kurt Maisch Architekt",
    "wof:placetype":"venue"
},
  "geometry": {"coordinates":[9.960534,49.812782],"type":"Point"}
}