{
  "type": "Feature",
  "properties": {
    "iso:country":"DE",
    "sg:address":"Senkingstr. 1-3",
    "sg:city":"Hildesheim",
    "sg:postcode":"31137",
    "sg:province":"Niedersachsen",
    "wof:name":"Giftge Consult Gmbh",
    "wof:placetype":"venue"
},
  "geometry": {"coordinates":[9.9409694672,52.1578826904],"type":"Point"}
}