{
  "type": "Feature",
  "properties": {
    "iso:country":"DE",
    "sg:address":"Kaiserstr. 58-2",
    "sg:city":"Rastatt",
    "sg:phone":"+49 7222/200957",
    "sg:postcode":"76437",
    "sg:province":"Baden-W\u00fcrttemberg",
    "wof:name":"Manfred Resch Anlageberater",
    "wof:placetype":"venue"
},
  "geometry": {"coordinates":[8.1998939514,48.860622406],"type":"Point"}
}