{
  "type": "Feature",
  "properties": {
    "iso:country":"DE",
    "sg:address":"L\u00fcbnitzer Str. 27a",
    "sg:city":"Belzig",
    "sg:phone":"+49 33841/8359",
    "sg:postcode":"14806",
    "sg:province":"Brandenburg",
    "wof:name":"H.-p. Henkel Steuerberater",
    "wof:placetype":"venue"
},
  "geometry": {"coordinates":[12.5801010132,52.1434631348],"type":"Point"}
}