{
  "type": "Feature",
  "properties": {
    "iso:country":"DE",
    "sg:address":"S\u00fcdendstra\u00dfe 31-33",
    "sg:city":"Berlin",
    "sg:phone":"+49 30",
    "sg:postcode":"12169",
    "sg:province":"Berlin",
    "wof:name":"Rossoll-feuerung Gmbh Heizung Sanit\u00e4r",
    "wof:placetype":"venue"
},
  "geometry": {"coordinates":[13.336256,52.455269],"type":"Point"}
}