{
  "type": "Feature",
  "properties": {
    "iso:country":"DE",
    "sg:address":"Wormser Landstr. 196",
    "sg:city":"Speyer",
    "sg:phone":"+49 6232/640079",
    "sg:postcode":"67346",
    "sg:province":"Rheinland-Pfalz",
    "wof:name":"John Smart Lagerdirektverkauf Gmbh",
    "wof:placetype":"venue"
},
  "geometry": {"coordinates":[8.429183,49.33849],"type":"Point"}
}