{
  "type": "Feature",
  "properties": {
    "iso:country":"DE",
    "sg:address":"Brinkstr. 28",
    "sg:city":"Borken",
    "sg:phone":"+49 2861/602720",
    "sg:postcode":"46325",
    "sg:province":"Nordrhein-Westfalen",
    "wof:name":"L. Wischerhoff",
    "wof:placetype":"venue"
},
  "geometry": {"coordinates":[6.8564648628,51.8447494507],"type":"Point"}
}