{
  "type": "Feature",
  "properties": {
    "iso:country":"DE",
    "sg:address":"Bahnhofstr. 7",
    "sg:city":"Lauingen",
    "sg:phone":"+49 9072/2566",
    "sg:postcode":"89415",
    "sg:province":"Bayern",
    "wof:name":"Kraus Gmbh",
    "wof:placetype":"venue"
},
  "geometry": {"coordinates":[10.4259147644,48.5743408203],"type":"Point"}
}