{
  "type": "Feature",
  "properties": {
    "iso:country":"DE",
    "sg:address":"Otto-Lilienthal-Str. 18",
    "sg:city":"Markdorf",
    "sg:phone":"+49 7544/5050",
    "sg:postcode":"88677",
    "sg:province":"Baden-W\u00fcrttemberg",
    "wof:name":"J. Wagner Gmbh",
    "wof:placetype":"venue"
},
  "geometry": {"coordinates":[9.4016752243,47.7075996399],"type":"Point"}
}