{
  "type": "Feature",
  "properties": {
    "iso:country":"DE",
    "sg:address":"Alte Bottroper Str. 92",
    "sg:city":"Essen",
    "sg:phone":"+49 201/613030",
    "sg:postcode":"45356",
    "sg:province":"Nordrhein-Westfalen",
    "wof:name":"Tekonet Medien Gmbh",
    "wof:placetype":"venue"
},
  "geometry": {"coordinates":[6.9573869705,51.4896354675],"type":"Point"}
}