{
  "type": "Feature",
  "properties": {
    "iso:country":"DE",
    "sg:address":"Bahnhofstr.",
    "sg:city":"Schopsdorf",
    "sg:postcode":"39291",
    "sg:province":"Sachsen-Anhalt",
    "wof:name":"Mutterkuhhaltung Schopsdorf Gmbh",
    "wof:placetype":"venue"
},
  "geometry": {"coordinates":[12.224446,52.236019],"type":"Point"}
}