{
  "type": "Feature",
  "properties": {
    "iso:country":"DE",
    "sg:address":"Lange Str. 56",
    "sg:city":"Essen",
    "sg:phone":"+49 5434/1027",
    "sg:postcode":"49632",
    "sg:province":"Niedersachsen",
    "wof:name":"Garrell Verwaltungs- Und Beteiligungsgesellschaft Mbh",
    "wof:placetype":"venue"
},
  "geometry": {"coordinates":[7.95455,52.722912],"type":"Point"}
}