{
  "type": "Feature",
  "properties": {
    "iso:country":"DE",
    "sg:address":"Winzerweg 4",
    "sg:city":"Kirchroth",
    "sg:phone":"+49 9428/8226",
    "sg:postcode":"94356",
    "sg:province":"Bayern",
    "wof:name":"H. Egle",
    "wof:placetype":"venue"
},
  "geometry": {"coordinates":[12.499761,48.975609],"type":"Point"}
}