{
  "type": "Feature",
  "properties": {
    "iso:country":"DE",
    "sg:address":"Hospitalstr. 5",
    "sg:city":"Nienburg",
    "sg:phone":"+49 34721/22594",
    "sg:postcode":"06429",
    "sg:province":"Sachsen-Anhalt",
    "wof:name":"Evangelisches Pfarramt Hospital",
    "wof:placetype":"venue"
},
  "geometry": {"coordinates":[11.769377,51.834446],"type":"Point"}
}