{
  "type": "Feature",
  "properties": {
    "iso:country":"DE",
    "sg:address":"Breitengraserstr. 6",
    "sg:city":"Nuernberg",
    "sg:phone":"+49 911",
    "sg:postcode":"90482",
    "sg:province":"Bayern",
    "wof:name":"Kewo - Exquisit, Ofenfrische Kundengeschenke",
    "wof:placetype":"venue"
},
  "geometry": {"coordinates":[11.123256,49.456585],"type":"Point"}
}