{
  "type": "Feature",
  "properties": {
    "iso:country":"DE",
    "sg:address":"Spitalgasse 15",
    "sg:city":"W\u00fcrzburg",
    "sg:phone":"+49 931/4502567",
    "sg:postcode":"97082",
    "sg:province":"Bayern",
    "wof:name":"Artwerk Gmbh",
    "wof:placetype":"venue"
},
  "geometry": {"coordinates":[9.9236049652,49.792049408],"type":"Point"}
}