{
  "type": "Feature",
  "properties": {
    "iso:country":"DE",
    "sg:address":"Rauscher Str. 6",
    "sg:city":"Herrsching",
    "sg:phone":"+49 8152/3603",
    "sg:postcode":"82211",
    "sg:province":"Bayern",
    "wof:name":"Kornelia Zangl",
    "wof:placetype":"venue"
},
  "geometry": {"coordinates":[11.1628742218,48.00963974],"type":"Point"}
}