{
  "type": "Feature",
  "properties": {
    "iso:country":"DE",
    "sg:address":"Postfach 1546",
    "sg:city":"Meppen",
    "sg:phone":"+49 5932/2091",
    "sg:postcode":"49705",
    "sg:province":"Niedersachsen",
    "wof:name":"Kraftwerk Meppen",
    "wof:placetype":"venue"
},
  "geometry": {"coordinates":[7.29116,52.687511],"type":"Point"}
}