{
  "type": "Feature",
  "properties": {
    "iso:country":"DE",
    "sg:address":"Hoest 54",
    "sg:city":"Ennigerloh",
    "sg:phone":"+49 2524/2133",
    "sg:postcode":"59320",
    "sg:province":"Nordrhein-Westfalen",
    "wof:name":"M. Zimmermeyer Metallverarbeitungs Gmbh",
    "wof:placetype":"venue"
},
  "geometry": {"coordinates":[8.071843,51.830761],"type":"Point"}
}