{
  "type": "Feature",
  "properties": {
    "iso:country":"DE",
    "sg:address":"Schlesische Str. 61",
    "sg:city":"Straubing",
    "sg:phone":"+49 9421/60809",
    "sg:postcode":"94315",
    "sg:province":"Bayern",
    "wof:name":"L. Wandersleb",
    "wof:placetype":"venue"
},
  "geometry": {"coordinates":[12.5980167389,48.8871498108],"type":"Point"}
}