{
  "type": "Feature",
  "properties": {
    "iso:country":"DE",
    "sg:address":"Zum Hohlen Berg 27",
    "sg:city":"Wehringen",
    "sg:phone":"+49 8234/2901",
    "sg:postcode":"86517",
    "sg:province":"Bayern",
    "wof:name":"Theodor Rupp",
    "wof:placetype":"venue"
},
  "geometry": {"coordinates":[10.7982654572,48.2387199402],"type":"Point"}
}