{
  "type": "Feature",
  "properties": {
    "iso:country":"DE",
    "sg:address":"Am Kalverkamp 15",
    "sg:city":"Oelde",
    "sg:phone":"+49 2522/2808",
    "sg:postcode":"59302",
    "sg:province":"Nordrhein-Westfalen",
    "wof:name":"Werner Kamphusmann",
    "wof:placetype":"venue"
},
  "geometry": {"coordinates":[8.1440105438,51.820438385],"type":"Point"}
}