{
  "type": "Feature",
  "properties": {
    "iso:country":"DE",
    "sg:address":"August-Bebel-Str. 84",
    "sg:city":"Bielefeld",
    "sg:phone":"+49 521/172728",
    "sg:postcode":"33602",
    "sg:province":"Nordrhein-Westfalen",
    "wof:name":"Us-bundeswehr- Und Freizeit-shop Bielefeld",
    "wof:placetype":"venue"
},
  "geometry": {"coordinates":[8.539594,52.02494],"type":"Point"}
}