{
  "type": "Feature",
  "properties": {
    "iso:country":"DE",
    "sg:address":"Goldtalstr. 4",
    "sg:city":"Bad Abbach",
    "sg:phone":"+49 9405/95420",
    "sg:postcode":"93077",
    "sg:province":"Bayern",
    "wof:name":"Alfred Beck Verwaltungsges. Mbh",
    "wof:placetype":"venue"
},
  "geometry": {"coordinates":[12.052963,48.937679],"type":"Point"}
}