{
  "type": "Feature",
  "properties": {
    "iso:country":"DE",
    "sg:address":"Klapperstr. 31",
    "sg:city":"D\u00fcren",
    "sg:phone":"+49 2421/84155",
    "sg:postcode":"52353",
    "sg:province":"Nordrhein-Westfalen",
    "wof:name":"Helmut Kurth",
    "wof:placetype":"venue"
},
  "geometry": {"coordinates":[6.4211711884,50.8469276428],"type":"Point"}
}