{
  "type": "Feature",
  "properties": {
    "iso:country":"DE",
    "sg:address":"Kreuzb\u00fchlstr. 28",
    "sg:city":"Albstadt",
    "sg:phone":"+49 7431/3122",
    "sg:postcode":"72458",
    "sg:province":"Baden-W\u00fcrttemberg",
    "wof:name":"Retter Automation Und Messtechnik Gmbh",
    "wof:placetype":"venue"
},
  "geometry": {"coordinates":[9.010017,48.218941],"type":"Point"}
}