{
  "type": "Feature",
  "properties": {
    "iso:country":"DE",
    "sg:address":"Odenthaler Str. 2",
    "sg:city":"K\u00fcrten",
    "sg:phone":"+49 2207/909956",
    "sg:postcode":"51515",
    "sg:province":"Nordrhein-Westfalen",
    "wof:name":"Matrix Systeml\u00f6sungen Klaus Batke E. K.",
    "wof:placetype":"venue"
},
  "geometry": {"coordinates":[7.2065758705,51.0388755798],"type":"Point"}
}