{
  "type": "Feature",
  "properties": {
    "iso:country":"DE",
    "sg:address":"Karlstr. 15",
    "sg:city":"Darmstadt",
    "sg:phone":"+49 6151/25853",
    "sg:postcode":"64283",
    "sg:province":"Hessen",
    "wof:name":"Sitte",
    "wof:placetype":"venue"
},
  "geometry": {"coordinates":[8.6564950943,49.8695602417],"type":"Point"}
}