{
  "type": "Feature",
  "properties": {
    "iso:country":"DE",
    "sg:address":"D\u00fcrener Str. 312",
    "sg:city":"Kerpen",
    "sg:phone":"+49 2275/1897",
    "sg:postcode":"50171",
    "sg:province":"Nordrhein-Westfalen",
    "wof:name":"Volksbank Kerpen Eg",
    "wof:placetype":"venue"
},
  "geometry": {"coordinates":[6.630286,50.854378],"type":"Point"}
}