{
  "type": "Feature",
  "properties": {
    "iso:country":"DE",
    "sg:address":"Ringstr. 49",
    "sg:city":"Wernigerode",
    "sg:phone":"+49 3943/632404",
    "sg:postcode":"38855",
    "sg:province":"Sachsen-Anhalt",
    "wof:name":"K. Jahns",
    "wof:placetype":"venue"
},
  "geometry": {"coordinates":[10.787527,51.835278],"type":"Point"}
}