{
  "type": "Feature",
  "properties": {
    "iso:country":"DE",
    "sg:address":"Dahlienstr. 54",
    "sg:city":"Krefeld",
    "sg:phone":"+49 2151/595676",
    "sg:postcode":"47800",
    "sg:province":"Nordrhein-Westfalen",
    "wof:name":"Ispoma Sport Marketing Gmbh",
    "wof:placetype":"venue"
},
  "geometry": {"coordinates":[6.6117219925,51.3409385681],"type":"Point"}
}