{
  "type": "Feature",
  "properties": {
    "iso:country":"DE",
    "sg:address":"Sendlinger Str. 50",
    "sg:city":"M\u00fcnchen",
    "sg:postcode":"80331",
    "sg:province":"Bayern",
    "wof:name":"Gp German Properties Gmbh",
    "wof:placetype":"venue"
},
  "geometry": {"coordinates":[11.568469,48.134476],"type":"Point"}
}