{
  "type": "Feature",
  "properties": {
    "iso:country":"DE",
    "sg:address":"Westerheide 10-",
    "sg:city":"M\u00fcnster",
    "sg:phone":"+49 251/328950",
    "sg:postcode":"48157",
    "sg:province":"Nordrhein-Westfalen",
    "wof:name":"Comdata Computer Und Datensysteme Gmbh",
    "wof:placetype":"venue"
},
  "geometry": {"coordinates":[7.6748838425,52.0291748047],"type":"Point"}
}