{
  "type": "Feature",
  "properties": {
    "iso:country":"DE",
    "sg:address":"Am Kirchberg 22",
    "sg:city":"Kreuth",
    "sg:phone":"+49 8029/477",
    "sg:postcode":"83708",
    "sg:province":"Bayern",
    "wof:name":"G\u00e4stehaus Josef Deininger",
    "wof:placetype":"venue"
},
  "geometry": {"coordinates":[11.7413368225,47.6458969116],"type":"Point"}
}