{
  "type": "Feature",
  "properties": {
    "iso:country":"DE",
    "sg:address":"Sch\u00fctzenstr. 13",
    "sg:city":"Teuchern",
    "sg:phone":"+49 34443/20362",
    "sg:postcode":"06682",
    "sg:province":"Sachsen-Anhalt",
    "wof:name":"Guter Tropfen",
    "wof:placetype":"venue"
},
  "geometry": {"coordinates":[12.0287408829,51.1203193665],"type":"Point"}
}