{
  "type": "Feature",
  "properties": {
    "iso:country":"DE",
    "sg:address":"Possartstrasse 6::",
    "sg:city":"Munich",
    "sg:phone":"+49 89/4195950",
    "sg:postcode":"81679",
    "sg:province":"Bayern",
    "wof:name":"Ava Gesellschaft F\u00fcr Anlagevermittlung Verm\u00f6gensplanung Allfinanzdienst Mbh",
    "wof:placetype":"venue"
},
  "geometry": {"coordinates":[11.606817,48.140392],"type":"Point"}
}