{
  "type": "Feature",
  "properties": {
    "iso:country":"DE",
    "sg:address":"Robert-Koch-Str. 11",
    "sg:city":"Mainz",
    "sg:phone":"+49 6131/593003",
    "sg:postcode":"55129",
    "sg:province":"Rheinland-Pfalz",
    "wof:name":"Intervideo Fimproduktion E. K.",
    "wof:placetype":"venue"
},
  "geometry": {"coordinates":[8.2660560608,49.9638023376],"type":"Point"}
}