{
  "type": "Feature",
  "properties": {
    "iso:country":"DE",
    "sg:address":"Feldschl\u00f6\u00dfchenstr. 5",
    "sg:city":"Greiz",
    "sg:phone":"+49 3661/2063",
    "sg:postcode":"07973",
    "sg:province":"Th\u00fcringen",
    "wof:name":"Feldschl\u00f6\u00dfchen Greiz Gesch\u00e4ftsf\u00fchrungs Gmbh",
    "wof:placetype":"venue"
},
  "geometry": {"coordinates":[12.2298631668,50.6561470032],"type":"Point"}
}