{
  "type": "Feature",
  "properties": {
    "iso:country":"DE",
    "sg:address":"Max-Beckmann-Str. 4",
    "sg:city":"M\u00fcnchen",
    "sg:phone":"+49 89/425699",
    "sg:postcode":"81735",
    "sg:province":"Bayern",
    "wof:name":"Abis Bautenschutz Gmbh",
    "wof:placetype":"venue"
},
  "geometry": {"coordinates":[11.651597023,48.1124343872],"type":"Point"}
}