{
  "type": "Feature",
  "properties": {
    "iso:country":"DE",
    "sg:address":"Obere Hauptstr. 31",
    "sg:city":"Colmnitz",
    "sg:phone":"+49 35202/50188",
    "sg:postcode":"01738",
    "sg:province":"Sachsen",
    "wof:name":"Eberhard B\u00dcttner",
    "wof:placetype":"venue"
},
  "geometry": {"coordinates":[13.5044574738,50.9059524536],"type":"Point"}
}