{
  "type": "Feature",
  "properties": {
    "iso:country":"DE",
    "sg:address":"Oststr. 57",
    "sg:city":"Norderstedt",
    "sg:phone":"+49 40/5228071",
    "sg:postcode":"22844",
    "sg:province":"Schleswig-Holstein",
    "wof:name":"Retec Gesellschaft F\u00fcr Regel- Und Elektrotechnik Mbh",
    "wof:placetype":"venue"
},
  "geometry": {"coordinates":[10.0228099823,53.726890564],"type":"Point"}
}