{
  "type": "Feature",
  "properties": {
    "iso:country":"DE",
    "sg:address":"Bahnhofsplatz 4",
    "sg:city":"Oppenweiler",
    "sg:phone":"+49 7191/940194",
    "sg:postcode":"71570",
    "sg:province":"Baden-W\u00fcrttemberg",
    "wof:name":"Dr. C. G. Beuthe Ingenieur",
    "wof:placetype":"venue"
},
  "geometry": {"coordinates":[9.4587230682,48.9827423096],"type":"Point"}
}