{
  "type": "Feature",
  "properties": {
    "iso:country":"DE",
    "sg:address":"Wilhelm-Raabe-Str. 34",
    "sg:city":"Kamp-Lintfort",
    "sg:phone":"+49 2842/7640",
    "sg:postcode":"47475",
    "sg:province":"Nordrhein-Westfalen",
    "wof:name":"Josef Gregoric",
    "wof:placetype":"venue"
},
  "geometry": {"coordinates":[6.5331082344,51.4871864319],"type":"Point"}
}