{
  "type": "Feature",
  "properties": {
    "iso:country":"DE",
    "sg:address":"Gabelsbergerstr. 3",
    "sg:city":"Wiesbaden",
    "sg:phone":"+49 611/528900",
    "sg:postcode":"65195",
    "sg:province":"Hessen",
    "wof:name":"Kinderheim Der Arbeiterwohlfahrt",
    "wof:placetype":"venue"
},
  "geometry": {"coordinates":[8.230796814,50.0855331421],"type":"Point"}
}