{
  "type": "Feature",
  "properties": {
    "iso:country":"DE",
    "sg:address":"Eisengasse 1",
    "sg:city":"Bad Bellingen",
    "sg:phone":"+49 7635/1337",
    "sg:postcode":"79415",
    "sg:province":"Baden-W\u00fcrttemberg",
    "wof:name":"G\u00e4stehaus R. Berndt",
    "wof:placetype":"venue"
},
  "geometry": {"coordinates":[7.5564231873,47.7318458557],"type":"Point"}
}