{
  "type": "Feature",
  "properties": {
    "iso:country":"DE",
    "sg:address":"Br\u00fchl 4",
    "sg:city":"Leipzig",
    "sg:phone":"+49 341/141810",
    "sg:postcode":"04109",
    "sg:province":"Sachsen",
    "wof:name":"Rheinhyp Rheinische Hypothekenbank Ag",
    "wof:placetype":"venue"
},
  "geometry": {"coordinates":[12.3730220795,51.343044281],"type":"Point"}
}