{
  "type": "Feature",
  "properties": {
    "iso:country":"DE",
    "sg:address":"Seifertshofer Str. 19",
    "sg:city":"Ebershausen",
    "sg:phone":"+49 8282/4707",
    "sg:postcode":"86491",
    "sg:province":"Bayern",
    "wof:name":"H. Steurer",
    "wof:placetype":"venue"
},
  "geometry": {"coordinates":[10.3150815964,48.2076148987],"type":"Point"}
}