{
  "type": "Feature",
  "properties": {
    "iso:country":"DE",
    "sg:address":"In der Borg 10",
    "sg:city":"Haltern",
    "sg:phone":"+49 2364/13669",
    "sg:postcode":"45721",
    "sg:province":"Nordrhein-Westfalen",
    "wof:name":"Ursula Bontrup Heilpraktikerin",
    "wof:placetype":"venue"
},
  "geometry": {"coordinates":[7.1890897751,51.7489738464],"type":"Point"}
}