{
  "type": "Feature",
  "properties": {
    "iso:country":"DE",
    "sg:address":"Kirchstr. 3",
    "sg:city":"Straupitz",
    "sg:phone":"+49 35475/380",
    "sg:postcode":"15913",
    "sg:province":"Brandenburg",
    "wof:name":"R. Kunze",
    "wof:placetype":"venue"
},
  "geometry": {"coordinates":[14.122245,51.91169],"type":"Point"}
}