{
  "type": "Feature",
  "properties": {
    "iso:country":"DE",
    "sg:address":"Am Bahrehang 76",
    "sg:city":"Chemnitz",
    "sg:phone":"+49 371/3363260",
    "sg:postcode":"09114",
    "sg:province":"Sachsen",
    "wof:name":"K. Katzschner",
    "wof:placetype":"venue"
},
  "geometry": {"coordinates":[12.892349,50.872959],"type":"Point"}
}