{
  "type": "Feature",
  "properties": {
    "iso:country":"DE",
    "sg:address":"Borsigstr. 7",
    "sg:city":"\u00dcbach-Palenberg",
    "sg:phone":"+49 2451/46504",
    "sg:postcode":"52531",
    "sg:province":"Nordrhein-Westfalen",
    "wof:name":"Rockfabrik",
    "wof:placetype":"venue"
},
  "geometry": {"coordinates":[6.1194939613,50.9198150635],"type":"Point"}
}