{
  "type": "Feature",
  "properties": {
    "iso:country":"DE",
    "sg:address":"Sodenstich 66",
    "sg:city":"Bremen",
    "sg:phone":"+49 421/444163",
    "sg:postcode":"28207",
    "sg:province":"Bremen",
    "wof:name":"Capri Eiscafe Und Restaurant Betreiberges. Mbh",
    "wof:placetype":"venue"
},
  "geometry": {"coordinates":[8.8697252274,53.0678024292],"type":"Point"}
}