{
  "type": "Feature",
  "properties": {
    "iso:country":"DE",
    "sg:address":"Isarpromenade 3",
    "sg:city":"Landshut",
    "sg:phone":"+49 871/9247917",
    "sg:postcode":"84028",
    "sg:province":"Bayern",
    "wof:name":"Alt Landshut",
    "wof:placetype":"venue"
},
  "geometry": {"coordinates":[12.1591062546,48.5423851013],"type":"Point"}
}