{
  "type": "Feature",
  "properties": {
    "iso:country":"DE",
    "sg:address":"Wilhelmstr. 3 c",
    "sg:city":"Burgdorf",
    "sg:phone":"+49 5136/6057",
    "sg:postcode":"31303",
    "sg:province":"Niedersachsen",
    "wof:name":"Manfred Oetzmann Steuerberater",
    "wof:placetype":"venue"
},
  "geometry": {"coordinates":[10.0045967102,52.448387146],"type":"Point"}
}