{
  "type": "Feature",
  "properties": {
    "iso:country":"DE",
    "sg:address":"Wetschhauser Hof 1a",
    "sg:city":"Ottweiler",
    "sg:phone":"+49 6858/1338",
    "sg:postcode":"66564",
    "sg:province":"Saarland",
    "wof:name":"Ute Bund",
    "wof:placetype":"venue"
},
  "geometry": {"coordinates":[7.208685,49.420959],"type":"Point"}
}