{
  "type": "Feature",
  "properties": {
    "iso:country":"DE",
    "sg:address":"Kirchplatz 1",
    "sg:city":"Rudelzhausen",
    "sg:phone":"+49 8754/96010",
    "sg:postcode":"84104",
    "sg:province":"Bayern",
    "wof:name":"Gr\u00fcnwiedl Gmbh & Co. Kg",
    "wof:placetype":"venue"
},
  "geometry": {"coordinates":[11.763327,48.589077],"type":"Point"}
}