{
  "type": "Feature",
  "properties": {
    "iso:country":"DE",
    "sg:address":"Neusser Str. 33",
    "sg:city":"Dormagen",
    "sg:phone":"+49 2133/90107",
    "sg:postcode":"41542",
    "sg:province":"Nordrhein-Westfalen",
    "wof:name":"H. Neuenhofer",
    "wof:placetype":"venue"
},
  "geometry": {"coordinates":[6.76962,51.116615],"type":"Point"}
}