{
  "type": "Feature",
  "properties": {
    "iso:country":"DE",
    "sg:address":"Am Kalkofen 3",
    "sg:city":"W\u00f6llstadt",
    "sg:phone":"+49 6034/91910",
    "sg:postcode":"61206",
    "sg:province":"Hessen",
    "wof:name":"Astech Electronic Gmbh & Co. Kg",
    "wof:placetype":"venue"
},
  "geometry": {"coordinates":[8.7646684647,50.2796096802],"type":"Point"}
}