{
  "type": "Feature",
  "properties": {
    "iso:country":"DE",
    "sg:address":"Am G\u00fcllenacker 15",
    "sg:city":"March",
    "sg:phone":"+49 7665/4840",
    "sg:postcode":"79232",
    "sg:province":"Baden-W\u00fcrttemberg",
    "wof:name":"Heinz Denzler",
    "wof:placetype":"venue"
},
  "geometry": {"coordinates":[7.778031826,48.0559616089],"type":"Point"}
}