{
  "type": "Feature",
  "properties": {
    "iso:country":"DE",
    "sg:address":"Untersteinbach",
    "sg:city":"Georgensgm\u00fcnd",
    "sg:phone":"+49 9172/2618",
    "sg:postcode":"91166",
    "sg:province":"Bayern",
    "wof:name":"Hans Gro\u00dfberger",
    "wof:placetype":"venue"
},
  "geometry": {"coordinates":[10.9861736298,49.2085609436],"type":"Point"}
}