{
  "type": "Feature",
  "properties": {
    "iso:country":"DE",
    "sg:address":"Am Gaishof 16",
    "sg:city":"Ebringen",
    "sg:phone":"+49 7664/7808",
    "sg:postcode":"79285",
    "sg:province":"Baden-W\u00fcrttemberg",
    "wof:name":"Gerhard Neugebauer Gmbh",
    "wof:placetype":"venue"
},
  "geometry": {"coordinates":[7.775198,47.949654],"type":"Point"}
}