{
  "type": "Feature",
  "properties": {
    "iso:country":"DE",
    "sg:address":"Veronikastr. 47",
    "sg:city":"Essen",
    "sg:phone":"+49 201/771402",
    "sg:postcode":"45131",
    "sg:province":"Nordrhein-Westfalen",
    "wof:name":"D. Pielucha",
    "wof:placetype":"venue"
},
  "geometry": {"coordinates":[7.014161,51.430141],"type":"Point"}
}