{
  "type": "Feature",
  "properties": {
    "iso:country":"DE",
    "sg:address":"Zum Eisenhammer 5B",
    "sg:city":"Oberhausen",
    "sg:phone":"+49 208/855399",
    "sg:postcode":"46049",
    "sg:province":"Nordrhein-Westfalen",
    "wof:name":"Chon Chi Gesundheitszentrum",
    "wof:placetype":"venue"
},
  "geometry": {"coordinates":[6.8433089256,51.4845962524],"type":"Point"}
}