{
  "type": "Feature",
  "properties": {
    "iso:country":"DE",
    "sg:address":"Friedrichstr. 6",
    "sg:city":"Bad Pyrmont",
    "sg:phone":"+49 5281/4562",
    "sg:postcode":"31812",
    "sg:province":"Niedersachsen",
    "wof:name":"G\u00e4stehaus Haus Rubin Fam. Beek",
    "wof:placetype":"venue"
},
  "geometry": {"coordinates":[9.2533073425,51.9890022278],"type":"Point"}
}