{
  "type": "Feature",
  "properties": {
    "iso:country":"DE",
    "sg:address":"Feldweg 5",
    "sg:city":"Oppach",
    "sg:phone":"+49 35872/32536",
    "sg:postcode":"02736",
    "sg:province":"Sachsen",
    "wof:name":"Johannes Kunze",
    "wof:placetype":"venue"
},
  "geometry": {"coordinates":[14.497945,51.059853],"type":"Point"}
}