{
  "type": "Feature",
  "properties": {
    "iso:country":"DE",
    "sg:address":"Gereonstr. 2",
    "sg:city":"Titz",
    "sg:phone":"+49 2463/5058",
    "sg:postcode":"52445",
    "sg:province":"Nordrhein-Westfalen",
    "wof:name":"As Friseurbedarf Gmbh",
    "wof:placetype":"venue"
},
  "geometry": {"coordinates":[6.41213,50.978855],"type":"Point"}
}