{
  "type": "Feature",
  "properties": {
    "iso:country":"DE",
    "sg:address":"Ro\u00dfstr. 9",
    "sg:city":"Triptis",
    "sg:phone":"+49 36482/48378",
    "sg:postcode":"07819",
    "sg:province":"Th\u00fcringen",
    "wof:name":"R. St\u00f6ckel",
    "wof:placetype":"venue"
},
  "geometry": {"coordinates":[11.86536026,50.7346000671],"type":"Point"}
}