{
  "type": "Feature",
  "properties": {
    "iso:country":"DE",
    "sg:address":"Behrensallee 7",
    "sg:city":"Pinneberg",
    "sg:phone":"+49 4101",
    "sg:postcode":"25421",
    "sg:province":"Schleswig-Holstein",
    "wof:name":"Dha - Deutsche Hockey Agentur",
    "wof:placetype":"venue"
},
  "geometry": {"coordinates":[9.794045,53.622726],"type":"Point"}
}