{
  "type": "Feature",
  "properties": {
    "iso:country":"DE",
    "sg:address":"Franzstr. 21",
    "sg:city":"Bocholt",
    "sg:phone":"+49 2871/16060",
    "sg:postcode":"46395",
    "sg:province":"Nordrhein-Westfalen",
    "wof:name":"Old Paddy",
    "wof:placetype":"venue"
},
  "geometry": {"coordinates":[6.62474823,51.8319702148],"type":"Point"}
}