{
  "type": "Feature",
  "properties": {
    "iso:country":"DE",
    "sg:address":"Magdalenenstr. 47",
    "sg:city":"Gelsenkirchen",
    "sg:phone":"+49 209/85936",
    "sg:postcode":"45889",
    "sg:province":"Nordrhein-Westfalen",
    "wof:name":"Katholisches Pfarramt Hl. Dreifaltigkeit",
    "wof:placetype":"venue"
},
  "geometry": {"coordinates":[7.1209402084,51.5297393799],"type":"Point"}
}