{
  "type": "Feature",
  "properties": {
    "iso:country":"DE",
    "sg:address":"Friedhofsweg 15",
    "sg:city":"Cottbus",
    "sg:postcode":"03053",
    "sg:province":"Brandenburg",
    "wof:name":"Bezirksschornsteinfegermeister Konrad Golz",
    "wof:placetype":"venue"
},
  "geometry": {"coordinates":[14.383106,51.807949],"type":"Point"}
}