{
  "type": "Feature",
  "properties": {
    "iso:country":"DE",
    "sg:address":"Kesselheimer Weg 86",
    "sg:city":"Koblenz",
    "sg:phone":"+49 261/86090",
    "sg:postcode":"56070",
    "sg:province":"Rheinland-Pfalz",
    "wof:name":"Bst Bau-sanier-technik Gmbh",
    "wof:placetype":"venue"
},
  "geometry": {"coordinates":[7.5870919228,50.3857192993],"type":"Point"}
}