{
  "type": "Feature",
  "properties": {
    "iso:country":"DE",
    "sg:address":"L\u00e4rchenstr. 3",
    "sg:city":"Ernsgaden",
    "sg:phone":"+49 8452/2808",
    "sg:postcode":"85119",
    "sg:province":"Bayern",
    "wof:name":"Alois Schmelzer Steuerberater",
    "wof:placetype":"venue"
},
  "geometry": {"coordinates":[11.5761766434,48.7314491272],"type":"Point"}
}