{
  "type": "Feature",
  "properties": {
    "iso:country":"DE",
    "sg:address":"Jakob-Brand-Str. 6",
    "sg:city":"Schierling",
    "sg:phone":"+49 9451/3424",
    "sg:postcode":"84069",
    "sg:province":"Bayern",
    "wof:name":"Unterpaintner",
    "wof:placetype":"venue"
},
  "geometry": {"coordinates":[12.138857,48.838421],"type":"Point"}
}