{
  "type": "Feature",
  "properties": {
    "iso:country":"DE",
    "sg:address":"Wendelsteinstr. 1",
    "sg:city":"Gr\u00e4felfing",
    "sg:phone":"+49 89/8544147",
    "sg:postcode":"82166",
    "sg:province":"Bayern",
    "wof:name":"Dr. Georg Graf Rechtsanwalt",
    "wof:placetype":"venue"
},
  "geometry": {"coordinates":[11.4278821945,48.1179695129],"type":"Point"}
}