{
  "type": "Feature",
  "properties": {
    "iso:country":"DE",
    "sg:address":"Altstadtweg 21",
    "sg:city":"Miltenberg",
    "sg:phone":"+49 9371/3791",
    "sg:postcode":"63897",
    "sg:province":"Bayern",
    "wof:name":"Franz Ott",
    "wof:placetype":"venue"
},
  "geometry": {"coordinates":[9.229992,49.709187],"type":"Point"}
}