{
  "type": "Feature",
  "properties": {
    "iso:country":"DE",
    "sg:address":"Hauptstr. 22-32",
    "sg:city":"Heidelberg",
    "sg:phone":"+49 6221/24181",
    "sg:postcode":"69117",
    "sg:province":"Baden-W\u00fcrttemberg",
    "wof:name":"Singer",
    "wof:placetype":"venue"
},
  "geometry": {"coordinates":[8.6957597733,49.4100265503],"type":"Point"}
}