{
  "type": "Feature",
  "properties": {
    "iso:country":"DE",
    "sg:address":"Richard-Lehmann-Str. 62 a",
    "sg:city":"Leipzig",
    "sg:phone":"+49 341/3014213",
    "sg:postcode":"04275",
    "sg:province":"Sachsen",
    "wof:name":"Erholung S\u00fcd",
    "wof:placetype":"venue"
},
  "geometry": {"coordinates":[12.3797721863,51.314655304],"type":"Point"}
}