{
  "type": "Feature",
  "properties": {
    "iso:country":"DE",
    "sg:address":"Gro\u00dfe Gebind 3",
    "sg:city":"Kranichfeld",
    "sg:postcode":"99448",
    "sg:province":"Th\u00fcringen",
    "wof:name":"Dr. Med. Elisabeth Brinkmann",
    "wof:placetype":"venue"
},
  "geometry": {"coordinates":[11.199673,50.852413],"type":"Point"}
}