{
  "type": "Feature",
  "properties": {
    "iso:country":"DE",
    "sg:address":"Schillerstra\u00dfe 20",
    "sg:city":"Niederndodeleben",
    "sg:phone":"+49 39204/251",
    "sg:postcode":"39167",
    "sg:province":"Sachsen-Anhalt",
    "wof:name":"Raiffeisenbank U. Handeslgen.",
    "wof:placetype":"venue"
},
  "geometry": {"coordinates":[11.496174,52.138374],"type":"Point"}
}