{
  "type": "Feature",
  "properties": {
    "iso:country":"DE",
    "sg:address":"Pegauer Str. 38",
    "sg:city":"Nessa",
    "sg:phone":"+49 34443/20427",
    "sg:postcode":"06682",
    "sg:province":"Sachsen-Anhalt",
    "wof:name":"Manfred Erfurth",
    "wof:placetype":"venue"
},
  "geometry": {"coordinates":[12.0058078766,51.1446380615],"type":"Point"}
}