{
  "type": "Feature",
  "properties": {
    "iso:country":"DE",
    "sg:address":"Juri-Gagarin-Str. 103",
    "sg:city":"Stenn",
    "sg:phone":"+49 375/783353",
    "sg:postcode":"08144",
    "sg:province":"Sachsen",
    "wof:name":"F. M\u00fcller",
    "wof:placetype":"venue"
},
  "geometry": {"coordinates":[-95.18807983400001,41.0944595337],"type":"Point"}
}