{
  "type": "Feature",
  "properties": {
    "iso:country":"DE",
    "sg:address":"Pfaffplatz 1",
    "sg:city":"Kaiserslautern",
    "sg:phone":"+49 631/13019",
    "sg:postcode":"67655",
    "sg:province":"Rheinland-Pfalz",
    "wof:name":"G\u00e4stehaus Hofschuster",
    "wof:placetype":"venue"
},
  "geometry": {"coordinates":[7.7585759163,49.4432296753],"type":"Point"}
}