{
  "type": "Feature",
  "properties": {
    "iso:country":"DE",
    "sg:address":"Hauptstr. 19",
    "sg:city":"Kalletal",
    "sg:phone":"+49 5264/381",
    "sg:postcode":"32689",
    "sg:province":"Nordrhein-Westfalen",
    "wof:name":"K. Linneweber Gmbh",
    "wof:placetype":"venue"
},
  "geometry": {"coordinates":[8.965273,52.14674],"type":"Point"}
}