{
  "type": "Feature",
  "properties": {
    "iso:country":"DE",
    "sg:address":"Auf der Kegelbahn 2",
    "sg:city":"Kall",
    "sg:phone":"+49 2441/779316",
    "sg:postcode":"53925",
    "sg:province":"Nordrhein-Westfalen",
    "wof:name":"Handys Und Kartenvertr\u00e4ge Zu Top-konditionen",
    "wof:placetype":"venue"
},
  "geometry": {"coordinates":[6.519674778,50.5235061646],"type":"Point"}
}