{
  "type": "Feature",
  "properties": {
    "iso:country":"DE",
    "sg:address":"M\u00fchlengasse 6",
    "sg:city":"Kreuzau",
    "sg:phone":"+49 2422/1682",
    "sg:postcode":"52372",
    "sg:province":"Nordrhein-Westfalen",
    "wof:name":"Marianne Dahmen",
    "wof:placetype":"venue"
},
  "geometry": {"coordinates":[6.488577,50.745686],"type":"Point"}
}