{
  "type": "Feature",
  "properties": {
    "iso:country":"DE",
    "sg:address":"Patriotischer Weg 134",
    "sg:city":"Rostock",
    "sg:postcode":"18057",
    "sg:province":"Mecklenburg-Vorpommern",
    "wof:name":"Ostseebau Graal-m\u00fcritz Verwaltungsgesellschaft Mbh",
    "wof:placetype":"venue"
},
  "geometry": {"coordinates":[12.126704216,54.0899658203],"type":"Point"}
}