{
  "type": "Feature",
  "properties": {
    "iso:country":"DE",
    "sg:address":"Buch 44",
    "sg:city":"Gremsdorf",
    "sg:postcode":"91350",
    "sg:province":"Bayern",
    "wof:name":"Anna Rost Bau Gmbh",
    "wof:placetype":"venue"
},
  "geometry": {"coordinates":[10.860894,49.679653],"type":"Point"}
}