{
  "type": "Feature",
  "properties": {
    "iso:country":"DE",
    "sg:address":"Hauptstr. 1",
    "sg:city":"Lichtentanne",
    "sg:phone":"+49 375/528044",
    "sg:postcode":"08115",
    "sg:province":"Sachsen",
    "wof:name":"Cornelia Beier",
    "wof:placetype":"venue"
},
  "geometry": {"coordinates":[12.416371,50.697014],"type":"Point"}
}