{
  "type": "Feature",
  "properties": {
    "iso:country":"DE",
    "sg:address":"Rabensteinstr. 33",
    "sg:city":"Egloffstein",
    "sg:phone":"+49 9197/627139",
    "sg:postcode":"91349",
    "sg:province":"Bayern",
    "wof:name":"Restaurant Schluckspecht",
    "wof:placetype":"venue"
},
  "geometry": {"coordinates":[11.258348465,49.7026977539],"type":"Point"}
}