{
  "type": "Feature",
  "properties": {
    "iso:country":"DE",
    "sg:address":"Bendsteg 24",
    "sg:city":"Kamp-Lintfort",
    "sg:phone":"+49 2842/80126",
    "sg:postcode":"47475",
    "sg:province":"Nordrhein-Westfalen",
    "wof:name":"Arnold Hubben Rechtsanwalt",
    "wof:placetype":"venue"
},
  "geometry": {"coordinates":[6.5402350426,51.4929656982],"type":"Point"}
}