{
  "type": "Feature",
  "properties": {
    "iso:country":"DE",
    "sg:address":"Am Handelshof",
    "sg:city":"Essen",
    "sg:phone":"+49 201/227765",
    "sg:postcode":"45127",
    "sg:province":"Nordrhein-Westfalen",
    "wof:name":"Lunatic Hannelore Setareh Gmbh",
    "wof:placetype":"venue"
},
  "geometry": {"coordinates":[7.013799,51.452919],"type":"Point"}
}