{
  "type": "Feature",
  "properties": {
    "iso:country":"DE",
    "sg:address":"Reintal 15 a",
    "sg:city":"Reichersbeuern",
    "sg:phone":"+49 8041/760130",
    "sg:postcode":"83677",
    "sg:province":"Bayern",
    "wof:name":"Lupus Spezialist F\u00fcr B\u00fcro Und Ausbildungsmaterial Und",
    "wof:placetype":"venue"
},
  "geometry": {"coordinates":[11.620057,47.756958],"type":"Point"}
}