{
  "type": "Feature",
  "properties": {
    "iso:country":"DE",
    "sg:address":"Hauptstr. 10",
    "sg:city":"Rottenburg",
    "sg:phone":"+49 8781/693",
    "sg:postcode":"84056",
    "sg:province":"Bayern",
    "wof:name":"P. Neidhart Jun.",
    "wof:placetype":"venue"
},
  "geometry": {"coordinates":[11.999569,48.692459],"type":"Point"}
}