{
  "type": "Feature",
  "properties": {
    "iso:country":"DE",
    "sg:address":"St.-Gebhard-Platz 5",
    "sg:city":"Konstanz",
    "sg:phone":"+49 7531/65481",
    "sg:postcode":"78467",
    "sg:province":"Baden-W\u00fcrttemberg",
    "wof:name":"Adolf Berges",
    "wof:placetype":"venue"
},
  "geometry": {"coordinates":[9.1818418503,47.6705665588],"type":"Point"}
}