{
  "type": "Feature",
  "properties": {
    "iso:country":"DE",
    "sg:address":"Bahnhofstr. 60",
    "sg:city":"D\u00f6rentrup",
    "sg:phone":"+49 5263/2228",
    "sg:postcode":"32694",
    "sg:province":"Nordrhein-Westfalen",
    "wof:name":"Karl Dubbert Gmbh & Co. Kg",
    "wof:placetype":"venue"
},
  "geometry": {"coordinates":[9.0596199036,52.0100708008],"type":"Point"}
}