{
  "type": "Feature",
  "properties": {
    "iso:country":"DE",
    "sg:address":"Fuhrstr. 21",
    "sg:city":"Solingen",
    "sg:phone":"+49 212/314066",
    "sg:postcode":"42719",
    "sg:province":"Nordrhein-Westfalen",
    "wof:name":"Groka Verbrauchermarkt Gmbh & Co. Kg",
    "wof:placetype":"venue"
},
  "geometry": {"coordinates":[7.0566210747,51.1941146851],"type":"Point"}
}