{
  "type": "Feature",
  "properties": {
    "iso:country":"DE",
    "sg:address":"Friedrichstr. 18",
    "sg:city":"K\u00f6then",
    "sg:phone":"+49 3496/216232",
    "sg:postcode":"06366",
    "sg:province":"Sachsen-Anhalt",
    "wof:name":"J. Kristensen",
    "wof:placetype":"venue"
},
  "geometry": {"coordinates":[11.9828567505,51.7540855408],"type":"Point"}
}