{
  "type": "Feature",
  "properties": {
    "iso:country":"DE",
    "sg:address":"Gallberg 8-14",
    "sg:city":"Schleswig",
    "sg:phone":"+49 4621/24794",
    "sg:postcode":"24837",
    "sg:province":"Schleswig-Holstein",
    "wof:name":"Gothaer Versicherungen Rudolf Kohlhaas",
    "wof:placetype":"venue"
},
  "geometry": {"coordinates":[9.5698471069,54.5174636841],"type":"Point"}
}