{
  "type": "Feature",
  "properties": {
    "iso:country":"DE",
    "sg:address":"Mackenrothweg 20",
    "sg:city":"Dortmund",
    "sg:phone":"+49 231/5028860",
    "sg:postcode":"44328",
    "sg:province":"Nordrhein-Westfalen",
    "wof:name":"Hallenbad Scharnhorst",
    "wof:placetype":"venue"
},
  "geometry": {"coordinates":[7.5434269905,51.5516471863],"type":"Point"}
}