{
  "type": "Feature",
  "properties": {
    "iso:country":"DE",
    "sg:address":"Demmeringstr. 63",
    "sg:city":"Leipzig",
    "sg:phone":"+49 341/4800313",
    "sg:postcode":"04177",
    "sg:province":"Sachsen",
    "wof:name":"Progress-ingenieurgesellschaft F\u00fcr Bauwesen Mbh",
    "wof:placetype":"venue"
},
  "geometry": {"coordinates":[12.325126,51.335522],"type":"Point"}
}