{
  "type": "Feature",
  "properties": {
    "iso:country":"DE",
    "sg:address":"Nikolaibergstr. 16",
    "sg:city":"Wartenberg",
    "sg:phone":"+49 8762/1862",
    "sg:postcode":"85456",
    "sg:province":"Bayern",
    "wof:name":"Immogru Gmbh",
    "wof:placetype":"venue"
},
  "geometry": {"coordinates":[11.992207,48.404888],"type":"Point"}
}