{
  "type": "Feature",
  "properties": {
    "iso:country":"DE",
    "sg:address":"Bahnhofstr. 7",
    "sg:city":"Gr\u00e4felfing",
    "sg:phone":"+49 89/8988970",
    "sg:postcode":"82166",
    "sg:province":"Bayern",
    "wof:name":"Gss&i, Beratung F\u00fcr Zeitungsverlage",
    "wof:placetype":"venue"
},
  "geometry": {"coordinates":[11.432984,48.116955],"type":"Point"}
}