{
  "type": "Feature",
  "properties": {
    "iso:country":"DE",
    "sg:address":"Bahnhofstr.",
    "sg:city":"Kirchheim",
    "sg:postcode":"67281",
    "sg:province":"Rheinland-Pfalz",
    "wof:name":"Schreinerei Kempf & Grimm Gmbh",
    "wof:placetype":"venue"
},
  "geometry": {"coordinates":[8.181855,49.537411],"type":"Point"}
}