{
  "type": "Feature",
  "properties": {
    "iso:country":"DE",
    "sg:address":"Bahnhofstr. 6",
    "sg:city":"Sch\u00f6nhausen",
    "sg:phone":"+49 39323/38341",
    "sg:postcode":"39524",
    "sg:province":"Sachsen-Anhalt",
    "wof:name":"Thermoplast Sch\u00f6nhausen Gmbh",
    "wof:placetype":"venue"
},
  "geometry": {"coordinates":[12.0364875793,52.5855140686],"type":"Point"}
}