{
  "type": "Feature",
  "properties": {
    "iso:country":"DE",
    "sg:address":"K\u00f6lner Str. 119",
    "sg:city":"Remscheid",
    "sg:phone":"+49 2191/997626",
    "sg:postcode":"42897",
    "sg:province":"Nordrhein-Westfalen",
    "wof:name":"Lennep 119",
    "wof:placetype":"venue"
},
  "geometry": {"coordinates":[7.2541217804,51.1841468811],"type":"Point"}
}