{
  "type": "Feature",
  "properties": {
    "iso:country":"DE",
    "sg:address":"Oldenburger Str. 43",
    "sg:city":"Zeuthen",
    "sg:phone":"+49 33762/73250",
    "sg:postcode":"15738",
    "sg:province":"Brandenburg",
    "wof:name":"Klaus-peter Prylewski",
    "wof:placetype":"venue"
},
  "geometry": {"coordinates":[13.621336,52.353214],"type":"Point"}
}