{
  "type": "Feature",
  "properties": {
    "iso:country":"DE",
    "sg:address":"Thiemstr. 54 c",
    "sg:city":"Cottbus",
    "sg:phone":"+49 355/422260",
    "sg:postcode":"03050",
    "sg:province":"Brandenburg",
    "wof:name":"Dr. Med. Ingrid Willuhn",
    "wof:placetype":"venue"
},
  "geometry": {"coordinates":[14.32622,51.740788],"type":"Point"}
}