{
  "type": "Feature",
  "properties": {
    "iso:country":"DE",
    "sg:address":"Stra\u00dfe der Einheit 11",
    "sg:city":"Kodersdorf",
    "sg:phone":"+49 35825/5309",
    "sg:postcode":"02923",
    "sg:province":"Sachsen",
    "wof:name":"Stafa Stahl- Und Fahrzeug Gmbh",
    "wof:placetype":"venue"
},
  "geometry": {"coordinates":[14.897236,51.228367],"type":"Point"}
}