{
  "type": "Feature",
  "properties": {
    "iso:country":"DE",
    "sg:address":"Johannisberger Str. 2",
    "sg:city":"Hofheim",
    "sg:postcode":"65719",
    "sg:province":"Hessen",
    "wof:name":"Bt Gv Bautr\u00e4ger- Und Grundst\u00fccksverwalt. Gmbh",
    "wof:placetype":"venue"
},
  "geometry": {"coordinates":[8.367915,50.06459],"type":"Point"}
}