{
  "type": "Feature",
  "properties": {
    "iso:country":"DE",
    "sg:address":"Frankfurter Str. 76",
    "sg:city":"Eisenach",
    "sg:phone":"+49 3691/221070",
    "sg:postcode":"99817",
    "sg:province":"Th\u00fcringen",
    "wof:name":"Ludwig",
    "wof:placetype":"venue"
},
  "geometry": {"coordinates":[10.301651001,50.975025177],"type":"Point"}
}