{
  "type": "Feature",
  "properties": {
    "iso:country":"DE",
    "sg:address":"Waldweg 1",
    "sg:city":"Nauheim",
    "sg:phone":"+49 6152/62708",
    "sg:postcode":"64569",
    "sg:province":"Hessen",
    "wof:name":"Christel Fl\u00fcgge Heilpraktikerin",
    "wof:placetype":"venue"
},
  "geometry": {"coordinates":[8.4563140869,49.9477081299],"type":"Point"}
}