{
  "type": "Feature",
  "properties": {
    "iso:country":"DE",
    "sg:address":"Eichsfelder Str. 15",
    "sg:city":"D\u00fcsseldorf",
    "sg:phone":"+49 211/702630",
    "sg:postcode":"40595",
    "sg:province":"Nordrhein-Westfalen",
    "wof:name":"Isca Information Service Und Consulting Gmbh",
    "wof:placetype":"venue"
},
  "geometry": {"coordinates":[6.9145278931,51.1314811707],"type":"Point"}
}