{
  "type": "Feature",
  "properties": {
    "iso:country":"DE",
    "sg:address":"Hahnstr. 11",
    "sg:city":"Niedererbach",
    "sg:phone":"+49 6485/1333",
    "sg:postcode":"56412",
    "sg:province":"Rheinland-Pfalz",
    "wof:name":"A. B\u00f6rner",
    "wof:placetype":"venue"
},
  "geometry": {"coordinates":[7.9731221199,50.4265670776],"type":"Point"}
}