{
  "type": "Feature",
  "properties": {
    "iso:country":"DE",
    "sg:address":"Am W\u00f6rdebrink 12",
    "sg:city":"Enger",
    "sg:phone":"+49 5224/790268",
    "sg:postcode":"32130",
    "sg:province":"Nordrhein-Westfalen",
    "wof:name":"K & P Handelsagentur Kielnerowski & P\u00e4tzelt Ohg",
    "wof:placetype":"venue"
},
  "geometry": {"coordinates":[8.5674343109,52.1369895935],"type":"Point"}
}