{
  "type": "Feature",
  "properties": {
    "iso:country":"DE",
    "sg:address":"Friedrich-Franz-Str. 8",
    "sg:city":"Rostock",
    "sg:phone":"+49 381/5191847",
    "sg:postcode":"18119",
    "sg:province":"Mecklenburg-Vorpommern",
    "wof:name":"Sunlight Gmbh",
    "wof:placetype":"venue"
},
  "geometry": {"coordinates":[12.0854234695,54.1778144836],"type":"Point"}
}