{
  "type": "Feature",
  "properties": {
    "iso:country":"DE",
    "sg:address":"Buchenweg 22",
    "sg:city":"Obergriesbach",
    "sg:phone":"+49 8251/1669",
    "sg:postcode":"86573",
    "sg:province":"Bayern",
    "wof:name":"Hubert Rathay",
    "wof:placetype":"venue"
},
  "geometry": {"coordinates":[11.0717983246,48.4230880737],"type":"Point"}
}