{
  "type": "Feature",
  "properties": {
    "iso:country":"DE",
    "sg:address":"Hauptstr. 2",
    "sg:city":"Schl\u00fcchtern",
    "sg:phone":"+49 6109/32848",
    "sg:postcode":"36381",
    "sg:province":"Hessen",
    "wof:name":"Regenbogen Michael Kraus",
    "wof:placetype":"venue"
},
  "geometry": {"coordinates":[9.5964069366,50.3399925232],"type":"Point"}
}