{
  "type": "Feature",
  "properties": {
    "iso:country":"DE",
    "sg:address":"Sonneberger Str. 45",
    "sg:city":"Steinach",
    "sg:phone":"+49 36762/31234",
    "sg:postcode":"96523",
    "sg:province":"Th\u00fcringen",
    "wof:name":"Uwe M\u00fcller Gmbh",
    "wof:placetype":"venue"
},
  "geometry": {"coordinates":[11.1646518707,50.4237670898],"type":"Point"}
}