{
  "type": "Feature",
  "properties": {
    "iso:country":"DE",
    "sg:address":"Bussardstr. 12",
    "sg:city":"Gr\u00e4felfing",
    "sg:phone":"+49 89/8589666",
    "sg:postcode":"82166",
    "sg:province":"Bayern",
    "wof:name":"Bernhard Gl\u00fcck Kies-sand- Hartsteinsplitt Gmbh & Co.",
    "wof:placetype":"venue"
},
  "geometry": {"coordinates":[11.446352005,48.1172828674],"type":"Point"}
}