{
  "type": "Feature",
  "properties": {
    "iso:country":"DE",
    "sg:address":"Otto-Brenner-Str. 5",
    "sg:city":"Alsdorf",
    "sg:phone":"+49 2404/26066",
    "sg:postcode":"52477",
    "sg:province":"Nordrhein-Westfalen",
    "wof:name":"Hans Heinz Riemer",
    "wof:placetype":"venue"
},
  "geometry": {"coordinates":[6.156607151,50.8676185608],"type":"Point"}
}