{
  "type": "Feature",
  "properties": {
    "iso:country":"DE",
    "sg:address":"Manthalstr. 1",
    "sg:city":"Berg",
    "sg:phone":"+49 8151/444767",
    "sg:postcode":"82335",
    "sg:province":"Bayern",
    "wof:name":"Waldgastst\u00e4tte Manthal",
    "wof:placetype":"venue"
},
  "geometry": {"coordinates":[11.3727884293,47.989238739],"type":"Point"}
}