{
  "type": "Feature",
  "properties": {
    "iso:country":"DE",
    "sg:address":"Sebastian-Kneipp-Str. 42 b",
    "sg:city":"Witzenhausen",
    "sg:phone":"+49 5545/1200",
    "sg:postcode":"37217",
    "sg:province":"Hessen",
    "wof:name":"Thomas Koschak Gmbh",
    "wof:placetype":"venue"
},
  "geometry": {"coordinates":[9.7567882538,51.3675918579],"type":"Point"}
}