{
  "type": "Feature",
  "properties": {
    "iso:country":"DE",
    "sg:address":"Goethestr. 24",
    "sg:city":"Wernshausen",
    "sg:phone":"+49 36848/22505",
    "sg:postcode":"98590",
    "sg:province":"Th\u00fcringen",
    "wof:name":"Karl Fischer",
    "wof:placetype":"venue"
},
  "geometry": {"coordinates":[10.349739,50.721111],"type":"Point"}
}