{
  "type": "Feature",
  "properties": {
    "iso:country":"DE",
    "sg:address":"Porzelstr. 9",
    "sg:city":"M\u00f6hrenbach",
    "sg:phone":"+49 36783/80219",
    "sg:postcode":"98708",
    "sg:province":"Th\u00fcringen",
    "wof:name":"Helmut Eberhardt",
    "wof:placetype":"venue"
},
  "geometry": {"coordinates":[10.998496,50.622578],"type":"Point"}
}