{
  "type": "Feature",
  "properties": {
    "iso:country":"DE",
    "sg:address":"Upsprunger Str. 18",
    "sg:city":"Salzkotten",
    "sg:phone":"+49 5258/8437",
    "sg:postcode":"33154",
    "sg:province":"Nordrhein-Westfalen",
    "wof:name":"Restaurant Kruse",
    "wof:placetype":"venue"
},
  "geometry": {"coordinates":[8.600525856,51.6667251587],"type":"Point"}
}