{
  "type": "Feature",
  "properties": {
    "iso:country":"DE",
    "sg:address":"Eschelbronner Str. 4",
    "sg:city":"Epfenbach",
    "sg:phone":"+49 4972/635732",
    "sg:postcode":"74925",
    "sg:province":"Baden-W\u00fcrttemberg",
    "wof:name":"Volksbank Schwarzbachtal Eg",
    "wof:placetype":"venue"
},
  "geometry": {"coordinates":[8.909468,49.33696],"type":"Point"}
}