{
  "type": "Feature",
  "properties": {
    "iso:country":"DE",
    "sg:address":"Jahnplatz 1",
    "sg:city":"Aachen",
    "sg:phone":"+49 241/60588",
    "sg:postcode":"52066",
    "sg:province":"Nordrhein-Westfalen",
    "wof:name":"S. Deckardt & J. Kessen",
    "wof:placetype":"venue"
},
  "geometry": {"coordinates":[6.0869250298,50.7505569458],"type":"Point"}
}