{
  "type": "Feature",
  "properties": {
    "iso:country":"DE",
    "sg:address":"Burkhardshof 16",
    "sg:city":"Winnenden",
    "sg:phone":"+49 7195/74966",
    "sg:postcode":"71364",
    "sg:province":"Baden-W\u00fcrttemberg",
    "wof:name":"G. Duschek",
    "wof:placetype":"venue"
},
  "geometry": {"coordinates":[9.417354,48.865986],"type":"Point"}
}