{
  "type": "Feature",
  "properties": {
    "iso:country":"DE",
    "sg:address":"Ravensberger Str. 42",
    "sg:city":"L\u00fcbbecke",
    "sg:postcode":"32312",
    "sg:province":"Nordrhein-Westfalen",
    "wof:name":"Lvm-versicherungen",
    "wof:placetype":"venue"
},
  "geometry": {"coordinates":[8.6994457245,52.3015136719],"type":"Point"}
}