{
  "type": "Feature",
  "properties": {
    "iso:country":"DE",
    "sg:address":"Am Alten Eisenwerk 2",
    "sg:city":"L\u00fcneburg",
    "sg:phone":"+49 4131/37379",
    "sg:postcode":"21339",
    "sg:province":"Niedersachsen",
    "wof:name":"Bft-tankstelle",
    "wof:placetype":"venue"
},
  "geometry": {"coordinates":[10.4112758636,53.2564277649],"type":"Point"}
}