{
  "type": "Feature",
  "properties": {
    "iso:country":"DE",
    "sg:address":"Oberstr. 51",
    "sg:city":"Rieden",
    "sg:phone":"+49 2655/960360",
    "sg:postcode":"56745",
    "sg:province":"Rheinland-Pfalz",
    "wof:name":"R & B Naturstein Gmbh",
    "wof:placetype":"venue"
},
  "geometry": {"coordinates":[7.1825828552,50.3918876648],"type":"Point"}
}