{
  "type": "Feature",
  "properties": {
    "iso:country":"DE",
    "sg:address":"Lachmannweg 48",
    "sg:city":"Hamburg",
    "sg:phone":"+49 40/877211",
    "sg:postcode":"22589",
    "sg:province":"Hamburg",
    "wof:name":"Rolf Bieschke Architekt",
    "wof:placetype":"venue"
},
  "geometry": {"coordinates":[9.828673,53.569984],"type":"Point"}
}