{
  "type": "Feature",
  "properties": {
    "iso:country":"DE",
    "sg:address":"Rottalstr. 31",
    "sg:city":"Bad Griesbach",
    "sg:phone":"+49 8532/920700",
    "sg:postcode":"94086",
    "sg:province":"Bayern",
    "wof:name":"Gottfried Kopplst\u00e4tter",
    "wof:placetype":"venue"
},
  "geometry": {"coordinates":[13.214704,48.418453],"type":"Point"}
}