{
  "type": "Feature",
  "properties": {
    "iso:country":"DE",
    "sg:address":"Obere Schrangenstr. 5",
    "sg:city":"L\u00fcneburg",
    "sg:postcode":"21335",
    "sg:province":"Niedersachsen",
    "wof:name":"L\u00fcne-info",
    "wof:placetype":"venue"
},
  "geometry": {"coordinates":[10.4055128098,53.247882843],"type":"Point"}
}