{
  "type": "Feature",
  "properties": {
    "iso:country":"DE",
    "sg:address":"Ilhorn 1",
    "sg:city":"Neuenkirchen",
    "sg:postcode":"29643",
    "sg:province":"Niedersachsen",
    "wof:name":"Agrar Energie Hohe Heide Gmbh",
    "wof:placetype":"venue"
},
  "geometry": {"coordinates":[9.739995,53.05674],"type":"Point"}
}