{
  "type": "Feature",
  "properties": {
    "iso:country":"DE",
    "sg:address":"Rawiestr. 7",
    "sg:city":"Osnabr\u00fcck",
    "sg:phone":"+49 541/74324",
    "sg:postcode":"49084",
    "sg:province":"Niedersachsen",
    "wof:name":"Bosna - Bodenbel\u00e4ge Service Und Handel",
    "wof:placetype":"venue"
},
  "geometry": {"coordinates":[8.0869951248,52.2703819275],"type":"Point"}
}