{
  "type": "Feature",
  "properties": {
    "iso:country":"DE",
    "sg:address":"R\u00fcsselsheimer Str. 15",
    "sg:city":"Kelsterbach",
    "sg:phone":"+49 6107/2258",
    "sg:postcode":"65451",
    "sg:province":"Hessen",
    "wof:name":"F. D\u00fcrr",
    "wof:placetype":"venue"
},
  "geometry": {"coordinates":[8.529,50.062717],"type":"Point"}
}