{
  "type": "Feature",
  "properties": {
    "iso:country":"DE",
    "sg:address":"Maybachstr. 6",
    "sg:city":"Renningen",
    "sg:phone":"+49 7159/8663",
    "sg:postcode":"71272",
    "sg:province":"Baden-W\u00fcrttemberg",
    "wof:name":"Wiebau Baubedarf Gmbh",
    "wof:placetype":"venue"
},
  "geometry": {"coordinates":[8.929555,48.776409],"type":"Point"}
}