{
  "type": "Feature",
  "properties": {
    "iso:country":"DE",
    "sg:address":"Obere Vorstadt 18",
    "sg:city":"Gundelfingen",
    "sg:phone":"+49 9073/2221",
    "sg:postcode":"89423",
    "sg:province":"Bayern",
    "wof:name":"H. Ebert",
    "wof:placetype":"venue"
},
  "geometry": {"coordinates":[10.3619470596,48.5507507324],"type":"Point"}
}