{
  "type": "Feature",
  "properties": {
    "iso:country":"DE",
    "sg:address":"Weinstr. 93",
    "sg:city":"Bockenheim",
    "sg:phone":"+49 6359/4217",
    "sg:postcode":"67278",
    "sg:province":"Rheinland-Pfalz",
    "wof:name":"Neuh\u00e4usel",
    "wof:placetype":"venue"
},
  "geometry": {"coordinates":[8.1817588806,49.6113739014],"type":"Point"}
}