{
  "type": "Feature",
  "properties": {
    "iso:country":"DE",
    "sg:address":"Brandenburgische Str. 42",
    "sg:city":"Berlin",
    "sg:postcode":"10707",
    "sg:province":"Berlin",
    "wof:name":"Australien Backpackers Deutschland Gmbh",
    "wof:placetype":"venue"
},
  "geometry": {"coordinates":[13.3076763153,52.4969940186],"type":"Point"}
}