{
  "type": "Feature",
  "properties": {
    "iso:country":"DE",
    "sg:address":"Otto-Bussmann-Str. 52a",
    "sg:city":"Bad Vilbel",
    "sg:phone":"+49 6101/582304",
    "sg:postcode":"61118",
    "sg:province":"Hessen",
    "wof:name":"I. V. B. Lampe Gmbh & Co. Individuelle Verm\u00f6gens-",
    "wof:placetype":"venue"
},
  "geometry": {"coordinates":[8.7150745392,50.1720466614],"type":"Point"}
}