{
  "type": "Feature",
  "properties": {
    "iso:country":"DE",
    "sg:address":"Sonsbecker Str. 46",
    "sg:city":"Xanten",
    "sg:postcode":"46509",
    "sg:province":"Nordrhein-Westfalen",
    "wof:name":"Mbl Leasing Gmbh",
    "wof:placetype":"venue"
},
  "geometry": {"coordinates":[6.4331269264,51.6522827148],"type":"Point"}
}