{
  "type": "Feature",
  "properties": {
    "iso:country":"DE",
    "sg:address":"Avenue Charl de Gaulle 9",
    "sg:city":"Berlin",
    "sg:postcode":"13469",
    "sg:province":"Berlin",
    "wof:name":"Lewa-normbau Gmbh",
    "wof:placetype":"venue"
},
  "geometry": {"coordinates":[13.321523,52.602169],"type":"Point"}
}