{
  "type": "Feature",
  "properties": {
    "iso:country":"DE",
    "sg:address":"S\u00fcdfeld 21",
    "sg:city":"Kamen",
    "sg:phone":"+49 2307/43457",
    "sg:postcode":"59174",
    "sg:province":"Nordrhein-Westfalen",
    "wof:name":"Udo Mattheis",
    "wof:placetype":"venue"
},
  "geometry": {"coordinates":[7.7163238525,51.572681427],"type":"Point"}
}