{
  "type": "Feature",
  "properties": {
    "iso:country":"DE",
    "sg:address":"Alsfelder Str. 41",
    "sg:city":"Gr\u00fcnberg",
    "sg:phone":"+49 6401/3008",
    "sg:postcode":"35305",
    "sg:province":"Hessen",
    "wof:name":"Montronix Gmbh",
    "wof:placetype":"venue"
},
  "geometry": {"coordinates":[8.967365,50.592438],"type":"Point"}
}