{
  "type": "Feature",
  "properties": {
    "iso:country":"DE",
    "sg:address":"Wandsbeker Zollstr. 11",
    "sg:city":"Hamburg",
    "sg:postcode":"22041",
    "sg:province":"Hamburg",
    "wof:name":"Finanz Partner Service Gmbh",
    "wof:placetype":"venue"
},
  "geometry": {"coordinates":[10.073627,53.574814],"type":"Point"}
}