{
  "type": "Feature",
  "properties": {
    "iso:country":"DE",
    "sg:address":"Ernst-Th\u00e4lmann-Str. 137",
    "sg:city":"Kleinmachnow",
    "sg:phone":"+49 33203/22364",
    "sg:postcode":"14532",
    "sg:province":"Brandenburg",
    "wof:name":"Lutz Schmidt",
    "wof:placetype":"venue"
},
  "geometry": {"coordinates":[13.2174949646,52.4133529663],"type":"Point"}
}