{
  "type": "Feature",
  "properties": {
    "iso:country":"DE",
    "sg:address":"Gro\u00dfe Gartenstr. 16",
    "sg:city":"Harsefeld",
    "sg:phone":"+49 4164/811141",
    "sg:postcode":"21698",
    "sg:province":"Niedersachsen",
    "wof:name":"Hergen Drube",
    "wof:placetype":"venue"
},
  "geometry": {"coordinates":[9.4972190857,53.4531555176],"type":"Point"}
}