{
  "type": "Feature",
  "properties": {
    "iso:country":"DE",
    "sg:address":"An der Pfarrkirche 6",
    "sg:city":"Bergheim",
    "sg:phone":"+49 2238/42418",
    "sg:postcode":"50129",
    "sg:province":"Nordrhein-Westfalen",
    "wof:name":"Heinz Prill",
    "wof:placetype":"venue"
},
  "geometry": {"coordinates":[6.7401218414,50.9928016663],"type":"Point"}
}