{
  "type": "Feature",
  "properties": {
    "iso:country":"DE",
    "sg:address":"Knappenstr. 88",
    "sg:city":"Katzwinkel",
    "sg:phone":"+49 2741/8814",
    "sg:postcode":"57581",
    "sg:province":"Rheinland-Pfalz",
    "wof:name":"Sparkasse",
    "wof:placetype":"venue"
},
  "geometry": {"coordinates":[7.821706,50.815155],"type":"Point"}
}