{
  "type": "Feature",
  "properties": {
    "iso:country":"DE",
    "sg:address":"Taunusstr. 40",
    "sg:city":"Oestrich-Winkel",
    "sg:phone":"+49 6723/999658",
    "sg:postcode":"65375",
    "sg:province":"Hessen",
    "wof:name":"W. Semmler Weinanbau",
    "wof:placetype":"venue"
},
  "geometry": {"coordinates":[8.0269317627,50.0302391052],"type":"Point"}
}