{
  "type": "Feature",
  "properties": {
    "iso:country":"DE",
    "sg:address":"Treitschkestr. 11",
    "sg:city":"M\u00fcnchen",
    "sg:phone":"+49 89/1414526",
    "sg:postcode":"80992",
    "sg:province":"Bayern",
    "wof:name":"Vereinte Kranken- Versicherung Ag",
    "wof:placetype":"venue"
},
  "geometry": {"coordinates":[11.5225563049,48.1773300171],"type":"Point"}
}