{
  "type": "Feature",
  "properties": {
    "iso:country":"DE",
    "sg:address":"Bahnhofstr. 6",
    "sg:city":"Zaatzke",
    "sg:phone":"+49 3394/445566",
    "sg:postcode":"16909",
    "sg:province":"Brandenburg",
    "wof:name":"Landbistro",
    "wof:placetype":"venue"
},
  "geometry": {"coordinates":[12.4088468552,53.1915664673],"type":"Point"}
}