{
  "type": "Feature",
  "properties": {
    "iso:country":"DE",
    "sg:address":"Rehberg 11",
    "sg:city":"Feilitzsch",
    "sg:postcode":"95183",
    "sg:province":"Bayern",
    "wof:name":"H\u00e4nselstein Wohn- Und Pflege- Heim F\u00fcr Psychisch Kranke",
    "wof:placetype":"venue"
},
  "geometry": {"coordinates":[11.9202604294,50.4130783081],"type":"Point"}
}