{
  "type": "Feature",
  "properties": {
    "iso:country":"DE",
    "sg:address":"Gro\u00dfweg 6",
    "sg:city":"Hannover",
    "sg:phone":"+49 511/462419",
    "sg:postcode":"30457",
    "sg:province":"Niedersachsen",
    "wof:name":"J\u00fcrgen Siebert Steuerberater",
    "wof:placetype":"venue"
},
  "geometry": {"coordinates":[9.6838722229,52.3342437744],"type":"Point"}
}