{
  "type": "Feature",
  "properties": {
    "iso:country":"DE",
    "sg:address":"Hermann-L\u00f6ns-Weg 127",
    "sg:city":"Rellingen",
    "sg:phone":"+49 4101/41367",
    "sg:postcode":"25462",
    "sg:province":"Schleswig-Holstein",
    "wof:name":"Torsten Perrau Baumschule E. K.",
    "wof:placetype":"venue"
},
  "geometry": {"coordinates":[9.88435,53.637402],"type":"Point"}
}