{
  "type": "Feature",
  "properties": {
    "iso:country":"DE",
    "sg:address":"Gutenbergstr. 12",
    "sg:city":"L\u00fcbeck",
    "sg:phone":"+49 451/605616",
    "sg:postcode":"23566",
    "sg:province":"Schleswig-Holstein",
    "wof:name":"Walter Brandt L\u00fcbecker Fahnenfabrik",
    "wof:placetype":"venue"
},
  "geometry": {"coordinates":[10.740927,53.851368],"type":"Point"}
}