{
  "type": "Feature",
  "properties": {
    "iso:country":"DE",
    "sg:address":"Gro\u00dfe Str. 58",
    "sg:city":"Verden",
    "sg:phone":"+49 4231/2558",
    "sg:postcode":"27283",
    "sg:province":"Niedersachsen",
    "wof:name":"Hans J. Holzhausen Stahl- Und Schneidwaren",
    "wof:placetype":"venue"
},
  "geometry": {"coordinates":[9.2289686203,52.9212379456],"type":"Point"}
}