{
  "type": "Feature",
  "properties": {
    "iso:country":"DE",
    "sg:address":"Oderstr. 20",
    "sg:city":"Hamminkeln",
    "sg:phone":"+49 2852/2822",
    "sg:postcode":"46499",
    "sg:province":"Nordrhein-Westfalen",
    "wof:name":"Peter Morlak",
    "wof:placetype":"venue"
},
  "geometry": {"coordinates":[6.6120471954,51.7397842407],"type":"Point"}
}