{
  "type": "Feature",
  "properties": {
    "iso:country":"DE",
    "sg:address":"Marienstr. 12",
    "sg:city":"Zschopau",
    "sg:phone":"+49 3725/23872",
    "sg:postcode":"09405",
    "sg:province":"Sachsen",
    "wof:name":"Johannes M\u00fcller",
    "wof:placetype":"venue"
},
  "geometry": {"coordinates":[13.070962,50.747818],"type":"Point"}
}