{
  "type": "Feature",
  "properties": {
    "iso:country":"DE",
    "sg:address":"Colonie 10",
    "sg:city":"Syke",
    "sg:phone":"+49 4240/413",
    "sg:postcode":"28857",
    "sg:province":"Niedersachsen",
    "wof:name":"Heinz Heusmann",
    "wof:placetype":"venue"
},
  "geometry": {"coordinates":[8.876321,52.865948],"type":"Point"}
}