{
  "type": "Feature",
  "properties": {
    "iso:country":"DE",
    "sg:address":"Werner-Str. 37",
    "sg:city":"Ludwigsburg",
    "sg:phone":"+49 4971/4193610",
    "sg:postcode":"71636",
    "sg:province":"Baden-W\u00fcrttemberg",
    "wof:name":"Benkiser Werk Gmbh & Co Kg",
    "wof:placetype":"venue"
},
  "geometry": {"coordinates":[9.1765480042,48.8950881958],"type":"Point"}
}