{
  "type": "Feature",
  "properties": {
    "iso:country":"DE",
    "sg:address":"Aalener Str 96",
    "sg:city":"Oberkochen",
    "sg:phone":"+49 7364/2910",
    "sg:postcode":"73447",
    "sg:province":"Baden-W\u00fcrttemberg",
    "wof:name":"Petershans & Betzler Gmbh & Co Kg",
    "wof:placetype":"venue"
},
  "geometry": {"coordinates":[10.11586,48.78611],"type":"Point"}
}