{
  "type": "Feature",
  "properties": {
    "iso:country":"DE",
    "sg:address":"Styrumer Str. 16",
    "sg:city":"Oberhausen",
    "sg:phone":"+49 208/809020",
    "sg:postcode":"46045",
    "sg:province":"Nordrhein-Westfalen",
    "wof:name":"Gastst\u00e4tte H.-g. Gr\u00fcning",
    "wof:placetype":"venue"
},
  "geometry": {"coordinates":[6.8483519554,51.4702377319],"type":"Point"}
}