{
  "type": "Feature",
  "properties": {
    "iso:country":"DE",
    "sg:address":"Am G\u00fcterbahnhof 15",
    "sg:city":"Klettgau",
    "sg:phone":"+49 4977/425261",
    "sg:postcode":"79771",
    "sg:province":"Baden-W\u00fcrttemberg",
    "wof:name":"Ena Gmbh",
    "wof:placetype":"venue"
},
  "geometry": {"coordinates":[8.431518,47.66037],"type":"Point"}
}