{
  "type": "Feature",
  "properties": {
    "iso:country":"DE",
    "sg:address":"Hauptstr. 23",
    "sg:city":"Goldenstedt",
    "sg:phone":"+49 4444/1855",
    "sg:postcode":"49424",
    "sg:province":"Niedersachsen",
    "wof:name":"Zur Post",
    "wof:placetype":"venue"
},
  "geometry": {"coordinates":[8.4307746887,52.7861480713],"type":"Point"}
}