{
  "type": "Feature",
  "properties": {
    "iso:country":"DE",
    "sg:address":"Cecilieng\u00e4rten 39",
    "sg:city":"Berlin",
    "sg:phone":"+49 30/8529020",
    "sg:postcode":"12159",
    "sg:province":"Berlin",
    "wof:name":"Kiki Foto-vertrieb Gmbh",
    "wof:placetype":"venue"
},
  "geometry": {"coordinates":[13.3430089951,52.4736022949],"type":"Point"}
}