{
  "type": "Feature",
  "properties": {
    "iso:country":"DE",
    "sg:address":"Marktplatz 12",
    "sg:city":"Weinheim",
    "sg:phone":"+49 6201/65586",
    "sg:postcode":"69469",
    "sg:province":"Baden-W\u00fcrttemberg",
    "wof:name":"Eichbaum",
    "wof:placetype":"venue"
},
  "geometry": {"coordinates":[8.6719532013,49.5465011597],"type":"Point"}
}