{
  "type": "Feature",
  "properties": {
    "iso:country":"DE",
    "sg:address":"Telleringstr. 46",
    "sg:city":"D\u00fcsseldorf",
    "sg:phone":"+49 211/995950",
    "sg:postcode":"40597",
    "sg:province":"Nordrhein-Westfalen",
    "wof:name":"Kopo West Handels Gmbh",
    "wof:placetype":"venue"
},
  "geometry": {"coordinates":[6.882033,51.163986],"type":"Point"}
}