{
  "type": "Feature",
  "properties": {
    "iso:country":"DE",
    "sg:address":"Hermann-Sussann-Weg 12",
    "sg:city":"Kenzingen",
    "sg:phone":"+49 7644/8899",
    "sg:postcode":"79341",
    "sg:province":"Baden-W\u00fcrttemberg",
    "wof:name":"Georg Reinbold",
    "wof:placetype":"venue"
},
  "geometry": {"coordinates":[7.7811632156,48.1913223267],"type":"Point"}
}