{
  "type": "Feature",
  "properties": {
    "iso:country":"DE",
    "sg:address":"Dr.-Illert-Str. 16",
    "sg:city":"Worms",
    "sg:phone":"+49 6241/75792",
    "sg:postcode":"67549",
    "sg:province":"Rheinland-Pfalz",
    "wof:name":"Roger Winkler",
    "wof:placetype":"venue"
},
  "geometry": {"coordinates":[8.3067884445,49.6403121948],"type":"Point"}
}