{
  "type": "Feature",
  "properties": {
    "iso:country":"DE",
    "sg:address":"F\u00f6pplstr. 21",
    "sg:city":"Leipzig",
    "sg:phone":"+49 341/2324236",
    "sg:postcode":"04347",
    "sg:province":"Sachsen",
    "wof:name":"G\u00fcnter Stauch",
    "wof:placetype":"venue"
},
  "geometry": {"coordinates":[12.436838,51.367523],"type":"Point"}
}