{
  "type": "Feature",
  "properties": {
    "iso:country":"DE",
    "sg:address":"Bauhofweg 1",
    "sg:city":"Wittstock",
    "sg:phone":"+49 2204/842500",
    "sg:postcode":"16909",
    "sg:province":"Brandenburg",
    "wof:name":"Accel Instruments Gmbh Forschungsausruestungen",
    "wof:placetype":"venue"
},
  "geometry": {"coordinates":[7.18473,50.959435],"type":"Point"}
}