{
  "type": "Feature",
  "properties": {
    "iso:country":"DE",
    "sg:address":"H\u00f6nnetalstr. 291",
    "sg:city":"Hemer",
    "sg:phone":"+49 4923/7296870",
    "sg:postcode":"58675",
    "sg:province":"Nordrhein-Westfalen",
    "wof:name":"Wkw-suma Gmbh & Co. Kg",
    "wof:placetype":"venue"
},
  "geometry": {"coordinates":[7.787257,51.374977],"type":"Point"}
}