{
  "type": "Feature",
  "properties": {
    "iso:country":"DE",
    "sg:address":"Solmsstr. 81",
    "sg:city":"Ahaus",
    "sg:phone":"+49 2561/8004",
    "sg:postcode":"48683",
    "sg:province":"Nordrhein-Westfalen",
    "wof:name":"Alw Ger\u00e4tebau Gmbh",
    "wof:placetype":"venue"
},
  "geometry": {"coordinates":[6.920446,52.08197],"type":"Point"}
}