{
  "type": "Feature",
  "properties": {
    "iso:country":"DE",
    "sg:address":"Hauptstr. 146",
    "sg:city":"Bad Lauterberg",
    "sg:phone":"+49 5524/80865",
    "sg:postcode":"37431",
    "sg:province":"Niedersachsen",
    "wof:name":"A. Schmidt",
    "wof:placetype":"venue"
},
  "geometry": {"coordinates":[10.46901,51.630718],"type":"Point"}
}