{
  "type": "Feature",
  "properties": {
    "iso:country":"DE",
    "sg:address":"Nordring 23",
    "sg:city":"B\u00fcnde",
    "sg:phone":"+49 5223/17870",
    "sg:postcode":"32257",
    "sg:province":"Nordrhein-Westfalen",
    "wof:name":"Jacobi-haus Im Evangelischen Johanneswerk E. V.",
    "wof:placetype":"venue"
},
  "geometry": {"coordinates":[8.582801,52.200085],"type":"Point"}
}