{
  "type": "Feature",
  "properties": {
    "iso:country":"DE",
    "sg:address":"Rittersturzstr. 1",
    "sg:city":"P\u00fcnderich",
    "sg:phone":"+49 6542/2573",
    "sg:postcode":"56862",
    "sg:province":"Rheinland-Pfalz",
    "wof:name":"Theo Buss",
    "wof:placetype":"venue"
},
  "geometry": {"coordinates":[7.1322288513,50.0397262573],"type":"Point"}
}