{
  "type": "Feature",
  "properties": {
    "iso:country":"DE",
    "sg:address":"Wehlenteichweg 1",
    "sg:city":"Lauchhammer",
    "sg:phone":"+49 3574/49170",
    "sg:postcode":"01979",
    "sg:province":"Brandenburg",
    "wof:name":"Rischke & Mehner Werbeagentur Gmbh",
    "wof:placetype":"venue"
},
  "geometry": {"coordinates":[13.772454,51.491741],"type":"Point"}
}