{
  "type": "Feature",
  "properties": {
    "iso:country":"DE",
    "sg:address":"Sohlst\u00e4ttenstr. 22",
    "sg:city":"Ratingen",
    "sg:phone":"+49 2102/41750",
    "sg:postcode":"40880",
    "sg:province":"Nordrhein-Westfalen",
    "wof:name":"Hansj\u00f6rg Kr\u00fcger",
    "wof:placetype":"venue"
},
  "geometry": {"coordinates":[6.818998,51.311256],"type":"Point"}
}