{
  "type": "Feature",
  "properties": {
    "iso:country":"DE",
    "sg:address":"Karl-Marx-Str. 20",
    "sg:city":"Bad Freienwalde",
    "sg:phone":"+49 3344/3577",
    "sg:postcode":"16259",
    "sg:province":"Brandenburg",
    "wof:name":"B. Fischer",
    "wof:placetype":"venue"
},
  "geometry": {"coordinates":[14.0316772461,52.7881011963],"type":"Point"}
}