{
  "type": "Feature",
  "properties": {
    "iso:country":"DE",
    "sg:address":"Gartenstr. 17",
    "sg:city":"Bodman-Ludwigshafen",
    "sg:postcode":"78351",
    "sg:province":"Baden-W\u00fcrttemberg",
    "wof:name":"K. H. Tbiemig",
    "wof:placetype":"venue"
},
  "geometry": {"coordinates":[9.056678,47.82103],"type":"Point"}
}