{
  "type": "Feature",
  "properties": {
    "iso:country":"DE",
    "sg:address":"H\u00f6lzlestr. 44/1",
    "sg:city":"Balingen",
    "sg:postcode":"72336",
    "sg:province":"Baden-W\u00fcrttemberg",
    "wof:name":"Ov Objekt-verwaltung Gmbh",
    "wof:placetype":"venue"
},
  "geometry": {"coordinates":[8.8635673523,48.2957115173],"type":"Point"}
}