{
  "type": "Feature",
  "properties": {
    "iso:country":"DE",
    "sg:address":"Bernhard-Friedrich-Weg 16",
    "sg:city":"Oldenburg",
    "sg:phone":"+49 441/9570470",
    "sg:postcode":"26129",
    "sg:province":"Niedersachsen",
    "wof:name":"Dieter H\u00f6gemann",
    "wof:placetype":"venue"
},
  "geometry": {"coordinates":[8.1532487869,53.1475296021],"type":"Point"}
}