{
  "type": "Feature",
  "properties": {
    "iso:country":"DE",
    "sg:address":"Lindenstr. 16",
    "sg:city":"Sch\u00f6nwalde",
    "sg:phone":"+49 33056/81362",
    "sg:postcode":"16352",
    "sg:province":"Mecklenburg-Vorpommern",
    "wof:name":"Torsten Schulz",
    "wof:placetype":"venue"
},
  "geometry": {"coordinates":[13.4364709854,52.6814994812],"type":"Point"}
}