{
  "type": "Feature",
  "properties": {
    "iso:country":"DE",
    "sg:address":"Schubertstr. 20",
    "sg:city":"Kahl",
    "sg:phone":"+49 6188/1377",
    "sg:postcode":"63796",
    "sg:province":"Bayern",
    "wof:name":"K. M. Sch\u00e4fer",
    "wof:placetype":"venue"
},
  "geometry": {"coordinates":[9.0144100189,50.0646133423],"type":"Point"}
}