{
  "type": "Feature",
  "properties": {
    "iso:country":"DE",
    "sg:address":"Heckstr. 18",
    "sg:city":"Essen",
    "sg:phone":"+49 201/491848",
    "sg:postcode":"45239",
    "sg:province":"Nordrhein-Westfalen",
    "wof:name":"Tuchmacher Stuben",
    "wof:placetype":"venue"
},
  "geometry": {"coordinates":[7.0029349327,51.3893699646],"type":"Point"}
}