{
  "type": "Feature",
  "properties": {
    "iso:country":"DE",
    "sg:address":"S\u00fcsterstr. 32",
    "sg:city":"Sch\u00fcttorf",
    "sg:phone":"+49 5923/2660",
    "sg:postcode":"48465",
    "sg:province":"Niedersachsen",
    "wof:name":"Christa Pierzina Masseurin",
    "wof:placetype":"venue"
},
  "geometry": {"coordinates":[7.22613,52.326839],"type":"Point"}
}