{
  "type": "Feature",
  "properties": {
    "iso:country":"DE",
    "sg:address":"Kulmainer Str. 12",
    "sg:city":"Immenreuth",
    "sg:phone":"+49 9642/2789",
    "sg:postcode":"95505",
    "sg:province":"Bayern",
    "wof:name":"Ev. Pfarramt",
    "wof:placetype":"venue"
},
  "geometry": {"coordinates":[11.875752449,49.9078788757],"type":"Point"}
}