{
  "type": "Feature",
  "properties": {
    "iso:country":"DE",
    "sg:address":"\u00c4u\u00dfere Bayreuther Str. 5",
    "sg:city":"N\u00fcrnberg",
    "sg:phone":"+49 911/3658468",
    "sg:postcode":"90409",
    "sg:province":"Bayern",
    "wof:name":"Blumenstube Walter",
    "wof:placetype":"venue"
},
  "geometry": {"coordinates":[11.09578,49.465221],"type":"Point"}
}