{
  "type": "Feature",
  "properties": {
    "iso:country":"DE",
    "sg:address":"H\u00e4rtsfeldstr. 4",
    "sg:city":"Bopfingen",
    "sg:phone":"+49 7362/5140",
    "sg:postcode":"73441",
    "sg:province":"Baden-W\u00fcrttemberg",
    "wof:name":"H\u00e4rtsfeldstube",
    "wof:placetype":"venue"
},
  "geometry": {"coordinates":[10.3495073318,48.858215332],"type":"Point"}
}