{
  "type": "Feature",
  "properties": {
    "iso:country":"DE",
    "sg:address":"An der Ziegelei 3",
    "sg:city":"Altdorf",
    "sg:phone":"+49 9187/97040",
    "sg:postcode":"90518",
    "sg:province":"Bayern",
    "wof:name":"Polyplast Sander Gmbh & Co. Betriebs-kg",
    "wof:placetype":"venue"
},
  "geometry": {"coordinates":[11.3314933777,49.3904075623],"type":"Point"}
}