{
  "type": "Feature",
  "properties": {
    "iso:country":"DE",
    "sg:address":"Leonhardsruhstr. 19",
    "sg:city":"Gunzenhausen",
    "sg:phone":"+49 9831/2591",
    "sg:postcode":"91710",
    "sg:province":"Bayern",
    "wof:name":"Peter M\u00e4hrlein",
    "wof:placetype":"venue"
},
  "geometry": {"coordinates":[10.766169,49.11417],"type":"Point"}
}