{
  "type": "Feature",
  "properties": {
    "iso:country":"DE",
    "sg:address":"Karlstr. 10",
    "sg:city":"Kenzingen",
    "sg:phone":"+49 7644/279",
    "sg:postcode":"79341",
    "sg:province":"Baden-W\u00fcrttemberg",
    "wof:name":"Sonne",
    "wof:placetype":"venue"
},
  "geometry": {"coordinates":[7.8168911934,48.1791229248],"type":"Point"}
}