{
  "type": "Feature",
  "properties": {
    "iso:country":"DE",
    "sg:address":"Otto-Prein-Str. 29",
    "sg:city":"Kamen",
    "sg:postcode":"59174",
    "sg:province":"Nordrhein-Westfalen",
    "wof:name":"Wellner Die B\u00e4ckerei Gmbh",
    "wof:placetype":"venue"
},
  "geometry": {"coordinates":[7.611409,51.581181],"type":"Point"}
}