{
  "type": "Feature",
  "properties": {
    "iso:country":"DE",
    "sg:address":"Volchlinstr. 11",
    "sg:city":"Buxheim",
    "sg:phone":"+49 8458/8807",
    "sg:postcode":"85114",
    "sg:province":"Bayern",
    "wof:name":"Johann Funk",
    "wof:placetype":"venue"
},
  "geometry": {"coordinates":[11.277657,48.823284],"type":"Point"}
}