{
  "type": "Feature",
  "properties": {
    "iso:country":"DE",
    "sg:address":"Zeisiggasse 9",
    "sg:city":"Kirchheim",
    "sg:phone":"+49 89/9045855",
    "sg:postcode":"85551",
    "sg:province":"Bayern",
    "wof:name":"B & S Beisser- Schierlinger Gmbh",
    "wof:placetype":"venue"
},
  "geometry": {"coordinates":[11.7541265488,48.1667976379],"type":"Point"}
}