{
  "type": "Feature",
  "properties": {
    "iso:country":"DE",
    "sg:address":"Ortwinstr. 16-18",
    "sg:city":"Berlin",
    "sg:phone":"+49 30/4012288",
    "sg:postcode":"13465",
    "sg:province":"Berlin",
    "wof:name":"Quast-automaten",
    "wof:placetype":"venue"
},
  "geometry": {"coordinates":[13.2824602127,52.6361465454],"type":"Point"}
}