{
  "type": "Feature",
  "properties": {
    "iso:country":"DE",
    "sg:address":"Villinger Str. 16",
    "sg:city":"Donaueschingen",
    "sg:phone":"+49 771/13782",
    "sg:postcode":"78166",
    "sg:province":"Baden-W\u00fcrttemberg",
    "wof:name":"R. Lauer",
    "wof:placetype":"venue"
},
  "geometry": {"coordinates":[8.4958677292,47.9547386169],"type":"Point"}
}