{
  "type": "Feature",
  "properties": {
    "iso:country":"DE",
    "sg:address":"Hans-Henny-Jahnn-Weg 9",
    "sg:city":"Hamburg",
    "sg:phone":"+49 40/22705220",
    "sg:postcode":"22085",
    "sg:province":"Hamburg",
    "wof:name":"Int Infosolution Gmbh",
    "wof:placetype":"venue"
},
  "geometry": {"coordinates":[10.014143,53.57972],"type":"Point"}
}