{
  "type": "Feature",
  "properties": {
    "iso:country":"DE",
    "sg:address":"Lindenstr. 14",
    "sg:city":"Stemmen",
    "sg:phone":"+49 4267/311",
    "sg:postcode":"27389",
    "sg:province":"Niedersachsen",
    "wof:name":"Heinrich Luttmann",
    "wof:placetype":"venue"
},
  "geometry": {"coordinates":[9.555817,53.227825],"type":"Point"}
}