{
  "type": "Feature",
  "properties": {
    "iso:country":"DE",
    "sg:address":"Werdener Str. 86",
    "sg:city":"L\u00fcdinghausen",
    "sg:phone":"+49 2591/79700",
    "sg:postcode":"59348",
    "sg:province":"Nordrhein-Westfalen",
    "wof:name":"Arno Meyer Architekt",
    "wof:placetype":"venue"
},
  "geometry": {"coordinates":[7.459215,51.776947],"type":"Point"}
}