{
  "type": "Feature",
  "properties": {
    "iso:country":"DE",
    "sg:address":"Ellertalstr. 40",
    "sg:city":"Litzendorf",
    "sg:phone":"+49 9505/6194",
    "sg:postcode":"96123",
    "sg:province":"Bayern",
    "wof:name":"Ludwig Hollfelder",
    "wof:placetype":"venue"
},
  "geometry": {"coordinates":[11.0512533188,49.9160232544],"type":"Point"}
}