{
  "type": "Feature",
  "properties": {
    "iso:country":"DE",
    "sg:address":"M\u00fchlenstr. 9",
    "sg:city":"Bad Laasphe",
    "sg:phone":"+49 2752/200654",
    "sg:postcode":"57334",
    "sg:province":"Nordrhein-Westfalen",
    "wof:name":"Hartmut Schr\u00f6der",
    "wof:placetype":"venue"
},
  "geometry": {"coordinates":[8.4131793976,50.9256896973],"type":"Point"}
}