{
  "type": "Feature",
  "properties": {
    "iso:country":"DE",
    "sg:address":"Egon-Erwin-Kisch-Str. 3",
    "sg:city":"Dresden",
    "sg:phone":"+49 351/436170",
    "sg:postcode":"01069",
    "sg:province":"Sachsen",
    "wof:name":"Dts Dietz Treuhand Steuerberatungs-gmbh",
    "wof:placetype":"venue"
},
  "geometry": {"coordinates":[13.7411289215,51.0309104919],"type":"Point"}
}