{
  "type": "Feature",
  "properties": {
    "iso:country":"DE",
    "sg:address":"Paul-Robeson-Str. 9",
    "sg:city":"Berlin",
    "sg:phone":"+49 30/4458593",
    "sg:postcode":"10439",
    "sg:province":"Berlin",
    "wof:name":"Otto Kabisch Inh. Bernard Weist",
    "wof:placetype":"venue"
},
  "geometry": {"coordinates":[13.41036,52.552555],"type":"Point"}
}