{
  "type": "Feature",
  "properties": {
    "iso:country":"DE",
    "sg:address":"Obersteinbach 4",
    "sg:city":"Gai\u00dfach",
    "sg:phone":"+49 8042/2327",
    "sg:postcode":"83674",
    "sg:province":"Bayern",
    "wof:name":"Hermann Lauer Architekt",
    "wof:placetype":"venue"
},
  "geometry": {"coordinates":[11.571362,47.701122],"type":"Point"}
}