{
  "type": "Feature",
  "properties": {
    "iso:country":"DE",
    "sg:address":"Kalandstr. 3",
    "sg:city":"M\u00fcnsterdorf",
    "sg:phone":"+49 4821/82302",
    "sg:postcode":"25587",
    "sg:province":"Schleswig-Holstein",
    "wof:name":"Ev. Pfarramt M\u00fcnsterdorf",
    "wof:placetype":"venue"
},
  "geometry": {"coordinates":[9.5412750244,53.9038467407],"type":"Point"}
}