{
  "type": "Feature",
  "properties": {
    "iso:country":"DE",
    "sg:address":"Wall 8",
    "sg:city":"Hann. M\u00fcnden",
    "sg:phone":"+49 5541/73880",
    "sg:postcode":"34346",
    "sg:province":"Niedersachsen",
    "wof:name":"Hans-ulrich Beiler Rechtsanwalt",
    "wof:placetype":"venue"
},
  "geometry": {"coordinates":[9.6533212662,51.4155044556],"type":"Point"}
}