{
  "type": "Feature",
  "properties": {
    "iso:country":"DE",
    "sg:address":"Lange Str. 30",
    "sg:city":"Landesbergen",
    "sg:phone":"+49 5025/6194",
    "sg:postcode":"31628",
    "sg:province":"Niedersachsen",
    "wof:name":"Kurt Hillmann",
    "wof:placetype":"venue"
},
  "geometry": {"coordinates":[9.119586,52.55674],"type":"Point"}
}