{
  "type": "Feature",
  "properties": {
    "iso:country":"DE",
    "sg:address":"Ackerstr. 10",
    "sg:city":"Meiningen",
    "sg:phone":"+49 3693/478955",
    "sg:postcode":"98617",
    "sg:province":"Th\u00fcringen",
    "wof:name":"A. W\u00f6lfing",
    "wof:placetype":"venue"
},
  "geometry": {"coordinates":[10.42706,50.572262],"type":"Point"}
}