{
  "type": "Feature",
  "properties": {
    "iso:country":"DE",
    "sg:address":"Stresemannallee 15",
    "sg:city":"Frankfurt",
    "sg:phone":"+49 69/6308347",
    "sg:postcode":"60596",
    "sg:province":"Hessen",
    "wof:name":"Dachverband Medizinische Technik",
    "wof:placetype":"venue"
},
  "geometry": {"coordinates":[8.6696710587,50.0990028381],"type":"Point"}
}