{
  "type": "Feature",
  "properties": {
    "iso:country":"DE",
    "sg:address":"Werftstr. 218",
    "sg:city":"Kiel",
    "sg:phone":"+49 431/70230",
    "sg:postcode":"24143",
    "sg:province":"Schleswig-Holstein",
    "wof:name":"Rrv Recycling Und Rohstoffverwertungs Gmbh",
    "wof:placetype":"venue"
},
  "geometry": {"coordinates":[10.1380090714,54.3102722168],"type":"Point"}
}