{
  "type": "Feature",
  "properties": {
    "iso:country":"DE",
    "sg:address":"Schlo\u00dfstr. 46",
    "sg:city":"Altenburg",
    "sg:phone":"+49 3447/502747",
    "sg:postcode":"04600",
    "sg:province":"Th\u00fcringen",
    "wof:name":"Etzold Gmbh",
    "wof:placetype":"venue"
},
  "geometry": {"coordinates":[12.459416,50.952675],"type":"Point"}
}