{
  "type": "Feature",
  "properties": {
    "iso:country":"DE",
    "sg:address":"Haldenstr.",
    "sg:city":"D\u00fcrmentingen",
    "sg:phone":"+49 7371/6389",
    "sg:postcode":"88525",
    "sg:province":"Baden-W\u00fcrttemberg",
    "wof:name":"Kath. Pfarramt",
    "wof:placetype":"venue"
},
  "geometry": {"coordinates":[9.5323448181,48.1420249939],"type":"Point"}
}