{
  "type": "Feature",
  "properties": {
    "iso:country":"DE",
    "sg:address":"Bahnhofstr. 8",
    "sg:city":"Sch\u00f6nberg",
    "sg:phone":"+49 4344/1300",
    "sg:postcode":"24217",
    "sg:province":"Schleswig-Holstein",
    "wof:name":"Franz Herger\u00f6der",
    "wof:placetype":"venue"
},
  "geometry": {"coordinates":[10.372555,54.392048],"type":"Point"}
}