{
  "type": "Feature",
  "properties": {
    "iso:country":"DE",
    "sg:address":"Heideweg 6",
    "sg:city":"Babenhausen",
    "sg:phone":"+49 8333/2872",
    "sg:postcode":"87727",
    "sg:province":"Bayern",
    "wof:name":"G. Steinle",
    "wof:placetype":"venue"
},
  "geometry": {"coordinates":[10.2421779633,48.1413078308],"type":"Point"}
}