{
  "type": "Feature",
  "properties": {
    "iso:country":"DE",
    "sg:address":"Sparrh\u00e4rmlingweg 56",
    "sg:city":"Stuttgart",
    "sg:phone":"+49 711/5091003",
    "sg:postcode":"70376",
    "sg:province":"Baden-W\u00fcrttemberg",
    "wof:name":"Altenburg",
    "wof:placetype":"venue"
},
  "geometry": {"coordinates":[9.2021083832,48.812122345],"type":"Point"}
}