{
  "type": "Feature",
  "properties": {
    "iso:country":"DE",
    "sg:address":"Orchesterstr. 10",
    "sg:city":"Kaiserslautern",
    "sg:postcode":"67655",
    "sg:province":"Rheinland-Pfalz",
    "wof:name":"Cd-paradies",
    "wof:placetype":"venue"
},
  "geometry": {"coordinates":[7.7732310295,49.4425239563],"type":"Point"}
}