{
  "type": "Feature",
  "properties": {
    "iso:country":"DE",
    "sg:address":"Enzianweg 18",
    "sg:city":"P\u00f6cking",
    "sg:phone":"+49 8157/7465",
    "sg:postcode":"82343",
    "sg:province":"Bayern",
    "wof:name":"Inge Schwarz",
    "wof:placetype":"venue"
},
  "geometry": {"coordinates":[11.3059854507,47.9729232788],"type":"Point"}
}