{
  "type": "Feature",
  "properties": {
    "iso:country":"DE",
    "sg:address":"Kellereistr. 26",
    "sg:city":"Eberbach",
    "sg:phone":"+49 6271/2378",
    "sg:postcode":"69412",
    "sg:province":"Baden-W\u00fcrttemberg",
    "wof:name":"Karl Zorn",
    "wof:placetype":"venue"
},
  "geometry": {"coordinates":[8.984287262,49.4620437622],"type":"Point"}
}