{
  "type": "Feature",
  "properties": {
    "iso:country":"DE",
    "sg:address":"Krekelingheide 9",
    "sg:city":"Essen",
    "sg:phone":"+49 201/221081",
    "sg:postcode":"45259",
    "sg:province":"Nordrhein-Westfalen",
    "wof:name":"Westschrott Gmbh",
    "wof:placetype":"venue"
},
  "geometry": {"coordinates":[7.06027,51.409958],"type":"Point"}
}