{
  "type": "Feature",
  "properties": {
    "iso:country":"DE",
    "sg:address":"Schierghoferstr. 7",
    "sg:city":"Traunstein",
    "sg:phone":"+49 861/2140",
    "sg:postcode":"83278",
    "sg:province":"Bayern",
    "wof:name":"Ing. Grad. Rudolf Simhofer Architekt",
    "wof:placetype":"venue"
},
  "geometry": {"coordinates":[12.630503,47.874706],"type":"Point"}
}