{
  "type": "Feature",
  "properties": {
    "iso:country":"DE",
    "sg:address":"Daimlerstr. 25",
    "sg:city":"Maulbronn",
    "sg:phone":"+49 7043/900000",
    "sg:postcode":"75433",
    "sg:province":"Baden-W\u00fcrttemberg",
    "wof:name":"Visitool Gmbh",
    "wof:placetype":"venue"
},
  "geometry": {"coordinates":[8.7906990051,48.9932899475],"type":"Point"}
}