{
  "type": "Feature",
  "properties": {
    "iso:country":"DE",
    "sg:address":"Balinger Str. 75",
    "sg:city":"Albstadt",
    "sg:phone":"+49 7435/268",
    "sg:postcode":"72459",
    "sg:province":"Baden-W\u00fcrttemberg",
    "wof:name":"Albrecht Schlegel",
    "wof:placetype":"venue"
},
  "geometry": {"coordinates":[8.918266,48.222973],"type":"Point"}
}