{
  "type": "Feature",
  "properties": {
    "iso:country":"DE",
    "sg:address":"Langelohstr. 5",
    "sg:city":"Eslohe",
    "sg:phone":"+49 2973/6525",
    "sg:postcode":"59889",
    "sg:province":"Nordrhein-Westfalen",
    "wof:name":"Rudolf Kersting",
    "wof:placetype":"venue"
},
  "geometry": {"coordinates":[8.1637783051,51.2494392395],"type":"Point"}
}