{
  "type": "Feature",
  "properties": {
    "iso:country":"DE",
    "sg:address":"Rolandstr. 11q",
    "sg:city":"Aachen",
    "sg:postcode":"52070",
    "sg:province":"Nordrhein-Westfalen",
    "wof:name":"Zoe Consulting Ohg",
    "wof:placetype":"venue"
},
  "geometry": {"coordinates":[6.0918970108,50.7847061157],"type":"Point"}
}