{
  "type": "Feature",
  "properties": {
    "iso:country":"DE",
    "sg:address":"Werkstr. 107",
    "sg:city":"Schwerin",
    "sg:phone":"+49 385/614607",
    "sg:postcode":"19061",
    "sg:province":"Mecklenburg-Vorpommern",
    "wof:name":"Manfred Maron",
    "wof:placetype":"venue"
},
  "geometry": {"coordinates":[11.3857660294,53.5760688782],"type":"Point"}
}