{
  "type": "Feature",
  "properties": {
    "iso:country":"DE",
    "sg:address":"Herzogstr. 15",
    "sg:city":"D\u00fcsseldorf",
    "sg:phone":"+49 211/82602",
    "sg:postcode":"40217",
    "sg:province":"Nordrhein-Westfalen",
    "wof:name":"Rw Finanzberatungs- Und Beteiligungs-gmbh",
    "wof:placetype":"venue"
},
  "geometry": {"coordinates":[6.77676,51.21563],"type":"Point"}
}