{
  "type": "Feature",
  "properties": {
    "iso:country":"DE",
    "sg:address":"M\u00fchlfelder Str. 18",
    "sg:city":"Herrsching",
    "sg:phone":"+49 8152/925176",
    "sg:postcode":"82211",
    "sg:province":"Bayern",
    "wof:name":"R. Lidl Und Partner",
    "wof:placetype":"venue"
},
  "geometry": {"coordinates":[11.175581,47.996983],"type":"Point"}
}