{
  "type": "Feature",
  "properties": {
    "iso:country":"DE",
    "sg:address":"Schweinfurter Str. 25",
    "sg:city":"Volkach",
    "sg:phone":"+49 9381/2688",
    "sg:postcode":"97332",
    "sg:province":"Bayern",
    "wof:name":"Paul Barthelme",
    "wof:placetype":"venue"
},
  "geometry": {"coordinates":[10.2262268066,49.8895721436],"type":"Point"}
}