{
  "type": "Feature",
  "properties": {
    "iso:country":"DE",
    "sg:address":"Ebitzweg 12",
    "sg:city":"Stuttgart",
    "sg:phone":"+49 711/523670",
    "sg:postcode":"70374",
    "sg:province":"Baden-W\u00fcrttemberg",
    "wof:name":"Koch & Hauptmann",
    "wof:placetype":"venue"
},
  "geometry": {"coordinates":[9.233068,48.803761],"type":"Point"}
}