{
  "type": "Feature",
  "properties": {
    "iso:country":"DE",
    "sg:address":"G\u00e4rtnerstr. 40",
    "sg:city":"Essen",
    "sg:phone":"+49 201/222641",
    "sg:postcode":"45128",
    "sg:province":"Nordrhein-Westfalen",
    "wof:name":"Kurt Vignold Gmbh & Co. Handels Kg",
    "wof:placetype":"venue"
},
  "geometry": {"coordinates":[7.018245,51.446312],"type":"Point"}
}