{
  "type": "Feature",
  "properties": {
    "iso:country":"DE",
    "sg:address":"Br\u00fcckenstr. 49",
    "sg:city":"Gummersbach",
    "sg:phone":"+49 2261/22484",
    "sg:postcode":"51643",
    "sg:province":"Nordrhein-Westfalen",
    "wof:name":"Wilhelm K\u00f6rfer Gmbh",
    "wof:placetype":"venue"
},
  "geometry": {"coordinates":[7.559196,51.024895],"type":"Point"}
}