{
  "type": "Feature",
  "properties": {
    "iso:country":"DE",
    "sg:address":"B\u00f6ttingerstr. 67",
    "sg:city":"M\u00fcnchen",
    "sg:phone":"+49 89/21020",
    "sg:postcode":"80796",
    "sg:province":"Bayern",
    "wof:name":"Radio Freies Europa",
    "wof:placetype":"venue"
},
  "geometry": {"coordinates":[11.5666904449,48.1672706604],"type":"Point"}
}