{
  "type": "Feature",
  "properties": {
    "iso:country":"DE",
    "sg:address":"Johann-Sigmund-Weg 2",
    "sg:city":"Memmingen",
    "sg:phone":"+49 8331/71741",
    "sg:postcode":"87700",
    "sg:province":"Bayern",
    "wof:name":"Irene Wendling Anlageberaterin",
    "wof:placetype":"venue"
},
  "geometry": {"coordinates":[10.1082801819,47.9422836304],"type":"Point"}
}