{
  "type": "Feature",
  "properties": {
    "iso:country":"DE",
    "sg:address":"Breiter Weg 2 a",
    "sg:city":"Bad Kreuznach",
    "sg:phone":"+49 671/2040",
    "sg:postcode":"55545",
    "sg:province":"Rheinland-Pfalz",
    "wof:name":"Praxis Dr. Med. Ewen Und F\u00f6rster",
    "wof:placetype":"venue"
},
  "geometry": {"coordinates":[7.8653311729,49.8677711487],"type":"Point"}
}