{
  "type": "Feature",
  "properties": {
    "iso:country":"DE",
    "sg:address":"Gesellensteig 18",
    "sg:city":"Salzgitter",
    "sg:phone":"+49 5341/86940",
    "sg:postcode":"38229",
    "sg:province":"Niedersachsen",
    "wof:name":"J\u00fcrgen Beer Gmbh",
    "wof:placetype":"venue"
},
  "geometry": {"coordinates":[10.3496332169,52.1659164429],"type":"Point"}
}