{
  "type": "Feature",
  "properties": {
    "iso:country":"DE",
    "sg:address":"Markelstr. 9",
    "sg:city":"Berlin",
    "sg:phone":"+49 30/79700800",
    "sg:postcode":"12163",
    "sg:province":"Berlin",
    "wof:name":"Tf Tecnic Filter Gmbh",
    "wof:placetype":"venue"
},
  "geometry": {"coordinates":[13.325616,52.463943],"type":"Point"}
}