{
  "type": "Feature",
  "properties": {
    "iso:country":"DE",
    "sg:address":"Hagener Str. 69",
    "sg:city":"Sundern",
    "sg:phone":"+49 2393/207",
    "sg:postcode":"59846",
    "sg:province":"Nordrhein-Westfalen",
    "wof:name":"Wilhelm Nolte",
    "wof:placetype":"venue"
},
  "geometry": {"coordinates":[7.964461,51.259754],"type":"Point"}
}