{
  "type": "Feature",
  "properties": {
    "iso:country":"DE",
    "sg:address":"Sandhofer Str 20",
    "sg:city":"Mannheim",
    "sg:phone":"+49 621/7482255",
    "sg:postcode":"68305",
    "sg:province":"Baden-W\u00fcrttemberg",
    "wof:name":"Ssd Schall- Und Schwingungs-d\u00e4mpfer Gmbh",
    "wof:placetype":"venue"
},
  "geometry": {"coordinates":[8.4719400406,49.5203208923],"type":"Point"}
}