{
  "type": "Feature",
  "properties": {
    "iso:country":"DE",
    "sg:address":"Worther Weg 105",
    "sg:city":"Geesthacht",
    "sg:phone":"+49 4152/841471",
    "sg:postcode":"21502",
    "sg:province":"Schleswig-Holstein",
    "wof:name":"H. Kampff",
    "wof:placetype":"venue"
},
  "geometry": {"coordinates":[10.393312,53.443287],"type":"Point"}
}