{
  "type": "Feature",
  "properties": {
    "iso:country":"DE",
    "sg:address":"Neundorfer Str. 8",
    "sg:city":"Plauen",
    "sg:postcode":"08523",
    "sg:province":"Sachsen",
    "wof:name":"Stadtbibliothek",
    "wof:placetype":"venue"
},
  "geometry": {"coordinates":[12.132277,50.494919],"type":"Point"}
}