{
  "type": "Feature",
  "properties": {
    "iso:country":"DE",
    "sg:address":"Reinhardstr. 11a",
    "sg:city":"Flieden",
    "sg:phone":"+49 6655/5554",
    "sg:postcode":"36103",
    "sg:province":"Hessen",
    "wof:name":"Stefan Scheich Masseur",
    "wof:placetype":"venue"
},
  "geometry": {"coordinates":[9.564763,50.424377],"type":"Point"}
}