{
  "type": "Feature",
  "properties": {
    "iso:country":"DE",
    "sg:address":"Hauptstr. 35",
    "sg:city":"Bermbach",
    "sg:postcode":"36419",
    "sg:province":"Th\u00fcringen",
    "wof:name":"Katholisches Pfarramt",
    "wof:placetype":"venue"
},
  "geometry": {"coordinates":[8.3124160767,50.2357673645],"type":"Point"}
}