{
  "type": "Feature",
  "properties": {
    "iso:country":"DE",
    "sg:address":"Rurtalstr. 50",
    "sg:city":"Heinsberg",
    "sg:phone":"+49 2453/446",
    "sg:postcode":"52525",
    "sg:province":"Nordrhein-Westfalen",
    "wof:name":"Jakob Hermanns",
    "wof:placetype":"venue"
},
  "geometry": {"coordinates":[6.1732778549,51.0399932861],"type":"Point"}
}