{
  "type": "Feature",
  "properties": {
    "iso:country":"DE",
    "sg:address":"Moselstr. 3",
    "sg:city":"Naunheim",
    "sg:phone":"+49 2654/7364",
    "sg:postcode":"56753",
    "sg:province":"Rheinland-Pfalz",
    "wof:name":"Werner J. Seul",
    "wof:placetype":"venue"
},
  "geometry": {"coordinates":[7.319972,50.25214],"type":"Point"}
}