{
  "type": "Feature",
  "properties": {
    "iso:country":"DE",
    "sg:address":"Dorfstr. 6",
    "sg:city":"Tensfeld",
    "sg:phone":"+49 4922/0231946",
    "sg:postcode":"23824",
    "sg:province":"Schleswig-Holstein",
    "wof:name":"Reitsport Monika Hanke Gmbh",
    "wof:placetype":"venue"
},
  "geometry": {"coordinates":[7.1363549232,50.9764137268],"type":"Point"}
}