{
  "type": "Feature",
  "properties": {
    "iso:country":"DE",
    "sg:address":"Stadtgraben 44",
    "sg:city":"G\u00fcsten",
    "sg:postcode":"39439",
    "sg:province":"Sachsen-Anhalt",
    "wof:name":"Vital Gesell. Zur Vorbereitung Von Touristikobjekten Mbh",
    "wof:placetype":"venue"
},
  "geometry": {"coordinates":[11.620207,51.797321],"type":"Point"}
}