{
  "type": "Feature",
  "properties": {
    "iso:country":"DE",
    "sg:address":"Untere Gartenstr. 1",
    "sg:city":"Sulzbach-Rosenberg",
    "sg:phone":"+49 9661/4956",
    "sg:postcode":"92237",
    "sg:province":"Bayern",
    "wof:name":"Rainer J\u00e4ger",
    "wof:placetype":"venue"
},
  "geometry": {"coordinates":[11.7451925278,49.5029830933],"type":"Point"}
}