{
  "type": "Feature",
  "properties": {
    "iso:country":"DE",
    "sg:address":"M\u00fcnsterstr. 20",
    "sg:city":"Versmold",
    "sg:phone":"+49 5423/7706",
    "sg:postcode":"33775",
    "sg:province":"Nordrhein-Westfalen",
    "wof:name":"Provinzial Versicherungen Beckmeier & M\u00fcller",
    "wof:placetype":"venue"
},
  "geometry": {"coordinates":[8.1517705917,52.0396194458],"type":"Point"}
}