{
  "type": "Feature",
  "properties": {
    "iso:country":"DE",
    "sg:address":"Nabweg 4",
    "sg:city":"Hamburg",
    "sg:phone":"+49 40/6404308",
    "sg:postcode":"22393",
    "sg:province":"Hamburg",
    "wof:name":"Kurt G\u00fcnther",
    "wof:placetype":"venue"
},
  "geometry": {"coordinates":[10.109266,53.63776],"type":"Point"}
}