{
  "type": "Feature",
  "properties": {
    "iso:country":"DE",
    "sg:address":"Schiffbr\u00fcckgasse 3",
    "sg:city":"Amberg",
    "sg:phone":"+49 9621/23705",
    "sg:postcode":"92224",
    "sg:province":"Bayern",
    "wof:name":"Adelmann-landgraf-sch\u00e4fer",
    "wof:placetype":"venue"
},
  "geometry": {"coordinates":[11.856505394,49.4438400269],"type":"Point"}
}