{
  "type": "Feature",
  "properties": {
    "iso:country":"DE",
    "sg:address":"Peterstr. 32",
    "sg:city":"Seligenstadt",
    "sg:phone":"+49 6182/21421",
    "sg:postcode":"63500",
    "sg:province":"Hessen",
    "wof:name":"Anny R\u00fcckert",
    "wof:placetype":"venue"
},
  "geometry": {"coordinates":[8.9781150818,50.0405387878],"type":"Point"}
}