{
  "type": "Feature",
  "properties": {
    "iso:country":"DE",
    "sg:address":"Kommi\u00dfstr. 2",
    "sg:city":"Wolfenb\u00fcttel",
    "sg:phone":"+49 5331/2598",
    "sg:postcode":"38300",
    "sg:province":"Niedersachsen",
    "wof:name":"Rupprecht",
    "wof:placetype":"venue"
},
  "geometry": {"coordinates":[10.5344552994,52.1613273621],"type":"Point"}
}