{
  "type": "Feature",
  "properties": {
    "iso:country":"DE",
    "sg:address":"Wallgasse 2",
    "sg:city":"Mainburg",
    "sg:phone":"+49 8751/1281",
    "sg:postcode":"84048",
    "sg:province":"Bayern",
    "wof:name":"Eduard Wild",
    "wof:placetype":"venue"
},
  "geometry": {"coordinates":[11.788314,48.642262],"type":"Point"}
}