{
  "type": "Feature",
  "properties": {
    "iso:country":"DE",
    "sg:address":"Akazienstr. 11",
    "sg:city":"M\u00fcnchenbernsdorf",
    "sg:phone":"+49 36604/80205",
    "sg:postcode":"07589",
    "sg:province":"Th\u00fcringen",
    "wof:name":"Meister B\u00e4cker Gmbh",
    "wof:placetype":"venue"
},
  "geometry": {"coordinates":[11.931422,50.819206],"type":"Point"}
}