{
  "type": "Feature",
  "properties": {
    "iso:country":"DE",
    "sg:address":"Maximilianstr. 45",
    "sg:city":"M\u00fcnchen",
    "sg:phone":"+49 89/220323",
    "sg:postcode":"80538",
    "sg:province":"Bayern",
    "wof:name":"Prof. V. Steiner Architekt",
    "wof:placetype":"venue"
},
  "geometry": {"coordinates":[11.587616,48.138126],"type":"Point"}
}