{
  "type": "Feature",
  "properties": {
    "iso:country":"DE",
    "sg:address":"Ochsenweg 3",
    "sg:city":"Melle",
    "sg:phone":"+49 5422/48255",
    "sg:postcode":"49324",
    "sg:province":"Niedersachsen",
    "wof:name":"M\u00f6ring",
    "wof:placetype":"venue"
},
  "geometry": {"coordinates":[8.317899704,52.2141609192],"type":"Point"}
}