{
  "type": "Feature",
  "properties": {
    "iso:country":"DE",
    "sg:address":"Johannisstr. 112",
    "sg:city":"Osnabr\u00fcck",
    "sg:phone":"+49 541/52222",
    "sg:postcode":"49074",
    "sg:province":"Niedersachsen",
    "wof:name":"Rosenhof 15",
    "wof:placetype":"venue"
},
  "geometry": {"coordinates":[8.0522651672,52.2683372498],"type":"Point"}
}