{
  "type": "Feature",
  "properties": {
    "iso:country":"DE",
    "sg:address":"Deckertstr. 81",
    "sg:city":"Bielefeld",
    "sg:phone":"+49 521/140443",
    "sg:postcode":"33617",
    "sg:province":"Nordrhein-Westfalen",
    "wof:name":"Egge-apotheke E. K. Inh. Elisabeth Bangel",
    "wof:placetype":"venue"
},
  "geometry": {"coordinates":[8.515463,52.001934],"type":"Point"}
}