{
  "type": "Feature",
  "properties": {
    "iso:country":"DE",
    "sg:address":"Max-Planck-Str. 5",
    "sg:city":"Berlin",
    "sg:postcode":"12489",
    "sg:province":"Berlin",
    "wof:name":"Pus Projekt Und Serviceges. F\u00fcr Verkehrswesen Mbh",
    "wof:placetype":"venue"
},
  "geometry": {"coordinates":[13.5361938477,52.4288902283],"type":"Point"}
}