{
  "type": "Feature",
  "properties": {
    "iso:country":"DE",
    "sg:address":"F\u00fcrstenbergplatz 8",
    "sg:city":"Leverkusen",
    "sg:phone":"+49 2171/47062",
    "sg:postcode":"51379",
    "sg:province":"Nordrhein-Westfalen",
    "wof:name":"Heinz L\u00f6w Ingenieur",
    "wof:placetype":"venue"
},
  "geometry": {"coordinates":[7.0036392212,51.0701141357],"type":"Point"}
}