{
  "type": "Feature",
  "properties": {
    "iso:country":"DE",
    "sg:address":"Professor-J\u00e4cklein-Str. 2",
    "sg:city":"Volkach",
    "sg:phone":"+49 9381/2029",
    "sg:postcode":"97332",
    "sg:province":"Bayern",
    "wof:name":"Jutta Donath",
    "wof:placetype":"venue"
},
  "geometry": {"coordinates":[10.2275896072,49.8643302917],"type":"Point"}
}