{
  "type": "Feature",
  "properties": {
    "iso:country":"DE",
    "sg:address":"Wolfratshauser Str. 28",
    "sg:city":"M\u00fcnchen",
    "sg:phone":"+49 89/7241061",
    "sg:postcode":"81379",
    "sg:province":"Bayern",
    "wof:name":"Gert R\u00f6hrl Immobilien- Treuhand Gmbh",
    "wof:placetype":"venue"
},
  "geometry": {"coordinates":[11.5411911011,48.1002655029],"type":"Point"}
}