{
  "type": "Feature",
  "properties": {
    "iso:country":"DE",
    "sg:address":"Blomberger Stra\u00dfe 24",
    "sg:city":"Horn-Bad Meinberg",
    "sg:phone":"+49 5234/894040",
    "sg:postcode":"32805",
    "sg:province":"Nordrhein-Westfalen",
    "wof:name":"Lippe-tip , Ein Neues Medium Im Internet",
    "wof:placetype":"venue"
},
  "geometry": {"coordinates":[8.9865427017,51.8999404907],"type":"Point"}
}