{
  "type": "Feature",
  "properties": {
    "iso:country":"DE",
    "sg:address":"Kaiser-Wilhelm-Platz 1",
    "sg:city":"Essen",
    "sg:phone":"+49 201/519817",
    "sg:postcode":"45276",
    "sg:province":"Nordrhein-Westfalen",
    "wof:name":"J. Bruchhausen Inh. Ch. Knoll",
    "wof:placetype":"venue"
},
  "geometry": {"coordinates":[7.077255,51.448013],"type":"Point"}
}