{
  "type": "Feature",
  "properties": {
    "iso:country":"DE",
    "sg:address":"Flosser Str. 17",
    "sg:city":"St\u00f6rnstein",
    "sg:phone":"+49 9602/8048",
    "sg:postcode":"92721",
    "sg:province":"Bayern",
    "wof:name":"Negnal",
    "wof:placetype":"venue"
},
  "geometry": {"coordinates":[12.206604,49.731483],"type":"Point"}
}