{
  "type": "Feature",
  "properties": {
    "iso:country":"DE",
    "sg:address":"Schumannstr. 1",
    "sg:city":"Beilstein",
    "sg:phone":"+49 7062/8344",
    "sg:postcode":"71717",
    "sg:province":"Baden-W\u00fcrttemberg",
    "wof:name":"Karl Brodt Bauunternehmen Gmbh",
    "wof:placetype":"venue"
},
  "geometry": {"coordinates":[9.3049764633,49.0410690308],"type":"Point"}
}