{
  "type": "Feature",
  "properties": {
    "iso:country":"DE",
    "sg:address":"K\u00f6sterbergstr. 74",
    "sg:city":"Hamburg",
    "sg:phone":"+49 40/868362",
    "sg:postcode":"22587",
    "sg:province":"Hamburg",
    "wof:name":"Falk Grundbesitz Kg",
    "wof:placetype":"venue"
},
  "geometry": {"coordinates":[9.7843112946,53.565738678],"type":"Point"}
}