{
  "type": "Feature",
  "properties": {
    "iso:country":"DE",
    "sg:address":"Moosweg 8",
    "sg:city":"Kressbronn",
    "sg:phone":"+49 7543/8847",
    "sg:postcode":"88079",
    "sg:province":"Baden-W\u00fcrttemberg",
    "wof:name":"H. Mayer Architekt",
    "wof:placetype":"venue"
},
  "geometry": {"coordinates":[9.604699,47.599724],"type":"Point"}
}