{
  "type": "Feature",
  "properties": {
    "iso:country":"DE",
    "sg:address":"Rathausplatz 12",
    "sg:city":"Marbach",
    "sg:phone":"+49 7144/37041",
    "sg:postcode":"71672",
    "sg:province":"Baden-W\u00fcrttemberg",
    "wof:name":"Ev. Pfarramt Rielingshausen",
    "wof:placetype":"venue"
},
  "geometry": {"coordinates":[9.475358963,48.063785553],"type":"Point"}
}