{
  "type": "Feature",
  "properties": {
    "iso:country":"DE",
    "sg:address":"Falckweg 2",
    "sg:city":"Hamburg",
    "sg:phone":"+49 40/8801583",
    "sg:postcode":"22605",
    "sg:province":"Hamburg",
    "wof:name":"Georg Fles Gmbh",
    "wof:placetype":"venue"
},
  "geometry": {"coordinates":[9.8869524002,53.5576591492],"type":"Point"}
}