{
  "type": "Feature",
  "properties": {
    "iso:country":"DE",
    "sg:address":"Hohewurthstr. 72",
    "sg:city":"Loxstedt",
    "sg:phone":"+49 4744/2016",
    "sg:postcode":"27612",
    "sg:province":"Niedersachsen",
    "wof:name":"I. Langner",
    "wof:placetype":"venue"
},
  "geometry": {"coordinates":[8.6439199448,53.4857597351],"type":"Point"}
}