{
  "type": "Feature",
  "properties": {
    "iso:country":"DE",
    "sg:address":"Bachstr. 54",
    "sg:city":"Winningen",
    "sg:phone":"+49 2606/215",
    "sg:postcode":"56333",
    "sg:province":"Rheinland-Pfalz",
    "wof:name":"E. Saas Haus- Und K\u00fcchenger\u00e4te",
    "wof:placetype":"venue"
},
  "geometry": {"coordinates":[7.5188150406,50.3138847351],"type":"Point"}
}