{
  "type": "Feature",
  "properties": {
    "iso:country":"DE",
    "sg:address":"Wei\u00dfenhorner Str. 2",
    "sg:city":"Nersingen",
    "sg:phone":"+49 7308/921840",
    "sg:postcode":"89278",
    "sg:province":"Bayern",
    "wof:name":"Papeterie Nersingen Gmbh",
    "wof:placetype":"venue"
},
  "geometry": {"coordinates":[10.1236572266,48.4283485413],"type":"Point"}
}