{
  "type": "Feature",
  "properties": {
    "iso:country":"DE",
    "sg:address":"Hallbergmoos",
    "sg:city":"Hallbergmoos",
    "sg:phone":"+49 811/1033",
    "sg:postcode":"85399",
    "sg:province":"Bayern",
    "wof:name":"Raiffeisenbank Hallbergmoos-goldach",
    "wof:placetype":"venue"
},
  "geometry": {"coordinates":[11.73276,48.313931],"type":"Point"}
}