{
  "type": "Feature",
  "properties": {
    "iso:country":"DE",
    "sg:address":"M\u00f6rscher Str. 149",
    "sg:city":"Frankenthal",
    "sg:phone":"+49 6233/63467",
    "sg:postcode":"67227",
    "sg:province":"Rheinland-Pfalz",
    "wof:name":"Ludwig Baro",
    "wof:placetype":"venue"
},
  "geometry": {"coordinates":[8.371016,49.545658],"type":"Point"}
}