{
  "type": "Feature",
  "properties": {
    "iso:country":"DE",
    "sg:address":"Garmser Str. 6",
    "sg:city":"Wangerland",
    "sg:phone":"+49 4463/430",
    "sg:postcode":"26434",
    "sg:province":"Niedersachsen",
    "wof:name":"Altdeutsche Stube",
    "wof:placetype":"venue"
},
  "geometry": {"coordinates":[7.8641619682,53.6735038757],"type":"Point"}
}