{
  "type": "Feature",
  "properties": {
    "iso:country":"DE",
    "sg:address":"Erich-Schmid-Str. 5",
    "sg:city":"Ludwigsburg",
    "sg:phone":"+49 7141/927792",
    "sg:postcode":"71638",
    "sg:province":"Baden-W\u00fcrttemberg",
    "wof:name":"Atlas Wohnbau Gmbh",
    "wof:placetype":"venue"
},
  "geometry": {"coordinates":[9.1934528351,48.8842773438],"type":"Point"}
}