{
  "type": "Feature",
  "properties": {
    "iso:country":"DE",
    "sg:address":"Tatzendpromenade 1 a",
    "sg:city":"Jena",
    "sg:phone":"+49 3641/29440",
    "sg:postcode":"07745",
    "sg:province":"Th\u00fcringen",
    "wof:name":"Lasos Lasertechnik Gmbh",
    "wof:placetype":"venue"
},
  "geometry": {"coordinates":[11.569538,50.919819],"type":"Point"}
}