{
  "type": "Feature",
  "properties": {
    "iso:country":"DE",
    "sg:address":"Pfullendorfer Str. 10",
    "sg:city":"Ostrach",
    "sg:phone":"+49 7585/1528",
    "sg:postcode":"88356",
    "sg:province":"Baden-W\u00fcrttemberg",
    "wof:name":"Otto Baier",
    "wof:placetype":"venue"
},
  "geometry": {"coordinates":[9.378927,47.953094],"type":"Point"}
}