{
  "type": "Feature",
  "properties": {
    "iso:country":"DE",
    "sg:address":"Tuchmachergasse 2",
    "sg:city":"Oederan",
    "sg:phone":"+49 37292/60575",
    "sg:postcode":"09569",
    "sg:province":"Sachsen",
    "wof:name":"Rainer Kl\u00f6ber",
    "wof:placetype":"venue"
},
  "geometry": {"coordinates":[13.1710700989,50.8614082336],"type":"Point"}
}