{
  "type": "Feature",
  "properties": {
    "iso:country":"DE",
    "sg:address":"Hauptstr. 78",
    "sg:city":"Porta Westfalica",
    "sg:phone":"+49 571/71108",
    "sg:postcode":"32457",
    "sg:province":"Nordrhein-Westfalen",
    "wof:name":"Gerhard Gottlob",
    "wof:placetype":"venue"
},
  "geometry": {"coordinates":[8.913853,52.235832],"type":"Point"}
}