{
  "type": "Feature",
  "properties": {
    "iso:country":"DE",
    "sg:address":"Oberweierer Hauptstr. 56",
    "sg:city":"Friesenheim",
    "sg:phone":"+49 7821/61398",
    "sg:postcode":"77948",
    "sg:province":"Baden-W\u00fcrttemberg",
    "wof:name":"Friedrich Schwend",
    "wof:placetype":"venue"
},
  "geometry": {"coordinates":[7.897735,48.377083],"type":"Point"}
}