{
  "type": "Feature",
  "properties": {
    "iso:country":"DE",
    "sg:address":"Im G\u00e4\u00dfle 1",
    "sg:city":"K\u00f6nigsheim",
    "sg:phone":"+49 7429/2354",
    "sg:postcode":"78598",
    "sg:province":"Baden-W\u00fcrttemberg",
    "wof:name":"Dreher Transporte Gmbh",
    "wof:placetype":"venue"
},
  "geometry": {"coordinates":[8.8616695404,48.1018218994],"type":"Point"}
}