{
  "type": "Feature",
  "properties": {
    "iso:country":"DE",
    "sg:city":"Sinzheim",
    "sg:phone":"+49 4972/2183942",
    "sg:postcode":"76547",
    "sg:province":"Baden-W\u00fcrttemberg",
    "wof:name":"Sparkasse B\u00fchl",
    "wof:placetype":"venue"
},
  "geometry": {"coordinates":[8.16564,48.76405],"type":"Point"}
}