{
  "type": "Feature",
  "properties": {
    "iso:country":"DE",
    "sg:address":"Postfach 248",
    "sg:city":"Herne",
    "sg:postcode":"44601",
    "sg:province":"Nordrhein-Westfalen",
    "wof:name":"Karl Emil Schulte Kg",
    "wof:placetype":"venue"
},
  "geometry": {"coordinates":[7.21924,51.538521],"type":"Point"}
}