{
  "type": "Feature",
  "properties": {
    "iso:country":"DE",
    "sg:address":"Gro\u00dfe Milower Str. 27a",
    "sg:city":"Rathenow",
    "sg:phone":"+49 3385/512844",
    "sg:postcode":"14712",
    "sg:province":"Brandenburg",
    "wof:name":"Annemarie Patermann",
    "wof:placetype":"venue"
},
  "geometry": {"coordinates":[12.3375091553,52.5985221863],"type":"Point"}
}