{
  "type": "Feature",
  "properties": {
    "iso:country":"DE",
    "sg:address":"Heinrich-Br\u00fcning-Str. 30A",
    "sg:city":"Oldenburg",
    "sg:postcode":"26133",
    "sg:province":"Niedersachsen",
    "wof:name":"Anton Backhus",
    "wof:placetype":"venue"
},
  "geometry": {"coordinates":[8.228345,53.094994],"type":"Point"}
}