{
  "type": "Feature",
  "properties": {
    "iso:country":"DE",
    "sg:address":"Augustinerstr. 42",
    "sg:city":"Erfurt",
    "sg:phone":"+49 361/5402220",
    "sg:postcode":"99084",
    "sg:province":"Th\u00fcringen",
    "wof:name":"Sabine Hollei",
    "wof:placetype":"venue"
},
  "geometry": {"coordinates":[11.030039,50.981873],"type":"Point"}
}