{
  "type": "Feature",
  "properties": {
    "iso:country":"DE",
    "sg:address":"Marienstr. 56",
    "sg:city":"Krefeld",
    "sg:phone":"+49 2151/306667",
    "sg:postcode":"47807",
    "sg:province":"Nordrhein-Westfalen",
    "wof:name":"Manfred Storms",
    "wof:placetype":"venue"
},
  "geometry": {"coordinates":[6.584867,51.306095],"type":"Point"}
}