{
  "type": "Feature",
  "properties": {
    "iso:country":"DE",
    "sg:address":"Petristr. 10",
    "sg:city":"Heilbad Heiligenstadt",
    "sg:phone":"+49 3606/614282",
    "sg:postcode":"37308",
    "sg:province":"Th\u00fcringen",
    "wof:name":"H.-joachim Rieckhof",
    "wof:placetype":"venue"
},
  "geometry": {"coordinates":[10.1331424713,51.3750534058],"type":"Point"}
}