{
  "type": "Feature",
  "properties": {
    "iso:country":"DE",
    "sg:address":"Am Heiderand 2",
    "sg:city":"Gro\u00dferkmannsdorf",
    "sg:phone":"+49 3528/442552",
    "sg:postcode":"01454",
    "sg:province":"Sachsen",
    "wof:name":"G. Kutsche",
    "wof:placetype":"venue"
},
  "geometry": {"coordinates":[13.9107265472,51.0954284668],"type":"Point"}
}