{
  "type": "Feature",
  "properties": {
    "iso:country":"DE",
    "sg:address":"Paffrather Str. 19",
    "sg:city":"Bergisch Gladbach",
    "sg:phone":"+49 2202/37057",
    "sg:postcode":"51465",
    "sg:province":"Nordrhein-Westfalen",
    "wof:name":"G\u00fcnter R. Mettmann Heilpraktiker",
    "wof:placetype":"venue"
},
  "geometry": {"coordinates":[7.1278967857,50.9921302795],"type":"Point"}
}