{
  "type": "Feature",
  "properties": {
    "iso:country":"DE",
    "sg:address":"Industriestr 28",
    "sg:city":"Dannstadt-Schauernheim",
    "sg:phone":"+49 6231/939810",
    "sg:postcode":"67125",
    "sg:province":"Rheinland-Pfalz",
    "wof:name":"Dk-therm-heizsysteme Vertriebs-gmbh",
    "wof:placetype":"venue"
},
  "geometry": {"coordinates":[8.321556,49.431084],"type":"Point"}
}