{
  "type": "Feature",
  "properties": {
    "iso:country":"DE",
    "sg:address":"Danziger Str. 20",
    "sg:city":"Fulda",
    "sg:phone":"+49 661/37366",
    "sg:postcode":"36043",
    "sg:province":"Hessen",
    "wof:name":"Ludwig B\u00fcttner Elektromeister",
    "wof:placetype":"venue"
},
  "geometry": {"coordinates":[9.702906,50.542065],"type":"Point"}
}