{
  "type": "Feature",
  "properties": {
    "iso:country":"DE",
    "sg:address":"Mainweg 1",
    "sg:city":"Frankfurt",
    "sg:phone":"+49 69/4738293",
    "sg:postcode":"65929",
    "sg:province":"Hessen",
    "wof:name":"African Art, Afrikanische Masken Und Figuren, Excl",
    "wof:placetype":"venue"
},
  "geometry": {"coordinates":[8.5502099991,50.1002044678],"type":"Point"}
}