{
  "type": "Feature",
  "properties": {
    "iso:country":"DE",
    "sg:address":"Osdorfer Landstr. 180",
    "sg:city":"Hamburg",
    "sg:phone":"+49 40/80995199",
    "sg:postcode":"22549",
    "sg:province":"Hamburg",
    "wof:name":"Hars Elektrotechnik Gmbh",
    "wof:placetype":"venue"
},
  "geometry": {"coordinates":[9.852103,53.572472],"type":"Point"}
}