{
  "type": "Feature",
  "properties": {
    "iso:country":"DE",
    "sg:address":"Pommernring 16",
    "sg:city":"Offenbach",
    "sg:phone":"+49 6348/940293",
    "sg:postcode":"76877",
    "sg:province":"Rheinland-Pfalz",
    "wof:name":"Oliver Harnisch",
    "wof:placetype":"venue"
},
  "geometry": {"coordinates":[8.1866483688,49.1964149475],"type":"Point"}
}