{
  "type": "Feature",
  "properties": {
    "iso:country":"DE",
    "sg:address":"Adolf-von-Vorwerk Strasse",
    "sg:city":"Wuppertal",
    "sg:phone":"+49 202/2462424",
    "sg:postcode":"42287",
    "sg:province":"Nordrhein-Westfalen",
    "wof:name":"Restposten365.de Die Restpostenplattform Im Internet",
    "wof:placetype":"venue"
},
  "geometry": {"coordinates":[7.2008948326,51.2445449829],"type":"Point"}
}