{
  "type": "Feature",
  "properties": {
    "iso:country":"DE",
    "sg:address":"Murtener Str. 5",
    "sg:city":"Berlin",
    "sg:postcode":"12205",
    "sg:province":"Berlin",
    "wof:name":"Dritte Gemeinn\u00fctzige Krankenhaus Gmbh",
    "wof:placetype":"venue"
},
  "geometry": {"coordinates":[13.2907791138,52.4306678772],"type":"Point"}
}