{
  "type": "Feature",
  "properties": {
    "iso:country":"DE",
    "sg:address":"Gordenhegge 1",
    "sg:city":"Rosendahl",
    "sg:postcode":"48720",
    "sg:province":"Nordrhein-Westfalen",
    "wof:name":"L\u00f6chtefeld Gmbh & Co. Kg",
    "wof:placetype":"venue"
},
  "geometry": {"coordinates":[7.1906108856,52.0170593262],"type":"Point"}
}