{
  "type": "Feature",
  "properties": {
    "iso:country":"DE",
    "sg:address":"Hecksbergstr. 1",
    "sg:city":"Braunfels",
    "sg:phone":"+49 6442/4053",
    "sg:postcode":"35619",
    "sg:province":"Hessen",
    "wof:name":"Wilbert Richter",
    "wof:placetype":"venue"
},
  "geometry": {"coordinates":[8.3870849609,50.5177459717],"type":"Point"}
}