{
  "type": "Feature",
  "properties": {
    "iso:country":"DE",
    "sg:address":"Marktstr 36",
    "sg:city":"Lohne",
    "sg:phone":"+49 69/29960",
    "sg:postcode":"49393",
    "sg:province":"Niedersachsen",
    "wof:name":"Lombard Odier Verm\u00f6egensbetreuung Gmbh",
    "wof:placetype":"venue"
},
  "geometry": {"coordinates":[8.673534,50.114159],"type":"Point"}
}