{
  "type": "Feature",
  "properties": {
    "iso:country":"DE",
    "sg:address":"Pontchateau-Platz 1",
    "sg:city":"Nassau",
    "sg:phone":"+49 2604/8686",
    "sg:postcode":"56377",
    "sg:province":"Rheinland-Pfalz",
    "wof:name":"Oranien-apotheke",
    "wof:placetype":"venue"
},
  "geometry": {"coordinates":[7.799181,50.313068],"type":"Point"}
}