{
  "type": "Feature",
  "properties": {
    "iso:country":"DE",
    "sg:address":"F\u00e4hrstr. 13",
    "sg:city":"Erden",
    "sg:phone":"+49 6532/3996",
    "sg:postcode":"54492",
    "sg:province":"Rheinland-Pfalz",
    "wof:name":"Eberhard Mentges Nachf. Gabriele Mentges",
    "wof:placetype":"venue"
},
  "geometry": {"coordinates":[7.0243082047,49.9790763855],"type":"Point"}
}