{
  "type": "Feature",
  "properties": {
    "iso:country":"DE",
    "sg:address":"Paplitzer Str. 19",
    "sg:city":"M\u00fcckendorf",
    "sg:phone":"+49 33704/66223",
    "sg:postcode":"15837",
    "sg:province":"Brandenburg",
    "wof:name":"Ernst Jahn",
    "wof:placetype":"venue"
},
  "geometry": {"coordinates":[13.50296,52.045071],"type":"Point"}
}