{
  "type": "Feature",
  "properties": {
    "iso:country":"DE",
    "sg:address":"Westerbrak 10",
    "sg:city":"Kirchbrak",
    "sg:phone":"+49 5533/2623",
    "sg:postcode":"37619",
    "sg:province":"Niedersachsen",
    "wof:name":"Archiv Der Von Grone",
    "wof:placetype":"venue"
},
  "geometry": {"coordinates":[9.556702,51.975063],"type":"Point"}
}