{
  "type": "Feature",
  "properties": {
    "iso:country":"DE",
    "sg:address":"Kornblumenring 80",
    "sg:city":"Berlin",
    "sg:phone":"+49 30/6645147",
    "sg:postcode":"12357",
    "sg:province":"Berlin",
    "wof:name":"Mario Skaletzki Malermeisterbetrieb Gmbh",
    "wof:placetype":"venue"
},
  "geometry": {"coordinates":[13.496886,52.422153],"type":"Point"}
}