{
  "type": "Feature",
  "properties": {
    "iso:country":"DE",
    "sg:address":"Schl\u00f6rplatz 3",
    "sg:city":"Weiden",
    "sg:phone":"+49 961/36535",
    "sg:postcode":"92637",
    "sg:province":"Bayern",
    "wof:name":"F. Fi\u00dfl",
    "wof:placetype":"venue"
},
  "geometry": {"coordinates":[12.1659574509,49.6768684387],"type":"Point"}
}