{
  "type": "Feature",
  "properties": {
    "iso:country":"DE",
    "sg:address":"H\u00fcnefeldstr. 11",
    "sg:city":"Zweibr\u00fccken",
    "sg:phone":"+49 6332/75144",
    "sg:postcode":"66482",
    "sg:province":"Rheinland-Pfalz",
    "wof:name":"Richard Rinsche",
    "wof:placetype":"venue"
},
  "geometry": {"coordinates":[7.3443827629,49.2586364746],"type":"Point"}
}