{
  "type": "Feature",
  "properties": {
    "iso:country":"DE",
    "sg:address":"Elisabethenstr. 31",
    "sg:city":"Ulm",
    "sg:phone":"+49 731/31325",
    "sg:postcode":"89077",
    "sg:province":"Baden-W\u00fcrttemberg",
    "wof:name":"Helmut Eder",
    "wof:placetype":"venue"
},
  "geometry": {"coordinates":[9.9746952057,48.39503479],"type":"Point"}
}