{
  "type": "Feature",
  "properties": {
    "iso:country":"DE",
    "sg:address":"Hermann-L\u00f6ns-Str. 7",
    "sg:city":"Zirndorf",
    "sg:phone":"+49 911/606771",
    "sg:postcode":"90513",
    "sg:province":"Bayern",
    "wof:name":"Geweniger Montagen Gmbh",
    "wof:placetype":"venue"
},
  "geometry": {"coordinates":[10.963653,49.445648],"type":"Point"}
}