{
  "type": "Feature",
  "properties": {
    "iso:country":"DE",
    "sg:address":"Marktstr. 4",
    "sg:city":"Kappeln",
    "sg:phone":"+49 4642/1614",
    "sg:postcode":"24376",
    "sg:province":"Schleswig-Holstein",
    "wof:name":"Klaus Bengelstorf",
    "wof:placetype":"venue"
},
  "geometry": {"coordinates":[9.929488,54.661892],"type":"Point"}
}