{
  "type": "Feature",
  "properties": {
    "iso:country":"DE",
    "sg:address":"Gehegder Weg 16",
    "sg:city":"Altena",
    "sg:phone":"+49 2352/23301",
    "sg:postcode":"58762",
    "sg:province":"Nordrhein-Westfalen",
    "wof:name":"Herriet M\u00fcller",
    "wof:placetype":"venue"
},
  "geometry": {"coordinates":[7.673213,51.307171],"type":"Point"}
}