{
  "type": "Feature",
  "properties": {
    "iso:country":"DE",
    "sg:address":"B\u00fcrgerm.-Notz-Str. 1",
    "sg:city":"Durach",
    "sg:phone":"+49 831/61938",
    "sg:postcode":"87471",
    "sg:province":"Bayern",
    "wof:name":"G\u00e4stehaus A. U. E. Harzenetter",
    "wof:placetype":"venue"
},
  "geometry": {"coordinates":[10.3462324142,47.6948699951],"type":"Point"}
}