{
  "type": "Feature",
  "properties": {
    "iso:country":"DE",
    "sg:address":"L\u00fcttringhauser Str. 18b",
    "sg:city":"Remscheid",
    "sg:phone":"+49 2191/690073",
    "sg:postcode":"42897",
    "sg:province":"Nordrhein-Westfalen",
    "wof:name":"Philippe Renaudin Heilpraktikerin",
    "wof:placetype":"venue"
},
  "geometry": {"coordinates":[7.2528247833,51.1944961548],"type":"Point"}
}