{
  "type": "Feature",
  "properties": {
    "iso:country":"DE",
    "sg:address":"Keplerstrasse 20",
    "sg:city":"Gera",
    "sg:postcode":"07549",
    "sg:province":"Th\u00fcringen",
    "wof:name":"Ugn-umweltconsult Gmbh",
    "wof:placetype":"venue"
},
  "geometry": {"coordinates":[12.058963,50.854202],"type":"Point"}
}