{
  "type": "Feature",
  "properties": {
    "iso:country":"DE",
    "sg:address":"Grenzweg 36",
    "sg:city":"Buchholz",
    "sg:phone":"+49 4181/99299",
    "sg:postcode":"21244",
    "sg:province":"Niedersachsen",
    "wof:name":"Mobiler Pflegedienst Buchholz",
    "wof:placetype":"venue"
},
  "geometry": {"coordinates":[9.850082,53.326248],"type":"Point"}
}