{
  "type": "Feature",
  "properties": {
    "iso:country":"DE",
    "sg:address":"Wiesenau 53",
    "sg:city":"Frankfurt",
    "sg:phone":"+49 69/97583777",
    "sg:postcode":"60323",
    "sg:province":"Hessen",
    "wof:name":"Acatis Anlageberatung F\u00fcr",
    "wof:placetype":"venue"
},
  "geometry": {"coordinates":[8.6617145538,50.1226043701],"type":"Point"}
}