{
  "type": "Feature",
  "properties": {
    "iso:country":"DE",
    "sg:address":"Eva-Maria-Buch-Str. 26",
    "sg:city":"Leipzig",
    "sg:phone":"+49 341/9212663",
    "sg:postcode":"04349",
    "sg:province":"Sachsen",
    "wof:name":"Heinz M\u00fcller",
    "wof:placetype":"venue"
},
  "geometry": {"coordinates":[12.438908577,51.3892440796],"type":"Point"}
}