{
  "type": "Feature",
  "properties": {
    "iso:country":"DE",
    "sg:address":"Ludwigstr. 25",
    "sg:city":"Bad Reichenhall",
    "sg:phone":"+49 8651/3332",
    "sg:postcode":"83435",
    "sg:province":"Bayern",
    "wof:name":"D\u00f6rfler & Riegel Gmbh",
    "wof:placetype":"venue"
},
  "geometry": {"coordinates":[12.879275322,47.7247314453],"type":"Point"}
}