{
  "type": "Feature",
  "properties": {
    "iso:country":"DE",
    "sg:city":"Esens",
    "sg:postcode":"26427",
    "sg:province":"Niedersachsen",
    "wof:name":"Ans Team",
    "wof:placetype":"venue"
},
  "geometry": {"coordinates":[7.608827,53.644341],"type":"Point"}
}