{
  "type": "Feature",
  "properties": {
    "iso:country":"DE",
    "sg:address":"Raiffeisenstr. 6",
    "sg:city":"Konz",
    "sg:phone":"+49 6501/18270",
    "sg:postcode":"54329",
    "sg:province":"Rheinland-Pfalz",
    "wof:name":"Guido Groetzner",
    "wof:placetype":"venue"
},
  "geometry": {"coordinates":[6.5916137695,49.7014312744],"type":"Point"}
}