{
  "type": "Feature",
  "properties": {
    "iso:country":"DE",
    "sg:address":"Gustav-Adolf-Str. 13",
    "sg:city":"L\u00fctzen",
    "sg:postcode":"06686",
    "sg:province":"Sachsen-Anhalt",
    "wof:name":"Karl-adolf Linsel",
    "wof:placetype":"venue"
},
  "geometry": {"coordinates":[12.144007,51.26067],"type":"Point"}
}