{
  "type": "Feature",
  "properties": {
    "iso:country":"DE",
    "sg:address":"B\u00f6nninghardter Str. 137",
    "sg:city":"Alpen",
    "sg:phone":"+49 2802/3702",
    "sg:postcode":"46519",
    "sg:province":"Nordrhein-Westfalen",
    "wof:name":"Helmut F\u00fcrtjes",
    "wof:placetype":"venue"
},
  "geometry": {"coordinates":[6.457239151,51.5784606934],"type":"Point"}
}