{
  "type": "Feature",
  "properties": {
    "iso:country":"DE",
    "sg:address":"Rosa-Luxemburg-Str. 10",
    "sg:city":"Schipkau",
    "sg:phone":"+49 35754/9688",
    "sg:postcode":"01993",
    "sg:province":"Brandenburg",
    "wof:name":"Arno Herrmann Architekt",
    "wof:placetype":"venue"
},
  "geometry": {"coordinates":[13.902813,51.518978],"type":"Point"}
}