{
  "type": "Feature",
  "properties": {
    "iso:country":"DE",
    "sg:address":"Friedrich-Ebert-Str. 283",
    "sg:city":"Krefeld",
    "sg:phone":"+49 2151/590018",
    "sg:postcode":"47800",
    "sg:province":"Nordrhein-Westfalen",
    "wof:name":"Baudesign Reymann Gmbh",
    "wof:placetype":"venue"
},
  "geometry": {"coordinates":[6.601766,51.346165],"type":"Point"}
}