{
  "type": "Feature",
  "properties": {
    "iso:country":"DE",
    "sg:address":"Nagelbachstr. 12",
    "sg:city":"Hausham",
    "sg:phone":"+49 8026/389036",
    "sg:postcode":"83734",
    "sg:province":"Bayern",
    "wof:name":"Klaus Zehetmair Ingenieur",
    "wof:placetype":"venue"
},
  "geometry": {"coordinates":[11.821097374,47.7514228821],"type":"Point"}
}