{
  "type": "Feature",
  "properties": {
    "iso:country":"DE",
    "sg:address":"Dresdner Str 124",
    "sg:city":"Hohenstein-Ernstthal",
    "sg:phone":"+49 3723/69520",
    "sg:postcode":"09337",
    "sg:province":"Sachsen",
    "wof:name":"Gericke & Co Gmbh",
    "wof:placetype":"venue"
},
  "geometry": {"coordinates":[12.7316598892,50.8039550781],"type":"Point"}
}