{
  "type": "Feature",
  "properties": {
    "iso:country":"DE",
    "sg:address":"Markt 13",
    "sg:city":"Gro\u00dfbreitenbach",
    "sg:postcode":"98701",
    "sg:province":"Th\u00fcringen",
    "wof:name":"Zentralbibliothek",
    "wof:placetype":"venue"
},
  "geometry": {"coordinates":[11.014113,50.584801],"type":"Point"}
}