{
  "type": "Feature",
  "properties": {
    "iso:country":"DE",
    "sg:address":"Gneisenaustr. 10 - 11",
    "sg:city":"Wuerzburg",
    "sg:phone":"+49 4967/166173",
    "sg:postcode":"97074",
    "sg:province":"Bayern",
    "wof:name":"Gebr Rossmann Gmbh & Co Kg",
    "wof:placetype":"venue"
},
  "geometry": {"coordinates":[7.8802881241,49.8526077271],"type":"Point"}
}