{
  "type": "Feature",
  "properties": {
    "iso:country":"DE",
    "sg:address":"Hausen 45",
    "sg:city":"Garching",
    "sg:phone":"+49 8634/8640",
    "sg:postcode":"84518",
    "sg:province":"Bayern",
    "wof:name":"Gemeindeb\u00fccherei Mauerberg",
    "wof:placetype":"venue"
},
  "geometry": {"coordinates":[12.567525,48.126316],"type":"Point"}
}