{
  "type": "Feature",
  "properties": {
    "iso:country":"DE",
    "sg:address":"Hauptstr. 111",
    "sg:city":"Schwelm",
    "sg:phone":"+49 2336/6021",
    "sg:postcode":"58332",
    "sg:province":"Nordrhein-Westfalen",
    "wof:name":"Jentzsch & Lorenz Ohg",
    "wof:placetype":"venue"
},
  "geometry": {"coordinates":[7.2986798286,51.2861938477],"type":"Point"}
}