{
  "type": "Feature",
  "properties": {
    "iso:country":"DE",
    "sg:address":"Langnis",
    "sg:city":"Westensee",
    "sg:phone":"+49 4305/790",
    "sg:postcode":"24259",
    "sg:province":"Schleswig-Holstein",
    "wof:name":"J\u00fcrgen J\u00f6rs Seefischerei",
    "wof:placetype":"venue"
},
  "geometry": {"coordinates":[9.9277410507,54.2757110596],"type":"Point"}
}