{
  "type": "Feature",
  "properties": {
    "iso:country":"DE",
    "sg:address":"Marienh\u00f6he 14",
    "sg:city":"Hamburg",
    "sg:phone":"+49 40/861341",
    "sg:postcode":"22587",
    "sg:province":"Hamburg",
    "wof:name":"Schilmann Gmbh",
    "wof:placetype":"venue"
},
  "geometry": {"coordinates":[9.793354,53.571228],"type":"Point"}
}