{
  "type": "Feature",
  "properties": {
    "iso:country":"DE",
    "sg:address":"Biebricher Allee 114a",
    "sg:city":"Wiesbaden",
    "sg:phone":"+49 611/62047",
    "sg:postcode":"65187",
    "sg:province":"Hessen",
    "wof:name":"Sanidor Gmbh",
    "wof:placetype":"venue"
},
  "geometry": {"coordinates":[8.2437677383,50.0569419861],"type":"Point"}
}