{
  "type": "Feature",
  "properties": {
    "iso:country":"DE",
    "sg:address":"Aachener Str. 21",
    "sg:city":"Niederkr\u00fcchten",
    "sg:phone":"+49 2163/4389",
    "sg:postcode":"41372",
    "sg:province":"Nordrhein-Westfalen",
    "wof:name":"Heinrich Kebeck",
    "wof:placetype":"venue"
},
  "geometry": {"coordinates":[6.222475,51.19825],"type":"Point"}
}