{
  "type": "Feature",
  "properties": {
    "iso:country":"DE",
    "sg:address":"Frankfurter Str. 7",
    "sg:city":"Fronhausen",
    "sg:phone":"+49 6426/6136",
    "sg:postcode":"35112",
    "sg:province":"Hessen",
    "wof:name":"Konrad Pfeffer",
    "wof:placetype":"venue"
},
  "geometry": {"coordinates":[8.721068,50.703972],"type":"Point"}
}