{
  "type": "Feature",
  "properties": {
    "iso:country":"DE",
    "sg:address":"M\u00fchlenstr. 8",
    "sg:city":"Elmshorn",
    "sg:phone":"+49 4121/81588",
    "sg:postcode":"25335",
    "sg:province":"Schleswig-Holstein",
    "wof:name":"Betten-pape",
    "wof:placetype":"venue"
},
  "geometry": {"coordinates":[9.6607236862,53.7546768188],"type":"Point"}
}