{
  "type": "Feature",
  "properties": {
    "iso:country":"DE",
    "sg:address":"Oberdorfstr. 18 a",
    "sg:city":"Wesseling",
    "sg:phone":"+49 2236/48326",
    "sg:postcode":"50389",
    "sg:province":"Nordrhein-Westfalen",
    "wof:name":"Hermann Schwartmanns",
    "wof:placetype":"venue"
},
  "geometry": {"coordinates":[6.969549,50.811924],"type":"Point"}
}