{
  "type": "Feature",
  "properties": {
    "iso:country":"DE",
    "sg:address":"Konrad-Adenauer-Str. 115",
    "sg:city":"Stolberg",
    "sg:phone":"+49 2402/25142",
    "sg:postcode":"52223",
    "sg:province":"Nordrhein-Westfalen",
    "wof:name":"A. Kremer",
    "wof:placetype":"venue"
},
  "geometry": {"coordinates":[6.2161121368,50.7552680969],"type":"Point"}
}