{
  "type": "Feature",
  "properties": {
    "iso:country":"DE",
    "sg:address":"Hertelstr. 6",
    "sg:city":"Neustrelitz",
    "sg:phone":"+49 3981/277118",
    "sg:postcode":"17235",
    "sg:province":"Mecklenburg-Vorpommern",
    "wof:name":"Theaterclub",
    "wof:placetype":"venue"
},
  "geometry": {"coordinates":[13.0589447021,53.3600158691],"type":"Point"}
}