{
  "type": "Feature",
  "properties": {
    "iso:country":"DE",
    "sg:address":"Polsumer Str. 19",
    "sg:city":"Gelsenkirchen",
    "sg:phone":"+49 4920/930700",
    "sg:postcode":"45894",
    "sg:province":"Nordrhein-Westfalen",
    "wof:name":"Werbedruck Heisterkamp Gmbh",
    "wof:placetype":"venue"
},
  "geometry": {"coordinates":[7.0502781868,51.5894393921],"type":"Point"}
}