{
  "type": "Feature",
  "properties": {
    "iso:country":"DE",
    "sg:address":"Hauptstr. 17",
    "sg:city":"Altenbuch",
    "sg:phone":"+49 9392/8883",
    "sg:postcode":"97901",
    "sg:province":"Bayern",
    "wof:name":"Leo Karl",
    "wof:placetype":"venue"
},
  "geometry": {"coordinates":[9.414186,49.823338],"type":"Point"}
}