{
  "type": "Feature",
  "properties": {
    "iso:country":"DE",
    "sg:address":"Hauptstr. 31",
    "sg:city":"Sulzbach",
    "sg:phone":"+49 6196/644044",
    "sg:postcode":"65843",
    "sg:province":"Hessen",
    "wof:name":"Burda Wtg - Infrarot Design Heizstrahler",
    "wof:placetype":"venue"
},
  "geometry": {"coordinates":[8.526584,50.133911],"type":"Point"}
}