{
  "type": "Feature",
  "properties": {
    "iso:country":"DE",
    "sg:address":"Industriestr. 90",
    "sg:city":"Bammental",
    "sg:phone":"+49 6223/861032",
    "sg:postcode":"69245",
    "sg:province":"Baden-W\u00fcrttemberg",
    "wof:name":"S.o.h. Support Of Handicapped Gmbh",
    "wof:placetype":"venue"
},
  "geometry": {"coordinates":[8.78449,49.345833],"type":"Point"}
}