{
  "type": "Feature",
  "properties": {
    "iso:country":"DE",
    "sg:address":"Eisenbahnstr. 22",
    "sg:city":"Mannheim",
    "sg:phone":"+49 621/850010",
    "sg:postcode":"68199",
    "sg:province":"Baden-W\u00fcrttemberg",
    "wof:name":"Schnitzler Gmbh",
    "wof:placetype":"venue"
},
  "geometry": {"coordinates":[8.496324,49.4608],"type":"Point"}
}