{
  "type": "Feature",
  "properties": {
    "iso:country":"DE",
    "sg:address":"Heinrich-C.-Busche-Weg 3",
    "sg:city":"Neustadt",
    "sg:phone":"+49 5072/7270",
    "sg:postcode":"31535",
    "sg:province":"Niedersachsen",
    "wof:name":"M. Urban Immobilienmakler",
    "wof:placetype":"venue"
},
  "geometry": {"coordinates":[9.5736541748,52.6065559387],"type":"Point"}
}