{
  "type": "Feature",
  "properties": {
    "iso:country":"DE",
    "sg:address":"Beim Zehntstadel 2",
    "sg:city":"Ehingen",
    "sg:postcode":"89584",
    "sg:province":"Baden-W\u00fcrttemberg",
    "wof:name":"Elemente Bau Schipplock Gmbh",
    "wof:placetype":"venue"
},
  "geometry": {"coordinates":[9.722369194,48.2632141113],"type":"Point"}
}