{
  "type": "Feature",
  "properties": {
    "iso:country":"DE",
    "sg:address":"Hauptstr. 117",
    "sg:city":"Markkleeberg",
    "sg:postcode":"04416",
    "sg:province":"Sachsen",
    "wof:name":"Markkleeberger Grundst\u00fccksentwicklungsges.",
    "wof:placetype":"venue"
},
  "geometry": {"coordinates":[12.378799,51.268688],"type":"Point"}
}