{
  "type": "Feature",
  "properties": {
    "iso:country":"DE",
    "sg:address":"Hauptstr. 35",
    "sg:city":"Leutenberg",
    "sg:phone":"+49 36734/22219",
    "sg:postcode":"07338",
    "sg:province":"Th\u00fcringen",
    "wof:name":"Stadt Apotheke Inh. Andreas M\u00f6ckel E. K.",
    "wof:placetype":"venue"
},
  "geometry": {"coordinates":[11.457584,50.562866],"type":"Point"}
}