{
  "type": "Feature",
  "properties": {
    "iso:country":"DE",
    "sg:address":"Paradiesstr. 12",
    "sg:city":"W\u00fcrzburg",
    "sg:phone":"+49 931/94238",
    "sg:postcode":"97080",
    "sg:province":"Bayern",
    "wof:name":"Jordan Transport Gmbh",
    "wof:placetype":"venue"
},
  "geometry": {"coordinates":[9.883641243,49.8032341003],"type":"Point"}
}