{
  "type": "Feature",
  "properties": {
    "iso:country":"DE",
    "sg:address":"Steindamm 50",
    "sg:city":"Grabow",
    "sg:phone":"+49 38756/27849",
    "sg:postcode":"19300",
    "sg:province":"Mecklenburg-Vorpommern",
    "wof:name":"Hardi Niederges\u00e4hs",
    "wof:placetype":"venue"
},
  "geometry": {"coordinates":[11.561699,53.280052],"type":"Point"}
}