{
  "type": "Feature",
  "properties": {
    "iso:country":"DE",
    "sg:address":"Dorfgraben 9",
    "sg:city":"R\u00f6delsee",
    "sg:phone":"+49 9323/5510",
    "sg:postcode":"97348",
    "sg:province":"Bayern",
    "wof:name":"G\u00e4stehaus Sulzbacher",
    "wof:placetype":"venue"
},
  "geometry": {"coordinates":[10.2456798553,49.7288856506],"type":"Point"}
}