{
  "type": "Feature",
  "properties": {
    "iso:country":"DE",
    "sg:address":"An Der Sparkasse 1-3",
    "sg:city":"Ilmenau",
    "sg:phone":"+49 3677/660101",
    "sg:postcode":"98693",
    "sg:province":"Th\u00fcringen",
    "wof:name":"Sparkasse Arnstadt-ilmenau",
    "wof:placetype":"venue"
},
  "geometry": {"coordinates":[10.912595,50.683022],"type":"Point"}
}