{
  "type": "Feature",
  "properties": {
    "iso:country":"DE",
    "sg:address":"Am Leuchselrain 5",
    "sg:city":"Bietigheim-Bissingen",
    "sg:postcode":"74321",
    "sg:province":"Baden-W\u00fcrttemberg",
    "wof:name":"Rolf Baumann Gmbh & Co. Kg",
    "wof:placetype":"venue"
},
  "geometry": {"coordinates":[9.1101064682,48.9418945312],"type":"Point"}
}