{
  "type": "Feature",
  "properties": {
    "iso:country":"DE",
    "sg:address":"Sch\u00f6mberger Str. 7",
    "sg:city":"Rottweil",
    "sg:phone":"+49 7427/8616",
    "sg:postcode":"78628",
    "sg:province":"Baden-W\u00fcrttemberg",
    "wof:name":"J. Ohnmacht",
    "wof:placetype":"venue"
},
  "geometry": {"coordinates":[8.697892189,48.1968269348],"type":"Point"}
}