{
  "type": "Feature",
  "properties": {
    "iso:country":"DE",
    "sg:address":"Postfach 1361:: 85423 Erding:: Germany.^^Postfach 1361:: Alois-Schiessl-Platz 4::",
    "sg:city":"Erding",
    "sg:phone":"+49 8341/8080",
    "sg:postcode":"85435",
    "sg:province":"Bayern",
    "wof:name":"Kreis-und Stadtsparkasse Kaufbeuren",
    "wof:placetype":"venue"
},
  "geometry": {"coordinates":[10.62393,47.879311],"type":"Point"}
}