{
  "type": "Feature",
  "properties": {
    "iso:country":"DE",
    "sg:address":"Verdener Str.8-10",
    "sg:city":"Schneverdingen",
    "sg:phone":"+49 5193/800131",
    "sg:postcode":"29640",
    "sg:province":"Niedersachsen",
    "wof:name":"Besser Sehen Durch Training !?!",
    "wof:placetype":"venue"
},
  "geometry": {"coordinates":[9.788577,53.116756],"type":"Point"}
}