{
  "type": "Feature",
  "properties": {
    "iso:country":"DE",
    "sg:address":"Kanalstr. 25",
    "sg:city":"Wismar",
    "sg:phone":"+49 3841/283967",
    "sg:postcode":"23970",
    "sg:province":"Mecklenburg-Vorpommern",
    "wof:name":"Nordprojekt Senst Gmbh",
    "wof:placetype":"venue"
},
  "geometry": {"coordinates":[11.472057,53.889267],"type":"Point"}
}