{
  "type": "Feature",
  "properties": {
    "iso:country":"DE",
    "sg:address":"Freiherr-vom-Stein-Allee 20",
    "sg:city":"Weimar",
    "sg:phone":"+49 3643/904361",
    "sg:postcode":"99425",
    "sg:province":"Th\u00fcringen",
    "wof:name":"H. Simon",
    "wof:placetype":"venue"
},
  "geometry": {"coordinates":[11.330447,50.969402],"type":"Point"}
}