{
  "type": "Feature",
  "properties": {
    "iso:country":"DE",
    "sg:address":"Wei\u00dfenbergerstr. 4",
    "sg:city":"H\u00f6sbach",
    "sg:phone":"+49 6021/51960",
    "sg:postcode":"63768",
    "sg:province":"Bayern",
    "wof:name":"Helga Engelmann",
    "wof:placetype":"venue"
},
  "geometry": {"coordinates":[9.196219,49.99984],"type":"Point"}
}