{
  "type": "Feature",
  "properties": {
    "iso:country":"DE",
    "sg:address":"Eifflerstr. 8",
    "sg:city":"Hamburg",
    "sg:phone":"+49 40/4320090",
    "sg:postcode":"22769",
    "sg:province":"Hamburg",
    "wof:name":"Silbersee Filmproduktion Gmbh",
    "wof:placetype":"venue"
},
  "geometry": {"coordinates":[9.9573669434,53.5612220764],"type":"Point"}
}