{
  "type": "Feature",
  "properties": {
    "iso:country":"DE",
    "sg:address":"91438",
    "sg:city":"Bad Windsheim",
    "sg:phone":"+49 9841/4214",
    "sg:postcode":"91438",
    "sg:province":"Bayern",
    "wof:name":"China-restaurant Mandarin",
    "wof:placetype":"venue"
},
  "geometry": {"coordinates":[10.440779686,49.5217781067],"type":"Point"}
}