{
  "type": "Feature",
  "properties": {
    "iso:country":"DE",
    "sg:address":"Neusatzer Str. 1",
    "sg:city":"Markt Schwaben",
    "sg:phone":"+49 8121/5833",
    "sg:postcode":"85570",
    "sg:province":"Bayern",
    "wof:name":"Helmuts Reisen Gmbh Helmut Larcher",
    "wof:placetype":"venue"
},
  "geometry": {"coordinates":[11.8624610901,48.1888923645],"type":"Point"}
}