{
  "type": "Feature",
  "properties": {
    "iso:country":"DE",
    "sg:address":"Bergstr. 91",
    "sg:city":"Premnitz",
    "sg:phone":"+49 3386/244000",
    "sg:postcode":"14727",
    "sg:province":"Brandenburg",
    "wof:name":"Polyamid 2000 Handel- U. Produktionsges. Premnitz Ag",
    "wof:placetype":"venue"
},
  "geometry": {"coordinates":[12.3524103165,52.5389671326],"type":"Point"}
}