{
  "type": "Feature",
  "properties": {
    "iso:country":"DE",
    "sg:address":"Hauptstr. 65",
    "sg:city":"Mosbach",
    "sg:phone":"+49 6261/5643",
    "sg:postcode":"74821",
    "sg:province":"Baden-W\u00fcrttemberg",
    "wof:name":"Odenwald-bierbrunnen",
    "wof:placetype":"venue"
},
  "geometry": {"coordinates":[9.1471738815,49.3538589478],"type":"Point"}
}