{
  "type": "Feature",
  "properties": {
    "iso:country":"DE",
    "sg:address":"Camberleystr. 41",
    "sg:city":"Bietigheim-Bissingen",
    "sg:phone":"+49 7142/52061",
    "sg:postcode":"74321",
    "sg:province":"Baden-W\u00fcrttemberg",
    "wof:name":"Immo Bezner",
    "wof:placetype":"venue"
},
  "geometry": {"coordinates":[9.1442203522,48.9379577637],"type":"Point"}
}