{
  "type": "Feature",
  "properties": {
    "iso:country":"DE",
    "sg:address":"Neuer Wall 77",
    "sg:city":"Hamburg",
    "sg:postcode":"20354",
    "sg:province":"Hamburg",
    "wof:name":"Siebte Amerika Schiffahrts- Gesellschaft Mbh & Co. Kg",
    "wof:placetype":"venue"
},
  "geometry": {"coordinates":[9.9863014221,53.5497741699],"type":"Point"}
}