{
  "type": "Feature",
  "properties": {
    "iso:country":"DE",
    "sg:address":"Burgwaldstr. 36",
    "sg:city":"Die\u00dfen",
    "sg:phone":"+49 8807/1711",
    "sg:postcode":"86911",
    "sg:province":"Bayern",
    "wof:name":"Hermann Griesbauer Gmbh",
    "wof:placetype":"venue"
},
  "geometry": {"coordinates":[11.08757,47.938938],"type":"Point"}
}