{
  "type": "Feature",
  "properties": {
    "iso:country":"DE",
    "sg:address":"Baustr. 32",
    "sg:city":"Duisburg",
    "sg:phone":"+49 203/445268",
    "sg:postcode":"47137",
    "sg:province":"Nordrhein-Westfalen",
    "wof:name":"Hubert K\u00f6ppen Farben Und Tapeten",
    "wof:placetype":"venue"
},
  "geometry": {"coordinates":[6.7728028297,51.4707489014],"type":"Point"}
}