{
  "type": "Feature",
  "properties": {
    "iso:country":"DE",
    "sg:address":"Weidemannweg 1",
    "sg:city":"Sylt-Ost",
    "sg:phone":"+49 4651/30120",
    "sg:postcode":"25980",
    "sg:province":"Schleswig-Holstein",
    "wof:name":"M & M",
    "wof:placetype":"venue"
},
  "geometry": {"coordinates":[8.373376,54.894283],"type":"Point"}
}