{
  "type": "Feature",
  "properties": {
    "iso:country":"DE",
    "sg:address":"M\u00fchlenstr. 38",
    "sg:city":"Bexbach",
    "sg:phone":"+49 6826/2577",
    "sg:postcode":"66450",
    "sg:province":"Saarland",
    "wof:name":"Johann Kr\u00e4mer Alt- Und Abfallstoffe",
    "wof:placetype":"venue"
},
  "geometry": {"coordinates":[7.287121,49.349747],"type":"Point"}
}