{
  "type": "Feature",
  "properties": {
    "iso:country":"DE",
    "sg:address":"Industriestr. 19",
    "sg:city":"Kronach",
    "sg:phone":"+49 9261/3629",
    "sg:postcode":"96317",
    "sg:province":"Bayern",
    "wof:name":"Witwe Maria Link Druck Gmbh & Co. Kg",
    "wof:placetype":"venue"
},
  "geometry": {"coordinates":[11.3438529968,50.2317504883],"type":"Point"}
}