{
  "type": "Feature",
  "properties": {
    "iso:country":"DE",
    "sg:address":"Fliederweg 4",
    "sg:city":"Remscheid",
    "sg:phone":"+49 2191/54244",
    "sg:postcode":"42899",
    "sg:province":"Nordrhein-Westfalen",
    "wof:name":"Friedrich Klein Verkaufsb\u00fcro Remscheid",
    "wof:placetype":"venue"
},
  "geometry": {"coordinates":[7.22960186,51.2095184326],"type":"Point"}
}