{
  "type": "Feature",
  "properties": {
    "iso:country":"DE",
    "sg:address":"Dorfstr. 23",
    "sg:city":"Wardow",
    "sg:phone":"+49 38459/36752",
    "sg:postcode":"18299",
    "sg:province":"Mecklenburg-Vorpommern",
    "wof:name":"Drk-altenpflegeheim",
    "wof:placetype":"venue"
},
  "geometry": {"coordinates":[12.316874,53.960289],"type":"Point"}
}