{
  "type": "Feature",
  "properties": {
    "iso:country":"DE",
    "sg:address":"Loestr. 15",
    "sg:city":"Marl",
    "sg:phone":"+49 2365/16511",
    "sg:postcode":"45768",
    "sg:province":"Nordrhein-Westfalen",
    "wof:name":"Ribitzki",
    "wof:placetype":"venue"
},
  "geometry": {"coordinates":[7.0837612152,51.648235321],"type":"Point"}
}