{
  "type": "Feature",
  "properties": {
    "iso:country":"DE",
    "sg:address":"Allersberger Str. 71",
    "sg:city":"N\u00fcrnberg",
    "sg:phone":"+49 911/466061",
    "sg:postcode":"90461",
    "sg:province":"Bayern",
    "wof:name":"Teppich-handelshaus Inh. Mahmoud Kianmehr E. K.",
    "wof:placetype":"venue"
},
  "geometry": {"coordinates":[11.0904111862,49.4413642883],"type":"Point"}
}