{
  "type": "Feature",
  "properties": {
    "iso:country":"DE",
    "sg:address":"Pleikartsf\u00f6rster Str 4",
    "sg:city":"Heidelberg",
    "sg:phone":"+49 6221/786100",
    "sg:postcode":"69124",
    "sg:province":"Baden-W\u00fcrttemberg",
    "wof:name":"S\u00fcndermann",
    "wof:placetype":"venue"
},
  "geometry": {"coordinates":[8.6656799316,49.3777923584],"type":"Point"}
}