{
  "type": "Feature",
  "properties": {
    "iso:country":"DE",
    "sg:address":"Am Spielplatz",
    "sg:city":"Aarbergen",
    "sg:postcode":"65326",
    "sg:province":"Hessen",
    "wof:name":"Mehrzweckhalle Aarbergen-panrod",
    "wof:placetype":"venue"
},
  "geometry": {"coordinates":[8.058979,50.227856],"type":"Point"}
}