{
  "type": "Feature",
  "properties": {
    "iso:country":"DE",
    "sg:address":"Arndtstr. 5-7",
    "sg:city":"Trappenkamp",
    "sg:phone":"+49 4943/2391170",
    "sg:postcode":"24610",
    "sg:province":"Schleswig-Holstein",
    "wof:name":"Alfred Ahlers Gmbh & Co.",
    "wof:placetype":"venue"
},
  "geometry": {"coordinates":[10.2117919922,54.0421180725],"type":"Point"}
}