{
  "type": "Feature",
  "properties": {
    "iso:country":"DE",
    "sg:address":"Scheidter Str. 71",
    "sg:city":"Saarbr\u00fccken",
    "sg:phone":"+49 681/3908142",
    "sg:postcode":"66123",
    "sg:province":"Saarland",
    "wof:name":"Berthold Hahn Architekt",
    "wof:placetype":"venue"
},
  "geometry": {"coordinates":[7.015192,49.239861],"type":"Point"}
}