{
  "type": "Feature",
  "properties": {
    "iso:country":"DE",
    "sg:address":"Poppensp\u00e4lerweg 2",
    "sg:city":"Hamburg",
    "sg:phone":"+49 40/6529247",
    "sg:postcode":"22149",
    "sg:province":"Hamburg",
    "wof:name":"Klaus K\u00fchn",
    "wof:placetype":"venue"
},
  "geometry": {"coordinates":[10.1788005829,53.5936164856],"type":"Point"}
}