{
  "type": "Feature",
  "properties": {
    "iso:country":"DE",
    "sg:address":"Hauptstr. 30",
    "sg:city":"Ostbevern",
    "sg:phone":"+49 2532/90538",
    "sg:postcode":"48346",
    "sg:province":"Nordrhein-Westfalen",
    "wof:name":"Wilfried L\u00fcning",
    "wof:placetype":"venue"
},
  "geometry": {"coordinates":[7.8397650719,52.0359611511],"type":"Point"}
}