{
  "type": "Feature",
  "properties": {
    "iso:country":"DE",
    "sg:address":"Friedrichstr. 6",
    "sg:city":"Mainz-Kostheim",
    "sg:phone":"+49 6134/63102",
    "sg:postcode":"55246",
    "sg:province":"Hessen",
    "wof:name":"Roth",
    "wof:placetype":"venue"
},
  "geometry": {"coordinates":[8.3032445908,50.0007858276],"type":"Point"}
}