{
  "type": "Feature",
  "properties": {
    "iso:country":"DE",
    "sg:address":"Vielandweg 96",
    "sg:city":"Alfhausen",
    "sg:phone":"+49 5464/2333",
    "sg:postcode":"49594",
    "sg:province":"Niedersachsen",
    "wof:name":"Franz Kruse",
    "wof:placetype":"venue"
},
  "geometry": {"coordinates":[7.975718,52.517334],"type":"Point"}
}