{
  "type": "Feature",
  "properties": {
    "iso:country":"DE",
    "sg:address":"Dotzheimer Str. 80",
    "sg:city":"Wiesbaden",
    "sg:phone":"+49 611/48068",
    "sg:postcode":"65197",
    "sg:province":"Hessen",
    "wof:name":"Axel Weber Gmbh",
    "wof:placetype":"venue"
},
  "geometry": {"coordinates":[8.225268364,50.0777015686],"type":"Point"}
}