{
  "type": "Feature",
  "properties": {
    "iso:country":"DE",
    "sg:address":"Coesfelder Str. 82",
    "sg:city":"D\u00fclmen",
    "sg:phone":"+49 2594/84211",
    "sg:postcode":"48249",
    "sg:province":"Nordrhein-Westfalen",
    "wof:name":"Beljan",
    "wof:placetype":"venue"
},
  "geometry": {"coordinates":[7.273185,51.834648],"type":"Point"}
}