{
  "type": "Feature",
  "properties": {
    "iso:country":"DE",
    "sg:address":"Am Rundling 17",
    "sg:city":"Wustrow",
    "sg:phone":"+49 5843/316",
    "sg:postcode":"29462",
    "sg:province":"Niedersachsen",
    "wof:name":"Karl Schulz",
    "wof:placetype":"venue"
},
  "geometry": {"coordinates":[11.069845,52.941914],"type":"Point"}
}