{
  "type": "Feature",
  "properties": {
    "iso:country":"DE",
    "sg:address":"Am Seeblick 5",
    "sg:city":"Glindow",
    "sg:postcode":"14542",
    "sg:province":"Brandenburg",
    "wof:name":"Hansa- Bau Gmbh",
    "wof:placetype":"venue"
},
  "geometry": {"coordinates":[12.892133,52.373848],"type":"Point"}
}