{
  "type": "Feature",
  "properties": {
    "iso:country":"DE",
    "sg:address":"Dahlienhof 3",
    "sg:city":"Rellingen",
    "sg:phone":"+49 4101/514280",
    "sg:postcode":"25462",
    "sg:province":"Schleswig-Holstein",
    "wof:name":"List & Meier",
    "wof:placetype":"venue"
},
  "geometry": {"coordinates":[9.826002121,53.6550674438],"type":"Point"}
}