{
  "type": "Feature",
  "properties": {
    "iso:country":"DE",
    "sg:address":"Bernhardtrg. 7",
    "sg:city":"Bremen",
    "sg:phone":"+49 4942/1682966",
    "sg:postcode":"28777",
    "sg:province":"Bremen",
    "wof:name":"Weingarten Maschinenbau Gmbh",
    "wof:placetype":"venue"
},
  "geometry": {"coordinates":[8.512537,53.204144],"type":"Point"}
}