{
  "type": "Feature",
  "properties": {
    "iso:country":"DE",
    "sg:address":"Lange Str. 6",
    "sg:city":"Westerstede",
    "sg:phone":"+49 4488/2309",
    "sg:postcode":"26655",
    "sg:province":"Niedersachsen",
    "wof:name":"J. B\u00fccking Kg Eisenwaren",
    "wof:placetype":"venue"
},
  "geometry": {"coordinates":[7.9258480072,53.2571983337],"type":"Point"}
}