{
  "type": "Feature",
  "properties": {
    "iso:country":"DE",
    "sg:address":"Dornbusch 45",
    "sg:city":"Vechta",
    "sg:phone":"+49 4441/81331",
    "sg:postcode":"49377",
    "sg:province":"Niedersachsen",
    "wof:name":"Hallenwellen- Und Freibad",
    "wof:placetype":"venue"
},
  "geometry": {"coordinates":[8.2968082428,52.7397689819],"type":"Point"}
}