{
  "type": "Feature",
  "properties": {
    "iso:country":"DE",
    "sg:address":"Ratinger Str. 24",
    "sg:city":"D\u00fcsseldorf",
    "sg:phone":"+49 211/323204",
    "sg:postcode":"40213",
    "sg:province":"Nordrhein-Westfalen",
    "wof:name":"Phils Store",
    "wof:placetype":"venue"
},
  "geometry": {"coordinates":[6.774981,51.229565],"type":"Point"}
}