{
  "type": "Feature",
  "properties": {
    "iso:country":"DE",
    "sg:address":"Preinstr. 55 a",
    "sg:city":"Dortmund",
    "sg:phone":"+49 231/468684",
    "sg:postcode":"44265",
    "sg:province":"Nordrhein-Westfalen",
    "wof:name":"K. Mohr",
    "wof:placetype":"venue"
},
  "geometry": {"coordinates":[7.490629,51.470924],"type":"Point"}
}