{
  "type": "Feature",
  "properties": {
    "iso:country":"DE",
    "sg:address":"Weserstr. 7",
    "sg:city":"Rinteln",
    "sg:phone":"+49 5751/2745",
    "sg:postcode":"31737",
    "sg:province":"Niedersachsen",
    "wof:name":"Pelz-klaus Inh. Anneliese Klaus",
    "wof:placetype":"venue"
},
  "geometry": {"coordinates":[9.080454,52.188614],"type":"Point"}
}