{
  "type": "Feature",
  "properties": {
    "iso:country":"DE",
    "sg:address":"Hirschbergstr. 21",
    "sg:city":"M\u00fcnchen",
    "sg:phone":"+49 89/16783303",
    "sg:postcode":"80634",
    "sg:province":"Bayern",
    "wof:name":"Karen Nemela",
    "wof:placetype":"venue"
},
  "geometry": {"coordinates":[11.5321235657,48.1483268738],"type":"Point"}
}