{
  "type": "Feature",
  "properties": {
    "iso:country":"DE",
    "sg:address":"Gartenstr. 9",
    "sg:city":"Elchingen",
    "sg:phone":"+49 731/263550",
    "sg:postcode":"89275",
    "sg:province":"Bayern",
    "wof:name":"Griss Tonstudio",
    "wof:placetype":"venue"
},
  "geometry": {"coordinates":[10.0516653061,48.4353752136],"type":"Point"}
}