{
  "type": "Feature",
  "properties": {
    "iso:country":"DE",
    "sg:address":"Pittenharter Str. 6",
    "sg:city":"Pittenhart",
    "sg:phone":"+49 8624/829945",
    "sg:postcode":"83132",
    "sg:province":"Bayern",
    "wof:name":"Anne Sigmund-illi Heilpraktiker",
    "wof:placetype":"venue"
},
  "geometry": {"coordinates":[12.4163856506,47.9651756287],"type":"Point"}
}