{
  "type": "Feature",
  "properties": {
    "iso:country":"DE",
    "sg:address":"Traminer Str. 5",
    "sg:city":"M\u00fcnchen",
    "sg:phone":"+49 89/644980",
    "sg:postcode":"81547",
    "sg:province":"Bayern",
    "wof:name":"G. Bender Immobilienmakler",
    "wof:placetype":"venue"
},
  "geometry": {"coordinates":[11.5704145432,48.0997543335],"type":"Point"}
}