{
  "type": "Feature",
  "properties": {
    "iso:country":"DE",
    "sg:address":"Carl-Orff-Str. 37",
    "sg:city":"Freising",
    "sg:phone":"+49 8161/85481",
    "sg:postcode":"85356",
    "sg:province":"Bayern",
    "wof:name":"Sch\u00e4dler Gmbh",
    "wof:placetype":"venue"
},
  "geometry": {"coordinates":[11.752407074,48.3843460083],"type":"Point"}
}