{
  "type": "Feature",
  "properties": {
    "iso:country":"DE",
    "sg:address":"Franz-Lenders-Str. 63",
    "sg:city":"Frechen",
    "sg:phone":"+49 2234/63110",
    "sg:postcode":"50226",
    "sg:province":"Nordrhein-Westfalen",
    "wof:name":"Telef\u00f6nchen",
    "wof:placetype":"venue"
},
  "geometry": {"coordinates":[6.7628397942,50.9430541992],"type":"Point"}
}