{
  "type": "Feature",
  "properties": {
    "iso:country":"DE",
    "sg:address":"Altenbergerstr. 212",
    "sg:city":"Steinfurt",
    "sg:phone":"+49 2552",
    "sg:postcode":"48565",
    "sg:province":"Nordrhein-Westfalen",
    "wof:name":"Bmw Autohaus Cyran Gmbh - Steinfurt",
    "wof:placetype":"venue"
},
  "geometry": {"coordinates":[7.4095702171,52.1002807617],"type":"Point"}
}