{
  "type": "Feature",
  "properties": {
    "iso:country":"DE",
    "sg:address":"Welserstr. 7",
    "sg:city":"Neuss",
    "sg:phone":"+49 2131/35799",
    "sg:postcode":"41468",
    "sg:province":"Nordrhein-Westfalen",
    "wof:name":"Max Mothes Gmbh & Co. Kg",
    "wof:placetype":"venue"
},
  "geometry": {"coordinates":[6.7770180702,51.1556472778],"type":"Point"}
}