{
  "type": "Feature",
  "properties": {
    "iso:country":"DE",
    "sg:address":"Romerstr. 5",
    "sg:city":"Coswig",
    "sg:postcode":"01640",
    "sg:province":"Sachsen",
    "wof:name":"Immobiliengesellschaft Fischhausstr. Gmbh & Co.",
    "wof:placetype":"venue"
},
  "geometry": {"coordinates":[13.570943,51.126053],"type":"Point"}
}