{
  "type": "Feature",
  "properties": {
    "iso:country":"DE",
    "sg:address":"Nordener Str. 26",
    "sg:city":"Westerholt",
    "sg:phone":"+49 4975/1661",
    "sg:postcode":"26556",
    "sg:province":"Niedersachsen",
    "wof:name":"Walter Frerichs",
    "wof:placetype":"venue"
},
  "geometry": {"coordinates":[7.4485321045,53.5893516541],"type":"Point"}
}