{
  "type": "Feature",
  "properties": {
    "iso:country":"DE",
    "sg:address":"Forstweg 21",
    "sg:city":"Wei\u00dfenborn",
    "sg:phone":"+49 3731/204329",
    "sg:postcode":"09600",
    "sg:province":"Sachsen",
    "wof:name":"Tischlerei H. Gregor",
    "wof:placetype":"venue"
},
  "geometry": {"coordinates":[13.401673,50.877525],"type":"Point"}
}