{
  "type": "Feature",
  "properties": {
    "iso:country":"DE",
    "sg:address":"Kirchstr. 15",
    "sg:city":"Norderney",
    "sg:phone":"+49 4932/1030",
    "sg:postcode":"26548",
    "sg:province":"Niedersachsen",
    "wof:name":"August Kreyenk\u00f6tter",
    "wof:placetype":"venue"
},
  "geometry": {"coordinates":[7.143488,53.706036],"type":"Point"}
}