{
  "type": "Feature",
  "properties": {
    "iso:country":"DE",
    "sg:address":"Kardinal-Hengsbach-Str. 2-4",
    "sg:city":"Bottrop",
    "sg:phone":"+49 2041/180232",
    "sg:postcode":"46236",
    "sg:province":"Nordrhein-Westfalen",
    "wof:name":"Geonet Ges. F. Geogr.-techn. Informa-",
    "wof:placetype":"venue"
},
  "geometry": {"coordinates":[6.933054924,51.5326690674],"type":"Point"}
}