{
  "type": "Feature",
  "properties": {
    "iso:country":"DE",
    "sg:address":"Havixbecker Str. 34",
    "sg:city":"M\u00fcnster",
    "sg:phone":"+49 2534/2781",
    "sg:postcode":"48161",
    "sg:province":"Nordrhein-Westfalen",
    "wof:name":"Zoo Br\u00fcner",
    "wof:placetype":"venue"
},
  "geometry": {"coordinates":[7.532376,51.956596],"type":"Point"}
}