{
  "type": "Feature",
  "properties": {
    "iso:country":"DE",
    "sg:address":"Vogelsang 44",
    "sg:city":"Euskirchen",
    "sg:phone":"+49 2255/4918",
    "sg:postcode":"53881",
    "sg:province":"Nordrhein-Westfalen",
    "wof:name":"D. Fettweis",
    "wof:placetype":"venue"
},
  "geometry": {"coordinates":[6.8291277885,50.6042442322],"type":"Point"}
}