{
  "type": "Feature",
  "properties": {
    "iso:country":"DE",
    "sg:address":"Coburger Str. 23",
    "sg:city":"Grub",
    "sg:phone":"+49 9560/92200",
    "sg:postcode":"96271",
    "sg:province":"Bayern",
    "wof:name":"Gemeindeb\u00fccherei Rathaus",
    "wof:placetype":"venue"
},
  "geometry": {"coordinates":[11.022761,50.227493],"type":"Point"}
}