{
  "type": "Feature",
  "properties": {
    "iso:country":"DE",
    "sg:address":"Kreuzholz 5",
    "sg:city":"Melle",
    "sg:phone":"+49 5226/801",
    "sg:postcode":"49328",
    "sg:province":"Niedersachsen",
    "wof:name":"Ingenieurb\u00fcro Bahr Gmbh",
    "wof:placetype":"venue"
},
  "geometry": {"coordinates":[8.4187364578,52.1774368286],"type":"Point"}
}