{
  "type": "Feature",
  "properties": {
    "iso:country":"DE",
    "sg:address":"Steindamm 36a",
    "sg:city":"Bremen",
    "sg:phone":"+49 421/630538",
    "sg:postcode":"28719",
    "sg:province":"Bremen",
    "wof:name":"Gl\u00fcckauf-bau Gmbh",
    "wof:placetype":"venue"
},
  "geometry": {"coordinates":[8.707241,53.161407],"type":"Point"}
}