{
  "type": "Feature",
  "properties": {
    "iso:country":"DE",
    "sg:address":"Irlm\u00fchle 2",
    "sg:city":"Ruderting",
    "sg:phone":"+49 8509/2332",
    "sg:postcode":"94161",
    "sg:province":"Bayern",
    "wof:name":"H. Meusel Jun.",
    "wof:placetype":"venue"
},
  "geometry": {"coordinates":[13.4208440781,48.663230896],"type":"Point"}
}