{
  "type": "Feature",
  "properties": {
    "iso:country":"DE",
    "sg:address":"Rockwinkeler Landstr. 113",
    "sg:city":"Bremen",
    "sg:phone":"+49 421/423287",
    "sg:postcode":"28325",
    "sg:province":"Bremen",
    "wof:name":"Peter D\u00f6hle",
    "wof:placetype":"venue"
},
  "geometry": {"coordinates":[8.939825,53.077209],"type":"Point"}
}