{
  "type": "Feature",
  "properties": {
    "iso:country":"DE",
    "sg:address":"Schlagbaum 2",
    "sg:city":"Ennepetal",
    "sg:phone":"+49 171 5714141",
    "sg:postcode":"58256",
    "sg:province":"Nordrhein-Westfalen",
    "wof:name":"Bernhard Heuer",
    "wof:placetype":"venue"
},
  "geometry": {"coordinates":[7.351084,51.247643],"type":"Point"}
}