{
  "type": "Feature",
  "properties": {
    "iso:country":"DE",
    "sg:address":"Am Grenzschlachthof 1-3",
    "sg:city":"Rostock",
    "sg:phone":"+49 381/801810",
    "sg:postcode":"18069",
    "sg:province":"Mecklenburg-Vorpommern",
    "wof:name":"Ws-technik Rostocker Anlagenbau Gmbh",
    "wof:placetype":"venue"
},
  "geometry": {"coordinates":[12.09126,54.106068],"type":"Point"}
}