{
  "type": "Feature",
  "properties": {
    "iso:country":"DE",
    "sg:address":"Hussenstr. 19",
    "sg:city":"Konstanz",
    "sg:phone":"+49 7531/23097",
    "sg:postcode":"78462",
    "sg:province":"Baden-W\u00fcrttemberg",
    "wof:name":"Wilfried Heger Rechtsanw\u00e4lte",
    "wof:placetype":"venue"
},
  "geometry": {"coordinates":[9.1726016998,47.6599197388],"type":"Point"}
}