{
  "type": "Feature",
  "properties": {
    "iso:country":"DE",
    "sg:address":"Neckarstr. 64",
    "sg:city":"K\u00f6ln",
    "sg:phone":"+49 2203/181941",
    "sg:postcode":"51149",
    "sg:province":"Nordrhein-Westfalen",
    "wof:name":"Bauunternehmung Kohl Gmbh",
    "wof:placetype":"venue"
},
  "geometry": {"coordinates":[7.0180702209,50.8977203369],"type":"Point"}
}