{
  "type": "Feature",
  "properties": {
    "iso:country":"DE",
    "sg:address":"Im Rusch 1",
    "sg:city":"Vollersode",
    "sg:postcode":"27729",
    "sg:province":"Niedersachsen",
    "wof:name":"H\u00fcwo Verwaltungs- Gmbh & Co. Kg",
    "wof:placetype":"venue"
},
  "geometry": {"coordinates":[8.918609,53.307983],"type":"Point"}
}