{
  "type": "Feature",
  "properties": {
    "iso:country":"DE",
    "sg:address":"Schustergasse 18",
    "sg:city":"Darmstadt",
    "sg:phone":"+49 6151/24012",
    "sg:postcode":"64283",
    "sg:province":"Hessen",
    "wof:name":"Blum-bauscher",
    "wof:placetype":"venue"
},
  "geometry": {"coordinates":[8.6566991806,49.8726921082],"type":"Point"}
}