{
  "type": "Feature",
  "properties": {
    "iso:country":"DE",
    "sg:address":"Schmiedeweg 8",
    "sg:city":"Kirchhundem",
    "sg:phone":"+49 2723/3675",
    "sg:postcode":"57399",
    "sg:province":"Nordrhein-Westfalen",
    "wof:name":"Klaus F\u00fchrt Gmbh",
    "wof:placetype":"venue"
},
  "geometry": {"coordinates":[8.123098,51.085533],"type":"Point"}
}