{
  "type": "Feature",
  "properties": {
    "iso:country":"DE",
    "sg:address":"Ringstr. 40",
    "sg:city":"Walsdorf",
    "sg:phone":"+49 6593/8810",
    "sg:postcode":"54578",
    "sg:province":"Rheinland-Pfalz",
    "wof:name":"Van Nerven Bedachungs Gmbh",
    "wof:placetype":"venue"
},
  "geometry": {"coordinates":[6.706013,50.281399],"type":"Point"}
}