{
  "type": "Feature",
  "properties": {
    "iso:country":"DE",
    "sg:address":"Am Bredenmoor 3",
    "sg:city":"Bremerhaven",
    "sg:phone":"+49 471/88005",
    "sg:postcode":"27578",
    "sg:province":"Bremen",
    "wof:name":"Mahrenholz Bremerhaven Gmbh & Co. Kg",
    "wof:placetype":"venue"
},
  "geometry": {"coordinates":[8.60615,53.58503],"type":"Point"}
}