{
  "type": "Feature",
  "properties": {
    "iso:country":"DE",
    "sg:address":"Salvador-Allende-Str. 17",
    "sg:city":"Magdeburg",
    "sg:phone":"+49 391/2531889",
    "sg:postcode":"39126",
    "sg:province":"Sachsen-Anhalt",
    "wof:name":"Prof. Dr. Horst-dieter Tietz",
    "wof:placetype":"venue"
},
  "geometry": {"coordinates":[11.6398668289,52.1707649231],"type":"Point"}
}