{
  "type": "Feature",
  "properties": {
    "iso:country":"DE",
    "sg:address":"Ritterstr. 8",
    "sg:city":"Senftenberg",
    "sg:postcode":"01968",
    "sg:province":"Brandenburg",
    "wof:name":"Evelin Reimers",
    "wof:placetype":"venue"
},
  "geometry": {"coordinates":[14.003808,51.517948],"type":"Point"}
}