{
  "type": "Feature",
  "properties": {
    "iso:country":"DE",
    "sg:address":"Heltweg 4",
    "sg:city":"Reken",
    "sg:phone":"+49 2864/6283",
    "sg:postcode":"48734",
    "sg:province":"Nordrhein-Westfalen",
    "wof:name":"Balmoral",
    "wof:placetype":"venue"
},
  "geometry": {"coordinates":[7.033823967,51.8525085449],"type":"Point"}
}