{
  "type": "Feature",
  "properties": {
    "iso:country":"DE",
    "sg:address":"Kraienbruch 67",
    "sg:city":"Essen",
    "sg:phone":"+49 201/669607",
    "sg:postcode":"45357",
    "sg:province":"Nordrhein-Westfalen",
    "wof:name":"Balkan-grill",
    "wof:placetype":"venue"
},
  "geometry": {"coordinates":[6.9398961067,51.4911384583],"type":"Point"}
}