{
  "type": "Feature",
  "properties": {
    "iso:country":"DE",
    "sg:address":"Marschenblick 6",
    "sg:city":"Hattstedt",
    "sg:phone":"+49 4846/1586",
    "sg:postcode":"25856",
    "sg:province":"Schleswig-Holstein",
    "wof:name":"Klaus Lorenzen",
    "wof:placetype":"venue"
},
  "geometry": {"coordinates":[9.0277233124,54.527469635],"type":"Point"}
}