{
  "type": "Feature",
  "properties": {
    "iso:country":"DE",
    "sg:address":"Schauflinger Str. 6",
    "sg:city":"Deggendorf",
    "sg:phone":"+49 991/290390",
    "sg:postcode":"94469",
    "sg:province":"Bayern",
    "wof:name":"Akustikbau Wimmer Gmbh",
    "wof:placetype":"venue"
},
  "geometry": {"coordinates":[12.963659,48.851662],"type":"Point"}
}