{
  "type": "Feature",
  "properties": {
    "iso:country":"DE",
    "sg:address":"Freiherr-vom-Stein-Ring 29",
    "sg:city":"Hochheim",
    "sg:phone":"+49 6146/835555",
    "sg:postcode":"65239",
    "sg:province":"Hessen",
    "wof:name":"Ursula Schmidt-thiele Steuerberaterin",
    "wof:placetype":"venue"
},
  "geometry": {"coordinates":[8.3611373901,50.012386322],"type":"Point"}
}