{
  "type": "Feature",
  "properties": {
    "iso:country":"DE",
    "sg:address":"Lauberstr. 3",
    "sg:city":"Kaufbeuren",
    "sg:phone":"+49 8341/16531",
    "sg:postcode":"87600",
    "sg:province":"Bayern",
    "wof:name":"Kpr-tankschutz Gmbh",
    "wof:placetype":"venue"
},
  "geometry": {"coordinates":[10.626623,47.887695],"type":"Point"}
}