{
  "type": "Feature",
  "properties": {
    "iso:country":"DE",
    "sg:address":"Parkstr. 73",
    "sg:city":"Bremen",
    "sg:phone":"+49 421/349065",
    "sg:postcode":"28209",
    "sg:province":"Bremen",
    "wof:name":"Born & Born Concertagentur Gmbh",
    "wof:placetype":"venue"
},
  "geometry": {"coordinates":[8.8249464035,53.0829582214],"type":"Point"}
}