{
  "type": "Feature",
  "properties": {
    "iso:country":"DE",
    "sg:address":"Kapellenstr. 126",
    "sg:city":"Oberhausen",
    "sg:phone":"+49 208/607693",
    "sg:postcode":"46119",
    "sg:province":"Nordrhein-Westfalen",
    "wof:name":"Ev. Pfarramt Ii Auferstehungskirche Osterfeld",
    "wof:placetype":"venue"
},
  "geometry": {"coordinates":[6.8811979294,51.5169563293],"type":"Point"}
}