{
  "type": "Feature",
  "properties": {
    "iso:country":"DE",
    "sg:address":"St.-Magnus-Str. 56",
    "sg:city":"Bremen",
    "sg:phone":"+49 421/3966078",
    "sg:postcode":"28217",
    "sg:province":"Bremen",
    "wof:name":"B. Chairsell",
    "wof:placetype":"venue"
},
  "geometry": {"coordinates":[8.7887306213,53.0942306519],"type":"Point"}
}