{
  "type": "Feature",
  "properties": {
    "iso:country":"DE",
    "sg:address":"Hellweg 14",
    "sg:city":"Bocholt",
    "sg:phone":"+49 2874/3215",
    "sg:postcode":"46399",
    "sg:province":"Nordrhein-Westfalen",
    "wof:name":"S. Liebrand",
    "wof:placetype":"venue"
},
  "geometry": {"coordinates":[6.496952,51.860981],"type":"Point"}
}