{
  "type": "Feature",
  "properties": {
    "iso:country":"DE",
    "sg:address":"Scheffelstr. 2",
    "sg:city":"Berlin",
    "sg:phone":"+49 30/5509144",
    "sg:postcode":"10367",
    "sg:province":"Berlin",
    "wof:name":"Matthias Martius",
    "wof:placetype":"venue"
},
  "geometry": {"coordinates":[13.4788398743,52.520526886],"type":"Point"}
}