{
  "type": "Feature",
  "properties": {
    "iso:country":"DE",
    "sg:address":"Kapellenstr. 3",
    "sg:city":"Konz",
    "sg:phone":"+49 6501/14042",
    "sg:postcode":"54329",
    "sg:province":"Rheinland-Pfalz",
    "wof:name":"Heinz Schmitt",
    "wof:placetype":"venue"
},
  "geometry": {"coordinates":[6.6277418137,49.6945419312],"type":"Point"}
}