{
  "type": "Feature",
  "properties": {
    "iso:country":"DE",
    "sg:address":"Lilienthalstrasse 4",
    "sg:city":"Regensburg",
    "sg:phone":"+49 941/3782150",
    "sg:postcode":"93051",
    "sg:province":"Bayern",
    "wof:name":"Zoo-markt-online",
    "wof:placetype":"venue"
},
  "geometry": {"coordinates":[12.059766,49.01136],"type":"Point"}
}