{
  "type": "Feature",
  "properties": {
    "iso:country":"DE",
    "sg:address":"Wackerstr. 52",
    "sg:city":"Burghausen",
    "sg:phone":"+49 8677/3562",
    "sg:postcode":"84489",
    "sg:province":"Bayern",
    "wof:name":"Mecki-club Burghausen 1975 Helmut Bittner",
    "wof:placetype":"venue"
},
  "geometry": {"coordinates":[12.8367300034,48.1705818176],"type":"Point"}
}