{
  "type": "Feature",
  "properties": {
    "iso:country":"DE",
    "sg:address":"Burgstr. 18",
    "sg:city":"Leinfelden-Echterdingen",
    "sg:phone":"+49 711/792446",
    "sg:postcode":"70771",
    "sg:province":"Baden-W\u00fcrttemberg",
    "wof:name":"Helmut Bayha",
    "wof:placetype":"venue"
},
  "geometry": {"coordinates":[9.169958,48.690304],"type":"Point"}
}