{
  "type": "Feature",
  "properties": {
    "iso:country":"DE",
    "sg:address":"Kapuzinerstr. 7",
    "sg:city":"Mainz",
    "sg:phone":"+49 6131/228838",
    "sg:postcode":"55116",
    "sg:province":"Rheinland-Pfalz",
    "wof:name":"Karl-ludwig Sch\u00e4fer",
    "wof:placetype":"venue"
},
  "geometry": {"coordinates":[8.279304,49.995102],"type":"Point"}
}