{
  "type": "Feature",
  "properties": {
    "iso:country":"DE",
    "sg:address":"Hasenpfad 2",
    "sg:city":"Kamen",
    "sg:postcode":"59174",
    "sg:province":"Nordrhein-Westfalen",
    "wof:name":"Doka Immobilien Gmbh",
    "wof:placetype":"venue"
},
  "geometry": {"coordinates":[7.6187739372,51.5624160767],"type":"Point"}
}