{
  "type": "Feature",
  "properties": {
    "iso:country":"DE",
    "sg:address":"Stavenort 18",
    "sg:city":"Buxtehude",
    "sg:phone":"+49 4161/51110",
    "sg:postcode":"21614",
    "sg:province":"Niedersachsen",
    "wof:name":"K. V. V. Kern Verm\u00f6gens- Verwaltungs Gmbh & Co. Kg",
    "wof:placetype":"venue"
},
  "geometry": {"coordinates":[9.7024679184,53.4766273499],"type":"Point"}
}