{
  "type": "Feature",
  "properties": {
    "iso:country":"DE",
    "sg:address":"Schillerstr. 29",
    "sg:city":"Hamburg",
    "sg:phone":"+49 40/3806189",
    "sg:postcode":"22767",
    "sg:province":"Hamburg",
    "wof:name":"Heiko R\u00f6bken Masseur",
    "wof:placetype":"venue"
},
  "geometry": {"coordinates":[9.937802,53.549797],"type":"Point"}
}