{
  "type": "Feature",
  "properties": {
    "iso:country":"DE",
    "sg:address":"Seidenbenderstr. 72a",
    "sg:city":"Worms",
    "sg:phone":"+49 6241/51064",
    "sg:postcode":"67549",
    "sg:province":"Rheinland-Pfalz",
    "wof:name":"Dsk-seniorenwohnungen E. V.",
    "wof:placetype":"venue"
},
  "geometry": {"coordinates":[8.353787,49.637684],"type":"Point"}
}