{
  "type": "Feature",
  "properties": {
    "iso:country":"DE",
    "sg:address":"Volkmannsgr\u00fcn",
    "sg:city":"Schauenstein",
    "sg:phone":"+49 9252/441",
    "sg:postcode":"95197",
    "sg:province":"Bayern",
    "wof:name":"W. Und Ch. Stark",
    "wof:placetype":"venue"
},
  "geometry": {"coordinates":[11.7423000336,50.2636985779],"type":"Point"}
}