{
  "type": "Feature",
  "properties": {
    "iso:country":"DE",
    "sg:address":"Pfarrhof 1 a",
    "sg:city":"Tacherting",
    "sg:phone":"+49 8622/437",
    "sg:postcode":"83342",
    "sg:province":"Bayern",
    "wof:name":"P. Fuchs Bildhauer",
    "wof:placetype":"venue"
},
  "geometry": {"coordinates":[12.4753904343,48.0886154175],"type":"Point"}
}