{
  "type": "Feature",
  "properties": {
    "iso:country":"DE",
    "sg:address":"Hauptstr. 109",
    "sg:city":"Sulzbach",
    "sg:phone":"+49 6196/26939",
    "sg:postcode":"65843",
    "sg:province":"Hessen",
    "wof:name":"Manfred Gerischer",
    "wof:placetype":"venue"
},
  "geometry": {"coordinates":[8.51631,50.138393],"type":"Point"}
}