{
  "type": "Feature",
  "properties": {
    "iso:country":"DE",
    "sg:address":"Borsigstr. 2",
    "sg:city":"Reinbek",
    "sg:postcode":"21465",
    "sg:province":"Schleswig-Holstein",
    "wof:name":"L\u00fcth Von Oppel Und Wuppermann Gmbh",
    "wof:placetype":"venue"
},
  "geometry": {"coordinates":[10.235994339,53.5239677429],"type":"Point"}
}