{
  "type": "Feature",
  "properties": {
    "iso:country":"DE",
    "sg:address":"Kastanienallee 36",
    "sg:city":"Strausberg",
    "sg:phone":"+49 3341/33230",
    "sg:postcode":"15344",
    "sg:province":"Brandenburg",
    "wof:name":"Raab Karcher Baustoffe",
    "wof:placetype":"venue"
},
  "geometry": {"coordinates":[13.895475,52.583336],"type":"Point"}
}