{
  "type": "Feature",
  "properties": {
    "iso:country":"DE",
    "sg:address":"Hauptstr. 25",
    "sg:city":"Langeoog",
    "sg:phone":"+49 4972/221",
    "sg:postcode":"26465",
    "sg:province":"Niedersachsen",
    "wof:name":"Inselb\u00e4ckerei Hans-helmut Wilken Gmbh",
    "wof:placetype":"venue"
},
  "geometry": {"coordinates":[7.479967,53.746761],"type":"Point"}
}