{
  "type": "Feature",
  "properties": {
    "iso:country":"DE",
    "sg:address":"Schlo\u00dfstr. 82",
    "sg:city":"Frankfurt",
    "sg:postcode":"60486",
    "sg:province":"Hessen",
    "wof:name":"G\u00fcnter Martin Gmbh",
    "wof:placetype":"venue"
},
  "geometry": {"coordinates":[8.6438989639,50.1186752319],"type":"Point"}
}