{
  "type": "Feature",
  "properties": {
    "iso:country":"DE",
    "sg:address":"Laventiestr. 17",
    "sg:city":"Iserlohn",
    "sg:phone":"+49 2371/460800",
    "sg:postcode":"58640",
    "sg:province":"Nordrhein-Westfalen",
    "wof:name":"Wigmann",
    "wof:placetype":"venue"
},
  "geometry": {"coordinates":[7.711223,51.418251],"type":"Point"}
}