{
  "type": "Feature",
  "properties": {
    "iso:country":"DE",
    "sg:address":"Wilhelmstr. 61",
    "sg:city":"Euskirchen",
    "sg:phone":"+49 2251/75003",
    "sg:postcode":"53879",
    "sg:province":"Nordrhein-Westfalen",
    "wof:name":"Hermann Sch\u00fcrmann Elektro-sparkauf Gmbh",
    "wof:placetype":"venue"
},
  "geometry": {"coordinates":[6.7883849144,50.6582183838],"type":"Point"}
}