{
  "type": "Feature",
  "properties": {
    "iso:country":"DE",
    "sg:address":"Schwarzenburgstr. 35",
    "sg:city":"Friesenried",
    "sg:phone":"+49 8347/1066",
    "sg:postcode":"87654",
    "sg:province":"Bayern",
    "wof:name":"Wolfgang Schmidle",
    "wof:placetype":"venue"
},
  "geometry": {"coordinates":[10.5098361969,47.8842468262],"type":"Point"}
}