{
  "type": "Feature",
  "properties": {
    "iso:country":"DE",
    "sg:address":"Herrenstr. 15",
    "sg:city":"Forchheim",
    "sg:phone":"+49 7642/40165",
    "sg:postcode":"79362",
    "sg:province":"Baden-W\u00fcrttemberg",
    "wof:name":"Raiffeisen Zentralgenossenschaft Eg",
    "wof:placetype":"venue"
},
  "geometry": {"coordinates":[7.702821,48.163113],"type":"Point"}
}