{
  "type": "Feature",
  "properties": {
    "iso:country":"DE",
    "sg:address":"B\u00fchlertalstr. 26",
    "sg:city":"B\u00fchl",
    "sg:phone":"+49 7223/1528",
    "sg:postcode":"77815",
    "sg:province":"Baden-W\u00fcrttemberg",
    "wof:name":"Eberhard Els\u00e4sser",
    "wof:placetype":"venue"
},
  "geometry": {"coordinates":[8.13834,48.69405],"type":"Point"}
}