{
  "type": "Feature",
  "properties": {
    "iso:country":"DE",
    "sg:address":"K\u00f6ppelsdorfer Str. 82",
    "sg:city":"Sonneberg",
    "sg:phone":"+49 3675/702969",
    "sg:postcode":"96515",
    "sg:province":"Th\u00fcringen",
    "wof:name":"Hermann Papp",
    "wof:placetype":"venue"
},
  "geometry": {"coordinates":[11.179494,50.35611],"type":"Point"}
}