{
  "type": "Feature",
  "properties": {
    "iso:country":"DE",
    "sg:address":"Jahnallee 47",
    "sg:city":"Leipzig",
    "sg:phone":"+49 341/9805432",
    "sg:postcode":"04109",
    "sg:province":"Sachsen",
    "wof:name":"Teestube Inh. Brunhilde Langer",
    "wof:placetype":"venue"
},
  "geometry": {"coordinates":[12.36079216,51.3421478271],"type":"Point"}
}