{
  "type": "Feature",
  "properties": {
    "iso:country":"DE",
    "sg:address":"Oberfeldstr. 5",
    "sg:city":"Porta Westfalica",
    "sg:phone":"+49 5731/76790",
    "sg:postcode":"32457",
    "sg:province":"Nordrhein-Westfalen",
    "wof:name":"Wiese Foto & Film Gmbh & Co. Kg",
    "wof:placetype":"venue"
},
  "geometry": {"coordinates":[8.8808050156,52.2026252747],"type":"Point"}
}