{
  "type": "Feature",
  "properties": {
    "iso:country":"DE",
    "sg:address":"Obere Haardtstr. 16",
    "sg:city":"Eppenbrunn",
    "sg:phone":"+49 6335/1354",
    "sg:postcode":"66957",
    "sg:province":"Rheinland-Pfalz",
    "wof:name":"Franz Frietsch",
    "wof:placetype":"venue"
},
  "geometry": {"coordinates":[7.562102,49.115784],"type":"Point"}
}