{
  "type": "Feature",
  "properties": {
    "iso:country":"DE",
    "sg:address":"Mahdentalstr. 112",
    "sg:city":"Sindelfingen",
    "sg:phone":"+49 7031/811519",
    "sg:postcode":"71065",
    "sg:province":"Baden-W\u00fcrttemberg",
    "wof:name":"Konrad Salmen",
    "wof:placetype":"venue"
},
  "geometry": {"coordinates":[9.040064,48.705124],"type":"Point"}
}