{
  "type": "Feature",
  "properties": {
    "iso:country":"DE",
    "sg:address":"Seestr. 78",
    "sg:city":"Balingen",
    "sg:phone":"+49 7433/382327",
    "sg:postcode":"72336",
    "sg:province":"Baden-W\u00fcrttemberg",
    "wof:name":"R. Und C. Fabing",
    "wof:placetype":"venue"
},
  "geometry": {"coordinates":[8.8585720062,48.2470474243],"type":"Point"}
}