{
  "type": "Feature",
  "properties": {
    "iso:country":"DE",
    "sg:address":"Kleine Heide 16",
    "sg:city":"Bielefeld",
    "sg:phone":"+49 521/872247",
    "sg:postcode":"33611",
    "sg:province":"Nordrhein-Westfalen",
    "wof:name":"Classic Gold Schmuckhandels Gmbh",
    "wof:placetype":"venue"
},
  "geometry": {"coordinates":[8.540936,52.053181],"type":"Point"}
}