{
  "type": "Feature",
  "properties": {
    "iso:country":"DE",
    "sg:address":"Grevenbroicher Str. 29",
    "sg:city":"Rommerskirchen",
    "sg:phone":"+49 2183/7045",
    "sg:postcode":"41569",
    "sg:province":"Nordrhein-Westfalen",
    "wof:name":"Landwirtschaftsmuseum Skulpturen-hallen",
    "wof:placetype":"venue"
},
  "geometry": {"coordinates":[6.663292,51.045822],"type":"Point"}
}