{
  "type": "Feature",
  "properties": {
    "iso:country":"DE",
    "sg:address":"Krapfstr. 29",
    "sg:city":"Stuttgart",
    "sg:phone":"+49 711/6407352",
    "sg:postcode":"70180",
    "sg:province":"Baden-W\u00fcrttemberg",
    "wof:name":"Kurt Raichle",
    "wof:placetype":"venue"
},
  "geometry": {"coordinates":[9.174878,48.76046],"type":"Point"}
}