{
  "type": "Feature",
  "properties": {
    "iso:country":"DE",
    "sg:address":"Marburger Str. 1",
    "sg:city":"Stadtallendorf",
    "sg:phone":"+49 6428/921080",
    "sg:postcode":"35260",
    "sg:province":"Hessen",
    "wof:name":"Okay-kauf",
    "wof:placetype":"venue"
},
  "geometry": {"coordinates":[9.0049943924,50.8300132751],"type":"Point"}
}