{
  "type": "Feature",
  "properties": {
    "iso:country":"DE",
    "sg:address":"Schlo\u00df-Wissener-Str. 8",
    "sg:city":"Kevelaer",
    "sg:phone":"+49 2832/8262",
    "sg:postcode":"47627",
    "sg:province":"Nordrhein-Westfalen",
    "wof:name":"Lambert Hornbergs",
    "wof:placetype":"venue"
},
  "geometry": {"coordinates":[6.260541,51.622505],"type":"Point"}
}