{
  "type": "Feature",
  "properties": {
    "iso:country":"DE",
    "sg:address":"Gl\u00f6tzleweg 43",
    "sg:city":"M\u00fcnchen",
    "sg:phone":"+49 89/797621",
    "sg:postcode":"81477",
    "sg:province":"Bayern",
    "wof:name":"Maren Matthes Kunstmaler",
    "wof:placetype":"venue"
},
  "geometry": {"coordinates":[11.507518,48.083694],"type":"Point"}
}