{
  "type": "Feature",
  "properties": {
    "iso:country":"DE",
    "sg:address":"Dr.-Rau-Allee 32",
    "sg:city":"Warendorf",
    "sg:phone":"+49 2581/3027",
    "sg:postcode":"48231",
    "sg:province":"Nordrhein-Westfalen",
    "wof:name":"Hans-dieter Heuke Bundeswehr-kantine",
    "wof:placetype":"venue"
},
  "geometry": {"coordinates":[7.993680954,51.9671936035],"type":"Point"}
}