{
  "type": "Feature",
  "properties": {
    "iso:country":"DE",
    "sg:address":"Am Untertor 6",
    "sg:city":"Wetter",
    "sg:phone":"+49 6423/7217",
    "sg:postcode":"35083",
    "sg:province":"Hessen",
    "wof:name":"Hans-j\u00fcrgen Freundner",
    "wof:placetype":"venue"
},
  "geometry": {"coordinates":[8.723137,50.904568],"type":"Point"}
}