{
  "type": "Feature",
  "properties": {
    "iso:country":"DE",
    "sg:address":"Oefte 12 A",
    "sg:city":"Essen",
    "sg:phone":"+49 2054/3152",
    "sg:postcode":"45219",
    "sg:province":"Nordrhein-Westfalen",
    "wof:name":"Josef Rose",
    "wof:placetype":"venue"
},
  "geometry": {"coordinates":[6.971652,51.35849],"type":"Point"}
}