{
  "type": "Feature",
  "properties": {
    "iso:country":"DE",
    "sg:address":"Fr\u00fchlingstr. 13",
    "sg:city":"Passau",
    "sg:phone":"+49 851/955420",
    "sg:postcode":"94032",
    "sg:province":"Bayern",
    "wof:name":"Wagenhuber Versicherungsmakler Gmbh",
    "wof:placetype":"venue"
},
  "geometry": {"coordinates":[13.4349870682,48.5712928772],"type":"Point"}
}