{
  "type": "Feature",
  "properties": {
    "iso:country":"DE",
    "sg:address":"Mangm\u00fchle 1",
    "sg:city":"Dietramszell",
    "sg:postcode":"83623",
    "sg:province":"Bayern",
    "wof:name":"Bavaria Kompressortechnik Gmbh",
    "wof:placetype":"venue"
},
  "geometry": {"coordinates":[11.4889268875,47.8901290894],"type":"Point"}
}