{
  "type": "Feature",
  "properties": {
    "iso:country":"DE",
    "sg:address":"Marienstr 19",
    "sg:city":"Paderborn",
    "sg:phone":"+49 5251/21305",
    "sg:postcode":"33098",
    "sg:province":"Nordrhein-Westfalen",
    "wof:name":"Filter Fest Spiel Zeiten",
    "wof:placetype":"venue"
},
  "geometry": {"coordinates":[8.748822,51.717892],"type":"Point"}
}