{
  "type": "Feature",
  "properties": {
    "iso:country":"DE",
    "sg:address":"Bachemer Str. 15",
    "sg:city":"H\u00fcrth",
    "sg:phone":"+49 2233/32481",
    "sg:postcode":"50354",
    "sg:province":"Nordrhein-Westfalen",
    "wof:name":"S. Gauer",
    "wof:placetype":"venue"
},
  "geometry": {"coordinates":[6.8796610832,50.8800964355],"type":"Point"}
}