{
  "type": "Feature",
  "properties": {
    "iso:country":"DE",
    "sg:address":"Eichenweg",
    "sg:city":"Neu-Isenburg",
    "sg:phone":"+49 6102/38546",
    "sg:postcode":"63263",
    "sg:province":"Hessen",
    "wof:name":"Reitersch\u00e4nke",
    "wof:placetype":"venue"
},
  "geometry": {"coordinates":[8.699016571,50.0435142517],"type":"Point"}
}