{
  "type": "Feature",
  "properties": {
    "iso:country":"DE",
    "sg:address":"Theresienstr. 29",
    "sg:city":"Ingolstadt",
    "sg:phone":"+49 841/17819",
    "sg:postcode":"85049",
    "sg:province":"Bayern",
    "wof:name":"Dr. C. Zenk Steuerberater",
    "wof:placetype":"venue"
},
  "geometry": {"coordinates":[11.4216842651,48.7640419006],"type":"Point"}
}