{
  "type": "Feature",
  "properties": {
    "iso:country":"DE",
    "sg:address":"Nobelstr 10",
    "sg:city":"Ettlingen",
    "sg:phone":"+49 7243/15991",
    "sg:postcode":"76275",
    "sg:province":"Baden-W\u00fcrttemberg",
    "wof:name":"Junior Systembau Karlsruhe Gmbh",
    "wof:placetype":"venue"
},
  "geometry": {"coordinates":[8.3766031265,48.9379119873],"type":"Point"}
}