{
  "type": "Feature",
  "properties": {
    "iso:country":"DE",
    "sg:address":"Schiffergasse 4",
    "sg:city":"Weisenheim am Sand",
    "sg:phone":"+49 6353/8208",
    "sg:postcode":"67256",
    "sg:province":"Rheinland-Pfalz",
    "wof:name":"Werner Merk",
    "wof:placetype":"venue"
},
  "geometry": {"coordinates":[8.2497730255,49.5196609497],"type":"Point"}
}