{
  "type": "Feature",
  "properties": {
    "iso:country":"DE",
    "sg:address":"Hauptstr. 19",
    "sg:city":"Staufen",
    "sg:phone":"+49 7633/5297",
    "sg:postcode":"79219",
    "sg:province":"Baden-W\u00fcrttemberg",
    "wof:name":"Hotel-restaurant Hirschen",
    "wof:placetype":"venue"
},
  "geometry": {"coordinates":[9.5614213943,51.3479042053],"type":"Point"}
}