{
  "type": "Feature",
  "properties": {
    "iso:country":"DE",
    "sg:address":"Achering 9",
    "sg:city":"Freising",
    "sg:postcode":"85354",
    "sg:province":"Bayern",
    "wof:name":"M M Galabau - Garten- Und Landschaftsbau Gmbh",
    "wof:placetype":"venue"
},
  "geometry": {"coordinates":[11.7083034515,48.3439750671],"type":"Point"}
}