{
  "type": "Feature",
  "properties": {
    "iso:country":"DE",
    "sg:address":"Aduchtstr. 5",
    "sg:city":"K\u00f6ln",
    "sg:postcode":"50668",
    "sg:province":"Nordrhein-Westfalen",
    "wof:name":"Abs Gesellschaft F\u00fcr Arch\u00e4ologische Baugrund-",
    "wof:placetype":"venue"
},
  "geometry": {"coordinates":[6.9647622108,50.9556465149],"type":"Point"}
}