{
  "type": "Feature",
  "properties": {
    "iso:country":"DE",
    "sg:address":"Karl-Marx-Str. 14",
    "sg:city":"Grevesm\u00fchlen",
    "sg:phone":"+49 3881/79049",
    "sg:postcode":"23936",
    "sg:province":"Mecklenburg-Vorpommern",
    "wof:name":"Visitec Mikrotechnik Gmbh",
    "wof:placetype":"venue"
},
  "geometry": {"coordinates":[11.182137,53.861042],"type":"Point"}
}