{
  "type": "Feature",
  "properties": {
    "iso:country":"DE",
    "sg:address":"Bempflinger Str. 9",
    "sg:city":"Gro\u00dfbettlingen",
    "sg:phone":"+49 7022/46407",
    "sg:postcode":"72663",
    "sg:province":"Baden-W\u00fcrttemberg",
    "wof:name":"Schmid",
    "wof:placetype":"venue"
},
  "geometry": {"coordinates":[9.3044281006,48.5899009705],"type":"Point"}
}