{
  "type": "Feature",
  "properties": {
    "iso:country":"DE",
    "sg:address":"W\u00f6rthstr. 13-15",
    "sg:city":"W\u00fcrzburg",
    "sg:postcode":"97082",
    "sg:province":"Bayern",
    "wof:name":"Bayerisches Kunststoff- Werk Gmbh",
    "wof:placetype":"venue"
},
  "geometry": {"coordinates":[9.916485,49.795944],"type":"Point"}
}