{
  "type": "Feature",
  "properties": {
    "iso:country":"DE",
    "sg:address":"Kirchplatz 2",
    "sg:city":"Menden",
    "sg:phone":"+49 2373/93760",
    "sg:postcode":"58706",
    "sg:province":"Nordrhein-Westfalen",
    "wof:name":"Bockelmann",
    "wof:placetype":"venue"
},
  "geometry": {"coordinates":[7.1606388092,50.7921218872],"type":"Point"}
}