{
  "type": "Feature",
  "properties": {
    "iso:country":"DE",
    "sg:address":"Birkenweg 23",
    "sg:city":"Teningen",
    "sg:phone":"+49 7641/42559",
    "sg:postcode":"79331",
    "sg:province":"Baden-W\u00fcrttemberg",
    "wof:name":"Heinrich Riedmann Ingenieur",
    "wof:placetype":"venue"
},
  "geometry": {"coordinates":[7.8243880272,48.1250267029],"type":"Point"}
}