{
  "type": "Feature",
  "properties": {
    "iso:country":"DE",
    "sg:address":"Petersstr. 24",
    "sg:city":"Freiberg",
    "sg:phone":"+49 3731/458854",
    "sg:postcode":"09599",
    "sg:province":"Sachsen",
    "wof:name":"Bernhauer Und Sch\u00fcrmann Rechtsanw\u00e4lte",
    "wof:placetype":"venue"
},
  "geometry": {"coordinates":[13.340842247,50.9159317017],"type":"Point"}
}