{
  "type": "Feature",
  "properties": {
    "iso:country":"DE",
    "sg:address":"Schulstr 8",
    "sg:city":"Wetzlar",
    "sg:phone":"+49 6441/26978",
    "sg:postcode":"35579",
    "sg:province":"Hessen",
    "wof:name":"Heiland Electronic Gmbh",
    "wof:placetype":"venue"
},
  "geometry": {"coordinates":[8.456434,50.547062],"type":"Point"}
}