{
  "type": "Feature",
  "properties": {
    "iso:country":"DE",
    "sg:address":"Scharfensteiner Str. 54",
    "sg:city":"Gro\u00dfolbersdorf",
    "sg:phone":"+49 4937/3691400",
    "sg:postcode":"09432",
    "sg:province":"Sachsen",
    "wof:name":"Landgut Am D\u00d6rrhaus'ag",
    "wof:placetype":"venue"
},
  "geometry": {"coordinates":[13.085783,50.690235],"type":"Point"}
}