{
  "type": "Feature",
  "properties": {
    "iso:country":"DE",
    "sg:address":"Wiesenstr. 104",
    "sg:city":"K\u00f6nigswinter",
    "sg:postcode":"53639",
    "sg:province":"Nordrhein-Westfalen",
    "wof:name":"Jvs Sales Und Technical Consultants Gmbh",
    "wof:placetype":"venue"
},
  "geometry": {"coordinates":[7.2359390259,50.7021942139],"type":"Point"}
}