{
  "type": "Feature",
  "properties": {
    "iso:country":"DE",
    "sg:address":"Blumenstr. 4",
    "sg:city":"M\u00f6ser",
    "sg:phone":"+49 39222/2243",
    "sg:postcode":"39291",
    "sg:province":"Sachsen-Anhalt",
    "wof:name":"G\u00e4rtnerei Lindenblatt",
    "wof:placetype":"venue"
},
  "geometry": {"coordinates":[11.808595,52.208893],"type":"Point"}
}