{
  "type": "Feature",
  "properties": {
    "iso:country":"DE",
    "sg:address":"Bahnhofstr. 9",
    "sg:city":"Denklingen",
    "sg:phone":"+49 8243/2667",
    "sg:postcode":"86920",
    "sg:province":"Bayern",
    "wof:name":"Gromzig Gmbh",
    "wof:placetype":"venue"
},
  "geometry": {"coordinates":[10.854531,47.915703],"type":"Point"}
}