{
  "type": "Feature",
  "properties": {
    "iso:country":"DE",
    "sg:address":"Valznerweiherstr. 13",
    "sg:city":"N\u00fcrnberg",
    "sg:phone":"+49 911/404010",
    "sg:postcode":"90480",
    "sg:province":"Bayern",
    "wof:name":"Angelika Ramser",
    "wof:placetype":"venue"
},
  "geometry": {"coordinates":[11.122966,49.442268],"type":"Point"}
}