{
  "type": "Feature",
  "properties": {
    "iso:country":"DE",
    "sg:address":"K\u00f6penicker Str. 295",
    "sg:city":"Berlin",
    "sg:phone":"+49 30/6144871",
    "sg:postcode":"12683",
    "sg:province":"Berlin",
    "wof:name":"Henri Borowsky",
    "wof:placetype":"venue"
},
  "geometry": {"coordinates":[13.5595626831,52.4754943848],"type":"Point"}
}