{
  "type": "Feature",
  "properties": {
    "iso:country":"DE",
    "sg:address":"Memminger Str. 64",
    "sg:city":"Wei\u00dfenhorn",
    "sg:phone":"+49 7309/96960",
    "sg:postcode":"89264",
    "sg:province":"Bayern",
    "wof:name":"Zur Rose",
    "wof:placetype":"venue"
},
  "geometry": {"coordinates":[10.1604614258,48.2969779968],"type":"Point"}
}