{
  "type": "Feature",
  "properties": {
    "iso:country":"DE",
    "sg:address":"Deichhauser Str. 47",
    "sg:city":"S\u00fcdbrookmerland",
    "sg:postcode":"26624",
    "sg:province":"Niedersachsen",
    "wof:name":"Beteiligungsgesellschaft Ulferts M\u00fcnkeboe Mbh",
    "wof:placetype":"venue"
},
  "geometry": {"coordinates":[7.390448,53.521587],"type":"Point"}
}