{
  "type": "Feature",
  "properties": {
    "iso:country":"DE",
    "sg:address":"Frankenstr. 58",
    "sg:city":"Neuss",
    "sg:phone":"+49 2131/58176",
    "sg:postcode":"41462",
    "sg:province":"Nordrhein-Westfalen",
    "wof:name":"Hans-peter Hegger",
    "wof:placetype":"venue"
},
  "geometry": {"coordinates":[6.676038,51.209831],"type":"Point"}
}