{
  "type": "Feature",
  "properties": {
    "iso:country":"DE",
    "sg:address":"Bahnhofstr. 104",
    "sg:city":"M\u00fccke",
    "sg:phone":"+49 6400/201904",
    "sg:postcode":"35325",
    "sg:province":"Hessen",
    "wof:name":"Sylvia Rahn-gontrum Rechtsanw\u00e4ltin",
    "wof:placetype":"venue"
},
  "geometry": {"coordinates":[9.0284767151,50.6169166565],"type":"Point"}
}