{
  "type": "Feature",
  "properties": {
    "iso:country":"DE",
    "sg:address":"Hardter Str. 34a",
    "sg:city":"Viersen",
    "sg:phone":"+49 2162/13355",
    "sg:postcode":"41747",
    "sg:province":"Nordrhein-Westfalen",
    "wof:name":"Pesch Backwaren Gmbh",
    "wof:placetype":"venue"
},
  "geometry": {"coordinates":[6.383253,51.245445],"type":"Point"}
}