{
  "type": "Feature",
  "properties": {
    "iso:country":"DE",
    "sg:address":"Frankfurter Str. 28",
    "sg:city":"Bad K\u00f6nig",
    "sg:phone":"+49 6063/2833",
    "sg:postcode":"64732",
    "sg:province":"Hessen",
    "wof:name":"Brunnengarten",
    "wof:placetype":"venue"
},
  "geometry": {"coordinates":[9.004327,49.743996],"type":"Point"}
}