{
  "type": "Feature",
  "properties": {
    "iso:country":"DE",
    "sg:address":"Friedenstr. 12",
    "sg:city":"Erlenbach",
    "sg:phone":"+49 9372/8902",
    "sg:postcode":"63906",
    "sg:province":"Bayern",
    "wof:name":"Volkmar Hauck Steuerberater",
    "wof:placetype":"venue"
},
  "geometry": {"coordinates":[9.1497077942,49.803894043],"type":"Point"}
}