{
  "type": "Feature",
  "properties": {
    "iso:country":"DE",
    "sg:address":"Neue Str. 18",
    "sg:city":"Wildeshausen",
    "sg:phone":"+49 4431/917349",
    "sg:postcode":"27793",
    "sg:province":"Niedersachsen",
    "wof:name":"Ssw",
    "wof:placetype":"venue"
},
  "geometry": {"coordinates":[8.4342880249,52.8962593079],"type":"Point"}
}