{
  "type": "Feature",
  "properties": {
    "iso:country":"DE",
    "sg:address":"Wartburgstr. 36",
    "sg:city":"Chemnitz",
    "sg:phone":"+49 371/585423",
    "sg:postcode":"09126",
    "sg:province":"Sachsen",
    "wof:name":"Peter-michael Kaufhold",
    "wof:placetype":"venue"
},
  "geometry": {"coordinates":[12.9369621277,50.8165473938],"type":"Point"}
}