{
  "type": "Feature",
  "properties": {
    "iso:country":"DE",
    "sg:address":"Ober Schneidersgarten 4",
    "sg:city":"Greimerath",
    "sg:phone":"+49 6574/948519",
    "sg:postcode":"54533",
    "sg:province":"Rheinland-Pfalz",
    "wof:name":"Elfriede Busch",
    "wof:placetype":"venue"
},
  "geometry": {"coordinates":[6.90752,50.038265],"type":"Point"}
}