{
  "type": "Feature",
  "properties": {
    "iso:country":"DE",
    "sg:address":"Huckarder Str. 348",
    "sg:city":"Dortmund",
    "sg:phone":"+49 231/313892",
    "sg:postcode":"44369",
    "sg:province":"Nordrhein-Westfalen",
    "wof:name":"E. Reimann",
    "wof:placetype":"venue"
},
  "geometry": {"coordinates":[7.4164152145,51.53150177],"type":"Point"}
}