{
  "type": "Feature",
  "properties": {
    "iso:country":"DE",
    "sg:address":"Lanfertsweg 24",
    "sg:city":"Meschede",
    "sg:phone":"+49 291/3939",
    "sg:postcode":"59872",
    "sg:province":"Nordrhein-Westfalen",
    "wof:name":"Holzverwertung G. Schrage",
    "wof:placetype":"venue"
},
  "geometry": {"coordinates":[8.2906131744,51.3610343933],"type":"Point"}
}