{
  "type": "Feature",
  "properties": {
    "iso:country":"DE",
    "sg:address":"Am Bahnhof 4",
    "sg:city":"Arholzen",
    "sg:phone":"+49 5532/3061",
    "sg:postcode":"37627",
    "sg:province":"Niedersachsen",
    "wof:name":"Oppermann Bau- Und Naturstein Gmbh",
    "wof:placetype":"venue"
},
  "geometry": {"coordinates":[9.580359,51.869221],"type":"Point"}
}