{
  "type": "Feature",
  "properties": {
    "iso:country":"DE",
    "sg:address":"Hermann-L\u00f6ns-Weg 5",
    "sg:city":"Winnenden",
    "sg:phone":"+49 7195/62393",
    "sg:postcode":"71364",
    "sg:province":"Baden-W\u00fcrttemberg",
    "wof:name":"Markus Baumeister Architekt",
    "wof:placetype":"venue"
},
  "geometry": {"coordinates":[9.40125,48.866653],"type":"Point"}
}