{
  "type": "Feature",
  "properties": {
    "iso:country":"DE",
    "sg:address":"Albertplatz 1",
    "sg:city":"Plauen",
    "sg:phone":"+49 3741/223847",
    "sg:postcode":"08523",
    "sg:province":"Sachsen",
    "wof:name":"Praxis Dr. Med. Rebentisch",
    "wof:placetype":"venue"
},
  "geometry": {"coordinates":[12.132604599,50.5022277832],"type":"Point"}
}