{
  "type": "Feature",
  "properties": {
    "iso:country":"DE",
    "sg:address":"Ursulastr. 25",
    "sg:city":"Duisburg",
    "sg:phone":"+49 203/6693195",
    "sg:postcode":"47226",
    "sg:province":"Nordrhein-Westfalen",
    "wof:name":"Prestige Gmbh",
    "wof:placetype":"venue"
},
  "geometry": {"coordinates":[6.7273797989,51.4046440125],"type":"Point"}
}