{
  "type": "Feature",
  "properties": {
    "iso:country":"DE",
    "sg:address":"Prinzregentenstr. 115",
    "sg:city":"M\u00fcnchen",
    "sg:phone":"+49 89/477309",
    "sg:postcode":"81677",
    "sg:province":"Bayern",
    "wof:name":"Optik Gerhard Gmbh",
    "wof:placetype":"venue"
},
  "geometry": {"coordinates":[11.6122198105,48.1384544373],"type":"Point"}
}