{
  "type": "Feature",
  "properties": {
    "iso:country":"DE",
    "sg:address":"Jahnstr. 3",
    "sg:city":"Althengstett",
    "sg:phone":"+49 7051/13468",
    "sg:postcode":"75382",
    "sg:province":"Baden-W\u00fcrttemberg",
    "wof:name":"Munzur Imbi\u00df",
    "wof:placetype":"venue"
},
  "geometry": {"coordinates":[8.7946081161,48.7253646851],"type":"Point"}
}