{
  "type": "Feature",
  "properties": {
    "iso:country":"DE",
    "sg:address":"Drechslerberg 6",
    "sg:city":"Offingen",
    "sg:phone":"+49 8224/1801",
    "sg:postcode":"89362",
    "sg:province":"Bayern",
    "wof:name":"Giso Wohnbau Gmbh",
    "wof:placetype":"venue"
},
  "geometry": {"coordinates":[10.361764,48.478195],"type":"Point"}
}