{
  "type": "Feature",
  "properties": {
    "iso:country":"DE",
    "sg:address":"Marbacher Str. 102",
    "sg:city":"D\u00fcsseldorf",
    "sg:phone":"+49 211/7118990",
    "sg:postcode":"40597",
    "sg:province":"Nordrhein-Westfalen",
    "wof:name":"Hermann Rainer",
    "wof:placetype":"venue"
},
  "geometry": {"coordinates":[6.860006,51.164661],"type":"Point"}
}