{
  "type": "Feature",
  "properties": {
    "iso:country":"DE",
    "sg:address":"Randersweide 1",
    "sg:city":"Hamburg",
    "sg:phone":"+49 40/73595680",
    "sg:postcode":"21035",
    "sg:province":"Hamburg",
    "wof:name":"Franz Klaus Union Armaturen Pumpen Gmbh & Co.",
    "wof:placetype":"venue"
},
  "geometry": {"coordinates":[10.1970396042,53.4778404236],"type":"Point"}
}