{
  "type": "Feature",
  "properties": {
    "iso:country":"DE",
    "sg:address":"Rosa-Luxemburg-Str. 9",
    "sg:city":"D\u00f6beln",
    "sg:phone":"+49 3431/7210",
    "sg:postcode":"04720",
    "sg:province":"Sachsen",
    "wof:name":"Stadtwerke D\u00f6beln Gmbh",
    "wof:placetype":"venue"
},
  "geometry": {"coordinates":[13.1157112122,51.1218681335],"type":"Point"}
}