{
  "type": "Feature",
  "properties": {
    "iso:country":"DE",
    "sg:address":"Jakob-Kneip-Str. 24",
    "sg:city":"D\u00fcsseldorf",
    "sg:postcode":"40595",
    "sg:province":"Nordrhein-Westfalen",
    "wof:name":"Vst Vertrieb & Service-team E. K.",
    "wof:placetype":"venue"
},
  "geometry": {"coordinates":[6.9000101089,51.1340560913],"type":"Point"}
}