{
  "type": "Feature",
  "properties": {
    "iso:country":"DE",
    "sg:address":"Sielower Str. 51",
    "sg:city":"Cottbus",
    "sg:postcode":"03044",
    "sg:province":"Brandenburg",
    "wof:name":"Wirtschafts-vermittlungs Agentur Bdbg Wvab",
    "wof:placetype":"venue"
},
  "geometry": {"coordinates":[14.3320608139,51.7665977478],"type":"Point"}
}