{
  "type": "Feature",
  "properties": {
    "iso:country":"DE",
    "sg:address":"Eisenbahnstr. 53",
    "sg:city":"Heusweiler",
    "sg:postcode":"66265",
    "sg:province":"Saarland",
    "wof:name":"Elektro-service Kiefer Gmbh",
    "wof:placetype":"venue"
},
  "geometry": {"coordinates":[6.937113,49.340099],"type":"Point"}
}