{
  "type": "Feature",
  "properties": {
    "iso:country":"DE",
    "sg:address":"Hauptstr34",
    "sg:city":"Scheidlingen",
    "sg:phone":"+49 5956/485",
    "sg:postcode":"08956",
    "wof:name":"Software-download-kostenlos",
    "wof:placetype":"venue"
},
  "geometry": {"coordinates":[-99.11669921879999,19.3833007812],"type":"Point"}
}