{
  "type": "Feature",
  "properties": {
    "iso:country":"DE",
    "sg:address":"Bundesstr. 23",
    "sg:city":"D\u00f6rentrup",
    "sg:phone":"+49 5265/531",
    "sg:postcode":"32694",
    "sg:province":"Nordrhein-Westfalen",
    "wof:name":"Heinz Dux",
    "wof:placetype":"venue"
},
  "geometry": {"coordinates":[9.0557394028,52.0267906189],"type":"Point"}
}