{
  "type": "Feature",
  "properties": {
    "iso:country":"DE",
    "sg:address":"Mutecke 23",
    "sg:city":"Lippstadt",
    "sg:phone":"+49 2945/5480",
    "sg:postcode":"59556",
    "sg:province":"Nordrhein-Westfalen",
    "wof:name":"Josef Funke Gmbh",
    "wof:placetype":"venue"
},
  "geometry": {"coordinates":[8.215973,51.656002],"type":"Point"}
}