{
  "type": "Feature",
  "properties": {
    "iso:country":"DE",
    "sg:address":"Hauert 18",
    "sg:city":"Dortmund",
    "sg:phone":"+49 231/9750000",
    "sg:postcode":"44227",
    "sg:province":"Nordrhein-Westfalen",
    "wof:name":"Raith Gmbh",
    "wof:placetype":"venue"
},
  "geometry": {"coordinates":[7.4018149376,51.489112854],"type":"Point"}
}