{
  "type": "Feature",
  "properties": {
    "iso:country":"DE",
    "sg:address":"Hauptstr. 1",
    "sg:city":"Himmelpforten",
    "sg:phone":"+49 4144/5520",
    "sg:postcode":"21709",
    "sg:province":"Niedersachsen",
    "wof:name":"R. Hillyer-funke",
    "wof:placetype":"venue"
},
  "geometry": {"coordinates":[9.3141040802,53.610004425],"type":"Point"}
}