{
  "type": "Feature",
  "properties": {
    "iso:country":"DE",
    "sg:address":"Wadenhardstr. 2",
    "sg:city":"Marienfeld",
    "sg:phone":"+49 5247/8133",
    "sg:postcode":"33428",
    "sg:province":"Nordrhein-Westfalen",
    "wof:name":"U. Bruns",
    "wof:placetype":"venue"
},
  "geometry": {"coordinates":[8.281532,51.951973],"type":"Point"}
}