{
  "type": "Feature",
  "properties": {
    "iso:country":"DE",
    "sg:address":"Albert-Einstein-Str. 4",
    "sg:city":"Landsberg",
    "sg:phone":"+49 8191/91660",
    "sg:postcode":"86899",
    "sg:province":"Bayern",
    "wof:name":"Manhart Gmbh",
    "wof:placetype":"venue"
},
  "geometry": {"coordinates":[10.857875,48.06892],"type":"Point"}
}