{
  "type": "Feature",
  "properties": {
    "iso:country":"DE",
    "sg:address":"Glash\u00fctte 4",
    "sg:city":"Lamspringe",
    "sg:phone":"+49 5183/1610",
    "sg:postcode":"31195",
    "sg:province":"Niedersachsen",
    "wof:name":"K. Meyer",
    "wof:placetype":"venue"
},
  "geometry": {"coordinates":[10.0706253052,51.9562568665],"type":"Point"}
}