{
  "type": "Feature",
  "properties": {
    "iso:country":"DE",
    "sg:address":"Welzheimer Str. 47",
    "sg:city":"Gschwend",
    "sg:phone":"+49 7972/5128",
    "sg:postcode":"74417",
    "sg:province":"Baden-W\u00fcrttemberg",
    "wof:name":"M. Dee\u00df",
    "wof:placetype":"venue"
},
  "geometry": {"coordinates":[9.737288,48.934673],"type":"Point"}
}