{
  "type": "Feature",
  "properties": {
    "iso:country":"DE",
    "sg:address":"Daimlerstr. 48",
    "sg:city":"Bottrop",
    "sg:phone":"+49 2041/32898",
    "sg:postcode":"46238",
    "sg:province":"Nordrhein-Westfalen",
    "wof:name":"Rolf Schnabel",
    "wof:placetype":"venue"
},
  "geometry": {"coordinates":[6.9611859322,51.5379638672],"type":"Point"}
}