{
  "type": "Feature",
  "properties": {
    "iso:country":"DE",
    "sg:address":"Am Gewerbegebiet 998",
    "sg:city":"Steimbke",
    "sg:phone":"+49 5026/264",
    "sg:postcode":"31634",
    "sg:province":"Niedersachsen",
    "wof:name":"Raiffeisen Eg",
    "wof:placetype":"venue"
},
  "geometry": {"coordinates":[9.40942,52.65683],"type":"Point"}
}