{
  "type": "Feature",
  "properties": {
    "iso:country":"DE",
    "sg:address":"Gleisdammstr. 1",
    "sg:city":"Sonneberg",
    "sg:phone":"+49 3675/89610",
    "sg:postcode":"96515",
    "sg:province":"Th\u00fcringen",
    "wof:name":"Honda Autohaus Am Eichberg",
    "wof:placetype":"venue"
},
  "geometry": {"coordinates":[11.164601326,50.3600234985],"type":"Point"}
}