{
  "type": "Feature",
  "properties": {
    "iso:country":"DE",
    "sg:address":"Engelschalkstr. 16",
    "sg:city":"Friedberg",
    "sg:postcode":"86316",
    "sg:province":"Bayern",
    "wof:name":"Aldi Gmbh & Co. Kg",
    "wof:placetype":"venue"
},
  "geometry": {"coordinates":[10.9943580627,48.3502388],"type":"Point"}
}