{
  "type": "Feature",
  "properties": {
    "iso:country":"DE",
    "sg:address":"Eichenlohweg 7",
    "sg:city":"Hamburg",
    "sg:phone":"+49 40/6316351",
    "sg:postcode":"22309",
    "sg:province":"Hamburg",
    "wof:name":"Sauberland Marco Blang",
    "wof:placetype":"venue"
},
  "geometry": {"coordinates":[10.044014,53.60944],"type":"Point"}
}