{
  "type": "Feature",
  "properties": {
    "iso:country":"DE",
    "sg:address":"Weschnitzstar\u00dfe 9",
    "sg:city":"Bensheim",
    "sg:phone":"+49 6251",
    "sg:postcode":"64625",
    "sg:province":"Hessen",
    "wof:name":"Ingenieurb\u00fcro K. Knippschild",
    "wof:placetype":"venue"
},
  "geometry": {"coordinates":[8.5920467377,49.6828918457],"type":"Point"}
}