{
  "type": "Feature",
  "properties": {
    "iso:country":"DE",
    "sg:address":"Waldauer Weg 2",
    "sg:city":"Lohfelden",
    "sg:phone":"+49 561/515162",
    "sg:postcode":"34253",
    "sg:province":"Hessen",
    "wof:name":"Hubert Sachs",
    "wof:placetype":"venue"
},
  "geometry": {"coordinates":[9.5469236374,51.2808380127],"type":"Point"}
}