{
  "type": "Feature",
  "properties": {
    "iso:country":"DE",
    "sg:address":"L\u00fcbbecker Str. 60",
    "sg:city":"Espelkamp",
    "sg:phone":"+49 5743/515",
    "sg:postcode":"32339",
    "sg:province":"Nordrhein-Westfalen",
    "wof:name":"Wiesengrund",
    "wof:placetype":"venue"
},
  "geometry": {"coordinates":[8.616399765,52.3584518433],"type":"Point"}
}