{
  "type": "Feature",
  "properties": {
    "iso:country":"DE",
    "sg:address":"Petrusplatz 15",
    "sg:city":"Neu-Ulm",
    "sg:phone":"+49 731/723208",
    "sg:postcode":"89231",
    "sg:province":"Bayern",
    "wof:name":"Eiscafe Da Venezia",
    "wof:placetype":"venue"
},
  "geometry": {"coordinates":[9.999872,48.393799],"type":"Point"}
}