{
  "type": "Feature",
  "properties": {
    "iso:country":"DE",
    "sg:address":"Heinrichstr. 9",
    "sg:city":"Dresden",
    "sg:phone":"+49 351/816710",
    "sg:postcode":"01097",
    "sg:province":"Sachsen",
    "wof:name":"Zumpe D\u00fcsterh\u00f6ft Richter Partnerschaft Architekten",
    "wof:placetype":"venue"
},
  "geometry": {"coordinates":[13.739664,51.060146],"type":"Point"}
}