{
  "type": "Feature",
  "properties": {
    "iso:country":"DE",
    "sg:address":"Barbaraweg 8",
    "sg:city":"Borkum",
    "sg:phone":"+49 4922/1066",
    "sg:postcode":"26757",
    "sg:province":"Niedersachsen",
    "wof:name":"G. Vieth",
    "wof:placetype":"venue"
},
  "geometry": {"coordinates":[6.6868028641,53.5935096741],"type":"Point"}
}