{
  "type": "Feature",
  "properties": {
    "iso:country":"DE",
    "sg:address":"Neue Unlinger Str. 4",
    "sg:city":"Riedlingen",
    "sg:phone":"+49 7371/10286",
    "sg:postcode":"88499",
    "sg:province":"Baden-W\u00fcrttemberg",
    "wof:name":"Aral-tankstelle",
    "wof:placetype":"venue"
},
  "geometry": {"coordinates":[9.485077858,48.1484718323],"type":"Point"}
}