{
  "type": "Feature",
  "properties": {
    "iso:country":"DE",
    "sg:address":"Tonnaer Str.",
    "sg:city":"Bad Langensalza",
    "sg:postcode":"99947",
    "sg:province":"Th\u00fcringen",
    "wof:name":"Koschi Schuhhandelsgesellschaft Mbh",
    "wof:placetype":"venue"
},
  "geometry": {"coordinates":[10.6576251984,51.1057395935],"type":"Point"}
}