{
  "type": "Feature",
  "properties": {
    "iso:country":"DE",
    "sg:address":"D\u00f6llingerstr. 2",
    "sg:city":"M\u00fcnchen",
    "sg:phone":"+49 89/1781096",
    "sg:postcode":"80639",
    "sg:province":"Bayern",
    "wof:name":"Pargos Electronic Gmbh",
    "wof:placetype":"venue"
},
  "geometry": {"coordinates":[11.514799118,48.1541862488],"type":"Point"}
}