{
  "type": "Feature",
  "properties": {
    "iso:country":"DE",
    "sg:address":"Br\u00fcckleinsweg 13 a",
    "sg:city":"Gem\u00fcnden",
    "sg:phone":"+49 9351/5522",
    "sg:postcode":"97737",
    "sg:province":"Bayern",
    "wof:name":"Heike Lind",
    "wof:placetype":"venue"
},
  "geometry": {"coordinates":[9.706029892,50.0487174988],"type":"Point"}
}