{
  "type": "Feature",
  "properties": {
    "iso:country":"DE",
    "sg:address":"Bahnhofstr. 15",
    "sg:city":"Hameln",
    "sg:phone":"+49 5151/14011",
    "sg:postcode":"31785",
    "sg:province":"Niedersachsen",
    "wof:name":"Gernat Gmbh",
    "wof:placetype":"venue"
},
  "geometry": {"coordinates":[9.371011734,52.102809906],"type":"Point"}
}