{
  "type": "Feature",
  "properties": {
    "iso:country":"DE",
    "sg:address":"Plettenbergstr. 38",
    "sg:city":"Stuttgart",
    "sg:phone":"+49 711/483624",
    "sg:postcode":"70186",
    "sg:province":"Baden-W\u00fcrttemberg",
    "wof:name":"William Reinert",
    "wof:placetype":"venue"
},
  "geometry": {"coordinates":[9.2165288925,48.7785263062],"type":"Point"}
}