{
  "type": "Feature",
  "properties": {
    "iso:country":"DE",
    "sg:address":"Ringstr. 7",
    "sg:city":"Hoogstede",
    "sg:phone":"+49 5944/345",
    "sg:postcode":"49846",
    "sg:province":"Niedersachsen",
    "wof:name":"Geert Mensen",
    "wof:placetype":"venue"
},
  "geometry": {"coordinates":[6.954041,52.557575],"type":"Point"}
}