{
  "type": "Feature",
  "properties": {
    "iso:country":"DE",
    "sg:address":"Caspar-Voght-Str. 44",
    "sg:city":"Hamburg",
    "sg:phone":"+49 40/214886",
    "sg:postcode":"20535",
    "sg:province":"Hamburg",
    "wof:name":"Rainer Koloski",
    "wof:placetype":"venue"
},
  "geometry": {"coordinates":[10.0617160797,53.5606231689],"type":"Point"}
}