{
  "type": "Feature",
  "properties": {
    "iso:country":"DE",
    "sg:address":"Lindenstr. 4",
    "sg:city":"Zell",
    "sg:phone":"+49 4971/646035",
    "sg:postcode":"73119",
    "sg:province":"Baden-W\u00fcrttemberg",
    "wof:name":"Kreissparkasse G\u00f6ppingen",
    "wof:placetype":"venue"
},
  "geometry": {"coordinates":[9.571498,48.648594],"type":"Point"}
}