{
  "type": "Feature",
  "properties": {
    "iso:country":"DE",
    "sg:address":"Gutenbergstr. 3",
    "sg:city":"Bingen",
    "sg:postcode":"55411",
    "sg:province":"Rheinland-Pfalz",
    "wof:name":"Kath. \u00d6ffentliche Bibliothek St. Rupertus U. St. Hildegart",
    "wof:placetype":"venue"
},
  "geometry": {"coordinates":[7.887059,49.96484],"type":"Point"}
}