{
  "type": "Feature",
  "properties": {
    "iso:country":"DE",
    "sg:address":"Saerbecker Str. 64",
    "sg:city":"Ladbergen",
    "sg:phone":"+49 5485/9508",
    "sg:postcode":"49549",
    "sg:province":"Nordrhein-Westfalen",
    "wof:name":"Prosilk Handels Gmbh",
    "wof:placetype":"venue"
},
  "geometry": {"coordinates":[7.71435,52.143082],"type":"Point"}
}