{
  "type": "Feature",
  "properties": {
    "iso:country":"DE",
    "sg:address":"Am Stadtrand 31-33",
    "sg:city":"Hamburg",
    "sg:postcode":"22047",
    "sg:province":"Hamburg",
    "wof:name":"Toom-baumarkt",
    "wof:placetype":"venue"
},
  "geometry": {"coordinates":[10.0994176865,53.5871353149],"type":"Point"}
}