{
  "type": "Feature",
  "properties": {
    "iso:country":"DE",
    "sg:address":"Heinrich-Heine-Str. 2",
    "sg:city":"W\u00fclfrath",
    "sg:phone":"+49 2058/70076",
    "sg:postcode":"42489",
    "sg:province":"Nordrhein-Westfalen",
    "wof:name":"H. Volke Steuerberater",
    "wof:placetype":"venue"
},
  "geometry": {"coordinates":[7.0212497711,51.2777786255],"type":"Point"}
}