{
  "type": "Feature",
  "properties": {
    "iso:country":"DE",
    "sg:address":"Ritterstr. 12",
    "sg:city":"F\u00fcssen",
    "sg:phone":"+49 8362/93820",
    "sg:postcode":"87629",
    "sg:province":"Bayern",
    "wof:name":"Kreisboten-verlag M\u00fchlfellner Kg",
    "wof:placetype":"venue"
},
  "geometry": {"coordinates":[10.6981496811,47.5678710938],"type":"Point"}
}