{
  "type": "Feature",
  "properties": {
    "iso:country":"DE",
    "sg:address":"Rothenbergstr. 12",
    "sg:city":"Dautphetal",
    "sg:phone":"+49 6466/912562",
    "sg:postcode":"35232",
    "sg:province":"Hessen",
    "wof:name":"B\u00fcrgerhaus Gastst\u00e4tte Budapest",
    "wof:placetype":"venue"
},
  "geometry": {"coordinates":[8.5985021591,50.8770294189],"type":"Point"}
}