{
  "type": "Feature",
  "properties": {
    "iso:country":"DE",
    "sg:address":"Dr.-Salvadore-Allende-Str. 2",
    "sg:city":"Weimar",
    "sg:phone":"+49 3643/8060",
    "sg:postcode":"99425",
    "sg:province":"Th\u00fcringen",
    "wof:name":"Ess Euro Senior-service Weimar Gmbh",
    "wof:placetype":"venue"
},
  "geometry": {"coordinates":[11.311606,50.97504],"type":"Point"}
}