{
  "type": "Feature",
  "properties": {
    "iso:country":"DE",
    "sg:address":"Passauer Str. 1",
    "sg:city":"Rotthalm\u00fcnster",
    "sg:postcode":"94094",
    "sg:province":"Bayern",
    "wof:name":"Bavaria Freizeitland Gmbh & Co. Grundst\u00fccks-",
    "wof:placetype":"venue"
},
  "geometry": {"coordinates":[13.203161,48.35973],"type":"Point"}
}