{
  "type": "Feature",
  "properties": {
    "iso:country":"DE",
    "sg:address":"Hohenofen 1",
    "sg:city":"Haselbach",
    "sg:postcode":"96523",
    "sg:province":"Th\u00fcringen",
    "wof:name":"Ev.-luth. Kirche",
    "wof:placetype":"venue"
},
  "geometry": {"coordinates":[11.1960983276,50.4572792053],"type":"Point"}
}