{
  "type": "Feature",
  "properties": {
    "iso:country":"DE",
    "sg:address":"Riedweg 12",
    "sg:city":"Tornesch",
    "sg:phone":"+49 4122/53762",
    "sg:postcode":"25436",
    "sg:province":"Schleswig-Holstein",
    "wof:name":"W. Gorhbandt",
    "wof:placetype":"venue"
},
  "geometry": {"coordinates":[9.725585,53.685146],"type":"Point"}
}