{
  "type": "Feature",
  "properties": {
    "iso:country":"DE",
    "sg:address":"Stra\u00dfe Der Einheit 4",
    "sg:city":"Annaberg-Buchholz",
    "sg:phone":"+49 4937/3342489",
    "sg:postcode":"09456",
    "sg:province":"Sachsen",
    "wof:name":"Heinz Spitzner",
    "wof:placetype":"venue"
},
  "geometry": {"coordinates":[13.0016994476,50.5733413696],"type":"Point"}
}