{
  "type": "Feature",
  "properties": {
    "iso:country":"DE",
    "sg:address":"Z\u00fclpicher Str. 3",
    "sg:city":"K\u00f6ln",
    "sg:phone":"+49 221/231002",
    "sg:postcode":"50674",
    "sg:province":"Nordrhein-Westfalen",
    "wof:name":"J. Haube",
    "wof:placetype":"venue"
},
  "geometry": {"coordinates":[6.938911,50.92992],"type":"Point"}
}