{
  "type": "Feature",
  "properties": {
    "iso:country":"DE",
    "sg:address":"Schwarzenbergstr. 2",
    "sg:city":"Hamburg",
    "sg:phone":"+49 40/6777715",
    "sg:postcode":"21073",
    "sg:province":"Hamburg",
    "wof:name":"Ambulanter Pflegedienst Meditas Gmbh",
    "wof:placetype":"venue"
},
  "geometry": {"coordinates":[9.97732,53.461029],"type":"Point"}
}