{
  "type": "Feature",
  "properties": {
    "iso:country":"DE",
    "sg:address":"Bitscher Str. 14",
    "sg:city":"H\u00f6hein\u00f6d",
    "sg:phone":"+49 6333/279279",
    "sg:postcode":"66989",
    "sg:province":"Rheinland-Pfalz",
    "wof:name":"Lawia Golf Gmbh",
    "wof:placetype":"venue"
},
  "geometry": {"coordinates":[7.6125650406,49.2882881165],"type":"Point"}
}