{
  "type": "Feature",
  "properties": {
    "iso:country":"DE",
    "sg:address":"Herrmannstr. 9",
    "sg:city":"Hohenstein-Ernstthal",
    "sg:phone":"+49 3723/42947",
    "sg:postcode":"09337",
    "sg:province":"Sachsen",
    "wof:name":"Blumen-sachse E. K. Inhaber: Mandy Zimmermann",
    "wof:placetype":"venue"
},
  "geometry": {"coordinates":[12.712167,50.800835],"type":"Point"}
}