{
  "type": "Feature",
  "properties": {
    "iso:country":"DE",
    "sg:address":"Eickener Str. 71",
    "sg:city":"Hattingen",
    "sg:phone":"+49 2324/92580",
    "sg:postcode":"45525",
    "sg:province":"Nordrhein-Westfalen",
    "wof:name":"T & A Systeme Gesell. F\u00fcr Dv-integration Mbh",
    "wof:placetype":"venue"
},
  "geometry": {"coordinates":[7.1701798439,51.3986320496],"type":"Point"}
}