{
  "type": "Feature",
  "properties": {
    "iso:country":"DE",
    "sg:address":"Am Bollenberg 2",
    "sg:city":"D\u00fcrnau",
    "sg:phone":"+49 7582/2005",
    "sg:postcode":"88422",
    "sg:province":"Baden-W\u00fcrttemberg",
    "wof:name":"Cmw Creativmarketing Marketing Und Vertriebs Gmbh",
    "wof:placetype":"venue"
},
  "geometry": {"coordinates":[9.553853,48.057632],"type":"Point"}
}