{
  "type": "Feature",
  "properties": {
    "iso:country":"DE",
    "sg:address":"Lohbachstr. 12",
    "sg:city":"Schwerte",
    "sg:phone":"+49 2304/943170",
    "sg:postcode":"58239",
    "sg:province":"Nordrhein-Westfalen",
    "wof:name":"Gefos Gesellschaft F\u00fcr Offene Systeme Mbh",
    "wof:placetype":"venue"
},
  "geometry": {"coordinates":[7.5798740387,51.4474067688],"type":"Point"}
}