{
  "type": "Feature",
  "properties": {
    "iso:country":"DE",
    "sg:address":"Reuttier Str. 53",
    "sg:city":"Neu-Ulm",
    "sg:phone":"+49 731/722405",
    "sg:postcode":"89231",
    "sg:province":"Bayern",
    "wof:name":"Heidi Kruckenberg",
    "wof:placetype":"venue"
},
  "geometry": {"coordinates":[10.0131368637,48.3906097412],"type":"Point"}
}