{
  "type": "Feature",
  "properties": {
    "iso:country":"DE",
    "sg:address":"Sehretstr. 13",
    "sg:city":"Langen",
    "sg:phone":"+49 6103/21523",
    "sg:postcode":"63225",
    "sg:province":"Hessen",
    "wof:name":"Thomas Klar",
    "wof:placetype":"venue"
},
  "geometry": {"coordinates":[8.6757202148,49.9844093323],"type":"Point"}
}