{
  "type": "Feature",
  "properties": {
    "iso:country":"DE",
    "sg:address":"Philippine-Welser-Str. 17",
    "sg:city":"Augsburg",
    "sg:phone":"+49 821/510436",
    "sg:postcode":"86150",
    "sg:province":"Bayern",
    "wof:name":"Chic - Damenmoden",
    "wof:placetype":"venue"
},
  "geometry": {"coordinates":[10.897405,48.367676],"type":"Point"}
}