{
  "type": "Feature",
  "properties": {
    "iso:country":"DE",
    "sg:address":"Kiefernweg 2",
    "sg:city":"Eiterfeld",
    "sg:phone":"+49 6672/1867",
    "sg:postcode":"36132",
    "sg:province":"Hessen",
    "wof:name":"Rudolf M\u00fcnkel",
    "wof:placetype":"venue"
},
  "geometry": {"coordinates":[9.8651943207,50.7450065613],"type":"Point"}
}