{
  "type": "Feature",
  "properties": {
    "iso:country":"DE",
    "sg:address":"Leitnerstr. 9",
    "sg:city":"Schliersee",
    "sg:phone":"+49 8026/6738",
    "sg:postcode":"83727",
    "sg:province":"Bayern",
    "wof:name":"Karlheinz Eder",
    "wof:placetype":"venue"
},
  "geometry": {"coordinates":[11.863249,47.737579],"type":"Point"}
}