{
  "type": "Feature",
  "properties": {
    "iso:country":"DE",
    "sg:address":"Drennesweg 3",
    "sg:city":"Moers",
    "sg:phone":"+49 2841/769595",
    "sg:postcode":"47445",
    "sg:province":"Nordrhein-Westfalen",
    "wof:name":"Verhoeven",
    "wof:placetype":"venue"
},
  "geometry": {"coordinates":[6.604888,51.477085],"type":"Point"}
}