{
  "type": "Feature",
  "properties": {
    "iso:country":"DE",
    "sg:address":"Siemensstr. 9",
    "sg:city":"Burgau",
    "sg:phone":"+49 8222/5025",
    "sg:postcode":"89331",
    "sg:province":"Bayern",
    "wof:name":"Walter Zink Gmbh",
    "wof:placetype":"venue"
},
  "geometry": {"coordinates":[10.42118,48.424072],"type":"Point"}
}