{
  "type": "Feature",
  "properties": {
    "iso:country":"DE",
    "sg:address":"Nikolaistr. 1 a",
    "sg:city":"Demmin",
    "sg:postcode":"17109",
    "sg:province":"Mecklenburg-Vorpommern",
    "wof:name":"Hatra Handel- Und Transport Gmbh",
    "wof:placetype":"venue"
},
  "geometry": {"coordinates":[13.0253334045,53.909866333],"type":"Point"}
}