{
  "type": "Feature",
  "properties": {
    "iso:country":"DE",
    "sg:address":"Gr\u00fcnwalder Str. 188",
    "sg:city":"M\u00fcnchen",
    "sg:phone":"+49 89/6423154",
    "sg:postcode":"81545",
    "sg:province":"Bayern",
    "wof:name":"K. Riedlinger",
    "wof:placetype":"venue"
},
  "geometry": {"coordinates":[11.563487,48.096584],"type":"Point"}
}