{
  "type": "Feature",
  "properties": {
    "iso:country":"DE",
    "sg:address":"Neuer Graben 11",
    "sg:city":"Osnabr\u00fcck",
    "sg:phone":"+49 541/259100",
    "sg:postcode":"49074",
    "sg:province":"Niedersachsen",
    "wof:name":"Cyber Games Handelsges. F\u00fcr Computer-",
    "wof:placetype":"venue"
},
  "geometry": {"coordinates":[8.0469341278,52.2721557617],"type":"Point"}
}