{
  "type": "Feature",
  "properties": {
    "iso:country":"DE",
    "sg:address":"Eichenstr. 19",
    "sg:city":"Eschweiler",
    "sg:phone":"+49 2403/51568",
    "sg:postcode":"52249",
    "sg:province":"Nordrhein-Westfalen",
    "wof:name":"W. Dickmeis",
    "wof:placetype":"venue"
},
  "geometry": {"coordinates":[6.2708182335,50.8374404907],"type":"Point"}
}