{
  "type": "Feature",
  "properties": {
    "iso:country":"DE",
    "sg:address":"Mittelstr. 6",
    "sg:city":"Elsfleth",
    "sg:phone":"+49 4404/3788",
    "sg:postcode":"26931",
    "sg:province":"Niedersachsen",
    "wof:name":"K. Behrens",
    "wof:placetype":"venue"
},
  "geometry": {"coordinates":[8.4351167679,53.265712738],"type":"Point"}
}