{
  "type": "Feature",
  "properties": {
    "iso:country":"DE",
    "sg:address":"Sigmaringer Str. 58",
    "sg:city":"Stuttgart",
    "sg:postcode":"70567",
    "sg:province":"Baden-W\u00fcrttemberg",
    "wof:name":"Martin Staiger Event- Marketing Gmbh",
    "wof:placetype":"venue"
},
  "geometry": {"coordinates":[9.15686,48.731529],"type":"Point"}
}