{
  "type": "Feature",
  "properties": {
    "iso:country":"DE",
    "sg:address":"Isabellastr. 16",
    "sg:city":"M\u00fcnchen",
    "sg:phone":"+49 89/2782550",
    "sg:postcode":"80798",
    "sg:province":"Bayern",
    "wof:name":"Dr. Peter Henke Ingenieur",
    "wof:placetype":"venue"
},
  "geometry": {"coordinates":[11.5712556839,48.1569786072],"type":"Point"}
}