{
  "type": "Feature",
  "properties": {
    "iso:country":"DE",
    "sg:address":"Postfach 1362:: 85368 Moosburg:: Germany.^^Stadtplatz 16::",
    "sg:city":"Moosburg",
    "sg:phone":"+49 8761/810",
    "sg:postcode":"85368",
    "sg:province":"Bayern",
    "wof:name":"Stadt-und Kreissparkasse Moosburg",
    "wof:placetype":"venue"
},
  "geometry": {"coordinates":[11.936375,48.49445],"type":"Point"}
}