{
  "type": "Feature",
  "properties": {
    "iso:country":"DE",
    "sg:address":"Steinstr. 9",
    "sg:city":"Offenburg",
    "sg:phone":"+49 781/23131",
    "sg:postcode":"77652",
    "sg:province":"Baden-W\u00fcrttemberg",
    "wof:name":"Jeans-corner 77 Inh. H.-p. Benz",
    "wof:placetype":"venue"
},
  "geometry": {"coordinates":[7.944674,48.469395],"type":"Point"}
}