{
  "type": "Feature",
  "properties": {
    "iso:country":"DE",
    "sg:address":"Carl-Troll-Str. 83",
    "sg:city":"Bonn",
    "sg:phone":"+49 228/265437",
    "sg:postcode":"53115",
    "sg:province":"Nordrhein-Westfalen",
    "wof:name":"Union-getr\u00e4nke-vertriebs- Verwaltungs- Gmbh",
    "wof:placetype":"venue"
},
  "geometry": {"coordinates":[7.084668,50.722569],"type":"Point"}
}