{
  "type": "Feature",
  "properties": {
    "iso:country":"DE",
    "sg:address":"Adersstr. 5",
    "sg:city":"Wuppertal",
    "sg:phone":"+49 202/2422276",
    "sg:postcode":"42119",
    "sg:province":"Nordrhein-Westfalen",
    "wof:name":"Naturnah Inh. Ortwin M\u00fcller",
    "wof:placetype":"venue"
},
  "geometry": {"coordinates":[7.1546177864,51.2531318665],"type":"Point"}
}