{
  "type": "Feature",
  "properties": {
    "iso:country":"DE",
    "sg:address":"Oberstr. 25",
    "sg:city":"Volkmarsen",
    "sg:phone":"+49 5693/5209",
    "sg:postcode":"34471",
    "sg:province":"Hessen",
    "wof:name":"Gerhard He\u00dfmert",
    "wof:placetype":"venue"
},
  "geometry": {"coordinates":[9.152933,51.376549],"type":"Point"}
}