{
  "type": "Feature",
  "properties": {
    "iso:country":"DE",
    "sg:address":"Hartmanns Au 14",
    "sg:city":"Saarbr\u00fccken",
    "sg:phone":"+49 681/852011",
    "sg:postcode":"66119",
    "sg:province":"Saarland",
    "wof:name":"Wacker-werke Gmbh & Co. Kg",
    "wof:placetype":"venue"
},
  "geometry": {"coordinates":[7.019445,49.201889],"type":"Point"}
}