{
  "type": "Feature",
  "properties": {
    "iso:country":"DE",
    "sg:address":"Franz-Mehring-Str. 18",
    "sg:city":"M\u00fcgeln",
    "sg:phone":"+49 34362/42330",
    "sg:postcode":"04769",
    "sg:province":"Sachsen",
    "wof:name":"Tenhagen Geb\u00c4udereinigung",
    "wof:placetype":"venue"
},
  "geometry": {"coordinates":[13.03687,51.236176],"type":"Point"}
}