{
  "type": "Feature",
  "properties": {
    "iso:country":"DE",
    "sg:address":"Graf-Eberhard-Str. 26",
    "sg:city":"Altena",
    "sg:phone":"+49 2352/23790",
    "sg:postcode":"58762",
    "sg:province":"Nordrhein-Westfalen",
    "wof:name":"V. Jonas",
    "wof:placetype":"venue"
},
  "geometry": {"coordinates":[7.6573529243,51.300907135],"type":"Point"}
}