{
  "type": "Feature",
  "properties": {
    "iso:country":"DE",
    "sg:address":"Annabergstr. 3",
    "sg:city":"Haltern",
    "sg:phone":"+49 2364/3689",
    "sg:postcode":"45721",
    "sg:province":"Nordrhein-Westfalen",
    "wof:name":"Hillmer Und Krail Architekten",
    "wof:placetype":"venue"
},
  "geometry": {"coordinates":[7.183701,51.738232],"type":"Point"}
}