{
  "type": "Feature",
  "properties": {
    "iso:country":"DE",
    "sg:address":"Innere Passauer Str. 13",
    "sg:city":"Straubing",
    "sg:phone":"+49 9421/10121",
    "sg:postcode":"94315",
    "sg:province":"Bayern",
    "wof:name":"L\u00f6wen Play Gmbh",
    "wof:placetype":"venue"
},
  "geometry": {"coordinates":[12.576300621,48.8812828064],"type":"Point"}
}