{
  "type": "Feature",
  "properties": {
    "iso:country":"DE",
    "sg:address":"Eisenbahnstr. 58",
    "sg:city":"Hausach",
    "sg:phone":"+49 7831/279",
    "sg:postcode":"77756",
    "sg:province":"Baden-W\u00fcrttemberg",
    "wof:name":"Ev. Pfarramt",
    "wof:placetype":"venue"
},
  "geometry": {"coordinates":[8.1803731918,48.285533905],"type":"Point"}
}