{
  "type": "Feature",
  "properties": {
    "iso:country":"DE",
    "sg:address":"Friedrich-Ebert-Str. 41",
    "sg:city":"Weiterstadt",
    "sg:phone":"+49 6150/2275",
    "sg:postcode":"64331",
    "sg:province":"Hessen",
    "wof:name":"Johann Kalawsky",
    "wof:placetype":"venue"
},
  "geometry": {"coordinates":[8.5842218399,49.9035186768],"type":"Point"}
}