{
  "type": "Feature",
  "properties": {
    "iso:country":"DE",
    "sg:address":"Horstring 16",
    "sg:city":"Landau",
    "sg:phone":"+49 6341/51050",
    "sg:postcode":"76829",
    "sg:province":"Rheinland-Pfalz",
    "wof:name":"Wilhelm Guth Gmbh & Co. Kg",
    "wof:placetype":"venue"
},
  "geometry": {"coordinates":[8.133823,49.206612],"type":"Point"}
}