{
  "type": "Feature",
  "properties": {
    "iso:country":"DE",
    "sg:address":"Heinrich-Hertz-Str. 9 B",
    "sg:city":"Greifswald",
    "sg:phone":"+49 3834/813142",
    "sg:postcode":"17491",
    "sg:province":"Mecklenburg-Vorpommern",
    "wof:name":"Olaf Aurich",
    "wof:placetype":"venue"
},
  "geometry": {"coordinates":[13.4003629684,54.0779876709],"type":"Point"}
}