{
  "type": "Feature",
  "properties": {
    "iso:country":"DE",
    "sg:address":"Beethovenstr. 12",
    "sg:city":"Winterbach",
    "sg:phone":"+49 7181/72943",
    "sg:postcode":"73650",
    "sg:province":"Baden-W\u00fcrttemberg",
    "wof:name":"Bms Sport Consulting Gmbh",
    "wof:placetype":"venue"
},
  "geometry": {"coordinates":[9.4877853394,48.796169281],"type":"Point"}
}