{
  "type": "Feature",
  "properties": {
    "iso:country":"DE",
    "sg:address":"Mauerstr. 1",
    "sg:city":"Schw\u00e4bisch Hall",
    "sg:phone":"+49 791/6131",
    "sg:postcode":"74523",
    "sg:province":"Baden-W\u00fcrttemberg",
    "wof:name":"Praxis Dr. Med. Erwin Kohler Dr. Med. Walter M\u00fcller",
    "wof:placetype":"venue"
},
  "geometry": {"coordinates":[9.732752,49.112846],"type":"Point"}
}