{
  "type": "Feature",
  "properties": {
    "iso:country":"DE",
    "sg:address":"Achternholt 2",
    "sg:city":"Kasseburg",
    "sg:phone":"+49 4154/83436",
    "sg:postcode":"22929",
    "sg:province":"Schleswig-Holstein",
    "wof:name":"Thomas Riedel Architekt",
    "wof:placetype":"venue"
},
  "geometry": {"coordinates":[10.420976,53.564255],"type":"Point"}
}