{
  "type": "Feature",
  "properties": {
    "iso:country":"DE",
    "sg:address":"Rohrbacher Str. 101",
    "sg:city":"Leimen",
    "sg:phone":"+49 6224/72178",
    "sg:postcode":"69181",
    "sg:province":"Baden-W\u00fcrttemberg",
    "wof:name":"Helmut Seeger",
    "wof:placetype":"venue"
},
  "geometry": {"coordinates":[8.6890048981,49.3586959839],"type":"Point"}
}