{
  "type": "Feature",
  "properties": {
    "iso:country":"DE",
    "sg:address":"Flurstr. 31",
    "sg:city":"Langenfeld",
    "sg:phone":"+49 2173/149120",
    "sg:postcode":"40764",
    "sg:province":"Nordrhein-Westfalen",
    "wof:name":"Hartmut Brust",
    "wof:placetype":"venue"
},
  "geometry": {"coordinates":[6.954019,51.097965],"type":"Point"}
}