{
  "type": "Feature",
  "properties": {
    "iso:country":"DE",
    "sg:address":"Theodor-Heuss-Str. 27",
    "sg:city":"Ingolstadt",
    "sg:phone":"+49 841/58890",
    "sg:postcode":"85055",
    "sg:province":"Bayern",
    "wof:name":"Pizzeria Michelangelo",
    "wof:placetype":"venue"
},
  "geometry": {"coordinates":[11.4397964478,48.779548645],"type":"Point"}
}