{
  "type": "Feature",
  "properties": {
    "iso:country":"DE",
    "sg:address":"Lange Str. 38-40",
    "sg:city":"Deilingen",
    "sg:phone":"+49 4974/261088",
    "sg:postcode":"78586",
    "sg:province":"Baden-W\u00fcrttemberg",
    "wof:name":"Johann Schnekenburger Gmbh",
    "wof:placetype":"venue"
},
  "geometry": {"coordinates":[8.783957,48.176426],"type":"Point"}
}