{
  "type": "Feature",
  "properties": {
    "iso:country":"DE",
    "sg:address":"Hafenbahnstr 16",
    "sg:city":"Stuttgart",
    "sg:phone":"+49 711/93745623",
    "sg:postcode":"70327",
    "sg:province":"Baden-W\u00fcrttemberg",
    "wof:name":"Berner Elektrotechnik Gmbh",
    "wof:placetype":"venue"
},
  "geometry": {"coordinates":[9.2589349747,48.7710876465],"type":"Point"}
}