{
  "type": "Feature",
  "properties": {
    "iso:country":"DE",
    "sg:address":"Lendershausen 25 1/2",
    "sg:city":"Hofheim",
    "sg:phone":"+49 9523/301",
    "sg:postcode":"97461",
    "sg:province":"Bayern",
    "wof:name":"Heinrich Sauer",
    "wof:placetype":"venue"
},
  "geometry": {"coordinates":[10.5223703384,50.1371421814],"type":"Point"}
}