{
  "type": "Feature",
  "properties": {
    "iso:country":"DE",
    "sg:address":"Leipziger Str. 61",
    "sg:city":"Liebertwolkwitz",
    "sg:phone":"+49 34297/42811",
    "sg:postcode":"04445",
    "wof:name":"Siegfried Bauer",
    "wof:placetype":"venue"
},
  "geometry": {"coordinates":[12.46435,51.28249],"type":"Point"}
}