{
  "type": "Feature",
  "properties": {
    "iso:country":"DE",
    "sg:address":"Kaiserstr. 1-7",
    "sg:city":"Herzogenrath",
    "sg:phone":"+49 2407/2223",
    "sg:postcode":"52134",
    "sg:province":"Nordrhein-Westfalen",
    "wof:name":"Modehaus Klee Gmbh",
    "wof:placetype":"venue"
},
  "geometry": {"coordinates":[6.0902152061,50.831199646],"type":"Point"}
}