{
  "type": "Feature",
  "properties": {
    "iso:country":"DE",
    "sg:address":"Bonner Str. 39",
    "sg:city":"Bonn",
    "sg:phone":"+49 228/313642",
    "sg:postcode":"53173",
    "sg:province":"Nordrhein-Westfalen",
    "wof:name":"China-restaurant Peking",
    "wof:placetype":"venue"
},
  "geometry": {"coordinates":[7.1519351006,50.6874046326],"type":"Point"}
}