{
  "type": "Feature",
  "properties": {
    "iso:country":"DE",
    "sg:address":"Lindenstr. 11",
    "sg:city":"G\u00fcstrow",
    "sg:phone":"+49 3843/681148",
    "sg:postcode":"18273",
    "sg:province":"Mecklenburg-Vorpommern",
    "wof:name":"Hans K\u00f6rner",
    "wof:placetype":"venue"
},
  "geometry": {"coordinates":[12.189131,53.807907],"type":"Point"}
}