{
  "type": "Feature",
  "properties": {
    "iso:country":"DE",
    "sg:address":"L\u00f6bauer Str. 66",
    "sg:city":"Reichenbach",
    "sg:phone":"+49 35828/72400",
    "sg:postcode":"02894",
    "sg:province":"Sachsen",
    "wof:name":"Herbert Frenzel",
    "wof:placetype":"venue"
},
  "geometry": {"coordinates":[14.789166,51.137478],"type":"Point"}
}