{
  "type": "Feature",
  "properties": {
    "iso:country":"DE",
    "sg:address":"Kreuzstr. 3",
    "sg:city":"Viernheim",
    "sg:postcode":"68519",
    "sg:province":"Hessen",
    "wof:name":"Dehas Medizintechnik Gmbh",
    "wof:placetype":"venue"
},
  "geometry": {"coordinates":[8.570314,49.53632],"type":"Point"}
}