{
  "type": "Feature",
  "properties": {
    "iso:country":"DE",
    "sg:address":"Heinrichstr. 15",
    "sg:city":"Hattingen",
    "sg:phone":"+49 2324/32828",
    "sg:postcode":"45525",
    "sg:province":"Nordrhein-Westfalen",
    "wof:name":"Klaus Schultdress",
    "wof:placetype":"venue"
},
  "geometry": {"coordinates":[7.186764,51.395374],"type":"Point"}
}