{
  "type": "Feature",
  "properties": {
    "iso:country":"DE",
    "sg:address":"J\u00fcdenstr. 27",
    "sg:city":"Lutherstadt Wittenberg",
    "sg:phone":"+49 3491/410882",
    "sg:postcode":"06886",
    "sg:province":"Sachsen-Anhalt",
    "wof:name":"B. Richter",
    "wof:placetype":"venue"
},
  "geometry": {"coordinates":[12.6472911835,51.8670578003],"type":"Point"}
}