{
  "type": "Feature",
  "properties": {
    "iso:country":"DE",
    "sg:address":"L\u00fcneburger Str. 13",
    "sg:city":"Uelzen",
    "sg:phone":"+49 581/2720",
    "sg:postcode":"29525",
    "sg:province":"Niedersachsen",
    "wof:name":"Optiker-thie Augenoptiker",
    "wof:placetype":"venue"
},
  "geometry": {"coordinates":[10.5603866577,52.9655570984],"type":"Point"}
}