{
  "type": "Feature",
  "properties": {
    "iso:country":"DE",
    "sg:address":"Augsburger Str. 80",
    "sg:city":"Landsberg",
    "sg:phone":"+49 8191/29674",
    "sg:postcode":"86899",
    "sg:province":"Bayern",
    "wof:name":"Lsl Computer-systems Gmbh",
    "wof:placetype":"venue"
},
  "geometry": {"coordinates":[10.876584,48.049541],"type":"Point"}
}