{
  "type": "Feature",
  "properties": {
    "iso:country":"DE",
    "sg:address":"Lange Kesselstr. 17",
    "sg:city":"Warendorf",
    "sg:phone":"+49 2581/2816",
    "sg:postcode":"48231",
    "sg:province":"Nordrhein-Westfalen",
    "wof:name":"Mary Meyer-sparenberg",
    "wof:placetype":"venue"
},
  "geometry": {"coordinates":[7.987463,51.951481],"type":"Point"}
}