{
  "type": "Feature",
  "properties": {
    "iso:country":"DE",
    "sg:address":"Rheinstr. 18",
    "sg:city":"Meerbusch",
    "sg:phone":"+49 2150/91920",
    "sg:postcode":"40668",
    "sg:province":"Nordrhein-Westfalen",
    "wof:name":"Terra Domicilbau Ges. F\u00fcr Gehobenen Wohnungsbau Mbh",
    "wof:placetype":"venue"
},
  "geometry": {"coordinates":[6.682858,51.304169],"type":"Point"}
}