{
  "type": "Feature",
  "properties": {
    "iso:country":"DE",
    "sg:address":"Kurze Str. 17",
    "sg:city":"M\u00f6nchengladbach",
    "sg:phone":"+49 2166/31670",
    "sg:postcode":"41239",
    "sg:province":"Nordrhein-Westfalen",
    "wof:name":"Siegfried F\u00fchrer Architekt",
    "wof:placetype":"venue"
},
  "geometry": {"coordinates":[6.426415,51.165886],"type":"Point"}
}