{
  "type": "Feature",
  "properties": {
    "iso:country":"DE",
    "sg:address":"Sonnenallee 174",
    "sg:city":"Berlin",
    "sg:phone":"+49 30/7869194",
    "sg:postcode":"12059",
    "sg:province":"Berlin",
    "wof:name":"Goldschmiedemeister Peter Giese",
    "wof:placetype":"venue"
},
  "geometry": {"coordinates":[13.448933,52.477074],"type":"Point"}
}