{
  "type": "Feature",
  "properties": {
    "iso:country":"DE",
    "sg:address":"Eichelsweg 7",
    "sg:city":"Emmelshausen",
    "sg:phone":"+49 6747/6936",
    "sg:postcode":"56281",
    "sg:province":"Rheinland-Pfalz",
    "wof:name":"Hubert Wagner",
    "wof:placetype":"venue"
},
  "geometry": {"coordinates":[7.5390782356,50.1472129822],"type":"Point"}
}