{
  "type": "Feature",
  "properties": {
    "iso:country":"DE",
    "sg:address":"Bahnhofstr. 21",
    "sg:city":"Dermbach",
    "sg:phone":"+49 36964/7096",
    "sg:postcode":"36466",
    "sg:province":"Th\u00fcringen",
    "wof:name":"Hotel Zum Rh\u00f6npaulus",
    "wof:placetype":"venue"
},
  "geometry": {"coordinates":[10.1228742599,50.7085723877],"type":"Point"}
}