{
  "type": "Feature",
  "properties": {
    "iso:country":"DE",
    "sg:address":"Bollmannshausener Weg 5",
    "sg:city":"Rastatt",
    "sg:phone":"+49 7222/24533",
    "sg:postcode":"76437",
    "sg:province":"Baden-W\u00fcrttemberg",
    "wof:name":"Ernst Klehr Steuerberater",
    "wof:placetype":"venue"
},
  "geometry": {"coordinates":[8.1621761322,48.8821868896],"type":"Point"}
}