{
  "type": "Feature",
  "properties": {
    "iso:country":"DE",
    "sg:address":"Sangerhauser Str. 36",
    "sg:city":"Bremen",
    "sg:phone":"+49 421/444753",
    "sg:postcode":"28329",
    "sg:province":"Bremen",
    "wof:name":"M. T\u00fcrke",
    "wof:placetype":"venue"
},
  "geometry": {"coordinates":[8.8672561646,53.0793418884],"type":"Point"}
}