{
  "type": "Feature",
  "properties": {
    "iso:country":"DE",
    "sg:address":"Bohlweg 49",
    "sg:city":"Wildemann",
    "sg:phone":"+49 5323/6108",
    "sg:postcode":"38709",
    "sg:province":"Niedersachsen",
    "wof:name":"Pension Haus G\u00fcnther",
    "wof:placetype":"venue"
},
  "geometry": {"coordinates":[10.2834253311,51.8250007629],"type":"Point"}
}