{
  "type": "Feature",
  "properties": {
    "iso:country":"DE",
    "sg:address":"Am Arrenberg 13",
    "sg:city":"Wuppertal",
    "sg:phone":"+49 202/2424442",
    "sg:postcode":"42117",
    "sg:province":"Nordrhein-Westfalen",
    "wof:name":"Impotax Treuhand Gmbh",
    "wof:placetype":"venue"
},
  "geometry": {"coordinates":[7.1262907982,51.245803833],"type":"Point"}
}