{
  "type": "Feature",
  "properties": {
    "iso:country":"DE",
    "sg:address":"Peter-Klein-Str. 9",
    "sg:city":"Bonn",
    "sg:phone":"+49 228/674824",
    "sg:postcode":"53117",
    "sg:province":"Nordrhein-Westfalen",
    "wof:name":"Walter Gondert",
    "wof:placetype":"venue"
},
  "geometry": {"coordinates":[7.056002,50.754971],"type":"Point"}
}