{
  "type": "Feature",
  "properties": {
    "iso:country":"DE",
    "sg:address":"Oskar-von-Miller-Str 1",
    "sg:city":"Neus\u00e4\u00df",
    "sg:phone":"+49 821/48010",
    "sg:postcode":"86356",
    "sg:province":"Bayern",
    "wof:name":"Kieser Druckerei Gmbh & Co Kg",
    "wof:placetype":"venue"
},
  "geometry": {"coordinates":[10.8305873871,48.3899917603],"type":"Point"}
}