{
  "type": "Feature",
  "properties": {
    "iso:country":"DE",
    "sg:address":"Im Park Sanssouci",
    "sg:city":"Potsdam",
    "sg:phone":"+49 331/23931",
    "sg:postcode":"14469",
    "sg:province":"Brandenburg",
    "wof:name":"Staatliche Schl\u00f6sser Und G\u00e4rten Potsdam-sanssouci",
    "wof:placetype":"venue"
},
  "geometry": {"coordinates":[13.0326,52.414944],"type":"Point"}
}