{
  "type": "Feature",
  "properties": {
    "iso:country":"DE",
    "sg:address":"Marienstr. 116",
    "sg:city":"Neuss",
    "sg:phone":"+49 2131/57001",
    "sg:postcode":"41462",
    "sg:province":"Nordrhein-Westfalen",
    "wof:name":"Media Gmbh Spezialunternehmen F\u00fcr Ind.-",
    "wof:placetype":"venue"
},
  "geometry": {"coordinates":[6.672643,51.203648],"type":"Point"}
}