{
  "type": "Feature",
  "properties": {
    "iso:country":"DE",
    "sg:address":"Langstr. 29",
    "sg:city":"Hanau",
    "sg:phone":"+49 6181/28578",
    "sg:postcode":"63450",
    "sg:province":"Hessen",
    "wof:name":"Lukosch Moden Gmbh",
    "wof:placetype":"venue"
},
  "geometry": {"coordinates":[8.918664,50.133682],"type":"Point"}
}