{
  "type": "Feature",
  "properties": {
    "iso:country":"DE",
    "sg:address":"Am Qu\u00e4hlenberge 7",
    "sg:city":"Wolfenb\u00fcttel",
    "sg:phone":"+49 5331/61924",
    "sg:postcode":"38300",
    "sg:province":"Niedersachsen",
    "wof:name":"Felix Rehwald",
    "wof:placetype":"venue"
},
  "geometry": {"coordinates":[10.5627660751,52.1545982361],"type":"Point"}
}