{
  "type": "Feature",
  "properties": {
    "iso:country":"DE",
    "sg:city":"Birkenau",
    "sg:phone":"+49 6201/399716",
    "sg:postcode":"69488",
    "sg:province":"Hessen",
    "wof:name":"Wolf Unternehmensberatung",
    "wof:placetype":"venue"
},
  "geometry": {"coordinates":[8.70981,49.561348],"type":"Point"}
}