{
  "type": "Feature",
  "properties": {
    "iso:country":"DE",
    "sg:address":"G\u00fcntherstr. 39",
    "sg:city":"Hamburg",
    "sg:phone":"+49 40/2540470",
    "sg:postcode":"22087",
    "sg:province":"Hamburg",
    "wof:name":"Bestform Neutraubling Gmbh & Co. Kg",
    "wof:placetype":"venue"
},
  "geometry": {"coordinates":[10.028755188,53.5642585754],"type":"Point"}
}