{
  "type": "Feature",
  "properties": {
    "iso:country":"DE",
    "sg:address":"Dr.-Johann-Hoffmann-Str. 15",
    "sg:city":"Hahnheim",
    "sg:phone":"+49 6737/9181",
    "sg:postcode":"55278",
    "sg:province":"Rheinland-Pfalz",
    "wof:name":"Marie-schlei-verein E. V.",
    "wof:placetype":"venue"
},
  "geometry": {"coordinates":[8.2706489563,49.8808746338],"type":"Point"}
}