{
  "type": "Feature",
  "properties": {
    "iso:country":"DE",
    "sg:address":"Uhlandstr. 1",
    "sg:city":"Berlin",
    "sg:phone":"+49 30/47756168",
    "sg:postcode":"13156",
    "sg:province":"Berlin",
    "wof:name":"Renate Max",
    "wof:placetype":"venue"
},
  "geometry": {"coordinates":[13.4011106491,52.5874023438],"type":"Point"}
}