{
  "type": "Feature",
  "properties": {
    "iso:country":"DE",
    "sg:address":"Juttaweg 21",
    "sg:city":"K\u00f6ln",
    "sg:phone":"+49 221/602136",
    "sg:postcode":"51069",
    "sg:province":"Nordrhein-Westfalen",
    "wof:name":"M. Klinkhammer Rechtsanwalt",
    "wof:placetype":"venue"
},
  "geometry": {"coordinates":[7.030878067,51.0034065247],"type":"Point"}
}