{
  "type": "Feature",
  "properties": {
    "iso:country":"DE",
    "sg:address":"Bozener Str. 107",
    "sg:city":"Friedberg",
    "sg:phone":"+49 821/260940",
    "sg:postcode":"86316",
    "sg:province":"Bayern",
    "wof:name":"Hans Weber Steuerberater",
    "wof:placetype":"venue"
},
  "geometry": {"coordinates":[10.9963197708,48.3601608276],"type":"Point"}
}