{
  "type": "Feature",
  "properties": {
    "iso:country":"DE",
    "sg:address":"Dahler Str. 20",
    "sg:city":"Wuppertal",
    "sg:phone":"+49 202/642010",
    "sg:postcode":"42389",
    "sg:province":"Nordrhein-Westfalen",
    "wof:name":"Dieter Ehlhardt Tief- Und Stra\u00dfenbau Gmbh",
    "wof:placetype":"venue"
},
  "geometry": {"coordinates":[7.2372841835,51.2779769897],"type":"Point"}
}