{
  "type": "Feature",
  "properties": {
    "iso:country":"DE",
    "sg:address":"Ludwigstr. 8",
    "sg:city":"W\u00fcrzburg",
    "sg:phone":"+49 931/30850",
    "sg:postcode":"97070",
    "sg:province":"Bayern",
    "wof:name":"Gemeinn\u00fctzige Baugesellschaft F\u00fcr Kleinwohnungen-mbh",
    "wof:placetype":"venue"
},
  "geometry": {"coordinates":[9.939139,49.796413],"type":"Point"}
}