{
  "type": "Feature",
  "properties": {
    "iso:country":"DE",
    "sg:address":"Wendelinusstr. 1a",
    "sg:city":"Schleiden",
    "sg:phone":"+49 2445/1880",
    "sg:postcode":"53937",
    "sg:province":"Nordrhein-Westfalen",
    "wof:name":"Reiner Dartenne Shell-tankstelle",
    "wof:placetype":"venue"
},
  "geometry": {"coordinates":[6.4046730995,50.5448265076],"type":"Point"}
}