{
  "type": "Feature",
  "properties": {
    "iso:country":"DE",
    "sg:address":"Schwarzach 22",
    "sg:city":"Mainleus",
    "sg:postcode":"95336",
    "sg:province":"Bayern",
    "wof:name":"Geyer-verwaltungs Gmbh",
    "wof:placetype":"venue"
},
  "geometry": {"coordinates":[11.3596916199,50.1092147827],"type":"Point"}
}