{
  "type": "Feature",
  "properties": {
    "iso:country":"DE",
    "sg:address":"Birkenweg 15",
    "sg:city":"Vellberg",
    "sg:phone":"+49 7907/320",
    "sg:postcode":"74541",
    "sg:province":"Baden-W\u00fcrttemberg",
    "wof:name":"Hermann Burkhard",
    "wof:placetype":"venue"
},
  "geometry": {"coordinates":[9.906478,49.122959],"type":"Point"}
}