{
  "type": "Feature",
  "properties": {
    "iso:country":"DE",
    "sg:address":"Freiheit 11",
    "sg:city":"Brehna",
    "sg:phone":"+49 34954/48527",
    "sg:postcode":"06796",
    "sg:province":"Sachsen-Anhalt",
    "wof:name":"U. Und B. Montage Gmbh",
    "wof:placetype":"venue"
},
  "geometry": {"coordinates":[12.210104,51.556484],"type":"Point"}
}