{
  "type": "Feature",
  "properties": {
    "iso:country":"DE",
    "sg:address":"Raiffeisenstr. 23",
    "sg:city":"Sachsenkam",
    "sg:phone":"+49 8021/88780",
    "sg:postcode":"83679",
    "sg:province":"Bayern",
    "wof:name":"E-business Messagelan By Networkdomains Gmbh",
    "wof:placetype":"venue"
},
  "geometry": {"coordinates":[11.645743,47.804024],"type":"Point"}
}