{
  "type": "Feature",
  "properties": {
    "iso:country":"DE",
    "sg:address":"Donaustr. 32",
    "sg:city":"Tuttlingen",
    "sg:phone":"+49 7461/77830",
    "sg:postcode":"78532",
    "sg:province":"Baden-W\u00fcrttemberg",
    "wof:name":"Egon Stotz",
    "wof:placetype":"venue"
},
  "geometry": {"coordinates":[8.8176794052,47.9852600098],"type":"Point"}
}