{
  "type": "Feature",
  "properties": {
    "iso:country":"DE",
    "sg:address":"Raiffeisenstr. 28",
    "sg:city":"Georgsmarienh\u00fctte",
    "sg:phone":"+49 5401/40204",
    "sg:postcode":"49124",
    "sg:province":"Niedersachsen",
    "wof:name":"Franz Sandk\u00fchler Gmbh & Co.",
    "wof:placetype":"venue"
},
  "geometry": {"coordinates":[8.077981,52.221935],"type":"Point"}
}