{
  "type": "Feature",
  "properties": {
    "iso:country":"DE",
    "sg:address":"Helmholtzstr 2-9",
    "sg:city":"Berlin",
    "sg:phone":"+49 30/3930991",
    "sg:postcode":"10587",
    "sg:province":"Berlin",
    "wof:name":"Sepserv Separation Service Berlin",
    "wof:placetype":"venue"
},
  "geometry": {"coordinates":[13.321957,52.520931],"type":"Point"}
}