{
  "type": "Feature",
  "properties": {
    "iso:country":"DE",
    "sg:address":"Steinfurt",
    "sg:city":"Stolberg",
    "sg:postcode":"52222",
    "sg:province":"Nordrhein-Westfalen",
    "wof:name":"Edeka-markt",
    "wof:placetype":"venue"
},
  "geometry": {"coordinates":[6.2279100418,50.7942199707],"type":"Point"}
}