{
  "type": "Feature",
  "properties": {
    "iso:country":"DE",
    "sg:address":"Rheindahlener Str. 32",
    "sg:city":"M\u00f6nchengladbach",
    "sg:phone":"+49 2166/57331",
    "sg:postcode":"41189",
    "sg:province":"Nordrhein-Westfalen",
    "wof:name":"Emmy Pfeiffer",
    "wof:placetype":"venue"
},
  "geometry": {"coordinates":[6.39934,51.13533],"type":"Point"}
}