{
  "type": "Feature",
  "properties": {
    "iso:country":"DE",
    "sg:address":"Bismarckstr. 41",
    "sg:city":"Berlin",
    "sg:phone":"+49 30/3426482",
    "sg:postcode":"10627",
    "sg:province":"Berlin",
    "wof:name":"Eric Isichei",
    "wof:placetype":"venue"
},
  "geometry": {"coordinates":[13.30629,52.511795],"type":"Point"}
}