{
  "type": "Feature",
  "properties": {
    "iso:country":"DE",
    "sg:address":"Am Berg 40",
    "sg:city":"Losheim",
    "sg:phone":"+49 6872/88167",
    "sg:postcode":"66679",
    "sg:province":"Saarland",
    "wof:name":"Johannes Wirth",
    "wof:placetype":"venue"
},
  "geometry": {"coordinates":[6.7430939674,49.502986908],"type":"Point"}
}