{
  "type": "Feature",
  "properties": {
    "iso:country":"DE",
    "sg:address":"Memminger Str. 6",
    "sg:city":"Heimertingen",
    "sg:phone":"+49 8335/8453",
    "sg:postcode":"87751",
    "sg:province":"Bayern",
    "wof:name":"Erika M\u00fcller",
    "wof:placetype":"venue"
},
  "geometry": {"coordinates":[10.1535968781,48.0394210815],"type":"Point"}
}