{
  "type": "Feature",
  "properties": {
    "iso:country":"DE",
    "sg:address":"Hubert-Underberg-Allee 1",
    "sg:city":"Rheinberg",
    "sg:phone":"+49 2843/92780",
    "sg:postcode":"47495",
    "sg:province":"Nordrhein-Westfalen",
    "wof:name":"Sportfit Holding Gmbh & Co. Kg",
    "wof:placetype":"venue"
},
  "geometry": {"coordinates":[6.595044136,51.5374946594],"type":"Point"}
}