{
  "type": "Feature",
  "properties": {
    "iso:country":"DE",
    "sg:address":"Hauptstr. 23",
    "sg:city":"Jetzendorf",
    "sg:postcode":"85305",
    "sg:province":"Bayern",
    "wof:name":"Zack Design Gmbh",
    "wof:placetype":"venue"
},
  "geometry": {"coordinates":[11.4215679169,48.4344291687],"type":"Point"}
}