{
  "type": "Feature",
  "properties": {
    "iso:country":"DE",
    "sg:address":"Hallesche Str. 74",
    "sg:city":"Lutherstadt Eisleben",
    "sg:phone":"+49 3475/603067",
    "sg:postcode":"06295",
    "sg:province":"Sachsen-Anhalt",
    "wof:name":"Hans-j\u00fcrgen M\u00fcller Gmbh",
    "wof:placetype":"venue"
},
  "geometry": {"coordinates":[11.556455,51.522865],"type":"Point"}
}