{
  "type": "Feature",
  "properties": {
    "iso:country":"DE",
    "sg:address":"Aachener Str. 529",
    "sg:city":"K\u00f6ln",
    "sg:phone":"+49 221/4911938",
    "sg:postcode":"50933",
    "sg:province":"Nordrhein-Westfalen",
    "wof:name":"Reiner Roeben",
    "wof:placetype":"venue"
},
  "geometry": {"coordinates":[6.8981151581,50.9370117188],"type":"Point"}
}