{
  "type": "Feature",
  "properties": {
    "iso:country":"DE",
    "sg:address":"Gottesackergasse 18",
    "sg:city":"Eggenfelden",
    "sg:phone":"+49 8721/3142",
    "sg:postcode":"84307",
    "sg:province":"Bayern",
    "wof:name":"Dr. Norbert Scheftner Tierarzt",
    "wof:placetype":"venue"
},
  "geometry": {"coordinates":[12.7596693039,48.4060096741],"type":"Point"}
}