{
  "type": "Feature",
  "properties": {
    "iso:country":"DE",
    "sg:address":"S\u00fc\u00dfmilchstr. 16",
    "sg:city":"Bischofswerda",
    "sg:phone":"+49 3594/77210",
    "sg:postcode":"01877",
    "sg:province":"Sachsen",
    "wof:name":"Steuda Steuerberatungs Gmbh",
    "wof:placetype":"venue"
},
  "geometry": {"coordinates":[14.1831130981,51.1227493286],"type":"Point"}
}