{
  "type": "Feature",
  "properties": {
    "iso:country":"DE",
    "sg:address":"Kirchgasse 5",
    "sg:city":"Ingersheim",
    "sg:phone":"+49 7142/53529",
    "sg:postcode":"74379",
    "sg:province":"Baden-W\u00fcrttemberg",
    "wof:name":"Heinz Sch\u00fctz",
    "wof:placetype":"venue"
},
  "geometry": {"coordinates":[9.1856536865,48.960483551],"type":"Point"}
}