{
  "type": "Feature",
  "properties": {
    "iso:country":"DE",
    "sg:address":"Gartenstr.48",
    "sg:city":"Steinheim",
    "sg:phone":"+49 5233/4264",
    "sg:postcode":"32839",
    "sg:province":"Nordrhein-Westfalen",
    "wof:name":"Urlaubsfotos Aus Kreta",
    "wof:placetype":"venue"
},
  "geometry": {"coordinates":[9.091727,51.86404],"type":"Point"}
}