{
  "type": "Feature",
  "properties": {
    "iso:country":"DE",
    "sg:address":"Grafeler Str. 9",
    "sg:city":"Anderlingen",
    "sg:phone":"+49 4284/8314",
    "sg:postcode":"27446",
    "sg:province":"Niedersachsen",
    "wof:name":"H. Brandtjen",
    "wof:placetype":"venue"
},
  "geometry": {"coordinates":[9.304644,53.376118],"type":"Point"}
}