{
  "type": "Feature",
  "properties": {
    "iso:country":"DE",
    "sg:address":"Fischerstr. 6",
    "sg:city":"Mannheim",
    "sg:phone":"+49 621/853226",
    "sg:postcode":"68199",
    "sg:province":"Baden-W\u00fcrttemberg",
    "wof:name":"Werner Herrmann",
    "wof:placetype":"venue"
},
  "geometry": {"coordinates":[8.493102,49.454025],"type":"Point"}
}