{
  "type": "Feature",
  "properties": {
    "iso:country":"DE",
    "sg:address":"Niersteiner Str. 5",
    "sg:city":"Trebur",
    "sg:phone":"+49 6147/644",
    "sg:postcode":"65468",
    "sg:province":"Hessen",
    "wof:name":"Heinrich Wulfert",
    "wof:placetype":"venue"
},
  "geometry": {"coordinates":[8.3865280151,49.8961524963],"type":"Point"}
}