{
  "type": "Feature",
  "properties": {
    "iso:country":"DE",
    "sg:address":"Brieystr. 2",
    "sg:city":"Bergheim",
    "sg:phone":"+49 2271/52979",
    "sg:postcode":"50129",
    "sg:province":"Nordrhein-Westfalen",
    "wof:name":"Niederau\u00dfemer Hof E. K.",
    "wof:placetype":"venue"
},
  "geometry": {"coordinates":[6.6757497787,50.9803504944],"type":"Point"}
}