{
  "type": "Feature",
  "properties": {
    "iso:country":"DE",
    "sg:address":"K\u00f6nigsberger Str. 20",
    "sg:city":"Weinheim",
    "sg:phone":"+49 6201/66687",
    "sg:postcode":"69469",
    "sg:province":"Baden-W\u00fcrttemberg",
    "wof:name":"Baer Gmbh",
    "wof:placetype":"venue"
},
  "geometry": {"coordinates":[8.639134,49.542435],"type":"Point"}
}