{
  "type": "Feature",
  "properties": {
    "iso:country":"DE",
    "sg:address":"Ernst-Barlach-Str. 6",
    "sg:city":"Sindelfingen",
    "sg:phone":"+49 7031/878230",
    "sg:postcode":"71065",
    "sg:province":"Baden-W\u00fcrttemberg",
    "wof:name":"R. Funk Versicherungsvertreter",
    "wof:placetype":"venue"
},
  "geometry": {"coordinates":[9.0345182419,48.7072296143],"type":"Point"}
}