{
  "type": "Feature",
  "properties": {
    "iso:country":"DE",
    "sg:address":"Hochriesstr. 27",
    "sg:city":"Ebersberg",
    "sg:phone":"+49 8092/22667",
    "sg:postcode":"85560",
    "sg:province":"Bayern",
    "wof:name":"Walter Pecher",
    "wof:placetype":"venue"
},
  "geometry": {"coordinates":[11.959883,48.075066],"type":"Point"}
}