{
  "type": "Feature",
  "properties": {
    "iso:country":"DE",
    "sg:address":"Robert-Bosch-Str 31",
    "sg:city":"V\u00f6hringen",
    "sg:phone":"+49 7306/950070",
    "sg:postcode":"89269",
    "sg:province":"Bayern",
    "wof:name":"Schnarrenberger Gmbh",
    "wof:placetype":"venue"
},
  "geometry": {"coordinates":[10.072584,48.293114],"type":"Point"}
}