{
  "type": "Feature",
  "properties": {
    "iso:country":"DE",
    "sg:address":"Kleine Beurhausstr. 3",
    "sg:city":"Dortmund",
    "sg:phone":"+49 231/147382",
    "sg:postcode":"44137",
    "sg:province":"Nordrhein-Westfalen",
    "wof:name":"Liz",
    "wof:placetype":"venue"
},
  "geometry": {"coordinates":[7.45286,51.508629],"type":"Point"}
}