{
  "type": "Feature",
  "properties": {
    "iso:country":"DE",
    "sg:address":"Nollendorfer Str. 27",
    "sg:city":"Jena",
    "sg:phone":"+49 3641/52040",
    "sg:postcode":"07743",
    "sg:province":"Th\u00fcringen",
    "wof:name":"Andreas Kreysa Rechtsanwalt",
    "wof:placetype":"venue"
},
  "geometry": {"coordinates":[11.5880250931,50.9359359741],"type":"Point"}
}