{
  "type": "Feature",
  "properties": {
    "iso:country":"DE",
    "sg:address":"Schlo\u00dfstr. 116",
    "sg:city":"J\u00fcchen",
    "sg:phone":"+49 2182/4813",
    "sg:postcode":"41363",
    "sg:province":"Nordrhein-Westfalen",
    "wof:name":"Hans Bremer",
    "wof:placetype":"venue"
},
  "geometry": {"coordinates":[6.5632801056,51.1336288452],"type":"Point"}
}