{
  "type": "Feature",
  "properties": {
    "iso:country":"DE",
    "sg:address":"Kattenheider Weg 1",
    "sg:city":"H\u00f6velhof",
    "sg:phone":"+49 5257/2433",
    "sg:postcode":"33161",
    "sg:province":"Nordrhein-Westfalen",
    "wof:name":"Gefl\u00fcgelhof Tanger Gefl\u00fcgel-handels-",
    "wof:placetype":"venue"
},
  "geometry": {"coordinates":[8.6032943726,51.8526954651],"type":"Point"}
}