{
  "type": "Feature",
  "properties": {
    "iso:country":"DE",
    "sg:address":"Neuenb\u00fcrger Str. 58",
    "sg:city":"Straubenhardt",
    "sg:phone":"+49 7082/50491",
    "sg:postcode":"75334",
    "sg:province":"Baden-W\u00fcrttemberg",
    "wof:name":"W\u00fcrttembergische Versicherung Simon Holger",
    "wof:placetype":"venue"
},
  "geometry": {"coordinates":[8.5383205414,48.8437843323],"type":"Point"}
}