{
  "type": "Feature",
  "properties": {
    "iso:country":"DE",
    "sg:address":"Reinhardtstr. 47",
    "sg:city":"Berlin",
    "sg:phone":"+49 30/2813462",
    "sg:postcode":"10117",
    "sg:province":"Berlin",
    "wof:name":"Dr. Med. Elisabeth Hilgenfeld",
    "wof:placetype":"venue"
},
  "geometry": {"coordinates":[13.37753,52.52219],"type":"Point"}
}