{
  "type": "Feature",
  "properties": {
    "iso:country":"DE",
    "sg:address":"Karlsbader Str. 104",
    "sg:city":"Sehmatal-Neudorf",
    "sg:phone":"+49 37342/7249",
    "sg:postcode":"09465",
    "sg:province":"Sachsen",
    "wof:name":"W. Lorenz",
    "wof:placetype":"venue"
},
  "geometry": {"coordinates":[12.975163,50.502724],"type":"Point"}
}