{
  "type": "Feature",
  "properties": {
    "iso:country":"DE",
    "sg:address":"Waldheimstr. 11",
    "sg:city":"Kierspe",
    "sg:phone":"+49 2359/4040",
    "sg:postcode":"58566",
    "sg:province":"Nordrhein-Westfalen",
    "wof:name":"Plastomatic Gabriela Trautmann",
    "wof:placetype":"venue"
},
  "geometry": {"coordinates":[7.591365,51.122238],"type":"Point"}
}