{
  "type": "Feature",
  "properties": {
    "iso:country":"DE",
    "sg:address":"Crottendorfer Str. 4",
    "sg:city":"Leipzig",
    "sg:postcode":"04317",
    "sg:province":"Sachsen",
    "wof:name":"Cab Bewehrungstechnik Gmbh",
    "wof:placetype":"venue"
},
  "geometry": {"coordinates":[12.407863,51.33691],"type":"Point"}
}