{
  "type": "Feature",
  "properties": {
    "iso:country":"DE",
    "sg:address":"Speyerer Str. 18-20",
    "sg:city":"Limburgerhof",
    "sg:phone":"+49 6236/48305",
    "sg:postcode":"67117",
    "sg:province":"Rheinland-Pfalz",
    "wof:name":"Zentrum Orthopaedie Limburgerhof",
    "wof:placetype":"venue"
},
  "geometry": {"coordinates":[8.394934,49.420254],"type":"Point"}
}