{
  "type": "Feature",
  "properties": {
    "iso:country":"DE",
    "sg:address":"Bahnhofsring 14",
    "sg:city":"Lutherstadt Eisleben",
    "sg:phone":"+49 3475/74580",
    "sg:postcode":"06295",
    "sg:province":"Sachsen-Anhalt",
    "wof:name":"Technologie- Und Gr\u00fcnder- Zentrum Mansfelder Land Gmbh",
    "wof:placetype":"venue"
},
  "geometry": {"coordinates":[11.5491285324,51.5200157166],"type":"Point"}
}