{
  "type": "Feature",
  "properties": {
    "iso:country":"DE",
    "sg:address":"Volgersweg 26",
    "sg:city":"Hannover",
    "sg:phone":"+49 511/343435",
    "sg:postcode":"30175",
    "sg:province":"Niedersachsen",
    "wof:name":"Ursula Und Claus-rud. L\u00f6ffler Rechtsanw\u00e4ltin Und Notarin",
    "wof:placetype":"venue"
},
  "geometry": {"coordinates":[9.7519464493,52.3793983459],"type":"Point"}
}