{
  "type": "Feature",
  "properties": {
    "iso:country":"DE",
    "sg:address":"Wichtenbecker Weg 5",
    "sg:city":"Gerdau",
    "sg:phone":"+49 5808/268",
    "sg:postcode":"29581",
    "sg:province":"Niedersachsen",
    "wof:name":"Heinrich Meyer",
    "wof:placetype":"venue"
},
  "geometry": {"coordinates":[10.393949,52.950172],"type":"Point"}
}