{
  "type": "Feature",
  "properties": {
    "iso:country":"DE",
    "sg:address":"Landstr. 25",
    "sg:city":"Weilheim",
    "sg:phone":"+49 7755/92000",
    "sg:postcode":"79809",
    "sg:province":"Baden-W\u00fcrttemberg",
    "wof:name":"Lignotrend Holzblock- Systeme Gesellschaft Mbh",
    "wof:placetype":"venue"
},
  "geometry": {"coordinates":[8.167894,47.676346],"type":"Point"}
}