{
  "type": "Feature",
  "properties": {
    "iso:country":"DE",
    "sg:address":"Hauptstr. 115",
    "sg:city":"Frankenthal",
    "sg:phone":"+49 35954/53288",
    "sg:postcode":"01909",
    "sg:province":"Sachsen",
    "wof:name":"Gro\u00df- Und Einzelhandel Plaste/ Elaste Michel Gmbh",
    "wof:placetype":"venue"
},
  "geometry": {"coordinates":[14.1200151443,51.1256332397],"type":"Point"}
}