{
  "type": "Feature",
  "properties": {
    "iso:country":"DE",
    "sg:address":"Bahnhofstr. 56",
    "sg:city":"Meschede",
    "sg:phone":"+49 2903/6044",
    "sg:postcode":"59872",
    "sg:province":"Nordrhein-Westfalen",
    "wof:name":"U. Gei\u00dfler",
    "wof:placetype":"venue"
},
  "geometry": {"coordinates":[8.1677694321,51.3687896729],"type":"Point"}
}