{
  "type": "Feature",
  "properties": {
    "iso:country":"DE",
    "sg:address":"Essener Str. 17",
    "sg:city":"K\u00f6ln",
    "sg:phone":"+49 2203/301540",
    "sg:postcode":"51145",
    "sg:province":"Nordrhein-Westfalen",
    "wof:name":"Peter Meurer",
    "wof:placetype":"venue"
},
  "geometry": {"coordinates":[7.071481,50.890182],"type":"Point"}
}