{
  "type": "Feature",
  "properties": {
    "iso:country":"DE",
    "sg:address":"Leipziger Str. 105",
    "sg:city":"T\u00f6nisvorst",
    "sg:phone":"+49 2151/796850",
    "sg:postcode":"47918",
    "sg:province":"Nordrhein-Westfalen",
    "wof:name":"Erika Herrmann",
    "wof:placetype":"venue"
},
  "geometry": {"coordinates":[6.505511,51.32423],"type":"Point"}
}