{
  "type": "Feature",
  "properties": {
    "iso:country":"DE",
    "sg:address":"Kennedyallee 34",
    "sg:city":"Frankfurt",
    "sg:phone":"+49 69/635419",
    "sg:postcode":"60596",
    "sg:province":"Hessen",
    "wof:name":"Restaurant Parthenon",
    "wof:placetype":"venue"
},
  "geometry": {"coordinates":[8.6744403839,50.1010169983],"type":"Point"}
}