{
  "type": "Feature",
  "properties": {
    "iso:country":"DE",
    "sg:address":"Frankfurter Str. 74",
    "sg:city":"Hochheim",
    "sg:phone":"+49 6146/4330",
    "sg:postcode":"65239",
    "sg:province":"Hessen",
    "wof:name":"Ti-k\u00fcchenmarkt Gmbh",
    "wof:placetype":"venue"
},
  "geometry": {"coordinates":[8.3638954163,50.0152320862],"type":"Point"}
}