{
  "type": "Feature",
  "properties": {
    "iso:country":"DE",
    "sg:address":"Heidelberger Landstr 31",
    "sg:city":"Darmstadt",
    "sg:phone":"+49 6151/538300",
    "sg:postcode":"64297",
    "sg:province":"Hessen",
    "wof:name":"Netzwerkplan Gmbh",
    "wof:placetype":"venue"
},
  "geometry": {"coordinates":[8.6453542709,49.839214325],"type":"Point"}
}