{
  "type": "Feature",
  "properties": {
    "iso:country":"DE",
    "sg:address":"Casparistr. 4",
    "sg:city":"Frankfurt",
    "sg:postcode":"60435",
    "sg:province":"Hessen",
    "wof:name":"Fms Facility Management Services Gmbh",
    "wof:placetype":"venue"
},
  "geometry": {"coordinates":[8.6855373383,50.1427307129],"type":"Point"}
}