{
  "type": "Feature",
  "properties": {
    "iso:country":"DE",
    "sg:address":"Hof\u00e4ckerstr. 13",
    "sg:city":"Irchenrieth",
    "sg:postcode":"92699",
    "sg:province":"Bayern",
    "wof:name":"H. Grubis",
    "wof:placetype":"venue"
},
  "geometry": {"coordinates":[12.2261590958,49.6209411621],"type":"Point"}
}