{
  "type": "Feature",
  "properties": {
    "iso:country":"DE",
    "sg:address":"Weyertal 15",
    "sg:city":"K\u00f6ln",
    "sg:phone":"+49 221/428859",
    "sg:postcode":"50937",
    "sg:province":"Nordrhein-Westfalen",
    "wof:name":"Gr\u00fcnlilie",
    "wof:placetype":"venue"
},
  "geometry": {"coordinates":[6.9282021523,50.9223022461],"type":"Point"}
}