{
  "type": "Feature",
  "properties": {
    "iso:country":"DE",
    "sg:address":"Leerer Landstr. 30",
    "sg:city":"Aurich",
    "sg:phone":"+49 4941/91010",
    "sg:postcode":"26603",
    "sg:province":"Niedersachsen",
    "wof:name":"Buss Paulat Und Janssen Rechtsanw\u00e4lte Und Notare",
    "wof:placetype":"venue"
},
  "geometry": {"coordinates":[7.4861721992,53.4658508301],"type":"Point"}
}