{
  "type": "Feature",
  "properties": {
    "iso:country":"DE",
    "sg:address":"Hauptstr. 9",
    "sg:city":"Jeber-Bergfrieden",
    "sg:phone":"+49 34907/20200",
    "sg:postcode":"06862",
    "sg:province":"Sachsen-Anhalt",
    "wof:name":"A. Jakob",
    "wof:placetype":"venue"
},
  "geometry": {"coordinates":[12.3489990234,51.9818458557],"type":"Point"}
}