{
  "type": "Feature",
  "properties": {
    "iso:country":"DE",
    "sg:address":"Neul\u00e4nder Str. 4",
    "sg:city":"Hatten",
    "sg:postcode":"26209",
    "sg:province":"Niedersachsen",
    "wof:name":"L\u00fcschen Gmbh",
    "wof:placetype":"venue"
},
  "geometry": {"coordinates":[8.338945,53.016712],"type":"Point"}
}