{
  "type": "Feature",
  "properties": {
    "iso:country":"DE",
    "sg:address":"Gartenstr. 22",
    "sg:city":"Duisburg",
    "sg:phone":"+49 2066/12386",
    "sg:postcode":"47198",
    "sg:province":"Nordrhein-Westfalen",
    "wof:name":"Ass Hydraulik Service Gmbh",
    "wof:placetype":"venue"
},
  "geometry": {"coordinates":[6.711567,51.452061],"type":"Point"}
}