{
  "type": "Feature",
  "properties": {
    "iso:country":"DE",
    "sg:address":"Rosenstr. 5",
    "sg:city":"Tegernsee",
    "sg:phone":"+49 8022/4382",
    "sg:postcode":"83684",
    "sg:province":"Bayern",
    "wof:name":"Trastevere",
    "wof:placetype":"venue"
},
  "geometry": {"coordinates":[11.7534093857,47.7108573914],"type":"Point"}
}