{
  "type": "Feature",
  "properties": {
    "iso:country":"DE",
    "sg:address":"Abelweg 15a",
    "sg:city":"Kronshagen",
    "sg:postcode":"24119",
    "sg:province":"Schleswig-Holstein",
    "wof:name":"Grundst\u00fccksverwaltungsges. Bartels Mbh & Co. Kg",
    "wof:placetype":"venue"
},
  "geometry": {"coordinates":[10.0905008316,54.3392868042],"type":"Point"}
}