{
  "type": "Feature",
  "properties": {
    "iso:country":"DE",
    "sg:address":"Achenbachstr. 155",
    "sg:city":"D\u00fcsseldorf",
    "sg:phone":"+49 211/672505",
    "sg:postcode":"40237",
    "sg:province":"Nordrhein-Westfalen",
    "wof:name":"Gr\u00e4fin Ewa Strachwitz-siebel",
    "wof:placetype":"venue"
},
  "geometry": {"coordinates":[6.7994279861,51.2373924255],"type":"Point"}
}