{
  "type": "Feature",
  "properties": {
    "iso:country":"DE",
    "sg:address":"Himmelreich 18",
    "sg:city":"Waldeck",
    "sg:phone":"+49 5634/817",
    "sg:postcode":"34513",
    "sg:province":"Hessen",
    "wof:name":"Gerhard Berthold",
    "wof:placetype":"venue"
},
  "geometry": {"coordinates":[8.992077,51.273914],"type":"Point"}
}