{
  "type": "Feature",
  "properties": {
    "iso:country":"DE",
    "sg:address":"Drosselweg 5",
    "sg:city":"N\u00fcrtingen",
    "sg:phone":"+49 7022/54984",
    "sg:postcode":"72622",
    "sg:province":"Baden-W\u00fcrttemberg",
    "wof:name":"Ruth H\u00f6rner Steuerberaterin",
    "wof:placetype":"venue"
},
  "geometry": {"coordinates":[9.3214130402,48.6237831116],"type":"Point"}
}