{
  "type": "Feature",
  "properties": {
    "iso:country":"DE",
    "sg:address":"Gauensieker Str. 42",
    "sg:city":"Drochtersen",
    "sg:phone":"+49 4143/7114",
    "sg:postcode":"21706",
    "sg:province":"Niedersachsen",
    "wof:name":"Helmut Willers Steuerberater",
    "wof:placetype":"venue"
},
  "geometry": {"coordinates":[9.3904790878,53.7078170776],"type":"Point"}
}