{
  "type": "Feature",
  "properties": {
    "iso:country":"DE",
    "sg:address":"Boker Str. 89",
    "sg:city":"Delbr\u00fcck",
    "sg:phone":"+49 5250/7665",
    "sg:postcode":"33129",
    "sg:province":"Nordrhein-Westfalen",
    "wof:name":"Bernhard Schniedermeyer Gmbh & Co. Kg",
    "wof:placetype":"venue"
},
  "geometry": {"coordinates":[8.56488,51.76281],"type":"Point"}
}