{
  "type": "Feature",
  "properties": {
    "iso:country":"DE",
    "sg:address":"Auf dem Platz 9",
    "sg:city":"Tuningen",
    "sg:phone":"+49 4974/64542",
    "sg:postcode":"78609",
    "sg:province":"Baden-W\u00fcrttemberg",
    "wof:name":"Kreissparkasse",
    "wof:placetype":"venue"
},
  "geometry": {"coordinates":[8.601301,48.025936],"type":"Point"}
}