{
  "type": "Feature",
  "properties": {
    "iso:country":"DE",
    "sg:address":"Weberstr. 6-10",
    "sg:city":"Monheim",
    "sg:phone":"+49 2173/53005",
    "sg:postcode":"40789",
    "sg:province":"Nordrhein-Westfalen",
    "wof:name":"Sg Computer Software Gmbh",
    "wof:placetype":"venue"
},
  "geometry": {"coordinates":[6.9034128189,51.0925292969],"type":"Point"}
}