{
  "type": "Feature",
  "properties": {
    "iso:country":"DE",
    "sg:address":"Kalte Weide 10",
    "sg:city":"Obernkirchen",
    "sg:phone":"+49 5724/8811",
    "sg:postcode":"31683",
    "sg:province":"Niedersachsen",
    "wof:name":"Barkow Gmbh",
    "wof:placetype":"venue"
},
  "geometry": {"coordinates":[9.1312589645,52.2747306824],"type":"Point"}
}