{
  "type": "Feature",
  "properties": {
    "iso:country":"DE",
    "sg:address":"Jahnstr. 23",
    "sg:city":"Gr\u00fcndau",
    "sg:phone":"+49 6051/12830",
    "sg:postcode":"63584",
    "sg:province":"Hessen",
    "wof:name":"Jahnstuben",
    "wof:placetype":"venue"
},
  "geometry": {"coordinates":[9.1202554703,50.2000427246],"type":"Point"}
}