{
  "type": "Feature",
  "properties": {
    "iso:country":"DE",
    "sg:address":"Rosenweg 6",
    "sg:city":"Altenburg",
    "sg:phone":"+49 3447/315817",
    "sg:postcode":"04600",
    "sg:province":"Th\u00fcringen",
    "wof:name":"G. Fischer",
    "wof:placetype":"venue"
},
  "geometry": {"coordinates":[12.423452,50.98822],"type":"Point"}
}