{
  "type": "Feature",
  "properties": {
    "iso:country":"DE",
    "sg:address":"Kirchberger Str. 27",
    "sg:city":"Aspach",
    "sg:phone":"+49 7148/8248",
    "sg:postcode":"71546",
    "sg:province":"Baden-W\u00fcrttemberg",
    "wof:name":"Friedrich Obenland",
    "wof:placetype":"venue"
},
  "geometry": {"coordinates":[9.36242,48.989403],"type":"Point"}
}