{
  "type": "Feature",
  "properties": {
    "iso:country":"DE",
    "sg:address":"Vorderreihe 35",
    "sg:city":"L\u00fcbeck",
    "sg:phone":"+49 4502/6666",
    "sg:postcode":"23570",
    "sg:province":"Schleswig-Holstein",
    "wof:name":"Charlotte Holleck Krankengymnastin",
    "wof:placetype":"venue"
},
  "geometry": {"coordinates":[10.869799614,53.9571723938],"type":"Point"}
}