{
  "type": "Feature",
  "properties": {
    "iso:country":"DE",
    "sg:address":"Gr\u00fcninger Str. 11",
    "sg:city":"Pohlheim",
    "sg:phone":"+49 6403/61155",
    "sg:postcode":"35415",
    "sg:province":"Hessen",
    "wof:name":"Otto Burger Steinmetz",
    "wof:placetype":"venue"
},
  "geometry": {"coordinates":[8.7475042343,50.5324401855],"type":"Point"}
}