{
  "type": "Feature",
  "properties": {
    "iso:country":"DE",
    "sg:address":"Pinassenweg 26",
    "sg:city":"L\u00fcbeck",
    "sg:postcode":"23558",
    "sg:province":"Schleswig-Holstein",
    "wof:name":"Aldi Gmbh & Co. Kg",
    "wof:placetype":"venue"
},
  "geometry": {"coordinates":[10.6448507309,53.851776123],"type":"Point"}
}