{
  "type": "Feature",
  "properties": {
    "iso:country":"DE",
    "sg:address":"Waldschmidtstr 9",
    "sg:city":"Viechtach",
    "sg:phone":"+49 9942/902407",
    "sg:postcode":"94234",
    "sg:province":"Bayern",
    "wof:name":"Druckerei Christian Karl",
    "wof:placetype":"venue"
},
  "geometry": {"coordinates":[12.8867588043,49.0777320862],"type":"Point"}
}