{
  "type": "Feature",
  "properties": {
    "iso:country":"DE",
    "sg:address":"Dr.-Muschak-Str. 24",
    "sg:city":"Kaufbeuren",
    "sg:phone":"+49 8341/62841",
    "sg:postcode":"87600",
    "sg:province":"Bayern",
    "wof:name":"M. Bauer",
    "wof:placetype":"venue"
},
  "geometry": {"coordinates":[10.629724,47.918259],"type":"Point"}
}