{
  "type": "Feature",
  "properties": {
    "iso:country":"DE",
    "sg:address":"Sch\u00fctzenhofstr. 97",
    "sg:city":"Oldenburg",
    "sg:phone":"+49 441/47372",
    "sg:postcode":"26133",
    "sg:province":"Niedersachsen",
    "wof:name":"Jacques Wein Depot",
    "wof:placetype":"venue"
},
  "geometry": {"coordinates":[8.2219629288,53.1233558655],"type":"Point"}
}