{
  "type": "Feature",
  "properties": {
    "iso:country":"DE",
    "sg:address":"Walther-Blumenstock-Str. 22",
    "sg:city":"Offenburg",
    "sg:phone":"+49 781/34157",
    "sg:postcode":"77654",
    "sg:province":"Baden-W\u00fcrttemberg",
    "wof:name":"J. Michael Dufner Masseur",
    "wof:placetype":"venue"
},
  "geometry": {"coordinates":[7.962982,48.467739],"type":"Point"}
}