{
  "type": "Feature",
  "properties": {
    "iso:country":"DE",
    "sg:address":"Oberkasselerstr. 100",
    "sg:city":"D\u00fcsseldorf",
    "sg:phone":"+49 4921/1577080",
    "sg:postcode":"40545",
    "sg:province":"Nordrhein-Westfalen",
    "wof:name":"Verlag Otto Sternefeld Gmbh",
    "wof:placetype":"venue"
},
  "geometry": {"coordinates":[6.7561020851,51.2326698303],"type":"Point"}
}