{
  "type": "Feature",
  "properties": {
    "iso:country":"DE",
    "sg:address":"Dorfstr. 42",
    "sg:city":"Gerbisbach",
    "sg:phone":"+49 3537/215580",
    "sg:postcode":"06922",
    "sg:province":"Sachsen-Anhalt",
    "wof:name":"Peter Richter Gbr",
    "wof:placetype":"venue"
},
  "geometry": {"coordinates":[-73.542252,41.05164],"type":"Point"}
}