{
  "type": "Feature",
  "properties": {
    "iso:country":"DE",
    "sg:address":"Am Hagenberg 1",
    "sg:city":"Lotte",
    "sg:phone":"+49 5456/1368",
    "sg:postcode":"49504",
    "sg:province":"Nordrhein-Westfalen",
    "wof:name":"Helmut Hinz",
    "wof:placetype":"venue"
},
  "geometry": {"coordinates":[7.906286,52.257214],"type":"Point"}
}