{
  "type": "Feature",
  "properties": {
    "iso:country":"DE",
    "sg:address":"Unteraltenburg 37",
    "sg:city":"Merseburg",
    "sg:phone":"+49 3461/205634",
    "sg:postcode":"06217",
    "sg:province":"Sachsen-Anhalt",
    "wof:name":"Pension M. Frischke",
    "wof:placetype":"venue"
},
  "geometry": {"coordinates":[11.9984283447,51.3615188599],"type":"Point"}
}