{
  "type": "Feature",
  "properties": {
    "iso:country":"DE",
    "sg:address":"Karl-Liebknecht-Str. 58",
    "sg:city":"Jena",
    "sg:phone":"+49 3641/443836",
    "sg:postcode":"07749",
    "sg:province":"Th\u00fcringen",
    "wof:name":"Ivb Th\u00fcringer Sanierungs- Und Entwicklungs-gmbh",
    "wof:placetype":"venue"
},
  "geometry": {"coordinates":[11.605312,50.931728],"type":"Point"}
}