{
  "type": "Feature",
  "properties": {
    "iso:country":"DE",
    "sg:address":"Dachauer Str. 22b",
    "sg:city":"Kollbach",
    "sg:phone":"+49 8137/808955",
    "sg:postcode":"85238",
    "sg:province":"Bayern",
    "wof:name":"Wolfgang-k.de - Der Webservice",
    "wof:placetype":"venue"
},
  "geometry": {"coordinates":[11.491558,48.392693],"type":"Point"}
}