{
  "type": "Feature",
  "properties": {
    "iso:country":"DE",
    "sg:address":"St.-Anna-Str. 5",
    "sg:city":"Neuss",
    "sg:phone":"+49 2131/81051",
    "sg:postcode":"41464",
    "sg:province":"Nordrhein-Westfalen",
    "wof:name":"Con-truck Neuss Rainer K\u00f6nnecke",
    "wof:placetype":"venue"
},
  "geometry": {"coordinates":[6.666774,51.197975],"type":"Point"}
}