{
  "type": "Feature",
  "properties": {
    "iso:country":"DE",
    "sg:address":"Gottlieb-Daimler-Str. 6",
    "sg:city":"Mitterteich",
    "sg:postcode":"95666",
    "sg:province":"Bayern",
    "wof:name":"Hotel Miratel E. K.",
    "wof:placetype":"venue"
},
  "geometry": {"coordinates":[12.227648735,49.9367446899],"type":"Point"}
}