{
  "type": "Feature",
  "properties": {
    "iso:country":"DE",
    "sg:address":"Pferdmengesstr. 50",
    "sg:city":"K\u00f6ln",
    "sg:phone":"+49 221/3980796",
    "sg:postcode":"50968",
    "sg:province":"Nordrhein-Westfalen",
    "wof:name":"Joachim Ernst Gmbh",
    "wof:placetype":"venue"
},
  "geometry": {"coordinates":[6.9746999741,50.8991279602],"type":"Point"}
}