{
  "type": "Feature",
  "properties": {
    "iso:country":"DE",
    "sg:address":"Oststr. 137",
    "sg:city":"Duisburg",
    "sg:phone":"+49 203/351308",
    "sg:postcode":"47057",
    "sg:province":"Nordrhein-Westfalen",
    "wof:name":"Th. Pagel",
    "wof:placetype":"venue"
},
  "geometry": {"coordinates":[6.7876200676,51.4274559021],"type":"Point"}
}