{
  "type": "Feature",
  "properties": {
    "iso:country":"DE",
    "sg:address":"Brambacher Str. 89",
    "sg:city":"Leipzig",
    "sg:postcode":"04207",
    "sg:province":"Sachsen",
    "wof:name":"Feierabendheim Gr\u00fcnau 4",
    "wof:placetype":"venue"
},
  "geometry": {"coordinates":[12.294432,51.312531],"type":"Point"}
}