{
  "type": "Feature",
  "properties": {
    "iso:country":"DE",
    "sg:address":"Apothekerstr. 28",
    "sg:city":"Arnsberg",
    "sg:phone":"+49 2932/82510",
    "sg:postcode":"59755",
    "sg:province":"Nordrhein-Westfalen",
    "wof:name":"Mutti-sauer",
    "wof:placetype":"venue"
},
  "geometry": {"coordinates":[7.9653658867,51.4513282776],"type":"Point"}
}