{
  "type": "Feature",
  "properties": {
    "iso:country":"DE",
    "sg:address":"Marchzipf",
    "sg:city":"Freyung",
    "sg:phone":"+49 8551/910034",
    "sg:postcode":"94078",
    "sg:province":"Bayern",
    "wof:name":"Ek-seminare Top Seminare Coaching",
    "wof:placetype":"venue"
},
  "geometry": {"coordinates":[13.5145587921,48.7981071472],"type":"Point"}
}