{
  "type": "Feature",
  "properties": {
    "iso:country":"DE",
    "sg:address":"Breiter Weg 8",
    "sg:city":"Hollstadt",
    "sg:postcode":"97618",
    "sg:province":"Bayern",
    "wof:name":"Es-tanzcafe-verwaltungs- Und Verpachtungs-gmbh",
    "wof:placetype":"venue"
},
  "geometry": {"coordinates":[10.356061,50.363258],"type":"Point"}
}