{
  "type": "Feature",
  "properties": {
    "iso:country":"DE",
    "sg:address":"Nibelungenstr. 48",
    "sg:city":"Gro\u00dfwallstadt",
    "sg:postcode":"63868",
    "sg:province":"Bayern",
    "wof:name":"Ersin Bauunternehmen Import Export Industrie Tourismus",
    "wof:placetype":"venue"
},
  "geometry": {"coordinates":[9.1622076035,49.8848648071],"type":"Point"}
}