{
  "type": "Feature",
  "properties": {
    "iso:country":"DE",
    "sg:city":"M\u00f6nchengladbach",
    "sg:postcode":"41236",
    "sg:province":"Nordrhein-Westfalen",
    "wof:name":"Funstrip-jeanette",
    "wof:placetype":"venue"
},
  "geometry": {"coordinates":[6.446815,51.168346],"type":"Point"}
}