{
  "type": "Feature",
  "properties": {
    "iso:country":"DE",
    "sg:address":"Hannoversche Str. 48",
    "sg:city":"Isernhagen",
    "sg:phone":"+49 511/610914",
    "sg:postcode":"30916",
    "sg:province":"Niedersachsen",
    "wof:name":"Hebu Heinrich Und Henning Burchard",
    "wof:placetype":"venue"
},
  "geometry": {"coordinates":[9.8603315353,52.4341773987],"type":"Point"}
}