{
  "type": "Feature",
  "properties": {
    "iso:country":"DE",
    "sg:address":"Im F\u00f6rsterbusch 10",
    "sg:city":"Hamb\u00fchren",
    "sg:phone":"+49 5084/92060",
    "sg:postcode":"29313",
    "sg:province":"Niedersachsen",
    "wof:name":"Hans-peter Zimmermann",
    "wof:placetype":"venue"
},
  "geometry": {"coordinates":[9.967516,52.625568],"type":"Point"}
}