{
  "type": "Feature",
  "properties": {
    "iso:country":"DE",
    "sg:address":"Heiskampstr. 19-21",
    "sg:city":"Hattingen",
    "sg:phone":"+49 2324/33029",
    "sg:postcode":"45527",
    "sg:province":"Nordrhein-Westfalen",
    "wof:name":"Pauli Gmbh",
    "wof:placetype":"venue"
},
  "geometry": {"coordinates":[7.2198758125,51.3972206116],"type":"Point"}
}