{
  "type": "Feature",
  "properties": {
    "iso:country":"DE",
    "sg:address":"Poststr. 25",
    "sg:city":"Werlte",
    "sg:phone":"+49 5951/3319",
    "sg:postcode":"49757",
    "sg:province":"Niedersachsen",
    "wof:name":"Johann A. Heermann",
    "wof:placetype":"venue"
},
  "geometry": {"coordinates":[7.6768941879,52.8491706848],"type":"Point"}
}