{
  "type": "Feature",
  "properties": {
    "iso:country":"DE",
    "sg:address":"Valentin-Dretzel-Str. 11",
    "sg:city":"N\u00fcrnberg",
    "sg:phone":"+49 911/481300",
    "sg:postcode":"90469",
    "sg:province":"Bayern",
    "wof:name":"Wilfried Meiers Reisen",
    "wof:placetype":"venue"
},
  "geometry": {"coordinates":[11.0851163864,49.406162262],"type":"Point"}
}