{
  "type": "Feature",
  "properties": {
    "iso:country":"DE",
    "sg:address":"Im Flecken 54",
    "sg:city":"Salzhemmendorf",
    "sg:phone":"+49 5153/6412",
    "sg:postcode":"31020",
    "sg:province":"Niedersachsen",
    "wof:name":"Hotel Lauensteiner Hof",
    "wof:placetype":"venue"
},
  "geometry": {"coordinates":[9.555680275,52.0774002075],"type":"Point"}
}