{
  "type": "Feature",
  "properties": {
    "iso:country":"DE",
    "sg:address":"Aumunder Heerweg 87",
    "sg:city":"Bremen",
    "sg:phone":"+49 421/666776",
    "sg:postcode":"28757",
    "sg:province":"Bremen",
    "wof:name":"Verbraucherzentrale Beratung",
    "wof:placetype":"venue"
},
  "geometry": {"coordinates":[8.6204252243,53.1740493774],"type":"Point"}
}