{
  "type": "Feature",
  "properties": {
    "iso:country":"DE",
    "sg:address":"Kindinger Str. 25 1/2",
    "sg:city":"Greding",
    "sg:postcode":"91171",
    "sg:province":"Bayern",
    "wof:name":"Aldi Gmbh & Co. Kg",
    "wof:placetype":"venue"
},
  "geometry": {"coordinates":[11.3524847031,49.0458908081],"type":"Point"}
}