{
  "type": "Feature",
  "properties": {
    "iso:country":"DE",
    "sg:address":"Am Beisenbusch 37",
    "sg:city":"Dorsten",
    "sg:postcode":"46282",
    "sg:province":"Nordrhein-Westfalen",
    "wof:name":"Bb Bau Gmbh",
    "wof:placetype":"venue"
},
  "geometry": {"coordinates":[6.954445,51.657513],"type":"Point"}
}