{
  "type": "Feature",
  "properties": {
    "iso:country":"DE",
    "sg:address":"P\u00f6litzer Weg 44",
    "sg:city":"Bad Oldesloe",
    "sg:phone":"+49 4531/84031",
    "sg:postcode":"23843",
    "sg:province":"Schleswig-Holstein",
    "wof:name":"Hopp Gmbh",
    "wof:placetype":"venue"
},
  "geometry": {"coordinates":[10.384057045,53.8004722595],"type":"Point"}
}