{
  "type": "Feature",
  "properties": {
    "iso:country":"DE",
    "sg:address":"Landhausstr. 62",
    "sg:city":"Stuttgart",
    "sg:phone":"+49 711/285440",
    "sg:postcode":"70190",
    "sg:province":"Baden-W\u00fcrttemberg",
    "wof:name":"Verein Der Koreanischen Evangelischen Gemeinde Im",
    "wof:placetype":"venue"
},
  "geometry": {"coordinates":[9.1955919266,48.7863578796],"type":"Point"}
}