{
  "type": "Feature",
  "properties": {
    "iso:country":"DE",
    "sg:address":"Postfach 20 01 34",
    "sg:city":"Gelsenkirchen",
    "sg:phone":"+49 209",
    "sg:postcode":"45458",
    "sg:province":"Nordrhein-Westfalen",
    "wof:name":"Add-versand",
    "wof:placetype":"venue"
},
  "geometry": {"coordinates":[7.0925002098,51.5113296509],"type":"Point"}
}