{
  "type": "Feature",
  "properties": {
    "iso:country":"DE",
    "sg:address":"In der Gerberwiese 4",
    "sg:city":"Leimen",
    "sg:phone":"+49 6224/76441",
    "sg:postcode":"69181",
    "sg:province":"Baden-W\u00fcrttemberg",
    "wof:name":"Technum Gmbh Maschinen Und Industrieanlagen",
    "wof:placetype":"venue"
},
  "geometry": {"coordinates":[8.6709079742,49.3264465332],"type":"Point"}
}