{
  "type": "Feature",
  "properties": {
    "iso:country":"DE",
    "sg:address":"Immenkamp 1",
    "sg:city":"Hamburg",
    "sg:phone":"+49 40/6959689",
    "sg:postcode":"22159",
    "sg:province":"Hamburg",
    "wof:name":"H. Brennecke",
    "wof:placetype":"venue"
},
  "geometry": {"coordinates":[10.1171178818,53.6165962219],"type":"Point"}
}