{
  "type": "Feature",
  "properties": {
    "iso:country":"DE",
    "sg:address":"Magirushof 2",
    "sg:city":"Ulm",
    "sg:phone":"+49 731/9691632",
    "sg:postcode":"89077",
    "sg:province":"Baden-W\u00fcrttemberg",
    "wof:name":"Roland Boley",
    "wof:placetype":"venue"
},
  "geometry": {"coordinates":[9.9836101532,48.3939056396],"type":"Point"}
}