{
  "type": "Feature",
  "properties": {
    "iso:country":"DE",
    "sg:address":"Schulstr. 76",
    "sg:city":"Ketsch",
    "sg:phone":"+49 6202/13008",
    "sg:postcode":"68775",
    "sg:province":"Baden-W\u00fcrttemberg",
    "wof:name":"J. Plath",
    "wof:placetype":"venue"
},
  "geometry": {"coordinates":[8.53016,49.362282],"type":"Point"}
}