{
  "type": "Feature",
  "properties": {
    "iso:country":"DE",
    "sg:address":"Moltkestr. 24",
    "sg:city":"Linden",
    "sg:phone":"+49 6403/5511",
    "sg:postcode":"35440",
    "sg:province":"Hessen",
    "wof:name":"B. Jochem",
    "wof:placetype":"venue"
},
  "geometry": {"coordinates":[8.6529159546,50.5296630859],"type":"Point"}
}