{
  "type": "Feature",
  "properties": {
    "iso:country":"DE",
    "sg:address":"H\u00fclser Str. 128",
    "sg:city":"Krefeld",
    "sg:phone":"+49 2151/758602",
    "sg:postcode":"47803",
    "sg:province":"Nordrhein-Westfalen",
    "wof:name":"M. Hermann",
    "wof:placetype":"venue"
},
  "geometry": {"coordinates":[6.5519309044,51.3432769775],"type":"Point"}
}