{
  "type": "Feature",
  "properties": {
    "iso:country":"DE",
    "sg:address":"Magdeburger Landstr. 5",
    "sg:city":"Brandenburg",
    "sg:phone":"+49 3381/302897",
    "sg:postcode":"14770",
    "sg:province":"Brandenburg",
    "wof:name":"Schwan-apotheke",
    "wof:placetype":"venue"
},
  "geometry": {"coordinates":[12.527199,52.413033],"type":"Point"}
}