{
  "type": "Feature",
  "properties": {
    "iso:country":"DE",
    "sg:address":"Am Espet 3",
    "sg:city":"Johanniskirchen",
    "sg:phone":"+49 8564/394",
    "sg:postcode":"84381",
    "sg:province":"Bayern",
    "wof:name":"Paul Voggenreiter",
    "wof:placetype":"venue"
},
  "geometry": {"coordinates":[12.998249054,48.5604362488],"type":"Point"}
}