{
  "type": "Feature",
  "properties": {
    "iso:country":"DE",
    "sg:address":"Schulstr. 15",
    "sg:city":"Samswegen",
    "sg:phone":"+49 39202/60278",
    "sg:postcode":"39326",
    "sg:province":"Sachsen-Anhalt",
    "wof:name":"Kaufcenter",
    "wof:placetype":"venue"
},
  "geometry": {"coordinates":[11.562513,52.259441],"type":"Point"}
}