{
  "type": "Feature",
  "properties": {
    "iso:country":"DE",
    "sg:address":"Miesbacher Str. 10",
    "sg:city":"Raubling",
    "sg:phone":"+49 8035/5142",
    "sg:postcode":"83064",
    "sg:province":"Bayern",
    "wof:name":"Pierpaolo Onnis Architekt",
    "wof:placetype":"venue"
},
  "geometry": {"coordinates":[12.115644,47.799435],"type":"Point"}
}