{
  "type": "Feature",
  "properties": {
    "iso:country":"DE",
    "sg:address":"Carl-Ludwig-Str. 3",
    "sg:city":"Witzenhausen",
    "sg:phone":"+49 5542/5796",
    "sg:postcode":"37213",
    "sg:province":"Hessen",
    "wof:name":"S. Caglar",
    "wof:placetype":"venue"
},
  "geometry": {"coordinates":[9.8590431213,51.3425331116],"type":"Point"}
}