{
  "type": "Feature",
  "properties": {
    "iso:country":"DE",
    "sg:address":"S\u00fclmerstr. 54",
    "sg:city":"Heilbronn",
    "sg:phone":"+49 7131/962781",
    "sg:postcode":"74072",
    "sg:province":"Baden-W\u00fcrttemberg",
    "wof:name":"Wolfgang Hafner Rechtsanwalt",
    "wof:placetype":"venue"
},
  "geometry": {"coordinates":[9.2209682465,49.1439781189],"type":"Point"}
}