{
  "type": "Feature",
  "properties": {
    "iso:country":"DE",
    "sg:address":"Adam-Klein-Str. 47",
    "sg:city":"N\u00fcrnberg",
    "sg:phone":"+49 911/262420",
    "sg:postcode":"90429",
    "sg:province":"Bayern",
    "wof:name":"Gostenhof-apotheke Zu St. Anton",
    "wof:placetype":"venue"
},
  "geometry": {"coordinates":[11.048223,49.451527],"type":"Point"}
}