{
  "type": "Feature",
  "properties": {
    "iso:country":"DE",
    "sg:address":"Manganstr. 2",
    "sg:city":"R\u00fcsselsheim",
    "sg:phone":"+49 6142/61011",
    "sg:postcode":"65428",
    "sg:province":"Hessen",
    "wof:name":"Glasbau Bockius",
    "wof:placetype":"venue"
},
  "geometry": {"coordinates":[8.4291257858,49.9777336121],"type":"Point"}
}