{
  "type": "Feature",
  "properties": {
    "iso:country":"DE",
    "sg:address":"Frohnauer Str. 135",
    "sg:city":"Berlin",
    "sg:phone":"+49 30/4013012",
    "sg:postcode":"13465",
    "sg:province":"Berlin",
    "wof:name":"Roland Zimmer Gmbh",
    "wof:placetype":"venue"
},
  "geometry": {"coordinates":[13.2871322632,52.6273994446],"type":"Point"}
}