{
  "type": "Feature",
  "properties": {
    "iso:country":"DE",
    "sg:address":"Alpenrosenweg 93",
    "sg:city":"Berlin",
    "sg:phone":"+49 30/6310784",
    "sg:postcode":"12437",
    "sg:province":"Berlin",
    "wof:name":"Henri Zanzow Ingenieur",
    "wof:placetype":"venue"
},
  "geometry": {"coordinates":[13.4872169495,52.4506988525],"type":"Point"}
}