{
  "type": "Feature",
  "properties": {
    "iso:country":"DE",
    "sg:address":"K\u00f6lner Str. 494",
    "sg:city":"K\u00fcrten",
    "sg:phone":"+49 2207/7414",
    "sg:postcode":"51515",
    "sg:province":"Nordrhein-Westfalen",
    "wof:name":"Franz H\u00fcppgen",
    "wof:placetype":"venue"
},
  "geometry": {"coordinates":[7.2046132088,51.02684021],"type":"Point"}
}