{
  "type": "Feature",
  "properties": {
    "iso:country":"DE",
    "sg:address":"Erich-Kuttner-Str. 10",
    "sg:city":"Berlin",
    "sg:phone":"+49 30/9716341",
    "sg:postcode":"10369",
    "sg:province":"Berlin",
    "wof:name":"Ronald Golembiewski Ingenieur",
    "wof:placetype":"venue"
},
  "geometry": {"coordinates":[13.4609727859,52.5278282166],"type":"Point"}
}