{
  "type": "Feature",
  "properties": {
    "iso:country":"DE",
    "sg:address":"Neue Str. 9",
    "sg:city":"L\u00fcbtheen",
    "sg:phone":"+49 38855/51314",
    "sg:postcode":"19249",
    "sg:province":"Mecklenburg-Vorpommern",
    "wof:name":"Richard Noreck",
    "wof:placetype":"venue"
},
  "geometry": {"coordinates":[11.080075,53.305244],"type":"Point"}
}