{
  "type": "Feature",
  "properties": {
    "iso:country":"DE",
    "sg:address":"Obermarkstr. 13",
    "sg:city":"Kobern-Gondorf",
    "sg:phone":"+49 2607/291",
    "sg:postcode":"56330",
    "sg:province":"Rheinland-Pfalz",
    "wof:name":"Gebr. Naunheim",
    "wof:placetype":"venue"
},
  "geometry": {"coordinates":[7.4579181671,50.3078842163],"type":"Point"}
}