{
  "type": "Feature",
  "properties": {
    "iso:country":"DE",
    "sg:address":"Postweg 43d",
    "sg:city":"Gro\u00dfefehn",
    "sg:phone":"+49 4943/4267",
    "sg:postcode":"26629",
    "sg:province":"Niedersachsen",
    "wof:name":"Veenhuis & Meyer Gmbh",
    "wof:placetype":"venue"
},
  "geometry": {"coordinates":[7.60393,53.394661],"type":"Point"}
}