{
  "type": "Feature",
  "properties": {
    "iso:country":"DE",
    "sg:address":"Schn\u00f6dhofweg 27",
    "sg:city":"Burgheim",
    "sg:phone":"+49 8432/1201",
    "sg:postcode":"86666",
    "sg:province":"Bayern",
    "wof:name":"Karl Mack",
    "wof:placetype":"venue"
},
  "geometry": {"coordinates":[11.006384,48.70649],"type":"Point"}
}