{
  "type": "Feature",
  "properties": {
    "iso:country":"DE",
    "sg:address":"Pfalzeler Str. 19",
    "sg:city":"Trier",
    "sg:phone":"+49 651/968050",
    "sg:postcode":"54293",
    "sg:province":"Rheinland-Pfalz",
    "wof:name":"H.-j. Wolff Steuerberater",
    "wof:placetype":"venue"
},
  "geometry": {"coordinates":[6.6898369789,49.7801895142],"type":"Point"}
}