{
  "type": "Feature",
  "properties": {
    "iso:country":"DE",
    "sg:address":"Rheingaustr. 8",
    "sg:city":"Hofheim",
    "sg:phone":"+49 6122/16574",
    "sg:postcode":"65719",
    "sg:province":"Hessen",
    "wof:name":"Meyer-gasters Bildverlag E. K.",
    "wof:placetype":"venue"
},
  "geometry": {"coordinates":[8.4406690598,50.0829086304],"type":"Point"}
}