{
  "type": "Feature",
  "properties": {
    "iso:country":"DE",
    "sg:address":"Bergheimer Str. 496",
    "sg:city":"Neuss",
    "sg:phone":"+49 2131/464162",
    "sg:postcode":"41466",
    "sg:province":"Nordrhein-Westfalen",
    "wof:name":"Hans Conrads Haus- Und Grundst\u00fccksverwaltung",
    "wof:placetype":"venue"
},
  "geometry": {"coordinates":[6.684858799,51.1692276001],"type":"Point"}
}