{
  "type": "Feature",
  "properties": {
    "iso:country":"DE",
    "sg:address":"Dieselstr. 12",
    "sg:city":"Gelsenkirchen",
    "sg:phone":"+49 209/970800",
    "sg:postcode":"45891",
    "sg:province":"Nordrhein-Westfalen",
    "wof:name":"Glg Grewer Lagerhaus Gmbh",
    "wof:placetype":"venue"
},
  "geometry": {"coordinates":[7.068638,51.544445],"type":"Point"}
}