{
  "type": "Feature",
  "properties": {
    "iso:country":"DE",
    "sg:address":"Am Sonderner Kopf",
    "sg:city":"Olpe",
    "sg:phone":"+49 2761/62520",
    "sg:postcode":"57462",
    "sg:province":"Nordrhein-Westfalen",
    "wof:name":"Biggesee-sondern Campingplatz",
    "wof:placetype":"venue"
},
  "geometry": {"coordinates":[7.856476,51.074364],"type":"Point"}
}