{
  "type": "Feature",
  "properties": {
    "iso:country":"DE",
    "sg:address":"Dorfweg 6",
    "sg:city":"Waldhufen",
    "sg:phone":"+49 3588/201335",
    "sg:postcode":"02906",
    "sg:province":"Sachsen",
    "wof:name":"Gfc Uwe Karau Gmbh",
    "wof:placetype":"venue"
},
  "geometry": {"coordinates":[14.8191757202,51.2559738159],"type":"Point"}
}