{
  "type": "Feature",
  "properties": {
    "iso:country":"DE",
    "sg:address":"K\u00f6nigstr. 72",
    "sg:city":"Rottenburg",
    "sg:phone":"+49 7472/6222",
    "sg:postcode":"72108",
    "sg:province":"Baden-W\u00fcrttemberg",
    "wof:name":"Meinrad Stehle",
    "wof:placetype":"venue"
},
  "geometry": {"coordinates":[8.9315061569,48.4739875793],"type":"Point"}
}