{
  "type": "Feature",
  "properties": {
    "iso:country":"DE",
    "sg:address":"Rolandstr. 3",
    "sg:city":"Bonn",
    "sg:phone":"+49 228/353061",
    "sg:postcode":"53179",
    "sg:province":"Nordrhein-Westfalen",
    "wof:name":"Kohli Chemie Handelsges. Mbh",
    "wof:placetype":"venue"
},
  "geometry": {"coordinates":[7.1725001335,50.6838874817],"type":"Point"}
}