{
  "type": "Feature",
  "properties": {
    "iso:country":"DE",
    "sg:address":"Bernhard-May-Str. 19",
    "sg:city":"Wiesbaden",
    "sg:phone":"+49 611/66658",
    "sg:postcode":"65203",
    "sg:province":"Hessen",
    "wof:name":"Gebr\u00fcder Dick Stein- Und Bildhauerei",
    "wof:placetype":"venue"
},
  "geometry": {"coordinates":[8.2476100922,50.047504425],"type":"Point"}
}