{
  "type": "Feature",
  "properties": {
    "iso:country":"DE",
    "sg:address":"Hauptstr. 18",
    "sg:city":"Tettenweis",
    "sg:phone":"+49 8534/277",
    "sg:postcode":"94167",
    "sg:province":"Bayern",
    "wof:name":"Eduard Kirschner",
    "wof:placetype":"venue"
},
  "geometry": {"coordinates":[13.269548,48.44265],"type":"Point"}
}