{
  "type": "Feature",
  "properties": {
    "iso:country":"DE",
    "sg:address":"Pr\u00e4ger B\u00f6den 2",
    "sg:city":"Todtnau",
    "sg:phone":"+49 7671/517",
    "sg:postcode":"79674",
    "sg:province":"Baden-W\u00fcrttemberg",
    "wof:name":"Berggasthaus",
    "wof:placetype":"venue"
},
  "geometry": {"coordinates":[7.9925498962,47.8171653748],"type":"Point"}
}