{
  "type": "Feature",
  "properties": {
    "iso:country":"DE",
    "sg:address":"Gartenstr. 39",
    "sg:city":"Bernkastel-Kues",
    "sg:phone":"+49 6531/95390",
    "sg:postcode":"54470",
    "sg:province":"Rheinland-Pfalz",
    "wof:name":"Waltrud Will-feld Steuerberaterin",
    "wof:placetype":"venue"
},
  "geometry": {"coordinates":[7.0666689873,49.9141731262],"type":"Point"}
}