{
  "type": "Feature",
  "properties": {
    "iso:country":"DE",
    "sg:address":"Oldesloer Str. 22",
    "sg:city":"Bad Segeberg",
    "sg:phone":"+49 4551/967005",
    "sg:postcode":"23795",
    "sg:province":"Schleswig-Holstein",
    "wof:name":"G. Str\u00fcver",
    "wof:placetype":"venue"
},
  "geometry": {"coordinates":[10.3106298447,53.9349632263],"type":"Point"}
}