{
  "type": "Feature",
  "properties": {
    "iso:country":"DE",
    "sg:address":"Gro\u00dfk\u00f6lnstr. 53",
    "sg:city":"Aachen",
    "sg:phone":"+49 241/28028",
    "sg:postcode":"52062",
    "sg:province":"Nordrhein-Westfalen",
    "wof:name":"Haselier Gmbh & Co. Kg",
    "wof:placetype":"venue"
},
  "geometry": {"coordinates":[6.0869898796,50.7776527405],"type":"Point"}
}