{
  "type": "Feature",
  "properties": {
    "iso:country":"DE",
    "sg:address":"Schmittgasse 62",
    "sg:city":"K\u00f6ln",
    "sg:phone":"+49 2203/87575",
    "sg:postcode":"51143",
    "sg:province":"Nordrhein-Westfalen",
    "wof:name":"Alexandra",
    "wof:placetype":"venue"
},
  "geometry": {"coordinates":[7.04565382,50.866481781],"type":"Point"}
}