{
  "type": "Feature",
  "properties": {
    "iso:country":"DE",
    "sg:address":"Maternusstr. 34",
    "sg:city":"K\u00f6ln",
    "sg:phone":"+49 221/353250",
    "sg:postcode":"50996",
    "sg:province":"Nordrhein-Westfalen",
    "wof:name":"G. Raabe",
    "wof:placetype":"venue"
},
  "geometry": {"coordinates":[6.9917011261,50.8918075562],"type":"Point"}
}