{
  "type": "Feature",
  "properties": {
    "iso:country":"DE",
    "sg:address":"Rauschwalder Str. 48a",
    "sg:city":"G\u00f6rlitz",
    "sg:postcode":"02826",
    "sg:province":"Sachsen",
    "wof:name":"Kerckhoff Meyer & Co. Gmbh",
    "wof:placetype":"venue"
},
  "geometry": {"coordinates":[14.9665803909,51.1520385742],"type":"Point"}
}