{
  "type": "Feature",
  "properties": {
    "iso:country":"DE",
    "sg:address":"Alter Postweg 223-233",
    "sg:city":"Bremen",
    "sg:phone":"+49 421/451094",
    "sg:postcode":"28207",
    "sg:province":"Bremen",
    "wof:name":"Olaf Siekmann",
    "wof:placetype":"venue"
},
  "geometry": {"coordinates":[8.8757066727,53.062953949],"type":"Point"}
}