{
  "type": "Feature",
  "properties": {
    "iso:country":"DE",
    "sg:address":"Ferrenbergstr. 24",
    "sg:city":"Bergisch Gladbach",
    "sg:phone":"+49 2202/1220",
    "sg:postcode":"51465",
    "sg:province":"Nordrhein-Westfalen",
    "wof:name":"Ev. Krankenhaus Ggmbh",
    "wof:placetype":"venue"
},
  "geometry": {"coordinates":[7.138864,50.989761],"type":"Point"}
}