{
  "type": "Feature",
  "properties": {
    "iso:country":"DE",
    "sg:address":"Ubierstr. 54",
    "sg:city":"Neuwied",
    "sg:phone":"+49 2631/974316",
    "sg:postcode":"56567",
    "sg:province":"Rheinland-Pfalz",
    "wof:name":"Volker Ecker Rechtsanwalt",
    "wof:placetype":"venue"
},
  "geometry": {"coordinates":[7.4511342049,50.447971344],"type":"Point"}
}