{
  "type": "Feature",
  "properties": {
    "iso:country":"DE",
    "sg:address":"Rauchstr. 9-11",
    "sg:city":"M\u00fcnchen",
    "sg:phone":"+49 89/99805100",
    "sg:postcode":"81679",
    "sg:province":"Bayern",
    "wof:name":"Helkon National Distribution Gmbh",
    "wof:placetype":"venue"
},
  "geometry": {"coordinates":[11.6041030884,48.1446876526],"type":"Point"}
}