{
  "type": "Feature",
  "properties": {
    "iso:country":"DE",
    "sg:address":"Hansastr. 61",
    "sg:city":"Dortmund",
    "sg:phone":"+49 231/9130630",
    "sg:postcode":"44137",
    "sg:province":"Nordrhein-Westfalen",
    "wof:name":"Aachener Bausparkasse Ag",
    "wof:placetype":"venue"
},
  "geometry": {"coordinates":[7.463652,51.513248],"type":"Point"}
}