{
  "type": "Feature",
  "properties": {
    "iso:country":"DE",
    "sg:address":"Augsburger Str. 9",
    "sg:city":"Bobingen",
    "sg:phone":"+49 8234/902738",
    "sg:postcode":"86399",
    "sg:province":"Bayern",
    "wof:name":"Marcus Fischer",
    "wof:placetype":"venue"
},
  "geometry": {"coordinates":[10.840202,48.278042],"type":"Point"}
}