{
  "type": "Feature",
  "properties": {
    "iso:country":"DE",
    "sg:address":"Elbinger Weg 3",
    "sg:city":"Welzheim",
    "sg:phone":"+49 7182/8583",
    "sg:postcode":"73642",
    "sg:province":"Baden-W\u00fcrttemberg",
    "wof:name":"Key Software Und Systeme Gmbh",
    "wof:placetype":"venue"
},
  "geometry": {"coordinates":[9.6257982254,48.8815994263],"type":"Point"}
}