{
  "type": "Feature",
  "properties": {
    "iso:country":"DE",
    "sg:address":"Darmst\u00e4dter Str. 7",
    "sg:city":"Darmstadt",
    "sg:phone":"+49 6151/372339",
    "sg:postcode":"64291",
    "sg:province":"Hessen",
    "wof:name":"Arheilger Stubb",
    "wof:placetype":"venue"
},
  "geometry": {"coordinates":[8.6565132141,49.9132194519],"type":"Point"}
}