{
  "type": "Feature",
  "properties": {
    "iso:country":"DE",
    "sg:address":"Seehofweg 10",
    "sg:city":"Lindenfels",
    "sg:phone":"+49 6255/3158",
    "sg:postcode":"64678",
    "sg:province":"Hessen",
    "wof:name":"Frank-j\u00fcrgen Pfeiffer Anlageberater",
    "wof:placetype":"venue"
},
  "geometry": {"coordinates":[8.7808885574,49.6779785156],"type":"Point"}
}