{
  "type": "Feature",
  "properties": {
    "iso:country":"DE",
    "sg:address":"Kolmergasse 30",
    "sg:city":"Greding",
    "sg:phone":"+49 8469/94020",
    "sg:postcode":"91171",
    "sg:province":"Bayern",
    "wof:name":"Frank Formenbau Gmbh",
    "wof:placetype":"venue"
},
  "geometry": {"coordinates":[11.304825,49.108257],"type":"Point"}
}