{
  "type": "Feature",
  "properties": {
    "iso:country":"DE",
    "sg:address":"Immenreich 11",
    "sg:city":"Gingen",
    "sg:phone":"+49 7162/3207",
    "sg:postcode":"73333",
    "sg:province":"Baden-W\u00fcrttemberg",
    "wof:name":"H. Janko Gmbh",
    "wof:placetype":"venue"
},
  "geometry": {"coordinates":[9.784207,48.65062],"type":"Point"}
}