{
  "type": "Feature",
  "properties": {
    "iso:country":"DE",
    "sg:address":"Volbedingstr. 2",
    "sg:city":"Leipzig",
    "sg:phone":"+49 341/6071272",
    "sg:postcode":"04357",
    "sg:province":"Sachsen",
    "wof:name":"Knofe-design",
    "wof:placetype":"venue"
},
  "geometry": {"coordinates":[12.4044446945,51.3633575439],"type":"Point"}
}