{
  "type": "Feature",
  "properties": {
    "iso:country":"DE",
    "sg:address":"Haus Bollheim",
    "sg:city":"Z\u00fclpich",
    "sg:phone":"+49 2252/5595",
    "sg:postcode":"53909",
    "sg:province":"Nordrhein-Westfalen",
    "wof:name":"Archiv Des Langenscher Familienverbandes E. V.",
    "wof:placetype":"venue"
},
  "geometry": {"coordinates":[6.711042,50.697598],"type":"Point"}
}