{
  "type": "Feature",
  "properties": {
    "iso:country":"DE",
    "sg:address":"Weissacher Str. 72",
    "sg:city":"Backnang",
    "sg:phone":"+49 7191/950961",
    "sg:postcode":"71522",
    "sg:province":"Baden-W\u00fcrttemberg",
    "wof:name":"Minimal",
    "wof:placetype":"venue"
},
  "geometry": {"coordinates":[9.4464483261,48.9368667603],"type":"Point"}
}