{
  "type": "Feature",
  "properties": {
    "iso:country":"DE",
    "sg:address":"Eiffestr. 596",
    "sg:city":"Hamburg",
    "sg:phone":"+49 40/21045100",
    "sg:postcode":"20537",
    "sg:province":"Hamburg",
    "wof:name":"Arbuma Holding Ag",
    "wof:placetype":"venue"
},
  "geometry": {"coordinates":[10.054088,53.551399],"type":"Point"}
}