{
  "type": "Feature",
  "properties": {
    "iso:country":"DE",
    "sg:address":"Randersacker Str. 54",
    "sg:city":"W\u00fcrzburg",
    "sg:phone":"+49 931/805295",
    "sg:postcode":"97070",
    "sg:province":"Bayern",
    "wof:name":"Mercedes-benz Finanz Gmbh",
    "wof:placetype":"venue"
},
  "geometry": {"coordinates":[9.936415,49.792793],"type":"Point"}
}