{
  "type": "Feature",
  "properties": {
    "iso:country":"DE",
    "sg:address":"Osnabr\u00fccker Str. 29",
    "sg:city":"Neuenkirchen-V\u00f6rden",
    "sg:phone":"+49 5495/279",
    "sg:postcode":"49434",
    "sg:province":"Niedersachsen",
    "wof:name":"Karl H. M\u00f6ller",
    "wof:placetype":"venue"
},
  "geometry": {"coordinates":[8.084171,52.474041],"type":"Point"}
}