{
  "type": "Feature",
  "properties": {
    "iso:country":"DE",
    "sg:address":"Residenzpark 5",
    "sg:city":"Raben Steinfeld",
    "sg:phone":"+49 3860/501877",
    "sg:postcode":"19065",
    "sg:province":"Mecklenburg-Vorpommern",
    "wof:name":"Kometh Assekuranzmakler Gmbh",
    "wof:placetype":"venue"
},
  "geometry": {"coordinates":[11.5016336441,53.5993843079],"type":"Point"}
}