{
  "type": "Feature",
  "properties": {
    "iso:country":"DE",
    "sg:address":"Bruchstr. 1",
    "sg:city":"Wetter",
    "sg:phone":"+49 2335/5218",
    "sg:postcode":"58300",
    "sg:province":"Nordrhein-Westfalen",
    "wof:name":"I. Pavlou",
    "wof:placetype":"venue"
},
  "geometry": {"coordinates":[7.3878488541,51.3866615295],"type":"Point"}
}