{
  "type": "Feature",
  "properties": {
    "iso:country":"DE",
    "sg:address":"Philipp-Reis-Str. 14",
    "sg:city":"Niederau",
    "sg:phone":"+49 4961/8790880",
    "sg:postcode":"61130",
    "sg:province":"Hessen",
    "wof:name":"Erich K. Schmitter Pr\u00c4sentionstechnik Gmbh",
    "wof:placetype":"venue"
},
  "geometry": {"coordinates":[-89.057388,42.316059],"type":"Point"}
}