{
  "type": "Feature",
  "properties": {
    "iso:country":"DE",
    "sg:address":"Nikolaistrasse 19-21",
    "sg:city":"Leipzig",
    "sg:phone":"+49 341/9137610",
    "sg:postcode":"04109",
    "sg:province":"Sachsen",
    "wof:name":"Opus61",
    "wof:placetype":"venue"
},
  "geometry": {"coordinates":[12.377844,51.341049],"type":"Point"}
}