{
  "type": "Feature",
  "properties": {
    "iso:country":"DE",
    "sg:address":"Sportplatzweg 6",
    "sg:city":"Hinterzarten",
    "sg:phone":"+49 7652/91170",
    "sg:postcode":"79856",
    "sg:province":"Baden-W\u00fcrttemberg",
    "wof:name":"Rudi Metzler Gmbh",
    "wof:placetype":"venue"
},
  "geometry": {"coordinates":[8.1092166901,47.9052848816],"type":"Point"}
}