{
  "type": "Feature",
  "properties": {
    "iso:country":"DE",
    "sg:address":"Schmalenbecker Str. 24",
    "sg:city":"Grasberg",
    "sg:phone":"+49 4208/1816",
    "sg:postcode":"28879",
    "sg:province":"Niedersachsen",
    "wof:name":"Herbert Marks",
    "wof:placetype":"venue"
},
  "geometry": {"coordinates":[9.06572,53.15226],"type":"Point"}
}