{
  "type": "Feature",
  "properties": {
    "iso:country":"DE",
    "sg:address":"Zirmenweg 11",
    "sg:city":"Pfronten",
    "sg:postcode":"87459",
    "sg:province":"Bayern",
    "wof:name":"Skischule Pfronten Ostallg\u00e4u & Co. Kg",
    "wof:placetype":"venue"
},
  "geometry": {"coordinates":[10.5699958801,47.5666007996],"type":"Point"}
}