{
  "type": "Feature",
  "properties": {
    "iso:country":"DE",
    "sg:address":"Robert-Bosch-Str. 1",
    "sg:city":"Northeim",
    "sg:postcode":"37154",
    "sg:province":"Niedersachsen",
    "wof:name":"Energie- Und Nachrichten- Anlagen Barnkothe Gmbh",
    "wof:placetype":"venue"
},
  "geometry": {"coordinates":[9.9837017059,51.6881523132],"type":"Point"}
}