{
  "type": "Feature",
  "properties": {
    "iso:country":"DE",
    "sg:address":"Friedrich-Wilhelm-Str 12",
    "sg:city":"Duisburg",
    "sg:phone":"+49 203/50390",
    "sg:postcode":"47051",
    "sg:province":"Nordrhein-Westfalen",
    "wof:name":"Sparkassen Informatik Gmbh & Co Kg",
    "wof:placetype":"venue"
},
  "geometry": {"coordinates":[6.7617840767,51.4314842224],"type":"Point"}
}