{
  "type": "Feature",
  "properties": {
    "iso:country":"DE",
    "sg:address":"Alpenveilchenstr. 42",
    "sg:city":"M\u00fcnchen",
    "sg:phone":"+49 89/5803476",
    "sg:postcode":"80689",
    "sg:province":"Bayern",
    "wof:name":"Alten- Und Servicezentrum Kleinhadern-blumenau",
    "wof:placetype":"venue"
},
  "geometry": {"coordinates":[11.4897,48.128445],"type":"Point"}
}