{
  "type": "Feature",
  "properties": {
    "iso:country":"DE",
    "sg:address":"Carl-Bosch-Str. 213",
    "sg:city":"Ludwigshafen",
    "sg:phone":"+49 621/699310",
    "sg:postcode":"67063",
    "sg:province":"Rheinland-Pfalz",
    "wof:name":"Zoo-teske-gmbh",
    "wof:placetype":"venue"
},
  "geometry": {"coordinates":[8.419428,49.497711],"type":"Point"}
}