{
  "type": "Feature",
  "properties": {
    "iso:country":"DE",
    "sg:address":"Lilienstr. 17",
    "sg:city":"Uhingen",
    "sg:phone":"+49 7161/38111",
    "sg:postcode":"73066",
    "sg:province":"Baden-W\u00fcrttemberg",
    "wof:name":"A. Maier",
    "wof:placetype":"venue"
},
  "geometry": {"coordinates":[9.5862798691,48.7234687805],"type":"Point"}
}