{
  "type": "Feature",
  "properties": {
    "iso:country":"DE",
    "sg:address":"Bl\u00fccherstr. 24",
    "sg:city":"Hof",
    "sg:phone":"+49 9281/93241",
    "sg:postcode":"95030",
    "sg:province":"Bayern",
    "wof:name":"Eduard Schuberth",
    "wof:placetype":"venue"
},
  "geometry": {"coordinates":[11.904966,50.310226],"type":"Point"}
}