{
  "type": "Feature",
  "properties": {
    "iso:country":"DE",
    "sg:address":"Felsbergstr. 3",
    "sg:city":"Lautertal",
    "sg:phone":"+49 6254/37394",
    "sg:postcode":"64686",
    "sg:province":"Hessen",
    "wof:name":"Molkereiprodukte Frischdienst",
    "wof:placetype":"venue"
},
  "geometry": {"coordinates":[8.69181633,49.7159576416],"type":"Point"}
}