{
  "type": "Feature",
  "properties": {
    "iso:country":"DE",
    "sg:address":"Bremer Str. 12",
    "sg:city":"Bohmte",
    "sg:phone":"+49 5471/4040",
    "sg:postcode":"49163",
    "sg:province":"Niedersachsen",
    "wof:name":"L\u00fcken-schencking Inh. U. Bockhorn",
    "wof:placetype":"venue"
},
  "geometry": {"coordinates":[8.3093338013,52.3615760803],"type":"Point"}
}