{
  "type": "Feature",
  "properties": {
    "iso:country":"DE",
    "sg:address":"Lindenstr. 25 b",
    "sg:city":"Bielefeld",
    "sg:phone":"+49 521/48386",
    "sg:postcode":"33649",
    "sg:province":"Nordrhein-Westfalen",
    "wof:name":"Wilhelm W\u00f6rmann",
    "wof:placetype":"venue"
},
  "geometry": {"coordinates":[8.4567012787,51.9704284668],"type":"Point"}
}