{
  "type": "Feature",
  "properties": {
    "iso:country":"DE",
    "sg:address":"Rudolf-Diesel-Str 3",
    "sg:city":"Bakum",
    "sg:phone":"+49 4446/96200",
    "sg:postcode":"49456",
    "sg:province":"Niedersachsen",
    "wof:name":"S\u00fcdbeck Nutzfahrzeuge Gmbh",
    "wof:placetype":"venue"
},
  "geometry": {"coordinates":[8.1757678986,52.7265434265],"type":"Point"}
}