{
  "type": "Feature",
  "properties": {
    "iso:country":"DE",
    "sg:address":"Industriestr. 30",
    "sg:city":"Bruchsal",
    "sg:phone":"+49 7251/97170",
    "sg:postcode":"76646",
    "sg:province":"Baden-W\u00fcrttemberg",
    "wof:name":"Stork Medien U. Verlag Kg",
    "wof:placetype":"venue"
},
  "geometry": {"coordinates":[8.57013,49.12743],"type":"Point"}
}