{
  "type": "Feature",
  "properties": {
    "iso:country":"DE",
    "sg:address":"Sperlingsweg 19",
    "sg:city":"Saarlouis",
    "sg:phone":"+49 6831/43949",
    "sg:postcode":"66740",
    "sg:province":"Saarland",
    "wof:name":"Erster Squash Club Saarlouis E.v.",
    "wof:placetype":"venue"
},
  "geometry": {"coordinates":[6.7380728722,49.307636261],"type":"Point"}
}