{
  "type": "Feature",
  "properties": {
    "iso:country":"DE",
    "sg:address":"Vogteiweg 15",
    "sg:city":"Hamburg",
    "sg:phone":"+49 40/2991817",
    "sg:postcode":"22083",
    "sg:province":"Hamburg",
    "wof:name":"Schwerpunkt Ronald Loeffler",
    "wof:placetype":"venue"
},
  "geometry": {"coordinates":[10.032559,53.574188],"type":"Point"}
}