{
  "type": "Feature",
  "properties": {
    "iso:country":"DE",
    "sg:address":"Hauptstr. 8",
    "sg:city":"Engen",
    "sg:phone":"+49 7733/7333",
    "sg:postcode":"78234",
    "sg:province":"Baden-W\u00fcrttemberg",
    "wof:name":"Norma Lebensmittel- Handelsgesellschaft Mbh",
    "wof:placetype":"venue"
},
  "geometry": {"coordinates":[8.7705907822,47.8519935608],"type":"Point"}
}