{
  "type": "Feature",
  "properties": {
    "iso:country":"DE",
    "sg:address":"Kruppstr. 41-47",
    "sg:city":"W\u00fclfrath",
    "sg:phone":"+49 4920/5892010",
    "sg:postcode":"42489",
    "sg:province":"Nordrhein-Westfalen",
    "wof:name":"Titania Fabrik Gmbh",
    "wof:placetype":"venue"
},
  "geometry": {"coordinates":[7.0438370705,51.2878417969],"type":"Point"}
}