{
  "type": "Feature",
  "properties": {
    "iso:country":"DE",
    "sg:address":"Ro\u00dflach",
    "sg:city":"Kronach",
    "sg:phone":"+49 9261/3928",
    "sg:postcode":"96317",
    "sg:province":"Bayern",
    "wof:name":"Berghof Ro\u00dflach",
    "wof:placetype":"venue"
},
  "geometry": {"coordinates":[11.3613767624,50.2638244629],"type":"Point"}
}