{
  "type": "Feature",
  "properties": {
    "iso:country":"DE",
    "sg:address":"Donaustr. 13",
    "sg:city":"Hengersberg",
    "sg:phone":"+49 9901/894",
    "sg:postcode":"94491",
    "sg:province":"Bayern",
    "wof:name":"Dkm Schwarz Und Bauer Gmbh",
    "wof:placetype":"venue"
},
  "geometry": {"coordinates":[13.048347,48.766071],"type":"Point"}
}