{
  "type": "Feature",
  "properties": {
    "iso:country":"DE",
    "sg:address":"F\u00f6hrenstr. 49",
    "sg:city":"Tuttlingen",
    "sg:postcode":"78532",
    "sg:province":"Baden-W\u00fcrttemberg",
    "wof:name":"M. M\u00fcller",
    "wof:placetype":"venue"
},
  "geometry": {"coordinates":[8.845749,47.976784],"type":"Point"}
}