{
  "type": "Feature",
  "properties": {
    "iso:country":"DE",
    "sg:address":"Mommstr. 15",
    "sg:city":"St. Wendel",
    "sg:phone":"+49 6851/939540",
    "sg:postcode":"66606",
    "sg:province":"Saarland",
    "wof:name":"Deutsche Post Ag",
    "wof:placetype":"venue"
},
  "geometry": {"coordinates":[7.1658902168,49.4661216736],"type":"Point"}
}