{
  "type": "Feature",
  "properties": {
    "iso:country":"DE",
    "sg:address":"Alte Stuttgarter Str. 11",
    "sg:city":"Magstadt",
    "sg:phone":"+49 7159/94780",
    "sg:postcode":"71106",
    "sg:province":"Baden-W\u00fcrttemberg",
    "wof:name":"Oppenl\u00e4nder",
    "wof:placetype":"venue"
},
  "geometry": {"coordinates":[8.9649915695,48.7423324585],"type":"Point"}
}