{
  "type": "Feature",
  "properties": {
    "iso:country":"DE",
    "sg:address":"Schweriner Str. 45",
    "sg:city":"Schwerin",
    "sg:phone":"+49 385/611051",
    "sg:postcode":"19061",
    "sg:province":"Mecklenburg-Vorpommern",
    "wof:name":"J\u00fcrgen Braun Bauhandwerksbetrieb",
    "wof:placetype":"venue"
},
  "geometry": {"coordinates":[11.399562,53.586124],"type":"Point"}
}