{
  "type": "Feature",
  "properties": {
    "iso:country":"DE",
    "sg:address":"Walder Str. 7",
    "sg:city":"Hilden",
    "sg:phone":"+49 2103/8209",
    "sg:postcode":"40724",
    "sg:province":"Nordrhein-Westfalen",
    "wof:name":"Jansen Fleischwaren Gmbh",
    "wof:placetype":"venue"
},
  "geometry": {"coordinates":[6.9416651726,51.1692657471],"type":"Point"}
}