{
  "type": "Feature",
  "properties": {
    "iso:country":"DE",
    "sg:address":"Hasselbusch 7",
    "sg:city":"Bargteheide",
    "sg:phone":"+49 4532/21417",
    "sg:postcode":"22941",
    "sg:province":"Schleswig-Holstein",
    "wof:name":"Schabbel-mader Und Zeitnitz Garten- Und",
    "wof:placetype":"venue"
},
  "geometry": {"coordinates":[10.250953,53.728222],"type":"Point"}
}