{
  "type": "Feature",
  "properties": {
    "iso:country":"DE",
    "sg:address":"Bayernallee 2",
    "sg:city":"Berlin",
    "sg:phone":"+49 30/3059943",
    "sg:postcode":"14052",
    "sg:province":"Berlin",
    "wof:name":"J\u00fcrgen Pally",
    "wof:placetype":"venue"
},
  "geometry": {"coordinates":[13.2673091888,52.5106582642],"type":"Point"}
}