{
  "type": "Feature",
  "properties": {
    "iso:country":"DE",
    "sg:address":"Rudolfstr. 97",
    "sg:city":"Stolberg",
    "sg:phone":"+49 2402/15600",
    "sg:postcode":"52223",
    "sg:province":"Nordrhein-Westfalen",
    "wof:name":"Arka Auto-wasch Gmbh",
    "wof:placetype":"venue"
},
  "geometry": {"coordinates":[6.2179350853,50.7355308533],"type":"Point"}
}