{
  "type": "Feature",
  "properties": {
    "iso:country":"DE",
    "sg:address":"Tailfinger Str. 25",
    "sg:city":"Stuttgart",
    "sg:phone":"+49 711/711647",
    "sg:postcode":"70567",
    "sg:province":"Baden-W\u00fcrttemberg",
    "wof:name":"Peter-michael Belz Ingenieur",
    "wof:placetype":"venue"
},
  "geometry": {"coordinates":[9.1473798752,48.733631134],"type":"Point"}
}