{
  "type": "Feature",
  "properties": {
    "iso:country":"DE",
    "sg:address":"Lindnerstr. 163",
    "sg:city":"Oberhausen",
    "sg:phone":"+49 208/654477",
    "sg:postcode":"46149",
    "sg:province":"Nordrhein-Westfalen",
    "wof:name":"W\u00fcrttembergische Versicherung Ag",
    "wof:placetype":"venue"
},
  "geometry": {"coordinates":[6.8572249413,51.4949607849],"type":"Point"}
}