{
  "type": "Feature",
  "properties": {
    "iso:country":"DE",
    "sg:address":"Hindenburgstr. 26",
    "sg:city":"Schwabach",
    "sg:phone":"+49 9122/4926",
    "sg:postcode":"91126",
    "sg:province":"Bayern",
    "wof:name":"Ludwig K\u00f6rber",
    "wof:placetype":"venue"
},
  "geometry": {"coordinates":[11.0217552185,49.3260536194],"type":"Point"}
}