{
  "type": "Feature",
  "properties": {
    "iso:country":"DE",
    "sg:address":"Brookdamm 36",
    "sg:city":"Ganderkesee",
    "sg:phone":"+49 4222/1501",
    "sg:postcode":"27777",
    "sg:province":"Niedersachsen",
    "wof:name":"R. Oltmanns Gmbh",
    "wof:placetype":"venue"
},
  "geometry": {"coordinates":[8.555487,53.034542],"type":"Point"}
}