{
  "type": "Feature",
  "properties": {
    "iso:country":"DE",
    "sg:address":"Dudweiler Stra\u00dfe 49",
    "sg:city":"Saarbr\u00fccken",
    "sg:phone":"+49 681",
    "sg:postcode":"66111",
    "sg:province":"Saarland",
    "wof:name":"Fahrschule Gerd Saar - Saarbr\u00fccken",
    "wof:placetype":"venue"
},
  "geometry": {"coordinates":[6.9974598885,49.2376022339],"type":"Point"}
}