{
  "type": "Feature",
  "properties": {
    "iso:country":"DE",
    "sg:address":"Im Schlot 1",
    "sg:city":"M\u00f6ckm\u00fchl",
    "sg:phone":"+49 6298",
    "sg:postcode":"74219",
    "sg:province":"Baden-W\u00fcrttemberg",
    "wof:name":"Onair",
    "wof:placetype":"venue"
},
  "geometry": {"coordinates":[9.349643,49.323112],"type":"Point"}
}