{
  "type": "Feature",
  "properties": {
    "iso:country":"DE",
    "sg:address":"August-Bebel-Str. 30",
    "sg:city":"Naunhof",
    "sg:phone":"+49 34293/33306",
    "sg:postcode":"04683",
    "sg:province":"Sachsen",
    "wof:name":"B\u00fcrowelt 2000 - B\u00fcroplanung Und Einrichtung",
    "wof:placetype":"venue"
},
  "geometry": {"coordinates":[12.5947380066,51.2712669373],"type":"Point"}
}