{
  "type": "Feature",
  "properties": {
    "iso:country":"DE",
    "sg:address":"Dantestr. 27",
    "sg:city":"M\u00fcnchen",
    "sg:phone":"+49 89/1575567",
    "sg:postcode":"80637",
    "sg:province":"Bayern",
    "wof:name":"Cafe Melange",
    "wof:placetype":"venue"
},
  "geometry": {"coordinates":[11.526708,48.167801],"type":"Point"}
}