{
  "type": "Feature",
  "properties": {
    "iso:country":"DE",
    "sg:address":"Bauhof 11",
    "sg:city":"R\u00f6tz",
    "sg:phone":"+49 9976/304",
    "sg:postcode":"92444",
    "sg:province":"Bayern",
    "wof:name":"Gastst\u00e4tte Johann Dirscherl",
    "wof:placetype":"venue"
},
  "geometry": {"coordinates":[12.5241708755,49.3389701843],"type":"Point"}
}