{
  "type": "Feature",
  "properties": {
    "iso:country":"DE",
    "sg:address":"Citypassage",
    "sg:city":"Memmingen",
    "sg:phone":"+49 8331/495533",
    "sg:postcode":"87700",
    "sg:province":"Bayern",
    "wof:name":"W. Kroll",
    "wof:placetype":"venue"
},
  "geometry": {"coordinates":[10.18151474,47.9846763611],"type":"Point"}
}