{
  "type": "Feature",
  "properties": {
    "iso:country":"DE",
    "sg:address":"Am Ohlenberg 35-37",
    "sg:city":"Erzhausen",
    "sg:phone":"+49 6150/96740",
    "sg:postcode":"64390",
    "sg:province":"Hessen",
    "wof:name":"Geppert-r\u00fchrtechnik Gmbh",
    "wof:placetype":"venue"
},
  "geometry": {"coordinates":[8.6434612274,49.9448242188],"type":"Point"}
}