{
  "type": "Feature",
  "properties": {
    "iso:country":"DE",
    "sg:address":"Rolandstr. 30",
    "sg:city":"D\u00fcsseldorf",
    "sg:phone":"+49 211/4380367",
    "sg:postcode":"40476",
    "sg:province":"Nordrhein-Westfalen",
    "wof:name":"W. Schott",
    "wof:placetype":"venue"
},
  "geometry": {"coordinates":[6.7753520012,51.2449913025],"type":"Point"}
}