{
  "type": "Feature",
  "properties": {
    "iso:country":"DE",
    "sg:address":"Romsch\u00fctz 1",
    "sg:city":"G\u00f6hren",
    "sg:phone":"+49 3447/505838",
    "sg:postcode":"04603",
    "sg:province":"Th\u00fcringen",
    "wof:name":"M. H. M\u00f6bel-collection Vertriebs Gmbh",
    "wof:placetype":"venue"
},
  "geometry": {"coordinates":[12.46714,50.974129],"type":"Point"}
}