{
  "type": "Feature",
  "properties": {
    "iso:country":"DE",
    "sg:address":"Haydnstr. 54",
    "sg:city":"D\u00fcsseldorf",
    "sg:phone":"+49 211/718853",
    "sg:postcode":"40593",
    "sg:province":"Nordrhein-Westfalen",
    "wof:name":"Lutz W. Braune Architekt",
    "wof:placetype":"venue"
},
  "geometry": {"coordinates":[6.874134,51.155666],"type":"Point"}
}