{
  "type": "Feature",
  "properties": {
    "iso:country":"DE",
    "sg:address":"\u00d6tigheimer Weg 59",
    "sg:city":"Rastatt",
    "sg:phone":"+49 7222/22244",
    "sg:postcode":"76437",
    "sg:province":"Baden-W\u00fcrttemberg",
    "wof:name":"Margot M\u00f6hrle",
    "wof:placetype":"venue"
},
  "geometry": {"coordinates":[8.219671,48.874065],"type":"Point"}
}