{
  "type": "Feature",
  "properties": {
    "iso:country":"DE",
    "sg:address":"Am Markt 9",
    "sg:city":"Kerpen",
    "sg:phone":"+49 2237/972126",
    "sg:postcode":"50169",
    "sg:province":"Nordrhein-Westfalen",
    "wof:name":"Uvm Detlef Schumacher E. K.",
    "wof:placetype":"venue"
},
  "geometry": {"coordinates":[6.7538809776,50.8600082397],"type":"Point"}
}