{
  "type": "Feature",
  "properties": {
    "iso:country":"DE",
    "sg:address":"Grenzh\u00f6fer Str. 38",
    "sg:city":"Eppelheim",
    "sg:phone":"+49 6221/766644",
    "sg:postcode":"69214",
    "sg:province":"Baden-W\u00fcrttemberg",
    "wof:name":"Hannelore Schuhmacher",
    "wof:placetype":"venue"
},
  "geometry": {"coordinates":[8.628857,49.401604],"type":"Point"}
}