{
  "type": "Feature",
  "properties": {
    "iso:country":"DE",
    "sg:address":"Ottenser Hauptstr. 34",
    "sg:city":"Hamburg",
    "sg:phone":"+49 40/397138",
    "sg:postcode":"22765",
    "sg:province":"Hamburg",
    "wof:name":"China Restaurant Han Kong",
    "wof:placetype":"venue"
},
  "geometry": {"coordinates":[9.9290800095,53.5521430969],"type":"Point"}
}