{
  "type": "Feature",
  "properties": {
    "iso:country":"DE",
    "sg:address":"Havelstr 9",
    "sg:city":"Darmstadt",
    "sg:phone":"+49 6151/3800",
    "sg:postcode":"64295",
    "sg:province":"Hessen",
    "wof:name":"Hoppenstedt Firmeninformationen Gmbh",
    "wof:placetype":"venue"
},
  "geometry": {"coordinates":[8.637049,49.869331],"type":"Point"}
}