{
  "type": "Feature",
  "properties": {
    "iso:country":"DE",
    "sg:address":"Feldstr. 4",
    "sg:city":"Quickborn",
    "sg:phone":"+49 4106/2268",
    "sg:postcode":"25451",
    "sg:province":"Schleswig-Holstein",
    "wof:name":"Knickrehm Gmbh",
    "wof:placetype":"venue"
},
  "geometry": {"coordinates":[9.8931941986,53.7363586426],"type":"Point"}
}