{
  "type": "Feature",
  "properties": {
    "iso:country":"DE",
    "sg:address":"Mittelb\u00fcgweg 5",
    "sg:city":"Schwaig",
    "sg:phone":"+49 911/505931",
    "sg:postcode":"90571",
    "sg:province":"Bayern",
    "wof:name":"Konrad Deuerlein",
    "wof:placetype":"venue"
},
  "geometry": {"coordinates":[11.198796,49.47411],"type":"Point"}
}