{
  "type": "Feature",
  "properties": {
    "iso:country":"DE",
    "sg:address":"Lippborger Str. 75",
    "sg:city":"Beckum",
    "sg:phone":"+49 2521/3331",
    "sg:postcode":"59269",
    "sg:province":"Nordrhein-Westfalen",
    "wof:name":"German Honeck Architekt",
    "wof:placetype":"venue"
},
  "geometry": {"coordinates":[8.04622,51.749535],"type":"Point"}
}