{
  "type": "Feature",
  "properties": {
    "iso:country":"DE",
    "sg:address":"Hans-Sachs-Str.",
    "sg:city":"Rodgau",
    "sg:phone":"+49 6106/14700",
    "sg:postcode":"63110",
    "sg:province":"Hessen",
    "wof:name":"Alexis Zorbas",
    "wof:placetype":"venue"
},
  "geometry": {"coordinates":[8.8785152435,50.0366096497],"type":"Point"}
}