{
  "type": "Feature",
  "properties": {
    "iso:country":"DE",
    "sg:address":"Brunnsteinweg 1",
    "sg:city":"Aschau",
    "sg:phone":"+49 8052/1067",
    "sg:postcode":"83229",
    "sg:province":"Bayern",
    "wof:name":"Brigitte L\u00f6ffler",
    "wof:placetype":"venue"
},
  "geometry": {"coordinates":[12.2604093552,47.6834716797],"type":"Point"}
}