{
  "type": "Feature",
  "properties": {
    "iso:country":"DE",
    "sg:address":"Meisenweg 23",
    "sg:city":"Halberstadt",
    "sg:phone":"+49 3941/27159",
    "sg:postcode":"38820",
    "sg:province":"Sachsen-Anhalt",
    "wof:name":"Friedrich Hildebrandt",
    "wof:placetype":"venue"
},
  "geometry": {"coordinates":[11.0155763626,51.9098243713],"type":"Point"}
}