{
  "type": "Feature",
  "properties": {
    "iso:country":"DE",
    "sg:address":"Salinenstr. 76",
    "sg:city":"Bad Kreuznach",
    "sg:phone":"+49 671/27250",
    "sg:postcode":"55543",
    "sg:province":"Rheinland-Pfalz",
    "wof:name":"Johanna Kollaritsch Krankengymnastin",
    "wof:placetype":"venue"
},
  "geometry": {"coordinates":[7.854454,49.837891],"type":"Point"}
}