{
  "type": "Feature",
  "properties": {
    "iso:country":"DE",
    "sg:address":"Johannes-Eberlin-Str. 40",
    "sg:city":"Leutershausen",
    "sg:postcode":"91578",
    "sg:province":"Bayern",
    "wof:name":"Architekturb\u00fcro Herbert Buchholz Platz\u00f6der",
    "wof:placetype":"venue"
},
  "geometry": {"coordinates":[10.419713974,49.2949447632],"type":"Point"}
}