{
  "type": "Feature",
  "properties": {
    "iso:country":"DE",
    "sg:address":"Gebersheimer Weg 62",
    "sg:city":"Ditzingen",
    "sg:phone":"+49 7152/53429",
    "sg:postcode":"71254",
    "sg:province":"Baden-W\u00fcrttemberg",
    "wof:name":"J. Amberg",
    "wof:placetype":"venue"
},
  "geometry": {"coordinates":[8.9811553955,48.8499298096],"type":"Point"}
}