{
  "type": "Feature",
  "properties": {
    "iso:country":"DE",
    "sg:address":"H\u00f6ferstr. 7A",
    "sg:city":"Reichenbach",
    "sg:phone":"+49 3765/63874",
    "sg:postcode":"08468",
    "sg:province":"Sachsen",
    "wof:name":"A. K\u00f6hler",
    "wof:placetype":"venue"
},
  "geometry": {"coordinates":[12.3017129898,50.6259155273],"type":"Point"}
}