{
  "type": "Feature",
  "properties": {
    "iso:country":"DE",
    "sg:address":"Ettlinger-Tor-Platz 2",
    "sg:city":"Karlsruhe",
    "sg:postcode":"76137",
    "sg:province":"Baden-W\u00fcrttemberg",
    "wof:name":"Oberpostdirektion Bibliothek",
    "wof:placetype":"venue"
},
  "geometry": {"coordinates":[8.40377,49.005375],"type":"Point"}
}