{
  "type": "Feature",
  "properties": {
    "iso:country":"DE",
    "sg:address":"Am Hauptbahnhof 10",
    "sg:city":"Korbach",
    "sg:phone":"+49 5631/1660",
    "sg:postcode":"34497",
    "sg:province":"Hessen",
    "wof:name":"Herbert G\u00f6bel",
    "wof:placetype":"venue"
},
  "geometry": {"coordinates":[8.872915,51.278557],"type":"Point"}
}