{
  "type": "Feature",
  "properties": {
    "iso:country":"DE",
    "sg:address":"In den Birken 30",
    "sg:city":"Stelzenberg",
    "sg:phone":"+49 6306/7223",
    "sg:postcode":"67705",
    "sg:province":"Rheinland-Pfalz",
    "wof:name":"Petra Korotschenko",
    "wof:placetype":"venue"
},
  "geometry": {"coordinates":[7.7410378456,49.3765678406],"type":"Point"}
}