{
  "type": "Feature",
  "properties": {
    "iso:country":"DE",
    "sg:address":"Sayntalstr.",
    "sg:city":"Mogendorf",
    "sg:phone":"+49 2623/5850",
    "sg:postcode":"56424",
    "sg:province":"Rheinland-Pfalz",
    "wof:name":"Waldklause",
    "wof:placetype":"venue"
},
  "geometry": {"coordinates":[7.7578802109,50.4942092896],"type":"Point"}
}