{
  "type": "Feature",
  "properties": {
    "iso:country":"DE",
    "sg:address":"Georg-Blank-Str 23",
    "sg:city":"Berlin",
    "sg:phone":"+49 30/4213834",
    "sg:postcode":"10409",
    "sg:province":"Berlin",
    "wof:name":"Druckerei Schneider",
    "wof:placetype":"venue"
},
  "geometry": {"coordinates":[13.432217,52.549076],"type":"Point"}
}