{
  "type": "Feature",
  "properties": {
    "iso:country":"DE",
    "sg:address":"Boschstr 1a",
    "sg:city":"Speyer",
    "sg:phone":"+49 6232/31430",
    "sg:postcode":"67346",
    "sg:province":"Rheinland-Pfalz",
    "wof:name":"Gfi Gesellschaft F\u00fcr Feuerschutz Und Installationen Mbh",
    "wof:placetype":"venue"
},
  "geometry": {"coordinates":[8.4214143753,49.3420257568],"type":"Point"}
}