{
  "type": "Feature",
  "properties": {
    "iso:country":"DE",
    "sg:address":"Leipziger Str. 44",
    "sg:city":"Taucha",
    "sg:phone":"+49 34298/65471",
    "sg:postcode":"04425",
    "sg:province":"Sachsen",
    "wof:name":"Studio 80",
    "wof:placetype":"venue"
},
  "geometry": {"coordinates":[12.4963331223,51.380657196],"type":"Point"}
}