{
  "type": "Feature",
  "properties": {
    "iso:country":"DE",
    "sg:address":"Steinstr. 9",
    "sg:city":"M\u00fcnchen",
    "sg:phone":"+49 89/485349",
    "sg:postcode":"81667",
    "sg:province":"Bayern",
    "wof:name":"Restaurant Taverna Italiana",
    "wof:placetype":"venue"
},
  "geometry": {"coordinates":[11.5964174271,48.1337356567],"type":"Point"}
}