{
  "type": "Feature",
  "properties": {
    "iso:country":"DE",
    "sg:address":"Mainstr. 47",
    "sg:city":"Kelsterbach",
    "sg:phone":"+49 6107/5716",
    "sg:postcode":"65451",
    "sg:province":"Hessen",
    "wof:name":"Heinrich Und Norbert M\u00f6ser Ohg",
    "wof:placetype":"venue"
},
  "geometry": {"coordinates":[8.5282945633,50.0695838928],"type":"Point"}
}