{
  "type": "Feature",
  "properties": {
    "iso:country":"DE",
    "sg:address":"Herscheider Landstr. 51",
    "sg:city":"L\u00fcdenscheid",
    "sg:phone":"+49 2351/40287",
    "sg:postcode":"58511",
    "sg:province":"Nordrhein-Westfalen",
    "wof:name":"Dr. Med. Hartmut Gehlhar Arzt F\u00fcr Allgemeinmedizin",
    "wof:placetype":"venue"
},
  "geometry": {"coordinates":[7.6512231827,51.2098846436],"type":"Point"}
}