{
  "type": "Feature",
  "properties": {
    "iso:country":"DE",
    "sg:address":"Heide 29",
    "sg:city":"Gie\u00dfen",
    "sg:phone":"+49 641/2636",
    "sg:postcode":"35398",
    "sg:province":"Hessen",
    "wof:name":"Thomas Trautwein",
    "wof:placetype":"venue"
},
  "geometry": {"coordinates":[8.6460542679,50.5543632507],"type":"Point"}
}