{
  "type": "Feature",
  "properties": {
    "iso:country":"DE",
    "sg:address":"Am Stau 3",
    "sg:city":"L\u00fcbeck",
    "sg:phone":"+49 4945/1393107",
    "sg:postcode":"23568",
    "sg:province":"Schleswig-Holstein",
    "wof:name":"M\u00dcller Busbau",
    "wof:placetype":"venue"
},
  "geometry": {"coordinates":[10.766371,53.897511],"type":"Point"}
}