{
  "type": "Feature",
  "properties": {
    "iso:country":"DE",
    "sg:address":"Brehnaer Str. 15",
    "sg:city":"Landsberg",
    "sg:phone":"+49 34602/21354",
    "sg:postcode":"06188",
    "sg:province":"Sachsen-Anhalt",
    "wof:name":"Bausior Stra\u00dfenbau-produkte Gmbh",
    "wof:placetype":"venue"
},
  "geometry": {"coordinates":[12.1704521179,51.5384902954],"type":"Point"}
}