{
  "type": "Feature",
  "properties": {
    "iso:country":"DE",
    "sg:address":"Silcherstr. 31",
    "sg:city":"Neckarsulm",
    "sg:postcode":"74172",
    "sg:province":"Baden-W\u00fcrttemberg",
    "wof:name":"Sysla Gmbh",
    "wof:placetype":"venue"
},
  "geometry": {"coordinates":[9.204266,49.195316],"type":"Point"}
}