{
  "type": "Feature",
  "properties": {
    "iso:country":"DE",
    "sg:address":"Obere Weingartenstr. 8",
    "sg:city":"Heiningen",
    "sg:phone":"+49 7161/4726",
    "sg:postcode":"73092",
    "sg:province":"Baden-W\u00fcrttemberg",
    "wof:name":"Kurt Haubensak Architekt",
    "wof:placetype":"venue"
},
  "geometry": {"coordinates":[9.648233,48.665333],"type":"Point"}
}