{
  "type": "Feature",
  "properties": {
    "iso:country":"DE",
    "sg:address":"V\u00f6rn Styg 10",
    "sg:city":"Hamburg",
    "sg:phone":"+49 40/8319186",
    "sg:postcode":"22607",
    "sg:province":"Hamburg",
    "wof:name":"Behrens & Kauffmann Verwaltungs- Gmbh",
    "wof:placetype":"venue"
},
  "geometry": {"coordinates":[9.873208046,53.5806846619],"type":"Point"}
}