{
  "type": "Feature",
  "properties": {
    "iso:country":"DE",
    "sg:address":"Richtstr. 22",
    "sg:city":"Essen",
    "sg:phone":"+49 201/697488",
    "sg:postcode":"45359",
    "sg:province":"Nordrhein-Westfalen",
    "wof:name":"A. Koch",
    "wof:placetype":"venue"
},
  "geometry": {"coordinates":[6.912036,51.483059],"type":"Point"}
}