{
  "type": "Feature",
  "properties": {
    "iso:country":"DE",
    "sg:address":"Kraisdorf",
    "sg:city":"Pfarrweisach",
    "sg:phone":"+49 9535/319",
    "sg:postcode":"96176",
    "sg:province":"Bayern",
    "wof:name":"Willi B\u00fchler",
    "wof:placetype":"venue"
},
  "geometry": {"coordinates":[10.728219986,50.136341095],"type":"Point"}
}