{
  "type": "Feature",
  "properties": {
    "iso:country":"DE",
    "sg:address":"Fr\u00f6nsberger Str. 31",
    "sg:city":"Hemer",
    "sg:phone":"+49 2372/80213",
    "sg:postcode":"58675",
    "sg:province":"Nordrhein-Westfalen",
    "wof:name":"Adolf Und Gerhard H\u00fclter",
    "wof:placetype":"venue"
},
  "geometry": {"coordinates":[7.750949,51.348721],"type":"Point"}
}