{
  "type": "Feature",
  "properties": {
    "iso:country":"DE",
    "sg:address":"Auer Talstr. 1",
    "sg:city":"Schlema",
    "sg:postcode":"08301",
    "sg:province":"Sachsen",
    "wof:name":"Ispm-ingenieurb\u00fcro F\u00fcr Stand- Ort- Und Strukturententwick-",
    "wof:placetype":"venue"
},
  "geometry": {"coordinates":[12.683152,50.612564],"type":"Point"}
}