{
  "type": "Feature",
  "properties": {
    "iso:country":"DE",
    "sg:address":"Schlo\u00dfstr. 20",
    "sg:city":"Barntrup",
    "sg:phone":"+49 5262/859",
    "sg:postcode":"32683",
    "sg:province":"Nordrhein-Westfalen",
    "wof:name":"Friedrich D\u00fcwel",
    "wof:placetype":"venue"
},
  "geometry": {"coordinates":[9.1224956512,52.0322265625],"type":"Point"}
}