{
  "type": "Feature",
  "properties": {
    "iso:country":"DE",
    "sg:address":"Lange Str. 90",
    "sg:city":"Castrop-Rauxel",
    "sg:phone":"+49 2305/73534",
    "sg:postcode":"44579",
    "sg:province":"Nordrhein-Westfalen",
    "wof:name":"Karl-heinz Scherer",
    "wof:placetype":"venue"
},
  "geometry": {"coordinates":[7.3165597916,51.5852775574],"type":"Point"}
}