{
  "type": "Feature",
  "properties": {
    "iso:country":"DE",
    "sg:address":"Hauptstr. 14",
    "sg:city":"Pronsfeld",
    "sg:phone":"+49 6556/511",
    "sg:postcode":"54597",
    "sg:province":"Rheinland-Pfalz",
    "wof:name":"Josef Klemes",
    "wof:placetype":"venue"
},
  "geometry": {"coordinates":[6.339546,50.159248],"type":"Point"}
}