{
  "type": "Feature",
  "properties": {
    "iso:country":"DE",
    "sg:address":"Hinsbecker Str. 34",
    "sg:city":"Nettetal",
    "sg:phone":"+49 2157/132061",
    "sg:postcode":"41334",
    "sg:province":"Nordrhein-Westfalen",
    "wof:name":"Hotel-restaurant Leuther M\u00fchle",
    "wof:placetype":"venue"
},
  "geometry": {"coordinates":[6.2430138588,51.33826828],"type":"Point"}
}