{
  "type": "Feature",
  "properties": {
    "iso:country":"DE",
    "sg:address":"Herbststr. 14",
    "sg:city":"Rosenheim",
    "sg:phone":"+49 8031/37065",
    "sg:postcode":"83022",
    "sg:province":"Bayern",
    "wof:name":"Primus Gold Edelmetall- Vertriebs-gmbh",
    "wof:placetype":"venue"
},
  "geometry": {"coordinates":[12.1248130798,47.8593559265],"type":"Point"}
}