{
  "type": "Feature",
  "properties": {
    "iso:country":"DE",
    "sg:address":"Breite Str. 25",
    "sg:city":"Bonn",
    "sg:phone":"+49 228/638762",
    "sg:postcode":"53111",
    "sg:province":"Nordrhein-Westfalen",
    "wof:name":"On Dialogue - Ondilo Gesellschaft F. Internationale",
    "wof:placetype":"venue"
},
  "geometry": {"coordinates":[7.0955748558,50.7377662659],"type":"Point"}
}