{
  "type": "Feature",
  "properties": {
    "iso:country":"DE",
    "sg:address":"Schmalegger Str 47",
    "sg:city":"Ravensburg",
    "sg:phone":"+49 751/7915508",
    "sg:postcode":"88213",
    "sg:province":"Baden-W\u00fcrttemberg",
    "wof:name":"Werbeteam Gmbh",
    "wof:placetype":"venue"
},
  "geometry": {"coordinates":[9.571447,47.784969],"type":"Point"}
}