{
  "type": "Feature",
  "properties": {
    "iso:country":"DE",
    "sg:address":"Birkenstr. 15",
    "sg:city":"Bremen",
    "sg:postcode":"28195",
    "sg:province":"Bremen",
    "wof:name":"Brunel Deutschland Gmbh",
    "wof:placetype":"venue"
},
  "geometry": {"coordinates":[8.808637,53.081272],"type":"Point"}
}