{
  "type": "Feature",
  "properties": {
    "iso:country":"DE",
    "sg:address":"Kieler Str. 44",
    "sg:city":"Kaltenkirchen",
    "sg:phone":"+49 4191/95240",
    "sg:postcode":"24568",
    "sg:province":"Schleswig-Holstein",
    "wof:name":"Holert Kalksandsteinwerke Gmbh & Co. Kg",
    "wof:placetype":"venue"
},
  "geometry": {"coordinates":[9.9460840225,53.8421592712],"type":"Point"}
}