{
  "type": "Feature",
  "properties": {
    "iso:country":"DE",
    "sg:address":"Aachener Str. 233-237",
    "sg:city":"K\u00f6ln",
    "sg:postcode":"50931",
    "sg:province":"Nordrhein-Westfalen",
    "wof:name":"Arzneimittelkommission Der Deutschen \u00c4rzteschaft",
    "wof:placetype":"venue"
},
  "geometry": {"coordinates":[6.920465,50.936481],"type":"Point"}
}