{
  "type": "Feature",
  "properties": {
    "iso:country":"DE",
    "sg:address":"Afrastr. 5",
    "sg:city":"Augsburg",
    "sg:phone":"+49 821/881450",
    "sg:postcode":"86179",
    "sg:province":"Bayern",
    "wof:name":"Anna Ullsperger",
    "wof:placetype":"venue"
},
  "geometry": {"coordinates":[10.9011468887,48.30701828],"type":"Point"}
}