{
  "type": "Feature",
  "properties": {
    "iso:country":"DE",
    "sg:address":"Libanonstr. 118",
    "sg:city":"Stuttgart",
    "sg:phone":"+49 711/467348",
    "sg:postcode":"70186",
    "sg:province":"Baden-W\u00fcrttemberg",
    "wof:name":"Brigitte Kriegisch",
    "wof:placetype":"venue"
},
  "geometry": {"coordinates":[9.206816,48.777748],"type":"Point"}
}