{
  "type": "Feature",
  "properties": {
    "iso:country":"DE",
    "sg:address":"Wittener Str. 77 A-C",
    "sg:city":"Wuppertal",
    "sg:phone":"+49 202/643330",
    "sg:postcode":"42279",
    "sg:province":"Nordrhein-Westfalen",
    "wof:name":"Blankennagel Beteiligungs-gmbh",
    "wof:placetype":"venue"
},
  "geometry": {"coordinates":[7.19655,51.271564],"type":"Point"}
}