{
  "type": "Feature",
  "properties": {
    "iso:country":"DE",
    "sg:address":"Heilbronner Str. 18",
    "sg:city":"Stuttgart",
    "sg:phone":"+49 711/228400",
    "sg:postcode":"70191",
    "sg:province":"Baden-W\u00fcrttemberg",
    "wof:name":"Price Waterhouse Coopers Veltins Rechtsanwalts Gmbh",
    "wof:placetype":"venue"
},
  "geometry": {"coordinates":[9.1806545258,48.7865638733],"type":"Point"}
}