{
  "type": "Feature",
  "properties": {
    "iso:country":"DE",
    "sg:address":"Heimatring 49",
    "sg:city":"Coburg",
    "sg:phone":"+49 9561/30929",
    "sg:postcode":"96450",
    "sg:province":"Bayern",
    "wof:name":"Hedwig Kittel",
    "wof:placetype":"venue"
},
  "geometry": {"coordinates":[10.938410759,50.2676963806],"type":"Point"}
}