{
  "type": "Feature",
  "properties": {
    "iso:country":"DE",
    "sg:address":"Maintalstr. 25",
    "sg:city":"Aschaffenburg",
    "sg:phone":"+49 6028/6369",
    "sg:postcode":"63743",
    "sg:province":"Bayern",
    "wof:name":"Dieter Gerlach",
    "wof:placetype":"venue"
},
  "geometry": {"coordinates":[9.1326179504,49.9354515076],"type":"Point"}
}