{
  "type": "Feature",
  "properties": {
    "iso:country":"DE",
    "sg:address":"Gausmannsweiler 9",
    "sg:city":"Welzheim",
    "sg:phone":"+49 7182/7884",
    "sg:postcode":"73642",
    "sg:province":"Baden-W\u00fcrttemberg",
    "wof:name":"E. Schad",
    "wof:placetype":"venue"
},
  "geometry": {"coordinates":[9.6215677261,48.9121284485],"type":"Point"}
}