{
  "type": "Feature",
  "properties": {
    "iso:country":"DE",
    "sg:address":"Auf dem Tigge 12",
    "sg:city":"Beckum",
    "sg:phone":"+49 2521/12150",
    "sg:postcode":"59269",
    "sg:province":"Nordrhein-Westfalen",
    "wof:name":"Tenniscenter Josef Mersmann",
    "wof:placetype":"venue"
},
  "geometry": {"coordinates":[8.0863342285,51.7588005066],"type":"Point"}
}