{
  "type": "Feature",
  "properties": {
    "iso:country":"DE",
    "sg:address":"Osterather Str. 7",
    "sg:city":"K\u00f6ln",
    "sg:phone":"+49 221/171091",
    "sg:postcode":"50739",
    "sg:province":"Nordrhein-Westfalen",
    "wof:name":"Kraus Messebau Gmbh",
    "wof:placetype":"venue"
},
  "geometry": {"coordinates":[6.9388251305,50.9582061768],"type":"Point"}
}