{
  "type": "Feature",
  "properties": {
    "iso:country":"DE",
    "sg:address":"Hechelner Str 32",
    "sg:city":"M\u00fchlingen",
    "sg:phone":"+49 7775/1215",
    "sg:postcode":"78357",
    "sg:province":"Baden-W\u00fcrttemberg",
    "wof:name":"China-br\u00dccke Dolmetscher Chinesisch - Deutsch",
    "wof:placetype":"venue"
},
  "geometry": {"coordinates":[9.0155448914,47.9119186401],"type":"Point"}
}