{
  "type": "Feature",
  "properties": {
    "iso:country":"DE",
    "sg:address":"\u00c4u\u00dfere Sulzbacher Str. 159-161",
    "sg:city":"N\u00fcrnberg",
    "sg:phone":"+49 911/9198080",
    "sg:postcode":"90491",
    "sg:province":"Bayern",
    "wof:name":"Abr Reiseb\u00fcro",
    "wof:placetype":"venue"
},
  "geometry": {"coordinates":[11.1231937408,49.4662818909],"type":"Point"}
}