{
  "type": "Feature",
  "properties": {
    "iso:country":"DE",
    "sg:address":"Sauerfelder Stra\u00dfe 7 - 11",
    "sg:city":"L\u00fcdenscheid",
    "sg:phone":"+49 2351",
    "sg:postcode":"58511",
    "sg:province":"Nordrhein-Westfalen",
    "wof:name":"Sparkasse L\u00fcdenscheid",
    "wof:placetype":"venue"
},
  "geometry": {"coordinates":[7.6445598602,51.2115402222],"type":"Point"}
}