{
  "type": "Feature",
  "properties": {
    "iso:country":"DE",
    "sg:address":"Hauptstr. 5",
    "sg:city":"Krefeld",
    "sg:phone":"+49 2151/736736",
    "sg:postcode":"47809",
    "sg:province":"Nordrhein-Westfalen",
    "wof:name":"Klimatechnik Pahlings",
    "wof:placetype":"venue"
},
  "geometry": {"coordinates":[6.628059864,51.3180007935],"type":"Point"}
}