{
  "type": "Feature",
  "properties": {
    "iso:country":"DE",
    "sg:address":"Bischoffstr. 6",
    "sg:city":"Miltenberg",
    "sg:phone":"+49 9371/2293",
    "sg:postcode":"63897",
    "sg:province":"Bayern",
    "wof:name":"Jung Und Schmitt Gmbh",
    "wof:placetype":"venue"
},
  "geometry": {"coordinates":[9.2506,49.703907],"type":"Point"}
}