{
  "type": "Feature",
  "properties": {
    "iso:country":"DE",
    "sg:address":"Hochstr. 9",
    "sg:city":"Niederro\u00dfbach",
    "sg:phone":"+49 2664/6490",
    "sg:postcode":"56479",
    "sg:province":"Rheinland-Pfalz",
    "wof:name":"Roger Jung",
    "wof:placetype":"venue"
},
  "geometry": {"coordinates":[8.035825,50.64093],"type":"Point"}
}