{
  "type": "Feature",
  "properties": {
    "iso:country":"DE",
    "sg:address":"Wilhelm-Koenen-Str.",
    "sg:city":"Sangerhausen",
    "sg:postcode":"06526",
    "sg:province":"Sachsen-Anhalt",
    "wof:name":"Pflegeheim Ii",
    "wof:placetype":"venue"
},
  "geometry": {"coordinates":[11.29007,51.456764],"type":"Point"}
}