{
  "type": "Feature",
  "properties": {
    "iso:country":"DE",
    "sg:address":"Magerauer Str. 54",
    "sg:city":"Herzogenrath",
    "sg:phone":"+49 2406/97010",
    "sg:postcode":"52134",
    "sg:province":"Nordrhein-Westfalen",
    "wof:name":"Kirchner",
    "wof:placetype":"venue"
},
  "geometry": {"coordinates":[6.1138539314,50.8840713501],"type":"Point"}
}