{
  "type": "Feature",
  "properties": {
    "iso:country":"DE",
    "sg:address":"Hauptstr. 13",
    "sg:city":"Wartmannsroth",
    "sg:phone":"+49 9737/281",
    "sg:postcode":"97797",
    "sg:province":"Bayern",
    "wof:name":"Kath. Pfarramt",
    "wof:placetype":"venue"
},
  "geometry": {"coordinates":[9.786857605,50.1664886475],"type":"Point"}
}