{
  "type": "Feature",
  "properties": {
    "iso:country":"DE",
    "sg:address":"Bernhard-Nocht-Str. 4",
    "sg:city":"Hamburg",
    "sg:phone":"+49 40/31790223",
    "sg:postcode":"20359",
    "sg:province":"Hamburg",
    "wof:name":"Applaus Entertainment Goldi Bettinger & Knuth Weidemann",
    "wof:placetype":"venue"
},
  "geometry": {"coordinates":[9.958046,53.54649],"type":"Point"}
}