{
  "type": "Feature",
  "properties": {
    "iso:country":"DE",
    "sg:address":"Stresemannstr. 18",
    "sg:city":"D\u00fcsseldorf",
    "sg:phone":"+49 211/326776",
    "sg:postcode":"40210",
    "sg:province":"Nordrhein-Westfalen",
    "wof:name":"Franz Draxler Architekt",
    "wof:placetype":"venue"
},
  "geometry": {"coordinates":[6.784466,51.221004],"type":"Point"}
}