{
  "type": "Feature",
  "properties": {
    "iso:country":"DE",
    "sg:address":"Nordendstr. 4",
    "sg:city":"M\u00f6rfelden-Walldorf",
    "sg:phone":"+49 6105/9570",
    "sg:postcode":"64546",
    "sg:province":"Hessen",
    "wof:name":"Airport Domizil",
    "wof:placetype":"venue"
},
  "geometry": {"coordinates":[8.5810537338,50.0130157471],"type":"Point"}
}