{
  "type": "Feature",
  "properties": {
    "iso:country":"DE",
    "sg:address":"Oberstebener Str. 19",
    "sg:city":"Bad Steben",
    "sg:phone":"+49 9288/6189",
    "sg:postcode":"95138",
    "sg:province":"Bayern",
    "wof:name":"G\u00e4stehaus Abendfrieden",
    "wof:placetype":"venue"
},
  "geometry": {"coordinates":[11.6362266541,50.3669929504],"type":"Point"}
}