{
  "type": "Feature",
  "properties": {
    "iso:country":"DE",
    "sg:address":"Landshuter Str. 30",
    "sg:city":"Adlkofen",
    "sg:phone":"+49 8707/932130",
    "sg:postcode":"84166",
    "sg:province":"Bayern",
    "wof:name":"Boiger Gmbh",
    "wof:placetype":"venue"
},
  "geometry": {"coordinates":[12.2648906708,48.549785614],"type":"Point"}
}