{
  "type": "Feature",
  "properties": {
    "iso:country":"DE",
    "sg:address":"Reitzenhainer Str 35",
    "sg:city":"Marienberg",
    "sg:phone":"+49 3735/66060",
    "sg:postcode":"09496",
    "sg:province":"Sachsen",
    "wof:name":"Tli-thermotransport Gmbh",
    "wof:placetype":"venue"
},
  "geometry": {"coordinates":[13.1578702927,50.6395530701],"type":"Point"}
}