{
  "type": "Feature",
  "properties": {
    "iso:country":"DE",
    "sg:address":"Gelderner Str. 18",
    "sg:city":"T\u00f6nisvorst",
    "sg:phone":"+49 2151/790217",
    "sg:postcode":"47918",
    "sg:province":"Nordrhein-Westfalen",
    "wof:name":"Hesse & Vormann Gmbh",
    "wof:placetype":"venue"
},
  "geometry": {"coordinates":[6.490649,51.322769],"type":"Point"}
}