{
  "type": "Feature",
  "properties": {
    "iso:country":"DE",
    "sg:address":"Borngasse 5",
    "sg:city":"Pfungstadt",
    "sg:phone":"+49 6157/2230",
    "sg:postcode":"64319",
    "sg:province":"Hessen",
    "wof:name":"Born-apotheke Inh. Ellen Leistner",
    "wof:placetype":"venue"
},
  "geometry": {"coordinates":[8.59643,49.802517],"type":"Point"}
}