{
  "type": "Feature",
  "properties": {
    "iso:country":"DE",
    "sg:address":"Vordergasse 45",
    "sg:city":"Rodgau",
    "sg:phone":"+49 6106/3383",
    "sg:postcode":"63110",
    "sg:province":"Hessen",
    "wof:name":"Eisen-rupp Eisenwaren",
    "wof:placetype":"venue"
},
  "geometry": {"coordinates":[8.8830060959,50.0258789062],"type":"Point"}
}