{
  "type": "Feature",
  "properties": {
    "iso:country":"DE",
    "sg:address":"Butschhofstr. 40",
    "sg:city":"Tuningen",
    "sg:phone":"+49 7464/1208",
    "sg:postcode":"78609",
    "sg:province":"Baden-W\u00fcrttemberg",
    "wof:name":"Manfred Hauser",
    "wof:placetype":"venue"
},
  "geometry": {"coordinates":[8.6044,48.028919],"type":"Point"}
}