{
  "type": "Feature",
  "properties": {
    "iso:country":"DE",
    "sg:address":"Richard-Wagner-Str. 6",
    "sg:city":"Pirna",
    "sg:phone":"+49 3501/548229",
    "sg:postcode":"01796",
    "sg:province":"Sachsen",
    "wof:name":"Richard-wagner-museum",
    "wof:placetype":"venue"
},
  "geometry": {"coordinates":[13.920353,50.999928],"type":"Point"}
}