{
  "type": "Feature",
  "properties": {
    "iso:country":"DE",
    "sg:address":"Schulberg 7",
    "sg:city":"Walluf",
    "sg:phone":"+49 6123/75728",
    "sg:postcode":"65396",
    "sg:province":"Hessen",
    "wof:name":"J. Boes Immobilienmakler",
    "wof:placetype":"venue"
},
  "geometry": {"coordinates":[8.1515636444,50.0393104553],"type":"Point"}
}