{
  "type": "Feature",
  "properties": {
    "iso:country":"DE",
    "sg:address":"Steinstr. 53",
    "sg:city":"Ilmenau",
    "sg:phone":"+49 3677/844122",
    "sg:postcode":"98693",
    "sg:province":"Th\u00fcringen",
    "wof:name":"E. Elsner",
    "wof:placetype":"venue"
},
  "geometry": {"coordinates":[10.9149093628,50.6760177612],"type":"Point"}
}