{
  "type": "Feature",
  "properties": {
    "iso:country":"DE",
    "sg:address":"Schlo\u00dfparkstr. 5",
    "sg:city":"Hemsbach",
    "sg:phone":"+49 6201/71375",
    "sg:postcode":"69502",
    "sg:province":"Baden-W\u00fcrttemberg",
    "wof:name":"Malerbetrieb B\u00f6hm Gmbh",
    "wof:placetype":"venue"
},
  "geometry": {"coordinates":[8.654515,49.589397],"type":"Point"}
}