{
  "type": "Feature",
  "properties": {
    "iso:country":"DE",
    "sg:address":"Ungererstr. 159",
    "sg:city":"M\u00fcnchen",
    "sg:phone":"+49 89/36101845",
    "sg:postcode":"80805",
    "sg:province":"Bayern",
    "wof:name":"Sylvia Breen Rechtsanw\u00e4ltin",
    "wof:placetype":"venue"
},
  "geometry": {"coordinates":[11.6002349854,48.1764297485],"type":"Point"}
}