{
  "type": "Feature",
  "properties": {
    "iso:country":"DE",
    "sg:address":"Industrieweg 14",
    "sg:city":"Harrislee",
    "sg:phone":"+49 4946/171568",
    "sg:postcode":"24955",
    "sg:province":"Schleswig-Holstein",
    "wof:name":"Hartmetall- Werkzeuge- Nord Gmbh & Co",
    "wof:placetype":"venue"
},
  "geometry": {"coordinates":[9.38094,54.796074],"type":"Point"}
}