{
  "type": "Feature",
  "properties": {
    "iso:country":"DE",
    "sg:address":"Essenberger Str. 2",
    "sg:city":"Moers",
    "sg:phone":"+49 2841/24990",
    "sg:postcode":"47441",
    "sg:province":"Nordrhein-Westfalen",
    "wof:name":"H.-g. Alefs",
    "wof:placetype":"venue"
},
  "geometry": {"coordinates":[6.636041,51.449551],"type":"Point"}
}