{
  "type": "Feature",
  "properties": {
    "iso:country":"DE",
    "sg:address":"Hauptstr. 20",
    "sg:city":"Eibelstadt",
    "sg:phone":"+49 9303/90720",
    "sg:postcode":"97246",
    "sg:province":"Bayern",
    "wof:name":"Roth Und Haas Architekten",
    "wof:placetype":"venue"
},
  "geometry": {"coordinates":[10.001317,49.723579],"type":"Point"}
}