{
  "type": "Feature",
  "properties": {
    "iso:country":"DE",
    "sg:address":"Industriestr. 13",
    "sg:city":"Neidenstein",
    "sg:phone":"+49 7263/1568",
    "sg:postcode":"74933",
    "sg:province":"Baden-W\u00fcrttemberg",
    "wof:name":"Karl Heinz Lang Gmbh",
    "wof:placetype":"venue"
},
  "geometry": {"coordinates":[8.898229599,49.3209381104],"type":"Point"}
}