{
  "type": "Feature",
  "properties": {
    "iso:country":"DE",
    "sg:address":"Oskar-Schwenk-Str. 24",
    "sg:city":"Waldenbuch",
    "sg:phone":"+49 7157/7036",
    "sg:postcode":"71111",
    "sg:province":"Baden-W\u00fcrttemberg",
    "wof:name":"Joachim Susenbeth Architekt",
    "wof:placetype":"venue"
},
  "geometry": {"coordinates":[9.136059,48.64077],"type":"Point"}
}