{
  "type": "Feature",
  "properties": {
    "iso:country":"DE",
    "sg:address":"Industriering Ost 58",
    "sg:city":"Kempen",
    "sg:phone":"+49 2152/5725",
    "sg:postcode":"47906",
    "sg:province":"Nordrhein-Westfalen",
    "wof:name":"P. Kops",
    "wof:placetype":"venue"
},
  "geometry": {"coordinates":[6.4351091385,51.3711242676],"type":"Point"}
}