{
  "type": "Feature",
  "properties": {
    "iso:country":"DE",
    "sg:address":"Paul-M\u00fcnch-Str. 24",
    "sg:city":"Kaiserslautern",
    "sg:postcode":"67663",
    "sg:province":"Rheinland-Pfalz",
    "wof:name":"P. Bernhardt",
    "wof:placetype":"venue"
},
  "geometry": {"coordinates":[7.744973,49.435928],"type":"Point"}
}