{
  "type": "Feature",
  "properties": {
    "iso:country":"DE",
    "sg:address":"Talstr. 10",
    "sg:city":"Emmingen-Liptingen",
    "sg:phone":"+49 7465/842",
    "sg:postcode":"78576",
    "sg:province":"Baden-W\u00fcrttemberg",
    "wof:name":"Johann Flesch Gmbh",
    "wof:placetype":"venue"
},
  "geometry": {"coordinates":[8.856098,47.931156],"type":"Point"}
}