{
  "type": "Feature",
  "properties": {
    "iso:country":"DE",
    "sg:address":"Rothenseer Str. 4",
    "sg:city":"Glindenberg",
    "sg:phone":"+49 39201/21582",
    "sg:postcode":"39326",
    "sg:province":"Sachsen-Anhalt",
    "wof:name":"Ewald L\u00f6hle",
    "wof:placetype":"venue"
},
  "geometry": {"coordinates":[11.683581,52.234993],"type":"Point"}
}