{
  "type": "Feature",
  "properties": {
    "iso:country":"DE",
    "sg:address":"Granting",
    "sg:city":"Taufkirchen",
    "sg:phone":"+49 8084/492",
    "sg:postcode":"84416",
    "sg:province":"Bayern",
    "wof:name":"F. Schatz",
    "wof:placetype":"venue"
},
  "geometry": {"coordinates":[12.17254,48.350189],"type":"Point"}
}