{
  "type": "Feature",
  "properties": {
    "iso:country":"DE",
    "sg:address":"Weinbergstr. 6",
    "sg:city":"Stadecken-Elsheim",
    "sg:phone":"+49 6136/3211",
    "sg:postcode":"55271",
    "sg:province":"Rheinland-Pfalz",
    "wof:name":"Walter Wolf",
    "wof:placetype":"venue"
},
  "geometry": {"coordinates":[8.1376581192,49.908000946],"type":"Point"}
}