{
  "type": "Feature",
  "properties": {
    "iso:country":"DE",
    "sg:address":"Amselstr. 10",
    "sg:city":"Bremerv\u00f6rde",
    "sg:phone":"+49 4761/4730",
    "sg:postcode":"27432",
    "sg:province":"Niedersachsen",
    "wof:name":"U. Schr\u00f6der",
    "wof:placetype":"venue"
},
  "geometry": {"coordinates":[9.190702,53.46452],"type":"Point"}
}