{
  "type": "Feature",
  "properties": {
    "iso:country":"DE",
    "sg:address":"Ankerstr. 18 A",
    "sg:city":"K\u00f6nigsbach-Stein",
    "sg:phone":"+49 7232/6822",
    "sg:postcode":"75203",
    "sg:province":"Baden-W\u00fcrttemberg",
    "wof:name":"Hermann Wagner",
    "wof:placetype":"venue"
},
  "geometry": {"coordinates":[8.6105718613,48.9655723572],"type":"Point"}
}