{
  "type": "Feature",
  "properties": {
    "iso:country":"DE",
    "sg:address":"Am S\u00fcdfeld 1",
    "sg:city":"Delmenhorst",
    "sg:phone":"+49 4221/452373",
    "sg:postcode":"27751",
    "sg:province":"Niedersachsen",
    "wof:name":"Richard Gareis",
    "wof:placetype":"venue"
},
  "geometry": {"coordinates":[8.659576,53.074455],"type":"Point"}
}