{
  "type": "Feature",
  "properties": {
    "iso:country":"DE",
    "sg:address":"Victor-Gollancz-Str. 30",
    "sg:city":"J\u00fclich",
    "sg:phone":"+49 2461/51307",
    "sg:postcode":"52428",
    "sg:province":"Nordrhein-Westfalen",
    "wof:name":"Erwin Loup",
    "wof:placetype":"venue"
},
  "geometry": {"coordinates":[6.350579,50.926514],"type":"Point"}
}