{
  "type": "Feature",
  "properties": {
    "iso:country":"DE",
    "sg:address":"Commandeurstrate 12",
    "sg:city":"Borkum",
    "sg:phone":"+49 4922/2396",
    "sg:postcode":"26757",
    "sg:province":"Niedersachsen",
    "wof:name":"Fritz-joachim Elter",
    "wof:placetype":"venue"
},
  "geometry": {"coordinates":[6.6880269051,53.5825843811],"type":"Point"}
}