{
  "type": "Feature",
  "properties": {
    "iso:country":"DE",
    "sg:address":"Geschwister-Scholl-Weg 20",
    "sg:city":"Ruhland",
    "sg:postcode":"01945",
    "sg:province":"Brandenburg",
    "wof:name":"Dr. Med. Siegbert Gendreitzki",
    "wof:placetype":"venue"
},
  "geometry": {"coordinates":[13.873936,51.430443],"type":"Point"}
}