{
  "type": "Feature",
  "properties": {
    "iso:country":"DE",
    "sg:address":"Bahnhofstr. 73",
    "sg:city":"Dei\u00dflingen",
    "sg:phone":"+49 4974/2092940",
    "sg:postcode":"78652",
    "sg:province":"Baden-W\u00fcrttemberg",
    "wof:name":"Gr\u00dcner Form U.technik Gmbh",
    "wof:placetype":"venue"
},
  "geometry": {"coordinates":[8.614402771,48.1122398376],"type":"Point"}
}