{
  "type": "Feature",
  "properties": {
    "iso:country":"DE",
    "sg:address":"Freiherr-vom-Stein-Str. 13",
    "sg:city":"Bretzenheim",
    "sg:phone":"+49 671/2985946",
    "sg:postcode":"55559",
    "sg:province":"Rheinland-Pfalz",
    "wof:name":"Microplan Deutschland Gmbh",
    "wof:placetype":"venue"
},
  "geometry": {"coordinates":[7.9022808075,49.8808021545],"type":"Point"}
}