{
  "type": "Feature",
  "properties": {
    "iso:country":"DE",
    "sg:address":"Kirchhellener Str. 5",
    "sg:city":"Bottrop",
    "sg:phone":"+49 2041/72240",
    "sg:postcode":"46236",
    "sg:province":"Nordrhein-Westfalen",
    "wof:name":"Braun Und Elbracht-h\u00fclseweh Rechtsanw\u00e4lte",
    "wof:placetype":"venue"
},
  "geometry": {"coordinates":[6.9256429672,51.523235321],"type":"Point"}
}