{
  "type": "Feature",
  "properties": {
    "iso:country":"DE",
    "sg:address":"Truberg 12",
    "sg:city":"Preetz",
    "sg:phone":"+49 4342/2444",
    "sg:postcode":"24211",
    "sg:province":"Schleswig-Holstein",
    "wof:name":"Helmuth Luther",
    "wof:placetype":"venue"
},
  "geometry": {"coordinates":[10.271422,54.233829],"type":"Point"}
}