{
  "type": "Feature",
  "properties": {
    "iso:country":"DE",
    "sg:address":"Br\u00fchlstr. 1",
    "sg:city":"Plochingen",
    "sg:phone":"+49 7153/21110",
    "sg:postcode":"73207",
    "sg:province":"Baden-W\u00fcrttemberg",
    "wof:name":"M. Walther",
    "wof:placetype":"venue"
},
  "geometry": {"coordinates":[9.4149570465,48.7128067017],"type":"Point"}
}