{
  "type": "Feature",
  "properties": {
    "iso:country":"DE",
    "sg:address":"Veilchenweg 2",
    "sg:city":"Neuching",
    "sg:phone":"+49 8123/1449",
    "sg:postcode":"85467",
    "sg:province":"Bayern",
    "wof:name":"Cornelius Knallinger",
    "wof:placetype":"venue"
},
  "geometry": {"coordinates":[11.844208,48.250374],"type":"Point"}
}