{
  "type": "Feature",
  "properties": {
    "iso:country":"DE",
    "sg:address":"Friedrichstra\u00dfe 25",
    "sg:city":"D\u00fcsseldorf",
    "sg:phone":"+49 211",
    "sg:postcode":"40217",
    "sg:province":"Nordrhein-Westfalen",
    "wof:name":"Pelzmodelle Kuhn",
    "wof:placetype":"venue"
},
  "geometry": {"coordinates":[6.7766461372,51.2171516418],"type":"Point"}
}