{
  "type": "Feature",
  "properties": {
    "iso:country":"DE",
    "sg:address":"Strasse des 17. Juni 25",
    "sg:city":"Dresden",
    "sg:phone":"+49 351/209090",
    "sg:postcode":"01257",
    "sg:province":"Sachsen",
    "wof:name":"Thf Gmbh & Co Kg",
    "wof:placetype":"venue"
},
  "geometry": {"coordinates":[13.826532,51.002426],"type":"Point"}
}