{
  "type": "Feature",
  "properties": {
    "iso:country":"DE",
    "sg:address":"Spitalstr. 3",
    "sg:city":"Weingarten",
    "sg:phone":"+49 751/45066",
    "sg:postcode":"88250",
    "sg:province":"Baden-W\u00fcrttemberg",
    "wof:name":"K\u00fchl Gmbh",
    "wof:placetype":"venue"
},
  "geometry": {"coordinates":[9.633101,47.802429],"type":"Point"}
}