{
  "type": "Feature",
  "properties": {
    "iso:country":"DE",
    "sg:address":"Schulgasse 2 b",
    "sg:city":"Aue",
    "sg:phone":"+49 3771/44311",
    "sg:postcode":"08280",
    "sg:province":"Sachsen",
    "wof:name":"Copy Plus Gmbh Handelsges. B\u00fcrom\u00f6bel",
    "wof:placetype":"venue"
},
  "geometry": {"coordinates":[12.7020893097,50.5877952576],"type":"Point"}
}