{
  "type": "Feature",
  "properties": {
    "iso:country":"DE",
    "sg:address":"Im Sand 14",
    "sg:city":"Bad Sch\u00f6nborn",
    "sg:phone":"+49 7253/94040",
    "sg:postcode":"76669",
    "sg:province":"Baden-W\u00fcrttemberg",
    "wof:name":"Eurotherm Antriebstechnik Gmbh",
    "wof:placetype":"venue"
},
  "geometry": {"coordinates":[8.633069,49.204838],"type":"Point"}
}