{
  "type": "Feature",
  "properties": {
    "iso:country":"DE",
    "sg:address":"M\u00fcnchner Str. 4",
    "sg:city":"Neuried",
    "sg:phone":"+49 89/74575566",
    "sg:postcode":"82061",
    "sg:province":"Bayern",
    "wof:name":"Fritsch & Co. Immobilienberatungsges. Mbh",
    "wof:placetype":"venue"
},
  "geometry": {"coordinates":[11.4673213959,48.093711853],"type":"Point"}
}