{
  "type": "Feature",
  "properties": {
    "iso:country":"DE",
    "sg:address":"Lindenstr. 51",
    "sg:city":"Schmelz",
    "sg:phone":"+49 6887/2759",
    "sg:postcode":"66839",
    "sg:province":"Saarland",
    "wof:name":"Josefine Schumacher",
    "wof:placetype":"venue"
},
  "geometry": {"coordinates":[6.8575839996,49.4377861023],"type":"Point"}
}