{
  "type": "Feature",
  "properties": {
    "iso:country":"DE",
    "sg:address":"Goethestr. 24",
    "sg:city":"Pulsnitz",
    "sg:phone":"+49 35955/8250",
    "sg:postcode":"01896",
    "sg:province":"Sachsen",
    "wof:name":"Swg St\u00e4dtische Wohnungs Gmbh",
    "wof:placetype":"venue"
},
  "geometry": {"coordinates":[14.0116539001,51.1826210022],"type":"Point"}
}