{
  "type": "Feature",
  "properties": {
    "iso:country":"DE",
    "sg:address":"Dorfstr. 8",
    "sg:city":"Insel",
    "sg:phone":"+49 39329/41382",
    "sg:postcode":"39599",
    "sg:province":"Sachsen-Anhalt",
    "wof:name":"Stendaler Blumengro\u00dfhandel Gmbh",
    "wof:placetype":"venue"
},
  "geometry": {"coordinates":[11.754995,52.561813],"type":"Point"}
}