{
  "type": "Feature",
  "properties": {
    "iso:country":"DE",
    "sg:address":"Trenkerm\u00fchlstr. 8",
    "sg:city":"Burgkirchen",
    "sg:phone":"+49 8679/6841",
    "sg:postcode":"84508",
    "sg:province":"Bayern",
    "wof:name":"Meryl Gmbh",
    "wof:placetype":"venue"
},
  "geometry": {"coordinates":[12.693801,48.164062],"type":"Point"}
}