{
  "type": "Feature",
  "properties": {
    "iso:country":"DE",
    "sg:address":"Teichstr. 16a",
    "sg:city":"Burgstall",
    "sg:phone":"+49 39364/4362",
    "sg:postcode":"39517",
    "sg:province":"Sachsen-Anhalt",
    "wof:name":"Dachdeckermeisterbetrieb Schulze & S\u00f6hne Gmbh",
    "wof:placetype":"venue"
},
  "geometry": {"coordinates":[11.693105,52.405701],"type":"Point"}
}