{
  "type": "Feature",
  "properties": {
    "iso:country":"DE",
    "sg:address":"Industriestr. 13",
    "sg:city":"Kusel",
    "sg:postcode":"66869",
    "sg:province":"Rheinland-Pfalz",
    "wof:name":"Rech Elektro-fachmarkt",
    "wof:placetype":"venue"
},
  "geometry": {"coordinates":[7.4213042259,49.5412101746],"type":"Point"}
}