{
  "type": "Feature",
  "properties": {
    "iso:country":"DE",
    "sg:address":"Schanzenweg 3",
    "sg:city":"Magdeburg",
    "sg:phone":"+49 391/4061700",
    "sg:postcode":"39104",
    "sg:province":"Sachsen-Anhalt",
    "wof:name":"Meb Bahndienstleistungen Gmbh",
    "wof:placetype":"venue"
},
  "geometry": {"coordinates":[11.6393117905,52.0973892212],"type":"Point"}
}