{
  "type": "Feature",
  "properties": {
    "iso:country":"DE",
    "sg:address":"Washingtonstr. 40",
    "sg:city":"Dresden",
    "sg:phone":"+49 351/8945960",
    "sg:postcode":"01139",
    "sg:province":"Sachsen",
    "wof:name":"Svg Service Und Vertrieb F\u00fcr Das Verkehrsgewerbe Gmbh",
    "wof:placetype":"venue"
},
  "geometry": {"coordinates":[13.6876497269,51.067691803],"type":"Point"}
}