{
  "type": "Feature",
  "properties": {
    "iso:country":"DE",
    "sg:address":"Peterstr. 87",
    "sg:city":"Wilhelmshaven",
    "sg:phone":"+49 4421/24529",
    "sg:postcode":"26382",
    "sg:province":"Niedersachsen",
    "wof:name":"Hans-herbert Raatz Heilpraktiker",
    "wof:placetype":"venue"
},
  "geometry": {"coordinates":[8.1026086807,53.5226860046],"type":"Point"}
}