{
  "type": "Feature",
  "properties": {
    "iso:country":"DE",
    "sg:address":"Brandenberg 21",
    "sg:city":"M\u00fclheim",
    "sg:postcode":"45478",
    "sg:province":"Nordrhein-Westfalen",
    "wof:name":"Ibav - Institut F\u00fcr Alters- Versorgung Und Software-",
    "wof:placetype":"venue"
},
  "geometry": {"coordinates":[6.8392271996,51.4160575867],"type":"Point"}
}