{
  "type": "Feature",
  "properties": {
    "iso:country":"DE",
    "sg:address":"Burggasse 5",
    "sg:city":"Dinkelscherben",
    "sg:phone":"+49 8292/2679",
    "sg:postcode":"86424",
    "sg:province":"Bayern",
    "wof:name":"G. Und H. Fr\u00f6schle",
    "wof:placetype":"venue"
},
  "geometry": {"coordinates":[10.5913705826,48.3498878479],"type":"Point"}
}