{
  "type": "Feature",
  "properties": {
    "iso:country":"DE",
    "sg:address":"Hauptstr. 149",
    "sg:city":"Ostrhauderfehn",
    "sg:phone":"+49 4952/942916",
    "sg:postcode":"26842",
    "sg:province":"Niedersachsen",
    "wof:name":"Ulrich Kr\u00fcger Nordstern Versicherungen",
    "wof:placetype":"venue"
},
  "geometry": {"coordinates":[7.6288537979,53.140537262],"type":"Point"}
}