{
  "type": "Feature",
  "properties": {
    "iso:country":"DE",
    "sg:address":"Stadtplatz",
    "sg:city":"Lindenberg",
    "sg:phone":"+49 8381/81849",
    "sg:postcode":"88161",
    "sg:province":"Bayern",
    "wof:name":"Gasthaus Zum L\u00f6wen",
    "wof:placetype":"venue"
},
  "geometry": {"coordinates":[9.8863649368,47.6013031006],"type":"Point"}
}