{
  "type": "Feature",
  "properties": {
    "iso:country":"DE",
    "sg:address":"Schlo\u00dfstr. 7",
    "sg:city":"Edertal",
    "sg:phone":"+49 5623/2137",
    "sg:postcode":"34549",
    "sg:province":"Hessen",
    "wof:name":"Dirk Knauf",
    "wof:placetype":"venue"
},
  "geometry": {"coordinates":[9.133072,51.16872],"type":"Point"}
}