{
  "type": "Feature",
  "properties": {
    "iso:country":"DE",
    "sg:address":"Kaltenbrunnstr. 48",
    "sg:city":"Ranschbach",
    "sg:phone":"+49 6345/5315",
    "sg:postcode":"76829",
    "sg:province":"Rheinland-Pfalz",
    "wof:name":"Fliesen Weigel Gmbh",
    "wof:placetype":"venue"
},
  "geometry": {"coordinates":[8.0243501663,49.196811676],"type":"Point"}
}