{
  "type": "Feature",
  "properties": {
    "iso:country":"DE",
    "sg:address":"Freiburger Str. 10",
    "sg:city":"Emmendingen",
    "sg:phone":"+49 7641/1295",
    "sg:postcode":"79312",
    "sg:province":"Baden-W\u00fcrttemberg",
    "wof:name":"B\u00e4ko B\u00e4ckergenossenschaft Emmendingen Eg",
    "wof:placetype":"venue"
},
  "geometry": {"coordinates":[7.851751,48.115299],"type":"Point"}
}