{
  "type": "Feature",
  "properties": {
    "iso:country":"DE",
    "sg:address":"Altmarkt 6",
    "sg:city":"Marl",
    "sg:phone":"+49 2365",
    "sg:postcode":"45768",
    "sg:province":"Nordrhein-Westfalen",
    "wof:name":"Kardiologische Praxis Dr. Stefan Marcin",
    "wof:placetype":"venue"
},
  "geometry": {"coordinates":[7.08307,51.647758],"type":"Point"}
}