{
  "type": "Feature",
  "properties": {
    "iso:country":"DE",
    "sg:address":"Am Randel 14a",
    "sg:city":"Sch\u00f6nebeck",
    "sg:phone":"+49 3928/81352",
    "sg:postcode":"39218",
    "sg:province":"Sachsen-Anhalt",
    "wof:name":"Irmgard Kelch",
    "wof:placetype":"venue"
},
  "geometry": {"coordinates":[11.7359027863,52.0126304626],"type":"Point"}
}