{
  "type": "Feature",
  "properties": {
    "iso:country":"DE",
    "sg:address":"Marktplatz 2",
    "sg:city":"F\u00fcrstenau",
    "sg:phone":"+49 5901/2718",
    "sg:postcode":"49584",
    "sg:province":"Niedersachsen",
    "wof:name":"R. Grafe",
    "wof:placetype":"venue"
},
  "geometry": {"coordinates":[7.6778678894,52.5181732178],"type":"Point"}
}