{
  "type": "Feature",
  "properties": {
    "iso:country":"DE",
    "sg:address":"Wilhelmshofallee 154",
    "sg:city":"Krefeld",
    "sg:phone":"+49 2151/501757",
    "sg:postcode":"47800",
    "sg:province":"Nordrhein-Westfalen",
    "wof:name":"Dr. Friedrich-wilhelm Lehmann Rechtsanwalt",
    "wof:placetype":"venue"
},
  "geometry": {"coordinates":[6.5892119408,51.3495101929],"type":"Point"}
}