{
  "type": "Feature",
  "properties": {
    "iso:country":"DE",
    "sg:address":"Unterschmiddorf 26",
    "sg:city":"Gangkofen",
    "sg:phone":"+49 8722/6186",
    "sg:postcode":"84140",
    "sg:province":"Bayern",
    "wof:name":"Sepp Da Hoizknecht Kimmt !",
    "wof:placetype":"venue"
},
  "geometry": {"coordinates":[12.543264,48.442871],"type":"Point"}
}