{
  "type": "Feature",
  "properties": {
    "iso:country":"DE",
    "sg:address":"Falkenweg 10",
    "sg:city":"Fichtenberg",
    "sg:phone":"+49 7971/8374",
    "sg:postcode":"74427",
    "sg:province":"Baden-W\u00fcrttemberg",
    "wof:name":"K\u00fchnle Gmbh",
    "wof:placetype":"venue"
},
  "geometry": {"coordinates":[9.7082853317,48.9902915955],"type":"Point"}
}