{
  "type": "Feature",
  "properties": {
    "iso:country":"DE",
    "sg:address":"Ulmenweg 50",
    "sg:city":"Augsburg",
    "sg:phone":"+49 821/700120",
    "sg:postcode":"86169",
    "sg:province":"Bayern",
    "wof:name":"Harald Wutte Steuerberater",
    "wof:placetype":"venue"
},
  "geometry": {"coordinates":[10.9140920639,48.4039268494],"type":"Point"}
}