{
  "type": "Feature",
  "properties": {
    "iso:country":"DE",
    "sg:address":"Wietbrede 22",
    "sg:city":"L\u00f6hne",
    "sg:phone":"+49 5732/73754",
    "sg:postcode":"32584",
    "sg:province":"Nordrhein-Westfalen",
    "wof:name":"Hema Bautenschutz Gmbh",
    "wof:placetype":"venue"
},
  "geometry": {"coordinates":[8.733499527,52.2168121338],"type":"Point"}
}