{
  "type": "Feature",
  "properties": {
    "iso:country":"DE",
    "sg:address":"Hebelstr. 3",
    "sg:city":"Mannheim",
    "sg:phone":"+49 621/10951",
    "sg:postcode":"68161",
    "sg:province":"Baden-W\u00fcrttemberg",
    "wof:name":"Hausmeister-service Lang Gmbh",
    "wof:placetype":"venue"
},
  "geometry": {"coordinates":[8.4767971039,49.4888343811],"type":"Point"}
}