{
  "type": "Feature",
  "properties": {
    "iso:country":"DE",
    "sg:address":"Paulinenstr. 49",
    "sg:city":"Stuttgart",
    "sg:phone":"+49 711/6150075",
    "sg:postcode":"70178",
    "sg:province":"Baden-W\u00fcrttemberg",
    "wof:name":"Gruber Und Fehrenbach Rechtsanw\u00e4lte",
    "wof:placetype":"venue"
},
  "geometry": {"coordinates":[9.1695957184,48.7732276917],"type":"Point"}
}