{
  "type": "Feature",
  "properties": {
    "iso:country":"DE",
    "sg:address":"Am Bahnhof",
    "sg:city":"Babenhausen",
    "sg:phone":"+49 8333/4296",
    "sg:postcode":"87727",
    "sg:province":"Bayern",
    "wof:name":"Raiffeisenbank Babenhausen-osterber",
    "wof:placetype":"venue"
},
  "geometry": {"coordinates":[10.248011,48.141544],"type":"Point"}
}