{
  "type": "Feature",
  "properties": {
    "iso:country":"DE",
    "sg:address":"Orterer Str. 27",
    "sg:city":"Kochel",
    "sg:phone":"+49 8851/5282",
    "sg:postcode":"82431",
    "sg:province":"Bayern",
    "wof:name":"Dr. Med. Annemarie Lohfeld Arzt F\u00fcr Allgemeinmedizin",
    "wof:placetype":"venue"
},
  "geometry": {"coordinates":[11.3483896255,47.6336212158],"type":"Point"}
}