{
  "type": "Feature",
  "properties": {
    "iso:country":"DE",
    "sg:address":"Tholenswehr 1a",
    "sg:city":"Emden",
    "sg:phone":"+49 4921/994000",
    "sg:postcode":"26725",
    "sg:province":"Niedersachsen",
    "wof:name":"Arnold Wenzel",
    "wof:placetype":"venue"
},
  "geometry": {"coordinates":[7.2251729965,53.3774986267],"type":"Point"}
}