{
  "type": "Feature",
  "properties": {
    "iso:country":"DE",
    "sg:address":"An der Stetze 12",
    "sg:city":"Kreuztal",
    "sg:phone":"+49 2732/8860",
    "sg:postcode":"57223",
    "sg:province":"Nordrhein-Westfalen",
    "wof:name":"P. A. B. Gmbh",
    "wof:placetype":"venue"
},
  "geometry": {"coordinates":[7.970646,50.974792],"type":"Point"}
}