{
  "type": "Feature",
  "properties": {
    "iso:country":"DE",
    "sg:address":"Raiffeisenstr. 1",
    "sg:city":"Minfeld",
    "sg:postcode":"76872",
    "sg:province":"Rheinland-Pfalz",
    "wof:name":"Acc Service U. Pflege Gmbh",
    "wof:placetype":"venue"
},
  "geometry": {"coordinates":[8.145568,49.070969],"type":"Point"}
}