{
  "type": "Feature",
  "properties": {
    "iso:country":"DE",
    "sg:address":"Pfaffenweg 6",
    "sg:city":"Eschwege",
    "sg:phone":"+49 5651/31714",
    "sg:postcode":"37269",
    "sg:province":"Hessen",
    "wof:name":"Ernst Herzog Ohg",
    "wof:placetype":"venue"
},
  "geometry": {"coordinates":[10.0663070679,51.1846313477],"type":"Point"}
}