{
  "type": "Feature",
  "properties": {
    "iso:country":"DE",
    "sg:address":"Grafenberger Allee 289",
    "sg:city":"D\u00fcsseldorf",
    "sg:phone":"+49 211/67070",
    "sg:postcode":"40237",
    "sg:province":"Nordrhein-Westfalen",
    "wof:name":"Gaz Gesellschaft F\u00fcr Akkreditierung Und",
    "wof:placetype":"venue"
},
  "geometry": {"coordinates":[6.819078,51.233932],"type":"Point"}
}