{
  "type": "Feature",
  "properties": {
    "iso:country":"DE",
    "sg:address":"Einern 126",
    "sg:city":"Wuppertal",
    "sg:phone":"+49 202/522301",
    "sg:postcode":"42279",
    "sg:province":"Nordrhein-Westfalen",
    "wof:name":"Walter St\u00f6cker",
    "wof:placetype":"venue"
},
  "geometry": {"coordinates":[7.212814,51.301861],"type":"Point"}
}