{
  "type": "Feature",
  "properties": {
    "iso:country":"DE",
    "sg:address":"Ernst-Th\u00e4lmann-Str. 7",
    "sg:city":"Gardelegen",
    "sg:phone":"+49 3907/2042",
    "sg:postcode":"39638",
    "sg:province":"Sachsen-Anhalt",
    "wof:name":"E. Hansmann",
    "wof:placetype":"venue"
},
  "geometry": {"coordinates":[11.3927316666,52.5257225037],"type":"Point"}
}