{
  "type": "Feature",
  "properties": {
    "iso:country":"DE",
    "sg:address":"Johannesflur 15",
    "sg:city":"Windischholzhausen",
    "sg:phone":"+49 361/416498",
    "sg:postcode":"99102",
    "sg:province":"Th\u00fcringen",
    "wof:name":"J\u00fcrgen Zerull",
    "wof:placetype":"venue"
},
  "geometry": {"coordinates":[11.0895299911,50.9461174011],"type":"Point"}
}