{
  "type": "Feature",
  "properties": {
    "iso:country":"DE",
    "sg:address":"Jahnstr. 40",
    "sg:city":"Wolfen",
    "sg:phone":"+49 3494/43035",
    "sg:postcode":"06766",
    "sg:province":"Sachsen-Anhalt",
    "wof:name":"K\u00f6hn Industrieservice- Gmbh",
    "wof:placetype":"venue"
},
  "geometry": {"coordinates":[12.269701,51.655537],"type":"Point"}
}