{
  "type": "Feature",
  "properties": {
    "iso:country":"DE",
    "sg:address":"Pattburger Bogen 27",
    "sg:city":"Harrislee",
    "sg:phone":"+49 461/7633",
    "sg:postcode":"24955",
    "sg:province":"Schleswig-Holstein",
    "wof:name":"Peter Fahl & Sohn Gmbh",
    "wof:placetype":"venue"
},
  "geometry": {"coordinates":[9.3763589859,54.8019714355],"type":"Point"}
}