{
  "type": "Feature",
  "properties": {
    "iso:country":"DE",
    "sg:address":"Max-Planck-Str. 7",
    "sg:city":"Dreieich",
    "sg:phone":"+49 6103/39040",
    "sg:postcode":"63303",
    "sg:province":"Hessen",
    "wof:name":"Delta Gmbh",
    "wof:placetype":"venue"
},
  "geometry": {"coordinates":[8.7042732239,50.02734375],"type":"Point"}
}