{
  "type": "Feature",
  "properties": {
    "iso:country":"DE",
    "sg:address":"Bubenorbiser Str.",
    "sg:city":"Mainhardt",
    "sg:phone":"+49 7903/3928",
    "sg:postcode":"74535",
    "sg:province":"Baden-W\u00fcrttemberg",
    "wof:name":"Bag Hohenlohe-raiffeisen-eg",
    "wof:placetype":"venue"
},
  "geometry": {"coordinates":[9.576655,49.090485],"type":"Point"}
}