{
  "type": "Feature",
  "properties": {
    "iso:country":"DE",
    "sg:address":"Hannoversche Str. 50",
    "sg:city":"Celle",
    "sg:phone":"+49 5141/214004",
    "sg:postcode":"29221",
    "sg:province":"Niedersachsen",
    "wof:name":"Heike Jablonsky Und Kollegen Rechtsanw\u00e4lte",
    "wof:placetype":"venue"
},
  "geometry": {"coordinates":[10.075381279,52.6186561584],"type":"Point"}
}