{
  "type": "Feature",
  "properties": {
    "iso:country":"DE",
    "sg:address":"Freiherr-vom-Stein-Str. 18r",
    "sg:city":"Neu-Isenburg",
    "sg:phone":"+49 6102/77793",
    "sg:postcode":"63263",
    "sg:province":"Hessen",
    "wof:name":"Wordstation Software- Und Dokumentations\u00fcbersetzung Und",
    "wof:placetype":"venue"
},
  "geometry": {"coordinates":[8.70287323,50.0529975891],"type":"Point"}
}