{
  "type": "Feature",
  "properties": {
    "iso:country":"DE",
    "sg:address":"Birkenwald 10",
    "sg:city":"Visbek",
    "sg:phone":"+49 4445/7649",
    "sg:postcode":"49429",
    "sg:province":"Niedersachsen",
    "wof:name":"Albert Siemer",
    "wof:placetype":"venue"
},
  "geometry": {"coordinates":[8.3172159195,52.8426094055],"type":"Point"}
}