{
  "type": "Feature",
  "properties": {
    "iso:country":"DE",
    "sg:address":"Im \u00c4hrenfeld 11",
    "sg:city":"Georgsmarienh\u00fctte",
    "sg:phone":"+49 541/59196",
    "sg:postcode":"49124",
    "sg:province":"Niedersachsen",
    "wof:name":"H\u00fclsmann & Giebmeyer Gmbh & Co.",
    "wof:placetype":"venue"
},
  "geometry": {"coordinates":[8.044055,52.23233],"type":"Point"}
}