{
  "type": "Feature",
  "properties": {
    "iso:country":"DE",
    "sg:address":"Westwall 43",
    "sg:city":"Stendal",
    "sg:phone":"+49 3931/212396",
    "sg:postcode":"39576",
    "sg:province":"Sachsen-Anhalt",
    "wof:name":"Dr. Med. Margarete Neumann",
    "wof:placetype":"venue"
},
  "geometry": {"coordinates":[11.859139,52.599827],"type":"Point"}
}