{
  "type": "Feature",
  "properties": {
    "iso:country":"DE",
    "sg:address":"Wilhelmstra\u00dfe 36",
    "sg:city":"Heidenheim",
    "sg:phone":"+49 7321/45663",
    "sg:postcode":"89518",
    "sg:province":"Baden-W\u00fcrttemberg",
    "wof:name":"Piano Pfaff",
    "wof:placetype":"venue"
},
  "geometry": {"coordinates":[10.146527,48.679398],"type":"Point"}
}