{
  "type": "Feature",
  "properties": {
    "iso:country":"DE",
    "sg:address":"Lochbachstr. 12",
    "sg:city":"Oberstdorf",
    "sg:postcode":"87561",
    "sg:province":"Bayern",
    "wof:name":"Cafe-restaurant Fa\u00dfnacht Inh. Josef Fa\u00dfnacht",
    "wof:placetype":"venue"
},
  "geometry": {"coordinates":[10.2410812378,47.4206085205],"type":"Point"}
}