{
  "type": "Feature",
  "properties": {
    "iso:country":"DE",
    "sg:address":"Vorderer Flo\u00dfanger 14",
    "sg:city":"Coburg",
    "sg:phone":"+49 9561/69188",
    "sg:postcode":"96450",
    "sg:province":"Bayern",
    "wof:name":"Vierlande Gastro-service Gmbh",
    "wof:placetype":"venue"
},
  "geometry": {"coordinates":[10.971004,50.270531],"type":"Point"}
}