{
  "type": "Feature",
  "properties": {
    "iso:country":"DE",
    "sg:address":"Gschnaidtstr. 11",
    "sg:city":"Deggendorf",
    "sg:phone":"+49 991/30066",
    "sg:postcode":"94469",
    "sg:province":"Bayern",
    "wof:name":"Karl Kainz Ingenieur",
    "wof:placetype":"venue"
},
  "geometry": {"coordinates":[12.9801187515,48.8139572144],"type":"Point"}
}