{
  "type": "Feature",
  "properties": {
    "iso:country":"DE",
    "sg:address":"Alte Lindenstr. 18",
    "sg:city":"Ehrenkirchen",
    "sg:phone":"+49 6171/79397",
    "sg:postcode":"79238",
    "sg:province":"Baden-W\u00fcrttemberg",
    "wof:name":"Friedrich W. T\u00f6pper Architekt",
    "wof:placetype":"venue"
},
  "geometry": {"coordinates":[7.75208,47.915569],"type":"Point"}
}