{
  "type": "Feature",
  "properties": {
    "iso:country":"DE",
    "sg:address":"Lenzener Chaussee 61",
    "sg:city":"Wittenberge",
    "sg:phone":"+49 3877/405850",
    "sg:postcode":"19322",
    "sg:province":"Brandenburg",
    "wof:name":"Restaurant Borkenk\u00e4fer'le",
    "wof:placetype":"venue"
},
  "geometry": {"coordinates":[11.7296924591,53.0009689331],"type":"Point"}
}