{
  "type": "Feature",
  "properties": {
    "iso:country":"DE",
    "sg:address":"Schleckerland",
    "sg:city":"Ehingen",
    "sg:postcode":"89579",
    "sg:province":"Baden-W\u00fcrttemberg",
    "wof:name":"Jeans Fritz",
    "wof:placetype":"venue"
},
  "geometry": {"coordinates":[9.72719,48.28207],"type":"Point"}
}