{
  "type": "Feature",
  "properties": {
    "iso:country":"DE",
    "sg:address":"H\u00f6henweg 27",
    "sg:city":"Nettersheim",
    "sg:phone":"+49 2486/284",
    "sg:postcode":"53947",
    "sg:province":"Nordrhein-Westfalen",
    "wof:name":"Bernadette Hein",
    "wof:placetype":"venue"
},
  "geometry": {"coordinates":[6.6250171661,50.4918670654],"type":"Point"}
}