{
  "type": "Feature",
  "properties": {
    "iso:country":"DE",
    "sg:address":"Am Steinberg 1",
    "sg:city":"Kitzingen",
    "sg:phone":"+49 9321/32885",
    "sg:postcode":"97318",
    "sg:province":"Bayern",
    "wof:name":"Joachim Gro\u00df",
    "wof:placetype":"venue"
},
  "geometry": {"coordinates":[10.204852,49.732296],"type":"Point"}
}