{
  "type": "Feature",
  "properties": {
    "iso:country":"DE",
    "sg:address":"Uferstr. 11",
    "sg:city":"Witten",
    "sg:phone":"+49 2302/30116",
    "sg:postcode":"58452",
    "sg:province":"Nordrhein-Westfalen",
    "wof:name":"Helmut Schulz Massagepraxis",
    "wof:placetype":"venue"
},
  "geometry": {"coordinates":[7.34282,51.42432],"type":"Point"}
}