{
  "type": "Feature",
  "properties": {
    "iso:country":"DE",
    "sg:address":"Karl-Marx-Str. 36",
    "sg:city":"L\u00fcbbenau",
    "sg:phone":"+49 3542/2276",
    "sg:postcode":"03222",
    "sg:province":"Brandenburg",
    "wof:name":"Wilhelm Otto",
    "wof:placetype":"venue"
},
  "geometry": {"coordinates":[13.98304,51.827961],"type":"Point"}
}