{
  "type": "Feature",
  "properties": {
    "iso:country":"DE",
    "sg:address":"Krumme Eiche 34",
    "sg:city":"Titz",
    "sg:phone":"+49 2463/1571",
    "sg:postcode":"52445",
    "sg:province":"Nordrhein-Westfalen",
    "wof:name":"Petra Hummelsheim",
    "wof:placetype":"venue"
},
  "geometry": {"coordinates":[6.459321022,50.9624252319],"type":"Point"}
}