{
  "type": "Feature",
  "properties": {
    "iso:country":"DE",
    "sg:address":"Vahrener Damm 8",
    "sg:city":"Cloppenburg",
    "sg:phone":"+49 4471/85340",
    "sg:postcode":"49661",
    "sg:province":"Niedersachsen",
    "wof:name":"Rugia Gastronomie-ein- Richtungsvertriebs Gmbh",
    "wof:placetype":"venue"
},
  "geometry": {"coordinates":[8.001889,52.827412],"type":"Point"}
}