{
  "type": "Feature",
  "properties": {
    "iso:country":"DE",
    "sg:address":"Br\u00fcckenstr 14",
    "sg:city":"Berlin",
    "sg:phone":"+49 30/2785076",
    "sg:postcode":"10179",
    "sg:province":"Berlin",
    "wof:name":"Abacus Consulting Gmbh",
    "wof:placetype":"venue"
},
  "geometry": {"coordinates":[13.4166479111,52.5118560791],"type":"Point"}
}