{
  "type": "Feature",
  "properties": {
    "iso:country":"DE",
    "sg:address":"Am Kulturhaus 8",
    "sg:city":"D\u00fctschow",
    "sg:phone":"+49 38726/20734",
    "sg:postcode":"19372",
    "sg:province":"Mecklenburg-Vorpommern",
    "wof:name":"Borng\u00e4sser",
    "wof:placetype":"venue"
},
  "geometry": {"coordinates":[11.6763553619,53.4033317566],"type":"Point"}
}