{
  "type": "Feature",
  "properties": {
    "iso:country":"DE",
    "sg:address":"Karl-Marx-Str. 27",
    "sg:city":"Unterma\u00dffeld",
    "sg:phone":"+49 36949/21546",
    "sg:postcode":"98617",
    "sg:province":"Th\u00fcringen",
    "wof:name":"Dr. Hermann Fickel Tierarzt",
    "wof:placetype":"venue"
},
  "geometry": {"coordinates":[10.4130573273,50.5345077515],"type":"Point"}
}