{
  "type": "Feature",
  "properties": {
    "iso:country":"DE",
    "sg:address":"Hanauer Landstr. 48a",
    "sg:city":"Frankfurt",
    "sg:phone":"+49 69/4970233",
    "sg:postcode":"60314",
    "sg:province":"Hessen",
    "wof:name":"Zvonko Turkali Architekt",
    "wof:placetype":"venue"
},
  "geometry": {"coordinates":[8.700947,50.112774],"type":"Point"}
}