{
  "type": "Feature",
  "properties": {
    "iso:country":"DE",
    "sg:address":"Haller Str. 27",
    "sg:city":"Rosenberg",
    "sg:phone":"+49 7967/1754",
    "sg:postcode":"73494",
    "sg:province":"Baden-W\u00fcrttemberg",
    "wof:name":"Rosa Geiger Hebamme",
    "wof:placetype":"venue"
},
  "geometry": {"coordinates":[10.028142,49.020416],"type":"Point"}
}