{
  "type": "Feature",
  "properties": {
    "iso:country":"DE",
    "sg:address":"Austr. 9",
    "sg:city":"Steinbach",
    "sg:phone":"+49 6171/74884",
    "sg:postcode":"61449",
    "sg:province":"Hessen",
    "wof:name":"Awf Allgemeine Wirtschafts- Und Finanzberatungsges. Mbh",
    "wof:placetype":"venue"
},
  "geometry": {"coordinates":[8.576166,50.168457],"type":"Point"}
}