{
  "type": "Feature",
  "properties": {
    "iso:country":"DE",
    "sg:address":"K\u00f6nigsberger Str. 2",
    "sg:city":"Hohenhameln",
    "sg:phone":"+49 5128/1030",
    "sg:postcode":"31249",
    "sg:province":"Niedersachsen",
    "wof:name":"Fr\u00f6scher Gmbh & Co. Kg",
    "wof:placetype":"venue"
},
  "geometry": {"coordinates":[10.112938,52.288593],"type":"Point"}
}