{
  "type": "Feature",
  "properties": {
    "iso:country":"DE",
    "sg:address":"Ludenberger Str. 39",
    "sg:city":"Erkrath",
    "sg:phone":"+49 211/2450020",
    "sg:postcode":"40699",
    "sg:province":"Nordrhein-Westfalen",
    "wof:name":"Dropmann Druck & Service Gmbh",
    "wof:placetype":"venue"
},
  "geometry": {"coordinates":[6.894951,51.22168],"type":"Point"}
}