{
  "type": "Feature",
  "properties": {
    "iso:country":"DE",
    "sg:address":"Sachsenstr. 12",
    "sg:city":"Holzwickede",
    "sg:phone":"+49 2301/4864",
    "sg:postcode":"59439",
    "sg:province":"Nordrhein-Westfalen",
    "wof:name":"K\u00f6nigsborn Getr\u00e4nkevertriebs Gmbh",
    "wof:placetype":"venue"
},
  "geometry": {"coordinates":[7.6244587898,51.5175170898],"type":"Point"}
}