{
  "type": "Feature",
  "properties": {
    "iso:country":"DE",
    "sg:address":"Steinfurther Hauptstr. 49",
    "sg:city":"Bad Nauheim",
    "sg:phone":"+49 6032/82144",
    "sg:postcode":"61231",
    "sg:province":"Hessen",
    "wof:name":"Hugo Huber",
    "wof:placetype":"venue"
},
  "geometry": {"coordinates":[8.744653,50.399693],"type":"Point"}
}