{
  "type": "Feature",
  "properties": {
    "iso:country":"DE",
    "sg:address":"Reinhold-Maier-Str. 5",
    "sg:city":"Balingen",
    "sg:phone":"+49 7433/381597",
    "sg:postcode":"72336",
    "sg:province":"Baden-W\u00fcrttemberg",
    "wof:name":"Jetter & Partner Immobilienmakler",
    "wof:placetype":"venue"
},
  "geometry": {"coordinates":[8.8735179901,48.2448654175],"type":"Point"}
}