{
  "type": "Feature",
  "properties": {
    "iso:country":"DE",
    "sg:address":"Ebbergstr.7",
    "sg:city":"Schwerte",
    "sg:phone":"+49 2304/67128",
    "sg:postcode":"58239",
    "sg:province":"Nordrhein-Westfalen",
    "wof:name":"Kongskilde Industrietechnik Gmbh",
    "wof:placetype":"venue"
},
  "geometry": {"coordinates":[7.5219187737,51.4232254028],"type":"Point"}
}