{
  "type": "Feature",
  "properties": {
    "iso:country":"DE",
    "sg:address":"Friedrich-Ebert-Ring 12",
    "sg:city":"Koblenz",
    "sg:phone":"+49 261/32467",
    "sg:postcode":"56068",
    "sg:province":"Rheinland-Pfalz",
    "wof:name":"Leis Und Ruland Rechtsanw\u00e4lte",
    "wof:placetype":"venue"
},
  "geometry": {"coordinates":[7.5967960358,50.3545227051],"type":"Point"}
}