{
  "type": "Feature",
  "properties": {
    "iso:country":"DE",
    "sg:address":"Blocker Str. 49",
    "sg:city":"Neuwied",
    "sg:phone":"+49 2622/82896",
    "sg:postcode":"56566",
    "sg:province":"Rheinland-Pfalz",
    "wof:name":"Hermann Blum",
    "wof:placetype":"venue"
},
  "geometry": {"coordinates":[7.52995,50.447529],"type":"Point"}
}