{
  "type": "Feature",
  "properties": {
    "iso:country":"DE",
    "sg:address":"Lange Str. 4",
    "sg:city":"Dorum",
    "sg:phone":"+49 4742/368",
    "sg:postcode":"27632",
    "sg:province":"Niedersachsen",
    "wof:name":"Brille & Mehr Gmbh",
    "wof:placetype":"venue"
},
  "geometry": {"coordinates":[8.567368,53.689034],"type":"Point"}
}