{
  "type": "Feature",
  "properties": {
    "iso:country":"DE",
    "sg:address":"Waldstr. 3",
    "sg:city":"Glash\u00fctten",
    "sg:phone":"+49 9279/976000",
    "sg:postcode":"95496",
    "sg:province":"Bayern",
    "wof:name":"Seniorenheim Glash\u00fctten",
    "wof:placetype":"venue"
},
  "geometry": {"coordinates":[11.447879,49.881161],"type":"Point"}
}