{
  "type": "Feature",
  "properties": {
    "iso:country":"DE",
    "sg:address":"Gerberau 4",
    "sg:city":"Freiburg",
    "sg:phone":"+49 761/382049",
    "sg:postcode":"79098",
    "sg:province":"Baden-W\u00fcrttemberg",
    "wof:name":"Becks Wohnetagen Inh. Ingrid Beck",
    "wof:placetype":"venue"
},
  "geometry": {"coordinates":[7.849286,47.993294],"type":"Point"}
}