{
  "type": "Feature",
  "properties": {
    "iso:country":"DE",
    "sg:address":"Lohhohl 24",
    "sg:city":"Linz",
    "sg:phone":"+49 2644/808318",
    "sg:postcode":"53545",
    "sg:province":"Rheinland-Pfalz",
    "wof:name":"M. Reul",
    "wof:placetype":"venue"
},
  "geometry": {"coordinates":[7.2806577682,50.5702400208],"type":"Point"}
}