{
  "type": "Feature",
  "properties": {
    "iso:country":"DE",
    "sg:address":"Kettelerstr. 16",
    "sg:city":"Schweinfurt",
    "sg:postcode":"97424",
    "sg:province":"Bayern",
    "wof:name":"B\u00f6llner Gmbh & Co. Kg",
    "wof:placetype":"venue"
},
  "geometry": {"coordinates":[10.2012453079,50.030708313],"type":"Point"}
}