{
  "type": "Feature",
  "properties": {
    "iso:country":"DE",
    "sg:address":"M\u00fchlstr. 192",
    "sg:city":"Pleinfeld",
    "sg:phone":"+49 9144/928880",
    "sg:postcode":"91785",
    "sg:province":"Bayern",
    "wof:name":"Fiegl Gmbh & Co.",
    "wof:placetype":"venue"
},
  "geometry": {"coordinates":[10.999685,49.122696],"type":"Point"}
}