{
  "type": "Feature",
  "properties": {
    "iso:country":"DE",
    "sg:address":"Ludwigstr. 4",
    "sg:city":"Sinn",
    "sg:phone":"+49 2772/53313",
    "sg:postcode":"35764",
    "sg:province":"Hessen",
    "wof:name":"B. Reuter & B. Weis",
    "wof:placetype":"venue"
},
  "geometry": {"coordinates":[8.32723,50.656227],"type":"Point"}
}