{
  "type": "Feature",
  "properties": {
    "iso:country":"DE",
    "sg:address":"Oberg\u00e4rten",
    "sg:city":"St\u00fchlingen",
    "sg:phone":"+49 7703/7820",
    "sg:postcode":"79780",
    "sg:province":"Baden-W\u00fcrttemberg",
    "wof:name":"Restaurant Obere Alp",
    "wof:placetype":"venue"
},
  "geometry": {"coordinates":[8.4252853394,47.7182502747],"type":"Point"}
}