{
  "type": "Feature",
  "properties": {
    "iso:country":"DE",
    "sg:address":"Stendaler Str. 16",
    "sg:city":"Tangerm\u00fcnde",
    "sg:phone":"+49 39322/43168",
    "sg:postcode":"39590",
    "sg:province":"Sachsen-Anhalt",
    "wof:name":"G\u00e4stehaus Frank G\u00f6rges",
    "wof:placetype":"venue"
},
  "geometry": {"coordinates":[11.9642343521,52.5426063538],"type":"Point"}
}