{
  "type": "Feature",
  "properties": {
    "iso:country":"DE",
    "sg:address":"Darsberger Weg 20",
    "sg:city":"Sch\u00f6nau",
    "sg:phone":"+49 6228/1485",
    "sg:postcode":"69250",
    "sg:province":"Baden-W\u00fcrttemberg",
    "wof:name":"R. & L. Haus- Und Gewerbebau Gmbh",
    "wof:placetype":"venue"
},
  "geometry": {"coordinates":[8.8162260056,49.4372062683],"type":"Point"}
}