{
  "type": "Feature",
  "properties": {
    "iso:country":"DE",
    "sg:address":"Koloniestr. 15",
    "sg:city":"Moormerland",
    "sg:phone":"+49 4954/4704",
    "sg:postcode":"26802",
    "sg:province":"Niedersachsen",
    "wof:name":"H. Und E. Kramer",
    "wof:placetype":"venue"
},
  "geometry": {"coordinates":[7.4923901558,53.2916870117],"type":"Point"}
}