{
  "type": "Feature",
  "properties": {
    "iso:country":"DE",
    "sg:address":"Hagener Str. 261",
    "sg:city":"Kreuztal",
    "sg:phone":"+49 2732/8800",
    "sg:postcode":"57223",
    "sg:province":"Nordrhein-Westfalen",
    "wof:name":"Krombacher Brauerei Vertriebs- Und Verwaltungs Gmbh",
    "wof:placetype":"venue"
},
  "geometry": {"coordinates":[7.956552,50.991257],"type":"Point"}
}