{
  "type": "Feature",
  "properties": {
    "iso:country":"DE",
    "sg:address":"Ortsstr. 19",
    "sg:city":"Oppurg",
    "sg:phone":"+49 3647/413430",
    "sg:postcode":"07381",
    "sg:province":"Th\u00fcringen",
    "wof:name":"Ralf Deistler",
    "wof:placetype":"venue"
},
  "geometry": {"coordinates":[11.670487,50.719398],"type":"Point"}
}