{
  "type": "Feature",
  "properties": {
    "iso:country":"DE",
    "sg:address":"Bgm-Weidemaier-Str 66",
    "sg:city":"Leimen",
    "sg:phone":"+49 6224/71749",
    "sg:postcode":"69181",
    "sg:province":"Baden-W\u00fcrttemberg",
    "wof:name":"Penny",
    "wof:placetype":"venue"
},
  "geometry": {"coordinates":[8.6878557205,49.3479537964],"type":"Point"}
}