{
  "type": "Feature",
  "properties": {
    "iso:country":"DE",
    "sg:address":"L\u00fcner Weg 2",
    "sg:city":"L\u00fcneburg",
    "sg:phone":"+49 4131/89150",
    "sg:postcode":"21337",
    "sg:province":"Niedersachsen",
    "wof:name":"L\u00fcnebest Molkerei L\u00fcneburg Hans Stamer Gmbh & Co. Kg",
    "wof:placetype":"venue"
},
  "geometry": {"coordinates":[10.4183530807,53.2518310547],"type":"Point"}
}