{
  "type": "Feature",
  "properties": {
    "iso:country":"DE",
    "sg:address":"Wildnis 12",
    "sg:city":"Herzogenrath",
    "sg:phone":"+49 2406/6999",
    "sg:postcode":"52134",
    "sg:province":"Nordrhein-Westfalen",
    "wof:name":"J. Winters",
    "wof:placetype":"venue"
},
  "geometry": {"coordinates":[6.096121,50.89386],"type":"Point"}
}