{
  "type": "Feature",
  "properties": {
    "iso:country":"DE",
    "sg:address":"Obermarkt 5",
    "sg:city":"Murnau",
    "sg:phone":"+49 8841/9507",
    "sg:postcode":"82418",
    "sg:province":"Bayern",
    "wof:name":"Die Linie Ulrike Thoma",
    "wof:placetype":"venue"
},
  "geometry": {"coordinates":[11.200782,47.67865],"type":"Point"}
}