{
  "type": "Feature",
  "properties": {
    "iso:country":"DE",
    "sg:address":"Pr\u00f6bstinger Busch 14",
    "sg:city":"Borken",
    "sg:phone":"+49 2861/7870",
    "sg:postcode":"46325",
    "sg:province":"Nordrhein-Westfalen",
    "wof:name":"Erholungsgebiet Dingdener Heide Paul Kathage & Co. Gmbh",
    "wof:placetype":"venue"
},
  "geometry": {"coordinates":[6.7859501839,51.8322525024],"type":"Point"}
}