{
  "type": "Feature",
  "properties": {
    "iso:country":"DE",
    "sg:address":"Adlerstr. 21",
    "sg:city":"Ehingen",
    "sg:phone":"+49 7391/2244",
    "sg:postcode":"89584",
    "sg:province":"Baden-W\u00fcrttemberg",
    "wof:name":"Ferdinand G\u00f6hmann",
    "wof:placetype":"venue"
},
  "geometry": {"coordinates":[9.706659,48.289837],"type":"Point"}
}