{
  "type": "Feature",
  "properties": {
    "iso:country":"DE",
    "sg:address":"Leipziger Str. 15",
    "sg:city":"Weiterstadt",
    "sg:phone":"+49 6150/14606",
    "sg:postcode":"64331",
    "sg:province":"Hessen",
    "wof:name":"Kosmetik-institut",
    "wof:placetype":"venue"
},
  "geometry": {"coordinates":[8.575279,49.91394],"type":"Point"}
}