{
  "type": "Feature",
  "properties": {
    "iso:country":"DE",
    "sg:address":"Gustav-Vorsteher-Str. 32",
    "sg:city":"Wetter",
    "sg:phone":"+49 2335/4458",
    "sg:postcode":"58300",
    "sg:province":"Nordrhein-Westfalen",
    "wof:name":"Wilfried Kallenbach",
    "wof:placetype":"venue"
},
  "geometry": {"coordinates":[7.396952,51.383999],"type":"Point"}
}