{
  "type": "Feature",
  "properties": {
    "iso:country":"DE",
    "sg:address":"Goethestr 44",
    "sg:city":"Bremerhaven",
    "sg:phone":"+49 471/43029",
    "sg:postcode":"27576",
    "sg:province":"Bremen",
    "wof:name":"Sicherheitstechnik Sperling Hochfeld Gmbh",
    "wof:placetype":"venue"
},
  "geometry": {"coordinates":[8.5805635452,53.5566291809],"type":"Point"}
}