{
  "type": "Feature",
  "properties": {
    "iso:country":"DE",
    "sg:address":"Mittelweg 1",
    "sg:city":"D\u00fclmen",
    "sg:phone":"+49 2594/2511",
    "sg:postcode":"48249",
    "sg:province":"Nordrhein-Westfalen",
    "wof:name":"M\u00f6llers Verwaltungs- Und",
    "wof:placetype":"venue"
},
  "geometry": {"coordinates":[7.1997799873,51.8491325378],"type":"Point"}
}