{
  "type": "Feature",
  "properties": {
    "iso:country":"DE",
    "sg:address":"Warftstr. 14",
    "sg:city":"D\u00f6mitz",
    "sg:phone":"+49 38758/24704",
    "sg:postcode":"19303",
    "sg:province":"Mecklenburg-Vorpommern",
    "wof:name":"E. Tank",
    "wof:placetype":"venue"
},
  "geometry": {"coordinates":[11.267345,53.138382],"type":"Point"}
}