{
  "type": "Feature",
  "properties": {
    "iso:country":"DE",
    "sg:address":"Schlesischer Platz 5b",
    "sg:city":"K\u00f6ln",
    "sg:phone":"+49 221/7409031",
    "sg:postcode":"50737",
    "sg:province":"Nordrhein-Westfalen",
    "wof:name":"Gwg K\u00f6ln-nord Gemeinn\u00fctzige Wohnungsgenossenschaft",
    "wof:placetype":"venue"
},
  "geometry": {"coordinates":[6.9503850937,50.9771652222],"type":"Point"}
}