{
  "type": "Feature",
  "properties": {
    "iso:country":"DE",
    "sg:address":"Gainharting 3a",
    "sg:city":"Trostberg",
    "sg:phone":"+49 180 5 324247",
    "sg:postcode":"83308",
    "sg:province":"Bayern",
    "wof:name":"Fcw Flight Consult Worldwide Travel Gmbh",
    "wof:placetype":"venue"
},
  "geometry": {"coordinates":[12.5328330994,48.0373802185],"type":"Point"}
}