{
  "type": "Feature",
  "properties": {
    "iso:country":"DE",
    "sg:address":"Karl-Marx-Str. 39",
    "sg:city":"Ostseebad Wustrow",
    "sg:phone":"+49 38220/305",
    "sg:postcode":"18347",
    "sg:province":"Mecklenburg-Vorpommern",
    "wof:name":"Karl-heinz K\u00f6ster Ingenieur",
    "wof:placetype":"venue"
},
  "geometry": {"coordinates":[12.3983802795,54.348941803],"type":"Point"}
}