{
  "type": "Feature",
  "properties": {
    "iso:country":"DE",
    "sg:address":"Mittelstr. 8",
    "sg:city":"Westfehmarn",
    "sg:phone":"+49 4372/332",
    "sg:postcode":"23769",
    "sg:province":"Schleswig-Holstein",
    "wof:name":"Hermann Westphal",
    "wof:placetype":"venue"
},
  "geometry": {"coordinates":[11.09954,54.439781],"type":"Point"}
}