{
  "type": "Feature",
  "properties": {
    "iso:country":"DE",
    "sg:address":"Hanns-Martin-Schleyer-Str. 8",
    "sg:city":"Sindelfingen",
    "sg:phone":"+49 7031/9350",
    "sg:postcode":"71063",
    "sg:province":"Baden-W\u00fcrttemberg",
    "wof:name":"Hotel-betriebs Gmbh Sindelfingen",
    "wof:placetype":"venue"
},
  "geometry": {"coordinates":[8.9999904633,48.7041549683],"type":"Point"}
}