{
  "type": "Feature",
  "properties": {
    "iso:country":"DE",
    "sg:address":"In der Au 30",
    "sg:city":"Karlsbad",
    "sg:phone":"+49 7202/3757",
    "sg:postcode":"76307",
    "sg:province":"Baden-W\u00fcrttemberg",
    "wof:name":"Dr. Med. Volker Baral",
    "wof:placetype":"venue"
},
  "geometry": {"coordinates":[8.5308837891,48.9412345886],"type":"Point"}
}