{
  "type": "Feature",
  "properties": {
    "iso:country":"DE",
    "sg:city":"Pritzwalk",
    "sg:postcode":"16928",
    "sg:province":"Brandenburg",
    "wof:name":"Tierzucht Gro\u00df Langerwisch Gmbh",
    "wof:placetype":"venue"
},
  "geometry": {"coordinates":[12.17473,53.15062],"type":"Point"}
}