{
  "type": "Feature",
  "properties": {
    "iso:country":"DE",
    "sg:address":"Peuerlstr. 8",
    "sg:city":"Weiden",
    "sg:phone":"+49 961/6344844",
    "sg:postcode":"92637",
    "sg:province":"Bayern",
    "wof:name":"Future 2 Web Gmbh & Co. Kg",
    "wof:placetype":"venue"
},
  "geometry": {"coordinates":[12.155292,49.679752],"type":"Point"}
}