{
  "type": "Feature",
  "properties": {
    "iso:country":"DE",
    "sg:address":"Hartenthaler Str. 19a",
    "sg:city":"Bad W\u00f6rishofen",
    "sg:phone":"+49 8247/32072",
    "sg:postcode":"86825",
    "sg:province":"Bayern",
    "wof:name":"Praxis Kohlmeier Und Prof.dr.med. Pries",
    "wof:placetype":"venue"
},
  "geometry": {"coordinates":[10.5829687119,47.9996185303],"type":"Point"}
}