{
  "type": "Feature",
  "properties": {
    "iso:country":"DE",
    "sg:address":"Wettringener Str. 1",
    "sg:city":"Metelen",
    "sg:phone":"+49 2556/283",
    "sg:postcode":"48629",
    "sg:province":"Nordrhein-Westfalen",
    "wof:name":"Wilhelm Rose",
    "wof:placetype":"venue"
},
  "geometry": {"coordinates":[7.220284,52.145359],"type":"Point"}
}