{
  "type": "Feature",
  "properties": {
    "iso:country":"DE",
    "sg:address":"Lichtenfelser Str. 58",
    "sg:city":"Hallstadt",
    "sg:phone":"+49 951/972360",
    "sg:postcode":"96103",
    "sg:province":"Bayern",
    "wof:name":"Otmar H\u00fcmmer Steuerberater",
    "wof:placetype":"venue"
},
  "geometry": {"coordinates":[10.8819961548,49.9318885803],"type":"Point"}
}