{
  "type": "Feature",
  "properties": {
    "iso:country":"DE",
    "sg:address":"Breslauer Str. 3",
    "sg:city":"Kirchbrak",
    "sg:phone":"+49 5533/1634",
    "sg:postcode":"37619",
    "sg:province":"Niedersachsen",
    "wof:name":"G. Grodowski Bau Gmbh",
    "wof:placetype":"venue"
},
  "geometry": {"coordinates":[9.567948,51.964371],"type":"Point"}
}