{
  "type": "Feature",
  "properties": {
    "iso:country":"DE",
    "sg:address":"Max-Planck-Str. 28",
    "sg:city":"Bad Salzuflen",
    "sg:phone":"+49 5222/58886",
    "sg:postcode":"32107",
    "sg:province":"Nordrhein-Westfalen",
    "wof:name":"Aug. Drexhage Metallbau Schlosserei Seit 1927",
    "wof:placetype":"venue"
},
  "geometry": {"coordinates":[8.7613191605,52.0372924805],"type":"Point"}
}