{
  "type": "Feature",
  "properties": {
    "iso:country":"DE",
    "sg:address":"Stetteritzring 119",
    "sg:city":"Ro\u00dfdorf",
    "sg:phone":"+49 6071/74393",
    "sg:postcode":"64380",
    "sg:province":"Hessen",
    "wof:name":"Ws Projektges. Mbh & Co. Entwicklungs Kg",
    "wof:placetype":"venue"
},
  "geometry": {"coordinates":[8.7942657471,49.8664169312],"type":"Point"}
}