{
  "type": "Feature",
  "properties": {
    "iso:country":"DE",
    "sg:address":"Harzer Str. 44",
    "sg:city":"Bremen",
    "sg:phone":"+49 421/480462",
    "sg:postcode":"28307",
    "sg:province":"Bremen",
    "wof:name":"Gregor Budelmann",
    "wof:placetype":"venue"
},
  "geometry": {"coordinates":[8.9125862122,53.0445022583],"type":"Point"}
}