{
  "type": "Feature",
  "properties": {
    "iso:country":"DE",
    "sg:address":"Altenburger Str. 64",
    "sg:city":"Waldenburg",
    "sg:phone":"+49 37608/22597",
    "sg:postcode":"08396",
    "sg:province":"Sachsen",
    "wof:name":"B. Zoladkiewicz",
    "wof:placetype":"venue"
},
  "geometry": {"coordinates":[12.593704,50.878223],"type":"Point"}
}