{
  "type": "Feature",
  "properties": {
    "iso:country":"DE",
    "sg:address":"Wachlange 53",
    "sg:city":"H\u00f6xter",
    "sg:phone":"+49 5257/32671",
    "sg:postcode":"37671",
    "sg:province":"Nordrhein-Westfalen",
    "wof:name":"G. Warnecke",
    "wof:placetype":"venue"
},
  "geometry": {"coordinates":[9.3920755386,51.8219642639],"type":"Point"}
}