{
  "type": "Feature",
  "properties": {
    "iso:country":"DE",
    "sg:address":"Stra\u00dfheimer Weg 49",
    "sg:city":"Rosbach",
    "sg:postcode":"61191",
    "sg:province":"Hessen",
    "wof:name":"Donau Trading Und Consulting Gmbh",
    "wof:placetype":"venue"
},
  "geometry": {"coordinates":[8.6958303452,50.3083267212],"type":"Point"}
}