{
  "type": "Feature",
  "properties": {
    "iso:country":"DE",
    "sg:address":"Brandenbergstr. 32",
    "sg:city":"Todtnau",
    "sg:phone":"+49 7671/455",
    "sg:postcode":"79674",
    "sg:province":"Baden-W\u00fcrttemberg",
    "wof:name":"Albert Dr\u00e4ndle",
    "wof:placetype":"venue"
},
  "geometry": {"coordinates":[7.954047,47.83131],"type":"Point"}
}