{
  "type": "Feature",
  "properties": {
    "iso:country":"DE",
    "sg:address":"Ostendstra\u00dfe 3",
    "sg:city":"Pfungstadt",
    "sg:phone":"+49 6157/806404",
    "sg:postcode":"64319",
    "sg:province":"Hessen",
    "wof:name":"Private Fernfachhochschule Darmstadt",
    "wof:placetype":"venue"
},
  "geometry": {"coordinates":[8.615856,49.813187],"type":"Point"}
}