{
  "type": "Feature",
  "properties": {
    "iso:country":"DE",
    "sg:address":"Elbchaussee 183a",
    "sg:city":"Hamburg",
    "sg:phone":"+49 40/8803243",
    "sg:postcode":"22605",
    "sg:province":"Hamburg",
    "wof:name":"Kurt P. Schuhmann Kg",
    "wof:placetype":"venue"
},
  "geometry": {"coordinates":[9.9073228836,53.5456886292],"type":"Point"}
}