{
  "type": "Feature",
  "properties": {
    "iso:country":"DE",
    "sg:address":"Hannoversche Str. 60",
    "sg:city":"Braunschweig",
    "sg:phone":"+49 531/52080",
    "sg:postcode":"38116",
    "sg:province":"Niedersachsen",
    "wof:name":"Von Dammsche Stiftung",
    "wof:placetype":"venue"
},
  "geometry": {"coordinates":[10.4949703217,52.2722015381],"type":"Point"}
}