{
  "type": "Feature",
  "properties": {
    "iso:country":"DE",
    "sg:address":"Breite Str. 4",
    "sg:city":"Recklinghausen",
    "sg:phone":"+49 2361/18050",
    "sg:postcode":"45657",
    "sg:province":"Nordrhein-Westfalen",
    "wof:name":"Recklingh\u00e4user Zeitung",
    "wof:placetype":"venue"
},
  "geometry": {"coordinates":[7.197712,51.61375],"type":"Point"}
}