{
  "type": "Feature",
  "properties": {
    "iso:country":"DE",
    "sg:address":"Irler Str. 23",
    "sg:city":"Solingen",
    "sg:phone":"+49 212/314233",
    "sg:postcode":"42719",
    "sg:province":"Nordrhein-Westfalen",
    "wof:name":"Picard & Co. Gmbh",
    "wof:placetype":"venue"
},
  "geometry": {"coordinates":[7.0579161644,51.1905822754],"type":"Point"}
}