{
  "type": "Feature",
  "properties": {
    "iso:country":"DE",
    "sg:address":"Neurather Str. 17",
    "sg:city":"Grevenbroich",
    "sg:phone":"+49 2181/5970",
    "sg:postcode":"41515",
    "sg:province":"Nordrhein-Westfalen",
    "wof:name":"Josef Selan",
    "wof:placetype":"venue"
},
  "geometry": {"coordinates":[6.627877,51.064396],"type":"Point"}
}