{
  "type": "Feature",
  "properties": {
    "iso:country":"DE",
    "sg:address":"Friedensstr. 7",
    "sg:city":"Karlstein",
    "sg:phone":"+49 6188/990809",
    "sg:postcode":"63791",
    "sg:province":"Bayern",
    "wof:name":"Restaurant Stehkragen",
    "wof:placetype":"venue"
},
  "geometry": {"coordinates":[9.0384550095,50.0398635864],"type":"Point"}
}