{
  "type": "Feature",
  "properties": {
    "iso:country":"DE",
    "sg:address":"Regensburger Str. 12",
    "sg:city":"Falkenstein",
    "sg:phone":"+49 9462/5292",
    "sg:postcode":"93167",
    "sg:province":"Bayern",
    "wof:name":"Neukauf",
    "wof:placetype":"venue"
},
  "geometry": {"coordinates":[12.4833087921,49.0966415405],"type":"Point"}
}