{
  "type": "Feature",
  "properties": {
    "iso:country":"DE",
    "sg:address":"Auf dem Saal 29",
    "sg:city":"Wendelsheim",
    "sg:phone":"+49 6734/1009",
    "sg:postcode":"55234",
    "sg:province":"Rheinland-Pfalz",
    "wof:name":"Nature And Regulatory Services Beratungsgesellschaft Mbh",
    "wof:placetype":"venue"
},
  "geometry": {"coordinates":[7.998363018,49.765007019],"type":"Point"}
}