{
  "type": "Feature",
  "properties": {
    "iso:country":"DE",
    "sg:address":"Schneeberger Str. 87",
    "sg:city":"Schwarzenberg",
    "sg:phone":"+49 3774/26022",
    "sg:postcode":"08340",
    "sg:province":"Sachsen",
    "wof:name":"Uni-hydraulik Gmbh",
    "wof:placetype":"venue"
},
  "geometry": {"coordinates":[12.763695,50.552238],"type":"Point"}
}