{
  "type": "Feature",
  "properties": {
    "iso:country":"DE",
    "sg:address":"Rheiner Str. 151",
    "sg:city":"Lingen",
    "sg:phone":"+49 591/58090",
    "sg:postcode":"49809",
    "sg:province":"Niedersachsen",
    "wof:name":"Rbl Zweiradvertrieb Gmbh",
    "wof:placetype":"venue"
},
  "geometry": {"coordinates":[7.324441,52.502377],"type":"Point"}
}