{
  "type": "Feature",
  "properties": {
    "iso:country":"DE",
    "sg:address":"Pfauenstr. 12",
    "sg:city":"Aalen",
    "sg:phone":"+49 7361/41960",
    "sg:postcode":"73434",
    "sg:province":"Baden-W\u00fcrttemberg",
    "wof:name":"Hermann Kunick Tanzschule",
    "wof:placetype":"venue"
},
  "geometry": {"coordinates":[10.0528488159,48.8325576782],"type":"Point"}
}