{
  "type": "Feature",
  "properties": {
    "iso:country":"DE",
    "sg:address":"Bahnhofstr. 24",
    "sg:city":"Morsbach",
    "sg:phone":"+49 2294/7158",
    "sg:postcode":"51597",
    "sg:province":"Nordrhein-Westfalen",
    "wof:name":"H. Breiderhoff",
    "wof:placetype":"venue"
},
  "geometry": {"coordinates":[7.72438,50.864445],"type":"Point"}
}