{
  "type": "Feature",
  "properties": {
    "iso:country":"DE",
    "sg:address":"Hauptstr. 67",
    "sg:city":"Ha\u00dfbergen",
    "sg:phone":"+49 5024/293",
    "sg:postcode":"31626",
    "sg:province":"Niedersachsen",
    "wof:name":"Dalli Fri\u00df",
    "wof:placetype":"venue"
},
  "geometry": {"coordinates":[9.2298221588,52.7286605835],"type":"Point"}
}