{
  "type": "Feature",
  "properties": {
    "iso:country":"DE",
    "sg:address":"Wei\u00dfachener Str. 24",
    "sg:city":"Bergen",
    "sg:phone":"+49 8662/8353",
    "sg:postcode":"83346",
    "sg:province":"Bayern",
    "wof:name":"Josef Viehhauser",
    "wof:placetype":"venue"
},
  "geometry": {"coordinates":[12.5847663879,47.8069534302],"type":"Point"}
}