{
  "type": "Feature",
  "properties": {
    "iso:country":"DE",
    "sg:address":"Seegartenstr. 9",
    "sg:city":"Messel",
    "sg:phone":"+49 6159/390",
    "sg:postcode":"64409",
    "sg:province":"Hessen",
    "wof:name":"A. Volk",
    "wof:placetype":"venue"
},
  "geometry": {"coordinates":[8.7411642075,49.9373168945],"type":"Point"}
}