{
  "type": "Feature",
  "properties": {
    "iso:country":"DE",
    "sg:address":"An Peters Ziegelei",
    "sg:city":"Wiesbaden",
    "sg:phone":"+49 611/9505511",
    "sg:postcode":"65201",
    "sg:province":"Hessen",
    "wof:name":"J\u00fcrgen Maurer",
    "wof:placetype":"venue"
},
  "geometry": {"coordinates":[8.2023954391,50.0469207764],"type":"Point"}
}