{
  "type": "Feature",
  "properties": {
    "iso:country":"DE",
    "sg:address":"Werkstr.",
    "sg:city":"Gro\u00dfkayna",
    "sg:postcode":"06242",
    "sg:province":"Sachsen-Anhalt",
    "wof:name":"Sbc Strahl- Und Beschichtungscentrum Gmbh",
    "wof:placetype":"venue"
},
  "geometry": {"coordinates":[11.944805,51.288902],"type":"Point"}
}