{
  "type": "Feature",
  "properties": {
    "iso:country":"DE",
    "sg:address":"Esserstr. 10",
    "sg:city":"H\u00fcrth",
    "sg:phone":"+49 2233/65716",
    "sg:postcode":"50354",
    "sg:province":"Nordrhein-Westfalen",
    "wof:name":"Ch. N\u00f6lke",
    "wof:placetype":"venue"
},
  "geometry": {"coordinates":[6.895554,50.895752],"type":"Point"}
}