{
  "type": "Feature",
  "properties": {
    "iso:country":"DE",
    "sg:address":"Gustav-Stresemann-Str. 3",
    "sg:city":"Schwetzingen",
    "sg:phone":"+49 6202/29573",
    "sg:postcode":"68723",
    "sg:province":"Baden-W\u00fcrttemberg",
    "wof:name":"Kaiser & Mathis Elektro Gmbh",
    "wof:placetype":"venue"
},
  "geometry": {"coordinates":[8.570236,49.392357],"type":"Point"}
}