{
  "type": "Feature",
  "properties": {
    "iso:country":"DE",
    "sg:address":"Elbinger STr. 57",
    "sg:city":"Backnang",
    "sg:postcode":"71522",
    "sg:province":"Baden-W\u00fcrttemberg",
    "wof:name":"Island Aktuell",
    "wof:placetype":"venue"
},
  "geometry": {"coordinates":[9.444502,48.956196],"type":"Point"}
}