{
  "type": "Feature",
  "properties": {
    "iso:country":"DE",
    "sg:address":"Willf\u00fchrstr. 4",
    "sg:city":"Hannover",
    "sg:phone":"+49 511/835034",
    "sg:postcode":"30459",
    "sg:province":"Niedersachsen",
    "wof:name":"A. Schwarz Kg",
    "wof:placetype":"venue"
},
  "geometry": {"coordinates":[9.7275819778,52.3484344482],"type":"Point"}
}