{
  "type": "Feature",
  "properties": {
    "iso:country":"DE",
    "sg:address":"Ilmnitzer Landstr. 1",
    "sg:city":"Z\u00f6llnitz",
    "sg:phone":"+49 3641/380243",
    "sg:postcode":"07751",
    "sg:province":"Th\u00fcringen",
    "wof:name":"Raab Karcher Baustoff-fliesen Sanit\u00e4rhandel Gera Gmbh",
    "wof:placetype":"venue"
},
  "geometry": {"coordinates":[11.64093,50.877411],"type":"Point"}
}