{
  "type": "Feature",
  "properties": {
    "iso:country":"DE",
    "sg:address":"Boschstr. 16",
    "sg:city":"Winsen",
    "sg:postcode":"21423",
    "sg:province":"Niedersachsen",
    "wof:name":"Qualimed Innovative Medizinprodukte Gmbh",
    "wof:placetype":"venue"
},
  "geometry": {"coordinates":[10.23185,53.371655],"type":"Point"}
}