{
  "type": "Feature",
  "properties": {
    "iso:country":"DE",
    "sg:address":"Schillerstr. 30",
    "sg:city":"J\u00fcterbog",
    "sg:phone":"+49 3372/403442",
    "sg:postcode":"14913",
    "sg:province":"Brandenburg",
    "wof:name":"Blumeneck",
    "wof:placetype":"venue"
},
  "geometry": {"coordinates":[13.078332,51.993122],"type":"Point"}
}