{
  "type": "Feature",
  "properties": {
    "iso:country":"DE",
    "sg:address":"Am Maibusch 102",
    "sg:city":"Gelsenkirchen",
    "sg:phone":"+49 209/941390",
    "sg:postcode":"45883",
    "sg:province":"Nordrhein-Westfalen",
    "wof:name":"Heide Pumpen Gmbh",
    "wof:placetype":"venue"
},
  "geometry": {"coordinates":[7.070035,51.524014],"type":"Point"}
}