{
  "type": "Feature",
  "properties": {
    "iso:country":"DE",
    "sg:address":"Hungenbach 6",
    "sg:city":"K\u00fcrten",
    "sg:phone":"+49 2268/1591",
    "sg:postcode":"51515",
    "sg:province":"Nordrhein-Westfalen",
    "wof:name":"Kreuzfeldt & Gregor Gmbh & Co. Kg Bergische Indus-",
    "wof:placetype":"venue"
},
  "geometry": {"coordinates":[7.262971,51.032578],"type":"Point"}
}