{
  "type": "Feature",
  "properties": {
    "iso:country":"DE",
    "sg:address":"Hauptstr. 79",
    "sg:city":"Sundern",
    "sg:phone":"+49 2933/789747",
    "sg:postcode":"59846",
    "sg:province":"Nordrhein-Westfalen",
    "wof:name":"Loft 79 Woman Fashion Angelika Schulte E. K.",
    "wof:placetype":"venue"
},
  "geometry": {"coordinates":[8.004298,51.327625],"type":"Point"}
}