{
  "type": "Feature",
  "properties": {
    "iso:country":"DE",
    "sg:address":"T\u00fcbinger Str. 10",
    "sg:city":"Deckenpfronn",
    "sg:phone":"+49 7056/8894",
    "sg:postcode":"75392",
    "sg:province":"Baden-W\u00fcrttemberg",
    "wof:name":"Dongus Ladenbau Und K\u00e4ltetechnik Gmbh",
    "wof:placetype":"venue"
},
  "geometry": {"coordinates":[8.815407,48.651211],"type":"Point"}
}