{
  "type": "Feature",
  "properties": {
    "iso:country":"DE",
    "sg:address":"Richthofenstr. 31",
    "sg:city":"Kiel",
    "sg:phone":"+49 431/36893",
    "sg:postcode":"24159",
    "sg:province":"Schleswig-Holstein",
    "wof:name":"Hans-georg Dreger Architekt",
    "wof:placetype":"venue"
},
  "geometry": {"coordinates":[10.140838,54.372166],"type":"Point"}
}