{
  "type": "Feature",
  "properties": {
    "iso:country":"DE",
    "sg:address":"Lange Str. 1",
    "sg:city":"Friesoythe",
    "sg:phone":"+49 4491/2279",
    "sg:postcode":"26169",
    "sg:province":"Niedersachsen",
    "wof:name":"Manfred Gamers",
    "wof:placetype":"venue"
},
  "geometry": {"coordinates":[7.8543977737,53.0299377441],"type":"Point"}
}