{
  "type": "Feature",
  "properties": {
    "iso:country":"DE",
    "sg:address":"Schweinfurter Str. 25",
    "sg:city":"Schwebheim",
    "sg:phone":"+49 9723/3558",
    "sg:postcode":"97525",
    "sg:province":"Bayern",
    "wof:name":"M. M\u00fcller",
    "wof:placetype":"venue"
},
  "geometry": {"coordinates":[10.2435789108,49.9997901917],"type":"Point"}
}