{
  "type": "Feature",
  "properties": {
    "iso:country":"DE",
    "sg:address":"Bessemerstr. 7",
    "sg:city":"Frankfurt",
    "sg:phone":"+49 6109/31314",
    "sg:postcode":"60388",
    "sg:province":"Hessen",
    "wof:name":"Bauer & Gutmann Pr\u00e4zizionsdrehteile Gmbh",
    "wof:placetype":"venue"
},
  "geometry": {"coordinates":[8.7499685287,50.1427841187],"type":"Point"}
}