{
  "type": "Feature",
  "properties": {
    "iso:country":"DE",
    "sg:address":"Immenst\u00e4dter Str. 4",
    "sg:city":"Waltenhofen",
    "sg:phone":"+49 8303/331",
    "sg:postcode":"87448",
    "sg:province":"Bayern",
    "wof:name":"M. Waluga",
    "wof:placetype":"venue"
},
  "geometry": {"coordinates":[10.302998,47.670662],"type":"Point"}
}