{
  "type": "Feature",
  "properties": {
    "iso:country":"DE",
    "sg:address":"Gro\u00dfe Wiesen 3",
    "sg:city":"Lichtenstein",
    "sg:phone":"+49 7129/922739",
    "sg:postcode":"72805",
    "sg:province":"Baden-W\u00fcrttemberg",
    "wof:name":"Alu-formenbau Gmbh",
    "wof:placetype":"venue"
},
  "geometry": {"coordinates":[9.26372,48.409668],"type":"Point"}
}