{
  "type": "Feature",
  "properties": {
    "iso:country":"DE",
    "sg:address":"Untertorstr. 41",
    "sg:city":"Erlenbach",
    "sg:phone":"+49 9391/2395",
    "sg:postcode":"97837",
    "sg:province":"Bayern",
    "wof:name":"Raiffeisenbank Marktheidenfeld Eg",
    "wof:placetype":"venue"
},
  "geometry": {"coordinates":[9.62739,49.818794],"type":"Point"}
}