{
  "type": "Feature",
  "properties": {
    "iso:country":"DE",
    "sg:address":"Ledder Dorfstr. 68",
    "sg:city":"Tecklenburg",
    "sg:postcode":"49545",
    "sg:province":"Nordrhein-Westfalen",
    "wof:name":"Evangelische Kirchengemeinde",
    "wof:placetype":"venue"
},
  "geometry": {"coordinates":[7.8100299835,52.2415504456],"type":"Point"}
}