{
  "type": "Feature",
  "properties": {
    "iso:country":"DE",
    "sg:address":"Bauseweinallee 120",
    "sg:city":"M\u00fcnchen",
    "sg:phone":"+49 89/8131766",
    "sg:postcode":"80999",
    "sg:province":"Bayern",
    "wof:name":"Fischer Profil Gmbh",
    "wof:placetype":"venue"
},
  "geometry": {"coordinates":[11.4709711075,48.1770820618],"type":"Point"}
}