{
  "type": "Feature",
  "properties": {
    "iso:country":"DE",
    "sg:address":"Reinsburgstr. 195",
    "sg:city":"Stuttgart",
    "sg:phone":"+49 711/6580023",
    "sg:postcode":"70197",
    "sg:province":"Baden-W\u00fcrttemberg",
    "wof:name":"Prause-sprachreisen",
    "wof:placetype":"venue"
},
  "geometry": {"coordinates":[9.1461877823,48.7700462341],"type":"Point"}
}