{
  "type": "Feature",
  "properties": {
    "iso:country":"DE",
    "sg:address":"Luisenstr. 3",
    "sg:city":"Wiesbaden",
    "sg:phone":"+49 611/305372",
    "sg:postcode":"65185",
    "sg:province":"Hessen",
    "wof:name":"P. Gottschild",
    "wof:placetype":"venue"
},
  "geometry": {"coordinates":[8.2442731857,50.0794715881],"type":"Point"}
}