{
  "type": "Feature",
  "properties": {
    "iso:country":"DE",
    "sg:address":"Alte Aue 27",
    "sg:city":"Seelze",
    "sg:phone":"+49 511/485810",
    "sg:postcode":"30926",
    "sg:province":"Niedersachsen",
    "wof:name":"Helmut H\u00f6pken",
    "wof:placetype":"venue"
},
  "geometry": {"coordinates":[9.6319723129,52.3975982666],"type":"Point"}
}