{
  "type": "Feature",
  "properties": {
    "iso:country":"DE",
    "sg:address":"Claudiusweg 16",
    "sg:city":"Darmstadt",
    "sg:phone":"+49 6151/421219",
    "sg:postcode":"64285",
    "sg:province":"Hessen",
    "wof:name":"Dr. Jost Schindel Rechtsanwalt",
    "wof:placetype":"venue"
},
  "geometry": {"coordinates":[8.666967392,49.8567123413],"type":"Point"}
}