{
  "type": "Feature",
  "properties": {
    "iso:country":"DE",
    "sg:address":"Dorfstr. 64",
    "sg:city":"Bethau",
    "sg:phone":"+49 35386/22342",
    "sg:postcode":"06925",
    "sg:province":"Sachsen-Anhalt",
    "wof:name":"Fred Lehmann",
    "wof:placetype":"venue"
},
  "geometry": {"coordinates":[12.996387,51.676842],"type":"Point"}
}