{
  "type": "Feature",
  "properties": {
    "iso:country":"DE",
    "sg:address":"Untere Sonnenstr. 6",
    "sg:city":"Ergolding",
    "sg:phone":"+49 871/70020",
    "sg:postcode":"84030",
    "sg:province":"Bayern",
    "wof:name":"Heinzel Gmbh & Co. Kg",
    "wof:placetype":"venue"
},
  "geometry": {"coordinates":[12.165564,48.560162],"type":"Point"}
}