{
  "type": "Feature",
  "properties": {
    "iso:country":"DE",
    "sg:address":"Matth\u00e4usweg 2",
    "sg:city":"Altenberg",
    "sg:phone":"+49 35052/4216",
    "sg:postcode":"01773",
    "sg:province":"Sachsen",
    "wof:name":"Pension Rehn",
    "wof:placetype":"venue"
},
  "geometry": {"coordinates":[13.6819410324,50.7877426147],"type":"Point"}
}