{
  "type": "Feature",
  "properties": {
    "iso:country":"DE",
    "sg:address":"Scheurener Str. 3",
    "sg:city":"Unkel",
    "sg:phone":"+49 4922/2472674",
    "sg:postcode":"53572",
    "sg:province":"Rheinland-Pfalz",
    "wof:name":"Becher Tiefbau Gmbh",
    "wof:placetype":"venue"
},
  "geometry": {"coordinates":[7.219855,50.603424],"type":"Point"}
}