{
  "type": "Feature",
  "properties": {
    "iso:country":"DE",
    "sg:address":"Zum Glockenberg 14",
    "sg:city":"Saldenburg",
    "sg:phone":"+49 8555/1600",
    "sg:postcode":"94163",
    "sg:province":"Bayern",
    "wof:name":"Konrad Persau",
    "wof:placetype":"venue"
},
  "geometry": {"coordinates":[13.3905439377,48.7828598022],"type":"Point"}
}