{
  "type": "Feature",
  "properties": {
    "iso:country":"DE",
    "sg:address":"B\u00fcrgerm.-Schirmer-Str. 11",
    "sg:city":"Hofgeismar",
    "sg:phone":"+49 5671/2068",
    "sg:postcode":"34369",
    "sg:province":"Hessen",
    "wof:name":"Gemeinn. Wohnungsbaugen. F\u00fcr Den Ehem. Landkreis",
    "wof:placetype":"venue"
},
  "geometry": {"coordinates":[9.3850698471,51.4954032898],"type":"Point"}
}