{
  "type": "Feature",
  "properties": {
    "iso:country":"DE",
    "sg:address":"Projensdorfer Str. 324",
    "sg:city":"Kiel",
    "sg:phone":"+49 4943/130580",
    "sg:postcode":"24106",
    "sg:province":"Schleswig-Holstein",
    "wof:name":"Walterwerk Kiel Gmbh & Co Kg",
    "wof:placetype":"venue"
},
  "geometry": {"coordinates":[10.1042118073,54.3679618835],"type":"Point"}
}