{
  "type": "Feature",
  "properties": {
    "iso:country":"DE",
    "sg:address":"Industriestr. 16",
    "sg:city":"Inden",
    "sg:phone":"+49 2428/1442",
    "sg:postcode":"52459",
    "sg:province":"Nordrhein-Westfalen",
    "wof:name":"K & F Kranbau Und F\u00f6rdertechnik Gmbh",
    "wof:placetype":"venue"
},
  "geometry": {"coordinates":[6.4177789688,50.8742599487],"type":"Point"}
}