{
  "type": "Feature",
  "properties": {
    "iso:country":"DE",
    "sg:address":"Lindenstr. 31",
    "sg:city":"Welsleben",
    "sg:phone":"+49 39296/20240",
    "sg:postcode":"39221",
    "sg:province":"Sachsen-Anhalt",
    "wof:name":"Karsten Stamm",
    "wof:placetype":"venue"
},
  "geometry": {"coordinates":[11.634156,52.001156],"type":"Point"}
}