{
  "type": "Feature",
  "properties": {
    "iso:country":"DE",
    "sg:address":"Ankergasse 15",
    "sg:city":"Miltenberg",
    "sg:phone":"+49 9371/2428",
    "sg:postcode":"63897",
    "sg:province":"Bayern",
    "wof:name":"Kurt Kirchgessner Lederwaren",
    "wof:placetype":"venue"
},
  "geometry": {"coordinates":[9.2575626373,49.7028961182],"type":"Point"}
}