{
  "type": "Feature",
  "properties": {
    "iso:country":"DE",
    "sg:address":"Hohenk\u00f6rbener Weg 85",
    "sg:city":"Nordhorn",
    "sg:phone":"+49 5921/82230",
    "sg:postcode":"48527",
    "sg:province":"Niedersachsen",
    "wof:name":"Nota Bene Software Gmbh",
    "wof:placetype":"venue"
},
  "geometry": {"coordinates":[7.0676760674,52.4478187561],"type":"Point"}
}