{
  "type": "Feature",
  "properties": {
    "iso:country":"DE",
    "sg:address":"Barnimstr. 36",
    "sg:city":"Berlin",
    "sg:phone":"+49 30/24720775",
    "sg:postcode":"10249",
    "sg:province":"Berlin",
    "wof:name":"Herwig Loeper Architekt",
    "wof:placetype":"venue"
},
  "geometry": {"coordinates":[13.422695,52.525555],"type":"Point"}
}