{
  "type": "Feature",
  "properties": {
    "iso:country":"DE",
    "sg:address":"Nerotal 1 a",
    "sg:city":"Wiesbaden",
    "sg:phone":"+49 611/525631",
    "sg:postcode":"65193",
    "sg:province":"Hessen",
    "wof:name":"G. Karg Kg Maschinen",
    "wof:placetype":"venue"
},
  "geometry": {"coordinates":[8.236237,50.09153],"type":"Point"}
}