{
  "type": "Feature",
  "properties": {
    "iso:country":"DE",
    "sg:address":"B\u00f6hringerstr. 31",
    "sg:city":"Stuttgart",
    "sg:phone":"+49 711/879931",
    "sg:postcode":"70435",
    "sg:province":"Baden-W\u00fcrttemberg",
    "wof:name":"Ps Pressevertriebsservice Gmbh",
    "wof:placetype":"venue"
},
  "geometry": {"coordinates":[9.170907,48.830502],"type":"Point"}
}