{
  "type": "Feature",
  "properties": {
    "iso:country":"DE",
    "sg:address":"Pr\u00e4lat-Neun-Str. 11",
    "sg:city":"Zwiesel",
    "sg:phone":"+49 9922/2342",
    "sg:postcode":"94227",
    "sg:province":"Bayern",
    "wof:name":"Jugendcafe",
    "wof:placetype":"venue"
},
  "geometry": {"coordinates":[13.233739,49.013],"type":"Point"}
}