{
  "type": "Feature",
  "properties": {
    "iso:country":"DE",
    "sg:address":"Feldmannstr. 92",
    "sg:city":"Saarbr\u00fccken",
    "sg:phone":"+49 681/926600",
    "sg:postcode":"66119",
    "sg:province":"Saarland",
    "wof:name":"Parit\u00e4tische Ges. F\u00fcr Qualit\u00e4t Mbh",
    "wof:placetype":"venue"
},
  "geometry": {"coordinates":[6.990012,49.223324],"type":"Point"}
}