{
  "type": "Feature",
  "properties": {
    "iso:country":"DE",
    "sg:address":"Gotenweg 29",
    "sg:city":"Sch\u00f6nwalde",
    "sg:phone":"+49 3322/203377",
    "sg:postcode":"14621",
    "sg:province":"Brandenburg",
    "wof:name":"Falcon Gmbh",
    "wof:placetype":"venue"
},
  "geometry": {"coordinates":[13.1234502792,52.6034698486],"type":"Point"}
}