{
  "type": "Feature",
  "properties": {
    "iso:country":"DE",
    "sg:address":"Remeyerhofstr. 19",
    "sg:city":"Worms",
    "sg:phone":"+49 6241/4761",
    "sg:postcode":"67547",
    "sg:province":"Rheinland-Pfalz",
    "wof:name":"Arbeiterwohlfahrt E. V.",
    "wof:placetype":"venue"
},
  "geometry": {"coordinates":[8.36617,49.636684],"type":"Point"}
}