{
  "type": "Feature",
  "properties": {
    "iso:country":"DE",
    "sg:address":"G\u00fcrrichstr. 6",
    "sg:city":"Karlsruhe",
    "sg:phone":"+49 721/9703200",
    "sg:postcode":"76149",
    "sg:province":"Baden-W\u00fcrttemberg",
    "wof:name":"Zenkner",
    "wof:placetype":"venue"
},
  "geometry": {"coordinates":[8.383263,49.050014],"type":"Point"}
}