{
  "type": "Feature",
  "properties": {
    "iso:country":"DE",
    "sg:address":"Dr.-Weinholz-Str. 33",
    "sg:city":"Rodgau",
    "sg:phone":"+49 6106/23479",
    "sg:postcode":"63110",
    "sg:province":"Hessen",
    "wof:name":"Richard Subtil",
    "wof:placetype":"venue"
},
  "geometry": {"coordinates":[8.8882217407,50.0102043152],"type":"Point"}
}