{
  "type": "Feature",
  "properties": {
    "iso:country":"DE",
    "sg:address":"Speckweg 50",
    "sg:city":"Wendlingen",
    "sg:phone":"+49 7024/3311",
    "sg:postcode":"73240",
    "sg:province":"Baden-W\u00fcrttemberg",
    "wof:name":"Freibad",
    "wof:placetype":"venue"
},
  "geometry": {"coordinates":[9.3967237473,48.6628570557],"type":"Point"}
}