{
  "type": "Feature",
  "properties": {
    "iso:country":"DE",
    "sg:address":"Lichtensteinstr. 19",
    "sg:city":"G\u00e4ufelden",
    "sg:phone":"+49 7032/72694",
    "sg:postcode":"71126",
    "sg:province":"Baden-W\u00fcrttemberg",
    "wof:name":"Helmut Funke Ingenieur",
    "wof:placetype":"venue"
},
  "geometry": {"coordinates":[8.8504867554,48.5636367798],"type":"Point"}
}