{
  "type": "Feature",
  "properties": {
    "iso:country":"DE",
    "sg:address":"Tailfinger Str. 28",
    "sg:city":"Herrenberg",
    "sg:phone":"+49 7032/74102",
    "sg:postcode":"71083",
    "sg:province":"Baden-W\u00fcrttemberg",
    "wof:name":"Friedrich Schmidt",
    "wof:placetype":"venue"
},
  "geometry": {"coordinates":[8.877252,48.570782],"type":"Point"}
}