{
  "type": "Feature",
  "properties": {
    "iso:country":"DE",
    "sg:address":"Zweibr\u00fccker Str. 16",
    "sg:city":"Dellfeld",
    "sg:phone":"+49 6336/6059",
    "sg:postcode":"66503",
    "sg:province":"Rheinland-Pfalz",
    "wof:name":"Hans B\u00f6tselaars Elektroinstallation",
    "wof:placetype":"venue"
},
  "geometry": {"coordinates":[7.467137,49.22953],"type":"Point"}
}