{
  "type": "Feature",
  "properties": {
    "iso:country":"DE",
    "sg:address":"Vogesenblick 1a",
    "sg:city":"Friesenheim",
    "sg:postcode":"77948",
    "sg:province":"Baden-W\u00fcrttemberg",
    "wof:name":"Web-tecmedia E. K.",
    "wof:placetype":"venue"
},
  "geometry": {"coordinates":[7.8945598602,48.4025115967],"type":"Point"}
}