{
  "type": "Feature",
  "properties": {
    "iso:country":"DE",
    "sg:address":"Am Kohlmarkt 11",
    "sg:city":"Warstein",
    "sg:phone":"+49 2902/2513",
    "sg:postcode":"59581",
    "sg:province":"Nordrhein-Westfalen",
    "wof:name":"Wilhelm Dicke",
    "wof:placetype":"venue"
},
  "geometry": {"coordinates":[8.3477315903,51.4462814331],"type":"Point"}
}