{
  "type": "Feature",
  "properties": {
    "iso:country":"DE",
    "sg:address":"M\u00fcnchehofer Weg 38",
    "sg:city":"M\u00fcncheberg",
    "sg:phone":"+49 33432/89269",
    "sg:postcode":"15374",
    "sg:province":"Brandenburg",
    "wof:name":"M\u00e4rkische Etiketten Gmbh",
    "wof:placetype":"venue"
},
  "geometry": {"coordinates":[14.1371917725,52.5101585388],"type":"Point"}
}