{
  "type": "Feature",
  "properties": {
    "iso:country":"DE",
    "sg:address":"Unterrather Str. 96",
    "sg:city":"D\u00fcsseldorf",
    "sg:phone":"+49 211/4220225",
    "sg:postcode":"40468",
    "sg:province":"Nordrhein-Westfalen",
    "wof:name":"Industrie-apotheke",
    "wof:placetype":"venue"
},
  "geometry": {"coordinates":[6.781642,51.273922],"type":"Point"}
}