{
  "type": "Feature",
  "properties": {
    "iso:country":"DE",
    "sg:address":"Krailing 2",
    "sg:city":"Heidenrod",
    "sg:phone":"+49 6120/7270",
    "sg:postcode":"65321",
    "sg:province":"Hessen",
    "wof:name":"A. Reintgen Anlageberater",
    "wof:placetype":"venue"
},
  "geometry": {"coordinates":[7.9928631783,50.2090568542],"type":"Point"}
}