{
  "type": "Feature",
  "properties": {
    "iso:country":"DE",
    "sg:address":"Zolaweg 80",
    "sg:city":"Leipzig",
    "sg:phone":"+49 341/8622126",
    "sg:postcode":"04289",
    "sg:province":"Sachsen",
    "wof:name":"Hans-g\u00fcnther Mischler",
    "wof:placetype":"venue"
},
  "geometry": {"coordinates":[12.435356,51.287277],"type":"Point"}
}