{
  "type": "Feature",
  "properties": {
    "iso:country":"DE",
    "sg:address":"Altenhofstr. 5",
    "sg:city":"Schifferstadt",
    "sg:phone":"+49 6235/3061",
    "sg:postcode":"67105",
    "sg:province":"Rheinland-Pfalz",
    "wof:name":"Josef Kurz Inh. Hans Kurz",
    "wof:placetype":"venue"
},
  "geometry": {"coordinates":[8.3689174652,49.386516571],"type":"Point"}
}