{
  "type": "Feature",
  "properties": {
    "iso:country":"DE",
    "sg:address":"Erlenweg 1",
    "sg:city":"Ammerndorf",
    "sg:phone":"+49 9127/578001",
    "sg:postcode":"90614",
    "sg:province":"Bayern",
    "wof:name":"Eiscafe San Marco",
    "wof:placetype":"venue"
},
  "geometry": {"coordinates":[10.857644,49.42178],"type":"Point"}
}