{
  "type": "Feature",
  "properties": {
    "iso:country":"DE",
    "sg:city":"Recklinghausen",
    "sg:postcode":"45663",
    "sg:province":"Nordrhein-Westfalen",
    "wof:name":"Erotik-chat Mit Sex-geilen Porno-girls",
    "wof:placetype":"venue"
},
  "geometry": {"coordinates":[7.23377,51.577412],"type":"Point"}
}