{
  "type": "Feature",
  "properties": {
    "iso:country":"DE",
    "sg:address":"Freiheitstr. 9",
    "sg:city":"Castrop-Rauxel",
    "sg:phone":"+49 2367/8581",
    "sg:postcode":"44581",
    "sg:province":"Nordrhein-Westfalen",
    "wof:name":"L. Aertken",
    "wof:placetype":"venue"
},
  "geometry": {"coordinates":[7.311788,51.598885],"type":"Point"}
}