{
  "type": "Feature",
  "properties": {
    "iso:country":"DE",
    "sg:address":"Radolfzeller Str. 7",
    "sg:city":"M\u00fcnchen",
    "sg:postcode":"81243",
    "sg:province":"Bayern",
    "wof:name":"Fink Media Heinrich Fink",
    "wof:placetype":"venue"
},
  "geometry": {"coordinates":[11.4353294373,48.1500167847],"type":"Point"}
}