{
  "type": "Feature",
  "properties": {
    "iso:country":"DE",
    "sg:address":"Industriestr. 10",
    "sg:city":"Gr\u00fcndau",
    "sg:phone":"+49 6051/471140",
    "sg:postcode":"63584",
    "sg:province":"Hessen",
    "wof:name":"Kohls Maschinenbau Gmbh",
    "wof:placetype":"venue"
},
  "geometry": {"coordinates":[9.121104,50.198475],"type":"Point"}
}