{
  "type": "Feature",
  "properties": {
    "iso:country":"DE",
    "sg:address":"Tillystr. 2",
    "sg:city":"Minden",
    "sg:phone":"+49 571/44857",
    "sg:postcode":"32425",
    "sg:province":"Nordrhein-Westfalen",
    "wof:name":"Dirk Boenisch",
    "wof:placetype":"venue"
},
  "geometry": {"coordinates":[8.8952093124,52.3072357178],"type":"Point"}
}