{
  "type": "Feature",
  "properties": {
    "iso:country":"DE",
    "sg:address":"D\u00fcrkheimer Str. 24",
    "sg:city":"Frankenstein",
    "sg:phone":"+49 6329/1338",
    "sg:postcode":"67468",
    "sg:province":"Rheinland-Pfalz",
    "wof:name":"Paydos",
    "wof:placetype":"venue"
},
  "geometry": {"coordinates":[7.9837069511,49.4402236938],"type":"Point"}
}