{
  "type": "Feature",
  "properties": {
    "iso:country":"DE",
    "sg:address":"Kluckstr. 29",
    "sg:city":"Berlin",
    "sg:postcode":"10785",
    "sg:province":"Berlin",
    "wof:name":"E. Merck Ohg",
    "wof:placetype":"venue"
},
  "geometry": {"coordinates":[13.361407,52.502644],"type":"Point"}
}