{
  "type": "Feature",
  "properties": {
    "iso:country":"DE",
    "sg:address":"M\u00fcndelheimer Weg 58",
    "sg:city":"D\u00fcsseldorf",
    "sg:phone":"+49 211/941040",
    "sg:postcode":"40472",
    "sg:province":"Nordrhein-Westfalen",
    "wof:name":"Nissei Asb Gmbh",
    "wof:placetype":"venue"
},
  "geometry": {"coordinates":[6.798936,51.287975],"type":"Point"}
}