{
  "type": "Feature",
  "properties": {
    "iso:country":"DE",
    "sg:address":"Siedlerh\u00f6fe 2",
    "sg:city":"Kandern",
    "sg:phone":"+49 7626/7341",
    "sg:postcode":"79400",
    "sg:province":"Baden-W\u00fcrttemberg",
    "wof:name":"Walter Hollenw\u00e4ger",
    "wof:placetype":"venue"
},
  "geometry": {"coordinates":[7.6513,47.68047],"type":"Point"}
}