{
  "type": "Feature",
  "properties": {
    "iso:country":"DE",
    "sg:address":"Bahnhofstr. 72",
    "sg:city":"Senden",
    "sg:postcode":"48308",
    "sg:province":"Nordrhein-Westfalen",
    "wof:name":"Rudolf Rincklake Van Endert Objekt Und Wohnen",
    "wof:placetype":"venue"
},
  "geometry": {"coordinates":[7.482363224,51.912776947],"type":"Point"}
}