{
  "type": "Feature",
  "properties": {
    "iso:country":"DE",
    "sg:address":"Martin-Luther-Str. 25",
    "sg:city":"Detmold",
    "sg:phone":"+49 5231/68655",
    "sg:postcode":"32756",
    "sg:province":"Nordrhein-Westfalen",
    "wof:name":"Raumausstatter Meinert Inh. Andreas Meinert E. K.",
    "wof:placetype":"venue"
},
  "geometry": {"coordinates":[8.8590221405,51.935092926],"type":"Point"}
}