{
  "type": "Feature",
  "properties": {
    "iso:country":"DE",
    "sg:address":"Ludwigstr. 117",
    "sg:city":"Offenbach",
    "sg:phone":"+49 69/822124",
    "sg:postcode":"63067",
    "sg:province":"Hessen",
    "wof:name":"Ristorante Da Bruno",
    "wof:placetype":"venue"
},
  "geometry": {"coordinates":[8.7520866394,50.1066246033],"type":"Point"}
}