{
  "type": "Feature",
  "properties": {
    "iso:country":"DE",
    "sg:address":"Waldring 64a",
    "sg:city":"Haldensleben",
    "sg:phone":"+49 3904/64317",
    "sg:postcode":"39340",
    "sg:province":"Sachsen-Anhalt",
    "wof:name":"Teufelsk\u00fcche",
    "wof:placetype":"venue"
},
  "geometry": {"coordinates":[11.3895816803,52.2798042297],"type":"Point"}
}