{
  "type": "Feature",
  "properties": {
    "iso:country":"DE",
    "sg:address":"Herderstr. 10",
    "sg:city":"Engelskirchen",
    "sg:phone":"+49 2263/60655",
    "sg:postcode":"51766",
    "sg:province":"Nordrhein-Westfalen",
    "wof:name":"Harald Busch",
    "wof:placetype":"venue"
},
  "geometry": {"coordinates":[7.4528560638,50.9924621582],"type":"Point"}
}