{
  "type": "Feature",
  "properties": {
    "iso:country":"DE",
    "sg:address":"Breite Str. 138",
    "sg:city":"G\u00f6rzke",
    "sg:phone":"+49 33847/40248",
    "sg:postcode":"14828",
    "sg:province":"Brandenburg",
    "wof:name":"Siedfried Pohlmann",
    "wof:placetype":"venue"
},
  "geometry": {"coordinates":[12.369106,52.172012],"type":"Point"}
}