{
  "type": "Feature",
  "properties": {
    "iso:country":"DE",
    "sg:address":"F\u00fcllerstr. 58",
    "sg:city":"Frankfurt",
    "sg:phone":"+49 69/538844",
    "sg:postcode":"60431",
    "sg:province":"Hessen",
    "wof:name":"Geskes Und Obermann Architekten",
    "wof:placetype":"venue"
},
  "geometry": {"coordinates":[8.650333,50.141899],"type":"Point"}
}