{
  "type": "Feature",
  "properties": {
    "iso:country":"DE",
    "sg:address":"Lindenallee 2",
    "sg:city":"Neunkirchen",
    "sg:phone":"+49 6821/22958",
    "sg:postcode":"66538",
    "sg:province":"Saarland",
    "wof:name":"Optic Zimmermann Gmbh",
    "wof:placetype":"venue"
},
  "geometry": {"coordinates":[7.174637,49.348415],"type":"Point"}
}