{
  "type": "Feature",
  "properties": {
    "iso:country":"DE",
    "sg:address":"Bredenscheider Str. 128",
    "sg:city":"Hattingen",
    "sg:phone":"+49 2324/24463",
    "sg:postcode":"45527",
    "sg:province":"Nordrhein-Westfalen",
    "wof:name":"Karl-heinz Lohmann",
    "wof:placetype":"venue"
},
  "geometry": {"coordinates":[7.191609,51.378174],"type":"Point"}
}