{
  "type": "Feature",
  "properties": {
    "iso:country":"DE",
    "sg:address":"Mustorstr. 12",
    "sg:city":"Trier",
    "sg:phone":"+49 651/71335",
    "sg:postcode":"54290",
    "sg:province":"Rheinland-Pfalz",
    "wof:name":"Kreiswasserwerk Trier-saarburg",
    "wof:placetype":"venue"
},
  "geometry": {"coordinates":[6.6460590363,49.7535629272],"type":"Point"}
}