{
  "type": "Feature",
  "properties": {
    "iso:country":"DE",
    "sg:address":"Meyerbeerstr. 13",
    "sg:city":"Wiesbaden",
    "sg:phone":"+49 611/526350",
    "sg:postcode":"65193",
    "sg:province":"Hessen",
    "wof:name":"Dr. Eberhard Krause Rechtsanwalt",
    "wof:placetype":"venue"
},
  "geometry": {"coordinates":[8.2486848831,50.090221405],"type":"Point"}
}