{
  "type": "Feature",
  "properties": {
    "iso:country":"DE",
    "sg:address":"Ansorgestr. 32",
    "sg:city":"Hamburg",
    "sg:phone":"+49 40/8802343",
    "sg:postcode":"22605",
    "sg:province":"Hamburg",
    "wof:name":"Maralde Meyer-minnemann \u00dcbersetzerin",
    "wof:placetype":"venue"
},
  "geometry": {"coordinates":[9.891194,53.550488],"type":"Point"}
}