{
  "type": "Feature",
  "properties": {
    "iso:country":"DE",
    "sg:address":"Milchstr. 10",
    "sg:city":"Hamburg",
    "sg:phone":"+49 40/45035047",
    "sg:postcode":"20148",
    "sg:province":"Hamburg",
    "wof:name":"Prinz & M\u00f6ller Fine Art Inh. Frank-christian M\u00f6ller",
    "wof:placetype":"venue"
},
  "geometry": {"coordinates":[9.9980554581,53.5708656311],"type":"Point"}
}