{
  "type": "Feature",
  "properties": {
    "iso:country":"DE",
    "sg:address":"Schmalzgrube 5",
    "sg:city":"Solingen",
    "sg:phone":"+49 4921/2222190",
    "sg:postcode":"42655",
    "sg:province":"Nordrhein-Westfalen",
    "wof:name":"Friedrich Bergmeister Gmbh",
    "wof:placetype":"venue"
},
  "geometry": {"coordinates":[7.0356302261,51.1637191772],"type":"Point"}
}