{
  "type": "Feature",
  "properties": {
    "iso:country":"DE",
    "sg:address":"Pollerstr. 57",
    "sg:city":"Wiesmoor",
    "sg:phone":"+49 4944/990255",
    "sg:postcode":"26639",
    "sg:province":"Niedersachsen",
    "wof:name":"Fle\u00dfner",
    "wof:placetype":"venue"
},
  "geometry": {"coordinates":[7.69305,53.408451],"type":"Point"}
}