{
  "type": "Feature",
  "properties": {
    "iso:country":"DE",
    "sg:address":"Wilhelm-W\u00f6rle-Str. 10a",
    "sg:city":"Augsburg",
    "sg:phone":"+49 821/528855",
    "sg:postcode":"86157",
    "sg:province":"Bayern",
    "wof:name":"Herbert K\u00fchn",
    "wof:placetype":"venue"
},
  "geometry": {"coordinates":[10.8655948639,48.3665657043],"type":"Point"}
}