{
  "type": "Feature",
  "properties": {
    "iso:country":"DE",
    "sg:address":"Alt-Godshorn 101",
    "sg:city":"Langenhagen",
    "sg:phone":"+49 511/782485",
    "sg:postcode":"30855",
    "sg:province":"Niedersachsen",
    "wof:name":"Linneweh Gmbh",
    "wof:placetype":"venue"
},
  "geometry": {"coordinates":[9.7012367249,52.4389686584],"type":"Point"}
}