{
  "type": "Feature",
  "properties": {
    "iso:country":"DE",
    "sg:address":"Gurtweiler Str.",
    "sg:city":"Waldshut-Tiengen",
    "sg:phone":"+49 7741/3361",
    "sg:postcode":"79761",
    "sg:province":"Baden-W\u00fcrttemberg",
    "wof:name":"A. Kaiser",
    "wof:placetype":"venue"
},
  "geometry": {"coordinates":[8.224908,47.623158],"type":"Point"}
}