{
  "type": "Feature",
  "properties": {
    "iso:country":"DE",
    "sg:address":"Kirchstr. 10",
    "sg:city":"Bad Schandau",
    "sg:phone":"+49 35022/42527",
    "sg:postcode":"01814",
    "sg:province":"Sachsen",
    "wof:name":"Alicia Hesse",
    "wof:placetype":"venue"
},
  "geometry": {"coordinates":[14.154769,50.918064],"type":"Point"}
}