{
  "type": "Feature",
  "properties": {
    "iso:country":"DE",
    "sg:address":"E.-Th\u00e4lmann-Str. 51",
    "sg:city":"Reitzenhain",
    "sg:phone":"+49 37364/8786",
    "sg:postcode":"09496",
    "sg:province":"Sachsen",
    "wof:name":"Ferienhaus M\u00fcnzner In Reitzenhain",
    "wof:placetype":"venue"
},
  "geometry": {"coordinates":[13.219235,50.558754],"type":"Point"}
}