{
  "type": "Feature",
  "properties": {
    "iso:country":"DE",
    "sg:address":"Hochstadenstr. 14",
    "sg:city":"Bad Neuenahr-Ahrweiler",
    "sg:phone":"+49 2641/34266",
    "sg:postcode":"53474",
    "sg:province":"Rheinland-Pfalz",
    "wof:name":"Fritz Kirstan Versicherungen",
    "wof:placetype":"venue"
},
  "geometry": {"coordinates":[7.1050648689,50.5441246033],"type":"Point"}
}