{
  "type": "Feature",
  "properties": {
    "iso:country":"DE",
    "sg:address":"Dorfstr. 50",
    "sg:city":"Hildburghausen",
    "sg:phone":"+49 3685/67141",
    "sg:postcode":"98646",
    "sg:province":"Th\u00fcringen",
    "wof:name":"R. Oestreicher",
    "wof:placetype":"venue"
},
  "geometry": {"coordinates":[10.6804971695,50.4469070435],"type":"Point"}
}