{
  "type": "Feature",
  "properties": {
    "iso:country":"DE",
    "sg:address":"Ledergasse 19 u. 43",
    "sg:city":"Schw\u00e4bisch Gm\u00fcnd",
    "sg:phone":"+49 7171/62733",
    "sg:postcode":"73525",
    "sg:province":"Baden-W\u00fcrttemberg",
    "wof:name":"Modeboutique Helga Markez",
    "wof:placetype":"venue"
},
  "geometry": {"coordinates":[9.7953548431,48.797000885],"type":"Point"}
}