{
  "type": "Feature",
  "properties": {
    "iso:country":"DE",
    "sg:address":"Dobrock 25",
    "sg:city":"Wingst",
    "sg:phone":"+49 4778/7773",
    "sg:postcode":"21789",
    "sg:province":"Niedersachsen",
    "wof:name":"Heinz Eckhoff",
    "wof:placetype":"venue"
},
  "geometry": {"coordinates":[9.08558,53.72459],"type":"Point"}
}