{
  "type": "Feature",
  "properties": {
    "iso:country":"DE",
    "sg:address":"Schillerstr. 44",
    "sg:city":"Schkeuditz",
    "sg:phone":"+49 34204/7510",
    "sg:postcode":"04435",
    "sg:province":"Sachsen",
    "wof:name":"R. Ockenfels Baustoffe Gmbh",
    "wof:placetype":"venue"
},
  "geometry": {"coordinates":[12.2204990387,51.4001159668],"type":"Point"}
}