{
  "type": "Feature",
  "properties": {
    "iso:country":"DE",
    "sg:address":"Siedlung 19",
    "sg:city":"Niederorschel",
    "sg:phone":"+49 36076/5750",
    "sg:postcode":"37355",
    "sg:province":"Th\u00fcringen",
    "wof:name":"Helmut Nolte",
    "wof:placetype":"venue"
},
  "geometry": {"coordinates":[10.424962,51.377186],"type":"Point"}
}