{
  "type": "Feature",
  "properties": {
    "iso:country":"DE",
    "sg:address":"Kirchberg 7",
    "sg:city":"Rodeberg",
    "sg:phone":"+49 36026/90308",
    "sg:postcode":"99976",
    "sg:province":"Th\u00fcringen",
    "wof:name":"L. Gebhardt",
    "wof:placetype":"venue"
},
  "geometry": {"coordinates":[10.31016,51.22224],"type":"Point"}
}