{
  "type": "Feature",
  "properties": {
    "iso:country":"DE",
    "sg:address":"Hauptstr. 109",
    "sg:city":"Kuchen",
    "sg:phone":"+49 7331/82365",
    "sg:postcode":"73329",
    "sg:province":"Baden-W\u00fcrttemberg",
    "wof:name":"Karl Hetzler",
    "wof:placetype":"venue"
},
  "geometry": {"coordinates":[9.7992591858,48.6361160278],"type":"Point"}
}