{
  "type": "Feature",
  "properties": {
    "iso:country":"DE",
    "sg:address":"Am Weiher 14",
    "sg:city":"Hamburg",
    "sg:phone":"+49 40/405612",
    "sg:postcode":"20255",
    "sg:province":"Hamburg",
    "wof:name":"M. Ostrowski-wenzel",
    "wof:placetype":"venue"
},
  "geometry": {"coordinates":[9.9588928223,53.5775871277],"type":"Point"}
}