{
  "type": "Feature",
  "properties": {
    "iso:country":"DE",
    "sg:address":"Limbacher Str. 42",
    "sg:city":"Schalkau",
    "sg:phone":"+49 36766/87646",
    "sg:postcode":"96528",
    "sg:province":"Th\u00fcringen",
    "wof:name":"Martin M\u00fcller",
    "wof:placetype":"venue"
},
  "geometry": {"coordinates":[11.030372,50.422737],"type":"Point"}
}