{
  "type": "Feature",
  "properties": {
    "iso:country":"DE",
    "sg:address":"Waldstr. 6",
    "sg:city":"Limburg",
    "sg:phone":"+49 6431/45839",
    "sg:postcode":"65550",
    "sg:province":"Hessen",
    "wof:name":"Heinz Becker",
    "wof:placetype":"venue"
},
  "geometry": {"coordinates":[8.092084,50.371719],"type":"Point"}
}