{
  "type": "Feature",
  "properties": {
    "iso:country":"DE",
    "sg:address":"Erlenstr. 9",
    "sg:city":"Trebur",
    "sg:phone":"+49 6147/8051",
    "sg:postcode":"65468",
    "sg:province":"Hessen",
    "wof:name":"Horst Und Renate Danker",
    "wof:placetype":"venue"
},
  "geometry": {"coordinates":[8.4158372879,49.9269142151],"type":"Point"}
}