{
  "type": "Feature",
  "properties": {
    "iso:country":"DE",
    "sg:address":"Frankfurter Str.54-56",
    "sg:city":"Kelkheim",
    "sg:phone":"+49 4961/952080",
    "sg:postcode":"65779",
    "sg:province":"Hessen",
    "wof:name":"Dresdner Bank",
    "wof:placetype":"venue"
},
  "geometry": {"coordinates":[8.45265,50.13282],"type":"Point"}
}