{
  "type": "Feature",
  "properties": {
    "iso:country":"DE",
    "sg:address":"D\u00fcrerstr. 121",
    "sg:city":"Homburg",
    "sg:phone":"+49 6841/78558",
    "sg:postcode":"66424",
    "sg:province":"Saarland",
    "wof:name":"\u00d6ko-plan Baubetreuung Gmbh & Co. Kg",
    "wof:placetype":"venue"
},
  "geometry": {"coordinates":[7.334252,49.339485],"type":"Point"}
}