{
  "type": "Feature",
  "properties": {
    "iso:country":"DE",
    "sg:address":"G\u00fcstener Str. 43",
    "sg:city":"Sta\u00dffurt",
    "sg:postcode":"39418",
    "sg:province":"Sachsen-Anhalt",
    "wof:name":"Bau-elze- Gmbh",
    "wof:placetype":"venue"
},
  "geometry": {"coordinates":[11.588737,51.836227],"type":"Point"}
}