{
  "type": "Feature",
  "properties": {
    "iso:country":"DE",
    "sg:address":"Kirchstr. 25",
    "sg:city":"Friesoythe",
    "sg:phone":"+49 4493/356",
    "sg:postcode":"26169",
    "sg:province":"Niedersachsen",
    "wof:name":"Kurt Vossmann",
    "wof:placetype":"venue"
},
  "geometry": {"coordinates":[7.86104,53.021412],"type":"Point"}
}