{
  "type": "Feature",
  "properties": {
    "iso:country":"DE",
    "sg:address":"R\u00f6vertannen 21",
    "sg:city":"G\u00fcstrow",
    "sg:phone":"+49 3843/69360",
    "sg:postcode":"18273",
    "sg:province":"Mecklenburg-Vorpommern",
    "wof:name":"Mecklenburger Spirituosenfabrik G. Winkelhausen Gmbh",
    "wof:placetype":"venue"
},
  "geometry": {"coordinates":[12.209609,53.799545],"type":"Point"}
}