{
  "type": "Feature",
  "properties": {
    "iso:country":"DE",
    "sg:address":"Altenwalder Str. 104",
    "sg:city":"St. Ingbert",
    "sg:phone":"+49 6894/2050",
    "sg:postcode":"66386",
    "sg:province":"Saarland",
    "wof:name":"Werner Hesse",
    "wof:placetype":"venue"
},
  "geometry": {"coordinates":[7.0992331505,49.2894935608],"type":"Point"}
}