{
  "type": "Feature",
  "properties": {
    "iso:country":"DE",
    "sg:address":"Bahnhofstr. 24",
    "sg:city":"Syke",
    "sg:phone":"+49 4242/50114",
    "sg:postcode":"28857",
    "sg:province":"Niedersachsen",
    "wof:name":"Greta Fellbusch",
    "wof:placetype":"venue"
},
  "geometry": {"coordinates":[8.811417,52.915081],"type":"Point"}
}