{
  "type": "Feature",
  "properties": {
    "iso:country":"DE",
    "sg:address":"Schildgasse 14",
    "sg:city":"N\u00fcrnberg",
    "sg:phone":"+49 911/203040",
    "sg:postcode":"90403",
    "sg:province":"Bayern",
    "wof:name":"A. Trapp Kg",
    "wof:placetype":"venue"
},
  "geometry": {"coordinates":[11.0793609619,49.4572486877],"type":"Point"}
}