{
  "type": "Feature",
  "properties": {
    "iso:country":"DE",
    "sg:address":"Gadenstedter Weg 6",
    "sg:city":"Lahstedt",
    "sg:phone":"+49 5172/2693",
    "sg:postcode":"31246",
    "sg:province":"Niedersachsen",
    "wof:name":"Gerhard Straube",
    "wof:placetype":"venue"
},
  "geometry": {"coordinates":[10.2439050674,52.2547721863],"type":"Point"}
}