{
  "type": "Feature",
  "properties": {
    "iso:country":"DE",
    "sg:address":"Am Brunnengarten 18",
    "sg:city":"Frankfurt",
    "sg:phone":"+49 69/506453",
    "sg:postcode":"60437",
    "sg:province":"Hessen",
    "wof:name":"Vincenzo Gebbia",
    "wof:placetype":"venue"
},
  "geometry": {"coordinates":[8.6391191483,50.1925697327],"type":"Point"}
}