{
  "type": "Feature",
  "properties": {
    "iso:country":"DE",
    "sg:address":"Heubacher Str 6",
    "sg:city":"Ebern",
    "sg:phone":"+49 9531/92240",
    "sg:postcode":"96106",
    "sg:province":"Bayern",
    "wof:name":"Spedition Hans-peter Ebner Gmbh",
    "wof:placetype":"venue"
},
  "geometry": {"coordinates":[10.7849693298,50.0921363831],"type":"Point"}
}