{
  "type": "Feature",
  "properties": {
    "iso:country":"DE",
    "sg:address":"Luisenstr. 29",
    "sg:city":"L\u00f6rrach",
    "sg:phone":"+49 7621/46070",
    "sg:postcode":"79539",
    "sg:province":"Baden-W\u00fcrttemberg",
    "wof:name":"Barbara Und Dr. G\u00fcnter Boll Und Kollegen",
    "wof:placetype":"venue"
},
  "geometry": {"coordinates":[7.6641921997,47.6156005859],"type":"Point"}
}