{
  "type": "Feature",
  "properties": {
    "iso:country":"DE",
    "sg:address":"Debusstr. 6",
    "sg:city":"Herzebrock-Clarholz",
    "sg:phone":"+49 5245/2622",
    "sg:postcode":"33442",
    "sg:province":"Nordrhein-Westfalen",
    "wof:name":"Elke Birke",
    "wof:placetype":"venue"
},
  "geometry": {"coordinates":[8.2397279739,51.8821601868],"type":"Point"}
}