{
  "type": "Feature",
  "properties": {
    "iso:country":"DE",
    "sg:address":"Gr\u00fcnwalder Weg 28g",
    "sg:city":"Oberhaching",
    "sg:classifiers":[
        {
            "category":"Professional",
            "subcategory":"Computer Services",
            "type":"Services"
        }
    ],
    "sg:postcode":"82041",
    "sg:tags":[
        "library",
        "libraries",
        "archives",
        "museums",
        "bibliographic-information",
        "bibliographic-records",
        "cataloging",
        "ill",
        "inter-library-loan",
        "metadata",
        "book-data"
    ],
    "sg:website":"http://www.oclc.org/",
    "wof:name":"OCLC",
    "wof:placetype":"venue"
},
  "geometry": {"coordinates":[11.584516,48.0284937],"type":"Point"}
}