{
  "type": "Feature",
  "properties": {
    "iso:country":"DE",
    "sg:address":"S\u00fcdstr 13",
    "sg:city":"Rehlingen-Siersburg",
    "sg:phone":"+49 6835/92270",
    "sg:postcode":"66780",
    "sg:province":"Saarland",
    "wof:name":"Oka Apparatebau Gmbh",
    "wof:placetype":"venue"
},
  "geometry": {"coordinates":[6.692415,49.368179],"type":"Point"}
}