{
  "type": "Feature",
  "properties": {
    "iso:country":"DE",
    "sg:address":"Waiblinger Str. 67",
    "sg:city":"Winnenden",
    "sg:phone":"+49 7195/174032",
    "sg:postcode":"71364",
    "sg:province":"Baden-W\u00fcrttemberg",
    "wof:name":"Agip Deutschland Ag",
    "wof:placetype":"venue"
},
  "geometry": {"coordinates":[9.3883228302,48.8727607727],"type":"Point"}
}