{
  "type": "Feature",
  "properties": {
    "iso:country":"DE",
    "sg:address":"Knorrstr. 135 f",
    "sg:city":"M\u00fcnchen",
    "sg:phone":"+49 89/3545274",
    "sg:postcode":"80937",
    "sg:province":"Bayern",
    "wof:name":"F. M\u00fcller-seewald Fotoatelier",
    "wof:placetype":"venue"
},
  "geometry": {"coordinates":[11.5720252991,48.1962585449],"type":"Point"}
}