{
  "type": "Feature",
  "properties": {
    "iso:country":"DE",
    "sg:address":"Koenigsallee 37a",
    "sg:city":"Berlin",
    "sg:phone":"+49 30/8260000",
    "sg:postcode":"14193",
    "sg:province":"Berlin",
    "wof:name":"Ims Industriemontage Schwei\u00dftechnik Gmbh",
    "wof:placetype":"venue"
},
  "geometry": {"coordinates":[13.26064,52.47823],"type":"Point"}
}