{
  "type": "Feature",
  "properties": {
    "iso:country":"DE",
    "sg:address":"Dammstr. 3",
    "sg:city":"Wiesloch",
    "sg:phone":"+49 6222/4848",
    "sg:postcode":"69168",
    "sg:province":"Baden-W\u00fcrttemberg",
    "wof:name":"Josef G\u00f6tz",
    "wof:placetype":"venue"
},
  "geometry": {"coordinates":[8.693239212,49.2915992737],"type":"Point"}
}