{
  "type": "Feature",
  "properties": {
    "iso:country":"DE",
    "sg:address":"An den Eichen 20 - 22",
    "sg:city":"Solingen",
    "sg:phone":"+49 212/262120",
    "sg:postcode":"42699",
    "sg:province":"Nordrhein-Westfalen",
    "wof:name":"Cuno Melcher Me-sportwaffen Gmbh & Co. Kg",
    "wof:placetype":"venue"
},
  "geometry": {"coordinates":[7.0257430077,51.1559638977],"type":"Point"}
}