{
  "type": "Feature",
  "properties": {
    "iso:country":"DE",
    "sg:address":"Am Gartenkamp 56",
    "sg:city":"Bochum",
    "sg:phone":"+49 234/903830",
    "sg:postcode":"44807",
    "sg:province":"Nordrhein-Westfalen",
    "wof:name":"Soyka Gmbh",
    "wof:placetype":"venue"
},
  "geometry": {"coordinates":[7.2071461678,51.5130615234],"type":"Point"}
}