{
  "type": "Feature",
  "properties": {
    "iso:country":"DE",
    "sg:address":"Poststr.",
    "sg:city":"Hindelang",
    "sg:phone":"+49 8324/2272",
    "sg:postcode":"87541",
    "sg:province":"Bayern",
    "wof:name":"E. Waibel",
    "wof:placetype":"venue"
},
  "geometry": {"coordinates":[10.370595,47.505539],"type":"Point"}
}