{
  "type": "Feature",
  "properties": {
    "iso:country":"DE",
    "sg:address":"Weidenweg 3",
    "sg:city":"Bretzfeld",
    "sg:phone":"+49 7946/8709",
    "sg:postcode":"74626",
    "sg:province":"Baden-W\u00fcrttemberg",
    "wof:name":"Eugen Pfisterer",
    "wof:placetype":"venue"
},
  "geometry": {"coordinates":[9.441658,49.162399],"type":"Point"}
}