{
  "type": "Feature",
  "properties": {
    "iso:country":"DE",
    "sg:address":"Salzstr. 1",
    "sg:city":"Gerolzhofen",
    "sg:phone":"+49 9382/269",
    "sg:postcode":"97447",
    "sg:province":"Bayern",
    "wof:name":"F\u00fcrstlich Castell'sche Bank",
    "wof:placetype":"venue"
},
  "geometry": {"coordinates":[10.348158,49.901585],"type":"Point"}
}