{
  "type": "Feature",
  "properties": {
    "iso:country":"DE",
    "sg:address":"Kupfergasse 6",
    "sg:city":"Esslingen",
    "sg:phone":"+49 711/359949",
    "sg:postcode":"73728",
    "sg:province":"Baden-W\u00fcrttemberg",
    "wof:name":"Hubert Pflieger",
    "wof:placetype":"venue"
},
  "geometry": {"coordinates":[9.311075,48.740372],"type":"Point"}
}