{
  "type": "Feature",
  "properties": {
    "iso:country":"DE",
    "sg:address":"Vogelweidestr. 3::",
    "sg:city":"M\u00fcnchen",
    "sg:phone":"+49 89/5515050",
    "sg:postcode":"81677",
    "sg:province":"Bayern",
    "wof:name":"Merkur Bank Kg Aa",
    "wof:placetype":"venue"
},
  "geometry": {"coordinates":[11.559701,48.139088],"type":"Point"}
}