{
  "type": "Feature",
  "properties": {
    "iso:country":"DE",
    "sg:address":"Klappertorstr. 47",
    "sg:city":"Monheim",
    "sg:phone":"+49 2173/96460",
    "sg:postcode":"40789",
    "sg:province":"Nordrhein-Westfalen",
    "wof:name":"Hotel Baumberger Rheinterrassen",
    "wof:placetype":"venue"
},
  "geometry": {"coordinates":[6.8790988922,51.1165008545],"type":"Point"}
}