{
  "type": "Feature",
  "properties": {
    "iso:country":"DE",
    "sg:address":"Vor dem Tor 16",
    "sg:city":"Rodenberg",
    "sg:phone":"+49 5723/913508",
    "sg:postcode":"31552",
    "sg:province":"Niedersachsen",
    "wof:name":"Walter M\u00fcnstermann",
    "wof:placetype":"venue"
},
  "geometry": {"coordinates":[9.3475627899,52.3072967529],"type":"Point"}
}