{
  "type": "Feature",
  "properties": {
    "iso:country":"DE",
    "sg:address":"Alfred-Brehm-Platz 16",
    "sg:city":"Frankfurt",
    "sg:phone":"+49 69/442052",
    "sg:postcode":"60316",
    "sg:province":"Hessen",
    "wof:name":"Zookiosk M\u00fchlberg Gmbh",
    "wof:placetype":"venue"
},
  "geometry": {"coordinates":[8.6988401413,50.1160087585],"type":"Point"}
}