{
  "type": "Feature",
  "properties": {
    "iso:country":"DE",
    "sg:address":"Argenstr. 27",
    "sg:city":"Kressbronn",
    "sg:phone":"+49 7543/6360",
    "sg:postcode":"88079",
    "sg:province":"Baden-W\u00fcrttemberg",
    "wof:name":"J. Seybold \u00dcbersetzungsb\u00fcro",
    "wof:placetype":"venue"
},
  "geometry": {"coordinates":[9.591853,47.596981],"type":"Point"}
}