{
  "type": "Feature",
  "properties": {
    "iso:country":"DE",
    "sg:address":"Bloher Landstr. 36",
    "sg:city":"Bad Zwischenahn",
    "sg:phone":"+49 441/69563",
    "sg:postcode":"26160",
    "sg:province":"Niedersachsen",
    "wof:name":"Wkr Import-export Handels Gmbh",
    "wof:placetype":"venue"
},
  "geometry": {"coordinates":[8.1391000748,53.1605911255],"type":"Point"}
}