{
  "type": "Feature",
  "properties": {
    "iso:country":"DE",
    "sg:address":"Hintere Dorfstr. 37",
    "sg:city":"Friesenheim",
    "sg:phone":"+49 7821/63929",
    "sg:postcode":"77948",
    "sg:province":"Baden-W\u00fcrttemberg",
    "wof:name":"Robert Kopf",
    "wof:placetype":"venue"
},
  "geometry": {"coordinates":[7.89706707,48.3754882812],"type":"Point"}
}