{
  "type": "Feature",
  "properties": {
    "iso:country":"DE",
    "sg:address":"Leiderer Stadtweg 67",
    "sg:city":"Aschaffenburg",
    "sg:phone":"+49 6021/89787",
    "sg:postcode":"63741",
    "sg:province":"Bayern",
    "wof:name":"Cnz Krebs Gmbh Computer Netzwerk Zubeh\u00f6r",
    "wof:placetype":"venue"
},
  "geometry": {"coordinates":[9.118574,49.974209],"type":"Point"}
}