{
  "type": "Feature",
  "properties": {
    "iso:country":"DE",
    "sg:address":"Eifelstr. 28",
    "sg:city":"Laubach",
    "sg:phone":"+49 2653/6163",
    "sg:postcode":"56759",
    "sg:province":"Rheinland-Pfalz",
    "wof:name":"A. Hermann",
    "wof:placetype":"venue"
},
  "geometry": {"coordinates":[7.072135,50.233173],"type":"Point"}
}