{
  "type": "Feature",
  "properties": {
    "iso:country":"DE",
    "sg:address":"Regensburger Str. 53",
    "sg:city":"Teublitz",
    "sg:phone":"+49 9471/98082",
    "sg:postcode":"93158",
    "sg:province":"Bayern",
    "wof:name":"Gastst\u00e4tte Hans Rauch",
    "wof:placetype":"venue"
},
  "geometry": {"coordinates":[12.086022377,49.2220649719],"type":"Point"}
}