{
  "type": "Feature",
  "properties": {
    "iso:country":"DE",
    "sg:address":"Sulzbrunnenstr. 12",
    "sg:city":"Sachsenheim",
    "sg:phone":"+49 7046/9810",
    "sg:postcode":"74343",
    "sg:province":"Baden-W\u00fcrttemberg",
    "wof:name":"Fontanis Mineralbrunnen Gmbh & Co. Kg",
    "wof:placetype":"venue"
},
  "geometry": {"coordinates":[9.0092105865,49.019153595],"type":"Point"}
}