{
  "type": "Feature",
  "properties": {
    "iso:country":"DE",
    "sg:address":"Bruchm\u00fchlen",
    "sg:city":"B\u00fcnde",
    "sg:phone":"+49 5226/5266",
    "sg:postcode":"32257",
    "sg:province":"Nordrhein-Westfalen",
    "wof:name":"Deutsche Bahn Ag",
    "wof:placetype":"venue"
},
  "geometry": {"coordinates":[8.5796699524,52.1968193054],"type":"Point"}
}