{
  "type": "Feature",
  "properties": {
    "iso:country":"DE",
    "sg:address":"Am Turm 15a",
    "sg:city":"Cottbus",
    "sg:phone":"+49 355/22902",
    "sg:postcode":"03046",
    "sg:province":"Brandenburg",
    "wof:name":"Sicherheitstechnik Am Turm Gmbh",
    "wof:placetype":"venue"
},
  "geometry": {"coordinates":[14.3325624466,51.758605957],"type":"Point"}
}