{
  "type": "Feature",
  "properties": {
    "iso:country":"DE",
    "sg:address":"Am Eichenhof 22",
    "sg:city":"Achim",
    "sg:postcode":"28832",
    "sg:province":"Niedersachsen",
    "wof:name":"Quinting Gmbh",
    "wof:placetype":"venue"
},
  "geometry": {"coordinates":[9.0515670776,53.0002746582],"type":"Point"}
}