{
  "type": "Feature",
  "properties": {
    "iso:country":"DE",
    "sg:address":"Bremer Str. 257c",
    "sg:city":"Delmenhorst",
    "sg:phone":"+49 4221/72973",
    "sg:postcode":"27751",
    "sg:province":"Niedersachsen",
    "wof:name":"B. Menkens",
    "wof:placetype":"venue"
},
  "geometry": {"coordinates":[8.6708126068,53.0533676147],"type":"Point"}
}