{
  "type": "Feature",
  "properties": {
    "iso:country":"DE",
    "sg:address":"Hauptstr. 20",
    "sg:city":"Leutesdorf",
    "sg:phone":"+49 2631/72771",
    "sg:postcode":"56599",
    "sg:province":"Rheinland-Pfalz",
    "wof:name":"A.-j. Braun",
    "wof:placetype":"venue"
},
  "geometry": {"coordinates":[7.3887228966,50.4501304626],"type":"Point"}
}