{
  "type": "Feature",
  "properties": {
    "iso:country":"DE",
    "sg:address":"Hermelsbacher Weg 75",
    "sg:city":"Siegen",
    "sg:phone":"+49 271/51295",
    "sg:postcode":"57072",
    "sg:province":"Nordrhein-Westfalen",
    "wof:name":"Ulrich Bebling",
    "wof:placetype":"venue"
},
  "geometry": {"coordinates":[8.0091753006,50.8835372925],"type":"Point"}
}