{
  "type": "Feature",
  "properties": {
    "iso:country":"DE",
    "sg:address":"Griesplatz 6",
    "sg:city":"Himmelkron",
    "sg:phone":"+49 9273/8179",
    "sg:postcode":"95502",
    "sg:province":"Bayern",
    "wof:name":"Jeanette Peter-p\u00f6hlmann Heilpraktikerin",
    "wof:placetype":"venue"
},
  "geometry": {"coordinates":[11.6010847092,50.0508880615],"type":"Point"}
}