{
  "type": "Feature",
  "properties": {
    "iso:country":"DE",
    "sg:address":"Am Wildb\u00e4dle 6",
    "sg:city":"Stuttgart",
    "sg:phone":"+49 711/4093994",
    "sg:postcode":"70329",
    "sg:province":"Baden-W\u00fcrttemberg",
    "wof:name":"R&m Datentr\u00e4ger-duplizierung",
    "wof:placetype":"venue"
},
  "geometry": {"coordinates":[9.247652,48.755627],"type":"Point"}
}