{
  "type": "Feature",
  "properties": {
    "iso:country":"DE",
    "sg:address":"Lindenallee 14",
    "sg:city":"Warlow",
    "sg:phone":"+49 38751/20106",
    "sg:postcode":"19288",
    "sg:province":"Mecklenburg-Vorpommern",
    "wof:name":"Gerhard Mellmann",
    "wof:placetype":"venue"
},
  "geometry": {"coordinates":[11.403226,53.348934],"type":"Point"}
}