{
  "type": "Feature",
  "properties": {
    "iso:country":"DE",
    "sg:address":"Breite Str. 14",
    "sg:city":"Bad Vilbel",
    "sg:phone":"+49 6101/41866",
    "sg:postcode":"61118",
    "sg:province":"Hessen",
    "wof:name":"K. Tebbenhoff-niebergall Heilpraktiker",
    "wof:placetype":"venue"
},
  "geometry": {"coordinates":[8.7216777802,50.1913490295],"type":"Point"}
}