{
  "type": "Feature",
  "properties": {
    "iso:country":"DE",
    "sg:address":"Kurf\u00fcrstenstr. 10",
    "sg:city":"Koblenz",
    "sg:phone":"+49 261/15515",
    "sg:postcode":"56068",
    "sg:province":"Rheinland-Pfalz",
    "wof:name":"Wolfgang Walter Steuerberater",
    "wof:placetype":"venue"
},
  "geometry": {"coordinates":[7.5963110924,50.3528175354],"type":"Point"}
}