{
  "type": "Feature",
  "properties": {
    "iso:country":"DE",
    "sg:address":"N\u00f6rvenicher Str. 4",
    "sg:city":"D\u00fcren",
    "sg:phone":"+49 2421/73206",
    "sg:postcode":"52351",
    "sg:province":"Nordrhein-Westfalen",
    "wof:name":"Kroneneck",
    "wof:placetype":"venue"
},
  "geometry": {"coordinates":[6.4979500771,50.8023910522],"type":"Point"}
}