{
  "type": "Feature",
  "properties": {
    "iso:country":"DE",
    "sg:address":"Rissener Str. 39",
    "sg:city":"Wedel",
    "sg:phone":"+49 4103/84837",
    "sg:postcode":"22880",
    "sg:province":"Schleswig-Holstein",
    "wof:name":"Markus Pr\u00f6hl",
    "wof:placetype":"venue"
},
  "geometry": {"coordinates":[9.7172727585,53.5830116272],"type":"Point"}
}