{
  "type": "Feature",
  "properties": {
    "iso:country":"DE",
    "sg:address":"Kreuzstr. 31",
    "sg:city":"Bielefeld",
    "sg:phone":"+49 521/520570",
    "sg:postcode":"33602",
    "sg:province":"Nordrhein-Westfalen",
    "wof:name":"Ras Objekt- Und Innen- Einrichtungen Gmbh",
    "wof:placetype":"venue"
},
  "geometry": {"coordinates":[8.526568,52.016949],"type":"Point"}
}