{
  "type": "Feature",
  "properties": {
    "iso:country":"DE",
    "sg:address":"Steinstra\u00dfe",
    "sg:city":"Reken",
    "sg:phone":"+49 2864",
    "sg:postcode":"48734",
    "sg:province":"Nordrhein-Westfalen",
    "wof:name":"Sh-e / Susanne Hagedorn - Ern\u00e4hrungsberatung",
    "wof:placetype":"venue"
},
  "geometry": {"coordinates":[7.04295,51.834332],"type":"Point"}
}