{
  "type": "Feature",
  "properties": {
    "iso:country":"DE",
    "sg:address":"Lindengasse 15",
    "sg:city":"Allendorf",
    "sg:phone":"+49 6407/5788",
    "sg:postcode":"35469",
    "sg:province":"Hessen",
    "wof:name":"Zur Post",
    "wof:placetype":"venue"
},
  "geometry": {"coordinates":[8.8206348419,50.6753501892],"type":"Point"}
}