{
  "type": "Feature",
  "properties": {
    "iso:country":"DE",
    "sg:address":"Hermannstr. 21",
    "sg:city":"Neu-Isenburg",
    "sg:phone":"+49 6102/800966",
    "sg:postcode":"63263",
    "sg:province":"Hessen",
    "wof:name":"R\u00f6mer-lackfabrik C. Faul Nachf.",
    "wof:placetype":"venue"
},
  "geometry": {"coordinates":[8.687253,50.043961],"type":"Point"}
}