{
  "type": "Feature",
  "properties": {
    "iso:country":"DE",
    "sg:address":"Engelgasse 28",
    "sg:city":"Friesenheim",
    "sg:phone":"+49 7821/6636",
    "sg:postcode":"77948",
    "sg:province":"Baden-W\u00fcrttemberg",
    "wof:name":"Fritz Fellmeth",
    "wof:placetype":"venue"
},
  "geometry": {"coordinates":[7.875422,48.372528],"type":"Point"}
}