{
  "type": "Feature",
  "properties": {
    "iso:country":"DE",
    "sg:address":"Oberbettringer Str. 21",
    "sg:city":"Schw\u00e4bisch Gm\u00fcnd",
    "sg:phone":"+49 7171/66096",
    "sg:postcode":"73525",
    "sg:province":"Baden-W\u00fcrttemberg",
    "wof:name":"Ev. Pfarramt Augustinuskirche Mitte",
    "wof:placetype":"venue"
},
  "geometry": {"coordinates":[9.8024110794,48.7984771729],"type":"Point"}
}