{
  "type": "Feature",
  "properties": {
    "iso:country":"DE",
    "sg:address":"Markt 7",
    "sg:city":"Sch\u00f6ppenstedt",
    "sg:phone":"+49 5332/1896",
    "sg:postcode":"38170",
    "sg:province":"Niedersachsen",
    "wof:name":"Horst Prange",
    "wof:placetype":"venue"
},
  "geometry": {"coordinates":[10.7745113373,52.1445426941],"type":"Point"}
}