{
  "type": "Feature",
  "properties": {
    "iso:country":"DE",
    "sg:address":"Michael-Haydn-Weg 1",
    "sg:city":"Seeon",
    "sg:phone":"+49 8624/2253",
    "sg:postcode":"83370",
    "sg:province":"Bayern",
    "wof:name":"Vdg-von Der Goltz Gmbh",
    "wof:placetype":"venue"
},
  "geometry": {"coordinates":[12.45843,47.977341],"type":"Point"}
}