{
  "type": "Feature",
  "properties": {
    "iso:country":"DE",
    "sg:address":"Maybachstr 6",
    "sg:city":"Hettingen",
    "sg:phone":"+49 7574/934950",
    "sg:postcode":"72513",
    "sg:province":"Baden-W\u00fcrttemberg",
    "wof:name":"Hvd Werkstoff-service Gmbh",
    "wof:placetype":"venue"
},
  "geometry": {"coordinates":[9.231933,48.216328],"type":"Point"}
}