{
  "type": "Feature",
  "properties": {
    "iso:country":"DE",
    "sg:address":"Friedensstr.",
    "sg:city":"Ifta",
    "sg:phone":"+49 36926/98732",
    "sg:postcode":"99831",
    "sg:province":"Th\u00fcringen",
    "wof:name":"E. Meier",
    "wof:placetype":"venue"
},
  "geometry": {"coordinates":[10.175866,51.063961],"type":"Point"}
}