{
  "type": "Feature",
  "properties": {
    "iso:country":"DE",
    "sg:address":"Osterwicker Str. 18",
    "sg:city":"Legden",
    "sg:postcode":"48739",
    "sg:province":"Nordrhein-Westfalen",
    "wof:name":"Rkw-telekommunikation Gmbh",
    "wof:placetype":"venue"
},
  "geometry": {"coordinates":[7.10808,52.030865],"type":"Point"}
}