{
  "type": "Feature",
  "properties": {
    "iso:country":"DE",
    "sg:address":"Wilhelm-H\u00f6gner-Str. 10",
    "sg:city":"Parsberg",
    "sg:phone":"+49 9492/1032",
    "sg:postcode":"92331",
    "sg:province":"Bayern",
    "wof:name":"Motorger\u00e4te S\u00f6llner Gmbh",
    "wof:placetype":"venue"
},
  "geometry": {"coordinates":[11.723229,49.16106],"type":"Point"}
}