{
  "type": "Feature",
  "properties": {
    "iso:country":"DE",
    "sg:address":"Osterfelder Str. 132",
    "sg:city":"Bottrop",
    "sg:phone":"+49 2041/721920",
    "sg:postcode":"46242",
    "sg:province":"Nordrhein-Westfalen",
    "wof:name":"Ganz-bautr\u00e4ger- Gmbh",
    "wof:placetype":"venue"
},
  "geometry": {"coordinates":[6.9105739594,51.5171661377],"type":"Point"}
}