{
  "type": "Feature",
  "properties": {
    "iso:country":"DE",
    "sg:address":"Kaemmererufer 20",
    "sg:city":"Hamburg",
    "sg:phone":"+49 40/6965763",
    "sg:postcode":"22303",
    "sg:province":"Hamburg",
    "wof:name":"M\u00fcller-knapp Und Partner Rechtsanw\u00e4lte",
    "wof:placetype":"venue"
},
  "geometry": {"coordinates":[10.0284519196,53.585105896],"type":"Point"}
}