{
  "type": "Feature",
  "properties": {
    "iso:country":"DE",
    "sg:address":"Zur Hall 3",
    "sg:city":"K\u00fcps",
    "sg:phone":"+49 9264/7143",
    "sg:postcode":"96328",
    "sg:province":"Bayern",
    "wof:name":"Alfred Rebhan",
    "wof:placetype":"venue"
},
  "geometry": {"coordinates":[11.260613,50.198421],"type":"Point"}
}