{
  "type": "Feature",
  "properties": {
    "iso:country":"DE",
    "sg:address":"N\u00fcrnberger Str. 3",
    "sg:city":"Leipzig",
    "sg:phone":"+49 341/269840",
    "sg:postcode":"04103",
    "sg:province":"Sachsen",
    "wof:name":"L-konzept Verwaltungs Gmbh & Co. C\u00f6thner Stra\u00dfe 47 Kg",
    "wof:placetype":"venue"
},
  "geometry": {"coordinates":[12.3850240707,51.3376655579],"type":"Point"}
}