{
  "type": "Feature",
  "properties": {
    "iso:country":"DE",
    "sg:address":"Steilshooper Str. 246",
    "sg:city":"Hamburg",
    "sg:phone":"+49 40/6300811",
    "sg:postcode":"22307",
    "sg:province":"Hamburg",
    "wof:name":"Fr. Lewino",
    "wof:placetype":"venue"
},
  "geometry": {"coordinates":[10.0510034561,53.6016845703],"type":"Point"}
}