{
  "type": "Feature",
  "properties": {
    "iso:country":"DE",
    "sg:address":"Goethestr. 2",
    "sg:city":"Blumberg",
    "sg:phone":"+49 7702/3262",
    "sg:postcode":"78176",
    "sg:province":"Baden-W\u00fcrttemberg",
    "wof:name":"Hasan Yazicigircin",
    "wof:placetype":"venue"
},
  "geometry": {"coordinates":[8.5312681198,47.8414306641],"type":"Point"}
}