{
  "type": "Feature",
  "properties": {
    "iso:country":"DE",
    "sg:address":"Nordhorner Str. 170",
    "sg:city":"G\u00fctersloh",
    "sg:phone":"+49 5241/77494",
    "sg:postcode":"33335",
    "sg:province":"Nordrhein-Westfalen",
    "wof:name":"Hans Fasse",
    "wof:placetype":"venue"
},
  "geometry": {"coordinates":[8.443375,51.930298],"type":"Point"}
}