{
  "type": "Feature",
  "properties": {
    "iso:country":"DE",
    "sg:address":"Berliner Str. 1",
    "sg:city":"Ronnenberg",
    "sg:phone":"+49 511/21450",
    "sg:postcode":"30952",
    "sg:province":"Niedersachsen",
    "wof:name":"Metro Distributions-logistik Gmbh & Co. Kg",
    "wof:placetype":"venue"
},
  "geometry": {"coordinates":[9.6697721481,52.3463783264],"type":"Point"}
}