{
  "type": "Feature",
  "properties": {
    "iso:country":"DE",
    "sg:address":"Loschwitzer Str. 31",
    "sg:city":"Dresden",
    "sg:phone":"+49 351/3103976",
    "sg:postcode":"01309",
    "sg:province":"Sachsen",
    "wof:name":"A-z Regale",
    "wof:placetype":"venue"
},
  "geometry": {"coordinates":[13.797356,51.053307],"type":"Point"}
}