{
  "type": "Feature",
  "properties": {
    "iso:country":"DE",
    "sg:address":"Hansastr. 98",
    "sg:city":"Wallenhorst",
    "sg:postcode":"49134",
    "sg:province":"Niedersachsen",
    "wof:name":"Wfg Digitalprinting Ohg",
    "wof:placetype":"venue"
},
  "geometry": {"coordinates":[7.964193,52.357998],"type":"Point"}
}