{
  "type": "Feature",
  "properties": {
    "iso:country":"DE",
    "sg:address":"Auf der Reute",
    "sg:city":"Reutlingen",
    "sg:phone":"+49 7072/5777",
    "sg:postcode":"72770",
    "sg:province":"Baden-W\u00fcrttemberg",
    "wof:name":"M. De Santis",
    "wof:placetype":"venue"
},
  "geometry": {"coordinates":[9.142235,48.448036],"type":"Point"}
}