{
  "type": "Feature",
  "properties": {
    "iso:country":"DE",
    "sg:address":"Carl-Bosch-Str. 2",
    "sg:city":"Neum\u00fcnster",
    "sg:phone":"+49 4321/909164",
    "sg:postcode":"24537",
    "sg:province":"Schleswig-Holstein",
    "wof:name":"Baumann Gmbh",
    "wof:placetype":"venue"
},
  "geometry": {"coordinates":[9.968069,54.105339],"type":"Point"}
}