{
  "type": "Feature",
  "properties": {
    "iso:country":"DE",
    "sg:address":"Poststr. 2",
    "sg:city":"Neuhaus",
    "sg:phone":"+49 38841/21464",
    "sg:postcode":"19273",
    "sg:province":"Mecklenburg-Vorpommern",
    "wof:name":"Bernd Tewes",
    "wof:placetype":"venue"
},
  "geometry": {"coordinates":[10.9308662415,53.2841758728],"type":"Point"}
}