{
  "type": "Feature",
  "properties": {
    "iso:country":"DE",
    "sg:address":"Straubinger Str. 8",
    "sg:city":"Abensberg",
    "sg:phone":"+49 9443/7666",
    "sg:postcode":"93326",
    "sg:province":"Bayern",
    "wof:name":"Schlemmertreff",
    "wof:placetype":"venue"
},
  "geometry": {"coordinates":[11.8507375717,48.8143730164],"type":"Point"}
}