{
  "type": "Feature",
  "properties": {
    "iso:country":"DE",
    "sg:address":"Adamstr. 25",
    "sg:city":"N\u00fcrnberg",
    "sg:phone":"+49 911/553572",
    "sg:postcode":"90489",
    "sg:province":"Bayern",
    "wof:name":"P. Spanheimer Massagepraxis",
    "wof:placetype":"venue"
},
  "geometry": {"coordinates":[11.097797,49.460995],"type":"Point"}
}