{
  "type": "Feature",
  "properties": {
    "iso:country":"DE",
    "sg:address":"M\u00fchlendamm 19",
    "sg:city":"Haren",
    "sg:phone":"+49 5932/2717",
    "sg:postcode":"49733",
    "sg:province":"Niedersachsen",
    "wof:name":"Heinrich Kiepe Binnenschiffahrt",
    "wof:placetype":"venue"
},
  "geometry": {"coordinates":[7.244102,52.793247],"type":"Point"}
}