{
  "type": "Feature",
  "properties": {
    "iso:country":"DE",
    "sg:address":"Niederoderwitzer Str. 10 d",
    "sg:city":"Spitzkunnersdorf",
    "sg:postcode":"02794",
    "sg:province":"Sachsen",
    "wof:name":"Allianz Versicherungs Ag",
    "wof:placetype":"venue"
},
  "geometry": {"coordinates":[14.6919059753,50.9385070801],"type":"Point"}
}