{
  "type": "Feature",
  "properties": {
    "iso:country":"DE",
    "sg:address":"M\u00fchltorstr. 8",
    "sg:city":"Lambsheim",
    "sg:phone":"+49 6233/352130",
    "sg:postcode":"67245",
    "sg:province":"Rheinland-Pfalz",
    "wof:name":"M\u00fchltor-apotheke",
    "wof:placetype":"venue"
},
  "geometry": {"coordinates":[8.288166,49.508324],"type":"Point"}
}