{
  "type": "Feature",
  "properties": {
    "iso:country":"DE",
    "sg:address":"Adelgundenstr. 21",
    "sg:city":"M\u00fcnchen",
    "sg:phone":"+49 89/21889480",
    "sg:postcode":"80538",
    "sg:province":"Bayern",
    "wof:name":"Digital Mountain Ag",
    "wof:placetype":"venue"
},
  "geometry": {"coordinates":[11.586247,48.136745],"type":"Point"}
}