{
  "type": "Feature",
  "properties": {
    "iso:country":"DE",
    "sg:address":"Gewerbering 3",
    "sg:city":"Crimmitschau",
    "sg:phone":"+49 3762/95210",
    "sg:postcode":"08451",
    "sg:province":"Sachsen",
    "wof:name":"Abc-allgemeiner Baubedarf Crimmitschau Gmbh",
    "wof:placetype":"venue"
},
  "geometry": {"coordinates":[12.4115610123,50.8215904236],"type":"Point"}
}