{
  "type": "Feature",
  "properties": {
    "iso:country":"DE",
    "sg:address":"Serlostr. 4",
    "sg:city":"Essen",
    "sg:phone":"+49 201/622150",
    "sg:postcode":"45143",
    "sg:province":"Nordrhein-Westfalen",
    "wof:name":"Do It Fitness-treff",
    "wof:placetype":"venue"
},
  "geometry": {"coordinates":[6.9763870239,51.461139679],"type":"Point"}
}