{
  "type": "Feature",
  "properties": {
    "iso:country":"DE",
    "sg:address":"R\u00fcgen-Galerie 26",
    "sg:city":"Sassnitz",
    "sg:phone":"+49 38392/50439",
    "sg:postcode":"18546",
    "sg:province":"Mecklenburg-Vorpommern",
    "wof:name":"Jesus Treff",
    "wof:placetype":"venue"
},
  "geometry": {"coordinates":[13.620844841,54.5158653259],"type":"Point"}
}