{
  "type": "Feature",
  "properties": {
    "iso:country":"DE",
    "sg:address":"Katzenbachstr. 5",
    "sg:city":"B\u00fchlertal",
    "sg:phone":"+49 7223/971753",
    "sg:postcode":"77830",
    "sg:province":"Baden-W\u00fcrttemberg",
    "wof:name":"M. Liebmann",
    "wof:placetype":"venue"
},
  "geometry": {"coordinates":[8.1899375916,48.6815834045],"type":"Point"}
}