{
  "type": "Feature",
  "properties": {
    "iso:country":"DE",
    "sg:address":"Paul-Straub-Str. 1a",
    "sg:city":"Tirschenreuth",
    "sg:phone":"+49 9631/1246",
    "sg:postcode":"95643",
    "sg:province":"Bayern",
    "wof:name":"Dr. Walter St\u00fctzel Notar",
    "wof:placetype":"venue"
},
  "geometry": {"coordinates":[12.3295497894,49.8816986084],"type":"Point"}
}