{
  "type": "Feature",
  "properties": {
    "iso:country":"DE",
    "sg:address":"Horstweg 27",
    "sg:city":"Berlin",
    "sg:phone":"+49 30/3214055",
    "sg:postcode":"14059",
    "sg:province":"Berlin",
    "wof:name":"Haupt",
    "wof:placetype":"venue"
},
  "geometry": {"coordinates":[13.290005,52.512207],"type":"Point"}
}