{
  "type": "Feature",
  "properties": {
    "iso:country":"DE",
    "sg:address":"Hanfweg 23",
    "sg:city":"St. Ingbert",
    "sg:phone":"+49 6894/7846",
    "sg:postcode":"66386",
    "sg:province":"Saarland",
    "wof:name":"Dimitri Gawlita Rechtsanwalt",
    "wof:placetype":"venue"
},
  "geometry": {"coordinates":[7.0984678268,49.2540168762],"type":"Point"}
}