{
  "type": "Feature",
  "properties": {
    "iso:country":"DE",
    "sg:address":"Baindter Str. 11",
    "sg:city":"Baienfurt",
    "sg:phone":"+49 751/561480",
    "sg:postcode":"88255",
    "sg:province":"Baden-W\u00fcrttemberg",
    "wof:name":"T\u00dcv S\u00fcdwest",
    "wof:placetype":"venue"
},
  "geometry": {"coordinates":[9.6539087296,47.8297271729],"type":"Point"}
}