{
  "type": "Feature",
  "properties": {
    "iso:country":"DE",
    "sg:address":"Brunnwiesenstr. 9",
    "sg:city":"Ostfildern",
    "sg:postcode":"73760",
    "sg:province":"Baden-W\u00fcrttemberg",
    "wof:name":"Diato Diamantwerkzeugent- Wicklung- Und Vertriebs-",
    "wof:placetype":"venue"
},
  "geometry": {"coordinates":[9.2439174652,48.7301673889],"type":"Point"}
}