{
  "type": "Feature",
  "properties": {
    "iso:country":"DE",
    "sg:address":"Merowingerstr. 12",
    "sg:city":"M\u00f6nchengladbach",
    "sg:phone":"+49 2166/20204",
    "sg:postcode":"41238",
    "sg:province":"Nordrhein-Westfalen",
    "wof:name":"Friedrich Blume Architekt",
    "wof:placetype":"venue"
},
  "geometry": {"coordinates":[6.470981,51.177006],"type":"Point"}
}