{
  "type": "Feature",
  "properties": {
    "iso:country":"DE",
    "sg:address":"Keithstr. 18-20",
    "sg:city":"Berlin",
    "sg:phone":"+49 30/2124770",
    "sg:postcode":"10787",
    "sg:province":"Berlin",
    "wof:name":"Aog Auktionen- Organisations-gmbh",
    "wof:placetype":"venue"
},
  "geometry": {"coordinates":[13.346174,52.503357],"type":"Point"}
}