{
  "type": "Feature",
  "properties": {
    "iso:country":"DE",
    "sg:address":"Siebiger\u00f6der Str. 5",
    "sg:city":"Helbra",
    "sg:phone":"+49 34772/27244",
    "sg:postcode":"06311",
    "sg:province":"Sachsen-Anhalt",
    "wof:name":"Drei Linden Eck",
    "wof:placetype":"venue"
},
  "geometry": {"coordinates":[11.4860696793,51.554725647],"type":"Point"}
}