{
  "type": "Feature",
  "properties": {
    "iso:country":"DE",
    "sg:address":"Ahle 88",
    "sg:city":"Heek",
    "sg:phone":"+49 2561/5434",
    "sg:postcode":"48619",
    "sg:province":"Nordrhein-Westfalen",
    "wof:name":"Gerd Und Ingrid Althoff",
    "wof:placetype":"venue"
},
  "geometry": {"coordinates":[7.0636267662,52.1013336182],"type":"Point"}
}