{
  "type": "Feature",
  "properties": {
    "iso:country":"DE",
    "sg:address":"Am Noll",
    "sg:city":"Hohenstein",
    "sg:phone":"+49 6124/3219",
    "sg:postcode":"65329",
    "sg:province":"Hessen",
    "wof:name":"Gsv Gesellschaft Selbst\u00e4ndiger Verkehrsunternehmen Im",
    "wof:placetype":"venue"
},
  "geometry": {"coordinates":[8.097345,50.195454],"type":"Point"}
}