{
  "type": "Feature",
  "properties": {
    "iso:country":"DE",
    "sg:address":"Zu dem Balken 9",
    "sg:city":"Wolfsburg",
    "sg:postcode":"38448",
    "sg:province":"Niedersachsen",
    "wof:name":"Aldi Gmbh & Co. Kg",
    "wof:placetype":"venue"
},
  "geometry": {"coordinates":[10.7810640335,52.4457321167],"type":"Point"}
}