{
  "type": "Feature",
  "properties": {
    "iso:country":"DE",
    "sg:address":"Rengers",
    "sg:city":"Isny",
    "sg:phone":"+49 7562/502",
    "sg:postcode":"88316",
    "sg:province":"Baden-W\u00fcrttemberg",
    "wof:name":"Anton Dieing",
    "wof:placetype":"venue"
},
  "geometry": {"coordinates":[10.0558986664,47.7186050415],"type":"Point"}
}