{
  "type": "Feature",
  "properties": {
    "iso:country":"DE",
    "sg:address":"Osterlandwehr 41",
    "sg:city":"Raesfeld",
    "sg:phone":"+49 2865/6455",
    "sg:postcode":"46348",
    "sg:province":"Nordrhein-Westfalen",
    "wof:name":"Alfons Heisterkamp Gmbh",
    "wof:placetype":"venue"
},
  "geometry": {"coordinates":[6.866819,51.753868],"type":"Point"}
}