{
  "type": "Feature",
  "properties": {
    "iso:country":"DE",
    "sg:address":"Walkm\u00fchlstr. 77",
    "sg:city":"Wiesbaden",
    "sg:phone":"+49 611/404331",
    "sg:postcode":"65195",
    "sg:province":"Hessen",
    "wof:name":"Besucherring Dr. Otto Kasten",
    "wof:placetype":"venue"
},
  "geometry": {"coordinates":[8.220051,50.09137],"type":"Point"}
}