{
  "type": "Feature",
  "properties": {
    "iso:country":"DE",
    "sg:address":"Freiherr-vom-Stein-Str. 8",
    "sg:city":"Nordhausen",
    "sg:phone":"+49 3631/982282",
    "sg:postcode":"99734",
    "sg:province":"Th\u00fcringen",
    "wof:name":"Donnerberg",
    "wof:placetype":"venue"
},
  "geometry": {"coordinates":[10.784964,51.497334],"type":"Point"}
}