{
  "type": "Feature",
  "properties": {
    "iso:country":"DE",
    "sg:address":"Clara-Zetkin-Str. 24",
    "sg:city":"Schwarzenberg",
    "sg:phone":"+49 3774/22796",
    "sg:postcode":"08340",
    "sg:province":"Sachsen",
    "wof:name":"Elektro-schneider",
    "wof:placetype":"venue"
},
  "geometry": {"coordinates":[12.776785,50.550423],"type":"Point"}
}