{
  "type": "Feature",
  "properties": {
    "iso:country":"DE",
    "sg:address":"Oberes-Rot-Str. 13",
    "sg:city":"W\u00f6rt",
    "sg:phone":"+49 7964/505",
    "sg:postcode":"73499",
    "sg:province":"Baden-W\u00fcrttemberg",
    "wof:name":"Dieter Waldsauer",
    "wof:placetype":"venue"
},
  "geometry": {"coordinates":[10.2710018158,49.0301437378],"type":"Point"}
}