{
  "type": "Feature",
  "properties": {
    "iso:country":"DE",
    "sg:address":"Kastanienallee 2 Thierbach",
    "sg:city":"Kitzscher",
    "sg:phone":"+49 3433/740133",
    "sg:postcode":"04567",
    "sg:province":"Sachsen",
    "wof:name":"Tara Paletten-handel- Und Reparaturdienst Gmbh",
    "wof:placetype":"venue"
},
  "geometry": {"coordinates":[12.54672,51.16993],"type":"Point"}
}