{
  "type": "Feature",
  "properties": {
    "iso:country":"DE",
    "sg:address":"Schwarzbachstr. 4",
    "sg:city":"Biberach",
    "sg:phone":"+49 7351/23530",
    "sg:postcode":"88400",
    "sg:province":"Baden-W\u00fcrttemberg",
    "wof:name":"Lore Zech",
    "wof:placetype":"venue"
},
  "geometry": {"coordinates":[9.792374,48.091164],"type":"Point"}
}