{
  "type": "Feature",
  "properties": {
    "iso:country":"DE",
    "sg:address":"Gildestr. 5",
    "sg:city":"Gl\u00fccksburg",
    "sg:phone":"+49 4631/622500",
    "sg:postcode":"24960",
    "sg:province":"Schleswig-Holstein",
    "wof:name":"Evergate Gmbh",
    "wof:placetype":"venue"
},
  "geometry": {"coordinates":[9.5389118195,54.8286361694],"type":"Point"}
}