{
  "type": "Feature",
  "properties": {
    "iso:country":"DE",
    "sg:address":"Vogelgesang 1 a",
    "sg:city":"Bagow",
    "sg:phone":"+49 33838/40367",
    "sg:postcode":"14778",
    "sg:province":"Brandenburg",
    "wof:name":"H. K\u00fchne",
    "wof:placetype":"venue"
},
  "geometry": {"coordinates":[12.53754,52.466873],"type":"Point"}
}