{
  "type": "Feature",
  "properties": {
    "iso:country":"DE",
    "sg:address":"L\u00f6bauer Str. 15",
    "sg:city":"Lawalde-Lauba",
    "sg:phone":"+49 35877/27263",
    "sg:postcode":"02708",
    "sg:province":"Sachsen",
    "wof:name":"Gabriele Fiedler",
    "wof:placetype":"venue"
},
  "geometry": {"coordinates":[14.6626195908,51.0877418518],"type":"Point"}
}