{
  "type": "Feature",
  "properties": {
    "iso:country":"DE",
    "sg:address":"Schiffgraben 59",
    "sg:city":"Hannover",
    "sg:phone":"+49 511/342129",
    "sg:postcode":"30175",
    "sg:province":"Niedersachsen",
    "wof:name":"Helmut Jander Wirtschaftsberater",
    "wof:placetype":"venue"
},
  "geometry": {"coordinates":[9.7524766922,52.3763465881],"type":"Point"}
}