{
  "type": "Feature",
  "properties": {
    "iso:country":"DE",
    "sg:address":"Niedereimerfeld 17",
    "sg:city":"Arnsberg",
    "sg:phone":"+49 4929/3196010",
    "sg:postcode":"59823",
    "sg:province":"Nordrhein-Westfalen",
    "wof:name":"Trachte-fahrzeugteile Gmbh",
    "wof:placetype":"venue"
},
  "geometry": {"coordinates":[8.0412044525,51.4199104309],"type":"Point"}
}