{
  "type": "Feature",
  "properties": {
    "iso:country":"DE",
    "sg:address":"Zweibr\u00fccker Str. 10",
    "sg:city":"Solingen",
    "sg:phone":"+49 212/78642",
    "sg:postcode":"42697",
    "sg:province":"Nordrhein-Westfalen",
    "wof:name":"G. Longwitz",
    "wof:placetype":"venue"
},
  "geometry": {"coordinates":[7.002407074,51.1590003967],"type":"Point"}
}