{
  "type": "Feature",
  "properties": {
    "iso:country":"DE",
    "sg:address":"L\u00fctzowstr 50",
    "sg:city":"Hagen",
    "sg:phone":"+49 2331/24811",
    "sg:postcode":"58095",
    "sg:province":"Nordrhein-Westfalen",
    "wof:name":"Edward Kopp Gmbh",
    "wof:placetype":"venue"
},
  "geometry": {"coordinates":[7.4835639,51.3623161316],"type":"Point"}
}