{
  "type": "Feature",
  "properties": {
    "iso:country":"DE",
    "sg:address":"Schulstr. 6",
    "sg:city":"Blieskastel",
    "sg:postcode":"66440",
    "sg:province":"Saarland",
    "wof:name":"Stadtb\u00fccherei Brenschelbach",
    "wof:placetype":"venue"
},
  "geometry": {"coordinates":[7.215193,49.203926],"type":"Point"}
}