{
  "type": "Feature",
  "properties": {
    "iso:country":"DE",
    "sg:address":"Kirchplatz 3",
    "sg:city":"Gransee",
    "sg:phone":"+49 3306/21469",
    "sg:postcode":"16775",
    "sg:province":"Brandenburg",
    "wof:name":"Redaktion Neues Granseer Tageblatt",
    "wof:placetype":"venue"
},
  "geometry": {"coordinates":[13.1572828293,53.007434845],"type":"Point"}
}