{
  "type": "Feature",
  "properties": {
    "iso:country":"DE",
    "sg:address":"Klever Str. 10",
    "sg:city":"Isselburg",
    "sg:phone":"+49 2874/98367",
    "sg:postcode":"46419",
    "sg:province":"Nordrhein-Westfalen",
    "wof:name":"Gpa Mechatronik Gmbh",
    "wof:placetype":"venue"
},
  "geometry": {"coordinates":[6.4234,51.844151],"type":"Point"}
}