{
  "type": "Feature",
  "properties": {
    "iso:country":"DE",
    "sg:address":"Holder\u00e4ckerstr. 10",
    "sg:city":"Stuttgart",
    "sg:postcode":"70499",
    "sg:province":"Baden-W\u00fcrttemberg",
    "wof:name":"Thales Communications Gmbh",
    "wof:placetype":"venue"
},
  "geometry": {"coordinates":[9.0992145538,48.8235969543],"type":"Point"}
}