{
  "type": "Feature",
  "properties": {
    "iso:country":"DE",
    "sg:address":"Leppestra\u00dfe 18-22",
    "sg:city":"Engelskirchen",
    "sg:phone":"+49 2263",
    "sg:postcode":"51766",
    "sg:province":"Nordrhein-Westfalen",
    "wof:name":"Druckerei Verlag Schiefeling Gmbh",
    "wof:placetype":"venue"
},
  "geometry": {"coordinates":[7.411806,50.988773],"type":"Point"}
}