{
  "type": "Feature",
  "properties": {
    "iso:country":"DE",
    "sg:address":"Georg-Engel-Str. 15b",
    "sg:city":"Greifswald",
    "sg:phone":"+49 3834/594135",
    "sg:postcode":"17489",
    "sg:province":"Mecklenburg-Vorpommern",
    "wof:name":"H. Und M. Zehm",
    "wof:placetype":"venue"
},
  "geometry": {"coordinates":[13.3694076538,54.0826416016],"type":"Point"}
}