{
  "type": "Feature",
  "properties": {
    "iso:country":"DE",
    "sg:address":"Raiffeisenstr 16a",
    "sg:city":"Friedberg",
    "sg:phone":"+49 6031/692929",
    "sg:postcode":"61169",
    "sg:province":"Hessen",
    "wof:name":"Avion Spedition Gmbh",
    "wof:placetype":"venue"
},
  "geometry": {"coordinates":[8.765477,50.324638],"type":"Point"}
}