{
  "type": "Feature",
  "properties": {
    "iso:country":"DE",
    "sg:address":"L\u00fcdersstr. 12",
    "sg:city":"M\u00fcnchen",
    "sg:phone":"+49 89/672004",
    "sg:postcode":"81737",
    "sg:province":"Bayern",
    "wof:name":"Katholisches Pfarramt St. Stephan",
    "wof:placetype":"venue"
},
  "geometry": {"coordinates":[11.6397066116,48.1014785767],"type":"Point"}
}