{
  "type": "Feature",
  "properties": {
    "iso:country":"DE",
    "sg:address":"Ilmstr. 4a",
    "sg:city":"Weimar",
    "sg:phone":"+49 3643/518748",
    "sg:postcode":"99425",
    "sg:province":"Th\u00fcringen",
    "wof:name":"Polozei",
    "wof:placetype":"venue"
},
  "geometry": {"coordinates":[11.343775,50.966015],"type":"Point"}
}