{
  "type": "Feature",
  "properties": {
    "iso:country":"DE",
    "sg:address":"Sittarder Str. 7",
    "sg:city":"Erkelenz",
    "sg:phone":"+49 2431/96630",
    "sg:postcode":"41812",
    "sg:province":"Nordrhein-Westfalen",
    "wof:name":"R & C Blechformtechnik Gmbh & Co. Kg",
    "wof:placetype":"venue"
},
  "geometry": {"coordinates":[6.3132128716,51.0649414062],"type":"Point"}
}