{
  "type": "Feature",
  "properties": {
    "iso:country":"DE",
    "sg:address":"Usedomweg 18",
    "sg:city":"G\u00fctersloh",
    "sg:phone":"+49 5241/460268",
    "sg:postcode":"33334",
    "sg:province":"Nordrhein-Westfalen",
    "wof:name":"Udo Niemuth Steuerberater",
    "wof:placetype":"venue"
},
  "geometry": {"coordinates":[8.4144001007,51.9478111267],"type":"Point"}
}