{
  "type": "Feature",
  "properties": {
    "iso:country":"DE",
    "sg:address":"Lange Str. 104",
    "sg:city":"Bad Driburg",
    "sg:phone":"+49 5253/2216",
    "sg:postcode":"33014",
    "sg:province":"Nordrhein-Westfalen",
    "wof:name":"Modehaus Wilhelm Maas Kg",
    "wof:placetype":"venue"
},
  "geometry": {"coordinates":[9.0213165283,51.7344665527],"type":"Point"}
}