{
  "type": "Feature",
  "properties": {
    "iso:country":"DE",
    "sg:address":"Lelbach B 12",
    "sg:city":"Korbach",
    "sg:phone":"+49 5631/8281",
    "sg:postcode":"34497",
    "sg:province":"Hessen",
    "wof:name":"Heinz-ludwig Saake",
    "wof:placetype":"venue"
},
  "geometry": {"coordinates":[8.82922,51.291664],"type":"Point"}
}