{
  "type": "Feature",
  "properties": {
    "iso:country":"DE",
    "sg:address":"Altersham 26",
    "sg:city":"Pfarrkirchen",
    "sg:phone":"+49 8561/1392",
    "sg:postcode":"84347",
    "sg:province":"Bayern",
    "wof:name":"Karl Meiereder",
    "wof:placetype":"venue"
},
  "geometry": {"coordinates":[12.9504,48.410679],"type":"Point"}
}