{
  "type": "Feature",
  "properties": {
    "iso:country":"DE",
    "sg:address":"Kurhessenstr. 121-123",
    "sg:city":"Frankfurt",
    "sg:phone":"+49 69/533029",
    "sg:postcode":"60431",
    "sg:province":"Hessen",
    "wof:name":"Bernd Gerich Ingenieur",
    "wof:placetype":"venue"
},
  "geometry": {"coordinates":[8.6557340622,50.1473426819],"type":"Point"}
}