{
  "type": "Feature",
  "properties": {
    "iso:country":"DE",
    "sg:address":"Siemensstr. 1",
    "sg:city":"Eggenstein-Leopoldshafen",
    "sg:phone":"+49 721/788801",
    "sg:postcode":"76344",
    "sg:province":"Baden-W\u00fcrttemberg",
    "wof:name":"Sportkegelcenter",
    "wof:placetype":"venue"
},
  "geometry": {"coordinates":[8.3790616989,49.0749206543],"type":"Point"}
}