{
  "type": "Feature",
  "properties": {
    "iso:country":"DE",
    "sg:address":"Lindenstr. 3",
    "sg:city":"Burgen",
    "sg:phone":"+49 6534/8845",
    "sg:postcode":"54472",
    "sg:province":"Rheinland-Pfalz",
    "wof:name":"Horst Sauer",
    "wof:placetype":"venue"
},
  "geometry": {"coordinates":[7.0003051758,49.880027771],"type":"Point"}
}