{
  "type": "Feature",
  "properties": {
    "iso:country":"DE",
    "sg:address":"Schulstr. 18",
    "sg:city":"Blaustein",
    "sg:postcode":"89134",
    "sg:province":"Baden-W\u00fcrttemberg",
    "wof:name":"Home Care",
    "wof:placetype":"venue"
},
  "geometry": {"coordinates":[9.912399,48.417519],"type":"Point"}
}