{
  "type": "Feature",
  "properties": {
    "iso:country":"DE",
    "sg:address":"Schlesienstr. 8",
    "sg:city":"Bad Camberg",
    "sg:phone":"+49 6434/7586",
    "sg:postcode":"65520",
    "sg:province":"Hessen",
    "wof:name":"Heio Dembach Architekt",
    "wof:placetype":"venue"
},
  "geometry": {"coordinates":[8.267684,50.301437],"type":"Point"}
}