{
  "type": "Feature",
  "properties": {
    "iso:country":"DE",
    "sg:address":"Klostergartenstr.",
    "sg:city":"Erftstadt",
    "sg:phone":"+49 2235/8148",
    "sg:postcode":"50374",
    "sg:province":"Nordrhein-Westfalen",
    "wof:name":"Texaco-tankstelle",
    "wof:placetype":"venue"
},
  "geometry": {"coordinates":[6.8096852303,50.8202095032],"type":"Point"}
}