{
  "type": "Feature",
  "properties": {
    "iso:country":"DE",
    "sg:address":"Hochofenstr. 12",
    "sg:city":"Ilsenburg",
    "sg:phone":"+49 39452/9806",
    "sg:postcode":"38871",
    "sg:province":"Sachsen-Anhalt",
    "wof:name":"Steuerberatungsgesellschaft Jrk Ostharz Mbh",
    "wof:placetype":"venue"
},
  "geometry": {"coordinates":[10.6828317642,51.8662033081],"type":"Point"}
}