{
  "type": "Feature",
  "properties": {
    "iso:country":"DE",
    "sg:address":"In der Perch 1",
    "sg:city":"Weiskirchen",
    "sg:phone":"+49 6876/665",
    "sg:postcode":"66709",
    "sg:province":"Saarland",
    "wof:name":"Hochwaldhalle Weiskirchen",
    "wof:placetype":"venue"
},
  "geometry": {"coordinates":[6.815116,49.556313],"type":"Point"}
}