{
  "type": "Feature",
  "properties": {
    "iso:country":"DE",
    "sg:address":"Pfarrstr. 46",
    "sg:city":"Neuwied",
    "sg:phone":"+49 2631/87170",
    "sg:postcode":"56564",
    "sg:province":"Rheinland-Pfalz",
    "wof:name":"Michael Kahn Rechtsanwalt",
    "wof:placetype":"venue"
},
  "geometry": {"coordinates":[7.4627799988,50.4283905029],"type":"Point"}
}