{
  "type": "Feature",
  "properties": {
    "iso:country":"DE",
    "sg:address":"Mendener Str. 1",
    "sg:city":"Menden",
    "sg:postcode":"58710",
    "sg:province":"Nordrhein-Westfalen",
    "wof:name":"Ludger Droste Gmbh",
    "wof:placetype":"venue"
},
  "geometry": {"coordinates":[7.828512,51.417538],"type":"Point"}
}