{
  "type": "Feature",
  "properties": {
    "iso:country":"DE",
    "sg:address":"Hauptstr. 34",
    "sg:city":"Fischbeck",
    "sg:phone":"+49 39323/38618",
    "sg:postcode":"39524",
    "sg:province":"Sachsen-Anhalt",
    "wof:name":"G\u00e4stehaus Eveline Smolnik",
    "wof:placetype":"venue"
},
  "geometry": {"coordinates":[12.016661644,52.5410728455],"type":"Point"}
}