{
  "type": "Feature",
  "properties": {
    "iso:country":"DE",
    "sg:address":"Gro\u00dfe Bergstr. 142",
    "sg:city":"Hamburg",
    "sg:phone":"+49 40/3895558",
    "sg:postcode":"22767",
    "sg:province":"Hamburg",
    "wof:name":"Top Ten Club Gastst\u00e4tten U. Automaten",
    "wof:placetype":"venue"
},
  "geometry": {"coordinates":[9.9474954605,53.5511550903],"type":"Point"}
}