{
  "type": "Feature",
  "properties": {
    "iso:country":"DE",
    "sg:address":"Dessauer Str. 178 -179",
    "sg:city":"Lutherstadt Wittenberg",
    "sg:postcode":"06886",
    "sg:province":"Sachsen-Anhalt",
    "wof:name":"Piesteritzer Siedlungs- Gesellschaft Mbh",
    "wof:placetype":"venue"
},
  "geometry": {"coordinates":[12.594895,51.867798],"type":"Point"}
}