{
  "type": "Feature",
  "properties": {
    "iso:country":"DE",
    "sg:address":"Dieselstr. 24",
    "sg:city":"Gerlingen",
    "sg:phone":"+49 4971/562090",
    "sg:postcode":"70839",
    "sg:province":"Baden-W\u00fcrttemberg",
    "wof:name":"Endress & Hauser Condukta Mess- U. Regeltechnik Gmbh",
    "wof:placetype":"venue"
},
  "geometry": {"coordinates":[9.07228,48.80645],"type":"Point"}
}