{
  "type": "Feature",
  "properties": {
    "iso:country":"DE",
    "sg:address":"Gerberstr. 2 -4",
    "sg:city":"Solingen",
    "sg:phone":"+49 212/590290",
    "sg:postcode":"42653",
    "sg:province":"Nordrhein-Westfalen",
    "wof:name":"Hotel Gr\u00e4frather Hof",
    "wof:placetype":"venue"
},
  "geometry": {"coordinates":[7.0714569092,51.2084159851],"type":"Point"}
}