{
  "type": "Feature",
  "properties": {
    "iso:country":"DE",
    "sg:address":"Schlo\u00dfstr. 4",
    "sg:city":"L\u00fctzen",
    "sg:phone":"+49 34444/20228",
    "sg:postcode":"06686",
    "sg:province":"Sachsen-Anhalt",
    "wof:name":"Museum Im Schlo\u00df L\u00fctzen",
    "wof:placetype":"venue"
},
  "geometry": {"coordinates":[12.140039444,51.2547225952],"type":"Point"}
}