{
  "type": "Feature",
  "properties": {
    "iso:country":"DE",
    "sg:address":"Wilhelmstr. 31",
    "sg:city":"Fellbach",
    "sg:phone":"+49 711/5789229",
    "sg:postcode":"70734",
    "sg:province":"Baden-W\u00fcrttemberg",
    "wof:name":"M. Brand",
    "wof:placetype":"venue"
},
  "geometry": {"coordinates":[9.2724781036,48.8044128418],"type":"Point"}
}