{
  "type": "Feature",
  "properties": {
    "iso:country":"DE",
    "sg:address":"Oehleckerring 6a",
    "sg:city":"Hamburg",
    "sg:phone":"+49 40/5332120",
    "sg:postcode":"22419",
    "sg:province":"Hamburg",
    "wof:name":"Ingenieur-gruppe-nord Ges. F\u00fcr Geb\u00e4udetechnische Gesamt-",
    "wof:placetype":"venue"
},
  "geometry": {"coordinates":[10.00595,53.660786],"type":"Point"}
}