{
  "type": "Feature",
  "properties": {
    "iso:country":"DE",
    "sg:address":"Oberrimbach 29",
    "sg:city":"Burghaslach",
    "sg:phone":"+49 9552/481",
    "sg:postcode":"96152",
    "sg:province":"Bayern",
    "wof:name":"Theodor Hammerbacher",
    "wof:placetype":"venue"
},
  "geometry": {"coordinates":[10.5347242355,49.7276153564],"type":"Point"}
}