{
  "type": "Feature",
  "properties": {
    "iso:country":"DE",
    "sg:address":"Am Bach 12",
    "sg:city":"Landau",
    "sg:phone":"+49 9951/59316",
    "sg:postcode":"94405",
    "sg:province":"Bayern",
    "wof:name":"Heinz Schade",
    "wof:placetype":"venue"
},
  "geometry": {"coordinates":[12.685422,48.663044],"type":"Point"}
}