{
  "type": "Feature",
  "properties": {
    "iso:country":"DE",
    "sg:address":"Neckarstr. 48",
    "sg:city":"Hattersheim",
    "sg:phone":"+49 6145/34123",
    "sg:postcode":"65795",
    "sg:province":"Hessen",
    "wof:name":"Ihre Polsterei Waldemar Sappik & Partner Gmbh",
    "wof:placetype":"venue"
},
  "geometry": {"coordinates":[8.4751243591,50.0432777405],"type":"Point"}
}