{
  "type": "Feature",
  "properties": {
    "iso:country":"DE",
    "sg:address":"Kimbernstieg 27",
    "sg:city":"Hamburg",
    "sg:phone":"+49 40/5514343",
    "sg:postcode":"22455",
    "sg:province":"Hamburg",
    "wof:name":"Helmut D\u00fcring Verlagsvertreter",
    "wof:placetype":"venue"
},
  "geometry": {"coordinates":[9.96817,53.64011],"type":"Point"}
}