{
  "type": "Feature",
  "properties": {
    "iso:country":"DE",
    "sg:address":"Obernstr. 129",
    "sg:city":"Achim",
    "sg:phone":"+49 4202/3011",
    "sg:postcode":"28832",
    "sg:province":"Niedersachsen",
    "wof:name":"Esso-tankstelle",
    "wof:placetype":"venue"
},
  "geometry": {"coordinates":[9.0460653305,53.0052871704],"type":"Point"}
}