{
  "type": "Feature",
  "properties": {
    "iso:country":"DE",
    "sg:address":"Rankestr. 26",
    "sg:city":"Essen",
    "sg:phone":"+49 201/762866",
    "sg:postcode":"45144",
    "sg:province":"Nordrhein-Westfalen",
    "wof:name":"Hu\u00dfmann K\u00e4lteanlagen Gmbh",
    "wof:placetype":"venue"
},
  "geometry": {"coordinates":[6.97513,51.450699],"type":"Point"}
}