{
  "type": "Feature",
  "properties": {
    "iso:country":"DE",
    "sg:address":"Goethestrasse",
    "sg:city":"Stuttgart",
    "sg:phone":"+49 711/123456",
    "sg:postcode":"70170",
    "sg:province":"Baden-W\u00fcrttemberg",
    "wof:name":"Kostenlose Private Erotische Community",
    "wof:placetype":"venue"
},
  "geometry": {"coordinates":[-91.552673,34.498363],"type":"Point"}
}