{
  "type": "Feature",
  "properties": {
    "iso:country":"DE",
    "sg:address":"Oststr. 1",
    "sg:city":"Radeberg",
    "sg:phone":"+49 3528/444244",
    "sg:postcode":"01454",
    "sg:province":"Sachsen",
    "wof:name":"Rainer Galle",
    "wof:placetype":"venue"
},
  "geometry": {"coordinates":[13.922432,51.111191],"type":"Point"}
}