{
  "type": "Feature",
  "properties": {
    "iso:country":"DE",
    "sg:address":"Tempelherrenstr. 31",
    "sg:city":"Trier",
    "sg:phone":"+49 651/85421",
    "sg:postcode":"54294",
    "sg:province":"Rheinland-Pfalz",
    "wof:name":"Gerhard Diemer",
    "wof:placetype":"venue"
},
  "geometry": {"coordinates":[6.603874,49.73772],"type":"Point"}
}