{
  "type": "Feature",
  "properties": {
    "iso:country":"DE",
    "sg:address":"Birkenhain 42",
    "sg:city":"L\u00f6hne",
    "sg:phone":"+49 5732/7657",
    "sg:postcode":"32584",
    "sg:province":"Nordrhein-Westfalen",
    "wof:name":"Siegfried H\u00fcbner",
    "wof:placetype":"venue"
},
  "geometry": {"coordinates":[8.696355,52.23431],"type":"Point"}
}