{
  "type": "Feature",
  "properties": {
    "iso:country":"DE",
    "sg:address":"Dorfstr. 53",
    "sg:city":"L\u00fcttgenrode",
    "sg:phone":"+49 39421/73973",
    "sg:postcode":"38835",
    "sg:province":"Sachsen-Anhalt",
    "wof:name":"Hasso Walter",
    "wof:placetype":"venue"
},
  "geometry": {"coordinates":[10.66427,51.969116],"type":"Point"}
}