{
  "type": "Feature",
  "properties": {
    "iso:country":"DE",
    "sg:address":"Flensburger Str. 49",
    "sg:city":"B\u00f6klund",
    "sg:phone":"+49 4623/180080",
    "sg:postcode":"24860",
    "sg:province":"Schleswig-Holstein",
    "wof:name":"Wi-lo Bau Gmbh",
    "wof:placetype":"venue"
},
  "geometry": {"coordinates":[9.57736,54.608139],"type":"Point"}
}