{
  "type": "Feature",
  "properties": {
    "iso:country":"DE",
    "sg:address":"Br\u00fccklein 4",
    "sg:city":"Neudrossenfeld",
    "sg:phone":"+49 9203/276",
    "sg:postcode":"95512",
    "sg:province":"Bayern",
    "wof:name":"Trine B\u00fcttner",
    "wof:placetype":"venue"
},
  "geometry": {"coordinates":[11.503367424,50.0155677795],"type":"Point"}
}