{
  "type": "Feature",
  "properties": {
    "iso:country":"DE",
    "sg:address":"Falkenweg 15",
    "sg:city":"Straubing",
    "sg:phone":"+49 9421/923077",
    "sg:postcode":"94315",
    "sg:province":"Bayern",
    "wof:name":"Horst Seiler",
    "wof:placetype":"venue"
},
  "geometry": {"coordinates":[12.5960521698,48.8781700134],"type":"Point"}
}