{
  "type": "Feature",
  "properties": {
    "iso:country":"DE",
    "sg:address":"Eosanderstr. 20",
    "sg:city":"Berlin",
    "sg:phone":"+49 30/3419388",
    "sg:postcode":"10587",
    "sg:province":"Berlin",
    "wof:name":"Gastst\u00e4tte Luisen-br\u00e4u",
    "wof:placetype":"venue"
},
  "geometry": {"coordinates":[13.2999153137,52.520149231],"type":"Point"}
}