{
  "type": "Feature",
  "properties": {
    "iso:country":"DE",
    "sg:address":"Saumstr. 14",
    "sg:city":"Hambr\u00fccken",
    "sg:phone":"+49 7255/2314",
    "sg:postcode":"76707",
    "sg:province":"Baden-W\u00fcrttemberg",
    "wof:name":"A. Neuberth",
    "wof:placetype":"venue"
},
  "geometry": {"coordinates":[8.5356731415,49.1863365173],"type":"Point"}
}