{
  "type": "Feature",
  "properties": {
    "iso:country":"DE",
    "sg:address":"Iltener Str 44",
    "sg:city":"Lehrte",
    "sg:phone":"+49 5132/823800",
    "sg:postcode":"31275",
    "sg:province":"Niedersachsen",
    "wof:name":"Dolmetscherb\u00fcro F\u00fcr Die Russische Sprache",
    "wof:placetype":"venue"
},
  "geometry": {"coordinates":[9.9686546326,52.3677597046],"type":"Point"}
}