{
  "type": "Feature",
  "properties": {
    "iso:country":"DE",
    "sg:address":"Kaakstr. 4",
    "sg:city":"Jever",
    "sg:postcode":"26441",
    "sg:province":"Niedersachsen",
    "wof:name":"Bz Event Away Gmbh",
    "wof:placetype":"venue"
},
  "geometry": {"coordinates":[7.905559063,53.5741462708],"type":"Point"}
}