{
  "type": "Feature",
  "properties": {
    "iso:country":"DE",
    "sg:address":"Lixfelder Weg 51",
    "sg:city":"Frankfurt",
    "sg:phone":"+49 69/783808",
    "sg:postcode":"60489",
    "sg:province":"Hessen",
    "wof:name":"Walter Fetscher",
    "wof:placetype":"venue"
},
  "geometry": {"coordinates":[8.600528,50.117947],"type":"Point"}
}