{
  "type": "Feature",
  "properties": {
    "iso:country":"DE",
    "sg:address":"Hospitalstrasse 33",
    "sg:city":"Stuttgart",
    "sg:postcode":"70174",
    "sg:province":"Baden-W\u00fcrttemberg",
    "wof:name":"2 Sichere Partner F\u00fcr Bauen Und Wohnen",
    "wof:placetype":"venue"
},
  "geometry": {"coordinates":[9.171277,48.776039],"type":"Point"}
}