{
  "type": "Feature",
  "properties": {
    "iso:country":"DE",
    "sg:address":"Istruper Str. 57",
    "sg:city":"Blomberg",
    "sg:postcode":"32825",
    "sg:province":"Nordrhein-Westfalen",
    "wof:name":"Artur Redecker Lebensmittelgesch\u00e4ft",
    "wof:placetype":"venue"
},
  "geometry": {"coordinates":[9.0289649963,51.9415512085],"type":"Point"}
}