{
  "type": "Feature",
  "properties": {
    "iso:country":"DE",
    "sg:address":"D\u00fcrrenhofstr. 50",
    "sg:city":"N\u00fcrnberg",
    "sg:postcode":"90402",
    "sg:province":"Bayern",
    "wof:name":"Esm Service Gmbh",
    "wof:placetype":"venue"
},
  "geometry": {"coordinates":[11.09724,49.449402],"type":"Point"}
}