{
  "type": "Feature",
  "properties": {
    "iso:country":"DE",
    "sg:address":"Gewerbering 14 e",
    "sg:city":"Zeestow",
    "sg:phone":"+49 33234/89701",
    "sg:postcode":"14641",
    "sg:province":"Brandenburg",
    "wof:name":"B. Heynert",
    "wof:placetype":"venue"
},
  "geometry": {"coordinates":[12.879175,52.608898],"type":"Point"}
}