{
  "type": "Feature",
  "properties": {
    "iso:country":"DE",
    "sg:address":"Marschall 75",
    "sg:city":"Holzkirchen",
    "sg:phone":"+49 8024/7141",
    "sg:postcode":"83607",
    "sg:province":"Bayern",
    "wof:name":"S\u00fcd-treibstoff Mineral\u00f6lhandelsgesellschaft",
    "wof:placetype":"venue"
},
  "geometry": {"coordinates":[11.7176446915,47.8719100952],"type":"Point"}
}