{
  "type": "Feature",
  "properties": {
    "iso:country":"DE",
    "sg:address":"S\u00fcdstr. 4",
    "sg:city":"Langenbrettach",
    "sg:phone":"+49 7946/2695",
    "sg:postcode":"74243",
    "sg:province":"Baden-W\u00fcrttemberg",
    "wof:name":"Rainer Vogt Gmbh",
    "wof:placetype":"venue"
},
  "geometry": {"coordinates":[9.4197673798,49.2119941711],"type":"Point"}
}