{
  "type": "Feature",
  "properties": {
    "iso:country":"DE",
    "sg:address":"Haderholzstr. 17",
    "sg:city":"Floh-Seligenthal",
    "sg:phone":"+49 4936/8369260",
    "sg:postcode":"98593",
    "sg:province":"Th\u00fcringen",
    "wof:name":"Dux Lederwaren Gmbh",
    "wof:placetype":"venue"
},
  "geometry": {"coordinates":[10.4754581451,50.7653961182],"type":"Point"}
}