{
  "type": "Feature",
  "properties": {
    "iso:country":"DE",
    "sg:address":"Klever Str. 26-28",
    "sg:city":"Goch",
    "sg:phone":"+49 4928/2393100",
    "sg:postcode":"47574",
    "sg:province":"Nordrhein-Westfalen",
    "wof:name":"Stadtwerke Goch Gmbh",
    "wof:placetype":"venue"
},
  "geometry": {"coordinates":[6.159395,51.685684],"type":"Point"}
}