{
  "type": "Feature",
  "properties": {
    "iso:country":"DE",
    "sg:address":"Rudolf-Diesel-Str 2-4",
    "sg:city":"Dormagen",
    "sg:phone":"+49 5545/91030",
    "sg:postcode":"41541",
    "sg:province":"Nordrhein-Westfalen",
    "wof:name":"Edgar Hausmann Gmbh",
    "wof:placetype":"venue"
},
  "geometry": {"coordinates":[9.7676687241,51.3933906555],"type":"Point"}
}