{
  "type": "Feature",
  "properties": {
    "iso:country":"DE",
    "sg:address":"H\u00f6velstr. 40",
    "sg:city":"Petersberg",
    "sg:phone":"+49 661/63501",
    "sg:postcode":"36100",
    "sg:province":"Hessen",
    "wof:name":"Marianne Und Ch. Kleineidam Krankengymnasten",
    "wof:placetype":"venue"
},
  "geometry": {"coordinates":[9.706276,50.555],"type":"Point"}
}