{
  "type": "Feature",
  "properties": {
    "iso:country":"DE",
    "sg:address":"Stra\u00dfe der Einheit 61",
    "sg:city":"Oranienburg",
    "sg:phone":"+49 3301/803713",
    "sg:postcode":"16515",
    "sg:province":"Brandenburg",
    "wof:name":"Baubetrieb Leisse Gmbh",
    "wof:placetype":"venue"
},
  "geometry": {"coordinates":[13.254107,52.764633],"type":"Point"}
}