{
  "type": "Feature",
  "properties": {
    "iso:country":"DE",
    "sg:address":"Eppsteiner Str. 22",
    "sg:city":"Frankenthal",
    "sg:phone":"+49 6233/55323",
    "sg:postcode":"67227",
    "sg:province":"Rheinland-Pfalz",
    "wof:name":"Avalon",
    "wof:placetype":"venue"
},
  "geometry": {"coordinates":[8.3341035843,49.5124015808],"type":"Point"}
}