{
  "type": "Feature",
  "properties": {
    "iso:country":"DE",
    "sg:address":"Meesmannstr. 74",
    "sg:city":"Witten",
    "sg:phone":"+49 2302/71318",
    "sg:postcode":"58456",
    "sg:province":"Nordrhein-Westfalen",
    "wof:name":"Familien- Und Krankenpflege E. V.",
    "wof:placetype":"venue"
},
  "geometry": {"coordinates":[7.280217,51.421001],"type":"Point"}
}