{
  "type": "Feature",
  "properties": {
    "iso:country":"DE",
    "sg:address":"Grasmannsdorf",
    "sg:city":"Furth im Wald",
    "sg:phone":"+49 9973/1007",
    "sg:postcode":"93437",
    "sg:province":"Bayern",
    "wof:name":"Gastst\u00e4tte Johann Und F. Sperl",
    "wof:placetype":"venue"
},
  "geometry": {"coordinates":[12.843460083,49.2896003723],"type":"Point"}
}