{
  "type": "Feature",
  "properties": {
    "iso:country":"DE",
    "sg:address":"Bahnhofstr. 12a",
    "sg:city":"Morsbach",
    "sg:phone":"+49 2294/380",
    "sg:postcode":"51597",
    "sg:province":"Nordrhein-Westfalen",
    "wof:name":"M\u00f6belhaus Schneider Gmbh",
    "wof:placetype":"venue"
},
  "geometry": {"coordinates":[7.726552,50.864357],"type":"Point"}
}