{
  "type": "Feature",
  "properties": {
    "iso:country":"DE",
    "sg:address":"Ehinger Str. 25",
    "sg:city":"Rottenacker",
    "sg:phone":"+49 7393/3200",
    "sg:postcode":"89616",
    "sg:province":"Baden-W\u00fcrttemberg",
    "wof:name":"Walter Baustoffe Inh. Lamparter E. K.",
    "wof:placetype":"venue"
},
  "geometry": {"coordinates":[9.687475,48.232746],"type":"Point"}
}