{
  "type": "Feature",
  "properties": {
    "iso:country":"DE",
    "sg:address":"Werkstr. 210",
    "sg:city":"Schwerin",
    "sg:phone":"+49 385/612002",
    "sg:postcode":"19061",
    "sg:province":"Mecklenburg-Vorpommern",
    "wof:name":"Lux Deutschland Gmbh",
    "wof:placetype":"venue"
},
  "geometry": {"coordinates":[11.382440567,53.5762138367],"type":"Point"}
}