{
  "type": "Feature",
  "properties": {
    "iso:country":"DE",
    "sg:address":"Illinger Str. 11",
    "sg:city":"Illingen",
    "sg:phone":"+49 7043/2149",
    "sg:postcode":"75428",
    "sg:province":"Baden-W\u00fcrttemberg",
    "wof:name":"G. Mayer",
    "wof:placetype":"venue"
},
  "geometry": {"coordinates":[8.9066696167,48.9561157227],"type":"Point"}
}