{
  "type": "Feature",
  "properties": {
    "iso:country":"DE",
    "sg:address":"Monschauer Str. 172",
    "sg:city":"D\u00fcren",
    "sg:phone":"+49 2421/83232",
    "sg:postcode":"52355",
    "sg:province":"Nordrhein-Westfalen",
    "wof:name":"H. - J. Karduck",
    "wof:placetype":"venue"
},
  "geometry": {"coordinates":[6.452673,50.771774],"type":"Point"}
}