{
  "type": "Feature",
  "properties": {
    "iso:country":"DE",
    "sg:address":"Hamburgerstr.129",
    "sg:city":"Ahrensburg",
    "sg:phone":"+49 4102/898302",
    "sg:postcode":"22926",
    "sg:province":"Schleswig-Holstein",
    "wof:name":"Surfen & Geld Verdienen",
    "wof:placetype":"venue"
},
  "geometry": {"coordinates":[10.224546,53.665581],"type":"Point"}
}