{
  "type": "Feature",
  "properties": {
    "iso:country":"DE",
    "sg:address":"Ulmer Str. 12",
    "sg:city":"Laupheim",
    "sg:phone":"+49 7392/18111",
    "sg:postcode":"88471",
    "sg:province":"Baden-W\u00fcrttemberg",
    "wof:name":"Peter Klotz",
    "wof:placetype":"venue"
},
  "geometry": {"coordinates":[9.877727,48.228851],"type":"Point"}
}