{
  "type": "Feature",
  "properties": {
    "iso:country":"DE",
    "sg:address":"Wegelystrasse 1",
    "sg:city":"Berlin",
    "sg:phone":"+49 30/3912012",
    "sg:postcode":"10623",
    "sg:province":"Berlin",
    "wof:name":"Tecedit Gmbh",
    "wof:placetype":"venue"
},
  "geometry": {"coordinates":[13.333078,52.515228],"type":"Point"}
}