{
  "type": "Feature",
  "properties": {
    "iso:country":"DE",
    "sg:address":"Kirchplatz 17",
    "sg:city":"Delbr\u00fcck",
    "sg:phone":"+49 5250/8003",
    "sg:postcode":"33129",
    "sg:province":"Nordrhein-Westfalen",
    "wof:name":"Heinz Kiko",
    "wof:placetype":"venue"
},
  "geometry": {"coordinates":[8.562382,51.764076],"type":"Point"}
}