{
  "type": "Feature",
  "properties": {
    "iso:country":"DE",
    "sg:address":"Hanns-Martin-Schleyer-Str. 1",
    "sg:city":"Willich",
    "sg:phone":"+49 4921/5492530",
    "sg:postcode":"47877",
    "sg:province":"Nordrhein-Westfalen",
    "wof:name":"Osterath Gmbh",
    "wof:placetype":"venue"
},
  "geometry": {"coordinates":[6.5101428032,51.2733802795],"type":"Point"}
}