{
  "type": "Feature",
  "properties": {
    "iso:country":"DE",
    "sg:address":"Riemeisterstr. 43",
    "sg:city":"Berlin",
    "sg:phone":"+49 30/81499863",
    "sg:postcode":"14169",
    "sg:province":"Berlin",
    "wof:name":"Hannelore Schroether Steuerberaterin",
    "wof:placetype":"venue"
},
  "geometry": {"coordinates":[13.2605352402,52.4448204041],"type":"Point"}
}