{
  "type": "Feature",
  "properties": {
    "iso:country":"DE",
    "sg:address":"Einsteinstr. 61",
    "sg:city":"Heilbronn",
    "sg:phone":"+49 7131/172503",
    "sg:postcode":"74074",
    "sg:province":"Baden-W\u00fcrttemberg",
    "wof:name":"Deutscher Amateur Radio-club E. V.",
    "wof:placetype":"venue"
},
  "geometry": {"coordinates":[9.2453279495,49.1347579956],"type":"Point"}
}