{
  "type": "Feature",
  "properties": {
    "iso:country":"DE",
    "sg:address":"Otlerstr. 16",
    "sg:city":"Bad Neuenahr-Ahrweiler",
    "sg:phone":"+49 2641/36104",
    "sg:postcode":"53474",
    "sg:province":"Rheinland-Pfalz",
    "wof:name":"Helmut Poppelreuter",
    "wof:placetype":"venue"
},
  "geometry": {"coordinates":[7.101364,50.539078],"type":"Point"}
}