{
  "type": "Feature",
  "properties": {
    "iso:country":"DE",
    "sg:address":"Hauptstr. 54",
    "sg:city":"Bessenbach",
    "sg:phone":"+49 6095/995496",
    "sg:postcode":"63856",
    "sg:province":"Bayern",
    "wof:name":"G. Osha Drogerie",
    "wof:placetype":"venue"
},
  "geometry": {"coordinates":[9.252605,49.971275],"type":"Point"}
}