{
  "type": "Feature",
  "properties": {
    "iso:country":"DE",
    "sg:address":"H\u00fcttlinger Weg 1",
    "sg:city":"Leonberg",
    "sg:phone":"+49 7152/72741",
    "sg:postcode":"71229",
    "sg:province":"Baden-W\u00fcrttemberg",
    "wof:name":"Richard Schuster Architekt",
    "wof:placetype":"venue"
},
  "geometry": {"coordinates":[8.995845,48.788811],"type":"Point"}
}