{
  "type": "Feature",
  "properties": {
    "iso:country":"DE",
    "sg:address":"Goethestr. 1",
    "sg:city":"L\u00f6\u00dfnitz",
    "sg:phone":"+49 3771/35766",
    "sg:postcode":"08294",
    "sg:province":"Sachsen",
    "wof:name":"Ferdi Grignard",
    "wof:placetype":"venue"
},
  "geometry": {"coordinates":[12.7160520554,50.6116867065],"type":"Point"}
}