{
  "type": "Feature",
  "properties": {
    "iso:country":"DE",
    "sg:address":"Nordstr. 4",
    "sg:city":"Sarstedt",
    "sg:phone":"+49 5066/3053",
    "sg:postcode":"31157",
    "sg:province":"Niedersachsen",
    "wof:name":"H. Alves Ingenieur",
    "wof:placetype":"venue"
},
  "geometry": {"coordinates":[9.8463878632,52.2347373962],"type":"Point"}
}