{
  "type": "Feature",
  "properties": {
    "iso:country":"DE",
    "sg:address":"Marienbader Str. 13",
    "sg:city":"Berlin",
    "sg:phone":"+49 30/8299920",
    "sg:postcode":"14199",
    "sg:province":"Berlin",
    "wof:name":"Lilolandia Grundst\u00fccks- Verwaltungs Gmbh & Co.",
    "wof:placetype":"venue"
},
  "geometry": {"coordinates":[13.2833414078,52.4768295288],"type":"Point"}
}