{
  "type": "Feature",
  "properties": {
    "iso:country":"DE",
    "sg:address":"Ebertsklinge 30",
    "sg:city":"W\u00fcrzburg",
    "sg:phone":"+49 931/74056",
    "sg:postcode":"97074",
    "sg:province":"Bayern",
    "wof:name":"Hans P. Gl\u00fcck Ingenieur",
    "wof:placetype":"venue"
},
  "geometry": {"coordinates":[9.950676918,49.7774581909],"type":"Point"}
}