{
  "type": "Feature",
  "properties": {
    "iso:country":"DE",
    "sg:address":"M\u00fcnchhausenstr 19",
    "sg:city":"Bevern",
    "sg:phone":"+49 5531/80714",
    "sg:postcode":"37639",
    "sg:province":"Niedersachsen",
    "wof:name":"Mbe",
    "wof:placetype":"venue"
},
  "geometry": {"coordinates":[9.496572,51.853554],"type":"Point"}
}