{
  "type": "Feature",
  "properties": {
    "iso:country":"DE",
    "sg:address":"Bergstr. 28",
    "sg:city":"Haundorf",
    "sg:phone":"+49 9837/96863",
    "sg:postcode":"91729",
    "sg:province":"Bayern",
    "wof:name":"G\u00fcnter Uebler Steuerberater",
    "wof:placetype":"venue"
},
  "geometry": {"coordinates":[10.8327589035,49.1916275024],"type":"Point"}
}