{
  "type": "Feature",
  "properties": {
    "iso:country":"DE",
    "sg:address":"Schnellrodaer Str.",
    "sg:city":"Albersroda",
    "sg:phone":"+49 34632/22600",
    "sg:postcode":"06268",
    "sg:province":"Sachsen-Anhalt",
    "wof:name":"E. Osterland",
    "wof:placetype":"venue"
},
  "geometry": {"coordinates":[11.7159204483,51.2869338989],"type":"Point"}
}