{
  "type": "Feature",
  "properties": {
    "iso:country":"DE",
    "sg:address":"Frankfurter Str. 65",
    "sg:city":"Hennef",
    "sg:phone":"+49 2242/80055",
    "sg:postcode":"53773",
    "sg:province":"Nordrhein-Westfalen",
    "wof:name":"Manfred E. Nagel Rechtsanwalt",
    "wof:placetype":"venue"
},
  "geometry": {"coordinates":[7.2885479927,50.7737846375],"type":"Point"}
}