{
  "type": "Feature",
  "properties": {
    "iso:country":"DE",
    "sg:address":"thomas-m\u00fcntzer-Stra\u00dfe 28",
    "sg:city":"M\u00fchlhausen",
    "sg:phone":"+49 36014/23883",
    "sg:postcode":"99974",
    "sg:province":"Th\u00fcringen",
    "wof:name":"Reifen-heyer",
    "wof:placetype":"venue"
},
  "geometry": {"coordinates":[10.4781990051,51.2052726746],"type":"Point"}
}