{
  "type": "Feature",
  "properties": {
    "iso:country":"DE",
    "sg:address":"aguilera",
    "sg:city":"biarritz",
    "sg:phone":"+49 5592/39109",
    "sg:postcode":"64200",
    "wof:name":"Pelote Basque Au Biarritz Athl\u00e9tic Club",
    "wof:placetype":"venue"
},
  "geometry": {"coordinates":[-1.535309,43.483891],"type":"Point"}
}