{
  "type": "Feature",
  "properties": {
    "iso:country":"DE",
    "sg:address":"Fasanenstr. 8 b",
    "sg:city":"Unterhaching",
    "sg:phone":"+49 89/6152426",
    "sg:postcode":"82008",
    "sg:province":"Bayern",
    "wof:name":"Mirwald Elektronik Gmbh",
    "wof:placetype":"venue"
},
  "geometry": {"coordinates":[11.611705,48.069145],"type":"Point"}
}