{
  "type": "Feature",
  "properties": {
    "iso:country":"DE",
    "sg:address":"Wallstr. 10",
    "sg:city":"Kleinwallstadt",
    "sg:phone":"+49 6022/21213",
    "sg:postcode":"63839",
    "sg:province":"Bayern",
    "wof:name":"J. D\u00f6lger",
    "wof:placetype":"venue"
},
  "geometry": {"coordinates":[9.166934,49.873516],"type":"Point"}
}