{
  "type": "Feature",
  "properties": {
    "iso:country":"DE",
    "sg:address":"Otto-Hahn-Str. 40",
    "sg:city":"Bad Salzuflen",
    "sg:phone":"+49 5222/95590",
    "sg:postcode":"32108",
    "sg:province":"Nordrhein-Westfalen",
    "wof:name":"Bco Gmbh",
    "wof:placetype":"venue"
},
  "geometry": {"coordinates":[8.7501983643,52.0646324158],"type":"Point"}
}