{
  "type": "Feature",
  "properties": {
    "iso:country":"DE",
    "sg:address":"R\u00f6ntgenstr. 35",
    "sg:city":"Ditzingen",
    "sg:phone":"+49 7152/59660",
    "sg:postcode":"71254",
    "sg:province":"Baden-W\u00fcrttemberg",
    "wof:name":"Gerhard Bauer",
    "wof:placetype":"venue"
},
  "geometry": {"coordinates":[8.99472,48.852043],"type":"Point"}
}