{
  "type": "Feature",
  "properties": {
    "iso:country":"DE",
    "sg:address":"Hesttoft 30",
    "sg:city":"Flensburg",
    "sg:phone":"+49 461/314310",
    "sg:postcode":"24943",
    "sg:province":"Schleswig-Holstein",
    "wof:name":"Cmh Consulting Und Verm\u00f6gensverwaltung Ag",
    "wof:placetype":"venue"
},
  "geometry": {"coordinates":[9.463438,54.79538],"type":"Point"}
}