{
  "type": "Feature",
  "properties": {
    "iso:country":"DE",
    "sg:address":"Burgallee 69",
    "sg:city":"Hanau",
    "sg:phone":"+49 6181/256148",
    "sg:postcode":"63454",
    "sg:province":"Hessen",
    "wof:name":"Michael Pulch Steuerberater",
    "wof:placetype":"venue"
},
  "geometry": {"coordinates":[8.8851079941,50.141456604],"type":"Point"}
}