{
  "type": "Feature",
  "properties": {
    "iso:country":"DE",
    "sg:address":"Konrad-Adenauer-Platz 6",
    "sg:city":"Altenkirchen",
    "sg:phone":"+49 2681/6492",
    "sg:postcode":"57610",
    "sg:province":"Rheinland-Pfalz",
    "wof:name":"Torsten Wengenroth",
    "wof:placetype":"venue"
},
  "geometry": {"coordinates":[7.6369137764,50.6844406128],"type":"Point"}
}