{
  "type": "Feature",
  "properties": {
    "iso:country":"DE",
    "sg:address":"Br\u00fcckstr. 60",
    "sg:city":"Emden",
    "sg:phone":"+49 4921/23846",
    "sg:postcode":"26725",
    "sg:province":"Niedersachsen",
    "wof:name":"Gerhard Elend",
    "wof:placetype":"venue"
},
  "geometry": {"coordinates":[7.2113928795,53.3671188354],"type":"Point"}
}