{
  "type": "Feature",
  "properties": {
    "iso:country":"DE",
    "sg:address":"An der Alten Schule 6 c",
    "sg:city":"Barsb\u00fcttel",
    "sg:phone":"+49 40/6700941",
    "sg:postcode":"22885",
    "sg:province":"Schleswig-Holstein",
    "wof:name":"Horst Arpe",
    "wof:placetype":"venue"
},
  "geometry": {"coordinates":[10.1546173096,53.5700912476],"type":"Point"}
}