{
  "type": "Feature",
  "properties": {
    "iso:country":"DE",
    "sg:address":"Zuckerstr. 35",
    "sg:city":"Dieburg",
    "sg:phone":"+49 6071/25766",
    "sg:postcode":"64807",
    "sg:province":"Hessen",
    "wof:name":"Hersa-mode-filialen-gmbh",
    "wof:placetype":"venue"
},
  "geometry": {"coordinates":[8.840568,49.898182],"type":"Point"}
}