{
  "type": "Feature",
  "properties": {
    "iso:country":"DE",
    "sg:address":"Landstr. 20",
    "sg:city":"Ziesendorf",
    "sg:phone":"+49 38207/6610",
    "sg:postcode":"18059",
    "sg:province":"Mecklenburg-Vorpommern",
    "wof:name":"Hagmans Gmbh",
    "wof:placetype":"venue"
},
  "geometry": {"coordinates":[12.037955,53.994362],"type":"Point"}
}