{
  "type": "Feature",
  "properties": {
    "iso:country":"DE",
    "sg:address":"Huyssenallee 86-88::",
    "sg:city":"Essen",
    "sg:postcode":"45128",
    "sg:province":"Nordrhein-Westfalen",
    "wof:name":"Innovationszentrum Kreislaufpolymere Gmbh",
    "wof:placetype":"venue"
},
  "geometry": {"coordinates":[11.743765,48.400795],"type":"Point"}
}