{
  "type": "Feature",
  "properties": {
    "iso:country":"DE",
    "sg:address":"Bohnhorsterh\u00f6fen 11",
    "sg:city":"Warmsen",
    "sg:phone":"+49 5767/305",
    "sg:postcode":"31606",
    "sg:province":"Niedersachsen",
    "wof:name":"Heinrich Gerling",
    "wof:placetype":"venue"
},
  "geometry": {"coordinates":[8.849331,52.456074],"type":"Point"}
}