{
  "type": "Feature",
  "properties": {
    "iso:country":"DE",
    "sg:address":"Haustadter-Tal-Str. 234",
    "sg:city":"Beckingen",
    "sg:phone":"+49 6835/7690",
    "sg:postcode":"66701",
    "sg:province":"Saarland",
    "wof:name":"Urhahn-adam",
    "wof:placetype":"venue"
},
  "geometry": {"coordinates":[6.726167202,49.4155044556],"type":"Point"}
}