{
  "type": "Feature",
  "properties": {
    "iso:country":"DE",
    "sg:address":"Mozartstr. 40",
    "sg:city":"Berlin",
    "sg:phone":"+49 30/7699060",
    "sg:postcode":"12247",
    "sg:province":"Berlin",
    "wof:name":"Dr. J\u00fcrgen Wagner Gmbh",
    "wof:placetype":"venue"
},
  "geometry": {"coordinates":[13.3326730728,52.4399299622],"type":"Point"}
}