{
  "type": "Feature",
  "properties": {
    "iso:country":"DE",
    "sg:address":"Obere H\u00e4user 13",
    "sg:city":"Deutschneudorf",
    "sg:phone":"+49 37368/236",
    "sg:postcode":"09548",
    "sg:province":"Sachsen",
    "wof:name":"Christoph Vorwerk",
    "wof:placetype":"venue"
},
  "geometry": {"coordinates":[13.4615774155,50.6134262085],"type":"Point"}
}