{
  "type": "Feature",
  "properties": {
    "iso:country":"DE",
    "sg:address":"Eifelstr 25",
    "sg:city":"Solingen",
    "sg:phone":"+49 212/330750",
    "sg:postcode":"42699",
    "sg:province":"Nordrhein-Westfalen",
    "wof:name":"T\u00fcckmantel & Co Gmbh",
    "wof:placetype":"venue"
},
  "geometry": {"coordinates":[7.025365,51.168159],"type":"Point"}
}