{
  "type": "Feature",
  "properties": {
    "iso:country":"DE",
    "sg:address":"Winkelhauser Str. 31",
    "sg:city":"Duisburg",
    "sg:phone":"+49 203/432939",
    "sg:postcode":"47228",
    "sg:province":"Nordrhein-Westfalen",
    "wof:name":"Abs Verkehrsbau Ges. F\u00fcr Verkehrslenkungs- Und",
    "wof:placetype":"venue"
},
  "geometry": {"coordinates":[6.696078,51.424908],"type":"Point"}
}