{
  "type": "Feature",
  "properties": {
    "iso:country":"DE",
    "sg:address":"Limmerstr. 25",
    "sg:city":"Hannover",
    "sg:postcode":"30451",
    "sg:province":"Niedersachsen",
    "wof:name":"Su-tex Handelsgesellschaft Mbh",
    "wof:placetype":"venue"
},
  "geometry": {"coordinates":[9.7097568512,52.3725204468],"type":"Point"}
}