{
  "type": "Feature",
  "properties": {
    "iso:country":"DE",
    "sg:address":"L\u00fcrriper Str. 1-13",
    "sg:city":"M\u00f6nchengladbach",
    "sg:phone":"+49 2161/943254",
    "sg:postcode":"41065",
    "sg:province":"Nordrhein-Westfalen",
    "wof:name":"Deutsche Post Ag",
    "wof:placetype":"venue"
},
  "geometry": {"coordinates":[6.4460120201,51.1947250366],"type":"Point"}
}