{
  "type": "Feature",
  "properties": {
    "iso:country":"DE",
    "sg:address":"K\u00f6niginstr. 34",
    "sg:city":"M\u00fcnchen",
    "sg:phone":"+49 89/333402",
    "sg:postcode":"80802",
    "sg:province":"Bayern",
    "wof:name":"Reitschule Cafe Und Konditorei",
    "wof:placetype":"venue"
},
  "geometry": {"coordinates":[11.5888519287,48.1553344727],"type":"Point"}
}