{
  "type": "Feature",
  "properties": {
    "iso:country":"DE",
    "sg:address":"Westpreu\u00dfenstr. 2",
    "sg:city":"Reppenstedt",
    "sg:phone":"+49 4131/61255",
    "sg:postcode":"21391",
    "sg:province":"Niedersachsen",
    "wof:name":"Ulrich Borchmann",
    "wof:placetype":"venue"
},
  "geometry": {"coordinates":[10.3473701477,53.2500801086],"type":"Point"}
}