{
  "type": "Feature",
  "properties": {
    "iso:country":"DE",
    "sg:address":"Reetputt 6",
    "sg:city":"Hamburg",
    "sg:phone":"+49 40/7426389",
    "sg:postcode":"21129",
    "sg:province":"Hamburg",
    "wof:name":"Walter Drews Kunstmaler",
    "wof:placetype":"venue"
},
  "geometry": {"coordinates":[9.855005,53.536259],"type":"Point"}
}