{
  "type": "Feature",
  "properties": {
    "iso:country":"DE",
    "sg:address":"Hangstr. 66",
    "sg:city":"Gauting",
    "sg:phone":"+49 89/8506411",
    "sg:postcode":"82131",
    "sg:province":"Bayern",
    "wof:name":"Gerda Angerer-lessmann",
    "wof:placetype":"venue"
},
  "geometry": {"coordinates":[11.3845806122,48.0747833252],"type":"Point"}
}