{
  "type": "Feature",
  "properties": {
    "iso:country":"DE",
    "sg:address":"Schulstr. 7",
    "sg:city":"Etzelwang",
    "sg:phone":"+49 9663/580",
    "sg:postcode":"92268",
    "sg:province":"Bayern",
    "wof:name":"Freibad",
    "wof:placetype":"venue"
},
  "geometry": {"coordinates":[11.5854663849,49.5281448364],"type":"Point"}
}