{
  "type": "Feature",
  "properties": {
    "iso:country":"DE",
    "sg:address":"Heidenheimer Str. 6",
    "sg:city":"K\u00f6nigsbronn",
    "sg:phone":"+49 7328/6428",
    "sg:postcode":"89551",
    "sg:province":"Baden-W\u00fcrttemberg",
    "wof:name":"Esso Tankstelle",
    "wof:placetype":"venue"
},
  "geometry": {"coordinates":[10.1153783798,48.7402801514],"type":"Point"}
}