{
  "type": "Feature",
  "properties": {
    "iso:country":"DE",
    "sg:address":"Moerserstr. 234",
    "sg:city":"Kamp Lintfort",
    "sg:phone":"+49 2842/2135",
    "sg:postcode":"47475",
    "sg:province":"Nordrhein-Westfalen",
    "wof:name":"Deutsche Bank Ag",
    "wof:placetype":"venue"
},
  "geometry": {"coordinates":[6.546465,51.502254],"type":"Point"}
}