{
  "type": "Feature",
  "properties": {
    "iso:country":"DE",
    "sg:address":"Duisburger Str. 4",
    "sg:city":"Berlin",
    "sg:phone":"+49 30/8812130",
    "sg:postcode":"10707",
    "sg:province":"Berlin",
    "wof:name":"J\u00fcrgen Rei\u00dfbach Rechtsanwalt",
    "wof:placetype":"venue"
},
  "geometry": {"coordinates":[13.3103837967,52.4982337952],"type":"Point"}
}