{
  "type": "Feature",
  "properties": {
    "iso:country":"DE",
    "sg:address":"Erfurter Str. 15",
    "sg:city":"Kassel",
    "sg:phone":"+49 561/572994",
    "sg:postcode":"34123",
    "sg:province":"Hessen",
    "wof:name":"M. Baden",
    "wof:placetype":"venue"
},
  "geometry": {"coordinates":[9.52542,51.295238],"type":"Point"}
}