{
  "type": "Feature",
  "properties": {
    "iso:country":"DE",
    "sg:address":"Sprengelstr. 40",
    "sg:city":"Berlin",
    "sg:phone":"+49 30/4531651",
    "sg:postcode":"13353",
    "sg:province":"Berlin",
    "wof:name":"Bulut Malereibetriebs Gmbh",
    "wof:placetype":"venue"
},
  "geometry": {"coordinates":[13.356331,52.541946],"type":"Point"}
}