{
  "type": "Feature",
  "properties": {
    "iso:country":"DE",
    "sg:address":"Claudiusstr. 49",
    "sg:city":"Dormagen",
    "sg:phone":"+49 2133/60665",
    "sg:postcode":"41540",
    "sg:province":"Nordrhein-Westfalen",
    "wof:name":"Walter Und Margret G\u00f6ddertz",
    "wof:placetype":"venue"
},
  "geometry": {"coordinates":[6.8179302216,51.0714874268],"type":"Point"}
}