{
  "type": "Feature",
  "properties": {
    "iso:country":"DE",
    "sg:address":"Bongardstr. 2",
    "sg:city":"Bochum",
    "sg:phone":"+49 234/15241",
    "sg:postcode":"44787",
    "sg:province":"Nordrhein-Westfalen",
    "wof:name":"Wilhelm Witteler Kg",
    "wof:placetype":"venue"
},
  "geometry": {"coordinates":[7.2162542343,51.4818191528],"type":"Point"}
}