{
  "type": "Feature",
  "properties": {
    "iso:country":"DE",
    "sg:address":"Rheiner Str. 112",
    "sg:city":"Lingen",
    "sg:phone":"+49 4959/1912940",
    "sg:postcode":"49809",
    "sg:province":"Niedersachsen",
    "wof:name":"M\u00d6bel Center Josef Berning Gmbh",
    "wof:placetype":"venue"
},
  "geometry": {"coordinates":[7.3231539726,52.5042953491],"type":"Point"}
}