{
  "type": "Feature",
  "properties": {
    "iso:country":"DE",
    "sg:address":"Arndtstr. 10",
    "sg:city":"Dortmund",
    "sg:phone":"+49 231/7214228",
    "sg:postcode":"44135",
    "sg:province":"Nordrhein-Westfalen",
    "wof:name":"J\u00f6rg Kottsieper Rechtsanwalt",
    "wof:placetype":"venue"
},
  "geometry": {"coordinates":[7.4740929604,51.5127487183],"type":"Point"}
}