{
  "type": "Feature",
  "properties": {
    "iso:country":"DE",
    "sg:address":"Bad Oberdorfer Str. 21",
    "sg:city":"Hindelang",
    "sg:phone":"+49 8324/2825",
    "sg:postcode":"87541",
    "sg:province":"Bayern",
    "wof:name":"C. Tannheimer",
    "wof:placetype":"venue"
},
  "geometry": {"coordinates":[10.377371,47.505238],"type":"Point"}
}