{
  "type": "Feature",
  "properties": {
    "iso:country":"DE",
    "sg:address":"Theodor-Storm-Str. 9",
    "sg:city":"Hanerau-Hademarschen",
    "sg:phone":"+49 4872/96080",
    "sg:postcode":"25557",
    "sg:province":"Schleswig-Holstein",
    "wof:name":"Theodor-storm-apotheke Inh. Rolf Hertlein",
    "wof:placetype":"venue"
},
  "geometry": {"coordinates":[9.416367,54.126228],"type":"Point"}
}