{
  "type": "Feature",
  "properties": {
    "iso:country":"DE",
    "sg:address":"Siemensstr. 36",
    "sg:city":"Schwabm\u00fcnchen",
    "sg:phone":"+49 8232/71229",
    "sg:postcode":"86830",
    "sg:province":"Bayern",
    "wof:name":"Manfred K\u00e4fer",
    "wof:placetype":"venue"
},
  "geometry": {"coordinates":[10.755359,48.167236],"type":"Point"}
}