{
  "type": "Feature",
  "properties": {
    "iso:country":"DE",
    "sg:address":"Beethovenstr. 2",
    "sg:city":"Malsch",
    "sg:phone":"+49 7246/8899",
    "sg:postcode":"76316",
    "sg:province":"Baden-W\u00fcrttemberg",
    "wof:name":"Stephan Daul",
    "wof:placetype":"venue"
},
  "geometry": {"coordinates":[8.3346443176,48.8837471008],"type":"Point"}
}