{
  "type": "Feature",
  "properties": {
    "iso:country":"DE",
    "sg:address":"Gr\u00fcne Str. 9",
    "sg:city":"Zernitz",
    "sg:postcode":"39264",
    "sg:province":"Sachsen-Anhalt",
    "wof:name":"R\u00fchlich Bau Gmbh",
    "wof:placetype":"venue"
},
  "geometry": {"coordinates":[12.086122,52.013962],"type":"Point"}
}