{
  "type": "Feature",
  "properties": {
    "iso:country":"DE",
    "sg:address":"St.-Johanner-Str. 7",
    "sg:city":"Sprendlingen",
    "sg:phone":"+49 6701/960304",
    "sg:postcode":"55576",
    "sg:province":"Rheinland-Pfalz",
    "wof:name":"Beate Biskup",
    "wof:placetype":"venue"
},
  "geometry": {"coordinates":[7.9873790741,49.8602027893],"type":"Point"}
}