{
  "type": "Feature",
  "properties": {
    "iso:country":"DE",
    "sg:address":"Ottmannshofer Str. 10",
    "sg:city":"Leutkirch",
    "sg:phone":"+49 7561/98490",
    "sg:postcode":"88299",
    "sg:province":"Baden-W\u00fcrttemberg",
    "wof:name":"Rosen-apotheke",
    "wof:placetype":"venue"
},
  "geometry": {"coordinates":[10.023658,47.8302],"type":"Point"}
}