{
  "type": "Feature",
  "properties": {
    "iso:country":"DE",
    "sg:address":"K\u00f6nigsberger Str. 10",
    "sg:city":"Frankfurt",
    "sg:phone":"+49 69/979000",
    "sg:postcode":"60487",
    "sg:province":"Hessen",
    "wof:name":"Jenisch Beteiligungs Gmbh",
    "wof:placetype":"venue"
},
  "geometry": {"coordinates":[8.624256134,50.1278572083],"type":"Point"}
}