{
  "type": "Feature",
  "properties": {
    "iso:country":"DE",
    "sg:address":"Dr.-Salvador-Allende-Str. 166",
    "sg:city":"Chemnitz",
    "sg:phone":"+49 371/221986",
    "sg:postcode":"09119",
    "sg:province":"Sachsen",
    "wof:name":"J. Bahr",
    "wof:placetype":"venue"
},
  "geometry": {"coordinates":[12.8871297836,50.8045845032],"type":"Point"}
}