{
  "type": "Feature",
  "properties": {
    "iso:country":"DE",
    "sg:address":"D\u00fcnblick 6",
    "sg:city":"Breitenbach",
    "sg:phone":"+49 3605/56930",
    "sg:postcode":"37327",
    "sg:province":"Th\u00fcringen",
    "wof:name":"Flurf\u00f6rdertechnik Roth",
    "wof:placetype":"venue"
},
  "geometry": {"coordinates":[10.3221521378,51.3876724243],"type":"Point"}
}