{
  "type": "Feature",
  "properties": {
    "iso:country":"DE",
    "sg:address":"August-Bebel-Str. 8",
    "sg:city":"Bautzen",
    "sg:phone":"+49 3591/497811",
    "sg:postcode":"02625",
    "sg:province":"Sachsen",
    "wof:name":"Strau\u00df Und Bolz Rechtsanw\u00e4lte",
    "wof:placetype":"venue"
},
  "geometry": {"coordinates":[14.4305973053,51.1762771606],"type":"Point"}
}