{
  "type": "Feature",
  "properties": {
    "iso:country":"DE",
    "sg:address":"Augsburger Str. 53",
    "sg:city":"N\u00f6rdlingen",
    "sg:phone":"+49 9081/21980",
    "sg:postcode":"86720",
    "sg:province":"Bayern",
    "wof:name":"Carl Heuchel Bauunternehmen Baustoffgro\u00dfhandel In",
    "wof:placetype":"venue"
},
  "geometry": {"coordinates":[10.5014619827,48.844959259],"type":"Point"}
}