{
  "type": "Feature",
  "properties": {
    "iso:country":"DE",
    "sg:address":"Schl\u00f6\u00dflesstr. 10",
    "sg:city":"Remseck",
    "sg:phone":"+49 7146/97195",
    "sg:postcode":"71686",
    "sg:province":"Baden-W\u00fcrttemberg",
    "wof:name":"Tagespflege Der Diakoniestation Remseck",
    "wof:placetype":"venue"
},
  "geometry": {"coordinates":[9.253892,48.866531],"type":"Point"}
}