{
  "type": "Feature",
  "properties": {
    "iso:country":"DE",
    "sg:address":"Hauptstr. 4/1",
    "sg:city":"Obermarchtal",
    "sg:phone":"+49 7375",
    "sg:postcode":"89611",
    "sg:province":"Baden-W\u00fcrttemberg",
    "wof:name":"Hubitron Steuerungstechnik",
    "wof:placetype":"venue"
},
  "geometry": {"coordinates":[9.5699644089,48.235004425],"type":"Point"}
}