{
  "type": "Feature",
  "properties": {
    "iso:country":"DE",
    "sg:address":"Claus-Jesup-Str. 13",
    "sg:city":"Wismar",
    "sg:phone":"+49 3841/40949",
    "sg:postcode":"23966",
    "sg:province":"Mecklenburg-Vorpommern",
    "wof:name":"Ralf Evers Steuerberatungs Gmbh",
    "wof:placetype":"venue"
},
  "geometry": {"coordinates":[11.4593954086,53.8920173645],"type":"Point"}
}