{
  "type": "Feature",
  "properties": {
    "iso:country":"DE",
    "sg:address":"Oleftalstr. 13",
    "sg:city":"Hellenthal",
    "sg:phone":"+49 2482/7151",
    "sg:postcode":"53940",
    "sg:province":"Nordrhein-Westfalen",
    "wof:name":"G\u00e4stehaus F. Hermanns",
    "wof:placetype":"venue"
},
  "geometry": {"coordinates":[6.4331440926,50.4925270081],"type":"Point"}
}