{
  "type": "Feature",
  "properties": {
    "iso:country":"DE",
    "sg:address":"Maxstr. 4-6",
    "sg:city":"Aachen",
    "sg:phone":"+49 241/9019545",
    "sg:postcode":"52070",
    "sg:province":"Nordrhein-Westfalen",
    "wof:name":"Corazzu Leder",
    "wof:placetype":"venue"
},
  "geometry": {"coordinates":[6.095625,50.776649],"type":"Point"}
}