{
  "type": "Feature",
  "properties": {
    "iso:country":"DE",
    "sg:address":"Hauptstr. 21",
    "sg:city":"Offenburg",
    "sg:phone":"+49 781/78850",
    "sg:postcode":"77652",
    "sg:province":"Baden-W\u00fcrttemberg",
    "wof:name":"Dickson-constant Gmbh",
    "wof:placetype":"venue"
},
  "geometry": {"coordinates":[7.9438028336,48.4728546143],"type":"Point"}
}