{
  "type": "Feature",
  "properties": {
    "iso:country":"DE",
    "sg:address":"Beckumer Str. 5",
    "sg:city":"Stadland",
    "sg:phone":"+49 4732/702",
    "sg:postcode":"26935",
    "sg:province":"Niedersachsen",
    "wof:name":"G. Stoll",
    "wof:placetype":"venue"
},
  "geometry": {"coordinates":[8.4266834259,53.4291267395],"type":"Point"}
}