{
  "type": "Feature",
  "properties": {
    "iso:country":"DE",
    "sg:address":"Stolzestr. 15",
    "sg:city":"Dortmund",
    "sg:phone":"+49 4923/1125081",
    "sg:postcode":"44139",
    "sg:province":"Nordrhein-Westfalen",
    "wof:name":"Neuwieder Couvertfabrik Gmbh",
    "wof:placetype":"venue"
},
  "geometry": {"coordinates":[7.4612941742,51.5056381226],"type":"Point"}
}