{
  "type": "Feature",
  "properties": {
    "iso:country":"DE",
    "sg:address":"Wichernweg 20",
    "sg:city":"M\u00fcnchen",
    "sg:phone":"+49 89/6378999",
    "sg:postcode":"81737",
    "sg:province":"Bayern",
    "wof:name":"Hans-peter Kraft",
    "wof:placetype":"venue"
},
  "geometry": {"coordinates":[11.635216713,48.0936317444],"type":"Point"}
}