{
  "type": "Feature",
  "properties": {
    "iso:country":"DE",
    "sg:address":"Alte Ricklinger Str. 20 A",
    "sg:city":"Garbsen",
    "sg:phone":"+49 5137/71776",
    "sg:postcode":"30823",
    "sg:province":"Niedersachsen",
    "wof:name":"Friedrich Gerland",
    "wof:placetype":"venue"
},
  "geometry": {"coordinates":[9.5812854767,52.4176940918],"type":"Point"}
}