{
  "type": "Feature",
  "properties": {
    "iso:country":"DE",
    "sg:address":"Kirchstr. 2",
    "sg:city":"Freihung",
    "sg:phone":"+49 9646/279",
    "sg:postcode":"92271",
    "sg:province":"Bayern",
    "wof:name":"M. Krau\u00df",
    "wof:placetype":"venue"
},
  "geometry": {"coordinates":[11.9124803543,49.620300293],"type":"Point"}
}