{
  "type": "Feature",
  "properties": {
    "iso:country":"DE",
    "sg:address":"Zeppelinstr. 16",
    "sg:city":"Bad Schussenried",
    "sg:phone":"+49 7583/587",
    "sg:postcode":"88427",
    "sg:province":"Baden-W\u00fcrttemberg",
    "wof:name":"Mvz-maschinenbau Und Verzahnungstechnik",
    "wof:placetype":"venue"
},
  "geometry": {"coordinates":[9.65383,48.010101],"type":"Point"}
}