{
  "type": "Feature",
  "properties": {
    "iso:country":"DE",
    "sg:address":"Nikolaus-Bahles-Str. 13",
    "sg:city":"Bad Neuenahr-Ahrweiler",
    "sg:phone":"+49 2641/25067",
    "sg:postcode":"53474",
    "sg:province":"Rheinland-Pfalz",
    "wof:name":"Delphi",
    "wof:placetype":"venue"
},
  "geometry": {"coordinates":[7.1843500137,50.5450057983],"type":"Point"}
}