{
  "type": "Feature",
  "properties": {
    "iso:country":"DE",
    "sg:address":"Kapellenstr. 8 a",
    "sg:city":"Walluf",
    "sg:phone":"+49 6123/73301",
    "sg:postcode":"65396",
    "sg:province":"Hessen",
    "wof:name":"Helmut Veit",
    "wof:placetype":"venue"
},
  "geometry": {"coordinates":[8.156807,50.037449],"type":"Point"}
}