{
  "type": "Feature",
  "properties": {
    "iso:country":"DE",
    "sg:address":"Ostring 36",
    "sg:city":"Ludwigshafen",
    "sg:phone":"+49 621/652287",
    "sg:postcode":"67069",
    "sg:province":"Rheinland-Pfalz",
    "wof:name":"Erich Arnold",
    "wof:placetype":"venue"
},
  "geometry": {"coordinates":[8.405794,49.52354],"type":"Point"}
}