{
  "type": "Feature",
  "properties": {
    "iso:country":"DE",
    "sg:address":"Goethestr. 5",
    "sg:city":"Aue",
    "sg:phone":"+49 3771/22858",
    "sg:postcode":"08280",
    "sg:province":"Sachsen",
    "wof:name":"Pils Pub Sir Henry",
    "wof:placetype":"venue"
},
  "geometry": {"coordinates":[12.6981582642,50.5875358582],"type":"Point"}
}