{
  "type": "Feature",
  "properties": {
    "iso:country":"DE",
    "sg:address":"Auestr.",
    "sg:city":"Kelbra",
    "sg:phone":"+49 34651/6310",
    "sg:postcode":"06537",
    "sg:province":"Sachsen-Anhalt",
    "wof:name":"Camping Kelbra",
    "wof:placetype":"venue"
},
  "geometry": {"coordinates":[11.037145,51.43293],"type":"Point"}
}