{
  "type": "Feature",
  "properties": {
    "iso:country":"DE",
    "sg:address":"Bahnhofplatz 5",
    "sg:city":"W\u00fcrzburg",
    "sg:phone":"+49 931/12060",
    "sg:postcode":"97070",
    "sg:province":"Bayern",
    "wof:name":"Europcar Autovermietung Gmbh",
    "wof:placetype":"venue"
},
  "geometry": {"coordinates":[9.93511,49.7985],"type":"Point"}
}