{
  "type": "Feature",
  "properties": {
    "iso:country":"DE",
    "sg:address":"Jasmunder Str. 9",
    "sg:city":"Berlin",
    "sg:phone":"+49 30/4634035",
    "sg:postcode":"13355",
    "sg:province":"Berlin",
    "wof:name":"Edelgard Schneider Steuerberaterin",
    "wof:placetype":"venue"
},
  "geometry": {"coordinates":[13.387597084,52.5404853821],"type":"Point"}
}