{
  "type": "Feature",
  "properties": {
    "iso:country":"DE",
    "sg:address":"Schulstr. 10",
    "sg:city":"Goldberg",
    "sg:phone":"+49 38736/40881",
    "sg:postcode":"19399",
    "sg:province":"Mecklenburg-Vorpommern",
    "wof:name":"Putz- Und Mauerwerksbau Gmbh",
    "wof:placetype":"venue"
},
  "geometry": {"coordinates":[12.092788,53.589897],"type":"Point"}
}