{
  "type": "Feature",
  "properties": {
    "iso:country":"DE",
    "sg:address":"Uhlandstr. 33",
    "sg:city":"Reutlingen",
    "sg:phone":"+49 4971/2147746",
    "sg:postcode":"72764",
    "sg:province":"Baden-W\u00fcrttemberg",
    "wof:name":"Kimmerle Filtertechnik Gmbh",
    "wof:placetype":"venue"
},
  "geometry": {"coordinates":[9.223997,48.488667],"type":"Point"}
}