{
  "type": "Feature",
  "properties": {
    "iso:country":"DE",
    "sg:address":"Herrenweg 6",
    "sg:city":"Dabel",
    "sg:phone":"+49 38485/20281",
    "sg:postcode":"19406",
    "sg:province":"Mecklenburg-Vorpommern",
    "wof:name":"N. Aulich",
    "wof:placetype":"venue"
},
  "geometry": {"coordinates":[11.8955564499,53.6570854187],"type":"Point"}
}