{
  "type": "Feature",
  "properties": {
    "iso:country":"DE",
    "sg:address":"Adlerstr. 41",
    "sg:city":"Stuttgart",
    "sg:postcode":"70199",
    "sg:province":"Baden-W\u00fcrttemberg",
    "wof:name":"Secutrada :: Tresore Sicherheit Accessoires",
    "wof:placetype":"venue"
},
  "geometry": {"coordinates":[9.162445,48.764355],"type":"Point"}
}