{
  "type": "Feature",
  "properties": {
    "iso:country":"DE",
    "sg:address":"Hagenstr. 30",
    "sg:city":"Bensheim",
    "sg:phone":"+49 6251/69445",
    "sg:postcode":"64625",
    "sg:province":"Hessen",
    "wof:name":"Josef M\u00fcller Innenarchitekt",
    "wof:placetype":"venue"
},
  "geometry": {"coordinates":[8.608242,49.679306],"type":"Point"}
}