{
  "type": "Feature",
  "properties": {
    "iso:country":"DE",
    "sg:city":"Bad Salzungen",
    "sg:phone":"+49 3695/623729",
    "sg:postcode":"36433",
    "sg:province":"Th\u00fcringen",
    "wof:name":"A. Hort",
    "wof:placetype":"venue"
},
  "geometry": {"coordinates":[10.231955,50.811886],"type":"Point"}
}