{
  "type": "Feature",
  "properties": {
    "iso:country":"DE",
    "sg:address":"Zur F\u00fcnte 2",
    "sg:city":"Melle",
    "sg:phone":"+49 5429/94440",
    "sg:postcode":"49326",
    "sg:province":"Niedersachsen",
    "wof:name":"Seling Ohg",
    "wof:placetype":"venue"
},
  "geometry": {"coordinates":[8.2752780914,52.1632652283],"type":"Point"}
}