{
  "type": "Feature",
  "properties": {
    "iso:country":"DE",
    "sg:address":"Friedrichstr. 140",
    "sg:city":"Velbert",
    "sg:phone":"+49 2051/52520",
    "sg:postcode":"42551",
    "sg:province":"Nordrhein-Westfalen",
    "wof:name":"A. Fischer",
    "wof:placetype":"venue"
},
  "geometry": {"coordinates":[7.0428099632,51.3412208557],"type":"Point"}
}