{
  "type": "Feature",
  "properties": {
    "iso:country":"DE",
    "sg:address":"Kirchstr. 9",
    "sg:city":"Schlo\u00df Holte-Stukenbrok",
    "sg:phone":"+49 5207/88333",
    "sg:postcode":"33758",
    "sg:province":"Nordrhein-Westfalen",
    "wof:name":"Andrea-moden Inh. Greinus",
    "wof:placetype":"venue"
},
  "geometry": {"coordinates":[-82.80056,27.965599],"type":"Point"}
}