{
  "type": "Feature",
  "properties": {
    "iso:country":"DE",
    "sg:address":"Kampstr. 10",
    "sg:city":"Enger",
    "sg:phone":"+49 5224/979555",
    "sg:postcode":"32130",
    "sg:province":"Nordrhein-Westfalen",
    "wof:name":"August Landwehrmann",
    "wof:placetype":"venue"
},
  "geometry": {"coordinates":[8.561284,52.136852],"type":"Point"}
}