{
  "type": "Feature",
  "properties": {
    "iso:country":"DE",
    "sg:address":"Steinhauser Str. 7",
    "sg:city":"Geseke",
    "sg:phone":"+49 2954/924202",
    "sg:postcode":"59590",
    "sg:province":"Nordrhein-Westfalen",
    "wof:name":"Ewald Dickhut Baugesellschaft Mbh",
    "wof:placetype":"venue"
},
  "geometry": {"coordinates":[8.4791288376,51.5873794556],"type":"Point"}
}