{
  "type": "Feature",
  "properties": {
    "iso:country":"DE",
    "sg:address":"Germanusstr 4",
    "sg:city":"Aachen",
    "sg:phone":"+49 241/16960",
    "sg:postcode":"52080",
    "sg:province":"Nordrhein-Westfalen",
    "wof:name":"Utimaco Safeware Ag",
    "wof:placetype":"venue"
},
  "geometry": {"coordinates":[6.124484,50.794834],"type":"Point"}
}