{
  "type": "Feature",
  "properties": {
    "iso:country":"DE",
    "sg:address":"Bahnhofstr. 4",
    "sg:city":"Ebersberg",
    "sg:phone":"+49 8092/22071",
    "sg:postcode":"85560",
    "sg:province":"Bayern",
    "wof:name":"Zimmermann Und Kollegen Rechtsanw\u00e4lte",
    "wof:placetype":"venue"
},
  "geometry": {"coordinates":[11.9706268311,48.0773582458],"type":"Point"}
}