{
  "type": "Feature",
  "properties": {
    "iso:country":"DE",
    "sg:address":"Liebigstr. 20",
    "sg:city":"Dresden",
    "sg:phone":"+49 351/4719333",
    "sg:postcode":"01187",
    "sg:province":"Sachsen",
    "wof:name":"Eisenwaren",
    "wof:placetype":"venue"
},
  "geometry": {"coordinates":[13.722188,51.033302],"type":"Point"}
}