{
  "type": "Feature",
  "properties": {
    "iso:country":"DE",
    "sg:address":"Tumblingerstr. 12",
    "sg:city":"M\u00fcnchen",
    "sg:phone":"+49 89/534663",
    "sg:postcode":"80337",
    "sg:province":"Bayern",
    "wof:name":"Gerhard Hohendanner Gmbh",
    "wof:placetype":"venue"
},
  "geometry": {"coordinates":[11.560443,48.127605],"type":"Point"}
}