{
  "type": "Feature",
  "properties": {
    "iso:country":"DE",
    "sg:address":"kon 12",
    "sg:city":"hamelnnn",
    "sg:phone":"+49 2351/54477",
    "sg:postcode":"55448",
    "wof:name":"Fg-webdesign Deutschland-hamm/westf.",
    "wof:placetype":"venue"
},
  "geometry": {"coordinates":[-93.280647,45.170341],"type":"Point"}
}