{
  "type": "Feature",
  "properties": {
    "iso:country":"DE",
    "sg:address":"Bahnhofstr. 22 a",
    "sg:city":"Zittau",
    "sg:phone":"+49 3583/708549",
    "sg:postcode":"02763",
    "sg:province":"Sachsen",
    "wof:name":"Axel Gaul Immobilienmakler",
    "wof:placetype":"venue"
},
  "geometry": {"coordinates":[14.8058996201,50.9013710022],"type":"Point"}
}