{
  "type": "Feature",
  "properties": {
    "iso:country":"DE",
    "sg:address":"Homburger Landstr. 241",
    "sg:city":"Frankfurt",
    "sg:phone":"+49 69/543671",
    "sg:postcode":"60435",
    "sg:province":"Hessen",
    "wof:name":"Berthold Emmerich",
    "wof:placetype":"venue"
},
  "geometry": {"coordinates":[8.689604,50.157681],"type":"Point"}
}