{
  "type": "Feature",
  "properties": {
    "iso:country":"DE",
    "sg:address":"Wulfsbrook 15",
    "sg:city":"Kiel",
    "sg:phone":"+49 431/684810",
    "sg:postcode":"24113",
    "sg:province":"Schleswig-Holstein",
    "wof:name":"S. Brandenburg Steuerberater",
    "wof:placetype":"venue"
},
  "geometry": {"coordinates":[10.1086616516,54.3042907715],"type":"Point"}
}