{
  "type": "Feature",
  "properties": {
    "iso:country":"DE",
    "sg:address":"Hauptstr. 41",
    "sg:city":"Dettenheim",
    "sg:phone":"+49 7247/6282",
    "sg:postcode":"76706",
    "sg:province":"Baden-W\u00fcrttemberg",
    "wof:name":"Heinrich Seitz",
    "wof:placetype":"venue"
},
  "geometry": {"coordinates":[8.415892601,49.1611175537],"type":"Point"}
}