{
  "type": "Feature",
  "properties": {
    "iso:country":"DE",
    "sg:address":"N\u00f6rdlinger Str. 25",
    "sg:city":"D\u00fcsseldorf",
    "sg:phone":"+49 211/715098",
    "sg:postcode":"40597",
    "sg:province":"Nordrhein-Westfalen",
    "wof:name":"Mani Gmbh Chemische Produkte",
    "wof:placetype":"venue"
},
  "geometry": {"coordinates":[6.863193,51.165806],"type":"Point"}
}