{
  "type": "Feature",
  "properties": {
    "iso:country":"DE",
    "sg:address":"Schlo\u00dfstra\u00dfe 40",
    "sg:city":"Neuwied",
    "sg:phone":"+49 2631",
    "sg:postcode":"56564",
    "sg:province":"Rheinland-Pfalz",
    "wof:name":"Hotel Drei Schweizer",
    "wof:placetype":"venue"
},
  "geometry": {"coordinates":[7.458851,50.429646],"type":"Point"}
}