{
  "type": "Feature",
  "properties": {
    "iso:country":"DE",
    "sg:address":"G\u00e4nsheidestr. 82",
    "sg:city":"Stuttgart",
    "sg:phone":"+49 711/233068",
    "sg:postcode":"70186",
    "sg:province":"Baden-W\u00fcrttemberg",
    "wof:name":"Peter Walser Architekt Und Ingenieur",
    "wof:placetype":"venue"
},
  "geometry": {"coordinates":[9.195626,48.768234],"type":"Point"}
}