{
  "type": "Feature",
  "properties": {
    "iso:country":"DE",
    "sg:address":"Am Baldhof",
    "sg:city":"Neuss",
    "sg:phone":"+49 2131/859001",
    "sg:postcode":"41464",
    "sg:province":"Nordrhein-Westfalen",
    "wof:name":"Parkett Laminat",
    "wof:placetype":"venue"
},
  "geometry": {"coordinates":[6.686709,51.180023],"type":"Point"}
}