{
  "type": "Feature",
  "properties": {
    "iso:country":"DE",
    "sg:address":"Schwerter Str. 229",
    "sg:city":"Hagen",
    "sg:phone":"+49 2331/61893",
    "sg:postcode":"58099",
    "sg:province":"Nordrhein-Westfalen",
    "wof:name":"H. Hasenberg",
    "wof:placetype":"venue"
},
  "geometry": {"coordinates":[7.4799480438,51.402507782],"type":"Point"}
}