{
  "type": "Feature",
  "properties": {
    "iso:country":"DE",
    "sg:address":"Roter Rain 3",
    "sg:city":"Sontra",
    "sg:phone":"+49 5653/619",
    "sg:postcode":"36205",
    "sg:province":"Hessen",
    "wof:name":"Erich Schwarze Kg",
    "wof:placetype":"venue"
},
  "geometry": {"coordinates":[9.948894,51.066814],"type":"Point"}
}