{
  "type": "Feature",
  "properties": {
    "iso:country":"DE",
    "sg:address":"Lindenstr. 45",
    "sg:city":"Parchim",
    "sg:phone":"+49 3871/267307",
    "sg:postcode":"19370",
    "sg:province":"Mecklenburg-Vorpommern",
    "wof:name":"Klaus-dieter Hildebrandt",
    "wof:placetype":"venue"
},
  "geometry": {"coordinates":[11.8494710922,53.4280090332],"type":"Point"}
}