{
  "type": "Feature",
  "properties": {
    "iso:country":"DE",
    "sg:address":"Graf-Siegfried-Str. 5",
    "sg:city":"Saarburg",
    "sg:phone":"+49 6581/3586",
    "sg:postcode":"54439",
    "sg:province":"Rheinland-Pfalz",
    "wof:name":"Harald M\u00fcller",
    "wof:placetype":"venue"
},
  "geometry": {"coordinates":[6.552582,49.609528],"type":"Point"}
}