{
  "type": "Feature",
  "properties": {
    "iso:country":"DE",
    "sg:address":"M\u00fcnstersche Str. 76",
    "sg:city":"Bad Rothenfelde",
    "sg:phone":"+49 5424/1566",
    "sg:postcode":"49214",
    "sg:province":"Niedersachsen",
    "wof:name":"Wilhelm Timpe",
    "wof:placetype":"venue"
},
  "geometry": {"coordinates":[8.1450653076,52.1053962708],"type":"Point"}
}