{
  "type": "Feature",
  "properties": {
    "iso:country":"DE",
    "sg:address":"Hertastr. 27",
    "sg:city":"Berlin",
    "sg:phone":"+49 30/6253905",
    "sg:postcode":"12051",
    "sg:province":"Berlin",
    "wof:name":"Renate Bluhm",
    "wof:placetype":"venue"
},
  "geometry": {"coordinates":[13.435733,52.46674],"type":"Point"}
}