{
  "type": "Feature",
  "properties": {
    "iso:country":"DE",
    "sg:address":"Mahrholzberg 17",
    "sg:city":"Ilsenburg",
    "sg:phone":"+49 39452/2625",
    "sg:postcode":"38871",
    "sg:province":"Sachsen-Anhalt",
    "wof:name":"Hans-georg Fischer",
    "wof:placetype":"venue"
},
  "geometry": {"coordinates":[10.6748104095,51.8695678711],"type":"Point"}
}