{
  "type": "Feature",
  "properties": {
    "iso:country":"DE",
    "sg:address":"Leppestr. 191",
    "sg:city":"Marienheide",
    "sg:postcode":"51709",
    "sg:province":"Nordrhein-Westfalen",
    "wof:name":"W. Und W. Klein Gmbh",
    "wof:placetype":"venue"
},
  "geometry": {"coordinates":[7.50554,51.054703],"type":"Point"}
}