{
  "type": "Feature",
  "properties": {
    "iso:country":"DE",
    "sg:address":"Rosenallee 4",
    "sg:city":"Mihla",
    "sg:phone":"+49 36924/3620",
    "sg:postcode":"99826",
    "sg:province":"Th\u00fcringen",
    "wof:name":"Atp Alltape Klebetechnik Gmbh",
    "wof:placetype":"venue"
},
  "geometry": {"coordinates":[10.3322610855,51.0741958618],"type":"Point"}
}