{
  "type": "Feature",
  "properties": {
    "iso:country":"DE",
    "sg:address":"Kahden 17c",
    "sg:city":"Hamburg",
    "sg:postcode":"22393",
    "sg:province":"Hamburg",
    "wof:name":"Mse Micro Sensoric Electronic Gmbh",
    "wof:placetype":"venue"
},
  "geometry": {"coordinates":[10.12697,53.64999],"type":"Point"}
}