{
  "type": "Feature",
  "properties": {
    "iso:country":"DE",
    "sg:address":"Mohn\u00e4ckerstr. 2",
    "sg:city":"Mannheim",
    "sg:phone":"+49 621/793833",
    "sg:postcode":"68259",
    "sg:province":"Baden-W\u00fcrttemberg",
    "wof:name":"Hans Martin",
    "wof:placetype":"venue"
},
  "geometry": {"coordinates":[8.5471153259,49.4896583557],"type":"Point"}
}