{
  "type": "Feature",
  "properties": {
    "iso:country":"DE",
    "sg:address":"Matterstockstr. 26",
    "sg:city":"W\u00fcrzburg",
    "sg:phone":"+49 931/26844",
    "sg:postcode":"97080",
    "sg:province":"Bayern",
    "wof:name":"Lbt Luftbefeuchtungs- Technik Gmbh",
    "wof:placetype":"venue"
},
  "geometry": {"coordinates":[9.9464473724,49.8024673462],"type":"Point"}
}