{
  "type": "Feature",
  "properties": {
    "iso:country":"DE",
    "sg:address":"Schulgasse 13",
    "sg:city":"Rochlitz",
    "sg:phone":"+49 3737/41862",
    "sg:postcode":"09306",
    "sg:province":"Sachsen",
    "wof:name":"Antje Uhlig",
    "wof:placetype":"venue"
},
  "geometry": {"coordinates":[12.8032550812,51.0464439392],"type":"Point"}
}