{
  "type": "Feature",
  "properties": {
    "iso:country":"DE",
    "sg:address":"Nordhorner Str. 18",
    "sg:city":"Lingen",
    "sg:phone":"+49 591/3514",
    "sg:postcode":"49808",
    "sg:province":"Niedersachsen",
    "wof:name":"Hubertushof Neerschulte Gmbh",
    "wof:placetype":"venue"
},
  "geometry": {"coordinates":[7.2958030701,52.5094146729],"type":"Point"}
}