{
  "type": "Feature",
  "properties": {
    "iso:country":"DE",
    "sg:address":"Im Carree 1",
    "sg:city":"Darmstadt",
    "sg:postcode":"64283",
    "sg:province":"Hessen",
    "wof:name":"Grundst\u00fccksgesellschaft Wilhelminenstr. 25",
    "wof:placetype":"venue"
},
  "geometry": {"coordinates":[8.65194,49.871975],"type":"Point"}
}