{
  "type": "Feature",
  "properties": {
    "iso:country":"DE",
    "sg:address":"Johann-Stelling-Str. 9",
    "sg:city":"Gadebusch",
    "sg:phone":"+49 3886/2389",
    "sg:postcode":"19205",
    "sg:province":"Mecklenburg-Vorpommern",
    "wof:name":"Friedrich Wendland",
    "wof:placetype":"venue"
},
  "geometry": {"coordinates":[11.1124486923,53.7008857727],"type":"Point"}
}