{
  "type": "Feature",
  "properties": {
    "iso:country":"DE",
    "sg:address":"Dorfstr. 4",
    "sg:city":"Salzwedel",
    "sg:phone":"+49 3901/80105",
    "sg:postcode":"29410",
    "sg:province":"Sachsen-Anhalt",
    "wof:name":"Rainer Kreft",
    "wof:placetype":"venue"
},
  "geometry": {"coordinates":[11.165309,52.802475],"type":"Point"}
}