{
  "type": "Feature",
  "properties": {
    "iso:country":"DE",
    "sg:address":"Riedlenstr. 18/2",
    "sg:city":"Ulm",
    "sg:phone":"+49 7305/24308",
    "sg:postcode":"89079",
    "sg:province":"Baden-W\u00fcrttemberg",
    "wof:name":"Pizza-express Bella Italia",
    "wof:placetype":"venue"
},
  "geometry": {"coordinates":[9.9387197495,48.3316497803],"type":"Point"}
}