{
  "type": "Feature",
  "properties": {
    "iso:country":"DE",
    "sg:address":"Schulstr. 6",
    "sg:city":"Oebisfelde",
    "sg:phone":"+49 39002/42038",
    "sg:postcode":"39646",
    "sg:province":"Sachsen-Anhalt",
    "wof:name":"Gasthaus An Der Aller",
    "wof:placetype":"venue"
},
  "geometry": {"coordinates":[10.9873523712,52.4303703308],"type":"Point"}
}