{
  "type": "Feature",
  "properties": {
    "iso:country":"DE",
    "sg:address":"Derichsweilerstr. 25",
    "sg:city":"D\u00fcren",
    "sg:phone":"+49 2421/64495",
    "sg:postcode":"52355",
    "sg:province":"Nordrhein-Westfalen",
    "wof:name":"P. P. Esser",
    "wof:placetype":"venue"
},
  "geometry": {"coordinates":[6.443339,50.794914],"type":"Point"}
}