{
  "type": "Feature",
  "properties": {
    "iso:country":"DE",
    "sg:address":"Jean-Paul-Str. 1",
    "sg:city":"Wunsiedel",
    "sg:phone":"+49 9232/4081",
    "sg:postcode":"95632",
    "sg:province":"Bayern",
    "wof:name":"Hotel Wunsiedler Hof Inh. Heinz Drenske",
    "wof:placetype":"venue"
},
  "geometry": {"coordinates":[12.0051794052,50.0388183594],"type":"Point"}
}