{
  "type": "Feature",
  "properties": {
    "iso:country":"DE",
    "sg:city":"Reischach",
    "sg:phone":"+49 8670/776",
    "sg:postcode":"84571",
    "sg:province":"Bayern",
    "wof:name":"Anton Langreiter",
    "wof:placetype":"venue"
},
  "geometry": {"coordinates":[12.725615,48.291389],"type":"Point"}
}