{
  "type": "Feature",
  "properties": {
    "iso:country":"DE",
    "sg:address":"Kirscheng\u00e4rtlesweg 7",
    "sg:city":"Eningen",
    "sg:phone":"+49 7121/81570",
    "sg:postcode":"72800",
    "sg:province":"Baden-W\u00fcrttemberg",
    "wof:name":"Ursula Zengerer Hebamme",
    "wof:placetype":"venue"
},
  "geometry": {"coordinates":[9.256792,48.487125],"type":"Point"}
}