{
  "type": "Feature",
  "properties": {
    "iso:country":"DE",
    "sg:address":"Lucile-Grahn-Str. 48",
    "sg:city":"M\u00fcnchen",
    "sg:phone":"+49 89/45758980",
    "sg:postcode":"81675",
    "sg:province":"Bayern",
    "wof:name":"Dr. Wolfgang Dorn-zachertz Rechtsanwalt",
    "wof:placetype":"venue"
},
  "geometry": {"coordinates":[11.6067447662,48.1385574341],"type":"Point"}
}