{
  "type": "Feature",
  "properties": {
    "iso:country":"DE",
    "sg:address":"Schulstr. 12",
    "sg:city":"Seffern",
    "sg:phone":"+49 6569/963130",
    "sg:postcode":"54636",
    "sg:province":"Rheinland-Pfalz",
    "wof:name":"P. Mulbach Gmbh",
    "wof:placetype":"venue"
},
  "geometry": {"coordinates":[6.5031919479,50.0678749084],"type":"Point"}
}