{
  "type": "Feature",
  "properties": {
    "iso:country":"DE",
    "sg:address":"Hauptstr. 26",
    "sg:city":"Tho\u00dffell",
    "sg:phone":"+49 3741/413263",
    "sg:postcode":"08541",
    "sg:province":"Sachsen",
    "wof:name":"W. Blei",
    "wof:placetype":"venue"
},
  "geometry": {"coordinates":[12.247633934,50.5252342224],"type":"Point"}
}