{
  "type": "Feature",
  "properties": {
    "iso:country":"DE",
    "sg:address":"Heilwigstr. 37",
    "sg:city":"Hamburg",
    "sg:phone":"+49 40/473295",
    "sg:postcode":"20249",
    "sg:province":"Hamburg",
    "wof:name":"Peter Dresel Architekt",
    "wof:placetype":"venue"
},
  "geometry": {"coordinates":[9.993581,53.584263],"type":"Point"}
}