{
  "type": "Feature",
  "properties": {
    "iso:country":"DE",
    "sg:address":"Neuer Weg 1",
    "sg:city":"Norden",
    "sg:phone":"+49 4931/2010",
    "sg:postcode":"26506",
    "sg:province":"Niedersachsen",
    "wof:name":"Tee-handels-haus Norden Inh. F. Von R\u00f6ssler-groth E.k.",
    "wof:placetype":"venue"
},
  "geometry": {"coordinates":[7.208468914,53.5961647034],"type":"Point"}
}