{
  "type": "Feature",
  "properties": {
    "iso:country":"DE",
    "sg:address":"Dorfstr. 28a",
    "sg:city":"Kevelaer",
    "sg:phone":"+49 2832/8246",
    "sg:postcode":"47624",
    "sg:province":"Nordrhein-Westfalen",
    "wof:name":"Kath. \u00f6ffentliche Bibliothek St. Quirinus",
    "wof:placetype":"venue"
},
  "geometry": {"coordinates":[6.212775,51.553711],"type":"Point"}
}