{
  "type": "Feature",
  "properties": {
    "iso:country":"DE",
    "sg:address":"Dorfstr. 14",
    "sg:city":"Aubstadt",
    "sg:phone":"+49 9761/2754",
    "sg:postcode":"97633",
    "sg:province":"Bayern",
    "wof:name":"Hilmar Damm",
    "wof:placetype":"venue"
},
  "geometry": {"coordinates":[10.433722,50.333321],"type":"Point"}
}