{
  "type": "Feature",
  "properties": {
    "iso:country":"DE",
    "sg:address":"Erzgang 2",
    "sg:city":"Neubrandenburg",
    "sg:phone":"+49 395/7792856",
    "sg:postcode":"17036",
    "sg:province":"Mecklenburg-Vorpommern",
    "wof:name":"E. Strege",
    "wof:placetype":"venue"
},
  "geometry": {"coordinates":[13.30834,53.550308],"type":"Point"}
}