{
  "type": "Feature",
  "properties": {
    "iso:country":"DE",
    "sg:address":"Bahnhofstr. 10",
    "sg:city":"Lich",
    "sg:phone":"+49 6404/7480",
    "sg:postcode":"35423",
    "sg:province":"Hessen",
    "wof:name":"Dietmar Andres Kg",
    "wof:placetype":"venue"
},
  "geometry": {"coordinates":[8.8224849701,50.5150299072],"type":"Point"}
}