{
  "type": "Feature",
  "properties": {
    "iso:country":"DE",
    "sg:address":"Marktstr. 40",
    "sg:city":"Bielefeld",
    "sg:phone":"+49 521/175260",
    "sg:postcode":"33602",
    "sg:province":"Nordrhein-Westfalen",
    "wof:name":"S. Dieckerhoff Und G. Schoon",
    "wof:placetype":"venue"
},
  "geometry": {"coordinates":[8.5386352539,52.0187683105],"type":"Point"}
}