{
  "type": "Feature",
  "properties": {
    "iso:country":"DE",
    "sg:address":"Hans-Z\u00f6ller-Str. 93",
    "sg:city":"Mainz",
    "sg:phone":"+49 6131/881755",
    "sg:postcode":"55130",
    "sg:province":"Rheinland-Pfalz",
    "wof:name":"Elektro Service Schirmacher Gmbh",
    "wof:placetype":"venue"
},
  "geometry": {"coordinates":[8.3097391129,49.9546394348],"type":"Point"}
}