{
  "type": "Feature",
  "properties": {
    "iso:country":"DE",
    "sg:address":"Feudenheimer Str. 4",
    "sg:city":"Heidelberg",
    "sg:phone":"+49 6221/831189",
    "sg:postcode":"69123",
    "sg:province":"Baden-W\u00fcrttemberg",
    "wof:name":"Peter Schindler",
    "wof:placetype":"venue"
},
  "geometry": {"coordinates":[8.6440925598,49.427482605],"type":"Point"}
}