{
  "type": "Feature",
  "properties": {
    "iso:country":"DE",
    "sg:address":"Uferstr. 1",
    "sg:city":"F\u00fcssen",
    "sg:phone":"+49 8362/6540",
    "sg:postcode":"87629",
    "sg:province":"Bayern",
    "wof:name":"Freibad Am Hopfensee",
    "wof:placetype":"venue"
},
  "geometry": {"coordinates":[10.6836824417,47.6035041809],"type":"Point"}
}