{
  "type": "Feature",
  "properties": {
    "iso:country":"DE",
    "sg:address":"Hintergasse 2",
    "sg:city":"Gr\u00fcnstadt",
    "sg:phone":"+49 6359/810925",
    "sg:postcode":"67269",
    "sg:province":"Rheinland-Pfalz",
    "wof:name":"Restaurant Am Bienenbrunnen",
    "wof:placetype":"venue"
},
  "geometry": {"coordinates":[8.156785965,49.5476112366],"type":"Point"}
}