{
  "type": "Feature",
  "properties": {
    "iso:country":"DE",
    "sg:address":"Dorfstr. 24",
    "sg:city":"Schelldorf",
    "sg:phone":"+49 39362/81352",
    "sg:postcode":"39517",
    "sg:province":"Sachsen-Anhalt",
    "wof:name":"Kunststoffverarbeitung Schelldorf Und Transport Gmbh",
    "wof:placetype":"venue"
},
  "geometry": {"coordinates":[11.980887,52.472424],"type":"Point"}
}