{
  "type": "Feature",
  "properties": {
    "iso:country":"DE",
    "sg:address":"Moorenringgasse 7",
    "sg:city":"Kempen",
    "sg:phone":"+49 2152/4887",
    "sg:postcode":"47906",
    "sg:province":"Nordrhein-Westfalen",
    "wof:name":"B. Bruckmann Ingenieur",
    "wof:placetype":"venue"
},
  "geometry": {"coordinates":[6.4242811203,51.3648948669],"type":"Point"}
}