{
  "type": "Feature",
  "properties": {
    "iso:country":"DE",
    "sg:address":"Dresdener Str. 1",
    "sg:city":"Kassel",
    "sg:phone":"+49 4956/153242",
    "sg:postcode":"34125",
    "sg:province":"Hessen",
    "wof:name":"Autokomp Marketingges. F\u00dcr Komponenten",
    "wof:placetype":"venue"
},
  "geometry": {"coordinates":[9.5121688843,51.3117637634],"type":"Point"}
}