{
  "type": "Feature",
  "properties": {
    "iso:country":"DE",
    "sg:address":"Alte Bottroper Str 15",
    "sg:city":"Essen",
    "sg:phone":"+49 201/662024",
    "sg:postcode":"45356",
    "sg:province":"Nordrhein-Westfalen",
    "wof:name":"Ipm - Industrie Planung Und Montage Gmbh",
    "wof:placetype":"venue"
},
  "geometry": {"coordinates":[6.9646749496,51.4859962463],"type":"Point"}
}