{
  "type": "Feature",
  "properties": {
    "iso:country":"DE",
    "sg:address":"Am Volksgut Gautzsch 13",
    "sg:city":"Markkleeberg",
    "sg:phone":"+49 341/3587337",
    "sg:postcode":"04416",
    "sg:province":"Sachsen",
    "wof:name":"Dieter Behrendt",
    "wof:placetype":"venue"
},
  "geometry": {"coordinates":[12.363173,51.275146],"type":"Point"}
}