{
  "type": "Feature",
  "properties": {
    "iso:country":"DE",
    "sg:address":"Jahnstr. 24",
    "sg:city":"Schwandorf",
    "sg:postcode":"92421",
    "sg:province":"Bayern",
    "wof:name":"Yvonne Joller",
    "wof:placetype":"venue"
},
  "geometry": {"coordinates":[12.1167516708,49.3280906677],"type":"Point"}
}