{
  "type": "Feature",
  "properties": {
    "iso:country":"DE",
    "sg:address":"Luisenstr. 1 a",
    "sg:city":"Norderney",
    "sg:phone":"+49 4932/2166",
    "sg:postcode":"26548",
    "sg:province":"Niedersachsen",
    "wof:name":"H. Schmedes",
    "wof:placetype":"venue"
},
  "geometry": {"coordinates":[7.1414489746,53.7045249939],"type":"Point"}
}