{
  "type": "Feature",
  "properties": {
    "iso:country":"DE",
    "sg:address":"Chiemseestr. 16",
    "sg:city":"Schnaitsee",
    "sg:phone":"+49 8074/8963",
    "sg:postcode":"83530",
    "sg:province":"Bayern",
    "wof:name":"Josef L\u00f6w",
    "wof:placetype":"venue"
},
  "geometry": {"coordinates":[12.37012,48.069191],"type":"Point"}
}