{
  "type": "Feature",
  "properties": {
    "iso:country":"DE",
    "sg:address":"An der Weberei 1",
    "sg:city":"Gundelfingen",
    "sg:postcode":"89423",
    "sg:province":"Bayern",
    "wof:name":"Old-factory-store",
    "wof:placetype":"venue"
},
  "geometry": {"coordinates":[10.3833503723,48.5545005798],"type":"Point"}
}