{
  "type": "Feature",
  "properties": {
    "iso:country":"DE",
    "sg:address":"K\u00fcpferlingstr. 62",
    "sg:city":"Rosenheim",
    "sg:phone":"+49 8031/14880",
    "sg:postcode":"83024",
    "sg:province":"Bayern",
    "wof:name":"Birgit Stein",
    "wof:placetype":"venue"
},
  "geometry": {"coordinates":[12.1078557968,47.8584403992],"type":"Point"}
}