{
  "type": "Feature",
  "properties": {
    "iso:country":"DE",
    "sg:address":"Hauptstr. 94",
    "sg:city":"G\u00f6cklingen",
    "sg:phone":"+49 6349/7373",
    "sg:postcode":"76831",
    "sg:province":"Rheinland-Pfalz",
    "wof:name":"Fritz Kuntz",
    "wof:placetype":"venue"
},
  "geometry": {"coordinates":[8.0336818695,49.1630325317],"type":"Point"}
}