{
  "type": "Feature",
  "properties": {
    "iso:country":"DE",
    "sg:address":"Angerstr. 6",
    "sg:city":"Hannover",
    "sg:phone":"+49 511/96966959",
    "sg:postcode":"30161",
    "sg:province":"Niedersachsen",
    "wof:name":"Bechstein Und Kollegen",
    "wof:placetype":"venue"
},
  "geometry": {"coordinates":[9.741361618,52.3819961548],"type":"Point"}
}