{
  "type": "Feature",
  "properties": {
    "iso:country":"DE",
    "sg:address":"Klosterstr. 17/1",
    "sg:city":"Tettnang-Oberlangnau",
    "sg:phone":"+49 4975/4395090",
    "sg:postcode":"88069",
    "sg:province":"Baden-W\u00fcrttemberg",
    "wof:name":"Michael Dewald Kunststoffverarbeitung Gmbh",
    "wof:placetype":"venue"
},
  "geometry": {"coordinates":[9.6587944031,47.6292572021],"type":"Point"}
}