{
  "type": "Feature",
  "properties": {
    "iso:country":"DE",
    "sg:address":"Rondorfer Str. 37",
    "sg:city":"H\u00fcrth",
    "sg:postcode":"50354",
    "sg:province":"Nordrhein-Westfalen",
    "wof:name":"Gfi Immobilien-gruppe Gmbh",
    "wof:placetype":"venue"
},
  "geometry": {"coordinates":[6.908331871,50.892288208],"type":"Point"}
}