{
  "type": "Feature",
  "properties": {
    "iso:country":"DE",
    "sg:address":"Steinstr. 18",
    "sg:city":"Sarstedt",
    "sg:phone":"+49 4950/6698040",
    "sg:postcode":"31157",
    "sg:province":"Niedersachsen",
    "wof:name":"Commerzbank Ag",
    "wof:placetype":"venue"
},
  "geometry": {"coordinates":[9.852887,52.23399],"type":"Point"}
}