{
  "type": "Feature",
  "properties": {
    "iso:country":"DE",
    "sg:address":"Ludwigshafener Str. 4b",
    "sg:city":"Frankenthal",
    "sg:phone":"+49 6233/66345",
    "sg:postcode":"67227",
    "sg:province":"Rheinland-Pfalz",
    "wof:name":"Computer Bv Gmbh",
    "wof:placetype":"venue"
},
  "geometry": {"coordinates":[8.3692398071,49.5440216064],"type":"Point"}
}