{
  "type": "Feature",
  "properties": {
    "iso:country":"DE",
    "sg:address":"Benzstrasse 16",
    "sg:city":"Durmersheim",
    "sg:phone":"+49 7245/92900",
    "sg:postcode":"76448",
    "sg:province":"Baden-W\u00fcrttemberg",
    "wof:name":"Stahl Mineral\u00f6lvertrieb Gmbh",
    "wof:placetype":"venue"
},
  "geometry": {"coordinates":[8.2685070038,48.9312973022],"type":"Point"}
}