{
  "type": "Feature",
  "properties": {
    "iso:country":"DE",
    "sg:address":"Leonberger Str. 99",
    "sg:city":"Leonberg",
    "sg:phone":"+49 7152/75457",
    "sg:postcode":"71229",
    "sg:province":"Baden-W\u00fcrttemberg",
    "wof:name":"Tanzschule Ritter",
    "wof:placetype":"venue"
},
  "geometry": {"coordinates":[9.010266304,48.7950630188],"type":"Point"}
}