{
  "type": "Feature",
  "properties": {
    "iso:country":"DE",
    "sg:address":"Wanne 6",
    "sg:city":"Backnang",
    "sg:phone":"+49 4971/911740",
    "sg:postcode":"71522",
    "sg:province":"Baden-W\u00fcrttemberg",
    "wof:name":"Sicpa-druckfarben Gmbh",
    "wof:placetype":"venue"
},
  "geometry": {"coordinates":[9.432515,48.948376],"type":"Point"}
}