{
  "type": "Feature",
  "properties": {
    "iso:country":"DE",
    "sg:address":"Bahnhofstr. 1",
    "sg:city":"Gundelfingen",
    "sg:phone":"+49 9073/7779",
    "sg:postcode":"89423",
    "sg:province":"Bayern",
    "wof:name":"Kaiser Augenoptik",
    "wof:placetype":"venue"
},
  "geometry": {"coordinates":[7.8701548576,48.0443649292],"type":"Point"}
}