{
  "type": "Feature",
  "properties": {
    "iso:country":"DE",
    "sg:address":"Vordere Karlstr. 12",
    "sg:city":"G\u00f6ppingen",
    "sg:phone":"+49 7161/963540",
    "sg:postcode":"73033",
    "sg:province":"Baden-W\u00fcrttemberg",
    "wof:name":"M. G\u00f6tz",
    "wof:placetype":"venue"
},
  "geometry": {"coordinates":[9.6614103317,48.7004814148],"type":"Point"}
}