{
  "type": "Feature",
  "properties": {
    "iso:country":"DE",
    "sg:city":"Bielefeld",
    "sg:postcode":"33719",
    "sg:province":"Nordrhein-Westfalen",
    "wof:name":"Filo Carpet Objekt-teppichbodendesign Gmbh, Bielefeld",
    "wof:placetype":"venue"
},
  "geometry": {"coordinates":[8.61879,52.023972],"type":"Point"}
}