{
  "type": "Feature",
  "properties": {
    "iso:country":"DE",
    "sg:address":"Balanstr. 8",
    "sg:city":"M\u00fcnchen",
    "sg:phone":"+49 89/481870",
    "sg:postcode":"81669",
    "sg:province":"Bayern",
    "wof:name":"H. Und B. Bischof",
    "wof:placetype":"venue"
},
  "geometry": {"coordinates":[11.5943346024,48.1276550293],"type":"Point"}
}