{
  "type": "Feature",
  "properties": {
    "iso:country":"DE",
    "sg:address":"Marktstr. 34",
    "sg:city":"Mayen",
    "sg:phone":"+49 2651/76048",
    "sg:postcode":"56727",
    "sg:province":"Rheinland-Pfalz",
    "wof:name":"Ellen Wilhelmy Heilpraktikerin",
    "wof:placetype":"venue"
},
  "geometry": {"coordinates":[7.2234668732,50.3296890259],"type":"Point"}
}