{
  "type": "Feature",
  "properties": {
    "iso:country":"DE",
    "sg:address":"Metallstr. 2",
    "sg:city":"Viersen",
    "sg:phone":"+49 2162/51039",
    "sg:postcode":"41751",
    "sg:province":"Nordrhein-Westfalen",
    "wof:name":"Das Sichere Dach P. K\u00fcrschner Dachdeckerm. Fachbetrieb Und",
    "wof:placetype":"venue"
},
  "geometry": {"coordinates":[6.3278698921,51.2327690125],"type":"Point"}
}