{
  "type": "Feature",
  "properties": {
    "iso:country":"DE",
    "sg:address":"J\u00fcdenstr. 1",
    "sg:city":"Lutherstadt Wittenberg",
    "sg:phone":"+49 3491/403631",
    "sg:postcode":"06886",
    "sg:province":"Sachsen-Anhalt",
    "wof:name":"G. Fiebig",
    "wof:placetype":"venue"
},
  "geometry": {"coordinates":[12.6441020966,51.8670654297],"type":"Point"}
}