{
  "type": "Feature",
  "properties": {
    "iso:country":"DE",
    "sg:address":"Nordheiderstr. 1",
    "sg:city":"Offenb\u00fcttel",
    "sg:phone":"+49 4835/462",
    "sg:postcode":"25767",
    "sg:province":"Schleswig-Holstein",
    "wof:name":"Hans Wohlers Landwirtschaftl. Lohnbetrieb",
    "wof:placetype":"venue"
},
  "geometry": {"coordinates":[9.350811,54.171242],"type":"Point"}
}