{
  "type": "Feature",
  "properties": {
    "iso:country":"DE",
    "sg:address":"Karl-Marx-Str. 205",
    "sg:city":"Sch\u00f6newerda",
    "sg:postcode":"06556",
    "sg:province":"Th\u00fcringen",
    "wof:name":"B\u00e4uerliche Handels- Genossenschaft",
    "wof:placetype":"venue"
},
  "geometry": {"coordinates":[11.365236,51.321678],"type":"Point"}
}