{
  "type": "Feature",
  "properties": {
    "iso:country":"DE",
    "sg:address":"F\u00fcrstenwall 26",
    "sg:city":"D\u00fcsseldorf",
    "sg:phone":"+49 211/3981434",
    "sg:postcode":"40219",
    "sg:province":"Nordrhein-Westfalen",
    "wof:name":"Glas-meyer-m\u00fcntz Inh. Manfred M\u00fcntz",
    "wof:placetype":"venue"
},
  "geometry": {"coordinates":[6.7642598152,51.2166824341],"type":"Point"}
}