{
  "type": "Feature",
  "properties": {
    "iso:country":"DE",
    "sg:address":"Badstr. 10",
    "sg:city":"Sigmaringen",
    "sg:phone":"+49 7571/13384",
    "sg:postcode":"72488",
    "sg:province":"Baden-W\u00fcrttemberg",
    "wof:name":"Georg Lang Architekt",
    "wof:placetype":"venue"
},
  "geometry": {"coordinates":[9.22564,48.080788],"type":"Point"}
}