{
  "type": "Feature",
  "properties": {
    "iso:country":"DE",
    "sg:address":"Roddener-Weg 50",
    "sg:city":"K\u00f6tschlitz",
    "sg:phone":"+49 34638/20249",
    "sg:postcode":"06254",
    "sg:province":"Sachsen-Anhalt",
    "wof:name":"Agrargenossenschaft Untere Aue Eg",
    "wof:placetype":"venue"
},
  "geometry": {"coordinates":[12.155085,51.345509],"type":"Point"}
}