{
  "type": "Feature",
  "properties": {
    "iso:country":"DE",
    "sg:address":"Langensaal 6",
    "sg:city":"Kiel",
    "sg:phone":"+49 431/28333",
    "sg:postcode":"24149",
    "sg:province":"Schleswig-Holstein",
    "wof:name":"Schl\u00fcter Versicherung Und Finanz-vermittlungsges.",
    "wof:placetype":"venue"
},
  "geometry": {"coordinates":[10.1818971634,54.3326148987],"type":"Point"}
}