{
  "type": "Feature",
  "properties": {
    "iso:country":"DE",
    "sg:address":"Haunstetter Str. 75",
    "sg:city":"K\u00f6nigsbrunn",
    "sg:phone":"+49 8231/96200",
    "sg:postcode":"86343",
    "sg:province":"Bayern",
    "wof:name":"Autohaus Knaller Gmbh & Co. Kg",
    "wof:placetype":"venue"
},
  "geometry": {"coordinates":[10.8940420151,48.283039093],"type":"Point"}
}