{
  "type": "Feature",
  "properties": {
    "iso:country":"DE",
    "sg:address":"Faulacker 7",
    "sg:city":"Weil am Rhein",
    "sg:phone":"+49 7621/798060",
    "sg:postcode":"79576",
    "sg:province":"Baden-W\u00fcrttemberg",
    "wof:name":"Ecr Eucam Clinical Research Gmbh",
    "wof:placetype":"venue"
},
  "geometry": {"coordinates":[7.631882,47.589348],"type":"Point"}
}