{
  "type": "Feature",
  "properties": {
    "iso:country":"DE",
    "sg:address":"Gewerbehof 12",
    "sg:city":"Werne",
    "sg:phone":"+49 2389/98480",
    "sg:postcode":"59368",
    "sg:province":"Nordrhein-Westfalen",
    "wof:name":"Alf Fahrzeugbau Und Beteiligungs Gmbh & Co. Kg",
    "wof:placetype":"venue"
},
  "geometry": {"coordinates":[7.6102957726,51.6613731384],"type":"Point"}
}