{
  "type": "Feature",
  "properties": {
    "iso:country":"DE",
    "sg:address":"Heilbronner Str. 42",
    "sg:city":"Neckarsulm",
    "sg:phone":"+49 4971/3293220",
    "sg:postcode":"74172",
    "sg:province":"Baden-W\u00fcrttemberg",
    "wof:name":"Telcos Tele-communikations- System Gmbh",
    "wof:placetype":"venue"
},
  "geometry": {"coordinates":[9.2243776321,49.186504364],"type":"Point"}
}