{
  "type": "Feature",
  "properties": {
    "iso:country":"DE",
    "sg:address":"Reuterdamm 45",
    "sg:city":"Langenhagen",
    "sg:phone":"+49 511/731169",
    "sg:postcode":"30853",
    "sg:province":"Niedersachsen",
    "wof:name":"Holsteinklause",
    "wof:placetype":"venue"
},
  "geometry": {"coordinates":[9.754114151,52.4528427124],"type":"Point"}
}