{
  "type": "Feature",
  "properties": {
    "iso:country":"DE",
    "sg:address":"Am Hauptbahnhof 6",
    "sg:city":"Frankfurt",
    "sg:phone":"+49 69/256100",
    "sg:postcode":"60069",
    "sg:province":"Brandenburg",
    "wof:name":"\u00d6kobank Eg",
    "wof:placetype":"venue"
},
  "geometry": {"coordinates":[8.6655435562,50.1069755554],"type":"Point"}
}