{
  "type": "Feature",
  "properties": {
    "iso:country":"DE",
    "sg:address":"Morsestr. 2",
    "sg:city":"Unterschlei\u00dfheim",
    "sg:phone":"+49 89/3106800",
    "sg:postcode":"85716",
    "sg:province":"Bayern",
    "wof:name":"Weing\u00e4rtner",
    "wof:placetype":"venue"
},
  "geometry": {"coordinates":[11.573552,48.289963],"type":"Point"}
}