{
  "type": "Feature",
  "properties": {
    "iso:country":"DE",
    "sg:address":"Kleine Markstr. 4",
    "sg:city":"Offenbach",
    "sg:phone":"+49 69/886968",
    "sg:postcode":"63065",
    "sg:province":"Hessen",
    "wof:name":"Wheap - Oldie-musik Live - 50er Bis 80er Jahre",
    "wof:placetype":"venue"
},
  "geometry": {"coordinates":[8.761984,50.103893],"type":"Point"}
}