{
  "type": "Feature",
  "properties": {
    "iso:country":"DE",
    "sg:address":"Unterer Haldenweg 43",
    "sg:city":"Wannweil",
    "sg:phone":"+49 7121/579288",
    "sg:postcode":"72827",
    "sg:province":"Baden-W\u00fcrttemberg",
    "wof:name":"Karola Leibl Hebamme",
    "wof:placetype":"venue"
},
  "geometry": {"coordinates":[9.145729,48.511578],"type":"Point"}
}