{
  "type": "Feature",
  "properties": {
    "iso:country":"DE",
    "sg:city":"Gersthofen",
    "sg:phone":"+49 821/495583",
    "sg:postcode":"86368",
    "sg:province":"Bayern",
    "wof:name":"Bernd-uwe Hubmann",
    "wof:placetype":"venue"
},
  "geometry": {"coordinates":[10.879137,48.423878],"type":"Point"}
}