{
  "type": "Feature",
  "properties": {
    "iso:country":"DE",
    "sg:address":"Untere Au 16",
    "sg:city":"Bruchsal",
    "sg:phone":"+49 7257/5203",
    "sg:postcode":"76646",
    "sg:province":"Baden-W\u00fcrttemberg",
    "wof:name":"Pw Bautr\u00e4ger Gmbh",
    "wof:placetype":"venue"
},
  "geometry": {"coordinates":[8.5771398544,49.078956604],"type":"Point"}
}