{
  "type": "Feature",
  "properties": {
    "iso:country":"DE",
    "sg:address":"Nikolausstr. 9",
    "sg:city":"Fulda",
    "sg:phone":"+49 661/79079",
    "sg:postcode":"36037",
    "sg:province":"Hessen",
    "wof:name":"Fischer Gmbh & Co. Kg",
    "wof:placetype":"venue"
},
  "geometry": {"coordinates":[9.6844577789,50.5527839661],"type":"Point"}
}