{
  "type": "Feature",
  "properties": {
    "iso:country":"DE",
    "sg:address":"Schnepfenreuther Weg 38",
    "sg:city":"Berlin",
    "sg:phone":"+49 30/35503220",
    "sg:postcode":"13587",
    "sg:province":"Berlin",
    "wof:name":"Carl Haenisch Dipl.-ing.",
    "wof:placetype":"venue"
},
  "geometry": {"coordinates":[13.2023429871,52.5589523315],"type":"Point"}
}