{
  "type": "Feature",
  "properties": {
    "iso:country":"DE",
    "sg:address":"Am Funkturm 61",
    "sg:city":"Colnrade",
    "sg:phone":"+49 4434/281",
    "sg:postcode":"27243",
    "sg:province":"Niedersachsen",
    "wof:name":"Horst Degen",
    "wof:placetype":"venue"
},
  "geometry": {"coordinates":[8.48114,52.822201],"type":"Point"}
}