{
  "type": "Feature",
  "properties": {
    "iso:country":"DE",
    "sg:address":"Birkenstr. 7",
    "sg:city":"Neubeuern",
    "sg:phone":"+49 8035/3243",
    "sg:postcode":"83115",
    "sg:province":"Bayern",
    "wof:name":"Johannes Dehmel Ingenieur",
    "wof:placetype":"venue"
},
  "geometry": {"coordinates":[12.135225296,47.7729530334],"type":"Point"}
}