{
  "type": "Feature",
  "properties": {
    "iso:country":"DE",
    "sg:address":"Feldkamp 74",
    "sg:city":"Gronau",
    "sg:phone":"+49 2565/4805",
    "sg:postcode":"48599",
    "sg:province":"Nordrhein-Westfalen",
    "wof:name":"Elisabeth Sch\u00f6n Steuerberaterin",
    "wof:placetype":"venue"
},
  "geometry": {"coordinates":[7.0576481819,52.1789970398],"type":"Point"}
}