{
  "type": "Feature",
  "properties": {
    "iso:country":"DE",
    "sg:address":"Am Sonnenhang 11",
    "sg:city":"Hofheim",
    "sg:phone":"+49 6192/935683",
    "sg:postcode":"65719",
    "sg:province":"Hessen",
    "wof:name":"Lutz Viertel Gmbh",
    "wof:placetype":"venue"
},
  "geometry": {"coordinates":[8.4227237701,50.0589294434],"type":"Point"}
}