{
  "type": "Feature",
  "properties": {
    "iso:country":"DE",
    "sg:address":"Griesstr. 61",
    "sg:city":"Monheim",
    "sg:phone":"+49 2173/63347",
    "sg:postcode":"40789",
    "sg:province":"Nordrhein-Westfalen",
    "wof:name":"Fritz Blank",
    "wof:placetype":"venue"
},
  "geometry": {"coordinates":[6.886709,51.114193],"type":"Point"}
}