{
  "type": "Feature",
  "properties": {
    "iso:country":"DE",
    "sg:address":"Gorkistr. 53",
    "sg:city":"Berlin",
    "sg:phone":"+49 30/4339529",
    "sg:postcode":"13509",
    "sg:province":"Berlin",
    "wof:name":"Ursula Pohle-pilasik",
    "wof:placetype":"venue"
},
  "geometry": {"coordinates":[13.293255806,52.5909042358],"type":"Point"}
}