{
  "type": "Feature",
  "properties": {
    "iso:country":"DE",
    "sg:address":"Eschenstr. 8",
    "sg:city":"Wiesbaden",
    "sg:phone":"+49 6122/91200",
    "sg:postcode":"65205",
    "sg:province":"Hessen",
    "wof:name":"G\u00fcnter Gehrmann Steuerberater",
    "wof:placetype":"venue"
},
  "geometry": {"coordinates":[8.348277092,50.0668792725],"type":"Point"}
}