{
  "type": "Feature",
  "properties": {
    "iso:country":"DE",
    "sg:address":"Johann-Christoph-Hilf-Str. 14",
    "sg:city":"Bad Elster",
    "sg:phone":"+49 37437/3923",
    "sg:postcode":"08645",
    "sg:province":"Sachsen",
    "wof:name":"H. Ro\u00dfbach",
    "wof:placetype":"venue"
},
  "geometry": {"coordinates":[12.236295,50.279366],"type":"Point"}
}