{
  "type": "Feature",
  "properties": {
    "iso:country":"DE",
    "sg:address":"Hermannstr. 2a",
    "sg:city":"Waltrop",
    "sg:phone":"+49 2309",
    "sg:postcode":"45731",
    "sg:province":"Nordrhein-Westfalen",
    "wof:name":"Schaeferhunde Hundewiese",
    "wof:placetype":"venue"
},
  "geometry": {"coordinates":[7.3651280403,51.6153831482],"type":"Point"}
}