{
  "type": "Feature",
  "properties": {
    "iso:country":"DE",
    "sg:address":"Sauerbruchstr. 42",
    "sg:city":"Recklinghausen",
    "sg:phone":"+49 2361/652111",
    "sg:postcode":"45661",
    "sg:province":"Nordrhein-Westfalen",
    "wof:name":"J\u00fclkenbeck Gmbh",
    "wof:placetype":"venue"
},
  "geometry": {"coordinates":[7.209542,51.570583],"type":"Point"}
}