{
  "type": "Feature",
  "properties": {
    "iso:country":"DE",
    "sg:address":"Schlo\u00dfberg 2",
    "sg:city":"Heidelberg",
    "sg:phone":"+49 6221/166604",
    "sg:postcode":"69117",
    "sg:province":"Baden-W\u00fcrttemberg",
    "wof:name":"The Health Service Group Gmbh",
    "wof:placetype":"venue"
},
  "geometry": {"coordinates":[8.710458,49.40974],"type":"Point"}
}