{
  "type": "Feature",
  "properties": {
    "iso:country":"DE",
    "sg:address":"Laurentiusstr. 13",
    "sg:city":"Mannheim",
    "sg:phone":"+49 621/335290",
    "sg:postcode":"68167",
    "sg:province":"Baden-W\u00fcrttemberg",
    "wof:name":"Holderstrauch",
    "wof:placetype":"venue"
},
  "geometry": {"coordinates":[8.4703960419,49.4976158142],"type":"Point"}
}