{
  "type": "Feature",
  "properties": {
    "iso:country":"DE",
    "sg:address":"Clemensstr. 12",
    "sg:city":"Stolberg",
    "sg:phone":"+49 2402",
    "sg:postcode":"52223",
    "sg:province":"Nordrhein-Westfalen",
    "wof:name":"Willkommen Bei Wiwico",
    "wof:placetype":"venue"
},
  "geometry": {"coordinates":[6.213656,50.733334],"type":"Point"}
}