{
  "type": "Feature",
  "properties": {
    "iso:country":"DE",
    "sg:address":"Freyung 630",
    "sg:city":"Landshut",
    "sg:phone":"+49 871/22873",
    "sg:postcode":"84028",
    "sg:province":"Bayern",
    "wof:name":"Studienseminar",
    "wof:placetype":"venue"
},
  "geometry": {"coordinates":[12.1587820053,48.5364456177],"type":"Point"}
}