{
  "type": "Feature",
  "properties": {
    "iso:country":"DE",
    "sg:address":"Heinrich-Tessenow-Weg 13",
    "sg:city":"Dresden",
    "sg:phone":"+49 351/8806162",
    "sg:postcode":"01109",
    "sg:province":"Sachsen",
    "wof:name":"Prof. Dr. Hans-joachim K\u00fchn",
    "wof:placetype":"venue"
},
  "geometry": {"coordinates":[13.7574520111,51.1128196716],"type":"Point"}
}