{
  "type": "Feature",
  "properties": {
    "iso:country":"DE",
    "sg:address":"Siedlungsweg 1",
    "sg:city":"Hohenthurm",
    "sg:phone":"+49 34602/50936",
    "sg:postcode":"06188",
    "sg:province":"Sachsen-Anhalt",
    "wof:name":"Barbara Albert",
    "wof:placetype":"venue"
},
  "geometry": {"coordinates":[12.0976696014,51.5189437866],"type":"Point"}
}