{
  "type": "Feature",
  "properties": {
    "iso:country":"DE",
    "sg:address":"Adalbertstr. 32",
    "sg:city":"D\u00fcsseldorf",
    "sg:phone":"+49 211/575263",
    "sg:postcode":"40545",
    "sg:province":"Nordrhein-Westfalen",
    "wof:name":"Peter Lippelt Architekt",
    "wof:placetype":"venue"
},
  "geometry": {"coordinates":[6.75435,51.229668],"type":"Point"}
}