{
  "type": "Feature",
  "properties": {
    "iso:country":"DE",
    "sg:address":"Nollendorfplatz 8",
    "sg:city":"Berlin",
    "sg:phone":"+49 30/2174292",
    "sg:postcode":"10777",
    "sg:province":"Berlin",
    "wof:name":"Klaus-peter Mann",
    "wof:placetype":"venue"
},
  "geometry": {"coordinates":[13.354387,52.499084],"type":"Point"}
}