{
  "type": "Feature",
  "properties": {
    "iso:country":"DE",
    "sg:address":"Am S\u00fcdpark 5",
    "sg:city":"Kelsterbach",
    "sg:phone":"+49 6107/90330",
    "sg:postcode":"65451",
    "sg:province":"Hessen",
    "wof:name":"Bcs Buck Cargo Services Gmbh",
    "wof:placetype":"venue"
},
  "geometry": {"coordinates":[8.5283632278,50.0525970459],"type":"Point"}
}