{
  "type": "Feature",
  "properties": {
    "iso:country":"DE",
    "sg:address":"Lebacher Str. 62",
    "sg:city":"Saarbr\u00fccken",
    "sg:phone":"+49 681/74432",
    "sg:postcode":"66113",
    "sg:province":"Saarland",
    "wof:name":"Super Star Gmbh",
    "wof:placetype":"venue"
},
  "geometry": {"coordinates":[6.970662117,49.2445869446],"type":"Point"}
}