{
  "type": "Feature",
  "properties": {
    "iso:country":"DE",
    "sg:address":"W\u00f6rthstr. 1",
    "sg:city":"Germersheim",
    "sg:phone":"+49 7274/1097",
    "sg:postcode":"76726",
    "sg:province":"Rheinland-Pfalz",
    "wof:name":"Gross & Co.",
    "wof:placetype":"venue"
},
  "geometry": {"coordinates":[8.3768596649,49.2288894653],"type":"Point"}
}