{
  "type": "Feature",
  "properties": {
    "iso:country":"DE",
    "sg:address":"Postfach 1180:: 31501 Wunstorf:: Germany.^^Lange Str 2::",
    "sg:city":"Wunstorf",
    "sg:phone":"+49 202/4882320",
    "sg:postcode":"31515",
    "sg:province":"Niedersachsen",
    "wof:name":"Stadtsparkasse Wuppertal",
    "wof:placetype":"venue"
},
  "geometry": {"coordinates":[7.146295,51.2589],"type":"Point"}
}