{
  "type": "Feature",
  "properties": {
    "iso:country":"DE",
    "sg:address":"Im Oberstein 8",
    "sg:city":"Weiterstadt",
    "sg:phone":"+49 6150/50020",
    "sg:postcode":"64331",
    "sg:province":"Hessen",
    "wof:name":"Grope",
    "wof:placetype":"venue"
},
  "geometry": {"coordinates":[8.582746,49.905846],"type":"Point"}
}