{
  "type": "Feature",
  "properties": {
    "iso:country":"DE",
    "sg:address":"Plankensteiner Weg 23",
    "sg:city":"Plankenfels",
    "sg:phone":"+49 9204/9150",
    "sg:postcode":"95515",
    "sg:province":"Bayern",
    "wof:name":"Otto G\u00f6rl Gmbh",
    "wof:placetype":"venue"
},
  "geometry": {"coordinates":[11.348713,49.89156],"type":"Point"}
}