{
  "type": "Feature",
  "properties": {
    "iso:country":"DE",
    "sg:address":"Augsburger Str.",
    "sg:city":"Dachau",
    "sg:postcode":"85221",
    "sg:province":"Bayern",
    "wof:name":"Dachauer Bauelemente Vertrieb Gmbh",
    "wof:placetype":"venue"
},
  "geometry": {"coordinates":[11.4293031693,48.2620277405],"type":"Point"}
}