{
  "type": "Feature",
  "properties": {
    "iso:country":"DE",
    "sg:address":"Kirchenstr. 24",
    "sg:city":"Ludwigshafen",
    "sg:phone":"+49 621/651051",
    "sg:postcode":"67069",
    "sg:province":"Rheinland-Pfalz",
    "wof:name":"Elke Beer Immobilienmaklerin",
    "wof:placetype":"venue"
},
  "geometry": {"coordinates":[8.4022979736,49.520275116],"type":"Point"}
}