{
  "type": "Feature",
  "properties": {
    "iso:country":"DE",
    "sg:address":"Bahnstr. 16",
    "sg:city":"Liederbach",
    "sg:phone":"+49 69/303169",
    "sg:postcode":"65835",
    "sg:province":"Hessen",
    "wof:name":"Franz Strobel Gmbh",
    "wof:placetype":"venue"
},
  "geometry": {"coordinates":[8.490166,50.119576],"type":"Point"}
}