{
  "type": "Feature",
  "properties": {
    "iso:country":"DE",
    "sg:address":"Forststr. 22",
    "sg:city":"K\u00fcnzell",
    "sg:phone":"+49 661/35971",
    "sg:postcode":"36093",
    "sg:province":"Hessen",
    "wof:name":"Ottmar Hohmann Architekt",
    "wof:placetype":"venue"
},
  "geometry": {"coordinates":[9.72509,50.538506],"type":"Point"}
}