{
  "type": "Feature",
  "properties": {
    "iso:country":"DE",
    "sg:address":"Elsenkamp 8",
    "sg:city":"Borken",
    "sg:phone":"+49 2862/2152",
    "sg:postcode":"46325",
    "sg:province":"Nordrhein-Westfalen",
    "wof:name":"Heinrich Finke",
    "wof:placetype":"venue"
},
  "geometry": {"coordinates":[6.83936,51.916267],"type":"Point"}
}