{
  "type": "Feature",
  "properties": {
    "iso:country":"DE",
    "sg:address":"Am Bredenbusch 17",
    "sg:city":"Bielefeld",
    "sg:phone":"+49 5202/80241",
    "sg:postcode":"33699",
    "sg:province":"Nordrhein-Westfalen",
    "wof:name":"A. K\u00f6bernik",
    "wof:placetype":"venue"
},
  "geometry": {"coordinates":[8.6418457031,52.0002059937],"type":"Point"}
}