{
  "type": "Feature",
  "properties": {
    "iso:country":"DE",
    "sg:address":"Klaus-Herrmann-Str. 19",
    "sg:city":"Guben",
    "sg:phone":"+49 3561/52062",
    "sg:postcode":"03172",
    "sg:province":"Brandenburg",
    "wof:name":"Fuchs Apotheke",
    "wof:placetype":"venue"
},
  "geometry": {"coordinates":[14.682442,51.95332],"type":"Point"}
}