{
  "type": "Feature",
  "properties": {
    "iso:country":"DE",
    "sg:address":"Hintenmeiswinkeler Weg 9",
    "sg:city":"Solingen",
    "sg:phone":"+49 212/811588",
    "sg:postcode":"42657",
    "sg:province":"Nordrhein-Westfalen",
    "wof:name":"Hugo Massberg E. K.",
    "wof:placetype":"venue"
},
  "geometry": {"coordinates":[7.063944,51.137299],"type":"Point"}
}