{
  "type": "Feature",
  "properties": {
    "iso:country":"DE",
    "sg:address":"Schwabacher Str. 32",
    "sg:city":"F\u00fcrth",
    "sg:phone":"+49 911/7492940",
    "sg:postcode":"90762",
    "sg:province":"Bayern",
    "wof:name":"Eichinger Und Partner Rechtsanw\u00e4lte",
    "wof:placetype":"venue"
},
  "geometry": {"coordinates":[10.98853302,49.4740333557],"type":"Point"}
}