{
  "type": "Feature",
  "properties": {
    "iso:country":"DE",
    "sg:address":"Charlottenstr. 62",
    "sg:city":"Berlin",
    "sg:postcode":"10117",
    "sg:province":"Berlin",
    "wof:name":"Investitionsgesellschaft Hausvogteiplatz 11",
    "wof:placetype":"venue"
},
  "geometry": {"coordinates":[13.391393,52.511692],"type":"Point"}
}