{
  "type": "Feature",
  "properties": {
    "iso:country":"DE",
    "sg:address":"Halsdorfer Str. 40 Wohra",
    "sg:city":"Wohratal",
    "sg:phone":"+49 4964/5391200",
    "sg:postcode":"35288",
    "sg:province":"Hessen",
    "wof:name":"M\u00d6belfabrik Wohra Gmbh",
    "wof:placetype":"venue"
},
  "geometry": {"coordinates":[8.9467086792,50.9355583191],"type":"Point"}
}