{
  "type": "Feature",
  "properties": {
    "iso:country":"DE",
    "sg:address":"Westfalenweg 18",
    "sg:city":"Wuppertal",
    "sg:phone":"+49 202/2642830",
    "sg:postcode":"42111",
    "sg:province":"Nordrhein-Westfalen",
    "wof:name":"Ikonenland",
    "wof:placetype":"venue"
},
  "geometry": {"coordinates":[7.126054,51.280727],"type":"Point"}
}