{
  "type": "Feature",
  "properties": {
    "iso:country":"DE",
    "sg:address":"Lambertusstr. 59",
    "sg:city":"Wassenberg",
    "sg:phone":"+49 2432/2526",
    "sg:postcode":"41849",
    "sg:province":"Nordrhein-Westfalen",
    "wof:name":"Hildegard Krebs",
    "wof:placetype":"venue"
},
  "geometry": {"coordinates":[6.1431798935,51.1157455444],"type":"Point"}
}