{
  "type": "Feature",
  "properties": {
    "iso:country":"DE",
    "sg:address":"F\u00f6hrenweg 22",
    "sg:city":"Berlin",
    "sg:phone":"+49 30/8417350",
    "sg:postcode":"14195",
    "sg:province":"Berlin",
    "wof:name":"Friedrich H. Bayer Verwaltungs-gmbh",
    "wof:placetype":"venue"
},
  "geometry": {"coordinates":[13.276559,52.458],"type":"Point"}
}