{
  "type": "Feature",
  "properties": {
    "iso:country":"DE",
    "sg:address":"Am Messehaus 23",
    "sg:city":"N\u00fcrnberg",
    "sg:phone":"+49 911/515120",
    "sg:postcode":"90489",
    "sg:province":"Bayern",
    "wof:name":"Werner Gradert",
    "wof:placetype":"venue"
},
  "geometry": {"coordinates":[11.1003227234,49.4650497437],"type":"Point"}
}