{
  "type": "Feature",
  "properties": {
    "iso:country":"DE",
    "sg:address":"Teichstr. 41",
    "sg:city":"Berlin",
    "sg:phone":"+49 30/4956021",
    "sg:postcode":"13407",
    "sg:province":"Berlin",
    "wof:name":"Seniorenwohnheim",
    "wof:placetype":"venue"
},
  "geometry": {"coordinates":[13.346967,52.568142],"type":"Point"}
}