{
  "type": "Feature",
  "properties": {
    "iso:country":"DE",
    "sg:address":"Poststr. 28",
    "sg:city":"Rheine",
    "sg:phone":"+49 5971/87403",
    "sg:postcode":"48431",
    "sg:province":"Nordrhein-Westfalen",
    "wof:name":"K. Von Der Forst Und Kollegen",
    "wof:placetype":"venue"
},
  "geometry": {"coordinates":[7.435338974,52.2795753479],"type":"Point"}
}