{
  "type": "Feature",
  "properties": {
    "iso:country":"DE",
    "sg:address":"Hanauer Landstr. 439",
    "sg:city":"Frankfurt",
    "sg:phone":"+49 69/94147555",
    "sg:postcode":"60314",
    "sg:province":"Hessen",
    "wof:name":"Kommunikationstechnik Rg & Partner",
    "wof:placetype":"venue"
},
  "geometry": {"coordinates":[8.7429637909,50.1238937378],"type":"Point"}
}