{
  "type": "Feature",
  "properties": {
    "iso:country":"DE",
    "sg:address":"Ganghoferstr. 3",
    "sg:city":"Thierhaupten",
    "sg:phone":"+49 8271/3807",
    "sg:postcode":"86672",
    "sg:province":"Bayern",
    "wof:name":"Wilhelm Kraus Architekt",
    "wof:placetype":"venue"
},
  "geometry": {"coordinates":[10.916683,48.563072],"type":"Point"}
}