{
  "type": "Feature",
  "properties": {
    "iso:country":"DE",
    "sg:address":"Achstr. 26",
    "sg:city":"Friedberg",
    "sg:phone":"+49 821/605011",
    "sg:postcode":"86316",
    "sg:province":"Bayern",
    "wof:name":"Vasita Grundbesitz Wolfgang Feldmayer",
    "wof:placetype":"venue"
},
  "geometry": {"coordinates":[10.9763498306,48.3556213379],"type":"Point"}
}