{
  "type": "Feature",
  "properties": {
    "iso:country":"DE",
    "sg:address":"Obere Glanstr. 29",
    "sg:city":"Odenbach",
    "sg:phone":"+49 6753/2202",
    "sg:postcode":"67748",
    "sg:province":"Rheinland-Pfalz",
    "wof:name":"G. Und E. Sievers",
    "wof:placetype":"venue"
},
  "geometry": {"coordinates":[7.644909,49.680927],"type":"Point"}
}