{
  "type": "Feature",
  "properties": {
    "iso:country":"DE",
    "sg:address":"Grundlachen 12",
    "sg:city":"Villingen-Schwenningen",
    "sg:phone":"+49 7721/909721",
    "sg:postcode":"78052",
    "sg:province":"Baden-W\u00fcrttemberg",
    "wof:name":"Poseidon Wassersysteme Gmbh",
    "wof:placetype":"venue"
},
  "geometry": {"coordinates":[8.4164609909,48.0359992981],"type":"Point"}
}