{
  "type": "Feature",
  "properties": {
    "iso:country":"DE",
    "sg:address":"Liederbachstr. 8",
    "sg:city":"Kelkheim",
    "sg:phone":"+49 6195/64766",
    "sg:postcode":"65779",
    "sg:province":"Hessen",
    "wof:name":"Rodeck Produkt Gmbh & Co.",
    "wof:placetype":"venue"
},
  "geometry": {"coordinates":[8.4523296356,50.1400642395],"type":"Point"}
}