{
  "type": "Feature",
  "properties": {
    "iso:country":"DE",
    "sg:address":"St\u00e4delstr. 10",
    "sg:city":"Frankfurt",
    "sg:phone":"+49 69/9621760",
    "sg:postcode":"60596",
    "sg:province":"Hessen",
    "wof:name":"Tebu Gmbh",
    "wof:placetype":"venue"
},
  "geometry": {"coordinates":[8.677146,50.103931],"type":"Point"}
}