{
  "type": "Feature",
  "properties": {
    "iso:country":"DE",
    "sg:address":"Gerokstr. 12",
    "sg:city":"Stuttgart",
    "sg:phone":"+49 711/2362449",
    "sg:postcode":"70188",
    "sg:province":"Baden-W\u00fcrttemberg",
    "wof:name":"M & L Kaffeehaus Gmbh",
    "wof:placetype":"venue"
},
  "geometry": {"coordinates":[9.19271,48.77969],"type":"Point"}
}