{
  "type": "Feature",
  "properties": {
    "iso:country":"DE",
    "sg:address":"Bornbachsteige 1",
    "sg:city":"Gerbrunn",
    "sg:phone":"+49 931/708017",
    "sg:postcode":"97218",
    "sg:province":"Bayern",
    "wof:name":"Georg Barth Handels Gmbh",
    "wof:placetype":"venue"
},
  "geometry": {"coordinates":[9.9877662659,49.7795028687],"type":"Point"}
}