{
  "type": "Feature",
  "properties": {
    "iso:country":"DE",
    "sg:address":"Gewerbestr. 32a",
    "sg:city":"Ainring",
    "sg:phone":"+49 8654",
    "sg:postcode":"83404",
    "sg:province":"Bayern",
    "wof:name":"Transporte Weber",
    "wof:placetype":"venue"
},
  "geometry": {"coordinates":[12.959672,47.818859],"type":"Point"}
}