{
  "type": "Feature",
  "properties": {
    "iso:country":"DE",
    "sg:address":"Schalldorf",
    "sg:city":"Postm\u00fcnster",
    "sg:phone":"+49 8561/8555",
    "sg:postcode":"84389",
    "sg:province":"Bayern",
    "wof:name":"M. Dureder",
    "wof:placetype":"venue"
},
  "geometry": {"coordinates":[12.89913,48.429054],"type":"Point"}
}