{
  "type": "Feature",
  "properties": {
    "iso:country":"DE",
    "sg:address":"Staffelder Str. 11 b",
    "sg:city":"B\u00f6rnicke",
    "sg:phone":"+49 33230/50269",
    "sg:postcode":"14641",
    "sg:province":"Brandenburg",
    "wof:name":"J\u00fcrgen Wolf & Sohn Gmbh",
    "wof:placetype":"venue"
},
  "geometry": {"coordinates":[12.9416370392,52.6904563904],"type":"Point"}
}