{
  "type": "Feature",
  "properties": {
    "iso:country":"DE",
    "sg:address":"Keltenstr. 18",
    "sg:city":"Sauerlach",
    "sg:phone":"+49 8104/887874",
    "sg:postcode":"82054",
    "sg:province":"Bayern",
    "wof:name":"Hans Beischl",
    "wof:placetype":"venue"
},
  "geometry": {"coordinates":[11.6392536163,47.969783783],"type":"Point"}
}