{
  "type": "Feature",
  "properties": {
    "iso:country":"DE",
    "sg:address":"Bahnhofstr 4",
    "sg:city":"B\u00fcrgel",
    "sg:phone":"+49 36692/22375",
    "sg:postcode":"07616",
    "sg:province":"Th\u00fcringen",
    "wof:name":"T\u00f6pferei Alt-b\u00fcrgeler Blau-wei\u00df Gmbh",
    "wof:placetype":"venue"
},
  "geometry": {"coordinates":[11.75895,50.944138],"type":"Point"}
}