{
  "type": "Feature",
  "properties": {
    "iso:country":"DE",
    "sg:address":"Horster Str. 404",
    "sg:city":"Bottrop",
    "sg:phone":"+49 2041/43327",
    "sg:postcode":"46240",
    "sg:province":"Nordrhein-Westfalen",
    "wof:name":"Elsbeth Bednarz",
    "wof:placetype":"venue"
},
  "geometry": {"coordinates":[6.9859099388,51.5362014771],"type":"Point"}
}