{
  "type": "Feature",
  "properties": {
    "iso:country":"DE",
    "sg:address":"Alter Markt",
    "sg:city":"Kiel",
    "sg:phone":"+49 431/974570",
    "sg:postcode":"24103",
    "sg:province":"Schleswig-Holstein",
    "wof:name":"Hof-apotheke Kiel",
    "wof:placetype":"venue"
},
  "geometry": {"coordinates":[10.139799,54.323029],"type":"Point"}
}