{
  "type": "Feature",
  "properties": {
    "iso:country":"DE",
    "sg:address":"Bilker Str. 16",
    "sg:city":"D\u00fcsseldorf",
    "sg:phone":"+49 211/324366",
    "sg:postcode":"40213",
    "sg:province":"Nordrhein-Westfalen",
    "wof:name":"P.-k. Wieczorek Antiquit\u00e4ten",
    "wof:placetype":"venue"
},
  "geometry": {"coordinates":[6.775735,51.227871],"type":"Point"}
}