{
  "type": "Feature",
  "properties": {
    "iso:country":"DE",
    "sg:address":"Bergstr 21",
    "sg:city":"Wiesensteig",
    "sg:phone":"+49 7335/2785",
    "sg:postcode":"73349",
    "sg:province":"Baden-W\u00fcrttemberg",
    "wof:name":"Alco",
    "wof:placetype":"venue"
},
  "geometry": {"coordinates":[9.629165,48.566303],"type":"Point"}
}