{
  "type": "Feature",
  "properties": {
    "iso:country":"DE",
    "sg:address":"Sondersh\u00e4user Str. 112",
    "sg:city":"Nohra",
    "sg:phone":"+49 36334/59770",
    "sg:postcode":"99735",
    "sg:province":"Th\u00fcringen",
    "wof:name":"Gerlinde Wenkel",
    "wof:placetype":"venue"
},
  "geometry": {"coordinates":[10.6991844177,51.4334106445],"type":"Point"}
}