{
  "type": "Feature",
  "properties": {
    "iso:country":"DE",
    "sg:address":"Kirchstr. 7",
    "sg:city":"Halblech",
    "sg:phone":"+49 8368/568",
    "sg:postcode":"87642",
    "sg:province":"Bayern",
    "wof:name":"Cafe Wiedemann",
    "wof:placetype":"venue"
},
  "geometry": {"coordinates":[10.8015270233,47.6250305176],"type":"Point"}
}