{
  "type": "Feature",
  "properties": {
    "iso:country":"DE",
    "sg:city":"M\u00fchlhausen",
    "sg:phone":"+49 4977/337885",
    "sg:postcode":"78259",
    "sg:province":"Baden-W\u00fcrttemberg",
    "wof:name":"Bezirkssparkasse Engen",
    "wof:placetype":"venue"
},
  "geometry": {"coordinates":[8.818665,47.807919],"type":"Point"}
}