{
  "type": "Feature",
  "properties": {
    "iso:country":"DE",
    "sg:address":"B\u00f6sperder Weg 6",
    "sg:city":"Menden",
    "sg:phone":"+49 2373/4055",
    "sg:postcode":"58708",
    "sg:province":"Nordrhein-Westfalen",
    "wof:name":"Ibb Ingenieurb\u00fcro B\u00f6hm Elektrovertriebs Gmbh",
    "wof:placetype":"venue"
},
  "geometry": {"coordinates":[7.7859687805,51.4613723755],"type":"Point"}
}