{
  "type": "Feature",
  "properties": {
    "iso:country":"DE",
    "sg:address":"Marienstr. 9",
    "sg:city":"Bad W\u00fcnnenberg",
    "sg:phone":"+49 2953/347",
    "sg:postcode":"33181",
    "sg:province":"Nordrhein-Westfalen",
    "wof:name":"Josef Coritzius Kg",
    "wof:placetype":"venue"
},
  "geometry": {"coordinates":[8.7424821854,51.5199928284],"type":"Point"}
}