{
  "type": "Feature",
  "properties": {
    "iso:country":"DE",
    "sg:address":"Professor-Hitzberger-Str. 5",
    "sg:city":"Garmisch-Partenkirchen",
    "sg:phone":"+49 8821/56121",
    "sg:postcode":"82467",
    "sg:province":"Bayern",
    "wof:name":"Josef L\u00f6dermann",
    "wof:placetype":"venue"
},
  "geometry": {"coordinates":[11.0982179642,47.5009346008],"type":"Point"}
}