{
  "type": "Feature",
  "properties": {
    "iso:country":"DE",
    "sg:address":"Andreas-Mau\u00dfner-Str. 45",
    "sg:city":"R\u00f6thenbach",
    "sg:phone":"+49 911/578645",
    "sg:postcode":"90552",
    "sg:province":"Bayern",
    "wof:name":"Kilian Nied",
    "wof:placetype":"venue"
},
  "geometry": {"coordinates":[11.2562503815,49.4928092957],"type":"Point"}
}