{
  "type": "Feature",
  "properties": {
    "iso:country":"DE",
    "sg:address":"Frauenlobstr. 86",
    "sg:city":"Frankfurt",
    "sg:postcode":"60487",
    "sg:province":"Hessen",
    "wof:name":"Ehs Bautr\u00e4ger Gmbh",
    "wof:placetype":"venue"
},
  "geometry": {"coordinates":[8.648069,50.131371],"type":"Point"}
}