{
  "type": "Feature",
  "properties": {
    "iso:country":"DE",
    "sg:address":"Tieberg 7",
    "sg:city":"Algermissen",
    "sg:phone":"+49 5126/96095",
    "sg:postcode":"31191",
    "sg:province":"Niedersachsen",
    "wof:name":"Restaurant Nanu",
    "wof:placetype":"venue"
},
  "geometry": {"coordinates":[9.9745502472,52.2548561096],"type":"Point"}
}