{
  "type": "Feature",
  "properties": {
    "iso:country":"DE",
    "sg:address":"Hansastr. 22",
    "sg:city":"Oberhausen",
    "sg:phone":"+49 4920/88360",
    "sg:postcode":"46049",
    "sg:province":"Nordrhein-Westfalen",
    "wof:name":"Heitmann Stahlhandel Gmbh & Co",
    "wof:placetype":"venue"
},
  "geometry": {"coordinates":[6.850563,51.4762],"type":"Point"}
}