{
  "type": "Feature",
  "properties": {
    "iso:country":"DE",
    "sg:address":"Karlstr. 35",
    "sg:city":"Friedrichshafen",
    "sg:phone":"+49 7541/70700",
    "sg:postcode":"88045",
    "sg:province":"Baden-W\u00fcrttemberg",
    "wof:name":"Redaktion \u00dcberlinger Zeitung",
    "wof:placetype":"venue"
},
  "geometry": {"coordinates":[9.4801559448,47.6497688293],"type":"Point"}
}