{
  "type": "Feature",
  "properties": {
    "iso:country":"DE",
    "sg:address":"M\u00fcnchner Str. 11",
    "sg:city":"Forstern",
    "sg:phone":"+49 8124/1721",
    "sg:postcode":"85659",
    "sg:province":"Bayern",
    "wof:name":"W. B\u00f6hm",
    "wof:placetype":"venue"
},
  "geometry": {"coordinates":[11.9748620987,48.1829376221],"type":"Point"}
}