{
  "type": "Feature",
  "properties": {
    "iso:country":"DE",
    "sg:address":"Zum Dornbachtal 17a",
    "sg:city":"Heidenrod",
    "sg:phone":"+49 6124/9182",
    "sg:postcode":"65321",
    "sg:province":"Hessen",
    "wof:name":"Scc Springen Klaus Weber",
    "wof:placetype":"venue"
},
  "geometry": {"coordinates":[7.9823098183,50.1428794861],"type":"Point"}
}