{
  "type": "Feature",
  "properties": {
    "iso:country":"DE",
    "sg:address":"Am Piekenbrocksbach 8p",
    "sg:city":"Bottrop",
    "sg:phone":"+49 2041/132020",
    "sg:postcode":"46238",
    "sg:province":"Nordrhein-Westfalen",
    "wof:name":"Kalff Gmbh & Co. Kg",
    "wof:placetype":"venue"
},
  "geometry": {"coordinates":[6.946113,51.513008],"type":"Point"}
}