{
  "type": "Feature",
  "properties": {
    "iso:country":"DE",
    "sg:address":"Brunnenstr. 5",
    "sg:city":"Obersinn",
    "sg:phone":"+49 9356/5314",
    "sg:postcode":"97791",
    "sg:province":"Bayern",
    "wof:name":"Helmut Ries",
    "wof:placetype":"venue"
},
  "geometry": {"coordinates":[9.613139,50.208611],"type":"Point"}
}