{
  "type": "Feature",
  "properties": {
    "iso:country":"DE",
    "sg:address":"Kobelweg 14",
    "sg:city":"Augsburg",
    "sg:phone":"+49 821/403050",
    "sg:postcode":"86156",
    "sg:province":"Bayern",
    "wof:name":"Kfz-sachverst\u00e4ndigenb\u00fcro Bodenberger Gmbh",
    "wof:placetype":"venue"
},
  "geometry": {"coordinates":[10.864334,48.384716],"type":"Point"}
}