{
  "type": "Feature",
  "properties": {
    "iso:country":"DE",
    "sg:address":"Ferdinand-Hoser-Str. 16",
    "sg:city":"Duisburg",
    "sg:phone":"+49 203/701136",
    "sg:postcode":"47249",
    "sg:province":"Nordrhein-Westfalen",
    "wof:name":"Petra Und R\u00fcdiger Wienand",
    "wof:placetype":"venue"
},
  "geometry": {"coordinates":[6.753387928,51.3850097656],"type":"Point"}
}