{
  "type": "Feature",
  "properties": {
    "iso:country":"DE",
    "sg:address":"Luitpoldstr. 64",
    "sg:city":"B\u00f6hl-Iggelheim",
    "sg:phone":"+49 6324/76663",
    "sg:postcode":"67459",
    "sg:province":"Rheinland-Pfalz",
    "wof:name":"Schreibwaren Titz Gmbh",
    "wof:placetype":"venue"
},
  "geometry": {"coordinates":[8.3121919632,49.3605880737],"type":"Point"}
}