{
  "type": "Feature",
  "properties": {
    "iso:country":"DE",
    "sg:address":"In der K\u00e4ufe 4",
    "sg:city":"Bad Arolsen",
    "sg:phone":"+49 5691/2626",
    "sg:postcode":"34454",
    "sg:province":"Hessen",
    "wof:name":"Karl Ashauer",
    "wof:placetype":"venue"
},
  "geometry": {"coordinates":[9.005511,51.388664],"type":"Point"}
}