{
  "type": "Feature",
  "properties": {
    "iso:country":"DE",
    "sg:address":"Ratzeburger Allee 160",
    "sg:city":"L\u00fcbeck",
    "sg:phone":"+49 451/5002860",
    "sg:postcode":"23562",
    "sg:province":"Schleswig-Holstein",
    "wof:name":"Klinisch-experimententeil Forschungseinrichtung",
    "wof:placetype":"venue"
},
  "geometry": {"coordinates":[10.708987236,53.8395729065],"type":"Point"}
}