{
  "type": "Feature",
  "properties": {
    "iso:country":"DE",
    "sg:address":"Kirchplatz 8",
    "sg:city":"Rothenburg",
    "sg:phone":"+49 9861/9700",
    "sg:postcode":"91541",
    "sg:province":"Bayern",
    "wof:name":"Hotel-reichsk\u00fcchenmeister Kleinschroth Und Niedner",
    "wof:placetype":"venue"
},
  "geometry": {"coordinates":[10.1788063049,49.3780021667],"type":"Point"}
}