{
  "type": "Feature",
  "properties": {
    "iso:country":"DE",
    "sg:address":"Danziger Str. 4",
    "sg:city":"Weilburg",
    "sg:phone":"+49 6471/923030",
    "sg:postcode":"35781",
    "sg:province":"Hessen",
    "wof:name":"Designworld Werbeagentur",
    "wof:placetype":"venue"
},
  "geometry": {"coordinates":[8.2832145691,50.4810562134],"type":"Point"}
}