{
  "type": "Feature",
  "properties": {
    "iso:country":"DE",
    "sg:address":"Hauptstr. 14",
    "sg:city":"Kissing",
    "sg:phone":"+49 8233/5660",
    "sg:postcode":"86438",
    "sg:province":"Bayern",
    "wof:name":"Michael Schuster",
    "wof:placetype":"venue"
},
  "geometry": {"coordinates":[10.988458,48.295742],"type":"Point"}
}