{
  "type": "Feature",
  "properties": {
    "iso:country":"DE",
    "sg:address":"H\u00e4ndelstr. 59",
    "sg:city":"Weinheim",
    "sg:phone":"+49 6201/186146",
    "sg:postcode":"69469",
    "sg:province":"Baden-W\u00fcrttemberg",
    "wof:name":"R. Guarnieri Finanzberater",
    "wof:placetype":"venue"
},
  "geometry": {"coordinates":[8.6553993225,49.5503578186],"type":"Point"}
}