{
  "type": "Feature",
  "properties": {
    "iso:country":"DE",
    "sg:address":"Im Waldring 58",
    "sg:city":"Wadern",
    "sg:phone":"+49 6874/6006",
    "sg:postcode":"66687",
    "sg:province":"Saarland",
    "wof:name":"Wolfgang Kl\u00f6ckner Masseur",
    "wof:placetype":"venue"
},
  "geometry": {"coordinates":[6.833864,49.49305],"type":"Point"}
}