{
  "type": "Feature",
  "properties": {
    "iso:country":"DE",
    "sg:address":"Koepfle 30",
    "sg:city":"Weisweil",
    "sg:postcode":"79367",
    "sg:province":"Baden-W\u00fcrttemberg",
    "wof:name":"Schanzlin Traktoren Und Maschinen Gmbh 79367 Weisweil",
    "wof:placetype":"venue"
},
  "geometry": {"coordinates":[7.6731648445,48.2031784058],"type":"Point"}
}