{
  "type": "Feature",
  "properties": {
    "iso:country":"DE",
    "sg:address":"Rheinstr. 34",
    "sg:city":"Bad Bellingen",
    "sg:phone":"+49 7635/723",
    "sg:postcode":"79415",
    "sg:province":"Baden-W\u00fcrttemberg",
    "wof:name":"Hans-joachim Gugelmeier",
    "wof:placetype":"venue"
},
  "geometry": {"coordinates":[7.556147,47.730473],"type":"Point"}
}