{
  "type": "Feature",
  "properties": {
    "iso:country":"DE",
    "sg:address":"Leininger Str. 22",
    "sg:city":"Gr\u00fcnstadt",
    "sg:phone":"+49 6359/84559",
    "sg:postcode":"67269",
    "sg:province":"Rheinland-Pfalz",
    "wof:name":"Fluch-gaul Weinanbau",
    "wof:placetype":"venue"
},
  "geometry": {"coordinates":[8.1519069672,49.5454216003],"type":"Point"}
}