{
  "type": "Feature",
  "properties": {
    "iso:country":"DE",
    "sg:address":"Goldsteinstr. 127",
    "sg:city":"Frankfurt",
    "sg:phone":"+49 69/6664668",
    "sg:postcode":"60528",
    "sg:province":"Hessen",
    "wof:name":"Reiseb\u00fcro Han",
    "wof:placetype":"venue"
},
  "geometry": {"coordinates":[8.6367883682,50.0846786499],"type":"Point"}
}