{
  "type": "Feature",
  "properties": {
    "iso:country":"DE",
    "sg:address":"Hauptstr. 47",
    "sg:city":"Seibersbach",
    "sg:phone":"+49 6724/3578",
    "sg:postcode":"55444",
    "sg:province":"Rheinland-Pfalz",
    "wof:name":"Werner Hochh\u00e4user",
    "wof:placetype":"venue"
},
  "geometry": {"coordinates":[7.722368,49.960777],"type":"Point"}
}