{
  "type": "Feature",
  "properties": {
    "iso:country":"DE",
    "sg:address":"Feldbergstr. 92",
    "sg:city":"Sindelfingen",
    "sg:phone":"+49 7031/802393",
    "sg:postcode":"71067",
    "sg:province":"Baden-W\u00fcrttemberg",
    "wof:name":"Sieglinde Wolfrum-m\u00fcller",
    "wof:placetype":"venue"
},
  "geometry": {"coordinates":[9.005967,48.725258],"type":"Point"}
}