{
  "type": "Feature",
  "properties": {
    "iso:country":"DE",
    "sg:address":"Wallstr. 9",
    "sg:city":"Waldshut-Tiengen",
    "sg:phone":"+49 7751/7788",
    "sg:postcode":"79761",
    "sg:province":"Baden-W\u00fcrttemberg",
    "wof:name":"Antonia Faustini Diva",
    "wof:placetype":"venue"
},
  "geometry": {"coordinates":[8.214455,47.623707],"type":"Point"}
}