{
  "type": "Feature",
  "properties": {
    "iso:country":"DE",
    "sg:address":"Landgrabenstr.",
    "sg:city":"N\u00fcrnberg",
    "sg:phone":"+49 911/428474",
    "sg:postcode":"90443",
    "sg:province":"Bayern",
    "wof:name":"Dos-edv-beratung Gmbh",
    "wof:placetype":"venue"
},
  "geometry": {"coordinates":[11.065290451,49.4400482178],"type":"Point"}
}