{
  "type": "Feature",
  "properties": {
    "iso:country":"DE",
    "sg:address":"Hauptstr. 45",
    "sg:city":"Bach",
    "sg:phone":"+49 9403/962791",
    "sg:postcode":"93090",
    "sg:province":"Bayern",
    "wof:name":"B\u00e4ckerei Schifferl Gmbh",
    "wof:placetype":"venue"
},
  "geometry": {"coordinates":[12.304106,49.020973],"type":"Point"}
}