{
  "type": "Feature",
  "properties": {
    "iso:country":"DE",
    "sg:address":"Droote 20",
    "sg:city":"Dortmund",
    "sg:phone":"+49 231/232838",
    "sg:postcode":"44328",
    "sg:province":"Nordrhein-Westfalen",
    "wof:name":"Videoplanet Verwaltungs Gmbh",
    "wof:placetype":"venue"
},
  "geometry": {"coordinates":[7.5401391983,51.5572395325],"type":"Point"}
}