{
  "type": "Feature",
  "properties": {
    "iso:country":"DE",
    "sg:address":"Ruhrtalstr. 23",
    "sg:city":"D\u00fcsseldorf",
    "sg:phone":"+49 211/7334124",
    "sg:postcode":"40233",
    "sg:province":"Nordrhein-Westfalen",
    "wof:name":"T. Melchior",
    "wof:placetype":"venue"
},
  "geometry": {"coordinates":[6.811455,51.22139],"type":"Point"}
}