{
  "type": "Feature",
  "properties": {
    "iso:country":"DE",
    "sg:address":"Fr\u00fchme\u00dfstr. 5",
    "sg:city":"Thannhausen",
    "sg:phone":"+49 8281/2033",
    "sg:postcode":"86470",
    "sg:province":"Bayern",
    "wof:name":"Blisle & Zepf",
    "wof:placetype":"venue"
},
  "geometry": {"coordinates":[10.4680738449,48.2824020386],"type":"Point"}
}