{
  "type": "Feature",
  "properties": {
    "iso:country":"DE",
    "sg:address":"Hohe Feldstr. 1",
    "sg:city":"Eschershausen",
    "sg:phone":"+49 5534/2287",
    "sg:postcode":"37632",
    "sg:province":"Niedersachsen",
    "wof:name":"Karl Bartzsch Elektromeister",
    "wof:placetype":"venue"
},
  "geometry": {"coordinates":[9.632718,51.93491],"type":"Point"}
}