{
  "type": "Feature",
  "properties": {
    "iso:country":"DE",
    "sg:address":"Am Bahnhof 5",
    "sg:city":"Wolfsburg",
    "sg:phone":"+49 5363/99123",
    "sg:postcode":"38448",
    "sg:province":"Niedersachsen",
    "wof:name":"Robert Eckhardt Gmbh & Co. Kg",
    "wof:placetype":"venue"
},
  "geometry": {"coordinates":[10.850225,52.431297],"type":"Point"}
}