{
  "type": "Feature",
  "properties": {
    "iso:country":"DE",
    "sg:address":"Alsterdorfer Str. 214",
    "sg:city":"Hamburg",
    "sg:phone":"+49 40/515424",
    "sg:postcode":"22297",
    "sg:province":"Hamburg",
    "wof:name":"E. Herm. Schwarz & Co.",
    "wof:placetype":"venue"
},
  "geometry": {"coordinates":[10.001744,53.606148],"type":"Point"}
}