{
  "type": "Feature",
  "properties": {
    "iso:country":"DE",
    "sg:address":"Frohnen Weg 5",
    "sg:city":"Meschede",
    "sg:phone":"+49 2903/6048",
    "sg:postcode":"59872",
    "sg:province":"Nordrhein-Westfalen",
    "wof:name":"Klaus Kathol",
    "wof:placetype":"venue"
},
  "geometry": {"coordinates":[8.16739,51.382298],"type":"Point"}
}