{
  "type": "Feature",
  "properties": {
    "iso:country":"DE",
    "sg:address":"Friedrichstr. 171",
    "sg:city":"Mannheim",
    "sg:phone":"+49 621/856000",
    "sg:postcode":"68199",
    "sg:province":"Baden-W\u00fcrttemberg",
    "wof:name":"Klaus Mierswa Rechtsanwalt",
    "wof:placetype":"venue"
},
  "geometry": {"coordinates":[8.4793920517,49.451877594],"type":"Point"}
}