{
  "type": "Feature",
  "properties": {
    "iso:country":"DE",
    "sg:address":"Bahnhofstr. 25",
    "sg:city":"Ortrand",
    "sg:phone":"+49 35755/6112",
    "sg:postcode":"01990",
    "sg:province":"Brandenburg",
    "wof:name":"Frank Sch\u00fctze",
    "wof:placetype":"venue"
},
  "geometry": {"coordinates":[13.760029,51.374992],"type":"Point"}
}