{
  "type": "Feature",
  "properties": {
    "iso:country":"DE",
    "sg:address":"Otto-Brenner-Str. 81",
    "sg:city":"Bielefeld",
    "sg:phone":"+49 521/2704338",
    "sg:postcode":"33607",
    "sg:province":"Nordrhein-Westfalen",
    "wof:name":"Christos Restaurant",
    "wof:placetype":"venue"
},
  "geometry": {"coordinates":[8.5665550232,52.0171394348],"type":"Point"}
}