{
  "type": "Feature",
  "properties": {
    "iso:country":"DE",
    "sg:address":"Am Fr\u00fchlingsberg 8",
    "sg:city":"Sch\u00f6nbach",
    "sg:phone":"+49 35872/33241",
    "sg:postcode":"02708",
    "sg:province":"Sachsen",
    "wof:name":"Reiner Mei\u00dfner",
    "wof:placetype":"venue"
},
  "geometry": {"coordinates":[14.5782012939,51.0617485046],"type":"Point"}
}