{
  "type": "Feature",
  "properties": {
    "iso:country":"DE",
    "sg:address":"Kaiserswerther Str. 115",
    "sg:city":"D\u00fcsseldorf",
    "sg:phone":"+49 211/452728",
    "sg:postcode":"40474",
    "sg:province":"Nordrhein-Westfalen",
    "wof:name":"Claus Siebel Ingenieur",
    "wof:placetype":"venue"
},
  "geometry": {"coordinates":[6.7717428207,51.2439117432],"type":"Point"}
}