{
  "type": "Feature",
  "properties": {
    "iso:country":"DE",
    "sg:address":"Erbacher Str. 5",
    "sg:city":"Hilgenroth",
    "sg:phone":"+49 2682/4443",
    "sg:postcode":"57612",
    "sg:province":"Rheinland-Pfalz",
    "wof:name":"Karl Hermann Link",
    "wof:placetype":"venue"
},
  "geometry": {"coordinates":[7.6521658897,50.735080719],"type":"Point"}
}