{
  "type": "Feature",
  "properties": {
    "iso:country":"DE",
    "sg:address":"Mergelgrund 6",
    "sg:city":"Hamburg",
    "sg:phone":"+49 40/6019446",
    "sg:postcode":"22393",
    "sg:province":"Hamburg",
    "wof:name":"Ewald Mertke",
    "wof:placetype":"venue"
},
  "geometry": {"coordinates":[10.1210193634,53.6564903259],"type":"Point"}
}