{
  "type": "Feature",
  "properties": {
    "iso:country":"DE",
    "sg:address":"Dieselstr. 45",
    "sg:city":"Gersthofen",
    "sg:postcode":"86368",
    "sg:province":"Bayern",
    "wof:name":"Holzwelt Gersthofen Ohg",
    "wof:placetype":"venue"
},
  "geometry": {"coordinates":[10.8639831543,48.4354972839],"type":"Point"}
}