{
  "type": "Feature",
  "properties": {
    "iso:country":"DE",
    "sg:address":"Bergstr. 3",
    "sg:city":"Eching",
    "sg:phone":"+49 8133/92530",
    "sg:postcode":"85386",
    "sg:province":"Bayern",
    "wof:name":"Adolf Prinzbach",
    "wof:placetype":"venue"
},
  "geometry": {"coordinates":[11.604113,48.319115],"type":"Point"}
}