{
  "type": "Feature",
  "properties": {
    "iso:country":"DE",
    "sg:address":"Hafenstr. 26",
    "sg:city":"Barth",
    "sg:phone":"+49 38231/2782",
    "sg:postcode":"18356",
    "sg:province":"Mecklenburg-Vorpommern",
    "wof:name":"Club",
    "wof:placetype":"venue"
},
  "geometry": {"coordinates":[12.7227897644,54.3701782227],"type":"Point"}
}