{
  "type": "Feature",
  "properties": {
    "iso:country":"DE",
    "sg:address":"Zum Hagelkreuz 30",
    "sg:city":"Eschweiler",
    "sg:phone":"+49 2403/53651",
    "sg:postcode":"52249",
    "sg:province":"Nordrhein-Westfalen",
    "wof:name":"Ignaz Freialdenhoven",
    "wof:placetype":"venue"
},
  "geometry": {"coordinates":[6.30174,50.845451],"type":"Point"}
}