{
  "type": "Feature",
  "properties": {
    "iso:country":"DE",
    "sg:address":"Hauptstr. 54",
    "sg:city":"Sassnitz",
    "sg:phone":"+49 38392/22574",
    "sg:postcode":"18546",
    "sg:province":"Mecklenburg-Vorpommern",
    "wof:name":"Otto Peters",
    "wof:placetype":"venue"
},
  "geometry": {"coordinates":[13.646689415,54.5193061829],"type":"Point"}
}