{
  "type": "Feature",
  "properties": {
    "iso:country":"DE",
    "sg:address":"W\u00fcrzburger Str. 476",
    "sg:city":"F\u00fcrth",
    "sg:phone":"+49 911/751140",
    "sg:postcode":"90768",
    "sg:province":"Bayern",
    "wof:name":"Goldene Krone",
    "wof:placetype":"venue"
},
  "geometry": {"coordinates":[10.9446601868,49.4849052429],"type":"Point"}
}