{
  "type": "Feature",
  "properties": {
    "iso:country":"DE",
    "sg:address":"Chopinstr. 18",
    "sg:city":"Leipzig",
    "sg:phone":"+49 341/9614512",
    "sg:postcode":"04103",
    "sg:province":"Sachsen",
    "wof:name":"Iq Steuerberatungs Gmbh",
    "wof:placetype":"venue"
},
  "geometry": {"coordinates":[12.3903274536,51.3432273865],"type":"Point"}
}