{
  "type": "Feature",
  "properties": {
    "iso:country":"DE",
    "sg:address":"Herrngasse 4",
    "sg:city":"Schalkau",
    "sg:phone":"+49 36766/20310",
    "sg:postcode":"96528",
    "sg:province":"Th\u00fcringen",
    "wof:name":"Gerhard Langguth",
    "wof:placetype":"venue"
},
  "geometry": {"coordinates":[11.0054073334,50.3943214417],"type":"Point"}
}