{
  "type": "Feature",
  "properties": {
    "iso:country":"DE",
    "sg:address":"Weitzmannstr. 45",
    "sg:city":"Munderkingen",
    "sg:phone":"+49 7393/1669",
    "sg:postcode":"89597",
    "sg:province":"Baden-W\u00fcrttemberg",
    "wof:name":"G\u00fcnter Vollmer",
    "wof:placetype":"venue"
},
  "geometry": {"coordinates":[9.645261,48.234909],"type":"Point"}
}