{
  "type": "Feature",
  "properties": {
    "iso:country":"DE",
    "sg:address":"Breesener Str.",
    "sg:city":"Langsdorf",
    "sg:phone":"+49 38320/47971",
    "sg:postcode":"18334",
    "sg:province":"Mecklenburg-Vorpommern",
    "wof:name":"Kieswerk Langsdorf Gmbh",
    "wof:placetype":"venue"
},
  "geometry": {"coordinates":[12.7219953537,54.0784416199],"type":"Point"}
}