{
  "type": "Feature",
  "properties": {
    "iso:country":"DE",
    "sg:address":"Aufse\u00dfplatz 18",
    "sg:city":"N\u00fcrnberg",
    "sg:phone":"+49 911/449077",
    "sg:postcode":"90459",
    "sg:province":"Bayern",
    "wof:name":"Der Niederndorf Beck",
    "wof:placetype":"venue"
},
  "geometry": {"coordinates":[11.079853,49.440887],"type":"Point"}
}