{
  "type": "Feature",
  "properties": {
    "iso:country":"DE",
    "sg:address":"Lange Str. 45",
    "sg:city":"Wunstorf",
    "sg:phone":"+49 5031/3077",
    "sg:postcode":"31515",
    "sg:province":"Niedersachsen",
    "wof:name":"Pallak",
    "wof:placetype":"venue"
},
  "geometry": {"coordinates":[9.4244785309,52.425453186],"type":"Point"}
}