{
  "type": "Feature",
  "properties": {
    "iso:country":"DE",
    "sg:address":"Menninger Str. 1",
    "sg:city":"Polling",
    "sg:phone":"+49 8631/681",
    "sg:postcode":"84570",
    "sg:province":"Bayern",
    "wof:name":"Allg\u00e4uer Alpenmilch Ag Werk Weiding",
    "wof:placetype":"venue"
},
  "geometry": {"coordinates":[12.580994606,48.2362785339],"type":"Point"}
}