{
  "type": "Feature",
  "properties": {
    "iso:country":"DE",
    "sg:address":"Ludwigstr. 28",
    "sg:city":"Bischofsheim",
    "sg:phone":"+49 9772/320",
    "sg:postcode":"97653",
    "sg:province":"Bayern",
    "wof:name":"Restaurant Adler",
    "wof:placetype":"venue"
},
  "geometry": {"coordinates":[10.0102338791,50.4006271362],"type":"Point"}
}