{
  "type": "Feature",
  "properties": {
    "iso:country":"DE",
    "sg:address":"G\u00fcterstra\u00dfe 11",
    "sg:city":"Pforzheim",
    "sg:phone":"+49 72313222534636",
    "sg:postcode":"75177",
    "sg:province":"Baden-W\u00fcrttemberg",
    "wof:name":"G\u00fcnther W. Busse Gmbh",
    "wof:placetype":"venue"
},
  "geometry": {"coordinates":[8.6963596344,48.8948326111],"type":"Point"}
}