{
  "type": "Feature",
  "properties": {
    "iso:country":"DE",
    "sg:address":"Wasserhorst 2",
    "sg:city":"Bremen",
    "sg:phone":"+49 421/640738",
    "sg:postcode":"28719",
    "sg:province":"Bremen",
    "wof:name":"Diedrich Garbade",
    "wof:placetype":"venue"
},
  "geometry": {"coordinates":[8.741469,53.163605],"type":"Point"}
}