{
  "type": "Feature",
  "properties": {
    "iso:country":"DE",
    "sg:address":"Hauptstr. 27",
    "sg:city":"Leisel",
    "sg:phone":"+49 6787/524",
    "sg:postcode":"55767",
    "sg:province":"Rheinland-Pfalz",
    "wof:name":"Ev. Pfarramt Leisel",
    "wof:placetype":"venue"
},
  "geometry": {"coordinates":[7.2017698288,49.7191009521],"type":"Point"}
}