{
  "type": "Feature",
  "properties": {
    "iso:country":"DE",
    "sg:address":"Sch\u00fctzenstr. 3",
    "sg:city":"Bergheim",
    "sg:phone":"+49 2271/47010",
    "sg:postcode":"50126",
    "sg:province":"Nordrhein-Westfalen",
    "wof:name":"Erftland Kommunale Wohnungsgesellschaft Mbh",
    "wof:placetype":"venue"
},
  "geometry": {"coordinates":[6.642675,50.954994],"type":"Point"}
}