{
  "type": "Feature",
  "properties": {
    "iso:country":"DE",
    "sg:address":"Am Anger 11",
    "sg:city":"Essenbach",
    "sg:phone":"+49 8703/583",
    "sg:postcode":"84051",
    "sg:province":"Bayern",
    "wof:name":"H. Kramlofsky",
    "wof:placetype":"venue"
},
  "geometry": {"coordinates":[12.2070579529,48.5931167603],"type":"Point"}
}