{
  "type": "Feature",
  "properties": {
    "iso:country":"DE",
    "sg:address":"Berliner Chaussee 22",
    "sg:city":"Genthin",
    "sg:phone":"+49 3933/3106",
    "sg:postcode":"39307",
    "sg:province":"Sachsen-Anhalt",
    "wof:name":"Toom Baumarkt",
    "wof:placetype":"venue"
},
  "geometry": {"coordinates":[12.1422643661,52.416683197],"type":"Point"}
}