{
  "type": "Feature",
  "properties": {
    "iso:country":"DE",
    "sg:address":"Spitalhofweg 3",
    "sg:city":"Isny",
    "sg:phone":"+49 7562/4519",
    "sg:postcode":"88316",
    "sg:province":"Baden-W\u00fcrttemberg",
    "wof:name":"Epp Gmbh",
    "wof:placetype":"venue"
},
  "geometry": {"coordinates":[10.032592,47.688858],"type":"Point"}
}