{
  "type": "Feature",
  "properties": {
    "iso:country":"DE",
    "sg:address":"Rebenreute 88",
    "sg:city":"Stuttgart",
    "sg:phone":"+49 711/609784",
    "sg:postcode":"70199",
    "sg:province":"Baden-W\u00fcrttemberg",
    "wof:name":"Ulrich Wondratschek Architekt",
    "wof:placetype":"venue"
},
  "geometry": {"coordinates":[9.14853,48.762218],"type":"Point"}
}