{
  "type": "Feature",
  "properties": {
    "iso:country":"DE",
    "sg:address":"S\u00fclldorfer M\u00fchlenweg 37 a",
    "sg:city":"Hamburg",
    "sg:phone":"+49 40/874798",
    "sg:postcode":"22589",
    "sg:province":"Hamburg",
    "wof:name":"Gerd-wilhelm Bosse Architekt",
    "wof:placetype":"venue"
},
  "geometry": {"coordinates":[9.792757,53.577568],"type":"Point"}
}