{
  "type": "Feature",
  "properties": {
    "iso:country":"DE",
    "sg:address":"Alte Landstr. 100",
    "sg:city":"Wegberg",
    "sg:phone":"+49 2434/1051",
    "sg:postcode":"41844",
    "sg:province":"Nordrhein-Westfalen",
    "wof:name":"Heinrich Kohlen",
    "wof:placetype":"venue"
},
  "geometry": {"coordinates":[6.2284607887,51.1383323669],"type":"Point"}
}