{
  "type": "Feature",
  "properties": {
    "iso:country":"DE",
    "sg:address":"Siedlung 16",
    "sg:city":"Pretzschendorf",
    "sg:phone":"+49 35058/41202",
    "sg:postcode":"01774",
    "sg:province":"Sachsen",
    "wof:name":"Werner Berndt",
    "wof:placetype":"venue"
},
  "geometry": {"coordinates":[13.528076,50.879368],"type":"Point"}
}