{
  "type": "Feature",
  "properties": {
    "iso:country":"DE",
    "sg:address":"Am Wieneb\u00fctteler Weg 14",
    "sg:city":"L\u00fcneburg",
    "sg:phone":"+49 4131/62996",
    "sg:postcode":"21339",
    "sg:province":"Niedersachsen",
    "wof:name":"Tennispark Hans-j\u00fcrgen Pfohe",
    "wof:placetype":"venue"
},
  "geometry": {"coordinates":[10.3881931305,53.2546882629],"type":"Point"}
}