{
  "type": "Feature",
  "properties": {
    "iso:country":"DE",
    "sg:address":"Altenburger Str. 26",
    "sg:city":"Mosel",
    "sg:phone":"+49 37604/2886",
    "sg:postcode":"08129",
    "wof:name":"Hoch- Und Tiefbau Gmbh",
    "wof:placetype":"venue"
},
  "geometry": {"coordinates":[12.47814,50.780029],"type":"Point"}
}