{
  "type": "Feature",
  "properties": {
    "iso:country":"DE",
    "sg:address":"Am Bruchsee 1",
    "sg:city":"Heppenheim",
    "sg:phone":"+49 4962/529600",
    "sg:postcode":"64646",
    "sg:province":"Hessen",
    "wof:name":"Hotel Am Bruchsee",
    "wof:placetype":"venue"
},
  "geometry": {"coordinates":[8.627403,49.62973],"type":"Point"}
}