{
  "type": "Feature",
  "properties": {
    "iso:country":"DE",
    "sg:address":"Eintrachtstr. 58",
    "sg:city":"Bocholt",
    "sg:phone":"+49 2871/38159",
    "sg:postcode":"46397",
    "sg:province":"Nordrhein-Westfalen",
    "wof:name":"Dea Tankstelle",
    "wof:placetype":"venue"
},
  "geometry": {"coordinates":[6.6221289635,51.8433456421],"type":"Point"}
}