{
  "type": "Feature",
  "properties": {
    "iso:country":"DE",
    "sg:address":"An den Rhing\u00e4rten 15",
    "sg:city":"Rheinsberg",
    "sg:phone":"+49 33931/2619",
    "sg:postcode":"16831",
    "sg:province":"Brandenburg",
    "wof:name":"Elektro-zillmann",
    "wof:placetype":"venue"
},
  "geometry": {"coordinates":[12.89511,53.092827],"type":"Point"}
}