{
  "type": "Feature",
  "properties": {
    "iso:country":"DE",
    "sg:address":"Hochrieth 1",
    "sg:city":"Uder",
    "sg:phone":"+49 36083/40411",
    "sg:postcode":"37318",
    "sg:province":"Th\u00fcringen",
    "wof:name":"Hermann Fischer",
    "wof:placetype":"venue"
},
  "geometry": {"coordinates":[10.070318,51.362434],"type":"Point"}
}