{
  "type": "Feature",
  "properties": {
    "iso:country":"DE",
    "sg:address":"Prielstr. 17",
    "sg:city":"Owingen",
    "sg:phone":"+49 7551/62496",
    "sg:postcode":"88696",
    "sg:province":"Baden-W\u00fcrttemberg",
    "wof:name":"Peter Manner",
    "wof:placetype":"venue"
},
  "geometry": {"coordinates":[9.1706466675,47.8066711426],"type":"Point"}
}