{
  "type": "Feature",
  "properties": {
    "iso:country":"DE",
    "sg:address":"Uhlandstr. 38",
    "sg:city":"Hamburg",
    "sg:phone":"+49 40/2276277",
    "sg:postcode":"22087",
    "sg:province":"Hamburg",
    "wof:name":"Zielke Handelsges. Mbh",
    "wof:placetype":"venue"
},
  "geometry": {"coordinates":[10.0287837982,53.5649414062],"type":"Point"}
}