{
  "type": "Feature",
  "properties": {
    "iso:country":"DE",
    "sg:address":"Marktplatz 13",
    "sg:city":"Heideck",
    "sg:phone":"+49 9177/1305",
    "sg:postcode":"91180",
    "sg:province":"Bayern",
    "wof:name":"Karin Halbig Rechtsanw\u00e4ltin",
    "wof:placetype":"venue"
},
  "geometry": {"coordinates":[11.125910759,49.1328697205],"type":"Point"}
}