{
  "type": "Feature",
  "properties": {
    "iso:country":"DE",
    "sg:address":"Dorfstrasse 8a",
    "sg:city":"Gimbke",
    "sg:postcode":"48268",
    "sg:province":"Nordrhein-Westfalen",
    "wof:name":"Britannia-steinfiguren",
    "wof:placetype":"venue"
},
  "geometry": {"coordinates":[-83.047791,42.331619],"type":"Point"}
}