{
  "type": "Feature",
  "properties": {
    "iso:country":"DE",
    "sg:address":"St\u00e4mmes\u00e4ckerstr. 112",
    "sg:city":"Reutlingen",
    "sg:phone":"+49 7121/290535",
    "sg:postcode":"72762",
    "sg:province":"Baden-W\u00fcrttemberg",
    "wof:name":"Rose Bader",
    "wof:placetype":"venue"
},
  "geometry": {"coordinates":[9.2088747025,48.4758110046],"type":"Point"}
}