{
  "type": "Feature",
  "properties": {
    "iso:country":"DE",
    "sg:address":"Neukircher Str 71",
    "sg:city":"Wilthen",
    "sg:phone":"+49 3592/33121",
    "sg:postcode":"02681",
    "sg:province":"Sachsen",
    "wof:name":"Tischlerei Schuster",
    "wof:placetype":"venue"
},
  "geometry": {"coordinates":[14.374535,51.097637],"type":"Point"}
}