{
  "type": "Feature",
  "properties": {
    "iso:country":"DE",
    "sg:address":"Erbsenwinkelstr. 10",
    "sg:city":"H\u00f6sbach",
    "sg:postcode":"63768",
    "sg:province":"Bayern",
    "wof:name":"Sr Objekt Idee E. K.",
    "wof:placetype":"venue"
},
  "geometry": {"coordinates":[9.2186489105,50.001953125],"type":"Point"}
}