{
  "type": "Feature",
  "properties": {
    "iso:country":"DE",
    "sg:address":"Hindenburgallee 19",
    "sg:city":"Munster",
    "sg:phone":"+49 5192/98440",
    "sg:postcode":"29633",
    "sg:province":"Niedersachsen",
    "wof:name":"Steuerberatungsges. Dransfeld Und Partner",
    "wof:placetype":"venue"
},
  "geometry": {"coordinates":[10.0865268707,52.99168396],"type":"Point"}
}