{
  "type": "Feature",
  "properties": {
    "iso:country":"DE",
    "sg:address":"Industriestr. 4a",
    "sg:city":"Parkstetten",
    "sg:phone":"+49 9421/80744",
    "sg:postcode":"94365",
    "sg:province":"Bayern",
    "wof:name":"Arnold Zimmerei Bedachung Innenausbau Gmbh",
    "wof:placetype":"venue"
},
  "geometry": {"coordinates":[12.6004314423,48.9106712341],"type":"Point"}
}