{
  "type": "Feature",
  "properties": {
    "iso:country":"DE",
    "sg:address":"Otto-Wels-Str. 12a",
    "sg:city":"Eschweiler",
    "sg:phone":"+49 2403/37859",
    "sg:postcode":"52249",
    "sg:province":"Nordrhein-Westfalen",
    "wof:name":"Christian Lewandowski",
    "wof:placetype":"venue"
},
  "geometry": {"coordinates":[6.271063,50.81871],"type":"Point"}
}