{
  "type": "Feature",
  "properties": {
    "iso:country":"DE",
    "sg:address":"Pfarrstr. 14",
    "sg:city":"Wernigerode",
    "sg:postcode":"38855",
    "sg:province":"Sachsen-Anhalt",
    "wof:name":"Die M\u00f6belscheune Gmbh",
    "wof:placetype":"venue"
},
  "geometry": {"coordinates":[10.789727211,51.8364639282],"type":"Point"}
}