{
  "type": "Feature",
  "properties": {
    "iso:country":"DE",
    "sg:address":"De-la-Chevallerie-Str. 40",
    "sg:city":"Gelsenkirchen",
    "sg:phone":"+49 209/370455",
    "sg:postcode":"45894",
    "sg:province":"Nordrhein-Westfalen",
    "wof:name":"Kodiak Trekking Gahlen Und Jatzkowski Gbr",
    "wof:placetype":"venue"
},
  "geometry": {"coordinates":[7.054781,51.580238],"type":"Point"}
}