{
  "type": "Feature",
  "properties": {
    "iso:country":"DE",
    "sg:address":"Heinrothstr. 18",
    "sg:city":"Leipzig",
    "sg:postcode":"04155",
    "sg:province":"Sachsen",
    "wof:name":"Einzelunternehmung C. S. A. Convention Security",
    "wof:placetype":"venue"
},
  "geometry": {"coordinates":[12.353218,51.361271],"type":"Point"}
}