{
  "type": "Feature",
  "properties": {
    "iso:country":"DE",
    "sg:address":"Hellerwaldstr. 3",
    "sg:city":"Boppard",
    "sg:phone":"+49 6742/87220",
    "sg:postcode":"56154",
    "sg:province":"Rheinland-Pfalz",
    "wof:name":"Gav Gmbh Schachtabdeckungen",
    "wof:placetype":"venue"
},
  "geometry": {"coordinates":[7.563079,50.20739],"type":"Point"}
}