{
  "type": "Feature",
  "properties": {
    "iso:country":"DE",
    "sg:address":"Angelh\u00e4user Str. 71",
    "sg:city":"Arnstadt",
    "sg:postcode":"99310",
    "sg:province":"Th\u00fcringen",
    "wof:name":"Imo-service Gmbh",
    "wof:placetype":"venue"
},
  "geometry": {"coordinates":[10.9696512222,50.8250961304],"type":"Point"}
}