{
  "type": "Feature",
  "properties": {
    "iso:country":"DE",
    "sg:address":"Emmersbach 2",
    "sg:city":"Biberach",
    "sg:phone":"+49 7835/7175",
    "sg:postcode":"77781",
    "sg:province":"Baden-W\u00fcrttemberg",
    "wof:name":"Konrad Beck",
    "wof:placetype":"venue"
},
  "geometry": {"coordinates":[8.011215,48.334873],"type":"Point"}
}