{
  "type": "Feature",
  "properties": {
    "iso:country":"DE",
    "sg:address":"Zeppelinstr. 102",
    "sg:city":"Abtsgm\u00fcnd",
    "sg:phone":"+49 7366/4532",
    "sg:postcode":"73453",
    "sg:province":"Baden-W\u00fcrttemberg",
    "wof:name":"Manfred Schneider Gmbh",
    "wof:placetype":"venue"
},
  "geometry": {"coordinates":[9.9949522018,48.8866195679],"type":"Point"}
}