{
  "type": "Feature",
  "properties": {
    "iso:country":"DE",
    "sg:address":"Friedrichstr. 14",
    "sg:city":"Norderney",
    "sg:phone":"+49 4932/83706",
    "sg:postcode":"26548",
    "sg:province":"Niedersachsen",
    "wof:name":"Gastst\u00e4tte K\u00f6-pi",
    "wof:placetype":"venue"
},
  "geometry": {"coordinates":[7.1431450844,53.7080383301],"type":"Point"}
}