{
  "type": "Feature",
  "properties": {
    "iso:country":"DE",
    "sg:address":"Johannnastr.24",
    "sg:city":"Berlin",
    "sg:phone":"+49 351/95423",
    "sg:postcode":"13581",
    "sg:province":"Berlin",
    "wof:name":"Dampferfahrten In Und Um Berlin",
    "wof:placetype":"venue"
},
  "geometry": {"coordinates":[13.179417,52.527866],"type":"Point"}
}