{
  "type": "Feature",
  "properties": {
    "iso:country":"DE",
    "sg:address":"Fleischstr. 32",
    "sg:city":"Trier",
    "sg:phone":"+49 651/18928",
    "sg:postcode":"54290",
    "sg:province":"Rheinland-Pfalz",
    "wof:name":"Disc Service Gesellschaft F\u00fcr Digitale Medienproduktion Mbh",
    "wof:placetype":"venue"
},
  "geometry": {"coordinates":[6.637351,49.754452],"type":"Point"}
}