{
  "type": "Feature",
  "properties": {
    "iso:country":"DE",
    "sg:address":"Demminer Str. 46",
    "sg:city":"Neubrandenburg",
    "sg:postcode":"17034",
    "sg:province":"Mecklenburg-Vorpommern",
    "wof:name":"Institut F\u00fcr Veterin\u00e4rwesen",
    "wof:placetype":"venue"
},
  "geometry": {"coordinates":[13.269116,53.569851],"type":"Point"}
}