{
  "type": "Feature",
  "properties": {
    "iso:country":"DE",
    "sg:address":"Landsknechtsweg 11",
    "sg:city":"Lauterbach",
    "sg:phone":"+49 6641/9190840",
    "sg:postcode":"36341",
    "sg:province":"Hessen",
    "wof:name":"Lohmeyer Medsystems Gmbh",
    "wof:placetype":"venue"
},
  "geometry": {"coordinates":[9.398785,50.637768],"type":"Point"}
}