{
  "type": "Feature",
  "properties": {
    "iso:country":"DE",
    "sg:address":"Am Blauenberg 5",
    "sg:city":"Schweppenhausen",
    "sg:postcode":"55444",
    "sg:province":"Rheinland-Pfalz",
    "wof:name":"Lbf Wohnungsbau Gmbh",
    "wof:placetype":"venue"
},
  "geometry": {"coordinates":[7.794081,49.925987],"type":"Point"}
}