{
  "type": "Feature",
  "properties": {
    "iso:country":"DE",
    "sg:address":"H\u00f6rsterstr. 32",
    "sg:city":"M\u00fcnster",
    "sg:phone":"+49 251/46269",
    "sg:postcode":"48143",
    "sg:province":"Nordrhein-Westfalen",
    "wof:name":"Mpb Gesellschaft F\u00fcr Medizin- Planung Und Beteiligung Mbh",
    "wof:placetype":"venue"
},
  "geometry": {"coordinates":[7.633347,51.96524],"type":"Point"}
}