{
  "type": "Feature",
  "properties": {
    "iso:country":"DE",
    "sg:address":"Heinersberger Str. 9",
    "sg:city":"Geroldsgr\u00fcn",
    "sg:phone":"+49 9288/92104",
    "sg:postcode":"95179",
    "sg:province":"Bayern",
    "wof:name":"Gastst\u00e4tte K. Oelschlegel",
    "wof:placetype":"venue"
},
  "geometry": {"coordinates":[11.5929918289,50.3745613098],"type":"Point"}
}