{
  "type": "Feature",
  "properties": {
    "iso:country":"DE",
    "sg:address":"Hauptstr. 8",
    "sg:city":"Heede",
    "sg:phone":"+49 4963/1799",
    "sg:postcode":"26892",
    "sg:province":"Niedersachsen",
    "wof:name":"Heinr. Pieper",
    "wof:placetype":"venue"
},
  "geometry": {"coordinates":[7.30411,52.993385],"type":"Point"}
}