{
  "type": "Feature",
  "properties": {
    "iso:country":"DE",
    "sg:address":"Heimgartenweg 10",
    "sg:city":"Murnau",
    "sg:phone":"+49 8841/9329",
    "sg:postcode":"82418",
    "sg:province":"Bayern",
    "wof:name":"Hans W. Rauch",
    "wof:placetype":"venue"
},
  "geometry": {"coordinates":[11.213118,47.672977],"type":"Point"}
}