{
  "type": "Feature",
  "properties": {
    "iso:country":"DE",
    "sg:address":"Wahrburger Str. 136",
    "sg:city":"Stendal",
    "sg:phone":"+49 3931/214091",
    "sg:postcode":"39576",
    "sg:province":"Sachsen-Anhalt",
    "wof:name":"Ingenieurb\u00fcro J\u00fcttner Und Partner Gmbh",
    "wof:placetype":"venue"
},
  "geometry": {"coordinates":[11.8396167755,52.5985984802],"type":"Point"}
}