{
  "type": "Feature",
  "properties": {
    "iso:country":"DE",
    "sg:address":"Eislebener Str. 6",
    "sg:city":"Solingen",
    "sg:phone":"+49 212/73004",
    "sg:postcode":"42697",
    "sg:province":"Nordrhein-Westfalen",
    "wof:name":"B. Und M. Kappen",
    "wof:placetype":"venue"
},
  "geometry": {"coordinates":[7.00265,51.162495],"type":"Point"}
}