{
  "type": "Feature",
  "properties": {
    "iso:country":"DE",
    "sg:address":"Irisstr. 19",
    "sg:city":"Eriskirch",
    "sg:phone":"+49 7541/82144",
    "sg:postcode":"88097",
    "sg:province":"Baden-W\u00fcrttemberg",
    "wof:name":"P. Mohr",
    "wof:placetype":"venue"
},
  "geometry": {"coordinates":[9.5275764465,47.6308746338],"type":"Point"}
}