{
  "type": "Feature",
  "properties": {
    "iso:country":"DE",
    "sg:address":"Grolmanstr. 27-28",
    "sg:city":"Berlin",
    "sg:phone":"+49 30/88551216",
    "sg:postcode":"10623",
    "sg:province":"Berlin",
    "wof:name":"Care Concept Fachkosmetik Vertriebs Gmbh",
    "wof:placetype":"venue"
},
  "geometry": {"coordinates":[13.32330513,52.5046234131],"type":"Point"}
}