{
  "type": "Feature",
  "properties": {
    "iso:country":"DE",
    "sg:address":"Prinzregentenstr. 24",
    "sg:city":"Rosenheim",
    "sg:phone":"+49 8031/15230",
    "sg:postcode":"83022",
    "sg:province":"Bayern",
    "wof:name":"Alfred Grauvogel Architekt",
    "wof:placetype":"venue"
},
  "geometry": {"coordinates":[12.122909,47.85672],"type":"Point"}
}