{
  "type": "Feature",
  "properties": {
    "iso:country":"DE",
    "sg:address":"Ferdinand-Thun-Str. 21",
    "sg:city":"Wuppertal",
    "sg:phone":"+49 202/559191",
    "sg:postcode":"42289",
    "sg:province":"Nordrhein-Westfalen",
    "wof:name":"Textilagentur Conrad Gmbh",
    "wof:placetype":"venue"
},
  "geometry": {"coordinates":[7.2040271759,51.2681694031],"type":"Point"}
}