{
  "type": "Feature",
  "properties": {
    "iso:country":"DE",
    "sg:address":"Hauptstr. 61",
    "sg:city":"Oberding",
    "sg:phone":"+49 8122",
    "sg:postcode":"85445",
    "sg:province":"Bayern",
    "wof:name":"Zweckverband Zur Wasserversorgung Moosrain",
    "wof:placetype":"venue"
},
  "geometry": {"coordinates":[11.848104,48.317722],"type":"Point"}
}