{
  "type": "Feature",
  "properties": {
    "iso:country":"DE",
    "sg:address":"Knorrstr. 35-39",
    "sg:city":"Kassel",
    "sg:phone":"+49 4956/1928890",
    "sg:postcode":"34121",
    "sg:province":"Hessen",
    "wof:name":"Druckerei Foto-litho J\u00c4ger Gmbh",
    "wof:placetype":"venue"
},
  "geometry": {"coordinates":[9.4774971008,51.2917900085],"type":"Point"}
}