{
  "type": "Feature",
  "properties": {
    "iso:country":"DE",
    "sg:address":"Podbielskistr. 92",
    "sg:city":"Hannover",
    "sg:phone":"+49 511/668830",
    "sg:postcode":"30177",
    "sg:province":"Niedersachsen",
    "wof:name":"H.d. P\u00f6hler",
    "wof:placetype":"venue"
},
  "geometry": {"coordinates":[9.762468338,52.3948326111],"type":"Point"}
}