{
  "type": "Feature",
  "properties": {
    "iso:country":"DE",
    "sg:address":"Traminerweg 5-9",
    "sg:city":"Mannheim",
    "sg:phone":"+49 621/733295",
    "sg:postcode":"68309",
    "sg:province":"Baden-W\u00fcrttemberg",
    "wof:name":"Adam Laier Papiergro\u00dfhandlung Gmbh",
    "wof:placetype":"venue"
},
  "geometry": {"coordinates":[8.506668,49.500626],"type":"Point"}
}