{
  "type": "Feature",
  "properties": {
    "iso:country":"DE",
    "sg:address":"Am G\u00fcterbahnhof 2",
    "sg:city":"Berchtesgaden",
    "sg:phone":"+49 8652/2532",
    "sg:postcode":"83471",
    "sg:province":"Bayern",
    "wof:name":"F. Schnurrer",
    "wof:placetype":"venue"
},
  "geometry": {"coordinates":[13.000498,47.628166],"type":"Point"}
}