{
  "type": "Feature",
  "properties": {
    "iso:country":"DE",
    "sg:address":"Goethestr. 30",
    "sg:city":"Kassel",
    "sg:phone":"+49 561/777887",
    "sg:postcode":"34119",
    "sg:province":"Hessen",
    "wof:name":"Ulenspiegel",
    "wof:placetype":"venue"
},
  "geometry": {"coordinates":[9.4725198746,51.3148345947],"type":"Point"}
}