{
  "type": "Feature",
  "properties": {
    "iso:country":"DE",
    "sg:address":"Jahnstr. 18",
    "sg:city":"Frankfurt",
    "sg:phone":"+49 69/9591180",
    "sg:postcode":"60318",
    "sg:province":"Hessen",
    "wof:name":"Hotel Wei\u00dfes Haus",
    "wof:placetype":"venue"
},
  "geometry": {"coordinates":[8.6846609116,50.1207466125],"type":"Point"}
}