{
  "type": "Feature",
  "properties": {
    "iso:country":"DE",
    "sg:address":"Industriestr. 17",
    "sg:city":"Billigheim-Ingenheim",
    "sg:phone":"+49 6349/3609",
    "sg:postcode":"76831",
    "sg:province":"Rheinland-Pfalz",
    "wof:name":"Kieffer",
    "wof:placetype":"venue"
},
  "geometry": {"coordinates":[8.1155347824,49.1336135864],"type":"Point"}
}