{
  "type": "Feature",
  "properties": {
    "iso:country":"DE",
    "sg:address":"Waldstr. 27",
    "sg:city":"Burgdorf",
    "sg:phone":"+49 5085/7628",
    "sg:postcode":"31303",
    "sg:province":"Niedersachsen",
    "wof:name":"Golfshop Des Burgdorfer Colf-clubs",
    "wof:placetype":"venue"
},
  "geometry": {"coordinates":[10.010791,52.522091],"type":"Point"}
}