{
  "type": "Feature",
  "properties": {
    "iso:country":"DE",
    "sg:address":"Br\u00fcckenstr. 1",
    "sg:city":"Hagen",
    "sg:phone":"+49 5401/99864",
    "sg:postcode":"49170",
    "sg:province":"Niedersachsen",
    "wof:name":"Helmut Plogmann",
    "wof:placetype":"venue"
},
  "geometry": {"coordinates":[7.991401,52.195148],"type":"Point"}
}