{
  "type": "Feature",
  "properties": {
    "iso:country":"DE",
    "sg:address":"Berliner Str. 19",
    "sg:city":"Kyritz",
    "sg:phone":"+49 33971/2055",
    "sg:postcode":"16866",
    "sg:province":"Brandenburg",
    "wof:name":"Grieben & Rahn Gbr",
    "wof:placetype":"venue"
},
  "geometry": {"coordinates":[12.406928,52.938843],"type":"Point"}
}