{
  "type": "Feature",
  "properties": {
    "iso:country":"DE",
    "sg:address":"Am Bahnhof 3",
    "sg:city":"Mintraching",
    "sg:phone":"+49 9406/443",
    "sg:postcode":"93098",
    "sg:province":"Bayern",
    "wof:name":"Attila Weickert Steuerberater",
    "wof:placetype":"venue"
},
  "geometry": {"coordinates":[12.2229766846,48.9486656189],"type":"Point"}
}