{
  "type": "Feature",
  "properties": {
    "iso:country":"DE",
    "sg:address":"Pritzwalker Str. 15",
    "sg:city":"Wittstock",
    "sg:phone":"+49 3394/443010",
    "sg:postcode":"16909",
    "sg:province":"Brandenburg",
    "wof:name":"Iwsw Ina Schmidt Gmbh",
    "wof:placetype":"venue"
},
  "geometry": {"coordinates":[12.4763002396,53.1615257263],"type":"Point"}
}