{
  "type": "Feature",
  "properties": {
    "iso:country":"DE",
    "sg:address":"Hauptstr. 127",
    "sg:city":"Behringen",
    "sg:postcode":"99947",
    "sg:province":"Th\u00fcringen",
    "wof:name":"Otto Schnauss",
    "wof:placetype":"venue"
},
  "geometry": {"coordinates":[10.5097808838,51.0216178894],"type":"Point"}
}