{
  "type": "Feature",
  "properties": {
    "iso:country":"DE",
    "sg:address":"Auf der Steige 22",
    "sg:city":"Rutesheim",
    "sg:phone":"+49 711/6150832",
    "sg:postcode":"71277",
    "sg:province":"Baden-W\u00fcrttemberg",
    "wof:name":"Movies",
    "wof:placetype":"venue"
},
  "geometry": {"coordinates":[8.9380531311,48.8077774048],"type":"Point"}
}