{
  "type": "Feature",
  "properties": {
    "iso:country":"DE",
    "sg:address":"Eichenstr. 9",
    "sg:city":"Strausberg",
    "sg:phone":"+49 3341/22601",
    "sg:postcode":"15344",
    "sg:province":"Brandenburg",
    "wof:name":"Ketrona Beteiligungs Gmbh",
    "wof:placetype":"venue"
},
  "geometry": {"coordinates":[13.895964,52.596508],"type":"Point"}
}