{
  "type": "Feature",
  "properties": {
    "iso:country":"DE",
    "sg:address":"Lohnertstr. 26",
    "sg:city":"Neunkirchen",
    "sg:phone":"+49 6821/865511",
    "sg:postcode":"66538",
    "sg:province":"Saarland",
    "wof:name":"Residenz Am Teich Immobilien Gmbh",
    "wof:placetype":"venue"
},
  "geometry": {"coordinates":[7.169931,49.327965],"type":"Point"}
}