{
  "type": "Feature",
  "properties": {
    "iso:country":"DE",
    "sg:address":"Leipziger Str. 167",
    "sg:city":"Dresden",
    "sg:phone":"+49 351/8491158",
    "sg:postcode":"01139",
    "sg:province":"Sachsen",
    "wof:name":"Klaus Mitzschke",
    "wof:placetype":"venue"
},
  "geometry": {"coordinates":[13.7091741562,51.0841560364],"type":"Point"}
}