{
  "type": "Feature",
  "properties": {
    "iso:country":"DE",
    "sg:address":"Legdenwiese 2",
    "sg:city":"Salzgitter",
    "sg:phone":"+49 5341/71449",
    "sg:postcode":"38229",
    "sg:province":"Niedersachsen",
    "wof:name":"Siegfried Tirrmann",
    "wof:placetype":"venue"
},
  "geometry": {"coordinates":[10.3576631546,52.1096725464],"type":"Point"}
}