{
  "type": "Feature",
  "properties": {
    "iso:country":"DE",
    "sg:address":"Am Bahnhof",
    "sg:city":"Kohren-Sahlis",
    "sg:phone":"+49 34344/61517",
    "sg:postcode":"04655",
    "sg:province":"Sachsen",
    "wof:name":"Konsumgenossenschaft Altenburg Und Umgebung Eg",
    "wof:placetype":"venue"
},
  "geometry": {"coordinates":[12.6033649445,51.0172119141],"type":"Point"}
}