{
  "type": "Feature",
  "properties": {
    "iso:country":"DE",
    "sg:address":"Steinstr. 16",
    "sg:city":"Wolgast",
    "sg:phone":"+49 3836/202704",
    "sg:postcode":"17438",
    "sg:province":"Mecklenburg-Vorpommern",
    "wof:name":"Holger Henselin Rechtsanwalt",
    "wof:placetype":"venue"
},
  "geometry": {"coordinates":[13.7752456665,54.0540275574],"type":"Point"}
}