{
  "type": "Feature",
  "properties": {
    "iso:country":"DE",
    "sg:address":"Trettaustr. 49",
    "sg:city":"Hamburg",
    "sg:phone":"+49 40/7510901",
    "sg:postcode":"21107",
    "sg:province":"Hamburg",
    "wof:name":"Beteiliungsges. Diamant M\u00fchle Hamburg Mbh",
    "wof:placetype":"venue"
},
  "geometry": {"coordinates":[9.983828,53.493439],"type":"Point"}
}