{
  "type": "Feature",
  "properties": {
    "iso:country":"DE",
    "sg:address":"Siedlung 10",
    "sg:city":"Gro\u00dfschirma",
    "sg:phone":"+49 37328/7963",
    "sg:postcode":"09603",
    "sg:province":"Sachsen",
    "wof:name":"Karlheinz Pilz",
    "wof:placetype":"venue"
},
  "geometry": {"coordinates":[13.277179,50.964787],"type":"Point"}
}