{
  "type": "Feature",
  "properties": {
    "iso:country":"DE",
    "sg:address":"Mittelgasse 9",
    "sg:city":"Br\u00e4unlingen",
    "sg:phone":"+49 771/6773",
    "sg:postcode":"78199",
    "sg:province":"Baden-W\u00fcrttemberg",
    "wof:name":"Maria Reis Masseurin",
    "wof:placetype":"venue"
},
  "geometry": {"coordinates":[8.44772,47.928925],"type":"Point"}
}