{
  "type": "Feature",
  "properties": {
    "iso:country":"DE",
    "sg:address":"Boschstr. 22",
    "sg:city":"Korb",
    "sg:phone":"+49 7151/31965",
    "sg:postcode":"71404",
    "sg:province":"Baden-W\u00fcrttemberg",
    "wof:name":"Wohnbau Schatz Gmbh",
    "wof:placetype":"venue"
},
  "geometry": {"coordinates":[9.365216,48.835114],"type":"Point"}
}