{
  "type": "Feature",
  "properties": {
    "iso:country":"DE",
    "sg:address":"Krayer Str. 197",
    "sg:city":"Essen",
    "sg:phone":"+49 201/591081",
    "sg:postcode":"45307",
    "sg:province":"Nordrhein-Westfalen",
    "wof:name":"Peter Bedenbecker Steuerberater",
    "wof:placetype":"venue"
},
  "geometry": {"coordinates":[7.0794529915,51.4642524719],"type":"Point"}
}