{
  "type": "Feature",
  "properties": {
    "iso:country":"DE",
    "sg:address":"Hauptstrasse 398",
    "sg:city":"Weil am Rhein",
    "sg:postcode":"79576",
    "sg:province":"Baden-W\u00fcrttemberg",
    "wof:name":"Zeitschriften Kiosk Illustrierte Abonnemente",
    "wof:placetype":"venue"
},
  "geometry": {"coordinates":[7.598036,47.590637],"type":"Point"}
}