{
  "type": "Feature",
  "properties": {
    "iso:country":"DE",
    "sg:address":"Spitalstr. 26",
    "sg:city":"Lauf",
    "sg:phone":"+49 9123/97750",
    "sg:postcode":"91207",
    "sg:province":"Bayern",
    "wof:name":"Kr-planung Und Baubetreuung Gmbh",
    "wof:placetype":"venue"
},
  "geometry": {"coordinates":[11.2814397812,49.5107307434],"type":"Point"}
}