{
  "type": "Feature",
  "properties": {
    "iso:country":"DE",
    "sg:address":"Klugham",
    "sg:city":"Kastl",
    "sg:phone":"+49 8671/5448",
    "sg:postcode":"84556",
    "sg:province":"Bayern",
    "wof:name":"G. Sterflinger Sen.",
    "wof:placetype":"venue"
},
  "geometry": {"coordinates":[12.68534,48.197933],"type":"Point"}
}