{
  "type": "Feature",
  "properties": {
    "iso:country":"DE",
    "sg:address":"Albert-Schalper-Str. 3",
    "sg:city":"Kolbermoor",
    "sg:phone":"+49 8031/91769",
    "sg:postcode":"83059",
    "sg:province":"Bayern",
    "wof:name":"Urban Wacker Formenbau U Kunststoffverarbeitung",
    "wof:placetype":"venue"
},
  "geometry": {"coordinates":[12.0483779907,47.8422012329],"type":"Point"}
}