{
  "type": "Feature",
  "properties": {
    "iso:country":"DE",
    "sg:address":"Nansenstr. 9",
    "sg:city":"Bremen",
    "sg:phone":"+49 421/385722",
    "sg:postcode":"28217",
    "sg:province":"Bremen",
    "wof:name":"Karibik-keller Handtke",
    "wof:placetype":"venue"
},
  "geometry": {"coordinates":[8.792287,53.090973],"type":"Point"}
}