{
  "type": "Feature",
  "properties": {
    "iso:country":"DE",
    "sg:address":"Stablostr. 21",
    "sg:city":"Kr\u00f6v",
    "sg:phone":"+49 6541/2317",
    "sg:postcode":"54536",
    "sg:province":"Rheinland-Pfalz",
    "wof:name":"Erwin Schnitzius",
    "wof:placetype":"venue"
},
  "geometry": {"coordinates":[7.0818581581,49.9745826721],"type":"Point"}
}