{
  "type": "Feature",
  "properties": {
    "iso:country":"DE",
    "sg:address":"Fuchsturmweg 3",
    "sg:city":"Jena",
    "sg:phone":"+49 3641",
    "sg:postcode":"07749",
    "sg:province":"Th\u00fcringen",
    "wof:name":"Erotik-boutique-christel",
    "wof:placetype":"venue"
},
  "geometry": {"coordinates":[11.5987920761,50.9283905029],"type":"Point"}
}