{
  "type": "Feature",
  "properties": {
    "iso:country":"DE",
    "sg:address":"F\u00fcrstenberger Str. 31",
    "sg:city":"Holzminden",
    "sg:phone":"+49 5531/6676",
    "sg:postcode":"37603",
    "sg:province":"Niedersachsen",
    "wof:name":"Eduard Fuchs Fitness-studio",
    "wof:placetype":"venue"
},
  "geometry": {"coordinates":[9.4484739304,51.8226280212],"type":"Point"}
}