{
  "type": "Feature",
  "properties": {
    "iso:country":"DE",
    "sg:address":"Weidenstr. 4",
    "sg:city":"Nettersheim",
    "sg:phone":"+49 2486/8583",
    "sg:postcode":"53947",
    "sg:province":"Nordrhein-Westfalen",
    "wof:name":"Peter Hermanns",
    "wof:placetype":"venue"
},
  "geometry": {"coordinates":[6.654004,50.511257],"type":"Point"}
}