{
  "type": "Feature",
  "properties": {
    "iso:country":"DE",
    "sg:address":"Ober-Laudenbacher Str. 52",
    "sg:city":"Heppenheim",
    "sg:phone":"+49 6252/2104",
    "sg:postcode":"64646",
    "sg:province":"Hessen",
    "wof:name":"K. Becker",
    "wof:placetype":"venue"
},
  "geometry": {"coordinates":[8.6781768799,49.6145095825],"type":"Point"}
}