{
  "type": "Feature",
  "properties": {
    "iso:country":"DE",
    "sg:address":"Rheinlandstr.",
    "sg:city":"Frankfurt",
    "sg:phone":"+49 69/2136718",
    "sg:postcode":"60529",
    "sg:province":"Hessen",
    "wof:name":"Stra\u00dfenbahnmuseum C-o Stra\u00dfenbahndepot",
    "wof:placetype":"venue"
},
  "geometry": {"coordinates":[8.591221,50.086151],"type":"Point"}
}