{
  "type": "Feature",
  "properties": {
    "iso:country":"DE",
    "sg:address":"Am Sportplatz 6",
    "sg:city":"Breisach-Oberrimsingen",
    "sg:phone":"+49 4976/642687",
    "sg:postcode":"79206",
    "sg:province":"Baden-W\u00fcrttemberg",
    "wof:name":"Ott Steuer- Und Regel- Technik Gmbh",
    "wof:placetype":"venue"
},
  "geometry": {"coordinates":[7.5821070671,48.0282096863],"type":"Point"}
}