{
  "type": "Feature",
  "properties": {
    "iso:country":"DE",
    "sg:address":"Heinzelberg 3",
    "sg:city":"Betzigau",
    "sg:postcode":"87488",
    "sg:province":"Bayern",
    "wof:name":"Gbc Golf-bau-concept Gmbh",
    "wof:placetype":"venue"
},
  "geometry": {"coordinates":[10.3868846893,47.7291221619],"type":"Point"}
}