{
  "type": "Feature",
  "properties": {
    "iso:country":"DE",
    "sg:address":"B\u00fcnder Str. 364",
    "sg:city":"Spenge",
    "sg:phone":"+49 5225/4404",
    "sg:postcode":"32139",
    "sg:province":"Nordrhein-Westfalen",
    "wof:name":"Irrlicht",
    "wof:placetype":"venue"
},
  "geometry": {"coordinates":[8.5172681808,52.1822166443],"type":"Point"}
}