{
  "type": "Feature",
  "properties": {
    "iso:country":"DE",
    "sg:address":"Rietschelstr. 49",
    "sg:city":"Leipzig",
    "sg:postcode":"04177",
    "sg:province":"Sachsen",
    "wof:name":"Kerstin Stange",
    "wof:placetype":"venue"
},
  "geometry": {"coordinates":[12.327627182,51.3438224792],"type":"Point"}
}