{
  "type": "Feature",
  "properties": {
    "iso:country":"DE",
    "sg:address":"Parkstr. 10",
    "sg:city":"Hemer",
    "sg:postcode":"58675",
    "sg:province":"Nordrhein-Westfalen",
    "wof:name":"Menzyk Consult Gmbh",
    "wof:placetype":"venue"
},
  "geometry": {"coordinates":[7.7614569664,51.3880157471],"type":"Point"}
}