{
  "type": "Feature",
  "properties": {
    "iso:country":"DE",
    "sg:address":"Zei\u00dfstr. 59",
    "sg:city":"Hamburg",
    "sg:phone":"+49 40/394760",
    "sg:postcode":"22765",
    "sg:province":"Hamburg",
    "wof:name":"M. Witek",
    "wof:placetype":"venue"
},
  "geometry": {"coordinates":[9.93139,53.555183],"type":"Point"}
}