{
  "type": "Feature",
  "properties": {
    "iso:country":"DE",
    "sg:address":"Ro\u00dfmarkt 13",
    "sg:city":"Frankfurt",
    "sg:phone":"+49 69/20727",
    "sg:postcode":"60311",
    "sg:province":"Hessen",
    "wof:name":"Sprachzentrum F\u00fcr Japanisch E. V.",
    "wof:placetype":"venue"
},
  "geometry": {"coordinates":[8.6774225235,50.1120834351],"type":"Point"}
}