{
  "type": "Feature",
  "properties": {
    "iso:country":"DE",
    "sg:address":"G\u00f6kerstr. 79a",
    "sg:city":"Wilhelmshaven",
    "sg:phone":"+49 4421/995530",
    "sg:postcode":"26384",
    "sg:province":"Niedersachsen",
    "wof:name":"Oquadrat",
    "wof:placetype":"venue"
},
  "geometry": {"coordinates":[8.1264839172,53.5307312012],"type":"Point"}
}