{
  "type": "Feature",
  "properties": {
    "iso:country":"DE",
    "sg:address":"Am Aubuckel 28",
    "sg:city":"Mannheim",
    "sg:phone":"+49 621/791312",
    "sg:postcode":"68259",
    "sg:province":"Baden-W\u00fcrttemberg",
    "wof:name":"Hans Hahn",
    "wof:placetype":"venue"
},
  "geometry": {"coordinates":[8.519954,49.490639],"type":"Point"}
}