{
  "type": "Feature",
  "properties": {
    "iso:country":"DE",
    "sg:address":"B\u00e4chleweg 2",
    "sg:city":"Bad S\u00e4ckingen",
    "sg:phone":"+49 7761/2841",
    "sg:postcode":"79713",
    "sg:province":"Baden-W\u00fcrttemberg",
    "wof:name":"Bernhard Mutter",
    "wof:placetype":"venue"
},
  "geometry": {"coordinates":[7.968334198,47.5615730286],"type":"Point"}
}