{
  "type": "Feature",
  "properties": {
    "iso:country":"DE",
    "sg:address":"Pestalozzistr. 14",
    "sg:city":"Bad Vilbel",
    "sg:phone":"+49 6101/86336",
    "sg:postcode":"61118",
    "sg:province":"Hessen",
    "wof:name":"Klaus Bornemann Rechtsanwalt",
    "wof:placetype":"venue"
},
  "geometry": {"coordinates":[8.7173547745,50.175113678],"type":"Point"}
}