{
  "type": "Feature",
  "properties": {
    "iso:country":"DE",
    "sg:address":"Kobergerstr. 81",
    "sg:city":"N\u00fcrnberg",
    "sg:phone":"+49 911/362558",
    "sg:postcode":"90408",
    "sg:province":"Bayern",
    "wof:name":"Hans Ulrich M\u00fcller",
    "wof:placetype":"venue"
},
  "geometry": {"coordinates":[11.072078,49.463741],"type":"Point"}
}