{
  "type": "Feature",
  "properties": {
    "iso:country":"DE",
    "sg:address":"Boberstr. 2",
    "sg:city":"Duisburg",
    "sg:phone":"+49 203/402470",
    "sg:postcode":"47169",
    "sg:province":"Nordrhein-Westfalen",
    "wof:name":"Kath. Pfarramt St. Konrad",
    "wof:placetype":"venue"
},
  "geometry": {"coordinates":[6.748896122,51.5160598755],"type":"Point"}
}