{
  "type": "Feature",
  "properties": {
    "iso:country":"DE",
    "sg:address":"Emdener Str. 5",
    "sg:city":"Aschendorf",
    "sg:phone":"+49 4962/5902",
    "sg:postcode":"26871",
    "sg:province":"Niedersachsen",
    "wof:name":"Hermann Evering",
    "wof:placetype":"venue"
},
  "geometry": {"coordinates":[7.339874,53.054089],"type":"Point"}
}