{
  "type": "Feature",
  "properties": {
    "iso:country":"DE",
    "sg:address":"Am Kirchplatz 12",
    "sg:city":"Dissen",
    "sg:phone":"+49 5421/94310",
    "sg:postcode":"49201",
    "sg:province":"Niedersachsen",
    "wof:name":"Hsb Hollenberg System Bau Gmbh",
    "wof:placetype":"venue"
},
  "geometry": {"coordinates":[8.20497,52.114082],"type":"Point"}
}