{
  "type": "Feature",
  "properties": {
    "iso:country":"DE",
    "sg:address":"Riepenstr. 12",
    "sg:city":"Hameln",
    "sg:phone":"+49 5151/66487",
    "sg:postcode":"31789",
    "sg:province":"Niedersachsen",
    "wof:name":"G. Pertz Heissmangel",
    "wof:placetype":"venue"
},
  "geometry": {"coordinates":[9.3477964401,52.0890922546],"type":"Point"}
}