{
  "type": "Feature",
  "properties": {
    "iso:country":"DE",
    "sg:address":"Rondeel 2",
    "sg:city":"Ahrensburg",
    "sg:phone":"+49 4102/50759",
    "sg:postcode":"22926",
    "sg:province":"Schleswig-Holstein",
    "wof:name":"Dr. Siegfried Barschkies Rechtsanwalt",
    "wof:placetype":"venue"
},
  "geometry": {"coordinates":[10.239033699,53.6732749939],"type":"Point"}
}