{
  "type": "Feature",
  "properties": {
    "iso:country":"DE",
    "sg:address":"Sundernstr. 51",
    "sg:city":"Peine",
    "sg:phone":"+49 5171/17620",
    "sg:postcode":"31224",
    "sg:province":"Niedersachsen",
    "wof:name":"Magnus Schmidtmeyer Grabdenkm\u00e4ler",
    "wof:placetype":"venue"
},
  "geometry": {"coordinates":[10.2246055603,52.3319244385],"type":"Point"}
}