{
  "type": "Feature",
  "properties": {
    "iso:country":"DE",
    "sg:address":"Wittelsbacherallee 91",
    "sg:city":"Frankfurt",
    "sg:postcode":"60385",
    "sg:province":"Hessen",
    "wof:name":"Halifax Chemie Produkte Gmbh",
    "wof:placetype":"venue"
},
  "geometry": {"coordinates":[8.708193,50.121536],"type":"Point"}
}