{
  "type": "Feature",
  "properties": {
    "iso:country":"DE",
    "sg:address":"Am Kleinbahnhof",
    "sg:city":"Ellrich",
    "sg:postcode":"99755",
    "sg:province":"Th\u00fcringen",
    "wof:name":"Kohlehandel Erfurt Gmbh",
    "wof:placetype":"venue"
},
  "geometry": {"coordinates":[10.6572,51.586788],"type":"Point"}
}