{
  "type": "Feature",
  "properties": {
    "iso:country":"DE",
    "sg:address":"Lepsiusstr. 41",
    "sg:city":"Berlin",
    "sg:phone":"+49 30/7915845",
    "sg:postcode":"12163",
    "sg:province":"Berlin",
    "wof:name":"Marianne Holtfreter",
    "wof:placetype":"venue"
},
  "geometry": {"coordinates":[13.319039,52.462372],"type":"Point"}
}