{
  "type": "Feature",
  "properties": {
    "iso:country":"DE",
    "sg:address":"R\u00f6ntgenstr. 13",
    "sg:city":"Essen",
    "sg:phone":"+49 201/640596",
    "sg:postcode":"45143",
    "sg:province":"Nordrhein-Westfalen",
    "wof:name":"Richard Oganowski",
    "wof:placetype":"venue"
},
  "geometry": {"coordinates":[6.973528,51.46027],"type":"Point"}
}