{
  "type": "Feature",
  "properties": {
    "iso:country":"DE",
    "sg:address":"Hochstr.",
    "sg:city":"Erftstadt",
    "sg:phone":"+49 2235/72912",
    "sg:postcode":"50374",
    "sg:province":"Nordrhein-Westfalen",
    "wof:name":"G. Alter",
    "wof:placetype":"venue"
},
  "geometry": {"coordinates":[6.710232,50.766239],"type":"Point"}
}