{
  "type": "Feature",
  "properties": {
    "iso:country":"DE",
    "sg:address":"Hamburger Str. 112",
    "sg:city":"Ammersbek",
    "sg:postcode":"22949",
    "sg:province":"Schleswig-Holstein",
    "wof:name":"Eurospar*",
    "wof:placetype":"venue"
},
  "geometry": {"coordinates":[10.1446475983,53.6777801514],"type":"Point"}
}