{
  "type": "Feature",
  "properties": {
    "iso:country":"DE",
    "sg:address":"Am G\u00e4rtling 28",
    "sg:city":"Wei\u00dfenborn-L\u00fcderode",
    "sg:phone":"+49 36072/90304",
    "sg:postcode":"37345",
    "sg:province":"Th\u00fcringen",
    "wof:name":"Bernhard Busse",
    "wof:placetype":"venue"
},
  "geometry": {"coordinates":[10.414733,51.534565],"type":"Point"}
}