{
  "type": "Feature",
  "properties": {
    "iso:country":"DE",
    "sg:address":"Bahnhofstr. 19",
    "sg:city":"H\u00f6henkirchen-Siegertbrn",
    "sg:postcode":"85635",
    "sg:province":"Bayern",
    "wof:name":"Altplast Gmbh",
    "wof:placetype":"venue"
},
  "geometry": {"coordinates":[11.7172269821,48.01953125],"type":"Point"}
}