{
  "type": "Feature",
  "properties": {
    "iso:country":"DE",
    "sg:address":"Ellmershausstr. 7",
    "sg:city":"Kronach",
    "sg:phone":"+49 9261/627448",
    "sg:postcode":"96317",
    "sg:province":"Bayern",
    "wof:name":"Pension Anna Rebhan",
    "wof:placetype":"venue"
},
  "geometry": {"coordinates":[11.2809467316,50.2378883362],"type":"Point"}
}