{
  "type": "Feature",
  "properties": {
    "iso:country":"DE",
    "sg:address":"Carsdorfer H\u00f6he 1",
    "sg:city":"Groitzsch",
    "sg:phone":"+49 34296/730",
    "sg:postcode":"04539",
    "sg:province":"Sachsen",
    "wof:name":"Stahlbau Westphal Kg",
    "wof:placetype":"venue"
},
  "geometry": {"coordinates":[12.29671,51.135891],"type":"Point"}
}