{
  "type": "Feature",
  "properties": {
    "iso:country":"DE",
    "sg:address":"Lilienthalstr. 8",
    "sg:city":"Herford",
    "sg:phone":"+49 5221/70780",
    "sg:postcode":"32052",
    "sg:province":"Nordrhein-Westfalen",
    "wof:name":"Dirk A. Everding",
    "wof:placetype":"venue"
},
  "geometry": {"coordinates":[8.682114,52.092216],"type":"Point"}
}