{
  "type": "Feature",
  "properties": {
    "iso:country":"DE",
    "sg:address":"Zumhaus 2",
    "sg:city":"Feuchtwangen",
    "sg:phone":"+49 7950/358",
    "sg:postcode":"91555",
    "sg:province":"Bayern",
    "wof:name":"Ernst Weber",
    "wof:placetype":"venue"
},
  "geometry": {"coordinates":[10.244342,49.213196],"type":"Point"}
}