{
  "type": "Feature",
  "properties": {
    "iso:country":"DE",
    "sg:address":"Bergstr. 5",
    "sg:city":"Waldachtal",
    "sg:phone":"+49 7164/910070",
    "sg:postcode":"72178",
    "sg:province":"Baden-W\u00fcrttemberg",
    "wof:name":"D. Kempf Gmbh",
    "wof:placetype":"venue"
},
  "geometry": {"coordinates":[-97.570084,35.4207],"type":"Point"}
}