{
  "type": "Feature",
  "properties": {
    "iso:country":"DE",
    "sg:address":"Hafenbahnstr. 26",
    "sg:city":"Stuttgart",
    "sg:postcode":"70329",
    "sg:province":"Baden-W\u00fcrttemberg",
    "wof:name":"S\u00fcddeutsche Zeitungszentrale Presse-grosso Gmbh",
    "wof:placetype":"venue"
},
  "geometry": {"coordinates":[9.267236,48.759338],"type":"Point"}
}