{
  "type": "Feature",
  "properties": {
    "iso:country":"DE",
    "sg:address":"Neue Steige 10",
    "sg:city":"Fronreute",
    "sg:phone":"+49 7502/4715",
    "sg:postcode":"88273",
    "sg:province":"Baden-W\u00fcrttemberg",
    "wof:name":"L. Und A. Rusch",
    "wof:placetype":"venue"
},
  "geometry": {"coordinates":[9.6003503799,47.8539199829],"type":"Point"}
}