{
  "type": "Feature",
  "properties": {
    "iso:country":"DE",
    "sg:address":"Wiesenstr. 11",
    "sg:city":"Fischbachtal",
    "sg:phone":"+49 6166/8277",
    "sg:postcode":"64405",
    "sg:province":"Hessen",
    "wof:name":"Georg Dascher",
    "wof:placetype":"venue"
},
  "geometry": {"coordinates":[8.815841,49.770424],"type":"Point"}
}