{
  "type": "Feature",
  "properties": {
    "iso:country":"DE",
    "sg:address":"Donaustr. 28",
    "sg:city":"Trostberg",
    "sg:phone":"+49 8621/3001",
    "sg:postcode":"83308",
    "sg:province":"Bayern",
    "wof:name":"Michael Wartha",
    "wof:placetype":"venue"
},
  "geometry": {"coordinates":[12.5364656448,48.0206260681],"type":"Point"}
}