{
  "type": "Feature",
  "properties": {
    "iso:country":"DE",
    "sg:address":"Professor-Baumgartner-Str. 29",
    "sg:city":"Bad Griesbach",
    "sg:phone":"+49 8532/920250",
    "sg:postcode":"94086",
    "sg:province":"Bayern",
    "wof:name":"Klaus W. Preissler Touristik Gmbh",
    "wof:placetype":"venue"
},
  "geometry": {"coordinates":[13.1945877075,48.4446144104],"type":"Point"}
}