{
  "type": "Feature",
  "properties": {
    "iso:country":"DE",
    "sg:address":"Hauptstr. 3",
    "sg:city":"Oberndorf",
    "sg:phone":"+49 7423/5421",
    "sg:postcode":"78727",
    "sg:province":"Baden-W\u00fcrttemberg",
    "wof:name":"Point",
    "wof:placetype":"venue"
},
  "geometry": {"coordinates":[7.809414,49.705273],"type":"Point"}
}