{
  "type": "Feature",
  "properties": {
    "iso:country":"DE",
    "sg:address":"Brabanter Str. 75",
    "sg:city":"Waldfeucht",
    "sg:phone":"+49 2455/436",
    "sg:postcode":"52525",
    "sg:province":"Nordrhein-Westfalen",
    "wof:name":"Ratsstube",
    "wof:placetype":"venue"
},
  "geometry": {"coordinates":[5.9879760742,51.0659751892],"type":"Point"}
}