{
  "type": "Feature",
  "properties": {
    "iso:country":"DE",
    "sg:address":"Am Rehbaum 5",
    "sg:city":"Dorsten",
    "sg:postcode":"46282",
    "sg:province":"Nordrhein-Westfalen",
    "wof:name":"Bvg Brennstoff-vertriebs Gmbh",
    "wof:placetype":"venue"
},
  "geometry": {"coordinates":[6.913794,51.656956],"type":"Point"}
}