{
  "type": "Feature",
  "properties": {
    "iso:country":"DE",
    "sg:address":"An der Olef 64",
    "sg:city":"Schleiden",
    "sg:phone":"+49 2445/7909",
    "sg:postcode":"53937",
    "sg:province":"Nordrhein-Westfalen",
    "wof:name":"G. Geschwind",
    "wof:placetype":"venue"
},
  "geometry": {"coordinates":[6.465624,50.517925],"type":"Point"}
}