{
  "type": "Feature",
  "properties": {
    "iso:country":"DE",
    "sg:address":"Klein Goldberg 1",
    "sg:city":"Mettmann",
    "sg:phone":"+49 2104/27612",
    "sg:postcode":"40822",
    "sg:province":"Nordrhein-Westfalen",
    "wof:name":"Helmut M\u00fcller",
    "wof:placetype":"venue"
},
  "geometry": {"coordinates":[6.9837269783,51.25365448],"type":"Point"}
}