{
  "type": "Feature",
  "properties": {
    "iso:country":"DE",
    "sg:address":"Im Ried 1",
    "sg:city":"Bodman-Ludwigshafen",
    "sg:phone":"+49 7773/5271",
    "sg:postcode":"78351",
    "sg:province":"Baden-W\u00fcrttemberg",
    "wof:name":"Edgar Sp\u00e4th",
    "wof:placetype":"venue"
},
  "geometry": {"coordinates":[9.015805,47.813934],"type":"Point"}
}