{
  "type": "Feature",
  "properties": {
    "iso:country":"DE",
    "sg:address":"Kapellenstr. 34",
    "sg:city":"Rastatt",
    "sg:phone":"+49 7222/33380",
    "sg:postcode":"76437",
    "sg:province":"Baden-W\u00fcrttemberg",
    "wof:name":"Pagodenburg",
    "wof:placetype":"venue"
},
  "geometry": {"coordinates":[8.20719,48.857285],"type":"Point"}
}