{
  "type": "Feature",
  "properties": {
    "iso:country":"DE",
    "sg:address":"Am Risisee 1",
    "sg:city":"Achern",
    "sg:postcode":"77855",
    "sg:province":"Baden-W\u00fcrttemberg",
    "wof:name":"Neckermann Versand Ag",
    "wof:placetype":"venue"
},
  "geometry": {"coordinates":[8.0300483704,48.6563453674],"type":"Point"}
}