{
  "type": "Feature",
  "properties": {
    "iso:country":"DE",
    "sg:address":"Schillerstr. 1",
    "sg:city":"Selb",
    "sg:phone":"+49 9287/870606",
    "sg:postcode":"95100",
    "sg:province":"Bayern",
    "wof:name":"Karin Fischer Rechtsanw\u00e4ltin",
    "wof:placetype":"venue"
},
  "geometry": {"coordinates":[12.1283149719,50.1702766418],"type":"Point"}
}