{
  "type": "Feature",
  "properties": {
    "iso:country":"DE",
    "sg:address":"Friedrichstr. 30a",
    "sg:city":"M\u00fclheim",
    "sg:phone":"+49 208/3881880",
    "sg:postcode":"45468",
    "sg:province":"Nordrhein-Westfalen",
    "wof:name":"Security Guard Bewachung Gmbh",
    "wof:placetype":"venue"
},
  "geometry": {"coordinates":[6.880945,51.424129],"type":"Point"}
}