{
  "type": "Feature",
  "properties": {
    "iso:country":"DE",
    "sg:address":"Postfach 14",
    "sg:city":"Bondorf",
    "sg:phone":"+49 7457",
    "sg:postcode":"71145",
    "sg:province":"Baden-W\u00fcrttemberg",
    "wof:name":"Briefmarkenversand Klaus-d. Hahn",
    "wof:placetype":"venue"
},
  "geometry": {"coordinates":[8.8369598389,48.5224533081],"type":"Point"}
}