{
  "type": "Feature",
  "properties": {
    "iso:country":"DE",
    "sg:address":"M\u00fchlgutstr. 7",
    "sg:city":"Neukirch",
    "sg:phone":"+49 35951/32303",
    "sg:postcode":"01904",
    "sg:province":"Sachsen",
    "wof:name":"J. Hermann",
    "wof:placetype":"venue"
},
  "geometry": {"coordinates":[14.322889,51.092442],"type":"Point"}
}