{
  "type": "Feature",
  "properties": {
    "iso:country":"DE",
    "sg:address":"Berghofer Str. 19",
    "sg:city":"Sonthofen",
    "sg:phone":"+49 8321/4253",
    "sg:postcode":"87527",
    "sg:province":"Bayern",
    "wof:name":"Kube Holzbau-gmbh",
    "wof:placetype":"venue"
},
  "geometry": {"coordinates":[10.289978981,47.5156211853],"type":"Point"}
}