{
  "type": "Feature",
  "properties": {
    "iso:country":"DE",
    "sg:address":"Oldesloer Str. 35",
    "sg:city":"Hamburg",
    "sg:phone":"+49 40/5502567",
    "sg:postcode":"22457",
    "sg:province":"Hamburg",
    "wof:name":"I. Grote",
    "wof:placetype":"venue"
},
  "geometry": {"coordinates":[9.93595,53.64735],"type":"Point"}
}