{
  "type": "Feature",
  "properties": {
    "iso:country":"DE",
    "sg:address":"Fritz-Geiges-Str. 8",
    "sg:city":"Freiburg",
    "sg:phone":"+49 761/69137",
    "sg:postcode":"79117",
    "sg:province":"Baden-W\u00fcrttemberg",
    "wof:name":"K. Hohwieler B\u00fcrobedarf",
    "wof:placetype":"venue"
},
  "geometry": {"coordinates":[7.8894739151,47.9878234863],"type":"Point"}
}