{
  "type": "Feature",
  "properties": {
    "iso:country":"DE",
    "sg:address":"Kolumbusstr. 10/12",
    "sg:city":"Hamburg",
    "sg:postcode":"22113",
    "sg:province":"Schleswig-Holstein",
    "wof:name":"Hermann Wetzel Gmbh",
    "wof:placetype":"venue"
},
  "geometry": {"coordinates":[10.088621,53.542412],"type":"Point"}
}