{
  "type": "Feature",
  "properties": {
    "iso:country":"DE",
    "sg:address":"Dunzerstr. 19",
    "sg:city":"Aschaffenburg",
    "sg:phone":"+49 6021/581790",
    "sg:postcode":"63739",
    "sg:province":"Bayern",
    "wof:name":"Zum S\u00fcdbahnhof",
    "wof:placetype":"venue"
},
  "geometry": {"coordinates":[9.1470766068,49.9687423706],"type":"Point"}
}