{
  "type": "Feature",
  "properties": {
    "iso:country":"DE",
    "sg:address":"Eckenhagener Str. 54",
    "sg:city":"Gummersbach",
    "sg:phone":"+49 2261/53069",
    "sg:postcode":"51645",
    "sg:province":"Nordrhein-Westfalen",
    "wof:name":"Carl Schmittseifer",
    "wof:placetype":"venue"
},
  "geometry": {"coordinates":[7.5386910439,50.9838562012],"type":"Point"}
}