{
  "type": "Feature",
  "properties": {
    "iso:country":"DE",
    "sg:address":"Friedhofsweg 2",
    "sg:city":"Hemmoor",
    "sg:phone":"+49 4771/2469",
    "sg:postcode":"21745",
    "sg:province":"Niedersachsen",
    "wof:name":"Erich Tiedemann",
    "wof:placetype":"venue"
},
  "geometry": {"coordinates":[9.1521911621,53.6916236877],"type":"Point"}
}