{
  "type": "Feature",
  "properties": {
    "iso:country":"DE",
    "sg:address":"Kapuzinerstr. 20",
    "sg:city":"Dillingen",
    "sg:phone":"+49 9071/9080",
    "sg:postcode":"89407",
    "sg:province":"Bayern",
    "wof:name":"Cafe-restaurant Josef Holzbock",
    "wof:placetype":"venue"
},
  "geometry": {"coordinates":[10.4955759048,48.5808258057],"type":"Point"}
}