{
  "type": "Feature",
  "properties": {
    "iso:country":"DE",
    "sg:address":"Heerstr. 6",
    "sg:city":"Straubing",
    "sg:phone":"+49 9421/80524",
    "sg:postcode":"94315",
    "sg:province":"Bayern",
    "wof:name":"Hans Fruhstorfer Inh. Klaus F\u00f6rg",
    "wof:placetype":"venue"
},
  "geometry": {"coordinates":[12.577457,48.880875],"type":"Point"}
}