{
  "type": "Feature",
  "properties": {
    "iso:country":"DE",
    "sg:address":"Altenweddinger Str. 24",
    "sg:city":"Bahrendorf",
    "sg:phone":"+49 39205/21285",
    "sg:postcode":"39171",
    "sg:province":"Sachsen-Anhalt",
    "wof:name":"Lothar K\u00e4rsten",
    "wof:placetype":"venue"
},
  "geometry": {"coordinates":[11.557601,51.996952],"type":"Point"}
}