{
  "type": "Feature",
  "properties": {
    "iso:country":"DE",
    "sg:address":"Kapellenstr. 2",
    "sg:city":"K\u00f6ln",
    "sg:phone":"+49 2233/21165",
    "sg:postcode":"50997",
    "sg:province":"Nordrhein-Westfalen",
    "wof:name":"Josef Kn\u00fcttgen",
    "wof:placetype":"venue"
},
  "geometry": {"coordinates":[6.9411802292,50.8760910034],"type":"Point"}
}