{
  "type": "Feature",
  "properties": {
    "iso:country":"DE",
    "sg:address":"Siegburger Str. 25",
    "sg:city":"Bonn",
    "sg:phone":"+49 228/478802",
    "sg:postcode":"53229",
    "sg:province":"Nordrhein-Westfalen",
    "wof:name":"Mini Pizza Angelo",
    "wof:placetype":"venue"
},
  "geometry": {"coordinates":[7.1291890144,50.7407112122],"type":"Point"}
}