{
  "type": "Feature",
  "properties": {
    "iso:country":"DE",
    "sg:address":"Friedensstr. 31",
    "sg:city":"Zittau",
    "sg:phone":"+49 3583/680102",
    "sg:postcode":"02763",
    "sg:province":"Sachsen",
    "wof:name":"O. Pramor",
    "wof:placetype":"venue"
},
  "geometry": {"coordinates":[14.815596,50.886185],"type":"Point"}
}