{
  "type": "Feature",
  "properties": {
    "iso:country":"DE",
    "sg:address":"Tuchplatz 3",
    "sg:city":"Altheim",
    "sg:phone":"+49 7340/7015",
    "sg:postcode":"89174",
    "sg:province":"Baden-W\u00fcrttemberg",
    "wof:name":"G. Keller Immobilienmakler",
    "wof:placetype":"venue"
},
  "geometry": {"coordinates":[10.0273828506,48.5856781006],"type":"Point"}
}