{
  "type": "Feature",
  "properties": {
    "iso:country":"DE",
    "sg:address":"M\u00fchlstr. 20",
    "sg:city":"T\u00fcbingen",
    "sg:phone":"+49 7071/92480",
    "sg:postcode":"72074",
    "sg:province":"Baden-W\u00fcrttemberg",
    "wof:name":"Edwin Raiser Architekt",
    "wof:placetype":"venue"
},
  "geometry": {"coordinates":[9.05779,48.521263],"type":"Point"}
}