{
  "type": "Feature",
  "properties": {
    "iso:country":"DE",
    "sg:address":"St.-Pauli-Str. 46",
    "sg:city":"Bremen",
    "sg:phone":"+49 421/700725",
    "sg:postcode":"28203",
    "sg:province":"Bremen",
    "wof:name":"Lloyd-druckerei Willi Bauer E. Kfm.",
    "wof:placetype":"venue"
},
  "geometry": {"coordinates":[8.819859,53.071449],"type":"Point"}
}