{
  "type": "Feature",
  "properties": {
    "iso:country":"DE",
    "sg:address":"\u00dcber dem Hainberg 5",
    "sg:city":"Weilburg",
    "sg:phone":"+49 6471/92640",
    "sg:postcode":"35781",
    "sg:province":"Hessen",
    "wof:name":"Lauk\u00f6tter Werbeagentur Gmbh",
    "wof:placetype":"venue"
},
  "geometry": {"coordinates":[8.259005,50.486065],"type":"Point"}
}