{
  "type": "Feature",
  "properties": {
    "iso:country":"DE",
    "sg:address":"Bachwiesenstr. 59",
    "sg:city":"Bad Steben",
    "sg:phone":"+49 9288/8724",
    "sg:postcode":"95138",
    "sg:province":"Bayern",
    "wof:name":"G\u00e4stehaus J. Sp\u00f6rl",
    "wof:placetype":"venue"
},
  "geometry": {"coordinates":[11.6199636459,50.3655776978],"type":"Point"}
}