{
  "type": "Feature",
  "properties": {
    "iso:country":"DE",
    "sg:address":"Liebigstr. 12",
    "sg:city":"Weiden",
    "sg:phone":"+49 961/37222",
    "sg:postcode":"92637",
    "sg:province":"Bayern",
    "wof:name":"Dsd Gastronomie- Und Entertainment Gmbh",
    "wof:placetype":"venue"
},
  "geometry": {"coordinates":[6.825429,50.940239],"type":"Point"}
}