{
  "type": "Feature",
  "properties": {
    "iso:country":"DE",
    "sg:address":"Bahnhofstr. 30",
    "sg:city":"Meppen",
    "sg:phone":"+49 5931/6456",
    "sg:postcode":"49716",
    "sg:province":"Niedersachsen",
    "wof:name":"Carl Keller",
    "wof:placetype":"venue"
},
  "geometry": {"coordinates":[7.2956018448,52.6951904297],"type":"Point"}
}