{
  "type": "Feature",
  "properties": {
    "iso:country":"DE",
    "sg:address":"Gormannsgasse 13",
    "sg:city":"M\u00f6nchengladbach",
    "sg:phone":"+49 2166/57424",
    "sg:postcode":"41189",
    "sg:province":"Nordrhein-Westfalen",
    "wof:name":"Helmut Conen",
    "wof:placetype":"venue"
},
  "geometry": {"coordinates":[6.414773941,51.0971260071],"type":"Point"}
}