{
  "type": "Feature",
  "properties": {
    "iso:country":"DE",
    "sg:address":"Pr\u00e4sident-Herwig-Str. 57-59",
    "sg:city":"Cuxhaven",
    "sg:phone":"+49 4721/63587",
    "sg:postcode":"27472",
    "sg:province":"Niedersachsen",
    "wof:name":"Futtermarkt Am Hafen Und Handelsgesellschaft Mbh",
    "wof:placetype":"venue"
},
  "geometry": {"coordinates":[8.7061357498,53.8640365601],"type":"Point"}
}