{
  "type": "Feature",
  "properties": {
    "iso:country":"DE",
    "sg:address":"Gemeinerstr. 3b",
    "sg:city":"Regensburg",
    "sg:phone":"+49 941/73812",
    "sg:postcode":"93053",
    "sg:province":"Bayern",
    "wof:name":"Hans Schwarzmayr",
    "wof:placetype":"venue"
},
  "geometry": {"coordinates":[12.1037769318,49.0101470947],"type":"Point"}
}