{
  "type": "Feature",
  "properties": {
    "iso:country":"DE",
    "sg:address":"Am Blink 5",
    "sg:city":"Wanna",
    "sg:phone":"+49 4757/413",
    "sg:postcode":"21776",
    "sg:province":"Niedersachsen",
    "wof:name":"Werner Busch",
    "wof:placetype":"venue"
},
  "geometry": {"coordinates":[8.809964,53.737686],"type":"Point"}
}