{
  "type": "Feature",
  "properties": {
    "iso:country":"DE",
    "sg:address":"Naglergasse 4",
    "sg:city":"Hindelang",
    "sg:phone":"+49 8324/634",
    "sg:postcode":"87541",
    "sg:province":"Bayern",
    "wof:name":"Pension Haus Keck",
    "wof:placetype":"venue"
},
  "geometry": {"coordinates":[10.384514,47.502586],"type":"Point"}
}