{
  "type": "Feature",
  "properties": {
    "iso:country":"DE",
    "sg:address":"Wilsumer Str. 24",
    "sg:city":"Itterbeck",
    "sg:postcode":"49847",
    "sg:province":"Niedersachsen",
    "wof:name":"Aaco Gastronomie Gmbh",
    "wof:placetype":"venue"
},
  "geometry": {"coordinates":[6.8108978271,52.5125007629],"type":"Point"}
}