{
  "type": "Feature",
  "properties": {
    "iso:country":"DE",
    "sg:address":"Waltroper Str. 60",
    "sg:city":"L\u00fcnen",
    "sg:phone":"+49 231/874045",
    "sg:postcode":"44536",
    "sg:province":"Nordrhein-Westfalen",
    "wof:name":"E. Safarpour",
    "wof:placetype":"venue"
},
  "geometry": {"coordinates":[7.4374761581,51.5998153687],"type":"Point"}
}