{
  "type": "Feature",
  "properties": {
    "iso:country":"DE",
    "sg:address":"Weiherstr. 3",
    "sg:city":"Pforzheim",
    "sg:phone":"+49 7231/23567",
    "sg:postcode":"75173",
    "sg:province":"Baden-W\u00fcrttemberg",
    "wof:name":"Kath. Pfarramt Herz-jesu",
    "wof:placetype":"venue"
},
  "geometry": {"coordinates":[8.6987085342,48.8885993958],"type":"Point"}
}