{
  "type": "Feature",
  "properties": {
    "iso:country":"DE",
    "sg:address":"Rochusstr. 274",
    "sg:city":"Bonn",
    "sg:phone":"+49 228/646408",
    "sg:postcode":"53123",
    "sg:province":"Nordrhein-Westfalen",
    "wof:name":"Ingeborg Bayer",
    "wof:placetype":"venue"
},
  "geometry": {"coordinates":[7.0443401337,50.7137336731],"type":"Point"}
}