{
  "type": "Feature",
  "properties": {
    "iso:country":"DE",
    "sg:address":"Bahnhofstr 46",
    "sg:city":"Lehrte",
    "sg:phone":"+49 5132/825550",
    "sg:postcode":"31275",
    "sg:province":"Niedersachsen",
    "wof:name":"A.a.a. Holk & Partner Gmbh Acryl-alu-akustik",
    "wof:placetype":"venue"
},
  "geometry": {"coordinates":[9.970113,52.379215],"type":"Point"}
}