{
  "type": "Feature",
  "properties": {
    "iso:country":"DE",
    "sg:address":"Volmarsteiner Str. 1-9",
    "sg:city":"Hagen",
    "sg:phone":"+49 2331/3870",
    "sg:postcode":"58089",
    "sg:province":"Nordrhein-Westfalen",
    "wof:name":"Otto Mansfeld Gmbh & Co. Kg",
    "wof:placetype":"venue"
},
  "geometry": {"coordinates":[7.398385,51.370277],"type":"Point"}
}