{
  "type": "Feature",
  "properties": {
    "iso:country":"DE",
    "sg:address":"Kluser Str. 17",
    "sg:city":"L\u00fcdenscheid",
    "sg:postcode":"58511",
    "sg:province":"Nordrhein-Westfalen",
    "wof:name":"Emrahs Haarstudio Gmbh",
    "wof:placetype":"venue"
},
  "geometry": {"coordinates":[7.6397461891,51.2197113037],"type":"Point"}
}