{
  "type": "Feature",
  "properties": {
    "iso:country":"DE",
    "sg:address":"Benzstr. 24 b",
    "sg:city":"Bottrop",
    "sg:phone":"+49 2041/730177",
    "sg:postcode":"46238",
    "sg:province":"Nordrhein-Westfalen",
    "wof:name":"Ulrich Hermann",
    "wof:placetype":"venue"
},
  "geometry": {"coordinates":[6.9602150917,51.5357208252],"type":"Point"}
}