{
  "type": "Feature",
  "properties": {
    "iso:country":"DE",
    "sg:address":"Bahnhofstr. 134",
    "sg:city":"Duisburg",
    "sg:phone":"+49 203/442999",
    "sg:postcode":"47137",
    "sg:province":"Nordrhein-Westfalen",
    "wof:name":"L\u00f6wen-apotheke",
    "wof:placetype":"venue"
},
  "geometry": {"coordinates":[6.777641,51.465225],"type":"Point"}
}