{
  "type": "Feature",
  "properties": {
    "iso:country":"DE",
    "sg:address":"Niem\u00f6llerstr. 1-2",
    "sg:city":"Belzig",
    "sg:phone":"+49 33841/910",
    "sg:postcode":"14806",
    "sg:province":"Brandenburg",
    "wof:name":"Kreisarchiv Landkreis Belzig",
    "wof:placetype":"venue"
},
  "geometry": {"coordinates":[12.584319,52.141743],"type":"Point"}
}