{
  "type": "Feature",
  "properties": {
    "iso:country":"DE",
    "sg:address":"Schlo\u00dfstr. 42",
    "sg:city":"Falkenstein",
    "sg:phone":"+49 3745/6877",
    "sg:postcode":"08223",
    "sg:province":"Sachsen",
    "wof:name":"Joachim Ruhs",
    "wof:placetype":"venue"
},
  "geometry": {"coordinates":[12.367115,50.47398],"type":"Point"}
}