{
  "type": "Feature",
  "properties": {
    "iso:country":"DE",
    "sg:address":"Pasinger Str. 6",
    "sg:city":"Gr\u00e4felfing",
    "sg:phone":"+49 89/851931",
    "sg:postcode":"82166",
    "sg:province":"Bayern",
    "wof:name":"Restaurant Kabir",
    "wof:placetype":"venue"
},
  "geometry": {"coordinates":[11.4373760223,48.1165847778],"type":"Point"}
}