{
  "type": "Feature",
  "properties": {
    "iso:country":"DE",
    "sg:address":"Am Rathaus 6",
    "sg:city":"Hauzenberg",
    "sg:phone":"+49 8586/1216",
    "sg:postcode":"94051",
    "sg:province":"Bayern",
    "wof:name":"Zum Stemplinger Hansl Ohg",
    "wof:placetype":"venue"
},
  "geometry": {"coordinates":[13.623452,48.652462],"type":"Point"}
}