{
  "type": "Feature",
  "properties": {
    "iso:country":"DE",
    "sg:address":"Fontaneweg 1",
    "sg:city":"Gie\u00dfen",
    "sg:phone":"+49 641/22339",
    "sg:postcode":"35398",
    "sg:province":"Hessen",
    "wof:name":"Lothar Schaum",
    "wof:placetype":"venue"
},
  "geometry": {"coordinates":[8.638081,50.557121],"type":"Point"}
}