{
  "type": "Feature",
  "properties": {
    "iso:country":"DE",
    "sg:address":"Gravensteiner Weg 12",
    "sg:city":"Rendsburg",
    "sg:postcode":"24768",
    "sg:province":"Schleswig-Holstein",
    "wof:name":"Media Tec Gmbh",
    "wof:placetype":"venue"
},
  "geometry": {"coordinates":[9.689661026,54.3055648804],"type":"Point"}
}