{
  "type": "Feature",
  "properties": {
    "iso:country":"DE",
    "sg:address":"Hauptstr. 17",
    "sg:city":"Ergoldsbach",
    "sg:phone":"+49 8771/3691",
    "sg:postcode":"84061",
    "sg:province":"Bayern",
    "wof:name":"Preissers",
    "wof:placetype":"venue"
},
  "geometry": {"coordinates":[12.203829,48.691116],"type":"Point"}
}