{
  "type": "Feature",
  "properties": {
    "iso:country":"DE",
    "sg:address":"Goethestr. 4",
    "sg:city":"Plettenberg",
    "sg:phone":"+49 2391/925222",
    "sg:postcode":"58840",
    "sg:province":"Nordrhein-Westfalen",
    "wof:name":"Hiby Tec Gmbh",
    "wof:placetype":"venue"
},
  "geometry": {"coordinates":[7.8815250397,51.2121810913],"type":"Point"}
}