{
  "type": "Feature",
  "properties": {
    "iso:country":"DE",
    "sg:address":"Ringgasse 4",
    "sg:city":"Bad K\u00f6nigshofen",
    "sg:phone":"+49 9761/1592",
    "sg:postcode":"97631",
    "sg:province":"Bayern",
    "wof:name":"H. Morber",
    "wof:placetype":"venue"
},
  "geometry": {"coordinates":[10.447116,50.286522],"type":"Point"}
}