{
  "type": "Feature",
  "properties": {
    "iso:country":"DE",
    "sg:address":"Olper H\u00fctte 4",
    "sg:city":"Olpe",
    "sg:phone":"+49 2761/65660",
    "sg:postcode":"57462",
    "sg:province":"Nordrhein-Westfalen",
    "wof:name":"Horst G. Zeppenfeld",
    "wof:placetype":"venue"
},
  "geometry": {"coordinates":[7.8632230759,51.0323486328],"type":"Point"}
}