{
  "type": "Feature",
  "properties": {
    "iso:country":"DE",
    "sg:address":"Buchenstr 15",
    "sg:city":"Sasbach",
    "sg:phone":"+49 7841/664910",
    "sg:postcode":"77880",
    "sg:province":"Baden-W\u00fcrttemberg",
    "wof:name":"Pickering Interfaces Gmbh",
    "wof:placetype":"venue"
},
  "geometry": {"coordinates":[8.114458,48.629135],"type":"Point"}
}