{
  "type": "Feature",
  "properties": {
    "iso:country":"DE",
    "sg:address":"Wetzlarer Str. 38",
    "sg:city":"Mittenaar",
    "sg:phone":"+49 6444/366",
    "sg:postcode":"35756",
    "sg:province":"Hessen",
    "wof:name":"Reiner Conrad",
    "wof:placetype":"venue"
},
  "geometry": {"coordinates":[8.415414,50.6688],"type":"Point"}
}