{
  "type": "Feature",
  "properties": {
    "iso:country":"DE",
    "sg:address":"Am Heidehang 17",
    "sg:city":"Mechernich",
    "sg:phone":"+49 2256/3463",
    "sg:postcode":"53894",
    "sg:province":"Nordrhein-Westfalen",
    "wof:name":"L. Salewski",
    "wof:placetype":"venue"
},
  "geometry": {"coordinates":[6.7046790123,50.637512207],"type":"Point"}
}