{
  "type": "Feature",
  "properties": {
    "iso:country":"DE",
    "sg:address":"Gro\u00dfe Bleiche 19",
    "sg:city":"Mainz",
    "sg:phone":"+49 6131/223838",
    "sg:postcode":"55116",
    "sg:province":"Rheinland-Pfalz",
    "wof:name":"Restaurant Lucky",
    "wof:placetype":"venue"
},
  "geometry": {"coordinates":[8.2650737762,50.0013046265],"type":"Point"}
}