{
  "type": "Feature",
  "properties": {
    "iso:country":"DE",
    "sg:address":"Ringstr. 199",
    "sg:city":"Essen",
    "sg:phone":"+49 2054/970870",
    "sg:postcode":"45219",
    "sg:province":"Nordrhein-Westfalen",
    "wof:name":"Rainer Alt Bauunternehmung Gmbh",
    "wof:placetype":"venue"
},
  "geometry": {"coordinates":[6.931496,51.35696],"type":"Point"}
}