{
  "type": "Feature",
  "properties": {
    "iso:country":"DE",
    "sg:address":"Waldseestr. 5",
    "sg:city":"Gommern",
    "sg:phone":"+49 39200/53453",
    "sg:postcode":"39245",
    "sg:province":"Sachsen-Anhalt",
    "wof:name":"B. Hintze Und T. Steeger",
    "wof:placetype":"venue"
},
  "geometry": {"coordinates":[11.8122301102,52.0668067932],"type":"Point"}
}