{
  "type": "Feature",
  "properties": {
    "iso:country":"DE",
    "sg:address":"Sigmaringer Str. 163 Ebingen",
    "sg:city":"Albstadt",
    "sg:phone":"+49 4969/301091",
    "sg:postcode":"72458",
    "sg:province":"Baden-W\u00fcrttemberg",
    "wof:name":"Acr Lautsprechersysteme Gmbh",
    "wof:placetype":"venue"
},
  "geometry": {"coordinates":[8.5431470871,50.1062965393],"type":"Point"}
}