{
  "type": "Feature",
  "properties": {
    "iso:country":"DE",
    "sg:address":"G\u00f6schwitzer Str 51-52",
    "sg:city":"Jena",
    "sg:phone":"+49 3641/220320",
    "sg:postcode":"07745",
    "sg:province":"Th\u00fcringen",
    "wof:name":"Asclepion Laser Technologies Gmbh",
    "wof:placetype":"venue"
},
  "geometry": {"coordinates":[11.595878,50.8866],"type":"Point"}
}