{
  "type": "Feature",
  "properties": {
    "iso:country":"DE",
    "sg:address":"Fabrikstr. 1",
    "sg:city":"Dirlewang",
    "sg:postcode":"87742",
    "sg:province":"Bayern",
    "wof:name":"Albert Frey Verpackungsent- Wicklungen Und Vertriebs-gmbh",
    "wof:placetype":"venue"
},
  "geometry": {"coordinates":[10.5253591537,47.9969177246],"type":"Point"}
}