{
  "type": "Feature",
  "properties": {
    "iso:country":"DE",
    "sg:address":"Hauptstr. 139",
    "sg:city":"Appenweier",
    "sg:phone":"+49 7805/59916",
    "sg:postcode":"77767",
    "sg:province":"Baden-W\u00fcrttemberg",
    "wof:name":"Braun",
    "wof:placetype":"venue"
},
  "geometry": {"coordinates":[7.970807,48.548676],"type":"Point"}
}