{
  "type": "Feature",
  "properties": {
    "iso:country":"DE",
    "sg:address":"Gregorstr. 19",
    "sg:city":"Aachen",
    "sg:phone":"+49 241/64779",
    "sg:postcode":"52066",
    "sg:province":"Nordrhein-Westfalen",
    "wof:name":"B & B Radsport Handels Gmbh",
    "wof:placetype":"venue"
},
  "geometry": {"coordinates":[6.09244,50.760155],"type":"Point"}
}