{
  "type": "Feature",
  "properties": {
    "iso:country":"DE",
    "sg:address":"Humboldtstr. 9",
    "sg:city":"Ludwigshafen",
    "sg:phone":"+49 621/651236",
    "sg:postcode":"67069",
    "sg:province":"Rheinland-Pfalz",
    "wof:name":"A. Appel Heissmangel",
    "wof:placetype":"venue"
},
  "geometry": {"coordinates":[8.3999204636,49.5263748169],"type":"Point"}
}