{
  "type": "Feature",
  "properties": {
    "iso:country":"DE",
    "sg:address":"Singergartenweg 6",
    "sg:city":"Roding",
    "sg:phone":"+49 9469/343",
    "sg:postcode":"93426",
    "sg:province":"Bayern",
    "wof:name":"E. Niklas Sen.",
    "wof:placetype":"venue"
},
  "geometry": {"coordinates":[12.4230623245,49.2346229553],"type":"Point"}
}