{
  "type": "Feature",
  "properties": {
    "iso:country":"DE",
    "sg:address":"Heinrich-Hoffmann-Str. 5",
    "sg:city":"Zwickau",
    "sg:phone":"+49 375/784310",
    "sg:postcode":"08062",
    "sg:province":"Sachsen",
    "wof:name":"Dr. E. Baumann Architekt",
    "wof:placetype":"venue"
},
  "geometry": {"coordinates":[12.474937,50.688324],"type":"Point"}
}