{
  "type": "Feature",
  "properties": {
    "iso:country":"DE",
    "sg:address":"Doberaner Str. 108",
    "sg:city":"Rostock",
    "sg:phone":"+49 381/2016815",
    "sg:postcode":"18057",
    "sg:province":"Mecklenburg-Vorpommern",
    "wof:name":"Hannelore Jahnke Drogerie",
    "wof:placetype":"venue"
},
  "geometry": {"coordinates":[12.112957,54.092045],"type":"Point"}
}