{
  "type": "Feature",
  "properties": {
    "iso:country":"DE",
    "sg:address":"Landesstr. 50",
    "sg:city":"Nordstemmen",
    "sg:phone":"+49 5069/2002",
    "sg:postcode":"31171",
    "sg:province":"Niedersachsen",
    "wof:name":"Raiffeisen Warengenossenschaft Gronau Eg",
    "wof:placetype":"venue"
},
  "geometry": {"coordinates":[9.81371,52.194931],"type":"Point"}
}