{
  "type": "Feature",
  "properties": {
    "iso:country":"DE",
    "sg:address":"Fr\u00f6belstr. 7",
    "sg:city":"Magdeburg",
    "sg:phone":"+49 391/30179",
    "sg:postcode":"39110",
    "sg:province":"Sachsen-Anhalt",
    "wof:name":"J. Igel",
    "wof:placetype":"venue"
},
  "geometry": {"coordinates":[11.6017942429,52.1285324097],"type":"Point"}
}