{
  "type": "Feature",
  "properties": {
    "iso:country":"DE",
    "sg:address":"Heilkenstr. 8a",
    "sg:city":"Wetter",
    "sg:phone":"+49 2335/96030",
    "sg:postcode":"58300",
    "sg:province":"Nordrhein-Westfalen",
    "wof:name":"Peter Janek Architekturb\u00fcro",
    "wof:placetype":"venue"
},
  "geometry": {"coordinates":[7.378751,51.373104],"type":"Point"}
}