{
  "type": "Feature",
  "properties": {
    "iso:country":"DE",
    "sg:address":"Sedentaler Str. 105",
    "sg:city":"Erkrath",
    "sg:phone":"+49 2104/45101",
    "sg:postcode":"40699",
    "sg:province":"Nordrhein-Westfalen",
    "wof:name":"Stadtb\u00fccherei Erkrath Hochdahl 1",
    "wof:placetype":"venue"
},
  "geometry": {"coordinates":[6.961092,51.207287],"type":"Point"}
}