{
  "type": "Feature",
  "properties": {
    "iso:country":"DE",
    "sg:address":"Gro\u00dfkopfstr. 6-7",
    "sg:city":"Berlin",
    "sg:postcode":"13403",
    "sg:province":"Berlin",
    "wof:name":"Hls Leasing Gmbh",
    "wof:placetype":"venue"
},
  "geometry": {"coordinates":[13.3305015564,52.565574646],"type":"Point"}
}