{
  "type": "Feature",
  "properties": {
    "iso:country":"DE",
    "sg:address":"Hirtenstr. 13",
    "sg:city":"Spechbach",
    "sg:phone":"+49 6226/41946",
    "sg:postcode":"74937",
    "sg:province":"Baden-W\u00fcrttemberg",
    "wof:name":"W. Herbold",
    "wof:placetype":"venue"
},
  "geometry": {"coordinates":[8.887178,49.347839],"type":"Point"}
}