{
  "type": "Feature",
  "properties": {
    "iso:country":"DE",
    "sg:address":"Herzog-Heinrich-Str. 24",
    "sg:city":"M\u00fcnchen",
    "sg:phone":"+49 89/74724719",
    "sg:postcode":"80336",
    "sg:province":"Bayern",
    "wof:name":"Adwork Gmbh",
    "wof:placetype":"venue"
},
  "geometry": {"coordinates":[11.5555830002,48.1297950745],"type":"Point"}
}