{
  "type": "Feature",
  "properties": {
    "iso:country":"DE",
    "sg:address":"Karl-Br\u00f6ger-Str. 9/St.1",
    "sg:city":"N\u00fcrnberg",
    "sg:phone":"+49 911/45080",
    "sg:postcode":"90459",
    "sg:province":"Bayern",
    "wof:name":"Awo Bezirksverband Ober & Mittel- Franken",
    "wof:placetype":"venue"
},
  "geometry": {"coordinates":[11.08096,49.437519],"type":"Point"}
}