{
  "type": "Feature",
  "properties": {
    "iso:country":"DE",
    "sg:address":"Thiergartenstr. 94",
    "sg:city":"B\u00fcdingen",
    "sg:phone":"+49 6042/7763",
    "sg:postcode":"63654",
    "sg:province":"Hessen",
    "wof:name":"Kurt Sprenger Ingenieur",
    "wof:placetype":"venue"
},
  "geometry": {"coordinates":[9.11739254,50.2763366699],"type":"Point"}
}