{
  "type": "Feature",
  "properties": {
    "iso:country":"DE",
    "sg:address":"Karl-Friedrich-Str. 13",
    "sg:city":"Emmendingen",
    "sg:phone":"+49 7641/572882",
    "sg:postcode":"79312",
    "sg:province":"Baden-W\u00fcrttemberg",
    "wof:name":"J.-t. Maier",
    "wof:placetype":"venue"
},
  "geometry": {"coordinates":[7.8467559814,48.1219940186],"type":"Point"}
}