{
  "type": "Feature",
  "properties": {
    "iso:country":"DE",
    "sg:address":"Blumenhagenstr. 6",
    "sg:city":"Hannover",
    "sg:phone":"+49 511/7010020",
    "sg:postcode":"30167",
    "sg:province":"Niedersachsen",
    "wof:name":"Harro Buttmann",
    "wof:placetype":"venue"
},
  "geometry": {"coordinates":[9.709775,52.388451],"type":"Point"}
}