{
  "type": "Feature",
  "properties": {
    "iso:country":"DE",
    "sg:address":"Wetzsteinstr. 13",
    "sg:city":"Gie\u00dfen",
    "sg:phone":"+49 641/389474",
    "sg:postcode":"35390",
    "sg:province":"Hessen",
    "wof:name":"Quantum",
    "wof:placetype":"venue"
},
  "geometry": {"coordinates":[8.6736097336,50.5878982544],"type":"Point"}
}