{
  "type": "Feature",
  "properties": {
    "iso:country":"DE",
    "sg:address":"Kr\u00e4henhoop 18",
    "sg:city":"Wolfsburg",
    "sg:phone":"+49 5361/68399",
    "sg:postcode":"38448",
    "sg:province":"Niedersachsen",
    "wof:name":"Georg Brandes Heilpraktiker",
    "wof:placetype":"venue"
},
  "geometry": {"coordinates":[10.8149528503,52.4417152405],"type":"Point"}
}