{
  "type": "Feature",
  "properties": {
    "iso:country":"DE",
    "sg:address":"Wolfsried 7",
    "sg:city":"Stiefenhofen",
    "sg:phone":"+49 8386/961147",
    "sg:postcode":"88167",
    "sg:province":"Bayern",
    "wof:name":"Xy",
    "wof:placetype":"venue"
},
  "geometry": {"coordinates":[10.0146217346,47.5820388794],"type":"Point"}
}