{
  "type": "Feature",
  "properties": {
    "iso:country":"DE",
    "sg:address":"Seestrasse 22",
    "sg:city":"Abstatt",
    "sg:phone":"+49 7062/63337",
    "sg:postcode":"74232",
    "sg:province":"Baden-W\u00fcrttemberg",
    "wof:name":"Protab Prozessortechnik Gmbh",
    "wof:placetype":"venue"
},
  "geometry": {"coordinates":[9.2947511673,49.0749931335],"type":"Point"}
}