{
  "type": "Feature",
  "properties": {
    "iso:country":"DE",
    "sg:address":"Gl\u00fcck-Auf-Str. 262",
    "sg:city":"Dorsten",
    "sg:phone":"+49 2362/947721",
    "sg:postcode":"46284",
    "sg:province":"Nordrhein-Westfalen",
    "wof:name":"Rolf Amerongen",
    "wof:placetype":"venue"
},
  "geometry": {"coordinates":[7.007758,51.672649],"type":"Point"}
}