{
  "type": "Feature",
  "properties": {
    "iso:country":"DE",
    "sg:address":"Schneiderstr. 1",
    "sg:city":"Arnstorf",
    "sg:phone":"+49 8723/2990",
    "sg:postcode":"94424",
    "sg:province":"Bayern",
    "wof:name":"Schadhauser Naturans Gmbh",
    "wof:placetype":"venue"
},
  "geometry": {"coordinates":[12.8062667847,48.564666748],"type":"Point"}
}