{
  "type": "Feature",
  "properties": {
    "iso:country":"DE",
    "sg:address":"Hauptstr. 35",
    "sg:city":"Reichenbach",
    "sg:phone":"+49 36601/5303",
    "sg:postcode":"07629",
    "sg:province":"Th\u00fcringen",
    "wof:name":"R. Lieser",
    "wof:placetype":"venue"
},
  "geometry": {"coordinates":[11.883313179,50.8709487915],"type":"Point"}
}