{
  "type": "Feature",
  "properties": {
    "iso:country":"DE",
    "sg:address":"D\u00fcrerstr. 176",
    "sg:city":"Moers",
    "sg:phone":"+49 2841/36295",
    "sg:postcode":"47447",
    "sg:province":"Nordrhein-Westfalen",
    "wof:name":"E. Geradts Steuerberaterin",
    "wof:placetype":"venue"
},
  "geometry": {"coordinates":[6.6626648903,51.4279823303],"type":"Point"}
}