{
  "type": "Feature",
  "properties": {
    "iso:country":"DE",
    "sg:address":"Kleinweingartner Weg 2",
    "sg:city":"Pleinfeld",
    "sg:phone":"+49 9144/94780",
    "sg:postcode":"91785",
    "sg:province":"Bayern",
    "wof:name":"Erwin Weber",
    "wof:placetype":"venue"
},
  "geometry": {"coordinates":[10.9906892776,49.1050415039],"type":"Point"}
}