{
  "type": "Feature",
  "properties": {
    "iso:country":"DE",
    "sg:address":"Pillenreuther Str. 55",
    "sg:city":"N\u00fcrnberg",
    "sg:phone":"+49 911/445424",
    "sg:postcode":"90459",
    "sg:province":"Bayern",
    "wof:name":"Friedrich Albig Rechtsanwalt",
    "wof:placetype":"venue"
},
  "geometry": {"coordinates":[11.0824165344,49.4395027161],"type":"Point"}
}