{
  "type": "Feature",
  "properties": {
    "iso:country":"DE",
    "sg:address":"Hei\u00dfener Str. 92",
    "sg:city":"M\u00fclheim",
    "sg:phone":"+49 4920/8472171",
    "sg:postcode":"45468",
    "sg:province":"Nordrhein-Westfalen",
    "wof:name":"Messe Bauer",
    "wof:placetype":"venue"
},
  "geometry": {"coordinates":[6.8947610855,51.4326400757],"type":"Point"}
}