{
  "type": "Feature",
  "properties": {
    "iso:country":"DE",
    "sg:address":"Klosterstr. 17",
    "sg:city":"Wallenhorst",
    "sg:phone":"+49 5407/6131",
    "sg:postcode":"49134",
    "sg:province":"Niedersachsen",
    "wof:name":"Gastst\u00e4tte M. Nieporte",
    "wof:placetype":"venue"
},
  "geometry": {"coordinates":[8.0537338257,52.3369102478],"type":"Point"}
}