{
  "type": "Feature",
  "properties": {
    "iso:country":"DE",
    "sg:address":"Esperantostr. 37",
    "sg:city":"Frankfurt",
    "sg:phone":"+49 69/6313299",
    "sg:postcode":"60598",
    "sg:province":"Hessen",
    "wof:name":"Dr. Wei\u00df & Spachmann Gmbh",
    "wof:placetype":"venue"
},
  "geometry": {"coordinates":[8.6829919815,50.0906105042],"type":"Point"}
}