{
  "type": "Feature",
  "properties": {
    "iso:country":"DE",
    "sg:address":"Bergwerkstr. 2",
    "sg:city":"Hausham",
    "sg:phone":"+49 8026/58270",
    "sg:postcode":"83734",
    "sg:province":"Bayern",
    "wof:name":"Georg H\u00f6hlein Apparatebau Und Schweisskonstruktionen Gmbh",
    "wof:placetype":"venue"
},
  "geometry": {"coordinates":[11.840958,47.751007],"type":"Point"}
}