{
  "type": "Feature",
  "properties": {
    "iso:country":"DE",
    "sg:address":"Hauptstr. 9",
    "sg:city":"Lehnin",
    "sg:postcode":"14797",
    "sg:province":"Brandenburg",
    "wof:name":"Katholisches Pfarramt Lehnin",
    "wof:placetype":"venue"
},
  "geometry": {"coordinates":[12.7448596954,52.3192100525],"type":"Point"}
}