{
  "type": "Feature",
  "properties": {
    "iso:country":"DE",
    "sg:address":"Franz-Schubert-Allee 3",
    "sg:city":"Gro\u00dfenhain",
    "sg:phone":"+49 3522/502613",
    "sg:postcode":"01558",
    "sg:province":"Sachsen",
    "wof:name":"Georg Weigel",
    "wof:placetype":"venue"
},
  "geometry": {"coordinates":[13.52849,51.293682],"type":"Point"}
}