{
  "type": "Feature",
  "properties": {
    "iso:country":"DE",
    "sg:address":"Hauptstr. 51",
    "sg:city":"Atting",
    "sg:postcode":"94348",
    "sg:province":"Bayern",
    "wof:name":"Pleischl Art E. K.",
    "wof:placetype":"venue"
},
  "geometry": {"coordinates":[12.4891767502,48.8982276917],"type":"Point"}
}