{
  "type": "Feature",
  "properties": {
    "iso:country":"DE",
    "sg:address":"Friedrich-Engels-Str. 15",
    "sg:city":"Heidenau",
    "sg:phone":"+49 3529/50570",
    "sg:postcode":"01809",
    "sg:province":"Sachsen",
    "wof:name":"Johanniter-seniorenheim Heidenau Gmbh",
    "wof:placetype":"venue"
},
  "geometry": {"coordinates":[13.875498,50.974674],"type":"Point"}
}