{
  "type": "Feature",
  "properties": {
    "iso:country":"DE",
    "sg:address":"Kinzigstr. 20",
    "sg:city":"Forst",
    "sg:phone":"+49 7251/15815",
    "sg:postcode":"76694",
    "sg:province":"Baden-W\u00fcrttemberg",
    "wof:name":"Holz-werner Gmbh",
    "wof:placetype":"venue"
},
  "geometry": {"coordinates":[8.5823297501,49.1552047729],"type":"Point"}
}