{
  "type": "Feature",
  "properties": {
    "iso:country":"DE",
    "sg:address":"Sonnentalstr. 1",
    "sg:city":"Hessisch Oldendorf",
    "sg:phone":"+49 5152/2231",
    "sg:postcode":"31840",
    "sg:province":"Niedersachsen",
    "wof:name":"B\u00e4ckerei R\u00fcgge Gmbh",
    "wof:placetype":"venue"
},
  "geometry": {"coordinates":[9.214946,52.141731],"type":"Point"}
}