{
  "type": "Feature",
  "properties": {
    "iso:country":"DE",
    "sg:address":"Rog\u00e4tzer Str.",
    "sg:city":"Wolmirstedt",
    "sg:phone":"+49 39201/20814",
    "sg:postcode":"39326",
    "sg:province":"Sachsen-Anhalt",
    "wof:name":"Rossmann Drogeriemarkt",
    "wof:placetype":"venue"
},
  "geometry": {"coordinates":[11.635825,52.258717],"type":"Point"}
}