{
  "type": "Feature",
  "properties": {
    "iso:country":"DE",
    "sg:address":"Schmalenbuchener Str. 7",
    "sg:city":"Neuhaus",
    "sg:phone":"+49 3679/722886",
    "sg:postcode":"98724",
    "sg:province":"Th\u00fcringen",
    "wof:name":"Egon Seeber",
    "wof:placetype":"venue"
},
  "geometry": {"coordinates":[11.148365,50.516514],"type":"Point"}
}