{
  "type": "Feature",
  "properties": {
    "iso:country":"DE",
    "sg:address":"Elmesp\u00f6ten 10",
    "sg:city":"R\u00fcthen",
    "sg:phone":"+49 2954/866",
    "sg:postcode":"59602",
    "sg:province":"Nordrhein-Westfalen",
    "wof:name":"P. Keinert",
    "wof:placetype":"venue"
},
  "geometry": {"coordinates":[8.4174156189,51.5052261353],"type":"Point"}
}