{
  "type": "Feature",
  "properties": {
    "iso:country":"DE",
    "sg:address":"Wenzel-Verner-Str. 10",
    "sg:city":"Chemnitz",
    "sg:postcode":"09120",
    "sg:province":"Sachsen",
    "wof:name":"Sportstudio \u00d6lschlegele",
    "wof:placetype":"venue"
},
  "geometry": {"coordinates":[12.8978128433,50.8094062805],"type":"Point"}
}