{
  "type": "Feature",
  "properties": {
    "iso:country":"DE",
    "sg:address":"Erfurter Str 52",
    "sg:city":"Stotternheim",
    "sg:phone":"+49 36204/6720",
    "sg:postcode":"99195",
    "sg:province":"Th\u00fcringen",
    "wof:name":"Mth-beton Gmbh & Co Kg",
    "wof:placetype":"venue"
},
  "geometry": {"coordinates":[11.1014146805,51.0913963318],"type":"Point"}
}