{
  "type": "Feature",
  "properties": {
    "iso:country":"DE",
    "sg:address":"Rigaer Str. 19",
    "sg:city":"Hennigsdorf",
    "sg:phone":"+49 3302/225599",
    "sg:postcode":"16761",
    "sg:province":"Brandenburg",
    "wof:name":"K.-h. Noack",
    "wof:placetype":"venue"
},
  "geometry": {"coordinates":[13.1975221634,52.6534004211],"type":"Point"}
}