{
  "type": "Feature",
  "properties": {
    "iso:country":"DE",
    "sg:address":"Im Brooken 1",
    "sg:city":"Ottersberg",
    "sg:phone":"+49 4205/618",
    "sg:postcode":"28870",
    "sg:province":"Niedersachsen",
    "wof:name":"Hans Koch",
    "wof:placetype":"venue"
},
  "geometry": {"coordinates":[9.1508369446,53.1052055359],"type":"Point"}
}