{
  "type": "Feature",
  "properties": {
    "iso:country":"DE",
    "sg:address":"Walterscheid 1",
    "sg:city":"Much",
    "sg:phone":"+49 2245/2912",
    "sg:postcode":"53804",
    "sg:province":"Nordrhein-Westfalen",
    "wof:name":"Friedrich Kemmerling",
    "wof:placetype":"venue"
},
  "geometry": {"coordinates":[7.41636,50.883461],"type":"Point"}
}