{
  "type": "Feature",
  "properties": {
    "iso:country":"DE",
    "sg:address":"Kaiser-Wilhelm-Str. 13",
    "sg:city":"B\u00fcnde",
    "sg:phone":"+49 5223/188859",
    "sg:postcode":"32257",
    "sg:province":"Nordrhein-Westfalen",
    "wof:name":"Ina Zernhoff Rechtsanw\u00e4ltin",
    "wof:placetype":"venue"
},
  "geometry": {"coordinates":[8.5868873596,52.1973266602],"type":"Point"}
}