{
  "type": "Feature",
  "properties": {
    "iso:country":"DE",
    "sg:address":"Albert-Schweitzer-Str. 51",
    "sg:city":"Halle",
    "sg:phone":"+49 345/520870",
    "sg:postcode":"06114",
    "sg:province":"Sachsen-Anhalt",
    "wof:name":"Projekt-bau",
    "wof:placetype":"venue"
},
  "geometry": {"coordinates":[11.971308,51.502018],"type":"Point"}
}