{
  "type": "Feature",
  "properties": {
    "iso:country":"DE",
    "sg:address":"An der Schule 4",
    "sg:city":"Wiesbaden",
    "sg:phone":"+49 6122/2280",
    "sg:postcode":"65205",
    "sg:province":"Hessen",
    "wof:name":"Bernd Kirchner Rechtsanwalt",
    "wof:placetype":"venue"
},
  "geometry": {"coordinates":[8.3420152664,50.0619277954],"type":"Point"}
}