{
  "type": "Feature",
  "properties": {
    "iso:country":"DE",
    "sg:address":"Clara-Zetkin-Weg 70",
    "sg:city":"Eberswalde",
    "sg:phone":"+49 3334/212131",
    "sg:postcode":"16225",
    "sg:province":"Brandenburg",
    "wof:name":"Christian Eder",
    "wof:placetype":"venue"
},
  "geometry": {"coordinates":[13.820206,52.850357],"type":"Point"}
}