{
  "type": "Feature",
  "properties": {
    "iso:country":"DE",
    "sg:address":"Dorfstr. 11",
    "sg:city":"Bargenstedt",
    "sg:phone":"+49 4832/1471",
    "sg:postcode":"25704",
    "sg:province":"Schleswig-Holstein",
    "wof:name":"W. Rohde",
    "wof:placetype":"venue"
},
  "geometry": {"coordinates":[9.1485414505,54.0963783264],"type":"Point"}
}