{
  "type": "Feature",
  "properties": {
    "iso:country":"DE",
    "sg:address":"Hauptstr. 121",
    "sg:city":"Merchweiler",
    "sg:phone":"+49 6825/5824",
    "sg:postcode":"66589",
    "sg:province":"Saarland",
    "wof:name":"Doris Albrecht",
    "wof:placetype":"venue"
},
  "geometry": {"coordinates":[7.05851,49.358959],"type":"Point"}
}