{
  "type": "Feature",
  "properties": {
    "iso:country":"DE",
    "sg:address":"Oberf\u00fcllbacher Str. 10",
    "sg:city":"Coburg",
    "sg:phone":"+49 9561/10754",
    "sg:postcode":"96450",
    "sg:province":"Bayern",
    "wof:name":"Werner Krug",
    "wof:placetype":"venue"
},
  "geometry": {"coordinates":[11.015431,50.255127],"type":"Point"}
}