{
  "type": "Feature",
  "properties": {
    "iso:country":"DE",
    "sg:address":"Arndtstr. 2",
    "sg:city":"Dortmund",
    "sg:phone":"+49 231/528689",
    "sg:postcode":"44135",
    "sg:province":"Nordrhein-Westfalen",
    "wof:name":"Amd Autovermietung Gmbh",
    "wof:placetype":"venue"
},
  "geometry": {"coordinates":[7.473069,51.512722],"type":"Point"}
}