{
  "type": "Feature",
  "properties": {
    "iso:country":"DE",
    "sg:address":"L\u00e4mmerweg 4",
    "sg:city":"Ulm",
    "sg:phone":"+49 7305/96260",
    "sg:postcode":"89079",
    "sg:province":"Baden-W\u00fcrttemberg",
    "wof:name":"G. Prinz",
    "wof:placetype":"venue"
},
  "geometry": {"coordinates":[9.9099750519,48.3530502319],"type":"Point"}
}