{
  "type": "Feature",
  "properties": {
    "iso:country":"DE",
    "sg:address":"Herpellstr. 5",
    "sg:city":"St. Goar",
    "sg:phone":"+49 6741/96278",
    "sg:postcode":"56329",
    "sg:province":"Rheinland-Pfalz",
    "wof:name":"Zwiebelgrotte",
    "wof:placetype":"venue"
},
  "geometry": {"coordinates":[7.7126660347,50.1514053345],"type":"Point"}
}