{
  "type": "Feature",
  "properties": {
    "iso:country":"DE",
    "sg:address":"Fontanestr. 66",
    "sg:city":"Cloppenburg",
    "sg:postcode":"49661",
    "sg:province":"Niedersachsen",
    "wof:name":"M & K Baubetreuungs- Gmbh",
    "wof:placetype":"venue"
},
  "geometry": {"coordinates":[8.040978,52.835186],"type":"Point"}
}