{
  "type": "Feature",
  "properties": {
    "iso:country":"DE",
    "sg:address":"Schwarzbach 138",
    "sg:city":"Wuppertal",
    "sg:phone":"+49 202/660221",
    "sg:postcode":"42277",
    "sg:province":"Nordrhein-Westfalen",
    "wof:name":"Zell Gmbh & Co. Kg",
    "wof:placetype":"venue"
},
  "geometry": {"coordinates":[7.2283668518,51.2833747864],"type":"Point"}
}