{
  "type": "Feature",
  "properties": {
    "iso:country":"DE",
    "sg:address":"Wiesentalstr. 14",
    "sg:city":"Wiesbaden",
    "sg:phone":"+49 611/540863",
    "sg:postcode":"65207",
    "sg:province":"Hessen",
    "wof:name":"Dr. Willi Wettlaufer Ingenieur",
    "wof:placetype":"venue"
},
  "geometry": {"coordinates":[8.2978172302,50.1093063354],"type":"Point"}
}