{
  "type": "Feature",
  "properties": {
    "iso:country":"DE",
    "sg:address":"Mannenstr. 60",
    "sg:city":"Moringen",
    "sg:phone":"+49 5554/993470",
    "sg:postcode":"37186",
    "sg:province":"Niedersachsen",
    "wof:name":"Stadtwerke Moringen",
    "wof:placetype":"venue"
},
  "geometry": {"coordinates":[9.876639,51.702225],"type":"Point"}
}