{
  "type": "Feature",
  "properties": {
    "iso:country":"DE",
    "sg:address":"Mozartstr. 19",
    "sg:city":"Gro\u00dfenl\u00fcder",
    "sg:phone":"+49 6648/7116",
    "sg:postcode":"36137",
    "sg:province":"Hessen",
    "wof:name":"Ferdinand Br\u00e4hler Architekt",
    "wof:placetype":"venue"
},
  "geometry": {"coordinates":[9.545183,50.590897],"type":"Point"}
}