{
  "type": "Feature",
  "properties": {
    "iso:country":"DE",
    "sg:address":"Jenastieg 16",
    "sg:city":"Braunschweig",
    "sg:phone":"+49 531/691534",
    "sg:postcode":"38124",
    "sg:province":"Niedersachsen",
    "wof:name":"Karl Michael",
    "wof:placetype":"venue"
},
  "geometry": {"coordinates":[10.534883,52.230286],"type":"Point"}
}