{
  "type": "Feature",
  "properties": {
    "iso:country":"DE",
    "sg:address":"B\u00e4ckerstr. 34 f",
    "sg:city":"M\u00fcnchen",
    "sg:phone":"+49 89/8888805",
    "sg:postcode":"81241",
    "sg:province":"Bayern",
    "wof:name":"G. Kilian",
    "wof:placetype":"venue"
},
  "geometry": {"coordinates":[11.458837,48.146893],"type":"Point"}
}