{
  "type": "Feature",
  "properties": {
    "iso:country":"DE",
    "sg:address":"Ro\u00dfbergstr. 36",
    "sg:city":"Schkeuditz",
    "sg:phone":"+49 34204/60015",
    "sg:postcode":"04435",
    "sg:province":"Sachsen",
    "wof:name":"Wolfgang Riedel",
    "wof:placetype":"venue"
},
  "geometry": {"coordinates":[12.1952981949,51.3947563171],"type":"Point"}
}