{
  "type": "Feature",
  "properties": {
    "iso:country":"DE",
    "sg:address":"Westweg 9 a",
    "sg:city":"Varel",
    "sg:phone":"+49 4451/3295",
    "sg:postcode":"26316",
    "sg:province":"Niedersachsen",
    "wof:name":"Fritz Niemeyer",
    "wof:placetype":"venue"
},
  "geometry": {"coordinates":[8.118266,53.419621],"type":"Point"}
}