{
  "type": "Feature",
  "properties": {
    "iso:country":"DE",
    "sg:address":"Berliner Str. 4",
    "sg:city":"Berlin",
    "sg:phone":"+49 30/4747910",
    "sg:postcode":"13127",
    "sg:province":"Berlin",
    "wof:name":"Trockel & Zingelmann Zimmerei Gmbh",
    "wof:placetype":"venue"
},
  "geometry": {"coordinates":[13.4328203201,52.5971450806],"type":"Point"}
}