{
  "type": "Feature",
  "properties": {
    "iso:country":"DE",
    "sg:address":"Firnhaberstr. 1",
    "sg:city":"Nordhorn",
    "sg:phone":"+49 5921/88727",
    "sg:postcode":"48529",
    "sg:province":"Niedersachsen",
    "wof:name":"Buddelei Gmbh",
    "wof:placetype":"venue"
},
  "geometry": {"coordinates":[7.070842,52.434978],"type":"Point"}
}