{
  "type": "Feature",
  "properties": {
    "iso:country":"DE",
    "sg:address":"Friedrichstr. 127",
    "sg:city":"Rheinfelden",
    "sg:phone":"+49 7623/1489",
    "sg:postcode":"79618",
    "sg:province":"Baden-W\u00fcrttemberg",
    "wof:name":"Probst Mineral\u00f6le",
    "wof:placetype":"venue"
},
  "geometry": {"coordinates":[7.8019361496,47.5705337524],"type":"Point"}
}