{
  "type": "Feature",
  "properties": {
    "iso:country":"DE",
    "sg:address":"Christazhofen",
    "sg:city":"Argenb\u00fchl",
    "sg:phone":"+49 7566/1263",
    "sg:postcode":"88260",
    "sg:province":"Baden-W\u00fcrttemberg",
    "wof:name":"Karl Hengge",
    "wof:placetype":"venue"
},
  "geometry": {"coordinates":[9.90613,47.722542],"type":"Point"}
}