{
  "type": "Feature",
  "properties": {
    "iso:country":"DE",
    "sg:address":"Pfaffengasse 24",
    "sg:city":"Aschaffenburg",
    "sg:postcode":"63739",
    "sg:province":"Bayern",
    "wof:name":"Staatl. Verwaltetes Studienseminar",
    "wof:placetype":"venue"
},
  "geometry": {"coordinates":[9.1443424225,49.9749794006],"type":"Point"}
}