{
  "type": "Feature",
  "properties": {
    "iso:country":"DE",
    "sg:address":"Steindamm 42",
    "sg:city":"Kronshagen",
    "sg:phone":"+49 431/582104",
    "sg:postcode":"24119",
    "sg:province":"Schleswig-Holstein",
    "wof:name":"Hans Klein Architekt",
    "wof:placetype":"venue"
},
  "geometry": {"coordinates":[10.081324,54.3358],"type":"Point"}
}