{
  "type": "Feature",
  "properties": {
    "iso:country":"DE",
    "sg:address":"Nieperfitz 9",
    "sg:city":"Nahrendorf",
    "sg:phone":"+49 5855/439",
    "sg:postcode":"21369",
    "sg:province":"Niedersachsen",
    "wof:name":"Helga Br\u00fcggemann",
    "wof:placetype":"venue"
},
  "geometry": {"coordinates":[10.872126,53.161331],"type":"Point"}
}