{
  "type": "Feature",
  "properties": {
    "iso:country":"DE",
    "sg:address":"Max-Eyth-Allee",
    "sg:city":"Potsdam",
    "sg:phone":"+49 331/501193",
    "sg:postcode":"14469",
    "sg:province":"Brandenburg",
    "wof:name":"Luka",
    "wof:placetype":"venue"
},
  "geometry": {"coordinates":[13.0140447617,52.4391746521],"type":"Point"}
}