{
  "type": "Feature",
  "properties": {
    "iso:country":"DE",
    "sg:address":"Bergstr. 1",
    "sg:city":"Mettmann",
    "sg:phone":"+49 2104/16465",
    "sg:postcode":"40822",
    "sg:province":"Nordrhein-Westfalen",
    "wof:name":"Bergklause",
    "wof:placetype":"venue"
},
  "geometry": {"coordinates":[6.9874458313,51.250289917],"type":"Point"}
}