{
  "type": "Feature",
  "properties": {
    "iso:country":"DE",
    "sg:address":"Bahnhofstr. 10",
    "sg:city":"Marbach",
    "sg:postcode":"71672",
    "sg:province":"Baden-W\u00fcrttemberg",
    "wof:name":"R. Von D\u00f6ry",
    "wof:placetype":"venue"
},
  "geometry": {"coordinates":[9.724461,50.617271],"type":"Point"}
}