{
  "type": "Feature",
  "properties": {
    "iso:country":"DE",
    "sg:address":"B\u00fcrgerm.-Bachmann-Str. 21",
    "sg:city":"Wald-Michelbach",
    "sg:phone":"+49 6207/2610",
    "sg:postcode":"69483",
    "sg:province":"Hessen",
    "wof:name":"Dieter Feist Immobilienmakler Vdm",
    "wof:placetype":"venue"
},
  "geometry": {"coordinates":[8.8239593506,49.5772094727],"type":"Point"}
}