{
  "type": "Feature",
  "properties": {
    "iso:country":"DE",
    "sg:address":"Liebigstr. 61",
    "sg:city":"Duisburg",
    "sg:phone":"+49 203/996380",
    "sg:postcode":"47053",
    "sg:province":"Nordrhein-Westfalen",
    "wof:name":"Remex Duisburg Gesellschaft F\u00fcr Baustoffaufbereitung Mbh",
    "wof:placetype":"venue"
},
  "geometry": {"coordinates":[6.74889,51.410709],"type":"Point"}
}