{
  "type": "Feature",
  "properties": {
    "iso:country":"DE",
    "sg:address":"Wiesenstr 14",
    "sg:city":"Lautzenbr\u00fccken",
    "sg:phone":"+49 2661/939314",
    "sg:postcode":"56472",
    "sg:province":"Rheinland-Pfalz",
    "wof:name":"Mp-mediencenter Mirko Pogacar",
    "wof:placetype":"venue"
},
  "geometry": {"coordinates":[7.963677,50.673828],"type":"Point"}
}