{
  "type": "Feature",
  "properties": {
    "iso:country":"DE",
    "sg:address":"Kriemhildenstr. 11",
    "sg:city":"Lampertheim",
    "sg:phone":"+49 6206/2225",
    "sg:postcode":"68623",
    "sg:province":"Hessen",
    "wof:name":"Arno Fippinger Masseur",
    "wof:placetype":"venue"
},
  "geometry": {"coordinates":[8.468243,49.600838],"type":"Point"}
}