{
  "type": "Feature",
  "properties": {
    "iso:country":"DE",
    "sg:address":"Am S\u00e4gewerk 5",
    "sg:city":"Baienfurt",
    "sg:phone":"+49 751/500245",
    "sg:postcode":"88255",
    "sg:province":"Baden-W\u00fcrttemberg",
    "wof:name":"B\u00fcrgergarde Gelbe Husaren Altahausen",
    "wof:placetype":"venue"
},
  "geometry": {"coordinates":[9.6249790192,47.8272628784],"type":"Point"}
}