{
  "type": "Feature",
  "properties": {
    "iso:country":"DE",
    "sg:address":"M\u00fchlenweg 48",
    "sg:city":"Gescher",
    "sg:phone":"+49 2542/4148",
    "sg:postcode":"48712",
    "sg:province":"Nordrhein-Westfalen",
    "wof:name":"A. Schellerhoff",
    "wof:placetype":"venue"
},
  "geometry": {"coordinates":[6.9878358841,51.9573020935],"type":"Point"}
}