{
  "type": "Feature",
  "properties": {
    "iso:country":"DE",
    "sg:address":"Landvogt-Johannsen-Str. 59",
    "sg:city":"Heide",
    "sg:phone":"+49 481/87959",
    "sg:postcode":"25746",
    "sg:province":"Schleswig-Holstein",
    "wof:name":"Schwimmzentrum Heide",
    "wof:placetype":"venue"
},
  "geometry": {"coordinates":[9.1137332916,54.2019042969],"type":"Point"}
}