{
  "type": "Feature",
  "properties": {
    "iso:country":"DE",
    "sg:address":"Darpestr. 8",
    "sg:city":"Bochum",
    "sg:phone":"+49 234/52666",
    "sg:postcode":"44793",
    "sg:province":"Nordrhein-Westfalen",
    "wof:name":"Rs-m\u00f6bel Gmbh",
    "wof:placetype":"venue"
},
  "geometry": {"coordinates":[7.184095,51.492111],"type":"Point"}
}