{
  "type": "Feature",
  "properties": {
    "iso:country":"DE",
    "sg:address":"Neupr\u00fcll 38",
    "sg:city":"Regensburg",
    "sg:phone":"+49 941/91965",
    "sg:postcode":"93051",
    "sg:province":"Bayern",
    "wof:name":"Otto K\u00f6rner Architekt",
    "wof:placetype":"venue"
},
  "geometry": {"coordinates":[12.08321,48.99218],"type":"Point"}
}