{
  "type": "Feature",
  "properties": {
    "iso:country":"DE",
    "sg:address":"Auf Wolfsgang",
    "sg:city":"Trierweiler",
    "sg:phone":"+49 651/810601",
    "sg:postcode":"54311",
    "sg:province":"Rheinland-Pfalz",
    "wof:name":"Mosel T\u00fcrenwerk Gmbh & Co. Kg",
    "wof:placetype":"venue"
},
  "geometry": {"coordinates":[6.589442,49.773609],"type":"Point"}
}