{
  "type": "Feature",
  "properties": {
    "iso:country":"DE",
    "sg:address":"Pfarrer-Hodecker-Str. 8",
    "sg:city":"K\u00fclsheim",
    "sg:phone":"+49 9345/6449",
    "sg:postcode":"97900",
    "sg:province":"Baden-W\u00fcrttemberg",
    "wof:name":"B. W\u00f6lfelschneider",
    "wof:placetype":"venue"
},
  "geometry": {"coordinates":[9.469669,49.688889],"type":"Point"}
}