{
  "type": "Feature",
  "properties": {
    "iso:country":"DE",
    "sg:address":"Rietheimer Str. 35-4",
    "sg:city":"Villingen-Schwenningen",
    "sg:phone":"+49 7721/903340",
    "sg:postcode":"78050",
    "sg:province":"Baden-W\u00fcrttemberg",
    "wof:name":"Helix Verbindungselemente Gmbh",
    "wof:placetype":"venue"
},
  "geometry": {"coordinates":[8.4609966278,48.0484771729],"type":"Point"}
}