{
  "type": "Feature",
  "properties": {
    "iso:country":"DE",
    "sg:address":"Breiter Weg 20",
    "sg:city":"Halberstadt",
    "sg:phone":"+49 3941/23092",
    "sg:postcode":"38820",
    "sg:province":"Sachsen-Anhalt",
    "wof:name":"Volksbank Halberstadt Eg",
    "wof:placetype":"venue"
},
  "geometry": {"coordinates":[11.053656,51.895744],"type":"Point"}
}