{
  "type": "Feature",
  "properties": {
    "iso:country":"DE",
    "sg:address":"Dorfstr. 46d",
    "sg:city":"Sch\u00f6nbeck",
    "sg:phone":"+49 3968/210414",
    "sg:postcode":"17349",
    "sg:province":"Mecklenburg-Vorpommern",
    "wof:name":"Regaltechnik Keulsh\u00fctte Vertriebs Gmbh",
    "wof:placetype":"venue"
},
  "geometry": {"coordinates":[13.571415,53.57616],"type":"Point"}
}