{
  "type": "Feature",
  "properties": {
    "iso:country":"DE",
    "sg:address":"Erdinger Str. 13",
    "sg:city":"Aschheim",
    "sg:phone":"+49 89/9043518",
    "sg:postcode":"85609",
    "sg:province":"Bayern",
    "wof:name":"Babyland Gmbh",
    "wof:placetype":"venue"
},
  "geometry": {"coordinates":[11.7194051743,48.1716270447],"type":"Point"}
}