{
  "type": "Feature",
  "properties": {
    "iso:country":"DE",
    "sg:address":"Lindenallee 54",
    "sg:city":"Rheinsberg",
    "sg:postcode":"16831",
    "sg:province":"Brandenburg",
    "wof:name":"Gerhard Conitz",
    "wof:placetype":"venue"
},
  "geometry": {"coordinates":[12.897393,53.089397],"type":"Point"}
}