{
  "type": "Feature",
  "properties": {
    "iso:country":"DE",
    "sg:address":"Sch\u00fctzenstr. 16",
    "sg:city":"Hallenberg",
    "sg:phone":"+49 2984/8337",
    "sg:postcode":"59969",
    "sg:province":"Nordrhein-Westfalen",
    "wof:name":"Pension Henze",
    "wof:placetype":"venue"
},
  "geometry": {"coordinates":[8.6149129868,51.1372947693],"type":"Point"}
}