{
  "type": "Feature",
  "properties": {
    "iso:country":"DE",
    "sg:address":"Freisinger Landstr. 64",
    "sg:city":"M\u00fcnchen",
    "sg:phone":"+49 89/3231698",
    "sg:postcode":"80939",
    "sg:province":"Bayern",
    "wof:name":"Salewa Heimtextil Gmbh",
    "wof:placetype":"venue"
},
  "geometry": {"coordinates":[11.6255493164,48.1974029541],"type":"Point"}
}