{
  "type": "Feature",
  "properties": {
    "iso:country":"DE",
    "sg:address":"Nassaustr. 17 D",
    "sg:city":"Hofheim",
    "sg:phone":"+49 6122/8168",
    "sg:postcode":"65719",
    "sg:province":"Hessen",
    "wof:name":"Schimansky",
    "wof:placetype":"venue"
},
  "geometry": {"coordinates":[8.3866968155,50.06848526],"type":"Point"}
}