{
  "type": "Feature",
  "properties": {
    "iso:country":"DE",
    "sg:address":"Futterstr. 14",
    "sg:city":"Saarbr\u00fccken",
    "sg:phone":"+49 681/36891",
    "sg:postcode":"66111",
    "sg:province":"Saarland",
    "wof:name":"A. Rheingans Inh. B. Rheingans",
    "wof:placetype":"venue"
},
  "geometry": {"coordinates":[6.994544,49.23682],"type":"Point"}
}