{
  "type": "Feature",
  "properties": {
    "iso:country":"DE",
    "sg:address":"Gartenstr. 18",
    "sg:city":"Karben",
    "sg:phone":"+49 6039/3036",
    "sg:postcode":"61184",
    "sg:province":"Hessen",
    "wof:name":"Kaden",
    "wof:placetype":"venue"
},
  "geometry": {"coordinates":[8.770776,50.229401],"type":"Point"}
}