{
  "type": "Feature",
  "properties": {
    "iso:country":"DE",
    "sg:address":"Luisenstr. 25",
    "sg:city":"M\u00fcnchen",
    "sg:phone":"+49 89/5504040",
    "sg:postcode":"80333",
    "sg:province":"Bayern",
    "wof:name":"Waschkuchl",
    "wof:placetype":"venue"
},
  "geometry": {"coordinates":[11.5627861023,48.1445808411],"type":"Point"}
}