{
  "type": "Feature",
  "properties": {
    "iso:country":"DE",
    "sg:address":"N\u00fcrnberger Str. 4",
    "sg:city":"Hanau",
    "sg:phone":"+49 6181/20269",
    "sg:postcode":"63450",
    "sg:province":"Hessen",
    "wof:name":"Conrad Fuss",
    "wof:placetype":"venue"
},
  "geometry": {"coordinates":[8.922501,50.131725],"type":"Point"}
}