{
  "type": "Feature",
  "properties": {
    "iso:country":"DE",
    "sg:address":"Liboristr. 8",
    "sg:city":"M\u00fcnster",
    "sg:phone":"+49 251/661275",
    "sg:postcode":"48155",
    "sg:province":"Nordrhein-Westfalen",
    "wof:name":"U. Bauer",
    "wof:placetype":"venue"
},
  "geometry": {"coordinates":[7.6520819664,51.9546890259],"type":"Point"}
}