{
  "type": "Feature",
  "properties": {
    "iso:country":"DE",
    "sg:address":"An der Thalach 7",
    "sg:city":"Thalm\u00e4ssing",
    "sg:phone":"+49 9173/79920",
    "sg:postcode":"91177",
    "sg:province":"Bayern",
    "wof:name":"G. Stoll",
    "wof:placetype":"venue"
},
  "geometry": {"coordinates":[11.224138,49.089447],"type":"Point"}
}