{
  "type": "Feature",
  "properties": {
    "iso:country":"DE",
    "sg:address":"Bahnhofstr. 5",
    "sg:city":"Groitzsch",
    "sg:phone":"+49 34296/40574",
    "sg:postcode":"04539",
    "sg:province":"Sachsen",
    "wof:name":"Iris Pub",
    "wof:placetype":"venue"
},
  "geometry": {"coordinates":[12.281779,51.156479],"type":"Point"}
}