{
  "type": "Feature",
  "properties": {
    "iso:country":"DE",
    "sg:address":"Neue Str. 23a",
    "sg:city":"Stadtoldendorf",
    "sg:phone":"+49 5532/4799",
    "sg:postcode":"37627",
    "sg:province":"Niedersachsen",
    "wof:name":"Polsterstudio Waldeyer Gmbh",
    "wof:placetype":"venue"
},
  "geometry": {"coordinates":[9.6271066666,51.8820228577],"type":"Point"}
}