{
  "type": "Feature",
  "properties": {
    "iso:country":"DE",
    "sg:address":"Finkenstr. 3",
    "sg:city":"Neuenstadt",
    "sg:phone":"+49 6264/371",
    "sg:postcode":"74196",
    "sg:province":"Baden-W\u00fcrttemberg",
    "wof:name":"Steffi Schmitt Hebamme",
    "wof:placetype":"venue"
},
  "geometry": {"coordinates":[9.2953,49.264324],"type":"Point"}
}