{
  "type": "Feature",
  "properties": {
    "iso:country":"DE",
    "sg:address":"Gellertstr. 10",
    "sg:city":"Hainichen",
    "sg:phone":"+49 37207/3670",
    "sg:postcode":"09661",
    "sg:province":"Sachsen",
    "wof:name":"Karin Hammerm\u00fcller",
    "wof:placetype":"venue"
},
  "geometry": {"coordinates":[13.1241979599,50.969783783],"type":"Point"}
}