{
  "type": "Feature",
  "properties": {
    "iso:country":"DE",
    "sg:address":"Sollingstr. 96",
    "sg:city":"Holzminden",
    "sg:phone":"+49 5531/6207",
    "sg:postcode":"37603",
    "sg:province":"Niedersachsen",
    "wof:name":"Christoph Schumann",
    "wof:placetype":"venue"
},
  "geometry": {"coordinates":[9.462213,51.828026],"type":"Point"}
}