{
  "type": "Feature",
  "properties": {
    "iso:country":"DE",
    "sg:address":"Pfarrer-Langenbacher-Str. 8",
    "sg:city":"Hardt",
    "sg:phone":"+49 7422/3182",
    "sg:postcode":"78739",
    "sg:province":"Baden-W\u00fcrttemberg",
    "wof:name":"Helmut Hilser",
    "wof:placetype":"venue"
},
  "geometry": {"coordinates":[8.4126358032,48.1856956482],"type":"Point"}
}