{
  "type": "Feature",
  "properties": {
    "iso:country":"DE",
    "sg:address":"Scharnweberstr. 7",
    "sg:city":"Berlin",
    "sg:phone":"+49 30/9821690",
    "sg:postcode":"13053",
    "sg:province":"Berlin",
    "wof:name":"Hans-j\u00f6rg Laubsch",
    "wof:placetype":"venue"
},
  "geometry": {"coordinates":[13.488831,52.546894],"type":"Point"}
}