{
  "type": "Feature",
  "properties": {
    "iso:country":"DE",
    "sg:address":"K\u00f6lnstr. 29",
    "sg:city":"Vettwei\u00df",
    "sg:phone":"+49 2252/2192",
    "sg:postcode":"52391",
    "sg:province":"Nordrhein-Westfalen",
    "wof:name":"Josef Schneppenheim",
    "wof:placetype":"venue"
},
  "geometry": {"coordinates":[6.670205,50.741653],"type":"Point"}
}