{
  "type": "Feature",
  "properties": {
    "iso:country":"DE",
    "sg:address":"Alpenstr. 9",
    "sg:city":"Immendingen",
    "sg:phone":"+49 7462/1777",
    "sg:postcode":"78194",
    "sg:province":"Baden-W\u00fcrttemberg",
    "wof:name":"A. Denzel",
    "wof:placetype":"venue"
},
  "geometry": {"coordinates":[8.779651,47.919903],"type":"Point"}
}