{
  "type": "Feature",
  "properties": {
    "iso:country":"DE",
    "sg:address":"Arntzstr. 2",
    "sg:city":"Kleve",
    "sg:phone":"+49 2821/17325",
    "sg:postcode":"47533",
    "sg:province":"Nordrhein-Westfalen",
    "wof:name":"Bar Madame",
    "wof:placetype":"venue"
},
  "geometry": {"coordinates":[6.133336,51.787762],"type":"Point"}
}