{
  "type": "Feature",
  "properties": {
    "iso:country":"DE",
    "sg:address":"Gr\u00e4frather Markt 4",
    "sg:city":"Solingen",
    "sg:phone":"+49 212/593360",
    "sg:postcode":"42653",
    "sg:province":"Nordrhein-Westfalen",
    "wof:name":"F. Lauterjung",
    "wof:placetype":"venue"
},
  "geometry": {"coordinates":[7.0711779594,51.2089233398],"type":"Point"}
}