{
  "type": "Feature",
  "properties": {
    "iso:country":"DE",
    "sg:address":"H\u00f6rnumer Str. 315",
    "sg:city":"Helgoland",
    "sg:phone":"+49 4725/254",
    "sg:postcode":"27498",
    "sg:province":"Schleswig-Holstein",
    "wof:name":"Henry W\u00fcrtz",
    "wof:placetype":"venue"
},
  "geometry": {"coordinates":[7.886862,54.182407],"type":"Point"}
}