{
  "type": "Feature",
  "properties": {
    "iso:country":"DE",
    "sg:address":"Gro\u00df Parin",
    "sg:city":"Bad Schwartau",
    "sg:phone":"+49 451/208253",
    "sg:postcode":"23611",
    "sg:province":"Schleswig-Holstein",
    "wof:name":"Hans Hardt",
    "wof:placetype":"venue"
},
  "geometry": {"coordinates":[10.699142,53.942474],"type":"Point"}
}