{
  "type": "Feature",
  "properties": {
    "iso:country":"DE",
    "sg:address":"Am Fuchsberg 3",
    "sg:city":"Markt Schwaben",
    "sg:phone":"+49 8121/912113",
    "sg:postcode":"85570",
    "sg:province":"Bayern",
    "wof:name":"Klaus Stadler Rechtsanwalt",
    "wof:placetype":"venue"
},
  "geometry": {"coordinates":[11.8696908951,48.1918067932],"type":"Point"}
}