{
  "type": "Feature",
  "properties": {
    "iso:country":"DE",
    "sg:address":"Teutoburger Str. 126",
    "sg:city":"Oberhausen",
    "sg:phone":"+49 208/663169",
    "sg:postcode":"46145",
    "sg:province":"Nordrhein-Westfalen",
    "wof:name":"Horst Und Marianne Niklass Anlageberater",
    "wof:placetype":"venue"
},
  "geometry": {"coordinates":[6.8685460091,51.5155105591],"type":"Point"}
}