{
  "type": "Feature",
  "properties": {
    "iso:country":"DE",
    "sg:address":"Sebaldsbr\u00fccker Heerstr. 313",
    "sg:city":"Bremen",
    "sg:phone":"+49 421/451842",
    "sg:postcode":"28309",
    "sg:province":"Bremen",
    "wof:name":"Hans Tod",
    "wof:placetype":"venue"
},
  "geometry": {"coordinates":[8.915155,53.059387],"type":"Point"}
}