{
  "type": "Feature",
  "properties": {
    "iso:country":"DE",
    "sg:address":"Weilerstr. 37",
    "sg:city":"Schorndorf",
    "sg:phone":"+49 7181/481387",
    "sg:postcode":"73614",
    "sg:province":"Baden-W\u00fcrttemberg",
    "wof:name":"Concept S. Ladenbau Und Objekt Design Gmbh",
    "wof:placetype":"venue"
},
  "geometry": {"coordinates":[9.51709,48.803165],"type":"Point"}
}