{
  "type": "Feature",
  "properties": {
    "iso:country":"DE",
    "sg:address":"Hedingsener Str. 88",
    "sg:city":"Bad Oeynhausen",
    "sg:phone":"+49 5734/2157",
    "sg:postcode":"32549",
    "sg:province":"Nordrhein-Westfalen",
    "wof:name":"Wilhelm R\u00fcter",
    "wof:placetype":"venue"
},
  "geometry": {"coordinates":[8.7661781311,52.2411117554],"type":"Point"}
}