{
  "type": "Feature",
  "properties": {
    "iso:country":"DE",
    "sg:address":"Mannheimer Str. 80",
    "sg:city":"Edingen-Neckarhausen",
    "sg:phone":"+49 6203/89680",
    "sg:postcode":"68535",
    "sg:province":"Baden-W\u00fcrttemberg",
    "wof:name":"Biria Gmbh",
    "wof:placetype":"venue"
},
  "geometry": {"coordinates":[8.593193,49.453835],"type":"Point"}
}