{
  "type": "Feature",
  "properties": {
    "iso:country":"DE",
    "sg:address":"Am Spritzenhaus 20c",
    "sg:city":"Gelsenkirchen",
    "sg:phone":"+49 209/610734",
    "sg:postcode":"45894",
    "sg:province":"Nordrhein-Westfalen",
    "wof:name":"Syhag Caetools Gmbh",
    "wof:placetype":"venue"
},
  "geometry": {"coordinates":[7.0450630188,51.5803031921],"type":"Point"}
}