{
  "type": "Feature",
  "properties": {
    "iso:country":"DE",
    "sg:address":"K\u00f6nigsteiner Str. 22",
    "sg:city":"Steinbach",
    "sg:postcode":"61449",
    "sg:province":"Hessen",
    "wof:name":"Zwei Design Gmbh",
    "wof:placetype":"venue"
},
  "geometry": {"coordinates":[8.5661277771,50.1680450439],"type":"Point"}
}