{
  "type": "Feature",
  "properties": {
    "iso:country":"DE",
    "sg:address":"Oswaldstr. 9",
    "sg:city":"Bergheim",
    "sg:phone":"+49 2271/76070",
    "sg:postcode":"50126",
    "sg:province":"Nordrhein-Westfalen",
    "wof:name":"Gottfried Ruland & S\u00f6hne Kg",
    "wof:placetype":"venue"
},
  "geometry": {"coordinates":[6.6222572327,50.9457015991],"type":"Point"}
}