{
  "type": "Feature",
  "properties": {
    "iso:country":"DE",
    "sg:address":"Palleskestr. 2",
    "sg:city":"Frankfurt",
    "sg:phone":"+49 69/21245670",
    "sg:postcode":"65929",
    "sg:province":"Hessen",
    "wof:name":"H\u00f6chst Jugenzentrum Stadt",
    "wof:placetype":"venue"
},
  "geometry": {"coordinates":[8.549474,50.104862],"type":"Point"}
}