{
  "type": "Feature",
  "properties": {
    "iso:country":"DE",
    "sg:address":"Thanner Str. 28",
    "sg:city":"Nittenau",
    "sg:phone":"+49 9436/8338",
    "sg:postcode":"93149",
    "sg:province":"Bayern",
    "wof:name":"Karl Sluka Gmbh",
    "wof:placetype":"venue"
},
  "geometry": {"coordinates":[12.2767496109,49.2070083618],"type":"Point"}
}