{
  "type": "Feature",
  "properties": {
    "iso:country":"DE",
    "sg:address":"Hauptstr. 15",
    "sg:city":"Bischofsgr\u00fcn",
    "sg:phone":"+49 9276/8114",
    "sg:postcode":"95493",
    "sg:province":"Bayern",
    "wof:name":"Peter's Wein U. Bierst\u00fcberl",
    "wof:placetype":"venue"
},
  "geometry": {"coordinates":[11.7973957062,50.0522270203],"type":"Point"}
}