{
  "type": "Feature",
  "properties": {
    "iso:country":"DE",
    "sg:address":"Im Eichw\u00e4ldchen 29",
    "sg:city":"Frankfurt",
    "sg:phone":"+49 4969/766637",
    "sg:postcode":"60488",
    "sg:province":"Hessen",
    "wof:name":"Sam Sensor-analyse-messtechnik Gmbh",
    "wof:placetype":"venue"
},
  "geometry": {"coordinates":[8.62105,50.13694],"type":"Point"}
}