{
  "type": "Feature",
  "properties": {
    "iso:country":"DE",
    "sg:address":"Buderusstr. 6",
    "sg:city":"Unna",
    "sg:phone":"+49 2303/53664",
    "sg:postcode":"59427",
    "sg:province":"Nordrhein-Westfalen",
    "wof:name":"Kadziela Gmbh",
    "wof:placetype":"venue"
},
  "geometry": {"coordinates":[7.63735,51.549583],"type":"Point"}
}