{
  "type": "Feature",
  "properties": {
    "iso:country":"DE",
    "sg:address":"Waldensberger Str. 71",
    "sg:city":"W\u00e4chtersbach",
    "sg:phone":"+49 6053/601062",
    "sg:postcode":"63607",
    "sg:province":"Hessen",
    "wof:name":"Karl Muck",
    "wof:placetype":"venue"
},
  "geometry": {"coordinates":[9.2628946304,50.2861061096],"type":"Point"}
}