{
  "type": "Feature",
  "properties": {
    "iso:country":"DE",
    "sg:address":"Alte Heerstr. 84",
    "sg:city":"Weeze",
    "sg:phone":"+49 2837/7291",
    "sg:postcode":"47652",
    "sg:province":"Nordrhein-Westfalen",
    "wof:name":"Dietrich Berger",
    "wof:placetype":"venue"
},
  "geometry": {"coordinates":[6.206808,51.619617],"type":"Point"}
}