{
  "type": "Feature",
  "properties": {
    "iso:country":"DE",
    "sg:address":"Neustr. 2",
    "sg:city":"Eschweiler",
    "sg:postcode":"52249",
    "sg:province":"Nordrhein-Westfalen",
    "wof:name":"Medizinischer Dienst Der Krankenversicherung Nordrhein",
    "wof:placetype":"venue"
},
  "geometry": {"coordinates":[6.2680001259,50.8188514709],"type":"Point"}
}