{
  "type": "Feature",
  "properties": {
    "iso:country":"DE",
    "sg:address":"Hans-Sachs-Str. 5",
    "sg:city":"Effeltrich",
    "sg:phone":"+49 9133/2674",
    "sg:postcode":"91090",
    "sg:province":"Bayern",
    "wof:name":"Franz Mehl",
    "wof:placetype":"venue"
},
  "geometry": {"coordinates":[11.099616,49.661175],"type":"Point"}
}