{
  "type": "Feature",
  "properties": {
    "iso:country":"DE",
    "sg:address":"Wiffertshauser Str 35",
    "sg:city":"Friedberg",
    "sg:phone":"+49 821/268920",
    "sg:postcode":"86316",
    "sg:province":"Bayern",
    "wof:name":"Ist Informations- Und Systemtechnik Dipl.-ing. (fh), Dipl.oec. C. H\u00f6lzl Gmbh",
    "wof:placetype":"venue"
},
  "geometry": {"coordinates":[10.9887237549,48.3557167053],"type":"Point"}
}