{
  "type": "Feature",
  "properties": {
    "iso:country":"DE",
    "sg:address":"S\u00e4gem\u00fchlenstr. 16",
    "sg:city":"Eschede",
    "sg:phone":"+49 5142/571",
    "sg:postcode":"29348",
    "sg:province":"Niedersachsen",
    "wof:name":"W. Lindhorst",
    "wof:placetype":"venue"
},
  "geometry": {"coordinates":[10.227568,52.73827],"type":"Point"}
}