{
  "type": "Feature",
  "properties": {
    "iso:country":"DE",
    "sg:address":"Uhlandstr. 15",
    "sg:city":"\u00dcberlingen",
    "sg:phone":"+49 7551/2015",
    "sg:postcode":"88662",
    "sg:province":"Baden-W\u00fcrttemberg",
    "wof:name":"H. G. Hipp Immobilienmakler Vdm",
    "wof:placetype":"venue"
},
  "geometry": {"coordinates":[9.1516389847,47.7726554871],"type":"Point"}
}