{
  "type": "Feature",
  "properties": {
    "iso:country":"DE",
    "sg:address":"Niederhechinger Str. 51",
    "sg:city":"Hechingen",
    "sg:phone":"+49 7471/4938",
    "sg:postcode":"72379",
    "sg:province":"Baden-W\u00fcrttemberg",
    "wof:name":"Weiherstube",
    "wof:placetype":"venue"
},
  "geometry": {"coordinates":[8.9573030472,48.360206604],"type":"Point"}
}