{
  "type": "Feature",
  "properties": {
    "iso:country":"DE",
    "sg:address":"Amselweg 3",
    "sg:city":"Plochingen",
    "sg:postcode":"73207",
    "sg:province":"Baden-W\u00fcrttemberg",
    "wof:name":"Ruland Heilpraktiker",
    "wof:placetype":"venue"
},
  "geometry": {"coordinates":[9.4253501892,48.7082290649],"type":"Point"}
}