{
  "type": "Feature",
  "properties": {
    "iso:country":"DE",
    "sg:address":"Wellendorf 69",
    "sg:city":"Suhlendorf",
    "sg:phone":"+49 5820/1880",
    "sg:postcode":"29562",
    "sg:province":"Niedersachsen",
    "wof:name":"Frit Up De Deel Gastst\u00e4tten- Betrieb Gmbh",
    "wof:placetype":"venue"
},
  "geometry": {"coordinates":[10.729991,52.947964],"type":"Point"}
}