{
  "type": "Feature",
  "properties": {
    "iso:country":"DE",
    "sg:address":"Friedenstr. 46",
    "sg:city":"Erlenbach",
    "sg:phone":"+49 7132/922343",
    "sg:postcode":"74235",
    "sg:province":"Baden-W\u00fcrttemberg",
    "wof:name":"V. Grupp",
    "wof:placetype":"venue"
},
  "geometry": {"coordinates":[9.2639350891,49.1724014282],"type":"Point"}
}