{
  "type": "Feature",
  "properties": {
    "iso:country":"DE",
    "sg:address":"Martin-Maier-Str. 82",
    "sg:city":"Flein",
    "sg:phone":"+49 7131/252337",
    "sg:postcode":"74223",
    "sg:province":"Baden-W\u00fcrttemberg",
    "wof:name":"Edda Haynold Hebamme",
    "wof:placetype":"venue"
},
  "geometry": {"coordinates":[9.202416,49.102428],"type":"Point"}
}