{
  "type": "Feature",
  "properties": {
    "iso:country":"DE",
    "sg:address":"Mausegatt 44",
    "sg:city":"Bochum",
    "sg:phone":"+49 2327/89889",
    "sg:postcode":"44866",
    "sg:province":"Nordrhein-Westfalen",
    "wof:name":"Buchwald Gesellschaft Mit Beschr\u00e4nkter Haftung",
    "wof:placetype":"venue"
},
  "geometry": {"coordinates":[7.1642751694,51.4840812683],"type":"Point"}
}