{
  "type": "Feature",
  "properties": {
    "iso:country":"DE",
    "sg:address":"Ernst-Th\u00e4lmann-Str. 88 a",
    "sg:city":"Kleinmachnow",
    "sg:phone":"+49 33203/22263",
    "sg:postcode":"14532",
    "sg:province":"Brandenburg",
    "wof:name":"Apotheke Kleinmachnow Inh. Frank Ruthe E. K.",
    "wof:placetype":"venue"
},
  "geometry": {"coordinates":[13.227014,52.413914],"type":"Point"}
}