{
  "type": "Feature",
  "properties": {
    "iso:country":"DE",
    "sg:address":"Am R\u00f6sehof 7",
    "sg:city":"Obernkirchen",
    "sg:phone":"+49 5724/51511",
    "sg:postcode":"31683",
    "sg:province":"Niedersachsen",
    "wof:name":"Gausmann Innenausbau Gmbh",
    "wof:placetype":"venue"
},
  "geometry": {"coordinates":[9.1368761063,52.281047821],"type":"Point"}
}