{
  "type": "Feature",
  "properties": {
    "iso:country":"DE",
    "sg:address":"\u00c4u\u00dfere Lauenstr. 38",
    "sg:city":"Bautzen",
    "sg:phone":"+49 3591/532799",
    "sg:postcode":"02625",
    "sg:province":"Sachsen",
    "wof:name":"Net Com Inh. Torsten Ei\u00dfler",
    "wof:placetype":"venue"
},
  "geometry": {"coordinates":[14.4233865738,51.1784896851],"type":"Point"}
}