{
  "type": "Feature",
  "properties": {
    "iso:country":"DE",
    "sg:address":"H\u00f6rhammerstr 4a",
    "sg:city":"Haag",
    "sg:phone":"+49 8167/6547",
    "sg:postcode":"85410",
    "sg:province":"Bayern",
    "wof:name":"Esr Klimatechnik Gmbh",
    "wof:placetype":"venue"
},
  "geometry": {"coordinates":[11.832975,48.458633],"type":"Point"}
}