{
  "type": "Feature",
  "properties": {
    "iso:country":"DE",
    "sg:address":"Weiherhalde",
    "sg:city":"Laupheim",
    "sg:phone":"+49 7392/8376",
    "sg:postcode":"88471",
    "sg:province":"Baden-W\u00fcrttemberg",
    "wof:name":"Gesellschaft F\u00fcr Lagereibetrieb Mbh",
    "wof:placetype":"venue"
},
  "geometry": {"coordinates":[9.893204,48.201275],"type":"Point"}
}