{
  "type": "Feature",
  "properties": {
    "iso:country":"DE",
    "sg:address":"Martin-Luther-Str. 11",
    "sg:city":"W\u00fcrzburg",
    "sg:phone":"+49 931/52803",
    "sg:postcode":"97072",
    "sg:province":"Bayern",
    "wof:name":"E. Geisend\u00f6rfer",
    "wof:placetype":"venue"
},
  "geometry": {"coordinates":[9.9442176819,49.7948913574],"type":"Point"}
}