{
  "type": "Feature",
  "properties": {
    "iso:country":"DE",
    "sg:address":"Lindenstr. 92",
    "sg:city":"Lauterbach",
    "sg:phone":"+49 6641/2860",
    "sg:postcode":"36341",
    "sg:province":"Hessen",
    "wof:name":"Reifen Brod Gmbh",
    "wof:placetype":"venue"
},
  "geometry": {"coordinates":[9.4080133438,50.6404075623],"type":"Point"}
}