{
  "type": "Feature",
  "properties": {
    "iso:country":"DE",
    "sg:address":"Beethovenstr. 27",
    "sg:city":"Hamb\u00fchren",
    "sg:phone":"+49 5084/5662",
    "sg:postcode":"29313",
    "sg:province":"Niedersachsen",
    "wof:name":"Gebr. Becker Gmbh",
    "wof:placetype":"venue"
},
  "geometry": {"coordinates":[9.9640817642,52.6313285828],"type":"Point"}
}