{
  "type": "Feature",
  "properties": {
    "iso:country":"DE",
    "sg:address":"Postfach 1126",
    "sg:city":"Nienburg",
    "sg:postcode":"31561",
    "sg:province":"Niedersachsen",
    "wof:name":"Ac-massivbau Gmbh",
    "wof:placetype":"venue"
},
  "geometry": {"coordinates":[9.20957,52.636688],"type":"Point"}
}