{
  "type": "Feature",
  "properties": {
    "iso:country":"DE",
    "sg:address":"Am Hellefelder Bach 13",
    "sg:city":"Arnsberg",
    "sg:phone":"+49 2931/939090",
    "sg:postcode":"59821",
    "sg:province":"Nordrhein-Westfalen",
    "wof:name":"Papier-profi",
    "wof:placetype":"venue"
},
  "geometry": {"coordinates":[8.076144,51.382252],"type":"Point"}
}