{
  "type": "Feature",
  "properties": {
    "iso:country":"DE",
    "sg:address":"Karl-Liebknecht-Str. 19",
    "sg:city":"Chemnitz",
    "sg:phone":"+49 371/414047",
    "sg:postcode":"09111",
    "sg:province":"Sachsen",
    "wof:name":"Arnold Und Dr. Barth Architekten",
    "wof:placetype":"venue"
},
  "geometry": {"coordinates":[12.924563,50.840179],"type":"Point"}
}