{
  "type": "Feature",
  "properties": {
    "iso:country":"DE",
    "sg:address":"Am Grund 10",
    "sg:city":"Leipzig",
    "sg:phone":"+49 341/9423431",
    "sg:postcode":"04207",
    "sg:province":"Sachsen",
    "wof:name":"Karl-heinz M\u00fcller",
    "wof:placetype":"venue"
},
  "geometry": {"coordinates":[12.264287,51.307598],"type":"Point"}
}