{
  "type": "Feature",
  "properties": {
    "iso:country":"DE",
    "sg:address":"Bringh\u00e4user Str. 14",
    "sg:city":"Edertal",
    "sg:phone":"+49 5623/930098",
    "sg:postcode":"34549",
    "sg:province":"Hessen",
    "wof:name":"Cafe Wind",
    "wof:placetype":"venue"
},
  "geometry": {"coordinates":[9.034016,51.179405],"type":"Point"}
}