{
  "type": "Feature",
  "properties": {
    "iso:country":"DE",
    "sg:address":"Bilderh\u00e4uslestr. 5/1",
    "sg:city":"Balingen",
    "sg:phone":"+49 7433/36456",
    "sg:postcode":"72336",
    "sg:province":"Baden-W\u00fcrttemberg",
    "wof:name":"Hans Denk Elektroinstallation",
    "wof:placetype":"venue"
},
  "geometry": {"coordinates":[8.814212,48.250519],"type":"Point"}
}