{
  "type": "Feature",
  "properties": {
    "iso:country":"DE",
    "sg:address":"Max-Planck-Ring 37",
    "sg:city":"Wiesbaden",
    "sg:phone":"+49 2204/842670",
    "sg:postcode":"65205",
    "sg:province":"Hessen",
    "wof:name":"Montwill Gmbh Technologie Park",
    "wof:placetype":"venue"
},
  "geometry": {"coordinates":[7.18473,50.959435],"type":"Point"}
}