{
  "type": "Feature",
  "properties": {
    "iso:country":"DE",
    "sg:address":"Steinberger Str. 14",
    "sg:city":"Steinbergkirche",
    "sg:phone":"+49 4632/87427",
    "sg:postcode":"24972",
    "sg:province":"Schleswig-Holstein",
    "wof:name":"Dalkowski Immobilien",
    "wof:placetype":"venue"
},
  "geometry": {"coordinates":[9.7188806534,54.7519989014],"type":"Point"}
}