{
  "type": "Feature",
  "properties": {
    "iso:country":"DE",
    "sg:address":"Rosenb\u00fchlstr 24",
    "sg:city":"Bernstadt",
    "sg:phone":"+49 7348/7755",
    "sg:postcode":"89182",
    "sg:province":"Baden-W\u00fcrttemberg",
    "wof:name":"Rapp Informatik Systeme Gmbh",
    "wof:placetype":"venue"
},
  "geometry": {"coordinates":[10.0244417191,48.4973258972],"type":"Point"}
}