{
  "type": "Feature",
  "properties": {
    "iso:country":"DE",
    "sg:address":"Forststr. 21",
    "sg:city":"Bad Oeynhausen",
    "sg:phone":"+49 5731/9941",
    "sg:postcode":"32547",
    "sg:province":"Nordrhein-Westfalen",
    "wof:name":"Forsthaus Alter F\u00f6rster",
    "wof:placetype":"venue"
},
  "geometry": {"coordinates":[8.8435153961,52.1837043762],"type":"Point"}
}