{
  "type": "Feature",
  "properties": {
    "iso:country":"DE",
    "sg:address":"Reginenstr. 11",
    "sg:city":"Essen",
    "sg:phone":"+49 201/774786",
    "sg:postcode":"45130",
    "sg:province":"Nordrhein-Westfalen",
    "wof:name":"J. Caesar",
    "wof:placetype":"venue"
},
  "geometry": {"coordinates":[7.009749,51.434078],"type":"Point"}
}