{
  "type": "Feature",
  "properties": {
    "iso:country":"DE",
    "sg:address":"Trierer Str. 18",
    "sg:city":"Wittlich",
    "sg:phone":"+49 6571/4024",
    "sg:postcode":"54516",
    "sg:province":"Rheinland-Pfalz",
    "wof:name":"Ertz & S\u00f6hne Gmbh",
    "wof:placetype":"venue"
},
  "geometry": {"coordinates":[6.886534214,49.9854354858],"type":"Point"}
}