{
  "type": "Feature",
  "properties": {
    "iso:country":"DE",
    "sg:address":"Ellwanger Str. 7",
    "sg:city":"Tamm",
    "sg:phone":"+49 7141/605015",
    "sg:postcode":"71732",
    "sg:province":"Baden-W\u00fcrttemberg",
    "wof:name":"Asm",
    "wof:placetype":"venue"
},
  "geometry": {"coordinates":[9.1221580505,48.9215316772],"type":"Point"}
}