{
  "type": "Feature",
  "properties": {
    "iso:country":"DE",
    "sg:address":"Poststr. 1+16",
    "sg:city":"Fischach",
    "sg:phone":"+49 8236/1309",
    "sg:postcode":"86850",
    "sg:province":"Bayern",
    "wof:name":"M\u00f6belhaus Anton Schi\u00dfler Gmbh",
    "wof:placetype":"venue"
},
  "geometry": {"coordinates":[10.6547927856,48.290348053],"type":"Point"}
}