{
  "type": "Feature",
  "properties": {
    "iso:country":"DE",
    "sg:address":"Wettiner Str. 12",
    "sg:city":"Gimritz",
    "sg:phone":"+49 34607/20098",
    "sg:postcode":"06198",
    "sg:province":"Sachsen-Anhalt",
    "wof:name":"Hbg Gmbh Hallen- Und Bausysteme Gimritz",
    "wof:placetype":"venue"
},
  "geometry": {"coordinates":[11.8683786392,51.5688209534],"type":"Point"}
}