{
  "type": "Feature",
  "properties": {
    "iso:country":"DE",
    "sg:address":"Dorfplatz 1",
    "sg:city":"Pouch",
    "sg:phone":"+49 3493/55229",
    "sg:postcode":"06774",
    "sg:province":"Sachsen-Anhalt",
    "wof:name":"Fischer-weberei Gmbh",
    "wof:placetype":"venue"
},
  "geometry": {"coordinates":[12.3991508484,51.6247673035],"type":"Point"}
}