{
  "type": "Feature",
  "properties": {
    "iso:country":"DE",
    "sg:address":"Ringstr. 25",
    "sg:city":"Prackenbach",
    "sg:phone":"+49 9942/8865",
    "sg:postcode":"94267",
    "sg:province":"Bayern",
    "wof:name":"Drachen-propangas Gmbh",
    "wof:placetype":"venue"
},
  "geometry": {"coordinates":[12.828198,49.093632],"type":"Point"}
}