{
  "type": "Feature",
  "properties": {
    "iso:country":"DE",
    "sg:address":"Katzbachstr. 25",
    "sg:city":"Berlin",
    "sg:phone":"+49 30/7865814",
    "sg:postcode":"10965",
    "sg:province":"Berlin",
    "wof:name":"Vereinigung Der Polen In Berlin E. V.",
    "wof:placetype":"venue"
},
  "geometry": {"coordinates":[13.37637043,52.4859733582],"type":"Point"}
}