{
  "type": "Feature",
  "properties": {
    "iso:country":"DE",
    "sg:address":"Whistlerweg 24 a",
    "sg:city":"M\u00fcnchen",
    "sg:phone":"+49 89/7916299",
    "sg:postcode":"81479",
    "sg:province":"Bayern",
    "wof:name":"Manfred Heise",
    "wof:placetype":"venue"
},
  "geometry": {"coordinates":[11.5233535767,48.0714836121],"type":"Point"}
}