{
  "type": "Feature",
  "properties": {
    "iso:country":"DE",
    "sg:address":"Kapuzinerberg 17",
    "sg:city":"Weil der Stadt",
    "sg:postcode":"71263",
    "sg:province":"Baden-W\u00fcrttemberg",
    "wof:name":"Pro-flies Pollex Gmbh",
    "wof:placetype":"venue"
},
  "geometry": {"coordinates":[8.8734312057,48.751159668],"type":"Point"}
}