{
  "type": "Feature",
  "properties": {
    "iso:country":"DE",
    "sg:address":"In den Weiden 2",
    "sg:city":"Bad Sooden-Allendorf",
    "sg:phone":"+49 5652/2217",
    "sg:postcode":"37242",
    "sg:province":"Hessen",
    "wof:name":"Rudolf Menthe",
    "wof:placetype":"venue"
},
  "geometry": {"coordinates":[9.961337,51.272232],"type":"Point"}
}