{
  "type": "Feature",
  "properties": {
    "iso:country":"DE",
    "sg:address":"Basler Landstr. 30",
    "sg:city":"Freiburg",
    "sg:postcode":"79111",
    "sg:province":"Baden-W\u00fcrttemberg",
    "wof:name":"Raco Metallwarenfabrik Gmbh",
    "wof:placetype":"venue"
},
  "geometry": {"coordinates":[7.79252,47.98061],"type":"Point"}
}