{
  "type": "Feature",
  "properties": {
    "iso:country":"DE",
    "sg:city":"Frankfurt am Main",
    "sg:postcode":"60322",
    "sg:province":"Hessen",
    "wof:name":"Spiegel-schule",
    "wof:placetype":"venue"
},
  "geometry": {"coordinates":[8.272315,50.000561],"type":"Point"}
}