{
  "type": "Feature",
  "properties": {
    "iso:country":"DE",
    "sg:address":"Olper Str. 11",
    "sg:city":"Freudenberg",
    "sg:phone":"+49 4927/3443620",
    "sg:postcode":"57258",
    "sg:province":"Nordrhein-Westfalen",
    "wof:name":"Horchler Gmbh & Co. Kg",
    "wof:placetype":"venue"
},
  "geometry": {"coordinates":[7.888974,50.906349],"type":"Point"}
}