{
  "type": "Feature",
  "properties": {
    "iso:country":"DE",
    "sg:address":"Narzissenweg 2",
    "sg:city":"Bergkamen",
    "sg:phone":"+49 2307/982840",
    "sg:postcode":"59192",
    "sg:province":"Nordrhein-Westfalen",
    "wof:name":"K.-h. Schlaap Und A. Biermann Steuerberater",
    "wof:placetype":"venue"
},
  "geometry": {"coordinates":[7.6708750725,51.6246871948],"type":"Point"}
}