{
  "type": "Feature",
  "properties": {
    "iso:country":"DE",
    "sg:address":"Am Treppenberg 71",
    "sg:city":"Schwerin",
    "sg:phone":"+49 385/719443",
    "sg:postcode":"19057",
    "sg:province":"Mecklenburg-Vorpommern",
    "wof:name":"M. Menzel",
    "wof:placetype":"venue"
},
  "geometry": {"coordinates":[11.37518,53.634167],"type":"Point"}
}