{
  "type": "Feature",
  "properties": {
    "iso:country":"DE",
    "sg:address":"Unterw\u00f6rthstr. 22",
    "sg:city":"Renningen",
    "sg:phone":"+49 7159/2049",
    "sg:postcode":"71272",
    "sg:province":"Baden-W\u00fcrttemberg",
    "wof:name":"Gerhard Breutner",
    "wof:placetype":"venue"
},
  "geometry": {"coordinates":[8.9384555817,48.7666091919],"type":"Point"}
}