{
  "type": "Feature",
  "properties": {
    "iso:country":"DE",
    "sg:address":"Tempelhofer Weg 101",
    "sg:city":"Berlin",
    "sg:phone":"+49 30/6419130",
    "sg:postcode":"12347",
    "sg:province":"Berlin",
    "wof:name":"Farben-frikell Gmbh",
    "wof:placetype":"venue"
},
  "geometry": {"coordinates":[13.434766,52.451382],"type":"Point"}
}