{
  "type": "Feature",
  "properties": {
    "iso:country":"DE",
    "sg:address":"An Der Kupka 1",
    "sg:city":"L\u00fcbben",
    "sg:phone":"+49 4935/463016",
    "sg:postcode":"15907",
    "sg:province":"Brandenburg",
    "wof:name":"Mario Ziemainz",
    "wof:placetype":"venue"
},
  "geometry": {"coordinates":[13.901967,51.94054],"type":"Point"}
}