{
  "type": "Feature",
  "properties": {
    "iso:country":"DE",
    "sg:address":"Steinstr. 9",
    "sg:city":"Rahden",
    "sg:phone":"+49 5771/1063",
    "sg:postcode":"32369",
    "sg:province":"Nordrhein-Westfalen",
    "wof:name":"Trend Moden",
    "wof:placetype":"venue"
},
  "geometry": {"coordinates":[8.611836,52.432377],"type":"Point"}
}