{
  "type": "Feature",
  "properties": {
    "iso:country":"DE",
    "sg:address":"Wiebelsheimer Str. 11",
    "sg:city":"Bad Windsheim",
    "sg:phone":"+49 9841/4436",
    "sg:postcode":"91438",
    "sg:province":"Bayern",
    "wof:name":"J\u00fcrgen Aurich Anlageberater",
    "wof:placetype":"venue"
},
  "geometry": {"coordinates":[10.4072389603,49.4995117188],"type":"Point"}
}