{
  "type": "Feature",
  "properties": {
    "iso:country":"DE",
    "sg:address":"Reitwallstr. 2",
    "sg:city":"Hannover",
    "sg:phone":"+49 511/3631083",
    "sg:postcode":"30159",
    "sg:province":"Niedersachsen",
    "wof:name":"Sex-world",
    "wof:placetype":"venue"
},
  "geometry": {"coordinates":[9.7332410812,52.3748245239],"type":"Point"}
}