{
  "type": "Feature",
  "properties": {
    "iso:country":"DE",
    "sg:address":"Wilhelmsh\u00f6he 16",
    "sg:city":"Altena",
    "sg:phone":"+49 2352/71186",
    "sg:postcode":"58762",
    "sg:province":"Nordrhein-Westfalen",
    "wof:name":"Erich Prinz Werkzeuge",
    "wof:placetype":"venue"
},
  "geometry": {"coordinates":[7.7302308083,51.304058075],"type":"Point"}
}