{
  "type": "Feature",
  "properties": {
    "iso:country":"DE",
    "sg:address":"Kronsforder Allee 27",
    "sg:city":"L\u00fcbeck",
    "sg:phone":"+49 451/796012",
    "sg:postcode":"23560",
    "sg:province":"Schleswig-Holstein",
    "wof:name":"H. -w. Peters Und H. Reinhold",
    "wof:placetype":"venue"
},
  "geometry": {"coordinates":[10.6886482239,53.8540306091],"type":"Point"}
}