{
  "type": "Feature",
  "properties": {
    "iso:country":"DE",
    "sg:address":"R\u00f6thenstr. 6",
    "sg:city":"K\u00fcps",
    "sg:phone":"+49 9264/357",
    "sg:postcode":"96328",
    "sg:province":"Bayern",
    "wof:name":"Albert Martin",
    "wof:placetype":"venue"
},
  "geometry": {"coordinates":[11.276679,50.189678],"type":"Point"}
}