{
  "type": "Feature",
  "properties": {
    "iso:country":"DE",
    "sg:address":"Lange Felder 5",
    "sg:city":"Lenzen",
    "sg:phone":"+49 38792/9890",
    "sg:postcode":"19309",
    "sg:province":"Brandenburg",
    "wof:name":"Rabau Gmbh",
    "wof:placetype":"venue"
},
  "geometry": {"coordinates":[11.4806499481,53.1003341675],"type":"Point"}
}