{
  "type": "Feature",
  "properties": {
    "iso:country":"DE",
    "sg:address":"Goethestr. 8",
    "sg:city":"Rangendingen",
    "sg:phone":"+49 7471/82328",
    "sg:postcode":"72414",
    "sg:province":"Baden-W\u00fcrttemberg",
    "wof:name":"Josef Strobel",
    "wof:placetype":"venue"
},
  "geometry": {"coordinates":[8.8824071884,48.3797836304],"type":"Point"}
}