{
  "type": "Feature",
  "properties": {
    "iso:country":"DE",
    "sg:address":"Luttersiefen 6",
    "sg:city":"Lindlar",
    "sg:phone":"+49 2207/6766",
    "sg:postcode":"51789",
    "sg:province":"Nordrhein-Westfalen",
    "wof:name":"Heinrich Remlinger Architekt",
    "wof:placetype":"venue"
},
  "geometry": {"coordinates":[7.282783,50.990314],"type":"Point"}
}