{
  "type": "Feature",
  "properties": {
    "iso:country":"DE",
    "sg:address":"Kirchplatz 3",
    "sg:city":"L\u00fcbbecke",
    "sg:phone":"+49 5741/4487",
    "sg:postcode":"32312",
    "sg:province":"Nordrhein-Westfalen",
    "wof:name":"L. Meier",
    "wof:placetype":"venue"
},
  "geometry": {"coordinates":[8.619145,52.301826],"type":"Point"}
}