{
  "type": "Feature",
  "properties": {
    "iso:country":"DE",
    "sg:address":"Gothaer Str. 15b",
    "sg:city":"Goldbach",
    "sg:phone":"+49 36255/80645",
    "sg:postcode":"99869",
    "sg:province":"Th\u00fcringen",
    "wof:name":"J\u00f6rg Otto",
    "wof:placetype":"venue"
},
  "geometry": {"coordinates":[10.657544136,50.9905586243],"type":"Point"}
}