{
  "type": "Feature",
  "properties": {
    "iso:country":"DE",
    "sg:address":"Dohnaer Str. 18",
    "sg:city":"Dresden",
    "sg:phone":"+49 351/4718063",
    "sg:postcode":"01219",
    "sg:province":"Sachsen",
    "wof:name":"Eberhard Morenz",
    "wof:placetype":"venue"
},
  "geometry": {"coordinates":[13.76381,51.025448],"type":"Point"}
}