{
  "type": "Feature",
  "properties": {
    "iso:country":"DE",
    "sg:address":"Caspersbroicher Weg 19",
    "sg:city":"Solingen",
    "sg:phone":"+49 212/336222",
    "sg:postcode":"42697",
    "sg:province":"Nordrhein-Westfalen",
    "wof:name":"Tenniscenter Caspersbroich Gmbh",
    "wof:placetype":"venue"
},
  "geometry": {"coordinates":[7.005146,51.171013],"type":"Point"}
}