{
  "type": "Feature",
  "properties": {
    "iso:country":"DE",
    "sg:address":"Friedrichsring 4",
    "sg:city":"Mannheim",
    "sg:phone":"+49 621/28139",
    "sg:postcode":"68161",
    "sg:province":"Baden-W\u00fcrttemberg",
    "wof:name":"G. Betz Immobilienmakler",
    "wof:placetype":"venue"
},
  "geometry": {"coordinates":[8.4758901596,49.4855766296],"type":"Point"}
}