{
  "type": "Feature",
  "properties": {
    "iso:country":"DE",
    "sg:address":"Kreisstr. 48",
    "sg:city":"Warstein",
    "sg:phone":"+49 2902/80550",
    "sg:postcode":"59581",
    "sg:province":"Nordrhein-Westfalen",
    "wof:name":"Weiken Und Seiffert Rechtsanw\u00e4lte Und Notare",
    "wof:placetype":"venue"
},
  "geometry": {"coordinates":[8.37025,51.454071],"type":"Point"}
}