{
  "type": "Feature",
  "properties": {
    "iso:country":"DE",
    "sg:address":"Vohenstrau\u00dfer Str. 3",
    "sg:city":"Waidhaus",
    "sg:phone":"+49 9652/1771",
    "sg:postcode":"92726",
    "sg:province":"Bayern",
    "wof:name":"Karls-apotheke Inh. Horst R\u00f6schlau",
    "wof:placetype":"venue"
},
  "geometry": {"coordinates":[12.490461,49.639458],"type":"Point"}
}