{
  "type": "Feature",
  "properties": {
    "iso:country":"DE",
    "sg:address":"Rennbachstr. 82",
    "sg:city":"Bad Wildbad",
    "sg:phone":"+49 7081/3382",
    "sg:postcode":"75323",
    "sg:province":"Baden-W\u00fcrttemberg",
    "wof:name":"Arno Beyer",
    "wof:placetype":"venue"
},
  "geometry": {"coordinates":[8.5438814163,48.7559394836],"type":"Point"}
}