{
  "type": "Feature",
  "properties": {
    "iso:country":"DE",
    "sg:address":"Robert-Kircher-Str. 17",
    "sg:city":"Fulda",
    "sg:phone":"+49 661/902630",
    "sg:postcode":"36037",
    "sg:province":"Hessen",
    "wof:name":"Quelle Verkaufshaus",
    "wof:placetype":"venue"
},
  "geometry": {"coordinates":[9.673932,50.549759],"type":"Point"}
}