{
  "type": "Feature",
  "properties": {
    "iso:country":"DE",
    "sg:address":"Kneippstr. 8",
    "sg:city":"Bad W\u00f6rishofen",
    "sg:phone":"+49 8247/3550",
    "sg:postcode":"86825",
    "sg:province":"Bayern",
    "wof:name":"Kneipp-kurklinik Sebastianeum",
    "wof:placetype":"venue"
},
  "geometry": {"coordinates":[10.592805,48.005398],"type":"Point"}
}