{
  "type": "Feature",
  "properties": {
    "iso:country":"DE",
    "sg:address":"Ellernstieg 2",
    "sg:city":"Hamburg",
    "sg:phone":"+49 40/7427131",
    "sg:postcode":"21129",
    "sg:province":"Hamburg",
    "wof:name":"Wilhelm Camper Seeschiffahrt-unternehmen",
    "wof:placetype":"venue"
},
  "geometry": {"coordinates":[9.875471,53.535908],"type":"Point"}
}