{
  "type": "Feature",
  "properties": {
    "iso:country":"DE",
    "sg:address":"Lembecker Str. 55",
    "sg:city":"Dorsten",
    "sg:phone":"+49 2866/4051",
    "sg:postcode":"46286",
    "sg:province":"Nordrhein-Westfalen",
    "wof:name":"Dst L\u00fcning Gmbh",
    "wof:placetype":"venue"
},
  "geometry": {"coordinates":[6.94803,51.752789],"type":"Point"}
}