{
  "type": "Feature",
  "properties": {
    "iso:country":"DE",
    "sg:address":"Steinekengang 5",
    "sg:city":"Burgwedel",
    "sg:phone":"+49 5139/2315",
    "sg:postcode":"30938",
    "sg:province":"Niedersachsen",
    "wof:name":"Otto Hartmann",
    "wof:placetype":"venue"
},
  "geometry": {"coordinates":[9.854112,52.492374],"type":"Point"}
}