{
  "type": "Feature",
  "properties": {
    "iso:country":"DE",
    "sg:address":"Colmarer Str. 25",
    "sg:city":"Schongau",
    "sg:phone":"+49 8861/8542",
    "sg:postcode":"86956",
    "sg:province":"Bayern",
    "wof:name":"Dezi Gmbh",
    "wof:placetype":"venue"
},
  "geometry": {"coordinates":[10.890534,47.803875],"type":"Point"}
}