{
  "type": "Feature",
  "properties": {
    "iso:country":"DE",
    "sg:address":"Markt 21",
    "sg:city":"Plau",
    "sg:phone":"+49 38735/44663",
    "sg:postcode":"19395",
    "sg:province":"Mecklenburg-Vorpommern",
    "wof:name":"Hans-heinrich Steinweg",
    "wof:placetype":"venue"
},
  "geometry": {"coordinates":[12.191889,53.370647],"type":"Point"}
}