{
  "type": "Feature",
  "properties": {
    "iso:country":"DE",
    "sg:address":"Daniel-Eckhardt-Str. 48",
    "sg:city":"Essen",
    "sg:postcode":"45356",
    "sg:province":"Nordrhein-Westfalen",
    "wof:name":"Heinz Verwaltungs Ges. Mbh",
    "wof:placetype":"venue"
},
  "geometry": {"coordinates":[6.992632,51.495956],"type":"Point"}
}