{
  "type": "Feature",
  "properties": {
    "iso:country":"DE",
    "sg:address":"Rachelstrasse 10",
    "sg:city":"Zwiesel",
    "sg:phone":"+49 9922/4291",
    "sg:postcode":"94227",
    "sg:province":"Bayern",
    "wof:name":"Glasbl\u00e4serei Weber Zwiesel Bayerischer Wald",
    "wof:placetype":"venue"
},
  "geometry": {"coordinates":[13.2422552109,49.0127334595],"type":"Point"}
}