{
  "type": "Feature",
  "properties": {
    "iso:country":"DE",
    "sg:address":"Kreuzbergstr. 9",
    "sg:city":"N\u00fcsttal",
    "sg:phone":"+49 6652/969300",
    "sg:postcode":"36167",
    "sg:province":"Hessen",
    "wof:name":"J. A. Quinkler",
    "wof:placetype":"venue"
},
  "geometry": {"coordinates":[9.8541841507,50.6791801453],"type":"Point"}
}