{
  "type": "Feature",
  "properties": {
    "iso:country":"DE",
    "sg:address":"Westendplatz 39",
    "sg:city":"Frankfurt",
    "sg:postcode":"60325",
    "sg:province":"Hessen",
    "wof:name":"Krawinkel Vermittlungs- Und Verwaltungs Gmbh",
    "wof:placetype":"venue"
},
  "geometry": {"coordinates":[8.66163,50.113331],"type":"Point"}
}