{
  "type": "Feature",
  "properties": {
    "iso:country":"DE",
    "sg:address":"Schiffgraben 33::",
    "sg:city":"Hannover",
    "sg:postcode":"30175",
    "sg:province":"Niedersachsen",
    "wof:name":"Nikko Bank (deutschland) Gmbh",
    "wof:placetype":"venue"
},
  "geometry": {"coordinates":[8.67113,50.11293],"type":"Point"}
}