{
  "type": "Feature",
  "properties": {
    "iso:country":"DE",
    "sg:address":"Wartbergstr. 56",
    "sg:city":"Heilbronn",
    "sg:phone":"+49 7131/173666",
    "sg:postcode":"74076",
    "sg:province":"Baden-W\u00fcrttemberg",
    "wof:name":"P. U. Quattl\u00e4nder",
    "wof:placetype":"venue"
},
  "geometry": {"coordinates":[9.231122,49.151035],"type":"Point"}
}