{
  "type": "Feature",
  "properties": {
    "iso:country":"DE",
    "sg:address":"Frankfurter Str. 3",
    "sg:city":"Bad Soden-Salm\u00fcnster",
    "sg:phone":"+49 6056/901479",
    "sg:postcode":"63628",
    "sg:province":"Hessen",
    "wof:name":"Restaurant R\u00fcbezahl",
    "wof:placetype":"venue"
},
  "geometry": {"coordinates":[9.3685674667,50.2774963379],"type":"Point"}
}