{
  "type": "Feature",
  "properties": {
    "iso:country":"DE",
    "sg:address":"Hertigerstr. 16",
    "sg:city":"Essen",
    "sg:postcode":"45276",
    "sg:province":"Nordrhein-Westfalen",
    "wof:name":"V. V. W. Hermann Leasing",
    "wof:placetype":"venue"
},
  "geometry": {"coordinates":[7.0714268684,51.4487762451],"type":"Point"}
}