{
  "type": "Feature",
  "properties": {
    "iso:country":"DE",
    "sg:address":"Hohe Str. 55",
    "sg:city":"Wesel",
    "sg:phone":"+49 281/339000",
    "sg:postcode":"46483",
    "sg:province":"Nordrhein-Westfalen",
    "wof:name":"J. Peitsch Reiseb\u00fcro",
    "wof:placetype":"venue"
},
  "geometry": {"coordinates":[6.6173501015,51.6573410034],"type":"Point"}
}