{
  "type": "Feature",
  "properties": {
    "iso:country":"DE",
    "sg:address":"Riga-Ring 6",
    "sg:city":"Soest",
    "sg:phone":"+49 2921/17684",
    "sg:postcode":"59494",
    "sg:province":"Nordrhein-Westfalen",
    "wof:name":"Schumacher Gmbh",
    "wof:placetype":"venue"
},
  "geometry": {"coordinates":[8.128898,51.570744],"type":"Point"}
}