{
  "type": "Feature",
  "properties": {
    "iso:country":"DE",
    "sg:address":"Hauptstr.",
    "sg:city":"Helferskirchen",
    "sg:phone":"+49 2626/5613",
    "sg:postcode":"56244",
    "sg:province":"Rheinland-Pfalz",
    "wof:name":"Volksbank Westerwald Eg",
    "wof:placetype":"venue"
},
  "geometry": {"coordinates":[7.813085,50.511559],"type":"Point"}
}