{
  "type": "Feature",
  "properties": {
    "iso:country":"DE",
    "sg:address":"Sandizeller Str. 6",
    "sg:city":"P\u00f6ttmes",
    "sg:phone":"+49 8253/543",
    "sg:postcode":"86554",
    "sg:province":"Bayern",
    "wof:name":"Alois Stegmeir",
    "wof:placetype":"venue"
},
  "geometry": {"coordinates":[11.151415,48.578827],"type":"Point"}
}