{
  "type": "Feature",
  "properties": {
    "iso:country":"DE",
    "sg:address":"Hopfengarten 15",
    "sg:city":"Bad Laasphe",
    "sg:phone":"+49 2754/218",
    "sg:postcode":"57334",
    "sg:province":"Nordrhein-Westfalen",
    "wof:name":"Hugo Griesenbeck Gmbh & Co. Kg",
    "wof:placetype":"venue"
},
  "geometry": {"coordinates":[8.3710155487,50.9494590759],"type":"Point"}
}