{
  "type": "Feature",
  "properties": {
    "iso:country":"DE",
    "sg:address":"Bahnhofstr 40",
    "sg:city":"Lauterecken",
    "sg:phone":"+49 6483/91410",
    "sg:postcode":"67742",
    "sg:province":"Rheinland-Pfalz",
    "wof:name":"Ober Selters Mineral- Und Heilquellen Gmbh",
    "wof:placetype":"venue"
},
  "geometry": {"coordinates":[8.291642,50.315453],"type":"Point"}
}