{
  "type": "Feature",
  "properties": {
    "iso:country":"DE",
    "sg:address":"Rothenburger Str. 18 a",
    "sg:city":"Oberasbach",
    "sg:phone":"+49 911/692992",
    "sg:postcode":"90522",
    "sg:province":"Bayern",
    "wof:name":"Reinhold Neuner",
    "wof:placetype":"venue"
},
  "geometry": {"coordinates":[10.980426,49.436932],"type":"Point"}
}