{
  "type": "Feature",
  "properties": {
    "iso:country":"DE",
    "sg:address":"Adam-Lauterbach-Weg 18",
    "sg:city":"Rosengarten",
    "sg:phone":"+49 791/9597974",
    "sg:postcode":"74538",
    "sg:province":"Baden-W\u00fcrttemberg",
    "wof:name":"Friedrich",
    "wof:placetype":"venue"
},
  "geometry": {"coordinates":[9.707859993,49.0689201355],"type":"Point"}
}