{
  "type": "Feature",
  "properties": {
    "iso:country":"DE",
    "sg:address":"Sedanstr. 13",
    "sg:city":"Minden",
    "sg:phone":"+49 571/30366",
    "sg:postcode":"32423",
    "sg:province":"Nordrhein-Westfalen",
    "wof:name":"Dr. Hans Georg Br\u00fcning Tierarzt",
    "wof:placetype":"venue"
},
  "geometry": {"coordinates":[8.9459695816,52.2893257141],"type":"Point"}
}