{
  "type": "Feature",
  "properties": {
    "iso:country":"DE",
    "sg:address":"Weinbergstr. 114",
    "sg:city":"Weil am Rhein",
    "sg:phone":"+49 7621/77811",
    "sg:postcode":"79576",
    "sg:province":"Baden-W\u00fcrttemberg",
    "wof:name":"Erler",
    "wof:placetype":"venue"
},
  "geometry": {"coordinates":[7.6192331314,47.6078643799],"type":"Point"}
}