{
  "type": "Feature",
  "properties": {
    "iso:country":"DE",
    "sg:address":"Peiner Str. 25a",
    "sg:city":"Edemissen",
    "sg:phone":"+49 5176/90492",
    "sg:postcode":"31234",
    "sg:province":"Niedersachsen",
    "wof:name":"Hl-markt",
    "wof:placetype":"venue"
},
  "geometry": {"coordinates":[10.2582988739,52.3850975037],"type":"Point"}
}