{
  "type": "Feature",
  "properties": {
    "iso:country":"DE",
    "sg:address":"Mainzerhofplatz 13",
    "sg:city":"Erfurt",
    "sg:phone":"+49 361/6431836",
    "sg:postcode":"99084",
    "sg:province":"Th\u00fcringen",
    "wof:name":"Apotheke Am Mainzerhofplatz Inge Schubarth",
    "wof:placetype":"venue"
},
  "geometry": {"coordinates":[11.019358,50.974957],"type":"Point"}
}