{
  "type": "Feature",
  "properties": {
    "iso:country":"DE",
    "sg:address":"Neckartalstr. 44",
    "sg:city":"Beerfelden",
    "sg:phone":"+49 6068/3278",
    "sg:postcode":"64743",
    "sg:province":"Hessen",
    "wof:name":"W. Hauck",
    "wof:placetype":"venue"
},
  "geometry": {"coordinates":[8.9648246765,49.5061378479],"type":"Point"}
}