{
  "type": "Feature",
  "properties": {
    "iso:country":"DE",
    "sg:address":"Franz-Pfaffenberger-Str. 1",
    "sg:city":"Kelheim",
    "sg:phone":"+49 9441/1397",
    "sg:postcode":"93309",
    "sg:province":"Bayern",
    "wof:name":"Gastst\u00e4tte M. Kaiser",
    "wof:placetype":"venue"
},
  "geometry": {"coordinates":[11.8786840439,48.9193763733],"type":"Point"}
}