{
  "type": "Feature",
  "properties": {
    "iso:country":"DE",
    "sg:address":"Pestalozzistr. 28",
    "sg:city":"Greifswald",
    "sg:phone":"+49 3834/502098",
    "sg:postcode":"17489",
    "sg:province":"Mecklenburg-Vorpommern",
    "wof:name":"H. Und W. Manthey",
    "wof:placetype":"venue"
},
  "geometry": {"coordinates":[13.3812932968,54.0869979858],"type":"Point"}
}