{
  "type": "Feature",
  "properties": {
    "iso:country":"DE",
    "sg:address":"Am Lachengraben 3a",
    "sg:city":"Dreieich",
    "sg:phone":"+49 6103/81013",
    "sg:postcode":"63303",
    "sg:province":"Hessen",
    "wof:name":"Thoma-druck Gmbh",
    "wof:placetype":"venue"
},
  "geometry": {"coordinates":[8.734654,50.000225],"type":"Point"}
}