{
  "type": "Feature",
  "properties": {
    "iso:country":"DE",
    "sg:address":"R\u00f6tzberg 25",
    "sg:city":"Neustadt",
    "sg:phone":"+49 5036/2661",
    "sg:postcode":"31535",
    "sg:province":"Niedersachsen",
    "wof:name":"Altenheim Haus Am R\u00f6tzberg",
    "wof:placetype":"venue"
},
  "geometry": {"coordinates":[9.335201,52.538223],"type":"Point"}
}