{
  "type": "Feature",
  "properties": {
    "iso:country":"DE",
    "sg:address":"Waldenauer Marktplatz 4",
    "sg:city":"Pinneberg",
    "sg:phone":"+49 4101/65329",
    "sg:postcode":"25421",
    "sg:province":"Schleswig-Holstein",
    "wof:name":"Holger Haarmeyer",
    "wof:placetype":"venue"
},
  "geometry": {"coordinates":[9.794825,53.621002],"type":"Point"}
}