{
  "type": "Feature",
  "properties": {
    "iso:country":"DE",
    "sg:address":"Mukraner Str. 1",
    "sg:city":"Sassnitz",
    "sg:postcode":"18546",
    "sg:province":"Mecklenburg-Vorpommern",
    "wof:name":"Eurospar",
    "wof:placetype":"venue"
},
  "geometry": {"coordinates":[13.6163215637,54.5106735229],"type":"Point"}
}