{
  "type": "Feature",
  "properties": {
    "iso:country":"DE",
    "sg:address":"K\u00f6lner Str. 18",
    "sg:city":"Wuppertal",
    "sg:phone":"+49 202/423366",
    "sg:postcode":"42119",
    "sg:province":"Nordrhein-Westfalen",
    "wof:name":"U. Knitterscheidt",
    "wof:placetype":"venue"
},
  "geometry": {"coordinates":[7.143175,51.251652],"type":"Point"}
}