{
  "type": "Feature",
  "properties": {
    "iso:country":"DE",
    "sg:address":"Pfeiffergasse 4",
    "sg:city":"Guxhagen",
    "sg:phone":"+49 5665/1095",
    "sg:postcode":"34302",
    "sg:province":"Hessen",
    "wof:name":"Heinrich Friedrich",
    "wof:placetype":"venue"
},
  "geometry": {"coordinates":[9.513973,51.212311],"type":"Point"}
}