{
  "type": "Feature",
  "properties": {
    "iso:country":"DE",
    "sg:address":"Zeughausweg 22",
    "sg:city":"Dietenheim",
    "sg:phone":"+49 7347/2625",
    "sg:postcode":"89165",
    "sg:province":"Baden-W\u00fcrttemberg",
    "wof:name":"Hans M\u00fcller",
    "wof:placetype":"venue"
},
  "geometry": {"coordinates":[10.0761480331,48.2084922791],"type":"Point"}
}