{
  "type": "Feature",
  "properties": {
    "iso:country":"DE",
    "sg:address":"Bismarckplatz 4",
    "sg:city":"Regensburg",
    "sg:phone":"+49 941/53908",
    "sg:postcode":"93047",
    "sg:province":"Bayern",
    "wof:name":"Falks Weinstube",
    "wof:placetype":"venue"
},
  "geometry": {"coordinates":[12.0892839432,49.0186843872],"type":"Point"}
}