{
  "type": "Feature",
  "properties": {
    "iso:country":"DE",
    "sg:address":"Theodor-Hanloser-Str. 1",
    "sg:city":"Singen",
    "sg:phone":"+49 7731/41214",
    "sg:postcode":"78224",
    "sg:province":"Baden-W\u00fcrttemberg",
    "wof:name":"C. D\u00f6ring Ingenieur",
    "wof:placetype":"venue"
},
  "geometry": {"coordinates":[8.8364515305,47.7633361816],"type":"Point"}
}