{
  "type": "Feature",
  "properties": {
    "iso:country":"DE",
    "sg:address":"Freinsheimer Weg 10",
    "sg:city":"Bissersheim",
    "sg:phone":"+49 6359/82124",
    "sg:postcode":"67281",
    "sg:province":"Rheinland-Pfalz",
    "wof:name":"Dietmar Bunk",
    "wof:placetype":"venue"
},
  "geometry": {"coordinates":[8.1999750137,49.5354995728],"type":"Point"}
}