{
  "type": "Feature",
  "properties": {
    "iso:country":"DE",
    "sg:address":"Heiderstr. 133",
    "sg:city":"Wegberg",
    "sg:phone":"+49 2436/781",
    "sg:postcode":"41844",
    "sg:province":"Nordrhein-Westfalen",
    "wof:name":"H. Krebs Gmbh",
    "wof:placetype":"venue"
},
  "geometry": {"coordinates":[6.207966,51.156624],"type":"Point"}
}