{
  "type": "Feature",
  "properties": {
    "iso:country":"DE",
    "sg:address":"Semmelweisstr. 27/28",
    "sg:city":"Bernburg",
    "sg:phone":"+49 4934/713270",
    "sg:postcode":"06406",
    "sg:province":"Sachsen-Anhalt",
    "wof:name":"Deutsches Rotes Kreuz Kreisverband Bernburg Ev",
    "wof:placetype":"venue"
},
  "geometry": {"coordinates":[11.73456,51.793259],"type":"Point"}
}