{
  "type": "Feature",
  "properties": {
    "iso:country":"DE",
    "sg:address":"Neue Landstr. 43",
    "sg:city":"Dautphetal",
    "sg:phone":"+49 6466/1219",
    "sg:postcode":"35232",
    "sg:province":"Hessen",
    "wof:name":"Hans Schneider",
    "wof:placetype":"venue"
},
  "geometry": {"coordinates":[8.5939254761,50.8720016479],"type":"Point"}
}