{
  "type": "Feature",
  "properties": {
    "iso:country":"DE",
    "sg:address":"Dieler Str. 18",
    "sg:city":"Weener",
    "sg:phone":"+49 4951/1368",
    "sg:postcode":"26826",
    "sg:province":"Niedersachsen",
    "wof:name":"Dieler Imbi\u00df",
    "wof:placetype":"venue"
},
  "geometry": {"coordinates":[7.3139801025,53.1207504272],"type":"Point"}
}