{
  "type": "Feature",
  "properties": {
    "iso:country":"DE",
    "sg:address":"Konstanzenstr 58",
    "sg:city":"N\u00fcrnberg",
    "sg:phone":"+49 911/610157",
    "sg:postcode":"90439",
    "sg:province":"Bayern",
    "wof:name":"Ek-elektronik",
    "wof:placetype":"venue"
},
  "geometry": {"coordinates":[11.0394153595,49.4374427795],"type":"Point"}
}