{
  "type": "Feature",
  "properties": {
    "iso:country":"DE",
    "sg:address":"Brunnenstr. 6",
    "sg:city":"Breuberg",
    "sg:phone":"+49 6165/6359",
    "sg:postcode":"64747",
    "sg:province":"Hessen",
    "wof:name":"R. B\u00fcchin",
    "wof:placetype":"venue"
},
  "geometry": {"coordinates":[9.0419168472,49.8341331482],"type":"Point"}
}