{
  "type": "Feature",
  "properties": {
    "iso:country":"DE",
    "sg:address":"Wandalenstr. 33a",
    "sg:city":"K\u00f6nigsbrunn",
    "sg:postcode":"86343",
    "sg:province":"Bayern",
    "wof:name":"J. M. H\u00f6rmann",
    "wof:placetype":"venue"
},
  "geometry": {"coordinates":[10.89414,48.286037],"type":"Point"}
}