{
  "type": "Feature",
  "properties": {
    "iso:country":"DE",
    "sg:address":"Am Dorfplatz 4",
    "sg:city":"Sankelmark",
    "sg:phone":"+49 4630/758",
    "sg:postcode":"24988",
    "sg:province":"Schleswig-Holstein",
    "wof:name":"Ludwig Jessen",
    "wof:placetype":"venue"
},
  "geometry": {"coordinates":[9.429771,54.700863],"type":"Point"}
}