{
  "type": "Feature",
  "properties": {
    "iso:country":"DE",
    "sg:address":"Aueweg 6",
    "sg:city":"Walkenried",
    "sg:phone":"+49 5525/1087",
    "sg:postcode":"37445",
    "sg:province":"Niedersachsen",
    "wof:name":"Husung & Brinkmann Gbr",
    "wof:placetype":"venue"
},
  "geometry": {"coordinates":[10.621375,51.591225],"type":"Point"}
}