{
  "type": "Feature",
  "properties": {
    "iso:country":"DE",
    "sg:address":"Kaiserstr. 52",
    "sg:city":"Haan",
    "sg:phone":"+49 212/959451",
    "sg:postcode":"42781",
    "sg:province":"Nordrhein-Westfalen",
    "wof:name":"Restaurant Kebaphaus",
    "wof:placetype":"venue"
},
  "geometry": {"coordinates":[7.0136752129,51.1930274963],"type":"Point"}
}