{
  "type": "Feature",
  "properties": {
    "iso:country":"DE",
    "sg:address":"Astwiesen 2",
    "sg:city":"Boll",
    "sg:phone":"+49 7164/6643",
    "sg:postcode":"73087",
    "sg:province":"Baden-W\u00fcrttemberg",
    "wof:name":"Sonnenhof",
    "wof:placetype":"venue"
},
  "geometry": {"coordinates":[9.599784,48.645473],"type":"Point"}
}