{
  "type": "Feature",
  "properties": {
    "iso:country":"DE",
    "sg:address":"Julius-Otto-Str. 13",
    "sg:city":"Korschenbroich",
    "sg:postcode":"41352",
    "sg:province":"Nordrhein-Westfalen",
    "wof:name":"Icon Immobilien- Beratungsgesellschaft Mbh",
    "wof:placetype":"venue"
},
  "geometry": {"coordinates":[6.5185790062,51.1910934448],"type":"Point"}
}