{
  "type": "Feature",
  "properties": {
    "iso:country":"DE",
    "sg:address":"Schlo\u00dfstr. 45",
    "sg:city":"Dormagen",
    "sg:phone":"+49 2133/210101",
    "sg:postcode":"41541",
    "sg:province":"Nordrhein-Westfalen",
    "wof:name":"Ambulante Krankenpflege Neuss",
    "wof:placetype":"venue"
},
  "geometry": {"coordinates":[6.849385,51.120232],"type":"Point"}
}