{
  "type": "Feature",
  "properties": {
    "iso:country":"DE",
    "sg:address":"Schillerweg 36",
    "sg:city":"K\u00f6ln",
    "sg:phone":"+49 4711",
    "sg:postcode":"50667",
    "sg:province":"Nordrhein-Westfalen",
    "wof:name":"Kostenlose Quickshops Bei Wowowo.clickware.de",
    "wof:placetype":"venue"
},
  "geometry": {"coordinates":[6.954792,50.936543],"type":"Point"}
}