{
  "type": "Feature",
  "properties": {
    "iso:country":"DE",
    "sg:address":"Birkenring 17",
    "sg:city":"Sehnde",
    "sg:phone":"+49 5132/86960",
    "sg:postcode":"31319",
    "sg:province":"Niedersachsen",
    "wof:name":"Franz Bollig Anlageberater",
    "wof:placetype":"venue"
},
  "geometry": {"coordinates":[9.9390602112,52.3476638794],"type":"Point"}
}