{
  "type": "Feature",
  "properties": {
    "iso:country":"DE",
    "sg:address":"Nordstr. 8",
    "sg:city":"Tr\u00f6glitz",
    "sg:phone":"+49 3443/84194",
    "sg:postcode":"06729",
    "sg:province":"Sachsen-Anhalt",
    "wof:name":"Autolackierfachbetrieb Lange Gmbh",
    "wof:placetype":"venue"
},
  "geometry": {"coordinates":[12.181728,51.060055],"type":"Point"}
}