{
  "type": "Feature",
  "properties": {
    "iso:country":"DE",
    "sg:address":"Goethestr. 7",
    "sg:city":"Hannover",
    "sg:phone":"+49 511/3008084",
    "sg:postcode":"30169",
    "sg:province":"Niedersachsen",
    "wof:name":"Cm Tele Com",
    "wof:placetype":"venue"
},
  "geometry": {"coordinates":[9.722784996,52.3726577759],"type":"Point"}
}