{
  "type": "Feature",
  "properties": {
    "iso:country":"DE",
    "sg:address":"Bahnhofstr. 7",
    "sg:city":"Weinsheim",
    "sg:phone":"+49 6558/304",
    "sg:postcode":"54595",
    "sg:province":"Rheinland-Pfalz",
    "wof:name":"A. Lorsy",
    "wof:placetype":"venue"
},
  "geometry": {"coordinates":[6.500644207,50.2341117859],"type":"Point"}
}