{
  "type": "Feature",
  "properties": {
    "iso:country":"DE",
    "sg:address":"M\u00fcnchner Str. 8",
    "sg:city":"Pfaffing",
    "sg:phone":"+49 8094/1424",
    "sg:postcode":"83539",
    "sg:province":"Bayern",
    "wof:name":"Jakob Zellner",
    "wof:placetype":"venue"
},
  "geometry": {"coordinates":[12.091763,48.081337],"type":"Point"}
}