{
  "type": "Feature",
  "properties": {
    "iso:country":"DE",
    "sg:address":"M\u00fchlgrabenstr. 4",
    "sg:city":"Meckenheim",
    "sg:phone":"+49 2225/88500",
    "sg:postcode":"53340",
    "sg:province":"Nordrhein-Westfalen",
    "wof:name":"Everhards Gmbh",
    "wof:placetype":"venue"
},
  "geometry": {"coordinates":[7.020503,50.640594],"type":"Point"}
}