{
  "type": "Feature",
  "properties": {
    "iso:country":"DE",
    "sg:address":"Robert-Bosch-Str. 16",
    "sg:city":"Heddesheim",
    "sg:postcode":"68542",
    "sg:province":"Baden-W\u00fcrttemberg",
    "wof:name":"Kufner Gmbh",
    "wof:placetype":"venue"
},
  "geometry": {"coordinates":[8.6032772064,49.5052909851],"type":"Point"}
}