{
  "type": "Feature",
  "properties": {
    "iso:country":"DE",
    "sg:address":"Bahnhofstr 8a",
    "sg:city":"Halbe",
    "sg:phone":"+49 33765/84828",
    "sg:postcode":"15757",
    "sg:province":"Brandenburg",
    "wof:name":"Didier Diamant Gmbh",
    "wof:placetype":"venue"
},
  "geometry": {"coordinates":[13.699945,52.111099],"type":"Point"}
}