{
  "type": "Feature",
  "properties": {
    "iso:country":"DE",
    "sg:address":"Maingasse 22",
    "sg:city":"Wertheim",
    "sg:phone":"+49 9342/9010",
    "sg:postcode":"97877",
    "sg:province":"Baden-W\u00fcrttemberg",
    "wof:name":"Fn Reiseb\u00fcro Der Fr\u00e4nkischen Nachrichten",
    "wof:placetype":"venue"
},
  "geometry": {"coordinates":[9.5163908005,49.7605323792],"type":"Point"}
}