{
  "type": "Feature",
  "properties": {
    "iso:country":"DE",
    "sg:address":"Waldfriede 2",
    "sg:city":"Nauheim",
    "sg:phone":"+49 6152/63511",
    "sg:postcode":"64569",
    "sg:province":"Hessen",
    "wof:name":"M. Eberhardt Gmbh",
    "wof:placetype":"venue"
},
  "geometry": {"coordinates":[8.4522342682,49.9534912109],"type":"Point"}
}