{
  "type": "Feature",
  "properties": {
    "iso:country":"DE",
    "sg:address":"Am Alten Weg 22",
    "sg:city":"Oberhaching",
    "sg:phone":"+49 89/6252194",
    "sg:postcode":"82041",
    "sg:province":"Bayern",
    "wof:name":"Jipp Grundst\u00fccksges. Mbh",
    "wof:placetype":"venue"
},
  "geometry": {"coordinates":[11.57305336,48.0327033997],"type":"Point"}
}