{
  "type": "Feature",
  "properties": {
    "iso:country":"DE",
    "sg:address":"F.-O.-Schimmel-Str. 12",
    "sg:city":"Chemnitz",
    "sg:phone":"+49 371/520620",
    "sg:postcode":"09120",
    "sg:province":"Sachsen",
    "wof:name":"Mobiltec Gmbh",
    "wof:placetype":"venue"
},
  "geometry": {"coordinates":[12.9243593216,50.8048095703],"type":"Point"}
}