{
  "type": "Feature",
  "properties": {
    "iso:country":"DE",
    "sg:address":"Karlstr. 7",
    "sg:city":"A\u00dflar",
    "sg:phone":"+49 6441/81109",
    "sg:postcode":"35614",
    "sg:province":"Hessen",
    "wof:name":"Heinrich Schneider Handarbeiten",
    "wof:placetype":"venue"
},
  "geometry": {"coordinates":[8.462165,50.592903],"type":"Point"}
}