{
  "type": "Feature",
  "properties": {
    "iso:country":"DE",
    "sg:address":"Am Markt 12",
    "sg:city":"Schwerin",
    "sg:phone":"+49 385/569326",
    "sg:postcode":"19055",
    "sg:province":"Mecklenburg-Vorpommern",
    "wof:name":"Eiscafe H.-j. Quednau",
    "wof:placetype":"venue"
},
  "geometry": {"coordinates":[11.415416,53.628704],"type":"Point"}
}