{
  "type": "Feature",
  "properties": {
    "iso:country":"DE",
    "sg:address":"Friedrichstr. 92",
    "sg:city":"Velbert",
    "sg:phone":"+49 2051/95610",
    "sg:postcode":"42551",
    "sg:province":"Nordrhein-Westfalen",
    "wof:name":"Dietmar Schellenberg Steuerberater",
    "wof:placetype":"venue"
},
  "geometry": {"coordinates":[7.0391511917,51.3423271179],"type":"Point"}
}