{
  "type": "Feature",
  "properties": {
    "iso:country":"DE",
    "sg:address":"W\u00fcrmstr. 58",
    "sg:city":"Dachau",
    "sg:phone":"+49 8131/26411",
    "sg:postcode":"85221",
    "sg:province":"Bayern",
    "wof:name":"Baur & Mayr",
    "wof:placetype":"venue"
},
  "geometry": {"coordinates":[11.464614,48.261604],"type":"Point"}
}