{
  "type": "Feature",
  "properties": {
    "iso:country":"DE",
    "sg:address":"Fastlingerstr. 4",
    "sg:city":"M\u00fchldorf",
    "sg:phone":"+49 8631/5296",
    "sg:postcode":"84453",
    "sg:province":"Bayern",
    "wof:name":"Dr. Karl Ernst Tierarzt",
    "wof:placetype":"venue"
},
  "geometry": {"coordinates":[12.5005722046,48.2470626831],"type":"Point"}
}