{
  "type": "Feature",
  "properties": {
    "iso:country":"DE",
    "sg:address":"August-Vilmar-Str. 19",
    "sg:city":"Homberg",
    "sg:phone":"+49 5681/4481",
    "sg:postcode":"34576",
    "sg:province":"Hessen",
    "wof:name":"Reiner Ziegler",
    "wof:placetype":"venue"
},
  "geometry": {"coordinates":[9.4204826355,51.0309677124],"type":"Point"}
}