{
  "type": "Feature",
  "properties": {
    "iso:country":"DE",
    "sg:address":"Sebastian-Merkle-Str. 22",
    "sg:city":"Ellwangen",
    "sg:phone":"+49 7961/2269",
    "sg:postcode":"73479",
    "sg:province":"Baden-W\u00fcrttemberg",
    "wof:name":"W. Thorwart",
    "wof:placetype":"venue"
},
  "geometry": {"coordinates":[10.1315450668,48.9657669067],"type":"Point"}
}