{
  "type": "Feature",
  "properties": {
    "iso:country":"DE",
    "sg:address":"Franz-Josef-R\u00f6der-Str 9",
    "sg:city":"Saarbr\u00fccken",
    "sg:phone":"+49 681/9520470",
    "sg:postcode":"66119",
    "sg:province":"Saarland",
    "wof:name":"Zentrale F\u00fcr Produktivit\u00e4t Und Technologie Saar Ev",
    "wof:placetype":"venue"
},
  "geometry": {"coordinates":[6.994376,49.229557],"type":"Point"}
}