{
  "type": "Feature",
  "properties": {
    "iso:country":"DE",
    "sg:address":"Loarbergsweg 5",
    "sg:city":"Uelsen",
    "sg:phone":"+49 5942/1703",
    "sg:postcode":"49843",
    "sg:province":"Niedersachsen",
    "wof:name":"Georg Arends",
    "wof:placetype":"venue"
},
  "geometry": {"coordinates":[6.879805,52.498608],"type":"Point"}
}