{
  "type": "Feature",
  "properties": {
    "iso:country":"DE",
    "sg:address":"Postfach 4",
    "sg:city":"Argenb\u00fchl",
    "sg:phone":"+49 7566/382",
    "sg:postcode":"88258",
    "sg:province":"Baden-W\u00fcrttemberg",
    "wof:name":"Moorbad Burg Gemeinde Eisenharz",
    "wof:placetype":"venue"
},
  "geometry": {"coordinates":[9.95942,47.688148],"type":"Point"}
}