{
  "type": "Feature",
  "properties": {
    "iso:country":"DE",
    "sg:address":"Parzivalstr. 63",
    "sg:city":"M\u00fcnchen",
    "sg:phone":"+49 89/3000980",
    "sg:postcode":"80804",
    "sg:province":"Bayern",
    "wof:name":"Damenstift Am Luitpoldpark",
    "wof:placetype":"venue"
},
  "geometry": {"coordinates":[11.575166,48.169975],"type":"Point"}
}