{
  "type": "Feature",
  "properties": {
    "iso:country":"DE",
    "sg:address":"Auguststr. 36",
    "sg:city":"Oldenburg",
    "sg:phone":"+49 441/73254",
    "sg:postcode":"26121",
    "sg:province":"Niedersachsen",
    "wof:name":"Wabe Warenbeschaffungs-und Vertriebsgesellschaft Mbh",
    "wof:placetype":"venue"
},
  "geometry": {"coordinates":[8.2040567398,53.1440086365],"type":"Point"}
}