{
  "type": "Feature",
  "properties": {
    "iso:country":"DE",
    "sg:address":"Marktplatz 8 a",
    "sg:city":"Hamm",
    "sg:phone":"+49 2381",
    "sg:postcode":"59065",
    "sg:province":"Nordrhein-Westfalen",
    "wof:name":"Brokbals Am Markt",
    "wof:placetype":"venue"
},
  "geometry": {"coordinates":[7.8202900887,51.6815414429],"type":"Point"}
}