{
  "type": "Feature",
  "properties": {
    "iso:country":"DE",
    "sg:address":"Elsenstr. 1",
    "sg:city":"Berlin",
    "sg:phone":"+49 30/2479178",
    "sg:postcode":"12435",
    "sg:province":"Berlin",
    "wof:name":"R\u00fcdiger Schulz",
    "wof:placetype":"venue"
},
  "geometry": {"coordinates":[13.4601545334,52.4938583374],"type":"Point"}
}