{
  "type": "Feature",
  "properties": {
    "iso:country":"DE",
    "sg:address":"Im Bifig 3",
    "sg:city":"Schopfheim",
    "sg:phone":"+49 7622/5261",
    "sg:postcode":"79650",
    "sg:province":"Baden-W\u00fcrttemberg",
    "wof:name":"H. Mertens Immobilienmakler",
    "wof:placetype":"venue"
},
  "geometry": {"coordinates":[7.8181829453,47.6511459351],"type":"Point"}
}