{
  "type": "Feature",
  "properties": {
    "iso:country":"DE",
    "sg:address":"Bredeneyer Str. 108",
    "sg:city":"Essen",
    "sg:phone":"+49 201/412412",
    "sg:postcode":"45133",
    "sg:province":"Nordrhein-Westfalen",
    "wof:name":"Herbert Venghaus",
    "wof:placetype":"venue"
},
  "geometry": {"coordinates":[6.99391,51.413017],"type":"Point"}
}