{
  "type": "Feature",
  "properties": {
    "iso:country":"DE",
    "sg:address":"Jahnstr. 16",
    "sg:city":"Eschweiler",
    "sg:phone":"+49 2403/24806",
    "sg:postcode":"52249",
    "sg:province":"Nordrhein-Westfalen",
    "wof:name":"Hallenbad",
    "wof:placetype":"venue"
},
  "geometry": {"coordinates":[6.2562799454,50.8197479248],"type":"Point"}
}