{
  "type": "Feature",
  "properties": {
    "iso:country":"DE",
    "sg:address":"Markt 24",
    "sg:city":"Mittweida",
    "sg:phone":"+49 3727/2374",
    "sg:postcode":"09648",
    "sg:province":"Sachsen",
    "wof:name":"Stadt- Und L\u00f6wen-apotheke",
    "wof:placetype":"venue"
},
  "geometry": {"coordinates":[12.986243,50.999504],"type":"Point"}
}