{
  "type": "Feature",
  "properties": {
    "iso:country":"DE",
    "sg:address":"Hintere Torstr. 6",
    "sg:city":"Oberthulba",
    "sg:phone":"+49 9736/1204",
    "sg:postcode":"97723",
    "sg:province":"Bayern",
    "wof:name":"Egid G\u00e4rtner",
    "wof:placetype":"venue"
},
  "geometry": {"coordinates":[9.960715,50.198956],"type":"Point"}
}