{
  "type": "Feature",
  "properties": {
    "iso:country":"DE",
    "sg:address":"Ringstr. 34",
    "sg:city":"Bad Oeynhausen",
    "sg:phone":"+49 5731/40310",
    "sg:postcode":"32549",
    "sg:province":"Nordrhein-Westfalen",
    "wof:name":"Werster Hof",
    "wof:placetype":"venue"
},
  "geometry": {"coordinates":[8.7798881531,52.2199478149],"type":"Point"}
}