{
  "type": "Feature",
  "properties": {
    "iso:country":"DE",
    "sg:address":"Marktplatz 4",
    "sg:city":"Schliengen",
    "sg:phone":"+49 7635/1395",
    "sg:postcode":"79418",
    "sg:province":"Baden-W\u00fcrttemberg",
    "wof:name":"Restaurant Schl\u00fcssel",
    "wof:placetype":"venue"
},
  "geometry": {"coordinates":[7.5769748688,47.7556419373],"type":"Point"}
}