{
  "type": "Feature",
  "properties": {
    "iso:country":"DE",
    "sg:address":"Wertachbrucker-Tor-Str. 9",
    "sg:city":"Augsburg",
    "sg:phone":"+49 821/510880",
    "sg:postcode":"86152",
    "sg:province":"Bayern",
    "wof:name":"Wirtshaus Am Wertachbrucker Tor",
    "wof:placetype":"venue"
},
  "geometry": {"coordinates":[10.8889245987,48.3762359619],"type":"Point"}
}