{
  "type": "Feature",
  "properties": {
    "iso:country":"DE",
    "sg:city":"Stadtoldendorf",
    "sg:phone":"+49 5532/3690",
    "sg:postcode":"37627",
    "sg:province":"Niedersachsen",
    "wof:name":"P\u00e4dagogische Videos Hello Chodura",
    "wof:placetype":"venue"
},
  "geometry": {"coordinates":[9.624008,51.882301],"type":"Point"}
}