{
  "type": "Feature",
  "properties": {
    "iso:country":"DE",
    "sg:address":"Templergraben 1",
    "sg:city":"Aachen",
    "sg:phone":"+49 241/30172",
    "sg:postcode":"52062",
    "sg:province":"Nordrhein-Westfalen",
    "wof:name":"Pizzeria Frascati",
    "wof:placetype":"venue"
},
  "geometry": {"coordinates":[6.0755372047,50.775806427],"type":"Point"}
}