{
  "type": "Feature",
  "properties": {
    "iso:country":"DE",
    "sg:address":"Obotritenring 169",
    "sg:city":"Schwerin",
    "sg:phone":"+49 385/710642",
    "sg:postcode":"19053",
    "sg:province":"Mecklenburg-Vorpommern",
    "wof:name":"Fritz Werner Immobilien Gmbh",
    "wof:placetype":"venue"
},
  "geometry": {"coordinates":[11.4012298584,53.6232299805],"type":"Point"}
}