{
  "type": "Feature",
  "properties": {
    "iso:country":"DE",
    "sg:address":"K\u00e4rntener Str. 12",
    "sg:city":"Oberhausen",
    "sg:phone":"+49 208/872248",
    "sg:postcode":"46047",
    "sg:province":"Nordrhein-Westfalen",
    "wof:name":"Ursula Sch\u00e4fer",
    "wof:placetype":"venue"
},
  "geometry": {"coordinates":[6.8858060837,51.4671669006],"type":"Point"}
}