{
  "type": "Feature",
  "properties": {
    "iso:country":"DE",
    "sg:address":"M\u00fchlweg 33",
    "sg:city":"Uttenweiler",
    "sg:phone":"+49 7374/558",
    "sg:postcode":"88524",
    "sg:province":"Baden-W\u00fcrttemberg",
    "wof:name":"Richard Stocker Fensterbau- Gmbh",
    "wof:placetype":"venue"
},
  "geometry": {"coordinates":[9.612622,48.15358],"type":"Point"}
}