{
  "type": "Feature",
  "properties": {
    "iso:country":"DE",
    "sg:address":"Hermann-L\u00f6ns-Str. 11",
    "sg:city":"L\u00fcneburg",
    "sg:phone":"+49 4131/52247",
    "sg:postcode":"21337",
    "sg:province":"Niedersachsen",
    "wof:name":"Burghard Moers",
    "wof:placetype":"venue"
},
  "geometry": {"coordinates":[10.4347162247,53.2619438171],"type":"Point"}
}