{
  "type": "Feature",
  "properties": {
    "iso:country":"DE",
    "sg:address":"Wallstr. 17",
    "sg:city":"Dresden",
    "sg:phone":"+49 351/4956574",
    "sg:postcode":"01067",
    "sg:province":"Sachsen",
    "wof:name":"Christel Hartig",
    "wof:placetype":"venue"
},
  "geometry": {"coordinates":[13.7347545624,51.0480613708],"type":"Point"}
}