{
  "type": "Feature",
  "properties": {
    "iso:country":"DE",
    "sg:address":"Endzeteler Str. 5",
    "sg:city":"Wittmund",
    "sg:phone":"+49 4467/447",
    "sg:postcode":"26409",
    "sg:province":"Niedersachsen",
    "wof:name":"Joachim Richter",
    "wof:placetype":"venue"
},
  "geometry": {"coordinates":[7.751866,53.641972],"type":"Point"}
}