{
  "type": "Feature",
  "properties": {
    "iso:country":"DE",
    "sg:address":"Winsstr. 11",
    "sg:city":"Berlin",
    "sg:postcode":"10405",
    "sg:province":"Berlin",
    "wof:name":"Johannes Richter",
    "wof:placetype":"venue"
},
  "geometry": {"coordinates":[13.424638,52.532852],"type":"Point"}
}