{
  "type": "Feature",
  "properties": {
    "iso:country":"DE",
    "sg:address":"Segeberger Chaussee 9",
    "sg:city":"Ahrensb\u00f6k",
    "sg:phone":"+49 4525/737",
    "sg:postcode":"23623",
    "sg:province":"Schleswig-Holstein",
    "wof:name":"Heinrich Klempan",
    "wof:placetype":"venue"
},
  "geometry": {"coordinates":[10.5670690536,54.0136947632],"type":"Point"}
}