{
  "type": "Feature",
  "properties": {
    "iso:country":"DE",
    "sg:address":"Werftallee 12",
    "sg:city":"Rostock",
    "sg:phone":"+49 381/5192368",
    "sg:postcode":"18119",
    "sg:province":"Mecklenburg-Vorpommern",
    "wof:name":"Wbs Warnem\u00fcnder Baustoff- Und Strahlmittelhandel Gmbh",
    "wof:placetype":"venue"
},
  "geometry": {"coordinates":[12.083159,54.162048],"type":"Point"}
}