{
  "type": "Feature",
  "properties": {
    "iso:country":"DE",
    "sg:address":"Markt 3",
    "sg:city":"Siebenlehn",
    "sg:phone":"+49 35242/62405",
    "sg:postcode":"09634",
    "sg:province":"Sachsen",
    "wof:name":"Sporthaus Haubold",
    "wof:placetype":"venue"
},
  "geometry": {"coordinates":[13.307208,51.030079],"type":"Point"}
}