{
  "type": "Feature",
  "properties": {
    "iso:country":"DE",
    "sg:address":"Brackh\u00f6vel 12",
    "sg:city":"Hamburg",
    "sg:phone":"+49 40/7544465",
    "sg:postcode":"21109",
    "sg:province":"Hamburg",
    "wof:name":"Erwin Henken",
    "wof:placetype":"venue"
},
  "geometry": {"coordinates":[10.0167694092,53.5103225708],"type":"Point"}
}