{
  "type": "Feature",
  "properties": {
    "iso:country":"DE",
    "sg:address":"Friedrich-Ebert-Str. 152",
    "sg:city":"Kassel",
    "sg:phone":"+49 561/78820",
    "sg:postcode":"34119",
    "sg:province":"Hessen",
    "wof:name":"Tagungszentrum Stadthalle Kassel Gmbh",
    "wof:placetype":"venue"
},
  "geometry": {"coordinates":[9.4608154297,51.3162384033],"type":"Point"}
}