{
  "type": "Feature",
  "properties": {
    "iso:country":"DE",
    "sg:address":"Darast 19",
    "sg:city":"Woringen",
    "sg:phone":"+49 8334/851",
    "sg:postcode":"87789",
    "sg:province":"Bayern",
    "wof:name":"Hans Steidele Gmbh",
    "wof:placetype":"venue"
},
  "geometry": {"coordinates":[10.2261295319,47.9091682434],"type":"Point"}
}