{
  "type": "Feature",
  "properties": {
    "iso:country":"DE",
    "sg:address":"Merianstr. 56",
    "sg:city":"Wehr",
    "sg:phone":"+49 7762/9312",
    "sg:postcode":"79664",
    "sg:province":"Baden-W\u00fcrttemberg",
    "wof:name":"Berthold Trefzger",
    "wof:placetype":"venue"
},
  "geometry": {"coordinates":[7.9023900032,47.6286811829],"type":"Point"}
}