{
  "type": "Feature",
  "properties": {
    "iso:country":"DE",
    "sg:address":"Andreasstr. 32",
    "sg:city":"Berlin",
    "sg:postcode":"10243",
    "sg:province":"Berlin",
    "wof:name":"Dr. Med. Margaret Heidicke",
    "wof:placetype":"venue"
},
  "geometry": {"coordinates":[13.432981,52.516464],"type":"Point"}
}