{
  "type": "Feature",
  "properties": {
    "iso:country":"DE",
    "sg:address":"Pater-Delp-Str. 5",
    "sg:city":"Viernheim",
    "sg:phone":"+49 6204/71682",
    "sg:postcode":"68519",
    "sg:province":"Hessen",
    "wof:name":"J. Schmitt",
    "wof:placetype":"venue"
},
  "geometry": {"coordinates":[8.5699367523,49.5289077759],"type":"Point"}
}