{
  "type": "Feature",
  "properties": {
    "iso:country":"DE",
    "sg:address":"Lerchenweg 11",
    "sg:city":"Hauneck",
    "sg:phone":"+49 6621/61660",
    "sg:postcode":"36282",
    "sg:province":"Hessen",
    "wof:name":"E. Grebner",
    "wof:placetype":"venue"
},
  "geometry": {"coordinates":[9.7385015488,50.8145484924],"type":"Point"}
}