{
  "type": "Feature",
  "properties": {
    "iso:country":"DE",
    "sg:address":"Friedrich-Engels-Str. 5",
    "sg:city":"Herzberg",
    "sg:postcode":"04916",
    "sg:province":"Brandenburg",
    "wof:name":"H. Schiementz Elektro",
    "wof:placetype":"venue"
},
  "geometry": {"coordinates":[13.230423,51.694397],"type":"Point"}
}