{
  "type": "Feature",
  "properties": {
    "iso:country":"DE",
    "sg:address":"Schwanenstr. 5",
    "sg:city":"Cham",
    "sg:phone":"+49 9971/1529",
    "sg:postcode":"93413",
    "sg:province":"Bayern",
    "wof:name":"Elisabeth Wartner",
    "wof:placetype":"venue"
},
  "geometry": {"coordinates":[12.6654243469,49.2188034058],"type":"Point"}
}