{
  "type": "Feature",
  "properties": {
    "iso:country":"DE",
    "sg:address":"Trierer Str. 18",
    "sg:city":"Monschau",
    "sg:phone":"+49 2472/4959",
    "sg:postcode":"52156",
    "sg:province":"Nordrhein-Westfalen",
    "wof:name":"M. Krings",
    "wof:placetype":"venue"
},
  "geometry": {"coordinates":[6.2520880699,50.593006134],"type":"Point"}
}