{
  "type": "Feature",
  "properties": {
    "iso:country":"DE",
    "sg:address":"Kirchplatz 14",
    "sg:city":"Steinhagen",
    "sg:phone":"+49 5204/3018",
    "sg:postcode":"33803",
    "sg:province":"Nordrhein-Westfalen",
    "wof:name":"Bistro Piano",
    "wof:placetype":"venue"
},
  "geometry": {"coordinates":[8.4135942459,52.0059165955],"type":"Point"}
}