{
  "type": "Feature",
  "properties": {
    "iso:country":"DE",
    "sg:address":"Bruchstr. 20",
    "sg:city":"Olpe",
    "sg:phone":"+49 2761/92480",
    "sg:postcode":"57462",
    "sg:province":"Nordrhein-Westfalen",
    "wof:name":"R & W Steuerberatungs Gmbh",
    "wof:placetype":"venue"
},
  "geometry": {"coordinates":[7.8437771797,51.025428772],"type":"Point"}
}