{
  "type": "Feature",
  "properties": {
    "iso:country":"DE",
    "sg:address":"R\u00f6gen 6",
    "sg:city":"Bad Oldesloe",
    "sg:phone":"+49 4531/670261",
    "sg:postcode":"23843",
    "sg:province":"Schleswig-Holstein",
    "wof:name":"Roland M\u00fcnzer",
    "wof:placetype":"venue"
},
  "geometry": {"coordinates":[10.342793,53.80006],"type":"Point"}
}