{
  "type": "Feature",
  "properties": {
    "iso:country":"DE",
    "sg:address":"Untere Gerberstr. 19",
    "sg:city":"Reutlingen",
    "sg:phone":"+49 7121/346606",
    "sg:postcode":"72764",
    "sg:province":"Baden-W\u00fcrttemberg",
    "wof:name":"Karl Scheuring",
    "wof:placetype":"venue"
},
  "geometry": {"coordinates":[9.2085409164,48.4926223755],"type":"Point"}
}