{
  "type": "Feature",
  "properties": {
    "iso:country":"DE",
    "sg:address":"Im Jagdgrund 8",
    "sg:city":"Karlsruhe",
    "sg:phone":"+49 721/579688",
    "sg:postcode":"76189",
    "sg:province":"Baden-W\u00fcrttemberg",
    "wof:name":"Fritschlachzentrum",
    "wof:placetype":"venue"
},
  "geometry": {"coordinates":[8.3285732269,49.0008354187],"type":"Point"}
}