{
  "type": "Feature",
  "properties": {
    "iso:country":"DE",
    "sg:address":"Bischofsgr\u00fcner Weg 88",
    "sg:city":"Berlin",
    "sg:phone":"+49 30/76802311",
    "sg:postcode":"12247",
    "sg:province":"Berlin",
    "wof:name":"G\u00fcnter Holz Ikg B\u00fcrger & Holz",
    "wof:placetype":"venue"
},
  "geometry": {"coordinates":[13.3649787903,52.4386749268],"type":"Point"}
}