{
  "type": "Feature",
  "properties": {
    "iso:country":"DE",
    "sg:address":"Westring 242",
    "sg:city":"Kiel",
    "sg:phone":"+49 431/15148",
    "sg:postcode":"24116",
    "sg:province":"Schleswig-Holstein",
    "wof:name":"Burg Hohenstaufen",
    "wof:placetype":"venue"
},
  "geometry": {"coordinates":[10.1137580872,54.3246688843],"type":"Point"}
}