{
  "type": "Feature",
  "properties": {
    "iso:country":"DE",
    "sg:address":"Daniel-Goldbach-Str. 25",
    "sg:city":"Ratingen",
    "sg:phone":"+49 2102/68921",
    "sg:postcode":"40880",
    "sg:province":"Nordrhein-Westfalen",
    "wof:name":"Rkr Beteiligungsges. Mbh",
    "wof:placetype":"venue"
},
  "geometry": {"coordinates":[6.825514,51.30254],"type":"Point"}
}