{
  "type": "Feature",
  "properties": {
    "iso:country":"DE",
    "sg:address":"Propst-Paulsen-Str. 1",
    "sg:city":"Hamburg",
    "sg:phone":"+49 40/860108",
    "sg:postcode":"22587",
    "sg:province":"Hamburg",
    "wof:name":"Rolf Hoyer Architekt",
    "wof:placetype":"venue"
},
  "geometry": {"coordinates":[9.8127,53.560932],"type":"Point"}
}