{
  "type": "Feature",
  "properties": {
    "iso:country":"DE",
    "sg:address":"Hochstr. 23",
    "sg:city":"M\u00fchltal",
    "sg:phone":"+49 6151/14118",
    "sg:postcode":"64367",
    "sg:province":"Hessen",
    "wof:name":"Kath. Pfarramt St. Michael",
    "wof:placetype":"venue"
},
  "geometry": {"coordinates":[8.6979389191,49.8269958496],"type":"Point"}
}