{
  "type": "Feature",
  "properties": {
    "iso:country":"DE",
    "sg:address":"Rietenauer Weg 2",
    "sg:city":"Oppenweiler",
    "sg:phone":"+49 7191/44417",
    "sg:postcode":"71570",
    "sg:province":"Baden-W\u00fcrttemberg",
    "wof:name":"Claus Peter Neumann Heilpraktiker",
    "wof:placetype":"venue"
},
  "geometry": {"coordinates":[9.4540758133,48.9851036072],"type":"Point"}
}