{
  "type": "Feature",
  "properties": {
    "iso:country":"DE",
    "sg:address":"H\u00f6rsteiner Str. 4",
    "sg:city":"Karlstein",
    "sg:phone":"+49 6188/990000",
    "sg:postcode":"63791",
    "sg:province":"Bayern",
    "wof:name":"Peter Wei\u00dfenberger",
    "wof:placetype":"venue"
},
  "geometry": {"coordinates":[9.0390663147,50.0414848328],"type":"Point"}
}