{
  "type": "Feature",
  "properties": {
    "iso:country":"DE",
    "sg:address":"Lindenplatz 6",
    "sg:city":"Wilnsdorf",
    "sg:postcode":"57234",
    "sg:province":"Nordrhein-Westfalen",
    "wof:name":"Steiner Verwaltungs-gmbh",
    "wof:placetype":"venue"
},
  "geometry": {"coordinates":[8.1279401779,50.8458786011],"type":"Point"}
}