{
  "type": "Feature",
  "properties": {
    "iso:country":"DE",
    "sg:address":"Witzenh\u00e4user Str. 27",
    "sg:city":"Bad Sooden-Allendorf",
    "sg:phone":"+49 5542/2385",
    "sg:postcode":"37242",
    "sg:province":"Hessen",
    "wof:name":"Uwe Brill",
    "wof:placetype":"venue"
},
  "geometry": {"coordinates":[9.9297552109,51.3074684143],"type":"Point"}
}