{
  "type": "Feature",
  "properties": {
    "iso:country":"DE",
    "sg:address":"Reinholdstr. 10",
    "sg:city":"Limbach-Oberfrohna",
    "sg:phone":"+49 3722/93435",
    "sg:postcode":"09212",
    "sg:province":"Sachsen",
    "wof:name":"Egon Lippmann",
    "wof:placetype":"venue"
},
  "geometry": {"coordinates":[12.743855,50.863441],"type":"Point"}
}