{
  "type": "Feature",
  "properties": {
    "iso:country":"DE",
    "sg:address":"Hingbergstr. 178",
    "sg:city":"M\u00fclheim",
    "sg:postcode":"45470",
    "sg:province":"Nordrhein-Westfalen",
    "wof:name":"Kath. \u00f6ffentliche Bibliothek St. Raphael",
    "wof:placetype":"venue"
},
  "geometry": {"coordinates":[6.902668,51.432411],"type":"Point"}
}