{
  "type": "Feature",
  "properties": {
    "iso:country":"DE",
    "sg:address":"Saarstr 2",
    "sg:city":"Idar-Oberstein",
    "sg:phone":"+49 4967/8146078",
    "sg:postcode":"55743",
    "sg:province":"Rheinland-Pfalz",
    "wof:name":"Horbach Industriebedarf Gmbh",
    "wof:placetype":"venue"
},
  "geometry": {"coordinates":[7.2966508865,49.7243385315],"type":"Point"}
}