{
  "type": "Feature",
  "properties": {
    "iso:country":"DE",
    "sg:address":"Kolleng. 1",
    "sg:city":"Adenau",
    "sg:phone":"+49 4926/9192330",
    "sg:postcode":"53518",
    "sg:province":"Rheinland-Pfalz",
    "wof:name":"Herbrand & Friedrich Gmbh",
    "wof:placetype":"venue"
},
  "geometry": {"coordinates":[6.9288520813,50.383014679],"type":"Point"}
}