{
  "type": "Feature",
  "properties": {
    "iso:country":"DE",
    "sg:address":"Buchenweg 51",
    "sg:city":"Illingen",
    "sg:phone":"+49 6825/44597",
    "sg:postcode":"66557",
    "sg:province":"Saarland",
    "wof:name":"Visage",
    "wof:placetype":"venue"
},
  "geometry": {"coordinates":[7.061399,49.389683],"type":"Point"}
}