{
  "type": "Feature",
  "properties": {
    "iso:country":"DE",
    "sg:address":"Schlo\u00dfstr. 2",
    "sg:city":"Finsterwalde",
    "sg:postcode":"03238",
    "sg:province":"Brandenburg",
    "wof:name":"Uwe Kr\u00fcger",
    "wof:placetype":"venue"
},
  "geometry": {"coordinates":[13.70952034,51.6293411255],"type":"Point"}
}