{
  "type": "Feature",
  "properties": {
    "iso:country":"DE",
    "sg:address":"Nevigeser Str. 22",
    "sg:city":"Velbert",
    "sg:phone":"+49 2051/2780",
    "sg:postcode":"42551",
    "sg:province":"Nordrhein-Westfalen",
    "wof:name":"Karl Fliether Beteiligungs-gmbh",
    "wof:placetype":"venue"
},
  "geometry": {"coordinates":[7.05579,51.328979],"type":"Point"}
}