{
  "type": "Feature",
  "properties": {
    "iso:country":"DE",
    "sg:address":"Bergstr. 4",
    "sg:city":"Sendenhorst",
    "sg:phone":"+49 2535/255",
    "sg:postcode":"48324",
    "sg:province":"Nordrhein-Westfalen",
    "wof:name":"Guido Abelmann E. K.",
    "wof:placetype":"venue"
},
  "geometry": {"coordinates":[7.73257,51.866985],"type":"Point"}
}