{
  "type": "Feature",
  "properties": {
    "iso:country":"DE",
    "sg:address":"Bertsdorfer Str. 19",
    "sg:city":"Bertsdorf-H\u00f6rnitz",
    "sg:phone":"+49 3583/704841",
    "sg:postcode":"02763",
    "sg:province":"Sachsen",
    "wof:name":"Bernd Starke",
    "wof:placetype":"venue"
},
  "geometry": {"coordinates":[14.754339,50.897621],"type":"Point"}
}