{
  "type": "Feature",
  "properties": {
    "iso:country":"DE",
    "sg:address":"R\u00f6thenweg 16",
    "sg:city":"Weitramsdorf",
    "sg:phone":"+49 9561/30319",
    "sg:postcode":"96479",
    "sg:province":"Bayern",
    "wof:name":"Gerhard Grau",
    "wof:placetype":"venue"
},
  "geometry": {"coordinates":[10.90814,50.263794],"type":"Point"}
}