{
  "type": "Feature",
  "properties": {
    "iso:country":"DE",
    "sg:address":"Landauer Str. 1",
    "sg:city":"Dannstadt-Schauernheim",
    "sg:phone":"+49 6231/1554",
    "sg:postcode":"67125",
    "sg:province":"Rheinland-Pfalz",
    "wof:name":"K\u00f6nig Und Partner Gmbh",
    "wof:placetype":"venue"
},
  "geometry": {"coordinates":[8.3178453445,49.4214553833],"type":"Point"}
}