{
  "type": "Feature",
  "properties": {
    "iso:country":"DE",
    "sg:address":"Bahnhofstr. 29",
    "sg:city":"Bischoffen",
    "sg:phone":"+49 4964/44880",
    "sg:postcode":"35649",
    "sg:province":"Hessen",
    "wof:name":"Bieber & Marburg Gmbh & Co Kg",
    "wof:placetype":"venue"
},
  "geometry": {"coordinates":[8.442548,50.703732],"type":"Point"}
}