{
  "type": "Feature",
  "properties": {
    "iso:country":"DE",
    "sg:address":"Harikseeweg 86",
    "sg:city":"Schwalmtal",
    "sg:phone":"+49 2163/82007",
    "sg:postcode":"41366",
    "sg:province":"Nordrhein-Westfalen",
    "wof:name":"Kurt Bone",
    "wof:placetype":"venue"
},
  "geometry": {"coordinates":[6.22772,51.220928],"type":"Point"}
}