{
  "type": "Feature",
  "properties": {
    "iso:country":"DE",
    "sg:address":"Hauptstr. 12",
    "sg:city":"Stockach",
    "sg:phone":"+49 7771/5360",
    "sg:postcode":"78333",
    "sg:province":"Baden-W\u00fcrttemberg",
    "wof:name":"Anton Schlecker Drogerie",
    "wof:placetype":"venue"
},
  "geometry": {"coordinates":[9.012785,47.852364],"type":"Point"}
}