{
  "type": "Feature",
  "properties": {
    "iso:country":"DE",
    "sg:address":"Bahnhofstr. 18",
    "sg:city":"Bad Aibling",
    "sg:phone":"+49 8061/91909",
    "sg:postcode":"83043",
    "sg:province":"Bayern",
    "wof:name":"Venezia",
    "wof:placetype":"venue"
},
  "geometry": {"coordinates":[12.007417,47.863056],"type":"Point"}
}