{
  "type": "Feature",
  "properties": {
    "iso:country":"DE",
    "sg:address":"Buxacher Str. 28",
    "sg:city":"Memmingen",
    "sg:postcode":"87700",
    "sg:province":"Bayern",
    "wof:name":"New Agro Gmbh",
    "wof:placetype":"venue"
},
  "geometry": {"coordinates":[10.1702709198,47.9859352112],"type":"Point"}
}