{
  "type": "Feature",
  "properties": {
    "iso:country":"DE",
    "sg:address":"Roter Hof 8",
    "sg:city":"Ludwigshafen",
    "sg:phone":"+49 621/5398006",
    "sg:postcode":"67067",
    "sg:province":"Rheinland-Pfalz",
    "wof:name":"R. Kruppenbacher",
    "wof:placetype":"venue"
},
  "geometry": {"coordinates":[8.4099969864,49.4610137939],"type":"Point"}
}