{
  "type": "Feature",
  "properties": {
    "iso:country":"DE",
    "sg:address":"Marienloher Str. 38 a",
    "sg:city":"Paderborn",
    "sg:phone":"+49 5254/12858",
    "sg:postcode":"33104",
    "sg:province":"Nordrhein-Westfalen",
    "wof:name":"Pizzeria Maria",
    "wof:placetype":"venue"
},
  "geometry": {"coordinates":[8.7329101562,51.7431106567],"type":"Point"}
}