{
  "type": "Feature",
  "properties": {
    "iso:country":"DE",
    "sg:address":"Stadthausstr. 1 A",
    "sg:city":"Mainz",
    "sg:phone":"+49 6131/129310",
    "sg:postcode":"55116",
    "sg:province":"Rheinland-Pfalz",
    "wof:name":"Mainz Kom",
    "wof:placetype":"venue"
},
  "geometry": {"coordinates":[8.2690486908,50.000995636],"type":"Point"}
}