{
  "type": "Feature",
  "properties": {
    "iso:country":"DE",
    "sg:address":"Rochusstr. 55",
    "sg:city":"D\u00fcsseldorf",
    "sg:phone":"+49 211/351298",
    "sg:postcode":"40479",
    "sg:province":"Nordrhein-Westfalen",
    "wof:name":"Norbert Mankowski Kunstmaler",
    "wof:placetype":"venue"
},
  "geometry": {"coordinates":[6.788211,51.232449],"type":"Point"}
}