{
  "type": "Feature",
  "properties": {
    "iso:country":"DE",
    "sg:address":"Ziegelerden 30",
    "sg:city":"Kronach",
    "sg:phone":"+49 9261/3789",
    "sg:postcode":"96317",
    "sg:province":"Bayern",
    "wof:name":"M. Ziegler",
    "wof:placetype":"venue"
},
  "geometry": {"coordinates":[11.3064584732,50.2324066162],"type":"Point"}
}