{
  "type": "Feature",
  "properties": {
    "iso:country":"DE",
    "sg:address":"Ringstr. 52",
    "sg:city":"L\u00fcdenscheid",
    "sg:phone":"+49 2351/45091",
    "sg:postcode":"58515",
    "sg:province":"Nordrhein-Westfalen",
    "wof:name":"Ipf Electronic Gmbh",
    "wof:placetype":"venue"
},
  "geometry": {"coordinates":[7.650701046,51.2018547058],"type":"Point"}
}