{
  "type": "Feature",
  "properties": {
    "iso:country":"DE",
    "sg:address":"Hauptstr. 10",
    "sg:city":"Schweigen-Rechtenbach",
    "sg:phone":"+49 6342/7279",
    "sg:postcode":"76889",
    "sg:province":"Rheinland-Pfalz",
    "wof:name":"Emil Bauer",
    "wof:placetype":"venue"
},
  "geometry": {"coordinates":[7.877333,49.126621],"type":"Point"}
}