{
  "type": "Feature",
  "properties": {
    "iso:country":"DE",
    "sg:address":"Mindener Str. 71",
    "sg:city":"Bissendorf",
    "sg:phone":"+49 5402/5558",
    "sg:postcode":"49143",
    "sg:province":"Niedersachsen",
    "wof:name":"Dorfgrill",
    "wof:placetype":"venue"
},
  "geometry": {"coordinates":[8.2164096832,52.2592506409],"type":"Point"}
}