{
  "type": "Feature",
  "properties": {
    "iso:country":"DE",
    "sg:address":"Gottlieb-Haefele-Str. 10",
    "sg:city":"Ebersbach",
    "sg:phone":"+49 7163/7147",
    "sg:postcode":"73061",
    "sg:province":"Baden-W\u00fcrttemberg",
    "wof:name":"Gleich & Folg Gmbh",
    "wof:placetype":"venue"
},
  "geometry": {"coordinates":[9.5380010605,48.7153663635],"type":"Point"}
}