{
  "type": "Feature",
  "properties": {
    "iso:country":"DE",
    "sg:address":"Virnsberger Str. 57",
    "sg:city":"N\u00fcrnberg",
    "sg:phone":"+49 911/6539661",
    "sg:postcode":"90431",
    "sg:province":"Bayern",
    "wof:name":"Karossereiebau A. Und G. Henke Gmbh",
    "wof:placetype":"venue"
},
  "geometry": {"coordinates":[11.007645607,49.4463157654],"type":"Point"}
}