{
  "type": "Feature",
  "properties": {
    "iso:country":"DE",
    "sg:address":"Seltersweg 55",
    "sg:city":"Gie\u00dfen",
    "sg:phone":"+49 641/71757",
    "sg:postcode":"35390",
    "sg:province":"Hessen",
    "wof:name":"Ulenspiegel",
    "wof:placetype":"venue"
},
  "geometry": {"coordinates":[8.6724834442,50.5834007263],"type":"Point"}
}