{
  "type": "Feature",
  "properties": {
    "iso:country":"DE",
    "sg:address":"Au",
    "sg:city":"Ainring",
    "sg:phone":"+49 8654/50395",
    "sg:postcode":"83404",
    "sg:province":"Bayern",
    "wof:name":"Bestattung Schmuck Gmbh",
    "wof:placetype":"venue"
},
  "geometry": {"coordinates":[12.94027,47.787331],"type":"Point"}
}