{
  "type": "Feature",
  "properties": {
    "iso:country":"DE",
    "sg:address":"Hauptstr. 47",
    "sg:city":"Wacken",
    "sg:phone":"+49 4827/2164",
    "sg:postcode":"25596",
    "sg:province":"Schleswig-Holstein",
    "wof:name":"K.-h. Hoops",
    "wof:placetype":"venue"
},
  "geometry": {"coordinates":[9.372315,54.02177],"type":"Point"}
}