{
  "type": "Feature",
  "properties": {
    "iso:country":"DE",
    "sg:address":"Freie-Vogel-Str. 15",
    "sg:city":"Dortmund",
    "sg:phone":"+49 231/4273200",
    "sg:postcode":"44263",
    "sg:province":"Nordrhein-Westfalen",
    "wof:name":"Rhein Ruhr Bauelemente Gmbh",
    "wof:placetype":"venue"
},
  "geometry": {"coordinates":[7.5198011398,51.4966316223],"type":"Point"}
}