{
  "type": "Feature",
  "properties": {
    "iso:country":"DE",
    "sg:address":"Hirtengasse 11",
    "sg:city":"D\u00fcrnau",
    "sg:phone":"+49 7582/1316",
    "sg:postcode":"88422",
    "sg:province":"Baden-W\u00fcrttemberg",
    "wof:name":"Bgf Wohn- Und Gewerbebau Gmbh",
    "wof:placetype":"venue"
},
  "geometry": {"coordinates":[9.556722,48.059105],"type":"Point"}
}