{
  "type": "Feature",
  "properties": {
    "iso:country":"DE",
    "sg:address":"Landsberger Str. 60",
    "sg:city":"Berlin",
    "sg:postcode":"12305",
    "sg:province":"Berlin",
    "wof:name":"S. U. C. Inh. Thomas Neumann",
    "wof:placetype":"venue"
},
  "geometry": {"coordinates":[13.4146776199,52.4064216614],"type":"Point"}
}