{
  "type": "Feature",
  "properties": {
    "iso:country":"DE",
    "sg:address":"Schivelbeiner Str. 4",
    "sg:city":"Berlin",
    "sg:phone":"+49 30/44733994",
    "sg:postcode":"10439",
    "sg:province":"Berlin",
    "wof:name":"Waffen Sport Sicherheit Outdoor Sports",
    "wof:placetype":"venue"
},
  "geometry": {"coordinates":[13.412502,52.55098],"type":"Point"}
}