{
  "type": "Feature",
  "properties": {
    "iso:country":"DE",
    "sg:address":"Erlauzwiesler Str.",
    "sg:city":"Waldkirchen",
    "sg:phone":"+49 8581/622",
    "sg:postcode":"94065",
    "sg:province":"Bayern",
    "wof:name":"R. Ascher",
    "wof:placetype":"venue"
},
  "geometry": {"coordinates":[13.6373157501,48.7173805237],"type":"Point"}
}