{
  "type": "Feature",
  "properties": {
    "iso:country":"DE",
    "sg:address":"Kirmesauer Str. 19",
    "sg:city":"Bad Bayersoien",
    "sg:phone":"+49 8845/9695",
    "sg:postcode":"82435",
    "sg:province":"Bayern",
    "wof:name":"Ph Hotelbetriebsges. Bayersoien Mbh",
    "wof:placetype":"venue"
},
  "geometry": {"coordinates":[11.0029716492,47.694393158],"type":"Point"}
}