{
  "type": "Feature",
  "properties": {
    "iso:country":"DE",
    "sg:address":"Friedberger Str. 89-97",
    "sg:city":"Bad Vilbel",
    "sg:postcode":"61118",
    "sg:province":"Hessen",
    "wof:name":"Hermann Fischer Gmbh",
    "wof:placetype":"venue"
},
  "geometry": {"coordinates":[8.742282,50.189754],"type":"Point"}
}