{
  "type": "Feature",
  "properties": {
    "iso:country":"DE",
    "sg:address":"Markt 10",
    "sg:city":"Merseburg",
    "sg:postcode":"06217",
    "sg:province":"Sachsen-Anhalt",
    "wof:name":"Bausparkasse",
    "wof:placetype":"venue"
},
  "geometry": {"coordinates":[11.998614,51.354729],"type":"Point"}
}