{
  "type": "Feature",
  "properties": {
    "iso:country":"DE",
    "sg:address":"Alte Kronsbergstr. 8",
    "sg:city":"Hannover",
    "sg:phone":"+49 511/865180",
    "sg:postcode":"30521",
    "sg:province":"Niedersachsen",
    "wof:name":"Laves",
    "wof:placetype":"venue"
},
  "geometry": {"coordinates":[9.806966,52.318291],"type":"Point"}
}