{
  "type": "Feature",
  "properties": {
    "iso:country":"DE",
    "sg:address":"Marktstr. 3",
    "sg:city":"Lippetal",
    "sg:postcode":"59510",
    "sg:province":"Nordrhein-Westfalen",
    "wof:name":"H. Nitschke",
    "wof:placetype":"venue"
},
  "geometry": {"coordinates":[8.04727,51.662003],"type":"Point"}
}