{
  "type": "Feature",
  "properties": {
    "iso:country":"DE",
    "sg:address":"Zimmermannstr. 15",
    "sg:city":"Stuttgart",
    "sg:phone":"+49 4971/1490900",
    "sg:postcode":"70182",
    "sg:province":"Baden-W\u00fcrttemberg",
    "wof:name":"Gtc Telecommunication Gmbh",
    "wof:placetype":"venue"
},
  "geometry": {"coordinates":[9.1827850342,48.770816803],"type":"Point"}
}