{
  "type": "Feature",
  "properties": {
    "iso:country":"DE",
    "sg:address":"Heinrich-Hertz-Str. 1",
    "sg:city":"Forst",
    "sg:postcode":"76694",
    "sg:province":"Baden-W\u00fcrttemberg",
    "wof:name":"Dhr Forst Oberfl\u00e4chen- Veredelung Gmbh",
    "wof:placetype":"venue"
},
  "geometry": {"coordinates":[8.5697050095,49.157043457],"type":"Point"}
}