{
  "type": "Feature",
  "properties": {
    "iso:country":"DE",
    "sg:address":"Lange Str 57::",
    "sg:city":"Wadersloh",
    "sg:postcode":"59329",
    "sg:province":"Nordrhein-Westfalen",
    "wof:name":"Volksbank Diestedde-liesborn-herzfeld Eg",
    "wof:placetype":"venue"
},
  "geometry": {"coordinates":[8.23551,51.738739],"type":"Point"}
}