{
  "type": "Feature",
  "properties": {
    "iso:country":"DE",
    "sg:address":"Stra\u00dfburger Str. 1",
    "sg:city":"Bielefeld",
    "sg:postcode":"33613",
    "sg:province":"Nordrhein-Westfalen",
    "wof:name":"Geg Gemeindeent- Wicklungsges. Mbh",
    "wof:placetype":"venue"
},
  "geometry": {"coordinates":[8.519124,52.049652],"type":"Point"}
}