{
  "type": "Feature",
  "properties": {
    "iso:country":"DE",
    "sg:address":"Grave 80",
    "sg:city":"Brev\u00f6rde",
    "sg:phone":"+49 5535/329",
    "sg:postcode":"37647",
    "sg:province":"Niedersachsen",
    "wof:name":"Wilhelm Giesemann",
    "wof:placetype":"venue"
},
  "geometry": {"coordinates":[9.40443,51.898975],"type":"Point"}
}