{
  "type": "Feature",
  "properties": {
    "iso:country":"DE",
    "sg:address":"Gebauerstr. 24",
    "sg:city":"Dresden",
    "sg:phone":"+49 351/4010788",
    "sg:postcode":"01189",
    "sg:province":"Sachsen",
    "wof:name":"Rolf Schreiber",
    "wof:placetype":"venue"
},
  "geometry": {"coordinates":[13.6970453262,51.0147705078],"type":"Point"}
}