{
  "type": "Feature",
  "properties": {
    "iso:country":"DE",
    "sg:address":"Ziegelstr. 7",
    "sg:city":"Hartmannsdorf",
    "sg:postcode":"09232",
    "sg:province":"Sachsen",
    "wof:name":"Itec Gmbh",
    "wof:placetype":"venue"
},
  "geometry": {"coordinates":[12.795498,50.890587],"type":"Point"}
}