{
  "type": "Feature",
  "properties": {
    "iso:country":"DE",
    "sg:address":"Karpfenweg 9",
    "sg:city":"Wielenbach",
    "sg:phone":"+49 881/40210",
    "sg:postcode":"82407",
    "sg:province":"Bayern",
    "wof:name":"Dr. Alexander K\u00f6lbing",
    "wof:placetype":"venue"
},
  "geometry": {"coordinates":[11.1589746475,47.8791122437],"type":"Point"}
}