{
  "type": "Feature",
  "properties": {
    "iso:country":"DE",
    "sg:address":"Elkan-Naumburg-Str. 35",
    "sg:city":"Treuchtlingen",
    "sg:phone":"+49 9142/96560",
    "sg:postcode":"91757",
    "sg:province":"Bayern",
    "wof:name":"Berger Gmbh & Co. Kg",
    "wof:placetype":"venue"
},
  "geometry": {"coordinates":[10.9116191864,48.9631614685],"type":"Point"}
}