{
  "type": "Feature",
  "properties": {
    "iso:country":"DE",
    "sg:address":"Dieselstr. 23",
    "sg:city":"Karben",
    "sg:phone":"+49 4960/396933",
    "sg:postcode":"61184",
    "sg:province":"Hessen",
    "wof:name":"Joachim R\u00d6\u00dfner",
    "wof:placetype":"venue"
},
  "geometry": {"coordinates":[8.76412,50.223213],"type":"Point"}
}