{
  "type": "Feature",
  "properties": {
    "iso:country":"DE",
    "sg:address":"Am Spring 12",
    "sg:city":"Ense",
    "sg:postcode":"59469",
    "sg:province":"Nordrhein-Westfalen",
    "wof:name":"Gerke-bauden- Bacher Partnerschaft",
    "wof:placetype":"venue"
},
  "geometry": {"coordinates":[7.958707,51.50346],"type":"Point"}
}