{
  "type": "Feature",
  "properties": {
    "iso:country":"DE",
    "sg:address":"Lessingstr. 36",
    "sg:city":"Kyritz",
    "sg:phone":"+49 33971/52260",
    "sg:postcode":"16866",
    "sg:province":"Brandenburg",
    "wof:name":"Rainer Lewe",
    "wof:placetype":"venue"
},
  "geometry": {"coordinates":[12.4130659103,52.9391860962],"type":"Point"}
}