{
  "type": "Feature",
  "properties": {
    "iso:country":"DE",
    "sg:address":"Wannweiler Str. 47",
    "sg:city":"Kirchentellinsfurt",
    "sg:postcode":"72138",
    "sg:province":"Baden-W\u00fcrttemberg",
    "wof:name":"Raiser Verwaltungs-gmbh",
    "wof:placetype":"venue"
},
  "geometry": {"coordinates":[9.142699,48.527336],"type":"Point"}
}