{
  "type": "Feature",
  "properties": {
    "iso:country":"DE",
    "sg:address":"Zu den M\u00fchlen 27",
    "sg:city":"Marl",
    "sg:phone":"+49 2365/72212",
    "sg:postcode":"45768",
    "sg:province":"Nordrhein-Westfalen",
    "wof:name":"Acut Soft- Und Hardware Gmbh",
    "wof:placetype":"venue"
},
  "geometry": {"coordinates":[7.0415530205,51.6251754761],"type":"Point"}
}