{
  "type": "Feature",
  "properties": {
    "iso:country":"DE",
    "sg:address":"Linsellesstr. 53",
    "sg:city":"Willich",
    "sg:phone":"+49 2154/6861",
    "sg:postcode":"47877",
    "sg:province":"Nordrhein-Westfalen",
    "wof:name":"Zur Waage",
    "wof:placetype":"venue"
},
  "geometry": {"coordinates":[6.5330867767,51.2342262268],"type":"Point"}
}