{
  "type": "Feature",
  "properties": {
    "iso:country":"DE",
    "sg:address":"Scharderhohlweg 8",
    "sg:city":"K\u00f6nigstein",
    "sg:phone":"+49 6174/930181",
    "sg:postcode":"61462",
    "sg:province":"Hessen",
    "wof:name":"R. C. Immobilien Sanierungs- Und Verwaltungs Gmbh",
    "wof:placetype":"venue"
},
  "geometry": {"coordinates":[8.4801054001,50.1945495605],"type":"Point"}
}