{
  "type": "Feature",
  "properties": {
    "iso:country":"DE",
    "sg:address":"Abbestr. 2 a",
    "sg:city":"Bremerhaven",
    "sg:postcode":"27580",
    "sg:province":"Bremen",
    "wof:name":"Computer- Und Mechanische Stickerei Gmbh",
    "wof:placetype":"venue"
},
  "geometry": {"coordinates":[8.5878162384,53.5746955872],"type":"Point"}
}