{
  "type": "Feature",
  "properties": {
    "iso:country":"DE",
    "sg:address":"Bungenstr.6",
    "sg:city":"Stade",
    "sg:postcode":"21682",
    "sg:province":"Niedersachsen",
    "wof:name":"Zahnarztpraxis Dr. Schwander, Stade",
    "wof:placetype":"venue"
},
  "geometry": {"coordinates":[9.475254,53.603374],"type":"Point"}
}