{
  "type": "Feature",
  "properties": {
    "iso:country":"DE",
    "sg:address":"Gittertor 23",
    "sg:city":"Salzgitter",
    "sg:phone":"+49 5341/82130",
    "sg:postcode":"38259",
    "sg:province":"Niedersachsen",
    "wof:name":"C. M\u00fcller Landmaschinen Gmbh",
    "wof:placetype":"venue"
},
  "geometry": {"coordinates":[10.365984,52.045261],"type":"Point"}
}