{
  "type": "Feature",
  "properties": {
    "iso:country":"DE",
    "sg:address":"Brunnenstr. 14",
    "sg:city":"Nagold",
    "sg:phone":"+49 7452/837070",
    "sg:postcode":"72202",
    "sg:province":"Baden-W\u00fcrttemberg",
    "wof:name":"Rilling Tank- Und Waschcenter Inh. Anna Marta Rilling E.kfr.",
    "wof:placetype":"venue"
},
  "geometry": {"coordinates":[8.727292,48.53846],"type":"Point"}
}