{
  "type": "Feature",
  "properties": {
    "iso:country":"DE",
    "sg:address":"Im Glockenziel 8",
    "sg:city":"Engen",
    "sg:phone":"+49 7733/7322",
    "sg:postcode":"78234",
    "sg:province":"Baden-W\u00fcrttemberg",
    "wof:name":"Heinz Becker Ingenieur",
    "wof:placetype":"venue"
},
  "geometry": {"coordinates":[8.765209198,47.8599472046],"type":"Point"}
}