{
  "type": "Feature",
  "properties": {
    "iso:country":"DE",
    "sg:address":"Hauptstr. 72",
    "sg:city":"Reilingen",
    "sg:phone":"+49 6205/4378",
    "sg:postcode":"68799",
    "sg:province":"Baden-W\u00fcrttemberg",
    "wof:name":"Katholisches Pfarramt St. Wendelin",
    "wof:placetype":"venue"
},
  "geometry": {"coordinates":[8.5708580017,49.2941207886],"type":"Point"}
}