{
  "type": "Feature",
  "properties": {
    "iso:country":"DE",
    "sg:address":"Gewerbepark 32",
    "sg:city":"Hamm",
    "sg:phone":"+49 2381/29635",
    "sg:postcode":"59069",
    "sg:province":"Nordrhein-Westfalen",
    "wof:name":"Seza Gmbh",
    "wof:placetype":"venue"
},
  "geometry": {"coordinates":[7.8517861366,51.6219787598],"type":"Point"}
}