{
  "type": "Feature",
  "properties": {
    "iso:country":"DE",
    "sg:address":"Bredenscheider Str. 47",
    "sg:city":"Hattingen",
    "sg:phone":"+49 2324/22767",
    "sg:postcode":"45525",
    "sg:province":"Nordrhein-Westfalen",
    "wof:name":"Kirchmeier",
    "wof:placetype":"venue"
},
  "geometry": {"coordinates":[7.1910052299,51.3961677551],"type":"Point"}
}