{
  "type": "Feature",
  "properties": {
    "iso:country":"DE",
    "sg:address":"Schellstr.",
    "sg:city":"Dahme",
    "sg:phone":"+49 35451/91591",
    "sg:postcode":"15936",
    "sg:province":"Brandenburg",
    "wof:name":"B. Krause",
    "wof:placetype":"venue"
},
  "geometry": {"coordinates":[13.433551,51.866859],"type":"Point"}
}