{
  "type": "Feature",
  "properties": {
    "iso:country":"DE",
    "sg:address":"Karl-Friedrich-Str. 76",
    "sg:city":"Aachen",
    "sg:phone":"+49 241/9388810",
    "sg:postcode":"52072",
    "sg:province":"Nordrhein-Westfalen",
    "wof:name":"Bergmoser & H\u00f6ller Verlag Ag",
    "wof:placetype":"venue"
},
  "geometry": {"coordinates":[6.05199,50.80846],"type":"Point"}
}