{
  "type": "Feature",
  "properties": {
    "iso:country":"DE",
    "sg:address":"Schwaben",
    "sg:city":"Prackenbach",
    "sg:phone":"+49 9942/8748",
    "sg:postcode":"94267",
    "sg:province":"Bayern",
    "wof:name":"Gastst\u00e4tte Ludwig Sch\u00f6tz",
    "wof:placetype":"venue"
},
  "geometry": {"coordinates":[12.828294754,49.089756012],"type":"Point"}
}