{
  "type": "Feature",
  "properties": {
    "iso:country":"DE",
    "sg:address":"Oberamteistr. 27",
    "sg:city":"Reutlingen",
    "sg:phone":"+49 7121/601140",
    "sg:postcode":"72764",
    "sg:province":"Baden-W\u00fcrttemberg",
    "wof:name":"En Ville Villforth Gmbh",
    "wof:placetype":"venue"
},
  "geometry": {"coordinates":[9.2117090225,48.4900512695],"type":"Point"}
}