{
  "type": "Feature",
  "properties": {
    "iso:country":"DE",
    "sg:address":"Am Waldesrand 80",
    "sg:city":"Hagen",
    "sg:phone":"+49 2331/53412",
    "sg:postcode":"58093",
    "sg:province":"Nordrhein-Westfalen",
    "wof:name":"Klara Schr\u00f6der",
    "wof:placetype":"venue"
},
  "geometry": {"coordinates":[7.492861,51.353577],"type":"Point"}
}