{
  "type": "Feature",
  "properties": {
    "iso:country":"DE",
    "sg:address":"Hauptstr. 54",
    "sg:city":"L\u00f6bau",
    "sg:phone":"+49 3585/482245",
    "sg:postcode":"02708",
    "sg:province":"Sachsen",
    "wof:name":"H. Wagner",
    "wof:placetype":"venue"
},
  "geometry": {"coordinates":[14.6108980179,51.1083297729],"type":"Point"}
}