{
  "type": "Feature",
  "properties": {
    "iso:country":"DE",
    "sg:address":"Bgm-Martin-Donandt-Pl 26",
    "sg:city":"Bremerhaven",
    "sg:phone":"+49 471/43766",
    "sg:postcode":"27568",
    "sg:province":"Bremen",
    "wof:name":"H. Weiterer Gmbh",
    "wof:placetype":"venue"
},
  "geometry": {"coordinates":[8.573435,53.55064],"type":"Point"}
}