{
  "type": "Feature",
  "properties": {
    "iso:country":"DE",
    "sg:address":"Raiffeisenstr. 17",
    "sg:city":"Mainz",
    "sg:phone":"+49 6131/41202",
    "sg:postcode":"55124",
    "sg:province":"Rheinland-Pfalz",
    "wof:name":"Landwirtschaftliche Bezugsgenossenschaft Egmbh",
    "wof:placetype":"venue"
},
  "geometry": {"coordinates":[8.213971,49.999321],"type":"Point"}
}