{
  "type": "Feature",
  "properties": {
    "iso:country":"DE",
    "sg:address":"Weinstr. 53",
    "sg:city":"Klingenm\u00fcnster",
    "sg:phone":"+49 4963/498771",
    "sg:postcode":"76889",
    "sg:province":"Rheinland-Pfalz",
    "wof:name":"Volksbank Eg",
    "wof:placetype":"venue"
},
  "geometry": {"coordinates":[8.018416,49.140476],"type":"Point"}
}