{
  "type": "Feature",
  "properties": {
    "iso:country":"DE",
    "sg:address":"Dorotheenstr. 1",
    "sg:city":"Limbach-Oberfrohna",
    "sg:phone":"+49 3722/93763",
    "sg:postcode":"09212",
    "sg:province":"Sachsen",
    "wof:name":"Elektro-sittner",
    "wof:placetype":"venue"
},
  "geometry": {"coordinates":[12.753381,50.857056],"type":"Point"}
}