{
  "type": "Feature",
  "properties": {
    "iso:country":"DE",
    "sg:address":"Oesfeldstr. 13",
    "sg:city":"L\u00f6\u00dfnitz",
    "sg:phone":"+49 3771/35439",
    "sg:postcode":"08294",
    "sg:province":"Sachsen",
    "wof:name":"C. M\u00fchlberg",
    "wof:placetype":"venue"
},
  "geometry": {"coordinates":[12.7296266556,50.6209030151],"type":"Point"}
}