{
  "type": "Feature",
  "properties": {
    "iso:country":"DE",
    "sg:address":"Niederl\u00f6ricker Str. 62",
    "sg:city":"Meerbusch",
    "sg:postcode":"40667",
    "sg:province":"Nordrhein-Westfalen",
    "wof:name":"Maisonette Modevertriebs Gmbh",
    "wof:placetype":"venue"
},
  "geometry": {"coordinates":[6.7195501328,51.2560310364],"type":"Point"}
}