{
  "type": "Feature",
  "properties": {
    "iso:country":"DE",
    "sg:address":"Schlo\u00dfweg 1",
    "sg:city":"Sulzdorf",
    "sg:phone":"+49 9763/424",
    "sg:postcode":"97528",
    "sg:province":"Bayern",
    "wof:name":"Trice-werbeartikel",
    "wof:placetype":"venue"
},
  "geometry": {"coordinates":[10.5379447937,50.2679748535],"type":"Point"}
}