{
  "type": "Feature",
  "properties": {
    "iso:country":"DE",
    "sg:address":"Friedenstr. 5",
    "sg:city":"Kaufering",
    "sg:phone":"+49 8191/7414",
    "sg:postcode":"86916",
    "sg:province":"Bayern",
    "wof:name":"Josef Nitsche",
    "wof:placetype":"venue"
},
  "geometry": {"coordinates":[10.8552494049,48.082649231],"type":"Point"}
}