{
  "type": "Feature",
  "properties": {
    "iso:country":"DE",
    "sg:address":"Berliner Str. 33",
    "sg:city":"Gro\u00df Warnow",
    "sg:phone":"+49 38788/50824",
    "sg:postcode":"19357",
    "sg:province":"Brandenburg",
    "wof:name":"Inventa-markisen Dr. Kr\u00fcger Kg",
    "wof:placetype":"venue"
},
  "geometry": {"coordinates":[11.619863,53.226978],"type":"Point"}
}