{
  "type": "Feature",
  "properties": {
    "iso:country":"DE",
    "sg:address":"Herrenwiese 5-7",
    "sg:city":"Kirchen",
    "sg:phone":"+49 2741/61030",
    "sg:postcode":"57548",
    "sg:province":"Rheinland-Pfalz",
    "wof:name":"Technisches B\u00fcro Ermert Gmbh",
    "wof:placetype":"venue"
},
  "geometry": {"coordinates":[7.8853068352,50.8149299622],"type":"Point"}
}