{
  "type": "Feature",
  "properties": {
    "iso:country":"DE",
    "sg:address":"Am Maibusch 108-110",
    "sg:city":"Gelsenkirchen",
    "sg:phone":"+49 209/940950",
    "sg:postcode":"45883",
    "sg:province":"Nordrhein-Westfalen",
    "wof:name":"Hansen & Reinders Gmbh Projektgesellschaft Polen",
    "wof:placetype":"venue"
},
  "geometry": {"coordinates":[7.070237,51.52449],"type":"Point"}
}