{
  "type": "Feature",
  "properties": {
    "iso:country":"DE",
    "sg:address":"Cottbuser Str. 8",
    "sg:city":"Riesa",
    "sg:phone":"+49 3525/741254",
    "sg:postcode":"01587",
    "sg:province":"Sachsen",
    "wof:name":"Jens Dietrich",
    "wof:placetype":"venue"
},
  "geometry": {"coordinates":[13.269021,51.305958],"type":"Point"}
}