{
  "type": "Feature",
  "properties": {
    "iso:country":"DE",
    "sg:address":"Hohenaschauer Str. 25",
    "sg:city":"M\u00fcnchen",
    "sg:phone":"+49 89/685335",
    "sg:postcode":"81669",
    "sg:province":"Bayern",
    "wof:name":"Rudolf Urban",
    "wof:placetype":"venue"
},
  "geometry": {"coordinates":[11.6086940765,48.1107978821],"type":"Point"}
}