{
  "type": "Feature",
  "properties": {
    "iso:country":"DE",
    "sg:address":"Am Zollhof 7",
    "sg:city":"Westerburg/WW",
    "sg:phone":"+49 2663/1040",
    "sg:postcode":"56457",
    "sg:province":"Rheinland-Pfalz",
    "wof:name":"Rad & Tat Gmbh.",
    "wof:placetype":"venue"
},
  "geometry": {"coordinates":[7.9760217667,50.5675888062],"type":"Point"}
}