{
  "type": "Feature",
  "properties": {
    "iso:country":"DE",
    "sg:address":"Zeppelinstr. 10",
    "sg:city":"B\u00f6blingen",
    "sg:phone":"+49 7031/220827",
    "sg:postcode":"71032",
    "sg:province":"Baden-W\u00fcrttemberg",
    "wof:name":"Wolfgang Fischer",
    "wof:placetype":"venue"
},
  "geometry": {"coordinates":[9.021715,48.690418],"type":"Point"}
}