{
  "type": "Feature",
  "properties": {
    "iso:country":"DE",
    "sg:address":"Hohenstaufenring 60",
    "sg:city":"K\u00f6ln",
    "sg:phone":"+49 221/923926",
    "sg:postcode":"50674",
    "sg:province":"Nordrhein-Westfalen",
    "wof:name":"Sdr Systemm\u00f6bel Gmbh",
    "wof:placetype":"venue"
},
  "geometry": {"coordinates":[6.940283,50.932972],"type":"Point"}
}