{
  "type": "Feature",
  "properties": {
    "iso:country":"DE",
    "sg:address":"Stra\u00dfe des Friedens 33",
    "sg:city":"Limbach-Oberfrohna",
    "sg:phone":"+49 3722/93675",
    "sg:postcode":"09212",
    "sg:province":"Sachsen",
    "wof:name":"Eichhorn & M\u00e4nnl",
    "wof:placetype":"venue"
},
  "geometry": {"coordinates":[12.754172,50.860088],"type":"Point"}
}