{
  "type": "Feature",
  "properties": {
    "iso:country":"DE",
    "sg:address":"Uedemer Str. 6",
    "sg:city":"Xanten",
    "sg:phone":"+49 2804/8092",
    "sg:postcode":"46509",
    "sg:province":"Nordrhein-Westfalen",
    "wof:name":"Michael Hennemann",
    "wof:placetype":"venue"
},
  "geometry": {"coordinates":[6.3704910278,51.694026947],"type":"Point"}
}