{
  "type": "Feature",
  "properties": {
    "iso:country":"DE",
    "sg:address":"Mauerstr. 7",
    "sg:city":"Rudolstadt",
    "sg:phone":"+49 3672/422772",
    "sg:postcode":"07407",
    "sg:province":"Th\u00fcringen",
    "wof:name":"G\u00fcnter K\u00fchn",
    "wof:placetype":"venue"
},
  "geometry": {"coordinates":[11.33998,50.719345],"type":"Point"}
}