{
  "type": "Feature",
  "properties": {
    "iso:country":"DE",
    "sg:address":"Ledergasse 27",
    "sg:city":"\u00d6hringen",
    "sg:phone":"+49 7941/38663",
    "sg:postcode":"74613",
    "sg:province":"Baden-W\u00fcrttemberg",
    "wof:name":"Caf\u00e9 Hamballe",
    "wof:placetype":"venue"
},
  "geometry": {"coordinates":[9.49914,49.200474],"type":"Point"}
}