{
  "type": "Feature",
  "properties": {
    "iso:country":"DE",
    "sg:address":"Marktstr. 7",
    "sg:city":"Kipfenberg",
    "sg:phone":"+49 8465/468",
    "sg:postcode":"85110",
    "sg:province":"Bayern",
    "wof:name":"Franz Gangauf",
    "wof:placetype":"venue"
},
  "geometry": {"coordinates":[11.394919,48.949909],"type":"Point"}
}