{
  "type": "Feature",
  "properties": {
    "iso:country":"DE",
    "sg:address":"Felix-Meindl-Weg 74b",
    "sg:city":"Landshut",
    "sg:phone":"+49 871/43917",
    "sg:postcode":"84036",
    "sg:province":"Bayern",
    "wof:name":"B. Premovic-m\u00e4rkl Dolmetscher",
    "wof:placetype":"venue"
},
  "geometry": {"coordinates":[12.15407,48.522083],"type":"Point"}
}