{
  "type": "Feature",
  "properties": {
    "iso:country":"DE",
    "sg:address":"Kortenhagen 21",
    "sg:city":"Bokholt-Hanredder",
    "sg:phone":"+49 4123/4559",
    "sg:postcode":"25335",
    "sg:province":"Schleswig-Holstein",
    "wof:name":"Siegfried Kruse Schlosserei",
    "wof:placetype":"venue"
},
  "geometry": {"coordinates":[9.7126893997,53.7864494324],"type":"Point"}
}