{
  "type": "Feature",
  "properties": {
    "iso:country":"DE",
    "sg:address":"Einsteinstr 6",
    "sg:city":"Herzogenaurach",
    "sg:phone":"+49 9132/744200",
    "sg:postcode":"91074",
    "sg:province":"Bayern",
    "wof:name":"Profichip Gmbh",
    "wof:placetype":"venue"
},
  "geometry": {"coordinates":[10.884136,49.577587],"type":"Point"}
}