{
  "type": "Feature",
  "properties": {
    "iso:country":"DE",
    "sg:address":"G\u00fcntherstr. 102",
    "sg:city":"Hamburg",
    "sg:phone":"+49 40/2512076",
    "sg:postcode":"22087",
    "sg:province":"Hamburg",
    "wof:name":"Redaktion Durchblick Christl. Verein Junger",
    "wof:placetype":"venue"
},
  "geometry": {"coordinates":[10.0330286026,53.5634613037],"type":"Point"}
}