{
  "type": "Feature",
  "properties": {
    "iso:country":"DE",
    "sg:address":"Brahmsallee 9",
    "sg:city":"Hamburg",
    "sg:phone":"+49 40/4147550",
    "sg:postcode":"20144",
    "sg:province":"Hamburg",
    "wof:name":"Brinkmann Und Partner Rechtsanw\u00e4lte Und Stb.",
    "wof:placetype":"venue"
},
  "geometry": {"coordinates":[9.9817447662,53.573299408],"type":"Point"}
}