{
  "type": "Feature",
  "properties": {
    "iso:country":"DE",
    "sg:address":"Karl-Marx-Str. 29",
    "sg:city":"Zerben",
    "sg:phone":"+49 39344/40733",
    "sg:postcode":"39317",
    "sg:province":"Sachsen-Anhalt",
    "wof:name":"Ida Lengsfeld",
    "wof:placetype":"venue"
},
  "geometry": {"coordinates":[11.9541511536,52.3574333191],"type":"Point"}
}