{
  "type": "Feature",
  "properties": {
    "iso:country":"DE",
    "sg:address":"Hafenstr. 25",
    "sg:city":"Bremerhaven",
    "sg:phone":"+49 471/42450",
    "sg:postcode":"27576",
    "sg:province":"Bremen",
    "wof:name":"C. Koch",
    "wof:placetype":"venue"
},
  "geometry": {"coordinates":[8.581469,53.552387],"type":"Point"}
}