{
  "type": "Feature",
  "properties": {
    "iso:country":"DE",
    "sg:address":"Dr.-Wilhelm-K\u00fclz-Str. 58",
    "sg:city":"F\u00fcrstenwalde",
    "sg:postcode":"15517",
    "sg:province":"Brandenburg",
    "wof:name":"Da Deutsche Allgemeine Versicherungs Ag",
    "wof:placetype":"venue"
},
  "geometry": {"coordinates":[14.0594892502,52.361541748],"type":"Point"}
}