{
  "type": "Feature",
  "properties": {
    "iso:country":"DE",
    "sg:address":"K\u00f6nigsallee 14",
    "sg:city":"D\u00fcsseldorf",
    "sg:phone":"+49 211/740047",
    "sg:postcode":"40212",
    "sg:province":"Nordrhein-Westfalen",
    "wof:name":"Bam Bau Gmbh",
    "wof:placetype":"venue"
},
  "geometry": {"coordinates":[6.779428,51.225609],"type":"Point"}
}