{
  "type": "Feature",
  "properties": {
    "iso:country":"DE",
    "sg:address":"L\u00fctzerathstr. 149k",
    "sg:city":"K\u00f6ln",
    "sg:phone":"+49 221/864755",
    "sg:postcode":"51107",
    "sg:province":"Nordrhein-Westfalen",
    "wof:name":"Karl Reith Gmbh",
    "wof:placetype":"venue"
},
  "geometry": {"coordinates":[7.086703,50.926792],"type":"Point"}
}