{
  "type": "Feature",
  "properties": {
    "iso:country":"DE",
    "sg:address":"Stefan-George-Str. 20",
    "sg:city":"Bingen",
    "sg:phone":"+49 6721/799890",
    "sg:postcode":"55411",
    "sg:province":"Rheinland-Pfalz",
    "wof:name":"J\u00fcrgen Peters Rechtsanwalt",
    "wof:placetype":"venue"
},
  "geometry": {"coordinates":[7.8928627968,49.9622154236],"type":"Point"}
}