{
  "type": "Feature",
  "properties": {
    "iso:country":"DE",
    "sg:address":"Am Pfarrwald 52",
    "sg:city":"Fl\u00f6ha",
    "sg:phone":"+49 3726/2079",
    "sg:postcode":"09557",
    "sg:province":"Sachsen",
    "wof:name":"Siegfried Wolf",
    "wof:placetype":"venue"
},
  "geometry": {"coordinates":[13.0877733231,50.868522644],"type":"Point"}
}