{
  "type": "Feature",
  "properties": {
    "iso:country":"DE",
    "sg:address":"Egmatinger Str. 3/I",
    "sg:city":"H\u00f6henkirchen-Siegertbrn",
    "sg:phone":"+49 8102/748417",
    "sg:postcode":"85635",
    "sg:province":"Bayern",
    "wof:name":"N & Z Wohn- Und Gewerbebau Gmbh",
    "wof:placetype":"venue"
},
  "geometry": {"coordinates":[11.712479,48.017044],"type":"Point"}
}