{
  "type": "Feature",
  "properties": {
    "iso:country":"DE",
    "sg:address":"Offenbacher Str. 14",
    "sg:city":"Hohenahr",
    "sg:phone":"+49 6444/92091",
    "sg:postcode":"35644",
    "sg:province":"Hessen",
    "wof:name":"Br\u00fcck Beteiligungsges. Mbh",
    "wof:placetype":"venue"
},
  "geometry": {"coordinates":[8.454962,50.683247],"type":"Point"}
}