{
  "type": "Feature",
  "properties": {
    "iso:country":"DE",
    "sg:address":"Ostpreu\u00dfenstr. 2",
    "sg:city":"Holle",
    "sg:phone":"+49 5062/1300",
    "sg:postcode":"31188",
    "sg:province":"Niedersachsen",
    "wof:name":"Tennis-center Holle Gmbh",
    "wof:placetype":"venue"
},
  "geometry": {"coordinates":[10.1559505463,52.0924110413],"type":"Point"}
}