{
  "type": "Feature",
  "properties": {
    "iso:country":"DE",
    "sg:address":"Mittelstr. 14",
    "sg:city":"Laasdorf",
    "sg:phone":"+49 36428/55435",
    "sg:postcode":"07646",
    "sg:province":"Th\u00fcringen",
    "wof:name":"Medenta Dental Products Gmbh",
    "wof:placetype":"venue"
},
  "geometry": {"coordinates":[11.675466,50.870594],"type":"Point"}
}