{
  "type": "Feature",
  "properties": {
    "iso:country":"DE",
    "sg:address":"Dycker Feld 50",
    "sg:city":"Solingen",
    "sg:phone":"+49 212/590508",
    "sg:postcode":"42653",
    "sg:province":"Nordrhein-Westfalen",
    "wof:name":"Metallgie\u00dferei Seifert Gmbh",
    "wof:placetype":"venue"
},
  "geometry": {"coordinates":[7.0771012306,51.2019805908],"type":"Point"}
}