{
  "type": "Feature",
  "properties": {
    "iso:country":"DE",
    "sg:address":"Schulstra\u00dfe 2",
    "sg:city":"Gro\u00df-Gerau",
    "sg:phone":"+49 6152/911895",
    "sg:postcode":"64521",
    "sg:province":"Hessen",
    "wof:name":"Redical Boardershop",
    "wof:placetype":"venue"
},
  "geometry": {"coordinates":[8.483745575,49.9210739136],"type":"Point"}
}