{
  "type": "Feature",
  "properties": {
    "iso:country":"DE",
    "sg:address":"Albert-Ruckdeschel-Str. 31",
    "sg:city":"Kulmbach",
    "sg:postcode":"95326",
    "sg:province":"Bayern",
    "wof:name":"Herold Verwaltungs Gmbh",
    "wof:placetype":"venue"
},
  "geometry": {"coordinates":[11.4569168091,50.1121482849],"type":"Point"}
}