{
  "type": "Feature",
  "properties": {
    "iso:country":"DE",
    "sg:address":"Industriestr. 8",
    "sg:city":"Lauf",
    "sg:phone":"+49 9123/5057",
    "sg:postcode":"91207",
    "sg:province":"Bayern",
    "wof:name":"Evb Ing.-b\u00fcro Gmbh",
    "wof:placetype":"venue"
},
  "geometry": {"coordinates":[11.2903146744,49.5013809204],"type":"Point"}
}