{
  "type": "Feature",
  "properties": {
    "iso:country":"DE",
    "sg:address":"Kreuzberger Ring 60",
    "sg:city":"Wiesbaden",
    "sg:phone":"+49 611/737370",
    "sg:postcode":"65205",
    "sg:province":"Hessen",
    "wof:name":"Medico-lab Ges. F\u00fcr Laborberatung Mbh",
    "wof:placetype":"venue"
},
  "geometry": {"coordinates":[8.290175,50.055984],"type":"Point"}
}