{
  "type": "Feature",
  "properties": {
    "iso:country":"DE",
    "sg:address":"F\u00e4rbergasse 23",
    "sg:city":"Markt Schwaben",
    "sg:phone":"+49 8121/41100",
    "sg:postcode":"85570",
    "sg:province":"Bayern",
    "wof:name":"Oswald Walkam",
    "wof:placetype":"venue"
},
  "geometry": {"coordinates":[11.868012,48.188812],"type":"Point"}
}