{
  "type": "Feature",
  "properties": {
    "iso:country":"DE",
    "sg:address":"Goethestr. 10",
    "sg:city":"Seedorf",
    "sg:phone":"+49 7402/910400",
    "sg:postcode":"78655",
    "sg:province":"Baden-W\u00fcrttemberg",
    "wof:name":"123-flyaway.de - Lastminute Reisen, Charter- & Linienfl\u00fcge",
    "wof:placetype":"venue"
},
  "geometry": {"coordinates":[8.494075,48.24572],"type":"Point"}
}