{
  "type": "Feature",
  "properties": {
    "iso:country":"DE",
    "sg:address":"Br\u00fchlstr. 23",
    "sg:city":"Reinsfeld",
    "sg:phone":"+49 6503/2922",
    "sg:postcode":"54421",
    "sg:province":"Rheinland-Pfalz",
    "wof:name":"Christina Spies Architektin",
    "wof:placetype":"venue"
},
  "geometry": {"coordinates":[6.871694,49.673946],"type":"Point"}
}