{
  "type": "Feature",
  "properties": {
    "iso:country":"DE",
    "sg:address":"Karlstr. 15",
    "sg:city":"Perleberg",
    "sg:phone":"+49 3876/785158",
    "sg:postcode":"19348",
    "sg:province":"Brandenburg",
    "wof:name":"Schwimmbad Perleberg",
    "wof:placetype":"venue"
},
  "geometry": {"coordinates":[11.8709421158,53.070690155],"type":"Point"}
}