{
  "type": "Feature",
  "properties": {
    "iso:country":"DE",
    "sg:address":"Alsfelder Str. 2",
    "sg:city":"Lauterbach",
    "sg:phone":"+49 6641/3470",
    "sg:postcode":"36341",
    "sg:province":"Hessen",
    "wof:name":"Gr\u00fcner Baum Maar",
    "wof:placetype":"venue"
},
  "geometry": {"coordinates":[9.3527708054,50.67628479],"type":"Point"}
}