{
  "type": "Feature",
  "properties": {
    "iso:country":"DE",
    "sg:address":"Kahlenstr. 4",
    "sg:city":"Lippstadt",
    "sg:phone":"+49 2941/59043",
    "sg:postcode":"59555",
    "sg:province":"Nordrhein-Westfalen",
    "wof:name":"C & A",
    "wof:placetype":"venue"
},
  "geometry": {"coordinates":[8.346777,51.673019],"type":"Point"}
}