{
  "type": "Feature",
  "properties": {
    "iso:country":"DE",
    "sg:address":"Heinrich-Bingemer-Weg 2a",
    "sg:city":"Frankfurt",
    "sg:postcode":"60388",
    "sg:province":"Hessen",
    "wof:name":"Bell Gmbh & Co. Kg",
    "wof:placetype":"venue"
},
  "geometry": {"coordinates":[8.7489557266,50.1518974304],"type":"Point"}
}