{
  "type": "Feature",
  "properties": {
    "iso:country":"DE",
    "sg:address":"Hiddeser Str. 19",
    "sg:city":"Detmold",
    "sg:phone":"+49 5231/68304",
    "sg:postcode":"32758",
    "sg:province":"Nordrhein-Westfalen",
    "wof:name":"Gerhard Strate Raumausstattung",
    "wof:placetype":"venue"
},
  "geometry": {"coordinates":[8.8310899734,51.9371910095],"type":"Point"}
}