{
  "type": "Feature",
  "properties": {
    "iso:country":"DE",
    "sg:address":"Kreuzeskirchstr. 37",
    "sg:city":"Essen",
    "sg:phone":"+49 4920/1247710",
    "sg:postcode":"45127",
    "sg:province":"Nordrhein-Westfalen",
    "wof:name":"Banneke Weine U.spirituosen Aus Aller Welt Werner Faber Gmbh",
    "wof:placetype":"venue"
},
  "geometry": {"coordinates":[7.007554,51.45924],"type":"Point"}
}