{
  "type": "Feature",
  "properties": {
    "iso:country":"DE",
    "sg:address":"Jahnstr.",
    "sg:city":"Appenweier",
    "sg:phone":"+49 7805/2362",
    "sg:postcode":"77767",
    "sg:province":"Baden-W\u00fcrttemberg",
    "wof:name":"H. Geiler",
    "wof:placetype":"venue"
},
  "geometry": {"coordinates":[7.967022,48.55756],"type":"Point"}
}