{
  "type": "Feature",
  "properties": {
    "iso:country":"DE",
    "sg:address":"Am Dom 13",
    "sg:city":"Stendal",
    "sg:phone":"+49 3931/217214",
    "sg:postcode":"39576",
    "sg:province":"Sachsen-Anhalt",
    "wof:name":"H. Und H. Kaschade Stiftung",
    "wof:placetype":"venue"
},
  "geometry": {"coordinates":[11.8592329025,52.6011123657],"type":"Point"}
}