{
  "type": "Feature",
  "properties": {
    "iso:country":"DE",
    "sg:address":"W\u00f6rthstra\u00dfe 15",
    "sg:city":"Hof",
    "sg:phone":"+49 9281/87388",
    "sg:postcode":"95028",
    "sg:province":"Bayern",
    "wof:name":"Finanzberatung Hofmann",
    "wof:placetype":"venue"
},
  "geometry": {"coordinates":[11.9179821014,50.3130378723],"type":"Point"}
}