{
  "type": "Feature",
  "properties": {
    "iso:country":"DE",
    "sg:address":"Hauptstr. 14",
    "sg:city":"Allmendingen",
    "sg:phone":"+49 7391/53584",
    "sg:postcode":"89604",
    "sg:province":"Baden-W\u00fcrttemberg",
    "wof:name":"K. K\u00e4uffer",
    "wof:placetype":"venue"
},
  "geometry": {"coordinates":[9.7245407104,48.3279380798],"type":"Point"}
}