{
  "type": "Feature",
  "properties": {
    "iso:country":"DE",
    "sg:address":"Frauenalber Str. 22",
    "sg:city":"Karlsruhe",
    "sg:phone":"+49 721/886429",
    "sg:postcode":"76199",
    "sg:province":"Baden-W\u00fcrttemberg",
    "wof:name":"Smyrna Touristik Gmbh",
    "wof:placetype":"venue"
},
  "geometry": {"coordinates":[8.4001846313,48.9653320312],"type":"Point"}
}