{
  "type": "Feature",
  "properties": {
    "iso:country":"DE",
    "sg:address":"Karwendelweg 6",
    "sg:city":"Kissing",
    "sg:phone":"+49 8233/5475",
    "sg:postcode":"86438",
    "sg:province":"Bayern",
    "wof:name":"M. Schneller",
    "wof:placetype":"venue"
},
  "geometry": {"coordinates":[10.9723596573,48.3009719849],"type":"Point"}
}