{
  "type": "Feature",
  "properties": {
    "iso:country":"DE",
    "sg:address":"Kirrweilerstr. 23 b",
    "sg:city":"Glanbr\u00fccken",
    "sg:phone":"+49 6387/7377",
    "sg:postcode":"66887",
    "sg:province":"Rheinland-Pfalz",
    "wof:name":"Ingo Hinkelmann",
    "wof:placetype":"venue"
},
  "geometry": {"coordinates":[7.526693821,49.6136779785],"type":"Point"}
}