{
  "type": "Feature",
  "properties": {
    "iso:country":"DE",
    "sg:address":"Am Waldfriedhof 6",
    "sg:city":"Straubing",
    "sg:phone":"+49 9421/6555",
    "sg:postcode":"94315",
    "sg:province":"Bayern",
    "wof:name":"Hans-j\u00fcrgen Hahn Architekt",
    "wof:placetype":"venue"
},
  "geometry": {"coordinates":[12.589267,48.878624],"type":"Point"}
}