{
  "type": "Feature",
  "properties": {
    "iso:country":"DE",
    "sg:address":"Ericaweg 10",
    "sg:city":"Ellerbek",
    "sg:postcode":"25474",
    "sg:province":"Schleswig-Holstein",
    "wof:name":"Us Automaten Aufstellbetriebs Gmbh",
    "wof:placetype":"venue"
},
  "geometry": {"coordinates":[9.894874,53.641857],"type":"Point"}
}