{
  "type": "Feature",
  "properties": {
    "iso:country":"DE",
    "sg:address":"Schyrenstr. 16",
    "sg:city":"M\u00fcnchen",
    "sg:phone":"+49 89/6516500",
    "sg:postcode":"81543",
    "sg:province":"Bayern",
    "wof:name":"Feine Fahrr\u00e4der Gmbh",
    "wof:placetype":"venue"
},
  "geometry": {"coordinates":[11.571499,48.119873],"type":"Point"}
}