{
  "type": "Feature",
  "properties": {
    "iso:country":"DE",
    "sg:address":"Tenderweg 9",
    "sg:city":"Essen",
    "sg:phone":"+49 4920/1866470",
    "sg:postcode":"45141",
    "sg:province":"Nordrhein-Westfalen",
    "wof:name":"Niessen Buch- U. Offsetdruckerei Gmbh",
    "wof:placetype":"venue"
},
  "geometry": {"coordinates":[6.9873180389,51.4766464233],"type":"Point"}
}