{
  "type": "Feature",
  "properties": {
    "iso:country":"DE",
    "sg:address":"Mei\u00dfenbachstr. 8",
    "sg:city":"Lauf",
    "sg:phone":"+49 9123/74390",
    "sg:postcode":"91207",
    "sg:province":"Bayern",
    "wof:name":"Konrad Seitz",
    "wof:placetype":"venue"
},
  "geometry": {"coordinates":[11.283964,49.512726],"type":"Point"}
}