{
  "type": "Feature",
  "properties": {
    "iso:country":"DE",
    "sg:address":"Aschthaler Str. 7",
    "sg:city":"Fuchstal",
    "sg:phone":"+49 8243/2185",
    "sg:postcode":"86925",
    "sg:province":"Bayern",
    "wof:name":"Hans Zientner",
    "wof:placetype":"venue"
},
  "geometry": {"coordinates":[10.8264541626,47.9300804138],"type":"Point"}
}