{
  "type": "Feature",
  "properties": {
    "iso:country":"DE",
    "sg:address":"Georgenstr. 11",
    "sg:city":"Reutlingen",
    "sg:phone":"+49 7121/29464",
    "sg:postcode":"72764",
    "sg:province":"Baden-W\u00fcrttemberg",
    "wof:name":"Silberbar",
    "wof:placetype":"venue"
},
  "geometry": {"coordinates":[9.2159910202,48.487285614],"type":"Point"}
}