{
  "type": "Feature",
  "properties": {
    "iso:country":"DE",
    "sg:address":"Kleinfeldstr. 10",
    "sg:city":"M\u00fcnchen",
    "sg:postcode":"81549",
    "sg:province":"Bayern",
    "wof:name":"Festival Sol\u00e8e Veranstaltungsservice Gmbh",
    "wof:placetype":"venue"
},
  "geometry": {"coordinates":[11.6104,48.093307],"type":"Point"}
}