{
  "type": "Feature",
  "properties": {
    "iso:country":"DE",
    "sg:address":"R\u00f6stenweg 12",
    "sg:city":"Coburg",
    "sg:phone":"+49 9561/60678",
    "sg:postcode":"96450",
    "sg:province":"Bayern",
    "wof:name":"S\u00e4gewerk Oberm\u00fchle Adolf H\u00fcl\u00df Inh. Johanna Schreiner Ohg",
    "wof:placetype":"venue"
},
  "geometry": {"coordinates":[10.952545166,50.2758598328],"type":"Point"}
}