{
  "type": "Feature",
  "properties": {
    "iso:country":"DE",
    "sg:address":"Roseggerstr. 4",
    "sg:city":"Leipzig",
    "sg:phone":"+49 341/8616051",
    "sg:postcode":"04289",
    "sg:province":"Sachsen",
    "wof:name":"Beate Angerm\u00fcller",
    "wof:placetype":"venue"
},
  "geometry": {"coordinates":[12.4338159561,51.2976722717],"type":"Point"}
}