{
  "type": "Feature",
  "properties": {
    "iso:country":"DE",
    "sg:address":"Am Wollhaus 1",
    "sg:city":"Heilbronn",
    "sg:phone":"+49 7131/68988",
    "sg:postcode":"74072",
    "sg:province":"Baden-W\u00fcrttemberg",
    "wof:name":"Holzteller",
    "wof:placetype":"venue"
},
  "geometry": {"coordinates":[9.220126152,49.1392669678],"type":"Point"}
}