{
  "type": "Feature",
  "properties": {
    "iso:country":"DE",
    "sg:address":"Vlothoer Str. 235",
    "sg:city":"Herford",
    "sg:phone":"+49 5221/25978",
    "sg:postcode":"32049",
    "sg:province":"Nordrhein-Westfalen",
    "wof:name":"Helena",
    "wof:placetype":"venue"
},
  "geometry": {"coordinates":[8.7248325348,52.1279220581],"type":"Point"}
}