{
  "type": "Feature",
  "properties": {
    "iso:country":"DE",
    "sg:address":"Corneliusstr. 7",
    "sg:city":"M\u00fcnchen",
    "sg:phone":"+49 172 8222339",
    "sg:postcode":"80469",
    "sg:province":"Bayern",
    "wof:name":"Superior Awegs Gesellschaft F\u00fcr Dental-handel Und",
    "wof:placetype":"venue"
},
  "geometry": {"coordinates":[11.5751676559,48.1324996948],"type":"Point"}
}