{
  "type": "Feature",
  "properties": {
    "iso:country":"DE",
    "sg:address":"M\u00fchlenweg 19",
    "sg:city":"S\u00fcptitz",
    "sg:phone":"+49 3421/705933",
    "sg:postcode":"04860",
    "sg:province":"Sachsen",
    "wof:name":"K. G\u00f6rlich",
    "wof:placetype":"venue"
},
  "geometry": {"coordinates":[12.9228992462,51.5667381287],"type":"Point"}
}