{
  "type": "Feature",
  "properties": {
    "iso:country":"DE",
    "sg:address":"Beim Rosenwasser 18",
    "sg:city":"L\u00fcbeck",
    "sg:postcode":"23568",
    "sg:province":"Schleswig-Holstein",
    "wof:name":"De Com Tec",
    "wof:placetype":"venue"
},
  "geometry": {"coordinates":[10.7891340256,53.8869400024],"type":"Point"}
}