{
  "type": "Feature",
  "properties": {
    "iso:country":"DE",
    "sg:address":"Benzstr. 7",
    "sg:city":"V\u00f6lklingen",
    "sg:phone":"+49 6898/26282",
    "sg:postcode":"66333",
    "sg:province":"Saarland",
    "wof:name":"Horst Rippel Ingenieur",
    "wof:placetype":"venue"
},
  "geometry": {"coordinates":[6.8466439247,49.2605514526],"type":"Point"}
}