{
  "type": "Feature",
  "properties": {
    "iso:country":"DE",
    "sg:address":"Hauptstr. 26",
    "sg:city":"Ellenberg",
    "sg:phone":"+49 7962/90200",
    "sg:postcode":"73488",
    "sg:province":"Baden-W\u00fcrttemberg",
    "wof:name":"Franz Lichtmaneker",
    "wof:placetype":"venue"
},
  "geometry": {"coordinates":[10.2151498795,49.0125656128],"type":"Point"}
}