{
  "type": "Feature",
  "properties": {
    "iso:country":"DE",
    "sg:address":"Carl-Natterer-Str. 20",
    "sg:city":"Augsburg",
    "sg:phone":"+49 821/703458",
    "sg:postcode":"86169",
    "sg:province":"Bayern",
    "wof:name":"Ingrid T\u00fcrpe",
    "wof:placetype":"venue"
},
  "geometry": {"coordinates":[10.899838,48.399429],"type":"Point"}
}