{
  "type": "Feature",
  "properties": {
    "iso:country":"DE",
    "sg:address":"Hauptstr. 131",
    "sg:city":"Schwelm",
    "sg:phone":"+49 2336/6506",
    "sg:postcode":"58332",
    "sg:province":"Nordrhein-Westfalen",
    "wof:name":"Erika Krewitt",
    "wof:placetype":"venue"
},
  "geometry": {"coordinates":[7.3005290031,51.2878456116],"type":"Point"}
}