{
  "type": "Feature",
  "properties": {
    "iso:country":"DE",
    "sg:address":"Bergstr. 13",
    "sg:city":"Todtenweis",
    "sg:phone":"+49 8237/1381",
    "sg:postcode":"86447",
    "sg:province":"Bayern",
    "wof:name":"Josef Pilz Gesch\u00e4ftsf\u00fchrung",
    "wof:placetype":"venue"
},
  "geometry": {"coordinates":[10.922437,48.515736],"type":"Point"}
}