{
  "type": "Feature",
  "properties": {
    "iso:country":"DE",
    "sg:address":"Oststr. 20",
    "sg:city":"Ibbenb\u00fcren",
    "sg:phone":"+49 5451/15380",
    "sg:postcode":"49477",
    "sg:province":"Nordrhein-Westfalen",
    "wof:name":"Cornelia Lehrter Heilpraktikerin",
    "wof:placetype":"venue"
},
  "geometry": {"coordinates":[7.7183971405,52.274684906],"type":"Point"}
}