{
  "type": "Feature",
  "properties": {
    "iso:country":"DE",
    "sg:address":"Daimlerstr. 13",
    "sg:city":"Steinbach",
    "sg:phone":"+49 6171/75582",
    "sg:postcode":"61449",
    "sg:province":"Hessen",
    "wof:name":"Willi Ape",
    "wof:placetype":"venue"
},
  "geometry": {"coordinates":[8.58477,50.169071],"type":"Point"}
}