{
  "type": "Feature",
  "properties": {
    "iso:country":"DE",
    "sg:address":"August-Berthelt-Str 2",
    "sg:city":"Gro\u00dfr\u00f6hrsdorf",
    "sg:phone":"+49 35952/4040",
    "sg:postcode":"01900",
    "sg:province":"Sachsen",
    "wof:name":"Metallwarenfabrik Haufe Gmbh & Co Kg",
    "wof:placetype":"venue"
},
  "geometry": {"coordinates":[14.046288,51.140839],"type":"Point"}
}