{
  "type": "Feature",
  "properties": {
    "iso:country":"DE",
    "sg:address":"Sch\u00f6n 1",
    "sg:city":"Patersdorf",
    "sg:phone":"+49 9929/1330",
    "sg:postcode":"94265",
    "sg:province":"Bayern",
    "wof:name":"Gastst\u00e4tte Eduard Schroll",
    "wof:placetype":"venue"
},
  "geometry": {"coordinates":[12.9400854111,49.0093040466],"type":"Point"}
}