{
  "type": "Feature",
  "properties": {
    "iso:country":"DE",
    "sg:address":"Sonnenb\u00fchlweg 15",
    "sg:city":"Hinterzarten",
    "sg:phone":"+49 7652/1375",
    "sg:postcode":"79856",
    "sg:province":"Baden-W\u00fcrttemberg",
    "wof:name":"G\u00e4stehaus Susanne Mallebrein",
    "wof:placetype":"venue"
},
  "geometry": {"coordinates":[8.0976896286,47.9102058411],"type":"Point"}
}