{
  "type": "Feature",
  "properties": {
    "iso:country":"DE",
    "sg:address":"Hauptstr. 15",
    "sg:city":"Bockelwitz",
    "sg:postcode":"04703",
    "sg:province":"Sachsen",
    "wof:name":"E. Gaudlitz",
    "wof:placetype":"venue"
},
  "geometry": {"coordinates":[12.986205,51.184612],"type":"Point"}
}