{
  "type": "Feature",
  "properties": {
    "iso:country":"DE",
    "sg:address":"Durlacher Str. 28",
    "sg:city":"Ketsch",
    "sg:phone":"+49 4962/026960",
    "sg:postcode":"68769",
    "sg:province":"Baden-W\u00fcrttemberg",
    "wof:name":"K\u00dcma Werkzeugmaschinen- Fabrik Gmbh & Co. Kg",
    "wof:placetype":"venue"
},
  "geometry": {"coordinates":[8.52436,49.367821],"type":"Point"}
}