{
  "type": "Feature",
  "properties": {
    "iso:country":"DE",
    "sg:address":"Jahnstr. 41",
    "sg:city":"Kandel",
    "sg:phone":"+49 7275/4100",
    "sg:postcode":"76870",
    "sg:province":"Rheinland-Pfalz",
    "wof:name":"Vereinsgastst\u00e4tte Vfr Clubhaus",
    "wof:placetype":"venue"
},
  "geometry": {"coordinates":[8.1958999634,49.0768699646],"type":"Point"}
}