{
  "type": "Feature",
  "properties": {
    "iso:country":"DE",
    "sg:address":"Hans-Porner-Str. 38",
    "sg:city":"Braunschweig",
    "sg:phone":"+49 531/691940",
    "sg:postcode":"38126",
    "sg:province":"Niedersachsen",
    "wof:name":"B\u00e4renstube",
    "wof:placetype":"venue"
},
  "geometry": {"coordinates":[10.5365610123,52.2442817688],"type":"Point"}
}