{
  "type": "Feature",
  "properties": {
    "iso:country":"DE",
    "sg:address":"Saarbr\u00fccker Str. 4",
    "sg:city":"Wadern",
    "sg:postcode":"66687",
    "sg:province":"Saarland",
    "wof:name":"Peter Esch",
    "wof:placetype":"venue"
},
  "geometry": {"coordinates":[6.839642,49.48695],"type":"Point"}
}