{
  "type": "Feature",
  "properties": {
    "iso:country":"DE",
    "sg:address":"H\u00fcttenstr. 125",
    "sg:city":"Bendorf",
    "sg:phone":"+49 2622/14597",
    "sg:postcode":"56170",
    "sg:province":"Rheinland-Pfalz",
    "wof:name":"Horst Dziwior",
    "wof:placetype":"venue"
},
  "geometry": {"coordinates":[7.558174,50.424873],"type":"Point"}
}