{
  "type": "Feature",
  "properties": {
    "iso:country":"DE",
    "sg:address":"Steinstr. 68",
    "sg:city":"Berlin",
    "sg:phone":"+49 30/7452062",
    "sg:postcode":"12307",
    "sg:province":"Berlin",
    "wof:name":"Kurt Schmidt",
    "wof:placetype":"venue"
},
  "geometry": {"coordinates":[13.3984603882,52.3910713196],"type":"Point"}
}