{
  "type": "Feature",
  "properties": {
    "iso:country":"DE",
    "sg:address":"St.-Georg-Str. 19",
    "sg:city":"Ravensburg",
    "sg:phone":"+49 7542/952266",
    "sg:postcode":"88214",
    "sg:province":"Baden-W\u00fcrttemberg",
    "wof:name":"Holz & Wolf Bautr\u00e4ger Gmbh",
    "wof:placetype":"venue"
},
  "geometry": {"coordinates":[9.592466,47.735634],"type":"Point"}
}