{
  "type": "Feature",
  "properties": {
    "iso:country":"DE",
    "sg:address":"Dresdner Str. 39",
    "sg:city":"Gro\u00dfenhain",
    "sg:phone":"+49 3522/63133",
    "sg:postcode":"01558",
    "sg:province":"Sachsen",
    "wof:name":"F. Schade",
    "wof:placetype":"venue"
},
  "geometry": {"coordinates":[13.53088,51.285999],"type":"Point"}
}