{
  "type": "Feature",
  "properties": {
    "iso:country":"DE",
    "sg:address":"Salzstetter Str. 40",
    "sg:city":"Haiterbach",
    "sg:phone":"+49 7456/7150",
    "sg:postcode":"72221",
    "sg:province":"Baden-W\u00fcrttemberg",
    "wof:name":"Huby - Motorcycle - Connection",
    "wof:placetype":"venue"
},
  "geometry": {"coordinates":[8.6457738876,48.5193977356],"type":"Point"}
}