{
  "type": "Feature",
  "properties": {
    "iso:country":"DE",
    "sg:address":"Wiesenweg 6",
    "sg:city":"Sch\u00f6nebeck",
    "sg:phone":"+49 391/5615698",
    "sg:postcode":"39218",
    "sg:province":"Sachsen-Anhalt",
    "wof:name":"Juergen Guenter",
    "wof:placetype":"venue"
},
  "geometry": {"coordinates":[11.748014,52.028732],"type":"Point"}
}