{
  "type": "Feature",
  "properties": {
    "iso:country":"DE",
    "sg:address":"Bergstr. 68",
    "sg:city":"Kamp-Lintfort",
    "sg:phone":"+49 2842/42438",
    "sg:postcode":"47475",
    "sg:province":"Nordrhein-Westfalen",
    "wof:name":"H. Han\u00dfen",
    "wof:placetype":"venue"
},
  "geometry": {"coordinates":[6.4988260269,51.495765686],"type":"Point"}
}