{
  "type": "Feature",
  "properties": {
    "iso:country":"DE",
    "sg:address":"Werdohler Str. 34",
    "sg:city":"L\u00fcdenscheid",
    "sg:phone":"+49 2351/82237",
    "sg:postcode":"58511",
    "sg:province":"Nordrhein-Westfalen",
    "wof:name":"Cafe Ortwin Wermter",
    "wof:placetype":"venue"
},
  "geometry": {"coordinates":[7.637307,51.218334],"type":"Point"}
}