{
  "type": "Feature",
  "properties": {
    "iso:country":"DE",
    "sg:address":"Am Erzweg 9",
    "sg:city":"Schmelz",
    "sg:phone":"+49 6887/91290",
    "sg:postcode":"66839",
    "sg:province":"Saarland",
    "wof:name":"Tsl Langenfeld Gmbh",
    "wof:placetype":"venue"
},
  "geometry": {"coordinates":[6.873896122,49.4404335022],"type":"Point"}
}