{
  "type": "Feature",
  "properties": {
    "iso:country":"DE",
    "sg:address":"Von-Werth-Str. 44",
    "sg:city":"K\u00f6ln",
    "sg:phone":"+49 221/131366",
    "sg:postcode":"50670",
    "sg:province":"Nordrhein-Westfalen",
    "wof:name":"Redaktion Dlt Flugzeit K\u00f6sler Verlag",
    "wof:placetype":"venue"
},
  "geometry": {"coordinates":[6.9450368881,50.9455413818],"type":"Point"}
}