{
  "type": "Feature",
  "properties": {
    "iso:country":"DE",
    "sg:address":"Wernerstr. 3",
    "sg:city":"Markgr\u00f6ningen",
    "sg:phone":"+49 7145/6148",
    "sg:postcode":"71706",
    "sg:province":"Baden-W\u00fcrttemberg",
    "wof:name":"K. Hammer",
    "wof:placetype":"venue"
},
  "geometry": {"coordinates":[9.085636,48.905308],"type":"Point"}
}