{
  "type": "Feature",
  "properties": {
    "iso:country":"DE",
    "sg:address":"Am Schertzer",
    "sg:city":"Steinbach-Hallenberg",
    "sg:postcode":"98587",
    "sg:province":"Th\u00fcringen",
    "wof:name":"M & M Disco Gmbh",
    "wof:placetype":"venue"
},
  "geometry": {"coordinates":[10.5565,50.674091],"type":"Point"}
}