{
  "type": "Feature",
  "properties": {
    "iso:country":"DE",
    "sg:address":"Pozzistr. 9",
    "sg:city":"Mannheim",
    "sg:phone":"+49 621/334441",
    "sg:postcode":"68167",
    "sg:province":"Baden-W\u00fcrttemberg",
    "wof:name":"Glaner Masseur",
    "wof:placetype":"venue"
},
  "geometry": {"coordinates":[8.476117,49.497524],"type":"Point"}
}