{
  "type": "Feature",
  "properties": {
    "iso:country":"DE",
    "sg:address":"Wiclefstr. 16-17",
    "sg:city":"Berlin",
    "sg:phone":"+49 30/3961246",
    "sg:postcode":"10551",
    "sg:province":"Berlin",
    "wof:name":"J\u00fcrgen Schnitt",
    "wof:placetype":"venue"
},
  "geometry": {"coordinates":[13.335335,52.530605],"type":"Point"}
}