{
  "type": "Feature",
  "properties": {
    "iso:country":"DE",
    "sg:address":"Birkenstr. 92",
    "sg:city":"Velbert",
    "sg:phone":"+49 2051/252367",
    "sg:postcode":"42549",
    "sg:province":"Nordrhein-Westfalen",
    "wof:name":"Dr. Horst Lappe Tierarzt",
    "wof:placetype":"venue"
},
  "geometry": {"coordinates":[7.0455741882,51.3367118835],"type":"Point"}
}