{
  "type": "Feature",
  "properties": {
    "iso:country":"DE",
    "sg:address":"Kirschallee 3",
    "sg:city":"Zerbst",
    "sg:phone":"+49 3923/780277",
    "sg:postcode":"39261",
    "sg:province":"Sachsen-Anhalt",
    "wof:name":"Bkb-gmbh & Co. K\u00fcchenspezialist-",
    "wof:placetype":"venue"
},
  "geometry": {"coordinates":[12.1026935577,51.9529304504],"type":"Point"}
}