{
  "type": "Feature",
  "properties": {
    "iso:country":"DE",
    "sg:address":"Stuttgarter Str. 130",
    "sg:city":"Waiblingen",
    "sg:phone":"+49 4971/511401",
    "sg:postcode":"71332",
    "sg:province":"Baden-W\u00fcrttemberg",
    "wof:name":"Robert Bosch Gmbh",
    "wof:placetype":"venue"
},
  "geometry": {"coordinates":[9.298085,48.82238],"type":"Point"}
}