{
  "type": "Feature",
  "properties": {
    "iso:country":"DE",
    "sg:address":"Hadermarkt 6",
    "sg:city":"Ruhpolding",
    "sg:phone":"+49 8663/1860",
    "sg:postcode":"83324",
    "sg:province":"Bayern",
    "wof:name":"Hans Staller",
    "wof:placetype":"venue"
},
  "geometry": {"coordinates":[12.6579189301,47.7599220276],"type":"Point"}
}