{
  "type": "Feature",
  "properties": {
    "iso:country":"DE",
    "sg:address":"Kirschallee 18",
    "sg:city":"Lebus",
    "sg:phone":"+49 33604/5130",
    "sg:postcode":"15326",
    "sg:province":"Brandenburg",
    "wof:name":"Wsf Bau- Und Industrie- Bedarf Gmbh",
    "wof:placetype":"venue"
},
  "geometry": {"coordinates":[14.53488,52.423424],"type":"Point"}
}