{
  "type": "Feature",
  "properties": {
    "iso:country":"DE",
    "sg:address":"Niedere K\u00f6ditzgasse 9",
    "sg:city":"Saalfeld",
    "sg:phone":"+49 3671/511414",
    "sg:postcode":"07318",
    "sg:province":"Th\u00fcringen",
    "wof:name":"Fronzek Und Gutheil",
    "wof:placetype":"venue"
},
  "geometry": {"coordinates":[11.364192009,50.6474685669],"type":"Point"}
}