{
  "type": "Feature",
  "properties": {
    "iso:country":"DE",
    "sg:address":"Rathausstr. 19",
    "sg:city":"Soest",
    "sg:phone":"+49 2921/13125",
    "sg:postcode":"59494",
    "sg:province":"Nordrhein-Westfalen",
    "wof:name":"Alfred Schmitz Farben-lacke-handel",
    "wof:placetype":"venue"
},
  "geometry": {"coordinates":[8.1079626083,51.5708694458],"type":"Point"}
}