{
  "type": "Feature",
  "properties": {
    "iso:country":"DE",
    "sg:address":"Au\u00dferhalb 44",
    "sg:city":"Ober-Ramstadt",
    "sg:phone":"+49 6154/53418",
    "sg:postcode":"64372",
    "sg:province":"Hessen",
    "wof:name":"Karl-heinz Bernhard",
    "wof:placetype":"venue"
},
  "geometry": {"coordinates":[8.762303,49.804504],"type":"Point"}
}