{
  "type": "Feature",
  "properties": {
    "iso:country":"DE",
    "sg:address":"D\u00f6rnchensweg 4",
    "sg:city":"Simmerath",
    "sg:phone":"+49 2473/2989",
    "sg:postcode":"52152",
    "sg:province":"Nordrhein-Westfalen",
    "wof:name":"Ulrich Breuer",
    "wof:placetype":"venue"
},
  "geometry": {"coordinates":[6.3317599297,50.6229705811],"type":"Point"}
}