{
  "type": "Feature",
  "properties": {
    "iso:country":"DE",
    "sg:address":"Splitting rechts 19",
    "sg:city":"Papenburg",
    "sg:phone":"+49 4961/7991",
    "sg:postcode":"26871",
    "sg:province":"Niedersachsen",
    "wof:name":"Volksbank Papenburg Filiale De",
    "wof:placetype":"venue"
},
  "geometry": {"coordinates":[7.440043,53.075451],"type":"Point"}
}