{
  "type": "Feature",
  "properties": {
    "iso:country":"DE",
    "sg:address":"Haus Hees",
    "sg:city":"Straelen",
    "sg:phone":"+49 2834/540",
    "sg:postcode":"47638",
    "sg:province":"Nordrhein-Westfalen",
    "wof:name":"Dr. H. B\u00fccken Tierarzt",
    "wof:placetype":"venue"
},
  "geometry": {"coordinates":[6.2982392311,51.454158783],"type":"Point"}
}