{
  "type": "Feature",
  "properties": {
    "iso:country":"DE",
    "sg:address":"Hauptstr. 40",
    "sg:city":"Kolpin",
    "sg:phone":"+49 33631/5220",
    "sg:postcode":"15518",
    "sg:province":"Brandenburg",
    "wof:name":"Kiko Kieswerk Kolpin Gmbh",
    "wof:placetype":"venue"
},
  "geometry": {"coordinates":[14.1648550034,52.4015159607],"type":"Point"}
}