{
  "type": "Feature",
  "properties": {
    "iso:country":"DE",
    "sg:address":"Lange Str. 31",
    "sg:city":"Lippstadt",
    "sg:phone":"+49 2941/4765",
    "sg:postcode":"59555",
    "sg:province":"Nordrhein-Westfalen",
    "wof:name":"Lehmann",
    "wof:placetype":"venue"
},
  "geometry": {"coordinates":[8.3472671509,51.6750946045],"type":"Point"}
}