{
  "type": "Feature",
  "properties": {
    "iso:country":"DE",
    "sg:address":"Forchenweg 7",
    "sg:city":"Zimmern",
    "sg:phone":"+49 741/33682",
    "sg:postcode":"78658",
    "sg:province":"Baden-W\u00fcrttemberg",
    "wof:name":"Manfred Mager Ingenieur",
    "wof:placetype":"venue"
},
  "geometry": {"coordinates":[8.5442895889,48.1480636597],"type":"Point"}
}