{
  "type": "Feature",
  "properties": {
    "iso:country":"DE",
    "sg:address":"Pra\u00dfbergstr. 28",
    "sg:city":"Wangen",
    "sg:postcode":"88239",
    "sg:province":"Baden-W\u00fcrttemberg",
    "wof:name":"Alt Ohg",
    "wof:placetype":"venue"
},
  "geometry": {"coordinates":[9.8335771561,47.6941833496],"type":"Point"}
}