{
  "type": "Feature",
  "properties": {
    "iso:country":"DE",
    "sg:address":"Postfach 1234",
    "sg:city":"Troisdorf",
    "sg:phone":"+49 800 9828000",
    "sg:postcode":"53822",
    "sg:province":"Nordrhein-Westfalen",
    "wof:name":"K\u00e4ltetechnik In K\u00f6ln",
    "wof:placetype":"venue"
},
  "geometry": {"coordinates":[7.15218,50.809109],"type":"Point"}
}