{
  "type": "Feature",
  "properties": {
    "iso:country":"DE",
    "sg:address":"L\u00f6ffelstr. 5",
    "sg:city":"Stuttgart",
    "sg:phone":"+49 711/766415",
    "sg:postcode":"70597",
    "sg:province":"Baden-W\u00fcrttemberg",
    "wof:name":"Florian Oelssner Heilpraktiker",
    "wof:placetype":"venue"
},
  "geometry": {"coordinates":[9.1688680649,48.748840332],"type":"Point"}
}