{
  "type": "Feature",
  "properties": {
    "iso:country":"DE",
    "sg:address":"Am Bahnhof",
    "sg:city":"Dippoldiswalde",
    "sg:postcode":"01744",
    "sg:province":"Sachsen",
    "wof:name":"Bhg",
    "wof:placetype":"venue"
},
  "geometry": {"coordinates":[13.671795,50.873875],"type":"Point"}
}