{
  "type": "Feature",
  "properties": {
    "iso:country":"DE",
    "sg:address":"Gutenbergring 55",
    "sg:city":"Norderstedt",
    "sg:postcode":"22848",
    "sg:province":"Schleswig-Holstein",
    "wof:name":"F. I. T. Fullspeed International Transport",
    "wof:placetype":"venue"
},
  "geometry": {"coordinates":[9.9856882095,53.6582794189],"type":"Point"}
}