{
  "type": "Feature",
  "properties": {
    "iso:country":"DE",
    "sg:address":"Osterkamp 51",
    "sg:city":"Handewitt",
    "sg:phone":"+49 4608/6831",
    "sg:postcode":"24983",
    "sg:province":"Schleswig-Holstein",
    "wof:name":"Manfred Schindler Architekt",
    "wof:placetype":"venue"
},
  "geometry": {"coordinates":[9.333878,54.765388],"type":"Point"}
}