{
  "type": "Feature",
  "properties": {
    "iso:country":"DE",
    "sg:address":"Meisterstr. 19",
    "sg:city":"Annaberg-Buchholz",
    "sg:phone":"+49 3733/64651",
    "sg:postcode":"09456",
    "sg:province":"Sachsen",
    "wof:name":"M\u00f6bel-k\u00f6rnig Inh. Michael R\u00f6bert",
    "wof:placetype":"venue"
},
  "geometry": {"coordinates":[12.994518,50.564369],"type":"Point"}
}