{
  "type": "Feature",
  "properties": {
    "iso:country":"DE",
    "sg:address":"Bamenohler Str. 93 Bamenohl",
    "sg:city":"Finnentrop",
    "sg:phone":"+49 4927/2151080",
    "sg:postcode":"57413",
    "sg:province":"Nordrhein-Westfalen",
    "wof:name":"Bernhard Heisiep, Lastwagentransport U. Spedition Gmbh",
    "wof:placetype":"venue"
},
  "geometry": {"coordinates":[7.9655079842,51.1738243103],"type":"Point"}
}