{
  "type": "Feature",
  "properties": {
    "iso:country":"DE",
    "sg:address":"Tornescher Weg 70",
    "sg:city":"Uetersen",
    "sg:phone":"+49 4122/7724",
    "sg:postcode":"25436",
    "sg:province":"Schleswig-Holstein",
    "wof:name":"Trend Beschriftung Und Werbetechnik Gmbh",
    "wof:placetype":"venue"
},
  "geometry": {"coordinates":[9.6876001358,53.6895217896],"type":"Point"}
}