{
  "type": "Feature",
  "properties": {
    "iso:country":"DE",
    "sg:address":"Hindenburgstr. 1",
    "sg:city":"Denkendorf",
    "sg:phone":"+49 711/3466694",
    "sg:postcode":"73770",
    "sg:province":"Baden-W\u00fcrttemberg",
    "wof:name":"Bistro Alte Backstube",
    "wof:placetype":"venue"
},
  "geometry": {"coordinates":[9.3201189041,48.6972465515],"type":"Point"}
}