{
  "type": "Feature",
  "properties": {
    "iso:country":"DE",
    "sg:address":"Werth 94",
    "sg:city":"Wuppertal",
    "sg:phone":"+49 202/594424",
    "sg:postcode":"42275",
    "sg:province":"Nordrhein-Westfalen",
    "wof:name":"Alfred Daume Verm\u00f6gensver- Waltung Gmbh",
    "wof:placetype":"venue"
},
  "geometry": {"coordinates":[7.205365181,51.2723426819],"type":"Point"}
}