{
  "type": "Feature",
  "properties": {
    "iso:country":"DE",
    "sg:address":"Lucherberger Str. 1",
    "sg:city":"Inden",
    "sg:phone":"+49 2465/905046",
    "sg:postcode":"52459",
    "sg:province":"Nordrhein-Westfalen",
    "wof:name":"Friedrich Schwarz Gmbh",
    "wof:placetype":"venue"
},
  "geometry": {"coordinates":[6.3967981339,50.8613471985],"type":"Point"}
}