{
  "type": "Feature",
  "properties": {
    "iso:country":"DE",
    "sg:address":"Oskar-J\u00e4ger-Str. 3",
    "sg:city":"K\u00f6ln",
    "sg:phone":"+49 221/5469360",
    "sg:postcode":"50931",
    "sg:province":"Nordrhein-Westfalen",
    "wof:name":"Joh. Schl\u00f6sser Gmbh",
    "wof:placetype":"venue"
},
  "geometry": {"coordinates":[6.911704,50.938084],"type":"Point"}
}