{
  "type": "Feature",
  "properties": {
    "iso:country":"DE",
    "sg:address":"Wilhelmstr. 93",
    "sg:city":"B\u00fcnde",
    "sg:phone":"+49 5223/2277",
    "sg:postcode":"32257",
    "sg:province":"Nordrhein-Westfalen",
    "wof:name":"G\u00fcnter Tiemann",
    "wof:placetype":"venue"
},
  "geometry": {"coordinates":[8.563083,52.198002],"type":"Point"}
}