{
  "type": "Feature",
  "properties": {
    "iso:country":"DE",
    "sg:address":"Wei\u00dfenfelser Str. 29",
    "sg:city":"Prittitz",
    "sg:phone":"+49 34445/21510",
    "sg:postcode":"06667",
    "sg:province":"Sachsen-Anhalt",
    "wof:name":"Eberhard Jenennchen",
    "wof:placetype":"venue"
},
  "geometry": {"coordinates":[11.929699,51.150326],"type":"Point"}
}