{
  "type": "Feature",
  "properties": {
    "iso:country":"DE",
    "sg:address":"Egerlandstr.80",
    "sg:city":"Geretsried",
    "sg:phone":"+49 8171/99890",
    "sg:postcode":"82538",
    "sg:province":"Bayern",
    "wof:name":"Ugt Union Gas + Technik Gmbh",
    "wof:placetype":"venue"
},
  "geometry": {"coordinates":[11.465419,47.876469],"type":"Point"}
}