{
  "type": "Feature",
  "properties": {
    "iso:country":"DE",
    "sg:address":"H\u00f6niger Str. 7",
    "sg:city":"Ruppertshofen",
    "sg:phone":"+49 7176/1314",
    "sg:postcode":"73577",
    "sg:province":"Baden-W\u00fcrttemberg",
    "wof:name":"Reinhold Sachsenmaier",
    "wof:placetype":"venue"
},
  "geometry": {"coordinates":[9.813893,48.883759],"type":"Point"}
}