{
  "type": "Feature",
  "properties": {
    "iso:country":"DE",
    "sg:address":"Landrat-Christians-Str. 95",
    "sg:city":"Bremen",
    "sg:postcode":"28779",
    "sg:province":"Bremen",
    "wof:name":"Ski Schl\u00fcsselfertiger Und Konstruktiver Industrie-",
    "wof:placetype":"venue"
},
  "geometry": {"coordinates":[8.576278,53.181236],"type":"Point"}
}