{
  "type": "Feature",
  "properties": {
    "iso:country":"DE",
    "sg:address":"Mummstr. 33",
    "sg:city":"Solingen",
    "sg:phone":"+49 212/208188",
    "sg:postcode":"42651",
    "sg:province":"Nordrhein-Westfalen",
    "wof:name":"N. Top-mensing",
    "wof:placetype":"venue"
},
  "geometry": {"coordinates":[7.0836100578,51.1742897034],"type":"Point"}
}