{
  "type": "Feature",
  "properties": {
    "iso:country":"DE",
    "sg:address":"Koblenzer Str. 15",
    "sg:city":"Mannheim",
    "sg:phone":"+49 621/734393",
    "sg:postcode":"68309",
    "sg:province":"Baden-W\u00fcrttemberg",
    "wof:name":"China-imbi\u00df",
    "wof:placetype":"venue"
},
  "geometry": {"coordinates":[8.5269594193,49.5091590881],"type":"Point"}
}