{
  "type": "Feature",
  "properties": {
    "iso:country":"DE",
    "sg:address":"W\u00f6rthstr. 5",
    "sg:city":"Reutlingen",
    "sg:phone":"+49 7121/92940",
    "sg:postcode":"72764",
    "sg:province":"Baden-W\u00fcrttemberg",
    "wof:name":"Knaak Und Reich",
    "wof:placetype":"venue"
},
  "geometry": {"coordinates":[9.216132164,48.4866828918],"type":"Point"}
}