{
  "type": "Feature",
  "properties": {
    "iso:country":"DE",
    "sg:address":"Freytagweg 63",
    "sg:city":"Stuttgart",
    "sg:postcode":"70565",
    "sg:province":"Baden-W\u00fcrttemberg",
    "wof:name":"F. I. A. B. Gmbh",
    "wof:placetype":"venue"
},
  "geometry": {"coordinates":[9.158978,48.711029],"type":"Point"}
}