{
  "type": "Feature",
  "properties": {
    "iso:country":"DE",
    "sg:address":"Breiteweg 10/1",
    "sg:city":"Nagold",
    "sg:phone":"+49 7459/1747",
    "sg:postcode":"72202",
    "sg:province":"Baden-W\u00fcrttemberg",
    "wof:name":"Dietmar Lepple Elektroinstallation",
    "wof:placetype":"venue"
},
  "geometry": {"coordinates":[8.746004,48.51313],"type":"Point"}
}