{
  "type": "Feature",
  "properties": {
    "iso:country":"DE",
    "sg:address":"Mallaustr. 87",
    "sg:city":"Mannheim",
    "sg:phone":"+49 621/873091",
    "sg:postcode":"68219",
    "sg:province":"Baden-W\u00fcrttemberg",
    "wof:name":"Boys Und Girls Fotografie Gmbh",
    "wof:placetype":"venue"
},
  "geometry": {"coordinates":[8.521424,49.452072],"type":"Point"}
}