{
  "type": "Feature",
  "properties": {
    "iso:country":"DE",
    "sg:address":"Auf dem Quellberg 19",
    "sg:city":"D\u00fclmen",
    "sg:phone":"+49 2594/949210",
    "sg:postcode":"48249",
    "sg:province":"Nordrhein-Westfalen",
    "wof:name":"Josef Tombrink",
    "wof:placetype":"venue"
},
  "geometry": {"coordinates":[7.29539,51.842239],"type":"Point"}
}