{
  "type": "Feature",
  "properties": {
    "iso:country":"DE",
    "sg:address":"Oststr. 1",
    "sg:city":"Apolda",
    "sg:phone":"+49 3644/563046",
    "sg:postcode":"99510",
    "sg:province":"Th\u00fcringen",
    "wof:name":"Olaf Micheel",
    "wof:placetype":"venue"
},
  "geometry": {"coordinates":[11.527434,51.020756],"type":"Point"}
}