{
  "type": "Feature",
  "properties": {
    "iso:country":"DE",
    "sg:address":"H\u00fcgelstr. 2",
    "sg:city":"Ostercappeln",
    "sg:phone":"+49 5473/2886",
    "sg:postcode":"49179",
    "sg:province":"Niedersachsen",
    "wof:name":"Ernst Ballmeyer",
    "wof:placetype":"venue"
},
  "geometry": {"coordinates":[8.215344,52.372101],"type":"Point"}
}