{
  "type": "Feature",
  "properties": {
    "iso:country":"DE",
    "sg:address":"Willst\u00e4tterstr. 30",
    "sg:city":"N\u00fcrnberg",
    "sg:phone":"+49 911/967120",
    "sg:postcode":"90449",
    "sg:province":"Bayern",
    "wof:name":"Begra Papier-handels- Gesellschaft Hermann Langewort",
    "wof:placetype":"venue"
},
  "geometry": {"coordinates":[11.017389,49.427551],"type":"Point"}
}