{
  "type": "Feature",
  "properties": {
    "iso:country":"DE",
    "sg:address":"Birresborner Str. 53",
    "sg:city":"K\u00f6ln",
    "sg:phone":"+49 221/431076",
    "sg:postcode":"50935",
    "sg:province":"Nordrhein-Westfalen",
    "wof:name":"Cityflor",
    "wof:placetype":"venue"
},
  "geometry": {"coordinates":[6.909519,50.920502],"type":"Point"}
}