{
  "type": "Feature",
  "properties": {
    "iso:country":"DE",
    "sg:address":"Klemkestr. 6",
    "sg:city":"Berlin",
    "sg:phone":"+49 30/4953344",
    "sg:postcode":"13409",
    "sg:province":"Berlin",
    "wof:name":"Szloma Albam",
    "wof:placetype":"venue"
},
  "geometry": {"coordinates":[13.3601970673,52.5741004944],"type":"Point"}
}