{
  "type": "Feature",
  "properties": {
    "iso:country":"DE",
    "sg:address":"Schillerstr. 21",
    "sg:city":"Euerbach",
    "sg:phone":"+49 9726/8680",
    "sg:postcode":"97502",
    "sg:province":"Bayern",
    "wof:name":"Gunda Wagner",
    "wof:placetype":"venue"
},
  "geometry": {"coordinates":[10.139665,50.060547],"type":"Point"}
}