{
  "type": "Feature",
  "properties": {
    "iso:country":"DE",
    "sg:address":"In der Rehre 29",
    "sg:city":"Hannover",
    "sg:phone":"+49 511/468595",
    "sg:postcode":"30457",
    "sg:province":"Niedersachsen",
    "wof:name":"Joachim Herrmann Architekt",
    "wof:placetype":"venue"
},
  "geometry": {"coordinates":[9.695217,52.329411],"type":"Point"}
}