{
  "type": "Feature",
  "properties": {
    "iso:country":"DE",
    "sg:address":"Hahnenstr. 73",
    "sg:city":"Pulheim",
    "sg:phone":"+49 2238/15859",
    "sg:postcode":"50259",
    "sg:province":"Nordrhein-Westfalen",
    "wof:name":"B. Schumann",
    "wof:placetype":"venue"
},
  "geometry": {"coordinates":[6.76989,51.047421],"type":"Point"}
}