{
  "type": "Feature",
  "properties": {
    "iso:country":"DE",
    "sg:address":"Georgenschwaigstr. 23",
    "sg:city":"M\u00fcnchen",
    "sg:postcode":"80807",
    "sg:province":"Bayern",
    "wof:name":"P. H. Events Gmbh",
    "wof:placetype":"venue"
},
  "geometry": {"coordinates":[11.5708627701,48.1808662415],"type":"Point"}
}