{
  "type": "Feature",
  "properties": {
    "iso:country":"DE",
    "sg:address":"Nordertorstriftweg 5",
    "sg:city":"Nienburg",
    "sg:phone":"+49 5021/4147",
    "sg:postcode":"31582",
    "sg:province":"Niedersachsen",
    "wof:name":"Dieter Schr\u00f6der Techn. Grosshandel",
    "wof:placetype":"venue"
},
  "geometry": {"coordinates":[9.213871,52.639702],"type":"Point"}
}