{
  "type": "Feature",
  "properties": {
    "iso:country":"DE",
    "sg:address":"M\u00fchlweg 2 c",
    "sg:city":"Sauerlach",
    "sg:phone":"+49 8104/89010",
    "sg:postcode":"82054",
    "sg:province":"Bayern",
    "wof:name":"Grude Systeme Gmbh",
    "wof:placetype":"venue"
},
  "geometry": {"coordinates":[11.6616048813,47.9673538208],"type":"Point"}
}