{
  "type": "Feature",
  "properties": {
    "iso:country":"DE",
    "sg:address":"Arnulfstr. 25",
    "sg:city":"M\u00fcnchen",
    "sg:postcode":"80335",
    "sg:province":"Bayern",
    "wof:name":"The Yueyang Power Holding Company Gmbh",
    "wof:placetype":"venue"
},
  "geometry": {"coordinates":[11.549854,48.143127],"type":"Point"}
}