{
  "type": "Feature",
  "properties": {
    "iso:country":"DE",
    "sg:address":"Tornescher Weg 133",
    "sg:city":"Uetersen",
    "sg:phone":"+49 4122/51604",
    "sg:postcode":"25436",
    "sg:province":"Schleswig-Holstein",
    "wof:name":"Werner Petke",
    "wof:placetype":"venue"
},
  "geometry": {"coordinates":[9.700174,53.690468],"type":"Point"}
}