{
  "type": "Feature",
  "properties": {
    "iso:country":"DE",
    "sg:address":"Martinstr. 58",
    "sg:city":"M\u00f6nchengladbach",
    "sg:phone":"+49 2161/23383",
    "sg:postcode":"41063",
    "sg:province":"Nordrhein-Westfalen",
    "wof:name":"A. Poepping",
    "wof:placetype":"venue"
},
  "geometry": {"coordinates":[6.449111,51.203697],"type":"Point"}
}