{
  "type": "Feature",
  "properties": {
    "iso:country":"DE",
    "sg:address":"Esch 7",
    "sg:city":"Laer",
    "sg:postcode":"48366",
    "sg:province":"Nordrhein-Westfalen",
    "wof:name":"Dr. Kreyenborg Gmbh",
    "wof:placetype":"venue"
},
  "geometry": {"coordinates":[7.348979,52.054806],"type":"Point"}
}