{
  "type": "Feature",
  "properties": {
    "iso:country":"DE",
    "sg:address":"W\u00f6hlerstr. 5",
    "sg:city":"Frankfurt",
    "sg:postcode":"60323",
    "sg:province":"Hessen",
    "wof:name":"Mbiv Ag & Co. Business Center Kg",
    "wof:placetype":"venue"
},
  "geometry": {"coordinates":[8.666719,50.118069],"type":"Point"}
}