{
  "type": "Feature",
  "properties": {
    "iso:country":"DE",
    "sg:address":"Peterstr. 57",
    "sg:city":"Baesweiler",
    "sg:phone":"+49 2401/2359",
    "sg:postcode":"52499",
    "sg:province":"Nordrhein-Westfalen",
    "wof:name":"R. Und H. Baues",
    "wof:placetype":"venue"
},
  "geometry": {"coordinates":[6.181045,50.902458],"type":"Point"}
}