{
  "type": "Feature",
  "properties": {
    "iso:country":"DE",
    "sg:address":"Steinwiesen 12",
    "sg:city":"Brigachtal",
    "sg:phone":"+49 7721/903085",
    "sg:postcode":"78086",
    "sg:province":"Baden-W\u00fcrttemberg",
    "wof:name":"I. M. Immobilien Management Ag",
    "wof:placetype":"venue"
},
  "geometry": {"coordinates":[8.4758167267,48.0068092346],"type":"Point"}
}