{
  "type": "Feature",
  "properties": {
    "iso:country":"DE",
    "sg:address":"Weingartlstr. 21",
    "sg:city":"Hengersberg",
    "sg:phone":"+49 9901/94100",
    "sg:postcode":"94491",
    "sg:province":"Bayern",
    "wof:name":"Karl Lausch",
    "wof:placetype":"venue"
},
  "geometry": {"coordinates":[13.0572929382,48.7871055603],"type":"Point"}
}