{
  "type": "Feature",
  "properties": {
    "iso:country":"DE",
    "sg:address":"Banzkower Str. 37",
    "sg:city":"Plate",
    "sg:phone":"+49 3861/2210",
    "sg:postcode":"19086",
    "sg:province":"Mecklenburg-Vorpommern",
    "wof:name":"A. Beckmann",
    "wof:placetype":"venue"
},
  "geometry": {"coordinates":[11.4996347427,53.5450248718],"type":"Point"}
}