{
  "type": "Feature",
  "properties": {
    "iso:country":"DE",
    "sg:address":"Am Dorfteich 22",
    "sg:city":"Westfehmarn",
    "sg:phone":"+49 4372/1300",
    "sg:postcode":"23769",
    "sg:province":"Schleswig-Holstein",
    "wof:name":"G\u00e4stehaus L. U. W. Widder",
    "wof:placetype":"venue"
},
  "geometry": {"coordinates":[11.0995397568,54.439781189],"type":"Point"}
}