{
  "type": "Feature",
  "properties": {
    "iso:country":"DE",
    "sg:address":"Im P\u00e4sken 10",
    "sg:city":"Dorsten",
    "sg:phone":"+49 2362/27391",
    "sg:postcode":"46282",
    "sg:province":"Nordrhein-Westfalen",
    "wof:name":"Bernd Ax Rechtsanwalt",
    "wof:placetype":"venue"
},
  "geometry": {"coordinates":[7.0114550591,51.635799408],"type":"Point"}
}