{
  "type": "Feature",
  "properties": {
    "iso:country":"DE",
    "sg:address":"M\u00fchlh\u00e4user Str. 305",
    "sg:city":"Stuttgart",
    "sg:phone":"+49 711/5302615",
    "sg:postcode":"70378",
    "sg:province":"Baden-W\u00fcrttemberg",
    "wof:name":"Vereinsgastst\u00e4tte Dlrg-heim",
    "wof:placetype":"venue"
},
  "geometry": {"coordinates":[9.218878746,48.834564209],"type":"Point"}
}