{
  "type": "Feature",
  "properties": {
    "iso:country":"DE",
    "sg:address":"Berliner Str. 53",
    "sg:city":"Leonberg",
    "sg:phone":"+49 7152/41040",
    "sg:postcode":"71229",
    "sg:province":"Baden-W\u00fcrttemberg",
    "wof:name":"R\u00f6ckle Gmbh",
    "wof:placetype":"venue"
},
  "geometry": {"coordinates":[9.017461,48.789574],"type":"Point"}
}