{
  "type": "Feature",
  "properties": {
    "iso:country":"DE",
    "sg:address":"L\u00fcpertzender Str. 76",
    "sg:city":"M\u00f6nchengladbach",
    "sg:phone":"+49 2161/16996",
    "sg:postcode":"41061",
    "sg:province":"Nordrhein-Westfalen",
    "wof:name":"Otto R\u00fcttger",
    "wof:placetype":"venue"
},
  "geometry": {"coordinates":[6.437772,51.191635],"type":"Point"}
}