{
  "type": "Feature",
  "properties": {
    "iso:country":"DE",
    "sg:address":"Bergstr. 75",
    "sg:city":"Dortmund",
    "sg:phone":"+49 231/857863",
    "sg:postcode":"44339",
    "sg:province":"Nordrhein-Westfalen",
    "wof:name":"R\u00f6mer Baubetreuung Gmbh",
    "wof:placetype":"venue"
},
  "geometry": {"coordinates":[7.4538779259,51.5517196655],"type":"Point"}
}