{
  "type": "Feature",
  "properties": {
    "iso:country":"DE",
    "sg:address":"M\u00fchlenstr. 2",
    "sg:city":"Lemwerder",
    "sg:phone":"+49 421/671514",
    "sg:postcode":"27809",
    "sg:province":"Niedersachsen",
    "wof:name":"Gebr. Wohlers Gmbh & Co.",
    "wof:placetype":"venue"
},
  "geometry": {"coordinates":[8.616768837,53.1627998352],"type":"Point"}
}