{
  "type": "Feature",
  "properties": {
    "iso:country":"DE",
    "sg:address":"Robert-Koch-Str. 22",
    "sg:city":"Wei\u00dfwasser",
    "sg:phone":"+49 3576/205532",
    "sg:postcode":"02943",
    "sg:province":"Sachsen",
    "wof:name":"Erich Feller Elektro",
    "wof:placetype":"venue"
},
  "geometry": {"coordinates":[14.655036,51.505821],"type":"Point"}
}