{
  "type": "Feature",
  "properties": {
    "iso:country":"DE",
    "sg:address":"Auelsweg 23",
    "sg:city":"Lohmar",
    "sg:phone":"+49 2246/300546",
    "sg:postcode":"53797",
    "sg:province":"Nordrhein-Westfalen",
    "wof:name":"E.h.p. Exclusive-hotel Publikationen",
    "wof:placetype":"venue"
},
  "geometry": {"coordinates":[7.2054128647,50.8356246948],"type":"Point"}
}