{
  "type": "Feature",
  "properties": {
    "iso:country":"DE",
    "sg:address":"Mozartstr. 4",
    "sg:city":"Kempten",
    "sg:phone":"+49 831/18868",
    "sg:postcode":"87435",
    "sg:province":"Bayern",
    "wof:name":"Bencker & Holzhaus",
    "wof:placetype":"venue"
},
  "geometry": {"coordinates":[10.313154,47.721725],"type":"Point"}
}