{
  "type": "Feature",
  "properties": {
    "iso:country":"DE",
    "sg:address":"Crossener Str. 1",
    "sg:city":"Wetterzeube",
    "sg:phone":"+49 6722/22210",
    "sg:postcode":"06722",
    "sg:province":"Sachsen-Anhalt",
    "wof:name":"L. Aderhold",
    "wof:placetype":"venue"
},
  "geometry": {"coordinates":[12.0065011978,51.0068244934],"type":"Point"}
}