{
  "type": "Feature",
  "properties": {
    "iso:country":"DE",
    "sg:address":"Hauser Str. 19",
    "sg:city":"Gauting",
    "sg:phone":"+49 89/8509505",
    "sg:postcode":"82131",
    "sg:province":"Bayern",
    "wof:name":"K. Weber",
    "wof:placetype":"venue"
},
  "geometry": {"coordinates":[11.3652210236,48.0572929382],"type":"Point"}
}