{
  "type": "Feature",
  "properties": {
    "iso:country":"DE",
    "sg:address":"An der Hauptstr. 9 B",
    "sg:city":"Ebersbach",
    "sg:phone":"+49 3431/613955",
    "sg:postcode":"04720",
    "sg:province":"Sachsen",
    "wof:name":"Dietmar Krause",
    "wof:placetype":"venue"
},
  "geometry": {"coordinates":[13.127661,51.098042],"type":"Point"}
}