{
  "type": "Feature",
  "properties": {
    "iso:country":"DE",
    "sg:address":"Im Gewerbepark 29",
    "sg:city":"Regensburg",
    "sg:phone":"+49 941/400021",
    "sg:postcode":"93059",
    "sg:province":"Bayern",
    "wof:name":"Bernhard Branekow Rechtsanwalt",
    "wof:placetype":"venue"
},
  "geometry": {"coordinates":[12.1271057129,49.0320549011],"type":"Point"}
}