{
  "type": "Feature",
  "properties": {
    "iso:country":"DE",
    "sg:address":"Sunderweg 8",
    "sg:city":"Bielefeld",
    "sg:phone":"+49 521/447060",
    "sg:postcode":"33649",
    "sg:province":"Nordrhein-Westfalen",
    "wof:name":"Willms & M\u00f6nnig Gmbh",
    "wof:placetype":"venue"
},
  "geometry": {"coordinates":[8.4913816452,51.9792900085],"type":"Point"}
}