{
  "type": "Feature",
  "properties": {
    "iso:country":"DE",
    "sg:address":"Im Sieringhoek 16",
    "sg:city":"Bad Bentheim",
    "sg:phone":"+49 5924/1684",
    "sg:postcode":"48455",
    "sg:province":"Niedersachsen",
    "wof:name":"Heinrich Hindriksherm",
    "wof:placetype":"venue"
},
  "geometry": {"coordinates":[7.140365,52.28484],"type":"Point"}
}