{
  "type": "Feature",
  "properties": {
    "iso:country":"DE",
    "sg:address":"Johann-Carl-Fuhlrott-Str. 72",
    "sg:city":"Leinefelde",
    "sg:phone":"+49 3605/2219",
    "sg:postcode":"37327",
    "sg:province":"Th\u00fcringen",
    "wof:name":"Remekasten",
    "wof:placetype":"venue"
},
  "geometry": {"coordinates":[10.3166704178,51.3880805969],"type":"Point"}
}