{
  "type": "Feature",
  "properties": {
    "iso:country":"DE",
    "sg:address":"Niedwiesenstr. 35",
    "sg:city":"Frankfurt",
    "sg:phone":"+49 69/512747",
    "sg:postcode":"60431",
    "sg:province":"Hessen",
    "wof:name":"August M\u00fcller",
    "wof:placetype":"venue"
},
  "geometry": {"coordinates":[8.6521530151,50.1560974121],"type":"Point"}
}