{
  "type": "Feature",
  "properties": {
    "iso:country":"DE",
    "sg:address":"Altst\u00e4dter Str. 9",
    "sg:city":"Rottweil",
    "sg:phone":"+49 741/2042",
    "sg:postcode":"78628",
    "sg:province":"Baden-W\u00fcrttemberg",
    "wof:name":"Rottweiler Privatbrauerei Wilhelm Mayer",
    "wof:placetype":"venue"
},
  "geometry": {"coordinates":[8.633272,48.160309],"type":"Point"}
}