{
  "type": "Feature",
  "properties": {
    "iso:country":"DE",
    "sg:address":"Am Sybillenstein 29",
    "sg:city":"Alzey",
    "sg:phone":"+49 4967/3141875",
    "sg:postcode":"55232",
    "sg:province":"Rheinland-Pfalz",
    "wof:name":"Willy Frey Gmbh",
    "wof:placetype":"venue"
},
  "geometry": {"coordinates":[8.062675,49.737198],"type":"Point"}
}