{
  "type": "Feature",
  "properties": {
    "iso:country":"DE",
    "sg:address":"Am Markt 6",
    "sg:city":"Storkow",
    "sg:postcode":"15859",
    "sg:province":"Brandenburg",
    "wof:name":"Pro Delikatesse Handelsges. F\u00fcr Feinkost U. Catering Gmbh",
    "wof:placetype":"venue"
},
  "geometry": {"coordinates":[13.9315519333,52.2546310425],"type":"Point"}
}