{
  "type": "Feature",
  "properties": {
    "iso:country":"DE",
    "sg:address":"Konrad-Adenauer-Str. 126",
    "sg:city":"Stolberg",
    "sg:phone":"+49 2402/25134",
    "sg:postcode":"52223",
    "sg:province":"Nordrhein-Westfalen",
    "wof:name":"Erasmus Moden",
    "wof:placetype":"venue"
},
  "geometry": {"coordinates":[6.216355,50.756092],"type":"Point"}
}