{
  "type": "Feature",
  "properties": {
    "iso:country":"DE",
    "sg:address":"Grambeker Weg 7",
    "sg:city":"M\u00f6lln",
    "sg:phone":"+49 4542/841287",
    "sg:postcode":"23879",
    "sg:province":"Schleswig-Holstein",
    "wof:name":"Zoo- Und Gartenmarkt Gmbh",
    "wof:placetype":"venue"
},
  "geometry": {"coordinates":[10.682635,53.623016],"type":"Point"}
}