{
  "type": "Feature",
  "properties": {
    "iso:country":"DE",
    "sg:address":"Hammer Deich 26-34",
    "sg:city":"Hamburg",
    "sg:phone":"+49 40/8512222",
    "sg:postcode":"20537",
    "sg:province":"Hamburg",
    "wof:name":"S\u00f6ffge Thermographie Gmbh",
    "wof:placetype":"venue"
},
  "geometry": {"coordinates":[10.0431890488,53.5467720032],"type":"Point"}
}