{
  "type": "Feature",
  "properties": {
    "iso:country":"DE",
    "sg:address":"Reichartsh\u00e4user Str. 20",
    "sg:city":"Schwarzach",
    "sg:phone":"+49 6262/1234",
    "sg:postcode":"74869",
    "sg:province":"Baden-W\u00fcrttemberg",
    "wof:name":"Manfred Frey Ingenieur",
    "wof:placetype":"venue"
},
  "geometry": {"coordinates":[8.979663,49.36927],"type":"Point"}
}