{
  "type": "Feature",
  "properties": {
    "iso:country":"DE",
    "sg:address":"Kleinschwand 45",
    "sg:city":"T\u00e4nnesberg",
    "sg:phone":"+49 9655/565",
    "sg:postcode":"92723",
    "sg:province":"Bayern",
    "wof:name":"Pension Heide",
    "wof:placetype":"venue"
},
  "geometry": {"coordinates":[12.3343858719,49.5567512512],"type":"Point"}
}