{
  "type": "Feature",
  "properties": {
    "iso:country":"DE",
    "sg:address":"Marktstr. 30",
    "sg:city":"Kobern-Gondorf",
    "sg:phone":"+49 2607/238",
    "sg:postcode":"56330",
    "sg:province":"Rheinland-Pfalz",
    "wof:name":"Restaurant M. Schwab",
    "wof:placetype":"venue"
},
  "geometry": {"coordinates":[7.4603981972,50.3123130798],"type":"Point"}
}