{
  "type": "Feature",
  "properties": {
    "iso:country":"DE",
    "sg:address":"Schulstr. 47",
    "sg:city":"Hattersheim",
    "sg:phone":"+49 6190/890200",
    "sg:postcode":"65795",
    "sg:province":"Hessen",
    "wof:name":"Verlag Von Graberg & G\u00d6rg Gmbh",
    "wof:placetype":"venue"
},
  "geometry": {"coordinates":[8.4809799194,50.064540863],"type":"Point"}
}