{
  "type": "Feature",
  "properties": {
    "iso:country":"DE",
    "sg:address":"Eichetstr. 31",
    "sg:city":"Neuburg",
    "sg:phone":"+49 8502/8586",
    "sg:postcode":"94127",
    "sg:province":"Bayern",
    "wof:name":"Bernd Mitschelen Architekt",
    "wof:placetype":"venue"
},
  "geometry": {"coordinates":[13.359107,48.525841],"type":"Point"}
}