{
  "type": "Feature",
  "properties": {
    "iso:country":"DE",
    "sg:address":"Bonifaz-Reile-Weg 2",
    "sg:city":"Bad W\u00f6rishofen",
    "sg:phone":"+49 8247/5177",
    "sg:postcode":"86825",
    "sg:province":"Bayern",
    "wof:name":"Margarete Last & Co",
    "wof:placetype":"venue"
},
  "geometry": {"coordinates":[10.594191,48.005947],"type":"Point"}
}