{
  "type": "Feature",
  "properties": {
    "iso:country":"DE",
    "sg:address":"Poststr. 48",
    "sg:city":"Ratingen",
    "sg:phone":"+49 2102/23952",
    "sg:postcode":"40878",
    "sg:province":"Nordrhein-Westfalen",
    "wof:name":"Johann Oberbanscheidt",
    "wof:placetype":"venue"
},
  "geometry": {"coordinates":[6.857806,51.295696],"type":"Point"}
}