{
  "type": "Feature",
  "properties": {
    "iso:country":"DE",
    "sg:address":"Goldgrube 4",
    "sg:city":"Windesheim",
    "sg:phone":"+49 6707/8287",
    "sg:postcode":"55452",
    "sg:province":"Rheinland-Pfalz",
    "wof:name":"R. Schumacher",
    "wof:placetype":"venue"
},
  "geometry": {"coordinates":[7.8191819191,49.9074935913],"type":"Point"}
}