{
  "type": "Feature",
  "properties": {
    "iso:country":"DE",
    "sg:address":"Schweigelstr. 23",
    "sg:city":"Rheinbach",
    "sg:phone":"+49 2226/92580",
    "sg:postcode":"53359",
    "sg:province":"Nordrhein-Westfalen",
    "wof:name":"Jugendwohnheim Haus Rheinbach Gmbh",
    "wof:placetype":"venue"
},
  "geometry": {"coordinates":[6.950026989,50.6279830933],"type":"Point"}
}