{
  "type": "Feature",
  "properties": {
    "iso:country":"DE",
    "sg:address":"Eichenallee 12",
    "sg:city":"Seevetal",
    "sg:phone":"+49 4105/84877",
    "sg:postcode":"21220",
    "sg:province":"Niedersachsen",
    "wof:name":"A. Zars",
    "wof:placetype":"venue"
},
  "geometry": {"coordinates":[10.0404434204,53.3921508789],"type":"Point"}
}