{
  "type": "Feature",
  "properties": {
    "iso:country":"DE",
    "sg:address":"M\u00f6nchr\u00f6dener Strasse 13",
    "sg:city":"R\u00f6dental",
    "sg:phone":"+49 4975/41770",
    "sg:postcode":"96472",
    "sg:province":"Bayern",
    "wof:name":"Zf Friedrichshafen Ag",
    "wof:placetype":"venue"
},
  "geometry": {"coordinates":[9.4942646027,47.6661224365],"type":"Point"}
}