{
  "type": "Feature",
  "properties": {
    "iso:country":"DE",
    "sg:address":"Waldaustr. 3",
    "sg:city":"N\u00fcrnberg",
    "sg:phone":"+49 911/662392",
    "sg:postcode":"90441",
    "sg:province":"Bayern",
    "wof:name":"Gustav Bach",
    "wof:placetype":"venue"
},
  "geometry": {"coordinates":[11.054147,49.433773],"type":"Point"}
}