{
  "type": "Feature",
  "properties": {
    "iso:country":"DE",
    "sg:address":"Haselbach",
    "sg:city":"Aschau",
    "sg:phone":"+49 8638/4746",
    "sg:postcode":"84544",
    "sg:province":"Bayern",
    "wof:name":"Monis Bierst\u00fcberl Inh. Monika Schnetzer",
    "wof:placetype":"venue"
},
  "geometry": {"coordinates":[12.3753499985,48.217540741],"type":"Point"}
}