{
  "type": "Feature",
  "properties": {
    "iso:country":"DE",
    "sg:address":"Hasenmoorer Str. 6",
    "sg:city":"Bim\u00f6hlen",
    "sg:phone":"+49 4192/7805",
    "sg:postcode":"24576",
    "sg:province":"Schleswig-Holstein",
    "wof:name":"Hans-otto Humfeldt",
    "wof:placetype":"venue"
},
  "geometry": {"coordinates":[9.951687,53.933666],"type":"Point"}
}