{
  "type": "Feature",
  "properties": {
    "iso:country":"DE",
    "sg:address":"Stimbergstr. 177",
    "sg:city":"Oer-Erkenschwick",
    "sg:phone":"+49 2368/53884",
    "sg:postcode":"45739",
    "sg:province":"Nordrhein-Westfalen",
    "wof:name":"Sphinx Spielhallenbetriebs Gmbh",
    "wof:placetype":"venue"
},
  "geometry": {"coordinates":[7.25674,51.64402],"type":"Point"}
}