{
  "type": "Feature",
  "properties": {
    "iso:country":"DE",
    "sg:address":"Obergraben 2",
    "sg:city":"L\u00f6\u00dfnitz",
    "sg:phone":"+49 3771/33010",
    "sg:postcode":"08294",
    "sg:province":"Sachsen",
    "wof:name":"G. Ficker Immobilienmakler",
    "wof:placetype":"venue"
},
  "geometry": {"coordinates":[12.7341327667,50.6226425171],"type":"Point"}
}