{
  "type": "Feature",
  "properties": {
    "iso:country":"DE",
    "sg:address":"Landsknechtsweg 3",
    "sg:city":"Lauterbach",
    "sg:phone":"+49 6641/919090",
    "sg:postcode":"36341",
    "sg:province":"Hessen",
    "wof:name":"Friedel",
    "wof:placetype":"venue"
},
  "geometry": {"coordinates":[9.3983297348,50.6374740601],"type":"Point"}
}