{
  "type": "Feature",
  "properties": {
    "iso:country":"DE",
    "sg:address":"Theodor-Storm-Str. 16 a",
    "sg:city":"Kolbermoor",
    "sg:phone":"+49 8031/91654",
    "sg:postcode":"83059",
    "sg:province":"Bayern",
    "wof:name":"Gerhard Wolf",
    "wof:placetype":"venue"
},
  "geometry": {"coordinates":[12.0544691086,47.8606185913],"type":"Point"}
}