{
  "type": "Feature",
  "properties": {
    "iso:country":"DE",
    "sg:address":"Potsdamer Platz 1",
    "sg:city":"Berlin",
    "sg:postcode":"10785",
    "sg:province":"Berlin",
    "wof:name":"Magna Park Germany Gmbh & Co. Kg",
    "wof:placetype":"venue"
},
  "geometry": {"coordinates":[13.3747663498,52.5091629028],"type":"Point"}
}