{
  "type": "Feature",
  "properties": {
    "iso:country":"DE",
    "sg:address":"Am Jagdstock 37",
    "sg:city":"Landau",
    "sg:phone":"+49 6341/30390",
    "sg:postcode":"76829",
    "sg:province":"Rheinland-Pfalz",
    "wof:name":"Richard Mohrbach",
    "wof:placetype":"venue"
},
  "geometry": {"coordinates":[8.0890073776,49.1946258545],"type":"Point"}
}