{
  "type": "Feature",
  "properties": {
    "iso:country":"DE",
    "sg:address":"D\u00fcrerstr. 19",
    "sg:city":"Velbert",
    "sg:phone":"+49 2051/55259",
    "sg:postcode":"42549",
    "sg:province":"Nordrhein-Westfalen",
    "wof:name":"J\u00fcrgen Konrad",
    "wof:placetype":"venue"
},
  "geometry": {"coordinates":[7.0399370193,51.3393173218],"type":"Point"}
}