{
  "type": "Feature",
  "properties": {
    "iso:country":"DE",
    "sg:address":"Industriestr. 6",
    "sg:city":"Schenefeld",
    "sg:phone":"+49 40/8393700",
    "sg:postcode":"22869",
    "sg:province":"Schleswig-Holstein",
    "wof:name":"Draht-grimm",
    "wof:placetype":"venue"
},
  "geometry": {"coordinates":[9.8384923935,53.6009483337],"type":"Point"}
}