{
  "type": "Feature",
  "properties": {
    "iso:country":"DE",
    "sg:address":"Friedrichstr. 12",
    "sg:city":"Bad S\u00e4ckingen",
    "sg:phone":"+49 7761/7416",
    "sg:postcode":"79713",
    "sg:province":"Baden-W\u00fcrttemberg",
    "wof:name":"Oskar Meisch",
    "wof:placetype":"venue"
},
  "geometry": {"coordinates":[7.941025,47.55489],"type":"Point"}
}