{
  "type": "Feature",
  "properties": {
    "iso:country":"DE",
    "sg:address":"Franckstr. 5",
    "sg:city":"Ludwigsburg",
    "sg:phone":"+49 7141/1270",
    "sg:postcode":"71636",
    "sg:province":"Baden-W\u00fcrttemberg",
    "wof:name":"Maggi Gmbh Werbegeschenk-hdl.",
    "wof:placetype":"venue"
},
  "geometry": {"coordinates":[9.1847457886,48.8907432556],"type":"Point"}
}