{
  "type": "Feature",
  "properties": {
    "iso:country":"DE",
    "sg:address":"Am Marschallfeld 17",
    "sg:city":"Valley",
    "sg:phone":"+49 8024/6400",
    "sg:postcode":"83626",
    "sg:province":"Bayern",
    "wof:name":"Data M Engineering Gmbh",
    "wof:placetype":"venue"
},
  "geometry": {"coordinates":[11.731423378,47.8762931824],"type":"Point"}
}