{
  "type": "Feature",
  "properties": {
    "iso:country":"DE",
    "sg:address":"Holtorfsloher Str. 4 A",
    "sg:city":"Seevetal",
    "sg:postcode":"21220",
    "sg:province":"Niedersachsen",
    "wof:name":"Immotrust Gmbh",
    "wof:placetype":"venue"
},
  "geometry": {"coordinates":[10.0523700714,53.3403892517],"type":"Point"}
}