{
  "type": "Feature",
  "properties": {
    "iso:country":"DE",
    "sg:address":"Friedhofstr. 11",
    "sg:city":"Hochstadt",
    "sg:phone":"+49 6347/1383",
    "sg:postcode":"76879",
    "sg:province":"Rheinland-Pfalz",
    "wof:name":"Fritz Sauerbrunn",
    "wof:placetype":"venue"
},
  "geometry": {"coordinates":[8.2224369049,49.2426834106],"type":"Point"}
}