{
  "type": "Feature",
  "properties": {
    "iso:country":"DE",
    "sg:address":"Brede 2",
    "sg:city":"Porta Westfalica",
    "sg:phone":"+49 571/70171",
    "sg:postcode":"32457",
    "sg:province":"Nordrhein-Westfalen",
    "wof:name":"Wolfgang Wiedermann Architekt",
    "wof:placetype":"venue"
},
  "geometry": {"coordinates":[8.871235,52.227016],"type":"Point"}
}