{
  "type": "Feature",
  "properties": {
    "iso:country":"DE",
    "sg:address":"M\u00fchlenkamp 1",
    "sg:city":"Barsbek",
    "sg:phone":"+49 4344/6108",
    "sg:postcode":"24217",
    "sg:province":"Schleswig-Holstein",
    "wof:name":"Werk- Und Lebensgemeinschaft E. V.",
    "wof:placetype":"venue"
},
  "geometry": {"coordinates":[10.3320999146,54.4049682617],"type":"Point"}
}