{
  "type": "Feature",
  "properties": {
    "iso:country":"DE",
    "sg:address":"Rathausstr. 28",
    "sg:city":"Viernheim",
    "sg:phone":"+49 6204/2271",
    "sg:postcode":"68519",
    "sg:province":"Hessen",
    "wof:name":"Textilhaus Haas Inh. Wolfgang Haas",
    "wof:placetype":"venue"
},
  "geometry": {"coordinates":[8.5792808533,49.5377082825],"type":"Point"}
}