{
  "type": "Feature",
  "properties": {
    "iso:country":"DE",
    "sg:address":"Riedstr. 2",
    "sg:city":"Steinheim",
    "sg:phone":"+49 4973/29970",
    "sg:postcode":"89555",
    "sg:province":"Baden-W\u00fcrttemberg",
    "wof:name":"Sigma-aldrich Chemie Gmbh",
    "wof:placetype":"venue"
},
  "geometry": {"coordinates":[10.076433,48.688332],"type":"Point"}
}