{
  "type": "Feature",
  "properties": {
    "iso:country":"DE",
    "sg:address":"Breitwasserweg 8",
    "sg:city":"Nesse",
    "sg:postcode":"26553",
    "sg:province":"Niedersachsen",
    "wof:name":"Grevenrath Kg",
    "wof:placetype":"venue"
},
  "geometry": {"coordinates":[7.378608,53.652447],"type":"Point"}
}