{
  "type": "Feature",
  "properties": {
    "iso:country":"DE",
    "sg:address":"Harpendorfer Weg 5 a",
    "sg:city":"Steinfeld",
    "sg:phone":"+49 5492/981246",
    "sg:postcode":"49439",
    "sg:province":"Niedersachsen",
    "wof:name":"Martin Klostermann",
    "wof:placetype":"venue"
},
  "geometry": {"coordinates":[8.179622,52.598885],"type":"Point"}
}