{
  "type": "Feature",
  "properties": {
    "iso:country":"DE",
    "sg:address":"Hainstr. 139",
    "sg:city":"Chemnitz",
    "sg:phone":"+49 371/4025396",
    "sg:postcode":"09130",
    "sg:province":"Sachsen",
    "wof:name":"Andreas Teubner Rechtsanwalt",
    "wof:placetype":"venue"
},
  "geometry": {"coordinates":[12.941280365,50.8448219299],"type":"Point"}
}