{
  "type": "Feature",
  "properties": {
    "iso:country":"DE",
    "sg:address":"Friedbergstr. 23",
    "sg:city":"Berlin",
    "sg:postcode":"14057",
    "sg:province":"Berlin",
    "wof:name":"Axtheim Und H. J. Kawski Architekten",
    "wof:placetype":"venue"
},
  "geometry": {"coordinates":[13.2946538925,52.5039749146],"type":"Point"}
}