{
  "type": "Feature",
  "properties": {
    "iso:country":"DE",
    "sg:city":"Altenmedingen",
    "sg:phone":"+49 5807/555",
    "sg:postcode":"29575",
    "sg:province":"Niedersachsen",
    "wof:name":"Karl-heinz Kemmer",
    "wof:placetype":"venue"
},
  "geometry": {"coordinates":[10.601549,53.130333],"type":"Point"}
}