{
  "type": "Feature",
  "properties": {
    "iso:country":"DE",
    "sg:address":"Moselstr. 9",
    "sg:city":"Kesten",
    "sg:phone":"+49 6535/308",
    "sg:postcode":"54518",
    "sg:province":"Rheinland-Pfalz",
    "wof:name":"V. Zimmer",
    "wof:placetype":"venue"
},
  "geometry": {"coordinates":[6.9571647644,49.9017944336],"type":"Point"}
}