{
  "type": "Feature",
  "properties": {
    "iso:country":"DE",
    "sg:address":"Alt Fr\u00f6sleer Weg 46",
    "sg:city":"Harrislee",
    "sg:phone":"+49 461/72100",
    "sg:postcode":"24955",
    "sg:province":"Schleswig-Holstein",
    "wof:name":"Otto Jessen",
    "wof:placetype":"venue"
},
  "geometry": {"coordinates":[9.3915605545,54.8083724976],"type":"Point"}
}