{
  "type": "Feature",
  "properties": {
    "iso:country":"DE",
    "sg:address":"Kilstetter Str. 16",
    "sg:city":"Berlin",
    "sg:phone":"+49 30/8111511",
    "sg:postcode":"14167",
    "sg:province":"Berlin",
    "wof:name":"Siegfried Messedat",
    "wof:placetype":"venue"
},
  "geometry": {"coordinates":[13.2742919922,52.4345397949],"type":"Point"}
}