{
  "type": "Feature",
  "properties": {
    "iso:country":"DE",
    "sg:address":"Im \u00c4uelchen 9",
    "sg:city":"Bonn",
    "sg:phone":"+49 228/351144",
    "sg:postcode":"53177",
    "sg:province":"Nordrhein-Westfalen",
    "wof:name":"Casa Rustica Trattoria",
    "wof:placetype":"venue"
},
  "geometry": {"coordinates":[7.1500039101,50.6815948486],"type":"Point"}
}