{
  "type": "Feature",
  "properties": {
    "iso:country":"DE",
    "sg:address":"Adrianstr. 149",
    "sg:city":"Bonn",
    "sg:phone":"+49 228/443122",
    "sg:postcode":"53227",
    "sg:province":"Nordrhein-Westfalen",
    "wof:name":"Hans F. H\u00fcbel Architekt",
    "wof:placetype":"venue"
},
  "geometry": {"coordinates":[7.169255,50.71299],"type":"Point"}
}