{
  "type": "Feature",
  "properties": {
    "iso:country":"DE",
    "sg:address":"Otto-Buchwitz-Platz 2",
    "sg:city":"G\u00f6rlitz",
    "sg:phone":"+49 3581/402687",
    "sg:postcode":"02826",
    "sg:province":"Sachsen",
    "wof:name":"Scheinpflug Rehatechnik",
    "wof:placetype":"venue"
},
  "geometry": {"coordinates":[14.9827747345,51.1527175903],"type":"Point"}
}