{
  "type": "Feature",
  "properties": {
    "iso:country":"DE",
    "sg:address":"Peterstr. 31",
    "sg:city":"Bad Zwischenahn",
    "sg:phone":"+49 4403/2542",
    "sg:postcode":"26160",
    "sg:province":"Niedersachsen",
    "wof:name":"Lieselotte Hillje Inh. Herbert Hillje",
    "wof:placetype":"venue"
},
  "geometry": {"coordinates":[8.007458,53.183769],"type":"Point"}
}