{
  "type": "Feature",
  "properties": {
    "iso:country":"DE",
    "sg:address":"Mainzer Str. 62",
    "sg:city":"Saarbr\u00fccken",
    "sg:phone":"+49 681/9681760",
    "sg:postcode":"66121",
    "sg:province":"Saarland",
    "wof:name":"M 3 Management F\u00fcr Bau B\u00fcro Haus Gmbh",
    "wof:placetype":"venue"
},
  "geometry": {"coordinates":[7.004942894,49.2303276062],"type":"Point"}
}