{
  "type": "Feature",
  "properties": {
    "iso:country":"DE",
    "sg:address":"Pfitznerstr. 8a",
    "sg:city":"M\u00fcnchen",
    "sg:phone":"+49 89/3595478",
    "sg:postcode":"80807",
    "sg:province":"Bayern",
    "wof:name":"Uta Hein",
    "wof:placetype":"venue"
},
  "geometry": {"coordinates":[11.573955,48.183357],"type":"Point"}
}