{
  "type": "Feature",
  "properties": {
    "iso:country":"DE",
    "sg:address":"Am Anger 7",
    "sg:city":"Seebruck",
    "sg:phone":"+49 8667/402",
    "sg:postcode":"83358",
    "sg:province":"Bayern",
    "wof:name":"Master Versicherungsdienst Ohg",
    "wof:placetype":"venue"
},
  "geometry": {"coordinates":[12.4734706879,47.9345054626],"type":"Point"}
}