{
  "type": "Feature",
  "properties": {
    "iso:country":"DE",
    "sg:address":"An Den R\u00f6then 4",
    "sg:city":"Meiningen",
    "sg:phone":"+49 4938/203576",
    "sg:postcode":"98617",
    "sg:province":"Th\u00fcringen",
    "wof:name":"Landwirtschaftsberatung Mecklenburg-vorpommern Gmbh",
    "wof:placetype":"venue"
},
  "geometry": {"coordinates":[11.891097,54.108776],"type":"Point"}
}