{
  "type": "Feature",
  "properties": {
    "iso:country":"DE",
    "sg:address":"Schmithofer Str. 202",
    "sg:city":"Aachen",
    "sg:phone":"+49 2408/7217",
    "sg:postcode":"52076",
    "sg:province":"Nordrhein-Westfalen",
    "wof:name":"Kath. Pfarramt St. Josef",
    "wof:placetype":"venue"
},
  "geometry": {"coordinates":[6.1620941162,50.6941871643],"type":"Point"}
}