{
  "type": "Feature",
  "properties": {
    "iso:country":"DE",
    "sg:address":"Braunsbacher Str. 24",
    "sg:city":"F\u00fcrth",
    "sg:phone":"+49 911/302304",
    "sg:postcode":"90765",
    "sg:province":"Bayern",
    "wof:name":"Karl Hetzner Gmbh",
    "wof:placetype":"venue"
},
  "geometry": {"coordinates":[11.019602,49.502697],"type":"Point"}
}