{
  "type": "Feature",
  "properties": {
    "iso:country":"DE",
    "sg:address":"Hauptstr. 156",
    "sg:city":"Westoverledingen",
    "sg:phone":"+49 4961/4913",
    "sg:postcode":"26810",
    "sg:province":"Niedersachsen",
    "wof:name":"Hermann Metz",
    "wof:placetype":"venue"
},
  "geometry": {"coordinates":[7.410093,53.094139],"type":"Point"}
}