{
  "type": "Feature",
  "properties": {
    "iso:country":"DE",
    "sg:address":"Eckdorfer Str. 8",
    "sg:city":"K\u00f6ln",
    "sg:postcode":"50968",
    "sg:province":"Nordrhein-Westfalen",
    "wof:name":"Blind Vision Media-produktions Gmbh",
    "wof:placetype":"venue"
},
  "geometry": {"coordinates":[6.9554028511,50.8946037292],"type":"Point"}
}