{
  "type": "Feature",
  "properties": {
    "iso:country":"DE",
    "sg:address":"Zum Rhein 1",
    "sg:city":"Rheinberg",
    "sg:phone":"+49 2843/2295",
    "sg:postcode":"47495",
    "sg:province":"Nordrhein-Westfalen",
    "wof:name":"Gr\u00fcnthal Gmbh",
    "wof:placetype":"venue"
},
  "geometry": {"coordinates":[6.6583971977,51.5472793579],"type":"Point"}
}