{
  "type": "Feature",
  "properties": {
    "iso:country":"DE",
    "sg:address":"Erbacher Str. 62",
    "sg:city":"F\u00fcrth",
    "sg:phone":"+49 6253/932144",
    "sg:postcode":"64658",
    "sg:province":"Hessen",
    "wof:name":"G\u00fcnther Schmitt Gmbh",
    "wof:placetype":"venue"
},
  "geometry": {"coordinates":[8.7862100601,49.6551094055],"type":"Point"}
}