{
  "type": "Feature",
  "properties": {
    "iso:country":"DE",
    "sg:address":"Hesseweg 5",
    "sg:city":"Herbrechtingen",
    "sg:phone":"+49 7324/919386",
    "sg:postcode":"89542",
    "sg:province":"Baden-W\u00fcrttemberg",
    "wof:name":"Josef Stetter",
    "wof:placetype":"venue"
},
  "geometry": {"coordinates":[10.1841001511,48.6198959351],"type":"Point"}
}