{
  "type": "Feature",
  "properties": {
    "iso:country":"DE",
    "sg:address":"Krempermarsch",
    "sg:city":"Bahrenfleth",
    "sg:phone":"+49 4824/926",
    "sg:postcode":"25569",
    "sg:province":"Schleswig-Holstein",
    "wof:name":"Schmidt",
    "wof:placetype":"venue"
},
  "geometry": {"coordinates":[9.4399051666,53.8712692261],"type":"Point"}
}