{
  "type": "Feature",
  "properties": {
    "iso:country":"DE",
    "sg:address":"Haagener Str 3",
    "sg:city":"L\u00f6rrach",
    "sg:phone":"+49 7621/403390",
    "sg:postcode":"79539",
    "sg:province":"Baden-W\u00fcrttemberg",
    "wof:name":"S\u00fcdwestdruck Gmbh",
    "wof:placetype":"venue"
},
  "geometry": {"coordinates":[7.6613130569,47.6150741577],"type":"Point"}
}