{
  "type": "Feature",
  "properties": {
    "iso:country":"DE",
    "sg:address":"Fruchtschuppenstr. 19",
    "sg:city":"Zweibr\u00fccken",
    "sg:phone":"+49 4963/323229",
    "sg:postcode":"66482",
    "sg:province":"Rheinland-Pfalz",
    "wof:name":"Schneider Holzbearbeitung Gmbh",
    "wof:placetype":"venue"
},
  "geometry": {"coordinates":[7.358039856,49.2469978333],"type":"Point"}
}