{
  "type": "Feature",
  "properties": {
    "iso:country":"DE",
    "sg:address":"Stadtrodaer Str. 60",
    "sg:city":"Jena",
    "sg:phone":"+49 3641/334770",
    "sg:postcode":"07747",
    "sg:province":"Th\u00fcringen",
    "wof:name":"G\u00c4rtnerei Boock Ohg",
    "wof:placetype":"venue"
},
  "geometry": {"coordinates":[11.621865,50.8778],"type":"Point"}
}