{
  "type": "Feature",
  "properties": {
    "iso:country":"DE",
    "sg:address":"M\u00fchlstr. 2",
    "sg:city":"Oettingen",
    "sg:phone":"+49 9082/2658",
    "sg:postcode":"86732",
    "sg:province":"Bayern",
    "wof:name":"Rose",
    "wof:placetype":"venue"
},
  "geometry": {"coordinates":[10.6063251495,48.9565925598],"type":"Point"}
}