{
  "type": "Feature",
  "properties": {
    "iso:country":"DE",
    "sg:address":"Tarostr. 1",
    "sg:city":"Leipzig",
    "sg:phone":"+49 341/2214385",
    "sg:postcode":"04103",
    "sg:province":"Sachsen",
    "wof:name":"Olaf Siegmund",
    "wof:placetype":"venue"
},
  "geometry": {"coordinates":[12.38741,51.325096],"type":"Point"}
}