{
  "type": "Feature",
  "properties": {
    "iso:country":"DE",
    "sg:address":"Goethestr. 2",
    "sg:city":"Achim",
    "sg:phone":"+49 4202/81747",
    "sg:postcode":"28832",
    "sg:province":"Niedersachsen",
    "wof:name":"Margret Zegula",
    "wof:placetype":"venue"
},
  "geometry": {"coordinates":[9.032531,53.014961],"type":"Point"}
}