{
  "type": "Feature",
  "properties": {
    "iso:country":"DE",
    "sg:address":"Bahnhofstr. 68",
    "sg:city":"Schweich",
    "sg:phone":"+49 6502/4848",
    "sg:postcode":"54338",
    "sg:province":"Rheinland-Pfalz",
    "wof:name":"Horst Greisler Gmbh",
    "wof:placetype":"venue"
},
  "geometry": {"coordinates":[6.744294,49.826836],"type":"Point"}
}