{
  "type": "Feature",
  "properties": {
    "iso:country":"DE",
    "sg:address":"Auf'm Wettsche 8",
    "sg:city":"D\u00fcsseldorf",
    "sg:phone":"+49 211/7590928",
    "sg:postcode":"40589",
    "sg:province":"Nordrhein-Westfalen",
    "wof:name":"Franz Schmitz",
    "wof:placetype":"venue"
},
  "geometry": {"coordinates":[6.813025,51.169285],"type":"Point"}
}