{
  "type": "Feature",
  "properties": {
    "iso:country":"DE",
    "sg:address":"Volmestr. 101",
    "sg:city":"L\u00fcdenscheid",
    "sg:phone":"+49 2351/79843",
    "sg:postcode":"58515",
    "sg:province":"Nordrhein-Westfalen",
    "wof:name":"S. Zaharoglu",
    "wof:placetype":"venue"
},
  "geometry": {"coordinates":[7.5676288605,51.2094230652],"type":"Point"}
}