{
  "type": "Feature",
  "properties": {
    "iso:country":"DE",
    "sg:address":"Am Mayenberg 28",
    "sg:city":"Bad Herrenalb",
    "sg:phone":"+49 7083/8566",
    "sg:postcode":"76332",
    "sg:province":"Baden-W\u00fcrttemberg",
    "wof:name":"Bim Kemi Gmbh",
    "wof:placetype":"venue"
},
  "geometry": {"coordinates":[8.4396400452,48.7972488403],"type":"Point"}
}