{
  "type": "Feature",
  "properties": {
    "iso:country":"DE",
    "sg:address":"Wieslocher Str. 9",
    "sg:city":"Rauenberg",
    "sg:phone":"+49 6222/661595",
    "sg:postcode":"69231",
    "sg:province":"Baden-W\u00fcrttemberg",
    "wof:name":"Lamm",
    "wof:placetype":"venue"
},
  "geometry": {"coordinates":[8.7043018341,49.2666702271],"type":"Point"}
}