{
  "type": "Feature",
  "properties": {
    "iso:country":"DE",
    "sg:address":"Lothringer Str. 12",
    "sg:city":"Oberhausen",
    "sg:phone":"+49 208/23322",
    "sg:postcode":"46045",
    "sg:province":"Nordrhein-Westfalen",
    "wof:name":"Dr. Karl-otto H\u00fctter",
    "wof:placetype":"venue"
},
  "geometry": {"coordinates":[6.8534650803,51.4679527283],"type":"Point"}
}