{
  "type": "Feature",
  "properties": {
    "iso:country":"DE",
    "sg:address":"Hartwicusstr. 11 b",
    "sg:city":"Hamburg",
    "sg:phone":"+49 40/22717390",
    "sg:postcode":"22087",
    "sg:province":"Hamburg",
    "wof:name":"Karl-heinz Baumann",
    "wof:placetype":"venue"
},
  "geometry": {"coordinates":[10.0216264725,53.5661697388],"type":"Point"}
}