{
  "type": "Feature",
  "properties": {
    "iso:country":"DE",
    "sg:address":"Brunnenplatz 10",
    "sg:city":"Dieskau",
    "sg:phone":"+49 345/5800956",
    "sg:postcode":"06184",
    "sg:province":"Sachsen-Anhalt",
    "wof:name":"B. Schmeling",
    "wof:placetype":"venue"
},
  "geometry": {"coordinates":[12.0406045914,51.4344291687],"type":"Point"}
}