{
  "type": "Feature",
  "properties": {
    "iso:country":"DE",
    "sg:address":"Rudolf-Diesel-Str. 4",
    "sg:city":"Stade",
    "sg:phone":"+49 4141/46873",
    "sg:postcode":"21684",
    "sg:province":"Niedersachsen",
    "wof:name":"Elbe-hydraulik In Stade Gmbh",
    "wof:placetype":"venue"
},
  "geometry": {"coordinates":[9.4920043945,53.579284668],"type":"Point"}
}