{
  "type": "Feature",
  "properties": {
    "iso:country":"DE",
    "sg:address":"Hauptstrasse 1",
    "sg:city":"Staufen i. Br.",
    "sg:postcode":"79219",
    "sg:province":"Baden-W\u00fcrttemberg",
    "wof:name":"Cascade Medienproduktions- Und Vertriebs Gmbh",
    "wof:placetype":"venue"
},
  "geometry": {"coordinates":[7.730853,47.883976],"type":"Point"}
}