{
  "type": "Feature",
  "properties": {
    "iso:country":"DE",
    "sg:address":"Ankerweg 1a",
    "sg:city":"Waltrop",
    "sg:phone":"+49 2363/61804",
    "sg:postcode":"45731",
    "sg:province":"Nordrhein-Westfalen",
    "wof:name":"Staasmeier Gmbh",
    "wof:placetype":"venue"
},
  "geometry": {"coordinates":[7.3211069107,51.6149597168],"type":"Point"}
}