{
  "type": "Feature",
  "properties": {
    "iso:country":"DE",
    "sg:address":"Dorfstr. 16e",
    "sg:city":"Zschaitz-Ottewig",
    "sg:phone":"+49 34324/22245",
    "sg:postcode":"04720",
    "sg:province":"Sachsen",
    "wof:name":"Sanit\u00e4r- Und Heizungstechnik Gmbh",
    "wof:placetype":"venue"
},
  "geometry": {"coordinates":[13.20304,51.151299],"type":"Point"}
}