{
  "type": "Feature",
  "properties": {
    "iso:country":"DE",
    "sg:address":"Sperenberger Str 5a",
    "sg:city":"Berlin",
    "sg:phone":"+49 30/7200040",
    "sg:postcode":"12277",
    "sg:province":"Berlin",
    "wof:name":"Matino Medical Gmbh & Co Kg",
    "wof:placetype":"venue"
},
  "geometry": {"coordinates":[13.378422,52.401119],"type":"Point"}
}