{
  "type": "Feature",
  "properties": {
    "iso:country":"DE",
    "sg:address":"Hildesheimer Str. 85",
    "sg:city":"Laatzen",
    "sg:phone":"+49 511/871472",
    "sg:postcode":"30880",
    "sg:province":"Niedersachsen",
    "wof:name":"Quadriceps",
    "wof:placetype":"venue"
},
  "geometry": {"coordinates":[9.8354072571,52.2788085938],"type":"Point"}
}