{
  "type": "Feature",
  "properties": {
    "iso:country":"DE",
    "sg:address":"Rosengartenweg 7",
    "sg:city":"Merchweiler",
    "sg:phone":"+49 6825/2926",
    "sg:postcode":"66589",
    "sg:province":"Saarland",
    "wof:name":"Josef Hoffmann Architekt",
    "wof:placetype":"venue"
},
  "geometry": {"coordinates":[7.08591,49.368382],"type":"Point"}
}