{
  "type": "Feature",
  "properties": {
    "iso:country":"DE",
    "sg:address":"Hinter dem Dorfe 32",
    "sg:city":"Diekholzen",
    "sg:phone":"+49 5121/265826",
    "sg:postcode":"31199",
    "sg:province":"Niedersachsen",
    "wof:name":"Ambulante Krankenpflege Und Seniorenbetreuung Krenauer",
    "wof:placetype":"venue"
},
  "geometry": {"coordinates":[9.958329,52.098347],"type":"Point"}
}