{
  "type": "Feature",
  "properties": {
    "iso:country":"DE",
    "sg:address":"Hans-Henny-Jahnn-Weg 15",
    "sg:city":"Hamburg",
    "sg:postcode":"22085",
    "sg:province":"Hamburg",
    "wof:name":"Sineus Ag",
    "wof:placetype":"venue"
},
  "geometry": {"coordinates":[10.0144948959,53.5801925659],"type":"Point"}
}