{
  "type": "Feature",
  "properties": {
    "iso:country":"DE",
    "sg:address":"Mayener Str. 9",
    "sg:city":"Ettringen",
    "sg:phone":"+49 2651/6423",
    "sg:postcode":"56729",
    "sg:province":"Rheinland-Pfalz",
    "wof:name":"Bludau & Hofmann Gmbh",
    "wof:placetype":"venue"
},
  "geometry": {"coordinates":[7.2219991684,50.3515777588],"type":"Point"}
}