{
  "type": "Feature",
  "properties": {
    "iso:country":"DE",
    "sg:address":"Mittelstr. 7",
    "sg:city":"Mannheim",
    "sg:phone":"+49 621/34264",
    "sg:postcode":"68169",
    "sg:province":"Baden-W\u00fcrttemberg",
    "wof:name":"Kurt Puzek",
    "wof:placetype":"venue"
},
  "geometry": {"coordinates":[8.4716529846,49.4973678589],"type":"Point"}
}