{
  "type": "Feature",
  "properties": {
    "iso:country":"DE",
    "sg:address":"Bahnhofstr. 2",
    "sg:city":"Vohenstrau\u00df",
    "sg:phone":"+49 9651/921111",
    "sg:postcode":"92648",
    "sg:province":"Bayern",
    "wof:name":"Maria Rupprecht",
    "wof:placetype":"venue"
},
  "geometry": {"coordinates":[12.3409490585,49.6251144409],"type":"Point"}
}