{
  "type": "Feature",
  "properties": {
    "iso:country":"DE",
    "sg:address":"Liebigstr. 22",
    "sg:city":"Ostfildern",
    "sg:phone":"+49 4971/5850110",
    "sg:postcode":"73760",
    "sg:province":"Baden-W\u00fcrttemberg",
    "wof:name":"Eder Gmbh",
    "wof:placetype":"venue"
},
  "geometry": {"coordinates":[9.2524938583,48.7081222534],"type":"Point"}
}