{
  "type": "Feature",
  "properties": {
    "iso:country":"DE",
    "sg:address":"Harburger Schlo\u00dfstr. 1",
    "sg:city":"Hamburg",
    "sg:postcode":"21079",
    "sg:province":"Hamburg",
    "wof:name":"Ision International Gmbh",
    "wof:placetype":"venue"
},
  "geometry": {"coordinates":[9.982244,53.464367],"type":"Point"}
}