{
  "type": "Feature",
  "properties": {
    "iso:country":"DE",
    "sg:address":"Albrechtsgasse 20",
    "sg:city":"Straubing",
    "sg:phone":"+49 9421/84370",
    "sg:postcode":"94315",
    "sg:province":"Bayern",
    "wof:name":"Karmelitenkloster Bibliothek",
    "wof:placetype":"venue"
},
  "geometry": {"coordinates":[12.572213,48.883701],"type":"Point"}
}