{
  "type": "Feature",
  "properties": {
    "iso:country":"DE",
    "sg:address":"Friedrich-Ebert-Str. 42",
    "sg:city":"Cottbus",
    "sg:phone":"+49 355/700656",
    "sg:postcode":"03044",
    "sg:province":"Brandenburg",
    "wof:name":"Opitz",
    "wof:placetype":"venue"
},
  "geometry": {"coordinates":[14.331847,51.763271],"type":"Point"}
}