{
  "type": "Feature",
  "properties": {
    "iso:country":"DE",
    "sg:address":"Arp-Schnittger-Str. 10",
    "sg:city":"Cappel",
    "sg:phone":"+49 4741/1280",
    "sg:postcode":"27632",
    "sg:province":"Niedersachsen",
    "wof:name":"G\u00fcnther Schade",
    "wof:placetype":"venue"
},
  "geometry": {"coordinates":[8.5688123703,53.727645874],"type":"Point"}
}