{
  "type": "Feature",
  "properties": {
    "iso:country":"DE",
    "sg:address":"N\u00fcrnberger Str. 17",
    "sg:city":"Berlin",
    "sg:phone":"+49 30/2184292",
    "sg:postcode":"10789",
    "sg:province":"Berlin",
    "wof:name":"Extraweit Gbr Inh. I. Becker U. R. Schl\u00fcter",
    "wof:placetype":"venue"
},
  "geometry": {"coordinates":[13.337851,52.501995],"type":"Point"}
}