{
  "type": "Feature",
  "properties": {
    "iso:country":"DE",
    "sg:address":"Neue Gasse 13",
    "sg:city":"Uffenheim",
    "sg:phone":"+49 9842/1777",
    "sg:postcode":"97215",
    "sg:province":"Bayern",
    "wof:name":"F. Sch\u00e4ffer",
    "wof:placetype":"venue"
},
  "geometry": {"coordinates":[10.227016449,49.5453033447],"type":"Point"}
}