{
  "type": "Feature",
  "properties": {
    "iso:country":"DE",
    "sg:address":"Donauw\u00f6rther Str. 4",
    "sg:city":"Asbach-B\u00e4umenheim",
    "sg:phone":"+49 906/91241",
    "sg:postcode":"86663",
    "sg:province":"Bayern",
    "wof:name":"K. Mahler",
    "wof:placetype":"venue"
},
  "geometry": {"coordinates":[10.8094053268,48.6817054749],"type":"Point"}
}