{
  "type": "Feature",
  "properties": {
    "iso:country":"DE",
    "sg:address":"Uetzer Weg 8",
    "sg:city":"Wathlingen",
    "sg:phone":"+49 5144/4567",
    "sg:postcode":"29339",
    "sg:province":"Niedersachsen",
    "wof:name":"Manfred Grotewohl",
    "wof:placetype":"venue"
},
  "geometry": {"coordinates":[10.1562204361,52.5366096497],"type":"Point"}
}