{
  "type": "Feature",
  "properties": {
    "iso:country":"DE",
    "sg:address":"Kleinenbroicher Str. 1",
    "sg:city":"M\u00f6nchengladbach",
    "sg:phone":"+49 2166/98590",
    "sg:postcode":"41238",
    "sg:province":"Nordrhein-Westfalen",
    "wof:name":"Tefma Bautr\u00e4ger Gmbh",
    "wof:placetype":"venue"
},
  "geometry": {"coordinates":[6.4903769493,51.1558914185],"type":"Point"}
}