{
  "type": "Feature",
  "properties": {
    "iso:country":"DE",
    "sg:address":"Leinenweberstr. 12",
    "sg:city":"Freiburg",
    "sg:phone":"+49 761/152340",
    "sg:postcode":"79108",
    "sg:province":"Baden-W\u00fcrttemberg",
    "wof:name":"Mattke Ag",
    "wof:placetype":"venue"
},
  "geometry": {"coordinates":[7.813011,48.037815],"type":"Point"}
}