{
  "type": "Feature",
  "properties": {
    "iso:country":"DE",
    "sg:address":"Kolumbusring 61",
    "sg:city":"Rostock",
    "sg:postcode":"18106",
    "sg:province":"Mecklenburg-Vorpommern",
    "wof:name":"F. & S. Handels- Und Freizeitanlagen Gbr",
    "wof:placetype":"venue"
},
  "geometry": {"coordinates":[12.0720853806,54.1343269348],"type":"Point"}
}