{
  "type": "Feature",
  "properties": {
    "iso:country":"DE",
    "sg:address":"Groenerstr. 19",
    "sg:city":"Berlin",
    "sg:postcode":"13585",
    "sg:province":"Berlin",
    "wof:name":"Groener Spielhallen Gmbh",
    "wof:placetype":"venue"
},
  "geometry": {"coordinates":[13.2031526566,52.5432510376],"type":"Point"}
}