{
  "type": "Feature",
  "properties": {
    "iso:country":"DE",
    "sg:address":"Luitpoldstr. 40",
    "sg:city":"Gelsenkirchen",
    "sg:postcode":"45881",
    "sg:province":"Nordrhein-Westfalen",
    "wof:name":"Ferien Ins Olsberg",
    "wof:placetype":"venue"
},
  "geometry": {"coordinates":[7.096299,51.516102],"type":"Point"}
}