{
  "type": "Feature",
  "properties": {
    "iso:country":"DE",
    "sg:address":"Sportfeld 52",
    "sg:city":"Gie\u00dfen",
    "sg:phone":"+49 641/202612",
    "sg:postcode":"35398",
    "sg:province":"Hessen",
    "wof:name":"Envicon Beratende Ingenieure F\u00fcr Umwelt Und Hygiene-",
    "wof:placetype":"venue"
},
  "geometry": {"coordinates":[8.6458272934,50.5612564087],"type":"Point"}
}