{
  "type": "Feature",
  "properties": {
    "iso:country":"DE",
    "sg:address":"Bredenscheider Str. 54",
    "sg:city":"Hattingen",
    "sg:phone":"+49 2324/5020",
    "sg:postcode":"45525",
    "sg:province":"Nordrhein-Westfalen",
    "wof:name":"Evangelisches Krankenhaus Hattingen Service Gmbh",
    "wof:placetype":"venue"
},
  "geometry": {"coordinates":[7.192807,51.394737],"type":"Point"}
}