{
  "type": "Feature",
  "properties": {
    "iso:country":"DE",
    "sg:address":"Pasteurstr. 12",
    "sg:city":"Neunkirchen",
    "sg:phone":"+49 6821/26025",
    "sg:postcode":"66538",
    "sg:province":"Saarland",
    "wof:name":"Jakob Und Jakob Rechtanw\u00e4lte",
    "wof:placetype":"venue"
},
  "geometry": {"coordinates":[7.176071167,49.347984314],"type":"Point"}
}