{
  "type": "Feature",
  "properties": {
    "iso:country":"DE",
    "sg:address":"Kaarster Str. 2",
    "sg:city":"Neuss",
    "sg:phone":"+49 2131/560054",
    "sg:postcode":"41462",
    "sg:province":"Nordrhein-Westfalen",
    "wof:name":"Sonnenstudio Sonnenland R. Tillmann",
    "wof:placetype":"venue"
},
  "geometry": {"coordinates":[6.662422,51.217506],"type":"Point"}
}