{
  "type": "Feature",
  "properties": {
    "iso:country":"DE",
    "sg:address":"Breiteweg 22",
    "sg:city":"Egeln",
    "sg:phone":"+49 39268/2300",
    "sg:postcode":"39435",
    "sg:province":"Sachsen-Anhalt",
    "wof:name":"Konditorei Ulrich",
    "wof:placetype":"venue"
},
  "geometry": {"coordinates":[11.4293479919,51.9419593811],"type":"Point"}
}