{
  "type": "Feature",
  "properties": {
    "iso:country":"DE",
    "sg:address":"Weddeln 13",
    "sg:city":"Bosau",
    "sg:postcode":"23715",
    "sg:province":"Schleswig-Holstein",
    "wof:name":"Thomas Anders Accessoires Gmbh",
    "wof:placetype":"venue"
},
  "geometry": {"coordinates":[10.572894,54.118874],"type":"Point"}
}