{
  "type": "Feature",
  "properties": {
    "iso:country":"DE",
    "sg:address":"S\u00fcdstr. 5",
    "sg:city":"Wissen",
    "sg:phone":"+49 2742/2452",
    "sg:postcode":"57537",
    "sg:province":"Rheinland-Pfalz",
    "wof:name":"Franz-ludwig Passerah",
    "wof:placetype":"venue"
},
  "geometry": {"coordinates":[7.7442860603,50.7784576416],"type":"Point"}
}