{
  "type": "Feature",
  "properties": {
    "iso:country":"DE",
    "sg:address":"Handorfer Weg 1",
    "sg:city":"Ilsede",
    "sg:phone":"+49 5172/8054",
    "sg:postcode":"31241",
    "sg:province":"Niedersachsen",
    "wof:name":"Karl-heinz Wilke",
    "wof:placetype":"venue"
},
  "geometry": {"coordinates":[10.222273,52.270775],"type":"Point"}
}