{
  "type": "Feature",
  "properties": {
    "iso:country":"DE",
    "sg:address":"Max-Reger-Str. 25",
    "sg:city":"Neusorg",
    "sg:phone":"+49 9234/219",
    "sg:postcode":"95700",
    "sg:province":"Bayern",
    "wof:name":"Heribert Seidinger Architekt",
    "wof:placetype":"venue"
},
  "geometry": {"coordinates":[11.964076,49.939331],"type":"Point"}
}