{
  "type": "Feature",
  "properties": {
    "iso:country":"DE",
    "sg:address":"Emserstrasse 39 D",
    "sg:city":"berlin",
    "sg:postcode":"10719",
    "sg:province":"Berlin",
    "wof:name":"Arbeitsgemeinschaft-berufsunf\u00e4higkeit",
    "wof:placetype":"venue"
},
  "geometry": {"coordinates":[13.320121,52.498264],"type":"Point"}
}