{
  "type": "Feature",
  "properties": {
    "iso:country":"DE",
    "sg:address":"Lindenkamp 6",
    "sg:city":"Bad Oldesloe",
    "sg:phone":"+49 4531/82134",
    "sg:postcode":"23843",
    "sg:province":"Schleswig-Holstein",
    "wof:name":"Joachim K\u00f6nig Architekt",
    "wof:placetype":"venue"
},
  "geometry": {"coordinates":[10.364844,53.799927],"type":"Point"}
}