{
  "type": "Feature",
  "properties": {
    "iso:country":"DE",
    "sg:address":"Hauptstr. 103",
    "sg:city":"Seedorf",
    "sg:phone":"+49 4284/95035",
    "sg:postcode":"27404",
    "sg:province":"Niedersachsen",
    "wof:name":"Baugesch\u00e4ft G. Hastedt Gmbh",
    "wof:placetype":"venue"
},
  "geometry": {"coordinates":[9.230806,53.349575],"type":"Point"}
}