{
  "type": "Feature",
  "properties": {
    "iso:country":"DE",
    "sg:address":"Graf-Adolf-Str 88",
    "sg:city":"D\u00fcsseldorf",
    "sg:phone":"+49 211/17541930",
    "sg:postcode":"40210",
    "sg:province":"Nordrhein-Westfalen",
    "wof:name":"Km2>>netz:innovationen.gmbh",
    "wof:placetype":"venue"
},
  "geometry": {"coordinates":[6.788397,51.219452],"type":"Point"}
}