{
  "type": "Feature",
  "properties": {
    "iso:country":"DE",
    "sg:address":"Herrenwald 75",
    "sg:city":"Nagold",
    "sg:phone":"+49 7459/8470",
    "sg:postcode":"72202",
    "sg:province":"Baden-W\u00fcrttemberg",
    "wof:name":"Bahnhofwirtschaft",
    "wof:placetype":"venue"
},
  "geometry": {"coordinates":[8.7020788193,48.5100517273],"type":"Point"}
}