{
  "type": "Feature",
  "properties": {
    "iso:country":"DE",
    "sg:address":"Lindwurmstr. 179",
    "sg:city":"M\u00fcnchen",
    "sg:phone":"+49 89/7233114",
    "sg:postcode":"80337",
    "sg:province":"Bayern",
    "wof:name":"Georg Stangl E. K. Inh. Fred Horrmann",
    "wof:placetype":"venue"
},
  "geometry": {"coordinates":[11.5464305878,48.1229629517],"type":"Point"}
}