{
  "type": "Feature",
  "properties": {
    "iso:country":"DE",
    "sg:address":"Gutenbergstr. 2",
    "sg:city":"Goslar",
    "sg:phone":"+49 5321/46228",
    "sg:postcode":"38640",
    "sg:province":"Niedersachsen",
    "wof:name":"Eduscho Gmbh",
    "wof:placetype":"venue"
},
  "geometry": {"coordinates":[10.4486198425,51.9164123535],"type":"Point"}
}