{
  "type": "Feature",
  "properties": {
    "iso:country":"DE",
    "sg:city":"Rennerod",
    "sg:postcode":"56477",
    "sg:province":"Rheinland-Pfalz",
    "wof:name":"Mohr-hausbau Gmbh",
    "wof:placetype":"venue"
},
  "geometry": {"coordinates":[8.066175,50.607063],"type":"Point"}
}