{
  "type": "Feature",
  "properties": {
    "iso:country":"DE",
    "sg:address":"August-Horch-Str. 11-13",
    "sg:city":"Koblenz",
    "sg:phone":"+49 261/8080730",
    "sg:postcode":"56070",
    "sg:province":"Rheinland-Pfalz",
    "wof:name":"R\u00f6lab Gmbh",
    "wof:placetype":"venue"
},
  "geometry": {"coordinates":[7.568869,50.390747],"type":"Point"}
}