{
  "type": "Feature",
  "properties": {
    "iso:country":"DE",
    "sg:address":"Berliner Str. 64b",
    "sg:city":"Hagen",
    "sg:phone":"+49 2331/41665",
    "sg:postcode":"58135",
    "sg:province":"Nordrhein-Westfalen",
    "wof:name":"Roland-apotheke Inh. Sigrun Schoenwald",
    "wof:placetype":"venue"
},
  "geometry": {"coordinates":[7.435269,51.349083],"type":"Point"}
}