{
  "type": "Feature",
  "properties": {
    "iso:country":"DE",
    "sg:address":"Ke\u00dflerstr. 24",
    "sg:city":"Hildesheim",
    "sg:phone":"+49 5121/31618",
    "sg:postcode":"31134",
    "sg:province":"Niedersachsen",
    "wof:name":"Claus J\u00f6rdens",
    "wof:placetype":"venue"
},
  "geometry": {"coordinates":[9.9552650452,52.1464347839],"type":"Point"}
}