{
  "type": "Feature",
  "properties": {
    "iso:country":"DE",
    "sg:address":"Bismarckallee 6",
    "sg:city":"Berlin",
    "sg:postcode":"14193",
    "sg:province":"Berlin",
    "wof:name":"Advice Services Gmbh",
    "wof:placetype":"venue"
},
  "geometry": {"coordinates":[13.2833786011,52.4906997681],"type":"Point"}
}