{
  "type": "Feature",
  "properties": {
    "iso:country":"DE",
    "sg:address":"Wiesenstr. 9",
    "sg:city":"Hardert",
    "sg:phone":"+49 2634/4070",
    "sg:postcode":"56579",
    "sg:province":"Rheinland-Pfalz",
    "wof:name":"Westf\u00e4lischer Hof",
    "wof:placetype":"venue"
},
  "geometry": {"coordinates":[7.5144438744,50.5147399902],"type":"Point"}
}