{
  "type": "Feature",
  "properties": {
    "iso:country":"DE",
    "sg:address":"Waldstr. 6",
    "sg:city":"Emskirchen",
    "sg:phone":"+49 9104/1535",
    "sg:postcode":"91448",
    "sg:province":"Bayern",
    "wof:name":"Anton Vogl",
    "wof:placetype":"venue"
},
  "geometry": {"coordinates":[10.7070589066,49.5543823242],"type":"Point"}
}