{
  "type": "Feature",
  "properties": {
    "iso:country":"DE",
    "sg:address":"Schmidhausener Str. 4",
    "sg:city":"Beilstein",
    "sg:phone":"+49 7062/23344",
    "sg:postcode":"71717",
    "sg:province":"Baden-W\u00fcrttemberg",
    "wof:name":"Karl Kussmann",
    "wof:placetype":"venue"
},
  "geometry": {"coordinates":[9.3172063828,49.0387611389],"type":"Point"}
}