{
  "type": "Feature",
  "properties": {
    "iso:country":"DE",
    "sg:city":"K\u00f6ln",
    "sg:phone":"+49 221",
    "sg:postcode":"50859",
    "sg:province":"Nordrhein-Westfalen",
    "wof:name":"Weihnachtsmann Service Koeln",
    "wof:placetype":"venue"
},
  "geometry": {"coordinates":[6.829694,50.94643],"type":"Point"}
}