{
  "type": "Feature",
  "properties": {
    "iso:country":"DE",
    "sg:address":"Berghauser Str 62",
    "sg:city":"Remscheid",
    "sg:phone":"+49 2191/900290",
    "sg:postcode":"42859",
    "sg:province":"Nordrhein-Westfalen",
    "wof:name":"Virtualliance Adler, F\u00f6rster & Cie Kg",
    "wof:placetype":"venue"
},
  "geometry": {"coordinates":[7.214878,51.168362],"type":"Point"}
}