{
  "type": "Feature",
  "properties": {
    "iso:country":"DE",
    "sg:address":"Leipziger Str. 45",
    "sg:city":"Markranst\u00e4dt",
    "sg:postcode":"04420",
    "sg:province":"Sachsen",
    "wof:name":"Th\u00fcringer Hof-lichtspiele Markranst\u00e4dt Mit Visionsbar",
    "wof:placetype":"venue"
},
  "geometry": {"coordinates":[12.2244348526,51.305229187],"type":"Point"}
}