{
  "type": "Feature",
  "properties": {
    "iso:country":"DE",
    "sg:address":"Dorfstr. 63",
    "sg:city":"Uhrsleben",
    "sg:postcode":"39343",
    "sg:province":"Sachsen-Anhalt",
    "wof:name":"P. Insensee",
    "wof:placetype":"venue"
},
  "geometry": {"coordinates":[11.2651748657,52.1931838989],"type":"Point"}
}