{
  "type": "Feature",
  "properties": {
    "iso:country":"DE",
    "sg:address":"Sofienstr. 11-13",
    "sg:city":"Duisburg",
    "sg:phone":"+49 2065/99203",
    "sg:postcode":"47226",
    "sg:province":"Nordrhein-Westfalen",
    "wof:name":"Mathias Illigen",
    "wof:placetype":"venue"
},
  "geometry": {"coordinates":[6.717663,51.407955],"type":"Point"}
}