{
  "type": "Feature",
  "properties": {
    "iso:country":"DE",
    "sg:address":"H\u00f6henweg 6B",
    "sg:city":"Velbert",
    "sg:phone":"+49 2051/82777",
    "sg:postcode":"42551",
    "sg:province":"Nordrhein-Westfalen",
    "wof:name":"Winfried Schardt Architekt",
    "wof:placetype":"venue"
},
  "geometry": {"coordinates":[7.037477,51.354965],"type":"Point"}
}