{
  "type": "Feature",
  "properties": {
    "iso:country":"DE",
    "sg:address":"Wandsbeker Str. 7",
    "sg:city":"Hamburg",
    "sg:postcode":"22179",
    "sg:province":"Hamburg",
    "wof:name":"F\u00fcnfundsechzigste Mercator Handelsgesellschaft Mbh",
    "wof:placetype":"venue"
},
  "geometry": {"coordinates":[10.0700330734,53.6000556946],"type":"Point"}
}