{
  "type": "Feature",
  "properties": {
    "iso:country":"DE",
    "sg:address":"Johanna-H\u00f6lters-Str. 38",
    "sg:city":"M\u00f6nchengladbach",
    "sg:phone":"+49 2161/592858",
    "sg:postcode":"41069",
    "sg:province":"Nordrhein-Westfalen",
    "wof:name":"Emce Gmbh",
    "wof:placetype":"venue"
},
  "geometry": {"coordinates":[6.4185700417,51.181312561],"type":"Point"}
}