{
  "type": "Feature",
  "properties": {
    "iso:country":"DE",
    "sg:address":"Industriestr. 19",
    "sg:city":"Senden",
    "sg:phone":"+49 2597/5086",
    "sg:postcode":"48308",
    "sg:province":"Nordrhein-Westfalen",
    "wof:name":"Bauunternehmung Dipl.-ing. Johannes",
    "wof:placetype":"venue"
},
  "geometry": {"coordinates":[7.4731249809,51.84532547],"type":"Point"}
}