{
  "type": "Feature",
  "properties": {
    "iso:country":"DE",
    "sg:address":"Rintheimer Str. 50",
    "sg:city":"Karlsruhe",
    "sg:phone":"+49 721/29711",
    "sg:postcode":"76131",
    "sg:province":"Baden-W\u00fcrttemberg",
    "wof:name":"Feka C. Berkmann Gmbh",
    "wof:placetype":"venue"
},
  "geometry": {"coordinates":[8.4302120209,49.0111122131],"type":"Point"}
}