{
  "type": "Feature",
  "properties": {
    "iso:country":"DE",
    "sg:address":"Taunusstr. 1 a",
    "sg:city":"Holzappel",
    "sg:phone":"+49 6439/5461",
    "sg:postcode":"56379",
    "sg:province":"Rheinland-Pfalz",
    "wof:name":"Adolf Und Beate Fetter",
    "wof:placetype":"venue"
},
  "geometry": {"coordinates":[7.8979182243,50.3503417969],"type":"Point"}
}