{
  "type": "Feature",
  "properties": {
    "iso:country":"DE",
    "sg:address":"Villinger Str. 32",
    "sg:city":"Riedlingen",
    "sg:phone":"+49 7371/8486",
    "sg:postcode":"88499",
    "sg:province":"Baden-W\u00fcrttemberg",
    "wof:name":"H. Hungeb\u00fchler",
    "wof:placetype":"venue"
},
  "geometry": {"coordinates":[9.4182634354,48.1724777222],"type":"Point"}
}