{
  "type": "Feature",
  "properties": {
    "iso:country":"DE",
    "sg:address":"Bei Der Neuen M\u00fcnze 17",
    "sg:city":"Hamburg",
    "sg:phone":"+49 40/6790800",
    "sg:postcode":"22145",
    "sg:province":"Hamburg",
    "wof:name":"Ha-ge-ha Klima- U. Lufttechnik Gmbh",
    "wof:placetype":"venue"
},
  "geometry": {"coordinates":[10.153317,53.623802],"type":"Point"}
}