{
  "type": "Feature",
  "properties": {
    "iso:country":"DE",
    "sg:address":"Burgstr. 18a",
    "sg:city":"Aremberg",
    "sg:phone":"+49 2693/281",
    "sg:postcode":"53533",
    "sg:province":"Rheinland-Pfalz",
    "wof:name":"Volksbank Bad Neuenahr-ahrweil",
    "wof:placetype":"venue"
},
  "geometry": {"coordinates":[6.80782,50.41576],"type":"Point"}
}