{
  "type": "Feature",
  "properties": {
    "iso:country":"DE",
    "sg:address":"Marie-Curie-Str. 5",
    "sg:city":"Rheinbach",
    "sg:postcode":"53359",
    "sg:province":"Nordrhein-Westfalen",
    "wof:name":"X. Tronics Gmbh",
    "wof:placetype":"venue"
},
  "geometry": {"coordinates":[6.952386,50.625816],"type":"Point"}
}