{
  "type": "Feature",
  "properties": {
    "iso:country":"DE",
    "sg:address":"Bahnhofstr. 1",
    "sg:city":"Th\u00fcngersheim",
    "sg:phone":"+49 9364/2734",
    "sg:postcode":"97291",
    "sg:province":"Bayern",
    "wof:name":"Richard D\u00fcrr",
    "wof:placetype":"venue"
},
  "geometry": {"coordinates":[9.8410196304,49.8777275085],"type":"Point"}
}