{
  "type": "Feature",
  "properties": {
    "iso:country":"DE",
    "sg:address":"Franz-Josef-Gall-Str. 19",
    "sg:city":"Tiefenbronn",
    "sg:phone":"+49 7234/4335",
    "sg:postcode":"75233",
    "sg:province":"Baden-W\u00fcrttemberg",
    "wof:name":"Josef B\u00f6ss",
    "wof:placetype":"venue"
},
  "geometry": {"coordinates":[8.801999,48.82431],"type":"Point"}
}