{
  "type": "Feature",
  "properties": {
    "iso:country":"DE",
    "sg:address":"Maximilianstr. 19",
    "sg:city":"Wunsiedel",
    "sg:phone":"+49 9232/2233",
    "sg:postcode":"95632",
    "sg:province":"Bayern",
    "wof:name":"Erhard Jahn",
    "wof:placetype":"venue"
},
  "geometry": {"coordinates":[12.0016212463,50.0377502441],"type":"Point"}
}