{
  "type": "Feature",
  "properties": {
    "iso:country":"DE",
    "sg:address":"R\u00f6ttinger Str. 19",
    "sg:city":"Westhausen",
    "sg:phone":"+49 7363/6167",
    "sg:postcode":"73463",
    "sg:province":"Baden-W\u00fcrttemberg",
    "wof:name":"P. Lenz K\u00fcferei",
    "wof:placetype":"venue"
},
  "geometry": {"coordinates":[10.256474,48.897888],"type":"Point"}
}