{
  "type": "Feature",
  "properties": {
    "iso:country":"DE",
    "sg:address":"Bernauer Str. 22",
    "sg:city":"Prien",
    "sg:phone":"+49 8051/1581",
    "sg:postcode":"83209",
    "sg:province":"Bayern",
    "wof:name":"H. Und L. Haaf",
    "wof:placetype":"venue"
},
  "geometry": {"coordinates":[12.3445196152,47.8531494141],"type":"Point"}
}