{
  "type": "Feature",
  "properties": {
    "iso:country":"DE",
    "sg:address":"H\u00f6hnerhof",
    "sg:city":"K\u00f6nigswinter",
    "sg:phone":"+49 2244/3402",
    "sg:postcode":"53639",
    "sg:province":"Nordrhein-Westfalen",
    "wof:name":"Heinz-peter Olbr\u00fcck",
    "wof:placetype":"venue"
},
  "geometry": {"coordinates":[7.238345,50.715496],"type":"Point"}
}