{
  "type": "Feature",
  "properties": {
    "iso:country":"DE",
    "sg:address":"Birkenstr. 8",
    "sg:city":"Giebelstadt",
    "sg:phone":"+49 9334/342",
    "sg:postcode":"97232",
    "sg:province":"Bayern",
    "wof:name":"Hugo Honecker Steinmetzbetrieb",
    "wof:placetype":"venue"
},
  "geometry": {"coordinates":[9.9506616592,49.6527442932],"type":"Point"}
}