{
  "type": "Feature",
  "properties": {
    "iso:country":"DE",
    "sg:address":"Hauptstr. 42",
    "sg:city":"Lohnweiler",
    "sg:postcode":"67744",
    "sg:province":"Rheinland-Pfalz",
    "wof:name":"Miethke Gmbh",
    "wof:placetype":"venue"
},
  "geometry": {"coordinates":[7.596272,49.635677],"type":"Point"}
}