{
  "type": "Feature",
  "properties": {
    "iso:country":"DE",
    "sg:address":"Ringstr. 32",
    "sg:city":"Gaggenau",
    "sg:phone":"+49 7225/77234",
    "sg:postcode":"76571",
    "sg:province":"Baden-W\u00fcrttemberg",
    "wof:name":"Komo-mottausch Gmbh",
    "wof:placetype":"venue"
},
  "geometry": {"coordinates":[8.3030328751,48.8173866272],"type":"Point"}
}