{
  "type": "Feature",
  "properties": {
    "iso:country":"DE",
    "sg:address":"Tannheimerstrasse 4",
    "sg:city":"Augsburg",
    "sg:phone":"+49 821/662723",
    "sg:postcode":"86163",
    "sg:province":"Bayern",
    "wof:name":"Exclusiv Wohnmobilreisen",
    "wof:placetype":"venue"
},
  "geometry": {"coordinates":[10.94048,48.360992],"type":"Point"}
}