{
  "type": "Feature",
  "properties": {
    "iso:country":"DE",
    "sg:address":"Duisburger Str. 187-189",
    "sg:city":"Duisburg",
    "sg:phone":"+49 203/554321",
    "sg:postcode":"47166",
    "sg:province":"Nordrhein-Westfalen",
    "wof:name":"Schreiber Automobilhandelsges. Mbh",
    "wof:placetype":"venue"
},
  "geometry": {"coordinates":[6.776654,51.492157],"type":"Point"}
}