{
  "type": "Feature",
  "properties": {
    "iso:country":"DE",
    "sg:address":"B\u00fclowstr. 27",
    "sg:city":"Berlin",
    "sg:phone":"+49 30/2168949",
    "sg:postcode":"10783",
    "sg:province":"Berlin",
    "wof:name":"Spielothek Kosmos Automaten Vertriebs Gmbh",
    "wof:placetype":"venue"
},
  "geometry": {"coordinates":[13.3627319336,52.49741745],"type":"Point"}
}