{
  "type": "Feature",
  "properties": {
    "iso:country":"DE",
    "sg:address":"Industriestr. 1",
    "sg:city":"Dreieich",
    "sg:postcode":"63303",
    "sg:province":"Hessen",
    "wof:name":"Neukirchinger Verlag",
    "wof:placetype":"venue"
},
  "geometry": {"coordinates":[8.7043676376,50.0034141541],"type":"Point"}
}