{
  "type": "Feature",
  "properties": {
    "iso:country":"DE",
    "sg:address":"Berliner Str. 46",
    "sg:city":"Berlin",
    "sg:postcode":"13189",
    "sg:province":"Berlin",
    "wof:name":"Fema Handelsgesellschaft Mbh",
    "wof:placetype":"venue"
},
  "geometry": {"coordinates":[13.412775,52.56023],"type":"Point"}
}