{
  "type": "Feature",
  "properties": {
    "iso:country":"DE",
    "sg:address":"Hamburger Str 69",
    "sg:city":"Heide",
    "sg:phone":"+49 481/850700",
    "sg:postcode":"25746",
    "sg:province":"Schleswig-Holstein",
    "wof:name":"Heider Offset- Und Verlagsdruckerei H. Pingel Gmbh",
    "wof:placetype":"venue"
},
  "geometry": {"coordinates":[9.1080179214,54.1966667175],"type":"Point"}
}