{
  "type": "Feature",
  "properties": {
    "iso:country":"DE",
    "sg:address":"Bretonischer Ring 9",
    "sg:city":"Grasbrunn",
    "sg:phone":"+49 89/4623180",
    "sg:postcode":"85630",
    "sg:province":"Bayern",
    "wof:name":"Multiresidence Baubetreuungs-gmbh",
    "wof:placetype":"venue"
},
  "geometry": {"coordinates":[11.764134407,48.1005973816],"type":"Point"}
}