{
  "type": "Feature",
  "properties": {
    "iso:country":"DE",
    "sg:address":"Dr.-Karl-Stern-Str. 4",
    "sg:city":"Cham",
    "sg:postcode":"93413",
    "sg:province":"Bayern",
    "wof:name":"Mako Plan Gmbh",
    "wof:placetype":"venue"
},
  "geometry": {"coordinates":[12.671491,49.227055],"type":"Point"}
}