{
  "type": "Feature",
  "properties": {
    "iso:country":"DE",
    "sg:address":"Am Treutengraben 40",
    "sg:city":"Frankfurt",
    "sg:phone":"+49 69/769421",
    "sg:postcode":"60488",
    "sg:province":"Hessen",
    "wof:name":"Dietrich Hasse Architekt",
    "wof:placetype":"venue"
},
  "geometry": {"coordinates":[8.622961,50.14286],"type":"Point"}
}