{
  "type": "Feature",
  "properties": {
    "iso:country":"DE",
    "sg:address":"Gro\u00dfe Seite 30",
    "sg:city":"Schellerten",
    "sg:phone":"+49 5123/2349",
    "sg:postcode":"31174",
    "sg:province":"Niedersachsen",
    "wof:name":"Hickmott",
    "wof:placetype":"venue"
},
  "geometry": {"coordinates":[10.0619468689,52.1646614075],"type":"Point"}
}