{
  "type": "Feature",
  "properties": {
    "iso:country":"DE",
    "sg:address":"Blumenhorst 6",
    "sg:city":"Stemwede",
    "sg:phone":"+49 4954/74680",
    "sg:postcode":"32351",
    "sg:province":"Nordrhein-Westfalen",
    "wof:name":"Depenbrock Bau Gmbh & Co Kg",
    "wof:placetype":"venue"
},
  "geometry": {"coordinates":[8.402453,52.421814],"type":"Point"}
}