{
  "type": "Feature",
  "properties": {
    "iso:country":"DE",
    "sg:address":"Neuendammer Str. 16",
    "sg:city":"Osterholz-Scharmbeck",
    "sg:phone":"+49 4791/57427",
    "sg:postcode":"27711",
    "sg:province":"Niedersachsen",
    "wof:name":"Gastst\u00e4tte Johanne Freese",
    "wof:placetype":"venue"
},
  "geometry": {"coordinates":[8.8171253204,53.2421836853],"type":"Point"}
}