{
  "type": "Feature",
  "properties": {
    "iso:country":"DE",
    "sg:address":"Dr.-C.-Otto-Str. 10",
    "sg:city":"Bochum",
    "sg:phone":"+49 234/492534",
    "sg:postcode":"44879",
    "sg:province":"Nordrhein-Westfalen",
    "wof:name":"Esso-tankstelle",
    "wof:placetype":"venue"
},
  "geometry": {"coordinates":[7.1592440605,51.4253768921],"type":"Point"}
}