{
  "type": "Feature",
  "properties": {
    "iso:country":"DE",
    "sg:address":"Reichenbachstr. 62",
    "sg:city":"Dresden",
    "sg:phone":"+49 351/4713193",
    "sg:postcode":"01217",
    "sg:province":"Sachsen",
    "wof:name":"Wilfried Panitz",
    "wof:placetype":"venue"
},
  "geometry": {"coordinates":[13.7449655533,51.0314598083],"type":"Point"}
}