{
  "type": "Feature",
  "properties": {
    "iso:country":"DE",
    "sg:address":"Am Ring 12",
    "sg:city":"B\u00f6hlen",
    "sg:phone":"+49 34206/5850",
    "sg:postcode":"04564",
    "sg:province":"Sachsen",
    "wof:name":"Wvg Wohnungs- Verwaltungsges. Mbh & Co.",
    "wof:placetype":"venue"
},
  "geometry": {"coordinates":[12.3876371384,51.2100715637],"type":"Point"}
}