{
  "type": "Feature",
  "properties": {
    "iso:country":"DE",
    "sg:address":"Hubertshalde 14",
    "sg:city":"Wilhelmsdorf",
    "sg:phone":"+49 7503/754",
    "sg:postcode":"88271",
    "sg:province":"Baden-W\u00fcrttemberg",
    "wof:name":"Christel Brodd Hebamme",
    "wof:placetype":"venue"
},
  "geometry": {"coordinates":[9.428865,47.863651],"type":"Point"}
}