{
  "type": "Feature",
  "properties": {
    "iso:country":"DE",
    "sg:address":"Friedrichstr. 41",
    "sg:city":"Wermelskirchen",
    "sg:phone":"+49 2196/2302",
    "sg:postcode":"42929",
    "sg:province":"Nordrhein-Westfalen",
    "wof:name":"Pietro Frangiamone",
    "wof:placetype":"venue"
},
  "geometry": {"coordinates":[7.2037620544,51.1345863342],"type":"Point"}
}