{
  "type": "Feature",
  "properties": {
    "iso:country":"DE",
    "sg:address":"Bahnhofsweg 7",
    "sg:city":"Stolpen",
    "sg:phone":"+49 35973/6506",
    "sg:postcode":"01833",
    "sg:province":"Sachsen",
    "wof:name":"Siegfried Lehmann",
    "wof:placetype":"venue"
},
  "geometry": {"coordinates":[14.079557,51.04723],"type":"Point"}
}