{
  "type": "Feature",
  "properties": {
    "iso:country":"DE",
    "sg:address":"Murrhardter Str 73",
    "sg:city":"Welzheim",
    "sg:phone":"+49 791/59505",
    "sg:postcode":"73642",
    "sg:province":"Baden-W\u00fcrttemberg",
    "wof:name":"Teco Technische Componenten Gmbh",
    "wof:placetype":"venue"
},
  "geometry": {"coordinates":[9.73924,49.09901],"type":"Point"}
}