{
  "type": "Feature",
  "properties": {
    "iso:country":"DE",
    "sg:address":"Vorderhainberg",
    "sg:city":"Ortenburg",
    "sg:phone":"+49 8542/2171",
    "sg:postcode":"94496",
    "sg:province":"Bayern",
    "wof:name":"Felix Eberle Masseur",
    "wof:placetype":"venue"
},
  "geometry": {"coordinates":[13.234776,48.544342],"type":"Point"}
}