{
  "type": "Feature",
  "properties": {
    "iso:country":"DE",
    "sg:address":"Oerschbachstr. 41-43",
    "sg:city":"D\u00fcsseldorf",
    "sg:phone":"+49 211/97960",
    "sg:postcode":"40599",
    "sg:province":"Nordrhein-Westfalen",
    "wof:name":"G\u00fcnther & Lochte Verwaltungsges. Mbh",
    "wof:placetype":"venue"
},
  "geometry": {"coordinates":[6.853675,51.183334],"type":"Point"}
}