{
  "type": "Feature",
  "properties": {
    "iso:country":"DE",
    "sg:address":"Keltenweg 87",
    "sg:city":"Kaiserslautern",
    "sg:phone":"+49 631/98323",
    "sg:postcode":"67663",
    "sg:province":"Rheinland-Pfalz",
    "wof:name":"Km Gesellschaft F\u00fcr Modernen Wohnungsbau Mbh",
    "wof:placetype":"venue"
},
  "geometry": {"coordinates":[7.719545,49.435452],"type":"Point"}
}