{
  "type": "Feature",
  "properties": {
    "iso:country":"DE",
    "sg:address":"Moltkestr. 62",
    "sg:city":"Hamburg",
    "sg:postcode":"20253",
    "sg:province":"Hamburg",
    "wof:name":"Second Floor Left Gmbh",
    "wof:placetype":"venue"
},
  "geometry": {"coordinates":[9.9708251953,53.5809898376],"type":"Point"}
}