{
  "type": "Feature",
  "properties": {
    "iso:country":"DE",
    "sg:address":"Schwerter Str. 295",
    "sg:city":"Dortmund",
    "sg:phone":"+49 231/443449",
    "sg:postcode":"44287",
    "sg:province":"Nordrhein-Westfalen",
    "wof:name":"Hans Bookjans Textilhandel Gmbh",
    "wof:placetype":"venue"
},
  "geometry": {"coordinates":[7.5690398216,51.4847793579],"type":"Point"}
}