{
  "type": "Feature",
  "properties": {
    "iso:country":"DE",
    "sg:address":"Alte Niederstr. 136",
    "sg:city":"Recklinghausen",
    "sg:phone":"+49 2361/943310",
    "sg:postcode":"45665",
    "sg:province":"Nordrhein-Westfalen",
    "wof:name":"Gregor Bomholt",
    "wof:placetype":"venue"
},
  "geometry": {"coordinates":[7.253211,51.59679],"type":"Point"}
}