{
  "type": "Feature",
  "properties": {
    "iso:country":"DE",
    "sg:address":"Uhlandstr. 32",
    "sg:city":"Sulz",
    "sg:phone":"+49 7454/8624",
    "sg:postcode":"72172",
    "sg:province":"Baden-W\u00fcrttemberg",
    "wof:name":"F. Buehner",
    "wof:placetype":"venue"
},
  "geometry": {"coordinates":[8.6967258453,48.3806533813],"type":"Point"}
}