{
  "type": "Feature",
  "properties": {
    "iso:country":"DE",
    "sg:address":"Braunschweiger Heerstr. 96",
    "sg:city":"Celle",
    "sg:phone":"+49 5141/98660",
    "sg:postcode":"29227",
    "sg:province":"Niedersachsen",
    "wof:name":"Trispel Gmbh",
    "wof:placetype":"venue"
},
  "geometry": {"coordinates":[10.1117610931,52.5939674377],"type":"Point"}
}