{
  "type": "Feature",
  "properties": {
    "iso:country":"DE",
    "sg:address":"Lauackerweg 5",
    "sg:city":"Pforzheim",
    "sg:phone":"+49 7231/970740",
    "sg:postcode":"75181",
    "sg:province":"Baden-W\u00fcrttemberg",
    "wof:name":"Mh Schmuck Gmbh",
    "wof:placetype":"venue"
},
  "geometry": {"coordinates":[8.7314081192,48.8546867371],"type":"Point"}
}