{
  "type": "Feature",
  "properties": {
    "iso:country":"DE",
    "sg:address":"Johanniskirchplatz 6",
    "sg:city":"Brandenburg",
    "sg:phone":"+49 3381/522371",
    "sg:postcode":"14770",
    "sg:province":"Brandenburg",
    "wof:name":"Hans-joachim Braune",
    "wof:placetype":"venue"
},
  "geometry": {"coordinates":[12.5550718307,52.4118537903],"type":"Point"}
}