{
  "type": "Feature",
  "properties": {
    "iso:country":"DE",
    "sg:address":"Hierstetterweg 8",
    "sg:city":"Furth im Wald",
    "sg:phone":"+49 9973/2777",
    "sg:postcode":"93437",
    "sg:province":"Bayern",
    "wof:name":"Franz Macht",
    "wof:placetype":"venue"
},
  "geometry": {"coordinates":[12.831752,49.306549],"type":"Point"}
}