{
  "type": "Feature",
  "properties": {
    "iso:country":"DE",
    "sg:address":"Hohe Gasse 2",
    "sg:city":"Ringgau",
    "sg:phone":"+49 5659/317",
    "sg:postcode":"37296",
    "sg:province":"Hessen",
    "wof:name":"Helmut Franke",
    "wof:placetype":"venue"
},
  "geometry": {"coordinates":[10.129673,51.088097],"type":"Point"}
}