{
  "type": "Feature",
  "properties": {
    "iso:country":"DE",
    "sg:address":"Peutestr. 57-59",
    "sg:city":"Hamburg",
    "sg:phone":"+49 40/7809820",
    "sg:postcode":"20539",
    "sg:province":"Hamburg",
    "wof:name":"Ascalia Gesellschaft F\u00fcr Entsorgung Von Sonder-",
    "wof:placetype":"venue"
},
  "geometry": {"coordinates":[10.049626,53.519764],"type":"Point"}
}