{
  "type": "Feature",
  "properties": {
    "iso:country":"DE",
    "sg:address":"S\u00fcdweststr. 16",
    "sg:city":"Bergheim",
    "sg:phone":"+49 2271/42742",
    "sg:postcode":"50126",
    "sg:province":"Nordrhein-Westfalen",
    "wof:name":"T. Wolf",
    "wof:placetype":"venue"
},
  "geometry": {"coordinates":[6.6410861015,50.9526557922],"type":"Point"}
}