{
  "type": "Feature",
  "properties": {
    "iso:country":"DE",
    "sg:address":"Domshof 26",
    "sg:city":"Bremen",
    "sg:postcode":"28195",
    "sg:province":"Bremen",
    "wof:name":"Bremische Grundst\u00fccks- Gmbh",
    "wof:placetype":"venue"
},
  "geometry": {"coordinates":[8.8087978363,53.0764427185],"type":"Point"}
}