{"geometry":{"type":"Point","coordinates":[7.347020,52.546329]},"type":"Feature","id":102560845,"bbox":[7.347020,52.546329,7.347020,52.546329],"properties":{"sg:province":"Niedersachsen","geom:longitude":7.347020,"wof:breaches":[],"sg:href":"http://api.simplegeo.com/1.0/features/SG_3fWp5Abz7ReuPhM9K535Nc_52.546329_7.347020@1306268793.json","sg:owner":"simplegeo","sg:postcode":"49811","geom:latitude":52.546329,"sg:classifiers":[],"sg:address":"Friedrich-Ebert-Str. 132::","sg:phone":"+49 4959/17021","wof:hierarchy":[{"locality_id":101748833,"venue_id":102560845,"country_id":85633111,"region_id":85682555,"county_id":102063975}],"geom:area":0.000000,"sg:city":"Lingen","wof:lastmodified":1438093379,"iso:country":"DE","wof:geomhash":"2f6290ca70c60099687b08725222e2f9","wof:name":"Zweckverband Schlachthof Emsland","wof:belongsto":[101748833,85633111,85682555,102063975],"src:geom":"simplegeo","wof:placetype":"venue","wof:supersedes":[],"wof:id":102560845,"wof:superseded_by":[],"wof:concordances":{"sg:id":"SG_3fWp5Abz7ReuPhM9K535Nc_52.546329_7.347020@1306268793"},"wof:parent_id":101748833}}