{
  "type": "Feature",
  "properties": {
    "iso:country":"DE",
    "sg:address":"K\u00f6lner Str. 83",
    "sg:city":"Lennestadt",
    "sg:phone":"+49 2721/3070",
    "sg:postcode":"57368",
    "sg:province":"Nordrhein-Westfalen",
    "wof:name":"Aral Ag Josef Zingler",
    "wof:placetype":"venue"
},
  "geometry": {"coordinates":[8.0146131516,51.1386604309],"type":"Point"}
}