{
  "type": "Feature",
  "properties": {
    "iso:country":"DE",
    "sg:address":"Lindenstr. 33-35",
    "sg:city":"B\u00f6hl-Iggelheim",
    "sg:phone":"+49 4963/2496690",
    "sg:postcode":"67459",
    "sg:province":"Rheinland-Pfalz",
    "wof:name":"S\u00dcd-b\u00d6l Metall- & Kunststoffverarbeitung Gmbh",
    "wof:placetype":"venue"
},
  "geometry": {"coordinates":[8.289826,49.386913],"type":"Point"}
}