{
  "type": "Feature",
  "properties": {
    "iso:country":"DE",
    "sg:address":"Kreuzherrenstr. 2",
    "sg:city":"Medebach",
    "sg:phone":"+49 2982/683",
    "sg:postcode":"59964",
    "sg:province":"Nordrhein-Westfalen",
    "wof:name":"Pension K.-j. Frankenstein",
    "wof:placetype":"venue"
},
  "geometry": {"coordinates":[8.6676111221,51.1702461243],"type":"Point"}
}