{
  "type": "Feature",
  "properties": {
    "iso:country":"DE",
    "sg:address":"Heusteigstr. 34",
    "sg:city":"Stuttgart",
    "sg:postcode":"70180",
    "sg:province":"Baden-W\u00fcrttemberg",
    "wof:name":"Hilfen F\u00fcr Fl\u00fcchtlinge Aus Eritrea Und \u00c4thiopien",
    "wof:placetype":"venue"
},
  "geometry": {"coordinates":[9.1789503098,48.7699966431],"type":"Point"}
}