{
  "type": "Feature",
  "properties": {
    "iso:country":"DE",
    "sg:address":"M\u00fchlfeldstr. 3",
    "sg:city":"Lahr",
    "sg:phone":"+49 7821/43954",
    "sg:postcode":"77933",
    "sg:province":"Baden-W\u00fcrttemberg",
    "wof:name":"Winzergenossenschaft Lahr Eg",
    "wof:placetype":"venue"
},
  "geometry": {"coordinates":[7.8357338905,48.3640174866],"type":"Point"}
}