{
  "type": "Feature",
  "properties": {
    "iso:country":"DE",
    "sg:address":"Wormser Str. 21",
    "sg:city":"Speyer",
    "sg:phone":"+49 6232/620435",
    "sg:postcode":"67346",
    "sg:province":"Rheinland-Pfalz",
    "wof:name":"B. Von B\u00fcren",
    "wof:placetype":"venue"
},
  "geometry": {"coordinates":[8.4324808121,49.3199043274],"type":"Point"}
}