{
  "type": "Feature",
  "properties": {
    "iso:country":"DE",
    "sg:address":"Pettenkoferstrasse 46",
    "sg:city":"Munich",
    "sg:phone":"+49 89/51519670",
    "sg:postcode":"80336",
    "sg:province":"Bayern",
    "wof:name":"W W W . S K A T E W I N G . C O M",
    "wof:placetype":"venue"
},
  "geometry": {"coordinates":[11.553907,48.135262],"type":"Point"}
}