{
  "type": "Feature",
  "properties": {
    "iso:country":"DE",
    "sg:address":"Hauptstr. 4",
    "sg:city":"Wennigsen",
    "sg:phone":"+49 5103/3434",
    "sg:postcode":"30974",
    "sg:province":"Niedersachsen",
    "wof:name":"Dr. Karl Meinecke Tierarzt",
    "wof:placetype":"venue"
},
  "geometry": {"coordinates":[9.5718946457,52.2731742859],"type":"Point"}
}