{
  "type": "Feature",
  "properties": {
    "iso:country":"DE",
    "sg:address":"Obere K\u00f6nigsstr. 26",
    "sg:city":"Kassel",
    "sg:phone":"+49 561/16354",
    "sg:postcode":"34117",
    "sg:province":"Hessen",
    "wof:name":"Jersey Ilany",
    "wof:placetype":"venue"
},
  "geometry": {"coordinates":[9.494296,51.313419],"type":"Point"}
}