{
  "type": "Feature",
  "properties": {
    "iso:country":"DE",
    "sg:address":"Dorfplatz 18",
    "sg:city":"Friedersdorf",
    "sg:phone":"+49 3493/511403",
    "sg:postcode":"06749",
    "sg:province":"Sachsen-Anhalt",
    "wof:name":"Metallbau Henning Gmbh",
    "wof:placetype":"venue"
},
  "geometry": {"coordinates":[12.366818428,51.6469955444],"type":"Point"}
}