{
  "type": "Feature",
  "properties": {
    "iso:country":"DE",
    "sg:address":"Bereiteranger 1",
    "sg:city":"M\u00fcnchen",
    "sg:phone":"+49 89/654680",
    "sg:postcode":"81541",
    "sg:province":"Bayern",
    "wof:name":"Angelika Schramm Heilpraktikerin",
    "wof:placetype":"venue"
},
  "geometry": {"coordinates":[11.5794334412,48.1268081665],"type":"Point"}
}