{
  "type": "Feature",
  "properties": {
    "iso:country":"DE",
    "sg:address":"Neusath 44",
    "sg:city":"Nabburg",
    "sg:phone":"+49 9433/6113",
    "sg:postcode":"92507",
    "sg:province":"Bayern",
    "wof:name":"Hans Mauthner",
    "wof:placetype":"venue"
},
  "geometry": {"coordinates":[12.2178888321,49.4667129517],"type":"Point"}
}