{
  "type": "Feature",
  "properties": {
    "iso:country":"DE",
    "sg:address":"Schlo\u00dfallee 7-9",
    "sg:city":"Herzebrock-Clarholz",
    "sg:phone":"+49 5245/87130",
    "sg:postcode":"33442",
    "sg:province":"Nordrhein-Westfalen",
    "wof:name":"Vossen Frottierwaren- Vertriebsgesellschaft Mbh",
    "wof:placetype":"venue"
},
  "geometry": {"coordinates":[8.2102003098,51.8609352112],"type":"Point"}
}