{
  "type": "Feature",
  "properties": {
    "iso:country":"DE",
    "sg:address":"Schaffhauser Str. 35",
    "sg:city":"Jestetten",
    "sg:phone":"+49 7745/7250",
    "sg:postcode":"79798",
    "sg:province":"Baden-W\u00fcrttemberg",
    "wof:name":"Red Rose",
    "wof:placetype":"venue"
},
  "geometry": {"coordinates":[8.576242,47.653484],"type":"Point"}
}