{
  "type": "Feature",
  "properties": {
    "iso:country":"DE",
    "sg:address":"Langer Acker 22",
    "sg:city":"Wedemark-Bissendorf",
    "sg:phone":"+49 5130/58890",
    "sg:postcode":"30900",
    "sg:province":"Niedersachsen",
    "wof:name":"Cvs-chemie-vertriebs-u.service Gmbh - Ein Unternehmen Der Pelox",
    "wof:placetype":"venue"
},
  "geometry": {"coordinates":[9.7411003113,52.5176963806],"type":"Point"}
}