{
  "type": "Feature",
  "properties": {
    "iso:country":"DE",
    "sg:address":"Fritz-Erler-Str. 12",
    "sg:city":"D\u00fcren",
    "sg:phone":"+49 2421/41136",
    "sg:postcode":"52349",
    "sg:province":"Nordrhein-Westfalen",
    "wof:name":"M\u00f6bel-halle Gisbert M\u00fcller",
    "wof:placetype":"venue"
},
  "geometry": {"coordinates":[6.4746880531,50.8077812195],"type":"Point"}
}