{
  "type": "Feature",
  "properties": {
    "iso:country":"DE",
    "sg:address":"Hauptstr. 146",
    "sg:city":"Idar-Oberstein",
    "sg:phone":"+49 6781/981761",
    "sg:postcode":"55743",
    "sg:province":"Rheinland-Pfalz",
    "wof:name":"Sks Schmuck Gmbh",
    "wof:placetype":"venue"
},
  "geometry": {"coordinates":[7.307114,49.717636],"type":"Point"}
}