{
  "type": "Feature",
  "properties": {
    "iso:country":"DE",
    "sg:address":"Lippramsdorfer Str. 347",
    "sg:city":"Dorsten",
    "sg:phone":"+49 2369/98300",
    "sg:postcode":"46286",
    "sg:province":"Nordrhein-Westfalen",
    "wof:name":"Peter Michalski Gmbh",
    "wof:placetype":"venue"
},
  "geometry": {"coordinates":[7.0372028351,51.7499275208],"type":"Point"}
}