{
  "type": "Feature",
  "properties": {
    "iso:country":"DE",
    "sg:address":"D\u00fcrrbachtal 30",
    "sg:city":"W\u00fcrzburg",
    "sg:phone":"+49 931/95751",
    "sg:postcode":"97080",
    "sg:province":"Bayern",
    "wof:name":"Dr. Horst Und Melita Klose Rechtsanw\u00e4lte",
    "wof:placetype":"venue"
},
  "geometry": {"coordinates":[9.9184703827,49.8187789917],"type":"Point"}
}