{
  "type": "Feature",
  "properties": {
    "iso:country":"DE",
    "sg:address":"Richard-Wagner-Str. 5",
    "sg:city":"M\u00fcnzenberg",
    "sg:phone":"+49 6033/60662",
    "sg:postcode":"35516",
    "sg:province":"Hessen",
    "wof:name":"B\u00e4rbel Schwab",
    "wof:placetype":"venue"
},
  "geometry": {"coordinates":[8.734161,50.462875],"type":"Point"}
}