{
  "type": "Feature",
  "properties": {
    "iso:country":"DE",
    "sg:address":"Preu\u00dfenallee 3-5",
    "sg:city":"Berlin",
    "sg:phone":"+49 30/2830540",
    "sg:postcode":"14052",
    "sg:province":"Berlin",
    "wof:name":"Eigene 4 W\u00e4nde Baubetreuungs Gmbh",
    "wof:placetype":"venue"
},
  "geometry": {"coordinates":[13.258794,52.509144],"type":"Point"}
}