{
  "type": "Feature",
  "properties": {
    "iso:country":"DE",
    "sg:address":"Bonner Talweg 8",
    "sg:city":"Bonn",
    "sg:phone":"+49 228/949160",
    "sg:postcode":"53113",
    "sg:province":"Nordrhein-Westfalen",
    "wof:name":"P. A\u00dfmann Rechtsanwalt",
    "wof:placetype":"venue"
},
  "geometry": {"coordinates":[7.0991330147,50.728099823],"type":"Point"}
}