{
  "type": "Feature",
  "properties": {
    "iso:country":"DE",
    "sg:address":"Trensweg 5",
    "sg:city":"Edemissen",
    "sg:postcode":"31234",
    "sg:province":"Niedersachsen",
    "wof:name":"Homepage Der Spd Edemissen",
    "wof:placetype":"venue"
},
  "geometry": {"coordinates":[10.254192,52.386692],"type":"Point"}
}