{
  "type": "Feature",
  "properties": {
    "iso:country":"DE",
    "sg:address":"H\u00f6rsten 3",
    "sg:city":"F\u00fcrstenau",
    "sg:phone":"+49 5901/1275",
    "sg:postcode":"49584",
    "sg:province":"Niedersachsen",
    "wof:name":"Josef Richter",
    "wof:placetype":"venue"
},
  "geometry": {"coordinates":[7.70736,52.47599],"type":"Point"}
}