{
  "type": "Feature",
  "properties": {
    "iso:country":"DE",
    "sg:address":"Passauer Str. 18",
    "sg:city":"Winzer",
    "sg:phone":"+49 9901/901459",
    "sg:postcode":"94577",
    "sg:province":"Bayern",
    "wof:name":"Gotthard Weber",
    "wof:placetype":"venue"
},
  "geometry": {"coordinates":[13.067963,48.726635],"type":"Point"}
}