{
  "type": "Feature",
  "properties": {
    "iso:country":"DE",
    "sg:address":"Schlatweg 13",
    "sg:city":"Schlierbach",
    "sg:phone":"+49 7021/2895",
    "sg:postcode":"73278",
    "sg:province":"Baden-W\u00fcrttemberg",
    "wof:name":"K. K\u00e4lberer Immobilienmakler",
    "wof:placetype":"venue"
},
  "geometry": {"coordinates":[9.5220384598,48.6711730957],"type":"Point"}
}