{
  "type": "Feature",
  "properties": {
    "iso:country":"DE",
    "sg:address":"Eberhardstr. 12",
    "sg:city":"Ludwigsburg",
    "sg:phone":"+49 7141/923779",
    "sg:postcode":"71634",
    "sg:province":"Baden-W\u00fcrttemberg",
    "wof:name":"Armin Feuerstein M\u00f6bel-polsterm\u00f6bel",
    "wof:placetype":"venue"
},
  "geometry": {"coordinates":[9.1929397583,48.8970184326],"type":"Point"}
}