{
  "type": "Feature",
  "properties": {
    "iso:country":"DE",
    "sg:address":"Hafenstr. 144",
    "sg:city":"Bremerhaven",
    "sg:phone":"+49 471/805580",
    "sg:postcode":"27576",
    "sg:province":"Bremen",
    "wof:name":"Se-pressereisen Gmbh",
    "wof:placetype":"venue"
},
  "geometry": {"coordinates":[8.5861959457,53.5608024597],"type":"Point"}
}