{
  "type": "Feature",
  "properties": {
    "iso:country":"DE",
    "sg:address":"Lockenfeld 7",
    "sg:city":"Marienheide",
    "sg:phone":"+49 2261/21027",
    "sg:postcode":"51709",
    "sg:province":"Nordrhein-Westfalen",
    "wof:name":"Rosenthal Maschinenbau Gmbh",
    "wof:placetype":"venue"
},
  "geometry": {"coordinates":[7.546301,51.053871],"type":"Point"}
}