{
  "type": "Feature",
  "properties": {
    "iso:country":"DE",
    "sg:address":"Marie-Curie-Str. 22",
    "sg:city":"Neum\u00fcnster",
    "sg:phone":"+49 4321/909210",
    "sg:postcode":"24537",
    "sg:province":"Schleswig-Holstein",
    "wof:name":"P. Hu\u00df Ingenieur",
    "wof:placetype":"venue"
},
  "geometry": {"coordinates":[9.964966774,54.1038169861],"type":"Point"}
}