{
  "type": "Feature",
  "properties": {
    "iso:country":"DE",
    "sg:address":"Palmaille 108",
    "sg:city":"Hamburg",
    "sg:phone":"+49 40/38618850",
    "sg:postcode":"22767",
    "sg:province":"Hamburg",
    "wof:name":"Hans Molenda Rechtsanwalt",
    "wof:placetype":"venue"
},
  "geometry": {"coordinates":[9.9383974075,53.5465202332],"type":"Point"}
}