{
  "type": "Feature",
  "properties": {
    "iso:country":"DE",
    "sg:address":"Schlo\u00dfstr. 15",
    "sg:city":"Ober-Ramstadt",
    "sg:phone":"+49 6154/3611",
    "sg:postcode":"64372",
    "sg:province":"Hessen",
    "wof:name":"Dorfschmiede",
    "wof:placetype":"venue"
},
  "geometry": {"coordinates":[8.7841434479,49.8119506836],"type":"Point"}
}