{
  "type": "Feature",
  "properties": {
    "iso:country":"DE",
    "sg:address":"Hans-Urmiller-Ring 24",
    "sg:city":"Wolfratshausen",
    "sg:phone":"+49 8171/42220",
    "sg:postcode":"82515",
    "sg:province":"Bayern",
    "wof:name":"Pek 3 Electronic Gmbh",
    "wof:placetype":"venue"
},
  "geometry": {"coordinates":[11.425181,47.903702],"type":"Point"}
}