{
  "type": "Feature",
  "properties": {
    "iso:country":"DE",
    "sg:address":"Busendorf 19",
    "sg:city":"Rattelsdorf",
    "sg:phone":"+49 9533/518",
    "sg:postcode":"96179",
    "sg:province":"Bayern",
    "wof:name":"Bruno Schug",
    "wof:placetype":"venue"
},
  "geometry": {"coordinates":[10.864704,50.077881],"type":"Point"}
}