{
  "type": "Feature",
  "properties": {
    "iso:country":"DE",
    "sg:address":"Baumeisterstr. 10",
    "sg:city":"M\u00fcnchen",
    "sg:phone":"+49 89/7911732",
    "sg:postcode":"81477",
    "sg:province":"Bayern",
    "wof:name":"J\u00f6rg Schlagenhauf Immobilien Gmbh",
    "wof:placetype":"venue"
},
  "geometry": {"coordinates":[11.512405,48.082157],"type":"Point"}
}