{
  "type": "Feature",
  "properties": {
    "iso:country":"DE",
    "sg:address":"Am Drosselschlag 24",
    "sg:city":"Heuchelheim",
    "sg:postcode":"35452",
    "sg:province":"Hessen",
    "wof:name":"Info Line Leib Gmbh",
    "wof:placetype":"venue"
},
  "geometry": {"coordinates":[8.62071,50.582947],"type":"Point"}
}