{
  "type": "Feature",
  "properties": {
    "iso:country":"DE",
    "sg:address":"Hintere Schildstr. 6",
    "sg:city":"Dortmund",
    "sg:phone":"+49 231/422643",
    "sg:postcode":"44263",
    "sg:province":"Nordrhein-Westfalen",
    "wof:name":"Artemis",
    "wof:placetype":"venue"
},
  "geometry": {"coordinates":[7.500307,51.486961],"type":"Point"}
}