{
  "type": "Feature",
  "properties": {
    "iso:country":"DE",
    "sg:address":"Friesengasse 8",
    "sg:city":"Frankfurt",
    "sg:phone":"+49 69/703089",
    "sg:postcode":"60487",
    "sg:province":"Hessen",
    "wof:name":"Martin M\u00fcller",
    "wof:placetype":"venue"
},
  "geometry": {"coordinates":[8.639933,50.123989],"type":"Point"}
}