{
  "type": "Feature",
  "properties": {
    "iso:country":"DE",
    "sg:address":"Dorfstr. 1",
    "sg:city":"Martinsrieth",
    "sg:phone":"+49 34656/30004",
    "sg:postcode":"06528",
    "sg:province":"Sachsen-Anhalt",
    "wof:name":"Gemeindesch\u00e4nke",
    "wof:placetype":"venue"
},
  "geometry": {"coordinates":[11.243601799,51.4408302307],"type":"Point"}
}