{
  "type": "Feature",
  "properties": {
    "iso:country":"DE",
    "sg:address":"Im Bultfeld 55",
    "sg:city":"Hemmingen",
    "sg:phone":"+49 5101/2155",
    "sg:postcode":"30966",
    "sg:province":"Niedersachsen",
    "wof:name":"Georg Becker Lebensmittel",
    "wof:placetype":"venue"
},
  "geometry": {"coordinates":[9.7336988449,52.3059577942],"type":"Point"}
}