{
  "type": "Feature",
  "properties": {
    "iso:country":"DE",
    "sg:address":"Rinnigweg 5",
    "sg:city":"R\u00f6ttenbach",
    "sg:phone":"+49 9195/6005",
    "sg:postcode":"91341",
    "sg:province":"Bayern",
    "wof:name":"Kraus & Gutbier",
    "wof:placetype":"venue"
},
  "geometry": {"coordinates":[10.929084,49.673809],"type":"Point"}
}