{
  "type": "Feature",
  "properties": {
    "iso:country":"DE",
    "sg:address":"Brunnenwiesen 16/1",
    "sg:city":"Neuhausen",
    "sg:phone":"+49 7234",
    "sg:postcode":"75242",
    "sg:province":"Baden-W\u00fcrttemberg",
    "wof:name":"Bodamer Kunststoffglas,\u00dcberdachungen,duschkabinen",
    "wof:placetype":"venue"
},
  "geometry": {"coordinates":[8.7831115723,48.7933425903],"type":"Point"}
}