{
  "type": "Feature",
  "properties": {
    "iso:country":"DE",
    "sg:address":"Uhlenhorster Weg 34",
    "sg:city":"Hamburg",
    "sg:phone":"+49 40/503673",
    "sg:postcode":"22085",
    "sg:province":"Hamburg",
    "wof:name":"Herbert Leibing",
    "wof:placetype":"venue"
},
  "geometry": {"coordinates":[10.020939827,53.5686759949],"type":"Point"}
}