{
  "type": "Feature",
  "properties": {
    "iso:country":"DE",
    "sg:address":"Karl-Lerbs-Str. 8",
    "sg:city":"Bremen",
    "sg:phone":"+49 421/559113",
    "sg:postcode":"28201",
    "sg:province":"Bremen",
    "wof:name":"Merlau Reisen Inh. Monika Merlau",
    "wof:placetype":"venue"
},
  "geometry": {"coordinates":[8.798157692,53.0594673157],"type":"Point"}
}