{
  "type": "Feature",
  "properties": {
    "iso:country":"DE",
    "sg:address":"Bremer Str. 73",
    "sg:city":"Hamburg",
    "sg:phone":"+49 40/779414",
    "sg:postcode":"21073",
    "sg:province":"Hamburg",
    "wof:name":"Redaktion Fl\u00fcstert\u00fcte Freie Sportvereinigung",
    "wof:placetype":"venue"
},
  "geometry": {"coordinates":[9.9760560989,53.4544219971],"type":"Point"}
}