{
  "type": "Feature",
  "properties": {
    "iso:country":"DE",
    "sg:address":"Stefan-Meier-Str. 31a",
    "sg:city":"Freiburg",
    "sg:phone":"+49 761/3196925",
    "sg:postcode":"79104",
    "sg:province":"Baden-W\u00fcrttemberg",
    "wof:name":"Www.jobs-in-freiburg.de",
    "wof:placetype":"venue"
},
  "geometry": {"coordinates":[7.84599,48.002213],"type":"Point"}
}