{
  "type": "Feature",
  "properties": {
    "iso:country":"DE",
    "sg:address":"Berliner Str. 6",
    "sg:city":"Wachtberg",
    "sg:phone":"+49 228/341664",
    "sg:postcode":"53343",
    "sg:province":"Nordrhein-Westfalen",
    "wof:name":"Fundus Gmbh & Co. Kg",
    "wof:placetype":"venue"
},
  "geometry": {"coordinates":[7.1736650467,50.6371154785],"type":"Point"}
}