{
  "type": "Feature",
  "properties": {
    "iso:country":"DE",
    "sg:address":"Freiligrathstr. 6",
    "sg:city":"Frankfurt",
    "sg:phone":"+49 69/40593772",
    "sg:postcode":"60385",
    "sg:province":"Hessen",
    "wof:name":"L. E. N. K. E. R. Industrie Handels Gmbh",
    "wof:placetype":"venue"
},
  "geometry": {"coordinates":[8.711145401,50.1208610535],"type":"Point"}
}