{
  "type": "Feature",
  "properties": {
    "iso:country":"DE",
    "sg:address":"Sterntalerweg 16",
    "sg:city":"Leipzig",
    "sg:phone":"+49 341/8774027",
    "sg:postcode":"04277",
    "sg:province":"Sachsen",
    "wof:name":"Horst Mei\u00dfner",
    "wof:placetype":"venue"
},
  "geometry": {"coordinates":[12.400472641,51.3070220947],"type":"Point"}
}