{
  "type": "Feature",
  "properties": {
    "iso:country":"DE",
    "sg:address":"Roskaul 2 a",
    "sg:city":"Baesweiler",
    "sg:phone":"+49 2401/7426",
    "sg:postcode":"52499",
    "sg:province":"Nordrhein-Westfalen",
    "wof:name":"Hilmar Koch",
    "wof:placetype":"venue"
},
  "geometry": {"coordinates":[6.1813879013,50.9070510864],"type":"Point"}
}