{
  "type": "Feature",
  "properties": {
    "iso:country":"DE",
    "sg:address":"Schulstr. 8",
    "sg:city":"Sonsbeck",
    "sg:phone":"+49 2801/4969",
    "sg:postcode":"47665",
    "sg:province":"Nordrhein-Westfalen",
    "wof:name":"Heinrich Pa\u00dfens",
    "wof:placetype":"venue"
},
  "geometry": {"coordinates":[6.381832,51.645439],"type":"Point"}
}