{
  "type": "Feature",
  "properties": {
    "iso:country":"DE",
    "sg:address":"Kurt-Schumacher-Weg 2",
    "sg:city":"Kulmbach",
    "sg:phone":"+49 9221/75884",
    "sg:postcode":"95326",
    "sg:province":"Bayern",
    "wof:name":"A. Herold",
    "wof:placetype":"venue"
},
  "geometry": {"coordinates":[11.4531326294,50.0960083008],"type":"Point"}
}