{
  "type": "Feature",
  "properties": {
    "iso:country":"DE",
    "sg:address":"Leonhard-Frank-Str. 106",
    "sg:city":"Suhl",
    "sg:phone":"+49 3681238342090",
    "sg:postcode":"98529",
    "sg:province":"Th\u00fcringen",
    "wof:name":"Max Walk & Willy Lehmann Kraftfahrzeuge-landmasch. Gmbh",
    "wof:placetype":"venue"
},
  "geometry": {"coordinates":[10.664695,50.600246],"type":"Point"}
}