{
  "type": "Feature",
  "properties": {
    "iso:country":"DE",
    "sg:address":"Rudolst\u00e4dter Str. 93",
    "sg:city":"Jena",
    "sg:phone":"+49 3641/6850",
    "sg:postcode":"07745",
    "sg:province":"Th\u00fcringen",
    "wof:name":"Jembo Motel Und Freizeit Verwaltungs Gmbh",
    "wof:placetype":"venue"
},
  "geometry": {"coordinates":[11.5882158279,50.8855743408],"type":"Point"}
}