{
  "type": "Feature",
  "properties": {
    "iso:country":"DE",
    "sg:address":"S\u00fcdkirchener Str. 22",
    "sg:city":"Selm",
    "sg:phone":"+49 2592/1312",
    "sg:postcode":"59379",
    "sg:province":"Nordrhein-Westfalen",
    "wof:name":"Johanna Thier",
    "wof:placetype":"venue"
},
  "geometry": {"coordinates":[7.472987175,51.7005767822],"type":"Point"}
}