{
  "type": "Feature",
  "properties": {
    "iso:country":"DE",
    "sg:address":"Kantstrasse 20",
    "sg:city":"Radebeul",
    "sg:phone":"+49 351/8364697",
    "sg:postcode":"01445",
    "sg:province":"Sachsen",
    "wof:name":"Eudaimonia-sachsen",
    "wof:placetype":"venue"
},
  "geometry": {"coordinates":[13.686393,51.103878],"type":"Point"}
}