{
  "type": "Feature",
  "properties": {
    "iso:country":"DE",
    "sg:address":"Auf der Strenge 13",
    "sg:city":"Hamburg",
    "sg:postcode":"22397",
    "sg:province":"Hamburg",
    "wof:name":"B\u00fcrgerverein Duvenstedt / Wohlstedt",
    "wof:placetype":"venue"
},
  "geometry": {"coordinates":[10.1545524597,53.6917266846],"type":"Point"}
}