{
  "type": "Feature",
  "properties": {
    "iso:country":"DE",
    "sg:address":"Andreas-Limmer-Str. 26",
    "sg:city":"Kronach",
    "sg:phone":"+49 9261/61720",
    "sg:postcode":"96317",
    "sg:province":"Bayern",
    "wof:name":"J\u00f6rg Krank Massagepraxis",
    "wof:placetype":"venue"
},
  "geometry": {"coordinates":[11.32936,50.2402],"type":"Point"}
}