{
  "type": "Feature",
  "properties": {
    "iso:country":"DE",
    "sg:address":"M\u00fchlenweg 2",
    "sg:city":"Zangenberg",
    "sg:phone":"+49 3441/80340",
    "sg:postcode":"06712",
    "sg:province":"Sachsen-Anhalt",
    "wof:name":"Metallbau Heppner Gmbh",
    "wof:placetype":"venue"
},
  "geometry": {"coordinates":[12.156662,51.076797],"type":"Point"}
}