{
  "type": "Feature",
  "properties": {
    "iso:country":"DE",
    "sg:address":"Heidehofweg 152",
    "sg:city":"Norderstedt",
    "sg:phone":"+49 40/5241199",
    "sg:postcode":"22850",
    "sg:province":"Schleswig-Holstein",
    "wof:name":"Wolfgang Schubert",
    "wof:placetype":"venue"
},
  "geometry": {"coordinates":[10.0193309784,53.6859588623],"type":"Point"}
}