{
  "type": "Feature",
  "properties": {
    "iso:country":"DE",
    "sg:address":"Sibylleng\u00e4\u00dfchen 2",
    "sg:city":"Wassenberg",
    "sg:phone":"+49 2432/2920",
    "sg:postcode":"41849",
    "sg:province":"Nordrhein-Westfalen",
    "wof:name":"F. J\u00e4gers Augenoptiker",
    "wof:placetype":"venue"
},
  "geometry": {"coordinates":[6.1570320129,51.1023674011],"type":"Point"}
}