{
  "type": "Feature",
  "properties": {
    "iso:country":"DE",
    "sg:address":"Lindlarer Str. 38 a",
    "sg:city":"Overath",
    "sg:phone":"+49 2204/72320",
    "sg:postcode":"51491",
    "sg:province":"Nordrhein-Westfalen",
    "wof:name":"Wilhelm Nicke",
    "wof:placetype":"venue"
},
  "geometry": {"coordinates":[7.2318668365,50.9566307068],"type":"Point"}
}