{
  "type": "Feature",
  "properties": {
    "iso:country":"DE",
    "sg:address":"Heinrich-Heine-Str. 12-14",
    "sg:city":"Falkenstein",
    "sg:postcode":"08223",
    "sg:province":"Sachsen",
    "wof:name":"Pmp Dienstleistung Gmbh",
    "wof:placetype":"venue"
},
  "geometry": {"coordinates":[12.368638,50.47765],"type":"Point"}
}