{
  "type": "Feature",
  "properties": {
    "iso:country":"DE",
    "sg:address":"Dietrichstr. 45",
    "sg:city":"Trier",
    "sg:phone":"+49 651/73190",
    "sg:postcode":"54290",
    "sg:province":"Rheinland-Pfalz",
    "wof:name":"Nicola Gross",
    "wof:placetype":"venue"
},
  "geometry": {"coordinates":[6.64072,49.756874],"type":"Point"}
}