{
  "type": "Feature",
  "properties": {
    "iso:country":"DE",
    "sg:address":"Auelsgasse 4",
    "sg:city":"Troisdorf",
    "sg:phone":"+49 2241/41341",
    "sg:postcode":"53844",
    "sg:province":"Nordrhein-Westfalen",
    "wof:name":"Elisabeth Duisberg",
    "wof:placetype":"venue"
},
  "geometry": {"coordinates":[7.107652,50.789425],"type":"Point"}
}