{
  "type": "Feature",
  "properties": {
    "iso:country":"DE",
    "sg:address":"Tr\u00fctzschlerstr. 6",
    "sg:city":"Chemnitz",
    "sg:phone":"+49 371/853336",
    "sg:postcode":"09117",
    "sg:province":"Sachsen",
    "wof:name":"Fritz Ehrentraut",
    "wof:placetype":"venue"
},
  "geometry": {"coordinates":[12.835549,50.831829],"type":"Point"}
}