{
  "type": "Feature",
  "properties": {
    "iso:country":"DE",
    "sg:address":"Industriestr 6a",
    "sg:city":"Marienheide",
    "sg:phone":"+49 2264/45900",
    "sg:postcode":"51709",
    "sg:province":"Nordrhein-Westfalen",
    "wof:name":"2 Komponenten Maschinenbau Gmbh",
    "wof:placetype":"venue"
},
  "geometry": {"coordinates":[7.563971,51.067516],"type":"Point"}
}