{
  "type": "Feature",
  "properties": {
    "iso:country":"DE",
    "sg:address":"Paul-Lincke-Weg 31",
    "sg:city":"Verl",
    "sg:phone":"+49 5246/2988",
    "sg:postcode":"33415",
    "sg:province":"Nordrhein-Westfalen",
    "wof:name":"Siegfried Kontecki",
    "wof:placetype":"venue"
},
  "geometry": {"coordinates":[8.507773,51.875114],"type":"Point"}
}