{
  "type": "Feature",
  "properties": {
    "iso:country":"DE",
    "sg:address":"Kasseler Str. 6",
    "sg:city":"Volkmarsen",
    "sg:phone":"+49 5693/7571",
    "sg:postcode":"34471",
    "sg:province":"Hessen",
    "wof:name":"Heimatstuben",
    "wof:placetype":"venue"
},
  "geometry": {"coordinates":[9.120473,51.413525],"type":"Point"}
}