{
  "type": "Feature",
  "properties": {
    "iso:country":"DE",
    "sg:address":"Weinbergstr. 1",
    "sg:city":"Ortenberg",
    "sg:phone":"+49 6046/941087",
    "sg:postcode":"63683",
    "sg:province":"Hessen",
    "wof:name":"Versicherungsagentur Lamek",
    "wof:placetype":"venue"
},
  "geometry": {"coordinates":[9.0856723785,50.3772201538],"type":"Point"}
}