{
  "type": "Feature",
  "properties": {
    "iso:country":"DE",
    "sg:address":"Danziger Str. 64",
    "sg:city":"Berlin",
    "sg:phone":"+49 30/88441617",
    "sg:postcode":"10435",
    "sg:province":"Berlin",
    "wof:name":"Unigrund Beteiligungen Ag",
    "wof:placetype":"venue"
},
  "geometry": {"coordinates":[13.4225292206,52.5392189026],"type":"Point"}
}