{
  "type": "Feature",
  "properties": {
    "iso:country":"DE",
    "sg:address":"Bockmayrstr. 9",
    "sg:city":"Tutzing",
    "sg:phone":"+49 8158/6067",
    "sg:postcode":"82327",
    "sg:province":"Bayern",
    "wof:name":"Ch Grundbesitz Gmbh",
    "wof:placetype":"venue"
},
  "geometry": {"coordinates":[11.281329155,47.9166183472],"type":"Point"}
}