{
  "type": "Feature",
  "properties": {
    "iso:country":"DE",
    "sg:address":"Schillerstr. 29",
    "sg:city":"M\u00fcnchen",
    "sg:phone":"+49 89/597295",
    "sg:postcode":"80336",
    "sg:province":"Bayern",
    "wof:name":"Wilfried Selig Architekt",
    "wof:placetype":"venue"
},
  "geometry": {"coordinates":[11.561073,48.135818],"type":"Point"}
}