{
  "type": "Feature",
  "properties": {
    "iso:country":"DE",
    "sg:address":"M\u00fcnchener Str. 160",
    "sg:city":"Ingolstadt",
    "sg:phone":"+49 841/7950",
    "sg:postcode":"85051",
    "sg:province":"Bayern",
    "wof:name":"Die Unglaubliche Schn\u00e4ppchen Aktion",
    "wof:placetype":"venue"
},
  "geometry": {"coordinates":[11.438478,48.736504],"type":"Point"}
}