{
  "type": "Feature",
  "properties": {
    "iso:country":"DE",
    "sg:address":"Feuchtwanger Str. 7",
    "sg:city":"Arberg",
    "sg:phone":"+49 9822/7469",
    "sg:postcode":"91722",
    "sg:province":"Bayern",
    "wof:name":"J. Engelhardt",
    "wof:placetype":"venue"
},
  "geometry": {"coordinates":[10.6159229279,49.1456604004],"type":"Point"}
}