{
  "type": "Feature",
  "properties": {
    "iso:country":"DE",
    "sg:address":"Im G\u00e4ssel 8",
    "sg:city":"Rothenberg",
    "sg:phone":"+49 6275/432",
    "sg:postcode":"64757",
    "sg:province":"Hessen",
    "wof:name":"Willi Beisel",
    "wof:placetype":"venue"
},
  "geometry": {"coordinates":[8.916767,49.50013],"type":"Point"}
}