{
  "type": "Feature",
  "properties": {
    "iso:country":"DE",
    "sg:address":"Breuelstr. 19",
    "sg:city":"Bramsche",
    "sg:phone":"+49 5461/2020",
    "sg:postcode":"49565",
    "sg:province":"Niedersachsen",
    "wof:name":"Werner Hollmann Rechtsanwalt Und Notar",
    "wof:placetype":"venue"
},
  "geometry": {"coordinates":[7.9767618179,52.4105491638],"type":"Point"}
}