{
  "type": "Feature",
  "properties": {
    "iso:country":"DE",
    "sg:address":"Mittelweg 4",
    "sg:city":"Schauenburg",
    "sg:phone":"+49 5601/2627",
    "sg:postcode":"34270",
    "sg:province":"Hessen",
    "wof:name":"Fr. Grabowski Elektroinstallation",
    "wof:placetype":"venue"
},
  "geometry": {"coordinates":[9.281842,51.288925],"type":"Point"}
}