{
  "type": "Feature",
  "properties": {
    "iso:country":"DE",
    "sg:address":"Nikolaistr. 2",
    "sg:city":"G\u00f6ttingen",
    "sg:phone":"+49 551/55284",
    "sg:postcode":"37073",
    "sg:province":"Niedersachsen",
    "wof:name":"Imbi\u00df Roma",
    "wof:placetype":"venue"
},
  "geometry": {"coordinates":[9.9346942902,51.5306549072],"type":"Point"}
}