{
  "type": "Feature",
  "properties": {
    "iso:country":"DE",
    "sg:address":"Drelsdorfer Str. 11",
    "sg:city":"Breklum",
    "sg:phone":"+49 4671/2309",
    "sg:postcode":"25821",
    "sg:province":"Schleswig-Holstein",
    "wof:name":"Siegfried Brodersen",
    "wof:placetype":"venue"
},
  "geometry": {"coordinates":[8.998355,54.608311],"type":"Point"}
}