{
  "type": "Feature",
  "properties": {
    "iso:country":"DE",
    "sg:address":"Eichenallee 15",
    "sg:city":"Berlin",
    "sg:postcode":"14050",
    "sg:province":"Berlin",
    "wof:name":"Moreba Baubetreuungs Gmbh",
    "wof:placetype":"venue"
},
  "geometry": {"coordinates":[13.272753,52.515972],"type":"Point"}
}