{
  "type": "Feature",
  "properties": {
    "iso:country":"DE",
    "sg:address":"ARAG-Platz 1",
    "sg:city":"D\u00fcsseldorf",
    "sg:phone":"+49 211/90860",
    "sg:postcode":"40472",
    "sg:province":"Nordrhein-Westfalen",
    "wof:name":"Cura Gesellschaft F\u00fcr Verm\u00f6gensverwaltung Und",
    "wof:placetype":"venue"
},
  "geometry": {"coordinates":[6.801636,51.249626],"type":"Point"}
}