{
  "type": "Feature",
  "properties": {
    "iso:country":"DE",
    "sg:address":"Talstr. 28",
    "sg:city":"Ingersheim",
    "sg:phone":"+49 7142/67447",
    "sg:postcode":"74379",
    "sg:province":"Baden-W\u00fcrttemberg",
    "wof:name":"Esposito Isolierungen Gmbh",
    "wof:placetype":"venue"
},
  "geometry": {"coordinates":[9.191803,48.963928],"type":"Point"}
}