{
  "type": "Feature",
  "properties": {
    "iso:country":"DE",
    "sg:address":"Rosenweg 3",
    "sg:city":"Olpe",
    "sg:phone":"+49 2761/61189",
    "sg:postcode":"57462",
    "sg:province":"Nordrhein-Westfalen",
    "wof:name":"Alfred Bieker",
    "wof:placetype":"venue"
},
  "geometry": {"coordinates":[7.841675,51.073643],"type":"Point"}
}