{
  "type": "Feature",
  "properties": {
    "iso:country":"DE",
    "sg:address":"Rudolf-Breitscheid-Str. 37",
    "sg:city":"Senftenberg",
    "sg:phone":"+49 3573/798765",
    "sg:postcode":"01968",
    "sg:province":"Brandenburg",
    "wof:name":"M. Proske Und U. B\u00f6rner",
    "wof:placetype":"venue"
},
  "geometry": {"coordinates":[14.0017204285,51.5241851807],"type":"Point"}
}