{
  "type": "Feature",
  "properties": {
    "iso:country":"DE",
    "sg:address":"Scheidestr. 17",
    "sg:city":"Hannover",
    "sg:phone":"+49 511/555553",
    "sg:postcode":"30625",
    "sg:province":"Niedersachsen",
    "wof:name":"If Boutique Inh. Ingrid Fey",
    "wof:placetype":"venue"
},
  "geometry": {"coordinates":[9.784663,52.372715],"type":"Point"}
}