{
  "type": "Feature",
  "properties": {
    "iso:country":"DE",
    "sg:address":"Landshuter Str. 26",
    "sg:city":"Mainburg",
    "sg:phone":"+49 8751/1321",
    "sg:postcode":"84048",
    "sg:province":"Bayern",
    "wof:name":"Josef Oberhofer",
    "wof:placetype":"venue"
},
  "geometry": {"coordinates":[11.7853298187,48.6388549805],"type":"Point"}
}