{
  "type": "Feature",
  "properties": {
    "iso:country":"DE",
    "sg:address":"Freibadstr. 83",
    "sg:city":"Detmold",
    "sg:phone":"+49 5231/69436",
    "sg:postcode":"32758",
    "sg:province":"Nordrhein-Westfalen",
    "wof:name":"R. Hellberg",
    "wof:placetype":"venue"
},
  "geometry": {"coordinates":[8.818,51.942719],"type":"Point"}
}