{
  "type": "Feature",
  "properties": {
    "iso:country":"DE",
    "sg:address":"Haigerlocher Str. 3",
    "sg:city":"Rottenburg",
    "sg:phone":"+49 7457/8416",
    "sg:postcode":"72108",
    "sg:province":"Baden-W\u00fcrttemberg",
    "wof:name":"Erwin Hertkorn",
    "wof:placetype":"venue"
},
  "geometry": {"coordinates":[8.81839,48.472145],"type":"Point"}
}