{
  "type": "Feature",
  "properties": {
    "iso:country":"DE",
    "sg:address":"Neckarstr. 2",
    "sg:city":"B\u00fcttelborn",
    "sg:phone":"+49 6152/4579",
    "sg:postcode":"64572",
    "sg:province":"Hessen",
    "wof:name":"Steakhaus Argentina Verica Blazic E. K.",
    "wof:placetype":"venue"
},
  "geometry": {"coordinates":[8.5409669876,49.9314155579],"type":"Point"}
}