{
  "type": "Feature",
  "properties": {
    "iso:country":"DE",
    "sg:address":"Eichendorffstr. 4",
    "sg:city":"Pressig",
    "sg:phone":"+49 9265/232",
    "sg:postcode":"96332",
    "sg:province":"Bayern",
    "wof:name":"S. Pfadenhauer",
    "wof:placetype":"venue"
},
  "geometry": {"coordinates":[11.3118038177,50.3548355103],"type":"Point"}
}