{
  "type": "Feature",
  "properties": {
    "iso:country":"DE",
    "sg:address":"Heide",
    "sg:city":"Bogel",
    "sg:phone":"+49 6772/7633",
    "sg:postcode":"56357",
    "sg:province":"Rheinland-Pfalz",
    "wof:name":"Erich Schaub Gmbh",
    "wof:placetype":"venue"
},
  "geometry": {"coordinates":[7.810994,50.189518],"type":"Point"}
}