{
  "type": "Feature",
  "properties": {
    "iso:country":"DE",
    "sg:address":"Goldschmiedstr. 10",
    "sg:city":"Neuhausen",
    "sg:phone":"+49 7234/8717",
    "sg:postcode":"75242",
    "sg:province":"Baden-W\u00fcrttemberg",
    "wof:name":"Elke L\u00f6rcher Masseurin",
    "wof:placetype":"venue"
},
  "geometry": {"coordinates":[8.7422,48.815979],"type":"Point"}
}