{
  "type": "Feature",
  "properties": {
    "iso:country":"DE",
    "sg:address":"Arndtstr. 12",
    "sg:city":"N\u00fcrnberg",
    "sg:phone":"+49 911/330874",
    "sg:postcode":"90419",
    "sg:province":"Bayern",
    "wof:name":"Blumen Hutzler Am Friedhof Inh. Pierre Thissen",
    "wof:placetype":"venue"
},
  "geometry": {"coordinates":[11.071097,49.460438],"type":"Point"}
}