{
  "type": "Feature",
  "properties": {
    "iso:country":"DE",
    "sg:address":"Neuburger Str 35",
    "sg:city":"Passau",
    "sg:phone":"+49 851/504770",
    "sg:postcode":"94032",
    "sg:province":"Bayern",
    "wof:name":"E-nfrastruktur Mehr Als Eine Standleitung",
    "wof:placetype":"venue"
},
  "geometry": {"coordinates":[13.442511,48.568378],"type":"Point"}
}