{
  "type": "Feature",
  "properties": {
    "iso:country":"DE",
    "sg:address":"Poststr. 28b",
    "sg:city":"Bremerhaven",
    "sg:phone":"+49 471/52666",
    "sg:postcode":"27576",
    "sg:province":"Bremen",
    "wof:name":"W. Bruns",
    "wof:placetype":"venue"
},
  "geometry": {"coordinates":[8.59376,53.565971],"type":"Point"}
}