{
  "type": "Feature",
  "properties": {
    "iso:country":"DE",
    "sg:address":"Georg-Urban-Str. 11",
    "sg:city":"Stutensee",
    "sg:phone":"+49 7249/7022",
    "sg:postcode":"76297",
    "sg:province":"Baden-W\u00fcrttemberg",
    "wof:name":"Dima Direktmarketing Gmbh",
    "wof:placetype":"venue"
},
  "geometry": {"coordinates":[8.511452,49.117168],"type":"Point"}
}