{
  "type": "Feature",
  "properties": {
    "iso:country":"DE",
    "sg:address":"Hauptstr. 29",
    "sg:city":"Porta Westfalica",
    "sg:phone":"+49 571/71218",
    "sg:postcode":"32457",
    "sg:province":"Nordrhein-Westfalen",
    "wof:name":"Petit",
    "wof:placetype":"venue"
},
  "geometry": {"coordinates":[8.922524,52.239223],"type":"Point"}
}