{
  "type": "Feature",
  "properties": {
    "iso:country":"DE",
    "sg:address":"Pestalozzistr. 33",
    "sg:city":"Berlin",
    "sg:phone":"+49 30/3134895",
    "sg:postcode":"10627",
    "sg:province":"Berlin",
    "wof:name":"Sottosopra",
    "wof:placetype":"venue"
},
  "geometry": {"coordinates":[13.3051757812,52.5080413818],"type":"Point"}
}