{
  "type": "Feature",
  "properties": {
    "iso:country":"DE",
    "sg:address":"Schlo\u00dfplatz 4",
    "sg:city":"Arzberg",
    "sg:phone":"+49 9233/9687",
    "sg:postcode":"95659",
    "sg:province":"Bayern",
    "wof:name":"Ernst H\u00f6llering Kunstmaler",
    "wof:placetype":"venue"
},
  "geometry": {"coordinates":[12.162745,50.056934],"type":"Point"}
}