{
  "type": "Feature",
  "properties": {
    "iso:country":"DE",
    "sg:address":"Hansestr. 22",
    "sg:city":"Borken",
    "sg:phone":"+49 2861/4850",
    "sg:postcode":"46325",
    "sg:province":"Nordrhein-Westfalen",
    "wof:name":"Armaturengro\u00dfhandlung M\u00f6ller",
    "wof:placetype":"venue"
},
  "geometry": {"coordinates":[6.883394,51.849617],"type":"Point"}
}