{
  "type": "Feature",
  "properties": {
    "iso:country":"DE",
    "sg:city":"Zschoppach",
    "sg:postcode":"04668",
    "sg:province":"Sachsen",
    "wof:name":"Gemeindeschwesterstation",
    "wof:placetype":"venue"
},
  "geometry": {"coordinates":[12.888078,51.214485],"type":"Point"}
}