{
  "type": "Feature",
  "properties": {
    "iso:country":"DE",
    "sg:address":"Kupferstr. 6",
    "sg:city":"Rheda-Wiedenbr\u00fcck",
    "sg:phone":"+49 5242/577525",
    "sg:postcode":"33378",
    "sg:province":"Nordrhein-Westfalen",
    "wof:name":"Werner Industrietechnik Gmbh",
    "wof:placetype":"venue"
},
  "geometry": {"coordinates":[8.3529348373,51.8332061768],"type":"Point"}
}