{
  "type": "Feature",
  "properties": {
    "iso:country":"DE",
    "sg:address":"Gewerbestr. 13",
    "sg:city":"Pliening",
    "sg:phone":"+49 89/9038570",
    "sg:postcode":"85652",
    "sg:province":"Bayern",
    "wof:name":"Pley-katex Karin Pleyer",
    "wof:placetype":"venue"
},
  "geometry": {"coordinates":[11.7698984146,48.1826972961],"type":"Point"}
}