{
  "type": "Feature",
  "properties": {
    "iso:country":"DE",
    "sg:address":"Dornestr. 17",
    "sg:city":"L\u00fcbeck",
    "sg:phone":"+49 451/85214",
    "sg:postcode":"23558",
    "sg:province":"Schleswig-Holstein",
    "wof:name":"Kleines Sch\u00f6n-eck",
    "wof:placetype":"venue"
},
  "geometry": {"coordinates":[10.6707210541,53.8618431091],"type":"Point"}
}