{
  "type": "Feature",
  "properties": {
    "iso:country":"DE",
    "sg:address":"Westerwikstr. 3",
    "sg:city":"Dortmund",
    "sg:phone":"+49 231/673945",
    "sg:postcode":"44379",
    "sg:province":"Nordrhein-Westfalen",
    "wof:name":"Axel Sch\u00f6nrock Steuerberater",
    "wof:placetype":"venue"
},
  "geometry": {"coordinates":[7.3678097725,51.5284309387],"type":"Point"}
}