{
  "type": "Feature",
  "properties": {
    "iso:country":"DE",
    "sg:address":"Hannoversche Str. 91",
    "sg:city":"Osnabr\u00fcck",
    "sg:postcode":"49084",
    "sg:province":"Niedersachsen",
    "wof:name":"Piepenbrock Geb\u00e4ude-management",
    "wof:placetype":"venue"
},
  "geometry": {"coordinates":[8.080619,52.259789],"type":"Point"}
}