{
  "type": "Feature",
  "properties": {
    "iso:country":"DE",
    "sg:address":"Am Markt 3",
    "sg:city":"Wesselburen",
    "sg:phone":"+49 4833/429555",
    "sg:postcode":"25764",
    "sg:province":"Schleswig-Holstein",
    "wof:name":"B. Wicht Masseur",
    "wof:placetype":"venue"
},
  "geometry": {"coordinates":[8.921655,54.212105],"type":"Point"}
}