{
  "type": "Feature",
  "properties": {
    "iso:country":"DE",
    "sg:address":"Stiftstr. 1",
    "sg:city":"Zwickau",
    "sg:phone":"+49 375/3541251",
    "sg:postcode":"08056",
    "sg:province":"Sachsen",
    "wof:name":"Stadtwerke Zwickau Holding Gmbh",
    "wof:placetype":"venue"
},
  "geometry": {"coordinates":[12.48671,50.718128],"type":"Point"}
}