{
  "type": "Feature",
  "properties": {
    "iso:country":"DE",
    "sg:address":"Neue Dorfstr. 11",
    "sg:city":"Godern",
    "sg:postcode":"19065",
    "sg:province":"Mecklenburg-Vorpommern",
    "wof:name":"J. F. Schneider Ohg",
    "wof:placetype":"venue"
},
  "geometry": {"coordinates":[11.541125,53.618069],"type":"Point"}
}