{
  "type": "Feature",
  "properties": {
    "iso:country":"DE",
    "sg:address":"Goethestr. 28",
    "sg:city":"Meerane",
    "sg:phone":"+49 3764/2891",
    "sg:postcode":"08393",
    "sg:province":"Sachsen",
    "wof:name":"U. Lorenz",
    "wof:placetype":"venue"
},
  "geometry": {"coordinates":[12.4570245743,50.8430366516],"type":"Point"}
}