{
  "type": "Feature",
  "properties": {
    "iso:country":"DE",
    "sg:address":"Blumenstr. 6",
    "sg:city":"Augsburg",
    "sg:phone":"+49 821/33110",
    "sg:postcode":"86152",
    "sg:province":"Bayern",
    "wof:name":"Ramsau",
    "wof:placetype":"venue"
},
  "geometry": {"coordinates":[10.8834218979,48.3733558655],"type":"Point"}
}