{
  "type": "Feature",
  "properties": {
    "iso:country":"DE",
    "sg:address":"Renzel 10",
    "sg:city":"Varrel",
    "sg:phone":"+49 5774/395",
    "sg:postcode":"27259",
    "sg:province":"Niedersachsen",
    "wof:name":"Ernst Fleddermann",
    "wof:placetype":"venue"
},
  "geometry": {"coordinates":[8.726697,52.578671],"type":"Point"}
}