{
  "type": "Feature",
  "properties": {
    "iso:country":"DE",
    "sg:address":"Am Wall 38",
    "sg:city":"Recke",
    "sg:phone":"+49 5453/7466",
    "sg:postcode":"49509",
    "sg:province":"Nordrhein-Westfalen",
    "wof:name":"Josef Kleingers",
    "wof:placetype":"venue"
},
  "geometry": {"coordinates":[7.726211,52.375088],"type":"Point"}
}