{
  "type": "Feature",
  "properties": {
    "iso:country":"DE",
    "sg:address":"Ochsenzoller Str. 195",
    "sg:city":"Norderstedt",
    "sg:phone":"+49 40/52883642",
    "sg:postcode":"22848",
    "sg:province":"Schleswig-Holstein",
    "wof:name":"L & S Trading Gmbh",
    "wof:placetype":"venue"
},
  "geometry": {"coordinates":[9.9938831329,53.6818580627],"type":"Point"}
}