{
  "type": "Feature",
  "properties": {
    "iso:country":"DE",
    "sg:address":"Am Zollstock 1",
    "sg:city":"Heusweiler",
    "sg:phone":"+49 6806/609260",
    "sg:postcode":"66265",
    "sg:province":"Saarland",
    "wof:name":"Marion Luttenberger Rechtsanw\u00e4ltin",
    "wof:placetype":"venue"
},
  "geometry": {"coordinates":[6.9214119911,49.3405456543],"type":"Point"}
}