{
  "type": "Feature",
  "properties": {
    "iso:country":"DE",
    "sg:address":"Heimstr. 2",
    "sg:city":"Wartenberg",
    "sg:postcode":"85456",
    "sg:province":"Bayern",
    "wof:name":"Sankt-josefs-anstalt",
    "wof:placetype":"venue"
},
  "geometry": {"coordinates":[11.991522789,48.4034423828],"type":"Point"}
}