{
  "type": "Feature",
  "properties": {
    "iso:country":"DE",
    "sg:address":"Dorfstr. 73",
    "sg:city":"Brekendorf",
    "sg:phone":"+49 4336/429",
    "sg:postcode":"24811",
    "sg:province":"Schleswig-Holstein",
    "wof:name":"Marco Westphal Baugesch\u00e4ft Gmbh",
    "wof:placetype":"venue"
},
  "geometry": {"coordinates":[9.626628,54.420528],"type":"Point"}
}