{
  "type": "Feature",
  "properties": {
    "iso:country":"DE",
    "sg:address":"Zeppelinstra\u00dfe 35",
    "sg:city":"Lutherstadt Wittenberg",
    "sg:phone":"+49 3491",
    "sg:postcode":"06886",
    "sg:province":"Sachsen-Anhalt",
    "wof:name":"Pegastar-partner Wolf-dieter Schnerpel",
    "wof:placetype":"venue"
},
  "geometry": {"coordinates":[12.6493778229,51.8737983704],"type":"Point"}
}