{
  "type": "Feature",
  "properties": {
    "iso:country":"DE",
    "sg:address":"Goethestr. 26",
    "sg:city":"Ginsheim-Gustavsburg",
    "sg:phone":"+49 6144/32256",
    "sg:postcode":"65462",
    "sg:province":"Hessen",
    "wof:name":"S. Dauborn Heilpraktiker",
    "wof:placetype":"venue"
},
  "geometry": {"coordinates":[8.34491539,49.9685287476],"type":"Point"}
}