{
  "type": "Feature",
  "properties": {
    "iso:country":"DE",
    "sg:address":"Bussardweg 12",
    "sg:city":"Wesseling",
    "sg:phone":"+49 2236/89330",
    "sg:postcode":"50389",
    "sg:province":"Nordrhein-Westfalen",
    "wof:name":"Dr. Rolf Dieter Flaccus Patentanwalt",
    "wof:placetype":"venue"
},
  "geometry": {"coordinates":[6.9797120094,50.8061485291],"type":"Point"}
}