{
  "type": "Feature",
  "properties": {
    "iso:country":"DE",
    "sg:address":"Ahornstr. 6",
    "sg:city":"Rechlin",
    "sg:phone":"+49 39823/2500",
    "sg:postcode":"17248",
    "sg:province":"Mecklenburg-Vorpommern",
    "wof:name":"Metallbau M\u00fcller Gmbh",
    "wof:placetype":"venue"
},
  "geometry": {"coordinates":[12.7238140106,53.3246002197],"type":"Point"}
}