{
  "type": "Feature",
  "properties": {
    "iso:country":"DE",
    "sg:address":"Wilhelmstr. 18",
    "sg:city":"Chemnitz",
    "sg:phone":"+49 371/854459",
    "sg:postcode":"09117",
    "sg:province":"Sachsen",
    "wof:name":"S. Helmdach",
    "wof:placetype":"venue"
},
  "geometry": {"coordinates":[12.823412,50.814816],"type":"Point"}
}