{
  "type": "Feature",
  "properties": {
    "iso:country":"DE",
    "sg:address":"Altenberger-Dom-Str. 80",
    "sg:city":"Odenthal",
    "sg:phone":"+49 2174/4469",
    "sg:postcode":"51519",
    "sg:province":"Nordrhein-Westfalen",
    "wof:name":"Johannes Simons",
    "wof:placetype":"venue"
},
  "geometry": {"coordinates":[7.12165,51.040218],"type":"Point"}
}