{
  "type": "Feature",
  "properties": {
    "iso:country":"DE",
    "sg:address":"Prager Str. 3",
    "sg:city":"Dresden",
    "sg:phone":"+49 351/4903014",
    "sg:postcode":"01069",
    "sg:province":"Sachsen",
    "wof:name":"Apotheke Prager Stra\u00dfe",
    "wof:placetype":"venue"
},
  "geometry": {"coordinates":[13.733933,51.041512],"type":"Point"}
}