{
  "type": "Feature",
  "properties": {
    "iso:country":"DE",
    "sg:address":"Morgenstr. 55",
    "sg:city":"Karlsruhe",
    "sg:phone":"+49 721/389172",
    "sg:postcode":"76137",
    "sg:province":"Baden-W\u00fcrttemberg",
    "wof:name":"Hermann Zeh",
    "wof:placetype":"venue"
},
  "geometry": {"coordinates":[8.413482666,48.999080658],"type":"Point"}
}