{
  "type": "Feature",
  "properties": {
    "iso:country":"DE",
    "sg:address":"Windorfer Str. 112",
    "sg:city":"Leipzig",
    "sg:phone":"+49 341",
    "sg:postcode":"04229",
    "sg:province":"Sachsen",
    "wof:name":"H.p.-dienstleistungen, Service Rund Um Immobilien",
    "wof:placetype":"venue"
},
  "geometry": {"coordinates":[12.32675,51.312981],"type":"Point"}
}