{
  "type": "Feature",
  "properties": {
    "iso:country":"DE",
    "sg:address":"Lessingstr. 5",
    "sg:city":"Adelmannsfelden",
    "sg:phone":"+49 7963/840009",
    "sg:postcode":"73486",
    "sg:province":"Baden-W\u00fcrttemberg",
    "wof:name":"Rudolf Funk Finanzberater",
    "wof:placetype":"venue"
},
  "geometry": {"coordinates":[10.0052042007,48.9520225525],"type":"Point"}
}