{
  "type": "Feature",
  "properties": {
    "iso:country":"DE",
    "sg:address":"Hasel\u00fcnner Str. 28",
    "sg:city":"Meppen",
    "sg:phone":"+49 5931/845819",
    "sg:postcode":"49716",
    "sg:province":"Niedersachsen",
    "wof:name":"Ferdinand Schnebeck",
    "wof:placetype":"venue"
},
  "geometry": {"coordinates":[7.300776,52.69862],"type":"Point"}
}