{
  "type": "Feature",
  "properties": {
    "iso:country":"DE",
    "sg:address":"Eichendorffstr. 106",
    "sg:city":"N\u00fcrnberg",
    "sg:phone":"+49 911/595324",
    "sg:postcode":"90491",
    "sg:province":"Bayern",
    "wof:name":"Kosmetik Erika Ruppert",
    "wof:placetype":"venue"
},
  "geometry": {"coordinates":[11.124503,49.475178],"type":"Point"}
}