{
  "type": "Feature",
  "properties": {
    "iso:country":"DE",
    "sg:address":"Spechtstr. 3",
    "sg:city":"Helmstadt",
    "sg:phone":"+49 9369/99399",
    "sg:postcode":"97264",
    "sg:province":"Bayern",
    "wof:name":"Burkard Fiederling",
    "wof:placetype":"venue"
},
  "geometry": {"coordinates":[9.7070941925,49.7645263672],"type":"Point"}
}