{
  "type": "Feature",
  "properties": {
    "iso:country":"DE",
    "sg:address":"Gr\u00fcnthaler Str.",
    "sg:city":"Olbernhau",
    "sg:phone":"+49 37360/2378",
    "sg:postcode":"09526",
    "sg:province":"Sachsen",
    "wof:name":"Total Fina Elf Holdings Deutschland Gmbh",
    "wof:placetype":"venue"
},
  "geometry": {"coordinates":[13.3407621384,50.6592407227],"type":"Point"}
}