{
  "type": "Feature",
  "properties": {
    "iso:country":"DE",
    "sg:address":"Hauptstr. 167",
    "sg:city":"Heidelberg",
    "sg:phone":"+49 6221/24557",
    "sg:postcode":"69117",
    "sg:province":"Baden-W\u00fcrttemberg",
    "wof:name":"Werbung Und Graphik Magdalena Gauweiler",
    "wof:placetype":"venue"
},
  "geometry": {"coordinates":[8.7079458237,49.4118118286],"type":"Point"}
}