{
  "type": "Feature",
  "properties": {
    "iso:country":"DE",
    "sg:address":"Wolkensteiner Str. 4 B",
    "sg:city":"Marienberg",
    "sg:phone":"+49 3735/266175",
    "sg:postcode":"09496",
    "sg:province":"Sachsen",
    "wof:name":"Christine Br\u00fcckner Ergotherapiepraxis",
    "wof:placetype":"venue"
},
  "geometry": {"coordinates":[13.161369,50.65033],"type":"Point"}
}