{
  "type": "Feature",
  "properties": {
    "iso:country":"DE",
    "sg:address":"Dieselstr. 7/1",
    "sg:city":"Flein",
    "sg:postcode":"74223",
    "sg:province":"Baden-W\u00fcrttemberg",
    "wof:name":"Eberling Verwaltungs Gmbh",
    "wof:placetype":"venue"
},
  "geometry": {"coordinates":[9.200776,49.102974],"type":"Point"}
}