{
  "type": "Feature",
  "properties": {
    "iso:country":"DE",
    "sg:address":"Granseer Str. 2",
    "sg:city":"L\u00f6wenberg",
    "sg:phone":"+49 33094/50385",
    "sg:postcode":"16775",
    "sg:province":"Brandenburg",
    "wof:name":"L\u00f6wen-center",
    "wof:placetype":"venue"
},
  "geometry": {"coordinates":[13.1552391052,52.89868927],"type":"Point"}
}