{
  "type": "Feature",
  "properties": {
    "iso:country":"DE",
    "sg:address":"Nu\u00dfleitenweg 5",
    "sg:city":"Lauf",
    "sg:phone":"+49 9123/81636",
    "sg:postcode":"91207",
    "sg:province":"Bayern",
    "wof:name":"Klaus-j\u00fcrgen Hauenstein Architekt",
    "wof:placetype":"venue"
},
  "geometry": {"coordinates":[11.268727,49.548096],"type":"Point"}
}