{
  "type": "Feature",
  "properties": {
    "iso:country":"DE",
    "sg:address":"Linzer Str. 1",
    "sg:city":"Bad Honnef",
    "sg:phone":"+49 2224/70434",
    "sg:postcode":"53604",
    "sg:province":"Nordrhein-Westfalen",
    "wof:name":"Betz Musikhaus",
    "wof:placetype":"venue"
},
  "geometry": {"coordinates":[7.2290549278,50.6437225342],"type":"Point"}
}