{
  "type": "Feature",
  "properties": {
    "iso:country":"DE",
    "sg:address":"Am Graben 28",
    "sg:city":"N\u00fcrnberg",
    "sg:phone":"+49 911/834305",
    "sg:postcode":"90475",
    "sg:province":"Bayern",
    "wof:name":"Gunter Teltenk\u00f6tter Ingenieur",
    "wof:placetype":"venue"
},
  "geometry": {"coordinates":[11.1700992584,49.4088592529],"type":"Point"}
}