{
  "type": "Feature",
  "properties": {
    "iso:country":"DE",
    "sg:address":"Im Kr\u00f6tental 121",
    "sg:city":"Worms",
    "sg:phone":"+49 6242/4929",
    "sg:postcode":"67550",
    "sg:province":"Rheinland-Pfalz",
    "wof:name":"Immobilien R. Reinecke",
    "wof:placetype":"venue"
},
  "geometry": {"coordinates":[8.3570585251,49.703453064],"type":"Point"}
}