{
  "type": "Feature",
  "properties": {
    "iso:country":"DE",
    "sg:address":"Hubertusstr. 24",
    "sg:city":"Mantel",
    "sg:phone":"+49 9605/2340",
    "sg:postcode":"92708",
    "sg:province":"Bayern",
    "wof:name":"H. Schmid",
    "wof:placetype":"venue"
},
  "geometry": {"coordinates":[12.048966,49.656075],"type":"Point"}
}