{
  "type": "Feature",
  "properties": {
    "iso:country":"DE",
    "sg:address":"Luisenstr. 71-73",
    "sg:city":"Siegburg",
    "sg:phone":"+49 2241",
    "sg:postcode":"53721",
    "sg:province":"Nordrhein-Westfalen",
    "wof:name":"Autozentrum Sieg",
    "wof:placetype":"venue"
},
  "geometry": {"coordinates":[7.1994700432,50.8051986694],"type":"Point"}
}