{
  "type": "Feature",
  "properties": {
    "iso:country":"DE",
    "sg:address":"Dieckerhoffstr. 10",
    "sg:city":"Wuppertal",
    "sg:phone":"+49 202/601667",
    "sg:postcode":"42389",
    "sg:province":"Nordrhein-Westfalen",
    "wof:name":"Max Ely Gmbh",
    "wof:placetype":"venue"
},
  "geometry": {"coordinates":[7.242616,51.271839],"type":"Point"}
}