{
  "type": "Feature",
  "properties": {
    "iso:country":"DE",
    "sg:address":"Meppener Str. 126",
    "sg:city":"Lingen",
    "sg:phone":"+49 591/963660",
    "sg:postcode":"49808",
    "sg:province":"Niedersachsen",
    "wof:name":"Hermann B\u00fcscher Architekt",
    "wof:placetype":"venue"
},
  "geometry": {"coordinates":[7.302464,52.53392],"type":"Point"}
}