{
  "type": "Feature",
  "properties": {
    "iso:country":"DE",
    "sg:address":"Br\u00fcderstr. 12",
    "sg:city":"Bochum",
    "sg:phone":"+49 234/681049",
    "sg:postcode":"44787",
    "sg:province":"Nordrhein-Westfalen",
    "wof:name":"Kebap-haus Inh. Erg\u00fcn Und Ertan Ilce",
    "wof:placetype":"venue"
},
  "geometry": {"coordinates":[7.2173137665,51.477771759],"type":"Point"}
}