{
  "type": "Feature",
  "properties": {
    "iso:country":"DE",
    "sg:address":"Hohenzollernring 32",
    "sg:city":"Aschaffenburg",
    "sg:phone":"+49 6021/3550",
    "sg:postcode":"63739",
    "sg:province":"Bayern",
    "wof:name":"St. Elisabeth Caritas Alten- Und Pflegeheim",
    "wof:placetype":"venue"
},
  "geometry": {"coordinates":[9.15878,49.978821],"type":"Point"}
}