{
  "type": "Feature",
  "properties": {
    "iso:country":"DE",
    "sg:address":"Wohlenbergstr. 3",
    "sg:city":"Hannover",
    "sg:phone":"+49 4951/167470",
    "sg:postcode":"30179",
    "sg:province":"Niedersachsen",
    "wof:name":"Ke Kommunikations - Elektronik Gmbh",
    "wof:placetype":"venue"
},
  "geometry": {"coordinates":[9.7316932678,52.417591095],"type":"Point"}
}