{
  "type": "Feature",
  "properties": {
    "iso:country":"DE",
    "sg:address":"Ronneburger Str. 1a",
    "sg:city":"Gro\u00dfenstein",
    "sg:phone":"+49 36602/50624",
    "sg:postcode":"07580",
    "sg:province":"Th\u00fcringen",
    "wof:name":"Wilhelm Orwat",
    "wof:placetype":"venue"
},
  "geometry": {"coordinates":[12.200931,50.903389],"type":"Point"}
}