{
  "type": "Feature",
  "properties": {
    "iso:country":"DE",
    "sg:address":"Riedmauer 03",
    "sg:city":"Arnstadt",
    "sg:phone":"+49 3628/642337",
    "sg:postcode":"99310",
    "sg:province":"Th\u00fcringen",
    "wof:name":"Hlf Leasing & Finanzierung Arnstadt E. K.",
    "wof:placetype":"venue"
},
  "geometry": {"coordinates":[10.949887,50.831928],"type":"Point"}
}