{
  "type": "Feature",
  "properties": {
    "iso:country":"DE",
    "sg:address":"Bahnhofstr. 21",
    "sg:city":"Framersheim",
    "sg:phone":"+49 6733/347",
    "sg:postcode":"55234",
    "sg:province":"Rheinland-Pfalz",
    "wof:name":"Katharina Strubel",
    "wof:placetype":"venue"
},
  "geometry": {"coordinates":[8.1739063263,49.7591743469],"type":"Point"}
}