{
  "type": "Feature",
  "properties": {
    "iso:country":"DE",
    "sg:address":"Hauptstr. 22",
    "sg:city":"Deggendorf",
    "sg:phone":"+49 991/370290",
    "sg:postcode":"94469",
    "sg:province":"Bayern",
    "wof:name":"Germania-inkassodienst",
    "wof:placetype":"venue"
},
  "geometry": {"coordinates":[12.9422702789,48.8231811523],"type":"Point"}
}