{
  "type": "Feature",
  "properties": {
    "iso:country":"DE",
    "sg:address":"Thadd\u00e4usstr. 91",
    "sg:city":"Verl",
    "sg:phone":"+49 5246/3398",
    "sg:postcode":"33415",
    "sg:province":"Nordrhein-Westfalen",
    "wof:name":"M. Woste",
    "wof:placetype":"venue"
},
  "geometry": {"coordinates":[8.458159,51.885567],"type":"Point"}
}