{
  "type": "Feature",
  "properties": {
    "iso:country":"DE",
    "sg:address":"Schillerstr. 36",
    "sg:city":"Bietigheim-Bissingen",
    "sg:phone":"+49 7142/30852",
    "sg:postcode":"74321",
    "sg:province":"Baden-W\u00fcrttemberg",
    "wof:name":"R. M\u00fcller",
    "wof:placetype":"venue"
},
  "geometry": {"coordinates":[9.103521347,48.9433403015],"type":"Point"}
}