{
  "type": "Feature",
  "properties": {
    "iso:country":"DE",
    "sg:address":"Himmelsth\u00fcrer Str. 61",
    "sg:city":"Hildesheim",
    "sg:phone":"+49 5121/66571",
    "sg:postcode":"31137",
    "sg:province":"Niedersachsen",
    "wof:name":"Christa Morda\u00df",
    "wof:placetype":"venue"
},
  "geometry": {"coordinates":[9.9157266617,52.153842926],"type":"Point"}
}