{
  "type": "Feature",
  "properties": {
    "iso:country":"DE",
    "sg:address":"Hauptstr. 14",
    "sg:city":"T\u00f6ging",
    "sg:phone":"+49 8631/99633",
    "sg:postcode":"84513",
    "sg:province":"Bayern",
    "wof:name":"Bayerische Vereinsbank Ag",
    "wof:placetype":"venue"
},
  "geometry": {"coordinates":[12.588574,48.255238],"type":"Point"}
}