{
  "type": "Feature",
  "properties": {
    "iso:country":"DE",
    "sg:address":"Im Silberloch 17",
    "sg:city":"Lauf",
    "sg:phone":"+49 7841/23455",
    "sg:postcode":"77886",
    "sg:province":"Baden-W\u00fcrttemberg",
    "wof:name":"K.brigitte Pr\u00f6bstl",
    "wof:placetype":"venue"
},
  "geometry": {"coordinates":[8.143609,48.649296],"type":"Point"}
}