{
  "type": "Feature",
  "properties": {
    "iso:country":"DE",
    "sg:address":"Wiesbadener Str. 46",
    "sg:city":"Wiesbaden",
    "sg:phone":"+49 611/410287",
    "sg:postcode":"65199",
    "sg:province":"Hessen",
    "wof:name":"Gerd Neli\u00dfen",
    "wof:placetype":"venue"
},
  "geometry": {"coordinates":[8.2012395859,50.0756492615],"type":"Point"}
}