{
  "type": "Feature",
  "properties": {
    "iso:country":"DE",
    "sg:address":"Postfach 1113",
    "sg:city":"Verl",
    "sg:phone":"+49 5246/92760",
    "sg:postcode":"33398",
    "sg:province":"Nordrhein-Westfalen",
    "wof:name":"Astec Klima-systeme Gmbh",
    "wof:placetype":"venue"
},
  "geometry": {"coordinates":[8.510720253,51.8820915222],"type":"Point"}
}