{
  "type": "Feature",
  "properties": {
    "iso:country":"DE",
    "sg:address":"Herrengasse 23",
    "sg:city":"Oberdischingen",
    "sg:phone":"+49 7305/4170",
    "sg:postcode":"89610",
    "sg:province":"Baden-W\u00fcrttemberg",
    "wof:name":"Wolfart Chemie Verwaltungs Gmbh",
    "wof:placetype":"venue"
},
  "geometry": {"coordinates":[9.8328170776,48.3016357422],"type":"Point"}
}