{
  "type": "Feature",
  "properties": {
    "iso:country":"DE",
    "sg:address":"Gro\u00dfenhainer Str. 6",
    "sg:city":"Riesa",
    "sg:phone":"+49 3525/735243",
    "sg:postcode":"01589",
    "sg:province":"Sachsen",
    "wof:name":"Dr. Stange & Co. Nachf. Immobilienmakler",
    "wof:placetype":"venue"
},
  "geometry": {"coordinates":[13.3127717972,51.3017120361],"type":"Point"}
}