{
  "type": "Feature",
  "properties": {
    "iso:country":"DE",
    "sg:address":"Leimenstr. 64",
    "sg:city":"Albstadt",
    "sg:phone":"+49 7432/7923",
    "sg:postcode":"72461",
    "sg:province":"Baden-W\u00fcrttemberg",
    "wof:name":"M\u00f6ve",
    "wof:placetype":"venue"
},
  "geometry": {"coordinates":[9.021781,48.251572],"type":"Point"}
}