{
  "type": "Feature",
  "properties": {
    "iso:country":"DE",
    "sg:address":"Oxfordstr. 2",
    "sg:city":"Bonn",
    "sg:phone":"+49 228/651280",
    "sg:postcode":"53111",
    "sg:province":"Nordrhein-Westfalen",
    "wof:name":"Schulte-beckhausen Und B\u00fchs Rechtsanw\u00e4lte",
    "wof:placetype":"venue"
},
  "geometry": {"coordinates":[7.1008071899,50.7375602722],"type":"Point"}
}