{
  "type": "Feature",
  "properties": {
    "iso:country":"DE",
    "sg:address":"Odilienplatz 10",
    "sg:city":"Dillingen",
    "sg:phone":"+49 6831/703936",
    "sg:postcode":"66763",
    "sg:province":"Saarland",
    "wof:name":"Brunnen-apotheke",
    "wof:placetype":"venue"
},
  "geometry": {"coordinates":[6.726854,49.354515],"type":"Point"}
}