{
  "type": "Feature",
  "properties": {
    "iso:country":"DE",
    "sg:address":"Zepziger Weg",
    "sg:city":"Bernburg",
    "sg:phone":"+49 3471/310816",
    "sg:postcode":"06406",
    "sg:province":"Sachsen-Anhalt",
    "wof:name":"Fachkauf-handelsbetrieb",
    "wof:placetype":"venue"
},
  "geometry": {"coordinates":[11.750657,51.782471],"type":"Point"}
}