{
  "type": "Feature",
  "properties": {
    "iso:country":"DE",
    "sg:address":"Im Romberg 28",
    "sg:city":"Recklinghausen",
    "sg:phone":"+49 2361/10360",
    "sg:postcode":"45657",
    "sg:province":"Nordrhein-Westfalen",
    "wof:name":"Altenheim St. Hedwig",
    "wof:placetype":"venue"
},
  "geometry": {"coordinates":[7.19868,51.622799],"type":"Point"}
}