{
  "type": "Feature",
  "properties": {
    "iso:country":"DE",
    "sg:address":"Lupfenstr. 65",
    "sg:city":"Villingen-Schwenningen",
    "sg:phone":"+49 7720/97320",
    "sg:postcode":"78056",
    "sg:province":"Baden-W\u00fcrttemberg",
    "wof:name":"Ismet Ag",
    "wof:placetype":"venue"
},
  "geometry": {"coordinates":[8.5558290482,48.0620002747],"type":"Point"}
}