{
  "type": "Feature",
  "properties": {
    "iso:country":"DE",
    "sg:address":"Breitenbergweg 37",
    "sg:city":"Stadtbergen",
    "sg:phone":"+49 821/438553",
    "sg:postcode":"86391",
    "sg:province":"Bayern",
    "wof:name":"Prof. Dr. Adolf G. Coenenberg Steuerberater",
    "wof:placetype":"venue"
},
  "geometry": {"coordinates":[10.821264267,48.36460495],"type":"Point"}
}