{
  "type": "Feature",
  "properties": {
    "iso:country":"DE",
    "sg:address":"Dorfstr. 22",
    "sg:city":"Breitnau",
    "sg:phone":"+49 7652/981748",
    "sg:postcode":"79874",
    "sg:province":"Baden-W\u00fcrttemberg",
    "wof:name":"K. Lickert Nachf.",
    "wof:placetype":"venue"
},
  "geometry": {"coordinates":[8.0841178894,47.9392051697],"type":"Point"}
}