{
  "type": "Feature",
  "properties": {
    "iso:country":"DE",
    "sg:address":"Stadionstr. 25",
    "sg:city":"Bad Mergentheim",
    "sg:phone":"+49 7931/8686",
    "sg:postcode":"97980",
    "sg:province":"Baden-W\u00fcrttemberg",
    "wof:name":"Karl-heinz Lipfert",
    "wof:placetype":"venue"
},
  "geometry": {"coordinates":[9.779592,49.485752],"type":"Point"}
}