{
  "type": "Feature",
  "properties": {
    "iso:country":"DE",
    "sg:address":"Oettinger Str. 6",
    "sg:city":"Gunzenhausen",
    "sg:postcode":"91710",
    "sg:province":"Bayern",
    "wof:name":"Weigand Gmbh & Co. Kg",
    "wof:placetype":"venue"
},
  "geometry": {"coordinates":[10.7529230118,49.1156768799],"type":"Point"}
}