{
  "type": "Feature",
  "properties": {
    "iso:country":"DE",
    "sg:address":"Unterm\u00fchlstr. 19",
    "sg:city":"Merching",
    "sg:phone":"+49 8233/30790",
    "sg:postcode":"86504",
    "sg:province":"Bayern",
    "wof:name":"P. Schramm",
    "wof:placetype":"venue"
},
  "geometry": {"coordinates":[10.984536171,48.2474975586],"type":"Point"}
}