{
  "type": "Feature",
  "properties": {
    "iso:country":"DE",
    "sg:address":"Wallstr. 16",
    "sg:city":"Winnenden",
    "sg:phone":"+49 7195/179672",
    "sg:postcode":"71364",
    "sg:province":"Baden-W\u00fcrttemberg",
    "wof:name":"Bernd Otto Gmbh",
    "wof:placetype":"venue"
},
  "geometry": {"coordinates":[9.3989028931,48.8749542236],"type":"Point"}
}