{
  "type": "Feature",
  "properties": {
    "iso:country":"DE",
    "sg:address":"Teichstr. 12",
    "sg:city":"Gladenbach",
    "sg:phone":"+49 6462/8286",
    "sg:postcode":"35075",
    "sg:province":"Hessen",
    "wof:name":"K. H. Zinser",
    "wof:placetype":"venue"
},
  "geometry": {"coordinates":[8.5811014175,50.7680702209],"type":"Point"}
}