{
  "type": "Feature",
  "properties": {
    "iso:country":"DE",
    "sg:address":"Lenggenstr. 10",
    "sg:city":"Hohentengen",
    "sg:phone":"+49 7742/91220",
    "sg:postcode":"79801",
    "sg:province":"Baden-W\u00fcrttemberg",
    "wof:name":"A. Kutt",
    "wof:placetype":"venue"
},
  "geometry": {"coordinates":[8.3723087311,47.5721588135],"type":"Point"}
}