{
  "type": "Feature",
  "properties": {
    "iso:country":"DE",
    "sg:address":"Schwabenheimer Str. 36",
    "sg:city":"Dossenheim",
    "sg:phone":"+49 6221/869005",
    "sg:postcode":"69221",
    "sg:province":"Baden-W\u00fcrttemberg",
    "wof:name":"K. Gries",
    "wof:placetype":"venue"
},
  "geometry": {"coordinates":[8.6686058044,49.4505348206],"type":"Point"}
}