{
  "type": "Feature",
  "properties": {
    "iso:country":"DE",
    "sg:address":"Schafh\u00e4user Str. 41",
    "sg:city":"Alzey",
    "sg:phone":"+49 4923/357408",
    "sg:postcode":"55232",
    "sg:province":"Rheinland-Pfalz",
    "wof:name":"Wilhelm Eckhardt & Sohn Gmbh",
    "wof:placetype":"venue"
},
  "geometry": {"coordinates":[7.3163280487,51.365688324],"type":"Point"}
}