{
  "type": "Feature",
  "properties": {
    "iso:country":"DE",
    "sg:address":"Martin-Luther-Str. 24",
    "sg:city":"M\u00fcnchen",
    "sg:postcode":"81539",
    "sg:province":"Bayern",
    "wof:name":"Kantcheff Import- Handelsvertr.-export Gmbh",
    "wof:placetype":"venue"
},
  "geometry": {"coordinates":[11.5764493942,48.1133422852],"type":"Point"}
}