{
  "type": "Feature",
  "properties": {
    "iso:country":"DE",
    "sg:address":"Dr.-Felix-Gerhardus-Str. 11",
    "sg:city":"Mechernich",
    "sg:phone":"+49 2443/901300",
    "sg:postcode":"53894",
    "sg:province":"Nordrhein-Westfalen",
    "wof:name":"Optic Himmrich Gmbh",
    "wof:placetype":"venue"
},
  "geometry": {"coordinates":[6.6552929878,50.5898704529],"type":"Point"}
}