{
  "type": "Feature",
  "properties": {
    "iso:country":"DE",
    "sg:address":"L\u00fcbecker str. 3",
    "sg:city":"Leimen",
    "sg:phone":"+49 6224/766841",
    "sg:postcode":"69181",
    "sg:province":"Baden-W\u00fcrttemberg",
    "wof:name":"Dream69 Erotische Dienstleistungen",
    "wof:placetype":"venue"
},
  "geometry": {"coordinates":[8.685684,49.352551],"type":"Point"}
}