{
  "type": "Feature",
  "properties": {
    "iso:country":"DE",
    "sg:address":"Hauptstr. 20",
    "sg:city":"Geising",
    "sg:postcode":"01778",
    "sg:province":"Sachsen",
    "wof:name":"Quelle Agentur",
    "wof:placetype":"venue"
},
  "geometry": {"coordinates":[13.7878398895,50.7610397339],"type":"Point"}
}