{
  "type": "Feature",
  "properties": {
    "iso:country":"DE",
    "sg:address":"Rhein-Wupper-Platz 4",
    "sg:city":"Leverkusen",
    "sg:phone":"+49 2171/42826",
    "sg:postcode":"51379",
    "sg:province":"Nordrhein-Westfalen",
    "wof:name":"Asta Boerner Krankengymnastin",
    "wof:placetype":"venue"
},
  "geometry": {"coordinates":[6.99395,51.064232],"type":"Point"}
}