{
  "type": "Feature",
  "properties": {
    "iso:country":"DE",
    "sg:address":"Woltmanstr. 16",
    "sg:city":"Hamburg",
    "sg:phone":"+49 40/5538418",
    "sg:postcode":"20097",
    "sg:province":"Hamburg",
    "wof:name":"Michael Sauer",
    "wof:placetype":"venue"
},
  "geometry": {"coordinates":[10.012461,53.54705],"type":"Point"}
}