{
  "type": "Feature",
  "properties": {
    "iso:country":"DE",
    "sg:address":"Weinsteigle 7",
    "sg:city":"Neuffen",
    "sg:phone":"+49 7025/83480",
    "sg:postcode":"72639",
    "sg:province":"Baden-W\u00fcrttemberg",
    "wof:name":"Woco Wohnconcept Gmbh",
    "wof:placetype":"venue"
},
  "geometry": {"coordinates":[9.379913,48.552643],"type":"Point"}
}