{
  "type": "Feature",
  "properties": {
    "iso:country":"DE",
    "sg:address":"Echternstr. 1",
    "sg:city":"Stadthagen",
    "sg:phone":"+49 5721/2318",
    "sg:postcode":"31655",
    "sg:province":"Niedersachsen",
    "wof:name":"L. Schr\u00f6der",
    "wof:placetype":"venue"
},
  "geometry": {"coordinates":[9.204167,52.323917],"type":"Point"}
}