{
  "type": "Feature",
  "properties": {
    "iso:country":"DE",
    "sg:address":"Kasernenstr. 15",
    "sg:city":"Offenbach",
    "sg:phone":"+49 69/814676",
    "sg:postcode":"63065",
    "sg:province":"Hessen",
    "wof:name":"Peter Freitag",
    "wof:placetype":"venue"
},
  "geometry": {"coordinates":[8.7744626999,50.1026115417],"type":"Point"}
}