{
  "type": "Feature",
  "properties": {
    "iso:country":"DE",
    "sg:address":"Carl-Zeiss-Str. 10",
    "sg:city":"Alsdorf",
    "sg:phone":"+49 2404/94010",
    "sg:postcode":"52477",
    "sg:province":"Nordrhein-Westfalen",
    "wof:name":"Druckerei Vahsen & Malchus Ohg",
    "wof:placetype":"venue"
},
  "geometry": {"coordinates":[6.186,50.872963],"type":"Point"}
}