{
  "type": "Feature",
  "properties": {
    "iso:country":"DE",
    "sg:address":"Harzstr. 37",
    "sg:city":"Niedersachswerfen",
    "sg:phone":"+49 36331/42250",
    "sg:postcode":"99762",
    "sg:province":"Th\u00fcringen",
    "wof:name":"Mab Maschinen- Und Anlagenbau Gmbh",
    "wof:placetype":"venue"
},
  "geometry": {"coordinates":[10.769378,51.55986],"type":"Point"}
}