{
  "type": "Feature",
  "properties": {
    "iso:country":"DE",
    "sg:address":"Scheidswaldstr. 73",
    "sg:city":"Frankfurt",
    "sg:phone":"+49 69/446002",
    "sg:postcode":"60385",
    "sg:province":"Hessen",
    "wof:name":"Grand Canyon Airlines",
    "wof:placetype":"venue"
},
  "geometry": {"coordinates":[8.709358,50.120495],"type":"Point"}
}