{
  "type": "Feature",
  "properties": {
    "iso:country":"DE",
    "sg:address":"Emsstr. 20",
    "sg:city":"Emsdetten",
    "sg:phone":"+49 2572/84130",
    "sg:postcode":"48282",
    "sg:province":"Nordrhein-Westfalen",
    "wof:name":"Clemens Bockel",
    "wof:placetype":"venue"
},
  "geometry": {"coordinates":[7.5293221474,52.1759033203],"type":"Point"}
}