{
  "type": "Feature",
  "properties": {
    "iso:country":"DE",
    "sg:address":"Stendorfer Str. 3",
    "sg:city":"Ritterhude",
    "sg:postcode":"27721",
    "sg:province":"Niedersachsen",
    "wof:name":"Aladomo Beteiligungs- Gmbh",
    "wof:placetype":"venue"
},
  "geometry": {"coordinates":[8.737348,53.185318],"type":"Point"}
}