{
  "type": "Feature",
  "properties": {
    "iso:country":"DE",
    "sg:address":"Am Sportplatz 3",
    "sg:city":"Bad Sulza",
    "sg:phone":"+49 36461/20462",
    "sg:postcode":"99518",
    "sg:province":"Th\u00fcringen",
    "wof:name":"Willi Kutsche",
    "wof:placetype":"venue"
},
  "geometry": {"coordinates":[11.6201438904,51.0836524963],"type":"Point"}
}