{
  "type": "Feature",
  "properties": {
    "iso:country":"DE",
    "sg:address":"Pritzwalker Str. 31",
    "sg:city":"Wittstock",
    "sg:phone":"+49 3394/444036",
    "sg:postcode":"16909",
    "sg:province":"Brandenburg",
    "wof:name":"Lidl",
    "wof:placetype":"venue"
},
  "geometry": {"coordinates":[12.4714670181,53.1608810425],"type":"Point"}
}