{
  "type": "Feature",
  "properties": {
    "iso:country":"DE",
    "sg:address":"Kuckucksruf 28",
    "sg:city":"Stolpe-S\u00fcd",
    "sg:phone":"+49 3302/810353",
    "sg:postcode":"16761",
    "sg:province":"Brandenburg",
    "wof:name":"Edith Wittchen",
    "wof:placetype":"venue"
},
  "geometry": {"coordinates":[13.235087,52.628265],"type":"Point"}
}