{
  "type": "Feature",
  "properties": {
    "iso:country":"DE",
    "sg:address":"Alte Dorfstr. 6",
    "sg:city":"B\u00fcdelsdorf",
    "sg:phone":"+49 4331",
    "sg:postcode":"24782",
    "sg:province":"Schleswig-Holstein",
    "wof:name":"Hotel Und Restaurant In B\u00fcdelsdorf",
    "wof:placetype":"venue"
},
  "geometry": {"coordinates":[9.662538,54.31245],"type":"Point"}
}