{
  "type": "Feature",
  "properties": {
    "iso:country":"DE",
    "sg:address":"Saarbr\u00fccker Str. 2",
    "sg:city":"Kleinblittersdorf",
    "sg:phone":"+49 6805/218787",
    "sg:postcode":"66271",
    "sg:province":"Saarland",
    "wof:name":"Kebap-h\u00fctte",
    "wof:placetype":"venue"
},
  "geometry": {"coordinates":[7.0344791412,49.1575241089],"type":"Point"}
}