{
  "type": "Feature",
  "properties": {
    "iso:country":"DE",
    "sg:address":"Ohmstr. 6",
    "sg:city":"Augsburg",
    "sg:phone":"+49 821/572377",
    "sg:postcode":"86199",
    "sg:province":"Bayern",
    "wof:name":"G. Schimpfle",
    "wof:placetype":"venue"
},
  "geometry": {"coordinates":[10.884016,48.3475],"type":"Point"}
}