{
  "type": "Feature",
  "properties": {
    "iso:country":"DE",
    "sg:address":"Gie\u00dfener Str. 26",
    "sg:city":"Lich",
    "sg:phone":"+49 6404/2560",
    "sg:postcode":"35423",
    "sg:province":"Hessen",
    "wof:name":"Restaurant Licher B\u00fcrgerstube",
    "wof:placetype":"venue"
},
  "geometry": {"coordinates":[8.8167667389,50.5225257874],"type":"Point"}
}