{
  "type": "Feature",
  "properties": {
    "iso:country":"DE",
    "sg:address":"Sch\u00f6ne Aussicht 34",
    "sg:city":"Wiesbaden",
    "sg:phone":"+49 611/525091",
    "sg:postcode":"65193",
    "sg:province":"Hessen",
    "wof:name":"Kempf Gmbh",
    "wof:placetype":"venue"
},
  "geometry": {"coordinates":[8.2495498657,50.0875511169],"type":"Point"}
}