{
  "type": "Feature",
  "properties": {
    "iso:country":"DE",
    "sg:address":"Lambertusweg 3",
    "sg:city":"Ayl",
    "sg:phone":"+49 6581/3174",
    "sg:postcode":"54441",
    "sg:province":"Rheinland-Pfalz",
    "wof:name":"Franz Greif",
    "wof:placetype":"venue"
},
  "geometry": {"coordinates":[6.5641980171,49.627155304],"type":"Point"}
}