{
  "type": "Feature",
  "properties": {
    "iso:country":"DE",
    "sg:address":"Hamburger Str. 205",
    "sg:city":"Elmshorn",
    "sg:postcode":"25337",
    "sg:province":"Schleswig-Holstein",
    "wof:name":"Sportlife Betriebsgesellschaft Mbh & Co. Kg",
    "wof:placetype":"venue"
},
  "geometry": {"coordinates":[9.691299,53.748501],"type":"Point"}
}