{
  "type": "Feature",
  "properties": {
    "iso:country":"DE",
    "sg:address":"Luisenstr. 21",
    "sg:city":"Oberhausen-Rheinhausen",
    "sg:phone":"+49 7254/8391",
    "sg:postcode":"68794",
    "sg:province":"Baden-W\u00fcrttemberg",
    "wof:name":"Kurt Michenfelder",
    "wof:placetype":"venue"
},
  "geometry": {"coordinates":[8.48652,49.256783],"type":"Point"}
}