{
  "type": "Feature",
  "properties": {
    "iso:country":"DE",
    "sg:address":"Elser Bruch 16",
    "sg:city":"Paderborn",
    "sg:phone":"+49 5254/60306",
    "sg:postcode":"33106",
    "sg:province":"Nordrhein-Westfalen",
    "wof:name":"Gabriele Potthoff",
    "wof:placetype":"venue"
},
  "geometry": {"coordinates":[8.6829652786,51.7443962097],"type":"Point"}
}