{
  "type": "Feature",
  "properties": {
    "iso:country":"DE",
    "sg:address":"Nauheimer Str. 86-1",
    "sg:city":"Stuttgart",
    "sg:phone":"+49 711/5590957",
    "sg:postcode":"70372",
    "sg:province":"Baden-W\u00fcrttemberg",
    "wof:name":"Corinna M\u00fcller-vo\u00df",
    "wof:placetype":"venue"
},
  "geometry": {"coordinates":[9.223234,48.802902],"type":"Point"}
}