{
  "type": "Feature",
  "properties": {
    "iso:country":"DE",
    "sg:address":"Im Sandberg 4",
    "sg:city":"Geilenkirchen",
    "sg:phone":"+49 2451/2998",
    "sg:postcode":"52511",
    "sg:province":"Nordrhein-Westfalen",
    "wof:name":"Leo Bischof",
    "wof:placetype":"venue"
},
  "geometry": {"coordinates":[6.07474,50.982925],"type":"Point"}
}