{
  "type": "Feature",
  "properties": {
    "iso:country":"DE",
    "sg:address":"Hanauer Landstr. 145",
    "sg:city":"Frankfurt",
    "sg:postcode":"60314",
    "sg:province":"Hessen",
    "wof:name":"Melstar Deutschland Gmbh",
    "wof:placetype":"venue"
},
  "geometry": {"coordinates":[8.7143859863,50.1124763489],"type":"Point"}
}