{
  "type": "Feature",
  "properties": {
    "iso:country":"DE",
    "sg:address":"Am Gierath 26",
    "sg:city":"Ratingen",
    "sg:phone":"+49 2102/18960",
    "sg:postcode":"40885",
    "sg:province":"Nordrhein-Westfalen",
    "wof:name":"Schmeisser Sport- Und Jagdwaffen Handelsges.",
    "wof:placetype":"venue"
},
  "geometry": {"coordinates":[6.8478450775,51.3375244141],"type":"Point"}
}