{
  "type": "Feature",
  "properties": {
    "iso:country":"DE",
    "sg:address":"Mittelweg 89",
    "sg:city":"Braunschweig",
    "sg:phone":"+49 531/335460",
    "sg:postcode":"38106",
    "sg:province":"Niedersachsen",
    "wof:name":"Ferdinand Eppers",
    "wof:placetype":"venue"
},
  "geometry": {"coordinates":[10.526169,52.277477],"type":"Point"}
}