{
  "type": "Feature",
  "properties": {
    "iso:country":"DE",
    "sg:address":"Kettelerstr. 1a",
    "sg:city":"Oberhausen",
    "sg:phone":"+49 208/890267",
    "sg:postcode":"46117",
    "sg:province":"Nordrhein-Westfalen",
    "wof:name":"E. N. Berg Mode- Und Bekleidungshaus",
    "wof:placetype":"venue"
},
  "geometry": {"coordinates":[6.883915,51.503014],"type":"Point"}
}