{
  "type": "Feature",
  "properties": {
    "iso:country":"DE",
    "sg:address":"Greutweg 21",
    "sg:city":"Schw\u00e4bisch Gm\u00fcnd",
    "sg:phone":"+49 7171/82003",
    "sg:postcode":"73529",
    "sg:province":"Baden-W\u00fcrttemberg",
    "wof:name":"Erich Bihlmaier Architekt",
    "wof:placetype":"venue"
},
  "geometry": {"coordinates":[9.836861,48.781746],"type":"Point"}
}