{
  "type": "Feature",
  "properties": {
    "iso:country":"DE",
    "sg:address":"Rathausstr. 11",
    "sg:city":"Karlsdorf-Neuthard",
    "sg:phone":"+49 7251/42129",
    "sg:postcode":"76689",
    "sg:province":"Baden-W\u00fcrttemberg",
    "wof:name":"R. Und U. Brunner",
    "wof:placetype":"venue"
},
  "geometry": {"coordinates":[8.540528,49.136669],"type":"Point"}
}