{
  "type": "Feature",
  "properties": {
    "iso:country":"DE",
    "sg:address":"Hauptstr. 10",
    "sg:city":"K\u00f6lbingen",
    "sg:phone":"+49 2663/7227",
    "sg:postcode":"56459",
    "sg:province":"Rheinland-Pfalz",
    "wof:name":"Holzbau H\u00f6hn Gmbh",
    "wof:placetype":"venue"
},
  "geometry": {"coordinates":[7.9364848137,50.5507926941],"type":"Point"}
}