{
  "type": "Feature",
  "properties": {
    "iso:country":"DE",
    "sg:address":"Klausenberg 15",
    "sg:city":"Augsburg",
    "sg:phone":"+49 821/97537",
    "sg:postcode":"86199",
    "sg:province":"Bayern",
    "wof:name":"H. Schuhb\u00e4ck",
    "wof:placetype":"venue"
},
  "geometry": {"coordinates":[10.872586,48.343464],"type":"Point"}
}