{
  "type": "Feature",
  "properties": {
    "iso:country":"DE",
    "sg:address":"Kirchstr. 10",
    "sg:city":"Rosendahl",
    "sg:phone":"+49 2566/3128",
    "sg:postcode":"48720",
    "sg:province":"Nordrhein-Westfalen",
    "wof:name":"Felix Eihsing B\u00e4ckerei",
    "wof:placetype":"venue"
},
  "geometry": {"coordinates":[7.130673,52.006573],"type":"Point"}
}