{
  "type": "Feature",
  "properties": {
    "iso:country":"DE",
    "sg:address":"Gustav-Meyer-Allee 25",
    "sg:city":"Berlin",
    "sg:phone":"+49 30/2826909",
    "sg:postcode":"13355",
    "sg:province":"Berlin",
    "wof:name":"Spree-akademie Schulung F\u00fcr Datenverarb.u.unternehmen.gmbh",
    "wof:placetype":"venue"
},
  "geometry": {"coordinates":[13.383289,52.542282],"type":"Point"}
}