{
  "type": "Feature",
  "properties": {
    "iso:country":"DE",
    "sg:address":"Kleinmockritz 9",
    "sg:city":"Kleinmockritz",
    "sg:postcode":"04720",
    "sg:province":"Sachsen",
    "wof:name":"Pension Und Reiterhof Helm",
    "wof:placetype":"venue"
},
  "geometry": {"coordinates":[13.2173900604,51.1415290833],"type":"Point"}
}