{
  "type": "Feature",
  "properties": {
    "iso:country":"DE",
    "sg:address":"Sachsendorfer Str. 5",
    "sg:city":"Gro\u00df Gaglow",
    "sg:postcode":"03058",
    "sg:province":"Brandenburg",
    "wof:name":"Aldi Gmbh & Co. Kg",
    "wof:placetype":"venue"
},
  "geometry": {"coordinates":[14.3178415298,51.7156066895],"type":"Point"}
}