{
  "type": "Feature",
  "properties": {
    "iso:country":"DE",
    "sg:address":"Selmbach 3",
    "sg:city":"Haiger",
    "sg:phone":"+49 2773/72405",
    "sg:postcode":"35708",
    "sg:province":"Hessen",
    "wof:name":"Becker-transporte Gmbh",
    "wof:placetype":"venue"
},
  "geometry": {"coordinates":[8.1902418137,50.7198982239],"type":"Point"}
}