{
  "type": "Feature",
  "properties": {
    "iso:country":"DE",
    "sg:address":"Bad Sodener Str. 19",
    "sg:city":"Sulzbach",
    "sg:postcode":"65843",
    "sg:province":"Hessen",
    "wof:name":"Pda-systems.com Java Technology",
    "wof:placetype":"venue"
},
  "geometry": {"coordinates":[8.518824,50.135044],"type":"Point"}
}