{
  "type": "Feature",
  "properties": {
    "iso:country":"DE",
    "sg:address":"Krappgartenstr. 37 - 41",
    "sg:city":"Arnstadt",
    "sg:phone":"+49 3628/641711",
    "sg:postcode":"99310",
    "sg:province":"Th\u00fcringen",
    "wof:name":"Restaurant China Town",
    "wof:placetype":"venue"
},
  "geometry": {"coordinates":[10.9455242157,50.8367958069],"type":"Point"}
}