{
  "type": "Feature",
  "properties": {
    "iso:country":"DE",
    "sg:address":"Haubergweg 4",
    "sg:city":"Iserlohn",
    "sg:phone":"+49 2371/45713",
    "sg:postcode":"58640",
    "sg:province":"Nordrhein-Westfalen",
    "wof:name":"Dieter Schl\u00fcter Handelsvertretungen E. K.",
    "wof:placetype":"venue"
},
  "geometry": {"coordinates":[7.6874928474,51.4046096802],"type":"Point"}
}