{
  "type": "Feature",
  "properties": {
    "iso:country":"DE",
    "sg:address":"Roddener Str. 35",
    "sg:city":"G\u00fcnthersdorf",
    "sg:phone":"+49 34638/20795",
    "sg:postcode":"06254",
    "sg:province":"Sachsen-Anhalt",
    "wof:name":"D. Und D. Nehls",
    "wof:placetype":"venue"
},
  "geometry": {"coordinates":[12.1702871323,51.3451576233],"type":"Point"}
}