{
  "type": "Feature",
  "properties": {
    "iso:country":"DE",
    "sg:address":"Auf der Hof 27",
    "sg:city":"Simmerath",
    "sg:phone":"+49 2473/2701",
    "sg:postcode":"52152",
    "sg:province":"Nordrhein-Westfalen",
    "wof:name":"Adolf Niessen",
    "wof:placetype":"venue"
},
  "geometry": {"coordinates":[6.333553,50.630184],"type":"Point"}
}