{
  "type": "Feature",
  "properties": {
    "iso:country":"DE",
    "sg:address":"Heiligenst\u00e4dter Str 21",
    "sg:city":"Dingelst\u00e4dt",
    "sg:phone":"+49 36075/350",
    "sg:postcode":"37351",
    "sg:province":"Th\u00fcringen",
    "wof:name":"Dima Dingelst\u00e4dter Maschinen- Und Anlagenbau Gmbh",
    "wof:placetype":"venue"
},
  "geometry": {"coordinates":[10.312361,51.316784],"type":"Point"}
}