{
  "type": "Feature",
  "properties": {
    "iso:country":"DE",
    "sg:address":"Altenparkstein",
    "sg:city":"Kirchendemenreuth",
    "sg:phone":"+49 9681/1666",
    "sg:postcode":"92665",
    "sg:province":"Bayern",
    "wof:name":"Haberland Baustoff- Handels Gmbh",
    "wof:placetype":"venue"
},
  "geometry": {"coordinates":[12.0782518387,49.7720336914],"type":"Point"}
}