{
  "type": "Feature",
  "properties": {
    "iso:country":"DE",
    "sg:address":"Kuglerstr. 11",
    "sg:city":"Regensburg",
    "sg:phone":"+49 941/35815",
    "sg:postcode":"93049",
    "sg:province":"Bayern",
    "wof:name":"Hans-joachim List",
    "wof:placetype":"venue"
},
  "geometry": {"coordinates":[12.0638990402,49.0146331787],"type":"Point"}
}