{
  "type": "Feature",
  "properties": {
    "iso:country":"DE",
    "sg:address":"Titiseeweg",
    "sg:city":"Dauchingen",
    "sg:phone":"+49 7720/5399",
    "sg:postcode":"78083",
    "sg:province":"Baden-W\u00fcrttemberg",
    "wof:name":"Eberhard Von Hauff Graphologe",
    "wof:placetype":"venue"
},
  "geometry": {"coordinates":[8.5523796082,48.0930480957],"type":"Point"}
}