{
  "type": "Feature",
  "properties": {
    "iso:country":"DE",
    "sg:address":"Leipziger Str. 35",
    "sg:city":"Wiesbaden",
    "sg:phone":"+49 611/50660",
    "sg:postcode":"65191",
    "sg:province":"Hessen",
    "wof:name":"Redaktion Kundendienst Deutscher Genossenschafts-",
    "wof:placetype":"venue"
},
  "geometry": {"coordinates":[8.2810592651,50.0909729004],"type":"Point"}
}