{
  "type": "Feature",
  "properties": {
    "iso:country":"DE",
    "sg:address":"Am Markt 19",
    "sg:city":"Warin",
    "sg:phone":"+49 38482/298",
    "sg:postcode":"19417",
    "sg:province":"Mecklenburg-Vorpommern",
    "wof:name":"E. Katelh\u00f6n",
    "wof:placetype":"venue"
},
  "geometry": {"coordinates":[11.70439,53.800606],"type":"Point"}
}