{
  "type": "Feature",
  "properties": {
    "iso:country":"DE",
    "sg:address":"Spechthausener Str.",
    "sg:city":"Finowfurt",
    "sg:postcode":"16244",
    "sg:province":"Brandenburg",
    "wof:name":"Trr Thyssen Rohstoff-recycling Gmbh",
    "wof:placetype":"venue"
},
  "geometry": {"coordinates":[13.6898,52.837856],"type":"Point"}
}