{
  "type": "Feature",
  "properties": {
    "iso:country":"DE",
    "sg:address":"H\u00f6henweg 20",
    "sg:city":"Zwickau",
    "sg:phone":"+49 375",
    "sg:postcode":"08064",
    "sg:province":"Sachsen",
    "wof:name":"Preiswerter Urlaub Mit Sunflowers-reisen",
    "wof:placetype":"venue"
},
  "geometry": {"coordinates":[12.48337,50.678928],"type":"Point"}
}