{
  "type": "Feature",
  "properties": {
    "iso:country":"DE",
    "sg:address":"Hauptstr. 41",
    "sg:city":"Kurort Seiffen",
    "sg:phone":"+49 37362/8217",
    "sg:postcode":"09548",
    "sg:province":"Sachsen",
    "wof:name":"Pension Zum Alten Bergmannshaus",
    "wof:placetype":"venue"
},
  "geometry": {"coordinates":[13.444314003,50.6479072571],"type":"Point"}
}