{
  "type": "Feature",
  "properties": {
    "iso:country":"DE",
    "sg:address":"Talstr. 12",
    "sg:city":"Steinach",
    "sg:phone":"+49 36762/32577",
    "sg:postcode":"96523",
    "sg:province":"Th\u00fcringen",
    "wof:name":"Autohaus Robert Koch",
    "wof:placetype":"venue"
},
  "geometry": {"coordinates":[11.1637029648,50.4327583313],"type":"Point"}
}