{
  "type": "Feature",
  "properties": {
    "iso:country":"DE",
    "sg:address":"Hauptstr. 125",
    "sg:city":"Lengenfeld unterm Stein",
    "sg:phone":"+49 36027/70124",
    "sg:postcode":"99976",
    "sg:province":"Th\u00fcringen",
    "wof:name":"B. Ga\u00dfmann",
    "wof:placetype":"venue"
},
  "geometry": {"coordinates":[10.229896,51.212711],"type":"Point"}
}