{
  "type": "Feature",
  "properties": {
    "iso:country":"DE",
    "sg:address":"Altes Bollwerk",
    "sg:city":"Ueckerm\u00fcnde",
    "sg:phone":"+49 39771/23357",
    "sg:postcode":"17373",
    "sg:province":"Mecklenburg-Vorpommern",
    "wof:name":"Adler-schiffe Verwaltungs Gmbh",
    "wof:placetype":"venue"
},
  "geometry": {"coordinates":[14.0494947433,53.7358703613],"type":"Point"}
}