{
  "type": "Feature",
  "properties": {
    "iso:country":"DE",
    "sg:address":"Talsperrenweg 2",
    "sg:city":"Gummersbach",
    "sg:phone":"+49 2261/25325",
    "sg:postcode":"51647",
    "sg:province":"Nordrhein-Westfalen",
    "wof:name":"Fritz Weyland Ingenieur",
    "wof:placetype":"venue"
},
  "geometry": {"coordinates":[7.6230387688,51.0457420349],"type":"Point"}
}