{
  "type": "Feature",
  "properties": {
    "iso:country":"DE",
    "sg:address":"Auf der Worth 2",
    "sg:city":"Kirchlengern",
    "sg:phone":"+49 5223/83390",
    "sg:postcode":"32278",
    "sg:province":"Nordrhein-Westfalen",
    "wof:name":"Heinrich Homburg Kg Farben Und Lacke",
    "wof:placetype":"venue"
},
  "geometry": {"coordinates":[8.6419668198,52.1965713501],"type":"Point"}
}