{
  "type": "Feature",
  "properties": {
    "iso:country":"DE",
    "sg:address":"Hauptstr. 28",
    "sg:city":"Erzhausen",
    "sg:phone":"+49 6150/82751",
    "sg:postcode":"64390",
    "sg:province":"Hessen",
    "wof:name":"G\u00fcnther F\u00fcckel",
    "wof:placetype":"venue"
},
  "geometry": {"coordinates":[8.6300563812,49.9531822205],"type":"Point"}
}