{
  "type": "Feature",
  "properties": {
    "iso:country":"DE",
    "sg:address":"Schulweg 1",
    "sg:city":"Pr\u00f6tzel",
    "sg:phone":"+49 33436/35735",
    "sg:postcode":"15345",
    "sg:province":"Brandenburg",
    "wof:name":"Sportlerclub",
    "wof:placetype":"venue"
},
  "geometry": {"coordinates":[13.9790735245,52.6340866089],"type":"Point"}
}