{
  "type": "Feature",
  "properties": {
    "iso:country":"DE",
    "sg:address":"Talstr. 27",
    "sg:city":"Homburg",
    "sg:phone":"+49 6841/64031",
    "sg:postcode":"66424",
    "sg:province":"Saarland",
    "wof:name":"Hexonet Support Gmbh",
    "wof:placetype":"venue"
},
  "geometry": {"coordinates":[7.339509964,49.3220596313],"type":"Point"}
}