{
  "type": "Feature",
  "properties": {
    "iso:country":"DE",
    "sg:address":"Brunnenstr. 35",
    "sg:city":"Osann-Monzel",
    "sg:phone":"+49 6535/267",
    "sg:postcode":"54518",
    "sg:province":"Rheinland-Pfalz",
    "wof:name":"Werner Wintrich Weinanbau",
    "wof:placetype":"venue"
},
  "geometry": {"coordinates":[6.9511651993,49.9116973877],"type":"Point"}
}