{
  "type": "Feature",
  "properties": {
    "iso:country":"DE",
    "sg:address":"Fabrikstr. 6",
    "sg:city":"Geislingen",
    "sg:phone":"+49 7331/947165",
    "sg:postcode":"73312",
    "sg:province":"Baden-W\u00fcrttemberg",
    "wof:name":"B. Fritsch",
    "wof:placetype":"venue"
},
  "geometry": {"coordinates":[9.83974,48.615616],"type":"Point"}
}