{
  "type": "Feature",
  "properties": {
    "iso:country":"DE",
    "sg:address":"Karl-Marx-Str. 6",
    "sg:city":"Zwickau",
    "sg:phone":"+49 375/454781",
    "sg:postcode":"08066",
    "sg:province":"Sachsen",
    "wof:name":"H. Grabi",
    "wof:placetype":"venue"
},
  "geometry": {"coordinates":[12.528684,50.736935],"type":"Point"}
}