{
  "type": "Feature",
  "properties": {
    "iso:country":"DE",
    "sg:address":"Mathildenstr. 6",
    "sg:city":"Ludwigsburg",
    "sg:phone":"+49 7141/923315",
    "sg:postcode":"71638",
    "sg:province":"Baden-W\u00fcrttemberg",
    "wof:name":"Karl Adolf M\u00fcller",
    "wof:placetype":"venue"
},
  "geometry": {"coordinates":[9.188829422,48.8939781189],"type":"Point"}
}