{
  "type": "Feature",
  "properties": {
    "iso:country":"DE",
    "sg:address":"Baumhofstr 116",
    "sg:city":"Osterode",
    "sg:phone":"+49 5731/779660",
    "sg:postcode":"37520",
    "sg:province":"Niedersachsen",
    "wof:name":"Ps Print & Medien Dienste Gmbh",
    "wof:placetype":"venue"
},
  "geometry": {"coordinates":[8.8141059875,52.1819114685],"type":"Point"}
}