{
  "type": "Feature",
  "properties": {
    "iso:country":"DE",
    "sg:address":"Dorfstr. 117",
    "sg:city":"Ritzerow",
    "sg:phone":"+49 39954/21388",
    "sg:postcode":"17153",
    "sg:province":"Mecklenburg-Vorpommern",
    "wof:name":"V. Barck",
    "wof:placetype":"venue"
},
  "geometry": {"coordinates":[12.9720201492,53.6639976501],"type":"Point"}
}