{
  "type": "Feature",
  "properties": {
    "iso:country":"DE",
    "sg:address":"Wiltbergstr. 30",
    "sg:city":"Berlin",
    "sg:phone":"+49 30/9462410",
    "sg:postcode":"13125",
    "sg:province":"Berlin",
    "wof:name":"Gerhard J\u00fcrgens & Co. Bau Gmbh",
    "wof:placetype":"venue"
},
  "geometry": {"coordinates":[13.4928026199,52.6367645264],"type":"Point"}
}