{
  "type": "Feature",
  "properties": {
    "iso:country":"DE",
    "sg:address":"Am Bahnhof 7",
    "sg:city":"Erding",
    "sg:phone":"+49 8122/93309",
    "sg:postcode":"85435",
    "sg:province":"Bayern",
    "wof:name":"J. Eicher",
    "wof:placetype":"venue"
},
  "geometry": {"coordinates":[11.912366,48.304287],"type":"Point"}
}