{
  "type": "Feature",
  "properties": {
    "iso:country":"DE",
    "sg:address":"Schillerstr. 2",
    "sg:city":"Rengsdorf",
    "sg:phone":"+49 2634/2237",
    "sg:postcode":"56579",
    "sg:province":"Rheinland-Pfalz",
    "wof:name":"Sparkasse Neuwied",
    "wof:placetype":"venue"
},
  "geometry": {"coordinates":[7.495731,50.503098],"type":"Point"}
}