{
  "type": "Feature",
  "properties": {
    "iso:country":"DE",
    "sg:address":"Ewaldstr. 113",
    "sg:city":"Herten",
    "sg:phone":"+49 2366/33036",
    "sg:postcode":"45699",
    "sg:province":"Nordrhein-Westfalen",
    "wof:name":"Abc-schilder Ohg",
    "wof:placetype":"venue"
},
  "geometry": {"coordinates":[7.145185,51.585777],"type":"Point"}
}