{
  "type": "Feature",
  "properties": {
    "iso:country":"DE",
    "sg:address":"Hafenplatz 9 A",
    "sg:city":"Bad Karlshafen",
    "sg:phone":"+49 5672/1433",
    "sg:postcode":"34385",
    "sg:province":"Hessen",
    "wof:name":"Deutscher Hugenottenverein E. V.",
    "wof:placetype":"venue"
},
  "geometry": {"coordinates":[9.4526767731,51.6424331665],"type":"Point"}
}