{
  "type": "Feature",
  "properties": {
    "iso:country":"DE",
    "sg:address":"Monschauer Str. 38 a",
    "sg:city":"M\u00f6nchengladbach",
    "sg:phone":"+49 2161/838096",
    "sg:postcode":"41068",
    "sg:province":"Nordrhein-Westfalen",
    "wof:name":"R\u00e4der Verwaltung Gmbh",
    "wof:placetype":"venue"
},
  "geometry": {"coordinates":[6.407271,51.188801],"type":"Point"}
}