{
  "type": "Feature",
  "properties": {
    "iso:country":"DE",
    "sg:address":"Im M\u00fchlahl 14",
    "sg:city":"Reichelsheim",
    "sg:phone":"+49 6035/920640",
    "sg:postcode":"61203",
    "sg:province":"Hessen",
    "wof:name":"Erwin Tegtmeyer Cnc-fr\u00e4stechnik Gmbh",
    "wof:placetype":"venue"
},
  "geometry": {"coordinates":[8.878368,50.362885],"type":"Point"}
}