{
  "type": "Feature",
  "properties": {
    "iso:country":"DE",
    "sg:address":"Am Alten Spital 2",
    "sg:city":"Pfullendorf",
    "sg:phone":"+49 7552/6898",
    "sg:postcode":"88630",
    "sg:province":"Baden-W\u00fcrttemberg",
    "wof:name":"Otto Oechsle Gmbh",
    "wof:placetype":"venue"
},
  "geometry": {"coordinates":[9.25526,47.924103],"type":"Point"}
}