{
  "type": "Feature",
  "properties": {
    "iso:country":"DE",
    "sg:address":"Swinem\u00fcnder Str. 34",
    "sg:city":"Usedom",
    "sg:phone":"+49 38372/70698",
    "sg:postcode":"17406",
    "sg:province":"Mecklenburg-Vorpommern",
    "wof:name":"Hans-joachim Priebs",
    "wof:placetype":"venue"
},
  "geometry": {"coordinates":[13.920562,53.874363],"type":"Point"}
}