{
  "type": "Feature",
  "properties": {
    "iso:country":"DE",
    "sg:address":"H\u00e4ndelstr. 10a",
    "sg:city":"Karlsruhe",
    "sg:phone":"+49 721/555949",
    "sg:postcode":"76185",
    "sg:province":"Baden-W\u00fcrttemberg",
    "wof:name":"Eva Theers Krankengymnastin",
    "wof:placetype":"venue"
},
  "geometry": {"coordinates":[8.368839,49.012802],"type":"Point"}
}