{
  "type": "Feature",
  "properties": {
    "iso:country":"DE",
    "sg:address":"Ravensburger Str. 1",
    "sg:city":"Berg",
    "sg:phone":"+49 751/560350",
    "sg:postcode":"88276",
    "sg:province":"Baden-W\u00fcrttemberg",
    "wof:name":"Kordeuter Gmbh",
    "wof:placetype":"venue"
},
  "geometry": {"coordinates":[9.60442,47.807388],"type":"Point"}
}