{
  "type": "Feature",
  "properties": {
    "iso:country":"DE",
    "sg:address":"Am Fleth 28",
    "sg:city":"Gl\u00fcckstadt",
    "sg:phone":"+49 4124/4495",
    "sg:postcode":"25348",
    "sg:province":"Schleswig-Holstein",
    "wof:name":"Stefan Hennings",
    "wof:placetype":"venue"
},
  "geometry": {"coordinates":[9.42164,53.788513],"type":"Point"}
}