{
  "type": "Feature",
  "properties": {
    "iso:country":"DE",
    "sg:address":"Gudesstr. 1",
    "sg:city":"Uelzn",
    "sg:phone":"+49 4958/15031",
    "sg:postcode":"29525",
    "sg:province":"Niedersachsen",
    "wof:name":"Deutsche Bank Ag",
    "wof:placetype":"venue"
},
  "geometry": {"coordinates":[10.560741,52.965099],"type":"Point"}
}