{
  "type": "Feature",
  "properties": {
    "iso:country":"DE",
    "sg:address":"Hans-Sachs-Gasse 12",
    "sg:city":"N\u00fcrnberg",
    "sg:phone":"+49 911/201060",
    "sg:postcode":"90403",
    "sg:province":"Bayern",
    "wof:name":"Esw Ingenieur- Und Bauberatungsgesellschaft Mbh",
    "wof:placetype":"venue"
},
  "geometry": {"coordinates":[11.079761,49.453773],"type":"Point"}
}