{
  "type": "Feature",
  "properties": {
    "iso:country":"DE",
    "sg:address":"Benzstr. 5",
    "sg:city":"Renningen",
    "sg:phone":"+49 7159/7473",
    "sg:postcode":"71272",
    "sg:province":"Baden-W\u00fcrttemberg",
    "wof:name":"Takko",
    "wof:placetype":"venue"
},
  "geometry": {"coordinates":[8.934373,48.778454],"type":"Point"}
}