{
  "type": "Feature",
  "properties": {
    "iso:country":"DE",
    "sg:address":"Georg-Pingler-Str.",
    "sg:city":"K\u00f6nigstein",
    "sg:phone":"+49 6174/5112",
    "sg:postcode":"61462",
    "sg:province":"Hessen",
    "wof:name":"Wolfgang Zettl",
    "wof:placetype":"venue"
},
  "geometry": {"coordinates":[8.4667253494,50.1825904846],"type":"Point"}
}