{
  "type": "Feature",
  "properties": {
    "iso:country":"DE",
    "sg:address":"Burgstr. 20",
    "sg:city":"Honerath",
    "sg:postcode":"53518",
    "sg:province":"Rheinland-Pfalz",
    "wof:name":"Michael Kreuer Fliesenlegerei",
    "wof:placetype":"venue"
},
  "geometry": {"coordinates":[6.9013748169,50.3789596558],"type":"Point"}
}