{
  "type": "Feature",
  "properties": {
    "iso:country":"DE",
    "sg:address":"Humboldtstr. 6",
    "sg:city":"Gera",
    "sg:postcode":"07545",
    "sg:province":"Th\u00fcringen",
    "wof:name":"Carola-reisen",
    "wof:placetype":"venue"
},
  "geometry": {"coordinates":[12.0836181641,50.878528595],"type":"Point"}
}