{
  "type": "Feature",
  "properties": {
    "iso:country":"DE",
    "sg:address":"Postfach 1171",
    "sg:city":"K\u00fcps",
    "sg:postcode":"96324",
    "sg:province":"Bayern",
    "wof:name":"Benno Schuster",
    "wof:placetype":"venue"
},
  "geometry": {"coordinates":[11.2749052048,50.1923217773],"type":"Point"}
}