{
  "type": "Feature",
  "properties": {
    "iso:country":"DE",
    "sg:address":"Unterer Markt 9",
    "sg:city":"Hersbruck",
    "sg:phone":"+49 9151/82810",
    "sg:postcode":"91217",
    "sg:province":"Bayern",
    "wof:name":"Nerlich Und Kollegen Rechtsanw\u00e4lte",
    "wof:placetype":"venue"
},
  "geometry": {"coordinates":[11.4293355942,49.5082511902],"type":"Point"}
}