{
  "type": "Feature",
  "properties": {
    "iso:country":"DE",
    "sg:address":"Sieben Ruten 15",
    "sg:city":"Hofheim",
    "sg:phone":"+49 6192/25661",
    "sg:postcode":"65719",
    "sg:province":"Hessen",
    "wof:name":"Peter Hubertus Rechtsanwalt",
    "wof:placetype":"venue"
},
  "geometry": {"coordinates":[8.3950538635,50.1106338501],"type":"Point"}
}