{
  "type": "Feature",
  "properties": {
    "iso:country":"DE",
    "sg:address":"Arensdorfer Weg 3",
    "sg:city":"K\u00f6then",
    "sg:phone":"+49 3496/40090",
    "sg:postcode":"06366",
    "sg:province":"Sachsen-Anhalt",
    "wof:name":"August Deissner & Sohn Gmbh",
    "wof:placetype":"venue"
},
  "geometry": {"coordinates":[11.9741477966,51.7495613098],"type":"Point"}
}