{
  "type": "Feature",
  "properties": {
    "iso:country":"DE",
    "sg:address":"Schirick 114",
    "sg:city":"Viersen",
    "sg:phone":"+49 2162/41427",
    "sg:postcode":"41751",
    "sg:province":"Nordrhein-Westfalen",
    "wof:name":"Reiterklause",
    "wof:placetype":"venue"
},
  "geometry": {"coordinates":[6.359213829,51.2614021301],"type":"Point"}
}