{
  "type": "Feature",
  "properties": {
    "iso:country":"DE",
    "sg:city":"Mengen",
    "sg:phone":"+49 7572/5588",
    "sg:postcode":"88512",
    "sg:province":"Baden-W\u00fcrttemberg",
    "wof:name":"Guiducci Cafe",
    "wof:placetype":"venue"
},
  "geometry": {"coordinates":[9.32715,48.047295],"type":"Point"}
}