{
  "type": "Feature",
  "properties": {
    "iso:country":"DE",
    "sg:address":"Reuderner Str. 54",
    "sg:city":"N\u00fcrtingen",
    "sg:phone":"+49 7022/930900",
    "sg:postcode":"72622",
    "sg:province":"Baden-W\u00fcrttemberg",
    "wof:name":"Gert Besemer",
    "wof:placetype":"venue"
},
  "geometry": {"coordinates":[9.3838596344,48.6288528442],"type":"Point"}
}