{
  "type": "Feature",
  "properties": {
    "iso:country":"DE",
    "sg:address":"Otto-Decker-Str. 1",
    "sg:city":"Idar-Oberstein",
    "sg:phone":"+49 6781/27464",
    "sg:postcode":"55743",
    "sg:province":"Rheinland-Pfalz",
    "wof:name":"M. Kohl",
    "wof:placetype":"venue"
},
  "geometry": {"coordinates":[7.32354,49.701969],"type":"Point"}
}