{
  "type": "Feature",
  "properties": {
    "iso:country":"DE",
    "sg:address":"Boymerstr. 2",
    "sg:city":"Werne",
    "sg:phone":"+49 2389/98310",
    "sg:postcode":"59368",
    "sg:province":"Nordrhein-Westfalen",
    "wof:name":"Joachim Nickel Steuerberater",
    "wof:placetype":"venue"
},
  "geometry": {"coordinates":[7.6990318298,51.6711235046],"type":"Point"}
}