{
  "type": "Feature",
  "properties": {
    "iso:country":"DE",
    "sg:address":"Dr.-Schellerer-Str. 1",
    "sg:city":"Viechtach",
    "sg:phone":"+49 9942/94470",
    "sg:postcode":"94234",
    "sg:province":"Bayern",
    "wof:name":"Fritz Beteiligungs-gmbh",
    "wof:placetype":"venue"
},
  "geometry": {"coordinates":[12.888204,49.078648],"type":"Point"}
}