{
  "type": "Feature",
  "properties": {
    "iso:country":"DE",
    "sg:address":"W\u00fcrzburger Str. 273",
    "sg:city":"Haibach",
    "sg:phone":"+49 6021/69681",
    "sg:postcode":"63808",
    "sg:province":"Bayern",
    "wof:name":"Vdk Gr\u00fcnmorsbach Willi Weber",
    "wof:placetype":"venue"
},
  "geometry": {"coordinates":[9.2161884308,49.9609870911],"type":"Point"}
}