{
  "type": "Feature",
  "properties": {
    "iso:country":"DE",
    "sg:address":"Wolfhag 5",
    "sg:city":"Oberkirch",
    "sg:phone":"+49 7802/3457",
    "sg:postcode":"77704",
    "sg:province":"Baden-W\u00fcrttemberg",
    "wof:name":"Josef Schappacher",
    "wof:placetype":"venue"
},
  "geometry": {"coordinates":[8.082588,48.54174],"type":"Point"}
}