{
  "type": "Feature",
  "properties": {
    "iso:country":"DE",
    "sg:address":"Hauptstr. 67",
    "sg:city":"Wiesenbach",
    "sg:phone":"+49 6223/4547",
    "sg:postcode":"69257",
    "sg:province":"Baden-W\u00fcrttemberg",
    "wof:name":"Berberich Gmbh",
    "wof:placetype":"venue"
},
  "geometry": {"coordinates":[8.810762,49.35957],"type":"Point"}
}