{
  "type": "Feature",
  "properties": {
    "iso:country":"DE",
    "sg:address":"Lerchenweg 22",
    "sg:city":"Aichtal",
    "sg:phone":"+49 7127/50621",
    "sg:postcode":"72631",
    "sg:province":"Baden-W\u00fcrttemberg",
    "wof:name":"Gebr. Greschner & Co. Gmbh",
    "wof:placetype":"venue"
},
  "geometry": {"coordinates":[9.2060003281,48.6218452454],"type":"Point"}
}