{
  "type": "Feature",
  "properties": {
    "iso:country":"DE",
    "sg:address":"Hegestr. 90",
    "sg:city":"Gladbeck",
    "sg:phone":"+49 2043/948054",
    "sg:postcode":"45966",
    "sg:province":"Nordrhein-Westfalen",
    "wof:name":"K\u00fcchen- Profi F. Majchrzak",
    "wof:placetype":"venue"
},
  "geometry": {"coordinates":[6.9431247711,51.5710945129],"type":"Point"}
}