{
  "type": "Feature",
  "properties": {
    "iso:country":"DE",
    "sg:address":"Lilienthalstr. 12",
    "sg:city":"Viernheim",
    "sg:phone":"+49 6204/97280",
    "sg:postcode":"68519",
    "sg:province":"Hessen",
    "wof:name":"Kmp Holding Gmbh",
    "wof:placetype":"venue"
},
  "geometry": {"coordinates":[8.5947227478,49.5462036133],"type":"Point"}
}