{
  "type": "Feature",
  "properties": {
    "iso:country":"DE",
    "sg:address":"Hohenzollerndamm 89",
    "sg:city":"Berlin",
    "sg:phone":"+49 30/8952910",
    "sg:postcode":"14199",
    "sg:province":"Berlin",
    "wof:name":"Peter E. Meissner Patentanwalt",
    "wof:placetype":"venue"
},
  "geometry": {"coordinates":[13.2835292816,52.4787521362],"type":"Point"}
}