{
  "type": "Feature",
  "properties": {
    "iso:country":"DE",
    "sg:address":"Fahrionstr. 9",
    "sg:city":"Stuttgart",
    "sg:phone":"+49 711/1357780",
    "sg:postcode":"70469",
    "sg:province":"Baden-W\u00fcrttemberg",
    "wof:name":"Rainer Lanz Gmbh",
    "wof:placetype":"venue"
},
  "geometry": {"coordinates":[9.1640329361,48.8087005615],"type":"Point"}
}