{
  "type": "Feature",
  "properties": {
    "iso:country":"DE",
    "sg:address":"Lange Stege 49",
    "sg:city":"G\u00fcstrow",
    "sg:phone":"+49 3843/215311",
    "sg:postcode":"18273",
    "sg:province":"Mecklenburg-Vorpommern",
    "wof:name":"Jan Eichler",
    "wof:placetype":"venue"
},
  "geometry": {"coordinates":[12.187579155,53.7987747192],"type":"Point"}
}