{
  "type": "Feature",
  "properties": {
    "iso:country":"DE",
    "sg:address":"Hauptstr. 14",
    "sg:city":"Annweiler",
    "sg:phone":"+49 6346/7016",
    "sg:postcode":"76855",
    "sg:province":"Rheinland-Pfalz",
    "wof:name":"Werner Schwarz",
    "wof:placetype":"venue"
},
  "geometry": {"coordinates":[7.9621901512,49.2036018372],"type":"Point"}
}