{
  "type": "Feature",
  "properties": {
    "iso:country":"DE",
    "sg:address":"Dorfackerstr. 22",
    "sg:city":"Kemmern",
    "sg:phone":"+49 9544/5494",
    "sg:postcode":"96164",
    "sg:province":"Bayern",
    "wof:name":"Silvia Stark",
    "wof:placetype":"venue"
},
  "geometry": {"coordinates":[10.87973,49.953434],"type":"Point"}
}