{
  "type": "Feature",
  "properties": {
    "iso:country":"DE",
    "sg:address":"August-L\u00fctgenau-Str. 13",
    "sg:city":"H\u00fcckeswagen",
    "sg:phone":"+49 2192/931107",
    "sg:postcode":"42499",
    "sg:province":"Nordrhein-Westfalen",
    "wof:name":"G. Kose",
    "wof:placetype":"venue"
},
  "geometry": {"coordinates":[7.3323168755,51.1481132507],"type":"Point"}
}