{
  "type": "Feature",
  "properties": {
    "iso:country":"DE",
    "sg:address":"Wisbyer Str. 13",
    "sg:city":"Berlin",
    "sg:phone":"+49 30/2085333",
    "sg:postcode":"10439",
    "sg:province":"Berlin",
    "wof:name":"Di & Da Bau- Gmbh",
    "wof:placetype":"venue"
},
  "geometry": {"coordinates":[13.419222,52.552986],"type":"Point"}
}