{
  "type": "Feature",
  "properties": {
    "iso:country":"DE",
    "sg:address":"Graben",
    "sg:city":"Graben",
    "sg:postcode":"86836",
    "sg:province":"Bayern",
    "wof:name":"Pfister Gmbh",
    "wof:placetype":"venue"
},
  "geometry": {"coordinates":[10.8072843552,48.16173172],"type":"Point"}
}