{
  "type": "Feature",
  "properties": {
    "iso:country":"DE",
    "sg:address":"Rheinallee 1",
    "sg:city":"Eltville",
    "sg:phone":"+49 6723/640",
    "sg:postcode":"65347",
    "sg:province":"Hessen",
    "wof:name":"Hotel-restaurant Kronenschl\u00f6\u00dfchen",
    "wof:placetype":"venue"
},
  "geometry": {"coordinates":[8.0616378784,50.0133476257],"type":"Point"}
}