{
  "type": "Feature",
  "properties": {
    "iso:country":"DE",
    "sg:address":"Franz-Kirrmeier-Str. 19",
    "sg:city":"Speyer",
    "sg:phone":"+49 6232/35091",
    "sg:postcode":"67346",
    "sg:province":"Rheinland-Pfalz",
    "wof:name":"M\u00fcnch Industrieservice Gmbh",
    "wof:placetype":"venue"
},
  "geometry": {"coordinates":[8.447595,49.326328],"type":"Point"}
}