{
  "type": "Feature",
  "properties": {
    "iso:country":"DE",
    "sg:address":"Im Sand 3",
    "sg:city":"Kirchberg",
    "sg:phone":"+49 7954/7337",
    "sg:postcode":"74592",
    "sg:province":"Baden-W\u00fcrttemberg",
    "wof:name":"J. Kraft",
    "wof:placetype":"venue"
},
  "geometry": {"coordinates":[9.9653921127,49.2047462463],"type":"Point"}
}