{
  "type": "Feature",
  "properties": {
    "iso:country":"DE",
    "sg:address":"Hauptstr. 27",
    "sg:city":"Schrobenhausen",
    "sg:phone":"+49 8252/2410",
    "sg:postcode":"86529",
    "sg:province":"Bayern",
    "wof:name":"Ludwig Heggenstaller",
    "wof:placetype":"venue"
},
  "geometry": {"coordinates":[11.2038345337,48.5453567505],"type":"Point"}
}