{
  "type": "Feature",
  "properties": {
    "iso:country":"DE",
    "sg:address":"Hintergasse 18",
    "sg:city":"Schwansee",
    "sg:phone":"+49 36204/52272",
    "sg:postcode":"99195",
    "sg:province":"Th\u00fcringen",
    "wof:name":"K\u00fcstermann Gmbh",
    "wof:placetype":"venue"
},
  "geometry": {"coordinates":[11.0871562958,51.0800209045],"type":"Point"}
}