{
  "type": "Feature",
  "properties": {
    "iso:country":"DE",
    "sg:address":"Husumer Str. 66",
    "sg:city":"Flensburg",
    "sg:phone":"+49 461/96113",
    "sg:postcode":"24941",
    "sg:province":"Schleswig-Holstein",
    "wof:name":"R. Hagene",
    "wof:placetype":"venue"
},
  "geometry": {"coordinates":[9.423955,54.772411],"type":"Point"}
}