{
  "type": "Feature",
  "properties": {
    "iso:country":"DE",
    "sg:address":"Marzahner Str. 30 d",
    "sg:city":"Berlin",
    "sg:phone":"+49 30/9810050",
    "sg:postcode":"13053",
    "sg:province":"Berlin",
    "wof:name":"Adco Attwods & Dixi Umweltschutz Gmbh",
    "wof:placetype":"venue"
},
  "geometry": {"coordinates":[13.5251483917,52.5445709229],"type":"Point"}
}