{
  "type": "Feature",
  "properties": {
    "iso:country":"DE",
    "sg:address":"Nikolausstr. 18",
    "sg:city":"Stuttgart",
    "sg:phone":"+49 711/2626269",
    "sg:postcode":"70190",
    "sg:province":"Baden-W\u00fcrttemberg",
    "wof:name":"B. Kiolbassa",
    "wof:placetype":"venue"
},
  "geometry": {"coordinates":[9.1964025497,48.7879905701],"type":"Point"}
}