{
  "type": "Feature",
  "properties": {
    "iso:country":"DE",
    "sg:address":"Lindberghstr. 1",
    "sg:city":"Meckenbeuren",
    "sg:phone":"+49 7542/3350",
    "sg:postcode":"88074",
    "sg:province":"Baden-W\u00fcrttemberg",
    "wof:name":"Raphael-apotheke",
    "wof:placetype":"venue"
},
  "geometry": {"coordinates":[9.562848,47.697544],"type":"Point"}
}