{
  "type": "Feature",
  "properties": {
    "iso:country":"DE",
    "sg:address":"Klettwitzer Str. 11",
    "sg:city":"Annah\u00fctte",
    "sg:phone":"+49 35754/10098",
    "sg:postcode":"01994",
    "sg:province":"Brandenburg",
    "wof:name":"Acon Immobilien Gmbh",
    "wof:placetype":"venue"
},
  "geometry": {"coordinates":[13.896732,51.559132],"type":"Point"}
}