{
  "type": "Feature",
  "properties": {
    "iso:country":"DE",
    "sg:address":"Klingenberger Str. 13",
    "sg:city":"Erlenbach",
    "sg:phone":"+49 9372/4201",
    "sg:postcode":"63906",
    "sg:province":"Bayern",
    "wof:name":"Restaurant Zum Unkelbach",
    "wof:placetype":"venue"
},
  "geometry": {"coordinates":[9.161318779,49.801158905],"type":"Point"}
}