{
  "type": "Feature",
  "properties": {
    "iso:country":"DE",
    "sg:address":"G\u00f6rlitzer Str. 14",
    "sg:city":"Schwieberdingen",
    "sg:phone":"+49 7150/31551",
    "sg:postcode":"71701",
    "sg:province":"Baden-W\u00fcrttemberg",
    "wof:name":"D. Und U. G\u00f6tz Steuerberater",
    "wof:placetype":"venue"
},
  "geometry": {"coordinates":[9.0777359009,48.869758606],"type":"Point"}
}