{
  "type": "Feature",
  "properties": {
    "iso:country":"DE",
    "sg:address":"Fabrikstr. 12",
    "sg:city":"Ohmden",
    "sg:postcode":"73275",
    "sg:province":"Baden-W\u00fcrttemberg",
    "wof:name":"Omb Maschinenbau Gmbh",
    "wof:placetype":"venue"
},
  "geometry": {"coordinates":[9.517193,48.646023],"type":"Point"}
}