{
  "type": "Feature",
  "properties": {
    "iso:country":"DE",
    "sg:address":"Maximilianstr. 25",
    "sg:city":"Ingolstadt",
    "sg:phone":"+49 841/975566",
    "sg:postcode":"85051",
    "sg:province":"Bayern",
    "wof:name":"Djk Ingolstadt E.v.",
    "wof:placetype":"venue"
},
  "geometry": {"coordinates":[11.4238443375,48.7432365417],"type":"Point"}
}