{
  "type": "Feature",
  "properties": {
    "iso:country":"DE",
    "sg:address":"Langer Weg 29",
    "sg:city":"Dickel",
    "sg:phone":"+49 5445/1673",
    "sg:postcode":"49453",
    "sg:province":"Niedersachsen",
    "wof:name":"G. G\u00f6ttsch Gmbh",
    "wof:placetype":"venue"
},
  "geometry": {"coordinates":[8.4513292313,52.6380996704],"type":"Point"}
}