{
  "type": "Feature",
  "properties": {
    "iso:country":"DE",
    "sg:address":"Rathausstra\u00dfe 20",
    "sg:city":"Wiesbaden",
    "sg:phone":"+49 611/65151",
    "sg:postcode":"65203",
    "sg:province":"Hessen",
    "wof:name":"Hairline-ek In Wiesbaden",
    "wof:placetype":"venue"
},
  "geometry": {"coordinates":[8.237834,50.038197],"type":"Point"}
}