{
  "type": "Feature",
  "properties": {
    "iso:country":"DE",
    "sg:address":"Kapuzinerstr. 70",
    "sg:city":"Geldern",
    "sg:phone":"+49 2831/4124",
    "sg:postcode":"47608",
    "sg:province":"Nordrhein-Westfalen",
    "wof:name":"Hubertus Wolters",
    "wof:placetype":"venue"
},
  "geometry": {"coordinates":[6.327039,51.51619],"type":"Point"}
}