{
  "type": "Feature",
  "properties": {
    "iso:country":"DE",
    "sg:address":"Kirner Str. 17",
    "sg:city":"Hochstetten-Dhaun",
    "sg:phone":"+49 6752/2340",
    "sg:postcode":"55606",
    "sg:province":"Rheinland-Pfalz",
    "wof:name":"Flesch Gmbh",
    "wof:placetype":"venue"
},
  "geometry": {"coordinates":[7.461105,49.78516],"type":"Point"}
}