{
  "type": "Feature",
  "properties": {
    "iso:country":"DE",
    "sg:address":"Auf dem Aurain 1 b",
    "sg:city":"Limburg",
    "sg:phone":"+49 6431/91960",
    "sg:postcode":"65549",
    "sg:province":"Hessen",
    "wof:name":"J\u00fcrgen Schang Ingenieur",
    "wof:placetype":"venue"
},
  "geometry": {"coordinates":[8.0807437897,50.3963279724],"type":"Point"}
}