{
  "type": "Feature",
  "properties": {
    "iso:country":"DE",
    "sg:address":"Rheinische Str. 70",
    "sg:city":"Dortmund",
    "sg:phone":"+49 231/7214290",
    "sg:postcode":"44137",
    "sg:province":"Nordrhein-Westfalen",
    "wof:name":"Pilskontor",
    "wof:placetype":"venue"
},
  "geometry": {"coordinates":[7.4468421936,51.5128593445],"type":"Point"}
}