{
  "type": "Feature",
  "properties": {
    "iso:country":"DE",
    "sg:address":"Eberhardstr. 36",
    "sg:city":"Villingen-Schwenningen",
    "sg:phone":"+49 7720/956243",
    "sg:postcode":"78056",
    "sg:province":"Baden-W\u00fcrttemberg",
    "wof:name":"Peter Wiech Werbegeschenke",
    "wof:placetype":"venue"
},
  "geometry": {"coordinates":[8.5414657593,48.0629501343],"type":"Point"}
}