{
  "type": "Feature",
  "properties": {
    "iso:country":"DE",
    "sg:address":"Hohe Str 26",
    "sg:city":"Langenbernsdorf",
    "sg:phone":"+49 3761/75143",
    "sg:postcode":"08428",
    "sg:province":"Sachsen",
    "wof:name":"Hans Linke",
    "wof:placetype":"venue"
},
  "geometry": {"coordinates":[12.288629,50.746193],"type":"Point"}
}