{
  "type": "Feature",
  "properties": {
    "iso:country":"DE",
    "sg:address":"Graf-Stauffenberg-Str. 11",
    "sg:city":"Naumburg",
    "sg:phone":"+49 3445/703197",
    "sg:postcode":"06618",
    "sg:province":"Sachsen-Anhalt",
    "wof:name":"Kompter Reifen- Und Autoservice Gmbh",
    "wof:placetype":"venue"
},
  "geometry": {"coordinates":[11.819084,51.156261],"type":"Point"}
}