{
  "type": "Feature",
  "properties": {
    "iso:country":"DE",
    "sg:address":"Mainbullau-Flugplatz 158",
    "sg:city":"Miltenberg",
    "sg:postcode":"63897",
    "sg:province":"Bayern",
    "wof:name":"Deutsche Telekom T-punkt",
    "wof:placetype":"venue"
},
  "geometry": {"coordinates":[9.1799945831,49.6926651001],"type":"Point"}
}