{
  "type": "Feature",
  "properties": {
    "iso:country":"DE",
    "sg:address":"In'n D\u00f6rp 19",
    "sg:city":"Schee\u00dfel",
    "sg:phone":"+49 4263/1489",
    "sg:postcode":"27383",
    "sg:province":"Niedersachsen",
    "wof:name":"Walter Rathjen",
    "wof:placetype":"venue"
},
  "geometry": {"coordinates":[9.50579,53.177231],"type":"Point"}
}