{
  "type": "Feature",
  "properties": {
    "iso:country":"DE",
    "sg:address":"Lachenstr. 2",
    "sg:city":"Dautphetal",
    "sg:phone":"+49 6466/515",
    "sg:postcode":"35232",
    "sg:province":"Hessen",
    "wof:name":"Manfred Damm",
    "wof:placetype":"venue"
},
  "geometry": {"coordinates":[8.59517,50.873432],"type":"Point"}
}