{
  "type": "Feature",
  "properties": {
    "iso:country":"DE",
    "sg:address":"Timm-Kr\u00f6ger-Str. 6",
    "sg:city":"Itzehoe",
    "sg:phone":"+49 4821/2592",
    "sg:postcode":"25524",
    "sg:province":"Schleswig-Holstein",
    "wof:name":"Horst L\u00fctje",
    "wof:placetype":"venue"
},
  "geometry": {"coordinates":[9.514006,53.927109],"type":"Point"}
}