{
  "type": "Feature",
  "properties": {
    "iso:country":"DE",
    "sg:address":"Frankfurter Str. 23",
    "sg:city":"Altenkirchen",
    "sg:phone":"+49 2681/95650",
    "sg:postcode":"57610",
    "sg:province":"Rheinland-Pfalz",
    "wof:name":"H. Heinemann Ingenieur",
    "wof:placetype":"venue"
},
  "geometry": {"coordinates":[7.6506071091,50.6866149902],"type":"Point"}
}