{
  "type": "Feature",
  "properties": {
    "iso:country":"DE",
    "sg:address":"Gereutstr. 6",
    "sg:city":"Gr\u00fcnwald",
    "sg:phone":"+49 89/6415333",
    "sg:postcode":"82031",
    "sg:province":"Bayern",
    "wof:name":"Dr. Herta Bargmann-huber Rechtsanw\u00e4ltin",
    "wof:placetype":"venue"
},
  "geometry": {"coordinates":[11.526925087,48.0514068604],"type":"Point"}
}