{
  "type": "Feature",
  "properties": {
    "iso:country":"DE",
    "sg:address":"Adolfstr. 6",
    "sg:city":"Dresden",
    "sg:phone":"+49 351/8496641",
    "sg:postcode":"01139",
    "sg:province":"Sachsen",
    "wof:name":"Novoplan Gmbh",
    "wof:placetype":"venue"
},
  "geometry": {"coordinates":[13.703119278,51.0871276855],"type":"Point"}
}