{
  "type": "Feature",
  "properties": {
    "iso:country":"DE",
    "sg:address":"Hauptstr. 4",
    "sg:city":"Heidgraben",
    "sg:phone":"+49 4122/44206",
    "sg:postcode":"25436",
    "sg:province":"Schleswig-Holstein",
    "wof:name":"Manfred Jeromin",
    "wof:placetype":"venue"
},
  "geometry": {"coordinates":[9.6869449615,53.7056312561],"type":"Point"}
}