{
  "type": "Feature",
  "properties": {
    "iso:country":"DE",
    "sg:address":"Friedrich-Ebert-Str. 85-87",
    "sg:city":"Witten",
    "sg:phone":"+49 2302/80481",
    "sg:postcode":"58454",
    "sg:province":"Nordrhein-Westfalen",
    "wof:name":"Sico Gmbh",
    "wof:placetype":"venue"
},
  "geometry": {"coordinates":[7.394015,51.45079],"type":"Point"}
}