{
  "type": "Feature",
  "properties": {
    "iso:country":"DE",
    "sg:address":"Alexanderstr. 71-77",
    "sg:city":"Hagen",
    "sg:phone":"+49 2331/98830",
    "sg:postcode":"58097",
    "sg:province":"Nordrhein-Westfalen",
    "wof:name":"Helhoch Grundst\u00fccksverwer- Tungs- Und Verwaltungs Gmbh",
    "wof:placetype":"venue"
},
  "geometry": {"coordinates":[7.470358,51.376938],"type":"Point"}
}