{
  "type": "Feature",
  "properties": {
    "iso:country":"DE",
    "sg:address":"Erikastr. 38a",
    "sg:city":"Hamburg",
    "sg:phone":"+49 40/46093500",
    "sg:postcode":"20251",
    "sg:province":"Hamburg",
    "wof:name":"Birgit Nimzik Architektin",
    "wof:placetype":"venue"
},
  "geometry": {"coordinates":[9.988137,53.595139],"type":"Point"}
}