{
  "type": "Feature",
  "properties": {
    "iso:country":"DE",
    "sg:address":"Hafenstr. 196",
    "sg:city":"Bremerhaven",
    "sg:phone":"+49 471/57373",
    "sg:postcode":"27568",
    "sg:province":"Bremen",
    "wof:name":"Marion Grafender",
    "wof:placetype":"venue"
},
  "geometry": {"coordinates":[8.586402,53.563976],"type":"Point"}
}