{
  "type": "Feature",
  "properties": {
    "iso:country":"DE",
    "sg:address":"Altendorfer Str. 97/101",
    "sg:city":"Essen",
    "sg:phone":"+49 201/1711",
    "sg:postcode":"45143",
    "sg:province":"Nordrhein-Westfalen",
    "wof:name":"Imi Overseas Investments Deutschland Gesellschaft",
    "wof:placetype":"venue"
},
  "geometry": {"coordinates":[6.996468,51.458668],"type":"Point"}
}