{
  "type": "Feature",
  "properties": {
    "iso:country":"DE",
    "sg:address":"Bahnhofstr. 21",
    "sg:city":"Wilthen",
    "sg:phone":"+49 3592/33056",
    "sg:postcode":"02681",
    "sg:province":"Sachsen",
    "wof:name":"Ernst Heinke",
    "wof:placetype":"venue"
},
  "geometry": {"coordinates":[14.3870229721,51.0975608826],"type":"Point"}
}