{
  "type": "Feature",
  "properties": {
    "iso:country":"DE",
    "sg:address":"Dorfstr. 18",
    "sg:city":"P\u00f6ttmes",
    "sg:phone":"+49 8253/1314",
    "sg:postcode":"86554",
    "sg:province":"Bayern",
    "wof:name":"Gregor Bichler",
    "wof:placetype":"venue"
},
  "geometry": {"coordinates":[11.118784,48.54768],"type":"Point"}
}