{
  "type": "Feature",
  "properties": {
    "iso:country":"DE",
    "sg:address":"Hauptstr. 23",
    "sg:city":"Vettelscho\u00df",
    "sg:phone":"+49 2645/2325",
    "sg:postcode":"53560",
    "sg:province":"Rheinland-Pfalz",
    "wof:name":"Klaus Rygulla",
    "wof:placetype":"venue"
},
  "geometry": {"coordinates":[7.346725,50.618187],"type":"Point"}
}