{
  "type": "Feature",
  "properties": {
    "iso:country":"DE",
    "sg:address":"P\u00f6rnbacher Str. 28",
    "sg:city":"Reichertshofen",
    "sg:phone":"+49 8453/30282",
    "sg:postcode":"85084",
    "sg:province":"Bayern",
    "wof:name":"Karl H\u00e4u\u00dfler",
    "wof:placetype":"venue"
},
  "geometry": {"coordinates":[11.513303,48.640125],"type":"Point"}
}