{
  "type": "Feature",
  "properties": {
    "iso:country":"DE",
    "sg:address":"Erwin-Salomon-Str. 43",
    "sg:city":"Quickborn",
    "sg:postcode":"25451",
    "sg:province":"Schleswig-Holstein",
    "wof:name":"Inneneinrichtungen Seegebart Gmbh",
    "wof:placetype":"venue"
},
  "geometry": {"coordinates":[9.894468,53.725315],"type":"Point"}
}