{
  "type": "Feature",
  "properties": {
    "iso:country":"DE",
    "sg:address":"Bei den vier Linden 25",
    "sg:city":"Bremen",
    "sg:postcode":"28207",
    "sg:province":"Bremen",
    "wof:name":"K@ktus De.sign",
    "wof:placetype":"venue"
},
  "geometry": {"coordinates":[8.8629198074,53.0663871765],"type":"Point"}
}