{
  "type": "Feature",
  "properties": {
    "iso:country":"DE",
    "sg:address":"Marderweg 17",
    "sg:city":"Remseck",
    "sg:phone":"+49 7146/90740",
    "sg:postcode":"71686",
    "sg:province":"Baden-W\u00fcrttemberg",
    "wof:name":"Erich M\u00fcller Rechtsanwalt",
    "wof:placetype":"venue"
},
  "geometry": {"coordinates":[9.2461595535,48.862033844],"type":"Point"}
}