{
  "type": "Feature",
  "properties": {
    "iso:country":"DE",
    "sg:address":"Gartenstr. 4",
    "sg:city":"Gehrden",
    "sg:phone":"+49 5108/7231",
    "sg:postcode":"30989",
    "sg:province":"Niedersachsen",
    "wof:name":"Albert Schmidt",
    "wof:placetype":"venue"
},
  "geometry": {"coordinates":[9.599511,52.315216],"type":"Point"}
}