{
  "type": "Feature",
  "properties": {
    "iso:country":"DE",
    "sg:address":"Tannenweg 4",
    "sg:city":"Badenweiler",
    "sg:phone":"+49 7632/5832",
    "sg:postcode":"79410",
    "sg:province":"Baden-W\u00fcrttemberg",
    "wof:name":"Dr. Gustav Faber",
    "wof:placetype":"venue"
},
  "geometry": {"coordinates":[7.6851649284,47.802772522],"type":"Point"}
}