{
  "type": "Feature",
  "properties": {
    "iso:country":"DE",
    "sg:address":"Berliner Allee 32",
    "sg:city":"D\u00fcsseldorf",
    "sg:phone":"+49 211/131043",
    "sg:postcode":"40212",
    "sg:province":"Nordrhein-Westfalen",
    "wof:name":"Grundst\u00fccksgesellschaft Heerdt Mbh",
    "wof:placetype":"venue"
},
  "geometry": {"coordinates":[6.7826471329,51.2216110229],"type":"Point"}
}