{
  "type": "Feature",
  "properties": {
    "iso:country":"DE",
    "sg:address":"Kaiserstr. 44",
    "sg:city":"Friedberg",
    "sg:phone":"+49 6031/4320",
    "sg:postcode":"61169",
    "sg:province":"Hessen",
    "wof:name":"Georgio Simakis",
    "wof:placetype":"venue"
},
  "geometry": {"coordinates":[8.754184,50.338135],"type":"Point"}
}