{
  "type": "Feature",
  "properties": {
    "iso:country":"DE",
    "sg:address":"Dorfmerkinger Str.",
    "sg:city":"Neresheim",
    "sg:phone":"+49 7326/919255",
    "sg:postcode":"73450",
    "sg:province":"Baden-W\u00fcrttemberg",
    "wof:name":"K. Schmitt",
    "wof:placetype":"venue"
},
  "geometry": {"coordinates":[10.3378162384,48.7974586487],"type":"Point"}
}