{
  "type": "Feature",
  "properties": {
    "iso:country":"DE",
    "sg:address":"Weinstr. 9",
    "sg:city":"Edenkoben",
    "sg:phone":"+49 6323/2310",
    "sg:postcode":"67480",
    "sg:province":"Rheinland-Pfalz",
    "wof:name":"Robert Schmiedel",
    "wof:placetype":"venue"
},
  "geometry": {"coordinates":[8.1204147339,49.2790603638],"type":"Point"}
}