{
  "type": "Feature",
  "properties": {
    "iso:country":"DE",
    "sg:address":"Waldkugelweg 27",
    "sg:city":"W\u00fcrzburg",
    "sg:phone":"+49 931/81229",
    "sg:postcode":"97082",
    "sg:province":"Bayern",
    "wof:name":"Walter Flohr",
    "wof:placetype":"venue"
},
  "geometry": {"coordinates":[9.923084,49.768665],"type":"Point"}
}