{
  "type": "Feature",
  "properties": {
    "iso:country":"DE",
    "sg:address":"Talstr. 160",
    "sg:city":"Schriesheim",
    "sg:phone":"+49 6203/69800",
    "sg:postcode":"69198",
    "sg:province":"Baden-W\u00fcrttemberg",
    "wof:name":"Coating-plast Sandstrahlarbeiten",
    "wof:placetype":"venue"
},
  "geometry": {"coordinates":[8.6783752441,49.476184845],"type":"Point"}
}