{
  "type": "Feature",
  "properties": {
    "iso:country":"DE",
    "sg:address":"Buchhaldenstr. 4",
    "sg:city":"Sigmaringen",
    "sg:phone":"+49 7571/13338",
    "sg:postcode":"72488",
    "sg:province":"Baden-W\u00fcrttemberg",
    "wof:name":"G. Ensabella",
    "wof:placetype":"venue"
},
  "geometry": {"coordinates":[9.2148046494,48.0847702026],"type":"Point"}
}