{
  "type": "Feature",
  "properties": {
    "iso:country":"DE",
    "sg:address":"Gernsbacher Str. 36",
    "sg:city":"Bad Herrenalb",
    "sg:phone":"+49 7083/51626",
    "sg:postcode":"76332",
    "sg:province":"Baden-W\u00fcrttemberg",
    "wof:name":"Friedenszeichen E. V.",
    "wof:placetype":"venue"
},
  "geometry": {"coordinates":[8.4331617355,48.7951698303],"type":"Point"}
}