{
  "type": "Feature",
  "properties": {
    "iso:country":"DE",
    "sg:address":"Alte Poststr. 114",
    "sg:city":"Schermbeck",
    "sg:phone":"+49 2853/954490",
    "sg:postcode":"46514",
    "sg:province":"Nordrhein-Westfalen",
    "wof:name":"Camping - Gase - Shop In Schermbeck",
    "wof:placetype":"venue"
},
  "geometry": {"coordinates":[6.84978,51.6814],"type":"Point"}
}