{
  "type": "Feature",
  "properties": {
    "iso:country":"DE",
    "sg:address":"Rheinfeldstr. 45",
    "sg:city":"Ludwigshafen",
    "sg:phone":"+49 621/631648",
    "sg:postcode":"67063",
    "sg:province":"Rheinland-Pfalz",
    "wof:name":"Restaurant Il Trulletto",
    "wof:placetype":"venue"
},
  "geometry": {"coordinates":[8.4224567413,49.4982757568],"type":"Point"}
}