{
  "type": "Feature",
  "properties": {
    "iso:country":"DE",
    "sg:address":"Herrnbaustr. 15",
    "sg:city":"Bad Soden",
    "sg:phone":"+49 6196/641112",
    "sg:postcode":"65812",
    "sg:province":"Hessen",
    "wof:name":"Georg Conrads Gmbh",
    "wof:placetype":"venue"
},
  "geometry": {"coordinates":[8.48548,50.151199],"type":"Point"}
}