{
  "type": "Feature",
  "properties": {
    "iso:country":"DE",
    "sg:address":"Josef-Ruhr-Str. 8",
    "sg:city":"Euskirchen",
    "sg:phone":"+49 2251/71022",
    "sg:postcode":"53879",
    "sg:province":"Nordrhein-Westfalen",
    "wof:name":"Christian Forst",
    "wof:placetype":"venue"
},
  "geometry": {"coordinates":[6.7830600739,50.6468925476],"type":"Point"}
}