{
  "type": "Feature",
  "properties": {
    "iso:country":"DE",
    "sg:address":"Herrnsheimer Hauptstr. 82",
    "sg:city":"Worms",
    "sg:phone":"+49 6241/58435",
    "sg:postcode":"67550",
    "sg:province":"Rheinland-Pfalz",
    "wof:name":"Raymund Scheuermann",
    "wof:placetype":"venue"
},
  "geometry": {"coordinates":[8.334185,49.653179],"type":"Point"}
}