{
  "type": "Feature",
  "properties": {
    "iso:country":"DE",
    "sg:address":"Breslauer Str. 12",
    "sg:city":"Haan",
    "sg:phone":"+49 212/91263",
    "sg:postcode":"42781",
    "sg:province":"Nordrhein-Westfalen",
    "wof:name":"Kehren Automaten Inh. Ursula Wolfertz",
    "wof:placetype":"venue"
},
  "geometry": {"coordinates":[7.0080528259,51.1996688843],"type":"Point"}
}