{
  "type": "Feature",
  "properties": {
    "iso:country":"DE",
    "sg:address":"Neckarstr. 86",
    "sg:city":"Esslingen",
    "sg:phone":"+49 711/316337",
    "sg:postcode":"73728",
    "sg:province":"Baden-W\u00fcrttemberg",
    "wof:name":"Gothaer Versicherung A.g. M. Rayer",
    "wof:placetype":"venue"
},
  "geometry": {"coordinates":[9.3169126511,48.7364692688],"type":"Point"}
}