{
  "type": "Feature",
  "properties": {
    "iso:country":"DE",
    "sg:address":"Hauptstr. 16",
    "sg:city":"Schleid",
    "sg:phone":"+49 6569/7312",
    "sg:postcode":"54636",
    "sg:province":"Rheinland-Pfalz",
    "wof:name":"Matthias Becker",
    "wof:placetype":"venue"
},
  "geometry": {"coordinates":[6.490123,50.059204],"type":"Point"}
}