{
  "type": "Feature",
  "properties": {
    "iso:country":"DE",
    "sg:address":"Grubenweg 12",
    "sg:city":"Quierschied",
    "sg:phone":"+49 6897/61912",
    "sg:postcode":"66287",
    "sg:province":"Saarland",
    "wof:name":"Artur Scherer Architekt",
    "wof:placetype":"venue"
},
  "geometry": {"coordinates":[7.05353,49.328838],"type":"Point"}
}