{
  "type": "Feature",
  "properties": {
    "iso:country":"DE",
    "sg:address":"Haldenweg 32",
    "sg:city":"Ravensburg",
    "sg:phone":"+49 751/31072",
    "sg:postcode":"88212",
    "sg:province":"Baden-W\u00fcrttemberg",
    "wof:name":"Wolfgang Ge\u00dfler Architekt",
    "wof:placetype":"venue"
},
  "geometry": {"coordinates":[9.62612,47.78244],"type":"Point"}
}