{
  "type": "Feature",
  "properties": {
    "iso:country":"DE",
    "sg:address":"Ostseeallee 7",
    "sg:city":"K\u00fchlungsborn",
    "sg:phone":"+49 38293/180",
    "sg:postcode":"18225",
    "sg:province":"Mecklenburg-Vorpommern",
    "wof:name":"Hotel Seeschloss Hotelbetriebsges. Mbh",
    "wof:placetype":"venue"
},
  "geometry": {"coordinates":[11.7570123672,54.1536598206],"type":"Point"}
}