{
  "type": "Feature",
  "properties": {
    "iso:country":"DE",
    "sg:address":"Albert-Einstein-Str 9",
    "sg:city":"Wiehl",
    "sg:phone":"+49 2261/5420",
    "sg:postcode":"51674",
    "sg:province":"Nordrhein-Westfalen",
    "wof:name":"As Creation Tapeten Ag",
    "wof:placetype":"venue"
},
  "geometry": {"coordinates":[7.5434799194,50.968914032],"type":"Point"}
}