{
  "type": "Feature",
  "properties": {
    "iso:country":"DE",
    "sg:address":"Lucas-Cranach-Str. 12",
    "sg:city":"Cottbus",
    "sg:phone":"+49 355/872405",
    "sg:postcode":"03044",
    "sg:province":"Brandenburg",
    "wof:name":"I. Raabe",
    "wof:placetype":"venue"
},
  "geometry": {"coordinates":[14.3298511505,51.7802238464],"type":"Point"}
}