{
  "type": "Feature",
  "properties": {
    "iso:country":"DE",
    "sg:address":"Hauptstr. 1a",
    "sg:city":"Kirchlauter",
    "sg:phone":"+49 9536/406",
    "sg:postcode":"96166",
    "sg:province":"Bayern",
    "wof:name":"H\u00fcmmer Reisen Inh. Bernhard H\u00fcmmer",
    "wof:placetype":"venue"
},
  "geometry": {"coordinates":[10.7103424072,50.0433082581],"type":"Point"}
}