{
  "type": "Feature",
  "properties": {
    "iso:country":"DE",
    "sg:address":"Reichenbacher Str. 18",
    "sg:city":"Striegistal",
    "sg:phone":"+49 37207/2721",
    "sg:postcode":"09661",
    "sg:province":"Sachsen",
    "wof:name":"Pension Striegistal",
    "wof:placetype":"venue"
},
  "geometry": {"coordinates":[13.2106056213,50.9881057739],"type":"Point"}
}