{
  "type": "Feature",
  "properties": {
    "iso:country":"DE",
    "sg:address":"Heilbronnerstr.66",
    "sg:city":"Gundelsheim",
    "sg:phone":"+49 4962/69337",
    "sg:postcode":"74831",
    "sg:province":"Baden-W\u00fcrttemberg",
    "wof:name":"Kallenberger S\u00c4gewerk Gmbh",
    "wof:placetype":"venue"
},
  "geometry": {"coordinates":[9.1597642899,49.2791252136],"type":"Point"}
}