{
  "type": "Feature",
  "properties": {
    "iso:country":"DE",
    "sg:address":"Oderchaussee 2 a",
    "sg:city":"Genschmar",
    "sg:postcode":"15328",
    "sg:province":"Brandenburg",
    "wof:name":"Genschmarer Fleischrind Gmbh",
    "wof:placetype":"venue"
},
  "geometry": {"coordinates":[14.5140218735,52.6093788147],"type":"Point"}
}