{
  "type": "Feature",
  "properties": {
    "iso:country":"DE",
    "sg:address":"Talstr. 2",
    "sg:city":"Kirchheim",
    "sg:phone":"+49 7143/91059",
    "sg:postcode":"74366",
    "sg:province":"Baden-W\u00fcrttemberg",
    "wof:name":"Ponto Transport Gmbh",
    "wof:placetype":"venue"
},
  "geometry": {"coordinates":[9.1407842636,49.0425796509],"type":"Point"}
}