{
  "type": "Feature",
  "properties": {
    "iso:country":"DE",
    "sg:address":"Blumenstr. 24",
    "sg:city":"Bessenbach",
    "sg:phone":"+49 6095/995790",
    "sg:postcode":"63856",
    "sg:province":"Bayern",
    "wof:name":"Anton Und Maria Hock",
    "wof:placetype":"venue"
},
  "geometry": {"coordinates":[9.24738,49.974419],"type":"Point"}
}