{
  "type": "Feature",
  "properties": {
    "iso:country":"DE",
    "sg:address":"Brautwiesenstr. 4",
    "sg:city":"G\u00f6rlitz",
    "sg:phone":"+49 3581/317386",
    "sg:postcode":"02826",
    "sg:province":"Sachsen",
    "wof:name":"Central",
    "wof:placetype":"venue"
},
  "geometry": {"coordinates":[14.9690227509,51.1509971619],"type":"Point"}
}