{
  "type": "Feature",
  "properties": {
    "iso:country":"DE",
    "sg:address":"Grevinghof 26",
    "sg:city":"Werne",
    "sg:phone":"+49 2389/40050",
    "sg:postcode":"59368",
    "sg:province":"Nordrhein-Westfalen",
    "wof:name":"Kurt Schmitz-kl\u00fcner Steuerberater",
    "wof:placetype":"venue"
},
  "geometry": {"coordinates":[7.6297450066,51.6703643799],"type":"Point"}
}