{
  "type": "Feature",
  "properties": {
    "iso:country":"DE",
    "sg:address":"Keltenweg 17",
    "sg:city":"Baden-Baden",
    "sg:phone":"+49 7221/63369",
    "sg:postcode":"76532",
    "sg:province":"Baden-W\u00fcrttemberg",
    "wof:name":"Friedrich Braunagel Architekt",
    "wof:placetype":"venue"
},
  "geometry": {"coordinates":[8.213182,48.781418],"type":"Point"}
}