{
  "type": "Feature",
  "properties": {
    "iso:country":"DE",
    "sg:address":"Afrikanische Str. 158",
    "sg:city":"Berlin",
    "sg:phone":"+49 30/4515050",
    "sg:postcode":"13351",
    "sg:province":"Berlin",
    "wof:name":"Checker Taxi New York Cap",
    "wof:placetype":"venue"
},
  "geometry": {"coordinates":[13.333704,52.560181],"type":"Point"}
}