{
  "type": "Feature",
  "properties": {
    "iso:country":"DE",
    "sg:address":"Steinbacher Str. 7b",
    "sg:city":"Bad Liebenstein",
    "sg:phone":"+49 36961/30664",
    "sg:postcode":"36448",
    "sg:province":"Th\u00fcringen",
    "wof:name":"Ellen Heckel",
    "wof:placetype":"venue"
},
  "geometry": {"coordinates":[10.342974,50.821392],"type":"Point"}
}