{
  "type": "Feature",
  "properties": {
    "iso:country":"DE",
    "sg:address":"An der Heerstr. 28",
    "sg:city":"Salzgitter",
    "sg:phone":"+49 5341/58245",
    "sg:postcode":"38228",
    "sg:province":"Niedersachsen",
    "wof:name":"Landgasthof Altes Zollhaus",
    "wof:placetype":"venue"
},
  "geometry": {"coordinates":[10.2674102783,52.1340904236],"type":"Point"}
}