{
  "type": "Feature",
  "properties": {
    "iso:country":"DE",
    "sg:address":"Beethovenstr 27-39",
    "sg:city":"Chemnitz",
    "sg:phone":"+49 371/434750",
    "sg:postcode":"09130",
    "sg:province":"Sachsen",
    "wof:name":"Neubauer Gmbh",
    "wof:placetype":"venue"
},
  "geometry": {"coordinates":[12.947036,50.839279],"type":"Point"}
}