{
  "type": "Feature",
  "properties": {
    "iso:country":"DE",
    "sg:address":"Kupferberg 1",
    "sg:city":"Glauchau",
    "sg:phone":"+49 3763/52093",
    "sg:postcode":"08371",
    "sg:province":"Sachsen",
    "wof:name":"A. Kolbe Immobilienmakler",
    "wof:placetype":"venue"
},
  "geometry": {"coordinates":[12.5483522415,50.8170051575],"type":"Point"}
}