{
  "type": "Feature",
  "properties": {
    "iso:country":"DE",
    "sg:address":"Eppsteiner Str. 42",
    "sg:city":"Frankfurt",
    "sg:phone":"+49 69/727476",
    "sg:postcode":"60323",
    "sg:province":"Hessen",
    "wof:name":"Income Incasso Gmbh",
    "wof:placetype":"venue"
},
  "geometry": {"coordinates":[8.6650867462,50.120349884],"type":"Point"}
}