{
  "type": "Feature",
  "properties": {
    "iso:country":"DE",
    "sg:address":"Bottroper Str. 7-9",
    "sg:city":"Gelsenkirchen",
    "sg:phone":"+49 209/951960",
    "sg:postcode":"45899",
    "sg:province":"Nordrhein-Westfalen",
    "wof:name":"Berghorn Verwaltungs Gmbh",
    "wof:placetype":"venue"
},
  "geometry": {"coordinates":[7.0180058479,51.5367393494],"type":"Point"}
}