{
  "type": "Feature",
  "properties": {
    "iso:country":"DE",
    "sg:address":"Herbartstr. 9",
    "sg:city":"Sande",
    "sg:phone":"+49 4422/2133",
    "sg:postcode":"26452",
    "sg:province":"Niedersachsen",
    "wof:name":"G. Kasper Heissmangelbetrieb",
    "wof:placetype":"venue"
},
  "geometry": {"coordinates":[8.0206708908,53.4993515015],"type":"Point"}
}