{
  "type": "Feature",
  "properties": {
    "iso:country":"DE",
    "sg:address":"Abt-Hyller-Str. 34",
    "sg:city":"Weingarten",
    "sg:phone":"+49 751/44742",
    "sg:postcode":"88250",
    "sg:province":"Baden-W\u00fcrttemberg",
    "wof:name":"E. Beller Versicherungen",
    "wof:placetype":"venue"
},
  "geometry": {"coordinates":[9.6345653534,47.8094558716],"type":"Point"}
}