{
  "type": "Feature",
  "properties": {
    "iso:country":"DE",
    "sg:address":"Serkenroder Str. 112",
    "sg:city":"Finnentrop",
    "sg:phone":"+49 2721/979306",
    "sg:postcode":"57413",
    "sg:province":"Nordrhein-Westfalen",
    "wof:name":"Reinhard L\u00e4mmchen",
    "wof:placetype":"venue"
},
  "geometry": {"coordinates":[7.9809088707,51.1747741699],"type":"Point"}
}