{
  "type": "Feature",
  "properties": {
    "iso:country":"DE",
    "sg:address":"Oberreihe 1a",
    "sg:city":"Kr\u00f6slin",
    "sg:phone":"+49 38370/20369",
    "sg:postcode":"17440",
    "sg:province":"Mecklenburg-Vorpommern",
    "wof:name":"Ute Heidmann",
    "wof:placetype":"venue"
},
  "geometry": {"coordinates":[13.725736,54.134335],"type":"Point"}
}