{
  "type": "Feature",
  "properties": {
    "iso:country":"DE",
    "sg:address":"R\u00fcgener Ring 35",
    "sg:city":"Sassnitz",
    "sg:phone":"+49 38392/35121",
    "sg:postcode":"18546",
    "sg:province":"Mecklenburg-Vorpommern",
    "wof:name":"Tmu Treuhandgesellschaft Mbh",
    "wof:placetype":"venue"
},
  "geometry": {"coordinates":[13.6187477112,54.5159111023],"type":"Point"}
}