{
  "type": "Feature",
  "properties": {
    "iso:country":"DE",
    "sg:address":"Brandstr. 3",
    "sg:city":"Eldingen",
    "sg:phone":"+49 5148/616",
    "sg:postcode":"29351",
    "sg:province":"Niedersachsen",
    "wof:name":"Bohr- Und Vortriebstechnik Celle Dralle & Nowak Gmbh",
    "wof:placetype":"venue"
},
  "geometry": {"coordinates":[10.339851,52.686497],"type":"Point"}
}