{
  "type": "Feature",
  "properties": {
    "iso:country":"DE",
    "sg:address":"Wiedemannstr. 51",
    "sg:city":"M\u00f6nchengladbach",
    "sg:phone":"+49 2166/601465",
    "sg:postcode":"41199",
    "sg:province":"Nordrhein-Westfalen",
    "wof:name":"Heinz Grimm Gmbh",
    "wof:placetype":"venue"
},
  "geometry": {"coordinates":[6.447094,51.13031],"type":"Point"}
}