{
  "type": "Feature",
  "properties": {
    "iso:country":"DE",
    "sg:address":"Im Bruch",
    "sg:city":"Philippsburg",
    "sg:phone":"+49 7256/4735",
    "sg:postcode":"76661",
    "sg:province":"Baden-W\u00fcrttemberg",
    "wof:name":"Hermann Herd",
    "wof:placetype":"venue"
},
  "geometry": {"coordinates":[8.46664,49.194294],"type":"Point"}
}