{
  "type": "Feature",
  "properties": {
    "iso:country":"DE",
    "sg:address":"Kantstr. 15",
    "sg:city":"Kirkel",
    "sg:phone":"+49 6841/8247",
    "sg:postcode":"66459",
    "sg:province":"Saarland",
    "wof:name":"Spray-strauch Otto John Inh. Helene Strauch",
    "wof:placetype":"venue"
},
  "geometry": {"coordinates":[7.29209,49.326553],"type":"Point"}
}