{
  "type": "Feature",
  "properties": {
    "iso:country":"DE",
    "sg:address":"Altenhainer Dorfstr. 39",
    "sg:city":"Chemnitz",
    "sg:phone":"+49 371/772342",
    "sg:postcode":"09128",
    "sg:province":"Sachsen",
    "wof:name":"Sauna- Und Schwimmbadbau Lutz Poser E. Kfm.",
    "wof:placetype":"venue"
},
  "geometry": {"coordinates":[13.020125,50.791744],"type":"Point"}
}