{
  "type": "Feature",
  "properties": {
    "iso:country":"DE",
    "sg:address":"Hauptstr. 29",
    "sg:city":"Dallgow",
    "sg:phone":"+49 3322/22184",
    "sg:postcode":"14624",
    "sg:province":"Brandenburg",
    "wof:name":"Gesellschaft F\u00fcr Bautenschutz Und Sch\u00e4dlingsbek\u00e4mpfung Mbh",
    "wof:placetype":"venue"
},
  "geometry": {"coordinates":[13.041636,52.543179],"type":"Point"}
}