{
  "type": "Feature",
  "properties": {
    "iso:country":"DE",
    "sg:address":"Ferdinand-Harten-Str. 5",
    "sg:city":"Ammersbek",
    "sg:postcode":"22949",
    "sg:province":"Schleswig-Holstein",
    "wof:name":"United Seals Beteiligungs-gmbh",
    "wof:placetype":"venue"
},
  "geometry": {"coordinates":[10.144165,53.678825],"type":"Point"}
}