{
  "type": "Feature",
  "properties": {
    "iso:country":"DE",
    "sg:address":"Lahnstr. 15",
    "sg:city":"Bad Laasphe",
    "sg:phone":"+49 2752/6252",
    "sg:postcode":"57334",
    "sg:province":"Nordrhein-Westfalen",
    "wof:name":"Dirk Duchardt",
    "wof:placetype":"venue"
},
  "geometry": {"coordinates":[8.4113531113,50.9246902466],"type":"Point"}
}