{
  "type": "Feature",
  "properties": {
    "iso:country":"DE",
    "sg:address":"Deichelweiherweg 12",
    "sg:city":"Freiburg",
    "sg:postcode":"79102",
    "sg:province":"Baden-W\u00fcrttemberg",
    "wof:name":"Darwin - Mlm F\u00fcr Kaufleute",
    "wof:placetype":"venue"
},
  "geometry": {"coordinates":[7.8652849197,47.9857254028],"type":"Point"}
}