{
  "type": "Feature",
  "properties": {
    "iso:country":"DE",
    "sg:address":"Starkenburger Str. 15",
    "sg:city":"Frankfurt",
    "sg:phone":"+49 69/423159",
    "sg:postcode":"60386",
    "sg:province":"Hessen",
    "wof:name":"K. Desoi",
    "wof:placetype":"venue"
},
  "geometry": {"coordinates":[8.7723722458,50.1202735901],"type":"Point"}
}