{
  "type": "Feature",
  "properties": {
    "iso:country":"DE",
    "sg:address":"Obergasse 7",
    "sg:city":"Alsfeld",
    "sg:phone":"+49 6631/72510",
    "sg:postcode":"36304",
    "sg:province":"Hessen",
    "wof:name":"Bauer",
    "wof:placetype":"venue"
},
  "geometry": {"coordinates":[9.270885,50.751415],"type":"Point"}
}