{
  "type": "Feature",
  "properties": {
    "iso:country":"DE",
    "sg:address":"Thedinghauser Str. 50",
    "sg:city":"Bremen",
    "sg:phone":"+49 421/553762",
    "sg:postcode":"28201",
    "sg:province":"Bremen",
    "wof:name":"Dieter R\u00f6mer",
    "wof:placetype":"venue"
},
  "geometry": {"coordinates":[8.793932,53.063671],"type":"Point"}
}