{
  "type": "Feature",
  "properties": {
    "iso:country":"DE",
    "sg:address":"Hans-Thoma-Str. 21",
    "sg:city":"Mannheim",
    "sg:postcode":"68163",
    "sg:province":"Baden-W\u00fcrttemberg",
    "wof:name":"Cecom Ag",
    "wof:placetype":"venue"
},
  "geometry": {"coordinates":[8.5279273987,49.4742774963],"type":"Point"}
}