{
  "type": "Feature",
  "properties": {
    "iso:country":"DE",
    "sg:address":"Linke Brandstr. 2",
    "sg:city":"Augsburg",
    "sg:phone":"+49 821/707171",
    "sg:postcode":"86167",
    "sg:province":"Bayern",
    "wof:name":"Da Vito",
    "wof:placetype":"venue"
},
  "geometry": {"coordinates":[10.9157943726,48.3877944946],"type":"Point"}
}