{
  "type": "Feature",
  "properties": {
    "iso:country":"DE",
    "sg:address":"Draht 20",
    "sg:city":"Pfaffenhofen",
    "sg:phone":"+49 8441/1515",
    "sg:postcode":"85276",
    "sg:province":"Bayern",
    "wof:name":"Anton B\u00e4uml",
    "wof:placetype":"venue"
},
  "geometry": {"coordinates":[11.5045862198,48.5276947021],"type":"Point"}
}