{
  "type": "Feature",
  "properties": {
    "iso:country":"DE",
    "sg:address":"Motzstr. 3",
    "sg:city":"Berlin",
    "sg:phone":"+49 30/2151818",
    "sg:postcode":"10777",
    "sg:province":"Berlin",
    "wof:name":"Emmy Schulzki",
    "wof:placetype":"venue"
},
  "geometry": {"coordinates":[13.3519420624,52.4988594055],"type":"Point"}
}