{
  "type": "Feature",
  "properties": {
    "iso:country":"DE",
    "sg:address":"B\u00e4uersche Str. 2",
    "sg:city":"Blankenburg",
    "sg:postcode":"38889",
    "sg:province":"Sachsen-Anhalt",
    "wof:name":"Karl Schmelzer",
    "wof:placetype":"venue"
},
  "geometry": {"coordinates":[10.953063,51.789608],"type":"Point"}
}