{
  "type": "Feature",
  "properties": {
    "iso:country":"DE",
    "sg:address":"Im Iller 19",
    "sg:city":"Felsberg",
    "sg:phone":"+49 5662/2218",
    "sg:postcode":"34587",
    "sg:province":"Hessen",
    "wof:name":"Bernhard Besse",
    "wof:placetype":"venue"
},
  "geometry": {"coordinates":[9.471831,51.10429],"type":"Point"}
}