{
  "type": "Feature",
  "properties": {
    "iso:country":"DE",
    "sg:address":"Drosselweg 28",
    "sg:city":"Edingen-Neckarhausen",
    "sg:phone":"+49 6203/81570",
    "sg:postcode":"68535",
    "sg:province":"Baden-W\u00fcrttemberg",
    "wof:name":"Winfried Busch",
    "wof:placetype":"venue"
},
  "geometry": {"coordinates":[8.6037435532,49.4446563721],"type":"Point"}
}