{
  "type": "Feature",
  "properties": {
    "iso:country":"DE",
    "sg:address":"Altenbr\u00fcckertorstr. 11 - 12",
    "sg:city":"L\u00fcneburg",
    "sg:phone":"+49 4131/44735",
    "sg:postcode":"21335",
    "sg:province":"Niedersachsen",
    "wof:name":"China-restaurant Altenbr\u00fccker Tor Gmbh",
    "wof:placetype":"venue"
},
  "geometry": {"coordinates":[10.4145803452,53.2476501465],"type":"Point"}
}