{
  "type": "Feature",
  "properties": {
    "iso:country":"DE",
    "sg:address":"Fridolinstr. 54",
    "sg:city":"K\u00f6ln",
    "sg:phone":"+49 221/5505123",
    "sg:postcode":"50825",
    "sg:province":"Nordrhein-Westfalen",
    "wof:name":"Joachim Stenger",
    "wof:placetype":"venue"
},
  "geometry": {"coordinates":[6.9195561409,50.9552192688],"type":"Point"}
}