{
  "type": "Feature",
  "properties": {
    "iso:country":"DE",
    "sg:address":"Im Kiwitt 33a",
    "sg:city":"Heiden",
    "sg:phone":"+49 4928/6797410",
    "sg:postcode":"46359",
    "sg:province":"Nordrhein-Westfalen",
    "wof:name":"Rcg Kartoffel-vertrieb Gmbh",
    "wof:placetype":"venue"
},
  "geometry": {"coordinates":[6.947132,51.824436],"type":"Point"}
}