{
  "type": "Feature",
  "properties": {
    "iso:country":"DE",
    "sg:address":"Curt-Goetz-Str. 75",
    "sg:city":"Mainz",
    "sg:postcode":"55127",
    "sg:province":"Rheinland-Pfalz",
    "wof:name":"Steinbacher Treuhand Gmbh",
    "wof:placetype":"venue"
},
  "geometry": {"coordinates":[8.1993818283,49.9757766724],"type":"Point"}
}