{
  "type": "Feature",
  "properties": {
    "iso:country":"DE",
    "sg:address":"Kanzlei 11",
    "sg:city":"Meerbusch",
    "sg:phone":"+49 2150/5775",
    "sg:postcode":"40667",
    "sg:province":"Nordrhein-Westfalen",
    "wof:name":"Zimmerei P\u00fctz Gmbh",
    "wof:placetype":"venue"
},
  "geometry": {"coordinates":[6.6818728447,51.2554206848],"type":"Point"}
}