{
  "type": "Feature",
  "properties": {
    "iso:country":"DE",
    "sg:address":"Vorwerk 12",
    "sg:city":"Lengefeld",
    "sg:phone":"+49 37367/82718",
    "sg:postcode":"09514",
    "sg:province":"Sachsen",
    "wof:name":"Reiner Fischer",
    "wof:placetype":"venue"
},
  "geometry": {"coordinates":[13.1708,50.714199],"type":"Point"}
}