{
  "type": "Feature",
  "properties": {
    "iso:country":"DE",
    "sg:address":"Dorf 8",
    "sg:city":"Moltenow",
    "sg:phone":"+49 38464/20275",
    "sg:postcode":"18246",
    "sg:province":"Mecklenburg-Vorpommern",
    "wof:name":"Owi Bautr\u00e4ger Gmbh & Co. Kg",
    "wof:placetype":"venue"
},
  "geometry": {"coordinates":[11.829994,53.908642],"type":"Point"}
}