{
  "type": "Feature",
  "properties": {
    "iso:country":"DE",
    "sg:address":"Daimlerstr. 14",
    "sg:city":"K\u00f6ln",
    "sg:phone":"+49 2234/77478",
    "sg:postcode":"50859",
    "sg:province":"Nordrhein-Westfalen",
    "wof:name":"Paracknowicz Gmbh",
    "wof:placetype":"venue"
},
  "geometry": {"coordinates":[6.842999,50.948822],"type":"Point"}
}