{
  "type": "Feature",
  "properties": {
    "iso:country":"DE",
    "sg:address":"Franz-Sigel-Str. 83",
    "sg:city":"Bruchsal",
    "sg:phone":"+49 7251/931830",
    "sg:postcode":"76646",
    "sg:province":"Baden-W\u00fcrttemberg",
    "wof:name":"Punkt-apotheke",
    "wof:placetype":"venue"
},
  "geometry": {"coordinates":[8.56891,49.112621],"type":"Point"}
}