{
  "type": "Feature",
  "properties": {
    "iso:country":"DE",
    "sg:address":"Im S\u00e4ssel 4",
    "sg:city":"Bassenheim",
    "sg:phone":"+49 2625/6262",
    "sg:postcode":"56220",
    "sg:province":"Rheinland-Pfalz",
    "wof:name":"W. Mathias",
    "wof:placetype":"venue"
},
  "geometry": {"coordinates":[7.46476,50.356667],"type":"Point"}
}