{
  "type": "Feature",
  "properties": {
    "iso:country":"DE",
    "sg:address":"Papiergarten 10",
    "sg:city":"Langelsheim",
    "sg:phone":"+49 5326/2244",
    "sg:postcode":"38685",
    "sg:province":"Niedersachsen",
    "wof:name":"Herm. Ehli",
    "wof:placetype":"venue"
},
  "geometry": {"coordinates":[10.333234787,51.9347190857],"type":"Point"}
}