{
  "type": "Feature",
  "properties": {
    "iso:country":"DE",
    "sg:address":"Kehlhofweg",
    "sg:city":"Tengen",
    "sg:phone":"+49 7736/544",
    "sg:postcode":"78250",
    "sg:province":"Baden-W\u00fcrttemberg",
    "wof:name":"Karl Maus",
    "wof:placetype":"venue"
},
  "geometry": {"coordinates":[8.6349,47.806629],"type":"Point"}
}