{
  "type": "Feature",
  "properties": {
    "iso:country":"DE",
    "sg:address":"Kaiser-Otto-Platz 4",
    "sg:city":"Meschede",
    "sg:phone":"+49 291/52123",
    "sg:postcode":"59872",
    "sg:province":"Nordrhein-Westfalen",
    "wof:name":"Amaro Marques",
    "wof:placetype":"venue"
},
  "geometry": {"coordinates":[8.283516,51.345806],"type":"Point"}
}