{
  "type": "Feature",
  "properties": {
    "iso:country":"DE",
    "sg:address":"Nemeterstr. 25",
    "sg:city":"K\u00f6ln",
    "sg:phone":"+49 221/353265",
    "sg:postcode":"50996",
    "sg:province":"Nordrhein-Westfalen",
    "wof:name":"Ursula Neumann-schlieder Steuerberaterin",
    "wof:placetype":"venue"
},
  "geometry": {"coordinates":[6.9895467758,50.8892631531],"type":"Point"}
}