{
  "type": "Feature",
  "properties": {
    "iso:country":"DE",
    "sg:address":"Fritz-M\u00fcller-Str. 10",
    "sg:city":"Esslingen",
    "sg:postcode":"73730",
    "sg:province":"Baden-W\u00fcrttemberg",
    "wof:name":"Kast & Schlecht Systemverkehre Gmbh",
    "wof:placetype":"venue"
},
  "geometry": {"coordinates":[9.327495,48.729362],"type":"Point"}
}