{
  "type": "Feature",
  "properties": {
    "iso:country":"DE",
    "sg:address":"Martinstr. 167",
    "sg:city":"Krefeld",
    "sg:phone":"+49 2151/311840",
    "sg:postcode":"47805",
    "sg:province":"Nordrhein-Westfalen",
    "wof:name":"Kaffeehaus Schmitz Cafe",
    "wof:placetype":"venue"
},
  "geometry": {"coordinates":[6.551744,51.318939],"type":"Point"}
}