{
  "type": "Feature",
  "properties": {
    "iso:country":"DE",
    "sg:address":"Hegelstr. 6",
    "sg:city":"N\u00fcrtingen",
    "sg:phone":"+49 7022/8892",
    "sg:postcode":"72622",
    "sg:province":"Baden-W\u00fcrttemberg",
    "wof:name":"H. Mellmann Ingenieur",
    "wof:placetype":"venue"
},
  "geometry": {"coordinates":[9.3520956039,48.6183815002],"type":"Point"}
}