{
  "type": "Feature",
  "properties": {
    "iso:country":"DE",
    "sg:address":"Am Zoll 3-5",
    "sg:city":"Losheim",
    "sg:phone":"+49 6872/92020",
    "sg:postcode":"66679",
    "sg:province":"Saarland",
    "wof:name":"Grimm Gmbh & Co Kg",
    "wof:placetype":"venue"
},
  "geometry": {"coordinates":[6.67214,49.527138],"type":"Point"}
}