{
  "type": "Feature",
  "properties": {
    "iso:country":"DE",
    "sg:address":"Korsorsstr. 444",
    "sg:city":"Wardenburg",
    "sg:phone":"+49 4407/6373",
    "sg:postcode":"26203",
    "sg:province":"Niedersachsen",
    "wof:name":"Erich Pannemann",
    "wof:placetype":"venue"
},
  "geometry": {"coordinates":[8.088698,53.070316],"type":"Point"}
}