{
  "type": "Feature",
  "properties": {
    "iso:country":"DE",
    "sg:address":"Fliederstr. 2",
    "sg:city":"L\u00f6ffingen",
    "sg:phone":"+49 7654/493",
    "sg:postcode":"79843",
    "sg:province":"Baden-W\u00fcrttemberg",
    "wof:name":"Hallenbad Dittishausen",
    "wof:placetype":"venue"
},
  "geometry": {"coordinates":[8.3644351959,47.902469635],"type":"Point"}
}