{
  "type": "Feature",
  "properties": {
    "iso:country":"DE",
    "sg:address":"Lilienthalstr. 23",
    "sg:city":"Leinfelden-Echterdingen",
    "sg:phone":"+49 711/792191",
    "sg:postcode":"70771",
    "sg:province":"Baden-W\u00fcrttemberg",
    "wof:name":"Marianne Mohrenweiser Krankengymnastin",
    "wof:placetype":"venue"
},
  "geometry": {"coordinates":[9.173683,48.69072],"type":"Point"}
}