{
  "type": "Feature",
  "properties": {
    "iso:country":"DE",
    "sg:address":"T\u00f6vener Str. 2",
    "sg:city":"Hamminkeln",
    "sg:phone":"+49 2857/2636",
    "sg:postcode":"46499",
    "sg:province":"Nordrhein-Westfalen",
    "wof:name":"Erich Gr\u00fcneboom",
    "wof:placetype":"venue"
},
  "geometry": {"coordinates":[6.516679,51.740059],"type":"Point"}
}