{
  "type": "Feature",
  "properties": {
    "iso:country":"DE",
    "sg:address":"Lindauer Str. 84",
    "sg:city":"Wei\u00dfensberg",
    "sg:phone":"+49 8389/1476",
    "sg:postcode":"88138",
    "sg:province":"Bayern",
    "wof:name":"Ski & Bergsport Josef Eggert Inh. Christiane Eggert",
    "wof:placetype":"venue"
},
  "geometry": {"coordinates":[9.7178001404,47.5816917419],"type":"Point"}
}