{
  "type": "Feature",
  "properties": {
    "iso:country":"DE",
    "sg:address":"Bachhauptener Weg 6",
    "sg:city":"Ostrach",
    "sg:phone":"+49 7585/422",
    "sg:postcode":"88356",
    "sg:province":"Baden-W\u00fcrttemberg",
    "wof:name":"Andreas Binder",
    "wof:placetype":"venue"
},
  "geometry": {"coordinates":[9.410627,47.97636],"type":"Point"}
}