{
  "type": "Feature",
  "properties": {
    "iso:country":"DE",
    "sg:address":"Am Weiher 6",
    "sg:city":"Kelsterbach",
    "sg:phone":"+49 6107/76200",
    "sg:postcode":"65451",
    "sg:province":"Hessen",
    "wof:name":"Universal Transport Gmbh",
    "wof:placetype":"venue"
},
  "geometry": {"coordinates":[8.5252523422,50.0533981323],"type":"Point"}
}