{
  "type": "Feature",
  "properties": {
    "iso:country":"DE",
    "sg:address":"Steinbacher Str. 68",
    "sg:city":"Baden-Baden",
    "sg:phone":"+49 7223/5410",
    "sg:postcode":"76534",
    "sg:province":"Baden-W\u00fcrttemberg",
    "wof:name":"Pension Hirsch",
    "wof:placetype":"venue"
},
  "geometry": {"coordinates":[8.1592750549,48.7282562256],"type":"Point"}
}