{
  "type": "Feature",
  "properties": {
    "iso:country":"DE",
    "sg:address":"Hirtenweg 11",
    "sg:city":"Emmendingen",
    "sg:phone":"+49 7641/52439",
    "sg:postcode":"79312",
    "sg:province":"Baden-W\u00fcrttemberg",
    "wof:name":"Ruth Freund-m\u00f6ssner Steuerberater",
    "wof:placetype":"venue"
},
  "geometry": {"coordinates":[7.8555679321,48.094959259],"type":"Point"}
}