{
  "type": "Feature",
  "properties": {
    "iso:country":"DE",
    "sg:address":"Scharfenberger Str. 67",
    "sg:city":"Dresden",
    "sg:postcode":"01139",
    "sg:province":"Sachsen",
    "wof:name":"Landesverband Gartenbau Sachsen E. V.",
    "wof:placetype":"venue"
},
  "geometry": {"coordinates":[13.6826524734,51.06980896],"type":"Point"}
}