{
  "type": "Feature",
  "properties": {
    "iso:country":"DE",
    "sg:address":"Untere Regenstr. 10",
    "sg:city":"Regensburg",
    "sg:phone":"+49 941/41887",
    "sg:postcode":"93059",
    "sg:province":"Bayern",
    "wof:name":"Josef Stadler Ohg",
    "wof:placetype":"venue"
},
  "geometry": {"coordinates":[12.1034440994,49.0288772583],"type":"Point"}
}