{
  "type": "Feature",
  "properties": {
    "iso:country":"DE",
    "sg:address":"In der Wormsheck 23a",
    "sg:city":"Viernheim",
    "sg:phone":"+49 6204/3275",
    "sg:postcode":"68519",
    "sg:province":"Hessen",
    "wof:name":"Meyer Heizungsbau Gmbh",
    "wof:placetype":"venue"
},
  "geometry": {"coordinates":[8.5665311813,49.542137146],"type":"Point"}
}