{
  "type": "Feature",
  "properties": {
    "iso:country":"DE",
    "sg:address":"Laubenweg 5 e",
    "sg:city":"Weiden",
    "sg:phone":"+49 961/27453",
    "sg:postcode":"92637",
    "sg:province":"Bayern",
    "wof:name":"J\u00fcrgen Und Claudia Meier",
    "wof:placetype":"venue"
},
  "geometry": {"coordinates":[12.1563549042,49.6740264893],"type":"Point"}
}