{
  "type": "Feature",
  "properties": {
    "iso:country":"DE",
    "sg:address":"Haid\u00f6sch 6",
    "sg:city":"Wangen",
    "sg:phone":"+49 7522/93070",
    "sg:postcode":"88239",
    "sg:province":"Baden-W\u00fcrttemberg",
    "wof:name":"Toom-baumarkt",
    "wof:placetype":"venue"
},
  "geometry": {"coordinates":[9.826171875,47.6935653687],"type":"Point"}
}