{
  "type": "Feature",
  "properties": {
    "iso:country":"DE",
    "sg:address":"Rapunzelweg 22",
    "sg:city":"Bad Krozingen",
    "sg:phone":"+49 7633/101567",
    "sg:postcode":"79189",
    "sg:province":"Baden-W\u00fcrttemberg",
    "wof:name":"Seidl-datenbank Service Gmbh",
    "wof:placetype":"venue"
},
  "geometry": {"coordinates":[7.706366,47.920605],"type":"Point"}
}