{
  "type": "Feature",
  "properties": {
    "iso:country":"DE",
    "sg:address":"Am Bahnhof 7",
    "sg:city":"Aidenbach",
    "sg:phone":"+49 8543/3652",
    "sg:postcode":"94501",
    "sg:province":"Bayern",
    "wof:name":"Rudolf Rettenberger",
    "wof:placetype":"venue"
},
  "geometry": {"coordinates":[13.080835,48.57048],"type":"Point"}
}