{
  "type": "Feature",
  "properties": {
    "iso:country":"DE",
    "sg:address":"Otto-Hahn-Str. 15",
    "sg:city":"Ingelheim",
    "sg:phone":"+49 6132/982320",
    "sg:postcode":"55218",
    "sg:province":"Rheinland-Pfalz",
    "wof:name":"Betonwerk Carl Pl\u00f6tner Gmbh & Co. Kg",
    "wof:placetype":"venue"
},
  "geometry": {"coordinates":[8.0355577469,49.9883651733],"type":"Point"}
}