{
  "type": "Feature",
  "properties": {
    "iso:country":"DE",
    "sg:address":"Rathausplatz",
    "sg:city":"Passau",
    "sg:postcode":"94032",
    "sg:province":"Bayern",
    "wof:name":"G\u00fcnter K\u00f6ck Beteiligungs Gmbh",
    "wof:placetype":"venue"
},
  "geometry": {"coordinates":[13.4686,48.575279],"type":"Point"}
}