{
  "type": "Feature",
  "properties": {
    "iso:country":"DE",
    "sg:address":"Eckernkampstr. 12",
    "sg:city":"Cremlingen",
    "sg:phone":"+49 5306/1602",
    "sg:postcode":"38162",
    "sg:province":"Niedersachsen",
    "wof:name":"Otto Und Ursula Daschke",
    "wof:placetype":"venue"
},
  "geometry": {"coordinates":[10.690988,52.272793],"type":"Point"}
}