{
  "type": "Feature",
  "properties": {
    "iso:country":"DE",
    "sg:address":"Hauptstr. 27",
    "sg:city":"Bad Orb",
    "sg:phone":"+49 6052/2264",
    "sg:postcode":"63619",
    "sg:province":"Hessen",
    "wof:name":"Dr. Ralf Geidel Rechtsanwalt Und Notar",
    "wof:placetype":"venue"
},
  "geometry": {"coordinates":[9.3481693268,50.226436615],"type":"Point"}
}