{
  "type": "Feature",
  "properties": {
    "iso:country":"DE",
    "sg:address":"Rundstr. 8",
    "sg:city":"Ederm\u00fcnde",
    "sg:phone":"+49 5603/3277",
    "sg:postcode":"34295",
    "sg:province":"Hessen",
    "wof:name":"Altenwohnheim",
    "wof:placetype":"venue"
},
  "geometry": {"coordinates":[9.382451,51.225418],"type":"Point"}
}