{
  "type": "Feature",
  "properties": {
    "iso:country":"DE",
    "sg:address":"Hardenbergstr. 22",
    "sg:city":"Kiel",
    "sg:postcode":"24105",
    "sg:province":"Schleswig-Holstein",
    "wof:name":"Highlights-multimedia",
    "wof:placetype":"venue"
},
  "geometry": {"coordinates":[10.133829,54.342625],"type":"Point"}
}