{
  "type": "Feature",
  "properties": {
    "iso:country":"DE",
    "sg:address":"Urbanusstr. 35",
    "sg:city":"Klingenberg",
    "sg:phone":"+49 9372/1892",
    "sg:postcode":"63911",
    "sg:province":"Bayern",
    "wof:name":"H. Benz",
    "wof:placetype":"venue"
},
  "geometry": {"coordinates":[9.189542,49.76936],"type":"Point"}
}