{
  "type": "Feature",
  "properties": {
    "iso:country":"DE",
    "sg:address":"Neuer Wall 69",
    "sg:city":"Hamburg",
    "sg:phone":"+49 40/377080",
    "sg:postcode":"20354",
    "sg:province":"Hamburg",
    "wof:name":"Bhw Bausparkassen",
    "wof:placetype":"venue"
},
  "geometry": {"coordinates":[9.98743,53.550156],"type":"Point"}
}