{
  "type": "Feature",
  "properties": {
    "iso:country":"DE",
    "sg:address":"Elbestr. 66",
    "sg:city":"Schortens",
    "sg:phone":"+49 4461/82345",
    "sg:postcode":"26419",
    "sg:province":"Niedersachsen",
    "wof:name":"Detlef Sch\u00f6n Immobilienmakler",
    "wof:placetype":"venue"
},
  "geometry": {"coordinates":[7.9530620575,53.5352554321],"type":"Point"}
}