{
  "type": "Feature",
  "properties": {
    "iso:country":"DE",
    "sg:address":"Naunheimer Str. 14",
    "sg:city":"Lahnau",
    "sg:phone":"+49 6441/62332",
    "sg:postcode":"35633",
    "sg:province":"Hessen",
    "wof:name":"G. Gissel",
    "wof:placetype":"venue"
},
  "geometry": {"coordinates":[8.549049,50.585461],"type":"Point"}
}