{
  "type": "Feature",
  "properties": {
    "iso:country":"DE",
    "sg:address":"Georg-Warring-Str. 15",
    "sg:city":"Emden",
    "sg:phone":"+49 4921/40484",
    "sg:postcode":"26721",
    "sg:province":"Niedersachsen",
    "wof:name":"G. Wolf",
    "wof:placetype":"venue"
},
  "geometry": {"coordinates":[7.22541,53.37949],"type":"Point"}
}