{
  "type": "Feature",
  "properties": {
    "iso:country":"DE",
    "sg:address":"Rheinstr. 17",
    "sg:city":"Stutensee",
    "sg:phone":"+49 7249/3490",
    "sg:postcode":"76297",
    "sg:province":"Baden-W\u00fcrttemberg",
    "wof:name":"Tapetenhaus Maurer Gro\u00df-und Einzelhandel Gmbh",
    "wof:placetype":"venue"
},
  "geometry": {"coordinates":[8.478723526,49.1075592041],"type":"Point"}
}