{
  "type": "Feature",
  "properties": {
    "iso:country":"DE",
    "sg:address":"H\u00f6henweg 27",
    "sg:city":"Bingen",
    "sg:phone":"+49 7571/681449",
    "sg:postcode":"72511",
    "sg:province":"Baden-W\u00fcrttemberg",
    "wof:name":"Joachim Stephan",
    "wof:placetype":"venue"
},
  "geometry": {"coordinates":[9.266544,48.114197],"type":"Point"}
}