{
  "type": "Feature",
  "properties": {
    "iso:country":"DE",
    "sg:address":"Holunderstr. 38",
    "sg:city":"Wedel",
    "sg:postcode":"22880",
    "sg:province":"Schleswig-Holstein",
    "wof:name":"Hans Schrattenholzer",
    "wof:placetype":"venue"
},
  "geometry": {"coordinates":[9.6959590912,53.5906562805],"type":"Point"}
}