{
  "type": "Feature",
  "properties": {
    "iso:country":"DE",
    "sg:address":"Reichsbahnstr. 76",
    "sg:city":"Hamburg",
    "sg:phone":"+49 40/5473530",
    "sg:postcode":"22525",
    "sg:province":"Hamburg",
    "wof:name":"Recovis Geselschaft F\u00fcr Digitale Kartierung Und",
    "wof:placetype":"venue"
},
  "geometry": {"coordinates":[9.9060850143,53.5977020264],"type":"Point"}
}