{
  "type": "Feature",
  "properties": {
    "iso:country":"DE",
    "sg:address":"Glasbronnenstr. 12",
    "sg:city":"Wurmberg",
    "sg:phone":"+49 7044/94580",
    "sg:postcode":"75449",
    "sg:province":"Baden-W\u00fcrttemberg",
    "wof:name":"Detectron Gmbh & Co.",
    "wof:placetype":"venue"
},
  "geometry": {"coordinates":[8.793278,48.881729],"type":"Point"}
}