{
  "type": "Feature",
  "properties": {
    "iso:country":"DE",
    "sg:address":"Herzog-Georg-Str. 90",
    "sg:city":"Lauingen",
    "sg:phone":"+49 9072/4567",
    "sg:postcode":"89415",
    "sg:province":"Bayern",
    "wof:name":"Helmut Kunz",
    "wof:placetype":"venue"
},
  "geometry": {"coordinates":[10.431482,48.572411],"type":"Point"}
}