{
  "type": "Feature",
  "properties": {
    "iso:country":"DE",
    "sg:address":"Z\u00f6rbiger Str. 18",
    "sg:city":"Stumsdorf",
    "sg:phone":"+49 34956/21241",
    "sg:postcode":"06780",
    "sg:province":"Sachsen-Anhalt",
    "wof:name":"H. Barthel Und J. Bharthel Gbr",
    "wof:placetype":"venue"
},
  "geometry": {"coordinates":[12.0648679733,51.6173400879],"type":"Point"}
}