{
  "type": "Feature",
  "properties": {
    "iso:country":"DE",
    "sg:address":"Rh\u00f6nbergstr. 17",
    "sg:city":"Petersberg",
    "sg:phone":"+49 661/65004",
    "sg:postcode":"36100",
    "sg:province":"Hessen",
    "wof:name":"Karl Aschenbr\u00fccker Mineral\u00f6lhandel",
    "wof:placetype":"venue"
},
  "geometry": {"coordinates":[9.7157468796,50.5594367981],"type":"Point"}
}