{
  "type": "Feature",
  "properties": {
    "iso:country":"DE",
    "sg:address":"Obere Dorfstr. 16",
    "sg:city":"G\u00fcnzburg",
    "sg:phone":"+49 8221/24457",
    "sg:postcode":"89312",
    "sg:province":"Bayern",
    "wof:name":"Body Cult Stefan Go\u00dfner E. K.",
    "wof:placetype":"venue"
},
  "geometry": {"coordinates":[10.292318,48.437237],"type":"Point"}
}