{
  "type": "Feature",
  "properties": {
    "iso:country":"DE",
    "sg:address":"An der Strangriede 52",
    "sg:city":"Hannover",
    "sg:phone":"+49 511/709428",
    "sg:postcode":"30167",
    "sg:province":"Niedersachsen",
    "wof:name":"H. Konerding Gmbh & Co. Kg",
    "wof:placetype":"venue"
},
  "geometry": {"coordinates":[9.718468,52.390671],"type":"Point"}
}