{
  "type": "Feature",
  "properties": {
    "iso:country":"DE",
    "sg:address":"In Den Haing\u00e4rten 1",
    "sg:city":"Allendorf",
    "sg:phone":"+49 4964/0791030",
    "sg:postcode":"35469",
    "sg:province":"Hessen",
    "wof:name":"Sch\u00d6nwandt Gmbh",
    "wof:placetype":"venue"
},
  "geometry": {"coordinates":[8.845452,50.691353],"type":"Point"}
}