{
  "type": "Feature",
  "properties": {
    "iso:country":"DE",
    "sg:address":"Windscheidstra\u00dfe 14",
    "sg:city":"Berlin",
    "sg:phone":"+49 30/3232731",
    "sg:postcode":"10627",
    "sg:province":"Berlin",
    "wof:name":"Siemensmeyer Consulting",
    "wof:placetype":"venue"
},
  "geometry": {"coordinates":[13.299074173,52.5064201355],"type":"Point"}
}