{
  "type": "Feature",
  "properties": {
    "iso:country":"DE",
    "sg:address":"Krefelder Str. 180",
    "sg:city":"Viersen",
    "sg:phone":"+49 2162/30003",
    "sg:postcode":"41748",
    "sg:province":"Nordrhein-Westfalen",
    "wof:name":"Stahlbau Josef Schmitz Gmbh",
    "wof:placetype":"venue"
},
  "geometry": {"coordinates":[6.408242,51.259842],"type":"Point"}
}