{
  "type": "Feature",
  "properties": {
    "iso:country":"DE",
    "sg:address":"Finkenweg 6",
    "sg:city":"Aschau",
    "sg:phone":"+49 8052/909626",
    "sg:postcode":"83229",
    "sg:province":"Bayern",
    "wof:name":"M\u00e4rlie Verlag Und Spiele Gmbh & Co. Kg",
    "wof:placetype":"venue"
},
  "geometry": {"coordinates":[12.2604093552,47.6834716797],"type":"Point"}
}