{
  "type": "Feature",
  "properties": {
    "iso:country":"DE",
    "sg:address":"Peter-Anton-Str. 6",
    "sg:city":"Obertshausen",
    "sg:phone":"+49 6104/71817",
    "sg:postcode":"63179",
    "sg:province":"Hessen",
    "wof:name":"Frankenstuben",
    "wof:placetype":"venue"
},
  "geometry": {"coordinates":[8.8603124619,50.0770988464],"type":"Point"}
}