{
  "type": "Feature",
  "properties": {
    "iso:country":"DE",
    "sg:address":"Ketzberg 44",
    "sg:city":"Wermelskirchen",
    "sg:phone":"+49 2193/3370",
    "sg:postcode":"42929",
    "sg:province":"Nordrhein-Westfalen",
    "wof:name":"Alt Ketzberg",
    "wof:placetype":"venue"
},
  "geometry": {"coordinates":[7.2005848885,51.0858955383],"type":"Point"}
}