{
  "type": "Feature",
  "properties": {
    "iso:country":"DE",
    "sg:address":"Eichenb\u00fchler Str. 77",
    "sg:city":"B\u00fcrgstadt",
    "sg:phone":"+49 9371/2431",
    "sg:postcode":"63927",
    "sg:province":"Bayern",
    "wof:name":"Frischdienst Bruno M\u00fcnch Gmbh",
    "wof:placetype":"venue"
},
  "geometry": {"coordinates":[9.2753858566,49.7055053711],"type":"Point"}
}