{
  "type": "Feature",
  "properties": {
    "iso:country":"DE",
    "sg:address":"Gottlieb-Wolfer-Str. 10",
    "sg:city":"Denkendorf",
    "sg:phone":"+49 711/9348030",
    "sg:postcode":"73770",
    "sg:province":"Baden-W\u00fcrttemberg",
    "wof:name":"J\u00dcrgen Rienth",
    "wof:placetype":"venue"
},
  "geometry": {"coordinates":[9.331328,48.695122],"type":"Point"}
}