{
  "type": "Feature",
  "properties": {
    "iso:country":"DE",
    "sg:address":"Neusser Str. 5",
    "sg:city":"Meerbusch",
    "sg:phone":"+49 2132/72561",
    "sg:postcode":"40667",
    "sg:province":"Nordrhein-Westfalen",
    "wof:name":"Hans Peter",
    "wof:placetype":"venue"
},
  "geometry": {"coordinates":[6.6973819733,51.2440032959],"type":"Point"}
}