{
  "type": "Feature",
  "properties": {
    "iso:country":"DE",
    "sg:address":"M\u00fcnchner Str. 13 A",
    "sg:city":"Moosinning",
    "sg:postcode":"85452",
    "sg:province":"Bayern",
    "wof:name":"Eao Lumitas Gmbh",
    "wof:placetype":"venue"
},
  "geometry": {"coordinates":[11.7748479843,48.2759666443],"type":"Point"}
}