{
  "type": "Feature",
  "properties": {
    "iso:country":"DE",
    "sg:address":"Bremer Str. 54",
    "sg:city":"F\u00fcrth",
    "sg:phone":"+49 911/785051",
    "sg:postcode":"90765",
    "sg:province":"Bayern",
    "wof:name":"Secondhanddeco - Gebrauchte Deko-artikel Aller Art",
    "wof:placetype":"venue"
},
  "geometry": {"coordinates":[10.990259,49.493572],"type":"Point"}
}