{
  "type": "Feature",
  "properties": {
    "iso:country":"DE",
    "sg:address":"Denkmalstr. 3",
    "sg:city":"Hornbach",
    "sg:phone":"+49 6338/1866",
    "sg:postcode":"66500",
    "sg:province":"Rheinland-Pfalz",
    "wof:name":"Harry Fickert",
    "wof:placetype":"venue"
},
  "geometry": {"coordinates":[7.3728427887,49.1906051636],"type":"Point"}
}