{
  "type": "Feature",
  "properties": {
    "iso:country":"DE",
    "sg:address":"Ulmer Str. 8",
    "sg:city":"Ravensburg",
    "sg:phone":"+49 751/366190",
    "sg:postcode":"88212",
    "sg:province":"Baden-W\u00fcrttemberg",
    "wof:name":"Hev Halbleiter Electronik Vertriebs Gmbh",
    "wof:placetype":"venue"
},
  "geometry": {"coordinates":[9.6105079651,47.787109375],"type":"Point"}
}