{
  "type": "Feature",
  "properties": {
    "iso:country":"DE",
    "sg:address":"Sch\u00fctzenstr. 12-14",
    "sg:city":"Billigheim",
    "sg:phone":"+49 6265/7058",
    "sg:postcode":"74842",
    "sg:province":"Baden-W\u00fcrttemberg",
    "wof:name":"Alfred M\u00fcller Gmbh & Co. Kg",
    "wof:placetype":"venue"
},
  "geometry": {"coordinates":[9.2471761703,49.3267974854],"type":"Point"}
}