{
  "type": "Feature",
  "properties": {
    "iso:country":"DE",
    "sg:address":"Prinzregentenstr. 23",
    "sg:city":"Ludwigshafen",
    "sg:phone":"+49 621/517770",
    "sg:postcode":"67063",
    "sg:province":"Rheinland-Pfalz",
    "wof:name":"Pro-pflege Pflegedienst Gmbh",
    "wof:placetype":"venue"
},
  "geometry": {"coordinates":[8.4397287369,49.4879341125],"type":"Point"}
}