{
  "type": "Feature",
  "properties": {
    "iso:country":"DE",
    "sg:address":"Burgharting",
    "sg:city":"Kirchberg",
    "sg:phone":"+49 8706/403",
    "sg:postcode":"84434",
    "sg:province":"Bayern",
    "wof:name":"Johann Schleibinger",
    "wof:placetype":"venue"
},
  "geometry": {"coordinates":[12.092347,48.422592],"type":"Point"}
}