{
  "type": "Feature",
  "properties": {
    "iso:country":"DE",
    "sg:address":"Beim kleinen Tagwerk 9",
    "sg:city":"Bremen",
    "sg:phone":"+49 421/488722",
    "sg:postcode":"28355",
    "sg:province":"Bremen",
    "wof:name":"Present Vertriebs Gmbh",
    "wof:placetype":"venue"
},
  "geometry": {"coordinates":[8.9080524445,53.0962295532],"type":"Point"}
}