{
  "type": "Feature",
  "properties": {
    "iso:country":"DE",
    "sg:address":"Unternaglbach 19",
    "sg:city":"Kirchberg i. Wald",
    "sg:phone":"+49 9927/223",
    "sg:postcode":"94259",
    "sg:province":"Bayern",
    "wof:name":"F. Radlinger",
    "wof:placetype":"venue"
},
  "geometry": {"coordinates":[13.1902751923,48.9186439514],"type":"Point"}
}