{
  "type": "Feature",
  "properties": {
    "iso:country":"DE",
    "sg:address":"Fr\u00fchlingstr. 25",
    "sg:city":"Miesbach",
    "sg:phone":"+49 8025/4634",
    "sg:postcode":"83714",
    "sg:province":"Bayern",
    "wof:name":"Leonh. Wank",
    "wof:placetype":"venue"
},
  "geometry": {"coordinates":[11.8312397003,47.7897987366],"type":"Point"}
}