{
  "type": "Feature",
  "properties": {
    "iso:country":"DE",
    "sg:address":"Pettenkoferstr. 17 a",
    "sg:city":"Berlin",
    "sg:postcode":"10247",
    "sg:province":"Berlin",
    "wof:name":"Kirschbl\u00fcten Verm\u00f6gens- Verwaltung- Und",
    "wof:placetype":"venue"
},
  "geometry": {"coordinates":[13.471307,52.518204],"type":"Point"}
}