{
  "type": "Feature",
  "properties": {
    "iso:country":"DE",
    "sg:address":"Sch\u00e4fflerstr. 1",
    "sg:city":"Jettingen-Scheppach",
    "sg:phone":"+49 8225/3185",
    "sg:postcode":"89343",
    "sg:province":"Bayern",
    "wof:name":"Pizzeria Sch\u00e4fflerstube",
    "wof:placetype":"venue"
},
  "geometry": {"coordinates":[10.4347391129,48.3868560791],"type":"Point"}
}