{
  "type": "Feature",
  "properties": {
    "iso:country":"DE",
    "sg:address":"Haid-und-Neu-Str. 7",
    "sg:city":"Karlsruhe",
    "sg:postcode":"76131",
    "sg:province":"Baden-W\u00fcrttemberg",
    "wof:name":"Cab Produkttechnik F\u00fcr Bauelemente Fertigungsmittel",
    "wof:placetype":"venue"
},
  "geometry": {"coordinates":[8.425708,49.012421],"type":"Point"}
}