{
  "type": "Feature",
  "properties": {
    "iso:country":"DE",
    "sg:address":"Erdinger Str. 35",
    "sg:city":"Moosinning",
    "sg:phone":"+49 8123/990058",
    "sg:postcode":"85452",
    "sg:province":"Bayern",
    "wof:name":"Emil Mayr",
    "wof:placetype":"venue"
},
  "geometry": {"coordinates":[11.8449163437,48.2771186829],"type":"Point"}
}