{
  "type": "Feature",
  "properties": {
    "iso:country":"DE",
    "sg:address":"Wintersteinstr.",
    "sg:city":"Ober-M\u00f6rlen",
    "sg:phone":"+49 6002/303",
    "sg:postcode":"61239",
    "sg:province":"Hessen",
    "wof:name":"Forsthaus Winterstein",
    "wof:placetype":"venue"
},
  "geometry": {"coordinates":[8.701292038,50.3577308655],"type":"Point"}
}