{
  "type": "Feature",
  "properties": {
    "iso:country":"DE",
    "sg:address":"Frankenstr.",
    "sg:city":"Hamburg",
    "sg:postcode":"20097",
    "sg:province":"Hamburg",
    "wof:name":"Frankenhof Vierte Beteiligungs Gmbh",
    "wof:placetype":"venue"
},
  "geometry": {"coordinates":[10.022935,53.547997],"type":"Point"}
}