{
  "type": "Feature",
  "properties": {
    "iso:country":"DE",
    "sg:address":"Rudolf-Diesel-Str. 5 a",
    "sg:city":"Dachau",
    "sg:phone":"+49 8131/321492",
    "sg:postcode":"85221",
    "sg:province":"Bayern",
    "wof:name":"Em Equipment Market Gmbh",
    "wof:placetype":"venue"
},
  "geometry": {"coordinates":[11.474409,48.264072],"type":"Point"}
}