{
  "type": "Feature",
  "properties": {
    "iso:country":"DE",
    "sg:address":"Kolpingstr. 8",
    "sg:city":"Havixbeck",
    "sg:phone":"+49 2507/1454",
    "sg:postcode":"48329",
    "sg:province":"Nordrhein-Westfalen",
    "wof:name":"Engelbert M\u00fcthing",
    "wof:placetype":"venue"
},
  "geometry": {"coordinates":[7.419727,51.97525],"type":"Point"}
}