{
  "type": "Feature",
  "properties": {
    "iso:country":"DE",
    "sg:address":"Huenersdorfstrasse 13",
    "sg:city":"Gotha",
    "sg:phone":"+49 3621/737905",
    "sg:postcode":"99867",
    "sg:province":"Th\u00fcringen",
    "wof:name":"Anwaltskanzlei Kellner",
    "wof:placetype":"venue"
},
  "geometry": {"coordinates":[10.703546,50.94936],"type":"Point"}
}