{
  "type": "Feature",
  "properties": {
    "iso:country":"DE",
    "sg:address":"Von-Katzbeck-Str. 53",
    "sg:city":"Wei\u00dfenhorn",
    "sg:phone":"+49 7309/3407",
    "sg:postcode":"89264",
    "sg:province":"Bayern",
    "wof:name":"Kath. Pfarramt St. Alban",
    "wof:placetype":"venue"
},
  "geometry": {"coordinates":[10.2087125778,48.331615448],"type":"Point"}
}