{
  "type": "Feature",
  "properties": {
    "iso:country":"DE",
    "sg:address":"Holzhofallee 17a",
    "sg:city":"Darmstadt",
    "sg:phone":"+49 6151/33010",
    "sg:postcode":"64295",
    "sg:province":"Hessen",
    "wof:name":"Kirchliche Zusatzversorgungs- Kasse Darmstadt",
    "wof:placetype":"venue"
},
  "geometry": {"coordinates":[8.6419229507,49.8651123047],"type":"Point"}
}