{
  "type": "Feature",
  "properties": {
    "iso:country":"DE",
    "sg:address":"Hiltroper Str. 254",
    "sg:city":"Bochum",
    "sg:phone":"+49 4923/4590816",
    "sg:postcode":"44805",
    "sg:province":"Nordrhein-Westfalen",
    "wof:name":"Hans Dieter Winkels & Co Gmbh",
    "wof:placetype":"venue"
},
  "geometry": {"coordinates":[7.244108,51.506268],"type":"Point"}
}