{
  "type": "Feature",
  "properties": {
    "iso:country":"DE",
    "sg:address":"Lindenstr. 8",
    "sg:city":"Bad Soden-Salm\u00fcnster",
    "sg:phone":"+49 6056/2891",
    "sg:postcode":"63628",
    "sg:province":"Hessen",
    "wof:name":"Ernst Seiler",
    "wof:placetype":"venue"
},
  "geometry": {"coordinates":[9.3912887573,50.3293151855],"type":"Point"}
}