{
  "type": "Feature",
  "properties": {
    "iso:country":"DE",
    "sg:address":"Hasenkampsweg 9",
    "sg:city":"Melle",
    "sg:phone":"+49 4954/2242522",
    "sg:postcode":"49328",
    "sg:province":"Niedersachsen",
    "wof:name":"Ratiomatic Verbindungstechnik Walter Fischer Gmbh",
    "wof:placetype":"venue"
},
  "geometry": {"coordinates":[8.39452,52.190269],"type":"Point"}
}