{
  "type": "Feature",
  "properties": {
    "iso:country":"DE",
    "sg:address":"\u00dcber dem Dorfe 15",
    "sg:city":"Adelebsen",
    "sg:phone":"+49 5506/1011",
    "sg:postcode":"37139",
    "sg:province":"Niedersachsen",
    "wof:name":"Hans Bindseil Architekt",
    "wof:placetype":"venue"
},
  "geometry": {"coordinates":[9.77852,51.54884],"type":"Point"}
}