{
  "type": "Feature",
  "properties": {
    "iso:country":"DE",
    "sg:address":"Robert-Bosch-Str 1",
    "sg:city":"Herne",
    "sg:phone":"+49 2323/99220",
    "sg:postcode":"44629",
    "sg:province":"Nordrhein-Westfalen",
    "wof:name":"Isap Ag",
    "wof:placetype":"venue"
},
  "geometry": {"coordinates":[7.206854,51.555279],"type":"Point"}
}