{
  "type": "Feature",
  "properties": {
    "iso:country":"DE",
    "sg:address":"Igelweg 2",
    "sg:city":"Hanau",
    "sg:phone":"+49 6181/572211",
    "sg:postcode":"63457",
    "sg:province":"Hessen",
    "wof:name":"Plural Gmbh",
    "wof:placetype":"venue"
},
  "geometry": {"coordinates":[8.9623622894,50.1049690247],"type":"Point"}
}