{
  "type": "Feature",
  "properties": {
    "iso:country":"DE",
    "sg:address":"Brauhofstr. 13",
    "sg:city":"Moritzburg",
    "sg:phone":"+49 35207/82091",
    "sg:postcode":"01468",
    "sg:province":"Sachsen",
    "wof:name":"Matthias Hanschmann",
    "wof:placetype":"venue"
},
  "geometry": {"coordinates":[13.675312,51.155273],"type":"Point"}
}