{
  "type": "Feature",
  "properties": {
    "iso:country":"DE",
    "sg:address":"Dresdner Str. 85",
    "sg:city":"Mei\u00dfen",
    "sg:phone":"+49 3521/730617",
    "sg:postcode":"01662",
    "sg:province":"Sachsen",
    "wof:name":"Karen Schmidtgen Heilpraktikerin",
    "wof:placetype":"venue"
},
  "geometry": {"coordinates":[13.4933099747,51.1497612],"type":"Point"}
}