{
  "type": "Feature",
  "properties": {
    "iso:country":"DE",
    "sg:address":"Regener Str. 5",
    "sg:city":"Rinchnach",
    "sg:phone":"+49 9921/8484",
    "sg:postcode":"94269",
    "sg:province":"Bayern",
    "wof:name":"Wolfgang Weber",
    "wof:placetype":"venue"
},
  "geometry": {"coordinates":[13.1972551346,48.9509010315],"type":"Point"}
}