{
  "type": "Feature",
  "properties": {
    "iso:country":"DE",
    "sg:address":"Gerolfinger Str. 100",
    "sg:city":"Ingolstadt",
    "sg:phone":"+49 841/81806",
    "sg:postcode":"85049",
    "sg:province":"Bayern",
    "wof:name":"Stern Verwaltungs Gmbh",
    "wof:placetype":"venue"
},
  "geometry": {"coordinates":[11.390063,48.763069],"type":"Point"}
}