{
  "type": "Feature",
  "properties": {
    "iso:country":"DE",
    "sg:address":"Kirchberg 5",
    "sg:city":"Gattendorf",
    "sg:phone":"+49 9281/40361",
    "sg:postcode":"95185",
    "sg:province":"Bayern",
    "wof:name":"Ev. Pfarramt Gem. Gattendorf",
    "wof:placetype":"venue"
},
  "geometry": {"coordinates":[12.0112009048,50.3240394592],"type":"Point"}
}