{
  "type": "Feature",
  "properties": {
    "iso:country":"DE",
    "sg:address":"Nymphenburger Str. 124",
    "sg:city":"M\u00fcnchen",
    "sg:phone":"+49 89/236870",
    "sg:postcode":"80636",
    "sg:province":"Bayern",
    "wof:name":"Rbm Consulting Gmbh",
    "wof:placetype":"venue"
},
  "geometry": {"coordinates":[11.5398111343,48.1513366699],"type":"Point"}
}