{
  "type": "Feature",
  "properties": {
    "iso:country":"DE",
    "sg:address":"Schlei\u00dfheimerstrasse",
    "sg:city":"Dachau",
    "sg:phone":"+49 8131/339799",
    "sg:postcode":"85221",
    "sg:province":"Bayern",
    "wof:name":"Creative21-new Media Solutions",
    "wof:placetype":"venue"
},
  "geometry": {"coordinates":[11.440245,48.257835],"type":"Point"}
}