{
  "type": "Feature",
  "properties": {
    "iso:country":"DE",
    "sg:address":"Vom-Stein-Str. 13",
    "sg:city":"Niestetal",
    "sg:phone":"+49 561/525428",
    "sg:postcode":"34266",
    "sg:province":"Hessen",
    "wof:name":"Uwe Naujeck Architekt",
    "wof:placetype":"venue"
},
  "geometry": {"coordinates":[9.557874,51.319855],"type":"Point"}
}