{
  "type": "Feature",
  "properties": {
    "iso:country":"DE",
    "sg:address":"Wagnerstr. 27",
    "sg:city":"Donzdorf",
    "sg:phone":"+49 7162/929640",
    "sg:postcode":"73072",
    "sg:province":"Baden-W\u00fcrttemberg",
    "wof:name":"Wolfgang Schmid Gmbh",
    "wof:placetype":"venue"
},
  "geometry": {"coordinates":[9.802027,48.683655],"type":"Point"}
}