{
  "type": "Feature",
  "properties": {
    "iso:country":"DE",
    "sg:address":"Barnerstr. 30",
    "sg:city":"Hamburg",
    "sg:phone":"+49 40/3908637",
    "sg:postcode":"22765",
    "sg:province":"Hamburg",
    "wof:name":"Matthias Kl\u00fcnder Heilpraktiker",
    "wof:placetype":"venue"
},
  "geometry": {"coordinates":[9.9295444489,53.5566215515],"type":"Point"}
}