{
  "type": "Feature",
  "properties": {
    "iso:country":"DE",
    "sg:address":"Brookdeich 8",
    "sg:city":"Hamburg",
    "sg:phone":"+49 40/7256546",
    "sg:postcode":"21029",
    "sg:province":"Hamburg",
    "wof:name":"Gebr. Glunz Gmbh & Co. Kg",
    "wof:placetype":"venue"
},
  "geometry": {"coordinates":[10.2407,53.47723],"type":"Point"}
}