{
  "type": "Feature",
  "properties": {
    "iso:country":"DE",
    "sg:address":"Zur Schiffsm\u00fchle 1",
    "sg:city":"Grimma OT H\u00f6fgen",
    "sg:phone":"+49 3437/76020",
    "sg:postcode":"04668",
    "sg:province":"Sachsen",
    "wof:name":"Zur Schiffsm\u00fchle Gmbh Hotel Und Restaurant",
    "wof:placetype":"venue"
},
  "geometry": {"coordinates":[12.7534914017,51.2135848999],"type":"Point"}
}