{
  "type": "Feature",
  "properties": {
    "iso:country":"DE",
    "sg:address":"Westend 17",
    "sg:city":"Titz",
    "sg:phone":"+49 2463/8112",
    "sg:postcode":"52445",
    "sg:province":"Nordrhein-Westfalen",
    "wof:name":"Wilhelm D\u00fcren",
    "wof:placetype":"venue"
},
  "geometry": {"coordinates":[6.387085,50.988937],"type":"Point"}
}