{
  "type": "Feature",
  "properties": {
    "iso:country":"DE",
    "sg:address":"Cunnersdorfer Str. 25",
    "sg:city":"Dresden",
    "sg:phone":"+49 351/430430",
    "sg:postcode":"01189",
    "sg:province":"Sachsen",
    "wof:name":"Nsr-sch\u00fcttgut Speditions- Gesellschaft Mbh",
    "wof:placetype":"venue"
},
  "geometry": {"coordinates":[13.7070159912,51.0160446167],"type":"Point"}
}