{
  "type": "Feature",
  "properties": {
    "iso:country":"DE",
    "sg:address":"Bechergasse 9",
    "sg:city":"K\u00f6ln",
    "sg:phone":"+49 221/2580738",
    "sg:postcode":"50667",
    "sg:province":"Nordrhein-Westfalen",
    "wof:name":"S. Mister",
    "wof:placetype":"venue"
},
  "geometry": {"coordinates":[6.9599599838,50.93983078],"type":"Point"}
}