{
  "type": "Feature",
  "properties": {
    "iso:country":"DE",
    "sg:address":"Im Boden 10",
    "sg:city":"V\u00f6hl",
    "sg:phone":"+49 5635/8020",
    "sg:postcode":"34516",
    "sg:province":"Hessen",
    "wof:name":"D. Wesche",
    "wof:placetype":"venue"
},
  "geometry": {"coordinates":[8.906542,51.207027],"type":"Point"}
}