{
  "type": "Feature",
  "properties": {
    "iso:country":"DE",
    "sg:address":"Rheinstr. 32",
    "sg:city":"Linz",
    "sg:phone":"+49 2644/2202",
    "sg:postcode":"53545",
    "sg:province":"Rheinland-Pfalz",
    "wof:name":"G. Schoop-k\u00f6kce & N. K\u00f6kce",
    "wof:placetype":"venue"
},
  "geometry": {"coordinates":[7.28038,50.565929],"type":"Point"}
}