{
  "type": "Feature",
  "properties": {
    "iso:country":"DE",
    "sg:address":"Schmiedebrink 13",
    "sg:city":"Bockenem",
    "sg:phone":"+49 5067/3382",
    "sg:postcode":"31167",
    "sg:province":"Niedersachsen",
    "wof:name":"Gerhard Uhde",
    "wof:placetype":"venue"
},
  "geometry": {"coordinates":[10.082916,52.036526],"type":"Point"}
}