{
  "type": "Feature",
  "properties": {
    "iso:country":"DE",
    "sg:address":"Hochstadenstr. 144",
    "sg:city":"M\u00f6nchengladbach",
    "sg:phone":"+49 2161/558463",
    "sg:postcode":"41189",
    "sg:province":"Nordrhein-Westfalen",
    "wof:name":"Irma-fashion Inh. Margit Moos",
    "wof:placetype":"venue"
},
  "geometry": {"coordinates":[6.41531,51.130348],"type":"Point"}
}