{
  "type": "Feature",
  "properties": {
    "iso:country":"DE",
    "sg:address":"Straubinger Str. 16",
    "sg:city":"Leiblfing",
    "sg:phone":"+49 9427/902140",
    "sg:postcode":"94339",
    "sg:province":"Bayern",
    "wof:name":"St. Florian-apotheke",
    "wof:placetype":"venue"
},
  "geometry": {"coordinates":[12.515024,48.773705],"type":"Point"}
}