{
  "type": "Feature",
  "properties": {
    "iso:country":"DE",
    "sg:address":"Friedrich-Engels-Allee 376",
    "sg:city":"Wuppertal",
    "sg:phone":"+49 202/555963",
    "sg:postcode":"42283",
    "sg:province":"Nordrhein-Westfalen",
    "wof:name":"Landwirtschaftlicher Versicherungsverein M\u00fcnster",
    "wof:placetype":"venue"
},
  "geometry": {"coordinates":[7.1895098686,51.2664260864],"type":"Point"}
}