{
  "type": "Feature",
  "properties": {
    "iso:country":"DE",
    "sg:address":"Schwalefelder Str. 34",
    "sg:city":"Willingen",
    "sg:phone":"+49 5632/6213",
    "sg:postcode":"34508",
    "sg:province":"Hessen",
    "wof:name":"Fritz Behle",
    "wof:placetype":"venue"
},
  "geometry": {"coordinates":[8.611714,51.298916],"type":"Point"}
}