{
  "type": "Feature",
  "properties": {
    "iso:country":"DE",
    "sg:address":"Nordstr. 6",
    "sg:city":"Schwalmtal",
    "sg:phone":"+49 2163/1483",
    "sg:postcode":"41366",
    "sg:province":"Nordrhein-Westfalen",
    "wof:name":"G. Fehlhaber",
    "wof:placetype":"venue"
},
  "geometry": {"coordinates":[6.2630519867,51.251033783],"type":"Point"}
}