{
  "type": "Feature",
  "properties": {
    "iso:country":"DE",
    "sg:address":"Waldstr. 19",
    "sg:city":"Gro\u00df-Zimmern",
    "sg:phone":"+49 6071/42242",
    "sg:postcode":"64846",
    "sg:province":"Hessen",
    "wof:name":"Dieter Bernhard",
    "wof:placetype":"venue"
},
  "geometry": {"coordinates":[8.827699,49.876541],"type":"Point"}
}