{
  "type": "Feature",
  "properties": {
    "iso:country":"DE",
    "sg:address":"Detmolder Str. 62",
    "sg:city":"Bad Lippspringe",
    "sg:phone":"+49 5252/4219",
    "sg:postcode":"33175",
    "sg:province":"Nordrhein-Westfalen",
    "wof:name":"B\u00fcrgerstube",
    "wof:placetype":"venue"
},
  "geometry": {"coordinates":[8.8101062775,51.7782096863],"type":"Point"}
}