{
  "type": "Feature",
  "properties": {
    "iso:country":"DE",
    "sg:address":"Beierfelder Str. 3",
    "sg:city":"Bernsbach",
    "sg:phone":"+49 3774/63350",
    "sg:postcode":"08315",
    "sg:province":"Sachsen",
    "wof:name":"Reinhold Riedel",
    "wof:placetype":"venue"
},
  "geometry": {"coordinates":[12.773809433,50.5756492615],"type":"Point"}
}