{
  "type": "Feature",
  "properties": {
    "iso:country":"DE",
    "sg:address":"Hansjakobstr. 3",
    "sg:city":"Emmendingen",
    "sg:phone":"+49 7641/7435",
    "sg:postcode":"79312",
    "sg:province":"Baden-W\u00fcrttemberg",
    "wof:name":"Arnold Frey Ingenieur",
    "wof:placetype":"venue"
},
  "geometry": {"coordinates":[7.8622689247,48.1099777222],"type":"Point"}
}