{
  "type": "Feature",
  "properties": {
    "iso:country":"DE",
    "sg:address":"Im stillen Winkel 3",
    "sg:city":"Kierspe",
    "sg:phone":"+49 2359/6883",
    "sg:postcode":"58566",
    "sg:province":"Nordrhein-Westfalen",
    "wof:name":"Redaktionsb\u00fcro Herbert K. Kalcher",
    "wof:placetype":"venue"
},
  "geometry": {"coordinates":[7.6011981964,51.1340789795],"type":"Point"}
}