{
  "type": "Feature",
  "properties": {
    "iso:country":"DE",
    "sg:address":"Zum Wallgraben 4",
    "sg:city":"Marburg",
    "sg:postcode":"35043",
    "sg:province":"Hessen",
    "wof:name":"Mehrzweckhalle Ginseldorf",
    "wof:placetype":"venue"
},
  "geometry": {"coordinates":[8.822009,50.84214],"type":"Point"}
}