{
  "type": "Feature",
  "properties": {
    "iso:country":"DE",
    "sg:address":"Ro\u00dfstr. 120",
    "sg:city":"D\u00fcsseldorf",
    "sg:phone":"+49 211/7182908",
    "sg:postcode":"40476",
    "sg:province":"Nordrhein-Westfalen",
    "wof:name":"Leg Gesellschaft F\u00fcr Vertrieb Und Mieterprivatisierung Mbh",
    "wof:placetype":"venue"
},
  "geometry": {"coordinates":[6.775027,51.249603],"type":"Point"}
}