{
  "type": "Feature",
  "properties": {
    "iso:country":"DE",
    "sg:address":"Weidenstr. 35a",
    "sg:city":"Lauben",
    "sg:phone":"+49 8327/9290",
    "sg:postcode":"87761",
    "sg:province":"Bayern",
    "wof:name":"Wohnplan Einrichtungs- Service Gmbh",
    "wof:placetype":"venue"
},
  "geometry": {"coordinates":[10.2945604324,48.0612792969],"type":"Point"}
}