{
  "type": "Feature",
  "properties": {
    "iso:country":"DE",
    "sg:address":"Gl\u00fcck-Auf-Str. 53",
    "sg:city":"Ibbenb\u00fcren",
    "sg:phone":"+49 5451/12600",
    "sg:postcode":"49477",
    "sg:province":"Nordrhein-Westfalen",
    "wof:name":"Marita Wohlgemuth",
    "wof:placetype":"venue"
},
  "geometry": {"coordinates":[7.726589,52.294693],"type":"Point"}
}