{
  "type": "Feature",
  "properties": {
    "iso:country":"DE",
    "sg:address":"Wehlaustr. 1",
    "sg:city":"Bochum",
    "sg:postcode":"44793",
    "sg:province":"Nordrhein-Westfalen",
    "wof:name":"Landis Maschinenbau Gmbh Landtechnik Und Ingen. Syst.",
    "wof:placetype":"venue"
},
  "geometry": {"coordinates":[7.177609,51.495914],"type":"Point"}
}