{
  "type": "Feature",
  "properties": {
    "iso:country":"DE",
    "sg:address":"Holzer Str. 7",
    "sg:city":"Riegelsberg",
    "sg:phone":"+49 6806/440077",
    "sg:postcode":"66292",
    "sg:province":"Saarland",
    "wof:name":"Reichsgraf Von Ingelheim Gen. Echter Von Und Zu",
    "wof:placetype":"venue"
},
  "geometry": {"coordinates":[6.9519491196,49.2966117859],"type":"Point"}
}