{
  "type": "Feature",
  "properties": {
    "iso:country":"DE",
    "sg:address":"Steinfurter Str. 132",
    "sg:city":"M\u00fcnster",
    "sg:phone":"+49 251/7636800",
    "sg:postcode":"48149",
    "sg:province":"Nordrhein-Westfalen",
    "wof:name":"Dmd Daten-melde-dienst Gmbh",
    "wof:placetype":"venue"
},
  "geometry": {"coordinates":[7.6028828621,51.9758148193],"type":"Point"}
}