{
  "type": "Feature",
  "properties": {
    "iso:country":"DE",
    "sg:address":"Am Markt 5",
    "sg:city":"M\u00e4rkisch Buchholz",
    "sg:phone":"+49 33765/80219",
    "sg:postcode":"15748",
    "sg:province":"Brandenburg",
    "wof:name":"Goldener Hirsch",
    "wof:placetype":"venue"
},
  "geometry": {"coordinates":[13.7615661621,52.1098518372],"type":"Point"}
}