{
  "type": "Feature",
  "properties": {
    "iso:country":"DE",
    "sg:address":"R\u00f6mstedter Str. 8",
    "sg:city":"Bad Bevensen",
    "sg:phone":"+49 5821/5090",
    "sg:postcode":"29549",
    "sg:province":"Niedersachsen",
    "wof:name":"Sport Centrum Bad Bevensen Gmbh",
    "wof:placetype":"venue"
},
  "geometry": {"coordinates":[10.591031,53.081284],"type":"Point"}
}