{
  "type": "Feature",
  "properties": {
    "iso:country":"DE",
    "sg:address":"Gro\u00dfmoorbogen 9",
    "sg:city":"Hamburg",
    "sg:postcode":"21079",
    "sg:province":"Hamburg",
    "wof:name":"Industrial Consulting For Business Relations Machines",
    "wof:placetype":"venue"
},
  "geometry": {"coordinates":[10.0101213455,53.4578170776],"type":"Point"}
}