{
  "type": "Feature",
  "properties": {
    "iso:country":"DE",
    "sg:address":"Im Haldenrain 52",
    "sg:city":"Kornwestheim",
    "sg:phone":"+49 7154/6496",
    "sg:postcode":"70806",
    "sg:province":"Baden-W\u00fcrttemberg",
    "wof:name":"Mode-paradies F. Fee Und F. Metzger",
    "wof:placetype":"venue"
},
  "geometry": {"coordinates":[9.200519,48.865211],"type":"Point"}
}