{
  "type": "Feature",
  "properties": {
    "iso:country":"DE",
    "sg:address":"Bleichstr.",
    "sg:city":"Friedrichsdorf",
    "sg:phone":"+49 6172/79681",
    "sg:postcode":"61381",
    "sg:province":"Hessen",
    "wof:name":"R. Michel",
    "wof:placetype":"venue"
},
  "geometry": {"coordinates":[8.647565,50.243343],"type":"Point"}
}