{
  "type": "Feature",
  "properties": {
    "iso:country":"DE",
    "sg:address":"Gablonzer Str. 8",
    "sg:city":"Karlsruhe",
    "sg:postcode":"76185",
    "sg:province":"Baden-W\u00fcrttemberg",
    "wof:name":"Load A Song Gmbh",
    "wof:placetype":"venue"
},
  "geometry": {"coordinates":[8.3537082672,49.0231628418],"type":"Point"}
}