{
  "type": "Feature",
  "properties": {
    "iso:country":"DE",
    "sg:address":"Antoniusstr. 2",
    "sg:city":"Trier",
    "sg:postcode":"54290",
    "sg:province":"Rheinland-Pfalz",
    "wof:name":"Lp Grundbesitz In Trier Verwaltungs Gmbh",
    "wof:placetype":"venue"
},
  "geometry": {"coordinates":[6.6360602379,49.7525596619],"type":"Point"}
}