{
  "type": "Feature",
  "properties": {
    "iso:country":"DE",
    "sg:address":"Mauerkircherstr. 180",
    "sg:city":"M\u00fcnchen",
    "sg:postcode":"81925",
    "sg:province":"Bayern",
    "wof:name":"Hjs Gelenk-system Gmbh",
    "wof:placetype":"venue"
},
  "geometry": {"coordinates":[11.621174,48.168518],"type":"Point"}
}