{
  "type": "Feature",
  "properties": {
    "iso:country":"DE",
    "sg:address":"An der Kirche 16",
    "sg:city":"Fritzlar",
    "sg:phone":"+49 5622/5556",
    "sg:postcode":"34560",
    "sg:province":"Hessen",
    "wof:name":"R. D\u00f6ring",
    "wof:placetype":"venue"
},
  "geometry": {"coordinates":[9.311196,51.156696],"type":"Point"}
}