{
  "type": "Feature",
  "properties": {
    "iso:country":"DE",
    "sg:address":"Industriestr 4",
    "sg:city":"Kevelaer",
    "sg:phone":"+49 2832/93100",
    "sg:postcode":"47623",
    "sg:province":"Nordrhein-Westfalen",
    "wof:name":"Reinhardt Lolly-spezialit\u00e4ten Gmbh",
    "wof:placetype":"venue"
},
  "geometry": {"coordinates":[6.270071,51.580929],"type":"Point"}
}