{
  "type": "Feature",
  "properties": {
    "iso:country":"DE",
    "sg:address":"Judengasse 11",
    "sg:city":"Friedberg",
    "sg:phone":"+49 6031/680485",
    "sg:postcode":"61169",
    "sg:province":"Hessen",
    "wof:name":"Hermann Mangels",
    "wof:placetype":"venue"
},
  "geometry": {"coordinates":[8.754858017,50.339302063],"type":"Point"}
}