{
  "type": "Feature",
  "properties": {
    "iso:country":"DE",
    "sg:address":"Oeltzenstr. 13",
    "sg:city":"Hannover",
    "sg:phone":"+49 511/1318560",
    "sg:postcode":"30169",
    "sg:province":"Niedersachsen",
    "wof:name":"Fachlabor Schrader",
    "wof:placetype":"venue"
},
  "geometry": {"coordinates":[9.7225790024,52.3756065369],"type":"Point"}
}