{
  "type": "Feature",
  "properties": {
    "iso:country":"DE",
    "sg:address":"H\u00f6gerstr. 38",
    "sg:city":"Anzing",
    "sg:phone":"+49 8121/3078",
    "sg:postcode":"85646",
    "sg:province":"Bayern",
    "wof:name":"Johann Gackstatter",
    "wof:placetype":"venue"
},
  "geometry": {"coordinates":[11.8532619476,48.15051651],"type":"Point"}
}