{
  "type": "Feature",
  "properties": {
    "iso:country":"DE",
    "sg:address":"Ernst-Diegel-Str. 8",
    "sg:city":"Alsfeld",
    "sg:phone":"+49 6631/72251",
    "sg:postcode":"36304",
    "sg:province":"Hessen",
    "wof:name":"Tla Transport Logistik Alsfeld Internationale Speditions Gmbh",
    "wof:placetype":"venue"
},
  "geometry": {"coordinates":[9.2848234177,50.747833252],"type":"Point"}
}