{
  "type": "Feature",
  "properties": {
    "iso:country":"DE",
    "sg:address":"Neumarkter Str. 45",
    "sg:city":"Postbauer-Heng",
    "sg:phone":"+49 9188/1670",
    "sg:postcode":"92353",
    "sg:province":"Bayern",
    "wof:name":"Georg Marx",
    "wof:placetype":"venue"
},
  "geometry": {"coordinates":[11.3577022552,49.29347229],"type":"Point"}
}