{
  "type": "Feature",
  "properties": {
    "iso:country":"DE",
    "sg:address":"Tiefe Gasse 2",
    "sg:city":"Redwitz",
    "sg:phone":"+49 9574/4350",
    "sg:postcode":"96257",
    "sg:province":"Bayern",
    "wof:name":"C. Ladegast",
    "wof:placetype":"venue"
},
  "geometry": {"coordinates":[11.2049818039,50.1719703674],"type":"Point"}
}