{
  "type": "Feature",
  "properties": {
    "iso:country":"DE",
    "sg:address":"Petersilienstr. 39",
    "sg:city":"Hasel\u00fcnne",
    "sg:phone":"+49 5961/345",
    "sg:postcode":"49740",
    "sg:province":"Niedersachsen",
    "wof:name":"Ewald Brackmann E. K.",
    "wof:placetype":"venue"
},
  "geometry": {"coordinates":[7.4843740463,52.6733360291],"type":"Point"}
}