{
  "type": "Feature",
  "properties": {
    "iso:country":"DE",
    "sg:address":"Ernst-Heinkel-Str. 4",
    "sg:city":"Straubing",
    "sg:phone":"+49 9421/933000",
    "sg:postcode":"94315",
    "sg:province":"Bayern",
    "wof:name":"Also Abc Trading Gmbh",
    "wof:placetype":"venue"
},
  "geometry": {"coordinates":[12.6224317551,48.8899459839],"type":"Point"}
}