{
  "type": "Feature",
  "properties": {
    "iso:country":"DE",
    "sg:address":"Alte Stube 2",
    "sg:city":"Heilbad Heiligenstadt",
    "sg:phone":"+49 3606/613414",
    "sg:postcode":"37308",
    "sg:province":"Th\u00fcringen",
    "wof:name":"Dr. Heinz Stitz Tierarzt",
    "wof:placetype":"venue"
},
  "geometry": {"coordinates":[10.138584,51.378136],"type":"Point"}
}