{
  "type": "Feature",
  "properties": {
    "iso:country":"DE",
    "sg:address":"Br\u00fcckenauer Str. 66",
    "sg:city":"Schl\u00fcchtern",
    "sg:phone":"+49 6661/2752",
    "sg:postcode":"36381",
    "sg:province":"Hessen",
    "wof:name":"Gasthof Zum L\u00f6wen",
    "wof:placetype":"venue"
},
  "geometry": {"coordinates":[9.5577869415,50.3473396301],"type":"Point"}
}