{
  "type": "Feature",
  "properties": {
    "iso:country":"DE",
    "sg:address":"Bahnhofstr. 23",
    "sg:city":"Marzling",
    "sg:phone":"+49 8161/61299",
    "sg:postcode":"85417",
    "sg:province":"Bayern",
    "wof:name":"Bs Abfallmanagement Und Umwelttechnik Gmbh",
    "wof:placetype":"venue"
},
  "geometry": {"coordinates":[11.7992048264,48.4086341858],"type":"Point"}
}