{
  "type": "Feature",
  "properties": {
    "iso:country":"DE",
    "sg:address":"Schulstr. 19",
    "sg:city":"Ebersbach",
    "sg:postcode":"01561",
    "sg:province":"Sachsen",
    "wof:name":"Evangelisches Pfarramt Naunhof",
    "wof:placetype":"venue"
},
  "geometry": {"coordinates":[13.6263408661,51.2160148621],"type":"Point"}
}