{
  "type": "Feature",
  "properties": {
    "iso:country":"DE",
    "sg:address":"L\u00e4mmersieth 19",
    "sg:city":"Hamburg",
    "sg:postcode":"22305",
    "sg:province":"Hamburg",
    "wof:name":"Graphischer Bund Hamburg E. V.",
    "wof:placetype":"venue"
},
  "geometry": {"coordinates":[10.0510396957,53.5843238831],"type":"Point"}
}