{
  "type": "Feature",
  "properties": {
    "iso:country":"DE",
    "sg:address":"Ecke Wagner/Poststr.",
    "sg:city":"Merzig",
    "sg:phone":"+49 6861/2129",
    "sg:postcode":"66663",
    "sg:province":"Saarland",
    "wof:name":"C. Tiator",
    "wof:placetype":"venue"
},
  "geometry": {"coordinates":[6.63651,49.442039],"type":"Point"}
}