{
  "type": "Feature",
  "properties": {
    "iso:country":"DE",
    "sg:address":"Virnsberger Str. 30 POSTFACH 820130",
    "sg:city":"N\u00fcrnberg",
    "sg:phone":"+49 911/9612970",
    "sg:postcode":"90252",
    "sg:province":"Bayern",
    "wof:name":"Hg Hans Geiger Formenbau Gmbh",
    "wof:placetype":"venue"
},
  "geometry": {"coordinates":[11.009572,49.445446],"type":"Point"}
}