{
  "type": "Feature",
  "properties": {
    "iso:country":"DE",
    "sg:address":"59 rue bellocier",
    "sg:city":"sens",
    "sg:phone":"+49 3869/54576",
    "sg:postcode":"89100",
    "wof:name":"Photos Du Groupe De Rock Festif Bbx Au 287",
    "wof:placetype":"venue"
},
  "geometry": {"coordinates":[3.269764,48.200359],"type":"Point"}
}