{
  "type": "Feature",
  "properties": {
    "iso:country":"DE",
    "sg:address":"Hoppe 2",
    "sg:city":"Sprockh\u00f6vel",
    "sg:phone":"+49 2339/13972",
    "sg:postcode":"45549",
    "sg:province":"Nordrhein-Westfalen",
    "wof:name":"Ernst Kleine",
    "wof:placetype":"venue"
},
  "geometry": {"coordinates":[7.30328,51.344841],"type":"Point"}
}