{
  "type": "Feature",
  "properties": {
    "iso:country":"DE",
    "sg:address":"Birkenstra\u00dfe 14",
    "sg:city":"Wald a.d. Alz",
    "sg:phone":"+49 8634/5880",
    "sg:postcode":"84518",
    "sg:province":"Bayern",
    "wof:name":"Infoseite Wald A.d. Alz",
    "wof:placetype":"venue"
},
  "geometry": {"coordinates":[12.597736,48.13018],"type":"Point"}
}