{
  "type": "Feature",
  "properties": {
    "iso:country":"DE",
    "sg:address":"B\u00f6seler Kirchweg 2",
    "sg:city":"Friesoythe",
    "sg:phone":"+49 4491/2856",
    "sg:postcode":"26169",
    "sg:province":"Niedersachsen",
    "wof:name":"Heinrich Wieborg",
    "wof:placetype":"venue"
},
  "geometry": {"coordinates":[7.889625,53.022034],"type":"Point"}
}