{
  "type": "Feature",
  "properties": {
    "iso:country":"DE",
    "sg:address":"Blankenburger Str. 13",
    "sg:city":"Saalfeld",
    "sg:phone":"+49 3671/53530",
    "sg:postcode":"07318",
    "sg:province":"Th\u00fcringen",
    "wof:name":"G\u00fcnther Elektro Und Schaltanlagenbau Gmbh",
    "wof:placetype":"venue"
},
  "geometry": {"coordinates":[11.3589191437,50.6481742859],"type":"Point"}
}