{
  "type": "Feature",
  "properties": {
    "iso:country":"DE",
    "sg:address":"Soldnerstr. 25",
    "sg:city":"F\u00fcrth",
    "sg:phone":"+49 911/731511",
    "sg:postcode":"90766",
    "sg:province":"Bayern",
    "wof:name":"G. Wenzl",
    "wof:placetype":"venue"
},
  "geometry": {"coordinates":[10.9559192657,49.4823570251],"type":"Point"}
}