{
  "type": "Feature",
  "properties": {
    "iso:country":"DE",
    "sg:address":"Ludwig-Erhard-Str 14",
    "sg:city":"Oberursel",
    "sg:phone":"+49 6171/78087",
    "sg:postcode":"61440",
    "sg:province":"Hessen",
    "wof:name":"Thinkware Gbr",
    "wof:placetype":"venue"
},
  "geometry": {"coordinates":[8.588132,50.188648],"type":"Point"}
}