{
  "type": "Feature",
  "properties": {
    "iso:country":"DE",
    "sg:address":"Friedrich-Koenig-Str 8",
    "sg:city":"Waldb\u00fcttelbrunn",
    "sg:phone":"+49 931/400665",
    "sg:postcode":"97297",
    "sg:province":"Bayern",
    "wof:name":"Wsg Werkzeugschleifereigesellschaft Mbh",
    "wof:placetype":"venue"
},
  "geometry": {"coordinates":[9.84585,49.793121],"type":"Point"}
}