{
  "type": "Feature",
  "properties": {
    "iso:country":"DE",
    "sg:address":"Gemarkenstr. 30",
    "sg:city":"Essen",
    "sg:phone":"+49 201/785752",
    "sg:postcode":"45147",
    "sg:province":"Nordrhein-Westfalen",
    "wof:name":"Harald Appelt Ingenieur",
    "wof:placetype":"venue"
},
  "geometry": {"coordinates":[6.9986481667,51.4422492981],"type":"Point"}
}