{
  "type": "Feature",
  "properties": {
    "iso:country":"DE",
    "sg:address":"Wiesenstr. 36 PF 100537",
    "sg:city":"M\u00fclheim",
    "sg:phone":"+49 208/4596270",
    "sg:postcode":"45473",
    "sg:province":"Nordrhein-Westfalen",
    "wof:name":"Dupec Pipelogistics Gmbh",
    "wof:placetype":"venue"
},
  "geometry": {"coordinates":[6.8932800293,51.4422683716],"type":"Point"}
}