{
  "type": "Feature",
  "properties": {
    "iso:country":"DE",
    "sg:address":"Linther Str. 3",
    "sg:city":"Linthe",
    "sg:phone":"+49 33844/5650",
    "sg:postcode":"14822",
    "sg:province":"Brandenburg",
    "wof:name":"K\u00f6lling Glas Gmbh & Co. Kg Objekt Linthe",
    "wof:placetype":"venue"
},
  "geometry": {"coordinates":[12.788186,52.163513],"type":"Point"}
}