{
  "type": "Feature",
  "properties": {
    "iso:country":"DE",
    "sg:address":"Groner-Tor-Str. 19",
    "sg:city":"G\u00f6ttingen",
    "sg:phone":"+49 551/56367",
    "sg:postcode":"37073",
    "sg:province":"Niedersachsen",
    "wof:name":"Friedrich Kintscher Modeatlier",
    "wof:placetype":"venue"
},
  "geometry": {"coordinates":[9.929367,51.53244],"type":"Point"}
}