{
  "type": "Feature",
  "properties": {
    "iso:country":"DE",
    "sg:address":"Gronauer Hof 6",
    "sg:city":"Nordhorn",
    "sg:phone":"+49 5921/88320",
    "sg:postcode":"48527",
    "sg:province":"Niedersachsen",
    "wof:name":"Hemmers Textil Import Export Gmbh",
    "wof:placetype":"venue"
},
  "geometry": {"coordinates":[7.0462679863,52.4156417847],"type":"Point"}
}