{
  "type": "Feature",
  "properties": {
    "iso:country":"DE",
    "sg:address":"Listlandstr. 6",
    "sg:city":"List",
    "sg:phone":"+49 4651/957088",
    "sg:postcode":"25992",
    "sg:province":"Schleswig-Holstein",
    "wof:name":"Outback",
    "wof:placetype":"venue"
},
  "geometry": {"coordinates":[8.427098,55.015133],"type":"Point"}
}