{
  "type": "Feature",
  "properties": {
    "iso:country":"DE",
    "sg:address":"Sternbuschweg 259",
    "sg:city":"Duisburg",
    "sg:phone":"+49 203/358327",
    "sg:postcode":"47057",
    "sg:province":"Nordrhein-Westfalen",
    "wof:name":"Peter Schilling",
    "wof:placetype":"venue"
},
  "geometry": {"coordinates":[6.782712,51.419262],"type":"Point"}
}