{
  "type": "Feature",
  "properties": {
    "iso:country":"DE",
    "sg:address":"Westl Krl-Friedr-Str 237",
    "sg:city":"Pforzheim",
    "sg:postcode":"75172",
    "sg:province":"Baden-W\u00fcrttemberg",
    "wof:name":"Ev. Pfarrgemeinde Pfarramt Christus",
    "wof:placetype":"venue"
},
  "geometry": {"coordinates":[8.700255394,48.8901367188],"type":"Point"}
}