{
  "type": "Feature",
  "properties": {
    "iso:country":"DE",
    "sg:address":"Schlachthofstr. 40",
    "sg:city":"Albstadt",
    "sg:phone":"+49 7431/2947",
    "sg:postcode":"72458",
    "sg:province":"Baden-W\u00fcrttemberg",
    "wof:name":"Josef Kleinfelder",
    "wof:placetype":"venue"
},
  "geometry": {"coordinates":[9.0417966843,48.2067108154],"type":"Point"}
}