{
  "type": "Feature",
  "properties": {
    "iso:country":"DE",
    "sg:address":"Markgrafenstr. 36",
    "sg:city":"Markgrafpieske",
    "sg:phone":"+49 33633/409",
    "sg:postcode":"15528",
    "sg:province":"Brandenburg",
    "wof:name":"Kurt Flemming",
    "wof:placetype":"venue"
},
  "geometry": {"coordinates":[13.9514169693,52.3295326233],"type":"Point"}
}