{
  "type": "Feature",
  "properties": {
    "iso:country":"DE",
    "sg:address":"Merkurstr. 4",
    "sg:city":"Baden-Baden",
    "sg:postcode":"76530",
    "sg:province":"Baden-W\u00fcrttemberg",
    "wof:name":"Schneider Holz-handels- Und Marketing Gmbh",
    "wof:placetype":"venue"
},
  "geometry": {"coordinates":[8.2411270142,48.7591972351],"type":"Point"}
}