{
  "type": "Feature",
  "properties": {
    "iso:country":"DE",
    "sg:address":"Bargfelder Weg 3",
    "sg:city":"Eimke",
    "sg:phone":"+49 5873/295",
    "sg:postcode":"29578",
    "sg:province":"Niedersachsen",
    "wof:name":"Georg Fisahn",
    "wof:placetype":"venue"
},
  "geometry": {"coordinates":[10.322622,52.960678],"type":"Point"}
}