{
  "type": "Feature",
  "properties": {
    "iso:country":"DE",
    "sg:address":"Ravensberger Str. 4",
    "sg:city":"Werther",
    "sg:phone":"+49 5203/6914",
    "sg:postcode":"33824",
    "sg:province":"Nordrhein-Westfalen",
    "wof:name":"B. K\u00fchnpast",
    "wof:placetype":"venue"
},
  "geometry": {"coordinates":[8.4137411118,52.0733642578],"type":"Point"}
}