{
  "type": "Feature",
  "properties": {
    "iso:country":"DE",
    "sg:address":"Reusrather Str. 1",
    "sg:city":"D\u00fcsseldorf",
    "sg:phone":"+49 211/761258",
    "sg:postcode":"40591",
    "sg:province":"Nordrhein-Westfalen",
    "wof:name":"Lutz Weidler",
    "wof:placetype":"venue"
},
  "geometry": {"coordinates":[6.82543,51.181587],"type":"Point"}
}