{
  "type": "Feature",
  "properties": {
    "iso:country":"DE",
    "sg:address":"Linsenhalde 15",
    "sg:city":"Winnenden",
    "sg:phone":"+49 7195/8046",
    "sg:postcode":"71364",
    "sg:province":"Baden-W\u00fcrttemberg",
    "wof:name":"Manfred H\u00e4u\u00dfler Verwaltungs Gmbh",
    "wof:placetype":"venue"
},
  "geometry": {"coordinates":[9.383009,48.870049],"type":"Point"}
}