{
  "type": "Feature",
  "properties": {
    "iso:country":"DE",
    "sg:address":"Schmiedestr. 32",
    "sg:city":"Wilster",
    "sg:phone":"+49 4823/412",
    "sg:postcode":"25554",
    "sg:province":"Schleswig-Holstein",
    "wof:name":"Friedrich T\u00f6nsing",
    "wof:placetype":"venue"
},
  "geometry": {"coordinates":[9.3752698898,53.9215965271],"type":"Point"}
}