{
  "type": "Feature",
  "properties": {
    "iso:country":"DE",
    "sg:address":"Ehrenzeller Str. 46",
    "sg:city":"Essen",
    "sg:phone":"+49 201/628736",
    "sg:postcode":"45143",
    "sg:province":"Nordrhein-Westfalen",
    "wof:name":"Ma\u00dfschneiderei Dragan",
    "wof:placetype":"venue"
},
  "geometry": {"coordinates":[6.980751,51.462502],"type":"Point"}
}