{
  "type": "Feature",
  "properties": {
    "iso:country":"DE",
    "sg:address":"Ruschestr. 64-70",
    "sg:city":"Berlin",
    "sg:phone":"+49 30/2017470",
    "sg:postcode":"10365",
    "sg:province":"Berlin",
    "wof:name":"Kahlen & Partner Bauplanungsb\u00fcro Gmbh",
    "wof:placetype":"venue"
},
  "geometry": {"coordinates":[13.4869394302,52.5209007263],"type":"Point"}
}