{
  "type": "Feature",
  "properties": {
    "iso:country":"DE",
    "sg:address":"Perwenitzer Chaussee 2",
    "sg:city":"Vehlefanz",
    "sg:phone":"+49 3304/502635",
    "sg:postcode":"16727",
    "sg:province":"Brandenburg",
    "wof:name":"Pagel & Wunderlich Fabrikation Von Laboratoriumsapparaten",
    "wof:placetype":"venue"
},
  "geometry": {"coordinates":[13.101061,52.713902],"type":"Point"}
}