{
  "type": "Feature",
  "properties": {
    "iso:country":"DE",
    "sg:address":"Im Kirchwinkel 9",
    "sg:city":"Otterfing",
    "sg:phone":"+49 8024/99250",
    "sg:postcode":"83624",
    "sg:province":"Bayern",
    "wof:name":"Rothbauer Und Weber Steuerberater",
    "wof:placetype":"venue"
},
  "geometry": {"coordinates":[11.6758880615,47.911441803],"type":"Point"}
}