{
  "type": "Feature",
  "properties": {
    "iso:country":"DE",
    "sg:address":"Spanierstr. 3",
    "sg:city":"Konstanz",
    "sg:postcode":"78467",
    "sg:province":"Baden-W\u00fcrttemberg",
    "wof:name":"Rheingold Gmbh",
    "wof:placetype":"venue"
},
  "geometry": {"coordinates":[9.1777057648,47.6676483154],"type":"Point"}
}