{
  "type": "Feature",
  "properties": {
    "iso:country":"DE",
    "sg:address":"Streitheide 55",
    "sg:city":"Weyhe",
    "sg:phone":"+49 421/804134",
    "sg:postcode":"28844",
    "sg:province":"Niedersachsen",
    "wof:name":"Heinz Hildebrand",
    "wof:placetype":"venue"
},
  "geometry": {"coordinates":[8.792025,52.967506],"type":"Point"}
}