{
  "type": "Feature",
  "properties": {
    "iso:country":"DE",
    "sg:address":"Kesselwasen 16 /2",
    "sg:city":"Esslingen",
    "sg:phone":"+49 711/3655368",
    "sg:postcode":"73728",
    "sg:province":"Baden-W\u00fcrttemberg",
    "wof:name":"Restaurant Asmara",
    "wof:placetype":"venue"
},
  "geometry": {"coordinates":[9.3061599731,48.7398605347],"type":"Point"}
}