{
  "type": "Feature",
  "properties": {
    "iso:country":"DE",
    "sg:address":"Klever Str. 77",
    "sg:city":"Goch",
    "sg:phone":"+49 4928/233250",
    "sg:postcode":"47574",
    "sg:province":"Nordrhein-Westfalen",
    "wof:name":"Derbystar Sportartikelfabrik Gmbh",
    "wof:placetype":"venue"
},
  "geometry": {"coordinates":[6.1585159302,51.687538147],"type":"Point"}
}