{
  "type": "Feature",
  "properties": {
    "iso:country":"DE",
    "sg:address":"Burgunderpl. 1",
    "sg:city":"Kappelrodeck",
    "sg:phone":"+49 4978/4299380",
    "sg:postcode":"77876",
    "sg:province":"Baden-W\u00fcrttemberg",
    "wof:name":"Winzerkeller Hex Vom Dasenstein Eg",
    "wof:placetype":"venue"
},
  "geometry": {"coordinates":[8.112972,48.590775],"type":"Point"}
}