{
  "type": "Feature",
  "properties": {
    "iso:country":"DE",
    "sg:address":"In der W\u00f6lpke 6",
    "sg:city":"Bad Oeynhausen",
    "sg:phone":"+49 5731/92177",
    "sg:postcode":"32547",
    "sg:province":"Nordrhein-Westfalen",
    "wof:name":"Teuko Gmbh",
    "wof:placetype":"venue"
},
  "geometry": {"coordinates":[8.83441,52.18116],"type":"Point"}
}