{
  "type": "Feature",
  "properties": {
    "iso:country":"DE",
    "sg:address":"Bahnkuhle 13",
    "sg:city":"Wegberg",
    "sg:phone":"+49 2434/4893",
    "sg:postcode":"41844",
    "sg:province":"Nordrhein-Westfalen",
    "wof:name":"August Kohlen",
    "wof:placetype":"venue"
},
  "geometry": {"coordinates":[6.2701268196,51.1454696655],"type":"Point"}
}