{
  "type": "Feature",
  "properties": {
    "iso:country":"DE",
    "sg:address":"Gosberger Str. 8",
    "sg:city":"Forchheim",
    "sg:phone":"+49 9191/13306",
    "sg:postcode":"91301",
    "sg:province":"Bayern",
    "wof:name":"Herbert Freiwald",
    "wof:placetype":"venue"
},
  "geometry": {"coordinates":[11.069867,49.684406],"type":"Point"}
}