{
  "type": "Feature",
  "properties": {
    "iso:country":"DE",
    "sg:address":"Eisenbahnstr. 12",
    "sg:city":"Landstuhl",
    "sg:phone":"+49 6371/9030",
    "sg:postcode":"66849",
    "sg:province":"Rheinland-Pfalz",
    "wof:name":"City-appartement-hotel",
    "wof:placetype":"venue"
},
  "geometry": {"coordinates":[7.5656638145,49.4158973694],"type":"Point"}
}