{
  "type": "Feature",
  "properties": {
    "iso:country":"DE",
    "sg:address":"Bahnhofstr. 3",
    "sg:city":"Mohlsdorf",
    "sg:phone":"+49 3661/433057",
    "sg:postcode":"07987",
    "sg:province":"Th\u00fcringen",
    "wof:name":"Ks Trend Bau Gmbh",
    "wof:placetype":"venue"
},
  "geometry": {"coordinates":[12.2665138245,50.6692886353],"type":"Point"}
}