{
  "type": "Feature",
  "properties": {
    "iso:country":"DE",
    "sg:address":"Molsheimer Str. 14",
    "sg:city":"Mannheim",
    "sg:phone":"+49 621/475093",
    "sg:postcode":"68229",
    "sg:province":"Baden-W\u00fcrttemberg",
    "wof:name":"Willi D\u00f6rr",
    "wof:placetype":"venue"
},
  "geometry": {"coordinates":[8.5719327927,49.4398918152],"type":"Point"}
}