{
  "type": "Feature",
  "properties": {
    "iso:country":"DE",
    "sg:address":"Hohe Str. 75",
    "sg:city":"Zeulenroda",
    "sg:phone":"+49 36628/82357",
    "sg:postcode":"07937",
    "sg:province":"Th\u00fcringen",
    "wof:name":"M\u00f6bel-basar M\u00f6belhandels Gmbh",
    "wof:placetype":"venue"
},
  "geometry": {"coordinates":[11.9878015518,50.6481208801],"type":"Point"}
}