{
  "type": "Feature",
  "properties": {
    "iso:country":"DE",
    "sg:address":"Am Birkenhain 3",
    "sg:city":"Limbach-Oberfrohna",
    "sg:phone":"+49 3722/84262",
    "sg:postcode":"09212",
    "sg:province":"Sachsen",
    "wof:name":"W. Walter",
    "wof:placetype":"venue"
},
  "geometry": {"coordinates":[12.7264413834,50.8670196533],"type":"Point"}
}