{
  "type": "Feature",
  "properties": {
    "iso:country":"DE",
    "sg:address":"Rathausstr. 78",
    "sg:city":"Viernheim",
    "sg:phone":"+49 6204/76311",
    "sg:postcode":"68519",
    "sg:province":"Hessen",
    "wof:name":"Walter Blae\u00df",
    "wof:placetype":"venue"
},
  "geometry": {"coordinates":[8.5749197006,49.5340385437],"type":"Point"}
}