{
  "type": "Feature",
  "properties": {
    "iso:country":"DE",
    "sg:address":"Sonnenallee 74",
    "sg:city":"Berlin",
    "sg:phone":"+49 30/6243523",
    "sg:postcode":"12045",
    "sg:province":"Berlin",
    "wof:name":"Norbert Albrecht Masseur",
    "wof:placetype":"venue"
},
  "geometry": {"coordinates":[13.43531,52.483746],"type":"Point"}
}