{
  "type": "Feature",
  "properties": {
    "iso:country":"DE",
    "sg:address":"Tessiner Str. 7",
    "sg:city":"Sanitz",
    "sg:phone":"+49 38209/760",
    "sg:postcode":"18190",
    "sg:province":"Mecklenburg-Vorpommern",
    "wof:name":"Thomsen High-tec Gmbh",
    "wof:placetype":"venue"
},
  "geometry": {"coordinates":[12.387016,54.076576],"type":"Point"}
}