{
  "type": "Feature",
  "properties": {
    "iso:country":"DE",
    "sg:address":"Borstm\u00fchle 1",
    "sg:city":"Burkardroth",
    "sg:phone":"+49 9734/5548",
    "sg:postcode":"97705",
    "sg:province":"Bayern",
    "wof:name":"M. A. I. Immobilien Gmbh",
    "wof:placetype":"venue"
},
  "geometry": {"coordinates":[10.0196352005,50.2532730103],"type":"Point"}
}