{
  "type": "Feature",
  "properties": {
    "iso:country":"DE",
    "sg:address":"Schumacherring 15",
    "sg:city":"Kempten",
    "sg:phone":"+49 831/574330",
    "sg:postcode":"87437",
    "sg:province":"Bayern",
    "wof:name":"D\u00f6bler Beteiligungsges. Mbh",
    "wof:placetype":"venue"
},
  "geometry": {"coordinates":[10.332061,47.724995],"type":"Point"}
}