{
  "type": "Feature",
  "properties": {
    "iso:country":"DE",
    "sg:address":"Alter Bahndamm 9",
    "sg:city":"Medebach",
    "sg:phone":"+49 2982/8319",
    "sg:postcode":"59964",
    "sg:province":"Nordrhein-Westfalen",
    "wof:name":"Pension Reinhold Rabe",
    "wof:placetype":"venue"
},
  "geometry": {"coordinates":[8.7191286087,51.2458648682],"type":"Point"}
}