{
  "type": "Feature",
  "properties": {
    "iso:country":"DE",
    "sg:address":"Bittermarkstr. 2",
    "sg:city":"Dortmund",
    "sg:phone":"+49 231/737071",
    "sg:postcode":"44229",
    "sg:province":"Nordrhein-Westfalen",
    "wof:name":"R\u00fcth Consult Gmbh",
    "wof:placetype":"venue"
},
  "geometry": {"coordinates":[7.465719223,51.4472389221],"type":"Point"}
}