{
  "type": "Feature",
  "properties": {
    "iso:country":"DE",
    "sg:address":"Jakobstr. 5",
    "sg:city":"Durmersheim",
    "sg:phone":"+49 7245",
    "sg:postcode":"76448",
    "sg:province":"Baden-W\u00fcrttemberg",
    "wof:name":"Http://www.studenten-worms.de",
    "wof:placetype":"venue"
},
  "geometry": {"coordinates":[8.272506,48.934879],"type":"Point"}
}