{
  "type": "Feature",
  "properties": {
    "iso:country":"DE",
    "sg:address":"Humboldtstr. 13",
    "sg:city":"Jena",
    "sg:phone":"+49 3641/58040",
    "sg:postcode":"07743",
    "sg:province":"Th\u00fcringen",
    "wof:name":"Dyckerhoff & Widmann Ag Niederlassung Jena",
    "wof:placetype":"venue"
},
  "geometry": {"coordinates":[11.5742397308,50.9327850342],"type":"Point"}
}