{
  "type": "Feature",
  "properties": {
    "iso:country":"DE",
    "sg:address":"Katharinenberg 17",
    "sg:city":"Zarrendorf",
    "sg:phone":"+49 38327/330",
    "sg:postcode":"18510",
    "sg:province":"Mecklenburg-Vorpommern",
    "wof:name":"J. Neumann",
    "wof:placetype":"venue"
},
  "geometry": {"coordinates":[13.094527,54.239529],"type":"Point"}
}