{
  "type": "Feature",
  "properties": {
    "iso:country":"DE",
    "sg:address":"Christian-R\u00fcbsamen-Str. 30",
    "sg:city":"Wetzlar",
    "sg:phone":"+49 6441/76601",
    "sg:postcode":"35578",
    "sg:province":"Hessen",
    "wof:name":"Restaurant Zum Heidekrug",
    "wof:placetype":"venue"
},
  "geometry": {"coordinates":[8.5326271057,50.5461616516],"type":"Point"}
}