{
  "type": "Feature",
  "properties": {
    "iso:country":"DE",
    "sg:address":"Juri-Gagarin-Str. 13-15",
    "sg:city":"Radeberg",
    "sg:phone":"+49 4935/284530",
    "sg:postcode":"01454",
    "sg:province":"Sachsen",
    "wof:name":"Megadenta Dentalprodukte Gmbh",
    "wof:placetype":"venue"
},
  "geometry": {"coordinates":[13.9116392136,51.1000938416],"type":"Point"}
}