{
  "type": "Feature",
  "properties": {
    "iso:country":"DE",
    "sg:address":"Tulpenfeld 7",
    "sg:city":"Bonn",
    "sg:phone":"+49 4922/824340",
    "sg:postcode":"53113",
    "sg:province":"Nordrhein-Westfalen",
    "wof:name":"Deutscher Entwicklungsdienst Gemein\u00dctzige Gmbh",
    "wof:placetype":"venue"
},
  "geometry": {"coordinates":[7.12299,50.716335],"type":"Point"}
}