{
  "type": "Feature",
  "properties": {
    "iso:country":"DE",
    "sg:address":"Klingenhagen 18",
    "sg:city":"Sassenberg",
    "sg:phone":"+49 2583/1275",
    "sg:postcode":"48336",
    "sg:province":"Nordrhein-Westfalen",
    "wof:name":"B\u00f6ckenholt-lackamp",
    "wof:placetype":"venue"
},
  "geometry": {"coordinates":[8.0426521301,51.9924125671],"type":"Point"}
}