{
  "type": "Feature",
  "properties": {
    "iso:country":"DE",
    "sg:address":"Vogelsangstr. 11",
    "sg:city":"Neustetten",
    "sg:phone":"+49 7472/282337",
    "sg:postcode":"72149",
    "sg:province":"Baden-W\u00fcrttemberg",
    "wof:name":"Bkz Anlagenbau Gmbh",
    "wof:placetype":"venue"
},
  "geometry": {"coordinates":[8.880578,48.482922],"type":"Point"}
}