{
  "type": "Feature",
  "properties": {
    "iso:country":"DE",
    "sg:address":"Jahnstr. 100",
    "sg:city":"Ravensburg",
    "sg:phone":"+49 751/23231",
    "sg:postcode":"88214",
    "sg:province":"Baden-W\u00fcrttemberg",
    "wof:name":"Carl Alber",
    "wof:placetype":"venue"
},
  "geometry": {"coordinates":[9.6027812958,47.7709236145],"type":"Point"}
}