{
  "type": "Feature",
  "properties": {
    "iso:country":"DE",
    "sg:address":"Bahnhofstr. 29",
    "sg:city":"Oelsnitz",
    "sg:phone":"+49 37296/2719",
    "sg:postcode":"09376",
    "sg:province":"Sachsen",
    "wof:name":"K\u00e4the Rasselnbruch",
    "wof:placetype":"venue"
},
  "geometry": {"coordinates":[12.6987409592,50.7275428772],"type":"Point"}
}