{
  "type": "Feature",
  "properties": {
    "iso:country":"DE",
    "sg:address":"Hauptstr. 10",
    "sg:city":"Walsleben",
    "sg:phone":"+49 39388/28736",
    "sg:postcode":"39606",
    "sg:province":"Sachsen-Anhalt",
    "wof:name":"H.-h. Thiele",
    "wof:placetype":"venue"
},
  "geometry": {"coordinates":[11.8593969345,52.7553138733],"type":"Point"}
}