{
  "type": "Feature",
  "properties": {
    "iso:country":"DE",
    "sg:address":"Untere Bahnhofstr. 4",
    "sg:city":"Burgbernheim",
    "sg:phone":"+49 9843/888",
    "sg:postcode":"91593",
    "sg:province":"Bayern",
    "wof:name":"Assel Agragar Gmbh",
    "wof:placetype":"venue"
},
  "geometry": {"coordinates":[10.324071,49.449013],"type":"Point"}
}