{
  "type": "Feature",
  "properties": {
    "iso:country":"DE",
    "sg:address":"Cicerostr. 3",
    "sg:city":"Berlin",
    "sg:postcode":"10709",
    "sg:province":"Berlin",
    "wof:name":"Christian Langer Handelsagentur E. K.",
    "wof:placetype":"venue"
},
  "geometry": {"coordinates":[13.3014688492,52.4980812073],"type":"Point"}
}