{
  "type": "Feature",
  "properties": {
    "iso:country":"DE",
    "sg:address":"Ilsenburger Str. 27a",
    "sg:city":"Wernigerode",
    "sg:phone":"+49 3943/9240",
    "sg:postcode":"38855",
    "sg:province":"Sachsen-Anhalt",
    "wof:name":"Stahlbau Und Montage Wernigerode Gmbh",
    "wof:placetype":"venue"
},
  "geometry": {"coordinates":[10.7917566299,51.8383369446],"type":"Point"}
}