{
  "type": "Feature",
  "properties": {
    "iso:country":"DE",
    "sg:address":"Flo\u00dfweg 26",
    "sg:city":"Bonn",
    "sg:phone":"+49 228/346266",
    "sg:postcode":"53179",
    "sg:province":"Nordrhein-Westfalen",
    "wof:name":"Ursula Hebestreit",
    "wof:placetype":"venue"
},
  "geometry": {"coordinates":[7.1746120453,50.6639633179],"type":"Point"}
}