{
  "type": "Feature",
  "properties": {
    "iso:country":"DE",
    "sg:city":"Gro\u00df-Rohrheim",
    "sg:phone":"+49 6245/6122",
    "sg:postcode":"68649",
    "sg:province":"Hessen",
    "wof:name":"B. Degen",
    "wof:placetype":"venue"
},
  "geometry": {"coordinates":[8.472658,49.716934],"type":"Point"}
}