{
  "type": "Feature",
  "properties": {
    "iso:country":"DE",
    "sg:address":"Liebenzeller Str. 7",
    "sg:city":"H\u00f6fen",
    "sg:phone":"+49 7081/6478",
    "sg:postcode":"75339",
    "sg:province":"Baden-W\u00fcrttemberg",
    "wof:name":"Axel Mettler",
    "wof:placetype":"venue"
},
  "geometry": {"coordinates":[8.585413,48.802883],"type":"Point"}
}