{
  "type": "Feature",
  "properties": {
    "iso:country":"DE",
    "sg:address":"Fraundorferstr. 5",
    "sg:city":"Aindling",
    "sg:phone":"+49 8237/7123",
    "sg:postcode":"86447",
    "sg:province":"Bayern",
    "wof:name":"Jakob Thr\u00e4 Ingenieur",
    "wof:placetype":"venue"
},
  "geometry": {"coordinates":[10.9518566132,48.5077552795],"type":"Point"}
}