{
  "type": "Feature",
  "properties": {
    "iso:country":"DE",
    "sg:address":"Hauptstr. 53",
    "sg:city":"Ruhpolding",
    "sg:phone":"+49 8663/1753",
    "sg:postcode":"83324",
    "sg:province":"Bayern",
    "wof:name":"Kreidl",
    "wof:placetype":"venue"
},
  "geometry": {"coordinates":[12.646815,47.762367],"type":"Point"}
}