{
  "type": "Feature",
  "properties": {
    "iso:country":"DE",
    "sg:address":"Humboldtstr. 15",
    "sg:city":"Bremen",
    "sg:phone":"+49 421/72278",
    "sg:postcode":"28203",
    "sg:province":"Bremen",
    "wof:name":"Johann Grimm Orthop\u00e4dieschuhmachermeister",
    "wof:placetype":"venue"
},
  "geometry": {"coordinates":[8.8237457275,53.0750389099],"type":"Point"}
}