{
  "type": "Feature",
  "properties": {
    "iso:country":"DE",
    "sg:address":"Ottersbekallee 15",
    "sg:city":"Hamburg",
    "sg:phone":"+49 40/4913917",
    "sg:postcode":"20255",
    "sg:province":"Hamburg",
    "wof:name":"Petra Martins-van Houtem Rechtsanw\u00e4ltin",
    "wof:placetype":"venue"
},
  "geometry": {"coordinates":[9.9565191269,53.5782279968],"type":"Point"}
}