{
  "type": "Feature",
  "properties": {
    "iso:country":"DE",
    "sg:address":"Kieselerweg 4",
    "sg:city":"R\u00fcdesheim am Rhein",
    "sg:phone":"+49 6722/3204",
    "sg:postcode":"65385",
    "sg:province":"Hessen",
    "wof:name":"Heinrich Dormann Weinanbau",
    "wof:placetype":"venue"
},
  "geometry": {"coordinates":[7.9289078712,49.984210968],"type":"Point"}
}