{
  "type": "Feature",
  "properties": {
    "iso:country":"DE",
    "sg:address":"Vor dem Wassertor 18 - 20",
    "sg:city":"Aschersleben",
    "sg:phone":"+49 3473/809563",
    "sg:postcode":"06449",
    "sg:province":"Sachsen-Anhalt",
    "wof:name":"Schnierer Fengler & Helbich Ohg",
    "wof:placetype":"venue"
},
  "geometry": {"coordinates":[11.457838,51.74979],"type":"Point"}
}