{
  "type": "Feature",
  "properties": {
    "iso:country":"DE",
    "sg:address":"8",
    "sg:city":"Annecy",
    "sg:phone":"+49 3304/50511394",
    "sg:postcode":"74000",
    "wof:name":"Finsaveur",
    "wof:placetype":"venue"
},
  "geometry": {"coordinates":[6.129201,45.897499],"type":"Point"}
}