{
  "type": "Feature",
  "properties": {
    "iso:country":"DE",
    "sg:address":"Dellbr\u00fccker Hauptstr. 114",
    "sg:city":"K\u00f6ln",
    "sg:phone":"+49 221/681933",
    "sg:postcode":"51069",
    "sg:province":"Nordrhein-Westfalen",
    "wof:name":"Von-quadt-apotheke Gerd Klein",
    "wof:placetype":"venue"
},
  "geometry": {"coordinates":[7.071634,50.977806],"type":"Point"}
}