{
  "type": "Feature",
  "properties": {
    "iso:country":"DE",
    "sg:address":"Kalkwerkstr. 57",
    "sg:city":"Finnentrop",
    "sg:phone":"+49 2724/287",
    "sg:postcode":"57413",
    "sg:province":"Nordrhein-Westfalen",
    "wof:name":"Josef Willerscheidt S\u00e4gewerk Und Holzhandlung",
    "wof:placetype":"venue"
},
  "geometry": {"coordinates":[8.0426702499,51.1892433167],"type":"Point"}
}