{
  "type": "Feature",
  "properties": {
    "iso:country":"DE",
    "sg:address":"Wiesenstr. 5",
    "sg:city":"Rannungen",
    "sg:phone":"+49 9738/304",
    "sg:postcode":"97517",
    "sg:province":"Bayern",
    "wof:name":"Leo Erhard B\u00fcrgermeister Der",
    "wof:placetype":"venue"
},
  "geometry": {"coordinates":[10.2028646469,50.1643333435],"type":"Point"}
}