{
  "type": "Feature",
  "properties": {
    "iso:country":"DE",
    "sg:address":"Wichheimer Str. 22",
    "sg:city":"K\u00f6ln",
    "sg:phone":"+49 221/631735",
    "sg:postcode":"51067",
    "sg:province":"Nordrhein-Westfalen",
    "wof:name":"M. Steindor",
    "wof:placetype":"venue"
},
  "geometry": {"coordinates":[7.021178,50.963741],"type":"Point"}
}