{
  "type": "Feature",
  "properties": {
    "iso:country":"DE",
    "sg:address":"B\u00e4umerstr. 9",
    "sg:city":"Ibbenb\u00fcren",
    "sg:phone":"+49 5451/91020",
    "sg:postcode":"49477",
    "sg:province":"Nordrhein-Westfalen",
    "wof:name":"H. Strier",
    "wof:placetype":"venue"
},
  "geometry": {"coordinates":[7.7112059593,52.2815742493],"type":"Point"}
}