{
  "type": "Feature",
  "properties": {
    "iso:country":"DE",
    "sg:address":"Bahnhofstr. 13",
    "sg:city":"Borna",
    "sg:phone":"+49 3433/201442",
    "sg:postcode":"04552",
    "sg:province":"Sachsen",
    "wof:name":"Tinas Reiseb\u00fcro Martina Sakel",
    "wof:placetype":"venue"
},
  "geometry": {"coordinates":[12.4949483871,51.1221351624],"type":"Point"}
}