{
  "type": "Feature",
  "properties": {
    "iso:country":"DE",
    "sg:address":"Feldschmiede 81",
    "sg:city":"Itzehoe",
    "sg:phone":"+49 4821/3014",
    "sg:postcode":"25524",
    "sg:province":"Schleswig-Holstein",
    "wof:name":"Cord Plesmann Rechtsanwalt",
    "wof:placetype":"venue"
},
  "geometry": {"coordinates":[9.5129423141,53.9263763428],"type":"Point"}
}