{
  "type": "Feature",
  "properties": {
    "iso:country":"DE",
    "sg:address":"Gretescher Weg 75",
    "sg:city":"Osnabr\u00fcck",
    "sg:phone":"+49 4954/1707879",
    "sg:postcode":"49084",
    "sg:province":"Niedersachsen",
    "wof:name":"Perlenimport Immo K\u00dcrtz",
    "wof:placetype":"venue"
},
  "geometry": {"coordinates":[8.1057491302,52.2818222046],"type":"Point"}
}