{
  "type": "Feature",
  "properties": {
    "iso:country":"DE",
    "sg:address":"West-Kraueler Bogen 30",
    "sg:city":"Hamburg",
    "sg:phone":"+49 40/7239530",
    "sg:postcode":"21037",
    "sg:province":"Hamburg",
    "wof:name":"E. Kr\u00f6ger",
    "wof:placetype":"venue"
},
  "geometry": {"coordinates":[10.221315,53.399113],"type":"Point"}
}