{
  "type": "Feature",
  "properties": {
    "iso:country":"DE",
    "sg:address":"Rostocker Str. 94",
    "sg:city":"Teterow",
    "sg:phone":"+49 3996/172788",
    "sg:postcode":"17166",
    "sg:province":"Mecklenburg-Vorpommern",
    "wof:name":"Hans Wendt",
    "wof:placetype":"venue"
},
  "geometry": {"coordinates":[12.572263,53.778511],"type":"Point"}
}