{
  "type": "Feature",
  "properties": {
    "iso:country":"DE",
    "sg:address":"Bedburger Str. 29",
    "sg:city":"Bergheim",
    "sg:phone":"+49 2272/6700",
    "sg:postcode":"50126",
    "sg:province":"Nordrhein-Westfalen",
    "wof:name":"Horst Commer",
    "wof:placetype":"venue"
},
  "geometry": {"coordinates":[6.589990139,50.9745368958],"type":"Point"}
}