{
  "type": "Feature",
  "properties": {
    "iso:country":"DE",
    "sg:address":"Hansastr. 75",
    "sg:city":"R\u00f6dinghausen",
    "sg:phone":"+49 5746/1655",
    "sg:postcode":"32289",
    "sg:province":"Nordrhein-Westfalen",
    "wof:name":"Hwd Industriebedarfs-gmbh",
    "wof:placetype":"venue"
},
  "geometry": {"coordinates":[8.535716,52.237045],"type":"Point"}
}