{
  "type": "Feature",
  "properties": {
    "iso:country":"DE",
    "sg:address":"Marktplatz 17",
    "sg:city":"Iphofen",
    "sg:phone":"+49 9323/3370",
    "sg:postcode":"97346",
    "sg:province":"Bayern",
    "wof:name":"Adolf St\u00f6hr",
    "wof:placetype":"venue"
},
  "geometry": {"coordinates":[10.260547,49.704147],"type":"Point"}
}