{
  "type": "Feature",
  "properties": {
    "iso:country":"DE",
    "sg:address":"Friedhofsallee 24",
    "sg:city":"Hannover",
    "sg:postcode":"30519",
    "sg:province":"Niedersachsen",
    "wof:name":"Multi Call Media Gmbh",
    "wof:placetype":"venue"
},
  "geometry": {"coordinates":[9.7826023102,52.3382110596],"type":"Point"}
}