{
  "type": "Feature",
  "properties": {
    "iso:country":"DE",
    "sg:address":"Gernr\u00f6der Str. 14",
    "sg:city":"Gernrode",
    "sg:phone":"+49 39485/61915",
    "sg:postcode":"37339",
    "sg:province":"Th\u00fcringen",
    "wof:name":"M\u00fcller Maschinen Hdl. Gmbh",
    "wof:placetype":"venue"
},
  "geometry": {"coordinates":[10.268205,51.47084],"type":"Point"}
}