{
  "type": "Feature",
  "properties": {
    "iso:country":"DE",
    "sg:address":"Achering 81/4",
    "sg:city":"Freising",
    "sg:phone":"+49 8165/95050",
    "sg:postcode":"85354",
    "sg:province":"Bayern",
    "wof:name":"Vsk Gmbh",
    "wof:placetype":"venue"
},
  "geometry": {"coordinates":[11.708303,48.343975],"type":"Point"}
}