{
  "type": "Feature",
  "properties": {
    "iso:country":"DE",
    "sg:address":"Ringstr. 15",
    "sg:city":"Prackenbach",
    "sg:phone":"+49 9942/902107",
    "sg:postcode":"94267",
    "sg:province":"Bayern",
    "wof:name":"Pizzeria Ristorante Zum Toni",
    "wof:placetype":"venue"
},
  "geometry": {"coordinates":[12.8259935379,49.0948028564],"type":"Point"}
}