{
  "type": "Feature",
  "properties": {
    "iso:country":"DE",
    "sg:address":"Heidentalring 12",
    "sg:city":"Nickenich",
    "sg:phone":"+49 2632/988024",
    "sg:postcode":"56645",
    "sg:province":"Rheinland-Pfalz",
    "wof:name":"Dieter Tomm Steuerberater",
    "wof:placetype":"venue"
},
  "geometry": {"coordinates":[7.327229023,50.4178695679],"type":"Point"}
}