{
  "type": "Feature",
  "properties": {
    "iso:country":"DE",
    "sg:address":"Chemnitzer Str 6-8",
    "sg:city":"Mannheim",
    "sg:phone":"+49 621/7176080",
    "sg:postcode":"68309",
    "sg:province":"Baden-W\u00fcrttemberg",
    "wof:name":"M\u00fcnch Industrie-technik Gmbh",
    "wof:placetype":"venue"
},
  "geometry": {"coordinates":[8.55188,49.51115],"type":"Point"}
}