{
  "type": "Feature",
  "properties": {
    "iso:country":"DE",
    "sg:address":"Hohenzollernstr. 109",
    "sg:city":"M\u00fcnchen",
    "sg:phone":"+49 89/919498",
    "sg:postcode":"80796",
    "sg:province":"Bayern",
    "wof:name":"Isar Hausverwaltung Gmbh",
    "wof:placetype":"venue"
},
  "geometry": {"coordinates":[11.5660572052,48.160823822],"type":"Point"}
}