{
  "type": "Feature",
  "properties": {
    "iso:country":"DE",
    "sg:address":"Hirtenweg 7",
    "sg:city":"Eichst\u00e4tt",
    "sg:phone":"+49 8421/2830",
    "sg:postcode":"85072",
    "sg:province":"Bayern",
    "wof:name":"Xaver Seitz",
    "wof:placetype":"venue"
},
  "geometry": {"coordinates":[11.1723890305,48.9059028625],"type":"Point"}
}