{
  "type": "Feature",
  "properties": {
    "iso:country":"DE",
    "sg:address":"Feldstr. 27",
    "sg:city":"Recklinghausen",
    "sg:phone":"+49 2361/61051",
    "sg:postcode":"45661",
    "sg:province":"Nordrhein-Westfalen",
    "wof:name":"Karl Piepenbrock",
    "wof:placetype":"venue"
},
  "geometry": {"coordinates":[7.2075037956,51.5689697266],"type":"Point"}
}