{
  "type": "Feature",
  "properties": {
    "iso:country":"DE",
    "sg:address":"Queichstr. 8",
    "sg:city":"Germersheim",
    "sg:phone":"+49 7274/76721",
    "sg:postcode":"76726",
    "sg:province":"Rheinland-Pfalz",
    "wof:name":"Shiraishi & Partner Marketing Und Dienstleist. Mbh",
    "wof:placetype":"venue"
},
  "geometry": {"coordinates":[8.362005,49.218555],"type":"Point"}
}