{
  "type": "Feature",
  "properties": {
    "iso:country":"DE",
    "sg:address":"\u00dcberm Talweg 17",
    "sg:city":"Alheim",
    "sg:phone":"+49 6623/3623",
    "sg:postcode":"36211",
    "sg:province":"Hessen",
    "wof:name":"Klaus Knierim",
    "wof:placetype":"venue"
},
  "geometry": {"coordinates":[9.66995,51.020885],"type":"Point"}
}