{
  "type": "Feature",
  "properties": {
    "iso:country":"DE",
    "sg:address":"Am Tiefen Graben 2",
    "sg:city":"Saarbr\u00fccken",
    "sg:phone":"+49 6898/32467",
    "sg:postcode":"66127",
    "sg:province":"Saarland",
    "wof:name":"Gottfried Fehr Architekt",
    "wof:placetype":"venue"
},
  "geometry": {"coordinates":[6.898739,49.235439],"type":"Point"}
}