{
  "type": "Feature",
  "properties": {
    "iso:country":"DE",
    "sg:address":"Ackerstr. 180",
    "sg:city":"D\u00fcsseldorf",
    "sg:phone":"+49 211/675310",
    "sg:postcode":"40235",
    "sg:province":"Nordrhein-Westfalen",
    "wof:name":"Maria Krklec - Howvat",
    "wof:placetype":"venue"
},
  "geometry": {"coordinates":[6.809677124,51.2308769226],"type":"Point"}
}