{
  "type": "Feature",
  "properties": {
    "iso:country":"DE",
    "sg:address":"Merkenicher Str. 60",
    "sg:city":"K\u00f6ln",
    "sg:phone":"+49 221/7122833",
    "sg:postcode":"50735",
    "sg:province":"Nordrhein-Westfalen",
    "wof:name":"E. Orlowski",
    "wof:placetype":"venue"
},
  "geometry": {"coordinates":[6.9665131569,50.9839172363],"type":"Point"}
}