{
  "type": "Feature",
  "properties": {
    "iso:country":"DE",
    "sg:address":"Brombeerweg 1",
    "sg:city":"Windhagen",
    "sg:postcode":"53578",
    "sg:province":"Rheinland-Pfalz",
    "wof:name":"Conexx-immobilien B\u00f6tel & Hauke Kg",
    "wof:placetype":"venue"
},
  "geometry": {"coordinates":[7.3628702164,50.6417388916],"type":"Point"}
}