{
  "type": "Feature",
  "properties": {
    "iso:country":"DE",
    "sg:address":"Olbernhauer Str. 44",
    "sg:city":"Gro\u00dfhartmannsdorf",
    "sg:phone":"+49 37329/4703",
    "sg:postcode":"09618",
    "sg:province":"Sachsen",
    "wof:name":"Gasthof Obersaida",
    "wof:placetype":"venue"
},
  "geometry": {"coordinates":[13.3253536224,50.7748031616],"type":"Point"}
}