{
  "type": "Feature",
  "properties": {
    "iso:country":"DE",
    "sg:address":"Ringmauerstr. 8",
    "sg:city":"Waldkirchen",
    "sg:phone":"+49 8581/1338",
    "sg:postcode":"94065",
    "sg:province":"Bayern",
    "wof:name":"Dr. Georg Graf",
    "wof:placetype":"venue"
},
  "geometry": {"coordinates":[13.599811554,48.7299537659],"type":"Point"}
}