{
  "type": "Feature",
  "properties": {
    "iso:country":"DE",
    "sg:address":"Alte Rathausstr. 8",
    "sg:city":"Prien",
    "sg:phone":"+49 8051/2127",
    "sg:postcode":"83209",
    "sg:province":"Bayern",
    "wof:name":"Peter Hofer",
    "wof:placetype":"venue"
},
  "geometry": {"coordinates":[12.3428173065,47.855670929],"type":"Point"}
}