{
  "type": "Feature",
  "properties": {
    "iso:country":"DE",
    "sg:address":"T\u00f6pferstr. 30",
    "sg:city":"Wachtberg",
    "sg:phone":"+49 2225/7578",
    "sg:postcode":"53343",
    "sg:province":"Nordrhein-Westfalen",
    "wof:name":"Restaurant Kr\u00e4utergarten",
    "wof:placetype":"venue"
},
  "geometry": {"coordinates":[7.0567731857,50.6132698059],"type":"Point"}
}