{
  "type": "Feature",
  "properties": {
    "iso:country":"DE",
    "sg:address":"Wittbr\u00e4ucker Str. 213",
    "sg:city":"Dortmund",
    "sg:phone":"+49 231/482636",
    "sg:postcode":"44269",
    "sg:province":"Nordrhein-Westfalen",
    "wof:name":"China-restaurant Mandarin",
    "wof:placetype":"venue"
},
  "geometry": {"coordinates":[7.5403847694,51.4748535156],"type":"Point"}
}