{
  "type": "Feature",
  "properties": {
    "iso:country":"DE",
    "sg:address":"Pl\u00f6nitzer Weg 2",
    "sg:city":"Taucha",
    "sg:postcode":"04425",
    "sg:province":"Sachsen",
    "wof:name":"Az Aare Holding Gmbh",
    "wof:placetype":"venue"
},
  "geometry": {"coordinates":[12.50463,51.385399],"type":"Point"}
}