{
  "type": "Feature",
  "properties": {
    "iso:country":"DE",
    "sg:address":"Kirchplatz 3",
    "sg:city":"Sinzig",
    "sg:phone":"+49 2642/980279",
    "sg:postcode":"53489",
    "sg:province":"Rheinland-Pfalz",
    "wof:name":"Snoopys Bistro",
    "wof:placetype":"venue"
},
  "geometry": {"coordinates":[7.25207901,50.5447654724],"type":"Point"}
}