{
  "type": "Feature",
  "properties": {
    "iso:country":"DE",
    "sg:address":"J\u00e4gerstr. 43",
    "sg:city":"Duisburg",
    "sg:phone":"+49 2065/62033",
    "sg:postcode":"47228",
    "sg:province":"Nordrhein-Westfalen",
    "wof:name":"Future Computer Vertriebs Gmbh",
    "wof:placetype":"venue"
},
  "geometry": {"coordinates":[6.687355,51.407528],"type":"Point"}
}