{
  "type": "Feature",
  "properties": {
    "iso:country":"DE",
    "sg:address":"Harwick 12",
    "sg:city":"Gescher",
    "sg:phone":"+49 2542/7727",
    "sg:postcode":"48712",
    "sg:province":"Nordrhein-Westfalen",
    "wof:name":"Wfh Eing Gmbh & Co. Kg",
    "wof:placetype":"venue"
},
  "geometry": {"coordinates":[6.9924449921,51.9673461914],"type":"Point"}
}