{
  "type": "Feature",
  "properties": {
    "iso:country":"DE",
    "sg:address":"Schillerstr. 39",
    "sg:city":"Jever",
    "sg:phone":"+49 4461/72244",
    "sg:postcode":"26441",
    "sg:province":"Niedersachsen",
    "wof:name":"Gothaer Versicherung",
    "wof:placetype":"venue"
},
  "geometry": {"coordinates":[7.9050559998,53.5779380798],"type":"Point"}
}