{
  "type": "Feature",
  "properties": {
    "iso:country":"DE",
    "sg:address":"Peter-D\u00f6rfler-Str. 2",
    "sg:city":"Schwandorf",
    "sg:phone":"+49 9431/42421",
    "sg:postcode":"92421",
    "sg:province":"Bayern",
    "wof:name":"Josef Schmid",
    "wof:placetype":"venue"
},
  "geometry": {"coordinates":[12.08988,49.344471],"type":"Point"}
}