{
  "type": "Feature",
  "properties": {
    "iso:country":"DE",
    "sg:address":"Hermann-L\u00f6ns-Str. 15",
    "sg:city":"Wendlingen",
    "sg:phone":"+49 7024",
    "sg:postcode":"73240",
    "sg:province":"Baden-W\u00fcrttemberg",
    "wof:name":"Gws Aktiengesellschaft F\u00fcr W\u00e4rme Und Strom",
    "wof:placetype":"venue"
},
  "geometry": {"coordinates":[9.390403,48.678505],"type":"Point"}
}