{
  "type": "Feature",
  "properties": {
    "iso:country":"DE",
    "sg:address":"Gr\u00fcnstr. 5",
    "sg:city":"Solingen",
    "sg:phone":"+49 212/2681314",
    "sg:postcode":"42697",
    "sg:province":"Nordrhein-Westfalen",
    "wof:name":"Modellbaushop Solingen",
    "wof:placetype":"venue"
},
  "geometry": {"coordinates":[6.998037,51.161842],"type":"Point"}
}