{
  "type": "Feature",
  "properties": {
    "iso:country":"DE",
    "sg:address":"Z\u00fclpicher Str. 320A",
    "sg:city":"K\u00f6ln",
    "sg:phone":"+49 221/415654",
    "sg:postcode":"50937",
    "sg:province":"Nordrhein-Westfalen",
    "wof:name":"Ristorante Bellavista",
    "wof:placetype":"venue"
},
  "geometry": {"coordinates":[6.9183697701,50.9212646484],"type":"Point"}
}