{
  "type": "Feature",
  "properties": {
    "iso:country":"DE",
    "sg:address":"Holzstr. 13",
    "sg:city":"M\u00fchlhausen",
    "sg:phone":"+49 36014/43400",
    "sg:postcode":"99974",
    "sg:province":"Th\u00fcringen",
    "wof:name":"Th\u00fcringer Sanierungs- Und Denkmalpflege Gmbh",
    "wof:placetype":"venue"
},
  "geometry": {"coordinates":[10.4519443512,51.2104110718],"type":"Point"}
}