{
  "type": "Feature",
  "properties": {
    "iso:country":"DE",
    "sg:address":"Friedhofweg 4",
    "sg:city":"Br\u00e4unlingen",
    "sg:phone":"+49 771/61121",
    "sg:postcode":"78199",
    "sg:province":"Baden-W\u00fcrttemberg",
    "wof:name":"L\u00f6wenbrauerei Br\u00e4unlingen Heinrich Kalb Kg",
    "wof:placetype":"venue"
},
  "geometry": {"coordinates":[8.450815,47.927139],"type":"Point"}
}