{
  "type": "Feature",
  "properties": {
    "iso:country":"DE",
    "sg:address":"Waltershofener Str 7",
    "sg:city":"Freiburg",
    "sg:phone":"+49 761/455600",
    "sg:postcode":"79111",
    "sg:province":"Baden-W\u00fcrttemberg",
    "wof:name":"Avm M\u00fcller Ohg",
    "wof:placetype":"venue"
},
  "geometry": {"coordinates":[7.793506,47.993908],"type":"Point"}
}