{
  "type": "Feature",
  "properties": {
    "iso:country":"DE",
    "sg:address":"Hauptstr. 63-67",
    "sg:city":"Bad Wimpfen",
    "sg:phone":"+49 7063/244",
    "sg:postcode":"74206",
    "sg:province":"Baden-W\u00fcrttemberg",
    "wof:name":"August Wieland Haus- Und K\u00fcchenger\u00e4te",
    "wof:placetype":"venue"
},
  "geometry": {"coordinates":[9.1612606049,49.229724884],"type":"Point"}
}