{
  "type": "Feature",
  "properties": {
    "iso:country":"DE",
    "sg:address":"Ahlener Str. 1",
    "sg:city":"Beckum",
    "sg:phone":"+49 2521/17718",
    "sg:postcode":"59269",
    "sg:province":"Nordrhein-Westfalen",
    "wof:name":"Relax Beckum Fitness- Und Gesundheitsstudio Gesch.-inh.",
    "wof:placetype":"venue"
},
  "geometry": {"coordinates":[8.0334367752,51.7553482056],"type":"Point"}
}