{
  "type": "Feature",
  "properties": {
    "iso:country":"DE",
    "sg:address":"Weinbergstr. 10",
    "sg:city":"Freiburg",
    "sg:phone":"+49 761/43840",
    "sg:postcode":"79111",
    "sg:province":"Baden-W\u00fcrttemberg",
    "wof:name":"W. Hodapp",
    "wof:placetype":"venue"
},
  "geometry": {"coordinates":[7.7946949005,47.9760475159],"type":"Point"}
}