{
  "type": "Feature",
  "properties": {
    "iso:country":"DE",
    "sg:address":"Sch\u00fctzenstr. 31",
    "sg:city":"Marburg",
    "sg:phone":"+49 6421/65663",
    "sg:postcode":"35039",
    "sg:province":"Hessen",
    "wof:name":"Burghard Jammer",
    "wof:placetype":"venue"
},
  "geometry": {"coordinates":[8.7779483795,50.8198013306],"type":"Point"}
}