{
  "type": "Feature",
  "properties": {
    "iso:country":"DE",
    "sg:address":"Frankenstr. 296",
    "sg:city":"Essen",
    "sg:phone":"+49 201/441799",
    "sg:postcode":"45133",
    "sg:province":"Nordrhein-Westfalen",
    "wof:name":"T. Beckmann Und E. Aich Rechtsanw\u00e4lte",
    "wof:placetype":"venue"
},
  "geometry": {"coordinates":[7.0205888748,51.4197883606],"type":"Point"}
}