{
  "type": "Feature",
  "properties": {
    "iso:country":"DE",
    "sg:address":"Eickener Str. 55",
    "sg:city":"M\u00f6nchengladbach",
    "sg:phone":"+49 2161/12788",
    "sg:postcode":"41061",
    "sg:province":"Nordrhein-Westfalen",
    "wof:name":"Beethoven-apotheke",
    "wof:placetype":"venue"
},
  "geometry": {"coordinates":[6.445611,51.200523],"type":"Point"}
}