{
  "type": "Feature",
  "properties": {
    "iso:country":"DE",
    "sg:address":"Lange Str. 116",
    "sg:city":"Delmenhorst",
    "sg:phone":"+49 4221/16963",
    "sg:postcode":"27749",
    "sg:province":"Niedersachsen",
    "wof:name":"M & S Mode",
    "wof:placetype":"venue"
},
  "geometry": {"coordinates":[8.628298,53.049675],"type":"Point"}
}