{
  "type": "Feature",
  "properties": {
    "iso:country":"DE",
    "sg:address":"Elisabethstr. 18",
    "sg:city":"Bonn",
    "sg:phone":"+49 4922/8820030",
    "sg:postcode":"53177",
    "sg:province":"Nordrhein-Westfalen",
    "wof:name":"Aloisiuskolleg Gmbh",
    "wof:placetype":"venue"
},
  "geometry": {"coordinates":[7.1511,50.678577],"type":"Point"}
}