{
  "type": "Feature",
  "properties": {
    "iso:country":"DE",
    "sg:address":"Ruhrstr. 95",
    "sg:city":"Witten",
    "sg:phone":"+49 2302/81085",
    "sg:postcode":"58452",
    "sg:province":"Nordrhein-Westfalen",
    "wof:name":"Teppichland Recklinghausen S\u00fcd Teppich-bodenbel\u00e4ge-farben-",
    "wof:placetype":"venue"
},
  "geometry": {"coordinates":[7.3362059593,51.430644989],"type":"Point"}
}