{
  "type": "Feature",
  "properties": {
    "iso:country":"DE",
    "sg:address":"Am F\u00f6rderturm 8",
    "sg:city":"M\u00fclheim",
    "sg:phone":"+49 208/803550",
    "sg:postcode":"45472",
    "sg:province":"Nordrhein-Westfalen",
    "wof:name":"B. E. T. Gbr",
    "wof:placetype":"venue"
},
  "geometry": {"coordinates":[6.9475030899,51.4424858093],"type":"Point"}
}