{
  "type": "Feature",
  "properties": {
    "iso:country":"DE",
    "sg:address":"Tannenkampstr. 49",
    "sg:city":"Bad Zwischenahn",
    "sg:phone":"+49 441/69606",
    "sg:postcode":"26160",
    "sg:province":"Niedersachsen",
    "wof:name":"Manfred Voigt",
    "wof:placetype":"venue"
},
  "geometry": {"coordinates":[8.12675,53.180172],"type":"Point"}
}