{
  "type": "Feature",
  "properties": {
    "iso:country":"DE",
    "sg:address":"Am Anger 10",
    "sg:city":"Osterode",
    "sg:phone":"+49 5522/82390",
    "sg:postcode":"37520",
    "sg:province":"Niedersachsen",
    "wof:name":"Bahnhofsgastst\u00e4tte",
    "wof:placetype":"venue"
},
  "geometry": {"coordinates":[10.2188539505,51.7452507019],"type":"Point"}
}