{
  "type": "Feature",
  "properties": {
    "iso:country":"DE",
    "sg:address":"Altewiekring 44a",
    "sg:city":"Braunschweig",
    "sg:phone":"+49 531/791997",
    "sg:postcode":"38102",
    "sg:province":"Niedersachsen",
    "wof:name":"Rolf Kr\u00fcckeberg-saathoff",
    "wof:placetype":"venue"
},
  "geometry": {"coordinates":[10.542231,52.264843],"type":"Point"}
}