{
  "type": "Feature",
  "properties": {
    "iso:country":"DE",
    "sg:address":"Truderinger Str. 315",
    "sg:city":"M\u00fcnchen",
    "sg:phone":"+49 89/426522",
    "sg:postcode":"81825",
    "sg:province":"Bayern",
    "wof:name":"Friedens-apotheke E. K.",
    "wof:placetype":"venue"
},
  "geometry": {"coordinates":[11.671601,48.12159],"type":"Point"}
}