{
  "type": "Feature",
  "properties": {
    "iso:country":"DE",
    "sg:address":"Wagenbauerstrasse 12",
    "sg:city":"M\u00fcnchen",
    "sg:postcode":"81677",
    "sg:province":"Bayern",
    "wof:name":"Fotodirect",
    "wof:placetype":"venue"
},
  "geometry": {"coordinates":[11.618713,48.139423],"type":"Point"}
}