{
  "type": "Feature",
  "properties": {
    "iso:country":"DE",
    "sg:address":"Neue Hohnst\u00e4dter Str. 7",
    "sg:city":"Grimma",
    "sg:phone":"+49 3437/917133",
    "sg:postcode":"04668",
    "sg:province":"Sachsen",
    "wof:name":"G. Genzel",
    "wof:placetype":"venue"
},
  "geometry": {"coordinates":[12.691142,51.259819],"type":"Point"}
}