{
  "type": "Feature",
  "properties": {
    "iso:country":"DE",
    "sg:address":"Bockenheimer Landstrasse 73-77",
    "sg:city":"Frankfurt",
    "sg:phone":"+49 8638/96820",
    "sg:postcode":"60325",
    "sg:province":"Hessen",
    "wof:name":"Miraphone E.g.",
    "wof:placetype":"venue"
},
  "geometry": {"coordinates":[12.4149856567,48.2158317566],"type":"Point"}
}