{
  "type": "Feature",
  "properties": {
    "iso:country":"DE",
    "sg:address":"In der Enz",
    "sg:city":"Neuerburg",
    "sg:phone":"+49 6564/2660",
    "sg:postcode":"54673",
    "sg:province":"Rheinland-Pfalz",
    "wof:name":"Campingplatz In Der Enz",
    "wof:placetype":"venue"
},
  "geometry": {"coordinates":[6.27939,50.019817],"type":"Point"}
}