{
  "type": "Feature",
  "properties": {
    "iso:country":"DE",
    "sg:address":"Langgasse 29",
    "sg:city":"Dornburg",
    "sg:phone":"+49 6436/1348",
    "sg:postcode":"65599",
    "sg:province":"Hessen",
    "wof:name":"Alfred Hartmann",
    "wof:placetype":"venue"
},
  "geometry": {"coordinates":[8.015162,50.484505],"type":"Point"}
}