{
  "type": "Feature",
  "properties": {
    "iso:country":"DE",
    "sg:address":"Bachemer Str. 54",
    "sg:city":"K\u00f6ln",
    "sg:phone":"+49 221/412125",
    "sg:postcode":"50931",
    "sg:province":"Nordrhein-Westfalen",
    "wof:name":"Wolfgang Hartmann Bier-grosshdl.",
    "wof:placetype":"venue"
},
  "geometry": {"coordinates":[6.920789,50.929821],"type":"Point"}
}