{
  "type": "Feature",
  "properties": {
    "iso:country":"DE",
    "sg:address":"V\u00f6lklinger Str 24",
    "sg:city":"D\u00fcsseldorf",
    "sg:phone":"+49 211/577010",
    "sg:postcode":"40221",
    "sg:province":"Nordrhein-Westfalen",
    "wof:name":"F.g. Conzen Gmbh",
    "wof:placetype":"venue"
},
  "geometry": {"coordinates":[6.758616,51.209816],"type":"Point"}
}