{
  "type": "Feature",
  "properties": {
    "iso:country":"DE",
    "sg:address":"Bahnhofstr. 35",
    "sg:city":"Weyhe",
    "sg:phone":"+49 4203/6018",
    "sg:postcode":"28844",
    "sg:province":"Niedersachsen",
    "wof:name":"Van Megen Und Dijkstra Rechtsanw\u00e4lte Und Notare",
    "wof:placetype":"venue"
},
  "geometry": {"coordinates":[8.8551454544,52.9838943481],"type":"Point"}
}