{
  "type": "Feature",
  "properties": {
    "iso:country":"DE",
    "sg:address":"Eichendorffstr. 87",
    "sg:city":"Bottrop",
    "sg:phone":"+49 2041/54040",
    "sg:postcode":"46242",
    "sg:province":"Nordrhein-Westfalen",
    "wof:name":"Heinrich Ingendoh & Co. Gmbh",
    "wof:placetype":"venue"
},
  "geometry": {"coordinates":[6.899204,51.530308],"type":"Point"}
}