{
  "type": "Feature",
  "properties": {
    "iso:country":"DE",
    "sg:address":"G\u00fcterbahnhofstr. 7",
    "sg:city":"Torgau",
    "sg:phone":"+49 3421/902758",
    "sg:postcode":"04860",
    "sg:province":"Sachsen",
    "wof:name":"Materiell-tech. Versorgung Der Landwirtschaft Leipzig",
    "wof:placetype":"venue"
},
  "geometry": {"coordinates":[12.990955,51.564476],"type":"Point"}
}