{
  "type": "Feature",
  "properties": {
    "iso:country":"DE",
    "sg:address":"Hafenstr. 49",
    "sg:city":"Greifswald",
    "sg:postcode":"17489",
    "sg:province":"Mecklenburg-Vorpommern",
    "wof:name":"Ghg Haushaltswaren Rostock",
    "wof:placetype":"venue"
},
  "geometry": {"coordinates":[13.3898200989,54.0991592407],"type":"Point"}
}