{
  "type": "Feature",
  "properties": {
    "iso:country":"DE",
    "sg:address":"Johann-Salomon-Str. 4",
    "sg:city":"W\u00fcrzburg",
    "sg:postcode":"97080",
    "sg:province":"Bayern",
    "wof:name":"Ica-innovative Consulting Association Ewiv",
    "wof:placetype":"venue"
},
  "geometry": {"coordinates":[9.9261484146,49.8213500977],"type":"Point"}
}