{
  "type": "Feature",
  "properties": {
    "iso:country":"DE",
    "sg:address":"Petersstr. 30",
    "sg:city":"Freiberg",
    "sg:phone":"+49 3731/3760",
    "sg:postcode":"09599",
    "sg:province":"Sachsen",
    "wof:name":"Redaktion Freie Presse",
    "wof:placetype":"venue"
},
  "geometry": {"coordinates":[13.3404855728,50.9157714844],"type":"Point"}
}