{
  "type": "Feature",
  "properties": {
    "iso:country":"DE",
    "sg:address":"Kammerrathsfeldstr. 76",
    "sg:city":"D\u00fcsseldorf",
    "sg:phone":"+49 211/702894",
    "sg:postcode":"40593",
    "sg:province":"Nordrhein-Westfalen",
    "wof:name":"Werner Rodewies",
    "wof:placetype":"venue"
},
  "geometry": {"coordinates":[6.8758640289,51.1498718262],"type":"Point"}
}