{
  "type": "Feature",
  "properties": {
    "iso:country":"DE",
    "sg:address":"H\u00fcnger 37",
    "sg:city":"Wermelskirchen",
    "sg:phone":"+49 2196/4273",
    "sg:postcode":"42929",
    "sg:province":"Nordrhein-Westfalen",
    "wof:name":"Hans-friedr. Wagner Innenarchitekt",
    "wof:placetype":"venue"
},
  "geometry": {"coordinates":[7.186493,51.138412],"type":"Point"}
}