{
  "type": "Feature",
  "properties": {
    "iso:country":"DE",
    "sg:address":"Kronenstr. 62",
    "sg:city":"D\u00fcsseldorf",
    "sg:phone":"+49 211/334573",
    "sg:postcode":"40217",
    "sg:province":"Nordrhein-Westfalen",
    "wof:name":"Verm\u00f6gensverwaltung Gmbh",
    "wof:placetype":"venue"
},
  "geometry": {"coordinates":[6.7741069794,51.2105026245],"type":"Point"}
}