{
  "type": "Feature",
  "properties": {
    "iso:country":"DE",
    "sg:address":"Max-von-Laue-Str 31",
    "sg:city":"W\u00fcrzburg",
    "sg:phone":"+49 931/9910220",
    "sg:postcode":"97080",
    "sg:province":"Bayern",
    "wof:name":"Sgs Druckform Service Gmbh",
    "wof:placetype":"venue"
},
  "geometry": {"coordinates":[9.889034,49.813908],"type":"Point"}
}