{
  "type": "Feature",
  "properties": {
    "iso:country":"DE",
    "sg:address":"Domstr. 46",
    "sg:city":"Grimmen",
    "sg:postcode":"18507",
    "sg:province":"Mecklenburg-Vorpommern",
    "wof:name":"Riesebeck Immobilien Und Verwaltungs Kg",
    "wof:placetype":"venue"
},
  "geometry": {"coordinates":[13.0428199768,54.1137886047],"type":"Point"}
}