{
  "type": "Feature",
  "properties": {
    "iso:country":"DE",
    "sg:address":"Fahrgasse 7",
    "sg:city":"Langen",
    "sg:phone":"+49 6103/23577",
    "sg:postcode":"63225",
    "sg:province":"Hessen",
    "wof:name":"F. W. Metzger",
    "wof:placetype":"venue"
},
  "geometry": {"coordinates":[8.679017067,49.9889526367],"type":"Point"}
}