{
  "type": "Feature",
  "properties": {
    "iso:country":"DE",
    "sg:address":"Kaiserstr. 16",
    "sg:city":"Landstuhl",
    "sg:phone":"+49 6371/3922",
    "sg:postcode":"66849",
    "sg:province":"Rheinland-Pfalz",
    "wof:name":"U. Jahn",
    "wof:placetype":"venue"
},
  "geometry": {"coordinates":[7.5668449402,49.4137115479],"type":"Point"}
}