{
  "type": "Feature",
  "properties": {
    "iso:country":"DE",
    "sg:address":"Obere Industriestr. 16",
    "sg:city":"Netphen",
    "sg:phone":"+49 2738/694929",
    "sg:postcode":"57250",
    "sg:province":"Nordrhein-Westfalen",
    "wof:name":"Herd Assekuranz",
    "wof:placetype":"venue"
},
  "geometry": {"coordinates":[8.0897340775,50.9117698669],"type":"Point"}
}