{
  "type": "Feature",
  "properties": {
    "iso:country":"DE",
    "sg:address":"St\u00fcffel 2 a",
    "sg:city":"Hamburg",
    "sg:phone":"+49 40/6048047",
    "sg:postcode":"22395",
    "sg:province":"Hamburg",
    "wof:name":"Warlich Immobilienmakler",
    "wof:placetype":"venue"
},
  "geometry": {"coordinates":[10.1344347,53.6695899963],"type":"Point"}
}