{
  "type": "Feature",
  "properties": {
    "iso:country":"DE",
    "sg:address":"Heinrich-Leifels-Str. 1",
    "sg:city":"Borken",
    "sg:phone":"+49 2861/91062",
    "sg:postcode":"46325",
    "sg:province":"Nordrhein-Westfalen",
    "wof:name":"Vereinte Versicherung Albert D\u00fcssel",
    "wof:placetype":"venue"
},
  "geometry": {"coordinates":[6.8592500687,51.8467483521],"type":"Point"}
}