{
  "type": "Feature",
  "properties": {
    "iso:country":"DE",
    "sg:address":"Hauptstr. 12",
    "sg:city":"Algermissen",
    "sg:phone":"+49 5126/432",
    "sg:postcode":"31191",
    "sg:province":"Niedersachsen",
    "wof:name":"Wilhelm Klug",
    "wof:placetype":"venue"
},
  "geometry": {"coordinates":[9.952716,52.273117],"type":"Point"}
}