{
  "type": "Feature",
  "properties": {
    "iso:country":"DE",
    "sg:address":"Fuggerstr. 6",
    "sg:city":"Ibbenb\u00fcren",
    "sg:phone":"+49 5451/9090",
    "sg:postcode":"49479",
    "sg:province":"Nordrhein-Westfalen",
    "wof:name":"M.- P. Versand Von Musikanlagen Gmbh",
    "wof:placetype":"venue"
},
  "geometry": {"coordinates":[7.776612,52.262054],"type":"Point"}
}