{
  "type": "Feature",
  "properties": {
    "iso:country":"DE",
    "sg:address":"Trierer Str. 239",
    "sg:city":"Monschau",
    "sg:phone":"+49 2472/1487",
    "sg:postcode":"52156",
    "sg:province":"Nordrhein-Westfalen",
    "wof:name":"Reiner Schmitz",
    "wof:placetype":"venue"
},
  "geometry": {"coordinates":[6.264187,50.572922],"type":"Point"}
}