{
  "type": "Feature",
  "properties": {
    "iso:country":"DE",
    "sg:address":"Heubischer Str. 26",
    "sg:city":"Neustadt",
    "sg:phone":"+49 9568/1404",
    "sg:postcode":"96465",
    "sg:province":"Bayern",
    "wof:name":"Stang",
    "wof:placetype":"venue"
},
  "geometry": {"coordinates":[11.123769,50.325497],"type":"Point"}
}