{
  "type": "Feature",
  "properties": {
    "iso:country":"DE",
    "sg:address":"Kattensteert 4",
    "sg:city":"Hamburg",
    "sg:postcode":"22119",
    "sg:province":"Hamburg",
    "wof:name":"Pd - Police Security Service Kg",
    "wof:placetype":"venue"
},
  "geometry": {"coordinates":[10.1010189056,53.5493125916],"type":"Point"}
}