{
  "type": "Feature",
  "properties": {
    "iso:country":"DE",
    "sg:address":"Mittelweg 45",
    "sg:city":"Hille",
    "sg:phone":"+49 5734/1316",
    "sg:postcode":"32479",
    "sg:province":"Nordrhein-Westfalen",
    "wof:name":"Dieter Kalusche",
    "wof:placetype":"venue"
},
  "geometry": {"coordinates":[8.792407,52.272999],"type":"Point"}
}