{
  "type": "Feature",
  "properties": {
    "iso:country":"DE",
    "sg:address":"Westerwaldstr. 60",
    "sg:city":"Bendorf",
    "sg:phone":"+49 2601/689",
    "sg:postcode":"56170",
    "sg:province":"Rheinland-Pfalz",
    "wof:name":"Hoppen",
    "wof:placetype":"venue"
},
  "geometry": {"coordinates":[7.5985507965,50.4572525024],"type":"Point"}
}