{
  "type": "Feature",
  "properties": {
    "iso:country":"DE",
    "sg:address":"Hauptstr. 16",
    "sg:city":"Hiltpoltstein",
    "sg:phone":"+49 9192/264",
    "sg:postcode":"91355",
    "sg:province":"Bayern",
    "wof:name":"Herbert Reichel",
    "wof:placetype":"venue"
},
  "geometry": {"coordinates":[11.316841,49.659885],"type":"Point"}
}