{
  "type": "Feature",
  "properties": {
    "iso:country":"DE",
    "sg:address":"Schwarzer Weg 12",
    "sg:city":"Minden",
    "sg:phone":"+49 571/31059",
    "sg:postcode":"32423",
    "sg:province":"Nordrhein-Westfalen",
    "wof:name":"Gustav Jakoci Kg",
    "wof:placetype":"venue"
},
  "geometry": {"coordinates":[8.932367,52.285954],"type":"Point"}
}