{
  "type": "Feature",
  "properties": {
    "iso:country":"DE",
    "sg:address":"Wackerstr. 48",
    "sg:city":"Offenburg",
    "sg:phone":"+49 781/22152",
    "sg:postcode":"77652",
    "sg:province":"Baden-W\u00fcrttemberg",
    "wof:name":"Hans Kurzbach",
    "wof:placetype":"venue"
},
  "geometry": {"coordinates":[7.952474,48.499844],"type":"Point"}
}