{
  "type": "Feature",
  "properties": {
    "iso:country":"DE",
    "sg:address":"Schabernackstr. 15",
    "sg:city":"Neuss",
    "sg:phone":"+49 2131/754040",
    "sg:postcode":"41462",
    "sg:province":"Nordrhein-Westfalen",
    "wof:name":"Heinz-berend Jansen Rechtsanwalt",
    "wof:placetype":"venue"
},
  "geometry": {"coordinates":[6.6653499603,51.2119483948],"type":"Point"}
}