{
  "type": "Feature",
  "properties": {
    "iso:country":"DE",
    "sg:address":"Teichweg 6",
    "sg:city":"Steinen",
    "sg:phone":"+49 7627/3149",
    "sg:postcode":"79585",
    "sg:province":"Baden-W\u00fcrttemberg",
    "wof:name":"Hornmann & Klose",
    "wof:placetype":"venue"
},
  "geometry": {"coordinates":[7.7485041618,47.6403808594],"type":"Point"}
}