{
  "type": "Feature",
  "properties": {
    "iso:country":"DE",
    "sg:address":"Dolmanstr. 36",
    "sg:city":"Bergisch Gladbach",
    "sg:phone":"+49 2204/60860",
    "sg:postcode":"51427",
    "sg:province":"Nordrhein-Westfalen",
    "wof:name":"J. Veithen",
    "wof:placetype":"venue"
},
  "geometry": {"coordinates":[7.114524,50.959293],"type":"Point"}
}