{
  "type": "Feature",
  "properties": {
    "iso:country":"DE",
    "sg:address":"Benedikt-Erhard-Str. 6",
    "sg:city":"Bad T\u00f6lz",
    "sg:phone":"+49 8041/77944",
    "sg:postcode":"83646",
    "sg:province":"Bayern",
    "wof:name":"G\u00e4stehaus Bergblick",
    "wof:placetype":"venue"
},
  "geometry": {"coordinates":[11.5728311539,47.7621841431],"type":"Point"}
}