{
  "type": "Feature",
  "properties": {
    "iso:country":"DE",
    "sg:address":"Hahnenbalz 35c",
    "sg:city":"N\u00fcrnberg",
    "sg:postcode":"90411",
    "sg:province":"Bayern",
    "wof:name":"Mst Medien Service Nordbayern Gmbh",
    "wof:placetype":"venue"
},
  "geometry": {"coordinates":[11.1089820862,49.5117645264],"type":"Point"}
}