{
  "type": "Feature",
  "properties": {
    "iso:country":"DE",
    "sg:address":"Auf dem Quabben 39",
    "sg:city":"Zeven",
    "sg:phone":"+49 4281/2199",
    "sg:postcode":"27404",
    "sg:province":"Niedersachsen",
    "wof:name":"Elektro Kohl Gmbh",
    "wof:placetype":"venue"
},
  "geometry": {"coordinates":[9.28068,53.287807],"type":"Point"}
}