{
  "type": "Feature",
  "properties": {
    "iso:country":"DE",
    "sg:address":"Hauptstr.",
    "sg:city":"Ventschow",
    "sg:postcode":"19417",
    "sg:province":"Mecklenburg-Vorpommern",
    "wof:name":"Bauger\u00e4te U. Diamantwerkzeuge",
    "wof:placetype":"venue"
},
  "geometry": {"coordinates":[11.580247,53.786652],"type":"Point"}
}