{
  "type": "Feature",
  "properties": {
    "iso:country":"DE",
    "sg:address":"In der Pfarrtanne 4a",
    "sg:city":"Alsbach-H\u00e4hnlein",
    "sg:postcode":"64665",
    "sg:province":"Hessen",
    "wof:name":"Walter Precht Masseur",
    "wof:placetype":"venue"
},
  "geometry": {"coordinates":[8.608484,49.74234],"type":"Point"}
}