{
  "type": "Feature",
  "properties": {
    "iso:country":"DE",
    "sg:address":"Varreler Str. 2",
    "sg:city":"Wagenfeld",
    "sg:phone":"+49 5774/1328",
    "sg:postcode":"49419",
    "sg:province":"Niedersachsen",
    "wof:name":"Life",
    "wof:placetype":"venue"
},
  "geometry": {"coordinates":[8.6927938461,52.5313415527],"type":"Point"}
}