{
  "type": "Feature",
  "properties": {
    "iso:country":"DE",
    "sg:address":"Passower Chaussee 109",
    "sg:city":"Schwedt",
    "sg:phone":"+49 3332/450880",
    "sg:postcode":"16303",
    "sg:province":"Brandenburg",
    "wof:name":"Velind Chemie Gmbh",
    "wof:placetype":"venue"
},
  "geometry": {"coordinates":[14.274600029,53.068561554],"type":"Point"}
}