{
  "type": "Feature",
  "properties": {
    "iso:country":"DE",
    "sg:address":"Auf dem Quellberg 16",
    "sg:city":"D\u00fclmen",
    "sg:phone":"+49 2594/5071",
    "sg:postcode":"48249",
    "sg:province":"Nordrhein-Westfalen",
    "wof:name":"Basar Waren- Und Kaufhaus",
    "wof:placetype":"venue"
},
  "geometry": {"coordinates":[7.2952599525,51.8427047729],"type":"Point"}
}