{
  "type": "Feature",
  "properties": {
    "iso:country":"DE",
    "sg:address":"Herrenkellergasse 2",
    "sg:city":"Ulm",
    "sg:phone":"+49 731/69063",
    "sg:postcode":"89073",
    "sg:province":"Baden-W\u00fcrttemberg",
    "wof:name":"Flor Markt Gmbh",
    "wof:placetype":"venue"
},
  "geometry": {"coordinates":[9.991256,48.400063],"type":"Point"}
}