{
  "type": "Feature",
  "properties": {
    "iso:country":"DE",
    "sg:address":"Saarlandstr. 111",
    "sg:city":"Dortmund",
    "sg:phone":"+49 231/7212927",
    "sg:postcode":"44139",
    "sg:province":"Nordrhein-Westfalen",
    "wof:name":"Warsteiner Runde",
    "wof:placetype":"venue"
},
  "geometry": {"coordinates":[7.4601531029,51.5046920776],"type":"Point"}
}