{
  "type": "Feature",
  "properties": {
    "iso:country":"DE",
    "sg:address":"Ramlinger Str. 9",
    "sg:city":"Burgwedel",
    "sg:phone":"+49 5139/894070",
    "sg:postcode":"30938",
    "sg:province":"Niedersachsen",
    "wof:name":"Will-com Gmbh",
    "wof:placetype":"venue"
},
  "geometry": {"coordinates":[9.9425992966,52.4993476868],"type":"Point"}
}