{
  "type": "Feature",
  "properties": {
    "iso:country":"DE",
    "sg:address":"Max-Becher-Str. 14",
    "sg:city":"Steinberg/Wildenau",
    "sg:phone":"+49 37462/4938",
    "sg:postcode":"08228",
    "sg:province":"Sachsen",
    "wof:name":"Ibl-hydronic",
    "wof:placetype":"venue"
},
  "geometry": {"coordinates":[12.4118204117,50.5340690613],"type":"Point"}
}