{
  "type": "Feature",
  "properties": {
    "iso:country":"DE",
    "sg:address":"Wilmersdorfer Str. 60",
    "sg:city":"Aachen",
    "sg:phone":"+49 241/154135",
    "sg:postcode":"52068",
    "sg:province":"Nordrhein-Westfalen",
    "wof:name":"F. Arnouts",
    "wof:placetype":"venue"
},
  "geometry": {"coordinates":[6.139102,50.785801],"type":"Point"}
}