{
  "type": "Feature",
  "properties": {
    "iso:country":"DE",
    "sg:address":"Untere Dorfstr. 30 d",
    "sg:city":"Hartmannsdorf-Reichenau",
    "sg:phone":"+49 37326/84038",
    "sg:postcode":"01762",
    "sg:province":"Sachsen",
    "wof:name":"U. Walther",
    "wof:placetype":"venue"
},
  "geometry": {"coordinates":[13.5754308701,50.7933578491],"type":"Point"}
}