{
  "type": "Feature",
  "properties": {
    "iso:country":"DE",
    "sg:address":"Neustadt 31-33",
    "sg:city":"Eschwege",
    "sg:phone":"+49 5651/31362",
    "sg:postcode":"37269",
    "sg:province":"Hessen",
    "wof:name":"Wilhelm G\u00fcnteroth Gmbh & Co. Kg",
    "wof:placetype":"venue"
},
  "geometry": {"coordinates":[10.061539,51.184864],"type":"Point"}
}