{
  "type": "Feature",
  "properties": {
    "iso:country":"DE",
    "sg:address":"Pappelweg 7",
    "sg:city":"Wolfsburg",
    "sg:phone":"+49 5362/51218",
    "sg:postcode":"38442",
    "sg:province":"Niedersachsen",
    "wof:name":"Heinrich Steiln Architekt",
    "wof:placetype":"venue"
},
  "geometry": {"coordinates":[10.692831,52.413193],"type":"Point"}
}