{
  "type": "Feature",
  "properties": {
    "iso:country":"DE",
    "sg:address":"Am Lakenbach 3",
    "sg:city":"L\u00fcgde",
    "sg:phone":"+49 5283/1276",
    "sg:postcode":"32676",
    "sg:province":"Nordrhein-Westfalen",
    "wof:name":"Heiner M\u00fcller",
    "wof:placetype":"venue"
},
  "geometry": {"coordinates":[9.33327,51.876781],"type":"Point"}
}