{
  "type": "Feature",
  "properties": {
    "iso:country":"DE",
    "sg:address":"Kaule 55",
    "sg:city":"Bergisch Gladbach",
    "sg:phone":"+49 2204/55944",
    "sg:postcode":"51429",
    "sg:province":"Nordrhein-Westfalen",
    "wof:name":"Kauler Hof",
    "wof:placetype":"venue"
},
  "geometry": {"coordinates":[7.1512007713,50.9592666626],"type":"Point"}
}