{
  "type": "Feature",
  "properties": {
    "iso:country":"DE",
    "sg:address":"Am Kalkofen 25",
    "sg:city":"Kerpen",
    "sg:phone":"+49 2273/1668",
    "sg:postcode":"50169",
    "sg:province":"Nordrhein-Westfalen",
    "wof:name":"Peter Dresen Ingenieur",
    "wof:placetype":"venue"
},
  "geometry": {"coordinates":[6.7065610886,50.913143158],"type":"Point"}
}