{
  "type": "Feature",
  "properties": {
    "iso:country":"DE",
    "sg:address":"Schmiedestr. 11",
    "sg:city":"M\u00fcssen",
    "sg:phone":"+49 4155/4411",
    "sg:postcode":"21516",
    "sg:province":"Schleswig-Holstein",
    "wof:name":"Erwin Thomsen",
    "wof:placetype":"venue"
},
  "geometry": {"coordinates":[10.562455,53.497669],"type":"Point"}
}