{
  "type": "Feature",
  "properties": {
    "iso:country":"DE",
    "sg:address":"Buchenweg 1",
    "sg:city":"Schorndorf",
    "sg:phone":"+49 7181/45248",
    "sg:postcode":"73614",
    "sg:province":"Baden-W\u00fcrttemberg",
    "wof:name":"Edeltraud M\u00e4rtz",
    "wof:placetype":"venue"
},
  "geometry": {"coordinates":[9.5325317383,48.7901191711],"type":"Point"}
}