{
  "type": "Feature",
  "properties": {
    "iso:country":"DE",
    "sg:address":"R\u00e4lingser Str. 312",
    "sg:city":"Uetze",
    "sg:phone":"+49 5147/315",
    "sg:postcode":"31311",
    "sg:province":"Niedersachsen",
    "wof:name":"G\u00fcnter Kliewer",
    "wof:placetype":"venue"
},
  "geometry": {"coordinates":[10.101834,52.457146],"type":"Point"}
}