{
  "type": "Feature",
  "properties": {
    "iso:country":"DE",
    "sg:address":"Am Waldbad",
    "sg:city":"Salzhausen",
    "sg:phone":"+49 4172/6574",
    "sg:postcode":"21376",
    "sg:province":"Niedersachsen",
    "wof:name":"Freibad",
    "wof:placetype":"venue"
},
  "geometry": {"coordinates":[10.1773538589,53.2220954895],"type":"Point"}
}