{
  "type": "Feature",
  "properties": {
    "iso:country":"DE",
    "sg:address":"Hektorstr.5",
    "sg:city":"Berlin",
    "sg:phone":"+49 30/32703830",
    "sg:postcode":"10711",
    "sg:province":"Berlin",
    "wof:name":"Screendesign By Screendesign.de",
    "wof:placetype":"venue"
},
  "geometry": {"coordinates":[13.2979669571,52.4995498657],"type":"Point"}
}