{
  "type": "Feature",
  "properties": {
    "iso:country":"DE",
    "sg:address":"M\u00f6rikestr. 17",
    "sg:city":"G\u00f6ppingen",
    "sg:phone":"+49 7161/72879",
    "sg:postcode":"73033",
    "sg:province":"Baden-W\u00fcrttemberg",
    "wof:name":"Haus Der Familie Familienbildungsst\u00e4tte",
    "wof:placetype":"venue"
},
  "geometry": {"coordinates":[9.6593065262,48.7034950256],"type":"Point"}
}