{
  "type": "Feature",
  "properties": {
    "iso:country":"DE",
    "sg:address":"Klein S\u00fcstedter Str. 3",
    "sg:city":"Suderburg",
    "sg:phone":"+49 5826/1547",
    "sg:postcode":"29556",
    "sg:province":"Niedersachsen",
    "wof:name":"Bernd Stahlbock Landwirtschaftl. Lohnbetrieb",
    "wof:placetype":"venue"
},
  "geometry": {"coordinates":[10.482153,52.912773],"type":"Point"}
}