{
  "type": "Feature",
  "properties": {
    "iso:country":"DE",
    "sg:address":"Bergweg 13",
    "sg:city":"Greiling",
    "sg:phone":"+49 8041/77414",
    "sg:postcode":"83677",
    "sg:province":"Bayern",
    "wof:name":"Immo-wohnbau Mangold Gmbh",
    "wof:placetype":"venue"
},
  "geometry": {"coordinates":[11.609256,47.761829],"type":"Point"}
}