{
  "type": "Feature",
  "properties": {
    "iso:country":"DE",
    "sg:address":"Obere Dorfstr. 16",
    "sg:city":"Aitzendorf",
    "sg:phone":"+49 37382/81593",
    "sg:postcode":"09326",
    "sg:province":"Sachsen",
    "wof:name":"Reiterhof Schlimpert",
    "wof:placetype":"venue"
},
  "geometry": {"coordinates":[12.8794622421,51.0669250488],"type":"Point"}
}