{
  "type": "Feature",
  "properties": {
    "iso:country":"DE",
    "sg:address":"Poststr. 36",
    "sg:city":"G\u00f6ppingen",
    "sg:phone":"+49 7161/73620",
    "sg:postcode":"73033",
    "sg:province":"Baden-W\u00fcrttemberg",
    "wof:name":"Cinema Gmbh Filmtheaterbetriebe",
    "wof:placetype":"venue"
},
  "geometry": {"coordinates":[9.656337738,48.702495575],"type":"Point"}
}