{
  "type": "Feature",
  "properties": {
    "iso:country":"DE",
    "sg:address":"Gro\u00dfe Str. 9",
    "sg:city":"Kranenburg",
    "sg:phone":"+49 2826/5650",
    "sg:postcode":"47559",
    "sg:province":"Nordrhein-Westfalen",
    "wof:name":"Bernhard Linsen",
    "wof:placetype":"venue"
},
  "geometry": {"coordinates":[6.009791,51.789284],"type":"Point"}
}