{
  "type": "Feature",
  "properties": {
    "iso:country":"DE",
    "sg:address":"Luxemburger Str. 8 b",
    "sg:city":"Bochum",
    "sg:phone":"+49 234/381103",
    "sg:postcode":"44789",
    "sg:province":"Nordrhein-Westfalen",
    "wof:name":"Franz Lohoff",
    "wof:placetype":"venue"
},
  "geometry": {"coordinates":[7.2293162346,51.4660987854],"type":"Point"}
}