{
  "type": "Feature",
  "properties": {
    "iso:country":"DE",
    "sg:address":"Kossaer Str. 3",
    "sg:city":"Leipzig",
    "sg:phone":"+49 341/5210371",
    "sg:postcode":"04356",
    "sg:province":"Sachsen",
    "wof:name":"Peter Stein",
    "wof:placetype":"venue"
},
  "geometry": {"coordinates":[12.3917541504,51.4102363586],"type":"Point"}
}