{
  "type": "Feature",
  "properties": {
    "iso:country":"DE",
    "sg:address":"Gr\u00fcnstr. 39",
    "sg:city":"Gengenbach",
    "sg:phone":"+49 7803/600855",
    "sg:postcode":"77723",
    "sg:province":"Baden-W\u00fcrttemberg",
    "wof:name":"Jahraus & Schr\u00f6ter Gmbh",
    "wof:placetype":"venue"
},
  "geometry": {"coordinates":[8.012608,48.402725],"type":"Point"}
}