{
  "type": "Feature",
  "properties": {
    "iso:country":"DE",
    "sg:address":"Kr\u00e4mpferstr. 26",
    "sg:city":"Erfurt",
    "sg:phone":"+49 361/6430940",
    "sg:postcode":"99084",
    "sg:province":"Th\u00fcringen",
    "wof:name":"Westhyp Westf\u00e4lische Hypotheken-, Bank Ag",
    "wof:placetype":"venue"
},
  "geometry": {"coordinates":[11.03716,50.978821],"type":"Point"}
}