{
  "type": "Feature",
  "properties": {
    "iso:country":"DE",
    "sg:address":"F\u00e4rberstr. 2",
    "sg:city":"B\u00f6ttingen",
    "sg:phone":"+49 7429/2384",
    "sg:postcode":"78583",
    "sg:province":"Baden-W\u00fcrttemberg",
    "wof:name":"M. Lehr",
    "wof:placetype":"venue"
},
  "geometry": {"coordinates":[8.8060512543,48.0998764038],"type":"Point"}
}