{
  "type": "Feature",
  "properties": {
    "iso:country":"DE",
    "sg:address":"Eching",
    "sg:city":"Moosinning",
    "sg:phone":"+49 8123/8313",
    "sg:postcode":"85452",
    "sg:province":"Bayern",
    "wof:name":"M. B\u00f6hm",
    "wof:placetype":"venue"
},
  "geometry": {"coordinates":[11.8538179398,48.2810707092],"type":"Point"}
}