{
  "type": "Feature",
  "properties": {
    "iso:country":"DE",
    "sg:address":"Alpenstr. 3",
    "sg:city":"Isen",
    "sg:postcode":"84424",
    "sg:province":"Bayern",
    "wof:name":"Michael Reutemann Ingenieur",
    "wof:placetype":"venue"
},
  "geometry": {"coordinates":[12.0304584503,48.1638832092],"type":"Point"}
}