{
  "type": "Feature",
  "properties": {
    "iso:country":"DE",
    "sg:address":"Rheinstr. 172",
    "sg:city":"Wilhelmshaven",
    "sg:phone":"+49 4421/202230",
    "sg:postcode":"26382",
    "sg:province":"Niedersachsen",
    "wof:name":"St.-willehad-apotheke",
    "wof:placetype":"venue"
},
  "geometry": {"coordinates":[8.105938,53.517857],"type":"Point"}
}