{
  "type": "Feature",
  "properties": {
    "iso:country":"DE",
    "sg:address":"Dicke Buche 10",
    "sg:city":"Kreuztal",
    "sg:phone":"+49 2732/89480",
    "sg:postcode":"57223",
    "sg:province":"Nordrhein-Westfalen",
    "wof:name":"Altenheimath\u00f6fe E. V.",
    "wof:placetype":"venue"
},
  "geometry": {"coordinates":[7.953859,50.995949],"type":"Point"}
}