{
  "type": "Feature",
  "properties": {
    "iso:country":"DE",
    "sg:address":"Bahnstr. 8",
    "sg:city":"Wiesbaden",
    "sg:phone":"+49 611/9742757",
    "sg:postcode":"65205",
    "sg:province":"Hessen",
    "wof:name":"Swn Intermedia Gmbh",
    "wof:placetype":"venue"
},
  "geometry": {"coordinates":[8.295952,50.05442],"type":"Point"}
}