{
  "type": "Feature",
  "properties": {
    "iso:country":"DE",
    "sg:address":"Torstr. 2",
    "sg:city":"D\u00f6mitz",
    "sg:postcode":"19303",
    "sg:province":"Mecklenburg-Vorpommern",
    "wof:name":"Deuruneft Deutsch-russische Mineral\u00f6lhandelsges. Mbh",
    "wof:placetype":"venue"
},
  "geometry": {"coordinates":[11.2481107712,53.1410446167],"type":"Point"}
}