{
  "type": "Feature",
  "properties": {
    "iso:country":"DE",
    "sg:address":"Ahrensdorfer Str. 4",
    "sg:city":"Vollersode",
    "sg:phone":"+49 4794/491",
    "sg:postcode":"27729",
    "sg:province":"Niedersachsen",
    "wof:name":"Johann Br\u00fcnjes",
    "wof:placetype":"venue"
},
  "geometry": {"coordinates":[8.929387,53.332596],"type":"Point"}
}