{
  "type": "Feature",
  "properties": {
    "iso:country":"DE",
    "sg:address":"Mittlerer Pfad 15::",
    "sg:city":"Stuttgart",
    "sg:phone":"+49 4971/19885",
    "sg:postcode":"70499",
    "sg:province":"Baden-W\u00fcrttemberg",
    "wof:name":"Schitag Ernst & Young Deutsche Allgemeine Treuhand Aktiengesellschaft Wirtschaftspruefungs",
    "wof:placetype":"venue"
},
  "geometry": {"coordinates":[9.095556,48.820175],"type":"Point"}
}