{
  "type": "Feature",
  "properties": {
    "iso:country":"DE",
    "sg:address":"Buxheimer Str. 82",
    "sg:city":"Memmingen",
    "sg:phone":"+49 8331/62031",
    "sg:postcode":"87700",
    "sg:province":"Bayern",
    "wof:name":"Dietrich Jaumann Architekt",
    "wof:placetype":"venue"
},
  "geometry": {"coordinates":[10.163672,47.991257],"type":"Point"}
}