{
  "type": "Feature",
  "properties": {
    "iso:country":"DE",
    "sg:address":"Fl\u00f6sserstr. 9",
    "sg:city":"Gau-Algesheim",
    "sg:phone":"+49 6725/4391",
    "sg:postcode":"55435",
    "sg:province":"Rheinland-Pfalz",
    "wof:name":"Dieter Ewald",
    "wof:placetype":"venue"
},
  "geometry": {"coordinates":[8.017187,49.956989],"type":"Point"}
}