{
  "type": "Feature",
  "properties": {
    "iso:country":"DE",
    "sg:address":"Habichtswalder Str. 19",
    "sg:city":"Kassel",
    "sg:phone":"+49 561/930940",
    "sg:postcode":"34119",
    "sg:province":"Hessen",
    "wof:name":"Manfred Hegger D. Hegger-luhnen",
    "wof:placetype":"venue"
},
  "geometry": {"coordinates":[9.450007,51.31868],"type":"Point"}
}