{
  "type": "Feature",
  "properties": {
    "iso:country":"DE",
    "sg:address":"Mittelstr. 82",
    "sg:city":"Gladbeck",
    "sg:phone":"+49 2043/22637",
    "sg:postcode":"45964",
    "sg:province":"Nordrhein-Westfalen",
    "wof:name":"G. Feilen",
    "wof:placetype":"venue"
},
  "geometry": {"coordinates":[6.984336,51.574844],"type":"Point"}
}