{
  "type": "Feature",
  "properties": {
    "iso:country":"DE",
    "sg:address":"Dorfstr. 5",
    "sg:city":"Steinach",
    "sg:phone":"+49 7832/8102",
    "sg:postcode":"77790",
    "sg:province":"Baden-W\u00fcrttemberg",
    "wof:name":"K. B. Vollmer Elektroinstallation",
    "wof:placetype":"venue"
},
  "geometry": {"coordinates":[8.01907,48.272552],"type":"Point"}
}