{
  "type": "Feature",
  "properties": {
    "iso:country":"DE",
    "sg:address":"Am Rathaus 2",
    "sg:city":"Weil am Rhein",
    "sg:phone":"+49 7621/98500",
    "sg:postcode":"79576",
    "sg:province":"Baden-W\u00fcrttemberg",
    "wof:name":"Invento Gmbh",
    "wof:placetype":"venue"
},
  "geometry": {"coordinates":[7.6121,47.593601],"type":"Point"}
}