{
  "type": "Feature",
  "properties": {
    "iso:country":"DE",
    "sg:address":"Wunsiedler Str. 2",
    "sg:city":"Kemnath",
    "sg:phone":"+49 9642/435",
    "sg:postcode":"95478",
    "sg:province":"Bayern",
    "wof:name":"E. Hahne",
    "wof:placetype":"venue"
},
  "geometry": {"coordinates":[11.8918743134,49.8713302612],"type":"Point"}
}