{
  "type": "Feature",
  "properties": {
    "iso:country":"DE",
    "sg:address":"Brunnengasse 12",
    "sg:city":"Naumburg",
    "sg:phone":"+49 3445/203307",
    "sg:postcode":"06618",
    "sg:province":"Sachsen-Anhalt",
    "wof:name":"Elektro Sattler",
    "wof:placetype":"venue"
},
  "geometry": {"coordinates":[11.820528,51.144073],"type":"Point"}
}