{
  "type": "Feature",
  "properties": {
    "iso:country":"DE",
    "sg:address":"Busdorfwall 24",
    "sg:city":"Paderborn",
    "sg:phone":"+49 5251/296347",
    "sg:postcode":"33098",
    "sg:province":"Nordrhein-Westfalen",
    "wof:name":"Bruno Surrey Rechtsanwalt",
    "wof:placetype":"venue"
},
  "geometry": {"coordinates":[8.7626829147,51.7181663513],"type":"Point"}
}