{
  "type": "Feature",
  "properties": {
    "iso:country":"DE",
    "sg:address":"Oskar-von-Miller-Ring 3",
    "sg:city":"M\u00fcnchen",
    "sg:phone":"+49 89/282728",
    "sg:postcode":"80333",
    "sg:province":"Bayern",
    "wof:name":"Marschner",
    "wof:placetype":"venue"
},
  "geometry": {"coordinates":[11.574271,48.14505],"type":"Point"}
}