{
  "type": "Feature",
  "properties": {
    "iso:country":"DE",
    "sg:address":"Katharinenstr. 51-53",
    "sg:city":"Mannheim",
    "sg:phone":"+49 621/842180",
    "sg:postcode":"68199",
    "sg:province":"Baden-W\u00fcrttemberg",
    "wof:name":"Puppet Promotion Gmbh",
    "wof:placetype":"venue"
},
  "geometry": {"coordinates":[8.4884967804,49.4564590454],"type":"Point"}
}