{
  "type": "Feature",
  "properties": {
    "iso:country":"DE",
    "sg:address":"Sch\u00fctzenstr. 58",
    "sg:city":"Traunstein",
    "sg:phone":"+49 861/15595",
    "sg:postcode":"83278",
    "sg:province":"Bayern",
    "wof:name":"Robert Geierstanger",
    "wof:placetype":"venue"
},
  "geometry": {"coordinates":[12.6474304199,47.8713111877],"type":"Point"}
}