{
  "type": "Feature",
  "properties": {
    "iso:country":"DE",
    "sg:address":"Heilbronner Str. 1",
    "sg:city":"Leinfelden-Echterdingen",
    "sg:phone":"+49 711/790840",
    "sg:postcode":"70771",
    "sg:province":"Baden-W\u00fcrttemberg",
    "wof:name":"Photo-studio 13 Gmbh",
    "wof:placetype":"venue"
},
  "geometry": {"coordinates":[9.1676301956,48.695854187],"type":"Point"}
}