{
  "type": "Feature",
  "properties": {
    "iso:country":"DE",
    "sg:address":"M\u00fchlenstr. 4",
    "sg:city":"Luckenwalde",
    "sg:phone":"+49 3371/632480",
    "sg:postcode":"14943",
    "sg:province":"Brandenburg",
    "wof:name":"F. Berg",
    "wof:placetype":"venue"
},
  "geometry": {"coordinates":[13.174779892,52.0918617249],"type":"Point"}
}