{
  "type": "Feature",
  "properties": {
    "iso:country":"DE",
    "sg:address":"Otto-Sendtner-Str. 12",
    "sg:city":"M\u00fcnchen",
    "sg:phone":"+49 89/325215",
    "sg:postcode":"80939",
    "sg:province":"Bayern",
    "wof:name":"Klaus M\u00fchlwitz",
    "wof:placetype":"venue"
},
  "geometry": {"coordinates":[11.632643,48.191597],"type":"Point"}
}