{
  "type": "Feature",
  "properties": {
    "iso:country":"DE",
    "sg:address":"Alpenblick 18",
    "sg:city":"P\u00f6cking",
    "sg:postcode":"82343",
    "sg:province":"Bayern",
    "wof:name":"Prostar Vertriebsgesellschaft F\u00fcr Elektronik Und Tele-",
    "wof:placetype":"venue"
},
  "geometry": {"coordinates":[11.2584257126,47.9650382996],"type":"Point"}
}