{
  "type": "Feature",
  "properties": {
    "iso:country":"DE",
    "sg:address":"Zaunk\u00f6nigweg 2",
    "sg:city":"Heidelberg",
    "sg:phone":"+49 6221/707910",
    "sg:postcode":"69123",
    "sg:province":"Baden-W\u00fcrttemberg",
    "wof:name":"Yakup Divrak Dolmetscherb\u00fcro",
    "wof:placetype":"venue"
},
  "geometry": {"coordinates":[8.643773,49.401718],"type":"Point"}
}