{
  "type": "Feature",
  "properties": {
    "iso:country":"DE",
    "sg:address":"Finkenried 5",
    "sg:city":"Norderstedt",
    "sg:phone":"+49 40/5217850",
    "sg:postcode":"22844",
    "sg:province":"Schleswig-Holstein",
    "wof:name":"Aqua-service Ohg",
    "wof:placetype":"venue"
},
  "geometry": {"coordinates":[10.004513,53.701859],"type":"Point"}
}