{
  "type": "Feature",
  "properties": {
    "iso:country":"DE",
    "sg:address":"Bernbergstr. 1",
    "sg:city":"Haiger",
    "sg:phone":"+49 2773/4475",
    "sg:postcode":"35708",
    "sg:province":"Hessen",
    "wof:name":"P. Lehr",
    "wof:placetype":"venue"
},
  "geometry": {"coordinates":[8.1745872498,50.7276115417],"type":"Point"}
}