{
  "type": "Feature",
  "properties": {
    "iso:country":"DE",
    "sg:address":"Grunewaldstr. 42",
    "sg:city":"Berlin",
    "sg:phone":"+49 30/2116167",
    "sg:postcode":"10825",
    "sg:province":"Berlin",
    "wof:name":"Horst Glasenapp",
    "wof:placetype":"venue"
},
  "geometry": {"coordinates":[13.342992,52.489033],"type":"Point"}
}