{
  "type": "Feature",
  "properties": {
    "iso:country":"DE",
    "sg:address":"Egerlandstr. 16",
    "sg:city":"Veitsh\u00f6chheim",
    "sg:phone":"+49 931/97316",
    "sg:postcode":"97209",
    "sg:province":"Bayern",
    "wof:name":"M. R. Radtke Gesellschaft F\u00fcr Biotechnologie-umweltgestalt.-",
    "wof:placetype":"venue"
},
  "geometry": {"coordinates":[9.891285,49.835854],"type":"Point"}
}