{
  "type": "Feature",
  "properties": {
    "iso:country":"DE",
    "sg:address":"Bahnhofstr 12",
    "sg:city":"Hechthausen",
    "sg:phone":"+49 4774/991114",
    "sg:postcode":"21755",
    "sg:province":"Niedersachsen",
    "wof:name":"Naturbau Joachim Gro\u00df",
    "wof:placetype":"venue"
},
  "geometry": {"coordinates":[9.235563,53.640392],"type":"Point"}
}