{
  "type": "Feature",
  "properties": {
    "iso:country":"DE",
    "sg:address":"Fasanenweg 10-12",
    "sg:city":"Salzgitter",
    "sg:phone":"+49 5341/6971",
    "sg:postcode":"38226",
    "sg:province":"Niedersachsen",
    "wof:name":"W. Wittal Kfz-reparatur Und Handel Gmbh",
    "wof:placetype":"venue"
},
  "geometry": {"coordinates":[10.33227,52.160278],"type":"Point"}
}