{
  "type": "Feature",
  "properties": {
    "iso:country":"DE",
    "sg:address":"Nibelungenstr. 9",
    "sg:city":"Lautertal",
    "sg:phone":"+49 6251/69814",
    "sg:postcode":"64686",
    "sg:province":"Hessen",
    "wof:name":"Horst Flath",
    "wof:placetype":"venue"
},
  "geometry": {"coordinates":[8.667446,49.699165],"type":"Point"}
}