{
  "type": "Feature",
  "properties": {
    "iso:country":"DE",
    "sg:address":"Wiethasestr. 19",
    "sg:city":"K\u00f6ln",
    "sg:phone":"+49 221/409006",
    "sg:postcode":"50933",
    "sg:province":"Nordrhein-Westfalen",
    "wof:name":"Paul Roscheck Inh. Stefan F. Ohm",
    "wof:placetype":"venue"
},
  "geometry": {"coordinates":[6.9012441635,50.9351806641],"type":"Point"}
}