{
  "type": "Feature",
  "properties": {
    "iso:country":"DE",
    "sg:address":"Pulverm\u00fchle",
    "sg:city":"Ruppichteroth",
    "sg:phone":"+49 2295/5332",
    "sg:postcode":"53809",
    "sg:province":"Nordrhein-Westfalen",
    "wof:name":"H. Vogel",
    "wof:placetype":"venue"
},
  "geometry": {"coordinates":[7.509437,50.853142],"type":"Point"}
}