{
  "type": "Feature",
  "properties": {
    "iso:country":"DE",
    "sg:address":"Berliner Chaussee 4",
    "sg:city":"Bad Muskau",
    "sg:postcode":"02953",
    "sg:province":"Sachsen",
    "wof:name":"Aldi Gmbh & Co. Kg",
    "wof:placetype":"venue"
},
  "geometry": {"coordinates":[14.7145061493,51.5509757996],"type":"Point"}
}