{
  "type": "Feature",
  "properties": {
    "iso:country":"DE",
    "sg:address":"Amtsgerichtstr. 6-8",
    "sg:city":"Regen",
    "sg:postcode":"94209",
    "sg:province":"Bayern",
    "wof:name":"Telecenter Regen Gmbh",
    "wof:placetype":"venue"
},
  "geometry": {"coordinates":[13.1275930405,48.971698761],"type":"Point"}
}