{
  "type": "Feature",
  "properties": {
    "iso:country":"DE",
    "sg:address":"Hermann-Hesse-Str. 64",
    "sg:city":"Berlin",
    "sg:phone":"+49 30/9172250",
    "sg:postcode":"13156",
    "sg:province":"Berlin",
    "wof:name":"Heide Diedrich",
    "wof:placetype":"venue"
},
  "geometry": {"coordinates":[13.3934278488,52.5766448975],"type":"Point"}
}