{
  "type": "Feature",
  "properties": {
    "iso:country":"DE",
    "sg:address":"Becherweg 34",
    "sg:city":"Berlin",
    "sg:phone":"+49 30/4964364",
    "sg:postcode":"13407",
    "sg:province":"Berlin",
    "wof:name":"Helmut Adolph",
    "wof:placetype":"venue"
},
  "geometry": {"coordinates":[13.344936,52.573166],"type":"Point"}
}