{
  "type": "Feature",
  "properties": {
    "iso:country":"DE",
    "sg:address":"Alte Parlerstr. 11",
    "sg:city":"N\u00fcrnberg",
    "sg:phone":"+49 911/335796",
    "sg:postcode":"90425",
    "sg:province":"Bayern",
    "wof:name":"Willi Berschinski E. K.",
    "wof:placetype":"venue"
},
  "geometry": {"coordinates":[11.042383,49.470402],"type":"Point"}
}