{
  "type": "Feature",
  "properties": {
    "iso:country":"DE",
    "sg:address":"Engerstr. 37",
    "sg:city":"Kempen",
    "sg:phone":"+49 2152/510947",
    "sg:postcode":"47906",
    "sg:province":"Nordrhein-Westfalen",
    "wof:name":"Boves Chic Mit Strick Inh. Hans-gerd Boves",
    "wof:placetype":"venue"
},
  "geometry": {"coordinates":[6.4227080345,51.3644599915],"type":"Point"}
}