{
  "type": "Feature",
  "properties": {
    "iso:country":"DE",
    "sg:address":"Alleestr. 13",
    "sg:city":"M\u00f6nchengladbach",
    "sg:phone":"+49 2161/41296",
    "sg:postcode":"41061",
    "sg:province":"Nordrhein-Westfalen",
    "wof:name":"Allee Grill",
    "wof:placetype":"venue"
},
  "geometry": {"coordinates":[6.4475240707,51.1906356812],"type":"Point"}
}