{
  "type": "Feature",
  "properties": {
    "iso:country":"DE",
    "sg:address":"Bahnhofsallee 24",
    "sg:city":"Hildesheim",
    "sg:phone":"+49 5121/511610",
    "sg:postcode":"31134",
    "sg:province":"Niedersachsen",
    "wof:name":"Albert Schur",
    "wof:placetype":"venue"
},
  "geometry": {"coordinates":[9.9535570145,52.1588134766],"type":"Point"}
}