{
  "type": "Feature",
  "properties": {
    "iso:country":"DE",
    "sg:address":"Schumannstr. 3",
    "sg:city":"Willich",
    "sg:phone":"+49 2154/2107",
    "sg:postcode":"47877",
    "sg:province":"Nordrhein-Westfalen",
    "wof:name":"Bernd Neuhaus Steuerberater",
    "wof:placetype":"venue"
},
  "geometry": {"coordinates":[6.5436968803,51.2630233765],"type":"Point"}
}