{
  "type": "Feature",
  "properties": {
    "iso:country":"DE",
    "sg:address":"Schrotsdorf 12",
    "sg:city":"Offenhausen",
    "sg:phone":"+49 9158/752",
    "sg:postcode":"91238",
    "sg:province":"Bayern",
    "wof:name":"Werner Wendler",
    "wof:placetype":"venue"
},
  "geometry": {"coordinates":[11.4003925323,49.4542121887],"type":"Point"}
}