{
  "type": "Feature",
  "properties": {
    "iso:country":"DE",
    "sg:address":"Hamburger Str. 53",
    "sg:city":"Lenzen",
    "sg:phone":"+49 38792/1588",
    "sg:postcode":"19309",
    "sg:province":"Brandenburg",
    "wof:name":"A. Haag",
    "wof:placetype":"venue"
},
  "geometry": {"coordinates":[11.474776,53.091179],"type":"Point"}
}