{
  "type": "Feature",
  "properties": {
    "iso:country":"DE",
    "sg:address":"Kurze Str. 4",
    "sg:city":"Fuldabr\u00fcck",
    "sg:postcode":"34277",
    "sg:province":"Hessen",
    "wof:name":"Scs Dienstleistungs Gmbh",
    "wof:placetype":"venue"
},
  "geometry": {"coordinates":[9.499710083,51.2645454407],"type":"Point"}
}