{
  "type": "Feature",
  "properties": {
    "iso:country":"DE",
    "sg:address":"Kleinb\u00fcchlberg",
    "sg:city":"Mitterteich",
    "sg:phone":"+49 9633/4328",
    "sg:postcode":"95666",
    "sg:province":"Bayern",
    "wof:name":"Monika Gmeiner",
    "wof:placetype":"venue"
},
  "geometry": {"coordinates":[12.214717,49.957966],"type":"Point"}
}