{
  "type": "Feature",
  "properties": {
    "iso:country":"DE",
    "sg:address":"Klasingstr. 1-11",
    "sg:city":"Bielefeld",
    "sg:postcode":"33602",
    "sg:province":"Nordrhein-Westfalen",
    "wof:name":"Flexi",
    "wof:placetype":"venue"
},
  "geometry": {"coordinates":[8.527707,52.019775],"type":"Point"}
}