{
  "type": "Feature",
  "properties": {
    "iso:country":"DE",
    "sg:address":"Gro\u00dfe Str. 35",
    "sg:city":"Bad Iburg",
    "sg:phone":"+49 5403/2288",
    "sg:postcode":"49186",
    "sg:province":"Niedersachsen",
    "wof:name":"Textilhaus Osterm\u00f6ller Kg",
    "wof:placetype":"venue"
},
  "geometry": {"coordinates":[8.045059,52.15583],"type":"Point"}
}