{
  "type": "Feature",
  "properties": {
    "iso:country":"DE",
    "sg:address":"Wettersteinstr. 24",
    "sg:city":"Neuried",
    "sg:phone":"+49 89/751887",
    "sg:postcode":"82061",
    "sg:province":"Bayern",
    "wof:name":"Franz Schattenkirchner",
    "wof:placetype":"venue"
},
  "geometry": {"coordinates":[11.472783,48.087135],"type":"Point"}
}