{
  "type": "Feature",
  "properties": {
    "iso:country":"DE",
    "sg:address":"Kirchstr. 2",
    "sg:city":"Breidenbach",
    "sg:phone":"+49 6465/1356",
    "sg:postcode":"35236",
    "sg:province":"Hessen",
    "wof:name":"Friedrich Weigel",
    "wof:placetype":"venue"
},
  "geometry": {"coordinates":[8.430432,50.885548],"type":"Point"}
}