{
  "type": "Feature",
  "properties": {
    "iso:country":"DE",
    "sg:address":"Eugen-Adolff-Str. 116",
    "sg:city":"Backnang",
    "sg:phone":"+49 7191/65135",
    "sg:postcode":"71522",
    "sg:province":"Baden-W\u00fcrttemberg",
    "wof:name":"Internart Gmbh",
    "wof:placetype":"venue"
},
  "geometry": {"coordinates":[9.445333,48.945477],"type":"Point"}
}