{
  "type": "Feature",
  "properties": {
    "iso:country":"DE",
    "sg:address":"Kaiserstr. 11",
    "sg:city":"W\u00fcrselen",
    "sg:phone":"+49 2405/2543",
    "sg:postcode":"52146",
    "sg:province":"Nordrhein-Westfalen",
    "wof:name":"Bistro K 11",
    "wof:placetype":"venue"
},
  "geometry": {"coordinates":[6.1319937706,50.8188095093],"type":"Point"}
}