{
  "type": "Feature",
  "properties": {
    "iso:country":"DE",
    "sg:address":"Ebersbach 18",
    "sg:city":"Kleinschmalkalden",
    "sg:phone":"+49 36849/21506",
    "sg:postcode":"98593",
    "sg:province":"Th\u00fcringen",
    "wof:name":"Hubert Venter",
    "wof:placetype":"venue"
},
  "geometry": {"coordinates":[10.4774961472,50.8002433777],"type":"Point"}
}