{
  "type": "Feature",
  "properties": {
    "iso:country":"DE",
    "sg:address":"Hermann-L\u00f6ns-Str. 27",
    "sg:city":"Ostrhauderfehn",
    "sg:phone":"+49 4952/5986",
    "sg:postcode":"26842",
    "sg:province":"Niedersachsen",
    "wof:name":"L. Und G. Saathoff Heissmangelbetrieb",
    "wof:placetype":"venue"
},
  "geometry": {"coordinates":[7.6164050102,53.1449737549],"type":"Point"}
}