{
  "type": "Feature",
  "properties": {
    "iso:country":"DE",
    "sg:address":"M\u00fchlenstr. 2",
    "sg:city":"Roetgen",
    "sg:phone":"+49 2471/4633",
    "sg:postcode":"52159",
    "sg:province":"Nordrhein-Westfalen",
    "wof:name":"Incla Consult Gmbh",
    "wof:placetype":"venue"
},
  "geometry": {"coordinates":[6.1780471802,50.6441268921],"type":"Point"}
}