{
  "type": "Feature",
  "properties": {
    "iso:country":"DE",
    "sg:address":"Kornmarkt 3",
    "sg:city":"Biersdorf am See",
    "sg:phone":"+49 6569/464",
    "sg:postcode":"54636",
    "sg:province":"Rheinland-Pfalz",
    "wof:name":"Hotel Haus Kornmarkt",
    "wof:placetype":"venue"
},
  "geometry": {"coordinates":[6.4517550468,50.0180969238],"type":"Point"}
}