{
  "type": "Feature",
  "properties": {
    "iso:country":"DE",
    "sg:address":"Lindenstr. 128",
    "sg:city":"M\u00f6nchengladbach",
    "sg:phone":"+49 2161/894825",
    "sg:postcode":"41063",
    "sg:province":"Nordrhein-Westfalen",
    "wof:name":"Club Bar",
    "wof:placetype":"venue"
},
  "geometry": {"coordinates":[6.420501,51.202232],"type":"Point"}
}