{
  "type": "Feature",
  "properties": {
    "iso:country":"DE",
    "sg:address":"Volmerswerther Str. 173",
    "sg:city":"D\u00fcsseldorf",
    "sg:phone":"+49 211/307950",
    "sg:postcode":"40221",
    "sg:province":"Nordrhein-Westfalen",
    "wof:name":"Erotic-navigator",
    "wof:placetype":"venue"
},
  "geometry": {"coordinates":[6.761584,51.201614],"type":"Point"}
}