{
  "type": "Feature",
  "properties": {
    "iso:country":"DE",
    "sg:address":"Hans-Klopfer-Weg 5",
    "sg:city":"Amberg",
    "sg:phone":"+49 9621/22755",
    "sg:postcode":"92224",
    "sg:province":"Bayern",
    "wof:name":"Georg Hirsch Architekt",
    "wof:placetype":"venue"
},
  "geometry": {"coordinates":[11.859714,49.45266],"type":"Point"}
}