{
  "type": "Feature",
  "properties": {
    "iso:country":"DE",
    "sg:address":"Theodor-Storm-Str. 2",
    "sg:city":"T\u00fcbingen",
    "sg:phone":"+49 7071/73594",
    "sg:postcode":"72070",
    "sg:province":"Baden-W\u00fcrttemberg",
    "wof:name":"Karl-heinz Helle",
    "wof:placetype":"venue"
},
  "geometry": {"coordinates":[8.991312027,48.5012054443],"type":"Point"}
}