{
  "type": "Feature",
  "properties": {
    "iso:country":"DE",
    "sg:address":"Herrenbreite 17",
    "sg:city":"Wolfenb\u00fcttel",
    "sg:phone":"+49 5331/31227",
    "sg:postcode":"38302",
    "sg:province":"Niedersachsen",
    "wof:name":"Vogt Ingenieur",
    "wof:placetype":"venue"
},
  "geometry": {"coordinates":[10.5499925613,52.1763534546],"type":"Point"}
}