{
  "type": "Feature",
  "properties": {
    "iso:country":"DE",
    "sg:address":"Im Leh 6",
    "sg:city":"L\u00f6rrach",
    "sg:phone":"+49 7621/51523",
    "sg:postcode":"79541",
    "sg:province":"Baden-W\u00fcrttemberg",
    "wof:name":"W. Meinzer",
    "wof:placetype":"venue"
},
  "geometry": {"coordinates":[7.7015209198,47.64427948],"type":"Point"}
}