{
  "type": "Feature",
  "properties": {
    "iso:country":"DE",
    "sg:address":"Klosterstr. 4",
    "sg:city":"Gerolstein",
    "sg:phone":"+49 6591/3389",
    "sg:postcode":"54568",
    "sg:province":"Rheinland-Pfalz",
    "wof:name":"Felix M\u00fcller",
    "wof:placetype":"venue"
},
  "geometry": {"coordinates":[6.639781,50.215988],"type":"Point"}
}