{
  "type": "Feature",
  "properties": {
    "iso:country":"DE",
    "sg:address":"Am Jochenstein 10",
    "sg:city":"Untergriesbach",
    "sg:phone":"+49 8591/1802",
    "sg:postcode":"94107",
    "sg:province":"Bayern",
    "wof:name":"Gasthaus Ludwig Kornexl",
    "wof:placetype":"venue"
},
  "geometry": {"coordinates":[13.7149000168,48.517364502],"type":"Point"}
}