{
  "type": "Feature",
  "properties": {
    "iso:country":"DE",
    "sg:address":"Friedensstr. 3",
    "sg:city":"Kaarst",
    "sg:phone":"+49 2131/68620",
    "sg:postcode":"41564",
    "sg:province":"Nordrhein-Westfalen",
    "wof:name":"Eiscafe M. Pastorelli",
    "wof:placetype":"venue"
},
  "geometry": {"coordinates":[6.6169,51.231728],"type":"Point"}
}