{
  "type": "Feature",
  "properties": {
    "iso:country":"DE",
    "sg:address":"Seestr. 14",
    "sg:city":"B\u00f6rgerende",
    "sg:phone":"+49 38203/81245",
    "sg:postcode":"18211",
    "sg:province":"Mecklenburg-Vorpommern",
    "wof:name":"Heimatstube B\u00f6rgerende- Rethwisch",
    "wof:placetype":"venue"
},
  "geometry": {"coordinates":[11.89913,54.147022],"type":"Point"}
}