{
  "type": "Feature",
  "properties": {
    "iso:country":"DE",
    "sg:address":"Auf dem Fu\u00dfberg 11",
    "sg:city":"Kreuzau",
    "sg:phone":"+49 2422/901411",
    "sg:postcode":"52372",
    "sg:province":"Nordrhein-Westfalen",
    "wof:name":"R. Reuscher Steuerberater",
    "wof:placetype":"venue"
},
  "geometry": {"coordinates":[6.4355220795,50.719291687],"type":"Point"}
}