{
  "type": "Feature",
  "properties": {
    "iso:country":"DE",
    "sg:address":"Taunusstr. 26",
    "sg:city":"Butzbach",
    "sg:phone":"+49 6033/5393",
    "sg:postcode":"35510",
    "sg:province":"Hessen",
    "wof:name":"O. Und Evelyn Hofmann",
    "wof:placetype":"venue"
},
  "geometry": {"coordinates":[8.6648330688,50.4311103821],"type":"Point"}
}