{
  "type": "Feature",
  "properties": {
    "iso:country":"DE",
    "sg:address":"Breite Gasse 2",
    "sg:city":"N\u00fcrnberg",
    "sg:phone":"+49 911/9921470",
    "sg:postcode":"90402",
    "sg:province":"Bayern",
    "wof:name":"D2-shop",
    "wof:placetype":"venue"
},
  "geometry": {"coordinates":[11.0776128769,49.4502029419],"type":"Point"}
}