{
  "type": "Feature",
  "properties": {
    "iso:country":"DE",
    "sg:address":"Schwendistr. 21",
    "sg:city":"Freiburg",
    "sg:phone":"+49 761/32468",
    "sg:postcode":"79102",
    "sg:province":"Baden-W\u00fcrttemberg",
    "wof:name":"Ch. Sihler-metzger",
    "wof:placetype":"venue"
},
  "geometry": {"coordinates":[7.8632459641,47.9898071289],"type":"Point"}
}