{
  "type": "Feature",
  "properties": {
    "iso:country":"DE",
    "sg:address":"Nikolastr. 36",
    "sg:city":"Landshut",
    "sg:phone":"+49 871/965580",
    "sg:postcode":"84034",
    "sg:province":"Bayern",
    "wof:name":"Zms-ziegel-marketing Und Service- Gmbh",
    "wof:placetype":"venue"
},
  "geometry": {"coordinates":[12.1421957016,48.5438041687],"type":"Point"}
}