{
  "type": "Feature",
  "properties": {
    "iso:country":"DE",
    "sg:address":"Langendorfer Str. 138",
    "sg:city":"Neuwied",
    "sg:phone":"+49 2631/353862",
    "sg:postcode":"56564",
    "sg:province":"Rheinland-Pfalz",
    "wof:name":"Eckard Ferger Architekt",
    "wof:placetype":"venue"
},
  "geometry": {"coordinates":[7.459686,50.428722],"type":"Point"}
}