{
  "type": "Feature",
  "properties": {
    "iso:country":"DE",
    "sg:address":"S\u00fcdring 100",
    "sg:city":"Rodenbach",
    "sg:phone":"+49 6184/51148",
    "sg:postcode":"63517",
    "sg:province":"Hessen",
    "wof:name":"H. Engelmann",
    "wof:placetype":"venue"
},
  "geometry": {"coordinates":[9.03563,50.13739],"type":"Point"}
}