{
  "type": "Feature",
  "properties": {
    "iso:country":"DE",
    "sg:address":"Wollgrasweg 37",
    "sg:city":"Stuttgart",
    "sg:phone":"+49 711/4587797",
    "sg:postcode":"70599",
    "sg:province":"Baden-W\u00fcrttemberg",
    "wof:name":"Wohn- Und Polsterwelt",
    "wof:placetype":"venue"
},
  "geometry": {"coordinates":[9.2002716064,48.7099571228],"type":"Point"}
}