{
  "type": "Feature",
  "properties": {
    "iso:country":"DE",
    "sg:address":"Weststr. 33-37",
    "sg:city":"Minden",
    "sg:phone":"+49 571/946080",
    "sg:postcode":"32425",
    "sg:province":"Nordrhein-Westfalen",
    "wof:name":"August Rathert & Sohn Baustoffe Und Transporte",
    "wof:placetype":"venue"
},
  "geometry": {"coordinates":[8.892793,52.34079],"type":"Point"}
}