{
  "type": "Feature",
  "properties": {
    "iso:country":"DE",
    "sg:address":"Pfarrer-Baumann-Str. 7",
    "sg:city":"Oberaurach",
    "sg:phone":"+49 9529/981024",
    "sg:postcode":"97514",
    "sg:province":"Bayern",
    "wof:name":"Fritz Gehrig",
    "wof:placetype":"venue"
},
  "geometry": {"coordinates":[10.598931,49.94743],"type":"Point"}
}