{
  "type": "Feature",
  "properties": {
    "iso:country":"DE",
    "sg:address":"Ohrsleber Weg 5 A",
    "sg:city":"Sch\u00f6ningen",
    "sg:phone":"+49 5352/2080",
    "sg:postcode":"38364",
    "sg:province":"Niedersachsen",
    "wof:name":"Metrofunkkabel-union Gmbh",
    "wof:placetype":"venue"
},
  "geometry": {"coordinates":[10.9727592468,52.1301689148],"type":"Point"}
}