{
  "type": "Feature",
  "properties": {
    "iso:country":"DE",
    "sg:address":"Otto-Hahn-Str. 12",
    "sg:city":"Lampertheim",
    "sg:phone":"+49 6206/2252",
    "sg:postcode":"68623",
    "sg:province":"Hessen",
    "wof:name":"Oberfeld Reisen",
    "wof:placetype":"venue"
},
  "geometry": {"coordinates":[8.4846849442,49.5981750488],"type":"Point"}
}