{
  "type": "Feature",
  "properties": {
    "iso:country":"DE",
    "sg:address":"Bahnhofstr. 38",
    "sg:city":"Rohrbach",
    "sg:postcode":"85296",
    "sg:province":"Bayern",
    "wof:name":"Ilmtaler \u00d6lm\u00fchle Gmbh",
    "wof:placetype":"venue"
},
  "geometry": {"coordinates":[11.5719213486,48.6044960022],"type":"Point"}
}