{
  "type": "Feature",
  "properties": {
    "iso:country":"DE",
    "sg:address":"Kreuzstr. 7-9",
    "sg:city":"Bielefeld",
    "sg:phone":"+49 521/173726",
    "sg:postcode":"33602",
    "sg:province":"Nordrhein-Westfalen",
    "wof:name":"Fingernadelstudio Beauty Nails",
    "wof:placetype":"venue"
},
  "geometry": {"coordinates":[8.5305814743,52.0160255432],"type":"Point"}
}