{
  "type": "Feature",
  "properties": {
    "iso:country":"DE",
    "sg:address":"Korbinianstr. 7",
    "sg:city":"W\u00f6rth",
    "sg:phone":"+49 8123/8528",
    "sg:postcode":"85457",
    "sg:province":"Bayern",
    "wof:name":"Ps-hochbauelemente Gmbh",
    "wof:placetype":"venue"
},
  "geometry": {"coordinates":[11.8789777756,48.2489089966],"type":"Point"}
}