{
  "type": "Feature",
  "properties": {
    "iso:country":"DE",
    "sg:address":"Obere Sehlhofstr. 22",
    "sg:city":"Wuppertal",
    "sg:postcode":"42289",
    "sg:province":"Nordrhein-Westfalen",
    "wof:name":"Netzkern Gmbh",
    "wof:placetype":"venue"
},
  "geometry": {"coordinates":[7.210296154,51.270488739],"type":"Point"}
}