{
  "type": "Feature",
  "properties": {
    "iso:country":"DE",
    "sg:address":"Wei\u00dfdornpfad 42",
    "sg:city":"Bremen",
    "sg:phone":"+49 421/256287",
    "sg:postcode":"28355",
    "sg:province":"Bremen",
    "wof:name":"K\u00fcllmer Taxenbetrieb Ohg",
    "wof:placetype":"venue"
},
  "geometry": {"coordinates":[8.9008598328,53.0975646973],"type":"Point"}
}