{
  "type": "Feature",
  "properties": {
    "iso:country":"DE",
    "sg:address":"Lindenweg 2",
    "sg:city":"Pohrsdorf",
    "sg:phone":"+49 35203/30265",
    "sg:postcode":"01737",
    "sg:province":"Sachsen",
    "wof:name":"Friedrich Erben",
    "wof:placetype":"venue"
},
  "geometry": {"coordinates":[13.5299510956,50.9985656738],"type":"Point"}
}