{
  "type": "Feature",
  "properties": {
    "iso:country":"DE",
    "sg:address":"Handwerkerstr 2-4",
    "sg:city":"Wesel",
    "sg:phone":"+49 281/966630",
    "sg:postcode":"46485",
    "sg:province":"Nordrhein-Westfalen",
    "wof:name":"Concept Projekt Ltd",
    "wof:placetype":"venue"
},
  "geometry": {"coordinates":[6.626760006,51.6751098633],"type":"Point"}
}