{
  "type": "Feature",
  "properties": {
    "iso:country":"DE",
    "sg:address":"Leibnizstr. 18",
    "sg:city":"B\u00f6blingen",
    "sg:phone":"+49 7031/419595",
    "sg:postcode":"71032",
    "sg:province":"Baden-W\u00fcrttemberg",
    "wof:name":"Dream-bowl B\u00f6blingen Ohg",
    "wof:placetype":"venue"
},
  "geometry": {"coordinates":[9.0171499252,48.6957893372],"type":"Point"}
}