{
  "type": "Feature",
  "properties": {
    "iso:country":"DE",
    "sg:address":"J\u00fcdenstr. 12",
    "sg:city":"G\u00f6ttingen",
    "sg:phone":"+49 551/57157",
    "sg:postcode":"37073",
    "sg:province":"Niedersachsen",
    "wof:name":"Central-hotel G\u00f6ttingen Albert Fette",
    "wof:placetype":"venue"
},
  "geometry": {"coordinates":[9.9365301132,51.5339241028],"type":"Point"}
}