{
  "type": "Feature",
  "properties": {
    "iso:country":"DE",
    "sg:address":"Hoorwaldstr. 42",
    "sg:city":"Burbach",
    "sg:phone":"+49 4927/3629500",
    "sg:postcode":"57299",
    "sg:province":"Nordrhein-Westfalen",
    "wof:name":"Zeidler & Uhl Gmbh",
    "wof:placetype":"venue"
},
  "geometry": {"coordinates":[8.132532,50.732315],"type":"Point"}
}