{
  "type": "Feature",
  "properties": {
    "iso:country":"DE",
    "sg:address":"Herweghstr. 20",
    "sg:city":"Dresden",
    "sg:phone":"+49 351/4210726",
    "sg:postcode":"01157",
    "sg:province":"Sachsen",
    "wof:name":"Detlef Reimer",
    "wof:placetype":"venue"
},
  "geometry": {"coordinates":[13.669574,51.062298],"type":"Point"}
}