{
  "type": "Feature",
  "properties": {
    "iso:country":"DE",
    "sg:address":"Pasteurstr.53",
    "sg:city":"M\u00fcnchen",
    "sg:postcode":"80997",
    "sg:province":"Bayern",
    "wof:name":"Folio Folienbeschriftung",
    "wof:placetype":"venue"
},
  "geometry": {"coordinates":[11.465924,48.20372],"type":"Point"}
}