{
  "type": "Feature",
  "properties": {
    "iso:country":"DE",
    "sg:address":"Rosengasse 2",
    "sg:city":"Burtenbach",
    "sg:phone":"+49 8285/1518",
    "sg:postcode":"89349",
    "sg:province":"Bayern",
    "wof:name":"F. \u00d6zcakir",
    "wof:placetype":"venue"
},
  "geometry": {"coordinates":[10.446672,48.338272],"type":"Point"}
}