{
  "type": "Feature",
  "properties": {
    "iso:country":"DE",
    "sg:address":"K\u00f6nigstr. 68",
    "sg:city":"Rottenburg",
    "sg:phone":"+49 7472/26103",
    "sg:postcode":"72108",
    "sg:province":"Baden-W\u00fcrttemberg",
    "wof:name":"Chinarestaurant Hongkong Gmbh",
    "wof:placetype":"venue"
},
  "geometry": {"coordinates":[8.9311666489,48.4748649597],"type":"Point"}
}