{
  "type": "Feature",
  "properties": {
    "iso:country":"DE",
    "sg:address":"Im Schemmerfeld 2",
    "sg:city":"Waldkappel",
    "sg:phone":"+49 5656/4432",
    "sg:postcode":"37284",
    "sg:province":"Hessen",
    "wof:name":"Haus Anna-katharina",
    "wof:placetype":"venue"
},
  "geometry": {"coordinates":[9.870629,51.141319],"type":"Point"}
}