{
  "type": "Feature",
  "properties": {
    "iso:country":"DE",
    "sg:address":"Garstedter Weg 16",
    "sg:city":"Hasloh",
    "sg:phone":"+49 4106/2875",
    "sg:postcode":"25474",
    "sg:province":"Schleswig-Holstein",
    "wof:name":"Heinz Kruse",
    "wof:placetype":"venue"
},
  "geometry": {"coordinates":[9.915885,53.69043],"type":"Point"}
}