{
  "type": "Feature",
  "properties": {
    "iso:country":"DE",
    "sg:address":"Edisonstr 11",
    "sg:city":"Unterschlei\u00dfheim",
    "sg:phone":"+49 89/3214700",
    "sg:postcode":"85716",
    "sg:province":"Bayern",
    "wof:name":"X-medianet Gmbh",
    "wof:placetype":"venue"
},
  "geometry": {"coordinates":[11.566786,48.284988],"type":"Point"}
}