{
  "type": "Feature",
  "properties": {
    "iso:country":"DE",
    "sg:address":"Am Taubenfeld 12",
    "sg:city":"Heidelberg",
    "sg:phone":"+49 6221/830518",
    "sg:postcode":"69123",
    "sg:province":"Baden-W\u00fcrttemberg",
    "wof:name":"Markus Cieluch Ingenieur",
    "wof:placetype":"venue"
},
  "geometry": {"coordinates":[8.642001152,49.4282455444],"type":"Point"}
}