{
  "type": "Feature",
  "properties": {
    "iso:country":"DE",
    "sg:address":"Hohenbrunner Weg 112",
    "sg:city":"Taufkirchen",
    "sg:phone":"+49 89/6371919",
    "sg:postcode":"82024",
    "sg:province":"Bayern",
    "wof:name":"D. Huber",
    "wof:placetype":"venue"
},
  "geometry": {"coordinates":[11.628256,48.041546],"type":"Point"}
}