{
  "type": "Feature",
  "properties": {
    "iso:country":"DE",
    "sg:address":"M\u00fclhauser Winkel 14",
    "sg:city":"Mannheim",
    "sg:phone":"+49 621/471843",
    "sg:postcode":"68229",
    "sg:province":"Baden-W\u00fcrttemberg",
    "wof:name":"Heinrich Zipf Archtitekt",
    "wof:placetype":"venue"
},
  "geometry": {"coordinates":[8.583028,49.438255],"type":"Point"}
}