{
  "type": "Feature",
  "properties": {
    "iso:country":"DE",
    "sg:address":"G\u00fcnzburger Str. 37",
    "sg:city":"Ichenhausen",
    "sg:phone":"+49 8223/960398",
    "sg:postcode":"89335",
    "sg:province":"Bayern",
    "wof:name":"Dr. Max Schubert Tierarzt",
    "wof:placetype":"venue"
},
  "geometry": {"coordinates":[10.3087368011,48.3729019165],"type":"Point"}
}