{
  "type": "Feature",
  "properties": {
    "iso:country":"DE",
    "sg:address":"Unterheydenerstr.30",
    "sg:city":"M\u00f6nchengladbach",
    "sg:phone":"+49 4921/6645850",
    "sg:postcode":"41236",
    "sg:province":"Nordrhein-Westfalen",
    "wof:name":"Anton Schneider S\u00d6hne Gmbh & Co. Kg",
    "wof:placetype":"venue"
},
  "geometry": {"coordinates":[6.450817,51.156868],"type":"Point"}
}