{
  "type": "Feature",
  "properties": {
    "iso:country":"DE",
    "sg:address":"G\u00f6penstr. 34",
    "sg:city":"Sangerhausen",
    "sg:phone":"+49 3464/578561",
    "sg:postcode":"06526",
    "sg:province":"Sachsen-Anhalt",
    "wof:name":"Manfred Liebsch Sport-center",
    "wof:placetype":"venue"
},
  "geometry": {"coordinates":[11.2976112366,51.4752922058],"type":"Point"}
}