{
  "type": "Feature",
  "properties": {
    "iso:country":"DE",
    "sg:address":"Schlesische Str. 38",
    "sg:city":"Berlin",
    "sg:phone":"+49 30/61702577",
    "sg:postcode":"10997",
    "sg:province":"Berlin",
    "wof:name":"Schulz & Co. Naturbaustoffe In Berlin Ohg",
    "wof:placetype":"venue"
},
  "geometry": {"coordinates":[13.444564,52.49987],"type":"Point"}
}