{
  "type": "Feature",
  "properties": {
    "iso:country":"DE",
    "sg:address":"Kaltenborner Str. 32-34",
    "sg:city":"Guben",
    "sg:postcode":"03172",
    "sg:province":"Brandenburg",
    "wof:name":"R & S China Food Importhandel Gmbh",
    "wof:placetype":"venue"
},
  "geometry": {"coordinates":[14.7084436417,51.9438400269],"type":"Point"}
}