{
  "type": "Feature",
  "properties": {
    "iso:country":"DE",
    "sg:address":"Niederwall 53",
    "sg:city":"Bielefeld",
    "sg:phone":"+49 521/5950",
    "sg:postcode":"33602",
    "sg:province":"Nordrhein-Westfalen",
    "wof:name":"Redaktion F\u00f6rderwerk K\u00f6nigstein Programm",
    "wof:placetype":"venue"
},
  "geometry": {"coordinates":[8.5336923599,52.0175018311],"type":"Point"}
}