{
  "type": "Feature",
  "properties": {
    "iso:country":"DE",
    "sg:address":"Arnoweg 4",
    "sg:city":"Teisendorf",
    "sg:phone":"+49 8666/6491",
    "sg:postcode":"83317",
    "sg:province":"Bayern",
    "wof:name":"Sporer & Probst Verwaltungs Gmbh",
    "wof:placetype":"venue"
},
  "geometry": {"coordinates":[12.8171348572,47.8502693176],"type":"Point"}
}