{
  "type": "Feature",
  "properties": {
    "iso:country":"DE",
    "sg:address":"Gro\u00dfe Austr. 21 a",
    "sg:city":"Gaggenau",
    "sg:phone":"+49 7225/1347",
    "sg:postcode":"76571",
    "sg:province":"Baden-W\u00fcrttemberg",
    "wof:name":"Karlheinz Heck",
    "wof:placetype":"venue"
},
  "geometry": {"coordinates":[8.308811,48.81255],"type":"Point"}
}