{
  "type": "Feature",
  "properties": {
    "iso:country":"DE",
    "sg:address":"Markt 3",
    "sg:city":"Crimmitschau",
    "sg:phone":"+49 3762/938193",
    "sg:postcode":"08451",
    "sg:province":"Sachsen",
    "wof:name":"City-apotheke",
    "wof:placetype":"venue"
},
  "geometry": {"coordinates":[12.386667,50.8162],"type":"Point"}
}