{
  "type": "Feature",
  "properties": {
    "iso:country":"DE",
    "sg:address":"Rosa-Luxemburg-Str. 14",
    "sg:city":"Markkleeberg",
    "sg:phone":"+49 341/3017460",
    "sg:postcode":"04416",
    "sg:province":"Sachsen",
    "wof:name":"K.-h. Glatz",
    "wof:placetype":"venue"
},
  "geometry": {"coordinates":[12.362335,51.279793],"type":"Point"}
}