{
  "type": "Feature",
  "properties": {
    "iso:country":"DE",
    "sg:address":"Veer\u00dfer Str. 53",
    "sg:city":"Uelzen",
    "sg:phone":"+49 581/82166",
    "sg:postcode":"29525",
    "sg:province":"Niedersachsen",
    "wof:name":"Kreisarchiv",
    "wof:placetype":"venue"
},
  "geometry": {"coordinates":[10.556797,52.961113],"type":"Point"}
}