{
  "type": "Feature",
  "properties": {
    "iso:country":"DE",
    "sg:address":"Forststr. 7",
    "sg:city":"Neustadt",
    "sg:phone":"+49 9445/7822",
    "sg:postcode":"93333",
    "sg:province":"Bayern",
    "wof:name":"Josef Enzinger",
    "wof:placetype":"venue"
},
  "geometry": {"coordinates":[13.763045,51.065403],"type":"Point"}
}