{
  "type": "Feature",
  "properties": {
    "iso:country":"DE",
    "sg:address":"Grafenberger Allee 56",
    "sg:city":"D\u00fcsseldorf",
    "sg:phone":"+49 211/679700",
    "sg:postcode":"40212",
    "sg:province":"Nordrhein-Westfalen",
    "wof:name":"Chemical Bank Ag",
    "wof:placetype":"venue"
},
  "geometry": {"coordinates":[6.800155,51.230473],"type":"Point"}
}