{
  "type": "Feature",
  "properties": {
    "iso:country":"DE",
    "sg:address":"Wittinger Str. 120",
    "sg:city":"Diesdorf",
    "sg:phone":"+49 3902/287",
    "sg:postcode":"29413",
    "sg:province":"Sachsen-Anhalt",
    "wof:name":"Willi Schilling",
    "wof:placetype":"venue"
},
  "geometry": {"coordinates":[10.9088087082,52.8005905151],"type":"Point"}
}