{
  "type": "Feature",
  "properties": {
    "iso:country":"DE",
    "sg:address":"Gartenstr. 5",
    "sg:city":"Lohmen",
    "sg:phone":"+49 38458/20015",
    "sg:postcode":"18276",
    "sg:province":"Mecklenburg-Vorpommern",
    "wof:name":"B. Klempkow",
    "wof:placetype":"venue"
},
  "geometry": {"coordinates":[12.0931997299,53.6819915771],"type":"Point"}
}