{
  "type": "Feature",
  "properties": {
    "iso:country":"DE",
    "sg:address":"Viktoriastr 12-14",
    "sg:city":"Viersen",
    "sg:phone":"+49 2162/35797",
    "sg:postcode":"41747",
    "sg:province":"Nordrhein-Westfalen",
    "wof:name":"Accente Einrichtungs Gmbh",
    "wof:placetype":"venue"
},
  "geometry": {"coordinates":[6.400124,51.254417],"type":"Point"}
}