{
  "type": "Feature",
  "properties": {
    "iso:country":"DE",
    "sg:address":"Henriettenstra\u00dfe 7/9",
    "sg:city":"Chemnitz",
    "sg:phone":"+49 371/3542060",
    "sg:postcode":"09112",
    "sg:province":"Sachsen",
    "wof:name":"K\u00fcchen Ingo",
    "wof:placetype":"venue"
},
  "geometry": {"coordinates":[12.909221,50.835968],"type":"Point"}
}