{
  "type": "Feature",
  "properties": {
    "iso:country":"DE",
    "sg:address":"Unterlinden 12",
    "sg:city":"Freiburg",
    "sg:phone":"+49 761/34178",
    "sg:postcode":"79098",
    "sg:province":"Baden-W\u00fcrttemberg",
    "wof:name":"Unterlinden-b\u00e4ckerei Gmbh",
    "wof:placetype":"venue"
},
  "geometry": {"coordinates":[7.848559,47.997414],"type":"Point"}
}