{
  "type": "Feature",
  "properties": {
    "iso:country":"DE",
    "sg:address":"Feldstr. 17",
    "sg:city":"Erlensee",
    "sg:phone":"+49 6183/4963",
    "sg:postcode":"63526",
    "sg:province":"Hessen",
    "wof:name":"Manfred Scheele Steuerberater",
    "wof:placetype":"venue"
},
  "geometry": {"coordinates":[8.9788198471,50.160282135],"type":"Point"}
}