{
  "type": "Feature",
  "properties": {
    "iso:country":"DE",
    "sg:address":"Hermann-Vo\u00df-Str. 20",
    "sg:city":"Altena",
    "sg:phone":"+49 2352/92870",
    "sg:postcode":"58762",
    "sg:province":"Nordrhein-Westfalen",
    "wof:name":"Ernst Wirthsmann Steuerberater",
    "wof:placetype":"venue"
},
  "geometry": {"coordinates":[7.6566162109,51.3088035583],"type":"Point"}
}