{
  "type": "Feature",
  "properties": {
    "iso:country":"DE",
    "sg:address":"Mathildenstr. 42",
    "sg:city":"Saarbr\u00fccken",
    "sg:phone":"+49 681/45658",
    "sg:postcode":"66128",
    "sg:province":"Saarland",
    "wof:name":"Werner Schmidt",
    "wof:placetype":"venue"
},
  "geometry": {"coordinates":[6.903462,49.239243],"type":"Point"}
}