{
  "type": "Feature",
  "properties": {
    "iso:country":"DE",
    "sg:address":"Franzstr. 2",
    "sg:city":"Aachen",
    "sg:phone":"+49 241/47940",
    "sg:postcode":"52064",
    "sg:province":"Nordrhein-Westfalen",
    "wof:name":"Huk-coburg-allgemeine Versicherungs-ag",
    "wof:placetype":"venue"
},
  "geometry": {"coordinates":[6.0845088959,50.7719421387],"type":"Point"}
}