{
  "type": "Feature",
  "properties": {
    "iso:country":"DE",
    "sg:address":"Am Sonnenbichl 10c",
    "sg:city":"Bobingen",
    "sg:postcode":"86399",
    "sg:province":"Bayern",
    "wof:name":"Steiner",
    "wof:placetype":"venue"
},
  "geometry": {"coordinates":[10.8308801651,48.2653694153],"type":"Point"}
}