{
  "type": "Feature",
  "properties": {
    "iso:country":"DE",
    "sg:address":"Fritz-Reuter-Str. 4",
    "sg:city":"Hamm",
    "sg:phone":"+49 2381/50486",
    "sg:postcode":"59063",
    "sg:province":"Nordrhein-Westfalen",
    "wof:name":"Fritz Niemann",
    "wof:placetype":"venue"
},
  "geometry": {"coordinates":[7.830318,51.667446],"type":"Point"}
}