{
  "type": "Feature",
  "properties": {
    "iso:country":"DE",
    "sg:address":"Vlothoer Str. 255",
    "sg:city":"Porta Westfalica",
    "sg:phone":"+49 5731/6201",
    "sg:postcode":"32457",
    "sg:province":"Nordrhein-Westfalen",
    "wof:name":"Gerhard Kohlmeier",
    "wof:placetype":"venue"
},
  "geometry": {"coordinates":[8.880114,52.216053],"type":"Point"}
}