{
  "type": "Feature",
  "properties": {
    "iso:country":"DE",
    "sg:address":"Geysostr. 9",
    "sg:city":"Braunschweig",
    "sg:phone":"+49 531/336673",
    "sg:postcode":"38106",
    "sg:province":"Niedersachsen",
    "wof:name":"Hausger\u00e4te - Service",
    "wof:placetype":"venue"
},
  "geometry": {"coordinates":[10.5283298492,52.2770195007],"type":"Point"}
}