{
  "type": "Feature",
  "properties": {
    "iso:country":"DE",
    "sg:address":"Dorfstr. 31b",
    "sg:city":"B\u00fcste",
    "sg:phone":"+49 39089/3504",
    "sg:postcode":"39624",
    "sg:province":"Sachsen-Anhalt",
    "wof:name":"Edgar Hackler",
    "wof:placetype":"venue"
},
  "geometry": {"coordinates":[11.54896,52.690231],"type":"Point"}
}