{
  "type": "Feature",
  "properties": {
    "iso:country":"DE",
    "sg:address":"Wilhelm-En\u00dfle-Str. 66",
    "sg:city":"Remshalden",
    "sg:phone":"+49 7151/75608",
    "sg:postcode":"73630",
    "sg:province":"Baden-W\u00fcrttemberg",
    "wof:name":"Ernst Roos",
    "wof:placetype":"venue"
},
  "geometry": {"coordinates":[9.448215,48.808281],"type":"Point"}
}