{
  "type": "Feature",
  "properties": {
    "iso:country":"DE",
    "sg:address":"Hekeler Str. 12",
    "sg:city":"Berne",
    "sg:phone":"+49 4406/928977",
    "sg:postcode":"27804",
    "sg:province":"Niedersachsen",
    "wof:name":"Clever Sonderposten- Und Warenvertriebs Gmbh",
    "wof:placetype":"venue"
},
  "geometry": {"coordinates":[8.5226068497,53.1582298279],"type":"Point"}
}