{
  "type": "Feature",
  "properties": {
    "iso:country":"DE",
    "sg:address":"Klemensplatz 3",
    "sg:city":"D\u00fcsseldorf",
    "sg:phone":"+49 211/404899",
    "sg:postcode":"40489",
    "sg:province":"Nordrhein-Westfalen",
    "wof:name":"Eiscafe G. Wild",
    "wof:placetype":"venue"
},
  "geometry": {"coordinates":[6.73879,51.300884],"type":"Point"}
}