{
  "type": "Feature",
  "properties": {
    "iso:country":"DE",
    "sg:address":"B\u00fcrgergasse 1",
    "sg:city":"Au",
    "sg:phone":"+49 8752/207",
    "sg:postcode":"84072",
    "sg:province":"Bayern",
    "wof:name":"Gastst\u00e4tte Stefan Tritscheler",
    "wof:placetype":"venue"
},
  "geometry": {"coordinates":[11.7415847778,48.5575523376],"type":"Point"}
}