{
  "type": "Feature",
  "properties": {
    "iso:country":"DE",
    "sg:address":"Asenhamer Str. 4",
    "sg:city":"K\u00f6\u00dflarn",
    "sg:phone":"+49 8536/505",
    "sg:postcode":"94149",
    "sg:province":"Bayern",
    "wof:name":"N. Messmer",
    "wof:placetype":"venue"
},
  "geometry": {"coordinates":[13.121875,48.372372],"type":"Point"}
}