{
  "type": "Feature",
  "properties": {
    "iso:country":"DE",
    "sg:address":"Dr.-Eckart-Weg 6",
    "sg:city":"Bruckm\u00fchl",
    "sg:phone":"+49 8061/35580",
    "sg:postcode":"83052",
    "sg:province":"Bayern",
    "wof:name":"Steinsdorfer Immobilien Gmbh",
    "wof:placetype":"venue"
},
  "geometry": {"coordinates":[11.968501,47.875851],"type":"Point"}
}