{
  "type": "Feature",
  "properties": {
    "iso:country":"DE",
    "sg:address":"Am Marstall 21",
    "sg:city":"Hannover",
    "sg:phone":"+49 511/3631481",
    "sg:postcode":"30159",
    "sg:province":"Niedersachsen",
    "wof:name":"Karl-h. Pawils V. Bartholomaei Antiquit\u00e4ten",
    "wof:placetype":"venue"
},
  "geometry": {"coordinates":[9.731339,52.373714],"type":"Point"}
}