{
  "type": "Feature",
  "properties": {
    "iso:country":"DE",
    "sg:address":"Frankfurter Str. 29",
    "sg:city":"R\u00f6dermark",
    "sg:phone":"+49 6074/97238",
    "sg:postcode":"63322",
    "sg:province":"Hessen",
    "wof:name":"Hellmuth Posautz Elektroinstallation",
    "wof:placetype":"venue"
},
  "geometry": {"coordinates":[8.825861,49.980072],"type":"Point"}
}