{
  "type": "Feature",
  "properties": {
    "iso:country":"DE",
    "sg:address":"Hunkelestr. 1 a",
    "sg:city":"M\u00fcnchen",
    "sg:phone":"+49 89/7559627",
    "sg:postcode":"81476",
    "sg:province":"Bayern",
    "wof:name":"Vee's Kaffee & Bohnen Gmbh",
    "wof:placetype":"venue"
},
  "geometry": {"coordinates":[11.4957838058,48.0940055847],"type":"Point"}
}