{
  "type": "Feature",
  "properties": {
    "iso:country":"DE",
    "sg:address":"Richard-Wagner-Str. 14",
    "sg:city":"M\u00fchldorf",
    "sg:phone":"+49 8631/5041",
    "sg:postcode":"84453",
    "sg:province":"Bayern",
    "wof:name":"M\u00fchl-baubedarf",
    "wof:placetype":"venue"
},
  "geometry": {"coordinates":[12.5121450424,48.2477912903],"type":"Point"}
}