{
  "type": "Feature",
  "properties": {
    "iso:country":"DE",
    "sg:address":"Mahdentalstr. 108",
    "sg:city":"Sindelfingen",
    "sg:phone":"+49 7031/873122",
    "sg:postcode":"71065",
    "sg:province":"Baden-W\u00fcrttemberg",
    "wof:name":"Dakota Warenhandels Gbr",
    "wof:placetype":"venue"
},
  "geometry": {"coordinates":[9.037303,48.705849],"type":"Point"}
}