{
  "type": "Feature",
  "properties": {
    "iso:country":"DE",
    "sg:city":"Niederkassel",
    "sg:postcode":"53859",
    "sg:province":"Nordrhein-Westfalen",
    "wof:name":"Dm Computing",
    "wof:placetype":"venue"
},
  "geometry": {"coordinates":[7.038248,50.812134],"type":"Point"}
}