{
  "type": "Feature",
  "properties": {
    "iso:country":"DE",
    "sg:address":"Mozartstr. 23",
    "sg:city":"M\u00fcnchen",
    "sg:phone":"+49 89/5380089",
    "sg:postcode":"80336",
    "sg:province":"Bayern",
    "wof:name":"Hauptfleisch Gmbh",
    "wof:placetype":"venue"
},
  "geometry": {"coordinates":[11.553944,48.129982],"type":"Point"}
}