{
  "type": "Feature",
  "properties": {
    "iso:country":"DE",
    "sg:address":"In den Schwarzwiesen 20",
    "sg:city":"Oberursel",
    "sg:phone":"+49 6171/97530",
    "sg:postcode":"61440",
    "sg:province":"Hessen",
    "wof:name":"Dmg Draht Und Metall Gmbh",
    "wof:placetype":"venue"
},
  "geometry": {"coordinates":[8.588010788,50.1880378723],"type":"Point"}
}