{
  "type": "Feature",
  "properties": {
    "iso:country":"DE",
    "sg:address":"Jahnstr. 6",
    "sg:city":"Selb",
    "sg:phone":"+49 9287/77102",
    "sg:postcode":"95100",
    "sg:province":"Bayern",
    "wof:name":"J. Grass Vergn\u00fcgungsst\u00e4tte",
    "wof:placetype":"venue"
},
  "geometry": {"coordinates":[12.131065,50.167381],"type":"Point"}
}