{
  "type": "Feature",
  "properties": {
    "iso:country":"DE",
    "sg:address":"Cimbernstr. 66d",
    "sg:city":"M\u00fcnchen",
    "sg:phone":"+49 89/718554",
    "sg:postcode":"81377",
    "sg:province":"Bayern",
    "wof:name":"Fox Multi-service Dienstlei- Stungs-systeme Gmbh",
    "wof:placetype":"venue"
},
  "geometry": {"coordinates":[11.507646,48.106804],"type":"Point"}
}