{
  "type": "Feature",
  "properties": {
    "iso:country":"DE",
    "sg:address":"Prohliser Allee 11",
    "sg:city":"Dresden",
    "sg:phone":"+49 351/2842956",
    "sg:postcode":"01239",
    "sg:province":"Sachsen",
    "wof:name":"H.-otto Rabisch",
    "wof:placetype":"venue"
},
  "geometry": {"coordinates":[13.8013143539,51.0065078735],"type":"Point"}
}