{
  "type": "Feature",
  "properties": {
    "iso:country":"DE",
    "sg:address":"Frauengartenring 10",
    "sg:city":"Sch\u00f6neck",
    "sg:phone":"+49 6187/5570",
    "sg:postcode":"61137",
    "sg:province":"Hessen",
    "wof:name":"Heinz Wolf",
    "wof:placetype":"venue"
},
  "geometry": {"coordinates":[8.856526,50.201847],"type":"Point"}
}