{
  "type": "Feature",
  "properties": {
    "iso:country":"DE",
    "sg:address":"Hauptstr. 2",
    "sg:city":"Helferskirchen",
    "sg:phone":"+49 2626/5603",
    "sg:postcode":"56244",
    "sg:province":"Rheinland-Pfalz",
    "wof:name":"Gerhard Adams",
    "wof:placetype":"venue"
},
  "geometry": {"coordinates":[7.815977,50.514332],"type":"Point"}
}