{
  "type": "Feature",
  "properties": {
    "iso:country":"DE",
    "sg:address":"Springstr. 20",
    "sg:city":"Recklinghausen",
    "sg:phone":"+49 2361/28474",
    "sg:postcode":"45657",
    "sg:province":"Nordrhein-Westfalen",
    "wof:name":"S. Walczak",
    "wof:placetype":"venue"
},
  "geometry": {"coordinates":[7.1993231773,51.6172218323],"type":"Point"}
}