{
  "type": "Feature",
  "properties": {
    "iso:country":"DE",
    "sg:address":"Stollberger Str. 135",
    "sg:city":"Chemnitz",
    "sg:phone":"+49 371/7226427",
    "sg:postcode":"09119",
    "sg:province":"Sachsen",
    "wof:name":"Scheibner Reisen Leipzig Gmbh",
    "wof:placetype":"venue"
},
  "geometry": {"coordinates":[12.895778656,50.8112792969],"type":"Point"}
}