{
  "type": "Feature",
  "properties": {
    "iso:country":"DE",
    "sg:address":"Th\u00fcrmchenswall 27",
    "sg:city":"K\u00f6ln",
    "sg:phone":"+49 221/818685",
    "sg:postcode":"50668",
    "sg:province":"Nordrhein-Westfalen",
    "wof:name":"Neon Media Productions Gmbh",
    "wof:placetype":"venue"
},
  "geometry": {"coordinates":[6.9600739479,50.9494285583],"type":"Point"}
}