{
  "type": "Feature",
  "properties": {
    "iso:country":"DE",
    "sg:address":"Eiderstedter Weg 1",
    "sg:city":"Berlin",
    "sg:phone":"+49 30/8013440",
    "sg:postcode":"14129",
    "sg:province":"Berlin",
    "wof:name":"Egon Braun Architekt",
    "wof:placetype":"venue"
},
  "geometry": {"coordinates":[13.217661,52.438103],"type":"Point"}
}