{
  "type": "Feature",
  "properties": {
    "iso:country":"DE",
    "sg:address":"Georgenstr. 48",
    "sg:city":"Mindelheim",
    "sg:phone":"+49 8261/1739",
    "sg:postcode":"87719",
    "sg:province":"Bayern",
    "wof:name":"B. Unglert Bildhauer",
    "wof:placetype":"venue"
},
  "geometry": {"coordinates":[10.486588,48.040215],"type":"Point"}
}