{
  "type": "Feature",
  "properties": {
    "iso:country":"DE",
    "sg:address":"Rudolf-Breitscheid-Allee 10",
    "sg:city":"Neuenhagen",
    "sg:phone":"+49 3342/202710",
    "sg:postcode":"15366",
    "sg:province":"Brandenburg",
    "wof:name":"Wolf-r\u00fcdiger Knospe",
    "wof:placetype":"venue"
},
  "geometry": {"coordinates":[13.6866703033,52.528503418],"type":"Point"}
}