{
  "type": "Feature",
  "properties": {
    "iso:country":"DE",
    "sg:address":"Waldstr. 23",
    "sg:city":"Dietzenbach",
    "sg:postcode":"63128",
    "sg:province":"Hessen",
    "wof:name":"Peak Technologies Holding Gmbh",
    "wof:placetype":"venue"
},
  "geometry": {"coordinates":[8.807742,50.024059],"type":"Point"}
}