{
  "type": "Feature",
  "properties": {
    "iso:country":"DE",
    "sg:address":"Rat-Scholz-Str. 2",
    "sg:city":"H\u00f6sbach",
    "sg:postcode":"63768",
    "sg:province":"Bayern",
    "wof:name":"Travel-contact E. K.",
    "wof:placetype":"venue"
},
  "geometry": {"coordinates":[9.1967306137,50.0013084412],"type":"Point"}
}