{
  "type": "Feature",
  "properties": {
    "iso:country":"DE",
    "sg:address":"Feldstrasse 12",
    "sg:city":"Kaltenkirchen",
    "sg:phone":"+49 4191",
    "sg:postcode":"24568",
    "sg:province":"Schleswig-Holstein",
    "wof:name":"Taxi-s\u00fcfke - Taxi- Und Busbetrieb",
    "wof:placetype":"venue"
},
  "geometry": {"coordinates":[9.98328,53.822861],"type":"Point"}
}