{
  "type": "Feature",
  "properties": {
    "iso:country":"DE",
    "sg:address":"Kirchstr. 6",
    "sg:city":"Damnatz",
    "sg:phone":"+49 5865/382",
    "sg:postcode":"29472",
    "sg:province":"Niedersachsen",
    "wof:name":"Jutta Und Wilhelm Mattiesch Schiffseigner",
    "wof:placetype":"venue"
},
  "geometry": {"coordinates":[11.177653,53.135933],"type":"Point"}
}