{
  "type": "Feature",
  "properties": {
    "iso:country":"DE",
    "sg:address":"Am H\u00fcnengrab 8",
    "sg:city":"Tostedt",
    "sg:postcode":"21255",
    "sg:province":"Niedersachsen",
    "wof:name":"Rolf Behrens S\u00fcsswaren",
    "wof:placetype":"venue"
},
  "geometry": {"coordinates":[9.7644100189,53.2844314575],"type":"Point"}
}