{
  "type": "Feature",
  "properties": {
    "iso:country":"DE",
    "sg:address":"Dorfplatz 2",
    "sg:city":"Eschenlohe",
    "sg:phone":"+49 8824/8484",
    "sg:postcode":"82438",
    "sg:province":"Bayern",
    "wof:name":"Franz Mangold",
    "wof:placetype":"venue"
},
  "geometry": {"coordinates":[11.185618,47.599094],"type":"Point"}
}