{
  "type": "Feature",
  "properties": {
    "iso:country":"DE",
    "sg:address":"Hansastr. 29",
    "sg:city":"Karlsruhe",
    "sg:phone":"+49 721/502012",
    "sg:postcode":"76189",
    "sg:province":"Baden-W\u00fcrttemberg",
    "wof:name":"Spielwarenvertriebs Gmbh Ralf M\u00fcller",
    "wof:placetype":"venue"
},
  "geometry": {"coordinates":[8.326174736,49.0121765137],"type":"Point"}
}