{
  "type": "Feature",
  "properties": {
    "iso:country":"DE",
    "sg:address":"Gro\u00dfe M\u00fchlenstr. 1",
    "sg:city":"Nortorf",
    "sg:phone":"+49 4392/4449",
    "sg:postcode":"24589",
    "sg:province":"Schleswig-Holstein",
    "wof:name":"W. Lepthien",
    "wof:placetype":"venue"
},
  "geometry": {"coordinates":[9.85476017,54.1688613892],"type":"Point"}
}