{
  "type": "Feature",
  "properties": {
    "iso:country":"DE",
    "sg:address":"Luebecker Str. 6",
    "sg:city":"Eutin",
    "sg:phone":"+49 4521/798633",
    "sg:postcode":"23701",
    "sg:province":"Schleswig-Holstein",
    "wof:name":"Buenning, Rainer Wolfgang",
    "wof:placetype":"venue"
},
  "geometry": {"coordinates":[10.617033,54.135403],"type":"Point"}
}