{
  "type": "Feature",
  "properties": {
    "iso:country":"DE",
    "sg:address":"Kirchgasse 7",
    "sg:city":"Unterp\u00f6rlitz",
    "sg:postcode":"98693",
    "sg:province":"Th\u00fcringen",
    "wof:name":"Schulze Hoch- Und Tiefbau Gmbh",
    "wof:placetype":"venue"
},
  "geometry": {"coordinates":[10.932465,50.70211],"type":"Point"}
}