{
  "type": "Feature",
  "properties": {
    "iso:country":"DE",
    "sg:address":"Sch\u00fcrbankstr. 23",
    "sg:city":"Dortmund",
    "sg:phone":"+49 231/452031",
    "sg:postcode":"44287",
    "sg:province":"Nordrhein-Westfalen",
    "wof:name":"Friedrich Demke",
    "wof:placetype":"venue"
},
  "geometry": {"coordinates":[7.55734,51.498234],"type":"Point"}
}