{
  "type": "Feature",
  "properties": {
    "iso:country":"DE",
    "sg:address":"Parkstr. 31",
    "sg:city":"Bad Elster",
    "sg:phone":"+49 37437/2535",
    "sg:postcode":"08645",
    "sg:province":"Sachsen",
    "wof:name":"Kurheim Pax",
    "wof:placetype":"venue"
},
  "geometry": {"coordinates":[12.2314147949,50.2834625244],"type":"Point"}
}