{
  "type": "Feature",
  "properties": {
    "iso:country":"DE",
    "sg:address":"Mainstr. 13",
    "sg:city":"Kemmern",
    "sg:phone":"+49 9544/20313",
    "sg:postcode":"96164",
    "sg:province":"Bayern",
    "wof:name":"Andreas H\u00e4fner",
    "wof:placetype":"venue"
},
  "geometry": {"coordinates":[10.8761196136,49.9505195618],"type":"Point"}
}