{
  "type": "Feature",
  "properties": {
    "iso:country":"DE",
    "sg:address":"Conrad-Schlaun-Str. 39",
    "sg:city":"Dormagen",
    "sg:phone":"+49 2133/92229",
    "sg:postcode":"41542",
    "sg:province":"Nordrhein-Westfalen",
    "wof:name":"Bernd Und Angelika Dicken",
    "wof:placetype":"venue"
},
  "geometry": {"coordinates":[6.7760691643,51.11095047],"type":"Point"}
}