{
  "type": "Feature",
  "properties": {
    "iso:country":"DE",
    "sg:address":"Sandkoul 3",
    "sg:city":"Selfkant",
    "sg:phone":"+49 2456/1361",
    "sg:postcode":"52538",
    "sg:province":"Nordrhein-Westfalen",
    "wof:name":"Kath. Pfarramt St. Gertrud",
    "wof:placetype":"venue"
},
  "geometry": {"coordinates":[5.9091000557,51.0373725891],"type":"Point"}
}