{
  "type": "Feature",
  "properties": {
    "iso:country":"DE",
    "sg:address":"Platenhofer Weg 4",
    "sg:city":"Berlin",
    "sg:phone":"+49 30/4319602",
    "sg:postcode":"13503",
    "sg:province":"Berlin",
    "wof:name":"Brigitte Kubisch Steuerberaterin",
    "wof:placetype":"venue"
},
  "geometry": {"coordinates":[13.2250919342,52.6140823364],"type":"Point"}
}