{
  "type": "Feature",
  "properties": {
    "iso:country":"DE",
    "sg:address":"Fischbecker Str. 52",
    "sg:city":"Hessisch Oldendorf",
    "sg:phone":"+49 5152/8476",
    "sg:postcode":"31840",
    "sg:province":"Niedersachsen",
    "wof:name":"Heinrich Kasten",
    "wof:placetype":"venue"
},
  "geometry": {"coordinates":[9.28992,52.157219],"type":"Point"}
}