{
  "type": "Feature",
  "properties": {
    "iso:country":"DE",
    "sg:address":"In den Osterwiesen 8",
    "sg:city":"Sigmarszell",
    "sg:phone":"+49 8389/8648",
    "sg:postcode":"88138",
    "sg:province":"Bayern",
    "wof:name":"J. St\u00f6tzer Und Partner Garten-und Land-",
    "wof:placetype":"venue"
},
  "geometry": {"coordinates":[9.748292,47.589485],"type":"Point"}
}