{
  "type": "Feature",
  "properties": {
    "iso:country":"DE",
    "sg:address":"Maximilianstr. 78",
    "sg:city":"Speyer",
    "sg:phone":"+49 6232/629037",
    "sg:postcode":"67346",
    "sg:province":"Rheinland-Pfalz",
    "wof:name":"Kochl\u00f6ffel Gmbh",
    "wof:placetype":"venue"
},
  "geometry": {"coordinates":[8.4358568192,49.3175621033],"type":"Point"}
}