{
  "type": "Feature",
  "properties": {
    "iso:country":"DE",
    "sg:address":"Herzogstr. 2",
    "sg:city":"N\u00fcrnberg",
    "sg:phone":"+49 911/402671",
    "sg:postcode":"90478",
    "sg:province":"Bayern",
    "wof:name":"Gastst\u00e4tte Post Dutzendteich",
    "wof:placetype":"venue"
},
  "geometry": {"coordinates":[11.1180505753,49.4358329773],"type":"Point"}
}