{
  "type": "Feature",
  "properties": {
    "iso:country":"DE",
    "sg:address":"Sigmundstr. 45",
    "sg:city":"N\u00fcrnberg",
    "sg:phone":"+49 911/314282",
    "sg:postcode":"90431",
    "sg:province":"Bayern",
    "wof:name":"Offsetdruck Karl Frey Gmbh",
    "wof:placetype":"venue"
},
  "geometry": {"coordinates":[11.0182,49.457462],"type":"Point"}
}