{
  "type": "Feature",
  "properties": {
    "iso:country":"DE",
    "sg:address":"St\u00fcrtzelstr. 15",
    "sg:city":"Freiburg",
    "sg:phone":"+49 761/31212",
    "sg:postcode":"79106",
    "sg:province":"Baden-W\u00fcrttemberg",
    "wof:name":"City-blitz",
    "wof:placetype":"venue"
},
  "geometry": {"coordinates":[7.83422,47.997784],"type":"Point"}
}