{
  "type": "Feature",
  "properties": {
    "iso:country":"DE",
    "sg:address":"H\u00f6henweg 30",
    "sg:city":"Happurg",
    "sg:phone":"+49 9151/4423",
    "sg:postcode":"91230",
    "sg:province":"Bayern",
    "wof:name":"Hotel Ruff",
    "wof:placetype":"venue"
},
  "geometry": {"coordinates":[11.4760522842,49.4902534485],"type":"Point"}
}