{
  "type": "Feature",
  "properties": {
    "iso:country":"DE",
    "sg:address":"An der Hansalinie 10",
    "sg:city":"M\u00fcnster",
    "sg:phone":"+49 251/719109",
    "sg:postcode":"48163",
    "sg:province":"Nordrhein-Westfalen",
    "wof:name":"Rainer Buddendieck",
    "wof:placetype":"venue"
},
  "geometry": {"coordinates":[7.561245,51.926407],"type":"Point"}
}