{
  "type": "Feature",
  "properties": {
    "iso:country":"DE",
    "sg:address":"Lange Str. 84",
    "sg:city":"Alpirsbach",
    "sg:phone":"+49 7444/6360",
    "sg:postcode":"72275",
    "sg:province":"Baden-W\u00fcrttemberg",
    "wof:name":"Alfred Schwenk",
    "wof:placetype":"venue"
},
  "geometry": {"coordinates":[8.4595851898,48.3396568298],"type":"Point"}
}