{
  "type": "Feature",
  "properties": {
    "iso:country":"DE",
    "sg:address":"Puschkinallee 7",
    "sg:city":"Gotha",
    "sg:phone":"+49 3621/300549",
    "sg:postcode":"99867",
    "sg:province":"Th\u00fcringen",
    "wof:name":"Stephan Becker Rechtsanwalt",
    "wof:placetype":"venue"
},
  "geometry": {"coordinates":[10.7000160217,50.9423294067],"type":"Point"}
}