{
  "type": "Feature",
  "properties": {
    "iso:country":"DE",
    "sg:address":"Breslauer Str. 13",
    "sg:city":"Mettmann",
    "sg:phone":"+49 2104/70370",
    "sg:postcode":"40822",
    "sg:province":"Nordrhein-Westfalen",
    "wof:name":"Karsten Gehrke",
    "wof:placetype":"venue"
},
  "geometry": {"coordinates":[6.96469,51.254921],"type":"Point"}
}