{
  "type": "Feature",
  "properties": {
    "iso:country":"DE",
    "sg:address":"Nordendstr. 12",
    "sg:city":"M\u00f6rfelden-Walldorf",
    "sg:phone":"+49 6105/75094",
    "sg:postcode":"64546",
    "sg:province":"Hessen",
    "wof:name":"Orient Kebab Haus",
    "wof:placetype":"venue"
},
  "geometry": {"coordinates":[8.5810861588,50.013874054],"type":"Point"}
}