{
  "type": "Feature",
  "properties": {
    "iso:country":"DE",
    "sg:address":"Hauptstr. 32",
    "sg:city":"Neuffen",
    "sg:phone":"+49 7025/7868",
    "sg:postcode":"72639",
    "sg:province":"Baden-W\u00fcrttemberg",
    "wof:name":"Landmetzgerei Scheu & Weber Gmbh",
    "wof:placetype":"venue"
},
  "geometry": {"coordinates":[9.3763141632,48.5538825989],"type":"Point"}
}