{
  "type": "Feature",
  "properties": {
    "iso:country":"DE",
    "sg:address":"Krefelder Str. 99",
    "sg:city":"T\u00f6nisvorst",
    "sg:phone":"+49 2151/790522",
    "sg:postcode":"47918",
    "sg:province":"Nordrhein-Westfalen",
    "wof:name":"Johannes Theunissen",
    "wof:placetype":"venue"
},
  "geometry": {"coordinates":[6.5014801025,51.3213882446],"type":"Point"}
}