{
  "type": "Feature",
  "properties": {
    "iso:country":"DE",
    "sg:address":"Oststr. 1",
    "sg:city":"Nottuln",
    "sg:phone":"+49 2502/94100",
    "sg:postcode":"48301",
    "sg:province":"Nordrhein-Westfalen",
    "wof:name":"Hagebaumarkt B. Frieling Gmbh",
    "wof:placetype":"venue"
},
  "geometry": {"coordinates":[7.364834,51.926785],"type":"Point"}
}