{
  "type": "Feature",
  "properties": {
    "iso:country":"DE",
    "sg:address":"Am Schulgarten 12",
    "sg:city":"Lahr",
    "sg:phone":"+49 7821/955420",
    "sg:postcode":"77933",
    "sg:province":"Baden-W\u00fcrttemberg",
    "wof:name":"Lothar Haller",
    "wof:placetype":"venue"
},
  "geometry": {"coordinates":[7.8387742043,48.3611335754],"type":"Point"}
}