{
  "type": "Feature",
  "properties": {
    "iso:country":"DE",
    "sg:address":"Waldgasse 22",
    "sg:city":"Baden-Baden",
    "sg:phone":"+49 7221/51558",
    "sg:postcode":"76532",
    "sg:province":"Baden-W\u00fcrttemberg",
    "wof:name":"O. Brenneisen Ingenieur",
    "wof:placetype":"venue"
},
  "geometry": {"coordinates":[8.2283992767,48.8070449829],"type":"Point"}
}