{
  "type": "Feature",
  "properties": {
    "iso:country":"DE",
    "sg:address":"K\u00f6lnstr. 7",
    "sg:city":"J\u00fclich",
    "sg:phone":"+49 2461/2443",
    "sg:postcode":"52428",
    "sg:province":"Nordrhein-Westfalen",
    "wof:name":"Johann R\u00f6ttgen",
    "wof:placetype":"venue"
},
  "geometry": {"coordinates":[6.3590760231,50.9223518372],"type":"Point"}
}