{
  "type": "Feature",
  "properties": {
    "iso:country":"DE",
    "sg:address":"Bessemerstr. 19-21",
    "sg:city":"Frankfurt",
    "sg:phone":"+49 6109/32428",
    "sg:postcode":"60388",
    "sg:province":"Hessen",
    "wof:name":"Armin Heinz Maschinenbau Kg",
    "wof:placetype":"venue"
},
  "geometry": {"coordinates":[8.7487068176,50.1436080933],"type":"Point"}
}