{
  "type": "Feature",
  "properties": {
    "iso:country":"DE",
    "sg:address":"Schl\u00fcmersweg 11",
    "sg:city":"Hamminkeln",
    "sg:phone":"+49 2856/753",
    "sg:postcode":"46499",
    "sg:province":"Nordrhein-Westfalen",
    "wof:name":"G\u00fcnter Tellmann",
    "wof:placetype":"venue"
},
  "geometry": {"coordinates":[6.639612,51.721973],"type":"Point"}
}