{
  "type": "Feature",
  "properties": {
    "iso:country":"DE",
    "sg:address":"Saarlandstr. 24",
    "sg:city":"Herne",
    "sg:phone":"+49 2325/32221",
    "sg:postcode":"44651",
    "sg:province":"Nordrhein-Westfalen",
    "wof:name":"Textilhaus Edith",
    "wof:placetype":"venue"
},
  "geometry": {"coordinates":[7.1807851791,51.5091705322],"type":"Point"}
}