{
  "type": "Feature",
  "properties": {
    "iso:country":"DE",
    "sg:address":"Von-Galen-Str. 20",
    "sg:city":"Erftstadt",
    "sg:phone":"+49 2235/959211",
    "sg:postcode":"50374",
    "sg:province":"Nordrhein-Westfalen",
    "wof:name":"Thelen Und P\u00e4sler",
    "wof:placetype":"venue"
},
  "geometry": {"coordinates":[6.7689900398,50.7962226868],"type":"Point"}
}