{
  "type": "Feature",
  "properties": {
    "iso:country":"DE",
    "sg:address":"Pfarrer-Menge-Weg 1",
    "sg:city":"Warstein",
    "sg:phone":"+49 2902/4990",
    "sg:postcode":"59581",
    "sg:province":"Nordrhein-Westfalen",
    "wof:name":"Klaus Grafe",
    "wof:placetype":"venue"
},
  "geometry": {"coordinates":[8.3531398773,51.4440803528],"type":"Point"}
}