{
  "type": "Feature",
  "properties": {
    "iso:country":"DE",
    "sg:address":"Herzfelder Steig 32",
    "sg:city":"Berlin",
    "sg:phone":"+49 30/64849832",
    "sg:postcode":"12589",
    "sg:province":"Berlin",
    "wof:name":"Titze Kabelbetriebs Kg",
    "wof:placetype":"venue"
},
  "geometry": {"coordinates":[13.710781,52.441109],"type":"Point"}
}