{
  "type": "Feature",
  "properties": {
    "iso:country":"DE",
    "sg:address":"Schwechater Str. 38",
    "sg:city":"Gladbeck",
    "sg:phone":"+49 2043/478350",
    "sg:postcode":"45966",
    "sg:province":"Nordrhein-Westfalen",
    "wof:name":"Dorotheen-apotheke",
    "wof:placetype":"venue"
},
  "geometry": {"coordinates":[6.962509,51.580639],"type":"Point"}
}