{
  "type": "Feature",
  "properties": {
    "iso:country":"DE",
    "sg:address":"Hinrich-Schmalfeldt-Str. 22",
    "sg:city":"Bremerhaven",
    "sg:phone":"+49 471/53797",
    "sg:postcode":"27576",
    "sg:province":"Bremen",
    "wof:name":"La Gondola",
    "wof:placetype":"venue"
},
  "geometry": {"coordinates":[8.5888710022,53.5590591431],"type":"Point"}
}