{
  "type": "Feature",
  "properties": {
    "iso:country":"DE",
    "sg:address":"Dornspachstr. 45",
    "sg:city":"Zittau",
    "sg:phone":"+49 3583/700371",
    "sg:postcode":"02763",
    "sg:province":"Sachsen",
    "wof:name":"Gottfried Meyrich",
    "wof:placetype":"venue"
},
  "geometry": {"coordinates":[14.8177404404,50.9046401978],"type":"Point"}
}