{
  "type": "Feature",
  "properties": {
    "iso:country":"DE",
    "sg:address":"Waldstr. 73",
    "sg:city":"Kelsterbach",
    "sg:phone":"+49 6107/62051",
    "sg:postcode":"65451",
    "sg:province":"Hessen",
    "wof:name":"Hotel Zeltinger Hof Inh. Rainer Heckmann",
    "wof:placetype":"venue"
},
  "geometry": {"coordinates":[8.5261659622,50.058757782],"type":"Point"}
}