{
  "type": "Feature",
  "properties": {
    "iso:country":"DE",
    "sg:address":"Grenzweg 4",
    "sg:city":"Alsdorf",
    "sg:phone":"+49 2404/7047",
    "sg:postcode":"52477",
    "sg:province":"Nordrhein-Westfalen",
    "wof:name":"I. Eiche",
    "wof:placetype":"venue"
},
  "geometry": {"coordinates":[6.1610059738,50.8726577759],"type":"Point"}
}