{
  "type": "Feature",
  "properties": {
    "iso:country":"DE",
    "sg:address":"Betziner Weg 18",
    "sg:city":"Fehrbellin",
    "sg:phone":"+49 33932/70229",
    "sg:postcode":"16833",
    "sg:province":"Brandenburg",
    "wof:name":"Agrar Gmbh",
    "wof:placetype":"venue"
},
  "geometry": {"coordinates":[12.77485,52.803047],"type":"Point"}
}