{
  "type": "Feature",
  "properties": {
    "iso:country":"DE",
    "sg:address":"Waschleither Str. 7",
    "sg:city":"Beierfeld",
    "sg:phone":"+49 3774/61682",
    "sg:postcode":"08340",
    "sg:province":"Sachsen",
    "wof:name":"M. Wagner",
    "wof:placetype":"venue"
},
  "geometry": {"coordinates":[12.791176796,50.563495636],"type":"Point"}
}