{
  "type": "Feature",
  "properties": {
    "iso:country":"DE",
    "sg:address":"Wiesenstr. 20",
    "sg:city":"Rimpar",
    "sg:phone":"+49 9365/2270",
    "sg:postcode":"97222",
    "sg:province":"Bayern",
    "wof:name":"K. Und T. Stock",
    "wof:placetype":"venue"
},
  "geometry": {"coordinates":[9.97077,49.850002],"type":"Point"}
}