{
  "type": "Feature",
  "properties": {
    "iso:country":"DE",
    "sg:address":"Saale Stausee",
    "sg:city":"Saalburg",
    "sg:phone":"+49 36647/441",
    "sg:postcode":"07929",
    "sg:province":"Th\u00fcringen",
    "wof:name":"An Der Bleichlochtalsperre",
    "wof:placetype":"venue"
},
  "geometry": {"coordinates":[11.731755,50.501583],"type":"Point"}
}