{
  "type": "Feature",
  "properties": {
    "iso:country":"DE",
    "sg:address":"Im Br\u00fcckerfeld 1",
    "sg:city":"Leichlingen",
    "sg:phone":"+49 2175/720570",
    "sg:postcode":"42799",
    "sg:province":"Nordrhein-Westfalen",
    "wof:name":"K. Langner",
    "wof:placetype":"venue"
},
  "geometry": {"coordinates":[7.0138120651,51.102684021],"type":"Point"}
}