{
  "type": "Feature",
  "properties": {
    "iso:country":"DE",
    "sg:address":"Am Hospizplatz",
    "sg:city":"Langeoog",
    "sg:phone":"+49 4972/350",
    "sg:postcode":"26465",
    "sg:province":"Niedersachsen",
    "wof:name":"Hotel Loccumer Inselhospiz",
    "wof:placetype":"venue"
},
  "geometry": {"coordinates":[7.4824919701,53.7506866455],"type":"Point"}
}