{
  "type": "Feature",
  "properties": {
    "iso:country":"DE",
    "sg:address":"Speyerer Str. 30-32",
    "sg:city":"Frankenthal",
    "sg:phone":"+49 6233/31600",
    "sg:postcode":"67227",
    "sg:province":"Rheinland-Pfalz",
    "wof:name":"Kisling & Cie Eisenwaren",
    "wof:placetype":"venue"
},
  "geometry": {"coordinates":[8.3537168503,49.5338172913],"type":"Point"}
}