{
  "type": "Feature",
  "properties": {
    "iso:country":"DE",
    "sg:address":"Nothgottesstr. 46",
    "sg:city":"Geisenheim",
    "sg:phone":"+49 6722/71862",
    "sg:postcode":"65366",
    "sg:province":"Hessen",
    "wof:name":"Manfred Buse",
    "wof:placetype":"venue"
},
  "geometry": {"coordinates":[7.954211235,49.9890861511],"type":"Point"}
}