{
  "type": "Feature",
  "properties": {
    "iso:country":"DE",
    "sg:address":"Siedlungsgut 3",
    "sg:city":"Mildenberg",
    "sg:postcode":"16775",
    "sg:province":"Brandenburg",
    "wof:name":"Andr\u00e9 Schr\u00f6der Beteiligungs Gmbh",
    "wof:placetype":"venue"
},
  "geometry": {"coordinates":[13.153723,52.897305],"type":"Point"}
}