{
  "type": "Feature",
  "properties": {
    "iso:country":"DE",
    "sg:address":"Kleinenborstel 76",
    "sg:city":"Martfeld",
    "sg:phone":"+49 4255/1486",
    "sg:postcode":"27327",
    "sg:province":"Niedersachsen",
    "wof:name":"Wilhelm Bartels",
    "wof:placetype":"venue"
},
  "geometry": {"coordinates":[9.022031,52.862228],"type":"Point"}
}