{
  "type": "Feature",
  "properties": {
    "iso:country":"DE",
    "sg:address":"Landauer Str. 597",
    "sg:city":"Stuttgart",
    "sg:postcode":"70499",
    "sg:province":"Baden-W\u00fcrttemberg",
    "wof:name":"Hermann Gastro Service",
    "wof:placetype":"venue"
},
  "geometry": {"coordinates":[9.112335,48.814381],"type":"Point"}
}