{
  "type": "Feature",
  "properties": {
    "iso:country":"DE",
    "sg:address":"Pl\u00f6ner Str. 10",
    "sg:city":"Bremen",
    "sg:phone":"+49 421/3966212",
    "sg:postcode":"28219",
    "sg:province":"Bremen",
    "wof:name":"Kurt Schuller Gmbh",
    "wof:placetype":"venue"
},
  "geometry": {"coordinates":[8.783266,53.102062],"type":"Point"}
}