{
  "type": "Feature",
  "properties": {
    "iso:country":"DE",
    "sg:address":"Bahnhofstr. 21",
    "sg:city":"Babenhausen",
    "sg:phone":"+49 6073/2388",
    "sg:postcode":"64832",
    "sg:province":"Hessen",
    "wof:name":"Erich Rinke",
    "wof:placetype":"venue"
},
  "geometry": {"coordinates":[8.912068,49.93964],"type":"Point"}
}