{
  "type": "Feature",
  "properties": {
    "iso:country":"DE",
    "sg:address":"Ziegeleiweg 37",
    "sg:city":"D\u00fcsseldorf",
    "sg:phone":"+49 211/774499",
    "sg:postcode":"40591",
    "sg:province":"Nordrhein-Westfalen",
    "wof:name":"Heinz Amen",
    "wof:placetype":"venue"
},
  "geometry": {"coordinates":[6.810066,51.196297],"type":"Point"}
}