{
  "type": "Feature",
  "properties": {
    "iso:country":"DE",
    "sg:address":"Innere M\u00fcnchener Str. 17",
    "sg:city":"Landshut",
    "sg:phone":"+49 871/43737",
    "sg:postcode":"84036",
    "sg:province":"Bayern",
    "wof:name":"Trausnitz Apotheke Inh. Apotheker",
    "wof:placetype":"venue"
},
  "geometry": {"coordinates":[12.146905,48.529602],"type":"Point"}
}