{
  "type": "Feature",
  "properties": {
    "iso:country":"DE",
    "sg:city":"Gusborn",
    "sg:phone":"+49 4958/65311",
    "sg:postcode":"29476",
    "sg:province":"Niedersachsen",
    "wof:name":"Volksbank Dannenberg Eg",
    "wof:placetype":"venue"
},
  "geometry": {"coordinates":[11.216565,53.080055],"type":"Point"}
}