{
  "type": "Feature",
  "properties": {
    "iso:country":"DE",
    "sg:address":"Gartenstr. 24",
    "sg:city":"Daun",
    "sg:phone":"+49 6592/2184",
    "sg:postcode":"54550",
    "sg:province":"Rheinland-Pfalz",
    "wof:name":"Sozialberatungsstelle Krs.-charitasverband",
    "wof:placetype":"venue"
},
  "geometry": {"coordinates":[6.830123,50.201649],"type":"Point"}
}