{
  "type": "Feature",
  "properties": {
    "iso:country":"DE",
    "sg:address":"Burgstr. 4",
    "sg:city":"Leinfelden-Echterdingen",
    "sg:phone":"+49 711/7944180",
    "sg:postcode":"70771",
    "sg:province":"Baden-W\u00fcrttemberg",
    "wof:name":"Restaurant Cabanas",
    "wof:placetype":"venue"
},
  "geometry": {"coordinates":[9.1696596146,48.689037323],"type":"Point"}
}