{
  "type": "Feature",
  "properties": {
    "iso:country":"DE",
    "sg:address":"Wilhelmstr. 5",
    "sg:city":"M\u00fcllheim",
    "sg:phone":"+49 7631/12474",
    "sg:postcode":"79379",
    "sg:province":"Baden-W\u00fcrttemberg",
    "wof:name":"Prema Geldbearbeitungs- Systeme Gmbh",
    "wof:placetype":"venue"
},
  "geometry": {"coordinates":[7.628844,47.806099],"type":"Point"}
}