{
  "type": "Feature",
  "properties": {
    "iso:country":"DE",
    "sg:address":"Duisburger Str. 5",
    "sg:city":"Dinslaken",
    "sg:phone":"+49 2064/53555",
    "sg:postcode":"46535",
    "sg:province":"Nordrhein-Westfalen",
    "wof:name":"M. Lippka",
    "wof:placetype":"venue"
},
  "geometry": {"coordinates":[6.7346110344,51.5618934631],"type":"Point"}
}