{
  "type": "Feature",
  "properties": {
    "iso:country":"DE",
    "sg:address":"Seeplatz 7",
    "sg:city":"Gstadt",
    "sg:phone":"+49 8054/535",
    "sg:postcode":"83257",
    "sg:province":"Bayern",
    "wof:name":"Gr\u00fcn\u00e4ugl",
    "wof:placetype":"venue"
},
  "geometry": {"coordinates":[12.418447,47.88382],"type":"Point"}
}