{
  "type": "Feature",
  "properties": {
    "iso:country":"DE",
    "sg:address":"Bangertstr. 13",
    "sg:city":"Hanau",
    "sg:phone":"+49 6181/21966",
    "sg:postcode":"63450",
    "sg:province":"Hessen",
    "wof:name":"Casa Dietlind Schultze",
    "wof:placetype":"venue"
},
  "geometry": {"coordinates":[8.9158649445,50.1362571716],"type":"Point"}
}