{
  "type": "Feature",
  "properties": {
    "iso:country":"DE",
    "sg:address":"Steinmetzstr. 4",
    "sg:city":"N\u00fcrnberg",
    "sg:phone":"+49 911/613758",
    "sg:postcode":"90431",
    "sg:province":"Bayern",
    "wof:name":"Ev. Luth. Pfarramt St. Leonhard Iii",
    "wof:placetype":"venue"
},
  "geometry": {"coordinates":[11.0346603394,49.4444198608],"type":"Point"}
}