{
  "type": "Feature",
  "properties": {
    "iso:country":"DE",
    "sg:address":"Am Berg 1",
    "sg:city":"Bebra",
    "sg:phone":"+49 6622/9310",
    "sg:postcode":"36179",
    "sg:province":"Hessen",
    "wof:name":"Hotel Sonnenblick",
    "wof:placetype":"venue"
},
  "geometry": {"coordinates":[9.8711204529,50.9785995483],"type":"Point"}
}