{
  "type": "Feature",
  "properties": {
    "iso:country":"DE",
    "sg:address":"Lenggrieser Str. 61",
    "sg:city":"Bad T\u00f6lz",
    "sg:phone":"+49 8041/8887",
    "sg:postcode":"83646",
    "sg:province":"Bayern",
    "wof:name":"Herbert Heuser",
    "wof:placetype":"venue"
},
  "geometry": {"coordinates":[11.563185,47.751442],"type":"Point"}
}