{
  "type": "Feature",
  "properties": {
    "iso:country":"DE",
    "sg:address":"Kahler Krug 18 b",
    "sg:city":"Bielefeld",
    "sg:phone":"+49 521/882125",
    "sg:postcode":"33739",
    "sg:province":"Nordrhein-Westfalen",
    "wof:name":"Marion Scharenberg",
    "wof:placetype":"venue"
},
  "geometry": {"coordinates":[8.5154848099,52.0710868835],"type":"Point"}
}