{
  "type": "Feature",
  "properties": {
    "iso:country":"DE",
    "sg:address":"Habichtweg 14",
    "sg:city":"Extertal",
    "sg:phone":"+49 5262/56546",
    "sg:postcode":"32699",
    "sg:province":"Nordrhein-Westfalen",
    "wof:name":"Manfred Schillo",
    "wof:placetype":"venue"
},
  "geometry": {"coordinates":[9.116885,52.075047],"type":"Point"}
}