{
  "type": "Feature",
  "properties": {
    "iso:country":"DE",
    "sg:address":"Au\u00dferhalb 85",
    "sg:city":"Weiterstadt",
    "sg:phone":"+49 6150/3852",
    "sg:postcode":"64331",
    "sg:province":"Hessen",
    "wof:name":"Kleintierzuchtverein H 348 Gesch\u00e4ftsstelle E. V.",
    "wof:placetype":"venue"
},
  "geometry": {"coordinates":[8.5610780716,49.9120597839],"type":"Point"}
}