{
  "type": "Feature",
  "properties": {
    "iso:country":"DE",
    "sg:address":"Obersteinbacher Str. 2",
    "sg:city":"Rauhenebrach",
    "sg:phone":"+49 9554/1348",
    "sg:postcode":"96181",
    "sg:province":"Bayern",
    "wof:name":"A. Aigner Finanzberater",
    "wof:placetype":"venue"
},
  "geometry": {"coordinates":[10.5488939285,49.8894233704],"type":"Point"}
}