{
  "type": "Feature",
  "properties": {
    "iso:country":"DE",
    "sg:address":"Am Kreuzberg 4",
    "sg:city":"Irxleben",
    "sg:phone":"+49 39204/7130",
    "sg:postcode":"39167",
    "sg:province":"Sachsen-Anhalt",
    "wof:name":"Grunewald Formen- Und Werkzeugbau Gmbh & Co. Kg",
    "wof:placetype":"venue"
},
  "geometry": {"coordinates":[11.49419,52.162861],"type":"Point"}
}