{
  "type": "Feature",
  "properties": {
    "iso:country":"DE",
    "sg:address":"Metzstr. 28",
    "sg:city":"M\u00fcnchen",
    "sg:phone":"+49 89/4488377",
    "sg:postcode":"81667",
    "sg:province":"Bayern",
    "wof:name":"Hans Buttermilch Und Knoll",
    "wof:placetype":"venue"
},
  "geometry": {"coordinates":[11.5988693237,48.1302032471],"type":"Point"}
}