{
  "type": "Feature",
  "properties": {
    "iso:country":"DE",
    "sg:address":"Wilhelm-Maybach-Str. 11",
    "sg:city":"Mainz",
    "sg:phone":"+49 6131/582015",
    "sg:postcode":"55129",
    "sg:province":"Rheinland-Pfalz",
    "wof:name":"Optek Danulat Gmbh",
    "wof:placetype":"venue"
},
  "geometry": {"coordinates":[8.256593,49.959766],"type":"Point"}
}