{
  "type": "Feature",
  "properties": {
    "iso:country":"DE",
    "sg:address":"Sinziger Str. 3",
    "sg:city":"Berlin",
    "sg:phone":"+49 30/5090324",
    "sg:postcode":"10318",
    "sg:province":"Berlin",
    "wof:name":"Melatec Medizin- Und Labortechnik-vertriebs Gmbh",
    "wof:placetype":"venue"
},
  "geometry": {"coordinates":[13.5254154205,52.4818191528],"type":"Point"}
}