{
  "type": "Feature",
  "properties": {
    "iso:country":"DE",
    "sg:city":"Ermlitz",
    "sg:postcode":"06184",
    "sg:province":"Sachsen-Anhalt",
    "wof:name":"Campingplatz Elsteraue",
    "wof:placetype":"venue"
},
  "geometry": {"coordinates":[12.100228,51.43808],"type":"Point"}
}