{
  "type": "Feature",
  "properties": {
    "iso:country":"DE",
    "sg:address":"Neuer Weg 49",
    "sg:city":"Ortenberg",
    "sg:phone":"+49 6046/3599",
    "sg:postcode":"63683",
    "sg:province":"Hessen",
    "wof:name":"Fotoatelier Cornelia Kemm Gmbh",
    "wof:placetype":"venue"
},
  "geometry": {"coordinates":[9.0534076691,50.3534584045],"type":"Point"}
}