{
  "type": "Feature",
  "properties": {
    "iso:country":"DE",
    "sg:address":"Messeler-Park-Str. 128",
    "sg:city":"Darmstadt",
    "sg:postcode":"64291",
    "sg:province":"Hessen",
    "wof:name":"Sch\u00e4fer Verwaltungs- Gesellschaft Mbh",
    "wof:placetype":"venue"
},
  "geometry": {"coordinates":[8.6607875824,49.9318275452],"type":"Point"}
}