{
  "type": "Feature",
  "properties": {
    "iso:country":"DE",
    "sg:address":"Am Weinberg 17",
    "sg:city":"Reinfeld",
    "sg:phone":"+49 4533/791744",
    "sg:postcode":"23858",
    "sg:province":"Schleswig-Holstein",
    "wof:name":"Inlogs-software Aus Reinfeld",
    "wof:placetype":"venue"
},
  "geometry": {"coordinates":[10.480961,53.835342],"type":"Point"}
}