{
  "type": "Feature",
  "properties": {
    "iso:country":"DE",
    "sg:address":"Sommerseite 47",
    "sg:city":"Schleiz",
    "sg:phone":"+49 3663/423563",
    "sg:postcode":"07907",
    "sg:province":"Th\u00fcringen",
    "wof:name":"B. Prager",
    "wof:placetype":"venue"
},
  "geometry": {"coordinates":[11.8352870941,50.5605964661],"type":"Point"}
}