{
  "type": "Feature",
  "properties": {
    "iso:country":"DE",
    "sg:address":"Heinrich-Becker-Str. 9",
    "sg:city":"Rinteln",
    "sg:phone":"+49 5754/92054",
    "sg:postcode":"31737",
    "sg:province":"Niedersachsen",
    "wof:name":"Deutscher Amateur-radio- Club E. V.",
    "wof:placetype":"venue"
},
  "geometry": {"coordinates":[9.1482067108,52.1356697083],"type":"Point"}
}