{
  "type": "Feature",
  "properties": {
    "iso:country":"DE",
    "sg:address":"Sudetenstr. 3",
    "sg:city":"Glauburg",
    "sg:phone":"+49 6041/223",
    "sg:postcode":"63695",
    "sg:province":"Hessen",
    "wof:name":"Kath. Pfarramt St. Judas Thadd\u00e4us",
    "wof:placetype":"venue"
},
  "geometry": {"coordinates":[9.0123176575,50.3263587952],"type":"Point"}
}