{
  "type": "Feature",
  "properties": {
    "iso:country":"DE",
    "sg:address":"Am Stadtpark 11",
    "sg:city":"Haldensleben",
    "sg:phone":"+49 3904/40314",
    "sg:postcode":"39340",
    "sg:province":"Sachsen-Anhalt",
    "wof:name":"Geotec Ingenieurleistungen Dr. Schubert Gmbh",
    "wof:placetype":"venue"
},
  "geometry": {"coordinates":[11.4227228165,52.2987823486],"type":"Point"}
}