{
  "type": "Feature",
  "properties": {
    "iso:country":"DE",
    "sg:address":"Engerser Str. 86",
    "sg:city":"Neuwied",
    "sg:phone":"+49 2631/22424",
    "sg:postcode":"56564",
    "sg:province":"Rheinland-Pfalz",
    "wof:name":"Rudolf Menzel",
    "wof:placetype":"venue"
},
  "geometry": {"coordinates":[7.4613962173,50.4248352051],"type":"Point"}
}