{
  "type": "Feature",
  "properties": {
    "iso:country":"DE",
    "sg:address":"Robert-Perthel-Str. 12",
    "sg:city":"K\u00f6ln",
    "sg:phone":"+49 221/175771",
    "sg:postcode":"50739",
    "sg:province":"Nordrhein-Westfalen",
    "wof:name":"Rook Innenausbau Gmbh & Co. Kg",
    "wof:placetype":"venue"
},
  "geometry": {"coordinates":[6.922929,50.979301],"type":"Point"}
}