{
  "type": "Feature",
  "properties": {
    "iso:country":"DE",
    "sg:address":"Kolberger Str. 12",
    "sg:city":"Leverkusen",
    "sg:phone":"+49 2171/760891",
    "sg:postcode":"51381",
    "sg:province":"Nordrhein-Westfalen",
    "wof:name":"Kawka & Co. Malerwerkstatt Gmbh",
    "wof:placetype":"venue"
},
  "geometry": {"coordinates":[7.025043,51.061527],"type":"Point"}
}