{
  "type": "Feature",
  "properties": {
    "iso:country":"DE",
    "sg:address":"B\u00f6dcherstr.",
    "sg:city":"Halberstadt",
    "sg:phone":"+49 3941/441167",
    "sg:postcode":"38820",
    "sg:province":"Sachsen-Anhalt",
    "wof:name":"Hallenbad",
    "wof:placetype":"venue"
},
  "geometry": {"coordinates":[11.0445899963,51.8972740173],"type":"Point"}
}