{
  "type": "Feature",
  "properties": {
    "iso:country":"DE",
    "sg:address":"Bahnhofstr. 33",
    "sg:city":"Halle",
    "sg:phone":"+49 5201/81633",
    "sg:postcode":"33790",
    "sg:province":"Nordrhein-Westfalen",
    "wof:name":"Schmidt Natursteinbetrieb Gmbh",
    "wof:placetype":"venue"
},
  "geometry": {"coordinates":[8.3596019745,52.0582504272],"type":"Point"}
}