{
  "type": "Feature",
  "properties": {
    "iso:country":"DE",
    "sg:address":"Maximilianstr. 10",
    "sg:city":"M\u00fcnchen",
    "sg:phone":"+49 89/2907370",
    "sg:postcode":"80539",
    "sg:province":"Bayern",
    "wof:name":"Prof. Peter Seifert Architekt",
    "wof:placetype":"venue"
},
  "geometry": {"coordinates":[11.580069,48.139053],"type":"Point"}
}