{
  "type": "Feature",
  "properties": {
    "iso:country":"DE",
    "sg:address":"Kirschenallee 4",
    "sg:city":"Neustrelitz",
    "sg:phone":"+49 3981/443510",
    "sg:postcode":"17235",
    "sg:province":"Mecklenburg-Vorpommern",
    "wof:name":"Europcar Autovermietung Gmbh",
    "wof:placetype":"venue"
},
  "geometry": {"coordinates":[13.075142,53.356449],"type":"Point"}
}