{
  "type": "Feature",
  "properties": {
    "iso:country":"DE",
    "sg:address":"Bahnhofstr. 61",
    "sg:city":"Baden-Baden",
    "sg:phone":"+49 4972/2150840",
    "sg:postcode":"76532",
    "sg:province":"Baden-W\u00fcrttemberg",
    "wof:name":"Kwh Metallwarenfabrik Wolf Gmbh",
    "wof:placetype":"venue"
},
  "geometry": {"coordinates":[8.213788,48.811569],"type":"Point"}
}