{
  "type": "Feature",
  "properties": {
    "iso:country":"DE",
    "sg:address":"Edisonstr. 19",
    "sg:city":"Berlin",
    "sg:phone":"+49 30/5371146",
    "sg:postcode":"12459",
    "sg:province":"Berlin",
    "wof:name":"Rossmann Drogeriemarkt",
    "wof:placetype":"venue"
},
  "geometry": {"coordinates":[13.513731,52.465061],"type":"Point"}
}