{
  "type": "Feature",
  "properties": {
    "iso:country":"DE",
    "sg:address":"Julius-Krais-Str. 34",
    "sg:city":"Talheim",
    "sg:phone":"+49 4971/3321896",
    "sg:postcode":"74388",
    "sg:province":"Baden-W\u00fcrttemberg",
    "wof:name":"Walter Medien Gmbh",
    "wof:placetype":"venue"
},
  "geometry": {"coordinates":[9.20038414,49.0837059021],"type":"Point"}
}