{
  "type": "Feature",
  "properties": {
    "iso:country":"DE",
    "sg:address":"Haeckelstr. 7",
    "sg:city":"Weimar",
    "sg:phone":"+49 3643/511390",
    "sg:postcode":"99425",
    "sg:province":"Th\u00fcringen",
    "wof:name":"Hanns Von M\u00fchlenfels Rechtsanwalt",
    "wof:placetype":"venue"
},
  "geometry": {"coordinates":[11.3307800293,50.9718208313],"type":"Point"}
}