{
  "type": "Feature",
  "properties": {
    "iso:country":"DE",
    "sg:address":"Berliner Str. 12",
    "sg:city":"Neu-Isenburg",
    "sg:phone":"+49 6102/33334",
    "sg:postcode":"63263",
    "sg:province":"Hessen",
    "wof:name":"Immobilien Consulting Gmbh",
    "wof:placetype":"venue"
},
  "geometry": {"coordinates":[8.705615,50.058285],"type":"Point"}
}