{
  "type": "Feature",
  "properties": {
    "iso:country":"DE",
    "sg:address":"Deutschherrnstr.19",
    "sg:city":"M\u00fcnnerstadt",
    "sg:phone":"+49 9733/4407",
    "sg:postcode":"97702",
    "sg:province":"Bayern",
    "wof:name":"Fussb\u00f6den Und Bel\u00e4ge Fa.reinhold Haupt.",
    "wof:placetype":"venue"
},
  "geometry": {"coordinates":[10.196795,50.250076],"type":"Point"}
}