{
  "type": "Feature",
  "properties": {
    "iso:country":"DE",
    "sg:address":"Hallgarten 11",
    "sg:city":"Dausenau",
    "sg:phone":"+49 2603/12849",
    "sg:postcode":"56132",
    "sg:province":"Rheinland-Pfalz",
    "wof:name":"Pension Quilitz",
    "wof:placetype":"venue"
},
  "geometry": {"coordinates":[7.7576889992,50.3277549744],"type":"Point"}
}