{
  "type": "Feature",
  "properties": {
    "iso:country":"DE",
    "sg:address":"Marienstr. 26",
    "sg:city":"Hannover",
    "sg:phone":"+49 511/3522255",
    "sg:postcode":"30171",
    "sg:province":"Niedersachsen",
    "wof:name":"P & H Gmbh",
    "wof:placetype":"venue"
},
  "geometry": {"coordinates":[9.747048378,52.3689918518],"type":"Point"}
}