{
  "type": "Feature",
  "properties": {
    "iso:country":"DE",
    "sg:address":"Wollankstr. 5 a",
    "sg:city":"Berlin",
    "sg:phone":"+49 30/4867165",
    "sg:postcode":"13187",
    "sg:province":"Berlin",
    "wof:name":"Haus Und Wohnen Immobilien- Hausverwaltungs- Und",
    "wof:placetype":"venue"
},
  "geometry": {"coordinates":[13.398631,52.568096],"type":"Point"}
}