{
  "type": "Feature",
  "properties": {
    "iso:country":"DE",
    "sg:address":"Hauptstr. 44",
    "sg:city":"Forchheim",
    "sg:phone":"+49 9191/2208",
    "sg:postcode":"91301",
    "sg:province":"Bayern",
    "wof:name":"J. Schweizer + E. Reif Inhaber Walter Reif",
    "wof:placetype":"venue"
},
  "geometry": {"coordinates":[11.0588912964,49.7189292908],"type":"Point"}
}