{
  "type": "Feature",
  "properties": {
    "iso:country":"DE",
    "sg:address":"Siemsstr. 2",
    "sg:city":"Braunschweig",
    "sg:phone":"+49 5307/4698",
    "sg:postcode":"38110",
    "sg:province":"Niedersachsen",
    "wof:name":"Kraft Gmbh",
    "wof:placetype":"venue"
},
  "geometry": {"coordinates":[10.515863,52.320721],"type":"Point"}
}