{
  "type": "Feature",
  "properties": {
    "iso:country":"DE",
    "sg:address":"Osterstr. 42",
    "sg:city":"Hamburg",
    "sg:phone":"+49 40/407387",
    "sg:postcode":"20259",
    "sg:province":"Hamburg",
    "wof:name":"Klaus Wiegratz Eisen- Und R\u00f6hrenhandel",
    "wof:placetype":"venue"
},
  "geometry": {"coordinates":[9.957974,53.57502],"type":"Point"}
}