{
  "type": "Feature",
  "properties": {
    "iso:country":"DE",
    "sg:address":"Bachstr. 35",
    "sg:city":"Rodewisch",
    "sg:phone":"+49 3744/48278",
    "sg:postcode":"08228",
    "sg:province":"Sachsen",
    "wof:name":"Armin Bauer",
    "wof:placetype":"venue"
},
  "geometry": {"coordinates":[12.419458,50.532352],"type":"Point"}
}