{
  "type": "Feature",
  "properties": {
    "iso:country":"DE",
    "sg:address":"Hauptstr. 1",
    "sg:city":"Greding",
    "sg:phone":"+49 8463/464",
    "sg:postcode":"91171",
    "sg:province":"Bayern",
    "wof:name":"Katholisches Pfarramt St. Leodegar",
    "wof:placetype":"venue"
},
  "geometry": {"coordinates":[11.2781095505,49.0211715698],"type":"Point"}
}