{
  "type": "Feature",
  "properties": {
    "iso:country":"DE",
    "sg:address":"H\u00f6lderlinstr. 11",
    "sg:city":"Berlin",
    "sg:postcode":"14050",
    "sg:province":"Berlin",
    "wof:name":"Papagei Verm\u00f6gens- Verwaltung Gmbh",
    "wof:placetype":"venue"
},
  "geometry": {"coordinates":[13.2730178833,52.5105247498],"type":"Point"}
}