{
  "type": "Feature",
  "properties": {
    "iso:country":"DE",
    "sg:address":"D\u00fcnhagen 9",
    "sg:city":"Betheln",
    "sg:phone":"+49 5182/1614",
    "sg:postcode":"31032",
    "sg:province":"Niedersachsen",
    "wof:name":"Dieter M\u00f6ller",
    "wof:placetype":"venue"
},
  "geometry": {"coordinates":[9.7964477539,52.1140708923],"type":"Point"}
}