{
  "type": "Feature",
  "properties": {
    "iso:country":"DE",
    "sg:address":"Am W\u00f6rlitzer Bahnhof",
    "sg:city":"Dessau",
    "sg:postcode":"06844",
    "sg:province":"Sachsen-Anhalt",
    "wof:name":"Kohlehandel Gmbh",
    "wof:placetype":"venue"
},
  "geometry": {"coordinates":[12.238025,51.840931],"type":"Point"}
}