{
  "type": "Feature",
  "properties": {
    "iso:country":"DE",
    "sg:address":"Comeniusstr. 139",
    "sg:city":"Dresden",
    "sg:postcode":"01309",
    "sg:province":"Sachsen",
    "wof:name":"Emv In Dresden Ges. F\u00fcr Pr\u00fcfung Elektromag-",
    "wof:placetype":"venue"
},
  "geometry": {"coordinates":[13.785076,51.036209],"type":"Point"}
}