{
  "type": "Feature",
  "properties": {
    "iso:country":"DE",
    "sg:address":"Anger 72",
    "sg:city":"Freienhagen",
    "sg:phone":"+49 36083/50071",
    "sg:postcode":"37318",
    "sg:province":"Th\u00fcringen",
    "wof:name":"Josef Kaspari",
    "wof:placetype":"venue"
},
  "geometry": {"coordinates":[10.053897,51.415577],"type":"Point"}
}