{
  "type": "Feature",
  "properties": {
    "iso:country":"DE",
    "sg:address":"Haus Nr. 9",
    "sg:city":"Furtwangen",
    "sg:phone":"+49 7723/7420",
    "sg:postcode":"78120",
    "sg:province":"Baden-W\u00fcrttemberg",
    "wof:name":"Gasthof Michelhof",
    "wof:placetype":"venue"
},
  "geometry": {"coordinates":[8.2065601349,48.0480384827],"type":"Point"}
}