{
  "type": "Feature",
  "properties": {
    "iso:country":"DE",
    "sg:address":"Lindenstr. 16",
    "sg:city":"Hohenstein",
    "sg:phone":"+49 6120/5409",
    "sg:postcode":"65329",
    "sg:province":"Hessen",
    "wof:name":"Aartal Omnibus Gmbh",
    "wof:placetype":"venue"
},
  "geometry": {"coordinates":[8.124261,50.192181],"type":"Point"}
}