{
  "type": "Feature",
  "properties": {
    "iso:country":"DE",
    "sg:address":"Paderborner Str. 33",
    "sg:city":"Salzkotten",
    "sg:phone":"+49 5258/940830",
    "sg:postcode":"33154",
    "sg:province":"Nordrhein-Westfalen",
    "wof:name":"Josef Lieneke",
    "wof:placetype":"venue"
},
  "geometry": {"coordinates":[8.6158733368,51.6750259399],"type":"Point"}
}