{
  "type": "Feature",
  "properties": {
    "iso:country":"DE",
    "sg:address":"Leddiner Weg 2",
    "sg:city":"Kyritz",
    "sg:phone":"+49 33971/52266",
    "sg:postcode":"16866",
    "sg:province":"Brandenburg",
    "wof:name":"Elektromotoren Und Pumpen Wagner",
    "wof:placetype":"venue"
},
  "geometry": {"coordinates":[12.397668,52.936333],"type":"Point"}
}