{
  "type": "Feature",
  "properties": {
    "iso:country":"DE",
    "sg:address":"Oberfeldstr. 1",
    "sg:city":"Frankfurt",
    "sg:phone":"+49 69/571931",
    "sg:postcode":"60439",
    "sg:province":"Hessen",
    "wof:name":"Horst Eise",
    "wof:placetype":"venue"
},
  "geometry": {"coordinates":[8.6227655411,50.1544418335],"type":"Point"}
}