{
  "type": "Feature",
  "properties": {
    "iso:country":"DE",
    "sg:address":"Talstr. 41",
    "sg:city":"Wegefarth",
    "sg:phone":"+49 37321/4553",
    "sg:postcode":"09600",
    "sg:province":"Sachsen",
    "wof:name":"Arnd Talkenberger",
    "wof:placetype":"venue"
},
  "geometry": {"coordinates":[13.2397842407,50.921913147],"type":"Point"}
}