{
  "type": "Feature",
  "properties": {
    "iso:country":"DE",
    "sg:address":"Im B\u00f6ge 3",
    "sg:city":"Peine",
    "sg:phone":"+49 5171/57133",
    "sg:postcode":"31226",
    "sg:province":"Niedersachsen",
    "wof:name":"W. Bronn",
    "wof:placetype":"venue"
},
  "geometry": {"coordinates":[10.176071167,52.2997055054],"type":"Point"}
}