{
  "type": "Feature",
  "properties": {
    "iso:country":"DE",
    "sg:address":"Hageb\u00f6cker Str. 99",
    "sg:city":"G\u00fcstrow",
    "sg:phone":"+49 3843/69540",
    "sg:postcode":"18273",
    "sg:province":"Mecklenburg-Vorpommern",
    "wof:name":"U. Neuendorff Architekt",
    "wof:placetype":"venue"
},
  "geometry": {"coordinates":[12.170994,53.793674],"type":"Point"}
}