{
  "type": "Feature",
  "properties": {
    "iso:country":"DE",
    "sg:address":"Uhlandstr. 39",
    "sg:city":"Dresden",
    "sg:phone":"+49 351/478130",
    "sg:postcode":"01069",
    "sg:province":"Sachsen",
    "wof:name":"Ernst & Young Deutsche Allgemeine Treuhand Ag",
    "wof:placetype":"venue"
},
  "geometry": {"coordinates":[13.7377300262,51.033367157],"type":"Point"}
}