{
  "type": "Feature",
  "properties": {
    "iso:country":"DE",
    "sg:address":"Eichenweg 9",
    "sg:city":"Kayhude",
    "sg:postcode":"23863",
    "sg:province":"Schleswig-Holstein",
    "wof:name":"Dieckmann Gmbh",
    "wof:placetype":"venue"
},
  "geometry": {"coordinates":[10.1329164505,53.7585830688],"type":"Point"}
}