{
  "type": "Feature",
  "properties": {
    "iso:country":"DE",
    "sg:address":"Nast\u00e4tter Str. 2",
    "sg:city":"Miehlen",
    "sg:phone":"+49 4967/725756",
    "sg:postcode":"56357",
    "sg:province":"Rheinland-Pfalz",
    "wof:name":"Harald Wrbalandproduktenhandel Undm\u00dchlenbetrieb Gmbh",
    "wof:placetype":"venue"
},
  "geometry": {"coordinates":[7.834205,50.221783],"type":"Point"}
}