{
  "type": "Feature",
  "properties": {
    "iso:country":"DE",
    "sg:address":"August-Grotehenne-Str. 10",
    "sg:city":"Langelsheim",
    "sg:phone":"+49 5326/1410",
    "sg:postcode":"38685",
    "sg:province":"Niedersachsen",
    "wof:name":"Post-apotheke",
    "wof:placetype":"venue"
},
  "geometry": {"coordinates":[10.332513,51.936016],"type":"Point"}
}