{
  "type": "Feature",
  "properties": {
    "iso:country":"DE",
    "sg:address":"Rodenberger Allee 37",
    "sg:city":"Bad Nenndorf",
    "sg:phone":"+49 5723/2185",
    "sg:postcode":"31542",
    "sg:province":"Niedersachsen",
    "wof:name":"Heinrich Kr\u00f6mer",
    "wof:placetype":"venue"
},
  "geometry": {"coordinates":[9.368161,52.328754],"type":"Point"}
}