{
  "type": "Feature",
  "properties": {
    "iso:country":"DE",
    "sg:address":"Marienstr. 7a",
    "sg:city":"Krauschwitz",
    "sg:phone":"+49 35771/69101",
    "sg:postcode":"02957",
    "sg:province":"Sachsen",
    "wof:name":"Birgit Schacher",
    "wof:placetype":"venue"
},
  "geometry": {"coordinates":[14.7213258743,51.5187225342],"type":"Point"}
}