{
  "type": "Feature",
  "properties": {
    "iso:country":"DE",
    "sg:address":"55278",
    "sg:city":"Dolgesheim",
    "sg:phone":"+49 6733/212",
    "sg:postcode":"55278",
    "sg:province":"Rheinland-Pfalz",
    "wof:name":"Ev. Pfarramt",
    "wof:placetype":"venue"
},
  "geometry": {"coordinates":[8.2562799454,49.7935791016],"type":"Point"}
}