{
  "type": "Feature",
  "properties": {
    "iso:country":"DE",
    "sg:address":"Katharinenstr. 7",
    "sg:city":"Blankenburg",
    "sg:phone":"+49 3944/364216",
    "sg:postcode":"38889",
    "sg:province":"Sachsen-Anhalt",
    "wof:name":"Elisabeth Brettschneider",
    "wof:placetype":"venue"
},
  "geometry": {"coordinates":[10.9547224045,51.7900505066],"type":"Point"}
}