{
  "type": "Feature",
  "properties": {
    "iso:country":"DE",
    "sg:address":"Franziskanerstr. 49",
    "sg:city":"Essen",
    "sg:phone":"+49 201/282526",
    "sg:postcode":"45139",
    "sg:province":"Nordrhein-Westfalen",
    "wof:name":"A. Pischner",
    "wof:placetype":"venue"
},
  "geometry": {"coordinates":[7.0288,51.454872],"type":"Point"}
}