{
  "type": "Feature",
  "properties": {
    "iso:country":"DE",
    "sg:address":"Postfach 1229:: 35437 Linden:: Germany.^^Kirchstr 12::",
    "sg:city":"Linden",
    "sg:phone":"+49 6403/6594",
    "sg:postcode":"35440",
    "sg:province":"Hessen",
    "wof:name":"Volksbank Leihgestern Eg",
    "wof:placetype":"venue"
},
  "geometry": {"coordinates":[8.676963,50.52861],"type":"Point"}
}