{
  "type": "Feature",
  "properties": {
    "iso:country":"DE",
    "sg:address":"Haar 8",
    "sg:city":"Illschwang",
    "sg:phone":"+49 9661/4266",
    "sg:postcode":"92278",
    "sg:province":"Bayern",
    "wof:name":"Schwab",
    "wof:placetype":"venue"
},
  "geometry": {"coordinates":[11.7182836533,49.4787216187],"type":"Point"}
}