{
  "type": "Feature",
  "properties": {
    "iso:country":"DE",
    "sg:address":"Ewaldstr. 1",
    "sg:city":"Bocholt",
    "sg:phone":"+49 2871/17209",
    "sg:postcode":"46395",
    "sg:province":"Nordrhein-Westfalen",
    "wof:name":"Haus Matschke",
    "wof:placetype":"venue"
},
  "geometry": {"coordinates":[6.6218829155,51.8344573975],"type":"Point"}
}