{
  "type": "Feature",
  "properties": {
    "iso:country":"DE",
    "sg:address":"Eilbeker Weg 161",
    "sg:city":"Hamburg",
    "sg:phone":"+49 40/20978882",
    "sg:postcode":"22089",
    "sg:province":"Hamburg",
    "wof:name":"B & S Pflegedienst Eilbek",
    "wof:placetype":"venue"
},
  "geometry": {"coordinates":[10.051702,53.572063],"type":"Point"}
}