{
  "type": "Feature",
  "properties": {
    "iso:country":"DE",
    "sg:address":"Glindower Str. 28",
    "sg:city":"Klaistow",
    "sg:phone":"+49 33206/60195",
    "sg:postcode":"14547",
    "sg:province":"Brandenburg",
    "wof:name":"Spargelhof Beelitz Beteiligungs- Und",
    "wof:placetype":"venue"
},
  "geometry": {"coordinates":[12.8527841568,52.2883377075],"type":"Point"}
}