{
  "type": "Feature",
  "properties": {
    "iso:country":"DE",
    "sg:address":"M\u00fchlweg 22",
    "sg:city":"Dillingen",
    "sg:phone":"+49 9071/3326",
    "sg:postcode":"89407",
    "sg:province":"Bayern",
    "wof:name":"Weimann",
    "wof:placetype":"venue"
},
  "geometry": {"coordinates":[10.541736,48.554882],"type":"Point"}
}