{
  "type": "Feature",
  "properties": {
    "iso:country":"DE",
    "sg:address":"Max-Planck-Str.",
    "sg:city":"Spaichingen",
    "sg:phone":"+49 7424/7849",
    "sg:postcode":"78549",
    "sg:province":"Baden-W\u00fcrttemberg",
    "wof:name":"Spielotheken- Und Gastst\u00e4tten Gmbh",
    "wof:placetype":"venue"
},
  "geometry": {"coordinates":[8.7349233627,48.0682029724],"type":"Point"}
}