{
  "type": "Feature",
  "properties": {
    "iso:country":"DE",
    "sg:address":"Weihergasse 14",
    "sg:city":"Wiesbaden",
    "sg:phone":"+49 611/61706",
    "sg:postcode":"65203",
    "sg:province":"Hessen",
    "wof:name":"Oberhof 24",
    "wof:placetype":"venue"
},
  "geometry": {"coordinates":[8.2369222641,50.0500488281],"type":"Point"}
}