{
  "type": "Feature",
  "properties": {
    "iso:country":"DE",
    "sg:address":"Kaiserhofstr. 4",
    "sg:city":"Schw\u00e4bisch Gm\u00fcnd",
    "sg:phone":"+49 7173/929992",
    "sg:postcode":"73529",
    "sg:province":"Baden-W\u00fcrttemberg",
    "wof:name":"G\u00fcnther Barth",
    "wof:placetype":"venue"
},
  "geometry": {"coordinates":[9.8875780106,48.7910308838],"type":"Point"}
}