{
  "type": "Feature",
  "properties": {
    "iso:country":"DE",
    "sg:address":"Hauptstr. 184",
    "sg:city":"Schwalbach",
    "sg:phone":"+49 6834/52038",
    "sg:postcode":"66773",
    "sg:province":"Saarland",
    "wof:name":"Walter Kreutzer Gmbh",
    "wof:placetype":"venue"
},
  "geometry": {"coordinates":[6.813522,49.302719],"type":"Point"}
}