{
  "type": "Feature",
  "properties": {
    "iso:country":"DE",
    "sg:address":"Brunnenberg",
    "sg:city":"Kirchheimbolanden",
    "sg:phone":"+49 6352/2149",
    "sg:postcode":"67292",
    "sg:province":"Rheinland-Pfalz",
    "wof:name":"Transportbeton Kirchheimbol. Verwaltungsges. Mbh",
    "wof:placetype":"venue"
},
  "geometry": {"coordinates":[7.9594268799,49.6794891357],"type":"Point"}
}