{
  "type": "Feature",
  "properties": {
    "iso:country":"DE",
    "sg:address":"Venantius-Arnold-Str. 8",
    "sg:city":"Wertheim",
    "sg:phone":"+49 9342/6788",
    "sg:postcode":"97877",
    "sg:province":"Baden-W\u00fcrttemberg",
    "wof:name":"Kath. Pfarramt St. Lioba",
    "wof:placetype":"venue"
},
  "geometry": {"coordinates":[9.5379190445,49.7643814087],"type":"Point"}
}