{
  "type": "Feature",
  "properties": {
    "iso:country":"DE",
    "sg:address":"Forststr. 4",
    "sg:city":"Brackenheim",
    "sg:phone":"+49 7135/6931",
    "sg:postcode":"74336",
    "sg:province":"Baden-W\u00fcrttemberg",
    "wof:name":"H. St\u00f6hr",
    "wof:placetype":"venue"
},
  "geometry": {"coordinates":[9.0745153427,49.0873146057],"type":"Point"}
}