{
  "type": "Feature",
  "properties": {
    "iso:country":"DE",
    "sg:address":"M\u00fchlfelder Str. 20",
    "sg:city":"Herrsching",
    "sg:phone":"+49 8152/1889",
    "sg:postcode":"82211",
    "sg:province":"Bayern",
    "wof:name":"Reich Gmbh",
    "wof:placetype":"venue"
},
  "geometry": {"coordinates":[11.1753511429,47.9966888428],"type":"Point"}
}