{
  "type": "Feature",
  "properties": {
    "iso:country":"DE",
    "sg:address":"Bergstr. 2",
    "sg:city":"Seesen",
    "sg:phone":"+49 5381/1200",
    "sg:postcode":"38723",
    "sg:province":"Niedersachsen",
    "wof:name":"Reiseb\u00fcro Weihrauch Gmbh",
    "wof:placetype":"venue"
},
  "geometry": {"coordinates":[10.1783571243,51.8875656128],"type":"Point"}
}