{
  "type": "Feature",
  "properties": {
    "iso:country":"DE",
    "sg:address":"Wassergartenstr. 1c",
    "sg:city":"Hanau",
    "sg:phone":"+49 6181/79808",
    "sg:postcode":"63454",
    "sg:province":"Hessen",
    "wof:name":"Pils-und Weinstube",
    "wof:placetype":"venue"
},
  "geometry": {"coordinates":[8.8893842697,50.1770896912],"type":"Point"}
}