{
  "type": "Feature",
  "properties": {
    "iso:country":"DE",
    "sg:address":"S\u00e4gemattenstr. 12",
    "sg:city":"Teningen",
    "sg:phone":"+49 7641/8321",
    "sg:postcode":"79331",
    "sg:province":"Baden-W\u00fcrttemberg",
    "wof:name":"W. Moessingen",
    "wof:placetype":"venue"
},
  "geometry": {"coordinates":[7.806351,48.135506],"type":"Point"}
}