{
  "type": "Feature",
  "properties": {
    "iso:country":"DE",
    "sg:address":"Feldstr. 6",
    "sg:city":"Neunkirchen",
    "sg:postcode":"91233",
    "sg:province":"Bayern",
    "wof:name":"Astec Anlagen Und Steuerungstechnik Gmbh",
    "wof:placetype":"venue"
},
  "geometry": {"coordinates":[11.345449,49.540703],"type":"Point"}
}