{
  "type": "Feature",
  "properties": {
    "iso:country":"DE",
    "sg:address":"Hauptstr. 6",
    "sg:city":"P\u00f6lich",
    "sg:phone":"+49 6507/3189",
    "sg:postcode":"54340",
    "sg:province":"Rheinland-Pfalz",
    "wof:name":"Adolf Schu",
    "wof:placetype":"venue"
},
  "geometry": {"coordinates":[6.8486428261,49.7961044312],"type":"Point"}
}