{
  "type": "Feature",
  "properties": {
    "iso:country":"DE",
    "sg:address":"Duchtlinger Str. 4d",
    "sg:city":"Hilzingen",
    "sg:phone":"+49 7731",
    "sg:postcode":"78247",
    "sg:province":"Baden-W\u00fcrttemberg",
    "wof:name":"Dream World Webdesign",
    "wof:placetype":"venue"
},
  "geometry": {"coordinates":[8.778841,47.765556],"type":"Point"}
}