{
  "type": "Feature",
  "properties": {
    "iso:country":"DE",
    "sg:address":"Hauptstr. 26",
    "sg:city":"Wiesenbach",
    "sg:phone":"+49 6223/40114",
    "sg:postcode":"69257",
    "sg:province":"Baden-W\u00fcrttemberg",
    "wof:name":"Heimatmuseum",
    "wof:placetype":"venue"
},
  "geometry": {"coordinates":[8.804827,49.359306],"type":"Point"}
}