{
  "type": "Feature",
  "properties": {
    "iso:country":"DE",
    "sg:address":"Lindenstr. 16",
    "sg:city":"Neuenhagen",
    "sg:phone":"+49 3342/80994",
    "sg:postcode":"15366",
    "sg:province":"Brandenburg",
    "wof:name":"Riemer & Dittrich Ohg",
    "wof:placetype":"venue"
},
  "geometry": {"coordinates":[13.6730871201,52.5242576599],"type":"Point"}
}