{
  "type": "Feature",
  "properties": {
    "iso:country":"DE",
    "sg:address":"Breite Str. 25",
    "sg:city":"Warendorf",
    "sg:phone":"+49 2581/8801",
    "sg:postcode":"48231",
    "sg:province":"Nordrhein-Westfalen",
    "wof:name":"Bernhard Brokamp",
    "wof:placetype":"venue"
},
  "geometry": {"coordinates":[7.996623,51.946198],"type":"Point"}
}