{
  "type": "Feature",
  "properties": {
    "iso:country":"DE",
    "sg:address":"Damm 2",
    "sg:city":"Braunschweig",
    "sg:phone":"+49 531/1212",
    "sg:postcode":"38100",
    "sg:province":"Niedersachsen",
    "wof:name":"Walter Kahn Gmbh & Co. Kg",
    "wof:placetype":"venue"
},
  "geometry": {"coordinates":[10.5224075317,52.262424469],"type":"Point"}
}