{
  "type": "Feature",
  "properties": {
    "iso:country":"DE",
    "sg:address":"Venloer Str. 412",
    "sg:city":"K\u00f6ln",
    "sg:phone":"+49 221/5506625",
    "sg:postcode":"50825",
    "sg:province":"Nordrhein-Westfalen",
    "wof:name":"Euro Trend Import-export Warenhandel E. K.",
    "wof:placetype":"venue"
},
  "geometry": {"coordinates":[6.9127278328,50.9528923035],"type":"Point"}
}