{
  "type": "Feature",
  "properties": {
    "iso:country":"DE",
    "sg:address":"Benzstr 22",
    "sg:city":"Malsch",
    "sg:phone":"+49 7246/92340",
    "sg:postcode":"76316",
    "sg:province":"Baden-W\u00fcrttemberg",
    "wof:name":"Malscher Sitzm\u00f6bel Heinrich St\u00f6cklein Gmbh",
    "wof:placetype":"venue"
},
  "geometry": {"coordinates":[8.314925,48.890308],"type":"Point"}
}