{
  "type": "Feature",
  "properties": {
    "iso:country":"DE",
    "sg:address":"Weberstra\u00dfe 14",
    "sg:city":"Kaiserslautern",
    "sg:phone":"+49 631/3607773",
    "sg:postcode":"67655",
    "sg:province":"Rheinland-Pfalz",
    "wof:name":"Wladi-rockstock - Internetkneipe In Kaiserslautern",
    "wof:placetype":"venue"
},
  "geometry": {"coordinates":[7.768697,49.440037],"type":"Point"}
}