{
  "type": "Feature",
  "properties": {
    "iso:country":"DE",
    "sg:address":"Markt 14",
    "sg:city":"St. Augustin",
    "sg:phone":"+49 2241/21075",
    "sg:postcode":"53757",
    "sg:province":"Nordrhein-Westfalen",
    "wof:name":"Dresdner Bank",
    "wof:placetype":"venue"
},
  "geometry": {"coordinates":[7.212401,50.778591],"type":"Point"}
}