{
  "type": "Feature",
  "properties": {
    "iso:country":"DE",
    "sg:address":"Schlachthausstr. 39",
    "sg:city":"G\u00fcnzburg",
    "sg:phone":"+49 8221/6550",
    "sg:postcode":"89312",
    "sg:province":"Bayern",
    "wof:name":"Restaurant Alexis Sorbas",
    "wof:placetype":"venue"
},
  "geometry": {"coordinates":[10.2760066986,48.4584503174],"type":"Point"}
}