{
  "type": "Feature",
  "properties": {
    "iso:country":"DE",
    "sg:address":"T\u00f6lzer Str. 8",
    "sg:city":"Brunnthal",
    "sg:postcode":"85649",
    "sg:province":"Bayern",
    "wof:name":"Dwc Dr. Wagner Consulting Gmbh",
    "wof:placetype":"venue"
},
  "geometry": {"coordinates":[11.659095,47.994736],"type":"Point"}
}