{
  "type": "Feature",
  "properties": {
    "iso:country":"DE",
    "sg:address":"Europaplatz 5",
    "sg:city":"Bad Kreuznach",
    "sg:postcode":"55543",
    "sg:province":"Rheinland-Pfalz",
    "wof:name":"Vertrauens\u00e4rztlicher-dienst Der Lva Rheinland-pfalz",
    "wof:placetype":"venue"
},
  "geometry": {"coordinates":[7.8645610809,49.8434906006],"type":"Point"}
}