{
  "type": "Feature",
  "properties": {
    "iso:country":"DE",
    "sg:address":"Ausbau Ost",
    "sg:city":"F\u00fcrstenwalde",
    "sg:postcode":"15517",
    "sg:province":"Brandenburg",
    "wof:name":"Priebe & Co. Gmbh",
    "wof:placetype":"venue"
},
  "geometry": {"coordinates":[14.0817899704,52.3679199219],"type":"Point"}
}