{
  "type": "Feature",
  "properties": {
    "iso:country":"DE",
    "sg:address":"Ulmenstr. 10",
    "sg:city":"Berlin",
    "sg:phone":"+49 30/40541151",
    "sg:postcode":"13467",
    "sg:province":"Berlin",
    "wof:name":"Greulich",
    "wof:placetype":"venue"
},
  "geometry": {"coordinates":[13.31114,52.616028],"type":"Point"}
}