{
  "type": "Feature",
  "properties": {
    "iso:country":"DE",
    "sg:address":"Helgol\u00e4nder Str. 2-10",
    "sg:city":"Rendsburg",
    "sg:phone":"+49 6103/921797",
    "sg:postcode":"24768",
    "sg:province":"Schleswig-Holstein",
    "wof:name":"Ritter Wolek Werbeagentur Gmbh",
    "wof:placetype":"venue"
},
  "geometry": {"coordinates":[8.377027,50.397953],"type":"Point"}
}