{
  "type": "Feature",
  "properties": {
    "iso:country":"DE",
    "sg:address":"Gildemeisterstr. 60",
    "sg:city":"Bielefeld",
    "sg:phone":"+49 4952/059590",
    "sg:postcode":"33689",
    "sg:province":"Nordrhein-Westfalen",
    "wof:name":"D\u00fcrkopp F\u00f6rdertechnik Gmbh",
    "wof:placetype":"venue"
},
  "geometry": {"coordinates":[8.5994768143,51.9284706116],"type":"Point"}
}