{
  "type": "Feature",
  "properties": {
    "iso:country":"DE",
    "sg:address":"Kornblumenweg 5",
    "sg:city":"Wunstorf",
    "sg:phone":"+49 5031",
    "sg:postcode":"31515",
    "sg:province":"Niedersachsen",
    "wof:name":"Pop-chor Wunstorf",
    "wof:placetype":"venue"
},
  "geometry": {"coordinates":[9.4782514572,52.4286804199],"type":"Point"}
}