{
  "type": "Feature",
  "properties": {
    "iso:country":"DE",
    "sg:address":"Berghofer Str. 135",
    "sg:city":"Dortmund",
    "sg:phone":"+49 231/484605",
    "sg:postcode":"44269",
    "sg:province":"Nordrhein-Westfalen",
    "wof:name":"Haus Gockel",
    "wof:placetype":"venue"
},
  "geometry": {"coordinates":[7.5320267677,51.4781684875],"type":"Point"}
}