{
  "type": "Feature",
  "properties": {
    "iso:country":"DE",
    "sg:address":"Einsteinstr 1",
    "sg:city":"Dillingen",
    "sg:phone":"+49 9071/79390",
    "sg:postcode":"89407",
    "sg:province":"Bayern",
    "wof:name":"Lippert Gmbh Blechbearbeitung",
    "wof:placetype":"venue"
},
  "geometry": {"coordinates":[10.51858,48.586941],"type":"Point"}
}