{
  "type": "Feature",
  "properties": {
    "iso:country":"DE",
    "sg:address":"Steinmeerstr. 7",
    "sg:city":"Haren",
    "sg:phone":"+49 5932/2660",
    "sg:postcode":"49733",
    "sg:province":"Niedersachsen",
    "wof:name":"B. Kr\u00fc\u00dfel",
    "wof:placetype":"venue"
},
  "geometry": {"coordinates":[7.327595,52.798256],"type":"Point"}
}