{
  "type": "Feature",
  "properties": {
    "iso:country":"DE",
    "sg:address":"Gereonstr. 1",
    "sg:city":"J\u00fclich",
    "sg:phone":"+49 2461/57710",
    "sg:postcode":"52428",
    "sg:province":"Nordrhein-Westfalen",
    "wof:name":"Rdw Datenverarbeitung F\u00fcr Die Wohnungswirtschaft Gmbh",
    "wof:placetype":"venue"
},
  "geometry": {"coordinates":[6.357034,50.909096],"type":"Point"}
}