{
  "type": "Feature",
  "properties": {
    "iso:country":"DE",
    "sg:address":"Scharoldstr. 6",
    "sg:city":"W\u00fcrzburg",
    "sg:phone":"+49 931/21296",
    "sg:postcode":"97080",
    "sg:province":"Bayern",
    "wof:name":"G\u00fcnther Steinhardt",
    "wof:placetype":"venue"
},
  "geometry": {"coordinates":[9.9489898682,49.8023681641],"type":"Point"}
}