{
  "type": "Feature",
  "properties": {
    "iso:country":"DE",
    "sg:address":"Ludwig-Ganghofer-Str. 7",
    "sg:city":"Gr\u00fcnwald",
    "sg:phone":"+49 89/6410481",
    "sg:postcode":"82031",
    "sg:province":"Bayern",
    "wof:name":"Wvag Wohnungsverm\u00f6gens Ag",
    "wof:placetype":"venue"
},
  "geometry": {"coordinates":[11.5306339264,48.0464401245],"type":"Point"}
}