{
  "type": "Feature",
  "properties": {
    "iso:country":"DE",
    "sg:address":"Manderscheider Str. 8",
    "sg:city":"K\u00f6ln",
    "sg:phone":"+49 221/421180",
    "sg:postcode":"50937",
    "sg:province":"Nordrhein-Westfalen",
    "wof:name":"Russiden Warenhandels Gmbh",
    "wof:placetype":"venue"
},
  "geometry": {"coordinates":[6.9242191315,50.9137802124],"type":"Point"}
}