{
  "type": "Feature",
  "properties": {
    "iso:country":"DE",
    "sg:address":"K\u00f6ditzer Str. 9",
    "sg:city":"Hof",
    "sg:phone":"+49 9281/63780",
    "sg:postcode":"95030",
    "sg:province":"Bayern",
    "wof:name":"Comet",
    "wof:placetype":"venue"
},
  "geometry": {"coordinates":[11.895532608,50.3224449158],"type":"Point"}
}