{
  "type": "Feature",
  "properties": {
    "iso:country":"DE",
    "sg:address":"Neust\u00e4dter Weg 70",
    "sg:city":"Hamm",
    "sg:phone":"+49 2307/18471",
    "sg:postcode":"59077",
    "sg:province":"Nordrhein-Westfalen",
    "wof:name":"Heinrich Sch\u00e4fer",
    "wof:placetype":"venue"
},
  "geometry": {"coordinates":[7.68831,51.635208],"type":"Point"}
}