{
  "type": "Feature",
  "properties": {
    "iso:country":"DE",
    "sg:address":"Byfanger Str. 228",
    "sg:city":"Essen",
    "sg:phone":"+49 201/483330",
    "sg:postcode":"45257",
    "sg:province":"Nordrhein-Westfalen",
    "wof:name":"Bauunternehmung Stephan Dunker Gmbh",
    "wof:placetype":"venue"
},
  "geometry": {"coordinates":[7.098482,51.397369],"type":"Point"}
}