{
  "type": "Feature",
  "properties": {
    "iso:country":"DE",
    "sg:address":"Schweriner Str. 58",
    "sg:city":"Wittenf\u00f6rden",
    "sg:postcode":"19073",
    "sg:province":"Mecklenburg-Vorpommern",
    "wof:name":"Immobilienverwaltungs- Gesellschaft Objekt Wiebendorf",
    "wof:placetype":"venue"
},
  "geometry": {"coordinates":[11.322465,53.628613],"type":"Point"}
}