{
  "type": "Feature",
  "properties": {
    "iso:country":"DE",
    "sg:address":"Fritz-Reuter-Str. 4",
    "sg:city":"Plauen",
    "sg:phone":"+49 3741/529641",
    "sg:postcode":"08525",
    "sg:province":"Sachsen",
    "wof:name":"Pension Vogtl\u00e4nder Inh. Roswitha Hertel",
    "wof:placetype":"venue"
},
  "geometry": {"coordinates":[12.1194887161,50.5132255554],"type":"Point"}
}