{
  "type": "Feature",
  "properties": {
    "iso:country":"DE",
    "sg:address":"Breite Str. 15",
    "sg:city":"Nufringen",
    "sg:phone":"+49 7032/82835",
    "sg:postcode":"71154",
    "sg:province":"Baden-W\u00fcrttemberg",
    "wof:name":"Karl Schneck",
    "wof:placetype":"venue"
},
  "geometry": {"coordinates":[8.889090538,48.6211929321],"type":"Point"}
}