{
  "type": "Feature",
  "properties": {
    "iso:country":"DE",
    "sg:address":"Schelde-Lahn-Str. 28",
    "sg:city":"Angelburg",
    "sg:phone":"+49 6464/404",
    "sg:postcode":"35719",
    "sg:province":"Hessen",
    "wof:name":"H. Jakobi",
    "wof:placetype":"venue"
},
  "geometry": {"coordinates":[8.411666,50.805542],"type":"Point"}
}