{
  "type": "Feature",
  "properties": {
    "iso:country":"DE",
    "sg:address":"Baumstr. 17",
    "sg:city":"Hannover",
    "sg:phone":"+49 511/810125",
    "sg:postcode":"30171",
    "sg:province":"Niedersachsen",
    "wof:name":"Cti Immobilien Gmbh",
    "wof:placetype":"venue"
},
  "geometry": {"coordinates":[9.7500658035,52.3682861328],"type":"Point"}
}