{
  "type": "Feature",
  "properties": {
    "iso:country":"DE",
    "sg:address":"Neue S\u00fclze 5-6",
    "sg:city":"L\u00fcneburg",
    "sg:postcode":"21335",
    "sg:province":"Niedersachsen",
    "wof:name":"L\u00fcneburger Assistenz Ggmbh",
    "wof:placetype":"venue"
},
  "geometry": {"coordinates":[10.404833,53.24884],"type":"Point"}
}