{
  "type": "Feature",
  "properties": {
    "iso:country":"DE",
    "sg:address":"Kempener Strasse 77",
    "sg:city":"Heinsberg",
    "sg:phone":"+49 2452/5000",
    "sg:postcode":"52525",
    "sg:province":"Nordrhein-Westfalen",
    "wof:name":"Parrot Breeding Farm (papageienzucht M. Wagner)",
    "wof:placetype":"venue"
},
  "geometry": {"coordinates":[6.098915,51.072384],"type":"Point"}
}