{
  "type": "Feature",
  "properties": {
    "iso:country":"DE",
    "sg:address":"M\u00fchlenstr. 2",
    "sg:city":"Liebenburg",
    "sg:phone":"+49 5346/1857",
    "sg:postcode":"38704",
    "sg:province":"Niedersachsen",
    "wof:name":"Gastwirtschaft Karlheinz Hansen",
    "wof:placetype":"venue"
},
  "geometry": {"coordinates":[10.4430246353,51.9978752136],"type":"Point"}
}