{
  "type": "Feature",
  "properties": {
    "iso:country":"DE",
    "sg:address":"Mittelstr. 18",
    "sg:city":"Lehrte",
    "sg:phone":"+49 5132/58013",
    "sg:postcode":"31275",
    "sg:province":"Niedersachsen",
    "wof:name":"Form 57 Ges. F\u00fcr Private Und Gewerbl. Objektplanungen Mbh",
    "wof:placetype":"venue"
},
  "geometry": {"coordinates":[9.974835,52.378475],"type":"Point"}
}