{
  "type": "Feature",
  "properties": {
    "iso:country":"DE",
    "sg:address":"Chasotstr. 25",
    "sg:city":"L\u00fcbeck",
    "sg:phone":"+49 451/610581",
    "sg:postcode":"23566",
    "sg:province":"Schleswig-Holstein",
    "wof:name":"Hotel Sch\u00f6nwald Garni",
    "wof:placetype":"venue"
},
  "geometry": {"coordinates":[10.7137393951,53.8684997559],"type":"Point"}
}