{
  "type": "Feature",
  "properties": {
    "iso:country":"DE",
    "sg:address":"Allmannsweilerstr. 25",
    "sg:city":"Friedrichshafen",
    "sg:phone":"+49 7541/770",
    "sg:postcode":"88046",
    "sg:province":"Baden-W\u00fcrttemberg",
    "wof:name":"Zf Friedrichshafen Ag",
    "wof:placetype":"venue"
},
  "geometry": {"coordinates":[9.4942646027,47.6661224365],"type":"Point"}
}