{
  "type": "Feature",
  "properties": {
    "iso:country":"DE",
    "sg:address":"Bahnhofstr. 7",
    "sg:city":"Pansdorf",
    "sg:phone":"+49 4945/04231",
    "sg:postcode":"23689",
    "sg:province":"Schleswig-Holstein",
    "wof:name":"Bertram & Graf Gmbh",
    "wof:placetype":"venue"
},
  "geometry": {"coordinates":[10.7084102631,53.9815788269],"type":"Point"}
}