{
  "type": "Feature",
  "properties": {
    "iso:country":"DE",
    "sg:address":"Hauptstr. 31",
    "sg:city":"Hennigsdorf",
    "sg:phone":"+49 3302/88980",
    "sg:postcode":"16761",
    "sg:province":"Brandenburg",
    "wof:name":"Autohaus Schmidt Gmbh",
    "wof:placetype":"venue"
},
  "geometry": {"coordinates":[13.208121,52.635628],"type":"Point"}
}