{
  "type": "Feature",
  "properties": {
    "iso:country":"DE",
    "sg:address":"Neuh\u00e4user Str. 32",
    "sg:city":"Wolfsburg",
    "sg:postcode":"38448",
    "sg:province":"Niedersachsen",
    "wof:name":"Sozialstation Vorsfelde Ggmbh",
    "wof:placetype":"venue"
},
  "geometry": {"coordinates":[10.847523,52.431049],"type":"Point"}
}