{
  "type": "Feature",
  "properties": {
    "iso:country":"DE",
    "sg:address":"B\u00fcrgerstr. 2",
    "sg:city":"Hagen",
    "sg:phone":"+49 2331/81458",
    "sg:postcode":"58097",
    "sg:province":"Nordrhein-Westfalen",
    "wof:name":"J. Greef",
    "wof:placetype":"venue"
},
  "geometry": {"coordinates":[7.4776887894,51.3764801025],"type":"Point"}
}