{
  "type": "Feature",
  "properties": {
    "iso:country":"DE",
    "sg:address":"Adam-Opel-Str. 49",
    "sg:city":"R\u00fcsselsheim",
    "sg:phone":"+49 6142/62663",
    "sg:postcode":"65428",
    "sg:province":"Hessen",
    "wof:name":"Aral Ag",
    "wof:placetype":"venue"
},
  "geometry": {"coordinates":[8.4295988083,49.9848403931],"type":"Point"}
}