{
  "type": "Feature",
  "properties": {
    "iso:country":"DE",
    "sg:address":"Untere K\u00f6nigsstr. 79",
    "sg:city":"Kassel",
    "sg:postcode":"34117",
    "sg:province":"Hessen",
    "wof:name":"Tres Metallhandels-gmbh",
    "wof:placetype":"venue"
},
  "geometry": {"coordinates":[9.500127,51.318375],"type":"Point"}
}