{
  "type": "Feature",
  "properties": {
    "iso:country":"DE",
    "sg:address":"Danziger Str. 5",
    "sg:city":"Laupheim",
    "sg:phone":"+49 7392/2278",
    "sg:postcode":"88471",
    "sg:province":"Baden-W\u00fcrttemberg",
    "wof:name":"Rudolf Seitz",
    "wof:placetype":"venue"
},
  "geometry": {"coordinates":[9.871829,48.222122],"type":"Point"}
}