{
  "type": "Feature",
  "properties": {
    "iso:country":"DE",
    "sg:address":"Lemgoer Str. 62",
    "sg:city":"Detmold",
    "sg:phone":"+49 5231/35161",
    "sg:postcode":"32756",
    "sg:province":"Nordrhein-Westfalen",
    "wof:name":"Blumenm\u00e4dchen",
    "wof:placetype":"venue"
},
  "geometry": {"coordinates":[8.879328,51.947769],"type":"Point"}
}