{
  "type": "Feature",
  "properties": {
    "iso:country":"DE",
    "sg:address":"Felix-Klipstein-Weg 17",
    "sg:city":"Laubach",
    "sg:phone":"+49 6405/6310",
    "sg:postcode":"35321",
    "sg:province":"Hessen",
    "wof:name":"Frei- Und Hallenbad",
    "wof:placetype":"venue"
},
  "geometry": {"coordinates":[8.9876384735,50.5482215881],"type":"Point"}
}