{
  "type": "Feature",
  "properties": {
    "iso:country":"DE",
    "sg:address":"Am Waldrain 6",
    "sg:city":"Bad D\u00fcrrheim",
    "sg:postcode":"78073",
    "sg:province":"Baden-W\u00fcrttemberg",
    "wof:name":"Kvg Kartographische Verlagsgesellschaft Ohg",
    "wof:placetype":"venue"
},
  "geometry": {"coordinates":[8.544141,48.021385],"type":"Point"}
}