{
  "type": "Feature",
  "properties": {
    "iso:country":"DE",
    "sg:address":"Kirchstr. 12",
    "sg:city":"Hoyerswerda",
    "sg:phone":"+49 3571/405141",
    "sg:postcode":"02977",
    "sg:province":"Sachsen",
    "wof:name":"Apotheke Am Kirchplatz",
    "wof:placetype":"venue"
},
  "geometry": {"coordinates":[14.241915,51.437817],"type":"Point"}
}