{
  "type": "Feature",
  "properties": {
    "iso:country":"DE",
    "sg:address":"Untere Alte Poststr. 126",
    "sg:city":"Warmensteinach",
    "sg:postcode":"95485",
    "sg:province":"Bayern",
    "wof:name":"Nele E. K.",
    "wof:placetype":"venue"
},
  "geometry": {"coordinates":[11.7762794495,49.9877586365],"type":"Point"}
}