{
  "type": "Feature",
  "properties": {
    "iso:country":"DE",
    "sg:address":"Feldstr. 39",
    "sg:city":"Worpswede",
    "sg:postcode":"27726",
    "sg:province":"Niedersachsen",
    "wof:name":"Gl\u00f6ckner-versand",
    "wof:placetype":"venue"
},
  "geometry": {"coordinates":[8.9622335434,53.2711677551],"type":"Point"}
}