{
  "type": "Feature",
  "properties": {
    "iso:country":"DE",
    "sg:address":"Hauptstr. 24",
    "sg:city":"Issersheilingen",
    "sg:phone":"+49 36043/70515",
    "sg:postcode":"99947",
    "sg:province":"Th\u00fcringen",
    "wof:name":"Werner Kapell",
    "wof:placetype":"venue"
},
  "geometry": {"coordinates":[10.6479921341,51.2048301697],"type":"Point"}
}