{
  "type": "Feature",
  "properties": {
    "iso:country":"DE",
    "sg:address":"Marktstr. 13",
    "sg:city":"Winnenden",
    "sg:phone":"+49 7195/3213",
    "sg:postcode":"71364",
    "sg:province":"Baden-W\u00fcrttemberg",
    "wof:name":"E. K\u00f6gel",
    "wof:placetype":"venue"
},
  "geometry": {"coordinates":[9.3969717026,48.8770103455],"type":"Point"}
}