{
  "type": "Feature",
  "properties": {
    "iso:country":"DE",
    "sg:address":"Schillerstr. 25",
    "sg:city":"Munderkingen",
    "sg:phone":"+49 7393/1347",
    "sg:postcode":"89597",
    "sg:province":"Baden-W\u00fcrttemberg",
    "wof:name":"Malerbetrieb Rudolf Sch\u00f6ttle",
    "wof:placetype":"venue"
},
  "geometry": {"coordinates":[9.644464,48.233006],"type":"Point"}
}