{
  "type": "Feature",
  "properties": {
    "iso:country":"DE",
    "sg:address":"Am Langen Steg 12",
    "sg:city":"Gelnhausen",
    "sg:phone":"+49 6051/923640",
    "sg:postcode":"63571",
    "sg:province":"Hessen",
    "wof:name":"Internetwork Marketing - Horst-dieter Schipporeit",
    "wof:placetype":"venue"
},
  "geometry": {"coordinates":[9.210893631,50.2039527893],"type":"Point"}
}