{
  "type": "Feature",
  "properties": {
    "iso:country":"DE",
    "sg:address":"Carl-von-Linne-Str. 25",
    "sg:city":"Neubrandenburg",
    "sg:phone":"+49 395/5823008",
    "sg:postcode":"17033",
    "sg:province":"Mecklenburg-Vorpommern",
    "wof:name":"Paul Verwaltungs- Und Vermietungs Gmbh & Co.",
    "wof:placetype":"venue"
},
  "geometry": {"coordinates":[13.2284584045,53.5593185425],"type":"Point"}
}