{
  "type": "Feature",
  "properties": {
    "iso:country":"DE",
    "sg:address":"Duisburger Str. 70",
    "sg:city":"N\u00fcrnberg",
    "sg:phone":"+49 911/5215498",
    "sg:postcode":"90451",
    "sg:province":"Bayern",
    "wof:name":"Reka Kabelgesellschaft Mbh",
    "wof:placetype":"venue"
},
  "geometry": {"coordinates":[11.047668,49.398899],"type":"Point"}
}