{
  "type": "Feature",
  "properties": {
    "iso:country":"DE",
    "sg:address":"Querstr. 2",
    "sg:city":"Gr\u00fcneberg",
    "sg:phone":"+49 33094/80798",
    "sg:postcode":"16775",
    "sg:province":"Brandenburg",
    "wof:name":"H. Sch\u00e4fer",
    "wof:placetype":"venue"
},
  "geometry": {"coordinates":[13.2108659744,52.8661842346],"type":"Point"}
}