{
  "type": "Feature",
  "properties": {
    "iso:country":"DE",
    "sg:address":"In den Blumentriftern 30",
    "sg:city":"Salzgitter",
    "sg:phone":"+49 4953/4117051",
    "sg:postcode":"38226",
    "sg:province":"Niedersachsen",
    "wof:name":"Allgemeine Privatkunden Ag",
    "wof:placetype":"venue"
},
  "geometry": {"coordinates":[10.33017,52.154194],"type":"Point"}
}