{
  "type": "Feature",
  "properties": {
    "iso:country":"DE",
    "sg:address":"Gunzenhausener Str. 3",
    "sg:city":"Bechhofen",
    "sg:phone":"+49 9822/277",
    "sg:postcode":"91572",
    "sg:province":"Bayern",
    "wof:name":"G. Weinmann",
    "wof:placetype":"venue"
},
  "geometry": {"coordinates":[10.5505046844,49.1585388184],"type":"Point"}
}