{
  "type": "Feature",
  "properties": {
    "iso:country":"DE",
    "sg:address":"Feuerwehrstr 2",
    "sg:city":"Singen",
    "sg:phone":"+49 7731/400361",
    "sg:postcode":"78224",
    "sg:province":"Baden-W\u00fcrttemberg",
    "wof:name":"Waldsch\u00fctz Gmbh",
    "wof:placetype":"venue"
},
  "geometry": {"coordinates":[8.835158,47.762634],"type":"Point"}
}