{
  "type": "Feature",
  "properties": {
    "iso:country":"DE",
    "sg:address":"J\u00f6llenbecker Str. 2",
    "sg:city":"Werther",
    "sg:phone":"+49 4952/0397190",
    "sg:postcode":"33824",
    "sg:province":"Nordrhein-Westfalen",
    "wof:name":"Ravensberger Schmierstoffvertrieb Gmbh",
    "wof:placetype":"venue"
},
  "geometry": {"coordinates":[8.424681,52.079506],"type":"Point"}
}