{
  "type": "Feature",
  "properties": {
    "iso:country":"DE",
    "sg:address":"Brunnenweg 38",
    "sg:city":"Offenbach",
    "sg:phone":"+49 69/852474",
    "sg:postcode":"63071",
    "sg:province":"Hessen",
    "wof:name":"Heinz Roth",
    "wof:placetype":"venue"
},
  "geometry": {"coordinates":[8.7785387039,50.0832633972],"type":"Point"}
}