{
  "type": "Feature",
  "properties": {
    "iso:country":"DE",
    "sg:address":"Sonnenstr. 46",
    "sg:city":"Mannheim",
    "sg:phone":"+49 621/771910",
    "sg:postcode":"68307",
    "sg:province":"Baden-W\u00fcrttemberg",
    "wof:name":"Margrethe Schnetzer",
    "wof:placetype":"venue"
},
  "geometry": {"coordinates":[8.4481811523,49.546661377],"type":"Point"}
}