{
  "type": "Feature",
  "properties": {
    "iso:country":"DE",
    "sg:address":"T\u00f6lzer Str. 27",
    "sg:city":"Reichersbeuern",
    "sg:phone":"+49 8041/3910",
    "sg:postcode":"83677",
    "sg:province":"Bayern",
    "wof:name":"Dichtl Gmbh",
    "wof:placetype":"venue"
},
  "geometry": {"coordinates":[11.6276473999,47.7653236389],"type":"Point"}
}