{
  "type": "Feature",
  "properties": {
    "iso:country":"DE",
    "sg:address":"Kampstr. 9",
    "sg:city":"Twistringen",
    "sg:phone":"+49 4243/93100",
    "sg:postcode":"27239",
    "sg:province":"Niedersachsen",
    "wof:name":"Zeltverleih Fritz Kuhlmann",
    "wof:placetype":"venue"
},
  "geometry": {"coordinates":[8.6414909363,52.7949752808],"type":"Point"}
}