{
  "type": "Feature",
  "properties": {
    "iso:country":"DE",
    "sg:address":"Altenhofer Str. 135",
    "sg:city":"Solingen",
    "sg:phone":"+49 212/331558",
    "sg:postcode":"42719",
    "sg:province":"Nordrhein-Westfalen",
    "wof:name":"H.-j. Schneider",
    "wof:placetype":"venue"
},
  "geometry": {"coordinates":[7.025391,51.181053],"type":"Point"}
}