{
  "type": "Feature",
  "properties": {
    "iso:country":"DE",
    "sg:address":"Luwenstr. 20",
    "sg:city":"Duisburg",
    "sg:phone":"+49 203/471950",
    "sg:postcode":"47178",
    "sg:province":"Nordrhein-Westfalen",
    "wof:name":"H. Hoffmann",
    "wof:placetype":"venue"
},
  "geometry": {"coordinates":[6.714149,51.549797],"type":"Point"}
}