{
  "type": "Feature",
  "properties": {
    "iso:country":"DE",
    "sg:address":"Am Sportplatz 2",
    "sg:city":"Zella-Mehlis",
    "sg:phone":"+49 3682/3868",
    "sg:postcode":"98544",
    "sg:province":"Th\u00fcringen",
    "wof:name":"Bergblick",
    "wof:placetype":"venue"
},
  "geometry": {"coordinates":[10.674551,50.664856],"type":"Point"}
}