{
  "type": "Feature",
  "properties": {
    "iso:country":"DE",
    "sg:address":"Gumbertstr. 178",
    "sg:city":"D\u00fcsseldorf",
    "sg:phone":"+49 211/213809",
    "sg:postcode":"40229",
    "sg:province":"Nordrhein-Westfalen",
    "wof:name":"Hotel-restaurant Haus Gumbert",
    "wof:placetype":"venue"
},
  "geometry": {"coordinates":[6.8433890343,51.1997566223],"type":"Point"}
}