{
  "type": "Feature",
  "properties": {
    "iso:country":"DE",
    "sg:address":"Teerofen 5",
    "sg:city":"Oranienburg",
    "sg:phone":"+49 33051/25545",
    "sg:postcode":"16515",
    "sg:province":"Brandenburg",
    "wof:name":"Biergarten-pension Waldfrieden",
    "wof:placetype":"venue"
},
  "geometry": {"coordinates":[13.2023496628,52.7920951843],"type":"Point"}
}