{
  "type": "Feature",
  "properties": {
    "iso:country":"DE",
    "sg:address":"Max-Planck-Str. 4",
    "sg:city":"D\u00fcsseldorf",
    "sg:postcode":"40237",
    "sg:province":"Nordrhein-Westfalen",
    "wof:name":"Industrieverband Zur F\u00f6rderung Bauens Mit Stahlblech",
    "wof:placetype":"venue"
},
  "geometry": {"coordinates":[6.812504,51.239899],"type":"Point"}
}