{
  "type": "Feature",
  "properties": {
    "iso:country":"DE",
    "sg:address":"Kistlerhofstr. 176",
    "sg:city":"M\u00fcnchen",
    "sg:phone":"+49 89/7485840",
    "sg:postcode":"81379",
    "sg:province":"Bayern",
    "wof:name":"Nibler Gmbh",
    "wof:placetype":"venue"
},
  "geometry": {"coordinates":[11.5068473816,48.0944671631],"type":"Point"}
}