{
  "type": "Feature",
  "properties": {
    "iso:country":"DE",
    "sg:address":"M\u00fcnzstr. 31",
    "sg:city":"Schongau",
    "sg:phone":"+49 8861/7341",
    "sg:postcode":"86956",
    "sg:province":"Bayern",
    "wof:name":"J. Vogl Mech. Werkstatt",
    "wof:placetype":"venue"
},
  "geometry": {"coordinates":[10.896723,47.813908],"type":"Point"}
}