{
  "type": "Feature",
  "properties": {
    "iso:country":"DE",
    "sg:address":"Am Propsteiberg 1",
    "sg:city":"Warstein",
    "sg:phone":"+49 2902/71087",
    "sg:postcode":"59581",
    "sg:province":"Nordrhein-Westfalen",
    "wof:name":"Katholisches Pfarramt St. Pankratius",
    "wof:placetype":"venue"
},
  "geometry": {"coordinates":[8.338139534,51.4836921692],"type":"Point"}
}