{
  "type": "Feature",
  "properties": {
    "iso:country":"DE",
    "sg:address":"Hirtengasse 6",
    "sg:city":"Salzhemmendorf",
    "sg:phone":"+49 5153/5314",
    "sg:postcode":"31020",
    "sg:province":"Niedersachsen",
    "wof:name":"G\u00fcnter Breyer",
    "wof:placetype":"venue"
},
  "geometry": {"coordinates":[9.651936,52.092697],"type":"Point"}
}