{
  "type": "Feature",
  "properties": {
    "iso:country":"DE",
    "sg:address":"Duracher Str. 15",
    "sg:city":"Durach",
    "sg:phone":"+49 831/65544",
    "sg:postcode":"87471",
    "sg:province":"Bayern",
    "wof:name":"Klaus-peter Seidel",
    "wof:placetype":"venue"
},
  "geometry": {"coordinates":[10.3272037506,47.696056366],"type":"Point"}
}