{
  "type": "Feature",
  "properties": {
    "iso:country":"DE",
    "sg:address":"Dorfstr. 4",
    "sg:city":"Teutschenthal",
    "sg:phone":"+49 34601/25355",
    "sg:postcode":"06179",
    "sg:province":"Sachsen-Anhalt",
    "wof:name":"Krebs & H\u00e4u\u00dfler",
    "wof:placetype":"venue"
},
  "geometry": {"coordinates":[11.802226,51.475159],"type":"Point"}
}