{
  "type": "Feature",
  "properties": {
    "iso:country":"DE",
    "sg:address":"Ringstr. 3",
    "sg:city":"Kammerstein",
    "sg:phone":"+49 9122/85630",
    "sg:postcode":"91126",
    "sg:province":"Bayern",
    "wof:name":"Herzog Kg",
    "wof:placetype":"venue"
},
  "geometry": {"coordinates":[10.9780330658,49.2873573303],"type":"Point"}
}