{
  "type": "Feature",
  "properties": {
    "iso:country":"DE",
    "sg:address":"Kruppstr. 21",
    "sg:city":"Ahlen",
    "sg:phone":"+49 2382/63554",
    "sg:postcode":"59227",
    "sg:province":"Nordrhein-Westfalen",
    "wof:name":"Bolte Ohg",
    "wof:placetype":"venue"
},
  "geometry": {"coordinates":[7.941193,51.775959],"type":"Point"}
}