{
  "type": "Feature",
  "properties": {
    "iso:country":"DE",
    "sg:address":"Heggelbacher Str. 4",
    "sg:city":"Leutkirch",
    "sg:phone":"+49 4975/613621",
    "sg:postcode":"88299",
    "sg:province":"Baden-W\u00fcrttemberg",
    "wof:name":"Binder Tiefbau Gmbh & Co. Kg",
    "wof:placetype":"venue"
},
  "geometry": {"coordinates":[9.982709,47.807915],"type":"Point"}
}