{
  "type": "Feature",
  "properties": {
    "iso:country":"DE",
    "sg:address":"Elmstr. 5",
    "sg:city":"Ennigerloh",
    "sg:phone":"+49 2524/2202",
    "sg:postcode":"59320",
    "sg:province":"Nordrhein-Westfalen",
    "wof:name":"B. Landwehr Tabakwarenhdl.",
    "wof:placetype":"venue"
},
  "geometry": {"coordinates":[8.0246076584,51.8348770142],"type":"Point"}
}