{
  "type": "Feature",
  "properties": {
    "iso:country":"DE",
    "sg:address":"Rathausstr. 27",
    "sg:city":"K\u00f6nigsbrunn",
    "sg:phone":"+49 8231/4490",
    "sg:postcode":"86343",
    "sg:province":"Bayern",
    "wof:name":"E. Hahn Optiker",
    "wof:placetype":"venue"
},
  "geometry": {"coordinates":[10.8948669434,48.26770401],"type":"Point"}
}