{
  "type": "Feature",
  "properties": {
    "iso:country":"DE",
    "sg:address":"Burgweg 3",
    "sg:city":"Schelklingen",
    "sg:phone":"+49 7384/6164",
    "sg:postcode":"89601",
    "sg:province":"Baden-W\u00fcrttemberg",
    "wof:name":"Lorenz Gmbh",
    "wof:placetype":"venue"
},
  "geometry": {"coordinates":[9.64468,48.395302],"type":"Point"}
}