{
  "type": "Feature",
  "properties": {
    "iso:country":"DE",
    "sg:address":"Ulmenweg 17",
    "sg:city":"Markgr\u00f6ningen",
    "sg:phone":"+49 7145/3968",
    "sg:postcode":"71706",
    "sg:province":"Baden-W\u00fcrttemberg",
    "wof:name":"Sca Systemhaus F\u00fcr Computeranwendungen Mbh",
    "wof:placetype":"venue"
},
  "geometry": {"coordinates":[9.0753221512,48.9053688049],"type":"Point"}
}