{
  "type": "Feature",
  "properties": {
    "iso:country":"DE",
    "sg:address":"Gartenweg 1",
    "sg:city":"Altenm\u00fcnster",
    "sg:phone":"+49 8295/659",
    "sg:postcode":"86450",
    "sg:province":"Bayern",
    "wof:name":"H. Miggenrieder",
    "wof:placetype":"venue"
},
  "geometry": {"coordinates":[10.5882263184,48.4611701965],"type":"Point"}
}