{
  "type": "Feature",
  "properties": {
    "iso:country":"DE",
    "sg:address":"Marienbergstr. 21",
    "sg:city":"Rehfelde",
    "sg:phone":"+49 33435/320",
    "sg:postcode":"15345",
    "sg:province":"Brandenburg",
    "wof:name":"Herbert Baier",
    "wof:placetype":"venue"
},
  "geometry": {"coordinates":[13.890111,52.535408],"type":"Point"}
}