{
  "type": "Feature",
  "properties": {
    "iso:country":"DE",
    "sg:address":"Ahrweg 51",
    "sg:city":"Alfter",
    "sg:phone":"+49 228/641636",
    "sg:postcode":"53347",
    "sg:province":"Nordrhein-Westfalen",
    "wof:name":"Im M\u00fchlengrund",
    "wof:placetype":"venue"
},
  "geometry": {"coordinates":[7.0196762085,50.7094841003],"type":"Point"}
}