{
  "type": "Feature",
  "properties": {
    "iso:country":"DE",
    "sg:address":"Taunusstr. 24",
    "sg:city":"M\u00fchlheim",
    "sg:phone":"+49 6108/74451",
    "sg:postcode":"63165",
    "sg:province":"Hessen",
    "wof:name":"G. Becker Kunststopferei",
    "wof:placetype":"venue"
},
  "geometry": {"coordinates":[8.8559989929,50.1211700439],"type":"Point"}
}