{
  "type": "Feature",
  "properties": {
    "iso:country":"DE",
    "sg:address":"Baumeisterstr. 17",
    "sg:city":"Hamburg",
    "sg:phone":"+49 40/245724",
    "sg:postcode":"20099",
    "sg:province":"Hamburg",
    "wof:name":"L. B\u00f6hm Immobilienmakler",
    "wof:placetype":"venue"
},
  "geometry": {"coordinates":[10.0102977753,53.5551872253],"type":"Point"}
}