{
  "type": "Feature",
  "properties": {
    "iso:country":"DE",
    "sg:address":"Storchenmatt 3",
    "sg:city":"Laufenburg",
    "sg:phone":"+49 7763/5212",
    "sg:postcode":"79725",
    "sg:province":"Baden-W\u00fcrttemberg",
    "wof:name":"G\u00e4rtnerklause",
    "wof:placetype":"venue"
},
  "geometry": {"coordinates":[8.0528564453,47.5667572021],"type":"Point"}
}