{
  "type": "Feature",
  "properties": {
    "iso:country":"DE",
    "sg:address":"89176",
    "sg:city":"Asselfingen",
    "sg:phone":"+49 7345/21284",
    "sg:postcode":"89176",
    "sg:province":"Baden-W\u00fcrttemberg",
    "wof:name":"Mehrzweckhalle",
    "wof:placetype":"venue"
},
  "geometry": {"coordinates":[10.188235,48.529572],"type":"Point"}
}