{
  "type": "Feature",
  "properties": {
    "iso:country":"DE",
    "sg:address":"Uerdinger Str. 348",
    "sg:city":"Krefeld",
    "sg:phone":"+49 2151/598297",
    "sg:postcode":"47800",
    "sg:province":"Nordrhein-Westfalen",
    "wof:name":"Maria Haase",
    "wof:placetype":"venue"
},
  "geometry": {"coordinates":[6.596756,51.340897],"type":"Point"}
}