{
  "type": "Feature",
  "properties": {
    "iso:country":"DE",
    "sg:address":"Krotzenburger Str. 14",
    "sg:city":"Hanau",
    "sg:phone":"+49 6181/54216",
    "sg:postcode":"63457",
    "sg:province":"Hessen",
    "wof:name":"Monika Werner",
    "wof:placetype":"venue"
},
  "geometry": {"coordinates":[8.944806,50.101879],"type":"Point"}
}