{
  "type": "Feature",
  "properties": {
    "iso:country":"DE",
    "sg:address":"Schleinkoferstr. 4",
    "sg:city":"Cham",
    "sg:phone":"+49 9971/2161",
    "sg:postcode":"93413",
    "sg:province":"Bayern",
    "wof:name":"Philipp Heselberger Rechtsanwalt",
    "wof:placetype":"venue"
},
  "geometry": {"coordinates":[12.6630458832,49.2217559814],"type":"Point"}
}