{
  "type": "Feature",
  "properties": {
    "iso:country":"DE",
    "sg:address":"Schumannstr. 17",
    "sg:city":"Bremen",
    "sg:phone":"+49 421/215354",
    "sg:postcode":"28213",
    "sg:province":"Bremen",
    "wof:name":"Hans-g\u00fcnther Heu\u00df Architekt",
    "wof:placetype":"venue"
},
  "geometry": {"coordinates":[8.850652,53.086643],"type":"Point"}
}