{
  "type": "Feature",
  "properties": {
    "iso:country":"DE",
    "sg:address":"F\u00fcnfhausen 1",
    "sg:city":"C\u00f6lbe",
    "sg:phone":"+49 6427/92240",
    "sg:postcode":"35091",
    "sg:province":"Hessen",
    "wof:name":"Dickert Electronic Gmbh",
    "wof:placetype":"venue"
},
  "geometry": {"coordinates":[8.783705,50.848652],"type":"Point"}
}