{
  "type": "Feature",
  "properties": {
    "iso:country":"DE",
    "sg:address":"Im Kattenbusch 4",
    "sg:city":"Herne",
    "sg:phone":"+49 2325/50888",
    "sg:postcode":"44649",
    "sg:province":"Nordrhein-Westfalen",
    "wof:name":"Franz Cerne",
    "wof:placetype":"venue"
},
  "geometry": {"coordinates":[7.1509160995,51.5246582031],"type":"Point"}
}