{
  "type": "Feature",
  "properties": {
    "iso:country":"DE",
    "sg:address":"Oberhofenstr. 9/2",
    "sg:city":"G\u00f6ppingen",
    "sg:postcode":"73033",
    "sg:province":"Baden-W\u00fcrttemberg",
    "wof:name":"Walter Dietrich Kfz Zulassungen",
    "wof:placetype":"venue"
},
  "geometry": {"coordinates":[9.658023,48.704021],"type":"Point"}
}