{
  "type": "Feature",
  "properties": {
    "iso:country":"DE",
    "sg:address":"Wiesenstr. 14",
    "sg:city":"Gummersbach",
    "sg:phone":"+49 2261/29411",
    "sg:postcode":"51643",
    "sg:province":"Nordrhein-Westfalen",
    "wof:name":"Wis Wamhoff Immobilien Service Gmbh",
    "wof:placetype":"venue"
},
  "geometry": {"coordinates":[7.5769238472,51.0231895447],"type":"Point"}
}