{
  "type": "Feature",
  "properties": {
    "iso:country":"DE",
    "sg:address":"Sch\u00f6nbornstr. 56",
    "sg:city":"Bad Kissingen",
    "sg:phone":"+49 971/2553",
    "sg:postcode":"97688",
    "sg:province":"Bayern",
    "wof:name":"Leonhard Wiedamann",
    "wof:placetype":"venue"
},
  "geometry": {"coordinates":[10.06287,50.194191],"type":"Point"}
}