{
  "type": "Feature",
  "properties": {
    "iso:country":"DE",
    "sg:address":"Pfarrstr. 3a",
    "sg:city":"Suhl",
    "sg:phone":"+49 3681/304810",
    "sg:postcode":"98527",
    "sg:province":"Th\u00fcringen",
    "wof:name":"Karl Thorwald",
    "wof:placetype":"venue"
},
  "geometry": {"coordinates":[10.695292,50.610222],"type":"Point"}
}