{
  "type": "Feature",
  "properties": {
    "iso:country":"DE",
    "sg:address":"Eulenkrugstr. 67",
    "sg:city":"Hamburg",
    "sg:phone":"+49 40/6034363",
    "sg:postcode":"22359",
    "sg:province":"Hamburg",
    "wof:name":"Hans Luther",
    "wof:placetype":"venue"
},
  "geometry": {"coordinates":[10.170936,53.648205],"type":"Point"}
}