{
  "type": "Feature",
  "properties": {
    "iso:country":"DE",
    "sg:address":"Bergweghof 1",
    "sg:city":"Illingen",
    "sg:phone":"+49 7042/22304",
    "sg:postcode":"75428",
    "sg:province":"Baden-W\u00fcrttemberg",
    "wof:name":"Helmut Fink",
    "wof:placetype":"venue"
},
  "geometry": {"coordinates":[8.908169,48.96323],"type":"Point"}
}