{
  "type": "Feature",
  "properties": {
    "iso:country":"DE",
    "sg:address":"Bergstr. 11",
    "sg:city":"Wuppertal",
    "sg:phone":"+49 202/3890333",
    "sg:postcode":"42105",
    "sg:province":"Nordrhein-Westfalen",
    "wof:name":"Caritas Pflegestation",
    "wof:placetype":"venue"
},
  "geometry": {"coordinates":[7.143734,51.259571],"type":"Point"}
}