{
  "type": "Feature",
  "properties": {
    "iso:country":"DE",
    "sg:address":"Ettaler Str. 10",
    "sg:city":"Farchant",
    "sg:phone":"+49 8821/6788",
    "sg:postcode":"82490",
    "sg:province":"Bayern",
    "wof:name":"Frey-bautenschutz Gmbh",
    "wof:placetype":"venue"
},
  "geometry": {"coordinates":[11.113493,47.534389],"type":"Point"}
}