{
  "type": "Feature",
  "properties": {
    "iso:country":"DE",
    "sg:address":"Marktplatz 1",
    "sg:city":"Neuhof",
    "sg:phone":"+49 9107/887",
    "sg:postcode":"90616",
    "sg:province":"Bayern",
    "wof:name":"Robert Schuler",
    "wof:placetype":"venue"
},
  "geometry": {"coordinates":[10.6433162689,49.4568519592],"type":"Point"}
}