{
  "type": "Feature",
  "properties": {
    "iso:country":"DE",
    "sg:address":"Alte Grenzstr. 129 G",
    "sg:city":"Recklinghausen",
    "sg:postcode":"45663",
    "sg:province":"Nordrhein-Westfalen",
    "wof:name":"Pm Baumaschinen Gmbh",
    "wof:placetype":"venue"
},
  "geometry": {"coordinates":[7.23377,51.577412],"type":"Point"}
}