{
  "type": "Feature",
  "properties": {
    "iso:country":"DE",
    "sg:address":"75417",
    "sg:city":"M\u00fchlacker",
    "sg:phone":"+49 7041/2087",
    "sg:postcode":"75417",
    "sg:province":"Baden-W\u00fcrttemberg",
    "wof:name":"Hallenbad Cafeteria",
    "wof:placetype":"venue"
},
  "geometry": {"coordinates":[8.84832,48.948589],"type":"Point"}
}