{
  "type": "Feature",
  "properties": {
    "iso:country":"DE",
    "sg:address":"Ochtmannier Dorfstr. 16",
    "sg:city":"S\u00fcstedt",
    "sg:phone":"+49 4247/449",
    "sg:postcode":"27305",
    "sg:province":"Niedersachsen",
    "wof:name":"Reinhard Bartolles Architekt",
    "wof:placetype":"venue"
},
  "geometry": {"coordinates":[8.902775,52.822067],"type":"Point"}
}