{
  "type": "Feature",
  "properties": {
    "iso:country":"DE",
    "sg:address":"Sudermanstr. 12",
    "sg:city":"K\u00f6ln",
    "sg:postcode":"50670",
    "sg:province":"Nordrhein-Westfalen",
    "wof:name":"Die Extra Vaganten Gmbh",
    "wof:placetype":"venue"
},
  "geometry": {"coordinates":[6.9556779861,50.9513053894],"type":"Point"}
}