{
  "type": "Feature",
  "properties": {
    "iso:country":"DE",
    "sg:address":"Nentmannsdorf 80",
    "sg:city":"Bahretal",
    "sg:phone":"+49 35025/50639",
    "sg:postcode":"01819",
    "sg:province":"Sachsen",
    "wof:name":"G. Neumann",
    "wof:placetype":"venue"
},
  "geometry": {"coordinates":[13.881769,50.8946],"type":"Point"}
}