{
  "type": "Feature",
  "properties": {
    "iso:country":"DE",
    "sg:address":"Neue M\u00fchle 6",
    "sg:city":"Legden",
    "sg:phone":"+49 2566/98220",
    "sg:postcode":"48739",
    "sg:province":"Nordrhein-Westfalen",
    "wof:name":"Haustechnik Sprey Uplengen Gmbh",
    "wof:placetype":"venue"
},
  "geometry": {"coordinates":[7.092438221,52.0417900085],"type":"Point"}
}