{
  "type": "Feature",
  "properties": {
    "iso:country":"DE",
    "sg:address":"Strandstr. 7",
    "sg:city":"Juist",
    "sg:phone":"+49 4935/914050",
    "sg:postcode":"26571",
    "sg:province":"Niedersachsen",
    "wof:name":"L\u00fcckemann",
    "wof:placetype":"venue"
},
  "geometry": {"coordinates":[6.995713,53.678715],"type":"Point"}
}