{
  "type": "Feature",
  "properties": {
    "iso:country":"DE",
    "sg:address":"Alte Landstr. 1",
    "sg:city":"Prutting",
    "sg:phone":"+49 8036/1202",
    "sg:postcode":"83134",
    "sg:province":"Bayern",
    "wof:name":"Kererwirt",
    "wof:placetype":"venue"
},
  "geometry": {"coordinates":[12.2000770569,47.8950424194],"type":"Point"}
}