{
  "type": "Feature",
  "properties": {
    "iso:country":"DE",
    "sg:address":"Gartenstra\u00dfe 15",
    "sg:city":"Rehfelde",
    "sg:phone":"+49 33435/273",
    "sg:postcode":"15345",
    "sg:province":"Brandenburg",
    "wof:name":"Bestattungen Marunde",
    "wof:placetype":"venue"
},
  "geometry": {"coordinates":[13.90627,52.532509],"type":"Point"}
}