{
  "type": "Feature",
  "properties": {
    "iso:country":"DE",
    "sg:address":"Sch\u00fcleinstr. 1",
    "sg:city":"M\u00fcnchen",
    "sg:phone":"+49 89/43660945",
    "sg:postcode":"81673",
    "sg:province":"Bayern",
    "wof:name":"Krone Ag",
    "wof:placetype":"venue"
},
  "geometry": {"coordinates":[11.6417865753,48.1268577576],"type":"Point"}
}