{
  "type": "Feature",
  "properties": {
    "iso:country":"DE",
    "sg:address":"Werstener Dorfstr. 114",
    "sg:city":"D\u00fcsseldorf",
    "sg:phone":"+49 211/7606343",
    "sg:postcode":"40591",
    "sg:province":"Nordrhein-Westfalen",
    "wof:name":"Global Project Management E.k.",
    "wof:placetype":"venue"
},
  "geometry": {"coordinates":[6.825192,51.189819],"type":"Point"}
}