{
  "type": "Feature",
  "properties": {
    "iso:country":"DE",
    "sg:address":"Hubertusstr. 1",
    "sg:city":"Suhl",
    "sg:phone":"+49 3681/801970",
    "sg:postcode":"98527",
    "sg:province":"Th\u00fcringen",
    "wof:name":"Glock Fliesenfachhandel Gmbh",
    "wof:placetype":"venue"
},
  "geometry": {"coordinates":[10.7142190933,50.5878677368],"type":"Point"}
}