{
  "type": "Feature",
  "properties": {
    "iso:country":"DE",
    "sg:address":"Amag-Hilpert-Str. 4",
    "sg:city":"Pegnitz",
    "sg:phone":"+49 9241/2475",
    "sg:postcode":"91257",
    "sg:province":"Bayern",
    "wof:name":"W. Rosemann",
    "wof:placetype":"venue"
},
  "geometry": {"coordinates":[11.5496902466,49.7665290833],"type":"Point"}
}