{
  "type": "Feature",
  "properties": {
    "iso:country":"DE",
    "sg:address":"Borweg 18",
    "sg:city":"Bad Oeynhausen",
    "sg:phone":"+49 5731/93498",
    "sg:postcode":"32547",
    "sg:province":"Nordrhein-Westfalen",
    "wof:name":"Andreas Brante",
    "wof:placetype":"venue"
},
  "geometry": {"coordinates":[8.834418,52.195477],"type":"Point"}
}