{
  "type": "Feature",
  "properties": {
    "iso:country":"DE",
    "sg:address":"Sudetenstr. 37",
    "sg:city":"Bietigheim-Bissingen",
    "sg:phone":"+49 7142/65713",
    "sg:postcode":"74321",
    "sg:province":"Baden-W\u00fcrttemberg",
    "wof:name":"L. Coskun",
    "wof:placetype":"venue"
},
  "geometry": {"coordinates":[9.1474227905,48.9440803528],"type":"Point"}
}