{
  "type": "Feature",
  "properties": {
    "iso:country":"DE",
    "sg:address":"Poststr. 40",
    "sg:city":"Merzig",
    "sg:phone":"+49 6861/2451",
    "sg:postcode":"66663",
    "sg:province":"Saarland",
    "wof:name":"Kunzler Fleischwarenfabrik Gmbh & Co. Kg",
    "wof:placetype":"venue"
},
  "geometry": {"coordinates":[6.6385231018,49.4434394836],"type":"Point"}
}