{
  "type": "Feature",
  "properties": {
    "iso:country":"DE",
    "sg:address":"Hauptstr. 47",
    "sg:city":"Mosbach",
    "sg:phone":"+49 6261/5390",
    "sg:postcode":"74821",
    "sg:province":"Baden-W\u00fcrttemberg",
    "wof:name":"Somogyi",
    "wof:placetype":"venue"
},
  "geometry": {"coordinates":[9.145961,49.352921],"type":"Point"}
}