{
  "type": "Feature",
  "properties": {
    "iso:country":"DE",
    "sg:address":"Theodor-J\u00f6rg-Str. 4",
    "sg:city":"Waltenhausen",
    "sg:phone":"+49 8282/960878",
    "sg:postcode":"86480",
    "sg:province":"Bayern",
    "wof:name":"Lothar Walter",
    "wof:placetype":"venue"
},
  "geometry": {"coordinates":[10.366106987,48.1901168823],"type":"Point"}
}