{
  "type": "Feature",
  "properties": {
    "iso:country":"DE",
    "sg:address":"Warliner Str. 2",
    "sg:city":"Neubrandenburg",
    "sg:phone":"+49 395/45560",
    "sg:postcode":"17034",
    "sg:province":"Mecklenburg-Vorpommern",
    "wof:name":"B\u00fcrgel Wirtschafts- Informationen Lampe Gmbh",
    "wof:placetype":"venue"
},
  "geometry": {"coordinates":[13.2839651108,53.565322876],"type":"Point"}
}