{
  "type": "Feature",
  "properties": {
    "iso:country":"DE",
    "sg:address":"Langefort 14",
    "sg:city":"Sassenberg",
    "sg:phone":"+49 2583/1070",
    "sg:postcode":"48336",
    "sg:province":"Nordrhein-Westfalen",
    "wof:name":"Sch\u00fctzenverein: Homepage Des B\u00fcrgersch\u00fctzenvereins",
    "wof:placetype":"venue"
},
  "geometry": {"coordinates":[8.043056,51.98629],"type":"Point"}
}