{
  "type": "Feature",
  "properties": {
    "iso:country":"DE",
    "sg:address":"Friedrichstr. 24",
    "sg:city":"Gotha",
    "sg:phone":"+49 3621/36840",
    "sg:postcode":"99867",
    "sg:province":"Th\u00fcringen",
    "wof:name":"Heim Pfleger & Fr\u00f6hlich Steuerberatungs-gmbh",
    "wof:placetype":"venue"
},
  "geometry": {"coordinates":[10.7106266022,50.9448051453],"type":"Point"}
}