{
  "type": "Feature",
  "properties": {
    "iso:country":"DE",
    "sg:address":"Oberndorf 9",
    "sg:city":"St\u00f6rnstein",
    "sg:phone":"+49 9602/8752",
    "sg:postcode":"92721",
    "sg:province":"Bayern",
    "wof:name":"Sebastian Scharnagl",
    "wof:placetype":"venue"
},
  "geometry": {"coordinates":[12.202846,49.751518],"type":"Point"}
}