{
  "type": "Feature",
  "properties": {
    "iso:country":"DE",
    "sg:address":"Neuwieder Str. 28",
    "sg:city":"Dierdorf",
    "sg:phone":"+49 2689/2012",
    "sg:postcode":"56269",
    "sg:province":"Rheinland-Pfalz",
    "wof:name":"Solidwood Holzbau Gmbh",
    "wof:placetype":"venue"
},
  "geometry": {"coordinates":[7.6491689682,50.5476722717],"type":"Point"}
}