{
  "type": "Feature",
  "properties": {
    "iso:country":"DE",
    "sg:address":"Frauenstr. 2",
    "sg:city":"Ulm",
    "sg:phone":"+49 731/23723",
    "sg:postcode":"89073",
    "sg:province":"Baden-W\u00fcrttemberg",
    "wof:name":"Schirm-g\u00f6bel",
    "wof:placetype":"venue"
},
  "geometry": {"coordinates":[9.9960079193,48.3976631165],"type":"Point"}
}