{
  "type": "Feature",
  "properties": {
    "iso:country":"DE",
    "sg:address":"Carl-Burger-Str. 8",
    "sg:city":"Bayreuth",
    "sg:phone":"+49 921/54380",
    "sg:postcode":"95445",
    "sg:province":"Bayern",
    "wof:name":"Schneidermarkt Gmbh",
    "wof:placetype":"venue"
},
  "geometry": {"coordinates":[11.5648965836,49.9434204102],"type":"Point"}
}