{
  "type": "Feature",
  "properties": {
    "iso:country":"DE",
    "sg:address":"Auricher Str. 71",
    "sg:city":"Esens",
    "sg:phone":"+49 4971/651",
    "sg:postcode":"26427",
    "sg:province":"Niedersachsen",
    "wof:name":"Berthold Lammers",
    "wof:placetype":"venue"
},
  "geometry": {"coordinates":[7.6141700745,53.6281471252],"type":"Point"}
}