{
  "type": "Feature",
  "properties": {
    "iso:country":"DE",
    "sg:address":"Tuchbleiche 5",
    "sg:city":"Hardthausen",
    "sg:phone":"+49 7139/932510",
    "sg:postcode":"74239",
    "sg:province":"Baden-W\u00fcrttemberg",
    "wof:name":"Sonnenschutz",
    "wof:placetype":"venue"
},
  "geometry": {"coordinates":[9.362847,49.237156],"type":"Point"}
}