{
  "type": "Feature",
  "properties": {
    "iso:country":"DE",
    "sg:address":"Uferstr. 80",
    "sg:city":"Hameln",
    "sg:phone":"+49 5151/67489",
    "sg:postcode":"31787",
    "sg:province":"Niedersachsen",
    "wof:name":"Restaurant Athen Im F\u00e4hrhaus",
    "wof:placetype":"venue"
},
  "geometry": {"coordinates":[9.3474578857,52.1094207764],"type":"Point"}
}