{
  "type": "Feature",
  "properties": {
    "iso:country":"DE",
    "sg:address":"Andershofer Weide 8",
    "sg:city":"Stralsund",
    "sg:phone":"+49 3831/279053",
    "sg:postcode":"18439",
    "sg:province":"Mecklenburg-Vorpommern",
    "wof:name":"Ambulanter Pflegedienst Hauskrankenpflege R. Hauth",
    "wof:placetype":"venue"
},
  "geometry": {"coordinates":[13.105846,54.272892],"type":"Point"}
}