{
  "type": "Feature",
  "properties": {
    "iso:country":"DE",
    "sg:address":"Hauptstr. 46",
    "sg:city":"Bad Laer",
    "sg:phone":"+49 5424/37166",
    "sg:postcode":"49196",
    "sg:province":"Niedersachsen",
    "wof:name":"Kath. Pfarramt St. Antonius Abt",
    "wof:placetype":"venue"
},
  "geometry": {"coordinates":[8.1116580963,52.1340332031],"type":"Point"}
}