{
  "type": "Feature",
  "properties": {
    "iso:country":"DE",
    "sg:address":"Platz des Friedens 8",
    "sg:city":"Baunatal",
    "sg:phone":"+49 561/9493730",
    "sg:postcode":"34225",
    "sg:province":"Hessen",
    "wof:name":"Cd-net Datenbanken Gmbh",
    "wof:placetype":"venue"
},
  "geometry": {"coordinates":[9.4137001038,51.253288269],"type":"Point"}
}