{
  "type": "Feature",
  "properties": {
    "iso:country":"DE",
    "sg:address":"R\u00f6tweg 2",
    "sg:city":"Waldachtal",
    "sg:phone":"+49 7443/6891",
    "sg:postcode":"72178",
    "sg:province":"Baden-W\u00fcrttemberg",
    "wof:name":"Ev. Pfarramt Tumlingen",
    "wof:placetype":"venue"
},
  "geometry": {"coordinates":[8.5736637115,48.4784126282],"type":"Point"}
}