{
  "type": "Feature",
  "properties": {
    "iso:country":"DE",
    "sg:address":"Kanalstr. 28",
    "sg:city":"Leverkusen",
    "sg:phone":"+49 2171/46642",
    "sg:postcode":"51379",
    "sg:province":"Nordrhein-Westfalen",
    "wof:name":"Jutta Blank Heilpraktikerin",
    "wof:placetype":"venue"
},
  "geometry": {"coordinates":[6.9982948303,51.062789917],"type":"Point"}
}