{
  "type": "Feature",
  "properties": {
    "iso:country":"DE",
    "sg:address":"Rohrbacher Str. 83",
    "sg:city":"Heidelberg",
    "sg:phone":"+49 6221/165600",
    "sg:postcode":"69115",
    "sg:province":"Baden-W\u00fcrttemberg",
    "wof:name":"Exquisit",
    "wof:placetype":"venue"
},
  "geometry": {"coordinates":[8.691113,49.400784],"type":"Point"}
}