{
  "type": "Feature",
  "properties": {
    "iso:country":"DE",
    "sg:address":"Industriestr. 13-15",
    "sg:city":"Singen",
    "sg:phone":"+49 7731/5920",
    "sg:postcode":"78224",
    "sg:province":"Baden-W\u00fcrttemberg",
    "wof:name":"F. X. Ruch Kg",
    "wof:placetype":"venue"
},
  "geometry": {"coordinates":[8.8493003845,47.74766922],"type":"Point"}
}