{
  "type": "Feature",
  "properties": {
    "iso:country":"DE",
    "sg:address":"Burgstr. 23",
    "sg:city":"Lingen",
    "sg:phone":"+49 591/831754",
    "sg:postcode":"49808",
    "sg:province":"Niedersachsen",
    "wof:name":"Quittek Immobilienmakler",
    "wof:placetype":"venue"
},
  "geometry": {"coordinates":[7.319633007,52.5228004456],"type":"Point"}
}