{
  "type": "Feature",
  "properties": {
    "iso:country":"DE",
    "sg:address":"Kalefeld",
    "sg:city":"Kalefeld",
    "sg:phone":"+49 5553/4046",
    "sg:postcode":"37589",
    "sg:province":"Niedersachsen",
    "wof:name":"Kreis-sparkasse Northeim",
    "wof:placetype":"venue"
},
  "geometry": {"coordinates":[10.07239,51.78125],"type":"Point"}
}