{
  "type": "Feature",
  "properties": {
    "iso:country":"DE",
    "sg:address":"Schwachhauser Heerstr. 190",
    "sg:city":"Bremen",
    "sg:phone":"+49 421/213036",
    "sg:postcode":"28213",
    "sg:province":"Bremen",
    "wof:name":"Gebr. Noltenius & Partner Gmbh",
    "wof:placetype":"venue"
},
  "geometry": {"coordinates":[8.857006073,53.0890884399],"type":"Point"}
}