{
  "type": "Feature",
  "properties": {
    "iso:country":"DE",
    "sg:address":"Br\u00fchlstr. 15",
    "sg:city":"Konstanz",
    "sg:phone":"+49 7533/93010",
    "sg:postcode":"78465",
    "sg:province":"Baden-W\u00fcrttemberg",
    "wof:name":"Bioforce Gmbh",
    "wof:placetype":"venue"
},
  "geometry": {"coordinates":[9.1137952805,47.7321968079],"type":"Point"}
}