{
  "type": "Feature",
  "properties": {
    "iso:country":"DE",
    "sg:address":"Schopenstehl 20",
    "sg:city":"Hamburg",
    "sg:postcode":"20095",
    "sg:province":"Hamburg",
    "wof:name":"Hanseaten Select",
    "wof:placetype":"venue"
},
  "geometry": {"coordinates":[9.9991855621,53.5486564636],"type":"Point"}
}