{
  "type": "Feature",
  "properties": {
    "iso:country":"DE",
    "sg:address":"Dalbergstr. 62",
    "sg:city":"Aschaffenburg",
    "sg:phone":"+49 6021/27690",
    "sg:postcode":"63739",
    "sg:province":"Bayern",
    "wof:name":"Bistro Krokodil",
    "wof:placetype":"venue"
},
  "geometry": {"coordinates":[9.1429100037,49.9723014832],"type":"Point"}
}