{
  "type": "Feature",
  "properties": {
    "iso:country":"DE",
    "sg:address":"Planegger Str. 24a",
    "sg:city":"M\u00fcnchen",
    "sg:phone":"+49 89/8888073",
    "sg:postcode":"81241",
    "sg:province":"Bayern",
    "wof:name":"Marina Wilbs",
    "wof:placetype":"venue"
},
  "geometry": {"coordinates":[11.456135,48.140259],"type":"Point"}
}