{
  "type": "Feature",
  "properties": {
    "iso:country":"DE",
    "sg:address":"Mannheimer Str. 151",
    "sg:city":"Bad Kreuznach",
    "sg:phone":"+49 671/837440",
    "sg:postcode":"55543",
    "sg:province":"Rheinland-Pfalz",
    "wof:name":"H. Heimrich Gmbh & Co. Kg",
    "wof:placetype":"venue"
},
  "geometry": {"coordinates":[7.861524,49.842705],"type":"Point"}
}