{
  "type": "Feature",
  "properties": {
    "iso:country":"DE",
    "sg:address":"Schlo\u00dfstr. 6",
    "sg:city":"Bechhofen",
    "sg:phone":"+49 9822/7510",
    "sg:postcode":"91572",
    "sg:province":"Bayern",
    "wof:name":"Hans Rammler",
    "wof:placetype":"venue"
},
  "geometry": {"coordinates":[10.549633,49.157131],"type":"Point"}
}