{
  "type": "Feature",
  "properties": {
    "iso:country":"DE",
    "sg:address":"Rudolf-Winkel-Str. 12",
    "sg:city":"G\u00f6ttingen",
    "sg:phone":"+49 551/61383",
    "sg:postcode":"37079",
    "sg:province":"Niedersachsen",
    "wof:name":"Leichtmetall Klapproth Gmbh & Co. Kg",
    "wof:placetype":"venue"
},
  "geometry": {"coordinates":[9.903395,51.544651],"type":"Point"}
}