{
  "type": "Feature",
  "properties": {
    "iso:country":"DE",
    "sg:address":"Bergstr. 2-2",
    "sg:city":"Bad Liebenzell",
    "sg:phone":"+49 7052/870",
    "sg:postcode":"75378",
    "sg:province":"Baden-W\u00fcrttemberg",
    "wof:name":"Siegbert Bahsler Architekt",
    "wof:placetype":"venue"
},
  "geometry": {"coordinates":[8.716427,48.764847],"type":"Point"}
}