{
  "type": "Feature",
  "properties": {
    "iso:country":"DE",
    "sg:address":"Plabennec Stra\u00dfe 30",
    "sg:city":"Waltenhofen",
    "sg:phone":"+49 4908/303331",
    "sg:postcode":"87448",
    "sg:province":"Bayern",
    "wof:name":"Allg\u00e4u \u00b4 Tauchcenter Waltenhofen \u00b4",
    "wof:placetype":"venue"
},
  "geometry": {"coordinates":[10.3103685379,47.6798782349],"type":"Point"}
}