{
  "type": "Feature",
  "properties": {
    "iso:country":"DE",
    "sg:address":"Implerstr. 18",
    "sg:city":"M\u00fcnchen",
    "sg:postcode":"81371",
    "sg:province":"Bayern",
    "wof:name":"Killi Verwaltungs Gmbh",
    "wof:placetype":"venue"
},
  "geometry": {"coordinates":[11.548255,48.121731],"type":"Point"}
}