{
  "type": "Feature",
  "properties": {
    "iso:country":"DE",
    "sg:address":"Hennstedter Str. 2",
    "sg:city":"Fedderingen",
    "sg:phone":"+49 4836/1739",
    "sg:postcode":"25779",
    "sg:province":"Schleswig-Holstein",
    "wof:name":"Helmut Hadenfeldt B\u00e4ckerei",
    "wof:placetype":"venue"
},
  "geometry": {"coordinates":[9.132814,54.28233],"type":"Point"}
}