{
  "type": "Feature",
  "properties": {
    "iso:country":"DE",
    "sg:address":"Am Wasserturm 2",
    "sg:city":"Burgdorf",
    "sg:phone":"+49 5136/971909",
    "sg:postcode":"31303",
    "sg:province":"Niedersachsen",
    "wof:name":"Andreas Rahmann Praxis F\u00fcr Ergotherapie",
    "wof:placetype":"venue"
},
  "geometry": {"coordinates":[10.00936,52.451275],"type":"Point"}
}