{
  "type": "Feature",
  "properties": {
    "iso:country":"DE",
    "sg:address":"K\u00e4the-Kollwitz-Str. 11",
    "sg:city":"Waldbr\u00f6l",
    "sg:postcode":"51545",
    "sg:province":"Nordrhein-Westfalen",
    "wof:name":"Skm Stahlbaumontage Und Kranverleih Und Allgemeine",
    "wof:placetype":"venue"
},
  "geometry": {"coordinates":[7.639491,50.888973],"type":"Point"}
}