{
  "type": "Feature",
  "properties": {
    "iso:country":"DE",
    "sg:address":"Bergwinkelweg 24",
    "sg:city":"Schl\u00fcchtern",
    "sg:phone":"+49 6661/3438",
    "sg:postcode":"36381",
    "sg:province":"Hessen",
    "wof:name":"Eberhard Heil Steuerberater",
    "wof:placetype":"venue"
},
  "geometry": {"coordinates":[9.5269346237,50.3408126831],"type":"Point"}
}