{
  "type": "Feature",
  "properties": {
    "iso:country":"DE",
    "sg:address":"Hochstr. 50a",
    "sg:city":"Hilchenbach",
    "sg:phone":"+49 2733/51675",
    "sg:postcode":"57271",
    "sg:province":"Nordrhein-Westfalen",
    "wof:name":"Rolf Herma",
    "wof:placetype":"venue"
},
  "geometry": {"coordinates":[8.0636825562,50.976776123],"type":"Point"}
}