{
  "type": "Feature",
  "properties": {
    "iso:country":"DE",
    "sg:address":"Schafanger 20",
    "sg:city":"Moringen",
    "sg:phone":"+49 4955/5599310",
    "sg:postcode":"37186",
    "sg:province":"Niedersachsen",
    "wof:name":"Feise Holzbau Gmbh",
    "wof:placetype":"venue"
},
  "geometry": {"coordinates":[9.7872133255,51.7379302979],"type":"Point"}
}