{
  "type": "Feature",
  "properties": {
    "iso:country":"DE",
    "sg:address":"Ringstr. 3",
    "sg:city":"Hannover",
    "sg:phone":"+49 511/946600",
    "sg:postcode":"30457",
    "sg:province":"Niedersachsen",
    "wof:name":"L. Spangenberg Beteiligungsgesellschaft Mbh",
    "wof:placetype":"venue"
},
  "geometry": {"coordinates":[9.691107,52.325047],"type":"Point"}
}