{
  "type": "Feature",
  "properties": {
    "iso:country":"DE",
    "sg:address":"Mallertshofener Str. 2",
    "sg:city":"Unterschlei\u00dfheim",
    "sg:phone":"+49 89/3106229",
    "sg:postcode":"85716",
    "sg:province":"Bayern",
    "wof:name":"W. Gruber",
    "wof:placetype":"venue"
},
  "geometry": {"coordinates":[11.5908069611,48.2619743347],"type":"Point"}
}