{
  "type": "Feature",
  "properties": {
    "iso:country":"DE",
    "sg:address":"Am Bahnhof 10",
    "sg:city":"Frankenstein",
    "sg:phone":"+49 37321/8860",
    "sg:postcode":"09569",
    "sg:province":"Sachsen",
    "wof:name":"Schulze & Conradi Gmbh Heft- Und Nageltechnik",
    "wof:placetype":"venue"
},
  "geometry": {"coordinates":[13.1746301651,50.8616752625],"type":"Point"}
}