{
  "type": "Feature",
  "properties": {
    "iso:country":"DE",
    "sg:address":"Gewerbegebiet S\u00fcd",
    "sg:city":"Nieb\u00fcll",
    "sg:phone":"+49 4661/96660",
    "sg:postcode":"25899",
    "sg:province":"Schleswig-Holstein",
    "wof:name":"Bauzentrum Detlef Christiansen Gmbh & Co. Kg",
    "wof:placetype":"venue"
},
  "geometry": {"coordinates":[8.827183,54.786598],"type":"Point"}
}