{
  "type": "Feature",
  "properties": {
    "iso:country":"DE",
    "sg:address":"Vordere Synagogenstr. 2",
    "sg:city":"Mainz",
    "sg:phone":"+49 6131/134043",
    "sg:postcode":"55116",
    "sg:province":"Rheinland-Pfalz",
    "wof:name":"Lbs Immobilien Gmbh",
    "wof:placetype":"venue"
},
  "geometry": {"coordinates":[8.268445015,50.0023384094],"type":"Point"}
}