{
  "type": "Feature",
  "properties": {
    "iso:country":"DE",
    "sg:address":"Sauerlacher Str. 11",
    "sg:city":"Egling",
    "sg:phone":"+49 8176/287",
    "sg:postcode":"82544",
    "sg:province":"Bayern",
    "wof:name":"Sebald Schmotz",
    "wof:placetype":"venue"
},
  "geometry": {"coordinates":[11.535981,47.928032],"type":"Point"}
}