{
  "type": "Feature",
  "properties": {
    "iso:country":"DE",
    "sg:address":"Willibrordusstr 5",
    "sg:city":"Grevenbroich",
    "sg:phone":"+49 2181/162138",
    "sg:postcode":"41517",
    "sg:province":"Nordrhein-Westfalen",
    "wof:name":"Aretz Gmbh",
    "wof:placetype":"venue"
},
  "geometry": {"coordinates":[6.5905299187,51.0675811768],"type":"Point"}
}