{
  "type": "Feature",
  "properties": {
    "iso:country":"DE",
    "sg:address":"Liliencronweg 23",
    "sg:city":"Flensburg",
    "sg:phone":"+49 461/59463",
    "sg:postcode":"24939",
    "sg:province":"Schleswig-Holstein",
    "wof:name":"Callsen",
    "wof:placetype":"venue"
},
  "geometry": {"coordinates":[9.405924,54.787575],"type":"Point"}
}