{
  "type": "Feature",
  "properties": {
    "iso:country":"DE",
    "sg:address":"Maistr. 69",
    "sg:city":"M\u00fcnchen",
    "sg:postcode":"80337",
    "sg:province":"Bayern",
    "wof:name":"1 Afit.de Ag",
    "wof:placetype":"venue"
},
  "geometry": {"coordinates":[11.561287,48.125984],"type":"Point"}
}