{
  "type": "Feature",
  "properties": {
    "iso:country":"DE",
    "sg:address":"Boschstr. 1",
    "sg:city":"K\u00e4mpfelbach",
    "sg:phone":"+49 7232/5468",
    "sg:postcode":"75236",
    "sg:province":"Baden-W\u00fcrttemberg",
    "wof:name":"Pilsst\u00fcble",
    "wof:placetype":"venue"
},
  "geometry": {"coordinates":[8.6251602173,48.9445991516],"type":"Point"}
}