{
  "type": "Feature",
  "properties": {
    "iso:country":"DE",
    "sg:address":"K\u00f6nigstr. 26",
    "sg:city":"B\u00fcren",
    "sg:postcode":"33142",
    "sg:province":"Nordrhein-Westfalen",
    "wof:name":"Landesbausparkasse Beratungsstelle",
    "wof:placetype":"venue"
},
  "geometry": {"coordinates":[8.560185,51.553085],"type":"Point"}
}