{
  "type": "Feature",
  "properties": {
    "iso:country":"DE",
    "sg:address":"Jahnstr. 16",
    "sg:city":"Bodenheim",
    "sg:phone":"+49 6135/2357",
    "sg:postcode":"55294",
    "sg:province":"Rheinland-Pfalz",
    "wof:name":"Klaus Sieben",
    "wof:placetype":"venue"
},
  "geometry": {"coordinates":[8.30717659,49.92943573],"type":"Point"}
}