{
  "type": "Feature",
  "properties": {
    "iso:country":"DE",
    "sg:address":"Moerser Str. 40",
    "sg:city":"Duisburg",
    "sg:postcode":"47198",
    "sg:province":"Nordrhein-Westfalen",
    "wof:name":"Pizzeria Calabrisella Sebastino Cosmo",
    "wof:placetype":"venue"
},
  "geometry": {"coordinates":[6.7075309753,51.4499168396],"type":"Point"}
}