{
  "type": "Feature",
  "properties": {
    "iso:country":"DE",
    "sg:address":"Rathausstr. 32",
    "sg:city":"L\u00fctzelbach",
    "sg:phone":"+49 6165/1368",
    "sg:postcode":"64750",
    "sg:province":"Hessen",
    "wof:name":"Karl W. Steiger",
    "wof:placetype":"venue"
},
  "geometry": {"coordinates":[9.0408601761,49.785320282],"type":"Point"}
}