{
  "type": "Feature",
  "properties": {
    "iso:country":"DE",
    "sg:address":"Burgstr. 12",
    "sg:city":"Ilsede",
    "sg:phone":"+49 5172/6263",
    "sg:postcode":"31241",
    "sg:province":"Niedersachsen",
    "wof:name":"Detlef Heyne",
    "wof:placetype":"venue"
},
  "geometry": {"coordinates":[10.2059192657,52.2651023865],"type":"Point"}
}