{
  "type": "Feature",
  "properties": {
    "iso:country":"DE",
    "sg:address":"Starkenstrasse",
    "sg:city":"Freiburg",
    "sg:phone":"+49 761/36397",
    "sg:postcode":"79104",
    "sg:province":"Baden-W\u00fcrttemberg",
    "wof:name":"Constantia-consulting Gmbh",
    "wof:placetype":"venue"
},
  "geometry": {"coordinates":[7.8604650497,48.002281189],"type":"Point"}
}