{
  "type": "Feature",
  "properties": {
    "iso:country":"DE",
    "sg:address":"Hauptstr. 20",
    "sg:city":"Rauhenebrach",
    "sg:postcode":"96181",
    "sg:province":"Bayern",
    "wof:name":"Aktiv-markt Straub",
    "wof:placetype":"venue"
},
  "geometry": {"coordinates":[10.5527954102,49.8885574341],"type":"Point"}
}