{
  "type": "Feature",
  "properties": {
    "iso:country":"DE",
    "sg:address":"Viktoriastr 26",
    "sg:city":"P\u00fcttlingen",
    "sg:phone":"+49 6898/64685",
    "sg:postcode":"66346",
    "sg:province":"Saarland",
    "wof:name":"Theisen S.a. Luxembourg",
    "wof:placetype":"venue"
},
  "geometry": {"coordinates":[6.8985228539,49.2837028503],"type":"Point"}
}