{
  "type": "Feature",
  "properties": {
    "iso:country":"DE",
    "sg:address":"Kohlstattweg 5",
    "sg:city":"Unterammergau",
    "sg:phone":"+49 8822/4724",
    "sg:postcode":"82497",
    "sg:province":"Bayern",
    "wof:name":"Johann Gansler Gmbh",
    "wof:placetype":"venue"
},
  "geometry": {"coordinates":[11.024061,47.617245],"type":"Point"}
}