{
  "type": "Feature",
  "properties": {
    "iso:country":"DE",
    "sg:address":"Kirchplatz 6-4",
    "sg:city":"Bad Rappenau",
    "sg:phone":"+49 7264/4380",
    "sg:postcode":"74906",
    "sg:province":"Baden-W\u00fcrttemberg",
    "wof:name":"Stefan Raffai",
    "wof:placetype":"venue"
},
  "geometry": {"coordinates":[9.1014471054,49.2399597168],"type":"Point"}
}