{"geometry":{"type":"Point","coordinates":[10.479169,48.173107]},"type":"Feature","id":102560579,"bbox":[10.479169,48.173107,10.479169,48.173107],"properties":{"sg:province":"Bayern","geom:longitude":10.479169,"wof:breaches":[],"sg:href":"http://api.simplegeo.com/1.0/features/SG_2KuiNtsOj9hBDCBCQupnBz_48.173107_10.479169@1306268793.json","sg:owner":"simplegeo","sg:postcode":"87757","geom:latitude":48.173107,"sg:classifiers":[],"sg:address":"Raiffeisenstr. 8::","sg:phone":"+49 8266/86030","wof:hierarchy":[{"locality_id":101786523,"venue_id":102560579,"country_id":85633111,"region_id":85682571,"county_id":102063255}],"geom:area":0.000000,"sg:city":"Kirchheim","wof:lastmodified":1438093296,"iso:country":"DE","wof:geomhash":"9012445cce9b0b8c462a03bb1c3f2826","wof:name":"Raiffeisenbank Kirchheim-mindelheim E.g.","wof:belongsto":[101786523,85633111,85682571,102063255],"src:geom":"simplegeo","wof:placetype":"venue","wof:supersedes":[],"wof:id":102560579,"wof:superseded_by":[],"wof:concordances":{"sg:id":"SG_2KuiNtsOj9hBDCBCQupnBz_48.173107_10.479169@1306268793"},"wof:parent_id":101786523}}