{
  "type": "Feature",
  "properties": {
    "iso:country":"DE",
    "sg:address":"Brede 15",
    "sg:city":"Extertal",
    "sg:phone":"+49 5754/964056",
    "sg:postcode":"32699",
    "sg:province":"Nordrhein-Westfalen",
    "wof:name":"Wesmo Consult Ohg",
    "wof:placetype":"venue"
},
  "geometry": {"coordinates":[9.0511798859,52.1106109619],"type":"Point"}
}