{
  "type": "Feature",
  "properties": {
    "iso:country":"DE",
    "sg:address":"Moselstr. 78",
    "sg:city":"Kr\u00f6v",
    "sg:phone":"+49 6541/9579",
    "sg:postcode":"54536",
    "sg:province":"Rheinland-Pfalz",
    "wof:name":"Gustav Schnitzius",
    "wof:placetype":"venue"
},
  "geometry": {"coordinates":[7.1207399368,49.9794311523],"type":"Point"}
}