{
  "type": "Feature",
  "properties": {
    "iso:country":"DE",
    "sg:address":"Obere Br\u00e4uhausstr. 11",
    "sg:city":"Waldm\u00fcnchen",
    "sg:phone":"+49 9972/8202",
    "sg:postcode":"93449",
    "sg:province":"Bayern",
    "wof:name":"Josef Klein",
    "wof:placetype":"venue"
},
  "geometry": {"coordinates":[12.7080001831,49.3773918152],"type":"Point"}
}