{
  "type": "Feature",
  "properties": {
    "iso:country":"DE",
    "sg:address":"Steinweg 36",
    "sg:city":"Halle",
    "sg:phone":"+49 345/2027323",
    "sg:postcode":"06110",
    "sg:province":"Sachsen-Anhalt",
    "wof:name":"Joachim Liebsch",
    "wof:placetype":"venue"
},
  "geometry": {"coordinates":[11.970225,51.475124],"type":"Point"}
}