{
  "type": "Feature",
  "properties": {
    "iso:country":"DE",
    "sg:address":"Hauptstr. 60",
    "sg:city":"Br\u00f6ckel",
    "sg:phone":"+49 5144/92632",
    "sg:postcode":"29356",
    "sg:province":"Niedersachsen",
    "wof:name":"Dirk Kanther",
    "wof:placetype":"venue"
},
  "geometry": {"coordinates":[10.216306,52.521622],"type":"Point"}
}