{
  "type": "Feature",
  "properties": {
    "iso:country":"DE",
    "sg:address":"Heyden-Linden-Str. 7",
    "sg:city":"Hannover",
    "sg:phone":"+49 511/666787",
    "sg:postcode":"30163",
    "sg:province":"Niedersachsen",
    "wof:name":"Winkel Maler-fachbetrieb-gmbh",
    "wof:placetype":"venue"
},
  "geometry": {"coordinates":[9.736829,52.395775],"type":"Point"}
}