{
  "type": "Feature",
  "properties": {
    "iso:country":"DE",
    "sg:address":"Meimsheimerstr. 10",
    "sg:city":"B\u00f6nnigheim",
    "sg:phone":"+49 4971/4388560",
    "sg:postcode":"74357",
    "sg:province":"Baden-W\u00fcrttemberg",
    "wof:name":"G.wein Gmbh & Co. Kg",
    "wof:placetype":"venue"
},
  "geometry": {"coordinates":[9.093686,49.043793],"type":"Point"}
}