{
  "type": "Feature",
  "properties": {
    "iso:country":"DE",
    "sg:address":"Uhlmannstr 41",
    "sg:city":"Laupheim",
    "sg:phone":"+49 7392/97050",
    "sg:postcode":"88471",
    "sg:province":"Baden-W\u00fcrttemberg",
    "wof:name":"Jordan Gamma Medizintechnik Gmbh",
    "wof:placetype":"venue"
},
  "geometry": {"coordinates":[9.872627,48.238274],"type":"Point"}
}