{
  "type": "Feature",
  "properties": {
    "iso:country":"DE",
    "sg:address":"Gabelsbergerstr. 2",
    "sg:city":"Mittweida",
    "sg:phone":"+49 3727/3068",
    "sg:postcode":"09648",
    "sg:province":"Sachsen",
    "wof:name":"Benno Lauckner",
    "wof:placetype":"venue"
},
  "geometry": {"coordinates":[12.9879903793,50.9825401306],"type":"Point"}
}