{
  "type": "Feature",
  "properties": {
    "iso:country":"DE",
    "sg:address":"Heinrich-Heine-Str. 27 a",
    "sg:city":"Waltershausen",
    "sg:postcode":"99880",
    "sg:province":"Th\u00fcringen",
    "wof:name":"Apotheke Ibenhain Inh. Winfried Dazert E. Kfm.",
    "wof:placetype":"venue"
},
  "geometry": {"coordinates":[10.570597,50.888443],"type":"Point"}
}