{
  "type": "Feature",
  "properties": {
    "iso:country":"DE",
    "sg:address":"Martinistr. 83",
    "sg:city":"Hamburg",
    "sg:phone":"+49 40/475757",
    "sg:postcode":"20251",
    "sg:province":"Hamburg",
    "wof:name":"Martin Und Clara Heimann-stift",
    "wof:placetype":"venue"
},
  "geometry": {"coordinates":[9.971925,53.587276],"type":"Point"}
}