{
  "type": "Feature",
  "properties": {
    "iso:country":"DE",
    "sg:address":"Vorstadt 5",
    "sg:city":"Schmitten",
    "sg:phone":"+49 6082/92100",
    "sg:postcode":"61389",
    "sg:province":"Hessen",
    "wof:name":"Hotel Haus Reifenberg",
    "wof:placetype":"venue"
},
  "geometry": {"coordinates":[8.4299592972,50.2464637756],"type":"Point"}
}