{
  "type": "Feature",
  "properties": {
    "iso:country":"DE",
    "sg:address":"Rotherstr. 25",
    "sg:city":"Bad Berneck",
    "sg:phone":"+49 9273/360",
    "sg:postcode":"95460",
    "sg:province":"Bayern",
    "wof:name":"Kur-apotheke Bad Berneck Kurt Unverdorben E. K.",
    "wof:placetype":"venue"
},
  "geometry": {"coordinates":[11.675495,50.048733],"type":"Point"}
}