{
  "type": "Feature",
  "properties": {
    "iso:country":"DE",
    "sg:address":"Kohlenbrunnerm\u00fchlstr. 9",
    "sg:city":"Neumarkt",
    "sg:phone":"+49 9181/41519",
    "sg:postcode":"92318",
    "sg:province":"Bayern",
    "wof:name":"Ernst Herrmann",
    "wof:placetype":"venue"
},
  "geometry": {"coordinates":[11.4749107361,49.2932167053],"type":"Point"}
}