{
  "type": "Feature",
  "properties": {
    "iso:country":"DE",
    "sg:address":"Siemensring 2",
    "sg:city":"Nauen",
    "sg:postcode":"14641",
    "sg:province":"Brandenburg",
    "wof:name":"Agrotechnic Handelsges. Mbh Zwndl. Nauen",
    "wof:placetype":"venue"
},
  "geometry": {"coordinates":[12.8941612244,52.5997962952],"type":"Point"}
}