{
  "type": "Feature",
  "properties": {
    "iso:country":"DE",
    "sg:address":"Friedenstr. 27",
    "sg:city":"M\u00f6nchweiler",
    "sg:phone":"+49 7721/63406",
    "sg:postcode":"78087",
    "sg:province":"Baden-W\u00fcrttemberg",
    "wof:name":"A. Eberhard",
    "wof:placetype":"venue"
},
  "geometry": {"coordinates":[8.4167022705,48.1042785645],"type":"Point"}
}