{
  "type": "Feature",
  "properties": {
    "iso:country":"DE",
    "sg:address":"Geltestr. 7a",
    "sg:city":"D\u00f6lbau",
    "sg:phone":"+49 34602/50265",
    "sg:postcode":"06184",
    "sg:province":"Sachsen-Anhalt",
    "wof:name":"Bernstein",
    "wof:placetype":"venue"
},
  "geometry": {"coordinates":[12.0981149673,51.4363746643],"type":"Point"}
}