{
  "type": "Feature",
  "properties": {
    "iso:country":"DE",
    "sg:address":"B\u00fctersworthstr. 11",
    "sg:city":"Hannover",
    "sg:phone":"+49 511/3481562",
    "sg:postcode":"30161",
    "sg:province":"Niedersachsen",
    "wof:name":"Prosecco",
    "wof:placetype":"venue"
},
  "geometry": {"coordinates":[9.7523651123,52.3826408386],"type":"Point"}
}