{
  "type": "Feature",
  "properties": {
    "iso:country":"DE",
    "sg:address":"Hauptstr. 25",
    "sg:city":"Vordorf",
    "sg:phone":"+49 5304/4082",
    "sg:postcode":"38533",
    "sg:province":"Niedersachsen",
    "wof:name":"Hans-j\u00fcrgen Eggers Architekt",
    "wof:placetype":"venue"
},
  "geometry": {"coordinates":[10.52319,52.366508],"type":"Point"}
}