{
  "type": "Feature",
  "properties": {
    "iso:country":"DE",
    "sg:address":"Tiergartenstr. 105",
    "sg:city":"Hannover",
    "sg:phone":"+49 511/954700",
    "sg:postcode":"30559",
    "sg:province":"Niedersachsen",
    "wof:name":"Signum Gmbh Wirtschaftspr\u00fcfungsges.",
    "wof:placetype":"venue"
},
  "geometry": {"coordinates":[9.8309707642,52.3612823486],"type":"Point"}
}