{
  "type": "Feature",
  "properties": {
    "iso:country":"DE",
    "sg:address":"Gro\u00dfenl\u00fcderer Weg 2",
    "sg:city":"Schlitz",
    "sg:phone":"+49 6642/6400",
    "sg:postcode":"36110",
    "sg:province":"Hessen",
    "wof:name":"Ev. Pfarramt Hartershausen",
    "wof:placetype":"venue"
},
  "geometry": {"coordinates":[9.5838403702,50.6327438354],"type":"Point"}
}