{
  "type": "Feature",
  "properties": {
    "iso:country":"DE",
    "sg:address":"Schlo\u00dfstr. 1",
    "sg:city":"Battenberg",
    "sg:phone":"+49 6452/3138",
    "sg:postcode":"35088",
    "sg:province":"Hessen",
    "wof:name":"Heinrich Becker",
    "wof:placetype":"venue"
},
  "geometry": {"coordinates":[8.631322,50.995499],"type":"Point"}
}