{
  "type": "Feature",
  "properties": {
    "iso:country":"DE",
    "sg:address":"Kaiserstr. 50",
    "sg:city":"Bonn",
    "sg:phone":"+49 228/9219100",
    "sg:postcode":"53113",
    "sg:province":"Nordrhein-Westfalen",
    "wof:name":"S. Romansky Rechtsanwalt",
    "wof:placetype":"venue"
},
  "geometry": {"coordinates":[7.1035218239,50.7293395996],"type":"Point"}
}