{
  "type": "Feature",
  "properties": {
    "iso:country":"DE",
    "sg:address":"Rheydter Str. 60",
    "sg:city":"M\u00f6nchengladbach",
    "sg:phone":"+49 2161/23530",
    "sg:postcode":"41065",
    "sg:province":"Nordrhein-Westfalen",
    "wof:name":"Ernst Jansen-winkeln Kunstmaler",
    "wof:placetype":"venue"
},
  "geometry": {"coordinates":[6.45103,51.193321],"type":"Point"}
}