{
  "type": "Feature",
  "properties": {
    "iso:country":"DE",
    "sg:address":"Rudolf-Breitscheid-Str 5",
    "sg:city":"Rehfelde",
    "sg:phone":"+49 33435/75113",
    "sg:postcode":"15345",
    "sg:province":"Brandenburg",
    "wof:name":"Sam Detlef Arnholdt",
    "wof:placetype":"venue"
},
  "geometry": {"coordinates":[13.8987407684,52.5213699341],"type":"Point"}
}