{
  "type": "Feature",
  "properties": {
    "iso:country":"DE",
    "sg:address":"Leinenweberstr. 1",
    "sg:city":"Bad Hersfeld",
    "sg:phone":"+49 6621/944111",
    "sg:postcode":"36251",
    "sg:province":"Hessen",
    "wof:name":"Strukturentwicklungsgesell- Schaft F\u00fcr Den Landkreis",
    "wof:placetype":"venue"
},
  "geometry": {"coordinates":[9.7284784317,50.8595581055],"type":"Point"}
}