{
  "type": "Feature",
  "properties": {
    "iso:country":"DE",
    "sg:address":"Am Alten Flugplatz 8",
    "sg:city":"Duisburg",
    "sg:phone":"+49 203/314848",
    "sg:postcode":"47059",
    "sg:province":"Nordrhein-Westfalen",
    "wof:name":"Rhein-ruhr-reisen G\u00fcnter Leutung",
    "wof:placetype":"venue"
},
  "geometry": {"coordinates":[6.7365489006,51.4360847473],"type":"Point"}
}