{
  "type": "Feature",
  "properties": {
    "iso:country":"DE",
    "sg:address":"Schlesierweg 17a",
    "sg:city":"Wunstorf",
    "sg:phone":"+49 5033/8700",
    "sg:postcode":"31515",
    "sg:province":"Niedersachsen",
    "wof:name":"M. Olboeter",
    "wof:placetype":"venue"
},
  "geometry": {"coordinates":[9.368915,52.459225],"type":"Point"}
}