{
  "type": "Feature",
  "properties": {
    "iso:country":"DE",
    "sg:address":"Kolpingstr. 1",
    "sg:city":"M\u00f6hnesee",
    "sg:phone":"+49 2924/97020",
    "sg:postcode":"59519",
    "sg:province":"Nordrhein-Westfalen",
    "wof:name":"Manfred J. Krampe Steuerberatungs-gmbh",
    "wof:placetype":"venue"
},
  "geometry": {"coordinates":[8.131070137,51.4970092773],"type":"Point"}
}