{
  "type": "Feature",
  "properties": {
    "iso:country":"DE",
    "sg:address":"Innstr. 9",
    "sg:city":"M\u00fcnchen",
    "sg:phone":"+49 89/988484",
    "sg:postcode":"81679",
    "sg:province":"Bayern",
    "wof:name":"Erich Durnes Architekt",
    "wof:placetype":"venue"
},
  "geometry": {"coordinates":[11.609389,48.144691],"type":"Point"}
}