{
  "type": "Feature",
  "properties": {
    "iso:country":"DE",
    "sg:address":"An der Eisenschmelze 27",
    "sg:city":"Sonthofen",
    "sg:phone":"+49 8321/1377",
    "sg:postcode":"87527",
    "sg:province":"Bayern",
    "wof:name":"Bavarese Squash-center Gmbh",
    "wof:placetype":"venue"
},
  "geometry": {"coordinates":[10.275472641,47.5211296082],"type":"Point"}
}