{
  "type": "Feature",
  "properties": {
    "iso:country":"DE",
    "sg:address":"Ingolst\u00e4dter Str. 8",
    "sg:city":"Mindelstetten",
    "sg:phone":"+49 8404/288",
    "sg:postcode":"93349",
    "sg:province":"Bayern",
    "wof:name":"Johann Thoma Transport- Unternehmen Gmbh",
    "wof:placetype":"venue"
},
  "geometry": {"coordinates":[11.6391143799,48.8507881165],"type":"Point"}
}