{
  "type": "Feature",
  "properties": {
    "iso:country":"DE",
    "sg:address":"Mosbacher Str. 6",
    "sg:city":"Ilvesheim",
    "sg:phone":"+49 621/492986",
    "sg:postcode":"68549",
    "sg:province":"Baden-W\u00fcrttemberg",
    "wof:name":"Schnepf Gmbh",
    "wof:placetype":"venue"
},
  "geometry": {"coordinates":[8.566688,49.471294],"type":"Point"}
}