{
  "type": "Feature",
  "properties": {
    "iso:country":"DE",
    "sg:address":"Hauptbahnhof",
    "sg:city":"Eisenach",
    "sg:phone":"+49 3691/203078",
    "sg:postcode":"99817",
    "sg:province":"Th\u00fcringen",
    "wof:name":"Bahnhofsgastst\u00e4tte Mitropa",
    "wof:placetype":"venue"
},
  "geometry": {"coordinates":[10.3254394531,50.9743804932],"type":"Point"}
}