{
  "type": "Feature",
  "properties": {
    "iso:country":"DE",
    "sg:address":"Tr\u00e4nkeweg 13a",
    "sg:city":"F\u00fcrstenwalde/Spree",
    "sg:phone":"+49 3361",
    "sg:postcode":"15517",
    "sg:province":"Brandenburg",
    "wof:name":"Dina Transporte Gmbh",
    "wof:placetype":"venue"
},
  "geometry": {"coordinates":[14.0861368179,52.3463363647],"type":"Point"}
}