{
  "type": "Feature",
  "properties": {
    "iso:country":"DE",
    "sg:address":"Wipperstr.17 a",
    "sg:city":"Wolfsburg",
    "sg:phone":"+49 4953/6168688",
    "sg:postcode":"38448",
    "sg:province":"Niedersachsen",
    "wof:name":"Dresdner Bank",
    "wof:placetype":"venue"
},
  "geometry": {"coordinates":[10.808683,52.444626],"type":"Point"}
}