{
  "type": "Feature",
  "properties": {
    "iso:country":"DE",
    "sg:address":"Stensstr. 74",
    "sg:city":"Bochum",
    "sg:phone":"+49 234/521478",
    "sg:postcode":"44795",
    "sg:province":"Nordrhein-Westfalen",
    "wof:name":"Deutsche Shell Ag",
    "wof:placetype":"venue"
},
  "geometry": {"coordinates":[7.2036218643,51.4562034607],"type":"Point"}
}