{
  "type": "Feature",
  "properties": {
    "iso:country":"DE",
    "sg:address":"Dorfstr. 45",
    "sg:city":"Oyten",
    "sg:phone":"+49 4207/4670",
    "sg:postcode":"28876",
    "sg:province":"Niedersachsen",
    "wof:name":"Johann Grote",
    "wof:placetype":"venue"
},
  "geometry": {"coordinates":[9.024307,53.057835],"type":"Point"}
}