{
  "type": "Feature",
  "properties": {
    "iso:country":"DE",
    "sg:address":"Neubaustr. 52",
    "sg:city":"Albertshofen",
    "sg:phone":"+49 9321/31743",
    "sg:postcode":"97320",
    "sg:province":"Bayern",
    "wof:name":"Walter Gimperlein",
    "wof:placetype":"venue"
},
  "geometry": {"coordinates":[10.162115,49.764591],"type":"Point"}
}