{
  "type": "Feature",
  "properties": {
    "iso:country":"DE",
    "sg:address":"Rudolf-Diesel-Str. 18 PF 5205",
    "sg:city":"Eschborn",
    "sg:phone":"+49 6173/937300",
    "sg:postcode":"65760",
    "sg:province":"Hessen",
    "wof:name":"H. Costenoble Gmbh & Co Kg",
    "wof:placetype":"venue"
},
  "geometry": {"coordinates":[8.572111,50.140415],"type":"Point"}
}