{
  "type": "Feature",
  "properties": {
    "iso:country":"DE",
    "sg:address":"Berliner Ring 127-129",
    "sg:city":"Bensheim",
    "sg:postcode":"64625",
    "sg:province":"Hessen",
    "wof:name":"Cos Concat Ag",
    "wof:placetype":"venue"
},
  "geometry": {"coordinates":[8.6088199615,49.6895294189],"type":"Point"}
}