{
  "type": "Feature",
  "properties": {
    "iso:country":"DE",
    "sg:address":"Laufertorgraben 8",
    "sg:city":"N\u00fcrnberg",
    "sg:phone":"+49 911/587870",
    "sg:postcode":"90489",
    "sg:province":"Bayern",
    "wof:name":"P. Vogel",
    "wof:placetype":"venue"
},
  "geometry": {"coordinates":[11.0875864029,49.4539299011],"type":"Point"}
}