{
  "type": "Feature",
  "properties": {
    "iso:country":"DE",
    "sg:address":"Dresdener Str. 21",
    "sg:city":"Hohenlockstedt",
    "sg:phone":"+49 4826/2849",
    "sg:postcode":"25551",
    "sg:province":"Schleswig-Holstein",
    "wof:name":"M. Schlei",
    "wof:placetype":"venue"
},
  "geometry": {"coordinates":[9.618606,53.973709],"type":"Point"}
}