{
  "type": "Feature",
  "properties": {
    "iso:country":"DE",
    "sg:address":"Schleusinger Str. 64",
    "sg:city":"Brattendorf",
    "sg:phone":"+49 36878/60759",
    "sg:postcode":"98673",
    "sg:province":"Th\u00fcringen",
    "wof:name":"Ramona Fischer",
    "wof:placetype":"venue"
},
  "geometry": {"coordinates":[10.844986,50.474266],"type":"Point"}
}