{
  "type": "Feature",
  "properties": {
    "iso:country":"DE",
    "sg:address":"Friedrich-Ebert-Str. 7",
    "sg:city":"Kempten",
    "sg:postcode":"87437",
    "sg:province":"Bayern",
    "wof:name":"Leben Und Erleben Touristik Gmbh",
    "wof:placetype":"venue"
},
  "geometry": {"coordinates":[10.3259897232,47.7052841187],"type":"Point"}
}