{
  "type": "Feature",
  "properties": {
    "iso:country":"DE",
    "sg:address":"Bramscher Str. 3",
    "sg:city":"Neuenkirchen",
    "sg:phone":"+49 5465/653",
    "sg:postcode":"49586",
    "sg:province":"Niedersachsen",
    "wof:name":"August Abing",
    "wof:placetype":"venue"
},
  "geometry": {"coordinates":[7.8438010216,52.4109687805],"type":"Point"}
}