{
  "type": "Feature",
  "properties": {
    "iso:country":"DE",
    "sg:address":"Im Ilmenautal 8",
    "sg:city":"Bad Bevensen",
    "sg:phone":"+49 5821/1718",
    "sg:postcode":"29549",
    "sg:province":"Niedersachsen",
    "wof:name":"Haus Eilenriede",
    "wof:placetype":"venue"
},
  "geometry": {"coordinates":[10.573964119,53.0851097107],"type":"Point"}
}