{
  "type": "Feature",
  "properties": {
    "iso:country":"DE",
    "sg:address":"Wahmstr. 9",
    "sg:city":"L\u00fcbeck",
    "sg:phone":"+49 451/77955",
    "sg:postcode":"23552",
    "sg:province":"Schleswig-Holstein",
    "wof:name":"Ludwig Raub Dipl.-augenoptiker",
    "wof:placetype":"venue"
},
  "geometry": {"coordinates":[10.685924,53.865852],"type":"Point"}
}