{
  "type": "Feature",
  "properties": {
    "iso:country":"DE",
    "sg:address":"Kniestr. 16",
    "sg:city":"Espelkamp",
    "sg:phone":"+49 5743/500",
    "sg:postcode":"32339",
    "sg:province":"Nordrhein-Westfalen",
    "wof:name":"Buschmann Gmbh",
    "wof:placetype":"venue"
},
  "geometry": {"coordinates":[8.5991630554,52.3667144775],"type":"Point"}
}