{
  "type": "Feature",
  "properties": {
    "iso:country":"DE",
    "sg:address":"Postfach 60 01 52",
    "sg:city":"Sindelfingen",
    "sg:phone":"+49 4970/313010",
    "sg:postcode":"71050",
    "sg:province":"Baden-W\u00fcrttemberg",
    "wof:name":"Solo Stirling Engine - Solo Und Stirling",
    "wof:placetype":"venue"
},
  "geometry": {"coordinates":[9.00357,48.708462],"type":"Point"}
}