{
  "type": "Feature",
  "properties": {
    "iso:country":"DE",
    "sg:address":"August-Bebel-Str. 14",
    "sg:city":"Brieskow-Finkenheerd",
    "sg:phone":"+49 33609/278",
    "sg:postcode":"15295",
    "sg:province":"Brandenburg",
    "wof:name":"Farbgebung Eg",
    "wof:placetype":"venue"
},
  "geometry": {"coordinates":[14.572762,52.253006],"type":"Point"}
}