{
  "type": "Feature",
  "properties": {
    "iso:country":"DE",
    "sg:address":"Stra\u00dfburger Weg 5",
    "sg:city":"Gelsenkirchen",
    "sg:phone":"+49 209/134393",
    "sg:postcode":"45884",
    "sg:province":"Nordrhein-Westfalen",
    "wof:name":"Bernhard Nowienski",
    "wof:placetype":"venue"
},
  "geometry": {"coordinates":[7.0776891708,51.485294342],"type":"Point"}
}