{
  "type": "Feature",
  "properties": {
    "iso:country":"DE",
    "sg:address":"Hildesheimer Str. 19",
    "sg:city":"Dortmund",
    "sg:postcode":"44143",
    "sg:province":"Nordrhein-Westfalen",
    "wof:name":"Event Und Action Gmbh",
    "wof:placetype":"venue"
},
  "geometry": {"coordinates":[7.5234937668,51.5210533142],"type":"Point"}
}