{
  "type": "Feature",
  "properties": {
    "iso:country":"DE",
    "sg:address":"Gerhart-Hauptmann-Str. 1",
    "sg:city":"Nassau",
    "sg:phone":"+49 2604/951595",
    "sg:postcode":"56377",
    "sg:province":"Rheinland-Pfalz",
    "wof:name":"B & O Metellbearbeitung Ohg",
    "wof:placetype":"venue"
},
  "geometry": {"coordinates":[7.798943,50.313492],"type":"Point"}
}