{
  "type": "Feature",
  "properties": {
    "iso:country":"DE",
    "sg:address":"Landsberger Allee 233",
    "sg:city":"Berlin",
    "sg:phone":"+49 30/9752313",
    "sg:postcode":"13055",
    "sg:province":"Berlin",
    "wof:name":"Norbert Wichmann",
    "wof:placetype":"venue"
},
  "geometry": {"coordinates":[13.4880800247,52.5351524353],"type":"Point"}
}