{
  "type": "Feature",
  "properties": {
    "iso:country":"DE",
    "sg:address":"Halzenbecke 53",
    "sg:city":"Ennepetal",
    "sg:phone":"+49 2333/73696",
    "sg:postcode":"58256",
    "sg:province":"Nordrhein-Westfalen",
    "wof:name":"Hans-hugo G\u00f6belsmann",
    "wof:placetype":"venue"
},
  "geometry": {"coordinates":[7.319191,51.285698],"type":"Point"}
}