{
  "type": "Feature",
  "properties": {
    "iso:country":"DE",
    "sg:address":"Fichtenweg 45",
    "sg:city":"Kempen",
    "sg:phone":"+49 2152/559794",
    "sg:postcode":"47906",
    "sg:province":"Nordrhein-Westfalen",
    "wof:name":"Power Akademie",
    "wof:placetype":"venue"
},
  "geometry": {"coordinates":[6.413311,51.35083],"type":"Point"}
}