{
  "type": "Feature",
  "properties": {
    "iso:country":"DE",
    "sg:address":"Am Bahnhof 1",
    "sg:city":"Dingelst\u00e4dt",
    "sg:phone":"+49 36075/6880",
    "sg:postcode":"37351",
    "sg:province":"Th\u00fcringen",
    "wof:name":"Th\u00fcringer Agrartechnik Und Maschinenbau Gmbh",
    "wof:placetype":"venue"
},
  "geometry": {"coordinates":[10.3247947693,51.3234786987],"type":"Point"}
}