{
  "type": "Feature",
  "properties": {
    "iso:country":"DE",
    "sg:address":"Emmastr. 72",
    "sg:city":"Essen",
    "sg:phone":"+49 201/776713",
    "sg:postcode":"45130",
    "sg:province":"Nordrhein-Westfalen",
    "wof:name":"Horst Kn\u00fcpfken",
    "wof:placetype":"venue"
},
  "geometry": {"coordinates":[7.012798,51.434349],"type":"Point"}
}