{
  "type": "Feature",
  "properties": {
    "iso:country":"DE",
    "sg:address":"Rheinstr. 5",
    "sg:city":"Neuenburg",
    "sg:phone":"+49 7634/2892",
    "sg:postcode":"79395",
    "sg:province":"Baden-W\u00fcrttemberg",
    "wof:name":"Otto Kraus",
    "wof:placetype":"venue"
},
  "geometry": {"coordinates":[7.590306,47.876175],"type":"Point"}
}