{
  "type": "Feature",
  "properties": {
    "iso:country":"DE",
    "sg:address":"Spittelstr. 1-5",
    "sg:city":"Villingen-Schwenningen",
    "sg:phone":"+49 7720/63633",
    "sg:postcode":"78056",
    "sg:province":"Baden-W\u00fcrttemberg",
    "wof:name":"Reiser Immobilien",
    "wof:placetype":"venue"
},
  "geometry": {"coordinates":[8.5364217758,48.0667915344],"type":"Point"}
}