{
  "type": "Feature",
  "properties": {
    "iso:country":"DE",
    "sg:address":"Neichener Heide 13a",
    "sg:city":"Bad Honnef",
    "sg:postcode":"53604",
    "sg:province":"Nordrhein-Westfalen",
    "wof:name":"Mercator Beteiligungen Gmbh",
    "wof:placetype":"venue"
},
  "geometry": {"coordinates":[7.298644,50.653496],"type":"Point"}
}