{
  "type": "Feature",
  "properties": {
    "iso:country":"DE",
    "sg:address":"Kirchhofallee 25",
    "sg:city":"Kiel",
    "sg:phone":"+49 431/676767",
    "sg:postcode":"24103",
    "sg:province":"Schleswig-Holstein",
    "wof:name":"Tanzschule Tessmann E. K.",
    "wof:placetype":"venue"
},
  "geometry": {"coordinates":[10.1248979568,54.317691803],"type":"Point"}
}