{
  "type": "Feature",
  "properties": {
    "iso:country":"DE",
    "sg:address":"Saarstr. 9",
    "sg:city":"Saarbr\u00fccken",
    "sg:phone":"+49 681/399313",
    "sg:postcode":"66111",
    "sg:province":"Saarland",
    "wof:name":"Journal",
    "wof:placetype":"venue"
},
  "geometry": {"coordinates":[6.9955639839,49.2323722839],"type":"Point"}
}