{
  "type": "Feature",
  "properties": {
    "iso:country":"DE",
    "sg:address":"Paradeplatz 19",
    "sg:city":"Bad D\u00fcben",
    "sg:phone":"+49 34243/25001",
    "sg:postcode":"04849",
    "sg:province":"Sachsen",
    "wof:name":"Eilenburger Busverkehr Gmbh",
    "wof:placetype":"venue"
},
  "geometry": {"coordinates":[12.5884485245,51.591178894],"type":"Point"}
}