{
  "type": "Feature",
  "properties": {
    "iso:country":"DE",
    "sg:address":"Am Gr\u00fcndlein 2",
    "sg:city":"R\u00f6dental",
    "sg:phone":"+49 9563/8203",
    "sg:postcode":"96472",
    "sg:province":"Bayern",
    "wof:name":"Gerhard K\u00e4thner",
    "wof:placetype":"venue"
},
  "geometry": {"coordinates":[11.0510959625,50.2985877991],"type":"Point"}
}