{
  "type": "Feature",
  "properties": {
    "iso:country":"DE",
    "sg:address":"Reinhard-Rube-Str. 27",
    "sg:city":"G\u00f6ttingen",
    "sg:postcode":"37077",
    "sg:province":"Niedersachsen",
    "wof:name":"Smart-event Gmbh",
    "wof:placetype":"venue"
},
  "geometry": {"coordinates":[9.926132,51.562153],"type":"Point"}
}