{
  "type": "Feature",
  "properties": {
    "iso:country":"DE",
    "sg:address":"Stettener Str. 75",
    "sg:city":"Niederstotzingen",
    "sg:phone":"+49 7325/8868",
    "sg:postcode":"89168",
    "sg:province":"Baden-W\u00fcrttemberg",
    "wof:name":"Matthias Klaiber",
    "wof:placetype":"venue"
},
  "geometry": {"coordinates":[10.23144,48.544392],"type":"Point"}
}