{
  "type": "Feature",
  "properties": {
    "iso:country":"DE",
    "sg:address":"Lollenboom 32",
    "sg:city":"Hamburg",
    "sg:phone":"+49 40/55760167",
    "sg:postcode":"22453",
    "sg:province":"Hamburg",
    "wof:name":"Alles \u00fcber Pflege Bed\u00fcrftiger Menschen - Pflege Deutschland",
    "wof:placetype":"venue"
},
  "geometry": {"coordinates":[9.9803323746,53.6156005859],"type":"Point"}
}