{
  "type": "Feature",
  "properties": {
    "iso:country":"DE",
    "sg:address":"Posthalterweg 10",
    "sg:city":"Oldenburg",
    "sg:phone":"+49 441/794288",
    "sg:postcode":"26129",
    "sg:province":"Niedersachsen",
    "wof:name":"Elisabeth Hemmisoltmanns Buchhandlung",
    "wof:placetype":"venue"
},
  "geometry": {"coordinates":[8.1715841293,53.1597137451],"type":"Point"}
}