{
  "type": "Feature",
  "properties": {
    "iso:country":"DE",
    "sg:address":"Schellingstr. 132",
    "sg:city":"M\u00fcnchen",
    "sg:phone":"+49 89/1291762",
    "sg:postcode":"80797",
    "sg:province":"Bayern",
    "wof:name":"Anna Maria Ovcar \u00dcbersetzungsb\u00fcro",
    "wof:placetype":"venue"
},
  "geometry": {"coordinates":[11.560752,48.15472],"type":"Point"}
}