{
  "type": "Feature",
  "properties": {
    "iso:country":"DE",
    "sg:address":"Winkelfeld 16",
    "sg:city":"K\u00f6ln",
    "sg:phone":"+49 221/861477",
    "sg:postcode":"51107",
    "sg:province":"Nordrhein-Westfalen",
    "wof:name":"W. Nal",
    "wof:placetype":"venue"
},
  "geometry": {"coordinates":[7.0758619308,50.918762207],"type":"Point"}
}