{
  "type": "Feature",
  "properties": {
    "iso:country":"DE",
    "sg:address":"Friedensstr. 13",
    "sg:city":"A\u00dflar",
    "sg:phone":"+49 6441/81320",
    "sg:postcode":"35614",
    "sg:province":"Hessen",
    "wof:name":"Katholisches Pfarramt Christ-k\u00f6nig",
    "wof:placetype":"venue"
},
  "geometry": {"coordinates":[8.4718503952,50.5881080627],"type":"Point"}
}