{
  "type": "Feature",
  "properties": {
    "iso:country":"DE",
    "sg:address":"Heidenkampsweg 44",
    "sg:city":"Hamburg",
    "sg:phone":"+49 40/237788",
    "sg:postcode":"20097",
    "sg:province":"Hamburg",
    "wof:name":"Stiftung Grs Batterien",
    "wof:placetype":"venue"
},
  "geometry": {"coordinates":[10.026774,53.549583],"type":"Point"}
}