{
  "type": "Feature",
  "properties": {
    "iso:country":"DE",
    "sg:city":"Reichshof",
    "sg:phone":"+49 2265/8786",
    "sg:postcode":"51580",
    "sg:province":"Nordrhein-Westfalen",
    "wof:name":"Vogelpark Eckenhagen",
    "wof:placetype":"venue"
},
  "geometry": {"coordinates":[7.654582,50.915478],"type":"Point"}
}