{
  "type": "Feature",
  "properties": {
    "iso:country":"DE",
    "sg:address":"Teichstr. 17",
    "sg:city":"Zschorlau",
    "sg:phone":"+49 3771/258388",
    "sg:postcode":"08321",
    "sg:province":"Sachsen",
    "wof:name":"D. Bauer",
    "wof:placetype":"venue"
},
  "geometry": {"coordinates":[12.649399,50.548138],"type":"Point"}
}