{
  "type": "Feature",
  "properties": {
    "iso:country":"DE",
    "sg:address":"Niederransch\u00fctz 9",
    "sg:city":"Gro\u00dfweitzschen",
    "sg:phone":"+49 3431/574402",
    "sg:postcode":"04720",
    "sg:province":"Sachsen",
    "wof:name":"Steurer Technik Gmbh",
    "wof:placetype":"venue"
},
  "geometry": {"coordinates":[13.118637085,51.1605606079],"type":"Point"}
}