{
  "type": "Feature",
  "properties": {
    "iso:country":"DE",
    "sg:address":"Ludolf-Krehl-Str. 9",
    "sg:city":"Heidelberg",
    "sg:phone":"+49 6221/480506",
    "sg:postcode":"69120",
    "sg:province":"Baden-W\u00fcrttemberg",
    "wof:name":"Fh Diedrichs & L. Post Gmbh",
    "wof:placetype":"venue"
},
  "geometry": {"coordinates":[8.692656,49.421394],"type":"Point"}
}