{
  "type": "Feature",
  "properties": {
    "iso:country":"DE",
    "sg:address":"Weinsberger Str. 15",
    "sg:city":"Obersulm",
    "sg:phone":"+49 7134",
    "sg:postcode":"74182",
    "sg:province":"Baden-W\u00fcrttemberg",
    "wof:name":"Kern Geschenke-shop",
    "wof:placetype":"venue"
},
  "geometry": {"coordinates":[9.3542814255,49.1362457275],"type":"Point"}
}