{
  "type": "Feature",
  "properties": {
    "iso:country":"DE",
    "sg:address":"Rottenburger Str. 4",
    "sg:city":"Elsendorf",
    "sg:phone":"+49 8753/910086",
    "sg:postcode":"84094",
    "sg:province":"Bayern",
    "wof:name":"Naturafit-nahrungserg\u00e4nzung",
    "wof:placetype":"venue"
},
  "geometry": {"coordinates":[11.8102293015,48.708732605],"type":"Point"}
}