{
  "type": "Feature",
  "properties": {
    "iso:country":"DE",
    "sg:address":"Schulstr. 12",
    "sg:city":"Wi\u00dfmannsdorf",
    "sg:phone":"+49 6527/932211",
    "sg:postcode":"54636",
    "sg:province":"Rheinland-Pfalz",
    "wof:name":"Relox Regiebau Gmbh",
    "wof:placetype":"venue"
},
  "geometry": {"coordinates":[6.4269399643,50.0002403259],"type":"Point"}
}