{
  "type": "Feature",
  "properties": {
    "iso:country":"DE",
    "sg:address":"Wingertstr. 6",
    "sg:city":"Schweinfurt",
    "sg:phone":"+49 9721/26124",
    "sg:postcode":"97422",
    "sg:province":"Bayern",
    "wof:name":"Wiederer Immobilien Gmbh",
    "wof:placetype":"venue"
},
  "geometry": {"coordinates":[10.240386,50.050362],"type":"Point"}
}