{
  "type": "Feature",
  "properties": {
    "iso:country":"DE",
    "sg:address":"Akazienstr. 7",
    "sg:city":"Detmold",
    "sg:phone":"+49 5231/88417",
    "sg:postcode":"32760",
    "sg:province":"Nordrhein-Westfalen",
    "wof:name":"Willi Jenseit",
    "wof:placetype":"venue"
},
  "geometry": {"coordinates":[8.843607,51.924862],"type":"Point"}
}