{
  "type": "Feature",
  "properties": {
    "iso:country":"DE",
    "sg:address":"Schulstr. 6",
    "sg:city":"Schwalbach",
    "sg:phone":"+49 6196/508550",
    "sg:postcode":"65824",
    "sg:province":"Hessen",
    "wof:name":"Planergruppe Rob Regional- Planung Ortsplanung Und",
    "wof:placetype":"venue"
},
  "geometry": {"coordinates":[6.8115801811,49.2999839783],"type":"Point"}
}