{
  "type": "Feature",
  "properties": {
    "iso:country":"DE",
    "sg:address":"Billrothstr. 28",
    "sg:city":"Essen",
    "sg:phone":"+49 201/703035",
    "sg:postcode":"45147",
    "sg:province":"Nordrhein-Westfalen",
    "wof:name":"Ka Team Amb. Kranken- Und Altenpflege",
    "wof:placetype":"venue"
},
  "geometry": {"coordinates":[6.992419,51.437122],"type":"Point"}
}