{
  "type": "Feature",
  "properties": {
    "iso:country":"DE",
    "sg:address":"Im Gewerbegebiet 2",
    "sg:city":"Achern",
    "sg:phone":"+49 7841/209514",
    "sg:postcode":"77855",
    "sg:province":"Baden-W\u00fcrttemberg",
    "wof:name":"Thorry Metalltechnik Gmbh",
    "wof:placetype":"venue"
},
  "geometry": {"coordinates":[8.0408391953,48.636302948],"type":"Point"}
}