{
  "type": "Feature",
  "properties": {
    "iso:country":"DE",
    "sg:address":"Postwiesenstr 5a",
    "sg:city":"Stuttgart",
    "sg:phone":"+49 711/6017520",
    "sg:postcode":"70327",
    "sg:province":"Baden-W\u00fcrttemberg",
    "wof:name":"K\u00f6gler",
    "wof:placetype":"venue"
},
  "geometry": {"coordinates":[9.252006,48.777233],"type":"Point"}
}