{
  "type": "Feature",
  "properties": {
    "iso:country":"DE",
    "sg:address":"Berner Str. 107 POSTFACH 560125",
    "sg:city":"Frankfurt",
    "sg:phone":"+49 4969/500020",
    "sg:postcode":"60406",
    "sg:province":"Brandenburg",
    "wof:name":"Imtech Deutschland Gmbh & Co. Kg Hauptniederlassung Frankfurt",
    "wof:placetype":"venue"
},
  "geometry": {"coordinates":[8.6843,50.112251],"type":"Point"}
}