{
  "type": "Feature",
  "properties": {
    "iso:country":"DE",
    "sg:address":"kramgasse 27",
    "sg:city":"andernach",
    "sg:phone":"+49 2632",
    "sg:postcode":"56626",
    "sg:province":"Rheinland-Pfalz",
    "wof:name":"Spielsachen-shop",
    "wof:placetype":"venue"
},
  "geometry": {"coordinates":[7.39971,50.438969],"type":"Point"}
}