{
  "type": "Feature",
  "properties": {
    "iso:country":"DE",
    "sg:address":"Schwimmbadstr. 32 a",
    "sg:city":"Breuberg",
    "sg:phone":"+49 6163/913345",
    "sg:postcode":"64747",
    "sg:province":"Hessen",
    "wof:name":"Walbrun Gmbh",
    "wof:placetype":"venue"
},
  "geometry": {"coordinates":[9.010708,49.818771],"type":"Point"}
}