{
  "type": "Feature",
  "properties": {
    "iso:country":"DE",
    "sg:address":"Riedstr. 6",
    "sg:city":"Weinbergen",
    "sg:phone":"+49 36014/40391",
    "sg:postcode":"99998",
    "sg:province":"Th\u00fcringen",
    "wof:name":"Piehl Gmbh & Co. Dachdeckerei Kg",
    "wof:placetype":"venue"
},
  "geometry": {"coordinates":[10.533442,51.198826],"type":"Point"}
}