{
  "type": "Feature",
  "properties": {
    "iso:country":"DE",
    "sg:address":"Heinrich-Heine-Str. 3",
    "sg:city":"L\u00fcbz",
    "sg:phone":"+49 38731/25212",
    "sg:postcode":"19386",
    "sg:province":"Mecklenburg-Vorpommern",
    "wof:name":"Hans-j\u00fcrgen Guder",
    "wof:placetype":"venue"
},
  "geometry": {"coordinates":[12.04609,53.458366],"type":"Point"}
}