{
  "type": "Feature",
  "properties": {
    "iso:country":"DE",
    "sg:address":"Siemensstr. 4",
    "sg:city":"Dorfen",
    "sg:phone":"+49 8081/938490",
    "sg:postcode":"84405",
    "sg:province":"Bayern",
    "wof:name":"Massivbau Haberkorn Gesellschaft F\u00fcr Bauabwicklung",
    "wof:placetype":"venue"
},
  "geometry": {"coordinates":[12.162435,48.267879],"type":"Point"}
}