{
  "type": "Feature",
  "properties": {
    "iso:country":"DE",
    "sg:address":"Hochfeldstr. 4",
    "sg:city":"Augsburg",
    "sg:phone":"+49 821/257800",
    "sg:postcode":"86159",
    "sg:province":"Bayern",
    "wof:name":"Cyril Kajnar Architekt",
    "wof:placetype":"venue"
},
  "geometry": {"coordinates":[10.899704,48.359116],"type":"Point"}
}