{
  "type": "Feature",
  "properties": {
    "iso:country":"DE",
    "sg:address":"Auf der H\u00f6he 20",
    "sg:city":"Hahnst\u00e4tten",
    "sg:phone":"+49 6430/1031",
    "sg:postcode":"65623",
    "sg:province":"Rheinland-Pfalz",
    "wof:name":"Imo- Gmbh Industriemontage",
    "wof:placetype":"venue"
},
  "geometry": {"coordinates":[8.0622682571,50.3071403503],"type":"Point"}
}