{
  "type": "Feature",
  "properties": {
    "iso:country":"DE",
    "sg:address":"Zugspitzstr. 25",
    "sg:city":"Ebersberg",
    "sg:phone":"+49 8092/21408",
    "sg:postcode":"85560",
    "sg:province":"Bayern",
    "wof:name":"Rudolf Weinzierl",
    "wof:placetype":"venue"
},
  "geometry": {"coordinates":[11.9590387344,48.0713729858],"type":"Point"}
}