{
  "type": "Feature",
  "properties": {
    "iso:country":"DE",
    "sg:address":"Kruppstra\u00dfe 58",
    "sg:city":"Kamp-Lintfort",
    "sg:postcode":"47475",
    "sg:province":"Nordrhein-Westfalen",
    "wof:name":"Aktiv Geb\u00e4udereinigung & Dienstleistungs Gmbh",
    "wof:placetype":"venue"
},
  "geometry": {"coordinates":[6.549805,51.516911],"type":"Point"}
}