{
  "type": "Feature",
  "properties": {
    "iso:country":"DE",
    "sg:address":"Annenheider Str. 243",
    "sg:city":"Delmenhorst",
    "sg:phone":"+49 4221/98610",
    "sg:postcode":"27755",
    "sg:province":"Niedersachsen",
    "wof:name":"Vereinigte Transportbeton- Werke Nordtrans Gmbh & Co.",
    "wof:placetype":"venue"
},
  "geometry": {"coordinates":[8.64301,53.020538],"type":"Point"}
}