{
  "type": "Feature",
  "properties": {
    "iso:country":"DE",
    "sg:address":"Gablenberger Hauptstr. 34b",
    "sg:city":"Stuttgart",
    "sg:phone":"+49 711/484185",
    "sg:postcode":"70186",
    "sg:province":"Baden-W\u00fcrttemberg",
    "wof:name":"Schwanen",
    "wof:placetype":"venue"
},
  "geometry": {"coordinates":[9.20703125,48.7789039612],"type":"Point"}
}