{
  "type": "Feature",
  "properties": {
    "iso:country":"DE",
    "sg:address":"Celler Str. 8a",
    "sg:city":"Bergen",
    "sg:phone":"+49 5051/3034",
    "sg:postcode":"29303",
    "sg:province":"Niedersachsen",
    "wof:name":"Anzeiger-verlag G\u00fcnter Ernst Gmbh",
    "wof:placetype":"venue"
},
  "geometry": {"coordinates":[9.96404,52.808178],"type":"Point"}
}