{
  "type": "Feature",
  "properties": {
    "iso:country":"DE",
    "sg:address":"Marbach 2",
    "sg:city":"Breitscheid",
    "sg:phone":"+49 2777/7851",
    "sg:postcode":"35767",
    "sg:province":"Hessen",
    "wof:name":"Eberhard Germann",
    "wof:placetype":"venue"
},
  "geometry": {"coordinates":[8.178172,50.664051],"type":"Point"}
}