{
  "type": "Feature",
  "properties": {
    "iso:country":"DE",
    "sg:address":"T\u00fcrkenlouisschanze 9",
    "sg:city":"Talheim",
    "sg:phone":"+49 7133/8144",
    "sg:postcode":"74388",
    "sg:province":"Baden-W\u00fcrttemberg",
    "wof:name":"Golo-wilhelm Maser Steuerberater",
    "wof:placetype":"venue"
},
  "geometry": {"coordinates":[9.1930980682,49.0886421204],"type":"Point"}
}