{
  "type": "Feature",
  "properties": {
    "iso:country":"DE",
    "sg:address":"Veit-Sto\u00df-Str. 13",
    "sg:city":"M\u00fcnchen",
    "sg:phone":"+49 89/565777",
    "sg:postcode":"80687",
    "sg:province":"Bayern",
    "wof:name":"Prodomos Palestis",
    "wof:placetype":"venue"
},
  "geometry": {"coordinates":[11.5094003677,48.1408119202],"type":"Point"}
}