{
  "type": "Feature",
  "properties": {
    "iso:country":"DE",
    "sg:address":"Probacher Str. 74",
    "sg:city":"Eitorf",
    "sg:phone":"+49 2243/81093",
    "sg:postcode":"53783",
    "sg:province":"Nordrhein-Westfalen",
    "wof:name":"R. Litschel",
    "wof:placetype":"venue"
},
  "geometry": {"coordinates":[7.45976,50.77776],"type":"Point"}
}