{
  "type": "Feature",
  "properties": {
    "iso:country":"DE",
    "sg:address":"Zwickauer Str. 485",
    "sg:city":"Chemnitz",
    "sg:phone":"+49 371/852022",
    "sg:postcode":"09117",
    "sg:province":"Sachsen",
    "wof:name":"Chemnitzer Athletenclub E. V.",
    "wof:placetype":"venue"
},
  "geometry": {"coordinates":[12.8282318115,50.811504364],"type":"Point"}
}