{
  "type": "Feature",
  "properties": {
    "iso:country":"DE",
    "sg:address":"Kurf\u00fcrstenstr. 13-19",
    "sg:city":"M\u00fclheim-K\u00e4rlich",
    "sg:phone":"+49 2630/959230",
    "sg:postcode":"56218",
    "sg:province":"Rheinland-Pfalz",
    "wof:name":"Paul Michael Dohmen Architekt",
    "wof:placetype":"venue"
},
  "geometry": {"coordinates":[7.498777,50.388134],"type":"Point"}
}