{
  "type": "Feature",
  "properties": {
    "iso:country":"DE",
    "sg:address":"Lagerhausstr. 9",
    "sg:city":"Garmisch-Partenkirchen",
    "sg:phone":"+49 8821/9190",
    "sg:postcode":"82467",
    "sg:province":"Bayern",
    "wof:name":"Haus An Der Partnach Seniorenwohn- Und Pflegeheim",
    "wof:placetype":"venue"
},
  "geometry": {"coordinates":[11.099426,47.490196],"type":"Point"}
}