{
  "type": "Feature",
  "properties": {
    "iso:country":"DE",
    "sg:address":"Peter-Spahn-Str. 11",
    "sg:city":"Oestrich-Winkel",
    "sg:phone":"+49 6723/2844",
    "sg:postcode":"65375",
    "sg:province":"Hessen",
    "wof:name":"Martin Freimuth",
    "wof:placetype":"venue"
},
  "geometry": {"coordinates":[8.00408,49.999969],"type":"Point"}
}