{
  "type": "Feature",
  "properties": {
    "iso:country":"DE",
    "sg:address":"Norisstr. 28",
    "sg:city":"Schwaig",
    "sg:phone":"+49 911/5075377",
    "sg:postcode":"90571",
    "sg:province":"Bayern",
    "wof:name":"Manfred Zerner",
    "wof:placetype":"venue"
},
  "geometry": {"coordinates":[11.192684,49.479427],"type":"Point"}
}