{
  "type": "Feature",
  "properties": {
    "iso:country":"DE",
    "sg:address":"Cannstatter Str. 132",
    "sg:city":"Fellbach",
    "sg:postcode":"70734",
    "sg:province":"Baden-W\u00fcrttemberg",
    "wof:name":"Volksbank Feudingen Eg",
    "wof:placetype":"venue"
},
  "geometry": {"coordinates":[8.35151,50.92424],"type":"Point"}
}