{
  "type": "Feature",
  "properties": {
    "iso:country":"DE",
    "sg:address":"Sportplatzweg 7",
    "sg:city":"Oelsberg",
    "sg:phone":"+49 6772/961767",
    "sg:postcode":"56357",
    "sg:province":"Rheinland-Pfalz",
    "wof:name":"G\u00fcnter Kauschmann",
    "wof:placetype":"venue"
},
  "geometry": {"coordinates":[7.8390388489,50.1966018677],"type":"Point"}
}