{
  "type": "Feature",
  "properties": {
    "iso:country":"DE",
    "sg:address":"Glaserstr. 18",
    "sg:city":"Duisburg",
    "sg:phone":"+49 203/734835",
    "sg:postcode":"47055",
    "sg:province":"Nordrhein-Westfalen",
    "wof:name":"Gastst\u00e4tte Glaserstube",
    "wof:placetype":"venue"
},
  "geometry": {"coordinates":[6.753098011,51.4044303894],"type":"Point"}
}