{
  "type": "Feature",
  "properties": {
    "iso:country":"DE",
    "sg:address":"Krummenackerstr. 235",
    "sg:city":"Esslingen",
    "sg:phone":"+49 711/378676",
    "sg:postcode":"73733",
    "sg:province":"Baden-W\u00fcrttemberg",
    "wof:name":"S. M\u00fcller",
    "wof:placetype":"venue"
},
  "geometry": {"coordinates":[9.2974996567,48.7623405457],"type":"Point"}
}