{
  "type": "Feature",
  "properties": {
    "iso:country":"DE",
    "sg:address":"Schenkendorfstr. 4",
    "sg:city":"Regensburg",
    "sg:phone":"+49 941/26302",
    "sg:postcode":"93049",
    "sg:province":"Bayern",
    "wof:name":"Manfred Leitl Gmbh",
    "wof:placetype":"venue"
},
  "geometry": {"coordinates":[12.078122139,49.0220603943],"type":"Point"}
}