{
  "type": "Feature",
  "properties": {
    "iso:country":"DE",
    "sg:address":"Esborner Str. 219",
    "sg:city":"Wetter",
    "sg:phone":"+49 2335/7960",
    "sg:postcode":"58300",
    "sg:province":"Nordrhein-Westfalen",
    "wof:name":"Manfred Sczech",
    "wof:placetype":"venue"
},
  "geometry": {"coordinates":[7.3343338966,51.3758163452],"type":"Point"}
}