{
  "type": "Feature",
  "properties": {
    "iso:country":"DE",
    "sg:address":"Kirchplatz 1",
    "sg:city":"Selm",
    "sg:phone":"+49 2592/7276",
    "sg:postcode":"59379",
    "sg:province":"Nordrhein-Westfalen",
    "wof:name":"B. Krause",
    "wof:placetype":"venue"
},
  "geometry": {"coordinates":[7.4665880203,51.6651763916],"type":"Point"}
}