{
  "type": "Feature",
  "properties": {
    "iso:country":"DE",
    "sg:address":"K\u00f6rnerstr. 7",
    "sg:city":"Rhede",
    "sg:phone":"+49 2872/3872",
    "sg:postcode":"46414",
    "sg:province":"Nordrhein-Westfalen",
    "wof:name":"Horst Und Ursula Steier",
    "wof:placetype":"venue"
},
  "geometry": {"coordinates":[6.6954078674,51.8288154602],"type":"Point"}
}