{
  "type": "Feature",
  "properties": {
    "iso:country":"DE",
    "sg:address":"Glauburgstr. 95",
    "sg:city":"Frankfurt",
    "sg:phone":"+49 69/550491",
    "sg:postcode":"60318",
    "sg:province":"Hessen",
    "wof:name":"P. J. Kleinhammer Immobilienmakler",
    "wof:placetype":"venue"
},
  "geometry": {"coordinates":[8.6825618744,50.1259613037],"type":"Point"}
}