{
  "type": "Feature",
  "properties": {
    "iso:country":"DE",
    "sg:address":"Marburger Str. 65",
    "sg:city":"Marburg",
    "sg:phone":"+49 6421/51576",
    "sg:postcode":"35043",
    "sg:province":"Hessen",
    "wof:name":"Martin List",
    "wof:placetype":"venue"
},
  "geometry": {"coordinates":[8.7681722641,50.7845840454],"type":"Point"}
}