{
  "type": "Feature",
  "properties": {
    "iso:country":"DE",
    "sg:address":"In der Bruchwiese 1",
    "sg:city":"Merzig",
    "sg:phone":"+49 6861/88615",
    "sg:postcode":"66663",
    "sg:province":"Saarland",
    "wof:name":"Manfred Baumann",
    "wof:placetype":"venue"
},
  "geometry": {"coordinates":[6.61628,49.464489],"type":"Point"}
}