{
  "type": "Feature",
  "properties": {
    "iso:country":"DE",
    "sg:address":"Hessenstr 2",
    "sg:city":"Bayreuth",
    "sg:phone":"+49 921/78640",
    "sg:postcode":"95448",
    "sg:province":"Bayern",
    "wof:name":"Tat-schwarzer",
    "wof:placetype":"venue"
},
  "geometry": {"coordinates":[11.5936088562,49.9391021729],"type":"Point"}
}