{
  "type": "Feature",
  "properties": {
    "iso:country":"DE",
    "sg:address":"Scharringhausen 17",
    "sg:city":"Kirchdorf",
    "sg:phone":"+49 4273/351",
    "sg:postcode":"27245",
    "sg:province":"Niedersachsen",
    "wof:name":"Gastst\u00e4tte Hans Plenge",
    "wof:placetype":"venue"
},
  "geometry": {"coordinates":[8.8066387177,52.5889816284],"type":"Point"}
}