{
  "type": "Feature",
  "properties": {
    "iso:country":"DE",
    "sg:address":"Dreifelderstr. 36",
    "sg:city":"Stuttgart",
    "sg:phone":"+49 711/458840",
    "sg:postcode":"70599",
    "sg:province":"Baden-W\u00fcrttemberg",
    "wof:name":"Geberit Gmbh",
    "wof:placetype":"venue"
},
  "geometry": {"coordinates":[9.220617,48.702969],"type":"Point"}
}