{
  "type": "Feature",
  "properties": {
    "iso:country":"DE",
    "sg:address":"Bahnhofstr. 15",
    "sg:city":"Deisenhofen",
    "sg:phone":"+49 89/6131504",
    "sg:postcode":"82041",
    "sg:province":"Bayern",
    "wof:name":"A.u.g. Strau\u00df Backhaus Gmbh",
    "wof:placetype":"venue"
},
  "geometry": {"coordinates":[11.588256,48.018761],"type":"Point"}
}