{
  "type": "Feature",
  "properties": {
    "iso:country":"DE",
    "sg:address":"Barbarastr. 1",
    "sg:city":"Lennestadt",
    "sg:phone":"+49 2721/8711",
    "sg:postcode":"57368",
    "sg:province":"Nordrhein-Westfalen",
    "wof:name":"Bau- Und M\u00f6belschreinerei Struwe Gmbh",
    "wof:placetype":"venue"
},
  "geometry": {"coordinates":[8.068219,51.124905],"type":"Point"}
}