{
  "type": "Feature",
  "properties": {
    "iso:country":"DE",
    "sg:address":"Str. B 1",
    "sg:city":"Hoyerswerda",
    "sg:phone":"+49 4935/7148540",
    "sg:postcode":"02977",
    "sg:province":"Sachsen",
    "wof:name":"Wiener Feinb\u00c4ckerei Heberer Gmbh Hoyerswerda",
    "wof:placetype":"venue"
},
  "geometry": {"coordinates":[14.28945,51.432869],"type":"Point"}
}