{
  "type": "Feature",
  "properties": {
    "iso:country":"DE",
    "sg:address":"Emmastr 1-3",
    "sg:city":"Bremen",
    "sg:phone":"+49 421/342755",
    "sg:postcode":"28213",
    "sg:province":"Bremen",
    "wof:name":"Hanseatic Promotion Bremen Ek",
    "wof:placetype":"venue"
},
  "geometry": {"coordinates":[8.8338031769,53.0942115784],"type":"Point"}
}