{
  "type": "Feature",
  "properties": {
    "iso:country":"DE",
    "sg:address":"Nickelstr. 44",
    "sg:city":"Eschweiler",
    "sg:phone":"+49 2403/24732",
    "sg:postcode":"52249",
    "sg:province":"Nordrhein-Westfalen",
    "wof:name":"Neukel Akustikbau Gmbh",
    "wof:placetype":"venue"
},
  "geometry": {"coordinates":[6.239251,50.824081],"type":"Point"}
}