{
  "type": "Feature",
  "properties": {
    "iso:country":"DE",
    "sg:address":"Kamperstr. 26",
    "sg:city":"Velbert",
    "sg:phone":"+49 2052/1481",
    "sg:postcode":"42555",
    "sg:province":"Nordrhein-Westfalen",
    "wof:name":"Fitzinger Musall Und Schreiber Rechtsanw\u00e4lte",
    "wof:placetype":"venue"
},
  "geometry": {"coordinates":[7.118789196,51.3518028259],"type":"Point"}
}