{
  "type": "Feature",
  "properties": {
    "iso:country":"DE",
    "sg:address":"Heisterort 7",
    "sg:city":"Syke",
    "sg:phone":"+49 4240/239",
    "sg:postcode":"28857",
    "sg:province":"Niedersachsen",
    "wof:name":"Landwirtschaftl. Verein Guntram Haase",
    "wof:placetype":"venue"
},
  "geometry": {"coordinates":[8.9053897858,52.8772201538],"type":"Point"}
}