{
  "type": "Feature",
  "properties": {
    "iso:country":"DE",
    "sg:address":"Am Bergwerkswald 20",
    "sg:city":"Linden",
    "sg:phone":"+49 641/29079",
    "sg:postcode":"35440",
    "sg:province":"Hessen",
    "wof:name":"Druckkollektiv Bergwerkswald Gmbh",
    "wof:placetype":"venue"
},
  "geometry": {"coordinates":[8.67899,50.561069],"type":"Point"}
}