{
  "type": "Feature",
  "properties": {
    "iso:country":"DE",
    "sg:address":"Lange Str. 11",
    "sg:city":"Spenge",
    "sg:phone":"+49 5225/5236",
    "sg:postcode":"32139",
    "sg:province":"Nordrhein-Westfalen",
    "wof:name":"Spenger Partyservice",
    "wof:placetype":"venue"
},
  "geometry": {"coordinates":[8.48246,52.139263],"type":"Point"}
}