{
  "type": "Feature",
  "properties": {
    "iso:country":"DE",
    "sg:address":"Poststr. 66",
    "sg:city":"Ibbenb\u00fcren",
    "sg:phone":"+49 5451/13866",
    "sg:postcode":"49477",
    "sg:province":"Nordrhein-Westfalen",
    "wof:name":"Wilhelm Stratmann Steuerberater",
    "wof:placetype":"venue"
},
  "geometry": {"coordinates":[7.7050552368,52.2785873413],"type":"Point"}
}