{
  "type": "Feature",
  "properties": {
    "iso:country":"DE",
    "sg:address":"Keplerstr. 21",
    "sg:city":"Chemnitz",
    "sg:phone":"+49 371/8577500",
    "sg:postcode":"09117",
    "sg:province":"Sachsen",
    "wof:name":"Genossenschaftsheim",
    "wof:placetype":"venue"
},
  "geometry": {"coordinates":[12.8496799469,50.8230171204],"type":"Point"}
}