{
  "type": "Feature",
  "properties": {
    "iso:country":"DE",
    "sg:city":"Hirschberg",
    "sg:phone":"+49 6201/507920",
    "sg:postcode":"69493",
    "sg:province":"Baden-W\u00fcrttemberg",
    "wof:name":"Bezirkssparkasse Weinheim",
    "wof:placetype":"venue"
},
  "geometry": {"coordinates":[8.659509,49.511929],"type":"Point"}
}