{
  "type": "Feature",
  "properties": {
    "iso:country":"DE",
    "sg:address":"Stockumer Str. 414",
    "sg:city":"Dortmund",
    "sg:phone":"+49 231/750880",
    "sg:postcode":"44227",
    "sg:province":"Nordrhein-Westfalen",
    "wof:name":"Claudia Schwenk",
    "wof:placetype":"venue"
},
  "geometry": {"coordinates":[7.406947,51.481319],"type":"Point"}
}