{
  "type": "Feature",
  "properties": {
    "iso:country":"DE",
    "sg:address":"S\u00fc\u00dfener Str. 20",
    "sg:city":"Stuttgart",
    "sg:phone":"+49 711/422436",
    "sg:postcode":"70327",
    "sg:province":"Baden-W\u00fcrttemberg",
    "wof:name":"H. Hirschle",
    "wof:placetype":"venue"
},
  "geometry": {"coordinates":[9.243705,48.774128],"type":"Point"}
}