{
  "type": "Feature",
  "properties": {
    "iso:country":"DE",
    "sg:address":"Kauzenburg",
    "sg:city":"Bad Kreuznach",
    "sg:phone":"+49 671/38000",
    "sg:postcode":"55545",
    "sg:province":"Rheinland-Pfalz",
    "wof:name":"Landhotel Kauzenberg Ingrid Wagner Kg",
    "wof:placetype":"venue"
},
  "geometry": {"coordinates":[7.8538341522,49.8447418213],"type":"Point"}
}