{
  "type": "Feature",
  "properties": {
    "iso:country":"DE",
    "sg:address":"Gewerbestr. 1",
    "sg:city":"Bippen",
    "sg:phone":"+49 5435/345",
    "sg:postcode":"49626",
    "sg:province":"Niedersachsen",
    "wof:name":"Adolf Neublum",
    "wof:placetype":"venue"
},
  "geometry": {"coordinates":[7.7483420372,52.5816192627],"type":"Point"}
}