{
  "type": "Feature",
  "properties": {
    "iso:country":"DE",
    "sg:address":"Alte Heerstr. 78",
    "sg:city":"Hameln",
    "sg:phone":"+49 5151/12928",
    "sg:postcode":"31789",
    "sg:province":"Niedersachsen",
    "wof:name":"Werner Br\u00fcggemann",
    "wof:placetype":"venue"
},
  "geometry": {"coordinates":[9.418611,52.113342],"type":"Point"}
}