{
  "type": "Feature",
  "properties": {
    "iso:country":"DE",
    "sg:address":"Stresemannallee 98-100",
    "sg:city":"Hamburg",
    "sg:phone":"+49 40/567046",
    "sg:postcode":"22529",
    "sg:province":"Hamburg",
    "wof:name":"Fritz Lange",
    "wof:placetype":"venue"
},
  "geometry": {"coordinates":[9.9554252625,53.5847854614],"type":"Point"}
}