{
  "type": "Feature",
  "properties": {
    "iso:country":"DE",
    "sg:address":"Kissinger Str. 58",
    "sg:city":"Hammelburg",
    "sg:phone":"+49 9732/91310",
    "sg:postcode":"97762",
    "sg:province":"Bayern",
    "wof:name":"Schilder Neeb",
    "wof:placetype":"venue"
},
  "geometry": {"coordinates":[9.895772,50.115227],"type":"Point"}
}