{
  "type": "Feature",
  "properties": {
    "iso:country":"DE",
    "sg:address":"Gotenstr. 3",
    "sg:city":"Sigmaringen",
    "sg:phone":"+49 7571/52064",
    "sg:postcode":"72488",
    "sg:province":"Baden-W\u00fcrttemberg",
    "wof:name":"Gerd M\u00fcller",
    "wof:placetype":"venue"
},
  "geometry": {"coordinates":[9.195452,48.083622],"type":"Point"}
}