{
  "type": "Feature",
  "properties": {
    "iso:country":"DE",
    "sg:address":"Fasanenplatz 1",
    "sg:city":"Moers",
    "sg:phone":"+49 2841/22110",
    "sg:postcode":"47441",
    "sg:province":"Nordrhein-Westfalen",
    "wof:name":"Helmut E\u00dfer",
    "wof:placetype":"venue"
},
  "geometry": {"coordinates":[6.6122059822,51.4477272034],"type":"Point"}
}