{
  "type": "Feature",
  "properties": {
    "iso:country":"DE",
    "sg:address":"Auf der Holzm\u00fchle 26",
    "sg:city":"Saarlouis",
    "sg:phone":"+49 6831/40694",
    "sg:postcode":"66740",
    "sg:province":"Saarland",
    "wof:name":"K. H. Freichel",
    "wof:placetype":"venue"
},
  "geometry": {"coordinates":[6.742215,49.300392],"type":"Point"}
}