{
  "type": "Feature",
  "properties": {
    "iso:country":"DE",
    "sg:address":"Dorfstr. 42",
    "sg:city":"B\u00f6rnichen",
    "sg:phone":"+49 37294/1422",
    "sg:postcode":"09437",
    "sg:province":"Sachsen",
    "wof:name":"Gerd Damm",
    "wof:placetype":"venue"
},
  "geometry": {"coordinates":[13.1413326263,50.7502593994],"type":"Point"}
}