{
  "type": "Feature",
  "properties": {
    "iso:country":"DE",
    "sg:address":"M\u00fchlstr. 2",
    "sg:city":"M\u00f6nchsdeggingen",
    "sg:phone":"+49 9088/342",
    "sg:postcode":"86751",
    "sg:province":"Bayern",
    "wof:name":"Margarete Scheidle",
    "wof:placetype":"venue"
},
  "geometry": {"coordinates":[10.5786180496,48.7762336731],"type":"Point"}
}