{
  "type": "Feature",
  "properties": {
    "iso:country":"DE",
    "sg:address":"Rosenallee 5-7",
    "sg:city":"Eschweiler",
    "sg:phone":"+49 2403/37307",
    "sg:postcode":"52249",
    "sg:province":"Nordrhein-Westfalen",
    "wof:name":"E.-j. Maiwald Rechtsanwalt",
    "wof:placetype":"venue"
},
  "geometry": {"coordinates":[6.2643499374,50.8169708252],"type":"Point"}
}