{
  "type": "Feature",
  "properties": {
    "iso:country":"DE",
    "sg:address":"Paul-List-Str. 17",
    "sg:city":"Leipzig",
    "sg:postcode":"04103",
    "sg:province":"Sachsen",
    "wof:name":"Christliche Lebenshilfe Leipzig E. V.",
    "wof:placetype":"venue"
},
  "geometry": {"coordinates":[12.3838644028,51.3303489685],"type":"Point"}
}