{
  "type": "Feature",
  "properties": {
    "iso:country":"DE",
    "sg:address":"Gaiganz",
    "sg:city":"Effeltrich",
    "sg:phone":"+49 9199/238",
    "sg:postcode":"91090",
    "sg:province":"Bayern",
    "wof:name":"G. Siebenhaar",
    "wof:placetype":"venue"
},
  "geometry": {"coordinates":[11.099383,49.662106],"type":"Point"}
}