{
  "type": "Feature",
  "properties": {
    "iso:country":"DE",
    "sg:address":"B\u00f6hmische Str. 1",
    "sg:city":"Altenberg",
    "sg:postcode":"01773",
    "sg:province":"Sachsen",
    "wof:name":"Eiscafe Sartor",
    "wof:placetype":"venue"
},
  "geometry": {"coordinates":[13.67151,50.795216],"type":"Point"}
}