{
  "type": "Feature",
  "properties": {
    "iso:country":"DE",
    "sg:address":"Regentenstr. 151",
    "sg:city":"M\u00f6nchengladbach",
    "sg:phone":"+49 2161/13495",
    "sg:postcode":"41061",
    "sg:province":"Nordrhein-Westfalen",
    "wof:name":"Hans-willi Schl\u00f6\u00dfer",
    "wof:placetype":"venue"
},
  "geometry": {"coordinates":[6.4437208176,51.2021598816],"type":"Point"}
}