{
  "type": "Feature",
  "properties": {
    "iso:country":"DE",
    "sg:address":"Adam-Opel-Str. 3",
    "sg:city":"Frankfurt",
    "sg:postcode":"60386",
    "sg:province":"Hessen",
    "wof:name":"Charter Air Services Gmbh",
    "wof:placetype":"venue"
},
  "geometry": {"coordinates":[8.751976,50.122612],"type":"Point"}
}