{
  "type": "Feature",
  "properties": {
    "iso:country":"DE",
    "sg:address":"Friedenstr. 21a",
    "sg:city":"Bad Oeynhausen",
    "sg:phone":"+49 5731/17840",
    "sg:postcode":"32547",
    "sg:province":"Nordrhein-Westfalen",
    "wof:name":"Diether Holzkamp Steuerberater",
    "wof:placetype":"venue"
},
  "geometry": {"coordinates":[8.8244552612,52.2090034485],"type":"Point"}
}