{
  "type": "Feature",
  "properties": {
    "iso:country":"DE",
    "sg:address":"B\u00f6nst\u00e4dter Str. 28",
    "sg:city":"Niddatal",
    "sg:phone":"+49 6034/2945",
    "sg:postcode":"61194",
    "sg:province":"Hessen",
    "wof:name":"Kurt G\u00e4rtner Bau- Und Kunstschlosserei",
    "wof:placetype":"venue"
},
  "geometry": {"coordinates":[8.8185892105,50.2962799072],"type":"Point"}
}