{
  "type": "Feature",
  "properties": {
    "iso:country":"DE",
    "sg:address":"Marktplatz 27",
    "sg:city":"Lehesten",
    "sg:phone":"+49 36653/22216",
    "sg:postcode":"07349",
    "sg:province":"Th\u00fcringen",
    "wof:name":"Gastst\u00e4tte Gl\u00fcckauf",
    "wof:placetype":"venue"
},
  "geometry": {"coordinates":[11.4481601715,50.4753417969],"type":"Point"}
}