{
  "type": "Feature",
  "properties": {
    "iso:country":"DE",
    "sg:address":"Arndtstr. 36",
    "sg:city":"Leipzig",
    "sg:phone":"+49 341/3010092",
    "sg:postcode":"04275",
    "sg:province":"Sachsen",
    "wof:name":"Weisses R\u00f6ssel",
    "wof:placetype":"venue"
},
  "geometry": {"coordinates":[12.3736896515,51.3232116699],"type":"Point"}
}