{
  "type": "Feature",
  "properties": {
    "iso:country":"DE",
    "sg:address":"Raiffeisenstr. 14",
    "sg:city":"Suhlendorf",
    "sg:postcode":"29562",
    "sg:province":"Niedersachsen",
    "wof:name":"C. Q. Canadische Qualit\u00e4ts- Produkte Vertriebsges. Mbh",
    "wof:placetype":"venue"
},
  "geometry": {"coordinates":[10.7647619247,52.9244041443],"type":"Point"}
}