{
  "type": "Feature",
  "properties": {
    "iso:country":"DE",
    "sg:address":"Lindenstr.",
    "sg:city":"H\u00f6hr-Grenzhausen",
    "sg:phone":"+49 2624/6395",
    "sg:postcode":"56203",
    "sg:province":"Rheinland-Pfalz",
    "wof:name":"Waldgasthaus Uhlenhorst",
    "wof:placetype":"venue"
},
  "geometry": {"coordinates":[7.6585588455,50.4422836304],"type":"Point"}
}