{
  "type": "Feature",
  "properties": {
    "iso:country":"DE",
    "sg:address":"Killertalstr. 6",
    "sg:city":"Jungingen",
    "sg:phone":"+49 7477/633",
    "sg:postcode":"72417",
    "sg:province":"Baden-W\u00fcrttemberg",
    "wof:name":"Killertal-apotheke",
    "wof:placetype":"venue"
},
  "geometry": {"coordinates":[9.04272,48.326294],"type":"Point"}
}