{
  "type": "Feature",
  "properties": {
    "iso:country":"DE",
    "sg:address":"Pf\u00e4lzer Str. 56a",
    "sg:city":"Gro\u00dfkarolinenfeld",
    "sg:phone":"+49 8031/5131",
    "sg:postcode":"83109",
    "sg:province":"Bayern",
    "wof:name":"O. U. H. Tristl",
    "wof:placetype":"venue"
},
  "geometry": {"coordinates":[12.084379,47.89793],"type":"Point"}
}