{
  "type": "Feature",
  "properties": {
    "iso:country":"DE",
    "sg:address":"Klausenerplatz 8",
    "sg:city":"Berlin",
    "sg:phone":"+49 30/3255696",
    "sg:postcode":"14059",
    "sg:province":"Berlin",
    "wof:name":"Klara Jahn",
    "wof:placetype":"venue"
},
  "geometry": {"coordinates":[13.292136,52.517738],"type":"Point"}
}