{
  "type": "Feature",
  "properties": {
    "iso:country":"DE",
    "sg:address":"Tulpenstra\u00dfe 2",
    "sg:city":"Bruckm\u00fchl",
    "sg:phone":"+49 8062/8099655",
    "sg:postcode":"83052",
    "sg:province":"Bayern",
    "wof:name":"Marketing & Communication",
    "wof:placetype":"venue"
},
  "geometry": {"coordinates":[11.937412,47.878036],"type":"Point"}
}