{
  "type": "Feature",
  "properties": {
    "iso:country":"DE",
    "sg:address":"Burgstr. 9",
    "sg:city":"Neuhausen",
    "sg:phone":"+49 7158/7200",
    "sg:postcode":"73765",
    "sg:province":"Baden-W\u00fcrttemberg",
    "wof:name":"Trend Bau Bautr\u00e4ger- Und Baubetreuungsgesellschaft Mbh",
    "wof:placetype":"venue"
},
  "geometry": {"coordinates":[9.2831468582,48.683719635],"type":"Point"}
}