{
  "type": "Feature",
  "properties": {
    "iso:country":"DE",
    "sg:address":"Flughafenstr. 30",
    "sg:city":"M\u00f6rfelden-Walldorf",
    "sg:phone":"+49 6105/74772",
    "sg:postcode":"64546",
    "sg:province":"Hessen",
    "wof:name":"Bernhard Und Gentzen Rechtsanw\u00e4lte Und Notare",
    "wof:placetype":"venue"
},
  "geometry": {"coordinates":[8.5766391754,50.0047111511],"type":"Point"}
}