{
  "type": "Feature",
  "properties": {
    "iso:country":"DE",
    "sg:address":"Krautstr. 2",
    "sg:city":"Memmingen",
    "sg:phone":"+49 8331/944500",
    "sg:postcode":"87700",
    "sg:province":"Bayern",
    "wof:name":"Mdle Medical Laboratories Europe Gmbh",
    "wof:placetype":"venue"
},
  "geometry": {"coordinates":[10.182476,47.987007],"type":"Point"}
}