{
  "type": "Feature",
  "properties": {
    "iso:country":"DE",
    "sg:address":"Am Weinberg 5",
    "sg:city":"Heideck",
    "sg:phone":"+49 9177/225",
    "sg:postcode":"91180",
    "sg:province":"Bayern",
    "wof:name":"Georg Kr\u00e4mer",
    "wof:placetype":"venue"
},
  "geometry": {"coordinates":[11.12375,49.13546],"type":"Point"}
}