{
  "type": "Feature",
  "properties": {
    "iso:country":"DE",
    "sg:address":"Bundesstr. 18",
    "sg:city":"Breisach",
    "sg:phone":"+49 7664/3693",
    "sg:postcode":"79206",
    "sg:province":"Baden-W\u00fcrttemberg",
    "wof:name":"Franz Weismann",
    "wof:placetype":"venue"
},
  "geometry": {"coordinates":[7.5821070671,48.0282096863],"type":"Point"}
}