{
  "type": "Feature",
  "properties": {
    "iso:country":"DE",
    "sg:address":"Ziegelwasen 6",
    "sg:city":"Balingen",
    "sg:phone":"+49 7433/99600",
    "sg:postcode":"72336",
    "sg:province":"Baden-W\u00fcrttemberg",
    "wof:name":"K\u00fcbler Gmbh",
    "wof:placetype":"venue"
},
  "geometry": {"coordinates":[8.8504734039,48.2370491028],"type":"Point"}
}