{
  "type": "Feature",
  "properties": {
    "iso:country":"DE",
    "sg:address":"Martin-Luther-Platz 6",
    "sg:city":"Wei\u00dfenburg",
    "sg:phone":"+49 9141/2064",
    "sg:postcode":"91781",
    "sg:province":"Bayern",
    "wof:name":"Bestattungsinstitut Denk",
    "wof:placetype":"venue"
},
  "geometry": {"coordinates":[10.970329,49.032238],"type":"Point"}
}