{
  "type": "Feature",
  "properties": {
    "iso:country":"DE",
    "sg:address":"Hugo-Asbach-Str. 35",
    "sg:city":"R\u00fcdesheim am Rhein",
    "sg:phone":"+49 6722/2810",
    "sg:postcode":"65385",
    "sg:province":"Hessen",
    "wof:name":"Karl Kremer Kohlen-handlung",
    "wof:placetype":"venue"
},
  "geometry": {"coordinates":[7.930944,49.983757],"type":"Point"}
}