{
  "type": "Feature",
  "properties": {
    "iso:country":"DE",
    "sg:address":"D\u00fclkenstr. 1",
    "sg:city":"K\u00f6ln",
    "sg:phone":"+49 2203/951013",
    "sg:postcode":"51143",
    "sg:province":"Nordrhein-Westfalen",
    "wof:name":"D\u00fclken-apotheke Inh. Hans-georg Hermeling",
    "wof:placetype":"venue"
},
  "geometry": {"coordinates":[7.054202,50.889641],"type":"Point"}
}