{
  "type": "Feature",
  "properties": {
    "iso:country":"DE",
    "sg:address":"Obere W\u00f6rthstr. 6",
    "sg:city":"N\u00fcrnberg",
    "sg:phone":"+49 911/225734",
    "sg:postcode":"90403",
    "sg:province":"Bayern",
    "wof:name":"H. H\u00fclf Und A. Fiehl",
    "wof:placetype":"venue"
},
  "geometry": {"coordinates":[11.0738897324,49.4524726868],"type":"Point"}
}