{
  "type": "Feature",
  "properties": {
    "iso:country":"DE",
    "sg:address":"Bahnhofstr 73",
    "sg:city":"Tuttlingen",
    "sg:phone":"+49 7461/2302",
    "sg:postcode":"78532",
    "sg:province":"Baden-W\u00fcrttemberg",
    "wof:name":"Karl Bollmann Gmbh & Co Kg",
    "wof:placetype":"venue"
},
  "geometry": {"coordinates":[8.81042,47.98283],"type":"Point"}
}