{
  "type": "Feature",
  "properties": {
    "iso:country":"DE",
    "sg:address":"Rektor-Ritter-Str. 2",
    "sg:city":"Hamburg",
    "sg:phone":"+49 40/7217240",
    "sg:postcode":"21029",
    "sg:province":"Hamburg",
    "wof:name":"Aydogan Bau Gmbh",
    "wof:placetype":"venue"
},
  "geometry": {"coordinates":[10.2156772614,53.4847602844],"type":"Point"}
}