{
  "type": "Feature",
  "properties": {
    "iso:country":"DE",
    "sg:address":"Vo\u00dfbergweg 79",
    "sg:city":"Hatten",
    "sg:phone":"+49 4481/7200",
    "sg:postcode":"26209",
    "sg:province":"Niedersachsen",
    "wof:name":"Hobbie Kurierdienst Gmbh",
    "wof:placetype":"venue"
},
  "geometry": {"coordinates":[8.284113884,53.0439300537],"type":"Point"}
}