{
  "type": "Feature",
  "properties": {
    "iso:country":"DE",
    "sg:address":"Mittelbeune 14",
    "sg:city":"Seligenstadt",
    "sg:postcode":"63500",
    "sg:province":"Hessen",
    "wof:name":"Balasai Verlag E. K.",
    "wof:placetype":"venue"
},
  "geometry": {"coordinates":[8.966881752,50.0408248901],"type":"Point"}
}