{
  "type": "Feature",
  "properties": {
    "iso:country":"DE",
    "sg:address":"Seeh\u00e4user Str. 80",
    "sg:city":"Arendsee",
    "sg:phone":"+49 39384/834",
    "sg:postcode":"39619",
    "sg:province":"Sachsen-Anhalt",
    "wof:name":"Holzverarbeitungs Gmbh",
    "wof:placetype":"venue"
},
  "geometry": {"coordinates":[11.441865,52.892143],"type":"Point"}
}