{
  "type": "Feature",
  "properties": {
    "iso:country":"DE",
    "sg:address":"Rechenberger Str. 22",
    "sg:city":"Jagstzell",
    "sg:phone":"+49 7967/8034",
    "sg:postcode":"73489",
    "sg:province":"Baden-W\u00fcrttemberg",
    "wof:name":"Frank Reinigungssysteme Gmbh",
    "wof:placetype":"venue"
},
  "geometry": {"coordinates":[10.096674,49.028278],"type":"Point"}
}