{
  "type": "Feature",
  "properties": {
    "iso:country":"DE",
    "sg:address":"Hauptstr. 39",
    "sg:city":"Petting",
    "sg:phone":"+49 8686/255",
    "sg:postcode":"83367",
    "sg:province":"Bayern",
    "wof:name":"H. Sammer Mech. Werkstatt",
    "wof:placetype":"venue"
},
  "geometry": {"coordinates":[12.814004,47.912525],"type":"Point"}
}