{
  "type": "Feature",
  "properties": {
    "iso:country":"DE",
    "sg:address":"Hauptstr. 229",
    "sg:city":"Troisdorf",
    "sg:phone":"+49 2241/408603",
    "sg:postcode":"53842",
    "sg:province":"Nordrhein-Westfalen",
    "wof:name":"Gamintchi Gamins Wein-depot",
    "wof:placetype":"venue"
},
  "geometry": {"coordinates":[7.1115999222,50.8316040039],"type":"Point"}
}