{
  "type": "Feature",
  "properties": {
    "iso:country":"DE",
    "sg:address":"Hauptstr. 14",
    "sg:city":"Ebstorf",
    "sg:phone":"+49 5822/3941",
    "sg:postcode":"29574",
    "sg:province":"Niedersachsen",
    "wof:name":"Ebstorfer-apotheke",
    "wof:placetype":"venue"
},
  "geometry": {"coordinates":[10.41603,53.028622],"type":"Point"}
}