{
  "type": "Feature",
  "properties": {
    "iso:country":"DE",
    "sg:address":"Vilbeler Str. 6",
    "sg:city":"Sch\u00f6neck",
    "sg:phone":"+49 6187/5690",
    "sg:postcode":"61137",
    "sg:province":"Hessen",
    "wof:name":"Otto Sch\u00e4fer",
    "wof:placetype":"venue"
},
  "geometry": {"coordinates":[8.8319358826,50.2136421204],"type":"Point"}
}