{
  "type": "Feature",
  "properties": {
    "iso:country":"DE",
    "sg:address":"Alte Dorfstr. 5b",
    "sg:city":"Kurort Seiffen",
    "sg:phone":"+49 37362/8348",
    "sg:postcode":"09548",
    "sg:province":"Sachsen",
    "wof:name":"Johannes Gl\u00f6ckner Dach- Und Bau Gmbh",
    "wof:placetype":"venue"
},
  "geometry": {"coordinates":[13.460484,50.646824],"type":"Point"}
}