{
  "type": "Feature",
  "properties": {
    "iso:country":"DE",
    "sg:address":"B\u00e4ringerstr. 8",
    "sg:city":"Goslar",
    "sg:phone":"+49 5321/23496",
    "sg:postcode":"38640",
    "sg:province":"Niedersachsen",
    "wof:name":"G\u00e4stehaus F. Zellmer",
    "wof:placetype":"venue"
},
  "geometry": {"coordinates":[10.4220304489,51.9065933228],"type":"Point"}
}