{
  "type": "Feature",
  "properties": {
    "iso:country":"DE",
    "sg:address":"Donker Str. 185",
    "sg:city":"M\u00f6nchengladbach",
    "sg:postcode":"41066",
    "sg:province":"Nordrhein-Westfalen",
    "wof:name":"Frw Hygieneberatung Gmbh",
    "wof:placetype":"venue"
},
  "geometry": {"coordinates":[6.468535,51.234901],"type":"Point"}
}