{
  "type": "Feature",
  "properties": {
    "iso:country":"DE",
    "sg:address":"Lauenthaler Weg 4",
    "sg:city":"Lahstedt",
    "sg:phone":"+49 5172/8217",
    "sg:postcode":"31246",
    "sg:province":"Niedersachsen",
    "wof:name":"Burghard Kommorowski",
    "wof:placetype":"venue"
},
  "geometry": {"coordinates":[10.203747,52.243393],"type":"Point"}
}