{
  "type": "Feature",
  "properties": {
    "iso:country":"DE",
    "sg:address":"Rippberger Str. 9",
    "sg:city":"Schneeberg",
    "sg:phone":"+49 9373/9400",
    "sg:postcode":"63936",
    "sg:province":"Bayern",
    "wof:name":"Dolzer Ma\u00dfschneider Gmbh",
    "wof:placetype":"venue"
},
  "geometry": {"coordinates":[9.2526664734,49.6408195496],"type":"Point"}
}