{
  "type": "Feature",
  "properties": {
    "iso:country":"DE",
    "sg:address":"Raboisen 2",
    "sg:city":"Hamburg",
    "sg:phone":"+49 40/323013",
    "sg:postcode":"20095",
    "sg:province":"Hamburg",
    "wof:name":"Ristorante I Italia Vero",
    "wof:placetype":"venue"
},
  "geometry": {"coordinates":[10.002199173,53.5545387268],"type":"Point"}
}