{
  "type": "Feature",
  "properties": {
    "iso:country":"DE",
    "sg:address":"Lehmweg 6",
    "sg:city":"Plettenberg",
    "sg:phone":"+49 2391/10878",
    "sg:postcode":"58840",
    "sg:province":"Nordrhein-Westfalen",
    "wof:name":"Fritz Herzhoff",
    "wof:placetype":"venue"
},
  "geometry": {"coordinates":[7.851017,51.200844],"type":"Point"}
}