{
  "type": "Feature",
  "properties": {
    "iso:country":"DE",
    "sg:address":"Hauptstr. 14",
    "sg:city":"Bad Nenndorf",
    "sg:postcode":"31542",
    "sg:province":"Niedersachsen",
    "wof:name":"K.-l. Ertmer Tankstellen Gmbh",
    "wof:placetype":"venue"
},
  "geometry": {"coordinates":[9.378302,52.336082],"type":"Point"}
}