{
  "type": "Feature",
  "properties": {
    "iso:country":"DE",
    "sg:address":"Neusser Str. 93",
    "sg:city":"Kaarst",
    "sg:phone":"+49 2131/602273",
    "sg:postcode":"41564",
    "sg:province":"Nordrhein-Westfalen",
    "wof:name":"Dls Drahtzaun Lenssen Stahlbau Gmbh & Co. Kg",
    "wof:placetype":"venue"
},
  "geometry": {"coordinates":[6.6351881027,51.230430603],"type":"Point"}
}