{
  "type": "Feature",
  "properties": {
    "iso:country":"DE",
    "sg:address":"Theresienstr. 102",
    "sg:city":"M\u00fcnchen",
    "sg:phone":"+49 89/5237484",
    "sg:postcode":"80333",
    "sg:province":"Bayern",
    "wof:name":"Isar Metall Handels Gmbh",
    "wof:placetype":"venue"
},
  "geometry": {"coordinates":[11.5665178299,48.1506347656],"type":"Point"}
}