{
  "type": "Feature",
  "properties": {
    "iso:country":"DE",
    "sg:address":"Butzener Str. 1",
    "sg:city":"Cottbus",
    "sg:phone":"+49 355/860721",
    "sg:postcode":"03044",
    "sg:province":"Brandenburg",
    "wof:name":"Lausitzer Baumpflege Cottbus Gmbh",
    "wof:placetype":"venue"
},
  "geometry": {"coordinates":[14.323332,51.782909],"type":"Point"}
}