{
  "type": "Feature",
  "properties": {
    "iso:country":"DE",
    "sg:address":"Moststr. 12",
    "sg:city":"F\u00fcrth",
    "sg:phone":"+49 911/9774690",
    "sg:postcode":"90762",
    "sg:province":"Bayern",
    "wof:name":"Apollo-optik Augenoptik",
    "wof:placetype":"venue"
},
  "geometry": {"coordinates":[10.9905424118,49.4738311768],"type":"Point"}
}