{
  "type": "Feature",
  "properties": {
    "iso:country":"DE",
    "sg:address":"Im Langen Bruch 5",
    "sg:city":"K\u00f6ln",
    "sg:postcode":"51109",
    "sg:province":"Nordrhein-Westfalen",
    "wof:name":"Der K\u00fcmerer E. K.",
    "wof:placetype":"venue"
},
  "geometry": {"coordinates":[7.077353,50.952682],"type":"Point"}
}