{
  "type": "Feature",
  "properties": {
    "iso:country":"DE",
    "sg:address":"Am Limberg 16",
    "sg:city":"Georgsmarienh\u00fctte",
    "sg:phone":"+49 5409/869",
    "sg:postcode":"49124",
    "sg:province":"Niedersachsen",
    "wof:name":"Fliesen Kutschki",
    "wof:placetype":"venue"
},
  "geometry": {"coordinates":[8.1169424057,52.1758995056],"type":"Point"}
}