{
  "type": "Feature",
  "properties": {
    "iso:country":"DE",
    "sg:address":"Im Dorfe 10",
    "sg:city":"Hamb\u00fchren",
    "sg:phone":"+49 5084/5344",
    "sg:postcode":"29313",
    "sg:province":"Niedersachsen",
    "wof:name":"Ernst Martin",
    "wof:placetype":"venue"
},
  "geometry": {"coordinates":[9.985612,52.636982],"type":"Point"}
}