{
  "type": "Feature",
  "properties": {
    "iso:country":"DE",
    "sg:address":"Lange Gasse 28",
    "sg:city":"Treuen",
    "sg:phone":"+49 37468/2223",
    "sg:postcode":"08233",
    "sg:province":"Sachsen",
    "wof:name":"Heinz St\u00f6ckel",
    "wof:placetype":"venue"
},
  "geometry": {"coordinates":[12.303457,50.541988],"type":"Point"}
}