{
  "type": "Feature",
  "properties": {
    "iso:country":"DE",
    "sg:address":"Sch\u00f6nbergweg 10",
    "sg:city":"Berlin",
    "sg:phone":"+49 30/6635408",
    "sg:postcode":"12355",
    "sg:province":"Berlin",
    "wof:name":"Willi Boos",
    "wof:placetype":"venue"
},
  "geometry": {"coordinates":[13.520813,52.412163],"type":"Point"}
}