{
  "type": "Feature",
  "properties": {
    "iso:country":"DE",
    "sg:address":"Unterer Krautgarten 10",
    "sg:city":"Bad Laasphe",
    "sg:phone":"+49 2752/1332",
    "sg:postcode":"57334",
    "sg:province":"Nordrhein-Westfalen",
    "wof:name":"Willi D\u00f6rr",
    "wof:placetype":"venue"
},
  "geometry": {"coordinates":[8.3618001938,50.9232978821],"type":"Point"}
}