{
  "type": "Feature",
  "properties": {
    "iso:country":"DE",
    "sg:address":"Lotter Str. 75",
    "sg:city":"Osnabr\u00fcck",
    "sg:phone":"+49 541/433152",
    "sg:postcode":"49078",
    "sg:province":"Niedersachsen",
    "wof:name":"Imbi\u00df Grillmaster",
    "wof:placetype":"venue"
},
  "geometry": {"coordinates":[8.0214166641,52.2739486694],"type":"Point"}
}