{
  "type": "Feature",
  "properties": {
    "iso:country":"DE",
    "sg:address":"R\u00f6dingsmarkt 16",
    "sg:city":"Hamburg",
    "sg:phone":"+49 40/361460",
    "sg:postcode":"20459",
    "sg:province":"Hamburg",
    "wof:name":"Verwaltung Schiffahrts-ges. Hansa Centurion Mbh",
    "wof:placetype":"venue"
},
  "geometry": {"coordinates":[9.985311,53.54715],"type":"Point"}
}