{
  "type": "Feature",
  "properties": {
    "iso:country":"DE",
    "sg:address":"Reddinger Weg 1",
    "sg:city":"Haste",
    "sg:phone":"+49 5723/8757",
    "sg:postcode":"31559",
    "sg:province":"Niedersachsen",
    "wof:name":"H. G\u00fcmmer",
    "wof:placetype":"venue"
},
  "geometry": {"coordinates":[9.3941221237,52.3812561035],"type":"Point"}
}