{
  "type": "Feature",
  "properties": {
    "iso:country":"DE",
    "sg:address":"Ahlersbacher Str. 20",
    "sg:city":"Schl\u00fcchtern",
    "sg:phone":"+49 6661/2711",
    "sg:postcode":"36381",
    "sg:province":"Hessen",
    "wof:name":"Oswald M\u00fcller",
    "wof:placetype":"venue"
},
  "geometry": {"coordinates":[9.557166,50.344849],"type":"Point"}
}