{
  "type": "Feature",
  "properties": {
    "iso:country":"DE",
    "sg:address":"Adlerstr. 10",
    "sg:city":"Titisee-Neustadt",
    "sg:phone":"+49 7651/2676",
    "sg:postcode":"79822",
    "sg:province":"Baden-W\u00fcrttemberg",
    "wof:name":"Schwarz Und Kn\u00f6pfle",
    "wof:placetype":"venue"
},
  "geometry": {"coordinates":[8.213236,47.912361],"type":"Point"}
}