{
  "type": "Feature",
  "properties": {
    "iso:country":"DE",
    "sg:address":"St.-Martin-Str. 5",
    "sg:city":"Langenargen",
    "sg:phone":"+49 7543/4789",
    "sg:postcode":"88085",
    "sg:province":"Baden-W\u00fcrttemberg",
    "wof:name":"Optimaler Gmbh",
    "wof:placetype":"venue"
},
  "geometry": {"coordinates":[9.532673,47.603909],"type":"Point"}
}