{
  "type": "Feature",
  "properties": {
    "iso:country":"DE",
    "sg:address":"Schlegldorf 21 A",
    "sg:city":"Lenggries",
    "sg:phone":"+49 8042/2557",
    "sg:postcode":"83661",
    "sg:province":"Bayern",
    "wof:name":"Wenig Mosterei",
    "wof:placetype":"venue"
},
  "geometry": {"coordinates":[11.559931,47.694862],"type":"Point"}
}