{
  "type": "Feature",
  "properties": {
    "iso:country":"DE",
    "sg:address":"Beatrixstr. 1",
    "sg:city":"Bad Kissingen",
    "sg:phone":"+49 971/99720",
    "sg:postcode":"97688",
    "sg:province":"Bayern",
    "wof:name":"Pension Sch\u00e4fli",
    "wof:placetype":"venue"
},
  "geometry": {"coordinates":[10.0872163773,50.1858482361],"type":"Point"}
}