{
  "type": "Feature",
  "properties": {
    "iso:country":"DE",
    "sg:address":"Beethovenstr. 22",
    "sg:city":"Georgsmarienh\u00fctte",
    "sg:phone":"+49 5401/86470",
    "sg:postcode":"49124",
    "sg:province":"Niedersachsen",
    "wof:name":"Wgs Energietechnik Gmbh",
    "wof:placetype":"venue"
},
  "geometry": {"coordinates":[8.0575437546,52.1954689026],"type":"Point"}
}