{
  "type": "Feature",
  "properties": {
    "iso:country":"DE",
    "sg:address":"Alte Dorfstr. 44",
    "sg:city":"Pl\u00f6tzin",
    "sg:phone":"+49 33207/32730",
    "sg:postcode":"14542",
    "sg:province":"Brandenburg",
    "wof:name":"Patricia Kreutzer",
    "wof:placetype":"venue"
},
  "geometry": {"coordinates":[12.833927,52.364586],"type":"Point"}
}