{
  "type": "Feature",
  "properties": {
    "iso:country":"DE",
    "sg:address":"Memminger Str. 10",
    "sg:city":"Bad Gr\u00f6nenbach",
    "sg:phone":"+49 8334/595",
    "sg:postcode":"87730",
    "sg:province":"Bayern",
    "wof:name":"Ludwig Zimmermann",
    "wof:placetype":"venue"
},
  "geometry": {"coordinates":[10.22033,47.877304],"type":"Point"}
}