{
  "type": "Feature",
  "properties": {
    "iso:country":"DE",
    "sg:address":"Schillerstr. 34",
    "sg:city":"Rodgau",
    "sg:phone":"+49 6106/4843",
    "sg:postcode":"63110",
    "sg:province":"Hessen",
    "wof:name":"Victor Weinerek",
    "wof:placetype":"venue"
},
  "geometry": {"coordinates":[8.893989563,50.0496177673],"type":"Point"}
}