{
  "type": "Feature",
  "properties": {
    "iso:country":"DE",
    "sg:address":"Ebertsheimer Str. 26",
    "sg:city":"Kerzenheim",
    "sg:phone":"+49 6351/42137",
    "sg:postcode":"67304",
    "sg:province":"Rheinland-Pfalz",
    "wof:name":"R. Und J. Wiesheu",
    "wof:placetype":"venue"
},
  "geometry": {"coordinates":[8.063712,49.576401],"type":"Point"}
}