{
  "type": "Feature",
  "properties": {
    "iso:country":"DE",
    "sg:address":"Frankenhaager Str. 3",
    "sg:city":"Mistelgau",
    "sg:phone":"+49 9279/9586",
    "sg:postcode":"95490",
    "sg:province":"Bayern",
    "wof:name":"A & A Computer Gmbh",
    "wof:placetype":"venue"
},
  "geometry": {"coordinates":[11.4619131088,49.9075088501],"type":"Point"}
}