{
  "type": "Feature",
  "properties": {
    "iso:country":"DE",
    "sg:address":"Postfach 1144",
    "sg:city":"Weiler-Simmerberg",
    "sg:phone":"+49 8387/1344",
    "sg:postcode":"88168",
    "sg:province":"Bayern",
    "wof:name":"Gemeindeb\u00fccherei Verkehrsamt",
    "wof:placetype":"venue"
},
  "geometry": {"coordinates":[9.94414,47.586399],"type":"Point"}
}