{
  "type": "Feature",
  "properties": {
    "iso:country":"DE",
    "sg:address":"Hiltensweiler",
    "sg:city":"Tettnang",
    "sg:phone":"+49 7543/8341",
    "sg:postcode":"88069",
    "sg:province":"Baden-W\u00fcrttemberg",
    "wof:name":"T. H\u00e4usler",
    "wof:placetype":"venue"
},
  "geometry": {"coordinates":[9.6579189301,47.6245384216],"type":"Point"}
}