{
  "type": "Feature",
  "properties": {
    "iso:country":"DE",
    "sg:address":"Raffenberg 42",
    "sg:city":"Hattingen",
    "sg:phone":"+49 2324/92510",
    "sg:postcode":"45529",
    "sg:province":"Nordrhein-Westfalen",
    "wof:name":"Hotel Haus Raffenberg",
    "wof:placetype":"venue"
},
  "geometry": {"coordinates":[7.1735391617,51.3652801514],"type":"Point"}
}