{
  "type": "Feature",
  "properties": {
    "iso:country":"DE",
    "sg:address":"Berliner Str. 23",
    "sg:city":"Villingen-Schwenningen",
    "sg:phone":"+49 7721/6020",
    "sg:postcode":"78048",
    "sg:province":"Baden-W\u00fcrttemberg",
    "wof:name":"Goldenburger Krankenhaus Dr. Adolf-k\u00fchne-stiftung",
    "wof:placetype":"venue"
},
  "geometry": {"coordinates":[8.4463262558,48.072971344],"type":"Point"}
}