{
  "type": "Feature",
  "properties": {
    "iso:country":"DE",
    "sg:address":"Altenburger Str. 36",
    "sg:city":"Waldenburg",
    "sg:phone":"+49 37608/22497",
    "sg:postcode":"08396",
    "sg:province":"Sachsen",
    "wof:name":"Eiscafe",
    "wof:placetype":"venue"
},
  "geometry": {"coordinates":[12.599382,50.875675],"type":"Point"}
}