{
  "type": "Feature",
  "properties": {
    "iso:country":"DE",
    "sg:address":"L\u00f6hrstr. 10",
    "sg:city":"Leipzig",
    "sg:phone":"+49 341/2115280",
    "sg:postcode":"04105",
    "sg:province":"Sachsen",
    "wof:name":"Ephraim Carlebach Stiftung E. V.",
    "wof:placetype":"venue"
},
  "geometry": {"coordinates":[12.3738307953,51.3453445435],"type":"Point"}
}