{
  "type": "Feature",
  "properties": {
    "iso:country":"DE",
    "sg:address":"Osterl\u00e4ngstr. 26",
    "sg:city":"Schw\u00e4bisch Gm\u00fcnd",
    "sg:phone":"+49 7171/71915",
    "sg:postcode":"73527",
    "sg:province":"Baden-W\u00fcrttemberg",
    "wof:name":"Thuma-kuhn",
    "wof:placetype":"venue"
},
  "geometry": {"coordinates":[9.820372,48.831612],"type":"Point"}
}