{
  "type": "Feature",
  "properties": {
    "iso:country":"DE",
    "sg:address":"Snirgelskamp 12 c",
    "sg:city":"Herten",
    "sg:phone":"+49 2366/81082",
    "sg:postcode":"45699",
    "sg:province":"Nordrhein-Westfalen",
    "wof:name":"Jutta Haug",
    "wof:placetype":"venue"
},
  "geometry": {"coordinates":[7.151107,51.599548],"type":"Point"}
}