{
  "type": "Feature",
  "properties": {
    "iso:country":"DE",
    "sg:address":"Planegger Str. 6",
    "sg:city":"Germering",
    "sg:phone":"+49 89/846800",
    "sg:postcode":"82110",
    "sg:province":"Bayern",
    "wof:name":"Bosco Apotheke Germering Ralf Egen",
    "wof:placetype":"venue"
},
  "geometry": {"coordinates":[11.368117,48.125751],"type":"Point"}
}