{
  "type": "Feature",
  "properties": {
    "iso:country":"DE",
    "sg:address":"Hildburghauser Str. 27 c",
    "sg:city":"Berlin",
    "sg:phone":"+49 30/7217221",
    "sg:postcode":"12279",
    "sg:province":"Berlin",
    "wof:name":"Uwe Lorenz",
    "wof:placetype":"venue"
},
  "geometry": {"coordinates":[13.3549642563,52.4132461548],"type":"Point"}
}