{
  "type": "Feature",
  "properties": {
    "iso:country":"DE",
    "sg:address":"Sch\u00fctzenstr. 6",
    "sg:city":"Meerbusch",
    "sg:phone":"+49 2150/4010",
    "sg:postcode":"40668",
    "sg:province":"Nordrhein-Westfalen",
    "wof:name":"Reitstall",
    "wof:placetype":"venue"
},
  "geometry": {"coordinates":[6.7087688446,51.2985801697],"type":"Point"}
}