{
  "type": "Feature",
  "properties": {
    "iso:country":"DE",
    "sg:address":"August-B\u00f6ger-Str. 4",
    "sg:city":"Barsinghausen",
    "sg:phone":"+49 5105/2449",
    "sg:postcode":"30890",
    "sg:province":"Niedersachsen",
    "wof:name":"Joachim Laubner",
    "wof:placetype":"venue"
},
  "geometry": {"coordinates":[9.4711408615,52.3064842224],"type":"Point"}
}