{
  "type": "Feature",
  "properties": {
    "iso:country":"DE",
    "sg:address":"F\u00fcrstenrieder Str. 90",
    "sg:city":"M\u00fcnchen",
    "sg:phone":"+49 89/5808013",
    "sg:postcode":"80686",
    "sg:province":"Bayern",
    "wof:name":"Dresdner Verm\u00f6gens- Beratungsgesellschaft Mbh",
    "wof:placetype":"venue"
},
  "geometry": {"coordinates":[11.5026102066,48.132610321],"type":"Point"}
}