{
  "type": "Feature",
  "properties": {
    "iso:country":"DE",
    "sg:address":"Falkenrotter Str. 7",
    "sg:city":"Vechta",
    "sg:phone":"+49 4441/3985",
    "sg:postcode":"49377",
    "sg:province":"Niedersachsen",
    "wof:name":"H.-c. Stilkenb\u00f6hmer Gmbh & Co. Kg",
    "wof:placetype":"venue"
},
  "geometry": {"coordinates":[8.2881212234,52.7314758301],"type":"Point"}
}