{
  "type": "Feature",
  "properties": {
    "iso:country":"DE",
    "sg:address":"Kuhnhofer Hauptstr. 22",
    "sg:city":"Lauf",
    "sg:phone":"+49 9123/4633",
    "sg:postcode":"91207",
    "sg:province":"Bayern",
    "wof:name":"Ibz Bau- Und Montage Handelsagentur Gmbh",
    "wof:placetype":"venue"
},
  "geometry": {"coordinates":[11.2740869522,49.5299034119],"type":"Point"}
}