{
  "type": "Feature",
  "properties": {
    "iso:country":"DE",
    "sg:address":"Schulstr. 9",
    "sg:city":"Bad Pyrmont",
    "sg:phone":"+49 5281/93480",
    "sg:postcode":"31812",
    "sg:province":"Niedersachsen",
    "wof:name":"G\u00e4stehaus Kurhaus Eibenhof Inh. F.-d. Klein",
    "wof:placetype":"venue"
},
  "geometry": {"coordinates":[9.2425842285,51.9881477356],"type":"Point"}
}