{
  "type": "Feature",
  "properties": {
    "iso:country":"DE",
    "sg:address":"M\u00fchlenstr. 3",
    "sg:city":"Frielendorf",
    "sg:phone":"+49 5684/1880",
    "sg:postcode":"34621",
    "sg:province":"Hessen",
    "wof:name":"J\u00fcrgen Feistner",
    "wof:placetype":"venue"
},
  "geometry": {"coordinates":[9.326151,50.975983],"type":"Point"}
}