{
  "type": "Feature",
  "properties": {
    "iso:country":"DE",
    "sg:address":"Gartenstr. 5",
    "sg:city":"Kaisersesch",
    "sg:phone":"+49 2653/910533",
    "sg:postcode":"56759",
    "sg:province":"Rheinland-Pfalz",
    "wof:name":"Signal",
    "wof:placetype":"venue"
},
  "geometry": {"coordinates":[7.1435379982,50.2302246094],"type":"Point"}
}