{
  "type": "Feature",
  "properties": {
    "iso:country":"DE",
    "sg:address":"Gerbstedter Str. 27",
    "sg:city":"Friedeburg",
    "sg:phone":"+49 34783/29817",
    "sg:postcode":"06347",
    "sg:province":"Sachsen-Anhalt",
    "wof:name":"Stemmer",
    "wof:placetype":"venue"
},
  "geometry": {"coordinates":[11.7404108047,51.61951828],"type":"Point"}
}