{
  "type": "Feature",
  "properties": {
    "iso:country":"DE",
    "sg:address":"Fischerstr. 1",
    "sg:city":"Pforzheim",
    "sg:phone":"+49 7231/72528",
    "sg:postcode":"75180",
    "sg:province":"Baden-W\u00fcrttemberg",
    "wof:name":"Stefan Knaus",
    "wof:placetype":"venue"
},
  "geometry": {"coordinates":[8.6803312302,48.8668403625],"type":"Point"}
}