{
  "type": "Feature",
  "properties": {
    "iso:country":"DE",
    "sg:address":"Dieselstrasse 22",
    "sg:city":"Kempten",
    "sg:phone":"+49 831/575190",
    "sg:postcode":"87437",
    "sg:province":"Bayern",
    "wof:name":"Dataex Aktenvernichtung",
    "wof:placetype":"venue"
},
  "geometry": {"coordinates":[10.31789,47.759182],"type":"Point"}
}