{
  "type": "Feature",
  "properties": {
    "iso:country":"DE",
    "sg:address":"Provinzialstr. 61",
    "sg:city":"Illingen",
    "sg:phone":"+49 6825/496623",
    "sg:postcode":"66557",
    "sg:province":"Saarland",
    "wof:name":"Neckura Holding Ag",
    "wof:placetype":"venue"
},
  "geometry": {"coordinates":[7.0691308975,49.3885688782],"type":"Point"}
}