{
  "type": "Feature",
  "properties": {
    "iso:country":"DE",
    "sg:address":"Breuershofstra\u00dfe 19",
    "sg:city":"Krefeld",
    "sg:phone":"+49 2151/31970",
    "sg:postcode":"47807",
    "sg:province":"Nordrhein-Westfalen",
    "wof:name":"Witz Werkzeugbau Gmbh",
    "wof:placetype":"venue"
},
  "geometry": {"coordinates":[6.565844059,51.3019866943],"type":"Point"}
}