{
  "type": "Feature",
  "properties": {
    "iso:country":"DE",
    "sg:address":"Seekoppelweg 18",
    "sg:city":"Kiel",
    "sg:phone":"+49 431/687084",
    "sg:postcode":"24113",
    "sg:province":"Schleswig-Holstein",
    "wof:name":"Eg\u00fc-modeversand Gmbh",
    "wof:placetype":"venue"
},
  "geometry": {"coordinates":[10.086706,54.296753],"type":"Point"}
}