{
  "type": "Feature",
  "properties": {
    "iso:country":"DE",
    "sg:address":"Enkheimer Str. 34",
    "sg:city":"Offenbach",
    "sg:phone":"+49 69/868204",
    "sg:postcode":"63075",
    "sg:province":"Hessen",
    "wof:name":"Malerbetrieb K\u00fchn Gmbh",
    "wof:placetype":"venue"
},
  "geometry": {"coordinates":[8.78628,50.120087],"type":"Point"}
}