{
  "type": "Feature",
  "properties": {
    "iso:country":"DE",
    "sg:address":"Bengdbruchstr. 29",
    "sg:city":"Willich",
    "sg:phone":"+49 2156/6336",
    "sg:postcode":"47877",
    "sg:province":"Nordrhein-Westfalen",
    "wof:name":"Reinhard Schmitz",
    "wof:placetype":"venue"
},
  "geometry": {"coordinates":[6.469528,51.254459],"type":"Point"}
}