{
  "type": "Feature",
  "properties": {
    "iso:country":"DE",
    "sg:address":"G\u00e4nsebruch 5",
    "sg:city":"Willebadessen",
    "sg:phone":"+49 5646/94016",
    "sg:postcode":"34439",
    "sg:province":"Nordrhein-Westfalen",
    "wof:name":"F.-j. Neuhaus",
    "wof:placetype":"venue"
},
  "geometry": {"coordinates":[9.0281076431,51.6266975403],"type":"Point"}
}