{
  "type": "Feature",
  "properties": {
    "iso:country":"DE",
    "sg:address":"Amiraplatz 3",
    "sg:city":"M\u00fcnchen",
    "sg:phone":"+49 89/2907590",
    "sg:postcode":"80333",
    "sg:province":"Bayern",
    "wof:name":"Bambynek Consulting Gmbh",
    "wof:placetype":"venue"
},
  "geometry": {"coordinates":[11.5752162933,48.1426620483],"type":"Point"}
}