{
  "type": "Feature",
  "properties": {
    "iso:country":"DE",
    "sg:address":"Giselastr. 5",
    "sg:city":"Waldkirch",
    "sg:phone":"+49 7681/7252",
    "sg:postcode":"79183",
    "sg:province":"Baden-W\u00fcrttemberg",
    "wof:name":"B. Klausmann",
    "wof:placetype":"venue"
},
  "geometry": {"coordinates":[7.9650230408,48.0928115845],"type":"Point"}
}