{
  "type": "Feature",
  "properties": {
    "iso:country":"DE",
    "sg:address":"Vogelbeerenstr. 12",
    "sg:city":"Rheine",
    "sg:phone":"+49 5971/71855",
    "sg:postcode":"48432",
    "sg:province":"Nordrhein-Westfalen",
    "wof:name":"Hubert Ruhe",
    "wof:placetype":"venue"
},
  "geometry": {"coordinates":[7.471007,52.258568],"type":"Point"}
}