{
  "type": "Feature",
  "properties": {
    "iso:country":"DE",
    "sg:address":"Postfach 141304",
    "sg:city":"Garbsen",
    "sg:postcode":"30813",
    "sg:province":"Niedersachsen",
    "wof:name":"Qosma Gesellschaft F\u00fcr Qualit\u00e4tssicherung Organisat.",
    "wof:placetype":"venue"
},
  "geometry": {"coordinates":[9.5881299973,52.413848877],"type":"Point"}
}