{
  "type": "Feature",
  "properties": {
    "iso:country":"DE",
    "sg:address":"Kasseler Str. 7",
    "sg:city":"Staufenberg",
    "sg:phone":"+49 5543/3139",
    "sg:postcode":"34355",
    "sg:province":"Niedersachsen",
    "wof:name":"Gastst\u00e4tte Magdalene Beumler",
    "wof:placetype":"venue"
},
  "geometry": {"coordinates":[9.6168889999,51.3301734924],"type":"Point"}
}