{
  "type": "Feature",
  "properties": {
    "iso:country":"DE",
    "sg:address":"Wolterstr. 30",
    "sg:city":"Neuenhagen",
    "sg:phone":"+49 3342/7493",
    "sg:postcode":"15366",
    "sg:province":"Brandenburg",
    "wof:name":"I. Menzel",
    "wof:placetype":"venue"
},
  "geometry": {"coordinates":[13.6975698471,52.5230407715],"type":"Point"}
}