{
  "type": "Feature",
  "properties": {
    "iso:country":"DE",
    "sg:address":"Mainzer Str. 28",
    "sg:city":"Limburg",
    "sg:phone":"+49 6431/946417",
    "sg:postcode":"65550",
    "sg:province":"Hessen",
    "wof:name":"Thomas Langlott Rechtsanwalt",
    "wof:placetype":"venue"
},
  "geometry": {"coordinates":[8.0944404602,50.3665504456],"type":"Point"}
}