{
  "type": "Feature",
  "properties": {
    "iso:country":"DE",
    "sg:address":"Heiligenstr. 112",
    "sg:city":"Saarlouis",
    "sg:phone":"+49 6831/80981",
    "sg:postcode":"66740",
    "sg:province":"Saarland",
    "wof:name":"I. Ernst",
    "wof:placetype":"venue"
},
  "geometry": {"coordinates":[6.7557368279,49.3349571228],"type":"Point"}
}