{
  "type": "Feature",
  "properties": {
    "iso:country":"DE",
    "sg:address":"\u00dcberlinger Str. 76",
    "sg:city":"Pfullendorf",
    "sg:phone":"+49 7552/8191",
    "sg:postcode":"88630",
    "sg:province":"Baden-W\u00fcrttemberg",
    "wof:name":"Betonwerk Pfullendorf Gmbh & Co. Holding Kg",
    "wof:placetype":"venue"
},
  "geometry": {"coordinates":[9.2430200577,47.928768158],"type":"Point"}
}