{
  "type": "Feature",
  "properties": {
    "iso:country":"DE",
    "sg:address":"P\u00f6ttkerdiek 20",
    "sg:city":"Lingen",
    "sg:phone":"+49 591/916880",
    "sg:postcode":"49808",
    "sg:province":"Niedersachsen",
    "wof:name":"Via Sat Multi Media Gmbh",
    "wof:placetype":"venue"
},
  "geometry": {"coordinates":[7.2825088501,52.5019264221],"type":"Point"}
}