{
  "type": "Feature",
  "properties": {
    "iso:country":"DE",
    "sg:address":"Holzstad 1",
    "sg:city":"Bad Sooden-Allendorf",
    "sg:phone":"+49 5652/4660",
    "sg:postcode":"37242",
    "sg:province":"Hessen",
    "wof:name":"Montawa-automaten Karl Montag Ohg",
    "wof:placetype":"venue"
},
  "geometry": {"coordinates":[9.9687719345,51.2707214355],"type":"Point"}
}