{
  "type": "Feature",
  "properties": {
    "iso:country":"DE",
    "sg:address":"Dreisesselbergstr. 12",
    "sg:city":"M\u00fcnchen",
    "sg:phone":"+49 89/686067",
    "sg:postcode":"81549",
    "sg:province":"Bayern",
    "wof:name":"Otto Grimm Architekt",
    "wof:placetype":"venue"
},
  "geometry": {"coordinates":[11.609516,48.091736],"type":"Point"}
}