{
  "type": "Feature",
  "properties": {
    "iso:country":"DE",
    "sg:address":"Mitterhausen 57",
    "sg:city":"Neu\u00f6tting",
    "sg:phone":"+49 8671/2360",
    "sg:postcode":"84524",
    "sg:province":"Bayern",
    "wof:name":"F. Schmid",
    "wof:placetype":"venue"
},
  "geometry": {"coordinates":[12.7639608383,48.2442932129],"type":"Point"}
}