{
  "type": "Feature",
  "properties": {
    "iso:country":"DE",
    "sg:address":"Theresienstr. 9",
    "sg:city":"Passau",
    "sg:phone":"+49 851/9666283",
    "sg:postcode":"94032",
    "sg:province":"Bayern",
    "wof:name":"Tessuti - Zweigniederlassung Der Firma Dretex Textil-",
    "wof:placetype":"venue"
},
  "geometry": {"coordinates":[13.4607362747,48.5739326477],"type":"Point"}
}