{
  "type": "Feature",
  "properties": {
    "iso:country":"DE",
    "sg:address":"Winterbacher Str. 15",
    "sg:city":"Stuttgart",
    "sg:phone":"+49 711/5204610",
    "sg:postcode":"70374",
    "sg:province":"Baden-W\u00fcrttemberg",
    "wof:name":"Schwarze Automation Gmbh",
    "wof:placetype":"venue"
},
  "geometry": {"coordinates":[9.247609,48.806107],"type":"Point"}
}