{
  "type": "Feature",
  "properties": {
    "iso:country":"DE",
    "sg:address":"Uetzer Weg 19",
    "sg:city":"Wathlingen",
    "sg:phone":"+49 5144/92302",
    "sg:postcode":"29339",
    "sg:province":"Niedersachsen",
    "wof:name":"T. Harms Rechtsanwalt",
    "wof:placetype":"venue"
},
  "geometry": {"coordinates":[10.1561155319,52.5351066589],"type":"Point"}
}