{
  "type": "Feature",
  "properties": {
    "iso:country":"DE",
    "sg:address":"Setzelbacher Str. 2",
    "sg:city":"Rasdorf",
    "sg:phone":"+49 6651/428",
    "sg:postcode":"36169",
    "sg:province":"Hessen",
    "wof:name":"Friedrich Puth Architekt",
    "wof:placetype":"venue"
},
  "geometry": {"coordinates":[9.897334,50.719746],"type":"Point"}
}