{
  "type": "Feature",
  "properties": {
    "iso:country":"DE",
    "sg:address":"Stumpfstr. 5",
    "sg:city":"Arnsberg",
    "sg:phone":"+49 2932/53673",
    "sg:postcode":"59757",
    "sg:province":"Nordrhein-Westfalen",
    "wof:name":"Franz Kraft Ingenieur",
    "wof:placetype":"venue"
},
  "geometry": {"coordinates":[7.9677791595,51.4198265076],"type":"Point"}
}