{
  "type": "Feature",
  "properties": {
    "iso:country":"DE",
    "sg:address":"Auf dem Quabben 3-5",
    "sg:city":"Zeven",
    "sg:postcode":"27404",
    "sg:province":"Niedersachsen",
    "wof:name":"Comet",
    "wof:placetype":"venue"
},
  "geometry": {"coordinates":[9.2782049179,53.2907218933],"type":"Point"}
}