{
  "type": "Feature",
  "properties": {
    "iso:country":"DE",
    "sg:address":"Staatsstr. 17",
    "sg:city":"Lindenberg",
    "sg:phone":"+49 6325/7539",
    "sg:postcode":"67473",
    "sg:province":"Rheinland-Pfalz",
    "wof:name":"Felten & Meier",
    "wof:placetype":"venue"
},
  "geometry": {"coordinates":[8.1008195877,49.3687515259],"type":"Point"}
}