{
  "type": "Feature",
  "properties": {
    "iso:country":"DE",
    "sg:address":"Viktoriastr. 13",
    "sg:city":"Norderney",
    "sg:phone":"+49 4932/606",
    "sg:postcode":"26548",
    "sg:province":"Niedersachsen",
    "wof:name":"Hotel Belvedere Am Meer",
    "wof:placetype":"venue"
},
  "geometry": {"coordinates":[7.1402702332,53.7044487],"type":"Point"}
}