{
  "type": "Feature",
  "properties": {
    "iso:country":"DE",
    "sg:address":"Isinger Str. 9",
    "sg:city":"Geislingen",
    "sg:phone":"+49 7433/16754",
    "sg:postcode":"72351",
    "sg:province":"Baden-W\u00fcrttemberg",
    "wof:name":"Durst",
    "wof:placetype":"venue"
},
  "geometry": {"coordinates":[8.8035068512,48.2842597961],"type":"Point"}
}