{
  "type": "Feature",
  "properties": {
    "iso:country":"DE",
    "sg:address":"Eifgen 5",
    "sg:city":"Wermelskirchen",
    "sg:phone":"+49 2196/3496",
    "sg:postcode":"42929",
    "sg:province":"Nordrhein-Westfalen",
    "wof:name":"A. Koll Und F. Hindrichs",
    "wof:placetype":"venue"
},
  "geometry": {"coordinates":[7.2307391167,51.1361503601],"type":"Point"}
}