{
  "type": "Feature",
  "properties": {
    "iso:country":"DE",
    "sg:address":"Robert-Bosch-Strasse 20",
    "sg:city":"Linden",
    "sg:phone":"+49 6403/7040",
    "sg:postcode":"35440",
    "sg:province":"Hessen",
    "wof:name":"Gs Versicherungs - Service",
    "wof:placetype":"venue"
},
  "geometry": {"coordinates":[8.654918,50.537762],"type":"Point"}
}