{
  "type": "Feature",
  "properties": {
    "iso:country":"DE",
    "sg:address":"Untergra\u00dflfing 50",
    "sg:city":"Laberweinting",
    "sg:phone":"+49 9454/891",
    "sg:postcode":"84082",
    "sg:province":"Bayern",
    "wof:name":"Georg Pf\u00e4ffinger",
    "wof:placetype":"venue"
},
  "geometry": {"coordinates":[12.281984,48.833344],"type":"Point"}
}