{
  "type": "Feature",
  "properties": {
    "iso:country":"DE",
    "sg:address":"Wei\u00dflenreuth 24",
    "sg:city":"Konradsreuth",
    "sg:phone":"+49 9292/210",
    "sg:postcode":"95176",
    "sg:province":"Bayern",
    "wof:name":"P\u00f6hlmann",
    "wof:placetype":"venue"
},
  "geometry": {"coordinates":[11.821141243,50.2424468994],"type":"Point"}
}