{
  "type": "Feature",
  "properties": {
    "iso:country":"DE",
    "sg:address":"Thomas-Mann-Str. 35",
    "sg:city":"Wermelskirchen",
    "sg:phone":"+49 2196/4091",
    "sg:postcode":"42929",
    "sg:province":"Nordrhein-Westfalen",
    "wof:name":"Elektrik Grosshandels Kg",
    "wof:placetype":"venue"
},
  "geometry": {"coordinates":[7.2206020355,51.1437339783],"type":"Point"}
}