{
  "type": "Feature",
  "properties": {
    "iso:country":"DE",
    "sg:address":"Lindenstr. 164",
    "sg:city":"Itzehoe",
    "sg:phone":"+49 4821/78078",
    "sg:postcode":"25524",
    "sg:province":"Schleswig-Holstein",
    "wof:name":"Autohansa-autovermietung- Mm Gmbh",
    "wof:placetype":"venue"
},
  "geometry": {"coordinates":[9.491471,53.932457],"type":"Point"}
}