{
  "type": "Feature",
  "properties": {
    "iso:country":"DE",
    "sg:address":"Weikersdorf",
    "sg:city":"Feuchtwangen",
    "sg:phone":"+49 9856/1019",
    "sg:postcode":"91555",
    "sg:province":"Bayern",
    "wof:name":"Walzerst\u00fcble",
    "wof:placetype":"venue"
},
  "geometry": {"coordinates":[10.3460226059,49.1624069214],"type":"Point"}
}