{
  "type": "Feature",
  "properties": {
    "iso:country":"DE",
    "sg:address":"Kirchplatz 8",
    "sg:city":"Lenzkirch",
    "sg:phone":"+49 7653/1492",
    "sg:postcode":"79853",
    "sg:province":"Baden-W\u00fcrttemberg",
    "wof:name":"Alte Flasche",
    "wof:placetype":"venue"
},
  "geometry": {"coordinates":[8.2025508881,47.8688926697],"type":"Point"}
}