{
  "type": "Feature",
  "properties": {
    "iso:country":"DE",
    "sg:address":"Tassilostr. 15",
    "sg:city":"Steinach",
    "sg:phone":"+49 9428/579",
    "sg:postcode":"94377",
    "sg:province":"Bayern",
    "wof:name":"Helmut Und Hannelore Kr\u00fcgl",
    "wof:placetype":"venue"
},
  "geometry": {"coordinates":[12.574813,48.953777],"type":"Point"}
}