{
  "type": "Feature",
  "properties": {
    "iso:country":"DE",
    "sg:address":"Pirnaer Landstr. 235",
    "sg:city":"Dresden",
    "sg:phone":"+49 351/2024729",
    "sg:postcode":"01259",
    "sg:province":"Sachsen",
    "wof:name":"Zschachwitz-center Kaufhaus Gmbh",
    "wof:placetype":"venue"
},
  "geometry": {"coordinates":[13.841711,51.003201],"type":"Point"}
}