{
  "type": "Feature",
  "properties": {
    "iso:country":"DE",
    "sg:address":"Industriestr. 10",
    "sg:city":"K\u00f6tz",
    "sg:phone":"+49 8221/5814",
    "sg:postcode":"89359",
    "sg:province":"Bayern",
    "wof:name":"Friedrich Gr\u00f6ger",
    "wof:placetype":"venue"
},
  "geometry": {"coordinates":[10.290520668,48.4161911011],"type":"Point"}
}