{
  "type": "Feature",
  "properties": {
    "iso:country":"DE",
    "sg:address":"Thierach 4",
    "sg:city":"R\u00f6dental",
    "sg:phone":"+49 9563/50590",
    "sg:postcode":"96472",
    "sg:province":"Bayern",
    "wof:name":"Rolf M\u00fcller",
    "wof:placetype":"venue"
},
  "geometry": {"coordinates":[11.0761413574,50.2806549072],"type":"Point"}
}