{
  "type": "Feature",
  "properties": {
    "iso:country":"DE",
    "sg:address":"Graf-Siegfried-Str. 17",
    "sg:city":"Saarburg",
    "sg:phone":"+49 6581/2388",
    "sg:postcode":"54439",
    "sg:province":"Rheinland-Pfalz",
    "wof:name":"Arthur F. L\u00f6wenberg Architekt",
    "wof:placetype":"venue"
},
  "geometry": {"coordinates":[6.55101,49.609486],"type":"Point"}
}