{
  "type": "Feature",
  "properties": {
    "iso:country":"DE",
    "sg:address":"Haarenstr. 43",
    "sg:city":"Oldenburg",
    "sg:phone":"+49 441/16547",
    "sg:postcode":"26122",
    "sg:province":"Niedersachsen",
    "wof:name":"Die Brille Inh. K. Reckemeier",
    "wof:placetype":"venue"
},
  "geometry": {"coordinates":[8.1951141357,53.1421546936],"type":"Point"}
}