{
  "type": "Feature",
  "properties": {
    "iso:country":"DE",
    "sg:address":"Mansfelder Str. 49",
    "sg:city":"Berlin",
    "sg:phone":"+49 30/39041900",
    "sg:postcode":"10709",
    "sg:province":"Berlin",
    "wof:name":"Generalagentur Mario Kr\u00fcger E. Kfm.",
    "wof:placetype":"venue"
},
  "geometry": {"coordinates":[13.3049669266,52.4905357361],"type":"Point"}
}