{
  "type": "Feature",
  "properties": {
    "iso:country":"DE",
    "sg:address":"Im Kettelbach 4a",
    "sg:city":"Hagen",
    "sg:phone":"+49 2331/45545",
    "sg:postcode":"58135",
    "sg:province":"Nordrhein-Westfalen",
    "wof:name":"Ne-metalle Alex Klawek Gmbh",
    "wof:placetype":"venue"
},
  "geometry": {"coordinates":[7.429133,51.330029],"type":"Point"}
}