{
  "type": "Feature",
  "properties": {
    "iso:country":"DE",
    "sg:address":"Utzschneiderstr. 7",
    "sg:city":"M\u00fcnchen",
    "sg:phone":"+49 89/268197",
    "sg:postcode":"80469",
    "sg:province":"Bayern",
    "wof:name":"Hilde Kadar-prass",
    "wof:placetype":"venue"
},
  "geometry": {"coordinates":[11.5761442184,48.1338539124],"type":"Point"}
}