{
  "type": "Feature",
  "properties": {
    "iso:country":"DE",
    "sg:address":"Humboldtstr. 4",
    "sg:city":"Erfurt",
    "sg:phone":"+49 361/3733708",
    "sg:postcode":"99096",
    "sg:province":"Th\u00fcringen",
    "wof:name":"Dr. Med. Dietrich Romeick",
    "wof:placetype":"venue"
},
  "geometry": {"coordinates":[11.033375,50.960571],"type":"Point"}
}