{
  "type": "Feature",
  "properties": {
    "iso:country":"DE",
    "sg:address":"Gelderner Str. 2",
    "sg:city":"Xanten",
    "sg:phone":"+49 2801/2209",
    "sg:postcode":"46509",
    "sg:province":"Nordrhein-Westfalen",
    "wof:name":"Theodor Kempken",
    "wof:placetype":"venue"
},
  "geometry": {"coordinates":[6.440131,51.647865],"type":"Point"}
}