{
  "type": "Feature",
  "properties": {
    "iso:country":"DE",
    "sg:address":"Br\u00fcsseler Str. 1",
    "sg:city":"Georgsmarienh\u00fctte",
    "sg:phone":"+49 5401/4870",
    "sg:postcode":"49124",
    "sg:province":"Niedersachsen",
    "wof:name":"Bauunternehmen Hein Gmbh",
    "wof:placetype":"venue"
},
  "geometry": {"coordinates":[8.085558,52.223293],"type":"Point"}
}