{
  "type": "Feature",
  "properties": {
    "iso:country":"DE",
    "sg:address":"Gro\u00dfe Austr. 4",
    "sg:city":"Gaggenau",
    "sg:phone":"+49 7225/78396",
    "sg:postcode":"76571",
    "sg:province":"Baden-W\u00fcrttemberg",
    "wof:name":"Hildegard Anselm Masseur",
    "wof:placetype":"venue"
},
  "geometry": {"coordinates":[8.306494,48.81303],"type":"Point"}
}