{
  "type": "Feature",
  "properties": {
    "iso:country":"DE",
    "sg:address":"Tannenweg 4",
    "sg:city":"Saarbr\u00fccken",
    "sg:phone":"+49 681/871443",
    "sg:postcode":"66130",
    "sg:province":"Saarland",
    "wof:name":"Chp Weinimport-export Gesch\u00e4ftsf\u00fchrungs Gmbh",
    "wof:placetype":"venue"
},
  "geometry": {"coordinates":[7.0391850471,49.201171875],"type":"Point"}
}