{
  "type": "Feature",
  "properties": {
    "iso:country":"DE",
    "sg:address":"D\u00fcppelstr. 11",
    "sg:city":"Gelsenkirchen",
    "sg:phone":"+49 209/597851",
    "sg:postcode":"45897",
    "sg:province":"Nordrhein-Westfalen",
    "wof:name":"H. Derse Gmbh",
    "wof:placetype":"venue"
},
  "geometry": {"coordinates":[7.044723,51.570831],"type":"Point"}
}