{
  "type": "Feature",
  "properties": {
    "iso:country":"DE",
    "sg:address":"Mainzer Str. 30",
    "sg:city":"Bad Kreuznach",
    "sg:phone":"+49 671/886180",
    "sg:postcode":"55545",
    "sg:province":"Rheinland-Pfalz",
    "wof:name":"Wagner & K\u00fchner Gmbh",
    "wof:placetype":"venue"
},
  "geometry": {"coordinates":[7.9061121941,49.8597221375],"type":"Point"}
}