{
  "type": "Feature",
  "properties": {
    "iso:country":"DE",
    "sg:address":"Regenkamp 13",
    "sg:city":"Herne",
    "sg:phone":"+49 2323/44219",
    "sg:postcode":"44625",
    "sg:province":"Nordrhein-Westfalen",
    "wof:name":"Lothar Kram",
    "wof:placetype":"venue"
},
  "geometry": {"coordinates":[7.212843,51.531918],"type":"Point"}
}