{
  "type": "Feature",
  "properties": {
    "iso:country":"DE",
    "sg:address":"Schelpmilser Weg 14",
    "sg:city":"Bielefeld",
    "sg:postcode":"33609",
    "sg:province":"Nordrhein-Westfalen",
    "wof:name":"Dieter Burghardt Gmbh",
    "wof:placetype":"venue"
},
  "geometry": {"coordinates":[8.606534,52.039246],"type":"Point"}
}