{
  "type": "Feature",
  "properties": {
    "iso:country":"DE",
    "sg:address":"Kugelm\u00fchlstr. 40",
    "sg:city":"Ainring",
    "sg:phone":"+49 8654/5654",
    "sg:postcode":"83404",
    "sg:province":"Bayern",
    "wof:name":"Peter Br\u00f6tzner",
    "wof:placetype":"venue"
},
  "geometry": {"coordinates":[12.963346,47.800423],"type":"Point"}
}