{
  "type": "Feature",
  "properties": {
    "iso:country":"DE",
    "sg:address":"Am Bocksberg 20",
    "sg:city":"Laudenbach",
    "sg:phone":"+49 9372/3612",
    "sg:postcode":"63925",
    "sg:province":"Bayern",
    "wof:name":"Siegfried H\u00f6fer Architekt",
    "wof:placetype":"venue"
},
  "geometry": {"coordinates":[9.171064,49.743454],"type":"Point"}
}