{
  "type": "Feature",
  "properties": {
    "iso:country":"DE",
    "sg:address":"Kalkgraben 40",
    "sg:city":"Reinfeld",
    "sg:phone":"+49 4533/8825",
    "sg:postcode":"23858",
    "sg:province":"Schleswig-Holstein",
    "wof:name":"Heike Und Thorsten Klohn",
    "wof:placetype":"venue"
},
  "geometry": {"coordinates":[10.4730491638,53.8223075867],"type":"Point"}
}