{
  "type": "Feature",
  "properties": {
    "iso:country":"DE",
    "sg:address":"Wehlingweg 25",
    "sg:city":"Weinheim",
    "sg:phone":"+49 6201/24227",
    "sg:postcode":"69469",
    "sg:province":"Baden-W\u00fcrttemberg",
    "wof:name":"Brand Ingenieur",
    "wof:placetype":"venue"
},
  "geometry": {"coordinates":[8.7273292542,49.5075836182],"type":"Point"}
}