{
  "type": "Feature",
  "properties": {
    "iso:country":"DE",
    "sg:address":"Nottbergstr. 58",
    "sg:city":"Rinteln",
    "sg:phone":"+49 5751/2727",
    "sg:postcode":"31737",
    "sg:province":"Niedersachsen",
    "wof:name":"Gastst\u00e4tte Bartram",
    "wof:placetype":"venue"
},
  "geometry": {"coordinates":[9.068304,52.158672],"type":"Point"}
}