{
  "type": "Feature",
  "properties": {
    "iso:country":"DE",
    "sg:address":"Unterer Graben 17",
    "sg:city":"Eibelstadt",
    "sg:phone":"+49 9303/980576",
    "sg:postcode":"97246",
    "sg:province":"Bayern",
    "wof:name":"Dr. Torsten Betzel Rechtsanwalt",
    "wof:placetype":"venue"
},
  "geometry": {"coordinates":[10.0060987473,49.7263031006],"type":"Point"}
}