{
  "type": "Feature",
  "properties": {
    "iso:country":"DE",
    "sg:address":"Im Hagen 24",
    "sg:city":"Wuppertal",
    "sg:phone":"+49 202/401529",
    "sg:postcode":"42349",
    "sg:province":"Nordrhein-Westfalen",
    "wof:name":"Schmitt-sasse Beteiligungs Gmbh",
    "wof:placetype":"venue"
},
  "geometry": {"coordinates":[7.158654,51.217777],"type":"Point"}
}