{
  "type": "Feature",
  "properties": {
    "iso:country":"DE",
    "sg:address":"Brink 66",
    "sg:city":"Ahaus",
    "sg:phone":"+49 2561/7919",
    "sg:postcode":"48683",
    "sg:province":"Nordrhein-Westfalen",
    "wof:name":"J. Meiners",
    "wof:placetype":"venue"
},
  "geometry": {"coordinates":[6.9765949249,52.1245536804],"type":"Point"}
}