{
  "type": "Feature",
  "properties": {
    "iso:country":"DE",
    "sg:address":"Norderstr. 6",
    "sg:city":"Aurich",
    "sg:phone":"+49 4941/63692",
    "sg:postcode":"26603",
    "sg:province":"Niedersachsen",
    "wof:name":"Jeansb\u00fcx",
    "wof:placetype":"venue"
},
  "geometry": {"coordinates":[7.482973,53.470806],"type":"Point"}
}