{
  "type": "Feature",
  "properties": {
    "iso:country":"DE",
    "sg:address":"Theresienstr. 63",
    "sg:city":"M\u00fcnchen",
    "sg:phone":"+49 89/521755",
    "sg:postcode":"80333",
    "sg:province":"Bayern",
    "wof:name":"Hela Beteiligungs- Gmbh",
    "wof:placetype":"venue"
},
  "geometry": {"coordinates":[11.563858,48.151073],"type":"Point"}
}