{
  "type": "Feature",
  "properties": {
    "iso:country":"DE",
    "sg:address":"Sportplatzstr. 4",
    "sg:city":"H\u00f6henkirchen",
    "sg:phone":"+49 8102/6660",
    "sg:postcode":"85635",
    "sg:province":"Bayern",
    "wof:name":"Motorradsport Schmid Gmbh",
    "wof:placetype":"venue"
},
  "geometry": {"coordinates":[11.7021656036,48.0242652893],"type":"Point"}
}