{
  "type": "Feature",
  "properties": {
    "iso:country":"DE",
    "sg:address":"Dammstr. 9",
    "sg:city":"Barsinghausen",
    "sg:phone":"+49 5035/540",
    "sg:postcode":"30890",
    "sg:province":"Niedersachsen",
    "wof:name":"Friedrich Flebbe",
    "wof:placetype":"venue"
},
  "geometry": {"coordinates":[9.478854,52.364155],"type":"Point"}
}