{
  "type": "Feature",
  "properties": {
    "iso:country":"DE",
    "sg:address":"Am H\u00f6ppel 6",
    "sg:city":"Freudenberg",
    "sg:phone":"+49 2734/6657",
    "sg:postcode":"57258",
    "sg:province":"Nordrhein-Westfalen",
    "wof:name":"Hein",
    "wof:placetype":"venue"
},
  "geometry": {"coordinates":[7.906031,50.861351],"type":"Point"}
}