{
  "type": "Feature",
  "properties": {
    "iso:country":"DE",
    "sg:address":"Lessingstr. 73",
    "sg:city":"Dortmund",
    "sg:phone":"+49 231/829170",
    "sg:postcode":"44147",
    "sg:province":"Nordrhein-Westfalen",
    "wof:name":"Parksch\u00e4nke",
    "wof:placetype":"venue"
},
  "geometry": {"coordinates":[7.4508738518,51.5229072571],"type":"Point"}
}