{
  "type": "Feature",
  "properties": {
    "iso:country":"DE",
    "sg:address":"Dresdener Str. 46",
    "sg:city":"T\u00f6nisvorst",
    "sg:phone":"+49 2151/797320",
    "sg:postcode":"47918",
    "sg:province":"Nordrhein-Westfalen",
    "wof:name":"G\u00fcnter Weyers",
    "wof:placetype":"venue"
},
  "geometry": {"coordinates":[6.5105447769,51.3246269226],"type":"Point"}
}