{
  "type": "Feature",
  "properties": {
    "iso:country":"DE",
    "sg:address":"Johann-Strau\u00df-Str. 8",
    "sg:city":"Bexbach",
    "sg:phone":"+49 6826/1760",
    "sg:postcode":"66450",
    "sg:province":"Saarland",
    "wof:name":"Wolfgang Marburger Steuerberater",
    "wof:placetype":"venue"
},
  "geometry": {"coordinates":[7.2621641159,49.3504333496],"type":"Point"}
}