{
  "type": "Feature",
  "properties": {
    "iso:country":"DE",
    "sg:address":"Am Fleith 15",
    "sg:city":"Lehrte",
    "sg:phone":"+49 5175/930672",
    "sg:postcode":"31275",
    "sg:province":"Niedersachsen",
    "wof:name":"Funk M\u00f6belwerkst\u00e4tten Gmbh",
    "wof:placetype":"venue"
},
  "geometry": {"coordinates":[10.062507,52.392139],"type":"Point"}
}