{
  "type": "Feature",
  "properties": {
    "iso:country":"DE",
    "sg:address":"Wandsbeker Chaussee 177",
    "sg:city":"Hamburg",
    "sg:phone":"+49 40/2098950",
    "sg:postcode":"22089",
    "sg:province":"Hamburg",
    "wof:name":"Neue Eilbeker Apotheke",
    "wof:placetype":"venue"
},
  "geometry": {"coordinates":[10.048876,53.568272],"type":"Point"}
}