{
  "type": "Feature",
  "properties": {
    "iso:country":"DE",
    "sg:address":"Bingstr. 30",
    "sg:city":"N\u00fcrnberg",
    "sg:phone":"+49 911/4030205",
    "sg:postcode":"90480",
    "sg:province":"Bayern",
    "wof:name":"Blomenhofer",
    "wof:placetype":"venue"
},
  "geometry": {"coordinates":[11.1309928894,49.445476532],"type":"Point"}
}