{
  "type": "Feature",
  "properties": {
    "iso:country":"DE",
    "sg:address":"Frommerding 1",
    "sg:city":"Iggensbach",
    "sg:phone":"+49 9903/465",
    "sg:postcode":"94547",
    "sg:province":"Bayern",
    "wof:name":"K. Sommer",
    "wof:placetype":"venue"
},
  "geometry": {"coordinates":[13.1551218033,48.7163505554],"type":"Point"}
}