{
  "type": "Feature",
  "properties": {
    "iso:country":"DE",
    "sg:address":"Gr\u00fcnstr. 16",
    "sg:city":"Hagen",
    "sg:phone":"+49 2331/331051",
    "sg:postcode":"58095",
    "sg:province":"Nordrhein-Westfalen",
    "wof:name":"Ev. Pfarramt",
    "wof:placetype":"venue"
},
  "geometry": {"coordinates":[7.4646029472,51.354598999],"type":"Point"}
}