{
  "type": "Feature",
  "properties": {
    "iso:country":"DE",
    "sg:address":"Bahnhofstr. 26",
    "sg:city":"Elsterwerda",
    "sg:phone":"+49 3533/162240",
    "sg:postcode":"04910",
    "sg:province":"Brandenburg",
    "wof:name":"Hans Jentzsch",
    "wof:placetype":"venue"
},
  "geometry": {"coordinates":[13.5215148926,51.4594993591],"type":"Point"}
}