{
  "type": "Feature",
  "properties": {
    "iso:country":"DE",
    "sg:address":"F\u00e4rbergasse 17",
    "sg:city":"Lohr",
    "sg:phone":"+49 9352/808782",
    "sg:postcode":"97816",
    "sg:province":"Bayern",
    "wof:name":"Bigis Wollshop Inh. Birgit Z\u00fcrn",
    "wof:placetype":"venue"
},
  "geometry": {"coordinates":[9.574171,49.994019],"type":"Point"}
}