{
  "type": "Feature",
  "properties": {
    "iso:country":"DE",
    "sg:address":"Wei\u00dfenfelder Str. 2",
    "sg:city":"Feldkirchen",
    "sg:phone":"+49 89/9006830",
    "sg:postcode":"85622",
    "sg:province":"Bayern",
    "wof:name":"Hiltl Beteiligungs-gmbh",
    "wof:placetype":"venue"
},
  "geometry": {"coordinates":[11.7500991821,48.1454048157],"type":"Point"}
}