{
  "type": "Feature",
  "properties": {
    "iso:country":"DE",
    "sg:address":"Obernstr. 32",
    "sg:city":"Bremen",
    "sg:phone":"+49 421/320585",
    "sg:postcode":"28195",
    "sg:province":"Bremen",
    "wof:name":"Fielmann Augenoptiker",
    "wof:placetype":"venue"
},
  "geometry": {"coordinates":[8.8052272797,53.077041626],"type":"Point"}
}