{
  "type": "Feature",
  "properties": {
    "iso:country":"DE",
    "sg:address":"Marktstr. 17",
    "sg:city":"Lohne",
    "sg:phone":"+49 4442/3298",
    "sg:postcode":"49393",
    "sg:province":"Niedersachsen",
    "wof:name":"A. Schmidt",
    "wof:placetype":"venue"
},
  "geometry": {"coordinates":[8.2360668182,52.665561676],"type":"Point"}
}