{
  "type": "Feature",
  "properties": {
    "iso:country":"DE",
    "sg:address":"Br\u00fcderstr. 22",
    "sg:city":"Werdau",
    "sg:phone":"+49 3761/888780",
    "sg:postcode":"08412",
    "sg:province":"Sachsen",
    "wof:name":"K2-telefonmarketing Gmbh",
    "wof:placetype":"venue"
},
  "geometry": {"coordinates":[12.378311,50.730816],"type":"Point"}
}