{
  "type": "Feature",
  "properties": {
    "iso:country":"DE",
    "sg:address":"Berckhusenstr. 13",
    "sg:city":"Hannover",
    "sg:phone":"+49 511/557429",
    "sg:postcode":"30625",
    "sg:province":"Niedersachsen",
    "wof:name":"Michael Ratkowski Gmbh",
    "wof:placetype":"venue"
},
  "geometry": {"coordinates":[9.788686,52.373798],"type":"Point"}
}