{
  "type": "Feature",
  "properties": {
    "iso:country":"DE",
    "sg:address":"Schuhstr. 71",
    "sg:city":"Lemgo",
    "sg:phone":"+49 5261/189194",
    "sg:postcode":"32657",
    "sg:province":"Nordrhein-Westfalen",
    "wof:name":"Lemgoer Gastst\u00e4tte",
    "wof:placetype":"venue"
},
  "geometry": {"coordinates":[8.9058952332,52.0256614685],"type":"Point"}
}