{
  "type": "Feature",
  "properties": {
    "iso:country":"DE",
    "sg:address":"Friedrich-Engels-Str. 69",
    "sg:city":"Sonneberg",
    "sg:phone":"+49 3675/745261",
    "sg:postcode":"96515",
    "sg:province":"Th\u00fcringen",
    "wof:name":"Joachim Engelhardt",
    "wof:placetype":"venue"
},
  "geometry": {"coordinates":[11.1898975372,50.3460388184],"type":"Point"}
}