{
  "type": "Feature",
  "properties": {
    "iso:country":"DE",
    "sg:address":"Mittelstr. 23",
    "sg:city":"D\u00fcsseldorf",
    "sg:phone":"+49 211/3239977",
    "sg:postcode":"40213",
    "sg:province":"Nordrhein-Westfalen",
    "wof:name":"Douglas Gmbh",
    "wof:placetype":"venue"
},
  "geometry": {"coordinates":[6.77404,51.224255],"type":"Point"}
}