{
  "type": "Feature",
  "properties": {
    "iso:country":"DE",
    "sg:address":"St.Wendeler Strasse 57",
    "sg:city":"Baltersweiler",
    "sg:phone":"+49 6851/1716",
    "sg:postcode":"66640",
    "sg:province":"Saarland",
    "wof:name":"Alfred Jung Thuringia Versicherungsagentur",
    "wof:placetype":"venue"
},
  "geometry": {"coordinates":[7.1633281708,49.4913597107],"type":"Point"}
}