{
  "type": "Feature",
  "properties": {
    "iso:country":"DE",
    "sg:address":"Eversteiner Str. 22",
    "sg:city":"Bevern",
    "sg:phone":"+49 5531/8350",
    "sg:postcode":"37639",
    "sg:province":"Niedersachsen",
    "wof:name":"Karl Tappe",
    "wof:placetype":"venue"
},
  "geometry": {"coordinates":[9.5253219604,51.866317749],"type":"Point"}
}