{
  "type": "Feature",
  "properties": {
    "iso:country":"DE",
    "sg:address":"Elsterweg 10",
    "sg:city":"Harsewinkel",
    "sg:phone":"+49 5247/4831",
    "sg:postcode":"33428",
    "sg:province":"Nordrhein-Westfalen",
    "wof:name":"Peterburs",
    "wof:placetype":"venue"
},
  "geometry": {"coordinates":[8.239323,51.96875],"type":"Point"}
}