{
  "type": "Feature",
  "properties": {
    "iso:country":"DE",
    "sg:address":"Hamburger Str. 23",
    "sg:city":"Hamburg",
    "sg:phone":"+49 40/2295498",
    "sg:postcode":"22083",
    "sg:province":"Hamburg",
    "wof:name":"Vahid-tehrani Masseur",
    "wof:placetype":"venue"
},
  "geometry": {"coordinates":[10.029276,53.571827],"type":"Point"}
}