{
  "type": "Feature",
  "properties": {
    "iso:country":"DE",
    "sg:city":"Rinchnach",
    "sg:phone":"+49 9921/7735",
    "sg:postcode":"94269",
    "sg:province":"Bayern",
    "wof:name":"T. Weiderer",
    "wof:placetype":"venue"
},
  "geometry": {"coordinates":[13.200247,48.949749],"type":"Point"}
}