{
  "type": "Feature",
  "properties": {
    "iso:country":"DE",
    "sg:address":"Friedrich-Engels-Str. 29",
    "sg:city":"Waldbr\u00f6l",
    "sg:phone":"+49 2291/924730",
    "sg:postcode":"51545",
    "sg:province":"Nordrhein-Westfalen",
    "wof:name":"P & M Hillringhaus Gmbh",
    "wof:placetype":"venue"
},
  "geometry": {"coordinates":[7.63973,50.89164],"type":"Point"}
}