{
  "type": "Feature",
  "properties": {
    "iso:country":"DE",
    "sg:address":"A Der Birkenphuhlheide 1",
    "sg:city":"Baruth",
    "sg:phone":"+49 4933/7049600",
    "sg:postcode":"15837",
    "sg:province":"Brandenburg",
    "wof:name":"Klenk Holz Ag",
    "wof:placetype":"venue"
},
  "geometry": {"coordinates":[13.5029602051,52.0450706482],"type":"Point"}
}