{
  "type": "Feature",
  "properties": {
    "iso:country":"DE",
    "sg:address":"Richthofenstr. 23",
    "sg:city":"K\u00f6nigsbrunn",
    "sg:phone":"+49 8231/85443",
    "sg:postcode":"86343",
    "sg:province":"Bayern",
    "wof:name":"Ewi Eichenseher & Willam Gmbh",
    "wof:placetype":"venue"
},
  "geometry": {"coordinates":[10.870098,48.250721],"type":"Point"}
}