{
  "type": "Feature",
  "properties": {
    "iso:country":"DE",
    "sg:address":"Arthur-Hoffmann-Str. 76",
    "sg:city":"Leipzig",
    "sg:phone":"+49 341/305080",
    "sg:postcode":"04275",
    "sg:province":"Sachsen",
    "wof:name":"Lucas Und Prestrich Rechtsanw\u00e4lte",
    "wof:placetype":"venue"
},
  "geometry": {"coordinates":[12.3782978058,51.3218536377],"type":"Point"}
}