{
  "type": "Feature",
  "properties": {
    "iso:country":"DE",
    "sg:address":"Landgrabenstr. 44-48",
    "sg:city":"N\u00fcrnberg",
    "sg:phone":"+49 911/426873",
    "sg:postcode":"90443",
    "sg:province":"Bayern",
    "wof:name":"G. Vetter",
    "wof:placetype":"venue"
},
  "geometry": {"coordinates":[11.0676670074,49.4393539429],"type":"Point"}
}