{
  "type": "Feature",
  "properties": {
    "iso:country":"DE",
    "sg:address":"Kirchditmolder Str. 33 a",
    "sg:city":"Kassel",
    "sg:phone":"+49 561/33106",
    "sg:postcode":"34131",
    "sg:province":"Hessen",
    "wof:name":"Werner Schulze-bahr",
    "wof:placetype":"venue"
},
  "geometry": {"coordinates":[9.440076,51.316746],"type":"Point"}
}