{
  "type": "Feature",
  "properties": {
    "iso:country":"DE",
    "sg:address":"Kantstr. 3",
    "sg:city":"Fredersdorf",
    "sg:phone":"+49 33439/76580",
    "sg:postcode":"15370",
    "sg:province":"Brandenburg",
    "wof:name":"R\u00fcdiger Moldt",
    "wof:placetype":"venue"
},
  "geometry": {"coordinates":[13.754588,52.540203],"type":"Point"}
}