{
  "type": "Feature",
  "properties": {
    "iso:country":"DE",
    "sg:address":"Wetteplatz 16",
    "sg:city":"Leinfelden-Echterdingen",
    "sg:phone":"+49 711/9905936",
    "sg:postcode":"70771",
    "sg:province":"Baden-W\u00fcrttemberg",
    "wof:name":"Weinstube Steck",
    "wof:placetype":"venue"
},
  "geometry": {"coordinates":[9.1642332077,48.6697502136],"type":"Point"}
}