{
  "type": "Feature",
  "properties": {
    "iso:country":"DE",
    "sg:address":"Hochstr. 51",
    "sg:city":"Gladbeck",
    "sg:phone":"+49 2043/64070",
    "sg:postcode":"45964",
    "sg:province":"Nordrhein-Westfalen",
    "wof:name":"Andreas G\u00f6bel",
    "wof:placetype":"venue"
},
  "geometry": {"coordinates":[6.994778,51.574051],"type":"Point"}
}