{
  "type": "Feature",
  "properties": {
    "iso:country":"DE",
    "sg:address":"Gemmiweg 4",
    "sg:city":"Sch\u00f6mberg",
    "sg:phone":"+49 7427/8129",
    "sg:postcode":"72355",
    "sg:province":"Baden-W\u00fcrttemberg",
    "wof:name":"Kolbe - Lift",
    "wof:placetype":"venue"
},
  "geometry": {"coordinates":[8.7445497513,48.181854248],"type":"Point"}
}