{
  "type": "Feature",
  "properties": {
    "iso:country":"DE",
    "sg:address":"W\u00f6lbattendorfer Weg 8",
    "sg:city":"Hof",
    "sg:phone":"+49 9281/3373",
    "sg:postcode":"95030",
    "sg:province":"Bayern",
    "wof:name":"Werner Pausch Steuerberater",
    "wof:placetype":"venue"
},
  "geometry": {"coordinates":[11.9059000015,50.3146705627],"type":"Point"}
}