{
  "type": "Feature",
  "properties": {
    "iso:country":"DE",
    "sg:address":"Montanusstr.",
    "sg:city":"Grevenbroich",
    "sg:postcode":"41515",
    "sg:province":"Nordrhein-Westfalen",
    "wof:name":"Globus S.b. Warenhaus Kaiser & Kellermann",
    "wof:placetype":"venue"
},
  "geometry": {"coordinates":[6.59381,51.092323],"type":"Point"}
}