{
  "type": "Feature",
  "properties": {
    "iso:country":"DE",
    "sg:address":"Steinstr. 5",
    "sg:city":"Emmerich",
    "sg:phone":"+49 2822/10056",
    "sg:postcode":"46446",
    "sg:province":"Nordrhein-Westfalen",
    "wof:name":"Dc Chemicals & Service Vertriebs-gmbh",
    "wof:placetype":"venue"
},
  "geometry": {"coordinates":[6.2416977882,51.83020401],"type":"Point"}
}