{
  "type": "Feature",
  "properties": {
    "iso:country":"DE",
    "sg:address":"Josef-Kistler-Str. 10",
    "sg:city":"Germering",
    "sg:phone":"+49 89/8414518",
    "sg:postcode":"82110",
    "sg:province":"Bayern",
    "wof:name":"Videothek Schanda",
    "wof:placetype":"venue"
},
  "geometry": {"coordinates":[11.3592796326,48.1336898804],"type":"Point"}
}