{
  "type": "Feature",
  "properties": {
    "iso:country":"DE",
    "sg:address":"Telgter Damm 46",
    "sg:city":"Ladbergen",
    "sg:phone":"+49 5485/1334",
    "sg:postcode":"49549",
    "sg:province":"Nordrhein-Westfalen",
    "wof:name":"Gravemeier Gmbh",
    "wof:placetype":"venue"
},
  "geometry": {"coordinates":[7.7458062172,52.1303825378],"type":"Point"}
}