{
  "type": "Feature",
  "properties": {
    "iso:country":"DE",
    "sg:address":"Ahrensfelde 4",
    "sg:city":"Westerau",
    "sg:phone":"+49 4539/396",
    "sg:postcode":"23847",
    "sg:province":"Schleswig-Holstein",
    "wof:name":"Rodent Arnold Hamann",
    "wof:placetype":"venue"
},
  "geometry": {"coordinates":[10.492108,53.76368],"type":"Point"}
}