{
  "type": "Feature",
  "properties": {
    "iso:country":"DE",
    "sg:address":"Am B\u00f6hmeufer 6",
    "sg:city":"Bomlitz",
    "sg:phone":"+49 5161/2211",
    "sg:postcode":"29699",
    "sg:province":"Niedersachsen",
    "wof:name":"M\u00c4x Art Verpackungs- Design Gmbh",
    "wof:placetype":"venue"
},
  "geometry": {"coordinates":[9.644449,52.886353],"type":"Point"}
}