{
  "type": "Feature",
  "properties": {
    "iso:country":"DE",
    "sg:address":"Engishausen 47",
    "sg:city":"Egg",
    "sg:postcode":"87743",
    "sg:province":"Bayern",
    "wof:name":"Norbert Weber E. K.",
    "wof:placetype":"venue"
},
  "geometry": {"coordinates":[10.271428,48.109409],"type":"Point"}
}