{
  "type": "Feature",
  "properties": {
    "iso:country":"DE",
    "sg:address":"Rudolf-Breitscheid-Str. 14",
    "sg:city":"L\u00fcbtheen",
    "sg:phone":"+49 38855/51126",
    "sg:postcode":"19249",
    "sg:province":"Mecklenburg-Vorpommern",
    "wof:name":"Siegfried L\u00fcben",
    "wof:placetype":"venue"
},
  "geometry": {"coordinates":[11.082118988,53.3054695129],"type":"Point"}
}