{
  "type": "Feature",
  "properties": {
    "iso:country":"DE",
    "sg:address":"N\u00fcrnberger Str. 54",
    "sg:city":"Barchfeld",
    "sg:phone":"+49 36961/40149",
    "sg:postcode":"36456",
    "sg:province":"Th\u00fcringen",
    "wof:name":"U. Kallenbach",
    "wof:placetype":"venue"
},
  "geometry": {"coordinates":[10.3116703033,50.8014335632],"type":"Point"}
}