{
  "type": "Feature",
  "properties": {
    "iso:country":"DE",
    "sg:address":"Basler Str. 104",
    "sg:city":"Schallstadt",
    "sg:phone":"+49 7664/6512",
    "sg:postcode":"79227",
    "sg:province":"Baden-W\u00fcrttemberg",
    "wof:name":"Gunther Joos",
    "wof:placetype":"venue"
},
  "geometry": {"coordinates":[7.764223,47.959007],"type":"Point"}
}