{
  "type": "Feature",
  "properties": {
    "iso:country":"DE",
    "sg:address":"Adelheider Str. 177",
    "sg:city":"Delmenhorst",
    "sg:phone":"+49 4221/289752",
    "sg:postcode":"27755",
    "sg:province":"Niedersachsen",
    "wof:name":"G. Abel",
    "wof:placetype":"venue"
},
  "geometry": {"coordinates":[8.61044,53.021511],"type":"Point"}
}