{
  "type": "Feature",
  "properties": {
    "iso:country":"DE",
    "sg:address":"Emsstr. 1",
    "sg:city":"Gudensberg",
    "sg:phone":"+49 5603/2139",
    "sg:postcode":"34281",
    "sg:province":"Hessen",
    "wof:name":"Hanskurt Ruppert",
    "wof:placetype":"venue"
},
  "geometry": {"coordinates":[9.351872,51.158653],"type":"Point"}
}