{
  "type": "Feature",
  "properties": {
    "iso:country":"DE",
    "sg:address":"Im Riemen 2",
    "sg:city":"Babenhausen",
    "sg:phone":"+49 6073/725912",
    "sg:postcode":"64832",
    "sg:province":"Hessen",
    "wof:name":"Rsz Ralf Sahlmen Zerspannungstechnik Gmbh",
    "wof:placetype":"venue"
},
  "geometry": {"coordinates":[8.9581203461,49.9521636963],"type":"Point"}
}