{
  "type": "Feature",
  "properties": {
    "iso:country":"DE",
    "sg:address":"Perlacher Str. 12",
    "sg:city":"Gr\u00fcnwald",
    "sg:phone":"+49 89/6411733",
    "sg:postcode":"82031",
    "sg:province":"Bayern",
    "wof:name":"Richard Strauss",
    "wof:placetype":"venue"
},
  "geometry": {"coordinates":[11.5258302689,48.0407218933],"type":"Point"}
}