{
  "type": "Feature",
  "properties": {
    "iso:country":"DE",
    "sg:address":"Poststr.",
    "sg:city":"Berlin",
    "sg:phone":"+49 30/2415697",
    "sg:postcode":"10178",
    "sg:province":"Berlin",
    "wof:name":"Gub Gastrononie- Gmbh",
    "wof:placetype":"venue"
},
  "geometry": {"coordinates":[13.40662,52.516575],"type":"Point"}
}