{
  "type": "Feature",
  "properties": {
    "iso:country":"DE",
    "sg:address":"Friedenstr. 22",
    "sg:city":"Gnoien",
    "sg:phone":"+49 39971/12725",
    "sg:postcode":"17179",
    "sg:province":"Mecklenburg-Vorpommern",
    "wof:name":"K. Kelch",
    "wof:placetype":"venue"
},
  "geometry": {"coordinates":[12.711062,53.968334],"type":"Point"}
}