{
  "type": "Feature",
  "properties": {
    "iso:country":"DE",
    "sg:address":"Lange Str. 29",
    "sg:city":"Spenge",
    "sg:phone":"+49 5225/5664",
    "sg:postcode":"32139",
    "sg:province":"Nordrhein-Westfalen",
    "wof:name":"Lampe",
    "wof:placetype":"venue"
},
  "geometry": {"coordinates":[8.482627,52.140892],"type":"Point"}
}