{
  "type": "Feature",
  "properties": {
    "iso:country":"DE",
    "sg:address":"Am Wald 8",
    "sg:city":"L\u00f6ningen",
    "sg:phone":"+49 5432/58552",
    "sg:postcode":"49624",
    "sg:province":"Niedersachsen",
    "wof:name":"R\u00f6we",
    "wof:placetype":"venue"
},
  "geometry": {"coordinates":[7.7205090523,52.7886619568],"type":"Point"}
}