{
  "type": "Feature",
  "properties": {
    "iso:country":"DE",
    "sg:address":"L\u00fcbecker Str. 16",
    "sg:city":"Kl\u00fctz",
    "sg:phone":"+49 38825/22571",
    "sg:postcode":"23948",
    "sg:province":"Mecklenburg-Vorpommern",
    "wof:name":"Dr. Erich M\u00f6ller Tierarzt",
    "wof:placetype":"venue"
},
  "geometry": {"coordinates":[11.158323288,53.9695053101],"type":"Point"}
}