{
  "type": "Feature",
  "properties": {
    "iso:country":"DE",
    "sg:address":"Herzog-Johann-Albrecht-Str. 34",
    "sg:city":"Braunlage",
    "sg:phone":"+49 4961/0236710",
    "sg:postcode":"38700",
    "sg:province":"Niedersachsen",
    "wof:name":"Therma Nicolet Gmbh",
    "wof:placetype":"venue"
},
  "geometry": {"coordinates":[8.717936,50.046413],"type":"Point"}
}