{
  "type": "Feature",
  "properties": {
    "iso:country":"DE",
    "sg:address":"H\u00fclsdauer Str. 95",
    "sg:city":"Marl",
    "sg:phone":"+49 2365/7418",
    "sg:postcode":"45768",
    "sg:province":"Nordrhein-Westfalen",
    "wof:name":"Johannes D\u00f6weling",
    "wof:placetype":"venue"
},
  "geometry": {"coordinates":[7.0426430702,51.6350326538],"type":"Point"}
}