{
  "type": "Feature",
  "properties": {
    "iso:country":"DE",
    "sg:address":"Sextrostr. 3-5",
    "sg:city":"Hannover",
    "sg:phone":"+49 511/808096",
    "sg:postcode":"30169",
    "sg:province":"Niedersachsen",
    "wof:name":"Videotechnik-lixfeld Gmbh",
    "wof:placetype":"venue"
},
  "geometry": {"coordinates":[9.7468585968,52.3635368347],"type":"Point"}
}