{
  "type": "Feature",
  "properties": {
    "iso:country":"DE",
    "sg:address":"Gutenbergstr 8",
    "sg:city":"Hemmingen",
    "sg:phone":"+49 511/94265830",
    "sg:postcode":"30966",
    "sg:province":"Niedersachsen",
    "wof:name":"Public Point Automatensysteme Gmbh",
    "wof:placetype":"venue"
},
  "geometry": {"coordinates":[9.721955,52.321587],"type":"Point"}
}