{
  "type": "Feature",
  "properties": {
    "iso:country":"DE",
    "sg:address":"Bahnhofstr. 18",
    "sg:city":"Cloppenburg",
    "sg:phone":"+49 4471/957352",
    "sg:postcode":"49661",
    "sg:province":"Niedersachsen",
    "wof:name":"Lohrey Gmbh",
    "wof:placetype":"venue"
},
  "geometry": {"coordinates":[8.0464305878,52.8455581665],"type":"Point"}
}