{
  "type": "Feature",
  "properties": {
    "iso:country":"DE",
    "sg:address":"Mole",
    "sg:city":"Norden",
    "sg:phone":"+49 4931/18020",
    "sg:postcode":"26506",
    "sg:province":"Niedersachsen",
    "wof:name":"Ag Reederei Norden-frisia",
    "wof:placetype":"venue"
},
  "geometry": {"coordinates":[7.168387,53.616589],"type":"Point"}
}