{
  "type": "Feature",
  "properties": {
    "iso:country":"DE",
    "sg:address":"H\u00fcttendorfer Str. 13",
    "sg:city":"Erlangen",
    "sg:phone":"+49 911/763203",
    "sg:postcode":"91056",
    "sg:province":"Bayern",
    "wof:name":"Wilhelm Menzel",
    "wof:placetype":"venue"
},
  "geometry": {"coordinates":[10.961225,49.540939],"type":"Point"}
}