{
  "type": "Feature",
  "properties": {
    "iso:country":"DE",
    "sg:address":"R\u00f6ckinghausener Str. 17",
    "sg:city":"Rheda-Wiedenbr\u00fcck",
    "sg:phone":"+49 5242/2320",
    "sg:postcode":"33378",
    "sg:province":"Nordrhein-Westfalen",
    "wof:name":"Hubert Diedam",
    "wof:placetype":"venue"
},
  "geometry": {"coordinates":[8.329077,51.8186],"type":"Point"}
}