{
  "type": "Feature",
  "properties": {
    "iso:country":"DE",
    "sg:address":"H\u00fctter Str. 36",
    "sg:city":"Hattert",
    "sg:phone":"+49 2662/1384",
    "sg:postcode":"57644",
    "sg:province":"Rheinland-Pfalz",
    "wof:name":"Friedhelm K\u00f6nig K\u00f6nig Pr\u00e4sente",
    "wof:placetype":"venue"
},
  "geometry": {"coordinates":[7.7772159576,50.6515808105],"type":"Point"}
}