{
  "type": "Feature",
  "properties": {
    "iso:country":"DE",
    "sg:address":"Hambloch-M\u00fchlen-Str. 19",
    "sg:city":"Frechen",
    "sg:postcode":"50226",
    "sg:province":"Nordrhein-Westfalen",
    "wof:name":"Hans Zimmermann",
    "wof:placetype":"venue"
},
  "geometry": {"coordinates":[6.7700500488,50.9343948364],"type":"Point"}
}