{
  "type": "Feature",
  "properties": {
    "iso:country":"DE",
    "sg:address":"Hauptstr. 11",
    "sg:city":"Quersa",
    "sg:phone":"+49 35248/81204",
    "sg:postcode":"01561",
    "sg:province":"Sachsen",
    "wof:name":"Eckehardt Jeschonek",
    "wof:placetype":"venue"
},
  "geometry": {"coordinates":[13.6430625916,51.3035774231],"type":"Point"}
}