{
  "type": "Feature",
  "properties": {
    "iso:country":"DE",
    "sg:address":"\u00c4u\u00dfere Leipziger Str. 45",
    "sg:city":"Schkeuditz",
    "sg:phone":"+49 34204/64967",
    "sg:postcode":"04435",
    "sg:province":"Sachsen",
    "wof:name":"Kalb",
    "wof:placetype":"venue"
},
  "geometry": {"coordinates":[12.2489099503,51.3880615234],"type":"Point"}
}