{
  "type": "Feature",
  "properties": {
    "iso:country":"DE",
    "sg:address":"Saarring 8a",
    "sg:city":"Minden",
    "sg:phone":"+49 571/63502",
    "sg:postcode":"32425",
    "sg:province":"Nordrhein-Westfalen",
    "wof:name":"Allianz Versicherungs Ag Brink Und Seifert",
    "wof:placetype":"venue"
},
  "geometry": {"coordinates":[8.9061479568,52.3077087402],"type":"Point"}
}