{
  "type": "Feature",
  "properties": {
    "iso:country":"DE",
    "sg:address":"Hauptstr. 210",
    "sg:city":"Herne",
    "sg:postcode":"44649",
    "sg:province":"Nordrhein-Westfalen",
    "wof:name":"Die Tageszeitung Beteiligungs- Und Verwaltungs-",
    "wof:placetype":"venue"
},
  "geometry": {"coordinates":[7.1600351334,51.5292854309],"type":"Point"}
}