{
  "type": "Feature",
  "properties": {
    "iso:country":"DE",
    "sg:address":"Berghofstr. 31",
    "sg:city":"Bovenden",
    "sg:phone":"+49 5593/717",
    "sg:postcode":"37120",
    "sg:province":"Niedersachsen",
    "wof:name":"Hartmut Wintzenburg",
    "wof:placetype":"venue"
},
  "geometry": {"coordinates":[9.8303,51.582069],"type":"Point"}
}