{
  "type": "Feature",
  "properties": {
    "iso:country":"DE",
    "sg:address":"Rostocker Str. 1",
    "sg:city":"Hamburg",
    "sg:phone":"+49 40/2802886",
    "sg:postcode":"20099",
    "sg:province":"Hamburg",
    "wof:name":"Abenteuer Medien Vertrieb J\u00fcrgen Pirner",
    "wof:placetype":"venue"
},
  "geometry": {"coordinates":[10.0124568939,53.555431366],"type":"Point"}
}