{
  "type": "Feature",
  "properties": {
    "iso:country":"DE",
    "sg:address":"Langenberger Str. 7",
    "sg:city":"Hude",
    "sg:phone":"+49 4408/426",
    "sg:postcode":"27798",
    "sg:province":"Niedersachsen",
    "wof:name":"Ing. Gerd Janzen Gmbh",
    "wof:placetype":"venue"
},
  "geometry": {"coordinates":[8.484542,53.098316],"type":"Point"}
}