{
  "type": "Feature",
  "properties": {
    "iso:country":"DE",
    "sg:address":"Wiesseer Str. 130",
    "sg:city":"Bad Wiessee",
    "sg:postcode":"83707",
    "sg:province":"Bayern",
    "wof:name":"Analog Gmbh",
    "wof:placetype":"venue"
},
  "geometry": {"coordinates":[11.7291183472,47.700340271],"type":"Point"}
}