{
  "type": "Feature",
  "properties": {
    "iso:country":"DE",
    "sg:address":"Lausitzer Str 7",
    "sg:city":"Geretsried",
    "sg:phone":"+49 8171/81780",
    "sg:postcode":"82538",
    "sg:province":"Bayern",
    "wof:name":"Dmg Gebrauchtmaschinen Gmbh",
    "wof:placetype":"venue"
},
  "geometry": {"coordinates":[11.494283,47.857384],"type":"Point"}
}