{
  "type": "Feature",
  "properties": {
    "iso:country":"DE",
    "sg:address":"Hochkamp 1",
    "sg:city":"Bar\u00dfel",
    "sg:phone":"+49 4497/8395",
    "sg:postcode":"26676",
    "sg:province":"Niedersachsen",
    "wof:name":"P. M\u00f6dden",
    "wof:placetype":"venue"
},
  "geometry": {"coordinates":[7.83634,53.113682],"type":"Point"}
}