{
  "type": "Feature",
  "properties": {
    "iso:country":"DE",
    "sg:city":"Rudersberg",
    "sg:phone":"+49 7183/936310",
    "sg:postcode":"73635",
    "sg:province":"Baden-W\u00fcrttemberg",
    "wof:name":"Jugendb\u00fccherei Grund- Und Hauptschule",
    "wof:placetype":"venue"
},
  "geometry": {"coordinates":[9.528045,48.885666],"type":"Point"}
}