{
  "type": "Feature",
  "properties": {
    "iso:country":"DE",
    "sg:address":"Deidesheimer Str. 2",
    "sg:city":"Ludwigshafen",
    "sg:phone":"+49 621/553324",
    "sg:postcode":"67067",
    "sg:province":"Rheinland-Pfalz",
    "wof:name":"Katholisches Pfarramt St. Bonifaz",
    "wof:placetype":"venue"
},
  "geometry": {"coordinates":[8.4060535431,49.4603004456],"type":"Point"}
}