{
  "type": "Feature",
  "properties": {
    "iso:country":"DE",
    "sg:address":"Maximiliansplatz 12b",
    "sg:city":"M\u00fcnchen",
    "sg:phone":"+49 89/224831",
    "sg:postcode":"80333",
    "sg:province":"Bayern",
    "wof:name":"Theodor G\u00e4bler",
    "wof:placetype":"venue"
},
  "geometry": {"coordinates":[11.573375,48.142448],"type":"Point"}
}