{
  "type": "Feature",
  "properties": {
    "iso:country":"DE",
    "sg:address":"Alte Bahnhofstr. 52",
    "sg:city":"Bochum",
    "sg:phone":"+49 234/286557",
    "sg:postcode":"44892",
    "sg:province":"Nordrhein-Westfalen",
    "wof:name":"Helga Lechniak",
    "wof:placetype":"venue"
},
  "geometry": {"coordinates":[7.3186650276,51.4710655212],"type":"Point"}
}