{
  "type": "Feature",
  "properties": {
    "iso:country":"DE",
    "sg:address":"Dormitzer Str. 31",
    "sg:city":"Neunkirchen",
    "sg:phone":"+49 9134/995504",
    "sg:postcode":"91077",
    "sg:province":"Bayern",
    "wof:name":"Horst Gosemann Architekt",
    "wof:placetype":"venue"
},
  "geometry": {"coordinates":[11.126388,49.605152],"type":"Point"}
}