{
  "type": "Feature",
  "properties": {
    "iso:country":"DE",
    "sg:address":"H\u00f6henweg 4 a",
    "sg:city":"Kempten",
    "sg:phone":"+49 831/5707822",
    "sg:postcode":"87437",
    "sg:province":"Bayern",
    "wof:name":"Msz-tools Pr\u00e4zisionswerkzeuge Verwaltungs Gmbh",
    "wof:placetype":"venue"
},
  "geometry": {"coordinates":[10.3372373581,47.7245330811],"type":"Point"}
}