{
  "type": "Feature",
  "properties": {
    "iso:country":"DE",
    "sg:address":"Zeppelinstr. 42",
    "sg:city":"Ostfildern",
    "sg:phone":"+49 711/4560021",
    "sg:postcode":"73760",
    "sg:province":"Baden-W\u00fcrttemberg",
    "wof:name":"Hirose Electric Gmbh",
    "wof:placetype":"venue"
},
  "geometry": {"coordinates":[9.222681,48.723457],"type":"Point"}
}