{
  "type": "Feature",
  "properties": {
    "iso:country":"DE",
    "sg:address":"Knappenweg 75",
    "sg:city":"Stuttgart",
    "sg:phone":"+49 711/682011",
    "sg:postcode":"70569",
    "sg:province":"Baden-W\u00fcrttemberg",
    "wof:name":"Dr. Walther Gerd Fleck Architekt",
    "wof:placetype":"venue"
},
  "geometry": {"coordinates":[9.12234,48.748253],"type":"Point"}
}