{
  "type": "Feature",
  "properties": {
    "iso:country":"DE",
    "sg:address":"Offenbacher Str. 19",
    "sg:city":"Dreieich",
    "sg:phone":"+49 6103/373346",
    "sg:postcode":"63303",
    "sg:province":"Hessen",
    "wof:name":"Ludwig Gg. Orth Schlosserei-metallbau",
    "wof:placetype":"venue"
},
  "geometry": {"coordinates":[8.696891,50.020065],"type":"Point"}
}