{
  "type": "Feature",
  "properties": {
    "iso:country":"DE",
    "sg:address":"Kleiner Werth 37-41",
    "sg:city":"Wuppertal",
    "sg:phone":"+49 202/595050",
    "sg:postcode":"42275",
    "sg:province":"Nordrhein-Westfalen",
    "wof:name":"Hans Klein Gmbh & Co Kg",
    "wof:placetype":"venue"
},
  "geometry": {"coordinates":[7.207053,51.275768],"type":"Point"}
}