{
  "type": "Feature",
  "properties": {
    "iso:country":"DE",
    "sg:address":"Amtsst\u00fcck 2",
    "sg:city":"Mainbernheim",
    "sg:phone":"+49 9323/451",
    "sg:postcode":"97350",
    "sg:province":"Bayern",
    "wof:name":"Karl Wolf",
    "wof:placetype":"venue"
},
  "geometry": {"coordinates":[10.215428,49.701015],"type":"Point"}
}