{
  "type": "Feature",
  "properties": {
    "iso:country":"DE",
    "sg:address":"Am Ludwigsplatz 6",
    "sg:city":"Saarbr\u00fccken",
    "sg:phone":"+49 681/5011201",
    "sg:postcode":"66117",
    "sg:province":"Saarland",
    "wof:name":"Deutsch Franz\u00f6sisches Hochschulinstitut F\u00fcr",
    "wof:placetype":"venue"
},
  "geometry": {"coordinates":[6.9870247841,49.2321777344],"type":"Point"}
}