{
  "type": "Feature",
  "properties": {
    "iso:country":"DE",
    "sg:address":"Morlaixplatz 27",
    "sg:city":"W\u00fcrselen",
    "sg:postcode":"52146",
    "sg:province":"Nordrhein-Westfalen",
    "wof:name":"Novotekt Bauprojektierung Gmbh",
    "wof:placetype":"venue"
},
  "geometry": {"coordinates":[6.13064,50.818089],"type":"Point"}
}