{
  "type": "Feature",
  "properties": {
    "iso:country":"DE",
    "sg:address":"Bachstr. 4",
    "sg:city":"Flemlingen",
    "sg:phone":"+49 6323/2760",
    "sg:postcode":"76835",
    "sg:province":"Rheinland-Pfalz",
    "wof:name":"Robert Herbst",
    "wof:placetype":"venue"
},
  "geometry": {"coordinates":[8.0935792923,49.2437553406],"type":"Point"}
}