{
  "type": "Feature",
  "properties": {
    "iso:country":"DE",
    "sg:address":"Bismarckstr. 2",
    "sg:city":"Sch\u00f6ningen",
    "sg:phone":"+49 5352/59760",
    "sg:postcode":"38364",
    "sg:province":"Niedersachsen",
    "wof:name":"D. Gorges",
    "wof:placetype":"venue"
},
  "geometry": {"coordinates":[10.9706478119,52.1383590698],"type":"Point"}
}