{
  "type": "Feature",
  "properties": {
    "iso:country":"DE",
    "sg:address":"Gerlingstr. 10-12",
    "sg:city":"Essen",
    "sg:phone":"+49 201/200011",
    "sg:postcode":"45127",
    "sg:province":"Nordrhein-Westfalen",
    "wof:name":"Al-andalus",
    "wof:placetype":"venue"
},
  "geometry": {"coordinates":[7.0157389641,51.4608764648],"type":"Point"}
}