{
  "type": "Feature",
  "properties": {
    "iso:country":"DE",
    "sg:address":"Barntruper Str. 32",
    "sg:city":"Paderborn",
    "sg:postcode":"33102",
    "sg:province":"Nordrhein-Westfalen",
    "wof:name":"Purus Umweltschutzdienst Gmbh",
    "wof:placetype":"venue"
},
  "geometry": {"coordinates":[8.769655,51.745338],"type":"Point"}
}