{
  "type": "Feature",
  "properties": {
    "iso:country":"DE",
    "sg:address":"Z\u00f6llinplatz 4",
    "sg:city":"Badenweiler",
    "sg:phone":"+49 7632/891576",
    "sg:postcode":"79410",
    "sg:province":"Baden-W\u00fcrttemberg",
    "wof:name":"Apotheke Am Z\u00f6llinplatz Inh. Monika R\u00f6ding",
    "wof:placetype":"venue"
},
  "geometry": {"coordinates":[7.677513,47.802959],"type":"Point"}
}