{
  "type": "Feature",
  "properties": {
    "iso:country":"DE",
    "sg:address":"Ernst-Th\u00e4lmann-Str. 5",
    "sg:city":"Themar",
    "sg:phone":"+49 36873/60310",
    "sg:postcode":"98660",
    "sg:province":"Th\u00fcringen",
    "wof:name":"Horst Heuer",
    "wof:placetype":"venue"
},
  "geometry": {"coordinates":[10.6146602631,50.5028190613],"type":"Point"}
}