{
  "type": "Feature",
  "properties": {
    "iso:country":"DE",
    "sg:address":"In den Emsenwehren 12",
    "sg:city":"Bad Sulza",
    "sg:phone":"+49 36461/20363",
    "sg:postcode":"99518",
    "sg:province":"Th\u00fcringen",
    "wof:name":"Hs Metall Hornbach- Stowasses Gmbh",
    "wof:placetype":"venue"
},
  "geometry": {"coordinates":[11.62312,51.095638],"type":"Point"}
}