{
  "type": "Feature",
  "properties": {
    "iso:country":"DE",
    "sg:address":"Adalbert-Stifter-Str. 10",
    "sg:city":"Maintal",
    "sg:phone":"+49 6109/64490",
    "sg:postcode":"63477",
    "sg:province":"Hessen",
    "wof:name":"Manfred Jockel",
    "wof:placetype":"venue"
},
  "geometry": {"coordinates":[8.8120193481,50.1494483948],"type":"Point"}
}