{
  "type": "Feature",
  "properties": {
    "iso:country":"DE",
    "sg:address":"Schulberg 2",
    "sg:city":"Schwieberdingen",
    "sg:phone":"+49 7150/35832",
    "sg:postcode":"71701",
    "sg:province":"Baden-W\u00fcrttemberg",
    "wof:name":"G. Demirtas",
    "wof:placetype":"venue"
},
  "geometry": {"coordinates":[9.0742387772,48.8767738342],"type":"Point"}
}