{
  "type": "Feature",
  "properties": {
    "iso:country":"DE",
    "sg:address":"Osterkoppel 17",
    "sg:city":"S\u00fcderbrarup",
    "sg:phone":"+49 4641/93260",
    "sg:postcode":"24392",
    "sg:province":"Schleswig-Holstein",
    "wof:name":"Eckhard Schwanebeck",
    "wof:placetype":"venue"
},
  "geometry": {"coordinates":[9.7866182327,54.6350135803],"type":"Point"}
}