{
  "type": "Feature",
  "properties": {
    "iso:country":"DE",
    "sg:address":"Reithammer Weg 8",
    "sg:city":"Osteel",
    "sg:phone":"+49 4934/4568",
    "sg:postcode":"26529",
    "sg:province":"Niedersachsen",
    "wof:name":"M. Nehring Immobilienmakler",
    "wof:placetype":"venue"
},
  "geometry": {"coordinates":[7.2627110481,53.5312919617],"type":"Point"}
}