{
  "type": "Feature",
  "properties": {
    "iso:country":"DE",
    "sg:address":"Hauptstr. 229",
    "sg:city":"Idar-Oberstein",
    "sg:phone":"+49 4967/8150040",
    "sg:postcode":"55743",
    "sg:province":"Rheinland-Pfalz",
    "wof:name":"Rudolf Cullmann E.k. Inh. Klaus Cullmann",
    "wof:placetype":"venue"
},
  "geometry": {"coordinates":[7.3140201569,49.7107048035],"type":"Point"}
}