{
  "type": "Feature",
  "properties": {
    "iso:country":"DE",
    "sg:address":"Stadtring Nordhorn 116",
    "sg:city":"G\u00fctersloh",
    "sg:phone":"+49 521/45577",
    "sg:postcode":"33334",
    "sg:province":"Nordrhein-Westfalen",
    "wof:name":"Weiland & Cie. Spezialfabrik Galvanotechnik",
    "wof:placetype":"venue"
},
  "geometry": {"coordinates":[8.408627,51.922417],"type":"Point"}
}