{
  "type": "Feature",
  "properties": {
    "iso:country":"DE",
    "sg:address":"H\u00f6lderlinstr. 26",
    "sg:city":"Friedrichshafen",
    "sg:phone":"+49 7541/52525",
    "sg:postcode":"88045",
    "sg:province":"Baden-W\u00fcrttemberg",
    "wof:name":"Herbert Schneider Architekt",
    "wof:placetype":"venue"
},
  "geometry": {"coordinates":[9.483796,47.66679],"type":"Point"}
}