{
  "type": "Feature",
  "properties": {
    "iso:country":"DE",
    "sg:address":"Vorderschneid 6",
    "sg:city":"Wertach",
    "sg:phone":"+49 8365/1786",
    "sg:postcode":"87497",
    "sg:province":"Bayern",
    "wof:name":"Gup Ganzheitl. Unternehmens- Und Personalentwicklung Gmbh",
    "wof:placetype":"venue"
},
  "geometry": {"coordinates":[10.414494,47.616131],"type":"Point"}
}