{
  "type": "Feature",
  "properties": {
    "iso:country":"DE",
    "sg:address":"Oppenheimer Str. 10",
    "sg:city":"R\u00fcsselsheim",
    "sg:phone":"+49 6142/12488",
    "sg:postcode":"65428",
    "sg:province":"Hessen",
    "wof:name":"Pizzeria Taormina",
    "wof:placetype":"venue"
},
  "geometry": {"coordinates":[8.4019603729,49.9816703796],"type":"Point"}
}