{
  "type": "Feature",
  "properties": {
    "iso:country":"DE",
    "sg:address":"C\u00e4cilienstr. 6",
    "sg:city":"Wilnsdorf",
    "sg:phone":"+49 271/3937570",
    "sg:postcode":"57234",
    "sg:province":"Nordrhein-Westfalen",
    "wof:name":"Dieter Bergmann Steuerberater",
    "wof:placetype":"venue"
},
  "geometry": {"coordinates":[8.0783452988,50.854888916],"type":"Point"}
}