{
  "type": "Feature",
  "properties": {
    "iso:country":"DE",
    "sg:address":"Ellerstr. 138",
    "sg:city":"D\u00fcsseldorf",
    "sg:phone":"+49 211/787623",
    "sg:postcode":"40227",
    "sg:province":"Nordrhein-Westfalen",
    "wof:name":"Joachim Pohl",
    "wof:placetype":"venue"
},
  "geometry": {"coordinates":[6.800425,51.215031],"type":"Point"}
}