{
  "type": "Feature",
  "properties": {
    "iso:country":"DE",
    "sg:address":"Kastellaunerstr.22",
    "sg:city":"Laubach",
    "sg:phone":"+49 6762/951652",
    "sg:postcode":"56288",
    "sg:province":"Rheinland-Pfalz",
    "wof:name":"Fachh\u00e4ndler F\u00fcr Motorr\u00e4der Bmw, Suzuki, In 55469 S",
    "wof:placetype":"venue"
},
  "geometry": {"coordinates":[7.508495,50.055828],"type":"Point"}
}