{
  "type": "Feature",
  "properties": {
    "iso:country":"DE",
    "sg:address":"Klinkumer Str. 17",
    "sg:city":"Wegberg",
    "sg:phone":"+49 2434/6312",
    "sg:postcode":"41844",
    "sg:province":"Nordrhein-Westfalen",
    "wof:name":"Erich Jan\u00dfen",
    "wof:placetype":"venue"
},
  "geometry": {"coordinates":[6.268293,51.137417],"type":"Point"}
}