{
  "type": "Feature",
  "properties": {
    "iso:country":"DE",
    "sg:address":"Gelthari-Ring 13",
    "sg:city":"Geldersheim",
    "sg:phone":"+49 9721/89077",
    "sg:postcode":"97505",
    "sg:province":"Bayern",
    "wof:name":"Lg Freizeitwelt Grosshandel Gmbh",
    "wof:placetype":"venue"
},
  "geometry": {"coordinates":[10.150384,50.050758],"type":"Point"}
}