{
  "type": "Feature",
  "properties": {
    "iso:country":"DE",
    "sg:address":"Marienplatz 25",
    "sg:city":"M\u00fcnchen",
    "sg:phone":"+49 89/2318020",
    "sg:postcode":"80331",
    "sg:province":"Bayern",
    "wof:name":"Bader Und Uhlig Notare",
    "wof:placetype":"venue"
},
  "geometry": {"coordinates":[11.5751962662,48.137008667],"type":"Point"}
}