{
  "type": "Feature",
  "properties": {
    "iso:country":"DE",
    "sg:address":"Rathenaustr. 1::",
    "sg:city":"Gie\u00dfen",
    "sg:phone":"+49 4964/179410",
    "sg:postcode":"35394",
    "sg:province":"Hessen",
    "wof:name":"Ordat Gesellschaft F\u00dcr Organisation U. Daten- Verarbeitung Mbh & Co.",
    "wof:placetype":"venue"
},
  "geometry": {"coordinates":[8.691814,50.572025],"type":"Point"}
}