{
  "type": "Feature",
  "properties": {
    "iso:country":"DE",
    "sg:address":"Henkelhofweg 2",
    "sg:city":"Grebenhain",
    "sg:phone":"+49 6643/211",
    "sg:postcode":"36355",
    "sg:province":"Hessen",
    "wof:name":"Willi Kaiser",
    "wof:placetype":"venue"
},
  "geometry": {"coordinates":[9.331823,50.523022],"type":"Point"}
}