{
  "type": "Feature",
  "properties": {
    "iso:country":"DE",
    "sg:address":"Adelsgasse 14",
    "sg:city":"Heroldsbach",
    "sg:phone":"+49 9190/92880",
    "sg:postcode":"91336",
    "sg:province":"Bayern",
    "wof:name":"Bauunternehmen Franz Kraus Gmbh",
    "wof:placetype":"venue"
},
  "geometry": {"coordinates":[11.003435,49.692978],"type":"Point"}
}