{
  "type": "Feature",
  "properties": {
    "iso:country":"DE",
    "sg:address":"Am G\u00f6bel 3",
    "sg:city":"Gr\u00fcnsfeld",
    "sg:phone":"+49 9346/8210",
    "sg:postcode":"97947",
    "sg:province":"Baden-W\u00fcrttemberg",
    "wof:name":"Reese-binder Kg",
    "wof:placetype":"venue"
},
  "geometry": {"coordinates":[9.745406,49.612972],"type":"Point"}
}