{
  "type": "Feature",
  "properties": {
    "iso:country":"DE",
    "sg:address":"Am Eselsborn 1a",
    "sg:city":"Nieder-Olm",
    "sg:phone":"+49 6136/46041",
    "sg:postcode":"55268",
    "sg:province":"Rheinland-Pfalz",
    "wof:name":"Michael Seiff Rechtsanwalt",
    "wof:placetype":"venue"
},
  "geometry": {"coordinates":[8.2063293457,49.9134254456],"type":"Point"}
}