{
  "type": "Feature",
  "properties": {
    "iso:country":"DE",
    "sg:address":"Trachenbergring 93",
    "sg:city":"Berlin",
    "sg:phone":"+49 30/349645",
    "sg:postcode":"12249",
    "sg:province":"Berlin",
    "wof:name":"Hans Brochier Gmbh & Co. Kg",
    "wof:placetype":"venue"
},
  "geometry": {"coordinates":[13.3684253693,52.4275550842],"type":"Point"}
}