{
  "type": "Feature",
  "properties": {
    "iso:country":"DE",
    "sg:address":"An der Berleburg 23",
    "sg:city":"Schlitz",
    "sg:phone":"+49 6642/919040",
    "sg:postcode":"36110",
    "sg:province":"Hessen",
    "wof:name":"Josef Minks Elektroinstallation",
    "wof:placetype":"venue"
},
  "geometry": {"coordinates":[9.552937,50.671314],"type":"Point"}
}