{
  "type": "Feature",
  "properties": {
    "iso:country":"DE",
    "sg:address":"Adalbertstr. 102",
    "sg:city":"Aachen",
    "sg:postcode":"52062",
    "sg:province":"Nordrhein-Westfalen",
    "wof:name":"Kaisers Drugstore",
    "wof:placetype":"venue"
},
  "geometry": {"coordinates":[6.093631,50.775005],"type":"Point"}
}