{
  "type": "Feature",
  "properties": {
    "iso:country":"DE",
    "sg:address":"Nagelschmiedstr. 2",
    "sg:city":"Neu\u00f6tting",
    "sg:phone":"+49 8671/3039",
    "sg:postcode":"84524",
    "sg:province":"Bayern",
    "wof:name":"Metall-glasbau Ibsch Gmbh",
    "wof:placetype":"venue"
},
  "geometry": {"coordinates":[12.7061195374,48.2409133911],"type":"Point"}
}