{
  "type": "Feature",
  "properties": {
    "iso:country":"DE",
    "sg:address":"Kapuzinerweg 12",
    "sg:city":"Kleinmachnow",
    "sg:phone":"+49 33203/70057",
    "sg:postcode":"14532",
    "sg:province":"Brandenburg",
    "wof:name":"Just Talk Software- Entwicklungsges. Mbh",
    "wof:placetype":"venue"
},
  "geometry": {"coordinates":[13.238120079,52.4145889282],"type":"Point"}
}