{
  "type": "Feature",
  "properties": {
    "iso:country":"DE",
    "sg:address":"Rintelner Str. 15",
    "sg:city":"Porta Westfalica",
    "sg:phone":"+49 571/71714",
    "sg:postcode":"32457",
    "sg:province":"Nordrhein-Westfalen",
    "wof:name":"Marianne Schmeding",
    "wof:placetype":"venue"
},
  "geometry": {"coordinates":[8.9809350967,52.2588768005],"type":"Point"}
}