{
  "type": "Feature",
  "properties": {
    "iso:country":"DE",
    "sg:address":"G\u00f6ttweiger Str. 46",
    "sg:city":"Passau",
    "sg:phone":"+49 851/35301",
    "sg:postcode":"94032",
    "sg:province":"Bayern",
    "wof:name":"Ambassador-club Passau Bernd D\u00e4mmrich",
    "wof:placetype":"venue"
},
  "geometry": {"coordinates":[13.4870014191,48.5681610107],"type":"Point"}
}