{
  "type": "Feature",
  "properties": {
    "iso:country":"DE",
    "sg:address":"Wingertstr. 20",
    "sg:city":"Langenselbold",
    "sg:phone":"+49 6184/63474",
    "sg:postcode":"63505",
    "sg:province":"Hessen",
    "wof:name":"Karl Kaufmann Schlosserei Und Industriebedarf Gmbh",
    "wof:placetype":"venue"
},
  "geometry": {"coordinates":[9.048169,50.17783],"type":"Point"}
}