{
  "type": "Feature",
  "properties": {
    "iso:country":"DE",
    "sg:address":"Holzhauser Str. 33",
    "sg:city":"Utting",
    "sg:phone":"+49 8806/7543",
    "sg:postcode":"86919",
    "sg:province":"Bayern",
    "wof:name":"Hermann Kammerl",
    "wof:placetype":"venue"
},
  "geometry": {"coordinates":[11.0885009766,48.0193634033],"type":"Point"}
}