{
  "type": "Feature",
  "properties": {
    "iso:country":"DE",
    "sg:address":"H\u00fcnersdorfstr. 16",
    "sg:city":"Gotha",
    "sg:phone":"+49 3621/853639",
    "sg:postcode":"99867",
    "sg:province":"Th\u00fcringen",
    "wof:name":"Arno Schwabe",
    "wof:placetype":"venue"
},
  "geometry": {"coordinates":[10.7031564713,50.9490242004],"type":"Point"}
}