{
  "type": "Feature",
  "properties": {
    "iso:country":"DE",
    "sg:address":"Sch\u00f6nh\u00f6her Weg 18",
    "sg:city":"Tauer",
    "sg:phone":"+49 35601/30321",
    "sg:postcode":"03185",
    "sg:province":"Brandenburg",
    "wof:name":"Peitzer \u00d6ko-dienste Gmbh",
    "wof:placetype":"venue"
},
  "geometry": {"coordinates":[14.4501695633,51.899520874],"type":"Point"}
}