{
  "type": "Feature",
  "properties": {
    "iso:country":"DE",
    "sg:address":"Hauptstr. 15",
    "sg:city":"Burgebrach",
    "sg:phone":"+49 9546/592516",
    "sg:postcode":"96138",
    "sg:province":"Bayern",
    "wof:name":"Steffen Neubauer",
    "wof:placetype":"venue"
},
  "geometry": {"coordinates":[10.7407855988,49.8282852173],"type":"Point"}
}