{
  "type": "Feature",
  "properties": {
    "iso:country":"DE",
    "sg:address":"Borbecker Str. 60",
    "sg:city":"Oberhausen",
    "sg:phone":"+49 208/690350",
    "sg:postcode":"46145",
    "sg:province":"Nordrhein-Westfalen",
    "wof:name":"Gerd Kr\u00fcger Steuerberater",
    "wof:placetype":"venue"
},
  "geometry": {"coordinates":[6.8574829102,51.5099029541],"type":"Point"}
}