{
  "type": "Feature",
  "properties": {
    "iso:country":"DE",
    "sg:address":"K\u00f6nigsberger Str. 1",
    "sg:city":"Butzbach",
    "sg:phone":"+49 6033/65309",
    "sg:postcode":"35510",
    "sg:province":"Hessen",
    "wof:name":"Herbert Lindner",
    "wof:placetype":"venue"
},
  "geometry": {"coordinates":[8.6568632126,50.4357223511],"type":"Point"}
}