{
  "type": "Feature",
  "properties": {
    "iso:country":"DE",
    "sg:address":"Celosstr. 30",
    "sg:city":"Emden",
    "sg:phone":"+49 4921/42906",
    "sg:postcode":"26721",
    "sg:province":"Niedersachsen",
    "wof:name":"Wilhelm Rinderhagen",
    "wof:placetype":"venue"
},
  "geometry": {"coordinates":[7.2080302238,53.3760490417],"type":"Point"}
}