{
  "type": "Feature",
  "properties": {
    "iso:country":"DE",
    "sg:address":"Braunschweiger Tor 6-7",
    "sg:city":"Helmstedt",
    "sg:postcode":"38350",
    "sg:province":"Niedersachsen",
    "wof:name":"Cbo Gmbh & Co. Kg",
    "wof:placetype":"venue"
},
  "geometry": {"coordinates":[10.9997615814,52.2292938232],"type":"Point"}
}