{
  "type": "Feature",
  "properties": {
    "iso:country":"DE",
    "sg:address":"Landweg 3",
    "sg:city":"Holzwickede",
    "sg:phone":"+49 2301/3090",
    "sg:postcode":"59439",
    "sg:province":"Nordrhein-Westfalen",
    "wof:name":"H. Hunscher Edv-beratung Gmbh",
    "wof:placetype":"venue"
},
  "geometry": {"coordinates":[7.6229667664,51.4891967773],"type":"Point"}
}