{
  "type": "Feature",
  "properties": {
    "iso:country":"DE",
    "sg:address":"Gereonstr. 7",
    "sg:city":"Viersen",
    "sg:phone":"+49 2162/29019",
    "sg:postcode":"41747",
    "sg:province":"Nordrhein-Westfalen",
    "wof:name":"Taxi-mietwagen Verein E. V.",
    "wof:placetype":"venue"
},
  "geometry": {"coordinates":[6.39614,51.252483],"type":"Point"}
}