{
  "type": "Feature",
  "properties": {
    "iso:country":"DE",
    "sg:address":"Wenzelstr. 2",
    "sg:city":"M\u00fcnchen",
    "sg:phone":"+49 89/3112531",
    "sg:postcode":"80937",
    "sg:province":"Bayern",
    "wof:name":"Pils-farm",
    "wof:placetype":"venue"
},
  "geometry": {"coordinates":[11.5837678909,48.1977157593],"type":"Point"}
}