{
  "type": "Feature",
  "properties": {
    "iso:country":"DE",
    "sg:address":"Parkstr. 1",
    "sg:city":"Bad Pyrmont",
    "sg:postcode":"31812",
    "sg:province":"Niedersachsen",
    "wof:name":"Drs Papier- Und Zellstoffhandel Gmbh",
    "wof:placetype":"venue"
},
  "geometry": {"coordinates":[9.2514476776,51.9828109741],"type":"Point"}
}