{
  "type": "Feature",
  "properties": {
    "iso:country":"DE",
    "sg:address":"Brunhildenstr. 30 B",
    "sg:city":"Neubiberg",
    "sg:phone":"+49 89/6888937",
    "sg:postcode":"85579",
    "sg:province":"Bayern",
    "wof:name":"Cinecomp Elektro Gmbh",
    "wof:placetype":"venue"
},
  "geometry": {"coordinates":[11.681544,48.077374],"type":"Point"}
}