{
  "type": "Feature",
  "properties": {
    "iso:country":"DE",
    "sg:address":"Schachtstr. 2",
    "sg:city":"Freital",
    "sg:phone":"+49 351/6491013",
    "sg:postcode":"01705",
    "sg:province":"Sachsen",
    "wof:name":"Freitaler Reise-eck",
    "wof:placetype":"venue"
},
  "geometry": {"coordinates":[13.6524677277,51.0024223328],"type":"Point"}
}