{
  "type": "Feature",
  "properties": {
    "iso:country":"DE",
    "sg:address":"Ostring 19",
    "sg:city":"Fuldabr\u00fcck",
    "sg:phone":"+49 561/959660",
    "sg:postcode":"34277",
    "sg:province":"Hessen",
    "wof:name":"Brendel Organisations- Gmbh & Co. Betriebs Kg",
    "wof:placetype":"venue"
},
  "geometry": {"coordinates":[9.4968967438,51.2724494934],"type":"Point"}
}