{
  "type": "Feature",
  "properties": {
    "iso:country":"DE",
    "sg:address":"Hermann-Schomburg-Str. 1",
    "sg:city":"Gro\u00dfdubrau",
    "sg:phone":"+49 35934/4528",
    "sg:postcode":"02694",
    "sg:province":"Sachsen",
    "wof:name":"Schugru Schuster Und Grundmann Gmbh",
    "wof:placetype":"venue"
},
  "geometry": {"coordinates":[14.453830719,51.2555656433],"type":"Point"}
}