{
  "type": "Feature",
  "properties": {
    "iso:country":"DE",
    "sg:address":"Vorsalzer Str. 26",
    "sg:city":"Salzgitter",
    "sg:phone":"+49 5341/391781",
    "sg:postcode":"38259",
    "sg:province":"Niedersachsen",
    "wof:name":"Altstadt Schenke",
    "wof:placetype":"venue"
},
  "geometry": {"coordinates":[10.3735046387,52.0492210388],"type":"Point"}
}