{
  "type": "Feature",
  "properties": {
    "iso:country":"DE",
    "sg:address":"Sandstra\u00dfe 162",
    "sg:city":"Frechen",
    "sg:phone":"+49 2234/278072",
    "sg:postcode":"50226",
    "sg:province":"Nordrhein-Westfalen",
    "wof:name":"Kontakthaus 2000 - Der Internetkontakter",
    "wof:placetype":"venue"
},
  "geometry": {"coordinates":[6.793538,50.90382],"type":"Point"}
}