{
  "type": "Feature",
  "properties": {
    "iso:country":"DE",
    "sg:address":"Klosterstr. 5",
    "sg:city":"Himmelpfort",
    "sg:phone":"+49 33089/41364",
    "sg:postcode":"16798",
    "sg:province":"Brandenburg",
    "wof:name":"J\u00fcrgen Galle Ingenieur",
    "wof:placetype":"venue"
},
  "geometry": {"coordinates":[13.2275695801,53.178150177],"type":"Point"}
}