{
  "type": "Feature",
  "properties": {
    "iso:country":"DE",
    "sg:address":"Cloppenburger Str. 436",
    "sg:city":"Oldenburg",
    "sg:phone":"+49 441/43282",
    "sg:postcode":"26133",
    "sg:province":"Niedersachsen",
    "wof:name":"China-restaurant Mekong Garden",
    "wof:placetype":"venue"
},
  "geometry": {"coordinates":[8.2060709,53.1053581238],"type":"Point"}
}