{
  "type": "Feature",
  "properties": {
    "iso:country":"DE",
    "sg:address":"Ulrichstr. 28",
    "sg:city":"Berglen",
    "sg:phone":"+49 7195/983010",
    "sg:postcode":"73663",
    "sg:province":"Baden-W\u00fcrttemberg",
    "wof:name":"Ifb Ingenieurgesellschaft F\u00fcr Bauphysik Und",
    "wof:placetype":"venue"
},
  "geometry": {"coordinates":[9.4684114456,48.854347229],"type":"Point"}
}