{
  "type": "Feature",
  "properties": {
    "iso:country":"DE",
    "sg:address":"Bornstr. 10",
    "sg:city":"Dortmund",
    "sg:phone":"+49 231/525623",
    "sg:postcode":"44135",
    "sg:province":"Nordrhein-Westfalen",
    "wof:name":"G\u00fcnter P\u00fctter",
    "wof:placetype":"venue"
},
  "geometry": {"coordinates":[7.4690918922,51.5178108215],"type":"Point"}
}