{
  "type": "Feature",
  "properties": {
    "iso:country":"DE",
    "sg:address":"Allmand 7",
    "sg:city":"Forchtenberg",
    "sg:phone":"+49 7947/2055",
    "sg:postcode":"74670",
    "sg:province":"Baden-W\u00fcrttemberg",
    "wof:name":"Heinrich Lindkamp Gmbh",
    "wof:placetype":"venue"
},
  "geometry": {"coordinates":[9.56397,49.290863],"type":"Point"}
}