{
  "type": "Feature",
  "properties": {
    "iso:country":"DE",
    "sg:address":"Lange Str. 30",
    "sg:city":"Hilter",
    "sg:phone":"+49 5424/23068",
    "sg:postcode":"49176",
    "sg:province":"Niedersachsen",
    "wof:name":"Tappmeyer Fleischwaren Gmbh",
    "wof:placetype":"venue"
},
  "geometry": {"coordinates":[8.1458797455,52.1392211914],"type":"Point"}
}