{
  "type": "Feature",
  "properties": {
    "iso:country":"DE",
    "sg:address":"Berliner Ring 65",
    "sg:city":"T\u00fcbingen",
    "sg:phone":"+49 7071/65556",
    "sg:postcode":"72076",
    "sg:province":"Baden-W\u00fcrttemberg",
    "wof:name":"Naturkostladen Im Schafbr\u00fchl Gmbh",
    "wof:placetype":"venue"
},
  "geometry": {"coordinates":[9.0564460754,48.5443382263],"type":"Point"}
}