{
  "type": "Feature",
  "properties": {
    "iso:country":"DE",
    "sg:address":"Friedrich-Alfred-Str. 102",
    "sg:city":"Duisburg",
    "sg:postcode":"47226",
    "sg:province":"Nordrhein-Westfalen",
    "wof:name":"Brasserie Inh. M. Niksic",
    "wof:placetype":"venue"
},
  "geometry": {"coordinates":[6.7180938721,51.408416748],"type":"Point"}
}