{
  "type": "Feature",
  "properties": {
    "iso:country":"DE",
    "sg:address":"Kuseyer Str. 1",
    "sg:city":"Neuferchau",
    "sg:phone":"+49 39008/761",
    "sg:postcode":"38486",
    "sg:province":"Sachsen-Anhalt",
    "wof:name":"Hotel Landhaus Birkenmoor",
    "wof:placetype":"venue"
},
  "geometry": {"coordinates":[11.0712394714,52.5743865967],"type":"Point"}
}