{
  "type": "Feature",
  "properties": {
    "iso:country":"DE",
    "sg:address":"Polcher Str. 54",
    "sg:city":"Mayen",
    "sg:phone":"+49 2651/1695",
    "sg:postcode":"56727",
    "sg:province":"Rheinland-Pfalz",
    "wof:name":"Skanditex Gmbh",
    "wof:placetype":"venue"
},
  "geometry": {"coordinates":[7.225727,50.324745],"type":"Point"}
}