{
  "type": "Feature",
  "properties": {
    "iso:country":"DE",
    "sg:address":"Postfach 1521",
    "sg:city":"Landau i. d. Pfalz",
    "sg:phone":"+49 6341/960954",
    "sg:postcode":"76805",
    "wof:name":"Hp-online - Karriere Und Mehr",
    "wof:placetype":"venue"
},
  "geometry": {"coordinates":[8.1128797531,49.1935081482],"type":"Point"}
}