{
  "type": "Feature",
  "properties": {
    "iso:country":"DE",
    "sg:address":"Justus-von-Liebig-Str. 27",
    "sg:city":"Gro\u00df-Bieberau",
    "sg:phone":"+49 6162/94050",
    "sg:postcode":"64401",
    "sg:province":"Hessen",
    "wof:name":"Walter Liebig Gmbh",
    "wof:placetype":"venue"
},
  "geometry": {"coordinates":[8.823885,49.805107],"type":"Point"}
}