{
  "type": "Feature",
  "properties": {
    "iso:country":"DE",
    "sg:address":"Gifhorner Str. 26",
    "sg:city":"Uetze",
    "sg:phone":"+49 5173/452",
    "sg:postcode":"31311",
    "sg:province":"Niedersachsen",
    "wof:name":"Wolfgang Bode",
    "wof:placetype":"venue"
},
  "geometry": {"coordinates":[10.2142763138,52.4706726074],"type":"Point"}
}