{
  "type": "Feature",
  "properties": {
    "iso:country":"DE",
    "sg:address":"Seeoner Str. 14",
    "sg:city":"Pittenhart",
    "sg:phone":"+49 8624/1221",
    "sg:postcode":"83132",
    "sg:province":"Bayern",
    "wof:name":"G. Steffens",
    "wof:placetype":"venue"
},
  "geometry": {"coordinates":[12.418034,47.964115],"type":"Point"}
}