{
  "type": "Feature",
  "properties": {
    "iso:country":"DE",
    "sg:address":"Auf dem Hardt 25",
    "sg:city":"Seewald",
    "sg:phone":"+49 7448/406",
    "sg:postcode":"72297",
    "sg:province":"Baden-W\u00fcrttemberg",
    "wof:name":"G\u00e4stehaus Keppler",
    "wof:placetype":"venue"
},
  "geometry": {"coordinates":[8.4819049835,48.5596656799],"type":"Point"}
}