{
  "type": "Feature",
  "properties": {
    "iso:country":"DE",
    "sg:address":"S\u00fcdbahnstr. 18",
    "sg:city":"Neubrandenburg",
    "sg:phone":"+49 395/5443205",
    "sg:postcode":"17033",
    "sg:province":"Mecklenburg-Vorpommern",
    "wof:name":"Gastroline Seelow Gmbh",
    "wof:placetype":"venue"
},
  "geometry": {"coordinates":[13.257847,53.561405],"type":"Point"}
}