{
  "type": "Feature",
  "properties": {
    "iso:country":"DE",
    "sg:address":"Heinrichstr. 71",
    "sg:city":"Bochum",
    "sg:postcode":"44805",
    "sg:province":"Nordrhein-Westfalen",
    "wof:name":"Imb Consult Gmbh",
    "wof:placetype":"venue"
},
  "geometry": {"coordinates":[7.2821798325,51.5164108276],"type":"Point"}
}