{
  "type": "Feature",
  "properties": {
    "iso:country":"DE",
    "sg:address":"Lange Str. 51",
    "sg:city":"Cloppenburg",
    "sg:phone":"+49 4471/81818",
    "sg:postcode":"49661",
    "sg:province":"Niedersachsen",
    "wof:name":"Heinz Lehmann",
    "wof:placetype":"venue"
},
  "geometry": {"coordinates":[8.038973,52.844456],"type":"Point"}
}