{
  "type": "Feature",
  "properties": {
    "iso:country":"DE",
    "sg:address":"Mainzweilerstr. 24",
    "sg:city":"St. Wendel",
    "sg:phone":"+49 6851/6104",
    "sg:postcode":"66606",
    "sg:province":"Saarland",
    "wof:name":"Hans Federkeil Gmbh",
    "wof:placetype":"venue"
},
  "geometry": {"coordinates":[7.1240291595,49.4365882874],"type":"Point"}
}