{
  "type": "Feature",
  "properties": {
    "iso:country":"DE",
    "sg:city":"Berlin",
    "sg:postcode":"13629",
    "sg:province":"Berlin",
    "wof:name":"Dataways Hochzeitsservice",
    "wof:placetype":"venue"
},
  "geometry": {"coordinates":[13.26413,52.538204],"type":"Point"}
}