{
  "type": "Feature",
  "properties": {
    "iso:country":"DE",
    "sg:address":"Altenaer Str. 174b",
    "sg:city":"L\u00fcdenscheid",
    "sg:phone":"+49 4923/5153711",
    "sg:postcode":"58513",
    "sg:province":"Nordrhein-Westfalen",
    "wof:name":"Michael Motzkus",
    "wof:placetype":"venue"
},
  "geometry": {"coordinates":[7.621979,51.243397],"type":"Point"}
}