{
  "type": "Feature",
  "properties": {
    "iso:country":"DE",
    "sg:address":"Tannenbergstr. 11",
    "sg:city":"N\u00fcrnberg",
    "sg:phone":"+49 911/522373",
    "sg:postcode":"90411",
    "sg:province":"Bayern",
    "wof:name":"Vorstadtverein N\u00fcrnberg- Nord E. V.",
    "wof:placetype":"venue"
},
  "geometry": {"coordinates":[11.1106557846,49.4875411987],"type":"Point"}
}