{
  "type": "Feature",
  "properties": {
    "iso:country":"DE",
    "sg:address":"Rietgasse 20",
    "sg:city":"Villingen-Schwenningen",
    "sg:phone":"+49 7721/92880",
    "sg:postcode":"78050",
    "sg:province":"Baden-W\u00fcrttemberg",
    "wof:name":"Franz Blaser Architekt",
    "wof:placetype":"venue"
},
  "geometry": {"coordinates":[8.45774,48.05777],"type":"Point"}
}