{
  "type": "Feature",
  "properties": {
    "iso:country":"DE",
    "sg:address":"Bahnhofstr. 15",
    "sg:city":"Schutterwald",
    "sg:phone":"+49 781/57792",
    "sg:postcode":"77746",
    "sg:province":"Baden-W\u00fcrttemberg",
    "wof:name":"Petra Kiefer",
    "wof:placetype":"venue"
},
  "geometry": {"coordinates":[7.888439,48.456402],"type":"Point"}
}