{
  "type": "Feature",
  "properties": {
    "iso:country":"DE",
    "sg:address":"Postfach 801109",
    "sg:city":"M\u00fcnchen",
    "sg:phone":"+49 89/4705369",
    "sg:postcode":"81663",
    "sg:province":"Bayern",
    "wof:name":"Dadc Luft- Und Raumfahrt Beteiligungs Ag",
    "wof:placetype":"venue"
},
  "geometry": {"coordinates":[11.58027,48.139099],"type":"Point"}
}