{
  "type": "Feature",
  "properties": {
    "iso:country":"DE",
    "sg:address":"Hammerstr. 15a",
    "sg:city":"Simmerath",
    "sg:phone":"+49 2473/6321",
    "sg:postcode":"52152",
    "sg:province":"Nordrhein-Westfalen",
    "wof:name":"G. Reitz",
    "wof:placetype":"venue"
},
  "geometry": {"coordinates":[6.355388,50.583923],"type":"Point"}
}