{
  "type": "Feature",
  "properties": {
    "iso:country":"DE",
    "sg:address":"Wittener Str. 52",
    "sg:city":"Castrop-Rauxel",
    "sg:phone":"+49 2305/24209",
    "sg:postcode":"44575",
    "sg:province":"Nordrhein-Westfalen",
    "wof:name":"Horst Schwarz",
    "wof:placetype":"venue"
},
  "geometry": {"coordinates":[7.3143677711,51.5462265015],"type":"Point"}
}