{
  "type": "Feature",
  "properties": {
    "iso:country":"DE",
    "sg:address":"Marktplatz 3",
    "sg:city":"Esslingen",
    "sg:phone":"+49 711/522237",
    "sg:postcode":"73728",
    "sg:province":"Baden-W\u00fcrttemberg",
    "wof:name":"Bistro Am Markt",
    "wof:placetype":"venue"
},
  "geometry": {"coordinates":[9.3065595627,48.7430763245],"type":"Point"}
}