{
  "type": "Feature",
  "properties": {
    "iso:country":"DE",
    "sg:address":"Lindenstr. 63",
    "sg:city":"Sandberg",
    "sg:phone":"+49 9701/390",
    "sg:postcode":"97657",
    "sg:province":"Bayern",
    "wof:name":"Willi Hauck",
    "wof:placetype":"venue"
},
  "geometry": {"coordinates":[9.978704,50.328758],"type":"Point"}
}