{
  "type": "Feature",
  "properties": {
    "iso:country":"DE",
    "sg:address":"Fr\u00f6belstr. 18",
    "sg:city":"Gr\u00f6ditz",
    "sg:phone":"+49 35263",
    "sg:postcode":"01609",
    "sg:province":"Sachsen",
    "wof:name":"Onlinekont@ktboerse - Die Kontaktboerse F\u00fcr Jeden.",
    "wof:placetype":"venue"
},
  "geometry": {"coordinates":[13.452517,51.414478],"type":"Point"}
}