{
  "type": "Feature",
  "properties": {
    "iso:country":"DE",
    "sg:address":"Johannishof",
    "sg:city":"Oberhaid",
    "sg:phone":"+49 9573/31655",
    "sg:postcode":"96173",
    "sg:province":"Bayern",
    "wof:name":"Dagmar Vogt Heilpraktiker",
    "wof:placetype":"venue"
},
  "geometry": {"coordinates":[10.8346242905,49.9407615662],"type":"Point"}
}