{
  "type": "Feature",
  "properties": {
    "iso:country":"DE",
    "sg:address":"Steinbachstr. 14",
    "sg:city":"Halle",
    "sg:phone":"+49 5201/3450",
    "sg:postcode":"33790",
    "sg:province":"Nordrhein-Westfalen",
    "wof:name":"Fritz Sch\u00f6ning",
    "wof:placetype":"venue"
},
  "geometry": {"coordinates":[8.266278,52.011028],"type":"Point"}
}