{
  "type": "Feature",
  "properties": {
    "iso:country":"DE",
    "sg:address":"Estermannstr. 157",
    "sg:city":"Bonn",
    "sg:phone":"+49 228/687201",
    "sg:postcode":"53117",
    "sg:province":"Nordrhein-Westfalen",
    "wof:name":"Sozialhilfeverein H\u00e4ste Nix- Kreste Nix E. V.",
    "wof:placetype":"venue"
},
  "geometry": {"coordinates":[7.0789899826,50.7626991272],"type":"Point"}
}