{
  "type": "Feature",
  "properties": {
    "iso:country":"DE",
    "sg:address":"Magnolienweg 2a",
    "sg:city":"M\u00fcnchen",
    "sg:phone":"+49 89/7149864",
    "sg:postcode":"81377",
    "sg:province":"Bayern",
    "wof:name":"I. Kopecky \u00dcbersetzer",
    "wof:placetype":"venue"
},
  "geometry": {"coordinates":[11.49168,48.112148],"type":"Point"}
}