{
  "type": "Feature",
  "properties": {
    "iso:country":"DE",
    "sg:address":"G\u00fcldenstr. 45",
    "sg:city":"Braunschweig",
    "sg:phone":"+49 531/16031",
    "sg:postcode":"38100",
    "sg:province":"Niedersachsen",
    "wof:name":"Baugesellschaft Strauch Und Hein Kg",
    "wof:placetype":"venue"
},
  "geometry": {"coordinates":[10.5144424438,52.2655143738],"type":"Point"}
}