{
  "type": "Feature",
  "properties": {
    "iso:country":"DE",
    "sg:address":"Aulendorfer Str. 37",
    "sg:city":"Bad Schussenried",
    "sg:phone":"+49 7583/3287",
    "sg:postcode":"88427",
    "sg:province":"Baden-W\u00fcrttemberg",
    "wof:name":"Sieben Schwaben-keller",
    "wof:placetype":"venue"
},
  "geometry": {"coordinates":[9.655976,48.001099],"type":"Point"}
}