{
  "type": "Feature",
  "properties": {
    "iso:country":"DE",
    "sg:address":"Hinter der Burg 6",
    "sg:city":"Bad Wurzach",
    "sg:phone":"+49 7568/1776",
    "sg:postcode":"88410",
    "sg:province":"Baden-W\u00fcrttemberg",
    "wof:name":"O. Gueter",
    "wof:placetype":"venue"
},
  "geometry": {"coordinates":[9.9858894348,47.946056366],"type":"Point"}
}