{
  "type": "Feature",
  "properties": {
    "iso:country":"DE",
    "sg:address":"Schweinfurter Str. 36",
    "sg:city":"Gochsheim",
    "sg:phone":"+49 9721/62424",
    "sg:postcode":"97469",
    "sg:province":"Bayern",
    "wof:name":"Apotheke Stenger",
    "wof:placetype":"venue"
},
  "geometry": {"coordinates":[10.281301,50.0214],"type":"Point"}
}