{
  "type": "Feature",
  "properties": {
    "iso:country":"DE",
    "sg:address":"Salierstr. 22",
    "sg:city":"Pforzheim",
    "sg:phone":"+49 7231/32024",
    "sg:postcode":"75177",
    "sg:province":"Baden-W\u00fcrttemberg",
    "wof:name":"Pizza Fontana",
    "wof:placetype":"venue"
},
  "geometry": {"coordinates":[8.7027130127,48.8964309692],"type":"Point"}
}