{
  "type": "Feature",
  "properties": {
    "iso:country":"DE",
    "sg:address":"Fabrikstr. 16",
    "sg:city":"Roigheim",
    "sg:phone":"+49 6298/1373",
    "sg:postcode":"74255",
    "sg:province":"Baden-W\u00fcrttemberg",
    "wof:name":"E. Bechtold Gmbh & Co.",
    "wof:placetype":"venue"
},
  "geometry": {"coordinates":[9.3383607864,49.3647041321],"type":"Point"}
}