{
  "type": "Feature",
  "properties": {
    "iso:country":"DE",
    "sg:address":"R\u00f6merstr. 28",
    "sg:city":"Bad Sch\u00f6nborn",
    "sg:phone":"+49 7253/954770",
    "sg:postcode":"76669",
    "sg:province":"Baden-W\u00fcrttemberg",
    "wof:name":"J\u00fcrgen G. Koriath Heilpraktiker",
    "wof:placetype":"venue"
},
  "geometry": {"coordinates":[8.642598,49.200592],"type":"Point"}
}