{
  "type": "Feature",
  "properties": {
    "iso:country":"DE",
    "sg:address":"G\u00f6rlitzstr. 37",
    "sg:city":"Braunschweig",
    "sg:phone":"+49 531/602753",
    "sg:postcode":"38124",
    "sg:province":"Niedersachsen",
    "wof:name":"Hermann Architekt",
    "wof:placetype":"venue"
},
  "geometry": {"coordinates":[10.523524,52.230751],"type":"Point"}
}