{
  "type": "Feature",
  "properties": {
    "iso:country":"DE",
    "sg:address":"Ziegelstr. 26",
    "sg:city":"Frankfurt",
    "sg:phone":"+49 335/6851362",
    "sg:postcode":"15230",
    "sg:province":"Brandenburg",
    "wof:name":"Huwe",
    "wof:placetype":"venue"
},
  "geometry": {"coordinates":[14.5543203354,52.3416786194],"type":"Point"}
}