{
  "type": "Feature",
  "properties": {
    "iso:country":"DE",
    "sg:address":"Am M\u00fchlgrund 4",
    "sg:city":"P\u00f6ttmes",
    "sg:phone":"+49 8253/6650",
    "sg:postcode":"86554",
    "sg:province":"Bayern",
    "wof:name":"P. Treffler Jun.",
    "wof:placetype":"venue"
},
  "geometry": {"coordinates":[11.013337,48.601097],"type":"Point"}
}