{
  "type": "Feature",
  "properties": {
    "iso:country":"DE",
    "sg:address":"Hemmendorfer Str.",
    "sg:city":"Salzhemmendorf",
    "sg:phone":"+49 5153/5969",
    "sg:postcode":"31020",
    "sg:province":"Niedersachsen",
    "wof:name":"Cafe Restaurant Okal",
    "wof:placetype":"venue"
},
  "geometry": {"coordinates":[9.572725296,52.0797691345],"type":"Point"}
}