{
  "type": "Feature",
  "properties": {
    "iso:country":"DE",
    "sg:address":"F\u00fcrstenstr. 46",
    "sg:city":"Reichenbach",
    "sg:phone":"+49 7153/58734",
    "sg:postcode":"73262",
    "sg:province":"Baden-W\u00fcrttemberg",
    "wof:name":"J\u00fcrgen Seidel",
    "wof:placetype":"venue"
},
  "geometry": {"coordinates":[9.4581165314,48.7098846436],"type":"Point"}
}