{
  "type": "Feature",
  "properties": {
    "iso:country":"DE",
    "sg:address":"Unter dem Berg 10",
    "sg:city":"Kaufbeuren",
    "sg:phone":"+49 8341/14004",
    "sg:postcode":"87600",
    "sg:province":"Bayern",
    "wof:name":"P. Huber",
    "wof:placetype":"venue"
},
  "geometry": {"coordinates":[10.618158,47.880791],"type":"Point"}
}