{
  "type": "Feature",
  "properties": {
    "iso:country":"DE",
    "sg:address":"Haardthofstr 1",
    "sg:city":"Schweich",
    "sg:phone":"+49 6502/91670",
    "sg:postcode":"54338",
    "sg:province":"Rheinland-Pfalz",
    "wof:name":"Johann Trossen Gmbh",
    "wof:placetype":"venue"
},
  "geometry": {"coordinates":[6.7258458138,49.8257331848],"type":"Point"}
}