{
  "type": "Feature",
  "properties": {
    "iso:country":"DE",
    "sg:address":"Dieselstr. 35",
    "sg:city":"Offenbach",
    "sg:phone":"+49 69/98542200",
    "sg:postcode":"63071",
    "sg:province":"Hessen",
    "wof:name":"Joh. W. Schimmel Technische Gro\u00dfhandlung Gmbh",
    "wof:placetype":"venue"
},
  "geometry": {"coordinates":[8.792355,50.101654],"type":"Point"}
}