{
  "type": "Feature",
  "properties": {
    "iso:country":"DE",
    "sg:address":"Gro\u00dfe Bockenheimer Str.6",
    "sg:city":"Frankfurt",
    "sg:phone":"+49 172 6903196",
    "sg:postcode":"60313",
    "sg:province":"Hessen",
    "wof:name":"Human Consult",
    "wof:placetype":"venue"
},
  "geometry": {"coordinates":[8.675771,50.114128],"type":"Point"}
}