{
  "type": "Feature",
  "properties": {
    "iso:country":"DE",
    "sg:address":"Poststr 22",
    "sg:city":"Rochlitz",
    "sg:phone":"+49 3737/149011",
    "sg:postcode":"09306",
    "sg:province":"Sachsen",
    "wof:name":"Schilderdienst Gr\u00e4nz Gmbh",
    "wof:placetype":"venue"
},
  "geometry": {"coordinates":[12.795047,51.047565],"type":"Point"}
}