{
  "type": "Feature",
  "properties": {
    "iso:country":"DE",
    "sg:address":"Reschstr. 2 b",
    "sg:city":"M\u00fcnchen",
    "sg:phone":"+49 89/429993",
    "sg:postcode":"81825",
    "sg:province":"Bayern",
    "wof:name":"G. Irlbeck",
    "wof:placetype":"venue"
},
  "geometry": {"coordinates":[11.670938,48.118626],"type":"Point"}
}