{
  "type": "Feature",
  "properties": {
    "iso:country":"DE",
    "sg:address":"Weender Landstr. 46",
    "sg:city":"G\u00f6ttingen",
    "sg:phone":"+49 551/4955160",
    "sg:postcode":"37073",
    "sg:province":"Niedersachsen",
    "wof:name":"Flyer Kommunikationsges. Mbh",
    "wof:placetype":"venue"
},
  "geometry": {"coordinates":[9.9354391098,51.5341873169],"type":"Point"}
}