{
  "type": "Feature",
  "properties": {
    "iso:country":"DE",
    "sg:address":"Sauertalstr. 18",
    "sg:city":"Montabaur",
    "sg:phone":"+49 2602/120298",
    "sg:postcode":"56410",
    "sg:province":"Rheinland-Pfalz",
    "wof:name":"Schlag & Rottke Gmbh",
    "wof:placetype":"venue"
},
  "geometry": {"coordinates":[7.8342208862,50.4366950989],"type":"Point"}
}