{
  "type": "Feature",
  "properties": {
    "iso:country":"DE",
    "sg:address":"St.-Anna-Str. 13",
    "sg:city":"Rascheid",
    "sg:phone":"+49 6586/1616",
    "sg:postcode":"54413",
    "sg:province":"Rheinland-Pfalz",
    "wof:name":"Jahnen Gmbh",
    "wof:placetype":"venue"
},
  "geometry": {"coordinates":[6.935251,49.714527],"type":"Point"}
}