{
  "type": "Feature",
  "properties": {
    "iso:country":"DE",
    "sg:address":"Herseler Str. 31",
    "sg:city":"Wesseling",
    "sg:phone":"+49 2236/44275",
    "sg:postcode":"50389",
    "sg:province":"Nordrhein-Westfalen",
    "wof:name":"Wesselinger Fliesen- Handel J\u00fclich",
    "wof:placetype":"venue"
},
  "geometry": {"coordinates":[6.9915809631,50.8045768738],"type":"Point"}
}