{
  "type": "Feature",
  "properties": {
    "iso:country":"DE",
    "sg:address":"Mundersumer Weg 1",
    "sg:city":"Messingen",
    "sg:phone":"+49 5905/1242",
    "sg:postcode":"49832",
    "sg:province":"Niedersachsen",
    "wof:name":"Bernhard Wobbe",
    "wof:placetype":"venue"
},
  "geometry": {"coordinates":[7.424994,52.477814],"type":"Point"}
}