{
  "type": "Feature",
  "properties": {
    "iso:country":"DE",
    "sg:address":"Ganghoferstr. 15",
    "sg:city":"Bad Aibling",
    "sg:phone":"+49 8061/49040",
    "sg:postcode":"83043",
    "sg:province":"Bayern",
    "wof:name":"Kai Sch\u00e4fer Rechtsanwalt",
    "wof:placetype":"venue"
},
  "geometry": {"coordinates":[12.0143995285,47.8556365967],"type":"Point"}
}