{
  "type": "Feature",
  "properties": {
    "iso:country":"DE",
    "sg:address":"Parlamentsplatz 4a",
    "sg:city":"Frankfurt",
    "sg:phone":"+49 69/447571",
    "sg:postcode":"60385",
    "sg:province":"Hessen",
    "wof:name":"Lukas-apotheke",
    "wof:placetype":"venue"
},
  "geometry": {"coordinates":[8.714764,50.119919],"type":"Point"}
}