{
  "type": "Feature",
  "properties": {
    "iso:country":"DE",
    "sg:address":"Pinneberger Str. 96",
    "sg:city":"Wedel",
    "sg:phone":"+49 4103/7460",
    "sg:postcode":"22880",
    "sg:province":"Schleswig-Holstein",
    "wof:name":"Rainer Vo\u00df",
    "wof:placetype":"venue"
},
  "geometry": {"coordinates":[9.7087001801,53.5917510986],"type":"Point"}
}