{
  "type": "Feature",
  "properties": {
    "iso:country":"DE",
    "sg:address":"Weinmarkt 6",
    "sg:city":"N\u00f6rdlingen",
    "sg:phone":"+49 9081/29240",
    "sg:postcode":"86720",
    "sg:province":"Bayern",
    "wof:name":"Helmut Stuber Steuerberater",
    "wof:placetype":"venue"
},
  "geometry": {"coordinates":[10.4863777161,48.8501853943],"type":"Point"}
}