{
  "type": "Feature",
  "properties": {
    "iso:country":"DE",
    "sg:address":"Klingbarg 7",
    "sg:city":"Bad Bramstedt",
    "sg:phone":"+49 4192/9537",
    "sg:postcode":"24576",
    "sg:province":"Schleswig-Holstein",
    "wof:name":"Jagodzik Kg",
    "wof:placetype":"venue"
},
  "geometry": {"coordinates":[9.8758354187,53.923828125],"type":"Point"}
}