{
  "type": "Feature",
  "properties": {
    "iso:country":"DE",
    "sg:address":"Marinusstr. 6",
    "sg:city":"Mehring",
    "sg:phone":"+49 6502/6338",
    "sg:postcode":"54346",
    "sg:province":"Rheinland-Pfalz",
    "wof:name":"Iris Diederich Krankengymnastin",
    "wof:placetype":"venue"
},
  "geometry": {"coordinates":[6.829255,49.793324],"type":"Point"}
}