{
  "type": "Feature",
  "properties": {
    "iso:country":"DE",
    "sg:address":"Sandgrube 13",
    "sg:city":"Neunkirchen",
    "sg:phone":"+49 9153/621",
    "sg:postcode":"91233",
    "sg:province":"Bayern",
    "wof:name":"Simon Klimatechnik Gmbh",
    "wof:placetype":"venue"
},
  "geometry": {"coordinates":[11.3367938995,49.5233612061],"type":"Point"}
}