{
  "type": "Feature",
  "properties": {
    "iso:country":"DE",
    "sg:address":"An der Viehtrift 20",
    "sg:city":"Gro\u00df-Gerau",
    "sg:phone":"+49 6152/97610",
    "sg:postcode":"64521",
    "sg:province":"Hessen",
    "wof:name":"B\u00fcro-service Rhein-main",
    "wof:placetype":"venue"
},
  "geometry": {"coordinates":[8.495076,49.936256],"type":"Point"}
}