{
  "type": "Feature",
  "properties": {
    "iso:country":"DE",
    "sg:address":"Hauptstr. 46",
    "sg:city":"Karlskron",
    "sg:phone":"+49 8450/1285",
    "sg:postcode":"85123",
    "sg:province":"Bayern",
    "wof:name":"Walter Dorbert",
    "wof:placetype":"venue"
},
  "geometry": {"coordinates":[11.41215,48.677532],"type":"Point"}
}