{
  "type": "Feature",
  "properties": {
    "iso:country":"DE",
    "sg:address":"Bruckrath 26",
    "sg:city":"Nettetal",
    "sg:phone":"+49 2153/71626",
    "sg:postcode":"41334",
    "sg:province":"Nordrhein-Westfalen",
    "wof:name":"Heinz-josef Kox",
    "wof:placetype":"venue"
},
  "geometry": {"coordinates":[6.234307,51.284565],"type":"Point"}
}