{
  "type": "Feature",
  "properties": {
    "iso:country":"DE",
    "sg:address":"Haldenstr. 4",
    "sg:city":"\u00dcberlingen",
    "sg:phone":"+49 7551/4430",
    "sg:postcode":"88662",
    "sg:province":"Baden-W\u00fcrttemberg",
    "wof:name":"W. H\u00f6hns Tanzschule",
    "wof:placetype":"venue"
},
  "geometry": {"coordinates":[9.1729230881,47.7718811035],"type":"Point"}
}