{
  "type": "Feature",
  "properties": {
    "iso:country":"DE",
    "sg:address":"Holstenstrasse 13-15",
    "sg:city":"Kiel",
    "sg:phone":"+49 431/9710310",
    "sg:postcode":"24103",
    "sg:province":"Schleswig-Holstein",
    "wof:name":"Eurobizz - Marketing For The It-business",
    "wof:placetype":"venue"
},
  "geometry": {"coordinates":[10.138545,54.322407],"type":"Point"}
}