{
  "type": "Feature",
  "properties": {
    "iso:country":"DE",
    "sg:address":"Hermann-Mende-Str. 4",
    "sg:city":"Dresden",
    "sg:phone":"+49 351/8498766",
    "sg:postcode":"01099",
    "sg:province":"Sachsen",
    "wof:name":"Wolfgang K\u00f6nig Gmbh",
    "wof:placetype":"venue"
},
  "geometry": {"coordinates":[13.766803,51.0863],"type":"Point"}
}