{
  "type": "Feature",
  "properties": {
    "iso:country":"DE",
    "sg:address":"Am Spitzlberg 19 a",
    "sg:city":"Baierbrunn",
    "sg:phone":"+49 89/74495950",
    "sg:postcode":"82065",
    "sg:province":"Bayern",
    "wof:name":"Gfe Gesellschaft F\u00fcr Angewandte Elektronik Mbh",
    "wof:placetype":"venue"
},
  "geometry": {"coordinates":[11.4889278412,48.0233535767],"type":"Point"}
}