{
  "type": "Feature",
  "properties": {
    "iso:country":"DE",
    "sg:address":"Obertorstr. 6",
    "sg:city":"Gro\u00df-Umstadt",
    "sg:phone":"+49 6078/911261",
    "sg:postcode":"64823",
    "sg:province":"Hessen",
    "wof:name":"Eric Breunig",
    "wof:placetype":"venue"
},
  "geometry": {"coordinates":[8.9539670944,49.9015350342],"type":"Point"}
}