{
  "type": "Feature",
  "properties": {
    "iso:country":"DE",
    "sg:address":"Biberacherhofstr. 2",
    "sg:city":"Markdorf",
    "sg:phone":"+49 7544/6116",
    "sg:postcode":"88677",
    "sg:province":"Baden-W\u00fcrttemberg",
    "wof:name":"Zoohandlung Prinz",
    "wof:placetype":"venue"
},
  "geometry": {"coordinates":[9.387436,47.721371],"type":"Point"}
}