{
  "type": "Feature",
  "properties": {
    "iso:country":"DE",
    "sg:address":"Kefersteinstr. 3",
    "sg:city":"Suhl",
    "sg:phone":"+49 3681/301730",
    "sg:postcode":"98527",
    "sg:province":"Th\u00fcringen",
    "wof:name":"Klaus Heimbach Rechtsanwalt",
    "wof:placetype":"venue"
},
  "geometry": {"coordinates":[10.6954698563,50.6144752502],"type":"Point"}
}