{
  "type": "Feature",
  "properties": {
    "iso:country":"DE",
    "sg:address":"Chemnitzer Str. 50",
    "sg:city":"Leipzig",
    "sg:phone":"+49 341/8640",
    "sg:postcode":"04289",
    "sg:province":"Sachsen",
    "wof:name":"Park-krankenhaus Leipzig- S\u00fcdost Gmbh",
    "wof:placetype":"venue"
},
  "geometry": {"coordinates":[12.4275922775,51.2917823792],"type":"Point"}
}