{
  "type": "Feature",
  "properties": {
    "iso:country":"DE",
    "sg:address":"Wollstegge 20",
    "sg:city":"Bocholt",
    "sg:phone":"+49 2871/46313",
    "sg:postcode":"46399",
    "sg:province":"Nordrhein-Westfalen",
    "wof:name":"Josef Degeling",
    "wof:placetype":"venue"
},
  "geometry": {"coordinates":[6.545918,51.854488],"type":"Point"}
}