{
  "type": "Feature",
  "properties": {
    "iso:country":"DE",
    "sg:address":"Speichergasse 33",
    "sg:city":"Zeulenroda",
    "sg:phone":"+49 36628/6760",
    "sg:postcode":"07937",
    "sg:province":"Th\u00fcringen",
    "wof:name":"Ead Energieabrechnungsdienst Zeulenroda Gmbh",
    "wof:placetype":"venue"
},
  "geometry": {"coordinates":[11.9869947433,50.6481704712],"type":"Point"}
}