{
  "type": "Feature",
  "properties": {
    "iso:country":"DE",
    "sg:address":"Heinrich-Mann-Allee 103",
    "sg:city":"Potsdam",
    "sg:phone":"+49 331/864478",
    "sg:postcode":"14473",
    "sg:province":"Brandenburg",
    "wof:name":"Arbeiterwohlfahrt Sozialstation Am Schlaatz",
    "wof:placetype":"venue"
},
  "geometry": {"coordinates":[13.074541,52.383911],"type":"Point"}
}