{
  "type": "Feature",
  "properties": {
    "iso:country":"DE",
    "sg:address":"Weiherweg 7",
    "sg:city":"Egweil",
    "sg:phone":"+49 8424/3355",
    "sg:postcode":"85116",
    "sg:province":"Bayern",
    "wof:name":"Peter Spreng",
    "wof:placetype":"venue"
},
  "geometry": {"coordinates":[11.232152,48.784622],"type":"Point"}
}