{
  "type": "Feature",
  "properties": {
    "iso:country":"DE",
    "sg:address":"Gm\u00fcnder Str. 10",
    "sg:city":"Gschwend",
    "sg:phone":"+49 7972/72430",
    "sg:postcode":"74417",
    "sg:province":"Baden-W\u00fcrttemberg",
    "wof:name":"Project-bau-consult Gmbh",
    "wof:placetype":"venue"
},
  "geometry": {"coordinates":[9.743196,48.933159],"type":"Point"}
}