{
  "type": "Feature",
  "properties": {
    "iso:country":"DE",
    "sg:address":"Neuenstadt 27",
    "sg:city":"F\u00fcrstenau",
    "sg:phone":"+49 5901/3253",
    "sg:postcode":"49584",
    "sg:province":"Niedersachsen",
    "wof:name":"Josef Schumacher",
    "wof:placetype":"venue"
},
  "geometry": {"coordinates":[7.677136,52.487576],"type":"Point"}
}