{
  "type": "Feature",
  "properties": {
    "iso:country":"DE",
    "sg:address":"Lindweg 47",
    "sg:city":"Grenzach-Wyhlen",
    "sg:phone":"+49 7624/7740",
    "sg:postcode":"79639",
    "sg:province":"Baden-W\u00fcrttemberg",
    "wof:name":"A. Wesslau \u00c4rztebedarf",
    "wof:placetype":"venue"
},
  "geometry": {"coordinates":[7.682409,47.541039],"type":"Point"}
}