{
  "type": "Feature",
  "properties": {
    "iso:country":"DE",
    "sg:address":"Johann-Seltmann-Str. 8",
    "sg:city":"Vohenstrau\u00df",
    "sg:phone":"+49 9651/91499",
    "sg:postcode":"92648",
    "sg:province":"Bayern",
    "wof:name":"Porzellanfabrik Vohenstrau\u00df Zweign. Der Skv",
    "wof:placetype":"venue"
},
  "geometry": {"coordinates":[12.3416996002,49.6236381531],"type":"Point"}
}