{
  "type": "Feature",
  "properties": {
    "iso:country":"DE",
    "sg:address":"Obertorplatz 18",
    "sg:city":"Hechingen",
    "sg:phone":"+49 7471/5760",
    "sg:postcode":"72379",
    "sg:province":"Baden-W\u00fcrttemberg",
    "wof:name":"Elisabeth St\u00fcrmer",
    "wof:placetype":"venue"
},
  "geometry": {"coordinates":[8.9625587463,48.3500938416],"type":"Point"}
}