{
  "type": "Feature",
  "properties": {
    "iso:country":"DE",
    "sg:address":"Bahnhofstr. 28",
    "sg:city":"Kranichfeld",
    "sg:postcode":"99448",
    "sg:province":"Th\u00fcringen",
    "wof:name":"Inter-factoring Gmbh",
    "wof:placetype":"venue"
},
  "geometry": {"coordinates":[11.2049303055,50.8586387634],"type":"Point"}
}