{
  "type": "Feature",
  "properties": {
    "iso:country":"DE",
    "sg:address":"J\u00fcdenstr. 6",
    "sg:city":"Hann. M\u00fcnden",
    "sg:phone":"+49 5541/8586",
    "sg:postcode":"34346",
    "sg:province":"Niedersachsen",
    "wof:name":"M. Eichentopf Ingenieur",
    "wof:placetype":"venue"
},
  "geometry": {"coordinates":[9.653216362,51.4166030884],"type":"Point"}
}