{
  "type": "Feature",
  "properties": {
    "iso:country":"DE",
    "sg:address":"Sudweyher Str. 7",
    "sg:city":"Syke",
    "sg:phone":"+49 4242/77467",
    "sg:postcode":"28857",
    "sg:province":"Niedersachsen",
    "wof:name":"Mutters Imbi\u00df",
    "wof:placetype":"venue"
},
  "geometry": {"coordinates":[8.8255643845,52.940864563],"type":"Point"}
}