{
  "type": "Feature",
  "properties": {
    "iso:country":"DE",
    "sg:address":"An der Oelm\u00fchle 6",
    "sg:city":"Straelen",
    "sg:postcode":"47638",
    "sg:province":"Nordrhein-Westfalen",
    "wof:name":"Seniorenresidenz Lichtenau Gmbh",
    "wof:placetype":"venue"
},
  "geometry": {"coordinates":[6.279985,51.442722],"type":"Point"}
}