{
  "type": "Feature",
  "properties": {
    "iso:country":"DE",
    "sg:address":"Holl\u00e4nderstr. 31",
    "sg:city":"Berlin",
    "sg:phone":"+49 30/4555099",
    "sg:postcode":"13407",
    "sg:province":"Berlin",
    "wof:name":"Pan E Vin",
    "wof:placetype":"venue"
},
  "geometry": {"coordinates":[13.3551721573,52.5622634888],"type":"Point"}
}