{
  "type": "Feature",
  "properties": {
    "iso:country":"DE",
    "sg:address":"Am Berg 16",
    "sg:city":"Oppurg",
    "sg:phone":"+49 3647/420872",
    "sg:postcode":"07381",
    "sg:province":"Th\u00fcringen",
    "wof:name":"H. Kochale",
    "wof:placetype":"venue"
},
  "geometry": {"coordinates":[11.6318063736,50.7133598328],"type":"Point"}
}