{
  "type": "Feature",
  "properties": {
    "iso:country":"DE",
    "sg:address":"Feyerabendstr. 14",
    "sg:city":"Schwabm\u00fcnchen",
    "sg:phone":"+49 8232/906706",
    "sg:postcode":"86830",
    "sg:province":"Bayern",
    "wof:name":"Martina Marquardt Rechtsanw\u00e4ltin",
    "wof:placetype":"venue"
},
  "geometry": {"coordinates":[10.7601718903,48.1769828796],"type":"Point"}
}