{
  "type": "Feature",
  "properties": {
    "iso:country":"DE",
    "sg:address":"Stadtpark 27",
    "sg:city":"Neustadt",
    "sg:phone":"+49 9161/2247",
    "sg:postcode":"91413",
    "sg:province":"Bayern",
    "wof:name":"F. Dornauer",
    "wof:placetype":"venue"
},
  "geometry": {"coordinates":[10.616998,49.576481],"type":"Point"}
}