{
  "type": "Feature",
  "properties": {
    "iso:country":"DE",
    "sg:address":"Kranichstr. 38",
    "sg:city":"Neubrandenburg",
    "sg:phone":"+49 395/4225440",
    "sg:postcode":"17034",
    "sg:province":"Mecklenburg-Vorpommern",
    "wof:name":"Cafe Zur Elster",
    "wof:placetype":"venue"
},
  "geometry": {"coordinates":[13.260404,53.565647],"type":"Point"}
}