{
  "type": "Feature",
  "properties": {
    "iso:country":"DE",
    "sg:address":"Talstr 170",
    "sg:city":"Asbach",
    "sg:phone":"+49 3683/783006",
    "sg:postcode":"98574",
    "sg:province":"Th\u00fcringen",
    "wof:name":"Erika Zimmer Drechslerei",
    "wof:placetype":"venue"
},
  "geometry": {"coordinates":[10.509955,50.735836],"type":"Point"}
}