{
  "type": "Feature",
  "properties": {
    "iso:country":"DE",
    "sg:address":"Brunsb\u00fctteler Damm 165-173",
    "sg:city":"Berlin",
    "sg:phone":"+49 30/33093300",
    "sg:postcode":"13581",
    "sg:province":"Berlin",
    "wof:name":"Chauvin Ankerpharm Gmbh",
    "wof:placetype":"venue"
},
  "geometry": {"coordinates":[13.172417,52.533482],"type":"Point"}
}