{
  "type": "Feature",
  "properties": {
    "iso:country":"DE",
    "sg:address":"Weilersbacher Str. 87",
    "sg:city":"Villingen-Schwenningen",
    "sg:phone":"+49 7720/38447",
    "sg:postcode":"78056",
    "sg:province":"Baden-W\u00fcrttemberg",
    "wof:name":"Hans-hermann Ketterer Architekt",
    "wof:placetype":"venue"
},
  "geometry": {"coordinates":[8.531342,48.073105],"type":"Point"}
}