{
  "type": "Feature",
  "properties": {
    "iso:country":"DE",
    "sg:address":"Nu\u00dfh\u00fctterweg",
    "sg:city":"Falkenstein",
    "sg:phone":"+49 6302/1439",
    "sg:postcode":"67808",
    "sg:province":"Rheinland-Pfalz",
    "wof:name":"Restaurant Falkensteiner Hof",
    "wof:placetype":"venue"
},
  "geometry": {"coordinates":[7.8752799034,49.6106491089],"type":"Point"}
}