{
  "type": "Feature",
  "properties": {
    "iso:country":"DE",
    "sg:address":"Gr\u00fcne Str. 6",
    "sg:city":"Stuhr",
    "sg:phone":"+49 4221/3661",
    "sg:postcode":"28816",
    "sg:province":"Niedersachsen",
    "wof:name":"Karl Mahlstedt",
    "wof:placetype":"venue"
},
  "geometry": {"coordinates":[8.710099,53.038013],"type":"Point"}
}