{
  "type": "Feature",
  "properties": {
    "iso:country":"DE",
    "sg:address":"Rommener Str. 2",
    "sg:city":"Waldbr\u00f6l",
    "sg:phone":"+49 2291/7198",
    "sg:postcode":"51545",
    "sg:province":"Nordrhein-Westfalen",
    "wof:name":"Paula Burbach",
    "wof:placetype":"venue"
},
  "geometry": {"coordinates":[7.6016588211,50.8382148743],"type":"Point"}
}