{
  "type": "Feature",
  "properties": {
    "iso:country":"DE",
    "sg:address":"Lindenstr. 22",
    "sg:city":"Illertissen",
    "sg:postcode":"89257",
    "sg:province":"Bayern",
    "wof:name":"Kulanz Und Service Immobilien Gmbh",
    "wof:placetype":"venue"
},
  "geometry": {"coordinates":[10.1117839813,48.2451782227],"type":"Point"}
}