{
  "type": "Feature",
  "properties": {
    "iso:country":"DE",
    "sg:address":"Weinb\u00f6hlaer Str. 69",
    "sg:city":"Dresden",
    "sg:phone":"+49 351/5023360",
    "sg:postcode":"01127",
    "sg:province":"Sachsen",
    "wof:name":"Schuster Gmbh",
    "wof:placetype":"venue"
},
  "geometry": {"coordinates":[13.737541,51.086292],"type":"Point"}
}