{
  "type": "Feature",
  "properties": {
    "iso:country":"DE",
    "sg:address":"Frundsbergstr. 39",
    "sg:city":"Stra\u00dflach-Dingharting",
    "sg:postcode":"82064",
    "sg:province":"Bayern",
    "wof:name":"Heinrich Willenborg Gmbh Betrieb Moderner Schau-fahr-",
    "wof:placetype":"venue"
},
  "geometry": {"coordinates":[11.505981,48.011524],"type":"Point"}
}