{
  "type": "Feature",
  "properties": {
    "iso:country":"DE",
    "sg:address":"Hagener Str. 431a",
    "sg:city":"Gevelsberg",
    "sg:phone":"+49 4923/3260035",
    "sg:postcode":"58285",
    "sg:province":"Nordrhein-Westfalen",
    "wof:name":"Gerstenmaier Druckerei",
    "wof:placetype":"venue"
},
  "geometry": {"coordinates":[7.3910698891,51.3383674622],"type":"Point"}
}