{
  "type": "Feature",
  "properties": {
    "iso:country":"DE",
    "sg:address":"Eleonorenring 26",
    "sg:city":"Bad Nauheim",
    "sg:phone":"+49 6032/32113",
    "sg:postcode":"61231",
    "sg:province":"Hessen",
    "wof:name":"Haus Am Eleonorenring",
    "wof:placetype":"venue"
},
  "geometry": {"coordinates":[8.7472457886,50.3627243042],"type":"Point"}
}