{
  "type": "Feature",
  "properties": {
    "iso:country":"DE",
    "sg:address":"Flachskamp 10",
    "sg:city":"Peine",
    "sg:phone":"+49 5171/82483",
    "sg:postcode":"31224",
    "sg:province":"Niedersachsen",
    "wof:name":"Hans Hermann Radeloff Architekt",
    "wof:placetype":"venue"
},
  "geometry": {"coordinates":[10.31676,52.305859],"type":"Point"}
}