{
  "type": "Feature",
  "properties": {
    "iso:country":"DE",
    "sg:address":"Stiftstr. 16",
    "sg:city":"Dessau",
    "sg:phone":"+49 340/2508690",
    "sg:postcode":"06844",
    "sg:province":"Sachsen-Anhalt",
    "wof:name":"Dr. Dirk Helmut Barth Notariat",
    "wof:placetype":"venue"
},
  "geometry": {"coordinates":[12.2425518036,51.8377990723],"type":"Point"}
}