{
  "type": "Feature",
  "properties": {
    "iso:country":"DE",
    "sg:address":"Euskirchener Str. 80",
    "sg:city":"Bonn",
    "sg:phone":"+49 228/5210",
    "sg:postcode":"53121",
    "sg:province":"Nordrhein-Westfalen",
    "wof:name":"Wabco Gmbh",
    "wof:placetype":"venue"
},
  "geometry": {"coordinates":[7.064577,50.72298],"type":"Point"}
}