{
  "type": "Feature",
  "properties": {
    "iso:country":"DE",
    "sg:address":"Alte Dorfstr. 160",
    "sg:city":"J\u00fclich",
    "sg:phone":"+49 2461/8687",
    "sg:postcode":"52428",
    "sg:province":"Nordrhein-Westfalen",
    "wof:name":"Arnold Jumpertz",
    "wof:placetype":"venue"
},
  "geometry": {"coordinates":[6.33152,50.952793],"type":"Point"}
}