{
  "type": "Feature",
  "properties": {
    "iso:country":"DE",
    "sg:address":"Heroldstr",
    "sg:city":"44145",
    "sg:phone":"+49 3476/543",
    "sg:postcode":"44143",
    "sg:province":"Nordrhein-Westfalen",
    "wof:name":"International Music",
    "wof:placetype":"venue"
},
  "geometry": {"coordinates":[-81.925652,41.452847],"type":"Point"}
}