{
  "type": "Feature",
  "properties": {
    "iso:country":"DE",
    "sg:address":"Burgweg 13",
    "sg:city":"Kronberg",
    "sg:phone":"+49 6173/950770",
    "sg:postcode":"61476",
    "sg:province":"Hessen",
    "wof:name":"Manfred Kimpel",
    "wof:placetype":"venue"
},
  "geometry": {"coordinates":[8.5060558319,50.1833610535],"type":"Point"}
}