{
  "type": "Feature",
  "properties": {
    "iso:country":"DE",
    "sg:address":"Mindelheimer Str. 12",
    "sg:city":"Dirlewang",
    "sg:phone":"+49 8267/369",
    "sg:postcode":"87742",
    "sg:province":"Bayern",
    "wof:name":"Mindeltal-apotheke Inh. Peter Sieke",
    "wof:placetype":"venue"
},
  "geometry": {"coordinates":[10.504773,48.003639],"type":"Point"}
}