{
  "type": "Feature",
  "properties": {
    "iso:country":"DE",
    "sg:address":"Freiherr-vom-Stein-Str. 32",
    "sg:city":"Kamp-Lintfort",
    "sg:phone":"+49 2842/13071",
    "sg:postcode":"47475",
    "sg:province":"Nordrhein-Westfalen",
    "wof:name":"Treuhandstelle F\u00fcr Bergmannswohnst. Im Rheinisch-",
    "wof:placetype":"venue"
},
  "geometry": {"coordinates":[6.5451521873,51.503528595],"type":"Point"}
}