{
  "type": "Feature",
  "properties": {
    "iso:country":"DE",
    "sg:address":"Putlitzer Str. 44",
    "sg:city":"Parchim",
    "sg:phone":"+49 3871/213334",
    "sg:postcode":"19370",
    "sg:province":"Mecklenburg-Vorpommern",
    "wof:name":"Ibus Parchim Ingenieurb\u00fcro F\u00fcr Umwelttechnik Und",
    "wof:placetype":"venue"
},
  "geometry": {"coordinates":[11.8448944092,53.4227333069],"type":"Point"}
}