{
  "type": "Feature",
  "properties": {
    "iso:country":"DE",
    "sg:address":"Dorfstr. 14",
    "sg:city":"Negernb\u00f6tel",
    "sg:phone":"+49 4551/4788",
    "sg:postcode":"23795",
    "sg:province":"Schleswig-Holstein",
    "wof:name":"K\u00fchl",
    "wof:placetype":"venue"
},
  "geometry": {"coordinates":[10.2501649857,53.9815483093],"type":"Point"}
}