{
  "type": "Feature",
  "properties": {
    "iso:country":"DE",
    "sg:address":"Hauptstr. 44",
    "sg:city":"Sennfeld",
    "sg:phone":"+49 9721/608070",
    "sg:postcode":"97526",
    "sg:province":"Bayern",
    "wof:name":"Weinstube Kohl",
    "wof:placetype":"venue"
},
  "geometry": {"coordinates":[10.2585430145,50.0413017273],"type":"Point"}
}