{
  "type": "Feature",
  "properties": {
    "iso:country":"DE",
    "sg:address":"Bachstr. 1",
    "sg:city":"H\u00f6xter",
    "sg:phone":"+49 5271/920292",
    "sg:postcode":"37671",
    "sg:province":"Nordrhein-Westfalen",
    "wof:name":"Neusehland Agentur F\u00fcr Kommunikation Gmbh & Co. Kg",
    "wof:placetype":"venue"
},
  "geometry": {"coordinates":[9.3846054077,51.7748908997],"type":"Point"}
}