{
  "type": "Feature",
  "properties": {
    "iso:country":"DE",
    "sg:address":"Philippine-Welser-Str. 11",
    "sg:city":"Augsburg",
    "sg:phone":"+49 821/151561",
    "sg:postcode":"86150",
    "sg:province":"Bayern",
    "wof:name":"Planters Caribic",
    "wof:placetype":"venue"
},
  "geometry": {"coordinates":[10.8971424103,48.3679237366],"type":"Point"}
}