{
  "type": "Feature",
  "properties": {
    "iso:country":"DE",
    "sg:address":"Zuckerleweg 6",
    "sg:city":"Stuttgart",
    "sg:phone":"+49 711/509930",
    "sg:postcode":"70374",
    "sg:province":"Baden-W\u00fcrttemberg",
    "wof:name":"Cannstatter Bettfedern- Fabrik Gmbh",
    "wof:placetype":"venue"
},
  "geometry": {"coordinates":[9.2296228409,48.8160018921],"type":"Point"}
}