{
  "type": "Feature",
  "properties": {
    "iso:country":"DE",
    "sg:address":"Hauptstr. 8",
    "sg:city":"Moos",
    "sg:phone":"+49 7732/52252",
    "sg:postcode":"78345",
    "sg:province":"Baden-W\u00fcrttemberg",
    "wof:name":"Adalbert Krekosch",
    "wof:placetype":"venue"
},
  "geometry": {"coordinates":[8.954402,47.711479],"type":"Point"}
}