{
  "type": "Feature",
  "properties": {
    "iso:country":"DE",
    "sg:address":"Karl-Marx-Str. 8",
    "sg:city":"Brieskow-Finkenheerd",
    "sg:postcode":"15295",
    "sg:province":"Brandenburg",
    "wof:name":"Horst Najorka",
    "wof:placetype":"venue"
},
  "geometry": {"coordinates":[14.578788,52.257759],"type":"Point"}
}