{
  "type": "Feature",
  "properties": {
    "iso:country":"DE",
    "sg:address":"Danziger Str. 2",
    "sg:city":"Neuwied",
    "sg:phone":"+49 2631/39580",
    "sg:postcode":"56564",
    "sg:province":"Rheinland-Pfalz",
    "wof:name":"H\u00fcwa Gmbh",
    "wof:placetype":"venue"
},
  "geometry": {"coordinates":[7.483422,50.432819],"type":"Point"}
}