{
  "type": "Feature",
  "properties": {
    "iso:country":"DE",
    "sg:address":"Br\u00fchlstr. 31",
    "sg:city":"Pl\u00fcderhausen",
    "sg:phone":"+49 7181/999710",
    "sg:postcode":"73655",
    "sg:province":"Baden-W\u00fcrttemberg",
    "wof:name":"W\u00fcrttembergische Versicherung Ag",
    "wof:placetype":"venue"
},
  "geometry": {"coordinates":[9.6010026932,48.7932319641],"type":"Point"}
}