{
  "type": "Feature",
  "properties": {
    "iso:country":"DE",
    "sg:address":"Am Ostbahnhof",
    "sg:city":"Dannenberg",
    "sg:phone":"+49 5861/343",
    "sg:postcode":"29451",
    "sg:province":"Niedersachsen",
    "wof:name":"Samen- Und Saatenzucht Dannenberg",
    "wof:placetype":"venue"
},
  "geometry": {"coordinates":[11.11804,53.104294],"type":"Point"}
}