{
  "type": "Feature",
  "properties": {
    "iso:country":"DE",
    "sg:address":"Kattunbleiche 23",
    "sg:city":"Hamburg",
    "sg:phone":"+49 40/683546",
    "sg:postcode":"22041",
    "sg:province":"Hamburg",
    "wof:name":"H. Hartogs Steuerberater",
    "wof:placetype":"venue"
},
  "geometry": {"coordinates":[10.070561409,53.5748138428],"type":"Point"}
}