{
  "type": "Feature",
  "properties": {
    "iso:country":"DE",
    "sg:address":"Breckenheimer Str. 1",
    "sg:city":"Hofheim",
    "sg:phone":"+49 6192/901593",
    "sg:postcode":"65719",
    "sg:province":"Hessen",
    "wof:name":"Medilog Gmbh",
    "wof:placetype":"venue"
},
  "geometry": {"coordinates":[8.4408340454,50.0832901001],"type":"Point"}
}