{
  "type": "Feature",
  "properties": {
    "iso:country":"DE",
    "sg:address":"Attendorner Weg 18",
    "sg:city":"Berlin",
    "sg:phone":"+49 30/43566881",
    "sg:postcode":"13507",
    "sg:province":"Berlin",
    "wof:name":"Dr. Hans-j\u00fcrgen Zastrow Rechtsanwalt",
    "wof:placetype":"venue"
},
  "geometry": {"coordinates":[13.2818603516,52.5730438232],"type":"Point"}
}