{
  "type": "Feature",
  "properties": {
    "iso:country":"DE",
    "sg:address":"J\u00fcrgenstr. 11",
    "sg:city":"Elmshorn",
    "sg:phone":"+49 4121/85805",
    "sg:postcode":"25335",
    "sg:province":"Schleswig-Holstein",
    "wof:name":"H & H Grundst\u00fccks- Verwaltung Gmbh",
    "wof:placetype":"venue"
},
  "geometry": {"coordinates":[9.6606807709,53.7560081482],"type":"Point"}
}