{
  "type": "Feature",
  "properties": {
    "iso:country":"DE",
    "sg:address":"Neugasse 39",
    "sg:city":"Ha\u00dfloch",
    "sg:phone":"+49 6324/2532",
    "sg:postcode":"67454",
    "sg:province":"Rheinland-Pfalz",
    "wof:name":"Otto Handrich",
    "wof:placetype":"venue"
},
  "geometry": {"coordinates":[8.2598400116,49.3589935303],"type":"Point"}
}