{
  "type": "Feature",
  "properties": {
    "iso:country":"DE",
    "sg:address":"Toronto Avenue 206",
    "sg:city":"Rheinm\u00fcnster",
    "sg:phone":"+49 7229/662288",
    "sg:postcode":"77836",
    "sg:province":"Baden-W\u00fcrttemberg",
    "wof:name":"B\u00fcrk Innovation Gmbh",
    "wof:placetype":"venue"
},
  "geometry": {"coordinates":[8.090745,48.778702],"type":"Point"}
}