{
  "type": "Feature",
  "properties": {
    "iso:country":"DE",
    "sg:address":"Dillweissensteiner Str. 31a",
    "sg:city":"Pforzheim",
    "sg:phone":"+49 7231/765727",
    "sg:postcode":"75180",
    "sg:province":"Baden-W\u00fcrttemberg",
    "wof:name":"Music Booking",
    "wof:placetype":"venue"
},
  "geometry": {"coordinates":[8.6647691727,48.8569221497],"type":"Point"}
}