{
  "type": "Feature",
  "properties": {
    "iso:country":"DE",
    "sg:address":"Werner-Friedmann-Bogen 26",
    "sg:city":"M\u00fcnchen",
    "sg:phone":"+49 89/1492444",
    "sg:postcode":"80993",
    "sg:province":"Bayern",
    "wof:name":"Irt Ges. F\u00fcr Investitions- Arbeiten U. Handel D. O. O.",
    "wof:placetype":"venue"
},
  "geometry": {"coordinates":[11.5377759933,48.1846427917],"type":"Point"}
}