{
  "type": "Feature",
  "properties": {
    "iso:country":"DE",
    "sg:address":"Butzendorfer Weg 20",
    "sg:city":"Wagenfeld",
    "sg:phone":"+49 5774/462",
    "sg:postcode":"49419",
    "sg:province":"Niedersachsen",
    "wof:name":"Wilhelm Fangmann",
    "wof:placetype":"venue"
},
  "geometry": {"coordinates":[8.685333,52.552937],"type":"Point"}
}