{
  "type": "Feature",
  "properties": {
    "iso:country":"DE",
    "sg:address":"Brentanostr. 9",
    "sg:city":"Seligenstadt",
    "sg:phone":"+49 6182/22415",
    "sg:postcode":"63500",
    "sg:province":"Hessen",
    "wof:name":"Alfons S\u00f6nning",
    "wof:placetype":"venue"
},
  "geometry": {"coordinates":[8.979268074,50.0370063782],"type":"Point"}
}