{
  "type": "Feature",
  "properties": {
    "iso:country":"DE",
    "sg:address":"Bretternhof 53",
    "sg:city":"Boizenburg",
    "sg:phone":"+49 38847/52712",
    "sg:postcode":"19258",
    "sg:province":"Mecklenburg-Vorpommern",
    "wof:name":"Harald Walczyk",
    "wof:placetype":"venue"
},
  "geometry": {"coordinates":[10.736472,53.380833],"type":"Point"}
}