{
  "type": "Feature",
  "properties": {
    "iso:country":"DE",
    "sg:address":"An der Plantane 14",
    "sg:city":"Boppard",
    "sg:phone":"+49 6742/81948",
    "sg:postcode":"56154",
    "sg:province":"Rheinland-Pfalz",
    "wof:name":"Bernd Leitzbach",
    "wof:placetype":"venue"
},
  "geometry": {"coordinates":[7.6059470177,50.2137107849],"type":"Point"}
}