{
  "type": "Feature",
  "properties": {
    "iso:country":"DE",
    "sg:address":"Odenthaler Str. 89",
    "sg:city":"K\u00f6ln",
    "sg:postcode":"51069",
    "sg:province":"Nordrhein-Westfalen",
    "wof:name":"Zb Transporte Karin Zabelberg E. Kfr.",
    "wof:placetype":"venue"
},
  "geometry": {"coordinates":[7.0471038818,50.9993057251],"type":"Point"}
}