{
  "type": "Feature",
  "properties": {
    "iso:country":"DE",
    "sg:address":"Breitenweg 29",
    "sg:city":"Bremen",
    "sg:postcode":"28195",
    "sg:province":"Bremen",
    "wof:name":"Bfg Bremische Finanz- Beteiligungs- Gmbh & Co. Kg",
    "wof:placetype":"venue"
},
  "geometry": {"coordinates":[8.807805,53.083794],"type":"Point"}
}