{
  "type": "Feature",
  "properties": {
    "iso:country":"DE",
    "sg:address":"Villenstr. 9-13",
    "sg:city":"M\u00f6nchengladbach",
    "sg:postcode":"41061",
    "sg:province":"Nordrhein-Westfalen",
    "wof:name":"Hompepage F\u00fcr Dessous Etc",
    "wof:placetype":"venue"
},
  "geometry": {"coordinates":[6.420454,51.190201],"type":"Point"}
}