{
  "type": "Feature",
  "properties": {
    "iso:country":"DE",
    "sg:address":"Fritz-Bechtold-Str. 3",
    "sg:city":"Traunstein",
    "sg:phone":"+49 861/2796",
    "sg:postcode":"83278",
    "sg:province":"Bayern",
    "wof:name":"G\u00fcnther Zippusch",
    "wof:placetype":"venue"
},
  "geometry": {"coordinates":[12.6354665756,47.8776817322],"type":"Point"}
}