{
  "type": "Feature",
  "properties": {
    "iso:country":"DE",
    "sg:address":"Osterather Weg 8",
    "sg:city":"Krefeld",
    "sg:phone":"+49 2151/300053",
    "sg:postcode":"47807",
    "sg:province":"Nordrhein-Westfalen",
    "wof:name":"A. Kunze Ingenieur",
    "wof:placetype":"venue"
},
  "geometry": {"coordinates":[6.596777916,51.2935028076],"type":"Point"}
}