{
  "type": "Feature",
  "properties": {
    "iso:country":"DE",
    "sg:address":"Karbener Weg 8-10",
    "sg:city":"Karben",
    "sg:phone":"+49 7621/164304",
    "sg:postcode":"61184",
    "sg:province":"Hessen",
    "wof:name":"E. Le\u00dfm\u00f6llmann Und K. Fink Rechtsanw\u00e4lte Und Notare",
    "wof:placetype":"venue"
},
  "geometry": {"coordinates":[8.7736110687,50.2312698364],"type":"Point"}
}