{
  "type": "Feature",
  "properties": {
    "iso:country":"DE",
    "sg:address":"Stellinger Steindamm 59",
    "sg:city":"Hamburg",
    "sg:phone":"+49 40/54763270",
    "sg:postcode":"22527",
    "sg:province":"Hamburg",
    "wof:name":"Tks Consulting Gmbh",
    "wof:placetype":"venue"
},
  "geometry": {"coordinates":[9.9296865463,53.5973701477],"type":"Point"}
}