{
  "type": "Feature",
  "properties": {
    "iso:country":"DE",
    "sg:address":"Pestalozzistr. 3",
    "sg:city":"Dohna",
    "sg:phone":"+49 3529/515501",
    "sg:postcode":"01809",
    "sg:province":"Sachsen",
    "wof:name":"Rudolf Werner",
    "wof:placetype":"venue"
},
  "geometry": {"coordinates":[13.854908,50.956753],"type":"Point"}
}