{
  "type": "Feature",
  "properties": {
    "iso:country":"DE",
    "sg:address":"Potsdamer Str. 23-25",
    "sg:city":"Bremerhaven",
    "sg:postcode":"27576",
    "sg:province":"Bremen",
    "wof:name":"Hansel M\u00e4rtins Gmbh",
    "wof:placetype":"venue"
},
  "geometry": {"coordinates":[8.581867218,53.5594444275],"type":"Point"}
}