{
  "type": "Feature",
  "properties": {
    "iso:country":"DE",
    "sg:address":"Oberrheinplatz 1",
    "sg:city":"Rheinfelden",
    "sg:phone":"+49 7623/2326",
    "sg:postcode":"79618",
    "sg:province":"Baden-W\u00fcrttemberg",
    "wof:name":"Irodion",
    "wof:placetype":"venue"
},
  "geometry": {"coordinates":[7.7845330238,47.5592727661],"type":"Point"}
}