{
  "type": "Feature",
  "properties": {
    "iso:country":"DE",
    "sg:address":"Ilmenauer Str. 11",
    "sg:city":"Berlin",
    "sg:phone":"+49 30/8959430",
    "sg:postcode":"14193",
    "sg:province":"Berlin",
    "wof:name":"Bernhard F\u00fcchsel Rechtsanw\u00e4lte",
    "wof:placetype":"venue"
},
  "geometry": {"coordinates":[13.2870903015,52.4813919067],"type":"Point"}
}