{
  "type": "Feature",
  "properties": {
    "iso:country":"DE",
    "sg:address":"Tejastr. 4",
    "sg:city":"Berlin",
    "sg:postcode":"12105",
    "sg:province":"Berlin",
    "wof:name":"Cema Gmbh",
    "wof:placetype":"venue"
},
  "geometry": {"coordinates":[13.3640899658,52.4479789734],"type":"Point"}
}