{
  "type": "Feature",
  "properties": {
    "iso:country":"DE",
    "sg:address":"Bernsbacher Str. 4",
    "sg:city":"Beierfeld",
    "sg:phone":"+49 3774/63001",
    "sg:postcode":"08340",
    "sg:province":"Sachsen",
    "wof:name":"Gfv Mbh",
    "wof:placetype":"venue"
},
  "geometry": {"coordinates":[12.7884101868,50.5295181274],"type":"Point"}
}