{
  "type": "Feature",
  "properties": {
    "iso:country":"DE",
    "sg:address":"Abteistr. 11",
    "sg:city":"Freyung",
    "sg:phone":"+49 8551/7088",
    "sg:postcode":"94078",
    "sg:province":"Bayern",
    "wof:name":"Franz Gibis",
    "wof:placetype":"venue"
},
  "geometry": {"coordinates":[13.5486936569,48.8066482544],"type":"Point"}
}