{
  "type": "Feature",
  "properties": {
    "iso:country":"DE",
    "sg:address":"Hirschbergstr. 57",
    "sg:city":"Ludwigsburg",
    "sg:phone":"+49 7141/31763",
    "sg:postcode":"71634",
    "sg:province":"Baden-W\u00fcrttemberg",
    "wof:name":"Albin Bogner",
    "wof:placetype":"venue"
},
  "geometry": {"coordinates":[9.1614599228,48.9080734253],"type":"Point"}
}