{
  "type": "Feature",
  "properties": {
    "iso:country":"DE",
    "sg:address":"Stra\u00dfe der Jugend 23",
    "sg:city":"Pretzier",
    "sg:phone":"+49 39037/523",
    "sg:postcode":"29416",
    "sg:province":"Sachsen-Anhalt",
    "wof:name":"P. R\u00d6hl",
    "wof:placetype":"venue"
},
  "geometry": {"coordinates":[11.258187,52.833992],"type":"Point"}
}