{
  "type": "Feature",
  "properties": {
    "iso:country":"DE",
    "sg:address":"Lucasweg 5",
    "sg:city":"Darmstadt",
    "sg:phone":"+49 6151/494139",
    "sg:postcode":"64287",
    "sg:province":"Hessen",
    "wof:name":"Genetrace Biotechnologische Ger\u00e4te Gmbh",
    "wof:placetype":"venue"
},
  "geometry": {"coordinates":[8.666879,49.878326],"type":"Point"}
}