{
  "type": "Feature",
  "properties": {
    "iso:country":"DE",
    "sg:address":"Robertstr. 38",
    "sg:city":"Kronau",
    "sg:phone":"+49 7253/1708",
    "sg:postcode":"76709",
    "sg:province":"Baden-W\u00fcrttemberg",
    "wof:name":"Walter Himmelsbach",
    "wof:placetype":"venue"
},
  "geometry": {"coordinates":[8.6299495697,49.2229652405],"type":"Point"}
}