{
  "type": "Feature",
  "properties": {
    "iso:country":"DE",
    "sg:address":"Buchenweg 1",
    "sg:city":"Kieselbronn",
    "sg:phone":"+49 7231/564143",
    "sg:postcode":"75249",
    "sg:province":"Baden-W\u00fcrttemberg",
    "wof:name":"Rita H\u00f6lle Steuerbevollm\u00e4chtigter",
    "wof:placetype":"venue"
},
  "geometry": {"coordinates":[8.7438011169,48.9324264526],"type":"Point"}
}