{
  "type": "Feature",
  "properties": {
    "iso:country":"DE",
    "sg:address":"Alexanderstr 46",
    "sg:city":"M\u00fclheim",
    "sg:phone":"+49 208/495850",
    "sg:postcode":"45472",
    "sg:province":"Nordrhein-Westfalen",
    "wof:name":"Isam Ag Gesellschaft F\u00fcr Angewandte Kybernetik",
    "wof:placetype":"venue"
},
  "geometry": {"coordinates":[6.931079,51.439297],"type":"Point"}
}