{
  "type": "Feature",
  "properties": {
    "iso:country":"DE",
    "sg:address":"Im Kleinen Feld 24",
    "sg:city":"Beverungen",
    "sg:phone":"+49 5273/1310",
    "sg:postcode":"37688",
    "sg:province":"Nordrhein-Westfalen",
    "wof:name":"Riepe Massivbau Beteiligungs Gmbh",
    "wof:placetype":"venue"
},
  "geometry": {"coordinates":[9.373918,51.660686],"type":"Point"}
}