{
  "type": "Feature",
  "properties": {
    "iso:country":"DE",
    "sg:address":"Martin-Behaim-Str. 12",
    "sg:city":"Neu-Isenburg",
    "sg:postcode":"63263",
    "sg:province":"Hessen",
    "wof:name":"Tropicana Products Europe Gmbh",
    "wof:placetype":"venue"
},
  "geometry": {"coordinates":[8.7137527466,50.047794342],"type":"Point"}
}