{
  "type": "Feature",
  "properties": {
    "iso:country":"DE",
    "sg:address":"Gneisenaustr. 3",
    "sg:city":"Ludwigsburg",
    "sg:phone":"+49 7141/451560",
    "sg:postcode":"71636",
    "sg:province":"Baden-W\u00fcrttemberg",
    "wof:name":"Schw\u00e4bische Hausverwaltung Gmbh",
    "wof:placetype":"venue"
},
  "geometry": {"coordinates":[9.1730213165,48.9004440308],"type":"Point"}
}