{
  "type": "Feature",
  "properties": {
    "iso:country":"DE",
    "sg:address":"Karlsbader Str. 26",
    "sg:city":"Regensburg",
    "sg:phone":"+49 941/64241",
    "sg:postcode":"93057",
    "sg:province":"Bayern",
    "wof:name":"Max Reiger Bildhauer",
    "wof:placetype":"venue"
},
  "geometry": {"coordinates":[12.1242551804,49.039981842],"type":"Point"}
}