{
  "type": "Feature",
  "properties": {
    "iso:country":"DE",
    "sg:address":"Schwarzbach 10",
    "sg:city":"Wuppertal",
    "sg:phone":"+49 202/667308",
    "sg:postcode":"42277",
    "sg:province":"Nordrhein-Westfalen",
    "wof:name":"Hansa Becher",
    "wof:placetype":"venue"
},
  "geometry": {"coordinates":[7.223777771,51.2760429382],"type":"Point"}
}