{
  "type": "Feature",
  "properties": {
    "iso:country":"DE",
    "sg:address":"Hauptstr. 80",
    "sg:city":"Wangen",
    "sg:phone":"+49 7161/15329",
    "sg:postcode":"73117",
    "sg:province":"Baden-W\u00fcrttemberg",
    "wof:name":"Richard Feil B\u00e4ckerei",
    "wof:placetype":"venue"
},
  "geometry": {"coordinates":[9.611219,48.729015],"type":"Point"}
}