{
  "type": "Feature",
  "properties": {
    "iso:country":"DE",
    "sg:address":"Robert-Bosch-Str 3",
    "sg:city":"Ditzingen",
    "sg:phone":"+49 7156/8755",
    "sg:postcode":"71254",
    "sg:province":"Baden-W\u00fcrttemberg",
    "wof:name":"Kunststoff-verarbeitung Koose",
    "wof:placetype":"venue"
},
  "geometry": {"coordinates":[9.0478162766,48.8340034485],"type":"Point"}
}