{
  "type": "Feature",
  "properties": {
    "iso:country":"DE",
    "sg:address":"Eichelgasse 51",
    "sg:city":"Wertheim",
    "sg:phone":"+49 9342/23372",
    "sg:postcode":"97877",
    "sg:province":"Baden-W\u00fcrttemberg",
    "wof:name":"Gertrud Keller Finanzberaterin",
    "wof:placetype":"venue"
},
  "geometry": {"coordinates":[9.5194215775,49.7604064941],"type":"Point"}
}