{
  "type": "Feature",
  "properties": {
    "iso:country":"DE",
    "sg:address":"Aindorferstr. 197",
    "sg:city":"M\u00fcnchen",
    "sg:phone":"+49 89/567070",
    "sg:postcode":"80689",
    "sg:province":"Bayern",
    "wof:name":"Johann-wolfgang Holste Architekt",
    "wof:placetype":"venue"
},
  "geometry": {"coordinates":[11.488629,48.133099],"type":"Point"}
}