{
  "type": "Feature",
  "properties": {
    "iso:country":"DE",
    "sg:address":"N\u00f6rdliche M\u00fcnchner Str. 17",
    "sg:city":"Gr\u00fcnwald",
    "sg:phone":"+49 89/6493110",
    "sg:postcode":"82031",
    "sg:province":"Bayern",
    "wof:name":"Eduard Dobroschke Rechtsanwalt",
    "wof:placetype":"venue"
},
  "geometry": {"coordinates":[11.5227146149,48.0396347046],"type":"Point"}
}