{
  "type": "Feature",
  "properties": {
    "iso:country":"DE",
    "sg:address":"Klauckestr. 15",
    "sg:city":"Augsburg",
    "sg:phone":"+49 821/159099",
    "sg:postcode":"86153",
    "sg:province":"Bayern",
    "wof:name":"P. Bolkart Immobilienmakler",
    "wof:placetype":"venue"
},
  "geometry": {"coordinates":[10.903008461,48.3771705627],"type":"Point"}
}