{
  "type": "Feature",
  "properties": {
    "iso:country":"DE",
    "sg:address":"Hauptstr. 41",
    "sg:city":"Gutach",
    "sg:phone":"+49 7833/1877",
    "sg:postcode":"77793",
    "sg:province":"Baden-W\u00fcrttemberg",
    "wof:name":"Traube",
    "wof:placetype":"venue"
},
  "geometry": {"coordinates":[8.2111406326,48.2482261658],"type":"Point"}
}