{
  "type": "Feature",
  "properties": {
    "iso:country":"DE",
    "sg:address":"Einhundertsiebz Ehrenh 117er 3",
    "sg:city":"Mainz",
    "sg:phone":"+49 6131/679031",
    "sg:postcode":"55118",
    "sg:province":"Rheinland-Pfalz",
    "wof:name":"Vertrauens\u00e4rztlicher-dienst Der Lva Rheinland-pfalz",
    "wof:placetype":"venue"
},
  "geometry": {"coordinates":[8.2647132874,50.0068321228],"type":"Point"}
}