{
  "type": "Feature",
  "properties": {
    "iso:country":"DE",
    "sg:address":"Sachsenstr. 4",
    "sg:city":"L\u00f6bau",
    "sg:phone":"+49 3585/457520",
    "sg:postcode":"02708",
    "sg:province":"Sachsen",
    "wof:name":"Dietrich A. Walter Heilpraktiker",
    "wof:placetype":"venue"
},
  "geometry": {"coordinates":[14.6671829224,51.0987548828],"type":"Point"}
}