{
  "type": "Feature",
  "properties": {
    "iso:country":"DE",
    "sg:address":"R\u00f6merstr. 10",
    "sg:city":"Wiehl",
    "sg:phone":"+49 2262/92113",
    "sg:postcode":"51674",
    "sg:province":"Nordrhein-Westfalen",
    "wof:name":"Klaus D. Schneider",
    "wof:placetype":"venue"
},
  "geometry": {"coordinates":[7.5538511276,50.9364356995],"type":"Point"}
}