{
  "type": "Feature",
  "properties": {
    "iso:country":"DE",
    "sg:address":"Hirschberger Str. 25",
    "sg:city":"Burgthann",
    "sg:phone":"+49 9183/1629",
    "sg:postcode":"90559",
    "sg:province":"Bayern",
    "wof:name":"Wuk Wohnbau Und Immobilien Gmbh",
    "wof:placetype":"venue"
},
  "geometry": {"coordinates":[11.305946,49.346043],"type":"Point"}
}