{
  "type": "Feature",
  "properties": {
    "iso:country":"DE",
    "sg:address":"Eberhardstr. 40",
    "sg:city":"M\u00fclheim",
    "sg:phone":"+49 208/401416",
    "sg:postcode":"45476",
    "sg:province":"Nordrhein-Westfalen",
    "wof:name":"Katholisches Pfarramt St. Albertus Magnus",
    "wof:placetype":"venue"
},
  "geometry": {"coordinates":[6.8533258438,51.4471435547],"type":"Point"}
}