{
  "type": "Feature",
  "properties": {
    "iso:country":"DE",
    "sg:address":"Am Steintor 18",
    "sg:city":"Halle",
    "sg:postcode":"06112",
    "sg:province":"Sachsen-Anhalt",
    "wof:name":"Steintor-elektronik Kiesewetter & Luppe Gbr",
    "wof:placetype":"venue"
},
  "geometry": {"coordinates":[11.9790363312,51.4882659912],"type":"Point"}
}