{
  "type": "Feature",
  "properties": {
    "iso:country":"DE",
    "sg:address":"Mittelweg 40",
    "sg:city":"Hamburg",
    "sg:phone":"+49 40/442770",
    "sg:postcode":"20148",
    "sg:province":"Hamburg",
    "wof:name":"Felix-eberhard Von Cube Komponist",
    "wof:placetype":"venue"
},
  "geometry": {"coordinates":[9.995100975,53.5704841614],"type":"Point"}
}