{
  "type": "Feature",
  "properties": {
    "iso:country":"DE",
    "sg:address":"Goethestr. 22",
    "sg:city":"Baltmannsweiler",
    "sg:phone":"+49 7153/41453",
    "sg:postcode":"73666",
    "sg:province":"Baden-W\u00fcrttemberg",
    "wof:name":"Ihlenfeld",
    "wof:placetype":"venue"
},
  "geometry": {"coordinates":[9.444278717,48.7473907471],"type":"Point"}
}