{
  "type": "Feature",
  "properties": {
    "iso:country":"DE",
    "sg:address":"Luxemburger Str. 160",
    "sg:city":"Trier",
    "sg:phone":"+49 651/821765",
    "sg:postcode":"54294",
    "sg:province":"Rheinland-Pfalz",
    "wof:name":"Andreas Gassel",
    "wof:placetype":"venue"
},
  "geometry": {"coordinates":[6.613019,49.738182],"type":"Point"}
}