{
  "type": "Feature",
  "properties": {
    "iso:country":"DE",
    "sg:address":"Selbitzer Str. 68",
    "sg:city":"Berlin",
    "sg:phone":"+49 30/32601666",
    "sg:postcode":"14089",
    "sg:province":"Berlin",
    "wof:name":"Dreiundzwanzig Headztorms Gmbh",
    "wof:placetype":"venue"
},
  "geometry": {"coordinates":[13.1247529984,52.4580383301],"type":"Point"}
}