{
  "type": "Feature",
  "properties": {
    "iso:country":"DE",
    "sg:address":"Goethestr. 1",
    "sg:city":"D\u00fcsseldorf",
    "sg:phone":"+49 211/671368",
    "sg:postcode":"40237",
    "sg:province":"Nordrhein-Westfalen",
    "wof:name":"Albert-schweitzer-apotheke Michael Kipping E. K.",
    "wof:placetype":"venue"
},
  "geometry": {"coordinates":[6.801339,51.231762],"type":"Point"}
}