{
  "type": "Feature",
  "properties": {
    "iso:country":"DE",
    "sg:address":"Feurigstr. 54",
    "sg:city":"Berlin",
    "sg:phone":"+49 30/7815159",
    "sg:postcode":"10827",
    "sg:province":"Berlin",
    "wof:name":"Schneider Druck Gerhard Schneider",
    "wof:placetype":"venue"
},
  "geometry": {"coordinates":[13.355264,52.483845],"type":"Point"}
}