{
  "type": "Feature",
  "properties": {
    "iso:country":"DE",
    "sg:address":"Lorcher Str. 46",
    "sg:city":"Schw\u00e4bisch Gm\u00fcnd",
    "sg:phone":"+49 7171/66313",
    "sg:postcode":"73525",
    "sg:province":"Baden-W\u00fcrttemberg",
    "wof:name":"Esso Deutschland Gmbh",
    "wof:placetype":"venue"
},
  "geometry": {"coordinates":[9.7835760117,48.7980957031],"type":"Point"}
}