{
  "type": "Feature",
  "properties": {
    "iso:country":"DE",
    "sg:address":"R\u00fcst 30",
    "sg:city":"Stolberg",
    "sg:phone":"+49 2402/98950",
    "sg:postcode":"52224",
    "sg:province":"Nordrhein-Westfalen",
    "wof:name":"Bsr Naturstein-aufbereitungs Gmbh",
    "wof:placetype":"venue"
},
  "geometry": {"coordinates":[6.24164,50.751827],"type":"Point"}
}