{
  "type": "Feature",
  "properties": {
    "iso:country":"DE",
    "sg:address":"Neanderstr. 7",
    "sg:city":"Mettmann",
    "sg:phone":"+49 2104/74979",
    "sg:postcode":"40822",
    "sg:province":"Nordrhein-Westfalen",
    "wof:name":"Baerbel Hartwig",
    "wof:placetype":"venue"
},
  "geometry": {"coordinates":[6.97517,51.250511],"type":"Point"}
}