{
  "type": "Feature",
  "properties": {
    "iso:country":"DE",
    "sg:address":"Jungenthaler Str. 75",
    "sg:city":"Kirchen",
    "sg:phone":"+49 2741/7278",
    "sg:postcode":"57548",
    "sg:province":"Rheinland-Pfalz",
    "wof:name":"G. Schneider",
    "wof:placetype":"venue"
},
  "geometry": {"coordinates":[7.8650050163,50.8105354309],"type":"Point"}
}