{
  "type": "Feature",
  "properties": {
    "iso:country":"DE",
    "sg:address":"Saatweg 5",
    "sg:city":"H\u00fcnxe",
    "sg:phone":"+49 2064/35285",
    "sg:postcode":"46569",
    "sg:province":"Nordrhein-Westfalen",
    "wof:name":"Joh.-wilhelm Driesen Masseur",
    "wof:placetype":"venue"
},
  "geometry": {"coordinates":[6.729739,51.602997],"type":"Point"}
}