{
  "type": "Feature",
  "properties": {
    "iso:country":"DE",
    "sg:address":"Friedrich-Ebert-Str. 7",
    "sg:city":"Kriftel",
    "sg:phone":"+49 6192/43277",
    "sg:postcode":"65830",
    "sg:province":"Hessen",
    "wof:name":"Gerhard Keil",
    "wof:placetype":"venue"
},
  "geometry": {"coordinates":[8.4747867584,50.0832099915],"type":"Point"}
}