{
  "type": "Feature",
  "properties": {
    "iso:country":"DE",
    "sg:address":"Wipperweg 2",
    "sg:city":"Halle",
    "sg:postcode":"06122",
    "sg:province":"Sachsen-Anhalt",
    "wof:name":"Seidel Verwaltungs Gmbh",
    "wof:placetype":"venue"
},
  "geometry": {"coordinates":[11.942644,51.48748],"type":"Point"}
}