{
  "type": "Feature",
  "properties": {
    "iso:country":"DE",
    "sg:address":"Hafenweg 46-48",
    "sg:city":"M\u00fcnster",
    "sg:phone":"+49 251/60670",
    "sg:postcode":"48155",
    "sg:province":"Nordrhein-Westfalen",
    "wof:name":"B & W Telefonmarketing Customer-care Solutions Gmbh",
    "wof:placetype":"venue"
},
  "geometry": {"coordinates":[7.649617,51.951962],"type":"Point"}
}