{
  "type": "Feature",
  "properties": {
    "iso:country":"DE",
    "sg:address":"Mauerwiesenstr. 1",
    "sg:city":"Jettingen",
    "sg:phone":"+49 7452/76760",
    "sg:postcode":"71131",
    "sg:province":"Baden-W\u00fcrttemberg",
    "wof:name":"Harald Wilms Masseur",
    "wof:placetype":"venue"
},
  "geometry": {"coordinates":[8.781544,48.56871],"type":"Point"}
}