{
  "type": "Feature",
  "properties": {
    "iso:country":"DE",
    "sg:address":"Schlo\u00dfstr. 49",
    "sg:city":"Berlin",
    "sg:phone":"+49 30/3416465",
    "sg:postcode":"14059",
    "sg:province":"Berlin",
    "wof:name":"Karl-heinz Stache Gmbh",
    "wof:placetype":"venue"
},
  "geometry": {"coordinates":[13.2971010208,52.5149345398],"type":"Point"}
}