{
  "type": "Feature",
  "properties": {
    "iso:country":"DE",
    "sg:address":"M\u00fcnsterstr. 45",
    "sg:city":"Rheine",
    "sg:phone":"+49 5971/56142",
    "sg:postcode":"48431",
    "sg:province":"Nordrhein-Westfalen",
    "wof:name":"Wilfried Hartmann",
    "wof:placetype":"venue"
},
  "geometry": {"coordinates":[7.4411420822,52.2772369385],"type":"Point"}
}