{
  "type": "Feature",
  "properties": {
    "iso:country":"DE",
    "sg:address":"Bahnhofstr. 42",
    "sg:city":"Worbis",
    "sg:phone":"+49 36074/92197",
    "sg:postcode":"37339",
    "sg:province":"Th\u00fcringen",
    "wof:name":"J\u00fcttner-orthop\u00e4die Kg",
    "wof:placetype":"venue"
},
  "geometry": {"coordinates":[10.3615436554,51.4190864563],"type":"Point"}
}