{
  "type": "Feature",
  "properties": {
    "iso:country":"DE",
    "sg:address":"Gietlstr. 8",
    "sg:city":"M\u00fcnchen",
    "sg:phone":"+49 89/6913246",
    "sg:postcode":"81541",
    "sg:province":"Bayern",
    "wof:name":"Ingeborg Gramlich",
    "wof:placetype":"venue"
},
  "geometry": {"coordinates":[11.5795850754,48.117023468],"type":"Point"}
}