{
  "type": "Feature",
  "properties": {
    "iso:country":"DE",
    "sg:address":"Ro\u00dfm\u00fchle 28",
    "sg:city":"Hamminkeln",
    "sg:phone":"+49 2852/72157",
    "sg:postcode":"46499",
    "sg:province":"Nordrhein-Westfalen",
    "wof:name":"Andreas Heinemann",
    "wof:placetype":"venue"
},
  "geometry": {"coordinates":[6.583905,51.727585],"type":"Point"}
}