{
  "type": "Feature",
  "properties": {
    "iso:country":"DE",
    "sg:address":"Silbergrund 5",
    "sg:city":"Suhl",
    "sg:phone":"+49 3681/44900",
    "sg:postcode":"98528",
    "sg:province":"Th\u00fcringen",
    "wof:name":"Intergeo Ingenieurgmbh",
    "wof:placetype":"venue"
},
  "geometry": {"coordinates":[10.7245569229,50.6403503418],"type":"Point"}
}