{
  "type": "Feature",
  "properties": {
    "iso:country":"DE",
    "sg:address":"Hauptstr. 7",
    "sg:city":"Pressath",
    "sg:phone":"+49 9644/287",
    "sg:postcode":"92690",
    "sg:province":"Bayern",
    "wof:name":"Gasthof Weyh",
    "wof:placetype":"venue"
},
  "geometry": {"coordinates":[11.9334335327,49.7693977356],"type":"Point"}
}