{
  "type": "Feature",
  "properties": {
    "iso:country":"DE",
    "sg:address":"Adolf-Dembach-Str. 5",
    "sg:city":"Krefeld",
    "sg:phone":"+49 2151/49350",
    "sg:postcode":"47829",
    "sg:province":"Nordrhein-Westfalen",
    "wof:name":"Deco Design F\u00fcrus Gmbh",
    "wof:placetype":"venue"
},
  "geometry": {"coordinates":[6.6399798393,51.3693504333],"type":"Point"}
}