{
  "type": "Feature",
  "properties": {
    "iso:country":"DE",
    "sg:address":"Maximilian-Kolbe-Str. 30",
    "sg:city":"Schwalmtal",
    "sg:phone":"+49 2163/10063",
    "sg:postcode":"41366",
    "sg:province":"Nordrhein-Westfalen",
    "wof:name":"Schumacher Baugesellschaft Mbh",
    "wof:placetype":"venue"
},
  "geometry": {"coordinates":[6.235461235,51.2314834595],"type":"Point"}
}