{
  "type": "Feature",
  "properties": {
    "iso:country":"DE",
    "sg:address":"Tonhallenstr. 2",
    "sg:city":"Minden",
    "sg:phone":"+49 571/84568",
    "sg:postcode":"32423",
    "sg:province":"Nordrhein-Westfalen",
    "wof:name":"Houcine Hamida Sport- Und Fitnesscenter",
    "wof:placetype":"venue"
},
  "geometry": {"coordinates":[8.9182271957,52.2873764038],"type":"Point"}
}