{
  "type": "Feature",
  "properties": {
    "iso:country":"DE",
    "sg:address":"Leipziger Str. 1",
    "sg:city":"Frankfurt",
    "sg:phone":"+49 69/9712880",
    "sg:postcode":"60487",
    "sg:province":"Hessen",
    "wof:name":"Cennections Zweigniederl. Der Usit",
    "wof:placetype":"venue"
},
  "geometry": {"coordinates":[8.6498632431,50.120223999],"type":"Point"}
}