{
  "type": "Feature",
  "properties": {
    "iso:country":"DE",
    "sg:address":"Egerlandring 17",
    "sg:city":"Kaufbeuren",
    "sg:phone":"+49 8341/64144",
    "sg:postcode":"87600",
    "sg:province":"Bayern",
    "wof:name":"H. J\u00e4hne",
    "wof:placetype":"venue"
},
  "geometry": {"coordinates":[10.6381187439,47.9019203186],"type":"Point"}
}