{
  "type": "Feature",
  "properties": {
    "iso:country":"DE",
    "sg:address":"Wackerstr. 78",
    "sg:city":"Burghausen",
    "sg:phone":"+49 8677/7726",
    "sg:postcode":"84489",
    "sg:province":"Bayern",
    "wof:name":"Hans Romeder Wettannahme",
    "wof:placetype":"venue"
},
  "geometry": {"coordinates":[12.838001,48.17268],"type":"Point"}
}