{
  "type": "Feature",
  "properties": {
    "iso:country":"DE",
    "sg:address":"Eichenstr. 101",
    "sg:city":"Moers",
    "sg:phone":"+49 2841/54670",
    "sg:postcode":"47443",
    "sg:province":"Nordrhein-Westfalen",
    "wof:name":"H. Rosing",
    "wof:placetype":"venue"
},
  "geometry": {"coordinates":[6.6731247902,51.451423645],"type":"Point"}
}