{
  "type": "Feature",
  "properties": {
    "iso:country":"DE",
    "sg:address":"Breslauer Str. 2",
    "sg:city":"Rehburg-Loccum",
    "sg:phone":"+49 5037/3641",
    "sg:postcode":"31547",
    "sg:province":"Niedersachsen",
    "wof:name":"W. Winkelhake",
    "wof:placetype":"venue"
},
  "geometry": {"coordinates":[9.225651741,52.4870414734],"type":"Point"}
}