{
  "type": "Feature",
  "properties": {
    "iso:country":"DE",
    "sg:address":"M\u00fcllheimer Str. 34",
    "sg:city":"Neuenburg",
    "sg:phone":"+49 7631/73991",
    "sg:postcode":"79395",
    "sg:province":"Baden-W\u00fcrttemberg",
    "wof:name":"Gubi Lebensmittel- Betriebe Gmbh & Co.",
    "wof:placetype":"venue"
},
  "geometry": {"coordinates":[7.5686979294,47.811920166],"type":"Point"}
}