{
  "type": "Feature",
  "properties": {
    "iso:country":"DE",
    "sg:address":"Reinickendorfer Str. 57",
    "sg:city":"Berlin",
    "sg:phone":"+49 30/4552075",
    "sg:postcode":"13347",
    "sg:province":"Berlin",
    "wof:name":"Kaiser-wilhelm Und Augusta-stiftung",
    "wof:placetype":"venue"
},
  "geometry": {"coordinates":[13.366742,52.553257],"type":"Point"}
}