{
  "type": "Feature",
  "properties": {
    "iso:country":"DE",
    "sg:address":"Langhansstr. 7",
    "sg:city":"Solingen",
    "sg:phone":"+49 212/74120",
    "sg:postcode":"42697",
    "sg:province":"Nordrhein-Westfalen",
    "wof:name":"Tapiros Rohsland Gmbh",
    "wof:placetype":"venue"
},
  "geometry": {"coordinates":[6.990719,51.155548],"type":"Point"}
}