{
  "type": "Feature",
  "properties": {
    "iso:country":"DE",
    "sg:address":"Bohlweg 66-68",
    "sg:city":"M\u00fcnster",
    "sg:postcode":"48147",
    "sg:province":"Nordrhein-Westfalen",
    "wof:name":"Aldi Gmbh & Co. Kg",
    "wof:placetype":"venue"
},
  "geometry": {"coordinates":[7.6424970627,51.9672355652],"type":"Point"}
}