{
  "type": "Feature",
  "properties": {
    "iso:country":"DE",
    "sg:address":"R\u00fcdigerstr. 20",
    "sg:city":"D\u00fcsseldorf",
    "sg:postcode":"40472",
    "sg:province":"Nordrhein-Westfalen",
    "wof:name":"Unterst\u00fctzungseinrichtung Nach Hermann R\u00f6mer Gmbh",
    "wof:placetype":"venue"
},
  "geometry": {"coordinates":[6.82225,51.261562],"type":"Point"}
}