{
  "type": "Feature",
  "properties": {
    "iso:country":"DE",
    "sg:address":"Martin-Luther-Str. 4",
    "sg:city":"Neugersdorf",
    "sg:phone":"+49 3586/702443",
    "sg:postcode":"02727",
    "sg:province":"Sachsen",
    "wof:name":"Bauspezi Baumarkt Kretschmer Gmbh",
    "wof:placetype":"venue"
},
  "geometry": {"coordinates":[14.6033735275,50.974822998],"type":"Point"}
}