{
  "type": "Feature",
  "properties": {
    "iso:country":"DE",
    "sg:address":"M\u00fcnsterstr. 33",
    "sg:city":"Senden",
    "sg:phone":"+49 2597/449",
    "sg:postcode":"48308",
    "sg:province":"Nordrhein-Westfalen",
    "wof:name":"Wilhelm Schr\u00f6der",
    "wof:placetype":"venue"
},
  "geometry": {"coordinates":[7.489085,51.856514],"type":"Point"}
}