{
  "type": "Feature",
  "properties": {
    "iso:country":"DE",
    "sg:address":"Eichwaldstr. 86",
    "sg:city":"Dortmund",
    "sg:phone":"+49 231/4270768",
    "sg:postcode":"44319",
    "sg:province":"Nordrhein-Westfalen",
    "wof:name":"Horst Pelz Sonnenschutz",
    "wof:placetype":"venue"
},
  "geometry": {"coordinates":[7.6012921333,51.5395126343],"type":"Point"}
}