{
  "type": "Feature",
  "properties": {
    "iso:country":"DE",
    "sg:address":"T\u00f6nisberger Str. 1",
    "sg:city":"Rheurdt",
    "sg:phone":"+49 2845/6202",
    "sg:postcode":"47509",
    "sg:province":"Nordrhein-Westfalen",
    "wof:name":"K. P. Hauser",
    "wof:placetype":"venue"
},
  "geometry": {"coordinates":[6.4836587906,51.4421424866],"type":"Point"}
}