{
  "type": "Feature",
  "properties": {
    "iso:country":"DE",
    "sg:address":"Rohrer H\u00f6he 60",
    "sg:city":"Stuttgart",
    "sg:phone":"+49 711/741690",
    "sg:postcode":"70565",
    "sg:province":"Baden-W\u00fcrttemberg",
    "wof:name":"Prof. Albert G. Burkhardt",
    "wof:placetype":"venue"
},
  "geometry": {"coordinates":[9.0927886963,48.7170143127],"type":"Point"}
}