{
  "type": "Feature",
  "properties": {
    "iso:country":"DE",
    "sg:address":"Ootmarsumer Weg 14",
    "sg:city":"Nordhorn",
    "sg:phone":"+49 5921/878398",
    "sg:postcode":"48527",
    "sg:province":"Niedersachsen",
    "wof:name":"St\u00e4dt. Galerie Nordhorn",
    "wof:placetype":"venue"
},
  "geometry": {"coordinates":[7.057168,52.43092],"type":"Point"}
}