{
  "type": "Feature",
  "properties": {
    "iso:country":"DE",
    "sg:address":"Prellerstr. 47",
    "sg:city":"Leipzig",
    "sg:phone":"+49 341/5852539",
    "sg:postcode":"04155",
    "sg:province":"Sachsen",
    "wof:name":"Bernd Heyne",
    "wof:placetype":"venue"
},
  "geometry": {"coordinates":[12.372132,51.358341],"type":"Point"}
}