{
  "type": "Feature",
  "properties": {
    "iso:country":"DE",
    "sg:city":"Oy-Mittelberg",
    "sg:phone":"+49 8366/494",
    "sg:postcode":"87466",
    "sg:province":"Bayern",
    "wof:name":"Gemeindeb\u00fccherei Schule",
    "wof:placetype":"venue"
},
  "geometry": {"coordinates":[10.4547,47.64336],"type":"Point"}
}