{
  "type": "Feature",
  "properties": {
    "iso:country":"DE",
    "sg:address":"Beckhausstr. 141",
    "sg:city":"Bielefeld",
    "sg:phone":"+49 521/81819",
    "sg:postcode":"33611",
    "sg:province":"Nordrhein-Westfalen",
    "wof:name":"Gisela Ebersbach",
    "wof:placetype":"venue"
},
  "geometry": {"coordinates":[8.544003,52.047699],"type":"Point"}
}