{
  "type": "Feature",
  "properties": {
    "iso:country":"DE",
    "sg:address":"Moorenstr. 4",
    "sg:city":"D\u00fcsseldorf",
    "sg:postcode":"40225",
    "sg:province":"Nordrhein-Westfalen",
    "wof:name":"Sun Life Reiseveranstaltungs Gmbh",
    "wof:placetype":"venue"
},
  "geometry": {"coordinates":[6.7834091187,51.1984443665],"type":"Point"}
}