{
  "type": "Feature",
  "properties": {
    "iso:country":"DE",
    "sg:address":"Vaihinger Str. 76",
    "sg:city":"Illingen",
    "sg:phone":"+49 7042/820072",
    "sg:postcode":"75428",
    "sg:province":"Baden-W\u00fcrttemberg",
    "wof:name":"Tino Peters Heilpraktiker",
    "wof:placetype":"venue"
},
  "geometry": {"coordinates":[8.9259519577,48.9515533447],"type":"Point"}
}