{
  "type": "Feature",
  "properties": {
    "iso:country":"DE",
    "sg:address":"Mozartstr. 14",
    "sg:city":"Spremberg",
    "sg:phone":"+49 3563/92628",
    "sg:postcode":"03130",
    "sg:province":"Brandenburg",
    "wof:name":"Arthur Wieland",
    "wof:placetype":"venue"
},
  "geometry": {"coordinates":[14.384852,51.575703],"type":"Point"}
}