{
  "type": "Feature",
  "properties": {
    "iso:country":"DE",
    "sg:address":"Kronsbruch 31",
    "sg:city":"Winsen",
    "sg:phone":"+49 4171/72227",
    "sg:postcode":"21423",
    "sg:province":"Niedersachsen",
    "wof:name":"Siegfried Wenske",
    "wof:placetype":"venue"
},
  "geometry": {"coordinates":[10.2205438614,53.3555183411],"type":"Point"}
}