{
  "type": "Feature",
  "properties": {
    "iso:country":"DE",
    "sg:address":"Igelweg 4",
    "sg:city":"Neuwied",
    "sg:phone":"+49 2622/83316",
    "sg:postcode":"56566",
    "sg:province":"Rheinland-Pfalz",
    "wof:name":"Autocolor Center Herbert Schlupp",
    "wof:placetype":"venue"
},
  "geometry": {"coordinates":[7.54422,50.43581],"type":"Point"}
}