{
  "type": "Feature",
  "properties": {
    "iso:country":"DE",
    "sg:address":"Am Hornberg 7",
    "sg:city":"Soltau",
    "sg:phone":"+49 5191/14148",
    "sg:postcode":"29614",
    "sg:province":"Niedersachsen",
    "wof:name":"Otto Elbers",
    "wof:placetype":"venue"
},
  "geometry": {"coordinates":[9.818266,52.972908],"type":"Point"}
}