{
  "type": "Feature",
  "properties": {
    "iso:country":"DE",
    "sg:address":"Hauptstr. 22",
    "sg:city":"Hambergen",
    "sg:phone":"+49 4793/1852",
    "sg:postcode":"27729",
    "sg:province":"Niedersachsen",
    "wof:name":"Apotheke",
    "wof:placetype":"venue"
},
  "geometry": {"coordinates":[8.832856,53.309437],"type":"Point"}
}