{
  "type": "Feature",
  "properties": {
    "iso:country":"DE",
    "sg:address":"Osterrade 33",
    "sg:city":"Hamburg",
    "sg:phone":"+49 40/7302657",
    "sg:postcode":"21031",
    "sg:province":"Hamburg",
    "wof:name":"Rolf Warmer Verwaltungsgesellschaft Mbh",
    "wof:placetype":"venue"
},
  "geometry": {"coordinates":[10.183355,53.510166],"type":"Point"}
}