{
  "type": "Feature",
  "properties": {
    "iso:country":"DE",
    "sg:address":"Hattenb\u00fchl 24",
    "sg:city":"Stuttgart",
    "sg:phone":"+49 711/855353",
    "sg:postcode":"70469",
    "sg:province":"Baden-W\u00fcrttemberg",
    "wof:name":"Verm\u00f6gensverwaltungsges. Joachim Seidl Mbh",
    "wof:placetype":"venue"
},
  "geometry": {"coordinates":[9.1483716965,48.8162689209],"type":"Point"}
}