{
  "type": "Feature",
  "properties": {
    "iso:country":"DE",
    "sg:address":"Rheinweg 1",
    "sg:city":"Bonn",
    "sg:phone":"+49 228/238264",
    "sg:postcode":"53113",
    "sg:province":"Nordrhein-Westfalen",
    "wof:name":"L. Schmitz Immobilienmakler",
    "wof:placetype":"venue"
},
  "geometry": {"coordinates":[7.1196460724,50.716999054],"type":"Point"}
}