{
  "type": "Feature",
  "properties": {
    "iso:country":"DE",
    "sg:address":"Kirchstr. 60",
    "sg:city":"Wagh\u00e4usel",
    "sg:phone":"+49 7254/4770",
    "sg:postcode":"68753",
    "sg:province":"Baden-W\u00fcrttemberg",
    "wof:name":"Theo Steinel",
    "wof:placetype":"venue"
},
  "geometry": {"coordinates":[8.518239975,49.2206573486],"type":"Point"}
}