{
  "type": "Feature",
  "properties": {
    "iso:country":"DE",
    "sg:address":"Fronm\u00fcllerstr. 78",
    "sg:city":"F\u00fcrth",
    "sg:phone":"+49 911/708789",
    "sg:postcode":"90763",
    "sg:province":"Bayern",
    "wof:name":"Pizza Hut",
    "wof:placetype":"venue"
},
  "geometry": {"coordinates":[11.0015993118,49.4584503174],"type":"Point"}
}