{
  "type": "Feature",
  "properties": {
    "iso:country":"DE",
    "sg:address":"Neerbargen 8",
    "sg:city":"Rhauderfehn",
    "sg:phone":"+49 4952/3737",
    "sg:postcode":"26817",
    "sg:province":"Niedersachsen",
    "wof:name":"U. Neelen",
    "wof:placetype":"venue"
},
  "geometry": {"coordinates":[7.534069,53.162636],"type":"Point"}
}