{
  "type": "Feature",
  "properties": {
    "iso:country":"DE",
    "sg:address":"Hauptstr. 23",
    "sg:city":"Sehnde",
    "sg:phone":"+49 5138/1323",
    "sg:postcode":"31319",
    "sg:province":"Niedersachsen",
    "wof:name":"Pohl",
    "wof:placetype":"venue"
},
  "geometry": {"coordinates":[10.005824,52.315536],"type":"Point"}
}