{
  "type": "Feature",
  "properties": {
    "iso:country":"DE",
    "sg:address":"Str\u00fcmpfelbacher Str. 71",
    "sg:city":"Aichwald",
    "sg:phone":"+49 711/361953",
    "sg:postcode":"73773",
    "sg:province":"Baden-W\u00fcrttemberg",
    "wof:name":"Reinhard Sucker",
    "wof:placetype":"venue"
},
  "geometry": {"coordinates":[9.3899202347,48.7760505676],"type":"Point"}
}