{
  "type": "Feature",
  "properties": {
    "iso:country":"DE",
    "sg:address":"Bahnhofstr. 13",
    "sg:city":"Neukirchen",
    "sg:phone":"+49 9663/1244",
    "sg:postcode":"92259",
    "sg:province":"Bayern",
    "wof:name":"Leonhard Strobel",
    "wof:placetype":"venue"
},
  "geometry": {"coordinates":[11.622508049,49.5263938904],"type":"Point"}
}