{
  "type": "Feature",
  "properties": {
    "iso:country":"DE",
    "sg:address":"Dorfstr. 1",
    "sg:city":"Wustrow",
    "sg:phone":"+49 39828/20128",
    "sg:postcode":"17255",
    "sg:province":"Mecklenburg-Vorpommern",
    "wof:name":"B. Plehn",
    "wof:placetype":"venue"
},
  "geometry": {"coordinates":[12.968856,53.23119],"type":"Point"}
}