{
  "type": "Feature",
  "properties": {
    "iso:country":"DE",
    "sg:address":"Fo\u00dfredder 26",
    "sg:city":"Hamburg",
    "sg:phone":"+49 40/6038272",
    "sg:postcode":"22359",
    "sg:province":"Hamburg",
    "wof:name":"Albert J\u00e4ger",
    "wof:placetype":"venue"
},
  "geometry": {"coordinates":[10.1719121933,53.6459960938],"type":"Point"}
}