{
  "type": "Feature",
  "properties": {
    "iso:country":"DE",
    "sg:address":"Vohwinkeler Str. 100",
    "sg:city":"Wuppertal",
    "sg:phone":"+49 202/747080",
    "sg:postcode":"42329",
    "sg:province":"Nordrhein-Westfalen",
    "wof:name":"Bluetek Gesellschaft F\u00fcr Telekommunikations-",
    "wof:placetype":"venue"
},
  "geometry": {"coordinates":[7.0604629517,51.2276535034],"type":"Point"}
}