{
  "type": "Feature",
  "properties": {
    "iso:country":"DE",
    "sg:address":"Wangern 17 a",
    "sg:city":"Insel Poel",
    "sg:phone":"+49 38425/21295",
    "sg:postcode":"23999",
    "sg:province":"Mecklenburg-Vorpommern",
    "wof:name":"Wirtshaus Steinhagen Inh. Torsten Feiler",
    "wof:placetype":"venue"
},
  "geometry": {"coordinates":[11.4107046127,53.9833335876],"type":"Point"}
}