{
  "type": "Feature",
  "properties": {
    "iso:country":"DE",
    "sg:address":"Hermannsteiner Str. 46",
    "sg:city":"Wetzlar",
    "sg:phone":"+49 6441/32862",
    "sg:postcode":"35576",
    "sg:province":"Hessen",
    "wof:name":"Werner Seidel",
    "wof:placetype":"venue"
},
  "geometry": {"coordinates":[8.4982004166,50.570274353],"type":"Point"}
}