{
  "type": "Feature",
  "properties": {
    "iso:country":"DE",
    "sg:address":"Goethestr. 21",
    "sg:city":"Potsdam",
    "sg:phone":"+49 331/716657",
    "sg:postcode":"14482",
    "sg:province":"Brandenburg",
    "wof:name":"Manfred Geyer",
    "wof:placetype":"venue"
},
  "geometry": {"coordinates":[13.1043262482,52.3959236145],"type":"Point"}
}