{
  "type": "Feature",
  "properties": {
    "iso:country":"DE",
    "sg:address":"Frankfurter Landstr. 116",
    "sg:city":"Darmstadt",
    "sg:postcode":"64291",
    "sg:province":"Hessen",
    "wof:name":"Satz- Und Verlags Gmbh",
    "wof:placetype":"venue"
},
  "geometry": {"coordinates":[8.6567678452,49.9085617065],"type":"Point"}
}