{
  "type": "Feature",
  "properties": {
    "iso:country":"DE",
    "sg:address":"Schillerstr. 2",
    "sg:city":"Pritzwalk",
    "sg:phone":"+49 3395/302019",
    "sg:postcode":"16928",
    "sg:province":"Brandenburg",
    "wof:name":"B. Pettke",
    "wof:placetype":"venue"
},
  "geometry": {"coordinates":[12.1784362793,53.1540718079],"type":"Point"}
}