{
  "type": "Feature",
  "properties": {
    "iso:country":"DE",
    "sg:address":"Oehmer Feld 1",
    "sg:city":"Leese",
    "sg:phone":"+49 5761/3293",
    "sg:postcode":"31633",
    "sg:province":"Niedersachsen",
    "wof:name":"Blindenwerkstatt",
    "wof:placetype":"venue"
},
  "geometry": {"coordinates":[9.132686,52.525131],"type":"Point"}
}