{
  "type": "Feature",
  "properties": {
    "iso:country":"DE",
    "sg:address":"Hauptstr. 13",
    "sg:city":"Bernkastel-Kues",
    "sg:phone":"+49 6531/2196",
    "sg:postcode":"54470",
    "sg:province":"Rheinland-Pfalz",
    "wof:name":"Gerd Friedrich",
    "wof:placetype":"venue"
},
  "geometry": {"coordinates":[7.059505,49.938667],"type":"Point"}
}