{
  "type": "Feature",
  "properties": {
    "iso:country":"DE",
    "sg:address":"Steinsdorf 76",
    "sg:city":"Steinsdorf",
    "sg:phone":"+49 36603/62723",
    "sg:postcode":"07570",
    "sg:province":"Th\u00fcringen",
    "wof:name":"Berthold Oettler",
    "wof:placetype":"venue"
},
  "geometry": {"coordinates":[12.03697,50.745354],"type":"Point"}
}