{
  "type": "Feature",
  "properties": {
    "iso:country":"DE",
    "sg:address":"Stettener Str. 9",
    "sg:city":"Meersburg",
    "sg:phone":"+49 7532/6088",
    "sg:postcode":"88709",
    "sg:province":"Baden-W\u00fcrttemberg",
    "wof:name":"Droste-museum Im F\u00fcrstenh\u00e4usle",
    "wof:placetype":"venue"
},
  "geometry": {"coordinates":[9.275667,47.694202],"type":"Point"}
}