{
  "type": "Feature",
  "properties": {
    "iso:country":"DE",
    "sg:address":"Im Anw\u00e4nder 25",
    "sg:city":"Auenwald",
    "sg:phone":"+49 7191/310733",
    "sg:postcode":"71549",
    "sg:province":"Baden-W\u00fcrttemberg",
    "wof:name":"Payer-tuning",
    "wof:placetype":"venue"
},
  "geometry": {"coordinates":[9.495479,48.944668],"type":"Point"}
}