{
  "type": "Feature",
  "properties": {
    "iso:country":"DE",
    "sg:address":"Kalistra\u00dfe 13",
    "sg:city":"Sollstedt",
    "sg:postcode":"99759",
    "sg:province":"Th\u00fcringen",
    "wof:name":"Ataa.de - Discount Autoteile Auf Abruf",
    "wof:placetype":"venue"
},
  "geometry": {"coordinates":[10.5283708572,51.4155235291],"type":"Point"}
}