{
  "type": "Feature",
  "properties": {
    "iso:country":"DE",
    "sg:address":"Hein-Sa\u00df-Weg 21",
    "sg:city":"Hamburg",
    "sg:phone":"+49 40/7421990",
    "sg:postcode":"21129",
    "sg:province":"Hamburg",
    "wof:name":"Heinrich Quast Sonderdrehteile Gmbh",
    "wof:placetype":"venue"
},
  "geometry": {"coordinates":[9.8654546738,53.5363082886],"type":"Point"}
}