{
  "type": "Feature",
  "properties": {
    "iso:country":"DE",
    "sg:address":"Bergedorfer Str. 106",
    "sg:city":"Hamburg",
    "sg:phone":"+49 491/80070",
    "sg:postcode":"21029",
    "sg:province":"Hamburg",
    "wof:name":"Kautex Textron Gmbh & Co.kg",
    "wof:placetype":"venue"
},
  "geometry": {"coordinates":[7.4124898911,53.2655487061],"type":"Point"}
}