{
  "type": "Feature",
  "properties": {
    "iso:country":"DE",
    "sg:address":"Klosterstr. 3",
    "sg:city":"\u00dcberlingen",
    "sg:phone":"+49 7551/67979",
    "sg:postcode":"88662",
    "sg:province":"Baden-W\u00fcrttemberg",
    "wof:name":"I. M\u00f6nkemeyer",
    "wof:placetype":"venue"
},
  "geometry": {"coordinates":[9.156544,47.767796],"type":"Point"}
}