{
  "type": "Feature",
  "properties": {
    "iso:country":"DE",
    "sg:address":"Wielandstr. 3",
    "sg:city":"Hermsdorf",
    "sg:phone":"+49 36601/82902",
    "sg:postcode":"07629",
    "sg:province":"Th\u00fcringen",
    "wof:name":"Eberhard Schmidt",
    "wof:placetype":"venue"
},
  "geometry": {"coordinates":[11.862119,50.899887],"type":"Point"}
}