{
  "type": "Feature",
  "properties": {
    "iso:country":"DE",
    "sg:address":"Pfarrer-Holtmann-Str. 5",
    "sg:city":"Vreden",
    "sg:phone":"+49 2564/4539",
    "sg:postcode":"48691",
    "sg:province":"Nordrhein-Westfalen",
    "wof:name":"Denno",
    "wof:placetype":"venue"
},
  "geometry": {"coordinates":[6.7661218643,52.0647964478],"type":"Point"}
}