{
  "type": "Feature",
  "properties": {
    "iso:country":"DE",
    "sg:address":"Altheck 18",
    "sg:city":"Longkamp",
    "sg:phone":"+49 6531/94677",
    "sg:postcode":"54472",
    "sg:province":"Rheinland-Pfalz",
    "wof:name":"Drachenflugschule Saar-mosel",
    "wof:placetype":"venue"
},
  "geometry": {"coordinates":[7.117524147,49.8927764893],"type":"Point"}
}