{
  "type": "Feature",
  "properties": {
    "iso:country":"DE",
    "sg:address":"Hauptstr. 7",
    "sg:city":"Tiefenbach",
    "sg:postcode":"84184",
    "sg:province":"Bayern",
    "wof:name":"Katholisches Pfarramt St. Michael",
    "wof:placetype":"venue"
},
  "geometry": {"coordinates":[12.0974092484,48.5106925964],"type":"Point"}
}