{
  "type": "Feature",
  "properties": {
    "iso:country":"DE",
    "sg:address":"M\u00fchlenbachstr. 2",
    "sg:city":"Neuss",
    "sg:phone":"+49 2131/542076",
    "sg:postcode":"41462",
    "sg:province":"Nordrhein-Westfalen",
    "wof:name":"Hans Panzer Elektroinstallation",
    "wof:placetype":"venue"
},
  "geometry": {"coordinates":[6.656836,51.225586],"type":"Point"}
}