{
  "type": "Feature",
  "properties": {
    "iso:country":"DE",
    "sg:address":"Hillmannstr. 23",
    "sg:city":"Alt\u00f6tting",
    "sg:phone":"+49 8671/5509",
    "sg:postcode":"84503",
    "sg:province":"Bayern",
    "wof:name":"Gesellschaft F\u00fcr Lagereibetriebe Mbh",
    "wof:placetype":"venue"
},
  "geometry": {"coordinates":[12.675228,48.220226],"type":"Point"}
}