{
  "type": "Feature",
  "properties": {
    "iso:country":"DE",
    "sg:address":"Nassauische Str. 45",
    "sg:city":"Berlin",
    "sg:phone":"+49 30/8739297",
    "sg:postcode":"10717",
    "sg:province":"Berlin",
    "wof:name":"Karl-heinz Ziefle Rechtsanwalt",
    "wof:placetype":"venue"
},
  "geometry": {"coordinates":[13.3267641068,52.4887046814],"type":"Point"}
}