{
  "type": "Feature",
  "properties": {
    "iso:country":"DE",
    "sg:address":"Markscheiderstr. 1",
    "sg:city":"Dortmund",
    "sg:phone":"+49 231/451939",
    "sg:postcode":"44269",
    "sg:province":"Nordrhein-Westfalen",
    "wof:name":"Gastst\u00e4tte Pik Bube",
    "wof:placetype":"venue"
},
  "geometry": {"coordinates":[7.5383849144,51.4977378845],"type":"Point"}
}