{
  "type": "Feature",
  "properties": {
    "iso:country":"DE",
    "sg:address":"Wilhelmsplatz 9",
    "sg:city":"Stuttgart",
    "sg:phone":"+49 711/210240",
    "sg:postcode":"70182",
    "sg:province":"Baden-W\u00fcrttemberg",
    "wof:name":"Hotel Am Wilhelmsplatz",
    "wof:placetype":"venue"
},
  "geometry": {"coordinates":[9.1787376404,48.770778656],"type":"Point"}
}