{
  "type": "Feature",
  "properties": {
    "iso:country":"DE",
    "sg:address":"Melkweg 2",
    "sg:city":"Schermbeck",
    "sg:phone":"+49 2853/4870",
    "sg:postcode":"46514",
    "sg:province":"Nordrhein-Westfalen",
    "wof:name":"Wilhelm M\u00f6lleken",
    "wof:placetype":"venue"
},
  "geometry": {"coordinates":[6.800012,51.679134],"type":"Point"}
}