{
  "type": "Feature",
  "properties": {
    "iso:country":"DE",
    "sg:address":"Oberweilerstr. 25",
    "sg:city":"Beuren",
    "sg:phone":"+49 7025/2833",
    "sg:postcode":"72660",
    "sg:province":"Baden-W\u00fcrttemberg",
    "wof:name":"E. Blank",
    "wof:placetype":"venue"
},
  "geometry": {"coordinates":[9.3896608353,48.5680618286],"type":"Point"}
}