{
  "type": "Feature",
  "properties": {
    "iso:country":"DE",
    "sg:address":"Meldorfer Str. 2",
    "sg:city":"Heide",
    "sg:phone":"+49 481/65232",
    "sg:postcode":"25746",
    "sg:province":"Schleswig-Holstein",
    "wof:name":"M\u00f6bel-laden Gmbh",
    "wof:placetype":"venue"
},
  "geometry": {"coordinates":[9.089852,54.192047],"type":"Point"}
}