{
  "type": "Feature",
  "properties": {
    "iso:country":"DE",
    "sg:address":"H\u00e4ndelstr. 7",
    "sg:city":"Elsdorf",
    "sg:phone":"+49 2274/6927",
    "sg:postcode":"50189",
    "sg:province":"Nordrhein-Westfalen",
    "wof:name":"Hans Dieter H\u00fctten Teppichhandlung",
    "wof:placetype":"venue"
},
  "geometry": {"coordinates":[6.568582058,50.9417648315],"type":"Point"}
}