{
  "type": "Feature",
  "properties": {
    "iso:country":"DE",
    "sg:address":"Uhlandweg 6",
    "sg:city":"Oerlinghausen",
    "sg:postcode":"33813",
    "sg:province":"Nordrhein-Westfalen",
    "wof:name":"Raimund Timmerhans Gmbh",
    "wof:placetype":"venue"
},
  "geometry": {"coordinates":[8.662713,51.937405],"type":"Point"}
}