{
  "type": "Feature",
  "properties": {
    "iso:country":"DE",
    "sg:address":"Dreim\u00fchlenstr. 16",
    "sg:city":"M\u00fcnchen",
    "sg:phone":"+49 89/764669",
    "sg:postcode":"80469",
    "sg:province":"Bayern",
    "wof:name":"Sami Hawari Antiquit\u00e4ten",
    "wof:placetype":"venue"
},
  "geometry": {"coordinates":[11.561077,48.122066],"type":"Point"}
}