{
  "type": "Feature",
  "properties": {
    "iso:country":"DE",
    "sg:address":"M\u00fchlgasse 15",
    "sg:city":"Rhodt",
    "sg:phone":"+49 6323/5164",
    "sg:postcode":"76835",
    "sg:province":"Rheinland-Pfalz",
    "wof:name":"Richard Anlag",
    "wof:placetype":"venue"
},
  "geometry": {"coordinates":[-81.12242126460001,38.9796791077],"type":"Point"}
}