{
  "type": "Feature",
  "properties": {
    "iso:country":"DE",
    "sg:address":"Theodor-Heuss-Stra\u00dfe 2-4",
    "sg:city":"Bonn",
    "sg:phone":"+49 228",
    "sg:postcode":"53095",
    "sg:province":"Nordrhein-Westfalen",
    "wof:name":"Fachverlag F\u00fcr Kommunikation Und Management",
    "wof:placetype":"venue"
},
  "geometry": {"coordinates":[7.161429882,50.6809043884],"type":"Point"}
}