{
  "type": "Feature",
  "properties": {
    "iso:country":"DE",
    "sg:address":"Forstenrieder Str. 10",
    "sg:city":"Neuried",
    "sg:phone":"+49 89/8999650",
    "sg:postcode":"82061",
    "sg:province":"Bayern",
    "wof:name":"Munich Biotech Ag",
    "wof:placetype":"venue"
},
  "geometry": {"coordinates":[11.467577,48.092037],"type":"Point"}
}