{
  "type": "Feature",
  "properties": {
    "iso:country":"DE",
    "sg:address":"Niedernstr. 12",
    "sg:city":"Sch\u00f6ningen",
    "sg:phone":"+49 4953/522045",
    "sg:postcode":"38364",
    "sg:province":"Niedersachsen",
    "wof:name":"Commerzbank Ag",
    "wof:placetype":"venue"
},
  "geometry": {"coordinates":[10.970074,52.138786],"type":"Point"}
}