{
  "type": "Feature",
  "properties": {
    "iso:country":"DE",
    "sg:address":"Rheinauer Str. 9",
    "sg:city":"Br\u00fchl",
    "sg:phone":"+49 6202/71210",
    "sg:postcode":"68782",
    "sg:province":"Baden-W\u00fcrttemberg",
    "wof:name":"Geppert Gmbh Mode",
    "wof:placetype":"venue"
},
  "geometry": {"coordinates":[8.521005,49.410072],"type":"Point"}
}