{
  "type": "Feature",
  "properties": {
    "iso:country":"DE",
    "sg:address":"M 2 17",
    "sg:city":"Mannheim",
    "sg:phone":"+49 621/20860",
    "sg:postcode":"68161",
    "sg:province":"Baden-W\u00fcrttemberg",
    "wof:name":"Siegels Bestattungs- Gesellschaft Mbh",
    "wof:placetype":"venue"
},
  "geometry": {"coordinates":[8.466785,49.486511],"type":"Point"}
}