{
  "type": "Feature",
  "properties": {
    "iso:country":"DE",
    "sg:address":"Widukindweg 11",
    "sg:city":"Marsberg",
    "sg:phone":"+49 2992/2295",
    "sg:postcode":"34431",
    "sg:province":"Nordrhein-Westfalen",
    "wof:name":"Schmitz Bau Gmbh",
    "wof:placetype":"venue"
},
  "geometry": {"coordinates":[8.831122,51.452553],"type":"Point"}
}