{
  "type": "Feature",
  "properties": {
    "iso:country":"DE",
    "sg:address":"Robert-Bosch-Str. 3",
    "sg:city":"Braunschweig",
    "sg:phone":"+49 4953/1210150",
    "sg:postcode":"38112",
    "sg:province":"Niedersachsen",
    "wof:name":"F.s. Fehrer Automotiv Foam Gmbh",
    "wof:placetype":"venue"
},
  "geometry": {"coordinates":[10.5075969696,52.3146591187],"type":"Point"}
}