{
  "type": "Feature",
  "properties": {
    "iso:country":"DE",
    "sg:address":"Bergstr. 4",
    "sg:city":"Kn\u00fcllwald",
    "sg:phone":"+49 5685/638",
    "sg:postcode":"34593",
    "sg:province":"Hessen",
    "wof:name":"Otto Siebert",
    "wof:placetype":"venue"
},
  "geometry": {"coordinates":[9.481691,51.04332],"type":"Point"}
}