{
  "type": "Feature",
  "properties": {
    "iso:country":"DE",
    "sg:address":"Brunnenstr. 4-6",
    "sg:city":"Hechingen",
    "sg:phone":"+49 7471/620715",
    "sg:postcode":"72379",
    "sg:province":"Baden-W\u00fcrttemberg",
    "wof:name":"Sternenb\u00e4ck Gmbh",
    "wof:placetype":"venue"
},
  "geometry": {"coordinates":[8.962621,48.367477],"type":"Point"}
}