{
  "type": "Feature",
  "properties": {
    "iso:country":"DE",
    "sg:address":"Stra\u00dfen 2",
    "sg:city":"Odenthal",
    "sg:phone":"+49 2202/79057",
    "sg:postcode":"51519",
    "sg:province":"Nordrhein-Westfalen",
    "wof:name":"Helmut Esser",
    "wof:placetype":"venue"
},
  "geometry": {"coordinates":[7.166566,51.014122],"type":"Point"}
}