{
  "type": "Feature",
  "properties": {
    "iso:country":"DE",
    "sg:address":"Weiherweg 6",
    "sg:city":"Bergen",
    "sg:phone":"+49 9148/828",
    "sg:postcode":"91790",
    "sg:province":"Bayern",
    "wof:name":"Willi Werzinger",
    "wof:placetype":"venue"
},
  "geometry": {"coordinates":[11.1165513992,49.0737304688],"type":"Point"}
}