{
  "type": "Feature",
  "properties": {
    "iso:country":"DE",
    "sg:address":"Weimarische Str. 6",
    "sg:city":"Buttelstedt",
    "sg:phone":"+49 36451/60462",
    "sg:postcode":"99439",
    "sg:province":"Th\u00fcringen",
    "wof:name":"A. Deregowski",
    "wof:placetype":"venue"
},
  "geometry": {"coordinates":[11.3426399231,51.0750427246],"type":"Point"}
}