{
  "type": "Feature",
  "properties": {
    "iso:country":"DE",
    "sg:address":"Arendsweg 58-74",
    "sg:city":"Berlin",
    "sg:phone":"+49 30/5588080",
    "sg:postcode":"13055",
    "sg:province":"Berlin",
    "wof:name":"Nas-berlin Homepage",
    "wof:placetype":"venue"
},
  "geometry": {"coordinates":[13.505658,52.539989],"type":"Point"}
}