{
  "type": "Feature",
  "properties": {
    "iso:country":"DE",
    "sg:address":"Pistoriusstr. 42",
    "sg:city":"Crailsheim",
    "sg:phone":"+49 7951/3040",
    "sg:postcode":"74564",
    "sg:province":"Baden-W\u00fcrttemberg",
    "wof:name":"B\u00f6hme Gmbh & Co. Kg",
    "wof:placetype":"venue"
},
  "geometry": {"coordinates":[10.0714797974,49.1295051575],"type":"Point"}
}