{
  "type": "Feature",
  "properties": {
    "iso:country":"DE",
    "sg:address":"Millener Weg 35",
    "sg:city":"Selfkant",
    "sg:phone":"+49 4924/563132",
    "sg:postcode":"52538",
    "sg:province":"Nordrhein-Westfalen",
    "wof:name":"Wilhelm Schroeder Lederhandelsgmbh",
    "wof:placetype":"venue"
},
  "geometry": {"coordinates":[5.887474,51.017506],"type":"Point"}
}