{
  "type": "Feature",
  "properties": {
    "iso:country":"DE",
    "sg:address":"Gr\u00fcninger Str. 5",
    "sg:city":"Stuttgart",
    "sg:phone":"+49 711/457420",
    "sg:postcode":"70599",
    "sg:province":"Baden-W\u00fcrttemberg",
    "wof:name":"Erich B\u00e4uerle Steuerberater",
    "wof:placetype":"venue"
},
  "geometry": {"coordinates":[9.2083396912,48.7215385437],"type":"Point"}
}