{
  "type": "Feature",
  "properties": {
    "iso:country":"DE",
    "sg:address":"Nordstr. 31",
    "sg:city":"J\u00fcchen",
    "sg:phone":"+49 2164/48392",
    "sg:postcode":"41363",
    "sg:province":"Nordrhein-Westfalen",
    "wof:name":"Heinz Aretz",
    "wof:placetype":"venue"
},
  "geometry": {"coordinates":[6.467341,51.075031],"type":"Point"}
}