{
  "type": "Feature",
  "properties": {
    "iso:country":"DE",
    "sg:address":"Herzog-Heinrich-Str. 4",
    "sg:city":"Stade",
    "sg:phone":"+49 4141/87428",
    "sg:postcode":"21683",
    "sg:province":"Niedersachsen",
    "wof:name":"Brunhilde Und Hans-h. Kittel",
    "wof:placetype":"venue"
},
  "geometry": {"coordinates":[9.4092302322,53.602016449],"type":"Point"}
}