{
  "type": "Feature",
  "properties": {
    "iso:country":"DE",
    "sg:address":"Paul-Seydel-Str. 13",
    "sg:city":"Limbach-Oberfrohna",
    "sg:postcode":"09212",
    "sg:province":"Sachsen",
    "wof:name":"Mirkwido-design",
    "wof:placetype":"venue"
},
  "geometry": {"coordinates":[12.757359,50.856667],"type":"Point"}
}