{
  "type": "Feature",
  "properties": {
    "iso:country":"DE",
    "sg:address":"Dorfplatz 14",
    "sg:city":"Neustadt",
    "sg:phone":"+49 36481/53764",
    "sg:postcode":"07806",
    "sg:province":"Th\u00fcringen",
    "wof:name":"Ellen Pieger",
    "wof:placetype":"venue"
},
  "geometry": {"coordinates":[10.467451,51.467964],"type":"Point"}
}