{
  "type": "Feature",
  "properties": {
    "iso:country":"DE",
    "sg:address":"Urdenbacher Dorfstr. 10",
    "sg:city":"D\u00fcsseldorf",
    "sg:phone":"+49 211/714979",
    "sg:postcode":"40593",
    "sg:province":"Nordrhein-Westfalen",
    "wof:name":"K. Braun",
    "wof:placetype":"venue"
},
  "geometry": {"coordinates":[6.867161,51.14893],"type":"Point"}
}