{
  "type": "Feature",
  "properties": {
    "iso:country":"DE",
    "sg:address":"Waldstr. 6",
    "sg:city":"Umkirch",
    "sg:phone":"+49 7665/7641",
    "sg:postcode":"79224",
    "sg:province":"Baden-W\u00fcrttemberg",
    "wof:name":"Cordula Lehrmann",
    "wof:placetype":"venue"
},
  "geometry": {"coordinates":[7.7680859566,48.0328102112],"type":"Point"}
}