{
  "type": "Feature",
  "properties": {
    "iso:country":"DE",
    "sg:address":"Josef-Frankl-Str. 44",
    "sg:city":"M\u00fcnchen",
    "sg:postcode":"80995",
    "sg:province":"Bayern",
    "wof:name":"Ps Promotion E. Kfm.",
    "wof:placetype":"venue"
},
  "geometry": {"coordinates":[11.5321702957,48.2151603699],"type":"Point"}
}