{
  "type": "Feature",
  "properties": {
    "iso:country":"DE",
    "sg:address":"Enzstr. 1 D",
    "sg:city":"Eggenstein-Leopoldshafen",
    "sg:phone":"+49 7247/22460",
    "sg:postcode":"76344",
    "sg:province":"Baden-W\u00fcrttemberg",
    "wof:name":"Otto Katalogshop H. Amann",
    "wof:placetype":"venue"
},
  "geometry": {"coordinates":[8.4030189514,49.0931053162],"type":"Point"}
}