{
  "type": "Feature",
  "properties": {
    "iso:country":"DE",
    "sg:address":"Habergasse 6",
    "sg:city":"Bamberg",
    "sg:phone":"+49 951/22566",
    "sg:postcode":"96047",
    "sg:province":"Bayern",
    "wof:name":"Weinstube R\u00fcckel",
    "wof:placetype":"venue"
},
  "geometry": {"coordinates":[10.8884420395,49.8920097351],"type":"Point"}
}