{
  "type": "Feature",
  "properties": {
    "iso:country":"DE",
    "sg:address":"Ziegelstr. 30",
    "sg:city":"Sindelfingen",
    "sg:phone":"+49 7031/810096",
    "sg:postcode":"71063",
    "sg:province":"Baden-W\u00fcrttemberg",
    "wof:name":"Juan Santos-rivera",
    "wof:placetype":"venue"
},
  "geometry": {"coordinates":[9.0016078949,48.7104415894],"type":"Point"}
}