{
  "type": "Feature",
  "properties": {
    "iso:country":"DE",
    "sg:address":"Paul-M\u00fcller-Str. 2",
    "sg:city":"Troisdorf",
    "sg:phone":"+49 2241/71576",
    "sg:postcode":"53840",
    "sg:province":"Nordrhein-Westfalen",
    "wof:name":"A. D\u00f6ren Rechtsanwalt",
    "wof:placetype":"venue"
},
  "geometry": {"coordinates":[7.1505250931,50.8158111572],"type":"Point"}
}