{
  "type": "Feature",
  "properties": {
    "iso:country":"DE",
    "sg:address":"Goethestr. 23",
    "sg:city":"Schwaikheim",
    "sg:phone":"+49 7195/51054",
    "sg:postcode":"71409",
    "sg:province":"Baden-W\u00fcrttemberg",
    "wof:name":"A. Bauer",
    "wof:placetype":"venue"
},
  "geometry": {"coordinates":[9.3494710922,48.875667572],"type":"Point"}
}