{
  "type": "Feature",
  "properties": {
    "iso:country":"DE",
    "sg:address":"Hauptstr. 17 a",
    "sg:city":"Rattiszell",
    "sg:phone":"+49 9964/610983",
    "sg:postcode":"94372",
    "sg:province":"Bayern",
    "wof:name":"Weber Gmbh",
    "wof:placetype":"venue"
},
  "geometry": {"coordinates":[12.609699,49.031551],"type":"Point"}
}