{
  "type": "Feature",
  "properties": {
    "iso:country":"DE",
    "sg:address":"Ismaninger Str. 19",
    "sg:city":"M\u00fcnchen",
    "sg:phone":"+49 89/47027220",
    "sg:postcode":"81675",
    "sg:province":"Bayern",
    "wof:name":"Mom Mall Of Munich Beteiligungs Gmbh & Co.",
    "wof:placetype":"venue"
},
  "geometry": {"coordinates":[11.598734,48.138424],"type":"Point"}
}