{
  "type": "Feature",
  "properties": {
    "iso:country":"DE",
    "sg:address":"Von-Einem-Str. 77",
    "sg:city":"Essen",
    "sg:phone":"+49 201/8852104",
    "sg:postcode":"45130",
    "sg:province":"Nordrhein-Westfalen",
    "wof:name":"Schwimmzentrum R\u00fcttenscheid",
    "wof:placetype":"venue"
},
  "geometry": {"coordinates":[7.0149898529,51.4351959229],"type":"Point"}
}