{
  "type": "Feature",
  "properties": {
    "iso:country":"DE",
    "sg:address":"Pappelweg 10",
    "sg:city":"Hohen Viecheln",
    "sg:phone":"+49 38423/54875",
    "sg:postcode":"23996",
    "sg:province":"Mecklenburg-Vorpommern",
    "wof:name":"Michael Kr\u00fcger Ingenieur",
    "wof:placetype":"venue"
},
  "geometry": {"coordinates":[11.5074958801,53.7856140137],"type":"Point"}
}