{
  "type": "Feature",
  "properties": {
    "iso:country":"DE",
    "sg:address":"Bleichwiesenstr 15a",
    "sg:city":"Wiesbaden",
    "sg:phone":"+49 611/66163",
    "sg:postcode":"65203",
    "sg:province":"Hessen",
    "wof:name":"Niedringhaus Gmbh",
    "wof:placetype":"venue"
},
  "geometry": {"coordinates":[8.238717,50.050751],"type":"Point"}
}