{
  "type": "Feature",
  "properties": {
    "iso:country":"DE",
    "sg:address":"Brunnenstr. 18",
    "sg:city":"Taben-Rodt",
    "sg:phone":"+49 6582/828",
    "sg:postcode":"54441",
    "sg:province":"Rheinland-Pfalz",
    "wof:name":"Karl Loch",
    "wof:placetype":"venue"
},
  "geometry": {"coordinates":[6.590199,49.5448],"type":"Point"}
}