{
  "type": "Feature",
  "properties": {
    "iso:country":"DE",
    "sg:address":"Bergstr. 5",
    "sg:city":"Anzing",
    "sg:phone":"+49 8121/5047",
    "sg:postcode":"85646",
    "sg:province":"Bayern",
    "wof:name":"Kontext Unternehmensberatung F\u00fcr Problemanalysen Und",
    "wof:placetype":"venue"
},
  "geometry": {"coordinates":[11.8490886688,48.148235321],"type":"Point"}
}