{
  "type": "Feature",
  "properties": {
    "iso:country":"DE",
    "sg:address":"Ruhrstr. 26",
    "sg:city":"Olsberg",
    "sg:phone":"+49 2962/2427",
    "sg:postcode":"59939",
    "sg:province":"Nordrhein-Westfalen",
    "wof:name":"Peter Kropff",
    "wof:placetype":"venue"
},
  "geometry": {"coordinates":[8.485698,51.353695],"type":"Point"}
}