{
  "type": "Feature",
  "properties": {
    "iso:country":"DE",
    "sg:address":"Wichmannsdorfer Str. 4",
    "sg:city":"Boitzenburg",
    "sg:phone":"+49 39889/243",
    "sg:postcode":"17268",
    "sg:province":"Brandenburg",
    "wof:name":"Boitzburger Bau Gmbh",
    "wof:placetype":"venue"
},
  "geometry": {"coordinates":[13.6108579636,53.2599639893],"type":"Point"}
}