{
  "type": "Feature",
  "properties": {
    "iso:country":"DE",
    "sg:address":"Herlinstr. 22",
    "sg:city":"N\u00f6rdlingen",
    "sg:phone":"+49 9081/3110",
    "sg:postcode":"86720",
    "sg:province":"Bayern",
    "wof:name":"J. Gotthardt & I. Wundel",
    "wof:placetype":"venue"
},
  "geometry": {"coordinates":[10.4865837097,48.8464584351],"type":"Point"}
}