{
  "type": "Feature",
  "properties": {
    "iso:country":"DE",
    "sg:address":"Haitzinger Str. 61",
    "sg:city":"Passau",
    "sg:phone":"+49 851/57385",
    "sg:postcode":"94032",
    "sg:province":"Bayern",
    "wof:name":"R. Langer Papier- Und Schreibwaren",
    "wof:placetype":"venue"
},
  "geometry": {"coordinates":[13.42632,48.57169],"type":"Point"}
}