{
  "type": "Feature",
  "properties": {
    "iso:country":"DE",
    "sg:address":"Lutstruter Str. 23",
    "sg:city":"Abtsgm\u00fcnd",
    "sg:phone":"+49 7963/220",
    "sg:postcode":"73453",
    "sg:province":"Baden-W\u00fcrttemberg",
    "wof:name":"Kundendienst St\u00fctz Gmbh",
    "wof:placetype":"venue"
},
  "geometry": {"coordinates":[9.98919,48.931416],"type":"Point"}
}