{
  "type": "Feature",
  "properties": {
    "iso:country":"DE",
    "sg:address":"Peter-Henlein-Str. 13",
    "sg:city":"G\u00fcnzburg",
    "sg:phone":"+49 8221/37700",
    "sg:postcode":"89312",
    "sg:province":"Bayern",
    "wof:name":"Real Satz Und Druck Gmbh",
    "wof:placetype":"venue"
},
  "geometry": {"coordinates":[10.2732248306,48.4726524353],"type":"Point"}
}