{
  "type": "Feature",
  "properties": {
    "iso:country":"DE",
    "sg:address":"Rottmannsiepe 4 Buer",
    "sg:city":"Gelsenkirchen",
    "sg:phone":"+49 4920/937445",
    "sg:postcode":"45894",
    "sg:province":"Nordrhein-Westfalen",
    "wof:name":"Radio-fernsehen Ing. Marten Gmbh",
    "wof:placetype":"venue"
},
  "geometry": {"coordinates":[7.053895,51.577209],"type":"Point"}
}