{
  "type": "Feature",
  "properties": {
    "iso:country":"DE",
    "sg:address":"Hauptstr. 7",
    "sg:city":"Leipzig",
    "sg:phone":"+49 34297/42298",
    "sg:postcode":"04288",
    "sg:province":"Sachsen",
    "wof:name":"Metallbau S\u00fcd Montage Gmbh",
    "wof:placetype":"venue"
},
  "geometry": {"coordinates":[12.46463,51.307014],"type":"Point"}
}