{
  "type": "Feature",
  "properties": {
    "iso:country":"DE",
    "sg:address":"Lahnstr. 92",
    "sg:city":"Netphen",
    "sg:phone":"+49 4927/386080",
    "sg:postcode":"57250",
    "sg:province":"Nordrhein-Westfalen",
    "wof:name":"Demler Spezialtiefbau Gmbh & Co. Kg",
    "wof:placetype":"venue"
},
  "geometry": {"coordinates":[8.108641,50.910484],"type":"Point"}
}