{
  "type": "Feature",
  "properties": {
    "iso:country":"DE",
    "sg:address":"W\u00e4ldlesweg 5",
    "sg:city":"Neuweiler",
    "sg:phone":"+49 7055/1415",
    "sg:postcode":"75389",
    "sg:province":"Baden-W\u00fcrttemberg",
    "wof:name":"A.-w. R\u00f6ssler Verm\u00f6gensverwaltung",
    "wof:placetype":"venue"
},
  "geometry": {"coordinates":[8.5837593079,48.6954689026],"type":"Point"}
}