{
  "type": "Feature",
  "properties": {
    "iso:country":"DE",
    "sg:address":"Am Bahnhof",
    "sg:city":"Sangerhausen",
    "sg:phone":"+49 3464/579132",
    "sg:postcode":"06526",
    "sg:province":"Sachsen-Anhalt",
    "wof:name":"Fib Car Recycling & Service Gmbh",
    "wof:placetype":"venue"
},
  "geometry": {"coordinates":[11.287485,51.479019],"type":"Point"}
}