{
  "type": "Feature",
  "properties": {
    "iso:country":"DE",
    "sg:address":"Ro\u00dfmarkt 9",
    "sg:city":"Esslingen",
    "sg:postcode":"73728",
    "sg:province":"Baden-W\u00fcrttemberg",
    "wof:name":"Wiwo Gastronomie Gmbh",
    "wof:placetype":"venue"
},
  "geometry": {"coordinates":[9.305199,48.74057],"type":"Point"}
}