{
  "type": "Feature",
  "properties": {
    "iso:country":"DE",
    "sg:address":"Gewerbestr. 1",
    "sg:city":"Titisee-Neustadt",
    "sg:phone":"+49 7651/8590",
    "sg:postcode":"79822",
    "sg:province":"Baden-W\u00fcrttemberg",
    "wof:name":"K. Fischer",
    "wof:placetype":"venue"
},
  "geometry": {"coordinates":[8.16749,47.909451],"type":"Point"}
}