{
  "type": "Feature",
  "properties": {
    "iso:country":"DE",
    "sg:address":"Am K\u00f6llnischen Park 1",
    "sg:city":"Berlin",
    "sg:phone":"+49 30/23198168",
    "sg:postcode":"10179",
    "sg:province":"Berlin",
    "wof:name":"Lychnus Vermietungsges. F\u00fcr Bewegliche Wirtschaftsg\u00fcter",
    "wof:placetype":"venue"
},
  "geometry": {"coordinates":[13.4155235291,52.5118865967],"type":"Point"}
}