{
  "type": "Feature",
  "properties": {
    "iso:country":"DE",
    "sg:address":"Kuhbach 5",
    "sg:city":"Farschweiler",
    "sg:phone":"+49 6500/292",
    "sg:postcode":"54317",
    "sg:province":"Rheinland-Pfalz",
    "wof:name":"Otto Messerig",
    "wof:placetype":"venue"
},
  "geometry": {"coordinates":[6.8287758827,49.7163543701],"type":"Point"}
}