{
  "type": "Feature",
  "properties": {
    "iso:country":"DE",
    "sg:address":"S\u00fclchenstr. 24",
    "sg:city":"Rottenburg",
    "sg:phone":"+49 7472/19222",
    "sg:postcode":"72108",
    "sg:province":"Baden-W\u00fcrttemberg",
    "wof:name":"Deutsches Rotes Kreuz",
    "wof:placetype":"venue"
},
  "geometry": {"coordinates":[8.9391231537,48.4799957275],"type":"Point"}
}