{
  "type": "Feature",
  "properties": {
    "iso:country":"DE",
    "sg:address":"Lanscher Str. 16",
    "sg:city":"L\u00fcbtheen",
    "sg:phone":"+49 38855/2634",
    "sg:postcode":"19249",
    "sg:province":"Mecklenburg-Vorpommern",
    "wof:name":"Lanscher Eck",
    "wof:placetype":"venue"
},
  "geometry": {"coordinates":[11.0817203522,53.2995185852],"type":"Point"}
}