{
  "type": "Feature",
  "properties": {
    "iso:country":"DE",
    "sg:address":"Birkenstr. 13",
    "sg:city":"Wangen",
    "sg:phone":"+49 7522/6294",
    "sg:postcode":"88239",
    "sg:province":"Baden-W\u00fcrttemberg",
    "wof:name":"Karl-heinz Gebhart",
    "wof:placetype":"venue"
},
  "geometry": {"coordinates":[9.7967920303,47.6733093262],"type":"Point"}
}