{
  "type": "Feature",
  "properties": {
    "iso:country":"DE",
    "sg:address":"Ostbleiche 20",
    "sg:city":"Warendorf",
    "sg:postcode":"48231",
    "sg:province":"Nordrhein-Westfalen",
    "wof:name":"Katholische \u00f6ffentliche Bibliothek Des Altenheimes",
    "wof:placetype":"venue"
},
  "geometry": {"coordinates":[7.99743,51.950859],"type":"Point"}
}