{
  "type": "Feature",
  "properties": {
    "iso:country":"DE",
    "sg:address":"Br\u00fcderstr. 4a",
    "sg:city":"Dorsten",
    "sg:phone":"+49 2362/664760",
    "sg:postcode":"46282",
    "sg:province":"Nordrhein-Westfalen",
    "wof:name":"Hallenbad Dorsten",
    "wof:placetype":"venue"
},
  "geometry": {"coordinates":[6.9619159698,51.666557312],"type":"Point"}
}