{
  "type": "Feature",
  "properties": {
    "iso:country":"DE",
    "sg:address":"Jahnshofer Weg",
    "sg:city":"Oldenburg",
    "sg:postcode":"23758",
    "sg:province":"Schleswig-Holstein",
    "wof:name":"Holger Wegener Bau Gmbh",
    "wof:placetype":"venue"
},
  "geometry": {"coordinates":[-85.206238,39.339813],"type":"Point"}
}