{
  "type": "Feature",
  "properties": {
    "iso:country":"DE",
    "sg:address":"Poppelstr. 9 a",
    "sg:city":"N\u00fcrnberg",
    "sg:postcode":"90419",
    "sg:province":"Bayern",
    "wof:name":"Phocus Event Marketing Verwaltungs Gmbh",
    "wof:placetype":"venue"
},
  "geometry": {"coordinates":[11.0561828613,49.4620933533],"type":"Point"}
}