{
  "type": "Feature",
  "properties": {
    "iso:country":"DE",
    "sg:address":"Willicher Damm 119",
    "sg:city":"M\u00f6nchengladbach",
    "sg:postcode":"41066",
    "sg:province":"Nordrhein-Westfalen",
    "wof:name":"Jofemar Deutschland Gmbh",
    "wof:placetype":"venue"
},
  "geometry": {"coordinates":[6.483956,51.221191],"type":"Point"}
}