{
  "type": "Feature",
  "properties": {
    "iso:country":"DE",
    "sg:address":"Welschhufer Str. 58",
    "sg:city":"Bannewitz",
    "sg:phone":"+49 351/4720630",
    "sg:postcode":"01728",
    "sg:province":"Sachsen",
    "wof:name":"H. Berthold",
    "wof:placetype":"venue"
},
  "geometry": {"coordinates":[13.708487,50.980976],"type":"Point"}
}