{
  "type": "Feature",
  "properties": {
    "iso:country":"DE",
    "sg:address":"Rissener Str. 16",
    "sg:city":"Wedel",
    "sg:phone":"+49 4103/2346",
    "sg:postcode":"22880",
    "sg:province":"Schleswig-Holstein",
    "wof:name":"Hans-joachim Ramcke",
    "wof:placetype":"venue"
},
  "geometry": {"coordinates":[9.712661,53.582108],"type":"Point"}
}