{
  "type": "Feature",
  "properties": {
    "iso:country":"DE",
    "sg:address":"M\u00fchlhauser Str. 54 M",
    "sg:city":"Augsburg",
    "sg:phone":"+49 821/748740",
    "sg:postcode":"86169",
    "sg:province":"Bayern",
    "wof:name":"Adac Fahrsicherheitszentrum Augsburg Verwaltungs- Gmbh",
    "wof:placetype":"venue"
},
  "geometry": {"coordinates":[10.91111,48.420311],"type":"Point"}
}