{
  "type": "Feature",
  "properties": {
    "iso:country":"DE",
    "sg:address":"Au\u00dferhalb 71",
    "sg:city":"B\u00fcrstadt",
    "sg:phone":"+49 6206/8753",
    "sg:postcode":"68642",
    "sg:province":"Hessen",
    "wof:name":"Armin Sch\u00e4fer Kieswerk B\u00fcrstadt Gmbh",
    "wof:placetype":"venue"
},
  "geometry": {"coordinates":[8.4544658661,49.6358718872],"type":"Point"}
}