{
  "type": "Feature",
  "properties": {
    "iso:country":"DE",
    "sg:address":"Ulrichstr. 9",
    "sg:city":"Alpen",
    "sg:phone":"+49 2802/2109",
    "sg:postcode":"46519",
    "sg:province":"Nordrhein-Westfalen",
    "wof:name":"Theodor Janssen",
    "wof:placetype":"venue"
},
  "geometry": {"coordinates":[6.509627,51.575859],"type":"Point"}
}