{
  "type": "Feature",
  "properties": {
    "iso:country":"DE",
    "sg:address":"Mittelstr. 9",
    "sg:city":"Rhinow",
    "sg:phone":"+49 33875/30125",
    "sg:postcode":"14728",
    "sg:province":"Brandenburg",
    "wof:name":"Heinz-j\u00fcrgen Scholz",
    "wof:placetype":"venue"
},
  "geometry": {"coordinates":[12.3415241241,52.7512626648],"type":"Point"}
}