{
  "type": "Feature",
  "properties": {
    "iso:country":"DE",
    "sg:address":"Nymphenburger Str. 92",
    "sg:city":"M\u00fcnchen",
    "sg:phone":"+49 89/187061",
    "sg:postcode":"80636",
    "sg:province":"Bayern",
    "wof:name":"Hanisch Und Kitzinger Rechtsanw\u00e4lte",
    "wof:placetype":"venue"
},
  "geometry": {"coordinates":[11.5450582504,48.1502876282],"type":"Point"}
}