{
  "type": "Feature",
  "properties": {
    "iso:country":"DE",
    "sg:address":"Blenhorster Str. 219",
    "sg:city":"Wietzen",
    "sg:phone":"+49 5022/270",
    "sg:postcode":"31613",
    "sg:province":"Niedersachsen",
    "wof:name":"August Schlemermeyer Inh. Gerhard Thies",
    "wof:placetype":"venue"
},
  "geometry": {"coordinates":[9.113882,52.716408],"type":"Point"}
}