{
  "type": "Feature",
  "properties": {
    "iso:country":"DE",
    "sg:address":"Wiesbadener Str. 31",
    "sg:city":"K\u00f6nigstein",
    "sg:phone":"+49 6174/7070",
    "sg:postcode":"61462",
    "sg:province":"Hessen",
    "wof:name":"Abl-werbung Gmbh",
    "wof:placetype":"venue"
},
  "geometry": {"coordinates":[8.4711914062,50.17628479],"type":"Point"}
}