{
  "type": "Feature",
  "properties": {
    "iso:country":"DE",
    "sg:address":"Max-Eyth-Str. 26",
    "sg:city":"Waiblingen",
    "sg:phone":"+49 7151/52515",
    "sg:postcode":"71332",
    "sg:province":"Baden-W\u00fcrttemberg",
    "wof:name":"Wallat",
    "wof:placetype":"venue"
},
  "geometry": {"coordinates":[9.298801,48.830284],"type":"Point"}
}