{
  "type": "Feature",
  "properties": {
    "iso:country":"DE",
    "sg:address":"Poststr. 1",
    "sg:city":"Lauf",
    "sg:phone":"+49 7841/7030",
    "sg:postcode":"77886",
    "sg:province":"Baden-W\u00fcrttemberg",
    "wof:name":"Zink Ingenieure Ingenieurb\u00fcro F\u00fcr Tief- Und Wasserbau Gmbh",
    "wof:placetype":"venue"
},
  "geometry": {"coordinates":[8.128115,48.648895],"type":"Point"}
}