{
  "type": "Feature",
  "properties": {
    "iso:country":"DE",
    "sg:address":"Jocketaer Str 35",
    "sg:city":"Plauen",
    "sg:phone":"+49 3741/527750",
    "sg:postcode":"08525",
    "sg:province":"Sachsen",
    "wof:name":"Ingenieurb\u00fcro Wei\u00dfflog",
    "wof:placetype":"venue"
},
  "geometry": {"coordinates":[12.149059,50.521748],"type":"Point"}
}