{
  "type": "Feature",
  "properties": {
    "iso:country":"DE",
    "sg:address":"Rheinstr. 104",
    "sg:city":"Kandel",
    "sg:phone":"+49 7275/1887",
    "sg:postcode":"76870",
    "sg:province":"Rheinland-Pfalz",
    "wof:name":"Manfred R\u00f6del",
    "wof:placetype":"venue"
},
  "geometry": {"coordinates":[8.208322,49.084721],"type":"Point"}
}