{
  "type": "Feature",
  "properties": {
    "iso:country":"DE",
    "sg:address":"L\u00f6wenplatz 1",
    "sg:city":"Weingarten",
    "sg:phone":"+49 751/561740",
    "sg:postcode":"88250",
    "sg:province":"Baden-W\u00fcrttemberg",
    "wof:name":"Kuoni Reisen Gmbh",
    "wof:placetype":"venue"
},
  "geometry": {"coordinates":[9.6406049728,47.806892395],"type":"Point"}
}