{
  "type": "Feature",
  "properties": {
    "iso:country":"DE",
    "sg:address":"Bismarckstr. 13",
    "sg:city":"Helmstedt",
    "sg:phone":"+49 5351/9480",
    "sg:postcode":"38350",
    "sg:province":"Niedersachsen",
    "wof:name":"Arnold Kempe",
    "wof:placetype":"venue"
},
  "geometry": {"coordinates":[11.0026712418,52.222114563],"type":"Point"}
}