{
  "type": "Feature",
  "properties": {
    "iso:country":"DE",
    "sg:address":"Sachsenstr. 23",
    "sg:city":"Darmstadt",
    "sg:phone":"+49 6151/55054",
    "sg:postcode":"64297",
    "sg:province":"Hessen",
    "wof:name":"Helmuth Mroczek",
    "wof:placetype":"venue"
},
  "geometry": {"coordinates":[8.63804245,49.8202438354],"type":"Point"}
}