{
  "type": "Feature",
  "properties": {
    "iso:country":"DE",
    "sg:address":"Glockenfeld 46",
    "sg:city":"Herdorf",
    "sg:phone":"+49 2744/5479",
    "sg:postcode":"57562",
    "sg:province":"Rheinland-Pfalz",
    "wof:name":"Norbert Fuchs",
    "wof:placetype":"venue"
},
  "geometry": {"coordinates":[7.9442658424,50.7750854492],"type":"Point"}
}