{
  "type": "Feature",
  "properties": {
    "iso:country":"DE",
    "sg:address":"Aue 46",
    "sg:city":"Wuppertal",
    "sg:postcode":"42103",
    "sg:province":"Nordrhein-Westfalen",
    "wof:name":"Grundst\u00fccksverwaltung Aue Gmbh & Co. Kg",
    "wof:placetype":"venue"
},
  "geometry": {"coordinates":[7.138215065,51.2544822693],"type":"Point"}
}