{
  "type": "Feature",
  "properties": {
    "iso:country":"DE",
    "sg:address":"Stuttgarter Str. 105",
    "sg:city":"Calw",
    "sg:phone":"+49 7051/928050",
    "sg:postcode":"75365",
    "sg:province":"Baden-W\u00fcrttemberg",
    "wof:name":"Smc M\u00fchlh\u00e4user Gmbh",
    "wof:placetype":"venue"
},
  "geometry": {"coordinates":[8.7602529526,48.709777832],"type":"Point"}
}