{
  "type": "Feature",
  "properties": {
    "iso:country":"DE",
    "sg:address":"Binzger Str. 20",
    "sg:city":"Laufenburg",
    "sg:phone":"+49 7763/7190",
    "sg:postcode":"79725",
    "sg:province":"Baden-W\u00fcrttemberg",
    "wof:name":"Fritz Huber",
    "wof:placetype":"venue"
},
  "geometry": {"coordinates":[8.052086,47.572281],"type":"Point"}
}