{
  "type": "Feature",
  "properties": {
    "iso:country":"DE",
    "sg:address":"Fenneweg 12",
    "sg:city":"Aurich",
    "sg:phone":"+49 4941/2819",
    "sg:postcode":"26605",
    "sg:province":"Niedersachsen",
    "wof:name":"Eilert Agena",
    "wof:placetype":"venue"
},
  "geometry": {"coordinates":[7.5607409477,53.4571762085],"type":"Point"}
}