{
  "type": "Feature",
  "properties": {
    "iso:country":"DE",
    "sg:address":"Dohnanyiweg 24",
    "sg:city":"Hannover",
    "sg:phone":"+49 511/467466",
    "sg:postcode":"30457",
    "sg:province":"Niedersachsen",
    "wof:name":"Koch & St\u00f6ckemann Gmbh",
    "wof:placetype":"venue"
},
  "geometry": {"coordinates":[9.6861228943,52.331703186],"type":"Point"}
}