{
  "type": "Feature",
  "properties": {
    "iso:country":"DE",
    "sg:address":"Hochstr. 93",
    "sg:city":"B\u00fcnde",
    "sg:phone":"+49 5223/61351",
    "sg:postcode":"32257",
    "sg:province":"Nordrhein-Westfalen",
    "wof:name":"Reinhold B\u00f6rmck Gmbh",
    "wof:placetype":"venue"
},
  "geometry": {"coordinates":[8.5577411652,52.1991462708],"type":"Point"}
}