{
  "type": "Feature",
  "properties": {
    "iso:country":"DE",
    "sg:address":"Auf dem Fels 5",
    "sg:city":"Tholey",
    "sg:phone":"+49 6853/2543",
    "sg:postcode":"66636",
    "sg:province":"Saarland",
    "wof:name":"Hans Otto",
    "wof:placetype":"venue"
},
  "geometry": {"coordinates":[7.0238847733,49.4996986389],"type":"Point"}
}