{
  "type": "Feature",
  "properties": {
    "iso:country":"DE",
    "sg:address":"Dobbelersweg 62",
    "sg:city":"Hamburg",
    "sg:postcode":"20537",
    "sg:province":"Hamburg",
    "wof:name":"Look East Gmbh",
    "wof:placetype":"venue"
},
  "geometry": {"coordinates":[10.0620470047,53.5516662598],"type":"Point"}
}