{
  "type": "Feature",
  "properties": {
    "iso:country":"DE",
    "sg:address":"Am Br\u00f6gel 19",
    "sg:city":"Wuppertal",
    "sg:phone":"+49 202/88595",
    "sg:postcode":"42285",
    "sg:province":"Nordrhein-Westfalen",
    "wof:name":"R. C\u00f6lln & M. Scholemann",
    "wof:placetype":"venue"
},
  "geometry": {"coordinates":[7.180374,51.266148],"type":"Point"}
}