{
  "type": "Feature",
  "properties": {
    "iso:country":"DE",
    "sg:address":"Alte Akademie 14",
    "sg:city":"Freising",
    "sg:phone":"+49 8161/713415",
    "sg:postcode":"85354",
    "sg:province":"Bayern",
    "wof:name":"Techn. Universit\u00e4t M\u00fcnchen Lehrstuhl F\u00fcr Wirtschaftslehre",
    "wof:placetype":"venue"
},
  "geometry": {"coordinates":[11.72711,48.395325],"type":"Point"}
}