{
  "type": "Feature",
  "properties": {
    "iso:country":"DE",
    "sg:address":"Rathenaustr. 4",
    "sg:city":"Hannover",
    "sg:phone":"+49 4951/136620",
    "sg:postcode":"30159",
    "sg:province":"Niedersachsen",
    "wof:name":"Dresdner Bank Ag",
    "wof:placetype":"venue"
},
  "geometry": {"coordinates":[9.738157,52.372276],"type":"Point"}
}