{
  "type": "Feature",
  "properties": {
    "iso:country":"DE",
    "sg:address":"Wilhelm-Soehnle-Str. 17",
    "sg:city":"Murrhardt",
    "sg:phone":"+49 7192/6495",
    "sg:postcode":"71540",
    "sg:province":"Baden-W\u00fcrttemberg",
    "wof:name":"A. Bayer",
    "wof:placetype":"venue"
},
  "geometry": {"coordinates":[9.5595159531,48.9868011475],"type":"Point"}
}