{
  "type": "Feature",
  "properties": {
    "iso:country":"DE",
    "sg:address":"Hauptstr. 30",
    "sg:city":"Niederkr\u00fcchten",
    "sg:phone":"+49 2163/81147",
    "sg:postcode":"41372",
    "sg:province":"Nordrhein-Westfalen",
    "wof:name":"Josef Jansen",
    "wof:placetype":"venue"
},
  "geometry": {"coordinates":[6.1670742035,51.2108764648],"type":"Point"}
}