{
  "type": "Feature",
  "properties": {
    "iso:country":"DE",
    "sg:address":"Bismarckstr. 104",
    "sg:city":"Heilbronn",
    "sg:phone":"+49 7131/1555390",
    "sg:postcode":"74074",
    "sg:province":"Baden-W\u00fcrttemberg",
    "wof:name":"F. Sch\u00e4fer",
    "wof:placetype":"venue"
},
  "geometry": {"coordinates":[9.2380142212,49.1399841309],"type":"Point"}
}