{
  "type": "Feature",
  "properties": {
    "iso:country":"DE",
    "sg:address":"Sebastian-Kneipp-Str. 108",
    "sg:city":"Villingen-Schwenningen",
    "sg:phone":"+49 7721/84440",
    "sg:postcode":"78048",
    "sg:province":"Baden-W\u00fcrttemberg",
    "wof:name":"Tdn Thanheiser Datensysteme Und Netzwerkl\u00f6sungen Gmbh",
    "wof:placetype":"venue"
},
  "geometry": {"coordinates":[8.438788414,48.0671424866],"type":"Point"}
}