{
  "type": "Feature",
  "properties": {
    "iso:country":"DE",
    "sg:address":"Theodor-Naarmann-Str 23",
    "sg:city":"Oelde",
    "sg:phone":"+49 2522/2765",
    "sg:postcode":"59302",
    "sg:province":"Nordrhein-Westfalen",
    "wof:name":"Markmann Gmbh",
    "wof:placetype":"venue"
},
  "geometry": {"coordinates":[8.135559,51.820995],"type":"Point"}
}