{
  "type": "Feature",
  "properties": {
    "iso:country":"DE",
    "sg:address":"Von-Guericke-Str. 1",
    "sg:city":"Helmstedt",
    "sg:phone":"+49 5351/539453",
    "sg:postcode":"38350",
    "sg:province":"Niedersachsen",
    "wof:name":"Deine Freizeit Fitness In Helmstedt",
    "wof:placetype":"venue"
},
  "geometry": {"coordinates":[10.9876899719,52.2413024902],"type":"Point"}
}