{
  "type": "Feature",
  "properties": {
    "iso:country":"DE",
    "sg:address":"Ernst-Abbe-Str. 3",
    "sg:city":"Garbsen",
    "sg:phone":"+49 5131/463356",
    "sg:postcode":"30827",
    "sg:province":"Niedersachsen",
    "wof:name":"Wohnmobile Panitz Gmbh",
    "wof:placetype":"venue"
},
  "geometry": {"coordinates":[9.6104345322,52.4485740662],"type":"Point"}
}