{
  "type": "Feature",
  "properties": {
    "iso:country":"DE",
    "sg:address":"Maximilian-Kolbe-Str. 40",
    "sg:city":"Bochum",
    "sg:postcode":"44787",
    "sg:province":"Nordrhein-Westfalen",
    "wof:name":"Flip Und Flap Gastro-technik Gmbh",
    "wof:placetype":"venue"
},
  "geometry": {"coordinates":[7.2131400108,51.4776000977],"type":"Point"}
}