{
  "type": "Feature",
  "properties": {
    "iso:country":"DE",
    "sg:address":"B\u00fcngelerfeld 15",
    "sg:city":"Dinslaken",
    "sg:phone":"+49 2064/92628",
    "sg:postcode":"46539",
    "sg:province":"Nordrhein-Westfalen",
    "wof:name":"E. Wuttge",
    "wof:placetype":"venue"
},
  "geometry": {"coordinates":[6.7720241547,51.5704536438],"type":"Point"}
}