{
  "type": "Feature",
  "properties": {
    "iso:country":"DE",
    "sg:address":"Wittenburger Str. 9",
    "sg:city":"Vellahn",
    "sg:postcode":"19260",
    "sg:province":"Mecklenburg-Vorpommern",
    "wof:name":"Ev.-lutherische Kirche",
    "wof:placetype":"venue"
},
  "geometry": {"coordinates":[10.9680995941,53.4015731812],"type":"Point"}
}