{
  "type": "Feature",
  "properties": {
    "iso:country":"DE",
    "sg:address":"Schumannstr. 9",
    "sg:city":"Velbert",
    "sg:phone":"+49 2051/967077",
    "sg:postcode":"42549",
    "sg:province":"Nordrhein-Westfalen",
    "wof:name":"Momberg Gmbh",
    "wof:placetype":"venue"
},
  "geometry": {"coordinates":[7.028436,51.339115],"type":"Point"}
}