{
  "type": "Feature",
  "properties": {
    "iso:country":"DE",
    "sg:address":"Allee 7",
    "sg:city":"Roth",
    "sg:phone":"+49 9171/2888",
    "sg:postcode":"91154",
    "sg:province":"Bayern",
    "wof:name":"W. Krause",
    "wof:placetype":"venue"
},
  "geometry": {"coordinates":[11.0930109024,49.2461433411],"type":"Point"}
}