{
  "type": "Feature",
  "properties": {
    "iso:country":"DE",
    "sg:address":"Achalmstr. 20",
    "sg:city":"Aalen",
    "sg:postcode":"73432",
    "sg:province":"Baden-W\u00fcrttemberg",
    "wof:name":"Sms Shareholder Management Service Gbr",
    "wof:placetype":"venue"
},
  "geometry": {"coordinates":[10.1984577179,48.821395874],"type":"Point"}
}