{
  "type": "Feature",
  "properties": {
    "iso:country":"DE",
    "sg:address":"Im Freudenspiel 70",
    "sg:city":"K\u00fcssaberg",
    "sg:phone":"+49 7741",
    "sg:postcode":"79790",
    "sg:province":"Baden-W\u00fcrttemberg",
    "wof:name":"Jennycam",
    "wof:placetype":"venue"
},
  "geometry": {"coordinates":[8.29855,47.611156],"type":"Point"}
}