{
  "type": "Feature",
  "properties": {
    "iso:country":"DE",
    "sg:address":"K\u00f6nigstr. 21",
    "sg:city":"N\u00fcrnberg",
    "sg:phone":"+49 911/230860",
    "sg:postcode":"90402",
    "sg:province":"Bayern",
    "wof:name":"Wacker Uns Wahl Notare",
    "wof:placetype":"venue"
},
  "geometry": {"coordinates":[11.0783481598,49.4505958557],"type":"Point"}
}