{
  "type": "Feature",
  "properties": {
    "iso:country":"DE",
    "sg:address":"St.-Josef-Str. 2",
    "sg:city":"Hopsten",
    "sg:postcode":"48496",
    "sg:province":"Nordrhein-Westfalen",
    "wof:name":"B\u00fccherei Halverde",
    "wof:placetype":"venue"
},
  "geometry": {"coordinates":[7.668631,52.413712],"type":"Point"}
}