{
  "type": "Feature",
  "properties": {
    "iso:country":"DE",
    "sg:address":"Obere Hauptstr. 7",
    "sg:city":"Freising",
    "sg:phone":"+49 8161/94540",
    "sg:postcode":"85354",
    "sg:province":"Bayern",
    "wof:name":"Glorys Boutique Gmbh",
    "wof:placetype":"venue"
},
  "geometry": {"coordinates":[11.743254,48.40015],"type":"Point"}
}