{
  "type": "Feature",
  "properties": {
    "iso:country":"DE",
    "sg:address":"Hohenzollernstr. 99",
    "sg:city":"Koblenz",
    "sg:phone":"+49 261/16702",
    "sg:postcode":"56068",
    "sg:province":"Rheinland-Pfalz",
    "wof:name":"Besser Wohnen Immobilien Inh. Martina Hahn",
    "wof:placetype":"venue"
},
  "geometry": {"coordinates":[7.58953619,50.3461494446],"type":"Point"}
}