{
  "type": "Feature",
  "properties": {
    "iso:country":"DE",
    "sg:address":"Pfifferhof 27",
    "sg:city":"Jandelsbrunn",
    "sg:phone":"+49 8583/1236",
    "sg:postcode":"94118",
    "sg:province":"Bayern",
    "wof:name":"Pension Max H\u00f6pfl",
    "wof:placetype":"venue"
},
  "geometry": {"coordinates":[13.7130451202,48.7409973145],"type":"Point"}
}