{
  "type": "Feature",
  "properties": {
    "iso:country":"DE",
    "sg:address":"Wilhelmsh\u00f6her Allee 1",
    "sg:city":"Kassel",
    "sg:phone":"+49 561/15138",
    "sg:postcode":"34117",
    "sg:province":"Hessen",
    "wof:name":"Praxis Von Dr. Wagner Und Dr.meinel",
    "wof:placetype":"venue"
},
  "geometry": {"coordinates":[9.48913,51.31131],"type":"Point"}
}