{
  "type": "Feature",
  "properties": {
    "iso:country":"DE",
    "sg:address":"Am Hulsberg 109",
    "sg:city":"Bremen",
    "sg:phone":"+49 421/4340107",
    "sg:postcode":"28205",
    "sg:province":"Bremen",
    "wof:name":"Lvm Versicherungen Thomas Lissner",
    "wof:placetype":"venue"
},
  "geometry": {"coordinates":[8.8488464355,53.0713310242],"type":"Point"}
}