{
  "type": "Feature",
  "properties": {
    "iso:country":"DE",
    "sg:address":"Gasberg 23",
    "sg:city":"Erkelenz",
    "sg:phone":"+49 2435/1353",
    "sg:postcode":"41812",
    "sg:province":"Nordrhein-Westfalen",
    "wof:name":"Johann Kremer",
    "wof:placetype":"venue"
},
  "geometry": {"coordinates":[6.330214,51.034405],"type":"Point"}
}