{
  "type": "Feature",
  "properties": {
    "iso:country":"DE",
    "sg:address":"Hauptstr. 71",
    "sg:city":"Tauberbischofsheim",
    "sg:phone":"+49 9341/3316",
    "sg:postcode":"97941",
    "sg:province":"Baden-W\u00fcrttemberg",
    "wof:name":"R\u00fcdiger A. Und Ortrud Paul Rechtsanw\u00e4lte",
    "wof:placetype":"venue"
},
  "geometry": {"coordinates":[9.6601428986,49.621673584],"type":"Point"}
}