{
  "type": "Feature",
  "properties": {
    "iso:country":"DE",
    "sg:address":"Weidenstr. 8",
    "sg:city":"Ahlen",
    "sg:phone":"+49 2382/61990",
    "sg:postcode":"59229",
    "sg:province":"Nordrhein-Westfalen",
    "wof:name":"Ulrich Magera",
    "wof:placetype":"venue"
},
  "geometry": {"coordinates":[7.8849701881,51.748626709],"type":"Point"}
}