{
  "type": "Feature",
  "properties": {
    "iso:country":"DE",
    "sg:address":"Schiffbr\u00fcckenplatz 14",
    "sg:city":"Rendsburg",
    "sg:postcode":"24768",
    "sg:province":"Schleswig-Holstein",
    "wof:name":"Grundst\u00fccksverwaltungsges. Schiffbr\u00fcckenplatz 15 Mbh",
    "wof:placetype":"venue"
},
  "geometry": {"coordinates":[9.6616268158,54.3050537109],"type":"Point"}
}