{
  "type": "Feature",
  "properties": {
    "iso:country":"DE",
    "sg:address":"Reyerh\u00fctte 51",
    "sg:city":"M\u00f6nchengladbach",
    "sg:postcode":"41065",
    "sg:province":"Nordrhein-Westfalen",
    "wof:name":"Allkauf-haus Verwaltungs- Gmbh",
    "wof:placetype":"venue"
},
  "geometry": {"coordinates":[6.4619989395,51.1923484802],"type":"Point"}
}