{
  "type": "Feature",
  "properties": {
    "iso:country":"DE",
    "sg:address":"Kornblumenweg 13",
    "sg:city":"Neufahrn",
    "sg:phone":"+49 8165/4523",
    "sg:postcode":"85375",
    "sg:province":"Bayern",
    "wof:name":"Sieglinde Grau Architekt",
    "wof:placetype":"venue"
},
  "geometry": {"coordinates":[11.661496,48.309769],"type":"Point"}
}