{
  "type": "Feature",
  "properties": {
    "iso:country":"DE",
    "sg:address":"Kurze Str 18",
    "sg:city":"Niederwiesa",
    "sg:phone":"+49 3726/58030",
    "sg:postcode":"09577",
    "sg:province":"Sachsen",
    "wof:name":"F.s. Gmbh & Co Elektroanlagen Kg",
    "wof:placetype":"venue"
},
  "geometry": {"coordinates":[13.0129499435,50.8672981262],"type":"Point"}
}