{
  "type": "Feature",
  "properties": {
    "iso:country":"DE",
    "sg:address":"Peterholzstr. 15",
    "sg:city":"Dessau",
    "sg:phone":"+49 340/8500852",
    "sg:postcode":"06849",
    "sg:province":"Sachsen-Anhalt",
    "wof:name":"Sieglinde Bittner",
    "wof:placetype":"venue"
},
  "geometry": {"coordinates":[12.234891,51.805347],"type":"Point"}
}