{
  "type": "Feature",
  "properties": {
    "iso:country":"DE",
    "sg:address":"St. Annenstr. 43",
    "sg:city":"St. Wendel",
    "sg:phone":"+49 6851/2525",
    "sg:postcode":"66606",
    "sg:province":"Saarland",
    "wof:name":"Kath. \u00f6ffentliche Bibliothek St. Anna",
    "wof:placetype":"venue"
},
  "geometry": {"coordinates":[7.161887,49.472107],"type":"Point"}
}