{
  "type": "Feature",
  "properties": {
    "iso:country":"DE",
    "sg:address":"Bauerstr. 1",
    "sg:city":"M\u00fcnchen",
    "sg:phone":"+49 89/2710921",
    "sg:postcode":"80796",
    "sg:province":"Bayern",
    "wof:name":"Stefanie Wurm",
    "wof:placetype":"venue"
},
  "geometry": {"coordinates":[11.574522,48.158672],"type":"Point"}
}