{
  "type": "Feature",
  "properties": {
    "iso:country":"DE",
    "sg:address":"Obermarkt 35",
    "sg:city":"Murnau",
    "sg:phone":"+49 8841/47046",
    "sg:postcode":"82418",
    "sg:province":"Bayern",
    "wof:name":"Jost Schlegtendal Rechtsanwalt",
    "wof:placetype":"venue"
},
  "geometry": {"coordinates":[11.200966835,47.6796684265],"type":"Point"}
}