{
  "type": "Feature",
  "properties": {
    "iso:country":"DE",
    "sg:address":"Am Reitenberg",
    "sg:city":"Mihla",
    "sg:phone":"+49 36924/42381",
    "sg:postcode":"99826",
    "sg:province":"Th\u00fcringen",
    "wof:name":"Landw. Unternehmen Mihla Gesch\u00e4ftsf\u00fchrungs Gmbh & Co.",
    "wof:placetype":"venue"
},
  "geometry": {"coordinates":[10.3298845291,51.0765800476],"type":"Point"}
}