{
  "type": "Feature",
  "properties": {
    "iso:country":"DE",
    "sg:address":"Wagenhofstr. 18",
    "sg:city":"Waldm\u00fcnchen",
    "sg:phone":"+49 9972/3359",
    "sg:postcode":"93449",
    "sg:province":"Bayern",
    "wof:name":"Zfv-express",
    "wof:placetype":"venue"
},
  "geometry": {"coordinates":[12.7204637527,49.3794174194],"type":"Point"}
}