{
  "type": "Feature",
  "properties": {
    "iso:country":"DE",
    "sg:address":"Strotweg 2",
    "sg:city":"B\u00fcnde",
    "sg:phone":"+49 5223/10044",
    "sg:postcode":"32257",
    "sg:province":"Nordrhein-Westfalen",
    "wof:name":"Reiner Biermann Steuerberater",
    "wof:placetype":"venue"
},
  "geometry": {"coordinates":[8.5868749619,52.1936035156],"type":"Point"}
}