{
  "type": "Feature",
  "properties": {
    "iso:country":"DE",
    "sg:address":"Schutterstr. 12",
    "sg:city":"Schutterwald",
    "sg:phone":"+49 781/51081",
    "sg:postcode":"77746",
    "sg:province":"Baden-W\u00fcrttemberg",
    "wof:name":"Empress-versand Verlag Und Marketing Gmbh",
    "wof:placetype":"venue"
},
  "geometry": {"coordinates":[7.8785181046,48.4641990662],"type":"Point"}
}