{
  "type": "Feature",
  "properties": {
    "iso:country":"DE",
    "sg:address":"Gr\u00f6benzeller Str. 29",
    "sg:city":"Dachau",
    "sg:phone":"+49 8131/71799",
    "sg:postcode":"85221",
    "sg:province":"Bayern",
    "wof:name":"Bayer",
    "wof:placetype":"venue"
},
  "geometry": {"coordinates":[11.442542,48.237831],"type":"Point"}
}