{
  "type": "Feature",
  "properties": {
    "iso:country":"DE",
    "sg:address":"Inneringer Str. 17",
    "sg:city":"Veringenstadt",
    "sg:phone":"+49 7577/93320",
    "sg:postcode":"72519",
    "sg:province":"Baden-W\u00fcrttemberg",
    "wof:name":"G. Heppeler Steuerberater",
    "wof:placetype":"venue"
},
  "geometry": {"coordinates":[9.2184429169,48.1789855957],"type":"Point"}
}