{
  "type": "Feature",
  "properties": {
    "iso:country":"DE",
    "sg:address":"Obere Str. 14",
    "sg:city":"Eberg\u00f6tzen",
    "sg:phone":"+49 5507/7323",
    "sg:postcode":"37136",
    "sg:province":"Niedersachsen",
    "wof:name":"Willi Vollbrecht",
    "wof:placetype":"venue"
},
  "geometry": {"coordinates":[10.1131153107,51.5732192993],"type":"Point"}
}