{
  "type": "Feature",
  "properties": {
    "iso:country":"DE",
    "sg:address":"K\u00f6llertalstr. 8",
    "sg:city":"P\u00fcttlingen",
    "sg:phone":"+49 6898/63874",
    "sg:postcode":"66346",
    "sg:province":"Saarland",
    "wof:name":"Fenster Jerusalem Gmbh",
    "wof:placetype":"venue"
},
  "geometry": {"coordinates":[6.886666,49.288944],"type":"Point"}
}