{
  "type": "Feature",
  "properties": {
    "iso:country":"DE",
    "sg:address":"Bismarckstr. 70",
    "sg:city":"Krefeld",
    "sg:phone":"+49 2151/596341",
    "sg:postcode":"47799",
    "sg:province":"Nordrhein-Westfalen",
    "wof:name":"Rosa Hasselmann",
    "wof:placetype":"venue"
},
  "geometry": {"coordinates":[6.5741648674,51.3402709961],"type":"Point"}
}