{
  "type": "Feature",
  "properties": {
    "iso:country":"DE",
    "sg:address":"Hauptstr. 17a",
    "sg:city":"Bischofsgr\u00fcn",
    "sg:phone":"+49 9276/1388",
    "sg:postcode":"95493",
    "sg:province":"Bayern",
    "wof:name":"Nkd Vertriebsges. Mbh",
    "wof:placetype":"venue"
},
  "geometry": {"coordinates":[11.7975740433,50.0520973206],"type":"Point"}
}