{
  "type": "Feature",
  "properties": {
    "iso:country":"DE",
    "sg:address":"III. H\u00fcllenweg 1",
    "sg:city":"Bar\u00dfel",
    "sg:phone":"+49 4499/358",
    "sg:postcode":"26676",
    "sg:province":"Niedersachsen",
    "wof:name":"Detert J. Burmann",
    "wof:placetype":"venue"
},
  "geometry": {"coordinates":[7.749121,53.170555],"type":"Point"}
}