{
  "type": "Feature",
  "properties": {
    "iso:country":"DE",
    "sg:address":"Gippes 2",
    "sg:city":"Wabern",
    "sg:phone":"+49 5683/469",
    "sg:postcode":"34590",
    "sg:province":"Hessen",
    "wof:name":"Ernst Eckhardt",
    "wof:placetype":"venue"
},
  "geometry": {"coordinates":[9.313102,51.110966],"type":"Point"}
}