{
  "type": "Feature",
  "properties": {
    "iso:country":"DE",
    "sg:address":"Tempelweg 71 a",
    "sg:city":"Z\u00f6blitz",
    "sg:postcode":"09517",
    "sg:province":"Sachsen",
    "wof:name":"Gerhard Kaulfuss",
    "wof:placetype":"venue"
},
  "geometry": {"coordinates":[13.230113,50.660038],"type":"Point"}
}