{
  "type": "Feature",
  "properties": {
    "iso:country":"DE",
    "sg:address":"Ovenh\u00e4user Str.",
    "sg:city":"H\u00f6xter",
    "sg:phone":"+49 5278/477",
    "sg:postcode":"37671",
    "sg:province":"Nordrhein-Westfalen",
    "wof:name":"Tebi Asphalt-baustoffe Verwaltungs Gmbh",
    "wof:placetype":"venue"
},
  "geometry": {"coordinates":[9.30306,51.750237],"type":"Point"}
}