{
  "type": "Feature",
  "properties": {
    "iso:country":"DE",
    "sg:address":"Bahnhofstr.7",
    "sg:city":"Traunstein",
    "sg:phone":"+49 861/14044",
    "sg:postcode":"83278",
    "sg:province":"Bayern",
    "wof:name":"Dresdner Bank",
    "wof:placetype":"venue"
},
  "geometry": {"coordinates":[12.640103,47.86985],"type":"Point"}
}