{
  "type": "Feature",
  "properties": {
    "iso:country":"DE",
    "sg:address":"Bundesstr. 56",
    "sg:city":"Katlenburg-Lindau",
    "sg:phone":"+49 5556/235",
    "sg:postcode":"37191",
    "sg:province":"Niedersachsen",
    "wof:name":"Karl Lindert Gmbh",
    "wof:placetype":"venue"
},
  "geometry": {"coordinates":[10.12609,51.654255],"type":"Point"}
}