{
  "type": "Feature",
  "properties": {
    "iso:country":"DE",
    "sg:address":"Itzehoer Str. 45",
    "sg:city":"Hohenwestedt",
    "sg:phone":"+49 4871/499525",
    "sg:postcode":"24594",
    "sg:province":"Schleswig-Holstein",
    "wof:name":"Versicherungsagentur Wisch & Partner",
    "wof:placetype":"venue"
},
  "geometry": {"coordinates":[9.6492347717,54.0859451294],"type":"Point"}
}