{
  "type": "Feature",
  "properties": {
    "iso:country":"DE",
    "sg:address":"Alt Sindlingen 5",
    "sg:city":"Frankfurt",
    "sg:phone":"+49 69/373865",
    "sg:postcode":"65931",
    "sg:province":"Hessen",
    "wof:name":"Ralf Lemster Financial Translations Gmbh",
    "wof:placetype":"venue"
},
  "geometry": {"coordinates":[8.518376,50.080776],"type":"Point"}
}