{
  "type": "Feature",
  "properties": {
    "iso:country":"DE",
    "sg:address":"Friedenstr. 85",
    "sg:city":"Frechen",
    "sg:phone":"+49 2234/59210",
    "sg:postcode":"50226",
    "sg:province":"Nordrhein-Westfalen",
    "wof:name":"Obf Organisationsb\u00fcro E. Jung Kg",
    "wof:placetype":"venue"
},
  "geometry": {"coordinates":[6.8118109703,50.9167442322],"type":"Point"}
}