{
  "type": "Feature",
  "properties": {
    "iso:country":"DE",
    "sg:address":"G\u00fctersloher Str 251",
    "sg:city":"Bielefeld",
    "sg:phone":"+49 521/4329134",
    "sg:postcode":"33649",
    "sg:province":"Nordrhein-Westfalen",
    "wof:name":"Activa Art Handels Gmbh",
    "wof:placetype":"venue"
},
  "geometry": {"coordinates":[8.4803800583,51.9816436768],"type":"Point"}
}