{
  "type": "Feature",
  "properties": {
    "iso:country":"DE",
    "sg:address":"Ernst-Leitz-Strasse 17-37",
    "sg:city":"Wetzlar",
    "sg:classifiers":[
        {
            "category":"Professional",
            "subcategory":"Research",
            "type":"Services"
        }
    ],
    "sg:postcode":"35578",
    "sg:website":"http://www.leica-microsystems.com",
    "wof:name":"Leica Microsystems",
    "wof:placetype":"venue"
},
  "geometry": {"coordinates":[8.4983505,50.5522509],"type":"Point"}
}