{
  "type": "Feature",
  "properties": {
    "iso:country":"DE",
    "sg:address":"Am Steinhof 4 a",
    "sg:city":"Paderborn",
    "sg:phone":"+49 5254/64660",
    "sg:postcode":"33106",
    "sg:province":"Nordrhein-Westfalen",
    "wof:name":"Tamm Und Meier Rechtsanw\u00e4lte",
    "wof:placetype":"venue"
},
  "geometry": {"coordinates":[8.6839351654,51.7336235046],"type":"Point"}
}