{
  "type": "Feature",
  "properties": {
    "iso:country":"DE",
    "sg:address":"Richard-Seiffert-Str. 4",
    "sg:city":"Bergisch Gladbach",
    "sg:phone":"+49 2202/36052",
    "sg:postcode":"51469",
    "sg:province":"Nordrhein-Westfalen",
    "wof:name":"Bernd Blendermann",
    "wof:placetype":"venue"
},
  "geometry": {"coordinates":[7.135099,50.978554],"type":"Point"}
}