{
  "type": "Feature",
  "properties": {
    "iso:country":"DE",
    "sg:address":"Friedrich-Ebert-Str. 59",
    "sg:city":"D\u00fcsseldorf",
    "sg:phone":"+49 211/381269",
    "sg:postcode":"40210",
    "sg:province":"Nordrhein-Westfalen",
    "wof:name":"Goldermann & Co. Inh. Anni Goldermann",
    "wof:placetype":"venue"
},
  "geometry": {"coordinates":[6.7916259766,51.2206382751],"type":"Point"}
}