{
  "type": "Feature",
  "properties": {
    "iso:country":"DE",
    "sg:address":"Haagstr. 2",
    "sg:city":"Erftstadt",
    "sg:phone":"+49 2235/5465",
    "sg:postcode":"50374",
    "sg:province":"Nordrhein-Westfalen",
    "wof:name":"Wilhelm Esser",
    "wof:placetype":"venue"
},
  "geometry": {"coordinates":[6.742612,50.835094],"type":"Point"}
}