{
  "type": "Feature",
  "properties": {
    "iso:country":"DE",
    "sg:address":"Berliner Str. 120",
    "sg:city":"Homburg",
    "sg:postcode":"66424",
    "sg:province":"Saarland",
    "wof:name":"Aldi Gmbh & Co. Kg",
    "wof:placetype":"venue"
},
  "geometry": {"coordinates":[7.3385338783,49.3396682739],"type":"Point"}
}