{
  "type": "Feature",
  "properties": {
    "iso:country":"DE",
    "sg:address":"Am Klangstein 18",
    "sg:city":"Haiger",
    "sg:phone":"+49 2771/300300",
    "sg:postcode":"35708",
    "sg:province":"Hessen",
    "wof:name":"Rink-kachelofen Gmbh",
    "wof:placetype":"venue"
},
  "geometry": {"coordinates":[8.2571296692,50.7444496155],"type":"Point"}
}