{
  "type": "Feature",
  "properties": {
    "iso:country":"DE",
    "sg:address":"Obere Hauptstr. 31",
    "sg:city":"Au",
    "sg:phone":"+49 8752/257",
    "sg:postcode":"84072",
    "sg:province":"Bayern",
    "wof:name":"Hadersdorfer Agentur",
    "wof:placetype":"venue"
},
  "geometry": {"coordinates":[11.7471580505,48.5557022095],"type":"Point"}
}