{
  "type": "Feature",
  "properties": {
    "iso:country":"DE",
    "sg:address":"Engter Str. 2",
    "sg:city":"Wallenhorst",
    "sg:phone":"+49 5407/2847",
    "sg:postcode":"49134",
    "sg:province":"Niedersachsen",
    "wof:name":"Alois Burmeister",
    "wof:placetype":"venue"
},
  "geometry": {"coordinates":[8.026051,52.35154],"type":"Point"}
}