{
  "type": "Feature",
  "properties": {
    "iso:country":"DE",
    "sg:address":"K\u00f6lner Str 10",
    "sg:city":"W\u00f6lfersheim",
    "sg:phone":"+49 6036/97870",
    "sg:postcode":"61200",
    "sg:province":"Hessen",
    "wof:name":"Was Gmbh",
    "wof:placetype":"venue"
},
  "geometry": {"coordinates":[8.813199,50.403725],"type":"Point"}
}