{
  "type": "Feature",
  "properties": {
    "iso:country":"DE",
    "sg:address":"Mannheimer Str. 134",
    "sg:city":"Bad Kreuznach",
    "sg:phone":"+49 671/27231",
    "sg:postcode":"55543",
    "sg:province":"Rheinland-Pfalz",
    "wof:name":"Grand Caree",
    "wof:placetype":"venue"
},
  "geometry": {"coordinates":[7.860104084,49.8431854248],"type":"Point"}
}