{
  "type": "Feature",
  "properties": {
    "iso:country":"DE",
    "sg:address":"Pr\u00f6schstr. 7",
    "sg:city":"Schwarzenbek",
    "sg:phone":"+49 4151/5286",
    "sg:postcode":"21493",
    "sg:province":"Schleswig-Holstein",
    "wof:name":"Portal Design Bauelemente Gmbh",
    "wof:placetype":"venue"
},
  "geometry": {"coordinates":[10.480807,53.504025],"type":"Point"}
}