{
  "type": "Feature",
  "properties": {
    "iso:country":"DE",
    "sg:address":"Gie\u00dfener Str. 4",
    "sg:city":"Dietzenbach",
    "sg:phone":"+49 6074/25469",
    "sg:postcode":"63128",
    "sg:province":"Hessen",
    "wof:name":"Antares Computer Verlag Gmbh",
    "wof:placetype":"venue"
},
  "geometry": {"coordinates":[8.7734766006,49.999584198],"type":"Point"}
}