{
  "type": "Feature",
  "properties": {
    "iso:country":"DE",
    "sg:address":"Hauptstrasse 34",
    "sg:city":"Koblenz",
    "sg:phone":"+49 4545/4545",
    "sg:postcode":"56072",
    "sg:province":"Rheinland-Pfalz",
    "wof:name":"Billige Dvd\u00b4s Copyshop Kopier Deine Dvd",
    "wof:placetype":"venue"
},
  "geometry": {"coordinates":[7.545823,50.343494],"type":"Point"}
}