{
  "type": "Feature",
  "properties": {
    "iso:country":"DE",
    "sg:address":"Branderstr. 16",
    "sg:city":"Ruhpolding",
    "sg:phone":"+49 8663/1254",
    "sg:postcode":"83324",
    "sg:province":"Bayern",
    "wof:name":"Heinz Steinbeisser Bildhauer",
    "wof:placetype":"venue"
},
  "geometry": {"coordinates":[12.644795,47.760498],"type":"Point"}
}