{
  "type": "Feature",
  "properties": {
    "iso:country":"DE",
    "sg:address":"Breite Str. 85",
    "sg:city":"Greiffenberg",
    "sg:phone":"+49 33334/70339",
    "sg:postcode":"16278",
    "sg:province":"Brandenburg",
    "wof:name":"Grilleck",
    "wof:placetype":"venue"
},
  "geometry": {"coordinates":[13.9558753967,53.0878219604],"type":"Point"}
}