{
  "type": "Feature",
  "properties": {
    "iso:country":"DE",
    "sg:address":"M\u00fchlenstr. 14",
    "sg:city":"L\u00fcdinghausen",
    "sg:phone":"+49 2591/6805",
    "sg:postcode":"59348",
    "sg:province":"Nordrhein-Westfalen",
    "wof:name":"H. Schmitfranz",
    "wof:placetype":"venue"
},
  "geometry": {"coordinates":[7.4444489479,51.7704620361],"type":"Point"}
}