{
  "type": "Feature",
  "properties": {
    "iso:country":"DE",
    "sg:address":"Alter Graben 12",
    "sg:city":"Kahl",
    "sg:phone":"+49 6188/2776",
    "sg:postcode":"63796",
    "sg:province":"Bayern",
    "wof:name":"Egon Kremer",
    "wof:placetype":"venue"
},
  "geometry": {"coordinates":[9.0125198364,50.0675010681],"type":"Point"}
}