{
  "type": "Feature",
  "properties": {
    "iso:country":"DE",
    "sg:address":"Dorfstr. 28",
    "sg:city":"D\u00e4tgen",
    "sg:phone":"+49 4329/393",
    "sg:postcode":"24589",
    "sg:province":"Schleswig-Holstein",
    "wof:name":"Helmut Schwarz B\u00fcrgermeister Der",
    "wof:placetype":"venue"
},
  "geometry": {"coordinates":[9.924773,54.180103],"type":"Point"}
}