{
  "type": "Feature",
  "properties": {
    "iso:country":"DE",
    "sg:address":"Kiechlinsberger Str. 11",
    "sg:city":"Endingen",
    "sg:phone":"+49 7642/7672",
    "sg:postcode":"79346",
    "sg:province":"Baden-W\u00fcrttemberg",
    "wof:name":"Helmut Henninger",
    "wof:placetype":"venue"
},
  "geometry": {"coordinates":[7.656145,48.13253],"type":"Point"}
}