{
  "type": "Feature",
  "properties": {
    "iso:country":"DE",
    "sg:address":"Bergstr. 2",
    "sg:city":"Ibbenb\u00fcren",
    "sg:phone":"+49 5451/3217",
    "sg:postcode":"49477",
    "sg:province":"Nordrhein-Westfalen",
    "wof:name":"O. Lehmann Tief- Und Rohrleitungsbau Gmbh",
    "wof:placetype":"venue"
},
  "geometry": {"coordinates":[7.722053051,52.2791595459],"type":"Point"}
}