{
  "type": "Feature",
  "properties": {
    "iso:country":"DE",
    "sg:address":"August-Vilmar-Str. 7",
    "sg:city":"Heringen",
    "sg:phone":"+49 6624/271",
    "sg:postcode":"36266",
    "sg:province":"Hessen",
    "wof:name":"Beate Hofmann",
    "wof:placetype":"venue"
},
  "geometry": {"coordinates":[10.008658,50.887497],"type":"Point"}
}