{
  "type": "Feature",
  "properties": {
    "iso:country":"DE",
    "sg:address":"Alte Amberger Str. 8",
    "sg:city":"Grafenw\u00f6hr",
    "sg:phone":"+49 9641/8613",
    "sg:postcode":"92655",
    "sg:province":"Bayern",
    "wof:name":"Richard Pappenberger & Gerhard Pappenberger",
    "wof:placetype":"venue"
},
  "geometry": {"coordinates":[11.9051027298,49.7186546326],"type":"Point"}
}