{
  "type": "Feature",
  "properties": {
    "iso:country":"DE",
    "sg:address":"Umlauf 24",
    "sg:city":"Plettenberg",
    "sg:phone":"+49 2391/3749",
    "sg:postcode":"58840",
    "sg:province":"Nordrhein-Westfalen",
    "wof:name":"Stadtsch\u00e4nke",
    "wof:placetype":"venue"
},
  "geometry": {"coordinates":[7.8725018501,51.2143669128],"type":"Point"}
}