{
  "type": "Feature",
  "properties": {
    "iso:country":"DE",
    "sg:address":"Obermattweg 11",
    "sg:city":"Badenweiler",
    "sg:phone":"+49 7632/5496",
    "sg:postcode":"79410",
    "sg:province":"Baden-W\u00fcrttemberg",
    "wof:name":"Maximilian Miehle Rechtsanwalt",
    "wof:placetype":"venue"
},
  "geometry": {"coordinates":[7.6772389412,47.7824020386],"type":"Point"}
}