{
  "type": "Feature",
  "properties": {
    "iso:country":"DE",
    "sg:address":"Haldenweg 2",
    "sg:city":"Ohmden",
    "sg:phone":"+49 7023/900470",
    "sg:postcode":"73275",
    "sg:province":"Baden-W\u00fcrttemberg",
    "wof:name":"Gitec Giessereitechnik Gmbh",
    "wof:placetype":"venue"
},
  "geometry": {"coordinates":[9.535475,48.646557],"type":"Point"}
}