{
  "type": "Feature",
  "properties": {
    "iso:country":"DE",
    "sg:address":"Pohlweg 55",
    "sg:city":"Paderborn",
    "sg:postcode":"33098",
    "sg:province":"Nordrhein-Westfalen",
    "wof:name":"Laboratorium F\u00fcr W\u00e4rme- Und K\u00e4ltetechnik",
    "wof:placetype":"venue"
},
  "geometry": {"coordinates":[8.7520399094,51.7181434631],"type":"Point"}
}