{
  "type": "Feature",
  "properties": {
    "iso:country":"DE",
    "sg:address":"Aidenbachstr. 36",
    "sg:city":"M\u00fcnchen",
    "sg:postcode":"81379",
    "sg:province":"Bayern",
    "wof:name":"E. Rid Verwaltungs Gmbh",
    "wof:placetype":"venue"
},
  "geometry": {"coordinates":[11.52342,48.098557],"type":"Point"}
}