{
  "type": "Feature",
  "properties": {
    "iso:country":"DE",
    "sg:address":"Otto-Suhr-Allee 95",
    "sg:city":"Berlin",
    "sg:phone":"+49 30/3418487",
    "sg:postcode":"10585",
    "sg:province":"Berlin",
    "wof:name":"Chr. Wahl & S. Wawrseniak",
    "wof:placetype":"venue"
},
  "geometry": {"coordinates":[13.3083534241,52.5165863037],"type":"Point"}
}