{
  "type": "Feature",
  "properties": {
    "iso:country":"DE",
    "sg:address":"Niederfeld 17",
    "sg:city":"Grefrath",
    "sg:phone":"+49 2158/2160",
    "sg:postcode":"47929",
    "sg:province":"Nordrhein-Westfalen",
    "wof:name":"J. Sanders",
    "wof:placetype":"venue"
},
  "geometry": {"coordinates":[6.36972,51.356731],"type":"Point"}
}