{
  "type": "Feature",
  "properties": {
    "iso:country":"DE",
    "sg:address":"Georg-Leppin-Str. 21",
    "sg:city":"L\u00fcneburg",
    "sg:phone":"+49 4131/872150",
    "sg:postcode":"21337",
    "sg:province":"Niedersachsen",
    "wof:name":"Fenster 2000 Lohrs & Wilhelm",
    "wof:placetype":"venue"
},
  "geometry": {"coordinates":[10.464815,53.238102],"type":"Point"}
}