{
  "type": "Feature",
  "properties": {
    "iso:country":"DE",
    "sg:address":"Neufang 1",
    "sg:city":"St. Andreasberg",
    "sg:phone":"+49 5582/706",
    "sg:postcode":"37444",
    "sg:province":"Niedersachsen",
    "wof:name":"Gast- Und Pensionshaus Neufang Gisela Mehmke",
    "wof:placetype":"venue"
},
  "geometry": {"coordinates":[10.5135478973,51.7139625549],"type":"Point"}
}