{
  "type": "Feature",
  "properties": {
    "iso:country":"DE",
    "sg:address":"Carl-Benz-Str. 4",
    "sg:city":"Neuhausen",
    "sg:phone":"+49 7467/1554",
    "sg:postcode":"78579",
    "sg:province":"Baden-W\u00fcrttemberg",
    "wof:name":"M. J\u00e4ckel",
    "wof:placetype":"venue"
},
  "geometry": {"coordinates":[8.9348592758,47.9740447998],"type":"Point"}
}