{
  "type": "Feature",
  "properties": {
    "iso:country":"DE",
    "sg:address":"Kiefernweg 5",
    "sg:city":"Wilster",
    "sg:phone":"+49 4836/1241",
    "sg:postcode":"25554",
    "sg:province":"Schleswig-Holstein",
    "wof:name":"Karl-l. Mahn",
    "wof:placetype":"venue"
},
  "geometry": {"coordinates":[9.385669,53.922691],"type":"Point"}
}