{
  "type": "Feature",
  "properties": {
    "iso:country":"DE",
    "sg:address":"Gabisweg 1",
    "sg:city":"Hohenwart",
    "sg:phone":"+49 8443/258",
    "sg:postcode":"86558",
    "sg:province":"Bayern",
    "wof:name":"Anton Schmid",
    "wof:placetype":"venue"
},
  "geometry": {"coordinates":[11.3819217682,48.5916976929],"type":"Point"}
}