{
  "type": "Feature",
  "properties": {
    "iso:country":"DE",
    "sg:address":"Ansbacher Str. 3",
    "sg:city":"Leutershausen",
    "sg:phone":"+49 9823/8106",
    "sg:postcode":"91578",
    "sg:province":"Bayern",
    "wof:name":"Karl Wagner",
    "wof:placetype":"venue"
},
  "geometry": {"coordinates":[10.481232,49.298637],"type":"Point"}
}