{
  "type": "Feature",
  "properties": {
    "iso:country":"DE",
    "sg:address":"Eisenbacher Str.",
    "sg:city":"Selters",
    "sg:phone":"+49 6483/5203",
    "sg:postcode":"65618",
    "sg:province":"Hessen",
    "wof:name":"Hubertushof",
    "wof:placetype":"venue"
},
  "geometry": {"coordinates":[8.2295999527,50.3378601074],"type":"Point"}
}