{
  "type": "Feature",
  "properties": {
    "iso:country":"DE",
    "sg:address":"Gregor-Wolf-Str. 10",
    "sg:city":"Betzdorf",
    "sg:phone":"+49 2741/22858",
    "sg:postcode":"57518",
    "sg:province":"Rheinland-Pfalz",
    "wof:name":"W. Neuhausen Inh. Gerold Hof",
    "wof:placetype":"venue"
},
  "geometry": {"coordinates":[7.865198,50.793709],"type":"Point"}
}