{
  "type": "Feature",
  "properties": {
    "iso:country":"DE",
    "sg:address":"Karl-Theodor-Str. 70",
    "sg:city":"M\u00fcnchen",
    "sg:phone":"+49 89/3004806",
    "sg:postcode":"80803",
    "sg:province":"Bayern",
    "wof:name":"Pkv Printkompress Verlags Gmbh",
    "wof:placetype":"venue"
},
  "geometry": {"coordinates":[11.5765552521,48.1670265198],"type":"Point"}
}