{
  "type": "Feature",
  "properties": {
    "iso:country":"DE",
    "sg:address":"Leibnizstr. 70a",
    "sg:city":"Stuttgart",
    "sg:phone":"+49 711/651445",
    "sg:postcode":"70193",
    "sg:province":"Baden-W\u00fcrttemberg",
    "wof:name":"Munir El Jundi Architekt",
    "wof:placetype":"venue"
},
  "geometry": {"coordinates":[9.141147,48.780449],"type":"Point"}
}