{
  "type": "Feature",
  "properties": {
    "iso:country":"DE",
    "sg:address":"Karmelitenplatz 6",
    "sg:city":"Abensberg",
    "sg:phone":"+49 9443/5935",
    "sg:postcode":"93326",
    "sg:province":"Bayern",
    "wof:name":"Alfons Heigl",
    "wof:placetype":"venue"
},
  "geometry": {"coordinates":[11.846012,48.815948],"type":"Point"}
}