{
  "type": "Feature",
  "properties": {
    "iso:country":"DE",
    "sg:address":"Industriestr. 40",
    "sg:city":"Dieburg",
    "sg:phone":"+49 6071/81544",
    "sg:postcode":"64807",
    "sg:province":"Hessen",
    "wof:name":"K. Kiendl",
    "wof:placetype":"venue"
},
  "geometry": {"coordinates":[8.852971,49.909874],"type":"Point"}
}