{
  "type": "Feature",
  "properties": {
    "iso:country":"DE",
    "sg:address":"Bierkellerstr. 28",
    "sg:city":"Kehl",
    "sg:phone":"+49 7851/76457",
    "sg:postcode":"77694",
    "sg:province":"Baden-W\u00fcrttemberg",
    "wof:name":"Oase",
    "wof:placetype":"venue"
},
  "geometry": {"coordinates":[7.813488,48.568432],"type":"Point"}
}