{
  "type": "Feature",
  "properties": {
    "iso:country":"DE",
    "sg:address":"Marktplatz 17",
    "sg:city":"Cadolzburg",
    "sg:postcode":"90556",
    "sg:province":"Bayern",
    "wof:name":"Cadion Vertriebsges. Mbh",
    "wof:placetype":"venue"
},
  "geometry": {"coordinates":[10.8522033691,49.4580535889],"type":"Point"}
}