{
  "type": "Feature",
  "properties": {
    "iso:country":"DE",
    "sg:address":"Vordere Ledergasse 14",
    "sg:city":"N\u00fcrnberg",
    "sg:phone":"+49 911/241320",
    "sg:postcode":"90403",
    "sg:province":"Bayern",
    "wof:name":"Der Uhrendoktor Gmbh",
    "wof:placetype":"venue"
},
  "geometry": {"coordinates":[11.071097374,49.4513168335],"type":"Point"}
}