{
  "type": "Feature",
  "properties": {
    "iso:country":"DE",
    "sg:address":"Lindenauer Str. 4",
    "sg:city":"Sontra",
    "sg:phone":"+49 5653/7888",
    "sg:postcode":"36205",
    "sg:province":"Hessen",
    "wof:name":"Gisela Kempfe",
    "wof:placetype":"venue"
},
  "geometry": {"coordinates":[9.935631,51.070244],"type":"Point"}
}