{
  "type": "Feature",
  "properties": {
    "iso:country":"DE",
    "sg:address":"Steddorfer Str. 23",
    "sg:city":"Heeslingen",
    "sg:phone":"+49 4287/1068",
    "sg:postcode":"27404",
    "sg:province":"Niedersachsen",
    "wof:name":"Johann Tramm Gmbh",
    "wof:placetype":"venue"
},
  "geometry": {"coordinates":[9.397543,53.346119],"type":"Point"}
}