{
  "type": "Feature",
  "properties": {
    "iso:country":"DE",
    "sg:address":"Fedelh\u00f6ren 54",
    "sg:city":"Bremen",
    "sg:phone":"+49 421/339088",
    "sg:postcode":"28203",
    "sg:province":"Bremen",
    "wof:name":"As Abrechnungsstelle F\u00fcr Heil- Hilfs- Und Pflegeberufe Gmbh",
    "wof:placetype":"venue"
},
  "geometry": {"coordinates":[8.822367,53.078636],"type":"Point"}
}