{
  "type": "Feature",
  "properties": {
    "iso:country":"DE",
    "sg:address":"Schmale Str. 10",
    "sg:city":"Moers",
    "sg:phone":"+49 2841/8876540",
    "sg:postcode":"47443",
    "sg:province":"Nordrhein-Westfalen",
    "wof:name":"Brumme-werbung",
    "wof:placetype":"venue"
},
  "geometry": {"coordinates":[6.6754808426,51.4484367371],"type":"Point"}
}