{
  "type": "Feature",
  "properties": {
    "iso:country":"DE",
    "sg:address":"Donaustr. 24",
    "sg:city":"Vohburg",
    "sg:phone":"+49 8457/9191",
    "sg:postcode":"85088",
    "sg:province":"Bayern",
    "wof:name":"Rudolf Band Eisenwaren",
    "wof:placetype":"venue"
},
  "geometry": {"coordinates":[11.6186523438,48.7720756531],"type":"Point"}
}