{
  "type": "Feature",
  "properties": {
    "iso:country":"DE",
    "sg:address":"Amselweg 4",
    "sg:city":"Glashuetten",
    "sg:postcode":"61479",
    "sg:province":"Hessen",
    "wof:name":"Arbeitszeugnis.com",
    "wof:placetype":"venue"
},
  "geometry": {"coordinates":[8.3838148117,50.2032165527],"type":"Point"}
}