{
  "type": "Feature",
  "properties": {
    "iso:country":"DE",
    "sg:address":"Am Weddel 4",
    "sg:city":"Cuxhaven",
    "sg:phone":"+49 4723/4207",
    "sg:postcode":"27478",
    "sg:province":"Niedersachsen",
    "wof:name":"R\u00f6sner Bau Gmbh",
    "wof:placetype":"venue"
},
  "geometry": {"coordinates":[8.6143093109,53.7957763672],"type":"Point"}
}