{
  "type": "Feature",
  "properties": {
    "iso:country":"DE",
    "sg:address":"Am Flachsberg 11",
    "sg:city":"Simmertal",
    "sg:phone":"+49 6754/8316",
    "sg:postcode":"55618",
    "sg:province":"Rheinland-Pfalz",
    "wof:name":"Margit Schappert",
    "wof:placetype":"venue"
},
  "geometry": {"coordinates":[7.529085,49.807686],"type":"Point"}
}