{
  "type": "Feature",
  "properties": {
    "iso:country":"DE",
    "sg:address":"Th\u00fcringenstr. 43",
    "sg:city":"Biberach",
    "sg:phone":"+49 7351/22710",
    "sg:postcode":"88400",
    "sg:province":"Baden-W\u00fcrttemberg",
    "wof:name":"G\u00fcnter Berg",
    "wof:placetype":"venue"
},
  "geometry": {"coordinates":[9.7836704254,48.0819091797],"type":"Point"}
}