{
  "type": "Feature",
  "properties": {
    "iso:country":"DE",
    "sg:address":"Tempelsweg 12-14",
    "sg:city":"T\u00f6nisvorst",
    "sg:phone":"+49 2151/70990",
    "sg:postcode":"47918",
    "sg:province":"Nordrhein-Westfalen",
    "wof:name":"Rico-werk Eiserlo & Emmrich Gmbh",
    "wof:placetype":"venue"
},
  "geometry": {"coordinates":[6.4705991745,51.318157196],"type":"Point"}
}