{
  "type": "Feature",
  "properties": {
    "iso:country":"DE",
    "sg:address":"Im Bruch 21",
    "sg:city":"Moers",
    "sg:phone":"+49 2841/59944",
    "sg:postcode":"47443",
    "sg:province":"Nordrhein-Westfalen",
    "wof:name":"Sylvia Schons Heilpraktikerin",
    "wof:placetype":"venue"
},
  "geometry": {"coordinates":[6.6574110985,51.4473609924],"type":"Point"}
}