{
  "type": "Feature",
  "properties": {
    "iso:country":"DE",
    "sg:address":"Marienstr. 37",
    "sg:city":"Hamburg",
    "sg:phone":"+49 40/775766",
    "sg:postcode":"21073",
    "sg:province":"Hamburg",
    "wof:name":"Heinz Rieck",
    "wof:placetype":"venue"
},
  "geometry": {"coordinates":[9.9736852646,53.4578399658],"type":"Point"}
}