{
  "type": "Feature",
  "properties": {
    "iso:country":"DE",
    "sg:address":"Ottobrunner Str. 1",
    "sg:city":"M\u00fcnchen",
    "sg:phone":"+49 89/68074300",
    "sg:postcode":"81737",
    "sg:province":"Bayern",
    "wof:name":"General-media-euro-promotion Uwe Binhardt E. K.",
    "wof:placetype":"venue"
},
  "geometry": {"coordinates":[11.616560936,48.1130752563],"type":"Point"}
}