{
  "type": "Feature",
  "properties": {
    "iso:country":"DE",
    "sg:address":"Seentalstr. 2",
    "sg:city":"Laubach",
    "sg:phone":"+49 6405/6153",
    "sg:postcode":"35321",
    "sg:province":"Hessen",
    "wof:name":"Ev. Pfarramt Freienseen",
    "wof:placetype":"venue"
},
  "geometry": {"coordinates":[9.0463752747,50.5623970032],"type":"Point"}
}