{
  "type": "Feature",
  "properties": {
    "iso:country":"DE",
    "sg:address":"K\u00f6pperweg 13",
    "sg:city":"Braunfels",
    "sg:phone":"+49 6442/5010",
    "sg:postcode":"35619",
    "sg:province":"Hessen",
    "wof:name":"Hardt Fitness-systeme",
    "wof:placetype":"venue"
},
  "geometry": {"coordinates":[8.384145,50.491444],"type":"Point"}
}