{
  "type": "Feature",
  "properties": {
    "iso:country":"DE",
    "sg:address":"Haager Str. 79",
    "sg:city":"Erding",
    "sg:phone":"+49 8122/13240",
    "sg:postcode":"85435",
    "sg:province":"Bayern",
    "wof:name":"Max. Neumaier Dental-labor Gmbh",
    "wof:placetype":"venue"
},
  "geometry": {"coordinates":[11.9107494354,48.294090271],"type":"Point"}
}