{
  "type": "Feature",
  "properties": {
    "iso:country":"DE",
    "sg:address":"Geslauer Str. 3",
    "sg:city":"Windelsbach",
    "sg:phone":"+49 9867/673",
    "sg:postcode":"91635",
    "sg:province":"Bayern",
    "wof:name":"Richard Hufnagel",
    "wof:placetype":"venue"
},
  "geometry": {"coordinates":[10.300102,49.3979],"type":"Point"}
}