{
  "type": "Feature",
  "properties": {
    "iso:country":"DE",
    "sg:address":"Bergstr. 6",
    "sg:city":"Wetzlar",
    "sg:phone":"+49 6441/22917",
    "sg:postcode":"35579",
    "sg:province":"Hessen",
    "wof:name":"Hugo Lotz",
    "wof:placetype":"venue"
},
  "geometry": {"coordinates":[8.5213546753,50.6112518311],"type":"Point"}
}