{
  "type": "Feature",
  "properties": {
    "iso:country":"DE",
    "sg:address":"Kordelstr. 19",
    "sg:city":"Traben-Trarbach",
    "sg:phone":"+49 6541/2128",
    "sg:postcode":"56841",
    "sg:province":"Rheinland-Pfalz",
    "wof:name":"K. E. M\u00fcllen",
    "wof:placetype":"venue"
},
  "geometry": {"coordinates":[7.1113839149,49.9534568787],"type":"Point"}
}