{
  "type": "Feature",
  "properties": {
    "iso:country":"DE",
    "sg:address":"Wieselweg 28",
    "sg:city":"Hamm",
    "sg:phone":"+49 700 0226 4678",
    "sg:postcode":"59071",
    "sg:province":"Nordrhein-Westfalen",
    "wof:name":"Canhost Ek",
    "wof:placetype":"venue"
},
  "geometry": {"coordinates":[7.8707752228,51.6919593811],"type":"Point"}
}