{
  "type": "Feature",
  "properties": {
    "iso:country":"DE",
    "sg:address":"Bahnhofstr. 46",
    "sg:city":"Quickborn",
    "sg:phone":"+49 4106/5073",
    "sg:postcode":"25451",
    "sg:province":"Schleswig-Holstein",
    "wof:name":"Dresdner Bank Aktiengesellscha",
    "wof:placetype":"venue"
},
  "geometry": {"coordinates":[9.90154,53.730682],"type":"Point"}
}