{
  "type": "Feature",
  "properties": {
    "iso:country":"DE",
    "sg:address":"Peterskirchhof 1-5",
    "sg:city":"Leipzig",
    "sg:phone":"+49 341/213980",
    "sg:postcode":"04109",
    "sg:province":"Sachsen",
    "wof:name":"Wessing Rechtsanw\u00e4lte",
    "wof:placetype":"venue"
},
  "geometry": {"coordinates":[12.3752317429,51.3372840881],"type":"Point"}
}