{
  "type": "Feature",
  "properties": {
    "iso:country":"DE",
    "sg:address":"Dusenbacher Str. 44",
    "sg:city":"H\u00f6chst",
    "sg:phone":"+49 6163/3371",
    "sg:postcode":"64739",
    "sg:province":"Hessen",
    "wof:name":"Spedition Schwan Kg",
    "wof:placetype":"venue"
},
  "geometry": {"coordinates":[9.0015583038,49.7983703613],"type":"Point"}
}