{
  "type": "Feature",
  "properties": {
    "iso:country":"DE",
    "sg:address":"Carl-Goerdeler-Str. 16",
    "sg:city":"Speyer",
    "sg:phone":"+49 6232/640333",
    "sg:postcode":"67346",
    "sg:province":"Rheinland-Pfalz",
    "wof:name":"Conventus-immobilien Und Bautr\u00e4ger Gmbh",
    "wof:placetype":"venue"
},
  "geometry": {"coordinates":[8.411195755,49.3263015747],"type":"Point"}
}