{
  "type": "Feature",
  "properties": {
    "iso:country":"DE",
    "sg:address":"Auf der Schaufel",
    "sg:city":"Lorch",
    "sg:postcode":"65391",
    "sg:province":"Rheinland-Pfalz",
    "wof:name":"Modehaus Arz Gmbh",
    "wof:placetype":"venue"
},
  "geometry": {"coordinates":[7.847851,50.102474],"type":"Point"}
}