{
  "type": "Feature",
  "properties": {
    "iso:country":"DE",
    "sg:address":"Oststr. 8",
    "sg:city":"Hattingen",
    "sg:phone":"+49 2324/202571",
    "sg:postcode":"45525",
    "sg:province":"Nordrhein-Westfalen",
    "wof:name":"Answer Edv-schulungs- Support-handel Gmbh",
    "wof:placetype":"venue"
},
  "geometry": {"coordinates":[7.1874761581,51.3999671936],"type":"Point"}
}