{
  "type": "Feature",
  "properties": {
    "iso:country":"DE",
    "sg:address":"Klybeckstr. 20 -1",
    "sg:city":"Weil am Rhein",
    "sg:phone":"+49 7621/79483",
    "sg:postcode":"79576",
    "sg:province":"Baden-W\u00fcrttemberg",
    "wof:name":"Ursula Manz",
    "wof:placetype":"venue"
},
  "geometry": {"coordinates":[7.596829,47.58876],"type":"Point"}
}