{
  "type": "Feature",
  "properties": {
    "iso:country":"DE",
    "sg:address":"Schulstr. 10",
    "sg:city":"Schwaan",
    "sg:phone":"+49 3844/890377",
    "sg:postcode":"18258",
    "sg:province":"Mecklenburg-Vorpommern",
    "wof:name":"W. Malitz",
    "wof:placetype":"venue"
},
  "geometry": {"coordinates":[12.106031,53.940178],"type":"Point"}
}