{
  "type": "Feature",
  "properties": {
    "iso:country":"DE",
    "sg:address":"Hasenwinkler Weg 4",
    "sg:city":"Reppenstedt",
    "sg:phone":"+49 4131/63677",
    "sg:postcode":"21391",
    "sg:province":"Niedersachsen",
    "wof:name":"Wng Handel Und Rep. Gmbh",
    "wof:placetype":"venue"
},
  "geometry": {"coordinates":[10.3681077957,53.2481842041],"type":"Point"}
}