{
  "type": "Feature",
  "properties": {
    "iso:country":"DE",
    "sg:address":"Hauptstr. 44",
    "sg:city":"Bad Salzuflen",
    "sg:phone":"+49 5222/22021",
    "sg:postcode":"32107",
    "sg:province":"Nordrhein-Westfalen",
    "wof:name":"Made In Italy Inh. Aldo Bruno",
    "wof:placetype":"venue"
},
  "geometry": {"coordinates":[8.7576980591,52.0370292664],"type":"Point"}
}