{
  "type": "Feature",
  "properties": {
    "iso:country":"DE",
    "sg:address":"Pleckenbrink 30 a",
    "sg:city":"Dortmund",
    "sg:postcode":"44319",
    "sg:province":"Nordrhein-Westfalen",
    "wof:name":"Novafrit Gmbh",
    "wof:placetype":"venue"
},
  "geometry": {"coordinates":[7.6160831451,51.5355682373],"type":"Point"}
}