{
  "type": "Feature",
  "properties": {
    "iso:country":"DE",
    "sg:address":"Weinbergstr. 6",
    "sg:city":"Moselkern",
    "sg:phone":"+49 2672/1294",
    "sg:postcode":"56254",
    "sg:province":"Rheinland-Pfalz",
    "wof:name":"Regina Pfeil",
    "wof:placetype":"venue"
},
  "geometry": {"coordinates":[7.369453907,50.1941719055],"type":"Point"}
}