{
  "type": "Feature",
  "properties": {
    "iso:country":"DE",
    "sg:address":"Parkstr. 9",
    "sg:city":"Plauen",
    "sg:phone":"+49 3741/526343",
    "sg:postcode":"08525",
    "sg:province":"Sachsen",
    "wof:name":"R. M\u00fcller",
    "wof:placetype":"venue"
},
  "geometry": {"coordinates":[12.1236772537,50.5112342834],"type":"Point"}
}