{
  "type": "Feature",
  "properties": {
    "iso:country":"DE",
    "sg:address":"Zum Camping 10/33",
    "sg:city":"Morbach",
    "sg:phone":"+49 6533",
    "sg:postcode":"54497",
    "sg:province":"Rheinland-Pfalz",
    "wof:name":"Ferienhaus Vermittlung Holiday-espana",
    "wof:placetype":"venue"
},
  "geometry": {"coordinates":[7.121416,49.808575],"type":"Point"}
}