{
  "type": "Feature",
  "properties": {
    "iso:country":"DE",
    "sg:address":"Dorfstr. 16",
    "sg:city":"S\u00fcderhackstedt",
    "sg:postcode":"24852",
    "sg:province":"Schleswig-Holstein",
    "wof:name":"Spedition Lindner Inh. Karin Mau-lindner",
    "wof:placetype":"venue"
},
  "geometry": {"coordinates":[9.2863874435,54.5913238525],"type":"Point"}
}