{
  "type": "Feature",
  "properties": {
    "iso:country":"DE",
    "sg:address":"Beethovenstr. 20",
    "sg:city":"Gro\u00dfkrotzenburg",
    "sg:phone":"+49 6186/7189",
    "sg:postcode":"63538",
    "sg:province":"Hessen",
    "wof:name":"R. Uschrowski",
    "wof:placetype":"venue"
},
  "geometry": {"coordinates":[8.9732542038,50.0830764771],"type":"Point"}
}