{
  "type": "Feature",
  "properties": {
    "iso:country":"DE",
    "sg:address":"Krapfenau 29",
    "sg:city":"Feuchtwangen",
    "sg:phone":"+49 9856/290",
    "sg:postcode":"91555",
    "sg:province":"Bayern",
    "wof:name":"Ernst D\u00e4ubler",
    "wof:placetype":"venue"
},
  "geometry": {"coordinates":[10.36664,49.13134],"type":"Point"}
}