{
  "type": "Feature",
  "properties": {
    "iso:country":"DE",
    "sg:address":"B\u00f6rsenstr. 145",
    "sg:city":"Solingen",
    "sg:phone":"+49 212/811565",
    "sg:postcode":"42657",
    "sg:province":"Nordrhein-Westfalen",
    "wof:name":"C. Kowol",
    "wof:placetype":"venue"
},
  "geometry": {"coordinates":[7.0677390099,51.1384658813],"type":"Point"}
}