{
  "type": "Feature",
  "properties": {
    "iso:country":"DE",
    "sg:address":"Moritzstr. 2",
    "sg:city":"Magdeburg",
    "sg:phone":"+49 391/25545",
    "sg:postcode":"39124",
    "sg:province":"Sachsen-Anhalt",
    "wof:name":"Henning Bartels Rechtsanwalt",
    "wof:placetype":"venue"
},
  "geometry": {"coordinates":[11.6352748871,52.1557846069],"type":"Point"}
}