{
  "type": "Feature",
  "properties": {
    "iso:country":"DE",
    "sg:address":"Kirchstr. 2",
    "sg:city":"Binzen",
    "sg:phone":"+49 7621/62560",
    "sg:postcode":"79589",
    "sg:province":"Baden-W\u00fcrttemberg",
    "wof:name":"G. Brendle Mech. Werkstatt",
    "wof:placetype":"venue"
},
  "geometry": {"coordinates":[7.624869,47.630989],"type":"Point"}
}