{
  "type": "Feature",
  "properties": {
    "iso:country":"DE",
    "sg:address":"Vogelsangstr. 58",
    "sg:city":"Stuttgart",
    "sg:phone":"+49 711/6366314",
    "sg:postcode":"70197",
    "sg:province":"Baden-W\u00fcrttemberg",
    "wof:name":"Ev. Diakoniestation West",
    "wof:placetype":"venue"
},
  "geometry": {"coordinates":[9.151614,48.774124],"type":"Point"}
}