{
  "type": "Feature",
  "properties": {
    "iso:country":"DE",
    "sg:address":"Heideweg 61a",
    "sg:city":"Moers",
    "sg:phone":"+49 2841/33591",
    "sg:postcode":"47447",
    "sg:province":"Nordrhein-Westfalen",
    "wof:name":"Ludger Lichtenberg Architekt",
    "wof:placetype":"venue"
},
  "geometry": {"coordinates":[6.647552,51.427425],"type":"Point"}
}