{
  "type": "Feature",
  "properties": {
    "iso:country":"DE",
    "sg:address":"Helgenst\u00f6ckle 11",
    "sg:city":"Freiamt",
    "sg:phone":"+49 7645/1821",
    "sg:postcode":"79348",
    "sg:province":"Baden-W\u00fcrttemberg",
    "wof:name":"Otto B\u00fcrklin",
    "wof:placetype":"venue"
},
  "geometry": {"coordinates":[7.897554,48.189602],"type":"Point"}
}