{
  "type": "Feature",
  "properties": {
    "iso:country":"DE",
    "sg:address":"Cramerstr. 1",
    "sg:city":"Delmenhorst",
    "sg:phone":"+49 4221/18582",
    "sg:postcode":"27749",
    "sg:province":"Niedersachsen",
    "wof:name":"Macy Mode Vertriebs-gmbh",
    "wof:placetype":"venue"
},
  "geometry": {"coordinates":[8.633722,53.049297],"type":"Point"}
}