{
  "type": "Feature",
  "properties": {
    "iso:country":"DE",
    "sg:address":"Baaderstr. 20",
    "sg:city":"M\u00fcnchen",
    "sg:phone":"+49 89/295314",
    "sg:postcode":"80469",
    "sg:province":"Bayern",
    "wof:name":"Alexander M\u00fcller Farben Und Tapeten",
    "wof:placetype":"venue"
},
  "geometry": {"coordinates":[11.5800323486,48.1322593689],"type":"Point"}
}