{
  "type": "Feature",
  "properties": {
    "iso:country":"DE",
    "sg:address":"Nittenauer Str. 1",
    "sg:city":"Steinberg",
    "sg:phone":"+49 9431/62313",
    "sg:postcode":"92449",
    "sg:province":"Bayern",
    "wof:name":"Dauerer",
    "wof:placetype":"venue"
},
  "geometry": {"coordinates":[12.18129,49.276775],"type":"Point"}
}