{
  "type": "Feature",
  "properties": {
    "iso:country":"DE",
    "sg:address":"Dr.-Wilhelm-K\u00fclz-Str. 17",
    "sg:city":"Zschopau",
    "sg:phone":"+49 3725/22083",
    "sg:postcode":"09405",
    "sg:province":"Sachsen",
    "wof:name":"Dr. Med. Hans Hupfer",
    "wof:placetype":"venue"
},
  "geometry": {"coordinates":[13.064599,50.75156],"type":"Point"}
}