{
  "type": "Feature",
  "properties": {
    "iso:country":"DE",
    "sg:address":"Ebersberger Str. 15",
    "sg:city":"Markt Schwaben",
    "sg:phone":"+49 8121/61117",
    "sg:postcode":"85570",
    "sg:province":"Bayern",
    "wof:name":"Vitis",
    "wof:placetype":"venue"
},
  "geometry": {"coordinates":[11.8694086075,48.1883735657],"type":"Point"}
}