{
  "type": "Feature",
  "properties": {
    "iso:country":"DE",
    "sg:address":"Hochmeisterstr. 3",
    "sg:city":"Freiburg",
    "sg:phone":"+49 761/296540",
    "sg:postcode":"79104",
    "sg:province":"Baden-W\u00fcrttemberg",
    "wof:name":"Dr. Bergmann-weidenbach Steuerberater-rechtsanwalt",
    "wof:placetype":"venue"
},
  "geometry": {"coordinates":[7.8593120575,47.9996528625],"type":"Point"}
}