{
  "type": "Feature",
  "properties": {
    "iso:country":"DE",
    "sg:address":"Feselenstr. 31",
    "sg:city":"Ingolstadt",
    "sg:phone":"+49 841/68300",
    "sg:postcode":"85053",
    "sg:province":"Bayern",
    "wof:name":"H.-g. Grafe Heilpraktiker",
    "wof:placetype":"venue"
},
  "geometry": {"coordinates":[11.4421720505,48.7535667419],"type":"Point"}
}