{
  "type": "Feature",
  "properties": {
    "iso:country":"DE",
    "sg:address":"Wilhelm-Busch-Str. 70",
    "sg:city":"Erfurt",
    "sg:phone":"+49 361/3457515",
    "sg:postcode":"99099",
    "sg:province":"Th\u00fcringen",
    "wof:name":"Wilhelm-busch Apotheke Christian Seiler",
    "wof:placetype":"venue"
},
  "geometry": {"coordinates":[11.044919,50.971245],"type":"Point"}
}