{
  "type": "Feature",
  "properties": {
    "iso:country":"DE",
    "sg:address":"Trierer Str. 334 a",
    "sg:city":"Koblenz",
    "sg:phone":"+49 261/22581",
    "sg:postcode":"56072",
    "sg:province":"Rheinland-Pfalz",
    "wof:name":"Anton Depre",
    "wof:placetype":"venue"
},
  "geometry": {"coordinates":[7.549372,50.364136],"type":"Point"}
}