{
  "type": "Feature",
  "properties": {
    "iso:country":"DE",
    "sg:address":"Altdorfer Str. 35",
    "sg:city":"Feucht",
    "sg:phone":"+49 9128/5243",
    "sg:postcode":"90537",
    "sg:province":"Bayern",
    "wof:name":"Ibhf Ingenieurb\u00fcro H\u00fcbel Gmbh",
    "wof:placetype":"venue"
},
  "geometry": {"coordinates":[11.2188472748,49.3785133362],"type":"Point"}
}