{
  "type": "Feature",
  "properties": {
    "iso:country":"DE",
    "sg:address":"Dorfstr. 9",
    "sg:city":"Henstedt-Ulzburg",
    "sg:phone":"+49 4193/3468",
    "sg:postcode":"24558",
    "sg:province":"Schleswig-Holstein",
    "wof:name":"Hans-heinrich Fr\u00f6hling",
    "wof:placetype":"venue"
},
  "geometry": {"coordinates":[10.002729,53.787338],"type":"Point"}
}