{
  "type": "Feature",
  "properties": {
    "iso:country":"DE",
    "sg:address":"Von-Sch\u00f6nau-Str. 14",
    "sg:city":"Wehr",
    "sg:phone":"+49 7762/3118",
    "sg:postcode":"79664",
    "sg:province":"Baden-W\u00fcrttemberg",
    "wof:name":"Josef Fien Gmbh Stahlhandel-eisenbiegerei",
    "wof:placetype":"venue"
},
  "geometry": {"coordinates":[7.913661,47.6273],"type":"Point"}
}