{
  "type": "Feature",
  "properties": {
    "iso:country":"DE",
    "sg:address":"Ortsstr. 72a",
    "sg:city":"Bremsnitz",
    "sg:postcode":"07646",
    "sg:province":"Th\u00fcringen",
    "wof:name":"Gewa Oberfl\u00e4chentechnik Gmbh",
    "wof:placetype":"venue"
},
  "geometry": {"coordinates":[11.75468,50.847301],"type":"Point"}
}