{
  "type": "Feature",
  "properties": {
    "iso:country":"DE",
    "sg:address":"Habsburgerstr. 59",
    "sg:city":"Freiburg",
    "sg:phone":"+49 761/515050",
    "sg:postcode":"79104",
    "sg:province":"Baden-W\u00fcrttemberg",
    "wof:name":"Herdern-apotheke Inh. Dr. Gottfried Krombholz",
    "wof:placetype":"venue"
},
  "geometry": {"coordinates":[7.855476,48.007668],"type":"Point"}
}