{
  "type": "Feature",
  "properties": {
    "iso:country":"DE",
    "sg:address":"Tulpenweg 3",
    "sg:city":"Bad Segeberg",
    "sg:phone":"+49 4551/4004",
    "sg:postcode":"23795",
    "sg:province":"Schleswig-Holstein",
    "wof:name":"Autokraft Gmbh",
    "wof:placetype":"venue"
},
  "geometry": {"coordinates":[10.3144512177,53.9266548157],"type":"Point"}
}