{
  "type": "Feature",
  "properties": {
    "iso:country":"DE",
    "sg:address":"M\u00f6nchbergstr. 7",
    "sg:city":"M\u00fcnchen",
    "sg:phone":"+49 89/423839",
    "sg:postcode":"81825",
    "sg:province":"Bayern",
    "wof:name":"Hoktec Haberlit Oberfl\u00e4chen- Und Kanten-technik Gmbh",
    "wof:placetype":"venue"
},
  "geometry": {"coordinates":[11.660525322,48.1167831421],"type":"Point"}
}