{
  "type": "Feature",
  "properties": {
    "iso:country":"DE",
    "sg:address":"Sachsenfelder Str. 85",
    "sg:city":"Schwarzenberg",
    "sg:postcode":"08340",
    "sg:province":"Sachsen",
    "wof:name":"Georgsklause Inh. G. R\u00f6der",
    "wof:placetype":"venue"
},
  "geometry": {"coordinates":[12.7816162109,50.5591773987],"type":"Point"}
}