{
  "type": "Feature",
  "properties": {
    "iso:country":"DE",
    "sg:address":"Wiesenstr. 22",
    "sg:city":"Ubstadt-Weiher",
    "sg:postcode":"76698",
    "sg:province":"Baden-W\u00fcrttemberg",
    "wof:name":"Bit Leasing Gmbh",
    "wof:placetype":"venue"
},
  "geometry": {"coordinates":[8.670194,49.178986],"type":"Point"}
}