{
  "type": "Feature",
  "properties": {
    "iso:country":"DE",
    "sg:address":"Schilfhof 26",
    "sg:city":"Potsdam",
    "sg:phone":"+49 331/872219",
    "sg:postcode":"14478",
    "sg:province":"Brandenburg",
    "wof:name":"Gastst\u00e4tte Auerochs",
    "wof:placetype":"venue"
},
  "geometry": {"coordinates":[13.09657,52.378105],"type":"Point"}
}