{
  "type": "Feature",
  "properties": {
    "iso:country":"DE",
    "sg:address":"Hauptstr. 117",
    "sg:city":"Friedrichsbrunn",
    "sg:phone":"+49 39487/415",
    "sg:postcode":"06507",
    "sg:province":"Sachsen-Anhalt",
    "wof:name":"Achim Berner",
    "wof:placetype":"venue"
},
  "geometry": {"coordinates":[11.0377321243,51.6895065308],"type":"Point"}
}