{
  "type": "Feature",
  "properties": {
    "iso:country":"DE",
    "sg:address":"Im Flanzer 3",
    "sg:city":"Sipplingen",
    "sg:phone":"+49 7551/1788",
    "sg:postcode":"78354",
    "sg:province":"Baden-W\u00fcrttemberg",
    "wof:name":"Hotel Haus Von Lippe",
    "wof:placetype":"venue"
},
  "geometry": {"coordinates":[9.1020145416,47.795009613],"type":"Point"}
}