{
  "type": "Feature",
  "properties": {
    "iso:country":"DE",
    "sg:address":"Deisterstr. 47",
    "sg:city":"Hameln",
    "sg:phone":"+49 5151/52666",
    "sg:postcode":"31785",
    "sg:province":"Niedersachsen",
    "wof:name":"Diskothek Shadow",
    "wof:placetype":"venue"
},
  "geometry": {"coordinates":[9.369973,52.104019],"type":"Point"}
}