{
  "type": "Feature",
  "properties": {
    "iso:country":"DE",
    "sg:address":"Kurf\u00fcrstendamm 69",
    "sg:city":"Berlin",
    "sg:phone":"+49 30/88625809",
    "sg:postcode":"10707",
    "sg:province":"Berlin",
    "wof:name":"Ivg Vermittlungsges. F\u00fcr Versicherungen Und",
    "wof:placetype":"venue"
},
  "geometry": {"coordinates":[13.3075857162,52.5002784729],"type":"Point"}
}