{
  "type": "Feature",
  "properties": {
    "iso:country":"DE",
    "sg:address":"Auf der Egart 11",
    "sg:city":"Lo\u00dfburg",
    "sg:phone":"+49 7446/2224",
    "sg:postcode":"72290",
    "sg:province":"Baden-W\u00fcrttemberg",
    "wof:name":"Dieter Eberhard Ingenieur",
    "wof:placetype":"venue"
},
  "geometry": {"coordinates":[8.4400100708,48.4193344116],"type":"Point"}
}