{
  "type": "Feature",
  "properties": {
    "iso:country":"DE",
    "sg:address":"Niedernstr. 49",
    "sg:city":"Stadthagen",
    "sg:phone":"+49 5721/82141",
    "sg:postcode":"31655",
    "sg:province":"Niedersachsen",
    "wof:name":"Carsten B\u00fcrgel Anlageberater",
    "wof:placetype":"venue"
},
  "geometry": {"coordinates":[9.2058982849,52.3240356445],"type":"Point"}
}