{
  "type": "Feature",
  "properties": {
    "iso:country":"DE",
    "sg:address":"Marktplatz 14",
    "sg:city":"Freystadt",
    "sg:phone":"+49 9179/5235",
    "sg:postcode":"92342",
    "sg:province":"Bayern",
    "wof:name":"Ludwig Ernst",
    "wof:placetype":"venue"
},
  "geometry": {"coordinates":[11.330159,49.198387],"type":"Point"}
}