{
  "type": "Feature",
  "properties": {
    "iso:country":"DE",
    "sg:address":"Schulstr. 20",
    "sg:city":"Dorsten",
    "sg:phone":"+49 2369/79125",
    "sg:postcode":"46286",
    "sg:province":"Nordrhein-Westfalen",
    "wof:name":"E. Heitmann",
    "wof:placetype":"venue"
},
  "geometry": {"coordinates":[7.001382,51.760815],"type":"Point"}
}