{
  "type": "Feature",
  "properties": {
    "iso:country":"DE",
    "sg:address":"Hildesheimer Str. 72",
    "sg:city":"Hannover",
    "sg:phone":"+49 511/804277",
    "sg:postcode":"30169",
    "sg:province":"Niedersachsen",
    "wof:name":"Philippe Enderlin",
    "wof:placetype":"venue"
},
  "geometry": {"coordinates":[9.7493715286,52.3612556458],"type":"Point"}
}