{
  "type": "Feature",
  "properties": {
    "iso:country":"DE",
    "sg:address":"Deutenbacher Str. 2 b",
    "sg:city":"Stein",
    "sg:phone":"+49 911/682262",
    "sg:postcode":"90547",
    "sg:province":"Bayern",
    "wof:name":"Pizzeria San Remo",
    "wof:placetype":"venue"
},
  "geometry": {"coordinates":[11.013589859,49.4128227234],"type":"Point"}
}