{
  "type": "Feature",
  "properties": {
    "iso:country":"DE",
    "sg:address":"Zettachring 12 A",
    "sg:city":"Stuttgart",
    "sg:phone":"+49 711/454677",
    "sg:postcode":"70567",
    "sg:province":"Baden-W\u00fcrttemberg",
    "wof:name":"Dr. Udo Unger",
    "wof:placetype":"venue"
},
  "geometry": {"coordinates":[9.1718158722,48.7082023621],"type":"Point"}
}