{
  "type": "Feature",
  "properties": {
    "iso:country":"DE",
    "sg:address":"Leimgrubenweg 21",
    "sg:city":"Ulm",
    "sg:phone":"+49 731/24258",
    "sg:postcode":"89075",
    "sg:province":"Baden-W\u00fcrttemberg",
    "wof:name":"Jacques Wein Depot Wein- Einzelhandel",
    "wof:placetype":"venue"
},
  "geometry": {"coordinates":[10.0010251999,48.4096641541],"type":"Point"}
}