{
  "type": "Feature",
  "properties": {
    "iso:country":"DE",
    "sg:address":"Dorfstr. 33",
    "sg:city":"Unterammergau",
    "sg:phone":"+49 8822/3583",
    "sg:postcode":"82497",
    "sg:province":"Bayern",
    "wof:name":"G\u00e4stehaus Hannes Hiergeist",
    "wof:placetype":"venue"
},
  "geometry": {"coordinates":[11.0286169052,47.61378479],"type":"Point"}
}