{
  "type": "Feature",
  "properties": {
    "iso:country":"DE",
    "sg:address":"Markt 16",
    "sg:city":"Finsterwalde",
    "sg:postcode":"03238",
    "sg:province":"Brandenburg",
    "wof:name":"Foto-studio-mewes",
    "wof:placetype":"venue"
},
  "geometry": {"coordinates":[13.7080783844,51.6302490234],"type":"Point"}
}