{
  "type": "Feature",
  "properties": {
    "iso:country":"DE",
    "sg:address":"Weststr. 31",
    "sg:city":"Beckum",
    "sg:phone":"+49 2521/4041",
    "sg:postcode":"59269",
    "sg:province":"Nordrhein-Westfalen",
    "wof:name":"Rudolf Kessenjohann",
    "wof:placetype":"venue"
},
  "geometry": {"coordinates":[8.037179,51.754776],"type":"Point"}
}