{
  "type": "Feature",
  "properties": {
    "iso:country":"DE",
    "sg:address":"Kronsberg 17",
    "sg:city":"Altenholz",
    "sg:phone":"+49 4956/912853",
    "sg:postcode":"24161",
    "sg:province":"Schleswig-Holstein",
    "wof:name":"Hans Jocksch",
    "wof:placetype":"venue"
},
  "geometry": {"coordinates":[8.9533100128,51.3911399841],"type":"Point"}
}