{
  "type": "Feature",
  "properties": {
    "iso:country":"DE",
    "sg:address":"Siekbruch 53",
    "sg:city":"Braunschweig",
    "sg:phone":"+49 5309/911050",
    "sg:postcode":"38108",
    "sg:province":"Niedersachsen",
    "wof:name":"Peter Seehafer",
    "wof:placetype":"venue"
},
  "geometry": {"coordinates":[10.597158432,52.3160438538],"type":"Point"}
}