{
  "type": "Feature",
  "properties": {
    "iso:country":"DE",
    "sg:address":"Franz-Marc-Str. 13",
    "sg:city":"Heidenheim",
    "sg:phone":"+49 7321/96360",
    "sg:postcode":"89520",
    "sg:province":"Baden-W\u00fcrttemberg",
    "wof:name":"Martin Wittmann Architekt",
    "wof:placetype":"venue"
},
  "geometry": {"coordinates":[10.147132,48.699986],"type":"Point"}
}