{
  "type": "Feature",
  "properties": {
    "iso:country":"DE",
    "sg:address":"Freigrafenweg 20",
    "sg:city":"Dortmund",
    "sg:phone":"+49 231/9370730",
    "sg:postcode":"44357",
    "sg:province":"Nordrhein-Westfalen",
    "wof:name":"Brauns Gmbh & Co. Kg",
    "wof:placetype":"venue"
},
  "geometry": {"coordinates":[7.37951,51.552643],"type":"Point"}
}