{
  "type": "Feature",
  "properties": {
    "iso:country":"DE",
    "sg:address":"Krefelder Str. 55",
    "sg:city":"Krefeld",
    "sg:phone":"+49 2151/731236",
    "sg:postcode":"47839",
    "sg:province":"Nordrhein-Westfalen",
    "wof:name":"Wolfgang Katzer Architekt",
    "wof:placetype":"venue"
},
  "geometry": {"coordinates":[6.511843,51.370811],"type":"Point"}
}