{
  "type": "Feature",
  "properties": {
    "iso:country":"DE",
    "sg:address":"Senator-Schwartz-Rg. 9",
    "sg:city":"Soest",
    "sg:phone":"+49 4929/2196290",
    "sg:postcode":"59494",
    "sg:province":"Nordrhein-Westfalen",
    "wof:name":"Hellweg-molkerei Eg",
    "wof:placetype":"venue"
},
  "geometry": {"coordinates":[8.0813903809,51.5633811951],"type":"Point"}
}