{
  "type": "Feature",
  "properties": {
    "iso:country":"DE",
    "sg:address":"K\u00f6nigstr. 90",
    "sg:city":"M\u00f6nchengladbach",
    "sg:phone":"+49 2166/41417",
    "sg:postcode":"41236",
    "sg:province":"Nordrhein-Westfalen",
    "wof:name":"Schl\u00f6ssers B\u00e4ckereifach- Gesch\u00e4fte Horst Schl\u00f6sser",
    "wof:placetype":"venue"
},
  "geometry": {"coordinates":[6.45247,51.16547],"type":"Point"}
}