{
  "type": "Feature",
  "properties": {
    "iso:country":"DE",
    "sg:address":"Ulmenallee 4",
    "sg:city":"Karlsruhe",
    "sg:phone":"+49 721/9574556",
    "sg:postcode":"76185",
    "sg:province":"Baden-W\u00fcrttemberg",
    "wof:name":"Medi Cal Health Care Gmbh",
    "wof:placetype":"venue"
},
  "geometry": {"coordinates":[8.3472328186,49.0024261475],"type":"Point"}
}