{
  "type": "Feature",
  "properties": {
    "iso:country":"DE",
    "sg:address":"Leipziger Str 1",
    "sg:city":"Naunhof",
    "sg:phone":"+49 34293/5250",
    "sg:postcode":"04683",
    "sg:province":"Sachsen",
    "wof:name":"Heep & Elzermann Gmbh",
    "wof:placetype":"venue"
},
  "geometry": {"coordinates":[12.5872249603,51.2778434753],"type":"Point"}
}