{
  "type": "Feature",
  "properties": {
    "iso:country":"DE",
    "sg:address":"Hauptstr. 38",
    "sg:city":"Ellhofen",
    "sg:phone":"+49 7134/15736",
    "sg:postcode":"74248",
    "sg:province":"Baden-W\u00fcrttemberg",
    "wof:name":"K. K\u00fchner",
    "wof:placetype":"venue"
},
  "geometry": {"coordinates":[9.321525,49.146194],"type":"Point"}
}