{
  "type": "Feature",
  "properties": {
    "iso:country":"DE",
    "sg:address":"Pfarrer-Hefter-Str. 4",
    "sg:city":"Bad Rippoldsau-Schapbach",
    "sg:phone":"+49 7839/246",
    "sg:postcode":"77776",
    "sg:province":"Baden-W\u00fcrttemberg",
    "wof:name":"Helmut Leuthner",
    "wof:placetype":"venue"
},
  "geometry": {"coordinates":[8.291016,48.377415],"type":"Point"}
}