{
  "type": "Feature",
  "properties": {
    "iso:country":"DE",
    "sg:address":"Uttersh\u00e4user Str. 2",
    "sg:city":"Borken",
    "sg:phone":"+49 5682/1420",
    "sg:postcode":"34582",
    "sg:province":"Hessen",
    "wof:name":"Heinz Ostheim",
    "wof:placetype":"venue"
},
  "geometry": {"coordinates":[9.346698,51.06282],"type":"Point"}
}