{
  "type": "Feature",
  "properties": {
    "iso:country":"DE",
    "sg:address":"Babbergerstr. 17",
    "sg:city":"Karlsruhe",
    "sg:postcode":"76189",
    "sg:province":"Baden-W\u00fcrttemberg",
    "wof:name":"Frey Elektrotechnik Gmbh",
    "wof:placetype":"venue"
},
  "geometry": {"coordinates":[8.3174848557,49.0053520203],"type":"Point"}
}