{
  "type": "Feature",
  "properties": {
    "iso:country":"DE",
    "sg:address":"Blindestr. 7",
    "sg:city":"Gelsenkirchen",
    "sg:phone":"+49 209/375352",
    "sg:postcode":"45894",
    "sg:province":"Nordrhein-Westfalen",
    "wof:name":"Franz-josef G\u00f6rres",
    "wof:placetype":"venue"
},
  "geometry": {"coordinates":[7.053618,51.579807],"type":"Point"}
}