{
  "type": "Feature",
  "properties": {
    "iso:country":"DE",
    "sg:address":"Neunkircher Str. 35",
    "sg:city":"Bexbach",
    "sg:phone":"+49 6826/96435",
    "sg:postcode":"66450",
    "sg:province":"Saarland",
    "wof:name":"Pan Akustik Gmbh",
    "wof:placetype":"venue"
},
  "geometry": {"coordinates":[7.2563061714,49.3622016907],"type":"Point"}
}