{
  "type": "Feature",
  "properties": {
    "iso:country":"DE",
    "sg:address":"Nordwall 65",
    "sg:city":"Geldern",
    "sg:phone":"+49 2831/87629",
    "sg:postcode":"47608",
    "sg:province":"Nordrhein-Westfalen",
    "wof:name":"Gelderner Zoo-shop",
    "wof:placetype":"venue"
},
  "geometry": {"coordinates":[6.326708,51.518993],"type":"Point"}
}