{
  "type": "Feature",
  "properties": {
    "iso:country":"DE",
    "sg:address":"Otto-Volger-Stra\u00dfe 15",
    "sg:city":"Sulzbach /Ts.",
    "sg:phone":"+49 4961/965760",
    "sg:postcode":"65843",
    "sg:province":"Hessen",
    "wof:name":"Andersen Consulting-willkommen",
    "wof:placetype":"venue"
},
  "geometry": {"coordinates":[8.516842,50.131371],"type":"Point"}
}