{
  "type": "Feature",
  "properties": {
    "iso:country":"DE",
    "sg:address":"Hintere Talstr. 24",
    "sg:city":"Bad Teinach-Zavelstein",
    "sg:phone":"+49 7053/8821",
    "sg:postcode":"75385",
    "sg:province":"Baden-W\u00fcrttemberg",
    "wof:name":"Waldhorn Und Wiesengrund",
    "wof:placetype":"venue"
},
  "geometry": {"coordinates":[8.6871957779,48.690486908],"type":"Point"}
}