{
  "type": "Feature",
  "properties": {
    "iso:country":"DE",
    "sg:address":"Kompstr. 6",
    "sg:city":"N\u00f6rvenich",
    "sg:phone":"+49 2235/75966",
    "sg:postcode":"52388",
    "sg:province":"Nordrhein-Westfalen",
    "wof:name":"Heinz H. Heinrichs",
    "wof:placetype":"venue"
},
  "geometry": {"coordinates":[6.69769,50.801235],"type":"Point"}
}