{
  "type": "Feature",
  "properties": {
    "iso:country":"DE",
    "sg:address":"Nirkendorfer Weg 1",
    "sg:city":"Nobitz",
    "sg:postcode":"04603",
    "sg:province":"Th\u00fcringen",
    "wof:name":"Siegfried Hofmann",
    "wof:placetype":"venue"
},
  "geometry": {"coordinates":[12.515407,50.943329],"type":"Point"}
}