{
  "type": "Feature",
  "properties": {
    "iso:country":"DE",
    "sg:address":"Christian-H\u00f6fer-Ring 50",
    "sg:city":"SELB",
    "sg:phone":"+49 9287/3464",
    "sg:postcode":"95100",
    "sg:province":"Bayern",
    "wof:name":"Luna-online",
    "wof:placetype":"venue"
},
  "geometry": {"coordinates":[12.134235,50.179462],"type":"Point"}
}