{
  "type": "Feature",
  "properties": {
    "iso:country":"DE",
    "sg:address":"Kornmarkt 1::",
    "sg:city":"Bautzen",
    "sg:phone":"+49 4935/9135650",
    "sg:postcode":"02625",
    "sg:province":"Sachsen",
    "wof:name":"Kreissparkasse Bautzen",
    "wof:placetype":"venue"
},
  "geometry": {"coordinates":[14.427408,51.18029],"type":"Point"}
}