{
  "type": "Feature",
  "properties": {
    "iso:country":"DE",
    "sg:address":"Uffenheimer Str. 11",
    "sg:city":"Ochsenfurt",
    "sg:postcode":"97199",
    "sg:province":"Bayern",
    "wof:name":"Contrac Steuerberatungs- Gesellschaft Mbh",
    "wof:placetype":"venue"
},
  "geometry": {"coordinates":[10.0693721771,49.6619148254],"type":"Point"}
}