{
  "type": "Feature",
  "properties": {
    "iso:country":"DE",
    "sg:address":"Salweidenbecke 23",
    "sg:city":"Bochum",
    "sg:phone":"+49 234/28211",
    "sg:postcode":"44894",
    "sg:province":"Nordrhein-Westfalen",
    "wof:name":"Deutsche Bahn Ag",
    "wof:placetype":"venue"
},
  "geometry": {"coordinates":[7.3078131676,51.4790420532],"type":"Point"}
}