{
  "type": "Feature",
  "properties": {
    "iso:country":"DE",
    "sg:address":"Neurieder Str 14",
    "sg:city":"M\u00fcnchen",
    "sg:phone":"+49 89/7594374",
    "sg:postcode":"80333",
    "sg:province":"Bayern",
    "wof:name":"Hypo-bank Ag",
    "wof:placetype":"venue"
},
  "geometry": {"coordinates":[11.48503,48.087101],"type":"Point"}
}