{
  "type": "Feature",
  "properties": {
    "iso:country":"DE",
    "sg:address":"Obere Stegwiesen",
    "sg:city":"Warthausen",
    "sg:postcode":"88447",
    "sg:province":"Baden-W\u00fcrttemberg",
    "wof:name":"Kaufland",
    "wof:placetype":"venue"
},
  "geometry": {"coordinates":[9.8032712936,48.1294631958],"type":"Point"}
}