{
  "type": "Feature",
  "properties": {
    "iso:country":"DE",
    "sg:address":"Turmstr. 1",
    "sg:city":"Lohr",
    "sg:phone":"+49 9352/4192",
    "sg:postcode":"97816",
    "sg:province":"Bayern",
    "wof:name":"P. R\u00fcgamer",
    "wof:placetype":"venue"
},
  "geometry": {"coordinates":[9.57598,49.994347],"type":"Point"}
}