{
  "type": "Feature",
  "properties": {
    "iso:country":"DE",
    "sg:address":"Gr\u00f6nfahrtweg 3",
    "sg:city":"Harrislee",
    "sg:phone":"+49 461/700160",
    "sg:postcode":"24955",
    "sg:province":"Schleswig-Holstein",
    "wof:name":"Logo Tape Gesellschaft F\u00fcr Selbstklebeb\u00e4nder Mbh & Co. Kg",
    "wof:placetype":"venue"
},
  "geometry": {"coordinates":[9.377322197,54.797454834],"type":"Point"}
}