{
  "type": "Feature",
  "properties": {
    "iso:country":"DE",
    "sg:address":"Neudorf",
    "sg:city":"Uplengen",
    "sg:phone":"+49 4956/2386",
    "sg:postcode":"26670",
    "sg:province":"Niedersachsen",
    "wof:name":"Manfred P\u00fclscher",
    "wof:placetype":"venue"
},
  "geometry": {"coordinates":[7.719854,53.349636],"type":"Point"}
}