{
  "type": "Feature",
  "properties": {
    "iso:country":"DE",
    "sg:address":"Rudolf-Diesel-Str. 14",
    "sg:city":"B\u00f6blingen",
    "sg:phone":"+49 4970/3127010",
    "sg:postcode":"71032",
    "sg:province":"Baden-W\u00fcrttemberg",
    "wof:name":"Pfinder Kg",
    "wof:placetype":"venue"
},
  "geometry": {"coordinates":[9.014836,48.676849],"type":"Point"}
}