{
  "type": "Feature",
  "properties": {
    "iso:country":"DE",
    "sg:address":"Am M\u00fchlanger 42",
    "sg:city":"Lengdorf",
    "sg:phone":"+49 8083/8675",
    "sg:postcode":"84435",
    "sg:province":"Bayern",
    "wof:name":"Horst Esslinger",
    "wof:placetype":"venue"
},
  "geometry": {"coordinates":[12.0477361679,48.2566986084],"type":"Point"}
}