{
  "type": "Feature",
  "properties": {
    "iso:country":"DE",
    "sg:address":"Hauptstr. 35",
    "sg:city":"Garrel",
    "sg:postcode":"49681",
    "sg:province":"Niedersachsen",
    "wof:name":"Alfred Arhling",
    "wof:placetype":"venue"
},
  "geometry": {"coordinates":[8.0245189667,52.9565620422],"type":"Point"}
}