{
  "type": "Feature",
  "properties": {
    "iso:country":"DE",
    "sg:address":"Herrenm\u00fchlstr. 10 a",
    "sg:city":"Alt\u00f6tting",
    "sg:phone":"+49 8671/84376",
    "sg:postcode":"84503",
    "sg:province":"Bayern",
    "wof:name":"Wolfgang Stinglwagner Rechtsanwalt",
    "wof:placetype":"venue"
},
  "geometry": {"coordinates":[12.6786441803,48.2296638489],"type":"Point"}
}