{
  "type": "Feature",
  "properties": {
    "iso:country":"DE",
    "sg:address":"Friedrich-Fr\u00f6bel-Str. 12",
    "sg:city":"Hanau",
    "sg:phone":"+49 6181/52572",
    "sg:postcode":"63457",
    "sg:province":"Hessen",
    "wof:name":"Cornelia Blomeyer-kilschautzk Rechtsanw\u00e4ltin",
    "wof:placetype":"venue"
},
  "geometry": {"coordinates":[8.9610137939,50.1235542297],"type":"Point"}
}