{
  "type": "Feature",
  "properties": {
    "iso:country":"DE",
    "sg:address":"Wellucker Str. 15",
    "sg:city":"Auerbach",
    "sg:phone":"+49 9643/92210",
    "sg:postcode":"91275",
    "sg:province":"Bayern",
    "wof:name":"Kobau Markt Gmbh",
    "wof:placetype":"venue"
},
  "geometry": {"coordinates":[11.6360607147,49.6866722107],"type":"Point"}
}