{
  "type": "Feature",
  "properties": {
    "iso:country":"DE",
    "sg:address":"Austr. 2",
    "sg:city":"Bodelshausen",
    "sg:phone":"+49 7471/96360",
    "sg:postcode":"72411",
    "sg:province":"Baden-W\u00fcrttemberg",
    "wof:name":"Kurt-michael Toussaint Steuerberater",
    "wof:placetype":"venue"
},
  "geometry": {"coordinates":[8.9710741043,48.3958129883],"type":"Point"}
}