{
  "type": "Feature",
  "properties": {
    "iso:country":"DE",
    "sg:address":"Neue Bahnhofstr. 16-17",
    "sg:city":"Berlin",
    "sg:phone":"+49 30/2933970",
    "sg:postcode":"10245",
    "sg:province":"Berlin",
    "wof:name":"Edu Element-decken Gmbh & Co. Kg",
    "wof:placetype":"venue"
},
  "geometry": {"coordinates":[13.471691,52.507435],"type":"Point"}
}