{
  "type": "Feature",
  "properties": {
    "iso:country":"DE",
    "sg:address":"Berliner Str. 39::",
    "sg:city":"Siegen",
    "sg:href":"http://api.simplegeo.com/1.0/features/SG_6TjneudXjygBJJPVJ2f8vg_50.872292_8.015470@1306268793.json",
    "sg:phone":"+49 4927/123000",
    "sg:postcode":"57072",
    "sg:province":"Nordrhein-Westfalen",
    "wof:name":"Volksbank Siegen-netphen Eg",
    "wof:placetype":"venue"
},
  "geometry": {"coordinates":[8.01547,50.872292],"type":"Point"}
}