{"geometry":{"type":"Point","coordinates":[8.015470,50.872292]},"type":"Feature","id":102560801,"bbox":[8.015470,50.872292,8.015470,50.872292],"properties":{"sg:province":"Nordrhein-Westfalen","geom:longitude":8.015470,"wof:breaches":[],"sg:href":"http://api.simplegeo.com/1.0/features/SG_6TjneudXjygBJJPVJ2f8vg_50.872292_8.015470@1306268793.json","sg:owner":"simplegeo","sg:postcode":"57072","geom:latitude":50.872292,"sg:classifiers":[],"sg:address":"Berliner Str. 39::","sg:phone":"+49 4927/123000","wof:hierarchy":[{"locality_id":101748643,"venue_id":102560801,"country_id":85633111,"region_id":85682513,"county_id":102063725}],"geom:area":0.000000,"sg:city":"Siegen","wof:lastmodified":1438093369,"iso:country":"DE","wof:geomhash":"6dd580d133cf00be142657d9ac0daade","wof:name":"Volksbank Siegen-netphen Eg","wof:belongsto":[101748643,85633111,85682513,102063725],"src:geom":"simplegeo","wof:placetype":"venue","wof:supersedes":[],"wof:id":102560801,"wof:superseded_by":[],"wof:concordances":{"sg:id":"SG_6TjneudXjygBJJPVJ2f8vg_50.872292_8.015470@1306268793"},"wof:parent_id":101748643}}