{
  "type": "Feature",
  "properties": {
    "iso:country":"DE",
    "sg:address":"Bahnhofstr. 28",
    "sg:city":"Kaufering",
    "sg:postcode":"86916",
    "sg:province":"Bayern",
    "wof:name":"Loh Datentechnik Gmbh",
    "wof:placetype":"venue"
},
  "geometry": {"coordinates":[10.852845192,48.0815849304],"type":"Point"}
}