{
  "type": "Feature",
  "properties": {
    "iso:country":"DE",
    "sg:address":"Siegfriedstr. 321",
    "sg:city":"Heppenheim",
    "sg:phone":"+49 6252/2719",
    "sg:postcode":"64646",
    "sg:province":"Hessen",
    "wof:name":"Daum Gmbh",
    "wof:placetype":"venue"
},
  "geometry": {"coordinates":[8.6785869598,49.6447029114],"type":"Point"}
}