{
  "type": "Feature",
  "properties": {
    "iso:country":"DE",
    "sg:address":"Eichendorffstr. 1",
    "sg:city":"Rot am See",
    "sg:phone":"+49 7955/1372",
    "sg:postcode":"74585",
    "sg:province":"Baden-W\u00fcrttemberg",
    "wof:name":"A. Krupka Sen.",
    "wof:placetype":"venue"
},
  "geometry": {"coordinates":[10.0230026245,49.2515983582],"type":"Point"}
}