{
  "type": "Feature",
  "properties": {
    "iso:country":"DE",
    "sg:address":"St.-Anna-Str. 10",
    "sg:city":"Dinkelscherben",
    "sg:phone":"+49 8292/1303",
    "sg:postcode":"86424",
    "sg:province":"Bayern",
    "wof:name":"Dr. Med. Otto Fischer",
    "wof:placetype":"venue"
},
  "geometry": {"coordinates":[10.5953073502,48.3506088257],"type":"Point"}
}