{
  "type": "Feature",
  "properties": {
    "iso:country":"DE",
    "sg:address":"Maria-Louisen-Str. 113",
    "sg:city":"Hamburg",
    "sg:phone":"+49 40/477715",
    "sg:postcode":"22301",
    "sg:province":"Hamburg",
    "wof:name":"B. Gatermann Ingenieur",
    "wof:placetype":"venue"
},
  "geometry": {"coordinates":[10.0052785873,53.5897903442],"type":"Point"}
}