{
  "type": "Feature",
  "properties": {
    "iso:country":"DE",
    "sg:address":"Welfenstr. 35",
    "sg:city":"F\u00fcssen",
    "sg:phone":"+49 8362/7675",
    "sg:postcode":"87629",
    "sg:province":"Bayern",
    "wof:name":"Dr. Med. Gerhard Thiele",
    "wof:placetype":"venue"
},
  "geometry": {"coordinates":[10.6800432205,47.5730247498],"type":"Point"}
}