{
  "type": "Feature",
  "properties": {
    "iso:country":"DE",
    "sg:address":"Weidachstr. 11",
    "sg:city":"Neckarsulm",
    "sg:phone":"+49 7132/3200",
    "sg:postcode":"74172",
    "sg:province":"Baden-W\u00fcrttemberg",
    "wof:name":"Friedrich Krieger Ii Suhr Bau- Heimwerkermarkt",
    "wof:placetype":"venue"
},
  "geometry": {"coordinates":[9.2204847336,49.198097229],"type":"Point"}
}