{
  "type": "Feature",
  "properties": {
    "iso:country":"DE",
    "sg:city":"Babenhausen",
    "sg:phone":"+49 8333/8533",
    "sg:postcode":"87727",
    "sg:province":"Bayern",
    "wof:name":"Sparkasse Illertissen",
    "wof:placetype":"venue"
},
  "geometry": {"coordinates":[10.254036,48.143723],"type":"Point"}
}