{
  "type": "Feature",
  "properties": {
    "iso:country":"DE",
    "sg:address":"Hofgartenweg 4",
    "sg:city":"G\u00fcnzburg",
    "sg:phone":"+49 8221/4067",
    "sg:postcode":"89312",
    "sg:province":"Bayern",
    "wof:name":"Matthias Beck Rechtsanwalt",
    "wof:placetype":"venue"
},
  "geometry": {"coordinates":[10.2767400742,48.453704834],"type":"Point"}
}