{
  "type": "Feature",
  "properties": {
    "iso:country":"DE",
    "sg:address":"Allweggasse",
    "sg:city":"Berchtesgaden",
    "sg:phone":"+49 8652/2396",
    "sg:postcode":"83471",
    "sg:province":"Bayern",
    "wof:name":"Camping Allweglehen",
    "wof:placetype":"venue"
},
  "geometry": {"coordinates":[13.037788,47.651215],"type":"Point"}
}