{
  "type": "Feature",
  "properties": {
    "iso:country":"DE",
    "sg:address":"Theodor-Fliedner-Str. 59",
    "sg:city":"Bergisch Gladbach",
    "sg:phone":"+49 2202/52525",
    "sg:postcode":"51469",
    "sg:province":"Nordrhein-Westfalen",
    "wof:name":"Wolfgang Flock",
    "wof:placetype":"venue"
},
  "geometry": {"coordinates":[7.1015019417,50.9930343628],"type":"Point"}
}