{
  "type": "Feature",
  "properties": {
    "iso:country":"DE",
    "sg:address":"Sudetenstr. 17",
    "sg:city":"W\u00e4chtersbach",
    "sg:phone":"+49 6053/3153",
    "sg:postcode":"63607",
    "sg:province":"Hessen",
    "wof:name":"Leo Baier",
    "wof:placetype":"venue"
},
  "geometry": {"coordinates":[9.2818918228,50.2480354309],"type":"Point"}
}