{
  "type": "Feature",
  "properties": {
    "iso:country":"DE",
    "sg:address":"Buchenstr. 5",
    "sg:city":"W\u00f6rth",
    "sg:phone":"+49 8122/92339",
    "sg:postcode":"85457",
    "sg:province":"Bayern",
    "wof:name":"Klaus H\u00fcniger",
    "wof:placetype":"venue"
},
  "geometry": {"coordinates":[11.9370927811,48.2446136475],"type":"Point"}
}