{
  "type": "Feature",
  "properties": {
    "iso:country":"DE",
    "sg:address":"Frankfurter Str. 87",
    "sg:city":"Hagen",
    "sg:phone":"+49 2331/31712",
    "sg:postcode":"58095",
    "sg:province":"Nordrhein-Westfalen",
    "wof:name":"Konstantinos Antoniadis",
    "wof:placetype":"venue"
},
  "geometry": {"coordinates":[7.4774069786,51.3548278809],"type":"Point"}
}