{
  "type": "Feature",
  "properties": {
    "iso:country":"DE",
    "sg:address":"Wald-Michelbacher-Str. 29",
    "sg:city":"Hirschhorn",
    "sg:phone":"+49 6272/2510",
    "sg:postcode":"69434",
    "sg:province":"Baden-W\u00fcrttemberg",
    "wof:name":"Pension Zur Krone",
    "wof:placetype":"venue"
},
  "geometry": {"coordinates":[8.8484659195,49.4725456238],"type":"Point"}
}