{
  "type": "Feature",
  "properties": {
    "iso:country":"DE",
    "sg:address":"Hauptstr. 1",
    "sg:city":"Fichtenau",
    "sg:postcode":"74579",
    "sg:province":"Baden-W\u00fcrttemberg",
    "wof:name":"M & H Bau Gmbh",
    "wof:placetype":"venue"
},
  "geometry": {"coordinates":[10.207797,49.070911],"type":"Point"}
}