{
  "type": "Feature",
  "properties": {
    "iso:country":"DE",
    "sg:address":"Gorch-Fock-Str. 4",
    "sg:city":"Heide",
    "sg:phone":"+49 481",
    "sg:postcode":"25746",
    "sg:province":"Schleswig-Holstein",
    "wof:name":"Rainer Beeck Online-agentur",
    "wof:placetype":"venue"
},
  "geometry": {"coordinates":[9.0962276459,54.1839942932],"type":"Point"}
}