{
  "type": "Feature",
  "properties": {
    "iso:country":"DE",
    "sg:address":"Rubensstr. 11",
    "sg:city":"M\u00fcnchen",
    "sg:phone":"+49 89/881442",
    "sg:postcode":"81245",
    "sg:province":"Bayern",
    "wof:name":"Eleonore Schneider",
    "wof:placetype":"venue"
},
  "geometry": {"coordinates":[11.448158,48.156937],"type":"Point"}
}