{
  "type": "Feature",
  "properties": {
    "iso:country":"DE",
    "sg:address":"Nebenstr. 6a",
    "sg:city":"Hasselroth",
    "sg:phone":"+49 6055/82441",
    "sg:postcode":"63594",
    "sg:province":"Hessen",
    "wof:name":"Weinpress",
    "wof:placetype":"venue"
},
  "geometry": {"coordinates":[9.1041297913,50.1547088623],"type":"Point"}
}