{
  "type": "Feature",
  "properties": {
    "iso:country":"DE",
    "sg:address":"Moltkestr. 18",
    "sg:city":"Wuppertal",
    "sg:phone":"+49 202/311406",
    "sg:postcode":"42115",
    "sg:province":"Nordrhein-Westfalen",
    "wof:name":"Guido Me\u00dfthaler Architekt",
    "wof:placetype":"venue"
},
  "geometry": {"coordinates":[7.127277,51.254276],"type":"Point"}
}