{
  "type": "Feature",
  "properties": {
    "iso:country":"DE",
    "sg:address":"Bergstr. 4",
    "sg:city":"Hosenfeld",
    "sg:phone":"+49 6650/8239",
    "sg:postcode":"36154",
    "sg:province":"Hessen",
    "wof:name":"Gastst\u00e4tte B. Michel",
    "wof:placetype":"venue"
},
  "geometry": {"coordinates":[9.4958553314,50.5400543213],"type":"Point"}
}