{
  "type": "Feature",
  "properties": {
    "iso:country":"DE",
    "sg:address":"Gartenstr. 27",
    "sg:city":"Heilbronn",
    "sg:phone":"+49 7131/89008",
    "sg:postcode":"74072",
    "sg:province":"Baden-W\u00fcrttemberg",
    "wof:name":"Gerd Fuhrmann",
    "wof:placetype":"venue"
},
  "geometry": {"coordinates":[9.224647,49.142879],"type":"Point"}
}