{
  "type": "Feature",
  "properties": {
    "iso:country":"DE",
    "sg:address":"Sch\u00fctzenstr. 32",
    "sg:city":"Ratingen",
    "sg:phone":"+49 2102/847662",
    "sg:postcode":"40878",
    "sg:province":"Nordrhein-Westfalen",
    "wof:name":"Wolfgang Trapp",
    "wof:placetype":"venue"
},
  "geometry": {"coordinates":[6.850581,51.292377],"type":"Point"}
}