{
  "type": "Feature",
  "properties": {
    "iso:country":"DE",
    "sg:address":"Str. Der Pariser Kommune 12",
    "sg:city":"Berlin",
    "sg:phone":"+49 30/29492288",
    "sg:postcode":"10234",
    "sg:province":"Berlin",
    "wof:name":"Calenberg Gmbh Weltweite Umzugslogistik",
    "wof:placetype":"venue"
},
  "geometry": {"coordinates":[13.4372663498,52.5105247498],"type":"Point"}
}