{
  "type": "Feature",
  "properties": {
    "iso:country":"DE",
    "sg:address":"Hauptstr. 110",
    "sg:city":"Wuppertal",
    "sg:phone":"+49 202/470232",
    "sg:postcode":"42349",
    "sg:province":"Nordrhein-Westfalen",
    "wof:name":"Hans Niepmann",
    "wof:placetype":"venue"
},
  "geometry": {"coordinates":[7.1402359009,51.2108268738],"type":"Point"}
}