{
  "type": "Feature",
  "properties": {
    "iso:country":"DE",
    "sg:address":"Planckstr. 17",
    "sg:city":"Celle",
    "sg:phone":"+49 5141/92880",
    "sg:postcode":"29221",
    "sg:province":"Niedersachsen",
    "wof:name":"Hotel Th\u00fcringer Hof",
    "wof:placetype":"venue"
},
  "geometry": {"coordinates":[10.0757951736,52.6128234863],"type":"Point"}
}