{
  "type": "Feature",
  "properties": {
    "iso:country":"DE",
    "sg:address":"Hauptstr. 38",
    "sg:city":"Mengerskirchen",
    "sg:phone":"+49 6476/741",
    "sg:postcode":"35794",
    "sg:province":"Hessen",
    "wof:name":"Reise- Und Verkehrsb\u00fcro Brinkmann",
    "wof:placetype":"venue"
},
  "geometry": {"coordinates":[8.1540155411,50.5631256104],"type":"Point"}
}