{
  "type": "Feature",
  "properties": {
    "iso:country":"DE",
    "sg:address":"Nahestr. 3",
    "sg:city":"Bensheim",
    "sg:phone":"+49 6251/62750",
    "sg:postcode":"64625",
    "sg:province":"Hessen",
    "wof:name":"Helmut Br\u00fcck",
    "wof:placetype":"venue"
},
  "geometry": {"coordinates":[8.6121501923,49.6753883362],"type":"Point"}
}