{
  "type": "Feature",
  "properties": {
    "iso:country":"DE",
    "sg:address":"Burgunderweg 1",
    "sg:city":"L\u00f6rzweiler",
    "sg:phone":"+49 6138/6863",
    "sg:postcode":"55296",
    "sg:province":"Rheinland-Pfalz",
    "wof:name":"Monika Bober",
    "wof:placetype":"venue"
},
  "geometry": {"coordinates":[8.2926340103,49.8980102539],"type":"Point"}
}