{
  "type": "Feature",
  "properties": {
    "iso:country":"DE",
    "sg:address":"Seestr. 45",
    "sg:city":"Berlin",
    "sg:postcode":"12589",
    "sg:province":"Berlin",
    "wof:name":"Arma Gastronomie Gmbh",
    "wof:placetype":"venue"
},
  "geometry": {"coordinates":[13.6829662323,52.4384117126],"type":"Point"}
}