{
  "type": "Feature",
  "properties": {
    "iso:country":"DE",
    "sg:city":"Langballig",
    "sg:phone":"+49 4636/1440",
    "sg:postcode":"24977",
    "sg:province":"Schleswig-Holstein",
    "wof:name":"Werkstattgemeinschaft Unewatt",
    "wof:placetype":"venue"
},
  "geometry": {"coordinates":[9.636853,54.797791],"type":"Point"}
}