{
  "type": "Feature",
  "properties": {
    "iso:country":"DE",
    "sg:address":"Gro\u00dfe Str. 9a",
    "sg:city":"Schee\u00dfel",
    "sg:phone":"+49 4263/3703",
    "sg:postcode":"27383",
    "sg:province":"Niedersachsen",
    "wof:name":"B. Theel",
    "wof:placetype":"venue"
},
  "geometry": {"coordinates":[9.483907,53.168671],"type":"Point"}
}