{
  "type": "Feature",
  "properties": {
    "iso:country":"DE",
    "sg:address":"Eidelstedter Weg 96",
    "sg:city":"Halstenbek",
    "sg:phone":"+49 4101/41788",
    "sg:postcode":"25469",
    "sg:province":"Schleswig-Holstein",
    "wof:name":"Edwin Walther",
    "wof:placetype":"venue"
},
  "geometry": {"coordinates":[9.856546,53.627457],"type":"Point"}
}