{
  "type": "Feature",
  "properties": {
    "iso:country":"DE",
    "sg:address":"Borriesstr. 94-100",
    "sg:city":"B\u00fcnde",
    "sg:phone":"+49 5223/48060",
    "sg:postcode":"32257",
    "sg:province":"Nordrhein-Westfalen",
    "wof:name":"Heinrich Fretthold Gmbh & Co.",
    "wof:placetype":"venue"
},
  "geometry": {"coordinates":[8.580166,52.205421],"type":"Point"}
}