{
  "type": "Feature",
  "properties": {
    "iso:country":"DE",
    "sg:address":"Gerhard-Storm-Str. 26",
    "sg:city":"Emmerich",
    "sg:phone":"+49 2822/97013",
    "sg:postcode":"46446",
    "sg:province":"Nordrhein-Westfalen",
    "wof:name":"Kanditenvertrieb Fokke Nijdeken",
    "wof:placetype":"venue"
},
  "geometry": {"coordinates":[6.2445530891,51.8382377625],"type":"Point"}
}