{
  "type": "Feature",
  "properties": {
    "iso:country":"DE",
    "sg:address":"Niederrheinische Str. 21",
    "sg:city":"Neukirchen",
    "sg:postcode":"34626",
    "sg:province":"Hessen",
    "wof:name":"Tr\u00fcmmer Verwaltungs- Gmbh",
    "wof:placetype":"venue"
},
  "geometry": {"coordinates":[9.3381977081,50.8717727661],"type":"Point"}
}