{
  "type": "Feature",
  "properties": {
    "iso:country":"DE",
    "sg:address":"Herforder Str. 150",
    "sg:city":"Lemgo",
    "sg:phone":"+49 5261/68302",
    "sg:postcode":"32657",
    "sg:province":"Nordrhein-Westfalen",
    "wof:name":"Erich Niebuhr",
    "wof:placetype":"venue"
},
  "geometry": {"coordinates":[8.862652,52.029037],"type":"Point"}
}