{
  "type": "Feature",
  "properties": {
    "iso:country":"DE",
    "sg:city":"Gars",
    "sg:phone":"+49 8073/634",
    "sg:postcode":"83536",
    "sg:province":"Bayern",
    "wof:name":"Hubert D\u00fcrbeck",
    "wof:placetype":"venue"
},
  "geometry": {"coordinates":[12.29508,48.166191],"type":"Point"}
}