{
  "type": "Feature",
  "properties": {
    "iso:country":"DE",
    "sg:address":"Schl\u00e4ferweg 36",
    "sg:city":"Diez",
    "sg:phone":"+49 6432/7120",
    "sg:postcode":"65582",
    "sg:province":"Rheinland-Pfalz",
    "wof:name":"J. Gr\u00fcn",
    "wof:placetype":"venue"
},
  "geometry": {"coordinates":[8.0183200836,50.3679885864],"type":"Point"}
}