{
  "type": "Feature",
  "properties": {
    "iso:country":"DE",
    "sg:address":"Lab\u00f6mitzer Str.",
    "sg:city":"Benz",
    "sg:postcode":"17429",
    "sg:province":"Mecklenburg-Vorpommern",
    "wof:name":"Tgb Benzer Transportbeton M\u00f6rtel- Und Kies Verwaltungs-",
    "wof:placetype":"venue"
},
  "geometry": {"coordinates":[14.0745792389,53.939289093],"type":"Point"}
}