{
  "type": "Feature",
  "properties": {
    "iso:country":"DE",
    "sg:address":"Westerwaldstr. 171",
    "sg:city":"Hennef",
    "sg:phone":"+49 2248/2637",
    "sg:postcode":"53773",
    "sg:province":"Nordrhein-Westfalen",
    "wof:name":"Klaus Kluth Drogerie",
    "wof:placetype":"venue"
},
  "geometry": {"coordinates":[7.368978,50.730713],"type":"Point"}
}