{
  "type": "Feature",
  "properties": {
    "iso:country":"DE",
    "sg:address":"Schultenhofstr. 40",
    "sg:city":"M\u00fclheim",
    "sg:phone":"+49 4920/8755060",
    "sg:postcode":"45475",
    "sg:province":"Nordrhein-Westfalen",
    "wof:name":"Systema Beleuchtungs- U. Deckengestaltungs Gmbh",
    "wof:placetype":"venue"
},
  "geometry": {"coordinates":[6.87795,51.457821],"type":"Point"}
}