{
  "type": "Feature",
  "properties": {
    "iso:country":"DE",
    "sg:address":"Gartenstrasse 18",
    "sg:city":"M\u00f6mbris",
    "sg:phone":"+49 6029/995861",
    "sg:postcode":"63776",
    "sg:province":"Bayern",
    "wof:name":"Reutec Gmbh",
    "wof:placetype":"venue"
},
  "geometry": {"coordinates":[9.184697,50.055401],"type":"Point"}
}