{
  "type": "Feature",
  "properties": {
    "iso:country":"DE",
    "sg:address":"Berliner Str. 7a",
    "sg:city":"Ingolstadt",
    "sg:phone":"+49 841/78211",
    "sg:postcode":"85051",
    "sg:province":"Bayern",
    "wof:name":"Dr. Med. Wolfgang Glaubitz Arzt F\u00fcr Allgemeinmedizin",
    "wof:placetype":"venue"
},
  "geometry": {"coordinates":[11.4124040604,48.7405471802],"type":"Point"}
}