{
  "type": "Feature",
  "properties": {
    "iso:country":"DE",
    "sg:address":"Eimsheimer Str. 11",
    "sg:city":"Wintersheim",
    "sg:phone":"+49 6733/6302",
    "sg:postcode":"67587",
    "sg:province":"Rheinland-Pfalz",
    "wof:name":"Karl Huxel",
    "wof:placetype":"venue"
},
  "geometry": {"coordinates":[8.2817382812,49.7787818909],"type":"Point"}
}