{
  "type": "Feature",
  "properties": {
    "iso:country":"DE",
    "sg:address":"Schmalkalder Str. 30",
    "sg:city":"Christes",
    "sg:phone":"+49 36844/40157",
    "sg:postcode":"98547",
    "sg:province":"Th\u00fcringen",
    "wof:name":"Horst Walther",
    "wof:placetype":"venue"
},
  "geometry": {"coordinates":[10.474929,50.663029],"type":"Point"}
}