{
  "type": "Feature",
  "properties": {
    "iso:country":"DE",
    "sg:address":"Hauptstr. 26",
    "sg:city":"Sch\u00f6neck",
    "sg:phone":"+49 37464/88457",
    "sg:postcode":"08261",
    "sg:province":"Sachsen",
    "wof:name":"Peter Meinel",
    "wof:placetype":"venue"
},
  "geometry": {"coordinates":[12.3324899673,50.3940238953],"type":"Point"}
}