{
  "type": "Feature",
  "properties": {
    "iso:country":"DE",
    "sg:address":"Neustadt 6",
    "sg:city":"B\u00fcdingen",
    "sg:phone":"+49 6042/2156",
    "sg:postcode":"63654",
    "sg:province":"Hessen",
    "wof:name":"H. Gilberz",
    "wof:placetype":"venue"
},
  "geometry": {"coordinates":[9.1158370972,50.2929229736],"type":"Point"}
}