{
  "type": "Feature",
  "properties": {
    "iso:country":"DE",
    "sg:address":"Bergstr. 8",
    "sg:city":"Hasbergen",
    "sg:phone":"+49 5405/1781",
    "sg:postcode":"49205",
    "sg:province":"Niedersachsen",
    "wof:name":"Wiko Neugebauer Ingenieur",
    "wof:placetype":"venue"
},
  "geometry": {"coordinates":[7.9604802132,52.2336502075],"type":"Point"}
}