{
  "type": "Feature",
  "properties": {
    "iso:country":"DE",
    "sg:address":"Gro\u00dfp\u00f6snaer Str. 36",
    "sg:city":"Leipzig",
    "sg:phone":"+49 34297/696430",
    "sg:postcode":"04288",
    "sg:province":"Sachsen",
    "wof:name":"Michael D\u00fcssler Rechtsanwalt",
    "wof:placetype":"venue"
},
  "geometry": {"coordinates":[12.4748601913,51.2785224915],"type":"Point"}
}