{
  "type": "Feature",
  "properties": {
    "iso:country":"DE",
    "sg:address":"Vichter Str. 108",
    "sg:city":"Stolberg",
    "sg:phone":"+49 2402/72495",
    "sg:postcode":"52224",
    "sg:province":"Nordrhein-Westfalen",
    "wof:name":"Elektro Straeck Gmbh",
    "wof:placetype":"venue"
},
  "geometry": {"coordinates":[6.275359,50.75098],"type":"Point"}
}