{
  "type": "Feature",
  "properties": {
    "iso:country":"DE",
    "sg:address":"Stormarnplatz 6",
    "sg:city":"Hamburg",
    "sg:phone":"+49 40/6011112",
    "sg:postcode":"22393",
    "sg:province":"Hamburg",
    "wof:name":"Hans-otto Noesselt",
    "wof:placetype":"venue"
},
  "geometry": {"coordinates":[10.094713,53.651165],"type":"Point"}
}