{
  "type": "Feature",
  "properties": {
    "iso:country":"DE",
    "sg:address":"Markgrafenstr. 7",
    "sg:city":"Emmendingen",
    "sg:phone":"+49 7641/8030",
    "sg:postcode":"79312",
    "sg:province":"Baden-W\u00fcrttemberg",
    "wof:name":"Heinz Greber",
    "wof:placetype":"venue"
},
  "geometry": {"coordinates":[7.8508691788,48.1203155518],"type":"Point"}
}