{
  "type": "Feature",
  "properties": {
    "iso:country":"DE",
    "sg:address":"Bielckenweg 19",
    "sg:city":"Berlin",
    "sg:phone":"+49 30/9416786",
    "sg:postcode":"13125",
    "sg:province":"Berlin",
    "wof:name":"Heinz Peter",
    "wof:placetype":"venue"
},
  "geometry": {"coordinates":[13.4998855591,52.6449012756],"type":"Point"}
}