{
  "type": "Feature",
  "properties": {
    "iso:country":"DE",
    "sg:address":"Kaiserstr. 21",
    "sg:city":"Landstuhl",
    "sg:phone":"+49 6371/16330",
    "sg:postcode":"66849",
    "sg:province":"Rheinland-Pfalz",
    "wof:name":"Werner Kesselring",
    "wof:placetype":"venue"
},
  "geometry": {"coordinates":[7.5674748421,49.4134979248],"type":"Point"}
}