{
  "type": "Feature",
  "properties": {
    "iso:country":"DE",
    "sg:address":"Oberer Hoppenlauweg 2-4",
    "sg:city":"Stuttgart",
    "sg:phone":"+49 711/1626311",
    "sg:postcode":"70174",
    "sg:province":"Baden-W\u00fcrttemberg",
    "wof:name":"Beratungsst. D. Weraheimes Beratung F. Werdende M\u00fctter",
    "wof:placetype":"venue"
},
  "geometry": {"coordinates":[9.166868,48.78363],"type":"Point"}
}