{
  "type": "Feature",
  "properties": {
    "iso:country":"DE",
    "sg:address":"Obergasse 14",
    "sg:city":"Hennweiler",
    "sg:phone":"+49 6752/8505",
    "sg:postcode":"55619",
    "sg:province":"Rheinland-Pfalz",
    "wof:name":"H. Schreiner Wwe. & Co.",
    "wof:placetype":"venue"
},
  "geometry": {"coordinates":[7.4334688187,49.8196411133],"type":"Point"}
}