{
  "type": "Feature",
  "properties": {
    "iso:country":"DE",
    "sg:address":"Zum Weiher 10",
    "sg:city":"Ruppichteroth",
    "sg:phone":"+49 2295/1720",
    "sg:postcode":"53809",
    "sg:province":"Nordrhein-Westfalen",
    "wof:name":"Schlamm",
    "wof:placetype":"venue"
},
  "geometry": {"coordinates":[7.4803519249,50.8757553101],"type":"Point"}
}