{
  "type": "Feature",
  "properties": {
    "iso:country":"DE",
    "sg:address":"Vordere Str. 43",
    "sg:city":"Fellbach",
    "sg:phone":"+49 711/581563",
    "sg:postcode":"70734",
    "sg:province":"Baden-W\u00fcrttemberg",
    "wof:name":"Hotel Kernenturm",
    "wof:placetype":"venue"
},
  "geometry": {"coordinates":[9.2796363831,48.8052406311],"type":"Point"}
}