{
  "type": "Feature",
  "properties": {
    "iso:country":"DE",
    "sg:address":"Weiherstr. 7",
    "sg:city":"Birkenfeld",
    "sg:phone":"+49 6782/7124",
    "sg:postcode":"55765",
    "sg:province":"Rheinland-Pfalz",
    "wof:name":"Hugo Brill",
    "wof:placetype":"venue"
},
  "geometry": {"coordinates":[7.153165,49.651688],"type":"Point"}
}