{
  "type": "Feature",
  "properties": {
    "iso:country":"DE",
    "sg:address":"Schulstr. 8",
    "sg:city":"Sendenhorst",
    "sg:phone":"+49 2526/1291",
    "sg:postcode":"48324",
    "sg:province":"Nordrhein-Westfalen",
    "wof:name":"Co Op",
    "wof:placetype":"venue"
},
  "geometry": {"coordinates":[7.8266129494,51.8445854187],"type":"Point"}
}