{
  "type": "Feature",
  "properties": {
    "iso:country":"DE",
    "sg:address":"Reuthstr. 3a",
    "sg:city":"Schechen",
    "sg:phone":"+49 8031/84800",
    "sg:postcode":"83135",
    "sg:province":"Bayern",
    "wof:name":"Dipl. Ing. Hans Weber Architekt",
    "wof:placetype":"venue"
},
  "geometry": {"coordinates":[12.128392,47.889702],"type":"Point"}
}