{
  "type": "Feature",
  "properties": {
    "iso:country":"DE",
    "sg:address":"Konrad-Adenauer-Str. 27",
    "sg:city":"Herborn",
    "sg:phone":"+49 2772/55666",
    "sg:postcode":"35745",
    "sg:province":"Hessen",
    "wof:name":"Reiner Birk",
    "wof:placetype":"venue"
},
  "geometry": {"coordinates":[8.3069868088,50.6732063293],"type":"Point"}
}