{
  "type": "Feature",
  "properties": {
    "iso:country":"DE",
    "sg:address":"Karl-Marx-Str. 276",
    "sg:city":"Seebergen",
    "sg:phone":"+49 36256/20455",
    "sg:postcode":"99869",
    "sg:province":"Th\u00fcringen",
    "wof:name":"G\u00fcnther Baumbach",
    "wof:placetype":"venue"
},
  "geometry": {"coordinates":[10.7781200409,50.892250061],"type":"Point"}
}