{
  "type": "Feature",
  "properties": {
    "iso:country":"DE",
    "sg:address":"Stadtweg 2",
    "sg:city":"Stade",
    "sg:phone":"+49 4141/61356",
    "sg:postcode":"21684",
    "sg:province":"Niedersachsen",
    "wof:name":"Johann Hinck",
    "wof:placetype":"venue"
},
  "geometry": {"coordinates":[9.466115,53.563244],"type":"Point"}
}