{
  "type": "Feature",
  "properties": {
    "iso:country":"DE",
    "sg:address":"Andreas-Fendt-Ring 1",
    "sg:city":"Bischofswiesen",
    "sg:phone":"+49 8652/7511",
    "sg:postcode":"83483",
    "sg:province":"Bayern",
    "wof:name":"K. Bittner-adamek",
    "wof:placetype":"venue"
},
  "geometry": {"coordinates":[12.96571,47.646095],"type":"Point"}
}