{
  "type": "Feature",
  "properties": {
    "iso:country":"DE",
    "sg:address":"Wasserturmstr. 5",
    "sg:city":"Schkeuditz",
    "sg:phone":"+49 34204/62888",
    "sg:postcode":"04435",
    "sg:province":"Sachsen",
    "wof:name":"Speba Spezial Bauausf\u00fchrungsgesellschaft Mbh",
    "wof:placetype":"venue"
},
  "geometry": {"coordinates":[12.24969,51.396572],"type":"Point"}
}