{
  "type": "Feature",
  "properties": {
    "iso:country":"DE",
    "sg:address":"Niedergasse 8",
    "sg:city":"Reichenberg",
    "sg:phone":"+49 351/8305367",
    "sg:postcode":"01468",
    "sg:province":"Sachsen",
    "wof:name":"G\u00fcnter Lingelbach",
    "wof:placetype":"venue"
},
  "geometry": {"coordinates":[13.682274,51.131821],"type":"Point"}
}