{
  "type": "Feature",
  "properties": {
    "iso:country":"DE",
    "sg:address":"Marktstr.",
    "sg:city":"Wissen",
    "sg:phone":"+49 2742/2360",
    "sg:postcode":"57537",
    "sg:province":"Rheinland-Pfalz",
    "wof:name":"Ludger M\u00fcller",
    "wof:placetype":"venue"
},
  "geometry": {"coordinates":[7.7354850769,50.7818717957],"type":"Point"}
}