{
  "type": "Feature",
  "properties": {
    "iso:country":"DE",
    "sg:address":"Laurentiusstr. 11",
    "sg:city":"Bad Neuenahr-Ahrweiler",
    "sg:phone":"+49 2641/34262",
    "sg:postcode":"53474",
    "sg:province":"Rheinland-Pfalz",
    "wof:name":"Rudolf Becker",
    "wof:placetype":"venue"
},
  "geometry": {"coordinates":[7.103831768,50.5367431641],"type":"Point"}
}