{
  "type": "Feature",
  "properties": {
    "iso:country":"DE",
    "sg:address":"Rathausstr. 61",
    "sg:city":"Wiesbaden",
    "sg:phone":"+49 611/6099499",
    "sg:postcode":"65203",
    "sg:province":"Hessen",
    "wof:name":"Ratskeller Biebrich",
    "wof:placetype":"venue"
},
  "geometry": {"coordinates":[8.2397651672,50.0413856506],"type":"Point"}
}