{
  "type": "Feature",
  "properties": {
    "iso:country":"DE",
    "sg:address":"R\u00f6merstr. 10",
    "sg:city":"Garmisch-Partenkirchen",
    "sg:phone":"+49 8821/53236",
    "sg:postcode":"82467",
    "sg:province":"Bayern",
    "wof:name":"Compr A Rechenzentrum B.hauck & Co.",
    "wof:placetype":"venue"
},
  "geometry": {"coordinates":[11.114068985,47.4938774109],"type":"Point"}
}