{
  "type": "Feature",
  "properties": {
    "iso:country":"DE",
    "sg:address":"Lindenallee 3",
    "sg:city":"Wrestedt",
    "sg:phone":"+49 5825/8225",
    "sg:postcode":"29559",
    "sg:province":"Niedersachsen",
    "wof:name":"Henry Sch\u00fctte",
    "wof:placetype":"venue"
},
  "geometry": {"coordinates":[10.578291893,52.9027404785],"type":"Point"}
}