{
  "type": "Feature",
  "properties": {
    "iso:country":"DE",
    "sg:address":"Bismarckstr. 60",
    "sg:city":"Berlin",
    "sg:phone":"+49 30/3416303",
    "sg:postcode":"10627",
    "sg:province":"Berlin",
    "wof:name":"Bernd Homa",
    "wof:placetype":"venue"
},
  "geometry": {"coordinates":[13.3005123138,52.5113983154],"type":"Point"}
}