{
  "type": "Feature",
  "properties": {
    "iso:country":"DE",
    "sg:address":"Koblenzer Str. 31",
    "sg:city":"Waldesch",
    "sg:phone":"+49 2628/778",
    "sg:postcode":"56323",
    "sg:province":"Rheinland-Pfalz",
    "wof:name":"Thomas Nentwich",
    "wof:placetype":"venue"
},
  "geometry": {"coordinates":[7.5469861031,50.2799491882],"type":"Point"}
}