{
  "type": "Feature",
  "properties": {
    "iso:country":"DE",
    "sg:address":"Prinzenallee 82",
    "sg:city":"Berlin",
    "sg:phone":"+49 30/7936028",
    "sg:postcode":"13357",
    "sg:province":"Berlin",
    "wof:name":"Alwitra",
    "wof:placetype":"venue"
},
  "geometry": {"coordinates":[13.382472,52.553913],"type":"Point"}
}