{
  "type": "Feature",
  "properties": {
    "iso:country":"DE",
    "sg:address":"Neuer Wall 10",
    "sg:city":"Hamburg",
    "sg:phone":"+49 40/354060",
    "sg:postcode":"20354",
    "sg:province":"Hamburg",
    "wof:name":"R. Raubart",
    "wof:placetype":"venue"
},
  "geometry": {"coordinates":[9.992317,53.552567],"type":"Point"}
}