{
  "type": "Feature",
  "properties": {
    "iso:country":"DE",
    "sg:address":"Pschorrstr. 9",
    "sg:city":"Feldafing",
    "sg:phone":"+49 8157/4900",
    "sg:postcode":"82340",
    "sg:province":"Bayern",
    "wof:name":"Utl Beteiligungs- Verwaltung Gmbh",
    "wof:placetype":"venue"
},
  "geometry": {"coordinates":[11.2960271835,47.9452400208],"type":"Point"}
}