{
  "type": "Feature",
  "properties": {
    "iso:country":"DE",
    "sg:address":"Meierstr. 18",
    "sg:city":"L\u00fcbeck",
    "sg:phone":"+49 451/83115",
    "sg:postcode":"23558",
    "sg:province":"Schleswig-Holstein",
    "wof:name":"B. Mischke",
    "wof:placetype":"venue"
},
  "geometry": {"coordinates":[10.6703233719,53.8623580933],"type":"Point"}
}