{
  "type": "Feature",
  "properties": {
    "iso:country":"DE",
    "sg:address":"Hauptstr. 336",
    "sg:city":"Idar-Oberstein",
    "sg:phone":"+49 6781/22569",
    "sg:postcode":"55743",
    "sg:province":"Rheinland-Pfalz",
    "wof:name":"Werner Reidenbach",
    "wof:placetype":"venue"
},
  "geometry": {"coordinates":[7.3220272064,49.7025642395],"type":"Point"}
}