{
  "type": "Feature",
  "properties": {
    "iso:country":"DE",
    "sg:address":"Hauptstr. 78",
    "sg:city":"Nordhausen",
    "sg:phone":"+49 3631/7902",
    "sg:postcode":"99734",
    "sg:province":"Th\u00fcringen",
    "wof:name":"Gem\u00fcsequelle",
    "wof:placetype":"venue"
},
  "geometry": {"coordinates":[10.7696352005,51.5157432556],"type":"Point"}
}