{
  "type": "Feature",
  "properties": {
    "iso:country":"DE",
    "sg:address":"Friedenfelser Str. 20",
    "sg:city":"Krummennaab",
    "sg:postcode":"92703",
    "sg:province":"Bayern",
    "wof:name":"Andreas Meisl Krummennaab Inh. Wolfgang Meisl E. Kfm.",
    "wof:placetype":"venue"
},
  "geometry": {"coordinates":[12.1038351059,49.8331184387],"type":"Point"}
}