{
  "type": "Feature",
  "properties": {
    "iso:country":"DE",
    "sg:address":"Dorfstr. 32",
    "sg:city":"Reinbek",
    "sg:phone":"+49 40/7223642",
    "sg:postcode":"21465",
    "sg:province":"Schleswig-Holstein",
    "wof:name":"Karlheinz Wagener Architekt",
    "wof:placetype":"venue"
},
  "geometry": {"coordinates":[10.252663,53.530979],"type":"Point"}
}