{
  "type": "Feature",
  "properties": {
    "iso:country":"DE",
    "sg:address":"Lippertsreuter Str. 16",
    "sg:city":"Frickingen",
    "sg:phone":"+49 7554/334",
    "sg:postcode":"88699",
    "sg:province":"Baden-W\u00fcrttemberg",
    "wof:name":"Fleisch- Und Wurstwarenfabrik Xaver Schwarz Gmbh & Co. Kg",
    "wof:placetype":"venue"
},
  "geometry": {"coordinates":[9.2702884674,47.8101387024],"type":"Point"}
}