{
  "type": "Feature",
  "properties": {
    "iso:country":"DE",
    "sg:address":"Lindenhofstr. 130",
    "sg:city":"Schw\u00e4bisch Gm\u00fcnd",
    "sg:postcode":"73529",
    "sg:province":"Baden-W\u00fcrttemberg",
    "wof:name":"Leugger Gmbh",
    "wof:placetype":"venue"
},
  "geometry": {"coordinates":[9.8599758148,48.7765960693],"type":"Point"}
}