{
  "type": "Feature",
  "properties": {
    "iso:country":"DE",
    "sg:address":"Schwarzwasserweg 11",
    "sg:city":"Suhl",
    "sg:phone":"+49 3681/21491",
    "sg:postcode":"98527",
    "sg:province":"Th\u00fcringen",
    "wof:name":"Dat Pr\u00fcf- Und Sch\u00e4tzungsstelle",
    "wof:placetype":"venue"
},
  "geometry": {"coordinates":[10.7051,50.619114],"type":"Point"}
}