{
  "type": "Feature",
  "properties": {
    "iso:country":"DE",
    "sg:address":"Hohe Warte 2",
    "sg:city":"Essen",
    "sg:postcode":"45147",
    "sg:province":"Nordrhein-Westfalen",
    "wof:name":"Taxi-as Gmbh",
    "wof:placetype":"venue"
},
  "geometry": {"coordinates":[6.9789290428,51.4389762878],"type":"Point"}
}