{
  "type": "Feature",
  "properties": {
    "iso:country":"DE",
    "sg:address":"Wiesentalstr. 3",
    "sg:city":"B\u00f6blingen",
    "sg:phone":"+49 7031/760610",
    "sg:postcode":"71034",
    "sg:province":"Baden-W\u00fcrttemberg",
    "wof:name":"Harald St\u00fcckel",
    "wof:placetype":"venue"
},
  "geometry": {"coordinates":[8.952422142,48.6917762756],"type":"Point"}
}