{
  "type": "Feature",
  "properties": {
    "iso:country":"DE",
    "sg:address":"T\u00e4nnelbachstr. 6",
    "sg:city":"Raubling",
    "sg:postcode":"83064",
    "sg:province":"Bayern",
    "wof:name":"Zaisserer Gmbh",
    "wof:placetype":"venue"
},
  "geometry": {"coordinates":[12.1135702133,47.8031158447],"type":"Point"}
}