{
  "type": "Feature",
  "properties": {
    "iso:country":"DE",
    "sg:address":"Hauptstr. 43",
    "sg:city":"Meerbusch",
    "sg:phone":"+49 2150/5856",
    "sg:postcode":"40668",
    "sg:province":"Nordrhein-Westfalen",
    "wof:name":"Werner Oellers",
    "wof:placetype":"venue"
},
  "geometry": {"coordinates":[6.6805567741,51.3035163879],"type":"Point"}
}