{
  "type": "Feature",
  "properties": {
    "iso:country":"DE",
    "sg:address":"Kattreppel 2",
    "sg:city":"Ostenfeld",
    "sg:phone":"+49 4845/950",
    "sg:postcode":"25872",
    "sg:province":"Schleswig-Holstein",
    "wof:name":"Inge Aretz Architektin",
    "wof:placetype":"venue"
},
  "geometry": {"coordinates":[9.230359,54.463943],"type":"Point"}
}