{
  "type": "Feature",
  "properties": {
    "iso:country":"DE",
    "sg:address":"Ring 23",
    "sg:city":"Markkleeberg",
    "sg:phone":"+49 341/3588045",
    "sg:postcode":"04416",
    "sg:province":"Sachsen",
    "wof:name":"Uwe Neidhardt Rechtsanwalt",
    "wof:placetype":"venue"
},
  "geometry": {"coordinates":[12.3674383163,51.2805671692],"type":"Point"}
}