{
  "type": "Feature",
  "properties": {
    "iso:country":"DE",
    "sg:address":"Schillerstr. 1",
    "sg:city":"Eschelbronn",
    "sg:phone":"+49 6226/42113",
    "sg:postcode":"74927",
    "sg:province":"Baden-W\u00fcrttemberg",
    "wof:name":"Walter W\u00f6hr Architekt",
    "wof:placetype":"venue"
},
  "geometry": {"coordinates":[8.85902,49.319267],"type":"Point"}
}