{
  "type": "Feature",
  "properties": {
    "iso:country":"DE",
    "sg:address":"Im Schlo\u00df 1",
    "sg:city":"T\u00fcbingen",
    "sg:phone":"+49 7071/602180",
    "sg:postcode":"72074",
    "sg:province":"Baden-W\u00fcrttemberg",
    "wof:name":"Kloster- Und Schlo\u00dfmuseum",
    "wof:placetype":"venue"
},
  "geometry": {"coordinates":[9.060472,48.562241],"type":"Point"}
}