{
  "type": "Feature",
  "properties": {
    "iso:country":"DE",
    "sg:address":"\u00dcberlinger Str. 38",
    "sg:city":"Pfullendorf",
    "sg:phone":"+49 7552/26070",
    "sg:postcode":"88630",
    "sg:province":"Baden-W\u00fcrttemberg",
    "wof:name":"Strobel Gmbh",
    "wof:placetype":"venue"
},
  "geometry": {"coordinates":[9.246546,47.928089],"type":"Point"}
}