{
  "type": "Feature",
  "properties": {
    "iso:country":"DE",
    "sg:address":"Gr\u00fcner Weg 82",
    "sg:city":"Norderstedt",
    "sg:phone":"+49 40/52950397",
    "sg:postcode":"22851",
    "sg:province":"Schleswig-Holstein",
    "wof:name":"H\u00fcttersen Gmbh Beratung F\u00fcr Marketing",
    "wof:placetype":"venue"
},
  "geometry": {"coordinates":[10.048078537,53.7009353638],"type":"Point"}
}