{
  "type": "Feature",
  "properties": {
    "iso:country":"DE",
    "sg:address":"Bergstr. 22",
    "sg:city":"Finnentrop",
    "sg:phone":"+49 2721/70786",
    "sg:postcode":"57413",
    "sg:province":"Nordrhein-Westfalen",
    "wof:name":"Herbert Pieper",
    "wof:placetype":"venue"
},
  "geometry": {"coordinates":[7.9589838982,51.1559410095],"type":"Point"}
}