{
  "type": "Feature",
  "properties": {
    "iso:country":"DE",
    "sg:address":"Dortmunder Str. 3",
    "sg:city":"St. Wendel",
    "sg:phone":"+49 6851/70011",
    "sg:postcode":"66606",
    "sg:province":"Saarland",
    "wof:name":"H. Erschens",
    "wof:placetype":"venue"
},
  "geometry": {"coordinates":[7.139138,49.465378],"type":"Point"}
}