{
  "type": "Feature",
  "properties": {
    "iso:country":"DE",
    "sg:address":"Magdeburger All 75",
    "sg:city":"Erfurt",
    "sg:phone":"+49 361/7314135",
    "sg:postcode":"99086",
    "sg:province":"Th\u00fcringen",
    "wof:name":"Akb Privat- & Handelsbank Ag",
    "wof:placetype":"venue"
},
  "geometry": {"coordinates":[11.025276,50.992046],"type":"Point"}
}