{
  "type": "Feature",
  "properties": {
    "iso:country":"DE",
    "sg:address":"Sch\u00f6nefeld-Airport",
    "sg:city":"Berlin",
    "sg:postcode":"12521",
    "sg:province":"Berlin",
    "wof:name":"Free Zone Berlin Brandenburg International Ag",
    "wof:placetype":"venue"
},
  "geometry": {"coordinates":[13.4119,52.523781],"type":"Point"}
}