{
  "type": "Feature",
  "properties": {
    "iso:country":"DE",
    "sg:address":"Kornstr. 49",
    "sg:city":"Stadtbergen",
    "sg:phone":"+49 821/4397599",
    "sg:postcode":"86391",
    "sg:province":"Bayern",
    "wof:name":"Treppauf - Treppab Gmbh",
    "wof:placetype":"venue"
},
  "geometry": {"coordinates":[10.8417005539,48.3468666077],"type":"Point"}
}