{
  "type": "Feature",
  "properties": {
    "iso:country":"DE",
    "sg:address":"An Der M\u00fchle 3",
    "sg:city":"Bliedersdorf",
    "sg:phone":"+49 4163/818910",
    "sg:postcode":"21640",
    "sg:province":"Niedersachsen",
    "wof:name":"Messmer Import Export Gmbh",
    "wof:placetype":"venue"
},
  "geometry": {"coordinates":[9.5775718689,53.4825286865],"type":"Point"}
}