{
  "type": "Feature",
  "properties": {
    "iso:country":"DE",
    "sg:address":"Am Sportplatz 7",
    "sg:city":"Barkelsby",
    "sg:phone":"+49 4351/81620",
    "sg:postcode":"24360",
    "sg:province":"Schleswig-Holstein",
    "wof:name":"Heinz Lorenzen Architekt",
    "wof:placetype":"venue"
},
  "geometry": {"coordinates":[9.834471,54.503914],"type":"Point"}
}