{
  "type": "Feature",
  "properties": {
    "iso:country":"DE",
    "sg:address":"Pfaffenwaldring 47",
    "sg:city":"Stuttgart",
    "sg:phone":"+49 711/6857250",
    "sg:postcode":"70569",
    "sg:province":"Baden-W\u00fcrttemberg",
    "wof:name":"Institut F\u00fcr Theorie Der Elektrotechnik",
    "wof:placetype":"venue"
},
  "geometry": {"coordinates":[9.102893,48.746651],"type":"Point"}
}