{
  "type": "Feature",
  "properties": {
    "iso:country":"DE",
    "sg:address":"Bleichstr. 39a",
    "sg:city":"Paderborn",
    "sg:phone":"+49 5251/136470",
    "sg:postcode":"33102",
    "sg:province":"Nordrhein-Westfalen",
    "wof:name":"Landwirtschaftlicher Betriebs Hilfsdienst F\u00fcr Den Kreis",
    "wof:placetype":"venue"
},
  "geometry": {"coordinates":[8.740625,51.719616],"type":"Point"}
}