{
  "type": "Feature",
  "properties": {
    "iso:country":"DE",
    "sg:address":"Industriestr. 1",
    "sg:city":"Mainz",
    "sg:phone":"+49 6131/681180",
    "sg:postcode":"55120",
    "sg:province":"Rheinland-Pfalz",
    "wof:name":"Albert Schneider",
    "wof:placetype":"venue"
},
  "geometry": {"coordinates":[8.237309,50.022076],"type":"Point"}
}