{
  "type": "Feature",
  "properties": {
    "iso:country":"DE",
    "sg:address":"Bruno-H.-B\u00fcrgel-Str. 50",
    "sg:city":"Fehrbellin",
    "sg:phone":"+49 33932/71680",
    "sg:postcode":"16833",
    "sg:province":"Brandenburg",
    "wof:name":"Ehemaliges Hotel Germania In Meyenburg!",
    "wof:placetype":"venue"
},
  "geometry": {"coordinates":[12.761428,52.81456],"type":"Point"}
}