{
  "type": "Feature",
  "properties": {
    "iso:country":"DE",
    "sg:address":"Altstadt 2",
    "sg:city":"Melsungen",
    "sg:phone":"+49 5661/2192",
    "sg:postcode":"34212",
    "sg:province":"Hessen",
    "wof:name":"Ev. Pfarramt Ii Obermelsungen",
    "wof:placetype":"venue"
},
  "geometry": {"coordinates":[9.5452508926,51.129524231],"type":"Point"}
}