{
  "type": "Feature",
  "properties": {
    "iso:country":"DE",
    "sg:address":"Kurze Str. 27",
    "sg:city":"Leutkirch",
    "sg:phone":"+49 7561/3142",
    "sg:postcode":"88299",
    "sg:province":"Baden-W\u00fcrttemberg",
    "wof:name":"Felix Redle Architekt",
    "wof:placetype":"venue"
},
  "geometry": {"coordinates":[10.02075,47.809978],"type":"Point"}
}