{
  "type": "Feature",
  "properties": {
    "iso:country":"DE",
    "sg:address":"Entenbachstr. 12",
    "sg:city":"M\u00fcnchen",
    "sg:phone":"+49 89/657794",
    "sg:postcode":"81541",
    "sg:province":"Bayern",
    "wof:name":"S. H\u00e4usler",
    "wof:placetype":"venue"
},
  "geometry": {"coordinates":[11.5788164139,48.1240005493],"type":"Point"}
}