{
  "type": "Feature",
  "properties": {
    "iso:country":"DE",
    "sg:address":"Hebelstr. 22",
    "sg:city":"Ispringen",
    "sg:phone":"+49 7231/82240",
    "sg:postcode":"75228",
    "sg:province":"Baden-W\u00fcrttemberg",
    "wof:name":"Wenninger",
    "wof:placetype":"venue"
},
  "geometry": {"coordinates":[8.668613,48.910652],"type":"Point"}
}