{
  "type": "Feature",
  "properties": {
    "iso:country":"DE",
    "sg:address":"Hesselbergstr. 17",
    "sg:city":"Ehingen",
    "sg:phone":"+49 9835/264",
    "sg:postcode":"91725",
    "sg:province":"Bayern",
    "wof:name":"Gerhard Siegmund",
    "wof:placetype":"venue"
},
  "geometry": {"coordinates":[10.539457,49.085495],"type":"Point"}
}