{
  "type": "Feature",
  "properties": {
    "iso:country":"DE",
    "sg:address":"Blasenbergstr. 26",
    "sg:city":"Scheidegg",
    "sg:phone":"+49 8381/1229",
    "sg:postcode":"88175",
    "sg:province":"Bayern",
    "wof:name":"Hentschel Gmbh",
    "wof:placetype":"venue"
},
  "geometry": {"coordinates":[9.851421,47.581337],"type":"Point"}
}