{
  "type": "Feature",
  "properties": {
    "iso:country":"DE",
    "sg:address":"M\u00fchlenstr 2-4",
    "sg:city":"Erkrath",
    "sg:phone":"+49 211/900000",
    "sg:postcode":"40699",
    "sg:province":"Nordrhein-Westfalen",
    "wof:name":"Lichttechnisches Werk Gmbh",
    "wof:placetype":"venue"
},
  "geometry": {"coordinates":[6.8949799538,51.2211456299],"type":"Point"}
}