{
  "type": "Feature",
  "properties": {
    "iso:country":"DE",
    "sg:address":"Lagerstr. 47",
    "sg:city":"Dieburg",
    "sg:phone":"+49 6071/92360",
    "sg:postcode":"64807",
    "sg:province":"Hessen",
    "wof:name":"Glas-lerchenm\u00fcller Gmbh",
    "wof:placetype":"venue"
},
  "geometry": {"coordinates":[8.8600759506,49.9097328186],"type":"Point"}
}