{
  "type": "Feature",
  "properties": {
    "iso:country":"DE",
    "sg:address":"Am Klosterberg 33",
    "sg:city":"Emmerich",
    "sg:phone":"+49 2822/45947",
    "sg:postcode":"46446",
    "sg:province":"Nordrhein-Westfalen",
    "wof:name":"Odontos Gmbh",
    "wof:placetype":"venue"
},
  "geometry": {"coordinates":[6.2398581505,51.8459625244],"type":"Point"}
}