{
  "type": "Feature",
  "properties": {
    "iso:country":"DE",
    "sg:address":"K\u00f6rnerstr. 2",
    "sg:city":"Witten",
    "sg:phone":"+49 2302/279250",
    "sg:postcode":"58452",
    "sg:province":"Nordrhein-Westfalen",
    "wof:name":"Kalin Und Schilling Rechtsanw\u00e4lte",
    "wof:placetype":"venue"
},
  "geometry": {"coordinates":[7.3370671272,51.4369163513],"type":"Point"}
}