{
  "type": "Feature",
  "properties": {
    "iso:country":"DE",
    "sg:address":"Im Schmidtenloch 34",
    "sg:city":"Mechernich",
    "sg:phone":"+49 2443/1017",
    "sg:postcode":"53894",
    "sg:province":"Nordrhein-Westfalen",
    "wof:name":"Rds Immobilien Gmbh & Co. Kg",
    "wof:placetype":"venue"
},
  "geometry": {"coordinates":[6.6470217705,50.5952186584],"type":"Point"}
}