{
  "type": "Feature",
  "properties": {
    "iso:country":"DE",
    "sg:address":"Schillerstr. 22",
    "sg:city":"Korb",
    "sg:phone":"+49 7151/33637",
    "sg:postcode":"71404",
    "sg:province":"Baden-W\u00fcrttemberg",
    "wof:name":"Friedrich Degler",
    "wof:placetype":"venue"
},
  "geometry": {"coordinates":[9.3633003235,48.8407707214],"type":"Point"}
}