{
  "type": "Feature",
  "properties": {
    "iso:country":"DE",
    "sg:address":"\u00d6schweg 12",
    "sg:city":"Wilhelmsdorf",
    "sg:phone":"+49 7503/1518",
    "sg:postcode":"88271",
    "sg:province":"Baden-W\u00fcrttemberg",
    "wof:name":"Dr. Med. Marcel Gerhardt Chiropraktiker",
    "wof:placetype":"venue"
},
  "geometry": {"coordinates":[9.4258298874,47.8626556396],"type":"Point"}
}