{
  "type": "Feature",
  "properties": {
    "iso:country":"DE",
    "sg:address":"Neuer Gr\u00fcner Weg 25",
    "sg:city":"K\u00f6ln",
    "sg:phone":"+49 221/49851",
    "sg:postcode":"50933",
    "sg:province":"Nordrhein-Westfalen",
    "wof:name":"Altenkranken- Und Pflegeheim Heinrich-p\u00fcschel-haus",
    "wof:placetype":"venue"
},
  "geometry": {"coordinates":[6.8784,50.944031],"type":"Point"}
}