{
  "type": "Feature",
  "properties": {
    "iso:country":"DE",
    "sg:address":"Pa\u00dfh\u00f6he 2",
    "sg:city":"Feldberg",
    "sg:phone":"+49 7676/214",
    "sg:postcode":"79868",
    "sg:province":"Baden-W\u00fcrttemberg",
    "wof:name":"Hans-georg Kapferer",
    "wof:placetype":"venue"
},
  "geometry": {"coordinates":[8.0467195511,47.8575172424],"type":"Point"}
}