{
  "type": "Feature",
  "properties": {
    "iso:country":"DE",
    "sg:address":"Neckarsteinacher Str. 52",
    "sg:city":"Neckargem\u00fcnd",
    "sg:phone":"+49 6223/74313",
    "sg:postcode":"69151",
    "sg:province":"Baden-W\u00fcrttemberg",
    "wof:name":"Jet Tankstelle",
    "wof:placetype":"venue"
},
  "geometry": {"coordinates":[8.8076906204,49.3951911926],"type":"Point"}
}