{
  "type": "Feature",
  "properties": {
    "iso:country":"DE",
    "sg:address":"Bahnhofstr. 35",
    "sg:city":"Schee\u00dfel",
    "sg:phone":"+49 4263/4945",
    "sg:postcode":"27383",
    "sg:province":"Niedersachsen",
    "wof:name":"G\u00fcnter Meinke",
    "wof:placetype":"venue"
},
  "geometry": {"coordinates":[9.488910675,53.1669921875],"type":"Point"}
}