{
  "type": "Feature",
  "properties": {
    "iso:country":"DE",
    "sg:address":"Fritz-Elsas-Str. 20",
    "sg:city":"Berlin",
    "sg:postcode":"10825",
    "sg:province":"Berlin",
    "wof:name":"Feldmann-jardon Verlagsvertreter",
    "wof:placetype":"venue"
},
  "geometry": {"coordinates":[13.344535,52.482491],"type":"Point"}
}