{
  "type": "Feature",
  "properties": {
    "iso:country":"DE",
    "sg:address":"Einsteinstr. 13",
    "sg:city":"Mayen",
    "sg:phone":"+49 2651/904002",
    "sg:postcode":"56727",
    "sg:province":"Rheinland-Pfalz",
    "wof:name":"Renate Kr\u00e4mer",
    "wof:placetype":"venue"
},
  "geometry": {"coordinates":[7.216132,50.32198],"type":"Point"}
}