{
  "type": "Feature",
  "properties": {
    "iso:country":"DE",
    "sg:address":"Gumpersdorfer Weg 8",
    "sg:city":"Tann",
    "sg:phone":"+49 8572/241",
    "sg:postcode":"84367",
    "sg:province":"Bayern",
    "wof:name":"Otto Lechl Kg",
    "wof:placetype":"venue"
},
  "geometry": {"coordinates":[12.892868042,48.3077812195],"type":"Point"}
}