{
  "type": "Feature",
  "properties": {
    "iso:country":"DE",
    "sg:address":"Postfach 155:: 46374 Bocholt:: Germany.^^Meckenemstrasse 10::",
    "sg:city":"Bocholt",
    "sg:phone":"+49 2871/9520",
    "sg:postcode":"46395",
    "sg:province":"Nordrhein-Westfalen",
    "wof:name":"Volksbank Bocholt Eg",
    "wof:placetype":"venue"
},
  "geometry": {"coordinates":[6.617612,51.834663],"type":"Point"}
}