{
  "type": "Feature",
  "properties": {
    "iso:country":"DE",
    "sg:address":"Dampfm\u00fchlenweg 58",
    "sg:city":"Krefeld",
    "sg:phone":"+49 2151/800957",
    "sg:postcode":"47799",
    "sg:province":"Nordrhein-Westfalen",
    "wof:name":"Poststuben",
    "wof:placetype":"venue"
},
  "geometry": {"coordinates":[6.5658159256,51.3355102539],"type":"Point"}
}