{
  "type": "Feature",
  "properties": {
    "iso:country":"DE",
    "sg:address":"Keplerstr. 38",
    "sg:city":"Hanau",
    "sg:phone":"+49 6181/254621",
    "sg:postcode":"63454",
    "sg:province":"Hessen",
    "wof:name":"H. Unkelbach",
    "wof:placetype":"venue"
},
  "geometry": {"coordinates":[8.8804397583,50.1300544739],"type":"Point"}
}