{
  "type": "Feature",
  "properties": {
    "iso:country":"DE",
    "sg:address":"Friedrichsthaler Str. 23",
    "sg:city":"Neunkirchen",
    "sg:phone":"+49 6821/97140",
    "sg:postcode":"66540",
    "sg:province":"Saarland",
    "wof:name":"Bauunternehmung R. Wagner Gmbh & Co. Kg",
    "wof:placetype":"venue"
},
  "geometry": {"coordinates":[7.118644,49.322319],"type":"Point"}
}