{
  "type": "Feature",
  "properties": {
    "iso:country":"DE",
    "sg:address":"Hamburger Str. 110",
    "sg:city":"Bad Oldesloe",
    "sg:phone":"+49 4531/885255",
    "sg:postcode":"23843",
    "sg:province":"Schleswig-Holstein",
    "wof:name":"Aral Ag",
    "wof:placetype":"venue"
},
  "geometry": {"coordinates":[10.3598232269,53.8033409119],"type":"Point"}
}