{
  "type": "Feature",
  "properties": {
    "iso:country":"DE",
    "sg:address":"Meininger Str. 282",
    "sg:city":"Suhl",
    "sg:phone":"+49 3681/24509",
    "sg:postcode":"98529",
    "sg:province":"Th\u00fcringen",
    "wof:name":"Dieter Hommel Ingenieur",
    "wof:placetype":"venue"
},
  "geometry": {"coordinates":[10.6372041702,50.603717804],"type":"Point"}
}