{
  "type": "Feature",
  "properties": {
    "iso:country":"DE",
    "sg:address":"Lange Str. 69",
    "sg:city":"Delbr\u00fcck",
    "sg:phone":"+49 5250/1749",
    "sg:postcode":"33129",
    "sg:province":"Nordrhein-Westfalen",
    "wof:name":"Grunewald",
    "wof:placetype":"venue"
},
  "geometry": {"coordinates":[8.5561361313,51.7618942261],"type":"Point"}
}