{
  "type": "Feature",
  "properties": {
    "iso:country":"DE",
    "sg:address":"Hauptstr. 31",
    "sg:city":"M\u00f6ckm\u00fchl",
    "sg:phone":"+49 6298/4953",
    "sg:postcode":"74219",
    "sg:province":"Baden-W\u00fcrttemberg",
    "wof:name":"Kallenberger",
    "wof:placetype":"venue"
},
  "geometry": {"coordinates":[9.3595581055,49.3237533569],"type":"Point"}
}