{
  "type": "Feature",
  "properties": {
    "iso:country":"DE",
    "sg:address":"Hammerweg 12",
    "sg:city":"Georgensgm\u00fcnd",
    "sg:phone":"+49 9172/68353",
    "sg:postcode":"91166",
    "sg:province":"Bayern",
    "wof:name":"B. Masin",
    "wof:placetype":"venue"
},
  "geometry": {"coordinates":[11.0102682114,49.18151474],"type":"Point"}
}