{
  "type": "Feature",
  "properties": {
    "iso:country":"DE",
    "sg:address":"Bahnhofstr. 3",
    "sg:city":"Neu-Isenburg",
    "sg:phone":"+49 6102/23903",
    "sg:postcode":"63263",
    "sg:province":"Hessen",
    "wof:name":"Artur Krumel",
    "wof:placetype":"venue"
},
  "geometry": {"coordinates":[8.6949605942,50.0529785156],"type":"Point"}
}