{
  "type": "Feature",
  "properties": {
    "iso:country":"DE",
    "sg:address":"Ringstr. 6",
    "sg:city":"Oberbergkirchen",
    "sg:phone":"+49 8637/828",
    "sg:postcode":"84564",
    "sg:province":"Bayern",
    "wof:name":"Alfred H\u00e4usler",
    "wof:placetype":"venue"
},
  "geometry": {"coordinates":[12.38598,48.306751],"type":"Point"}
}