{
  "type": "Feature",
  "properties": {
    "iso:country":"DE",
    "sg:address":"Feldweg 6",
    "sg:city":"Morsbach",
    "sg:phone":"+49 2294/8465",
    "sg:postcode":"51597",
    "sg:province":"Nordrhein-Westfalen",
    "wof:name":"Siegfried Fischer",
    "wof:placetype":"venue"
},
  "geometry": {"coordinates":[7.717993,50.869499],"type":"Point"}
}