{
  "type": "Feature",
  "properties": {
    "iso:country":"DE",
    "sg:city":"Speyer",
    "sg:postcode":"67346",
    "sg:province":"Rheinland-Pfalz",
    "wof:name":"Das \u00dcbersetzerportal",
    "wof:placetype":"venue"
},
  "geometry": {"coordinates":[8.431081,49.319332],"type":"Point"}
}