{
  "type": "Feature",
  "properties": {
    "iso:country":"DE",
    "sg:address":"Ulmer Str. 107",
    "sg:city":"Metzingen",
    "sg:phone":"+49 7123/4573",
    "sg:postcode":"72555",
    "sg:province":"Baden-W\u00fcrttemberg",
    "wof:name":"Dr. Emmerich Bakonyi",
    "wof:placetype":"venue"
},
  "geometry": {"coordinates":[9.2924203873,48.5344924927],"type":"Point"}
}