{
  "type": "Feature",
  "properties": {
    "iso:country":"DE",
    "sg:address":"Waldheimer Str. 3",
    "sg:city":"Hartha",
    "sg:phone":"+49 34328/42790",
    "sg:postcode":"04746",
    "sg:province":"Sachsen",
    "wof:name":"Hh Heiner Hauptmann Gmbh",
    "wof:placetype":"venue"
},
  "geometry": {"coordinates":[12.965879,51.096134],"type":"Point"}
}