{
  "type": "Feature",
  "properties": {
    "iso:country":"DE",
    "sg:address":"Bahnhofstr. 5",
    "sg:city":"Neckarsteinach",
    "sg:phone":"+49 6229/960145",
    "sg:postcode":"69239",
    "sg:province":"Hessen",
    "wof:name":"Oliver Stoll",
    "wof:placetype":"venue"
},
  "geometry": {"coordinates":[8.8387651443,49.4079360962],"type":"Point"}
}