{
  "type": "Feature",
  "properties": {
    "iso:country":"DE",
    "sg:address":"Heidentalstr. 26",
    "sg:city":"Detmold",
    "sg:phone":"+49 5231/8237",
    "sg:postcode":"32760",
    "sg:province":"Nordrhein-Westfalen",
    "wof:name":"Bela Consut Immobilien Verwaltung Und Verwertung",
    "wof:placetype":"venue"
},
  "geometry": {"coordinates":[8.8318281174,51.9225845337],"type":"Point"}
}