{
  "type": "Feature",
  "properties": {
    "iso:country":"DE",
    "sg:address":"Franz-Lehar-Str. 18",
    "sg:city":"Neu-Ulm",
    "sg:postcode":"89231",
    "sg:province":"Bayern",
    "wof:name":"Orosi Uhren Und Schmuck Vertriebs Gmbh",
    "wof:placetype":"venue"
},
  "geometry": {"coordinates":[10.0244321823,48.4059638977],"type":"Point"}
}