{
  "type": "Feature",
  "properties": {
    "iso:country":"DE",
    "sg:address":"Luxemburger Str. 5",
    "sg:city":"M\u00fcnchen",
    "sg:phone":"+49 89/3689533",
    "sg:postcode":"80805",
    "sg:province":"Bayern",
    "wof:name":"J. W. Schmidt",
    "wof:placetype":"venue"
},
  "geometry": {"coordinates":[11.5960969925,48.1704711914],"type":"Point"}
}