{
  "type": "Feature",
  "properties": {
    "iso:country":"DE",
    "sg:address":"Lessingstr. 51",
    "sg:city":"D\u00fcsseldorf",
    "sg:phone":"+49 211/772364",
    "sg:postcode":"40227",
    "sg:province":"Nordrhein-Westfalen",
    "wof:name":"Hans Hendrichs",
    "wof:placetype":"venue"
},
  "geometry": {"coordinates":[6.792751,51.213776],"type":"Point"}
}