{
  "type": "Feature",
  "properties": {
    "iso:country":"DE",
    "sg:address":"Holl\u00e4ndische Str. 156 a",
    "sg:city":"Kassel",
    "sg:phone":"+49 561/898443",
    "sg:postcode":"34127",
    "sg:province":"Hessen",
    "wof:name":"Angelika Hartmann Masseurin",
    "wof:placetype":"venue"
},
  "geometry": {"coordinates":[9.493957,51.334904],"type":"Point"}
}