{
  "type": "Feature",
  "properties": {
    "iso:country":"DE",
    "sg:address":"Dillizerstr. 6",
    "sg:city":"Herrsching",
    "sg:phone":"+49 8152/6053",
    "sg:postcode":"82211",
    "sg:province":"Bayern",
    "wof:name":"Bodo Becker Steuerberater",
    "wof:placetype":"venue"
},
  "geometry": {"coordinates":[11.1719198227,47.9941558838],"type":"Point"}
}