{
  "type": "Feature",
  "properties": {
    "iso:country":"DE",
    "sg:address":"Berliner Str. 62",
    "sg:city":"Cottbus",
    "sg:postcode":"03046",
    "sg:province":"Brandenburg",
    "wof:name":"R. Schuppenbnies",
    "wof:placetype":"venue"
},
  "geometry": {"coordinates":[14.3120212555,51.7575645447],"type":"Point"}
}