{
  "type": "Feature",
  "properties": {
    "iso:country":"DE",
    "sg:address":"Erlanger Str. 18",
    "sg:city":"Schnaittach",
    "sg:phone":"+49 9153/251",
    "sg:postcode":"91220",
    "sg:province":"Bayern",
    "wof:name":"Ev. Pfarramt",
    "wof:placetype":"venue"
},
  "geometry": {"coordinates":[11.3359479904,49.5602722168],"type":"Point"}
}