{
  "type": "Feature",
  "properties": {
    "iso:country":"DE",
    "sg:address":"Burgstr. 3",
    "sg:city":"H\u00fcnfeld",
    "sg:phone":"+49 6652/96060",
    "sg:postcode":"36088",
    "sg:province":"Hessen",
    "wof:name":"Kurheim Schloss Mackenzell",
    "wof:placetype":"venue"
},
  "geometry": {"coordinates":[9.7878751755,50.6559066772],"type":"Point"}
}