{
  "type": "Feature",
  "properties": {
    "iso:country":"DE",
    "sg:address":"Wiedensahler Str. 37",
    "sg:city":"Niedernw\u00f6hren",
    "sg:phone":"+49 5726/481",
    "sg:postcode":"31712",
    "sg:province":"Niedersachsen",
    "wof:name":"Helmut Wahlmann",
    "wof:placetype":"venue"
},
  "geometry": {"coordinates":[9.1371603012,52.3628616333],"type":"Point"}
}