{
  "type": "Feature",
  "properties": {
    "iso:country":"DE",
    "sg:address":"Zschopauer Str. 282",
    "sg:city":"Chemnitz",
    "sg:phone":"+49 371/50504",
    "sg:postcode":"09127",
    "sg:province":"Sachsen",
    "wof:name":"M. Kleinberg Ingenieur",
    "wof:placetype":"venue"
},
  "geometry": {"coordinates":[12.964012146,50.8104095459],"type":"Point"}
}