{
  "type": "Feature",
  "properties": {
    "iso:country":"DE",
    "sg:address":"Bremerweg 2",
    "sg:city":"Burgdorf",
    "sg:phone":"+49 5136/899887",
    "sg:postcode":"31303",
    "sg:province":"Niedersachsen",
    "wof:name":"Kommunal-leasing Gesellschaft Zur F\u00f6rderung Kommunaler",
    "wof:placetype":"venue"
},
  "geometry": {"coordinates":[10.0512552261,52.4623832703],"type":"Point"}
}