{
  "type": "Feature",
  "properties": {
    "iso:country":"DE",
    "sg:address":"Nobelstr. 9",
    "sg:city":"Bocholt",
    "sg:postcode":"46399",
    "sg:province":"Nordrhein-Westfalen",
    "wof:name":"Bsv Gmbh",
    "wof:placetype":"venue"
},
  "geometry": {"coordinates":[6.6139760017,51.8391532898],"type":"Point"}
}