{
  "type": "Feature",
  "properties": {
    "iso:country":"DE",
    "sg:address":"Gro\u00dfe Str. 26",
    "sg:city":"Ahrensburg",
    "sg:phone":"+49 4941/0232496",
    "sg:postcode":"22926",
    "sg:province":"Schleswig-Holstein",
    "wof:name":"Paperland Papier-handels-gmbh",
    "wof:placetype":"venue"
},
  "geometry": {"coordinates":[10.238740921,53.6745147705],"type":"Point"}
}