{
  "type": "Feature",
  "properties": {
    "iso:country":"DE",
    "sg:address":"An der Schmeilt 23",
    "sg:city":"Ratingen",
    "sg:phone":"+49 2102/31411",
    "sg:postcode":"40885",
    "sg:province":"Nordrhein-Westfalen",
    "wof:name":"Elfriede Mertens Steuerbevollm\u00e4chtigte",
    "wof:placetype":"venue"
},
  "geometry": {"coordinates":[6.8360080719,51.3349266052],"type":"Point"}
}