{
  "type": "Feature",
  "properties": {
    "iso:country":"DE",
    "sg:address":"Siegfriedstr. 34",
    "sg:city":"Pforzheim",
    "sg:phone":"+49 7231/442505",
    "sg:postcode":"75179",
    "sg:province":"Baden-W\u00fcrttemberg",
    "wof:name":"Gudrun Bechtold Gmbh",
    "wof:placetype":"venue"
},
  "geometry": {"coordinates":[8.675781,48.896351],"type":"Point"}
}