{
  "type": "Feature",
  "properties": {
    "iso:country":"DE",
    "sg:address":"Ahrenloher Str. 30",
    "sg:city":"Tornesch",
    "sg:phone":"+49 4122/52314",
    "sg:postcode":"25436",
    "sg:province":"Schleswig-Holstein",
    "wof:name":"Hans J. Wohlenberg Architekt",
    "wof:placetype":"venue"
},
  "geometry": {"coordinates":[9.720194,53.698635],"type":"Point"}
}