{
  "type": "Feature",
  "properties": {
    "iso:country":"DE",
    "sg:address":"Habichtsh\u00f6he 24",
    "sg:city":"Emsdetten",
    "sg:phone":"+49 2572/83245",
    "sg:postcode":"48282",
    "sg:province":"Nordrhein-Westfalen",
    "wof:name":"Josef Griese Gmbh",
    "wof:placetype":"venue"
},
  "geometry": {"coordinates":[7.512504,52.166485],"type":"Point"}
}