{
  "type": "Feature",
  "properties": {
    "iso:country":"DE",
    "sg:address":"Lindenstr. 15",
    "sg:city":"Ellefeld",
    "sg:phone":"+49 3745/6049",
    "sg:postcode":"08236",
    "sg:province":"Sachsen",
    "wof:name":"Vogtlandmoden Auerbach",
    "wof:placetype":"venue"
},
  "geometry": {"coordinates":[12.390392,50.485523],"type":"Point"}
}