{
  "type": "Feature",
  "properties": {
    "iso:country":"DE",
    "sg:address":"Kaiserstr. 23",
    "sg:city":"Laubach",
    "sg:phone":"+49 6405/1350",
    "sg:postcode":"35321",
    "sg:province":"Hessen",
    "wof:name":"Ernst-joachim R\u00fchl Architekt",
    "wof:placetype":"venue"
},
  "geometry": {"coordinates":[8.98993,50.539749],"type":"Point"}
}