{
  "type": "Feature",
  "properties": {
    "iso:country":"DE",
    "sg:address":"Hauptstr. 4",
    "sg:city":"Achstetten",
    "sg:phone":"+49 7392/3506",
    "sg:postcode":"88480",
    "sg:province":"Baden-W\u00fcrttemberg",
    "wof:name":"Ulrich Kohler",
    "wof:placetype":"venue"
},
  "geometry": {"coordinates":[9.9101448059,48.2474098206],"type":"Point"}
}