{
  "type": "Feature",
  "properties": {
    "iso:country":"DE",
    "sg:address":"Eduard-Grunow-Str. 5",
    "sg:city":"Bremen",
    "sg:phone":"+49 421/703820",
    "sg:postcode":"28203",
    "sg:province":"Bremen",
    "wof:name":"Hans-heinrich Wendt Architekt",
    "wof:placetype":"venue"
},
  "geometry": {"coordinates":[8.819911,53.076447],"type":"Point"}
}