{
  "type": "Feature",
  "properties": {
    "iso:country":"DE",
    "sg:address":"Halbergstr. 66",
    "sg:city":"Saarbr\u00fccken",
    "sg:phone":"+49 681/66236",
    "sg:postcode":"66121",
    "sg:province":"Saarland",
    "wof:name":"J\u00fcrgen St\u00f6rring Ingenieur",
    "wof:placetype":"venue"
},
  "geometry": {"coordinates":[7.0096640587,49.2315597534],"type":"Point"}
}