{
  "type": "Feature",
  "properties": {
    "iso:country":"DE",
    "sg:address":"Weststr. 16",
    "sg:city":"Emsdetten",
    "sg:phone":"+49 2572/5726",
    "sg:postcode":"48282",
    "sg:province":"Nordrhein-Westfalen",
    "wof:name":"M. M\u00f6ller-voss",
    "wof:placetype":"venue"
},
  "geometry": {"coordinates":[7.5225691795,52.1754112244],"type":"Point"}
}