{
  "type": "Feature",
  "properties": {
    "iso:country":"DE",
    "sg:address":"An der Wieste 6",
    "sg:city":"Sottrum",
    "sg:phone":"+49 4264/2319",
    "sg:postcode":"27367",
    "sg:province":"Niedersachsen",
    "wof:name":"Nico Lehmann",
    "wof:placetype":"venue"
},
  "geometry": {"coordinates":[9.2289924622,53.1194992065],"type":"Point"}
}