{
  "type": "Feature",
  "properties": {
    "iso:country":"DE",
    "sg:address":"Am Umspannwerk 1",
    "sg:city":"Bergen",
    "sg:postcode":"29303",
    "sg:province":"Niedersachsen",
    "wof:name":"Christa Wendland Na\u00df- Und Baggerarbeiten E. K.",
    "wof:placetype":"venue"
},
  "geometry": {"coordinates":[9.9624166489,52.8014450073],"type":"Point"}
}