{
  "type": "Feature",
  "properties": {
    "iso:country":"DE",
    "sg:address":"Talweg 30",
    "sg:city":"Lauterbach",
    "sg:phone":"+49 7422",
    "sg:postcode":"78730",
    "sg:province":"Baden-W\u00fcrttemberg",
    "wof:name":"Old News - Absolutely Live Rock Und Beathistory",
    "wof:placetype":"venue"
},
  "geometry": {"coordinates":[8.346809,48.227455],"type":"Point"}
}