{
  "type": "Feature",
  "properties": {
    "iso:country":"DE",
    "sg:address":"Huuskoppel 65",
    "sg:city":"Hamburg",
    "sg:phone":"+49 40/6080935",
    "sg:postcode":"22397",
    "sg:province":"Hamburg",
    "wof:name":"Christa Von Hantelmann Innenarchitektin",
    "wof:placetype":"venue"
},
  "geometry": {"coordinates":[10.103468,53.674793],"type":"Point"}
}