{
  "type": "Feature",
  "properties": {
    "iso:country":"DE",
    "sg:address":"Universit\u00e4tsstr. 6",
    "sg:city":"Marburg",
    "sg:postcode":"35037",
    "sg:province":"Hessen",
    "wof:name":"Krimiologische Abteilung",
    "wof:placetype":"venue"
},
  "geometry": {"coordinates":[8.7700471878,50.8070411682],"type":"Point"}
}