{
  "type": "Feature",
  "properties": {
    "iso:country":"DE",
    "sg:address":"Hirtenackerstr. 45",
    "sg:city":"Bindlach",
    "sg:phone":"+49 9208/6030",
    "sg:postcode":"95463",
    "sg:province":"Bayern",
    "wof:name":"Bartholom\u00e4us Wohnpark",
    "wof:placetype":"venue"
},
  "geometry": {"coordinates":[11.613872,49.983032],"type":"Point"}
}