{
  "type": "Feature",
  "properties": {
    "iso:country":"DE",
    "sg:address":"Torfbruchstr. 2",
    "sg:city":"Lichtenau",
    "sg:phone":"+49 5295/930024",
    "sg:postcode":"33165",
    "sg:province":"Nordrhein-Westfalen",
    "wof:name":"Rewe-markt Widmer Ohg",
    "wof:placetype":"venue"
},
  "geometry": {"coordinates":[8.90271,51.616978],"type":"Point"}
}