{
  "type": "Feature",
  "properties": {
    "iso:country":"DE",
    "sg:address":"Hospitalstr. 30",
    "sg:city":"Viersen",
    "sg:phone":"+49 2162/9702030",
    "sg:postcode":"41751",
    "sg:province":"Nordrhein-Westfalen",
    "wof:name":"Www.everynet.de - Ihr Provider",
    "wof:placetype":"venue"
},
  "geometry": {"coordinates":[6.337514,51.249638],"type":"Point"}
}