{
  "type": "Feature",
  "properties": {
    "iso:country":"DE",
    "sg:address":"Marktstr. 1",
    "sg:city":"Neuhausen",
    "sg:phone":"+49 7158/8723",
    "sg:postcode":"73765",
    "sg:province":"Baden-W\u00fcrttemberg",
    "wof:name":"Ingeborg-moden",
    "wof:placetype":"venue"
},
  "geometry": {"coordinates":[9.278966,48.684704],"type":"Point"}
}