{
  "type": "Feature",
  "properties": {
    "iso:country":"DE",
    "sg:address":"Hohenwaldeckstr. 23",
    "sg:city":"M\u00fcnchen",
    "sg:phone":"+49 89/69380547",
    "sg:postcode":"81541",
    "sg:province":"Bayern",
    "wof:name":"Krygowski Software Gmbh",
    "wof:placetype":"venue"
},
  "geometry": {"coordinates":[11.5944538116,48.116645813],"type":"Point"}
}