{
  "type": "Feature",
  "properties": {
    "iso:country":"DE",
    "sg:address":"Leinastr. 75",
    "sg:city":"Gotha",
    "sg:phone":"+49 3621/758007",
    "sg:postcode":"99867",
    "sg:province":"Th\u00fcringen",
    "wof:name":"Trend Ingenieur Baugesellschaft Mbh",
    "wof:placetype":"venue"
},
  "geometry": {"coordinates":[10.678751,50.934219],"type":"Point"}
}