{
  "type": "Feature",
  "properties": {
    "iso:country":"DE",
    "sg:address":"Langgasse 42",
    "sg:city":"Wachenheim",
    "sg:phone":"+49 6322/1811",
    "sg:postcode":"67157",
    "sg:province":"Rheinland-Pfalz",
    "wof:name":"Helmut Rastst\u00e4tter",
    "wof:placetype":"venue"
},
  "geometry": {"coordinates":[8.1813192368,49.4404525757],"type":"Point"}
}