{
  "type": "Feature",
  "properties": {
    "iso:country":"DE",
    "sg:address":"Hauptstr. 97",
    "sg:city":"Bad Lauterberg",
    "sg:phone":"+49 5524/5311",
    "sg:postcode":"37431",
    "sg:province":"Niedersachsen",
    "wof:name":"Rossmann Drogeriemarkt",
    "wof:placetype":"venue"
},
  "geometry": {"coordinates":[10.467213,51.630077],"type":"Point"}
}