{
  "type": "Feature",
  "properties": {
    "iso:country":"DE",
    "sg:address":"Rosenweg 2",
    "sg:city":"Angelbachtal",
    "sg:phone":"+49 7265/221",
    "sg:postcode":"74918",
    "sg:province":"Baden-W\u00fcrttemberg",
    "wof:name":"Max Leinert",
    "wof:placetype":"venue"
},
  "geometry": {"coordinates":[8.773503,49.23188],"type":"Point"}
}