{
  "type": "Feature",
  "properties": {
    "iso:country":"DE",
    "sg:address":"Weidenstr. 8",
    "sg:city":"Lohne",
    "sg:phone":"+49 4442/921622",
    "sg:postcode":"49393",
    "sg:province":"Niedersachsen",
    "wof:name":"Jochen Wenkert",
    "wof:placetype":"venue"
},
  "geometry": {"coordinates":[8.2535552979,52.6698913574],"type":"Point"}
}