{
  "type": "Feature",
  "properties": {
    "iso:country":"DE",
    "sg:address":"Robert-Bosch-Str. 32 a",
    "sg:city":"Bensheim",
    "sg:phone":"+49 6251/62005",
    "sg:postcode":"64625",
    "sg:province":"Hessen",
    "wof:name":"Hack Gmbh",
    "wof:placetype":"venue"
},
  "geometry": {"coordinates":[8.594901,49.67662],"type":"Point"}
}