{
  "type": "Feature",
  "properties": {
    "iso:country":"DE",
    "sg:address":"D\u00e4nische Str. 24",
    "sg:city":"Kiel",
    "sg:phone":"+49 431/974430",
    "sg:postcode":"24103",
    "sg:province":"Schleswig-Holstein",
    "wof:name":"Hoffmann Und Krug Architekten",
    "wof:placetype":"venue"
},
  "geometry": {"coordinates":[10.141096,54.324051],"type":"Point"}
}