{
  "type": "Feature",
  "properties": {
    "iso:country":"DE",
    "sg:address":"Flurstr. 25",
    "sg:city":"Remscheid",
    "sg:phone":"+49 2191/341881",
    "sg:postcode":"42859",
    "sg:province":"Nordrhein-Westfalen",
    "wof:name":"Ernst Herbertz Gmbh",
    "wof:placetype":"venue"
},
  "geometry": {"coordinates":[7.1926431656,51.166015625],"type":"Point"}
}