{
  "type": "Feature",
  "properties": {
    "iso:country":"DE",
    "sg:address":"Bahnhofstr. 29",
    "sg:city":"G\u00f6nnheim",
    "sg:phone":"+49 6322/64256",
    "sg:postcode":"67161",
    "sg:province":"Rheinland-Pfalz",
    "wof:name":"Rolf H\u00f6ning",
    "wof:placetype":"venue"
},
  "geometry": {"coordinates":[8.237305,49.450687],"type":"Point"}
}