{
  "type": "Feature",
  "properties": {
    "iso:country":"DE",
    "sg:address":"Kleiner Burstah 12",
    "sg:city":"Hamburg",
    "sg:phone":"+49 40/342565",
    "sg:postcode":"20457",
    "sg:province":"Hamburg",
    "wof:name":"Augenoptiker Amor Stritzke",
    "wof:placetype":"venue"
},
  "geometry": {"coordinates":[9.988820076,53.54737854],"type":"Point"}
}