{
  "type": "Feature",
  "properties": {
    "iso:country":"DE",
    "sg:address":"Hauptstr. 27",
    "sg:city":"Niedersteinebach",
    "sg:phone":"+49 2687/791",
    "sg:postcode":"56593",
    "sg:province":"Rheinland-Pfalz",
    "wof:name":"Haus Am Park Alten- Und Pflegeheim Gmbh",
    "wof:placetype":"venue"
},
  "geometry": {"coordinates":[7.505946,50.601334],"type":"Point"}
}