{
  "type": "Feature",
  "properties": {
    "iso:country":"DE",
    "sg:address":"Wei\u00dfinger Str. 15",
    "sg:city":"Elchingen",
    "sg:phone":"+49 7308/81780",
    "sg:postcode":"89275",
    "sg:province":"Bayern",
    "wof:name":"Eberhardt-maschinenbau E. K.",
    "wof:placetype":"venue"
},
  "geometry": {"coordinates":[10.135838,48.451542],"type":"Point"}
}