{
  "type": "Feature",
  "properties": {
    "iso:country":"DE",
    "sg:address":"Koblenzer Str. 76",
    "sg:city":"Siegen",
    "sg:phone":"+49 271/33721",
    "sg:postcode":"57072",
    "sg:province":"Nordrhein-Westfalen",
    "wof:name":"Landesstrassenbauamt",
    "wof:placetype":"venue"
},
  "geometry": {"coordinates":[8.0145921707,50.8709182739],"type":"Point"}
}