{
  "type": "Feature",
  "properties": {
    "iso:country":"DE",
    "sg:address":"Industriestr. 6",
    "sg:city":"Lauterbach",
    "sg:phone":"+49 4966/416680",
    "sg:postcode":"36341",
    "sg:province":"Hessen",
    "wof:name":"Eurodress Gmbh & Co",
    "wof:placetype":"venue"
},
  "geometry": {"coordinates":[9.390649,50.649467],"type":"Point"}
}