{
  "type": "Feature",
  "properties": {
    "iso:country":"DE",
    "sg:address":"Bauerntor 5",
    "sg:city":"G\u00f6denstorf",
    "sg:phone":"+49 4175/378",
    "sg:postcode":"21376",
    "sg:province":"Niedersachsen",
    "wof:name":"Seifert & M\u00fcller Bauges. Mbh",
    "wof:placetype":"venue"
},
  "geometry": {"coordinates":[10.098809,53.194832],"type":"Point"}
}