{
  "type": "Feature",
  "properties": {
    "iso:country":"DE",
    "sg:address":"Hauptstra\u00dfe 30",
    "sg:city":"Triefenstein-Trennfeld",
    "sg:phone":"+49 9395/97190",
    "sg:postcode":"97855",
    "sg:province":"Bayern",
    "wof:name":"Ing.-b\u00fcro Geier",
    "wof:placetype":"venue"
},
  "geometry": {"coordinates":[9.614984,49.79295],"type":"Point"}
}