{
  "type": "Feature",
  "properties": {
    "iso:country":"DE",
    "sg:address":"Kohlwaldstr. 3",
    "sg:city":"Ottweiler",
    "sg:phone":"+49 6824/4353",
    "sg:postcode":"66564",
    "sg:province":"Saarland",
    "wof:name":"Friedrich Sick Ingenieur",
    "wof:placetype":"venue"
},
  "geometry": {"coordinates":[7.1664209366,49.3980407715],"type":"Point"}
}