{
  "type": "Feature",
  "properties": {
    "iso:country":"DE",
    "sg:address":"Steingrundstr. 37",
    "sg:city":"Neuh\u00fctten",
    "sg:phone":"+49 6020/2321",
    "sg:postcode":"97843",
    "sg:province":"Bayern",
    "wof:name":"Peter Wiesner",
    "wof:placetype":"venue"
},
  "geometry": {"coordinates":[9.4241580963,50.0019760132],"type":"Point"}
}