{
  "type": "Feature",
  "properties": {
    "iso:country":"DE",
    "sg:address":"Forggenseestr. 31",
    "sg:city":"Ro\u00dfhaupten",
    "sg:phone":"+49 8367/312",
    "sg:postcode":"87672",
    "sg:province":"Bayern",
    "wof:name":"Xaver Linder",
    "wof:placetype":"venue"
},
  "geometry": {"coordinates":[10.72541,47.653759],"type":"Point"}
}