{
  "type": "Feature",
  "properties": {
    "iso:country":"DE",
    "sg:address":"Sonnenstr 6",
    "sg:city":"Hartha",
    "sg:phone":"+49 34328/38339",
    "sg:postcode":"04746",
    "sg:province":"Sachsen",
    "wof:name":"Elektroservice Hanns",
    "wof:placetype":"venue"
},
  "geometry": {"coordinates":[12.9771671295,51.0959358215],"type":"Point"}
}