{
  "type": "Feature",
  "properties": {
    "iso:country":"DE",
    "sg:address":"M\u00fchlenredder 1",
    "sg:city":"Reinbek",
    "sg:phone":"+49 40/7278411",
    "sg:postcode":"21465",
    "sg:province":"Schleswig-Holstein",
    "wof:name":"W. Z\u00fchlke",
    "wof:placetype":"venue"
},
  "geometry": {"coordinates":[10.250138,53.517727],"type":"Point"}
}