{
  "type": "Feature",
  "properties": {
    "iso:country":"DE",
    "sg:address":"Schmittgasse 184",
    "sg:city":"K\u00f6ln",
    "sg:phone":"+49 2203/87185",
    "sg:postcode":"51143",
    "sg:province":"Nordrhein-Westfalen",
    "wof:name":"Giovanni Noe Gmbh",
    "wof:placetype":"venue"
},
  "geometry": {"coordinates":[7.0377058983,50.8608894348],"type":"Point"}
}