{
  "type": "Feature",
  "properties": {
    "iso:country":"DE",
    "sg:address":"Marktler Str 47",
    "sg:city":"Burghausen",
    "sg:phone":"+49 8677/8705165",
    "sg:postcode":"84489",
    "sg:province":"Bayern",
    "wof:name":"Hypo-bank Ag",
    "wof:placetype":"venue"
},
  "geometry": {"coordinates":[12.829729,48.173901],"type":"Point"}
}