{
  "type": "Feature",
  "properties": {
    "iso:country":"DE",
    "sg:address":"Hoykenkamper Weg 11",
    "sg:city":"Delmenhorst",
    "sg:postcode":"27753",
    "sg:province":"Niedersachsen",
    "wof:name":"Hanse-fenster Wittenberg Gmbh",
    "wof:placetype":"venue"
},
  "geometry": {"coordinates":[8.6098966599,53.0653915405],"type":"Point"}
}