{
  "type": "Feature",
  "properties": {
    "iso:country":"DE",
    "sg:address":"H\u00f6henweg 15",
    "sg:city":"Bessenbach",
    "sg:phone":"+49 6095/993365",
    "sg:postcode":"63856",
    "sg:province":"Bayern",
    "wof:name":"Objekt Design Feuerstaetten",
    "wof:placetype":"venue"
},
  "geometry": {"coordinates":[9.2372684479,49.9610023499],"type":"Point"}
}