{
  "type": "Feature",
  "properties": {
    "iso:country":"DE",
    "sg:address":"L\u00fche 11",
    "sg:city":"Jork",
    "sg:phone":"+49 4142/2309",
    "sg:postcode":"21635",
    "sg:province":"Niedersachsen",
    "wof:name":"Mathias Heitmann Gmbh",
    "wof:placetype":"venue"
},
  "geometry": {"coordinates":[9.629522,53.565891],"type":"Point"}
}