{
  "type": "Feature",
  "properties": {
    "iso:country":"DE",
    "sg:address":"Jagowstr. 28",
    "sg:city":"Berlin",
    "sg:phone":"+49 30/4041298",
    "sg:postcode":"13467",
    "sg:province":"Berlin",
    "wof:name":"Brunhild Hennings Rechtsanw\u00e4ltin",
    "wof:placetype":"venue"
},
  "geometry": {"coordinates":[13.2987985611,52.6075515747],"type":"Point"}
}