{
  "type": "Feature",
  "properties": {
    "iso:country":"DE",
    "sg:address":"Walkm\u00fchlenstr. 121",
    "sg:city":"Bremerv\u00f6rde",
    "sg:phone":"+49 4761/5380",
    "sg:postcode":"27432",
    "sg:province":"Niedersachsen",
    "wof:name":"Herbert Gerdts",
    "wof:placetype":"venue"
},
  "geometry": {"coordinates":[9.178679,53.485313],"type":"Point"}
}