{
  "type": "Feature",
  "properties": {
    "iso:country":"DE",
    "sg:address":"Am Wall 71",
    "sg:city":"Bremen",
    "sg:phone":"+49 421/171019",
    "sg:postcode":"28195",
    "sg:province":"Bremen",
    "wof:name":"August Lutter",
    "wof:placetype":"venue"
},
  "geometry": {"coordinates":[8.799036,53.081642],"type":"Point"}
}