{
  "type": "Feature",
  "properties": {
    "iso:country":"DE",
    "sg:address":"Gartenstr. 5",
    "sg:city":"Villmar",
    "sg:phone":"+49 6482/4238",
    "sg:postcode":"65606",
    "sg:province":"Hessen",
    "wof:name":"Winfried M\u00fcller",
    "wof:placetype":"venue"
},
  "geometry": {"coordinates":[8.196579,50.389023],"type":"Point"}
}