{
  "type": "Feature",
  "properties": {
    "iso:country":"DE",
    "sg:address":"M\u00fchlstr. 9",
    "sg:city":"Blankenbach",
    "sg:phone":"+49 6024/8428",
    "sg:postcode":"63825",
    "sg:province":"Bayern",
    "wof:name":"M\u00fchlgrund",
    "wof:placetype":"venue"
},
  "geometry": {"coordinates":[9.2338657379,50.0645179749],"type":"Point"}
}