{
  "type": "Feature",
  "properties": {
    "iso:country":"DE",
    "sg:address":"Walther-Rathenau-Str. 2 a",
    "sg:city":"Neuruppin",
    "sg:phone":"+49 3391/650508",
    "sg:postcode":"16816",
    "sg:province":"Brandenburg",
    "wof:name":"Pfefferleins Speisegastst\u00e4tte",
    "wof:placetype":"venue"
},
  "geometry": {"coordinates":[12.8073654175,52.9326438904],"type":"Point"}
}