{
  "type": "Feature",
  "properties": {
    "iso:country":"DE",
    "sg:address":"Bert-Brecht-Str. 2",
    "sg:city":"Ingolstadt",
    "sg:phone":"+49 841/36435",
    "sg:postcode":"85055",
    "sg:province":"Bayern",
    "wof:name":"Alfred Euringer",
    "wof:placetype":"venue"
},
  "geometry": {"coordinates":[11.4652109146,48.7688941956],"type":"Point"}
}