{
  "type": "Feature",
  "properties": {
    "iso:country":"DE",
    "sg:address":"Verdistr. 2",
    "sg:city":"M\u00f6rlenbach",
    "sg:phone":"+49 6209/5444",
    "sg:postcode":"69509",
    "sg:province":"Hessen",
    "wof:name":"M\u00f6ba-massivhaus Rainer Richter E. K.",
    "wof:placetype":"venue"
},
  "geometry": {"coordinates":[8.7415456772,49.6064834595],"type":"Point"}
}