{
  "type": "Feature",
  "properties": {
    "iso:country":"DE",
    "sg:address":"Gottlieb-Daimler-Str. 30",
    "sg:city":"Magstadt",
    "sg:phone":"+49 7159/94103",
    "sg:postcode":"71106",
    "sg:province":"Baden-W\u00fcrttemberg",
    "wof:name":"Cardan- Und Hydraulik- Service Gmbh & Co. Kg",
    "wof:placetype":"venue"
},
  "geometry": {"coordinates":[8.9718494415,48.7359542847],"type":"Point"}
}