{
  "type": "Feature",
  "properties": {
    "iso:country":"DE",
    "sg:address":"Feldgasse 2",
    "sg:city":"Niederw\u00fcrschnitz",
    "sg:phone":"+49 37296/6461",
    "sg:postcode":"09399",
    "sg:province":"Sachsen",
    "wof:name":"Wolfgang Pfeifer",
    "wof:placetype":"venue"
},
  "geometry": {"coordinates":[12.749915123,50.7211074829],"type":"Point"}
}