{
  "type": "Feature",
  "properties": {
    "iso:country":"DE",
    "sg:address":"R\u00f6derbergweg 21",
    "sg:city":"Frankfurt",
    "sg:phone":"+49 69/446363",
    "sg:postcode":"60314",
    "sg:province":"Hessen",
    "wof:name":"As-werbung Fitze Gmbh",
    "wof:placetype":"venue"
},
  "geometry": {"coordinates":[8.7020521164,50.1137008667],"type":"Point"}
}