{
  "type": "Feature",
  "properties": {
    "iso:country":"DE",
    "sg:address":"Lommatzscher Str. 4",
    "sg:city":"Ostrau",
    "sg:phone":"+49 34324/21846",
    "sg:postcode":"04749",
    "sg:province":"Sachsen",
    "wof:name":"Wohnungsbau Gmbh",
    "wof:placetype":"venue"
},
  "geometry": {"coordinates":[13.1647424698,51.2013206482],"type":"Point"}
}