{
  "type": "Feature",
  "properties": {
    "iso:country":"DE",
    "sg:address":"Feldstr. 43",
    "sg:city":"Uetersen",
    "sg:phone":"+49 4122/44777",
    "sg:postcode":"25436",
    "sg:province":"Schleswig-Holstein",
    "wof:name":"Senioren- Und Pflegeheim Der Stadt Uetersen",
    "wof:placetype":"venue"
},
  "geometry": {"coordinates":[9.658895,53.687214],"type":"Point"}
}