{
  "type": "Feature",
  "properties": {
    "iso:country":"DE",
    "sg:address":"Hermann-J\u00e4ckel-Str. 12/1",
    "sg:city":"Lichtenstein",
    "sg:phone":"+49 7129/6575",
    "sg:postcode":"72805",
    "sg:province":"Baden-W\u00fcrttemberg",
    "wof:name":"Metin Kosanoglu",
    "wof:placetype":"venue"
},
  "geometry": {"coordinates":[9.2554597855,48.4335594177],"type":"Point"}
}