{
  "type": "Feature",
  "properties": {
    "iso:country":"DE",
    "sg:address":"Bethlehemer Str. 41",
    "sg:city":"Bergheim",
    "sg:phone":"+49 2271/45975",
    "sg:postcode":"50126",
    "sg:province":"Nordrhein-Westfalen",
    "wof:name":"Contakt",
    "wof:placetype":"venue"
},
  "geometry": {"coordinates":[6.646992,50.95586],"type":"Point"}
}