{
  "type": "Feature",
  "properties": {
    "iso:country":"DE",
    "sg:address":"Quintusstr. 5",
    "sg:city":"Fallingbostel",
    "sg:postcode":"29683",
    "sg:province":"Niedersachsen",
    "wof:name":"Panning Gmbh",
    "wof:placetype":"venue"
},
  "geometry": {"coordinates":[9.70071,52.86618],"type":"Point"}
}