{
  "type": "Feature",
  "properties": {
    "iso:country":"DE",
    "sg:address":"Hillaustr. 11",
    "sg:city":"Gernsbach",
    "sg:phone":"+49 7224/67243",
    "sg:postcode":"76593",
    "sg:province":"Baden-W\u00fcrttemberg",
    "wof:name":"Mebra Wassertechnik Breuer Gmbh & Co. Kg",
    "wof:placetype":"venue"
},
  "geometry": {"coordinates":[8.3441858292,48.7748565674],"type":"Point"}
}