{
  "type": "Feature",
  "properties": {
    "iso:country":"DE",
    "sg:address":"Am Sommerkeller 1",
    "sg:city":"Treuchtlingen",
    "sg:phone":"+49 9142/3725",
    "sg:postcode":"91757",
    "sg:province":"Bayern",
    "wof:name":"Lamm Gmbh",
    "wof:placetype":"venue"
},
  "geometry": {"coordinates":[10.955383,48.965416],"type":"Point"}
}