{
  "type": "Feature",
  "properties": {
    "iso:country":"DE",
    "sg:address":"Im Gellert 1",
    "sg:city":"Rohrbach",
    "sg:phone":"+49 8442/8170",
    "sg:postcode":"85296",
    "sg:province":"Bayern",
    "wof:name":"Georg Wiegartner",
    "wof:placetype":"venue"
},
  "geometry": {"coordinates":[11.568095,48.605984],"type":"Point"}
}