{
  "type": "Feature",
  "properties": {
    "iso:country":"DE",
    "sg:address":"Am Haar 29",
    "sg:city":"Beilngries",
    "sg:phone":"+49 8461/700178",
    "sg:postcode":"92339",
    "sg:province":"Bayern",
    "wof:name":"Streubel Automation Pneumatik - Hydraulik - Automatik",
    "wof:placetype":"venue"
},
  "geometry": {"coordinates":[11.4960069656,49.0140762329],"type":"Point"}
}