{
  "type": "Feature",
  "properties": {
    "iso:country":"DE",
    "sg:address":"Daimlerstr. 11 A",
    "sg:city":"Nattheim",
    "sg:phone":"+49 7321/72630",
    "sg:postcode":"89564",
    "sg:province":"Baden-W\u00fcrttemberg",
    "wof:name":"Rotef-rohrteilefertigung Gmbh",
    "wof:placetype":"venue"
},
  "geometry": {"coordinates":[10.235703,48.704411],"type":"Point"}
}