{
  "type": "Feature",
  "properties": {
    "iso:country":"DE",
    "sg:city":"M\u00fcnchen",
    "sg:postcode":"81245",
    "sg:province":"Bayern",
    "wof:name":"Katoptron\u00b4s Electronic Landscape",
    "wof:placetype":"venue"
},
  "geometry": {"coordinates":[11.475405,48.164436],"type":"Point"}
}