{
  "type": "Feature",
  "properties": {
    "iso:country":"DE",
    "sg:address":"Maybachstr. 29",
    "sg:city":"Waiblingen",
    "sg:phone":"+49 7151/59623",
    "sg:postcode":"71332",
    "sg:province":"Baden-W\u00fcrttemberg",
    "wof:name":"Gerhardt",
    "wof:placetype":"venue"
},
  "geometry": {"coordinates":[9.295891,48.831894],"type":"Point"}
}