{
  "type": "Feature",
  "properties": {
    "iso:country":"DE",
    "sg:address":"Bremer Str. 7",
    "sg:city":"Seelze",
    "sg:phone":"+49 5137/93109",
    "sg:postcode":"30926",
    "sg:province":"Niedersachsen",
    "wof:name":"Imbi\u00df Zur Alten Kastanie",
    "wof:placetype":"venue"
},
  "geometry": {"coordinates":[9.5922794342,52.3978919983],"type":"Point"}
}