{
  "type": "Feature",
  "properties": {
    "iso:country":"DE",
    "sg:address":"M\u00fchlstr. 11",
    "sg:city":"Ziegenr\u00fcck",
    "sg:phone":"+49 36483/22641",
    "sg:postcode":"07924",
    "sg:province":"Th\u00fcringen",
    "wof:name":"Imbi\u00dfgastst\u00e4tte Kohl",
    "wof:placetype":"venue"
},
  "geometry": {"coordinates":[11.6508922577,50.6123771667],"type":"Point"}
}