{
  "type": "Feature",
  "properties": {
    "iso:country":"DE",
    "sg:address":"Eichholzstr. 16",
    "sg:city":"Ebersbach",
    "sg:phone":"+49 7163/8988",
    "sg:postcode":"73061",
    "sg:province":"Baden-W\u00fcrttemberg",
    "wof:name":"Werner Flaig Wettannahme",
    "wof:placetype":"venue"
},
  "geometry": {"coordinates":[9.522963,48.708111],"type":"Point"}
}