{
  "type": "Feature",
  "properties": {
    "iso:country":"DE",
    "sg:address":"Ringhofstr. 15",
    "sg:city":"Kassel",
    "sg:phone":"+49 561/59669",
    "sg:postcode":"34123",
    "sg:province":"Hessen",
    "wof:name":"Bernd Schneehain",
    "wof:placetype":"venue"
},
  "geometry": {"coordinates":[9.5281867981,51.3067016602],"type":"Point"}
}