{
  "type": "Feature",
  "properties": {
    "iso:country":"DE",
    "sg:address":"Bahnhofstr. 12",
    "sg:city":"Eppingen",
    "sg:phone":"+49 7262/91310",
    "sg:postcode":"75031",
    "sg:province":"Baden-W\u00fcrttemberg",
    "wof:name":"Stadt-apotheke",
    "wof:placetype":"venue"
},
  "geometry": {"coordinates":[8.910066,49.136299],"type":"Point"}
}