{
  "type": "Feature",
  "properties": {
    "iso:country":"DE",
    "sg:address":"Z\u00e4hringerstr. 24",
    "sg:city":"Br\u00e4unlingen",
    "sg:phone":"+49 771/929050",
    "sg:postcode":"78199",
    "sg:province":"Baden-W\u00fcrttemberg",
    "wof:name":"Hotel Lindenhof",
    "wof:placetype":"venue"
},
  "geometry": {"coordinates":[8.4468040466,47.9299926758],"type":"Point"}
}