{
  "type": "Feature",
  "properties": {
    "iso:country":"DE",
    "sg:address":"Kantstr. 34",
    "sg:city":"Frankfurt",
    "sg:phone":"+49 335/325493",
    "sg:postcode":"15230",
    "sg:province":"Brandenburg",
    "wof:name":"Wolfgang Wegner",
    "wof:placetype":"venue"
},
  "geometry": {"coordinates":[14.530451,52.346935],"type":"Point"}
}