{
  "type": "Feature",
  "properties": {
    "iso:country":"DE",
    "sg:address":"Horstredder 4",
    "sg:city":"Brunsbek",
    "sg:phone":"+49 4107/7256",
    "sg:postcode":"22946",
    "sg:province":"Schleswig-Holstein",
    "wof:name":"Ernst Schacht",
    "wof:placetype":"venue"
},
  "geometry": {"coordinates":[10.273445,53.595242],"type":"Point"}
}