{
  "type": "Feature",
  "properties": {
    "iso:country":"DE",
    "sg:address":"Ludwig-Wolker-Str. 37",
    "sg:city":"M\u00fcnster",
    "sg:phone":"+49 251/143930",
    "sg:postcode":"48157",
    "sg:province":"Nordrhein-Westfalen",
    "wof:name":"Fotoforum-verlag E. K.",
    "wof:placetype":"venue"
},
  "geometry": {"coordinates":[7.7046,51.987621],"type":"Point"}
}