{
  "type": "Feature",
  "properties": {
    "iso:country":"DE",
    "sg:address":"Perlhuhnweg 11",
    "sg:city":"Berlin",
    "sg:phone":"+49 30/6634258",
    "sg:postcode":"12355",
    "sg:province":"Berlin",
    "wof:name":"F. Birkenstock",
    "wof:placetype":"venue"
},
  "geometry": {"coordinates":[13.4838609695,52.4103279114],"type":"Point"}
}