{
  "type": "Feature",
  "properties": {
    "iso:country":"DE",
    "sg:address":"Hauptstr. 11",
    "sg:city":"Borken",
    "sg:phone":"+49 2862/92007",
    "sg:postcode":"46325",
    "sg:province":"Nordrhein-Westfalen",
    "wof:name":"Duolab Invitro Diagnostika Und Software Gmbh",
    "wof:placetype":"venue"
},
  "geometry": {"coordinates":[6.8569498062,51.9091110229],"type":"Point"}
}