{
  "type": "Feature",
  "properties": {
    "iso:country":"DE",
    "sg:address":"An Der Salzbr\u00fccke",
    "sg:city":"Ritschenhausen",
    "sg:phone":"+49 4936/9492810",
    "sg:postcode":"98617",
    "sg:province":"Th\u00fcringen",
    "wof:name":"Th\u00dcsa S\u00dcdth\u00dcringer Fruchtsaft Gmbh",
    "wof:placetype":"venue"
},
  "geometry": {"coordinates":[10.429655,50.517696],"type":"Point"}
}