{
  "type": "Feature",
  "properties": {
    "iso:country":"DE",
    "sg:address":"Rahserfeld 11 B",
    "sg:city":"Viersen",
    "sg:phone":"+49 2162/939940",
    "sg:postcode":"41748",
    "sg:province":"Nordrhein-Westfalen",
    "wof:name":"Biastoch & Euler Ohg",
    "wof:placetype":"venue"
},
  "geometry": {"coordinates":[6.395228,51.263836],"type":"Point"}
}