{
  "type": "Feature",
  "properties": {
    "iso:country":"DE",
    "sg:address":"Sportplatzstr. 14",
    "sg:city":"Nalbach",
    "sg:phone":"+49 6838/2230",
    "sg:postcode":"66809",
    "sg:province":"Saarland",
    "wof:name":"Richard Kallenborn Architekt",
    "wof:placetype":"venue"
},
  "geometry": {"coordinates":[6.806182,49.387486],"type":"Point"}
}