{
  "type": "Feature",
  "properties": {
    "iso:country":"DE",
    "sg:address":"Turnstr. 70",
    "sg:city":"Pirmasens",
    "sg:phone":"+49 6331/64624",
    "sg:postcode":"66953",
    "sg:province":"Rheinland-Pfalz",
    "wof:name":"Bermann Und Sigmund Gmbh",
    "wof:placetype":"venue"
},
  "geometry": {"coordinates":[7.5952568054,49.2136230469],"type":"Point"}
}