{
  "type": "Feature",
  "properties": {
    "iso:country":"DE",
    "sg:address":"Hauptstr. 12",
    "sg:city":"Alerheim",
    "sg:phone":"+49 9085/254",
    "sg:postcode":"86733",
    "sg:province":"Bayern",
    "wof:name":"K. Hubel",
    "wof:placetype":"venue"
},
  "geometry": {"coordinates":[10.6212,48.844913],"type":"Point"}
}