{
  "type": "Feature",
  "properties": {
    "iso:country":"DE",
    "sg:address":"Westerfelder Str. 21",
    "sg:city":"Breckerfeld",
    "sg:phone":"+49 2338/8383",
    "sg:postcode":"58339",
    "sg:province":"Nordrhein-Westfalen",
    "wof:name":"Erich Silvestri",
    "wof:placetype":"venue"
},
  "geometry": {"coordinates":[7.4760971069,51.2641792297],"type":"Point"}
}