{
  "type": "Feature",
  "properties": {
    "iso:country":"DE",
    "sg:address":"Oed 1",
    "sg:city":"Feldkirchen-Westerham",
    "sg:phone":"+49 8063/6300",
    "sg:postcode":"83620",
    "sg:province":"Bayern",
    "wof:name":"Betriebsges. Golfanlage Mangfalltal Mbh",
    "wof:placetype":"venue"
},
  "geometry": {"coordinates":[11.84577,47.918114],"type":"Point"}
}