{
  "type": "Feature",
  "properties": {
    "iso:country":"DE",
    "sg:address":"Boniverstr. 3",
    "sg:city":"Gelsenkirchen",
    "sg:phone":"+49 209/498890",
    "sg:postcode":"45883",
    "sg:province":"Nordrhein-Westfalen",
    "wof:name":"Helmut Morgenstern",
    "wof:placetype":"venue"
},
  "geometry": {"coordinates":[7.0844340324,51.5095291138],"type":"Point"}
}