{
  "type": "Feature",
  "properties": {
    "iso:country":"DE",
    "sg:address":"Andernacher Str. 21",
    "sg:city":"N\u00fcrnberg",
    "sg:phone":"+49 911/525621",
    "sg:postcode":"90411",
    "sg:province":"Bayern",
    "wof:name":"V. Wessel",
    "wof:placetype":"venue"
},
  "geometry": {"coordinates":[11.0987768173,49.4902114868],"type":"Point"}
}