{
  "type": "Feature",
  "properties": {
    "iso:country":"DE",
    "sg:address":"Mittelweg 5",
    "sg:city":"Sulzbach-Rosenberg",
    "sg:phone":"+49 9661/6786",
    "sg:postcode":"92237",
    "sg:province":"Bayern",
    "wof:name":"Sigrid Sandig",
    "wof:placetype":"venue"
},
  "geometry": {"coordinates":[11.7703676224,49.4905776978],"type":"Point"}
}