{
  "type": "Feature",
  "properties": {
    "iso:country":"DE",
    "sg:address":"Nordwalder Str. 69",
    "sg:city":"Steinfurt",
    "sg:phone":"+49 2552/2242",
    "sg:postcode":"48565",
    "sg:province":"Nordrhein-Westfalen",
    "wof:name":"Br\u00fcnemeyer",
    "wof:placetype":"venue"
},
  "geometry": {"coordinates":[7.416542,52.123669],"type":"Point"}
}