{
  "type": "Feature",
  "properties": {
    "iso:country":"DE",
    "sg:address":"Hohenstaufenstr. 17",
    "sg:city":"Annweiler",
    "sg:phone":"+49 6346/3290",
    "sg:postcode":"76855",
    "sg:province":"Rheinland-Pfalz",
    "wof:name":"H.-p. Drendi Ingenieur",
    "wof:placetype":"venue"
},
  "geometry": {"coordinates":[7.9688858986,49.2047042847],"type":"Point"}
}