{
  "type": "Feature",
  "properties": {
    "iso:country":"DE",
    "sg:address":"Georg-Zapf Str. 14",
    "sg:city":"K\u00f6ln",
    "sg:phone":"+49 221/8602038",
    "sg:postcode":"51061",
    "sg:province":"Nordrhein-Westfalen",
    "wof:name":"Pension Am Park",
    "wof:placetype":"venue"
},
  "geometry": {"coordinates":[6.982595,50.997559],"type":"Point"}
}