{
  "type": "Feature",
  "properties": {
    "iso:country":"DE",
    "sg:address":"Jordanstr. 1",
    "sg:city":"Stolberg",
    "sg:postcode":"52222",
    "sg:province":"Nordrhein-Westfalen",
    "wof:name":"Toulouse",
    "wof:placetype":"venue"
},
  "geometry": {"coordinates":[6.224087,50.775486],"type":"Point"}
}