{
  "type": "Feature",
  "properties": {
    "iso:country":"DE",
    "sg:address":"Theodor-Heuss-Str. 6",
    "sg:city":"Neuenkirchen",
    "sg:phone":"+49 5465/776",
    "sg:postcode":"49586",
    "sg:province":"Niedersachsen",
    "wof:name":"G\u00fcnter Frye Heissmangel",
    "wof:placetype":"venue"
},
  "geometry": {"coordinates":[7.8334441185,52.4173049927],"type":"Point"}
}