{
  "type": "Feature",
  "properties": {
    "iso:country":"DE",
    "sg:address":"Marktplatz 8",
    "sg:city":"Iphofen",
    "sg:phone":"+49 9323/3448",
    "sg:postcode":"97346",
    "sg:province":"Bayern",
    "wof:name":"Fotospezialgesch\u00e4ft Seidel Inh. \u00dcbelacker",
    "wof:placetype":"venue"
},
  "geometry": {"coordinates":[10.2608880997,49.7043991089],"type":"Point"}
}