{
  "type": "Feature",
  "properties": {
    "iso:country":"DE",
    "sg:address":"Wilhelm-Kraut-Str. 88",
    "sg:city":"Balingen",
    "sg:phone":"+49 7433/23345",
    "sg:postcode":"72336",
    "sg:province":"Baden-W\u00fcrttemberg",
    "wof:name":"Borth Br\u00fcckl Und Peters Rechtsanw\u00e4lte",
    "wof:placetype":"venue"
},
  "geometry": {"coordinates":[8.851641655,48.265499115],"type":"Point"}
}