{
  "type": "Feature",
  "properties": {
    "iso:country":"DE",
    "sg:address":"Wilhelm-Henze-Weg 10",
    "sg:city":"Burgdorf",
    "sg:phone":"+49 5136/3371",
    "sg:postcode":"31303",
    "sg:province":"Niedersachsen",
    "wof:name":"Heinz Solle",
    "wof:placetype":"venue"
},
  "geometry": {"coordinates":[10.0178842545,52.4407310486],"type":"Point"}
}