{
  "type": "Feature",
  "properties": {
    "iso:country":"DE",
    "sg:address":"Am Burgfeld 12",
    "sg:city":"Eschweiler",
    "sg:phone":"+49 2403/702515",
    "sg:postcode":"52249",
    "sg:province":"Nordrhein-Westfalen",
    "wof:name":"Leusch-jacquemain Und Leusch Rechtsanw\u00e4lte",
    "wof:placetype":"venue"
},
  "geometry": {"coordinates":[6.2617678642,50.812171936],"type":"Point"}
}