{
  "type": "Feature",
  "properties": {
    "iso:country":"DE",
    "sg:address":"Monschauer Str. 64",
    "sg:city":"D\u00fcren",
    "sg:phone":"+49 2421/63094",
    "sg:postcode":"52355",
    "sg:province":"Nordrhein-Westfalen",
    "wof:name":"Kurtz Gmbh & Co.",
    "wof:placetype":"venue"
},
  "geometry": {"coordinates":[6.462997,50.781067],"type":"Point"}
}