{
  "type": "Feature",
  "properties": {
    "iso:country":"DE",
    "sg:address":"Kaiserallee 62",
    "sg:city":"Karlsruhe",
    "sg:phone":"+49 4972/1931640",
    "sg:postcode":"76137",
    "sg:province":"Baden-W\u00fcrttemberg",
    "wof:name":"Digital Team",
    "wof:placetype":"venue"
},
  "geometry": {"coordinates":[8.3673791885,49.0114784241],"type":"Point"}
}