{
  "type": "Feature",
  "properties": {
    "iso:country":"DE",
    "sg:address":"Friedrich-Ebert-Str. 41",
    "sg:city":"M\u00fchlheim",
    "sg:phone":"+49 6108/81484",
    "sg:postcode":"63165",
    "sg:province":"Hessen",
    "wof:name":"Dieter Fiedler Architekt",
    "wof:placetype":"venue"
},
  "geometry": {"coordinates":[8.857609,50.100086],"type":"Point"}
}