{
  "type": "Feature",
  "properties": {
    "iso:country":"DE",
    "sg:address":"Willinger Str. 8",
    "sg:city":"Korbach",
    "sg:postcode":"34497",
    "sg:province":"Hessen",
    "wof:name":"Torsten Becker",
    "wof:placetype":"venue"
},
  "geometry": {"coordinates":[8.8284320831,51.2891731262],"type":"Point"}
}