{
  "type": "Feature",
  "properties": {
    "iso:country":"DE",
    "sg:address":"Zum Oberntor 13",
    "sg:city":"Springe",
    "sg:phone":"+49 5041/4333",
    "sg:postcode":"31832",
    "sg:province":"Niedersachsen",
    "wof:name":"Stichweh Gmbh",
    "wof:placetype":"venue"
},
  "geometry": {"coordinates":[9.552353,52.208179],"type":"Point"}
}