{
  "type": "Feature",
  "properties": {
    "iso:country":"DE",
    "sg:address":"Ramerberg 1",
    "sg:city":"Ramerberg",
    "sg:phone":"+49 8039/1495",
    "sg:postcode":"83561",
    "sg:province":"Bayern",
    "wof:name":"Kath. Pfarramt St. Leonhard",
    "wof:placetype":"venue"
},
  "geometry": {"coordinates":[12.1451253891,48.017364502],"type":"Point"}
}