{
  "type": "Feature",
  "properties": {
    "iso:country":"DE",
    "sg:address":"Beim Dom 3",
    "sg:city":"Bardowick",
    "sg:phone":"+49 4131/120839",
    "sg:postcode":"21357",
    "sg:province":"Niedersachsen",
    "wof:name":"Croque-o-dil",
    "wof:placetype":"venue"
},
  "geometry": {"coordinates":[10.3891906738,53.2995605469],"type":"Point"}
}