{
  "type": "Feature",
  "properties": {
    "iso:country":"DE",
    "sg:address":"Blumenstr. 39",
    "sg:city":"Solingen",
    "sg:phone":"+49 212/203686",
    "sg:postcode":"42655",
    "sg:province":"Nordrhein-Westfalen",
    "wof:name":"A. Maus Farben Und Tapeten",
    "wof:placetype":"venue"
},
  "geometry": {"coordinates":[7.0816121101,51.1736907959],"type":"Point"}
}