{
  "type": "Feature",
  "properties": {
    "iso:country":"DE",
    "sg:address":"Jettenburger Str. 13",
    "sg:city":"Kusterdingen",
    "sg:phone":"+49 7071/32226",
    "sg:postcode":"72127",
    "sg:province":"Baden-W\u00fcrttemberg",
    "wof:name":"Willi Rilling",
    "wof:placetype":"venue"
},
  "geometry": {"coordinates":[9.112957,48.488167],"type":"Point"}
}