{
  "type": "Feature",
  "properties": {
    "iso:country":"DE",
    "sg:address":"Westfalenstr. 8",
    "sg:city":"D\u00fcsseldorf",
    "sg:phone":"+49 211/1785970",
    "sg:postcode":"40472",
    "sg:province":"Nordrhein-Westfalen",
    "wof:name":"Unit One Expo Team Messedienstleistungs Gmbh",
    "wof:placetype":"venue"
},
  "geometry": {"coordinates":[6.811308,51.262451],"type":"Point"}
}