{
  "type": "Feature",
  "properties": {
    "iso:country":"DE",
    "sg:address":"Riedstr. 25",
    "sg:city":"Schwabm\u00fcnchen",
    "sg:phone":"+49 8232/73780",
    "sg:postcode":"86830",
    "sg:province":"Bayern",
    "wof:name":"A. Deuringer",
    "wof:placetype":"venue"
},
  "geometry": {"coordinates":[10.7497301102,48.1774482727],"type":"Point"}
}