{
  "type": "Feature",
  "properties": {
    "iso:country":"DE",
    "sg:address":"Stargarder Str. 78",
    "sg:city":"Berlin",
    "sg:phone":"+49 30/4455253",
    "sg:postcode":"10437",
    "sg:province":"Berlin",
    "wof:name":"Kurt Gr\u00f6nke",
    "wof:placetype":"venue"
},
  "geometry": {"coordinates":[13.4150180817,52.547668457],"type":"Point"}
}