{
  "type": "Feature",
  "properties": {
    "iso:country":"DE",
    "sg:city":"Kronach",
    "sg:postcode":"96305",
    "sg:province":"Bayern",
    "wof:name":"Ffk Fahrzeugservice F\u00f6rtsch Gmbh",
    "wof:placetype":"venue"
},
  "geometry": {"coordinates":[11.32338,50.24007],"type":"Point"}
}