{
  "type": "Feature",
  "properties": {
    "iso:country":"DE",
    "sg:address":"Neuenb\u00fcrger Str. 45",
    "sg:city":"Straubenhardt",
    "sg:phone":"+49 7082/6775",
    "sg:postcode":"75334",
    "sg:province":"Baden-W\u00fcrttemberg",
    "wof:name":"Sonnen-apotheke",
    "wof:placetype":"venue"
},
  "geometry": {"coordinates":[8.537083,48.843296],"type":"Point"}
}