{
  "type": "Feature",
  "properties": {
    "iso:country":"DE",
    "sg:address":"Burgstr. 3",
    "sg:city":"Strasburg",
    "sg:phone":"+49 39753/20552",
    "sg:postcode":"17335",
    "sg:province":"Mecklenburg-Vorpommern",
    "wof:name":"W. Galla",
    "wof:placetype":"venue"
},
  "geometry": {"coordinates":[13.747575,53.50576],"type":"Point"}
}