{
  "type": "Feature",
  "properties": {
    "iso:country":"DE",
    "sg:address":"Au\u00dferhalb des Ortes 21",
    "sg:city":"Ginsheim-Gustavsburg",
    "sg:postcode":"65462",
    "sg:province":"Hessen",
    "wof:name":"Sqm Gmbh",
    "wof:placetype":"venue"
},
  "geometry": {"coordinates":[8.330094,49.981133],"type":"Point"}
}