{
  "type": "Feature",
  "properties": {
    "iso:country":"DE",
    "sg:address":"Kirchh\u00e4user Weg 46",
    "sg:city":"Massenbachhausen",
    "sg:phone":"+49 7138/920680",
    "sg:postcode":"74252",
    "sg:province":"Baden-W\u00fcrttemberg",
    "wof:name":"Werner Marbach Ingenieur",
    "wof:placetype":"venue"
},
  "geometry": {"coordinates":[9.0540533066,49.1751899719],"type":"Point"}
}