{
  "type": "Feature",
  "properties": {
    "iso:country":"DE",
    "sg:address":"Weringhauser Str. 17",
    "sg:city":"Erwitte",
    "sg:phone":"+49 2943/6106",
    "sg:postcode":"59597",
    "sg:province":"Nordrhein-Westfalen",
    "wof:name":"Kerkhoff",
    "wof:placetype":"venue"
},
  "geometry": {"coordinates":[8.347057,51.632778],"type":"Point"}
}