{
  "type": "Feature",
  "properties": {
    "iso:country":"DE",
    "sg:address":"Auweg 27",
    "sg:city":"Adelschlag",
    "sg:phone":"+49 8424/1818",
    "sg:postcode":"85111",
    "sg:province":"Bayern",
    "wof:name":"Am Alois Meyer Gmbh",
    "wof:placetype":"venue"
},
  "geometry": {"coordinates":[11.2169008255,48.840297699],"type":"Point"}
}