{
  "type": "Feature",
  "properties": {
    "iso:country":"DE",
    "sg:address":"Bondorfer Str. 11",
    "sg:city":"Bad Honnef",
    "sg:phone":"+49 2224/4873",
    "sg:postcode":"53604",
    "sg:province":"Nordrhein-Westfalen",
    "wof:name":"A. Besgen",
    "wof:placetype":"venue"
},
  "geometry": {"coordinates":[7.228078,50.651806],"type":"Point"}
}