{
  "type": "Feature",
  "properties": {
    "iso:country":"DE",
    "sg:address":"Pfarrm\u00fcnsterstr. 32",
    "sg:city":"Mihla",
    "sg:phone":"+49 36924/42107",
    "sg:postcode":"99826",
    "sg:province":"Th\u00fcringen",
    "wof:name":"Huk-coburg Ursula \u00dcbersch\u00e4r",
    "wof:placetype":"venue"
},
  "geometry": {"coordinates":[10.3395452499,51.0749435425],"type":"Point"}
}