{
  "type": "Feature",
  "properties": {
    "iso:country":"DE",
    "sg:address":"Pegnitzer Str. 3",
    "sg:city":"Pottenstein",
    "sg:phone":"+49 9243/273",
    "sg:postcode":"91278",
    "sg:province":"Bayern",
    "wof:name":"Adam Frosch",
    "wof:placetype":"venue"
},
  "geometry": {"coordinates":[11.406857,49.76997],"type":"Point"}
}