{
  "type": "Feature",
  "properties": {
    "iso:country":"DE",
    "sg:address":"Neuweiherstr. 17",
    "sg:city":"Baiersdorf",
    "sg:postcode":"91083",
    "sg:province":"Bayern",
    "wof:name":"Axel Bayer Kfz-sachverst\u00e4ndiger",
    "wof:placetype":"venue"
},
  "geometry": {"coordinates":[11.044832,49.644436],"type":"Point"}
}