{
  "type": "Feature",
  "properties": {
    "iso:country":"DE",
    "sg:address":"Aachener Str. 2",
    "sg:city":"Erkelenz",
    "sg:phone":"+49 2431/782176",
    "sg:postcode":"41812",
    "sg:province":"Nordrhein-Westfalen",
    "wof:name":"D2 - Shop",
    "wof:placetype":"venue"
},
  "geometry": {"coordinates":[6.3162670135,51.0792961121],"type":"Point"}
}