{
  "type": "Feature",
  "properties": {
    "iso:country":"DE",
    "sg:address":"Eichenweg 12",
    "sg:city":"Steinfurt",
    "sg:phone":"+49 2552/4040",
    "sg:postcode":"48565",
    "sg:province":"Nordrhein-Westfalen",
    "wof:name":"Walter Uhlenbrock Gmbh Handelsvertretung",
    "wof:placetype":"venue"
},
  "geometry": {"coordinates":[7.3809480667,52.1251029968],"type":"Point"}
}