{
  "type": "Feature",
  "properties": {
    "iso:country":"DE",
    "sg:address":"Anastasiastr. 26",
    "sg:city":"Rostock",
    "sg:postcode":"18119",
    "sg:province":"Mecklenburg-Vorpommern",
    "wof:name":"Hanseatische Baukontor Gmbh Handels- Und Vertriebsge-",
    "wof:placetype":"venue"
},
  "geometry": {"coordinates":[12.084588,54.179188],"type":"Point"}
}