{
  "type": "Feature",
  "properties": {
    "iso:country":"DE",
    "sg:address":"Michelsbergstr. 18",
    "sg:city":"Siegen",
    "sg:phone":"+49 271/3930190",
    "sg:postcode":"57080",
    "sg:province":"Nordrhein-Westfalen",
    "wof:name":"Eha Autoschilder Gmbh",
    "wof:placetype":"venue"
},
  "geometry": {"coordinates":[8.028462,50.829163],"type":"Point"}
}