{
  "type": "Feature",
  "properties": {
    "iso:country":"DE",
    "sg:address":"Im Ohl 4",
    "sg:city":"Arnsberg",
    "sg:phone":"+49 2932/23048",
    "sg:postcode":"59757",
    "sg:province":"Nordrhein-Westfalen",
    "wof:name":"Profix Industrieg\u00fcter Gmbh",
    "wof:placetype":"venue"
},
  "geometry": {"coordinates":[7.952131,51.456738],"type":"Point"}
}