{
  "type": "Feature",
  "properties": {
    "iso:country":"DE",
    "sg:address":"Felsenkellerpromenade 1",
    "sg:city":"Bad Suderode",
    "sg:phone":"+49 39485/258",
    "sg:postcode":"06507",
    "sg:province":"Sachsen-Anhalt",
    "wof:name":"Waldrestaurant Felsenkeller",
    "wof:placetype":"venue"
},
  "geometry": {"coordinates":[11.1165761948,51.7258796692],"type":"Point"}
}