{
  "type": "Feature",
  "properties": {
    "iso:country":"DE",
    "sg:address":"Horrenberger Str. 66",
    "sg:city":"Wiesloch",
    "sg:phone":"+49 6222/74240",
    "sg:postcode":"69168",
    "sg:province":"Baden-W\u00fcrttemberg",
    "wof:name":"Clubhaus",
    "wof:placetype":"venue"
},
  "geometry": {"coordinates":[8.7545986176,49.2954483032],"type":"Point"}
}