{
  "type": "Feature",
  "properties": {
    "iso:country":"DE",
    "sg:address":"Hagenstr. 7",
    "sg:city":"Lehrte",
    "sg:phone":"+49 5132/51319",
    "sg:postcode":"31275",
    "sg:province":"Niedersachsen",
    "wof:name":"R. Hahne",
    "wof:placetype":"venue"
},
  "geometry": {"coordinates":[9.9799041748,52.370098114],"type":"Point"}
}