{
  "type": "Feature",
  "properties": {
    "iso:country":"DE",
    "sg:address":"Bienenweg 14",
    "sg:city":"Gr\u00f6benzell",
    "sg:phone":"+49 8142/51617",
    "sg:postcode":"82194",
    "sg:province":"Bayern",
    "wof:name":"Dr. Med. B. Peper-litterscheid \u00c4rztin F\u00fcr Psychotherapie",
    "wof:placetype":"venue"
},
  "geometry": {"coordinates":[11.3727502823,48.1886901855],"type":"Point"}
}