{
  "type": "Feature",
  "properties": {
    "iso:country":"DE",
    "sg:address":"M\u00fchlenweg 16",
    "sg:city":"Lenzen",
    "sg:postcode":"19309",
    "sg:province":"Brandenburg",
    "wof:name":"Basys Gmbh",
    "wof:placetype":"venue"
},
  "geometry": {"coordinates":[11.485576,53.097591],"type":"Point"}
}