{
  "type": "Feature",
  "properties": {
    "iso:country":"DE",
    "sg:address":"Kreuzfeldweg 23",
    "sg:city":"A\u00dfling",
    "sg:phone":"+49 8092/9094",
    "sg:postcode":"85617",
    "sg:province":"Bayern",
    "wof:name":"Simon Riedl",
    "wof:placetype":"venue"
},
  "geometry": {"coordinates":[12.001234,47.990765],"type":"Point"}
}