{
  "type": "Feature",
  "properties": {
    "iso:country":"DE",
    "sg:address":"Brackeler Hellweg 116",
    "sg:city":"Dortmund",
    "sg:phone":"+49 231/252007",
    "sg:postcode":"44309",
    "sg:province":"Nordrhein-Westfalen",
    "wof:name":"Gotthardt Gmbh Augenoptiker",
    "wof:placetype":"venue"
},
  "geometry": {"coordinates":[7.54271698,51.5231666565],"type":"Point"}
}