{
  "type": "Feature",
  "properties": {
    "iso:country":"DE",
    "sg:address":"Feriendorf H\u00f6rgering",
    "sg:city":"Siegsdorf",
    "sg:phone":"+49 8662/9675",
    "sg:postcode":"83313",
    "sg:province":"Bayern",
    "wof:name":"Franz Obermayer",
    "wof:placetype":"venue"
},
  "geometry": {"coordinates":[12.649766922,47.7843132019],"type":"Point"}
}