{
  "type": "Feature",
  "properties": {
    "iso:country":"DE",
    "sg:address":"Hauptstr. 2",
    "sg:city":"Kulmbach",
    "sg:phone":"+49 9221/90540",
    "sg:postcode":"95326",
    "sg:province":"Bayern",
    "wof:name":"Kulmbacher Natursteinwerk Gmbh",
    "wof:placetype":"venue"
},
  "geometry": {"coordinates":[11.4194288254,50.0918693542],"type":"Point"}
}