{
  "type": "Feature",
  "properties": {
    "iso:country":"DE",
    "sg:address":"Neuer Weg 1",
    "sg:city":"Niefern-\u00d6schelbronn",
    "sg:phone":"+49 7233/3795",
    "sg:postcode":"75223",
    "sg:province":"Baden-W\u00fcrttemberg",
    "wof:name":"Bistro Akut",
    "wof:placetype":"venue"
},
  "geometry": {"coordinates":[8.7749700546,48.9202690125],"type":"Point"}
}