{
  "type": "Feature",
  "properties": {
    "iso:country":"DE",
    "sg:address":"Daimlerstr. 5",
    "sg:city":"Wangen",
    "sg:phone":"+49 7161/21167",
    "sg:postcode":"73117",
    "sg:province":"Baden-W\u00fcrttemberg",
    "wof:name":"Walter B\u00e4umler",
    "wof:placetype":"venue"
},
  "geometry": {"coordinates":[9.606945,48.721603],"type":"Point"}
}