{
  "type": "Feature",
  "properties": {
    "iso:country":"DE",
    "sg:address":"Brunnenstr. 9",
    "sg:city":"Tangerm\u00fcnde",
    "sg:postcode":"39590",
    "sg:province":"Sachsen-Anhalt",
    "wof:name":"J. Oemke",
    "wof:placetype":"venue"
},
  "geometry": {"coordinates":[11.967351,52.539597],"type":"Point"}
}