{
  "type": "Feature",
  "properties": {
    "iso:country":"DE",
    "sg:address":"L\u00fctticher Str. 12",
    "sg:city":"Troisdorf",
    "sg:postcode":"53842",
    "sg:province":"Nordrhein-Westfalen",
    "wof:name":"Viet Thai Exotische Waren Handelsges. Mbh",
    "wof:placetype":"venue"
},
  "geometry": {"coordinates":[7.1119918823,50.8405723572],"type":"Point"}
}