{
  "type": "Feature",
  "properties": {
    "iso:country":"DE",
    "sg:address":"Klingenberg 11",
    "sg:city":"Altef\u00e4hr",
    "sg:postcode":"18573",
    "sg:province":"Mecklenburg-Vorpommern",
    "wof:name":"Jonny P\u00e4ch",
    "wof:placetype":"venue"
},
  "geometry": {"coordinates":[13.126151,54.330795],"type":"Point"}
}