{
  "type": "Feature",
  "properties": {
    "iso:country":"DE",
    "sg:address":"Rantzaustr. 102",
    "sg:city":"Hamburg",
    "sg:phone":"+49 40/68268886",
    "sg:postcode":"22041",
    "sg:province":"Hamburg",
    "wof:name":"Zmc Import Und Export Gmbh",
    "wof:placetype":"venue"
},
  "geometry": {"coordinates":[10.076138,53.57056],"type":"Point"}
}