{
  "type": "Feature",
  "properties": {
    "iso:country":"DE",
    "sg:address":"Im Steinbruch 4",
    "sg:city":"Flonheim",
    "sg:phone":"+49 6734/1490",
    "sg:postcode":"55237",
    "sg:province":"Rheinland-Pfalz",
    "wof:name":"Uni-form Kunststoff- Verarb. Gmbh",
    "wof:placetype":"venue"
},
  "geometry": {"coordinates":[8.042581,49.78046],"type":"Point"}
}