{
  "type": "Feature",
  "properties": {
    "iso:country":"DE",
    "sg:address":"Lutherstr. 11",
    "sg:city":"Limbach-Oberfrohna",
    "sg:phone":"+49 3722/92497",
    "sg:postcode":"09212",
    "sg:province":"Sachsen",
    "wof:name":"Dr. Med. G\u00fcnter Gessner",
    "wof:placetype":"venue"
},
  "geometry": {"coordinates":[12.772686,50.85326],"type":"Point"}
}