{
  "type": "Feature",
  "properties": {
    "iso:country":"DE",
    "sg:address":"M\u00f6hnestr. 55",
    "sg:city":"Warstein",
    "sg:phone":"+49 2925/3420",
    "sg:postcode":"59581",
    "sg:province":"Nordrhein-Westfalen",
    "wof:name":"Leo Reinold",
    "wof:placetype":"venue"
},
  "geometry": {"coordinates":[8.261577,51.485901],"type":"Point"}
}