{
  "type": "Feature",
  "properties": {
    "iso:country":"DE",
    "sg:address":"Reinborner Weg 4",
    "sg:city":"Frankfurt",
    "sg:phone":"+49 69/784667",
    "sg:postcode":"60489",
    "sg:province":"Hessen",
    "wof:name":"Martin Hajos Tennislehrer",
    "wof:placetype":"venue"
},
  "geometry": {"coordinates":[8.6120862961,50.1307182312],"type":"Point"}
}