{
  "type": "Feature",
  "properties": {
    "iso:country":"DE",
    "sg:address":"Aalstr. 36",
    "sg:city":"Bad Oeynhausen",
    "sg:phone":"+49 5731/40184",
    "sg:postcode":"32549",
    "sg:province":"Nordrhein-Westfalen",
    "wof:name":"Herbert Bl\u00f6baum",
    "wof:placetype":"venue"
},
  "geometry": {"coordinates":[8.773683548,52.2171478271],"type":"Point"}
}