{
  "type": "Feature",
  "properties": {
    "iso:country":"DE",
    "sg:address":"Theodor-Groz-Str. 31 POSTFACH 100427",
    "sg:city":"Albstadt",
    "sg:phone":"+49 4974/311250",
    "sg:postcode":"72425",
    "sg:province":"Baden-W\u00fcrttemberg",
    "wof:name":"Hartner Gmbh",
    "wof:placetype":"venue"
},
  "geometry": {"coordinates":[9.02766,48.209728],"type":"Point"}
}