{
  "type": "Feature",
  "properties": {
    "iso:country":"DE",
    "sg:address":"Frankfurter Str. 129",
    "sg:city":"Dreieich",
    "sg:phone":"+49 6103/311853",
    "sg:postcode":"63303",
    "sg:province":"Hessen",
    "wof:name":"Rz Systemsupport Unternehmensberatung E. Kfr.",
    "wof:placetype":"venue"
},
  "geometry": {"coordinates":[8.6958904266,50.0303077698],"type":"Point"}
}