{
  "type": "Feature",
  "properties": {
    "iso:country":"DE",
    "sg:address":"Franz-Peter-Sigel-Str. 42",
    "sg:city":"Bad Sch\u00f6nborn",
    "sg:phone":"+49 7253/4033",
    "sg:postcode":"76669",
    "sg:province":"Baden-W\u00fcrttemberg",
    "wof:name":"Seniorenstift Bad Sch\u00f6nborn",
    "wof:placetype":"venue"
},
  "geometry": {"coordinates":[8.653864,49.201389],"type":"Point"}
}