{
  "type": "Feature",
  "properties": {
    "iso:country":"DE",
    "sg:address":"St. Wilhadistr. 1",
    "sg:city":"Bardowick",
    "sg:phone":"+49 4131/12739",
    "sg:postcode":"21357",
    "sg:province":"Niedersachsen",
    "wof:name":"Willi Cohrs",
    "wof:placetype":"venue"
},
  "geometry": {"coordinates":[10.397419,53.29385],"type":"Point"}
}