{
  "type": "Feature",
  "properties": {
    "iso:country":"DE",
    "sg:address":"Neugablonzer Str. 7",
    "sg:city":"Neutraubling",
    "sg:postcode":"93073",
    "sg:province":"Bayern",
    "wof:name":"Bvu Automotive Gmbh & Co. Kg",
    "wof:placetype":"venue"
},
  "geometry": {"coordinates":[12.19292,48.97768],"type":"Point"}
}