{
  "type": "Feature",
  "properties": {
    "iso:country":"DE",
    "sg:address":"Herzogstr. 38",
    "sg:city":"Herne",
    "sg:phone":"+49 2325/34247",
    "sg:postcode":"44651",
    "sg:province":"Nordrhein-Westfalen",
    "wof:name":"Heikes Blumenladen",
    "wof:placetype":"venue"
},
  "geometry": {"coordinates":[7.184988,51.514244],"type":"Point"}
}