{
  "type": "Feature",
  "properties": {
    "iso:country":"DE",
    "sg:address":"Weiherstr. 29",
    "sg:city":"Rheinbach",
    "sg:phone":"+49 2226/5140",
    "sg:postcode":"53359",
    "sg:province":"Nordrhein-Westfalen",
    "wof:name":"M. Mertens Steuerberater",
    "wof:placetype":"venue"
},
  "geometry": {"coordinates":[6.947535038,50.6238250732],"type":"Point"}
}