{
  "type": "Feature",
  "properties": {
    "iso:country":"DE",
    "sg:address":"Stadtplatz 27",
    "sg:city":"Eggenfelden",
    "sg:phone":"+49 8721/2728",
    "sg:postcode":"84307",
    "sg:province":"Bayern",
    "wof:name":"Jutta Hollay Heilpraktikerin",
    "wof:placetype":"venue"
},
  "geometry": {"coordinates":[12.7627563477,48.4034461975],"type":"Point"}
}