{
  "type": "Feature",
  "properties": {
    "iso:country":"DE",
    "sg:address":"Zittschower Weg 26",
    "sg:city":"Ratzeburg",
    "sg:phone":"+49 4541/82166",
    "sg:postcode":"23909",
    "sg:province":"Schleswig-Holstein",
    "wof:name":"Gerhard St\u00f6ber Steuerberater",
    "wof:placetype":"venue"
},
  "geometry": {"coordinates":[10.7961511612,53.6896286011],"type":"Point"}
}