{
  "type": "Feature",
  "properties": {
    "iso:country":"DE",
    "sg:address":"Schulstr. 7",
    "sg:city":"Kitzen",
    "sg:phone":"+49 34203/51381",
    "sg:postcode":"04460",
    "sg:province":"Sachsen",
    "wof:name":"Pegauer Fleisch- Und Wurstwaren Gmbh",
    "wof:placetype":"venue"
},
  "geometry": {"coordinates":[12.2216243744,51.2179603577],"type":"Point"}
}