{
  "type": "Feature",
  "properties": {
    "iso:country":"DE",
    "sg:address":"Hauptstr. 27",
    "sg:city":"Verl",
    "sg:phone":"+49 5246/3618",
    "sg:postcode":"33415",
    "sg:province":"Nordrhein-Westfalen",
    "wof:name":"Hermann Stratsteffen",
    "wof:placetype":"venue"
},
  "geometry": {"coordinates":[8.5075139999,51.8843345642],"type":"Point"}
}