{
  "type": "Feature",
  "properties": {
    "iso:country":"DE",
    "sg:address":"Langensalzaer Str. 16 a",
    "sg:city":"Gro\u00dfenlupnitz",
    "sg:phone":"+49 36920/80424",
    "sg:postcode":"99819",
    "sg:province":"Th\u00fcringen",
    "wof:name":"M. Gr\u00f6ger",
    "wof:placetype":"venue"
},
  "geometry": {"coordinates":[10.409253,50.996803],"type":"Point"}
}