{
  "type": "Feature",
  "properties": {
    "iso:country":"DE",
    "sg:address":"Stephanstr. 19",
    "sg:city":"Neustadt",
    "sg:phone":"+49 6321/80528",
    "sg:postcode":"67434",
    "sg:province":"Rheinland-Pfalz",
    "wof:name":"Franz Schweinhardt Finanzberater",
    "wof:placetype":"venue"
},
  "geometry": {"coordinates":[8.1361131668,49.3460159302],"type":"Point"}
}