{
  "type": "Feature",
  "properties": {
    "iso:country":"DE",
    "sg:address":"Ofener Str. 48",
    "sg:city":"Oldenburg",
    "sg:phone":"+49 441/72395",
    "sg:postcode":"26121",
    "sg:province":"Niedersachsen",
    "wof:name":"Tava",
    "wof:placetype":"venue"
},
  "geometry": {"coordinates":[8.1933679581,53.1431350708],"type":"Point"}
}