{
  "type": "Feature",
  "properties": {
    "iso:country":"DE",
    "sg:address":"Markstr. 411",
    "sg:city":"Bochum",
    "sg:phone":"+49 234/460227",
    "sg:postcode":"44795",
    "sg:province":"Nordrhein-Westfalen",
    "wof:name":"H. Hake Drogerie",
    "wof:placetype":"venue"
},
  "geometry": {"coordinates":[7.213898,51.441219],"type":"Point"}
}