{
  "type": "Feature",
  "properties": {
    "iso:country":"DE",
    "sg:address":"Schulthei\u00dfenweg 60",
    "sg:city":"Frankfurt",
    "sg:phone":"+49 69/785352",
    "sg:postcode":"60489",
    "sg:province":"Hessen",
    "wof:name":"Klaus Maier Steuerberater",
    "wof:placetype":"venue"
},
  "geometry": {"coordinates":[8.5955076218,50.1284484863],"type":"Point"}
}