{
  "type": "Feature",
  "properties": {
    "iso:country":"DE",
    "sg:address":"Adenauerallee 10",
    "sg:city":"Hamburg",
    "sg:phone":"+49 40/362581",
    "sg:postcode":"20097",
    "sg:province":"Hamburg",
    "wof:name":"Rantics Trading & Consulting Gmbh",
    "wof:placetype":"venue"
},
  "geometry": {"coordinates":[10.013244,53.552567],"type":"Point"}
}