{
  "type": "Feature",
  "properties": {
    "iso:country":"DE",
    "sg:address":"Birkenweg 23",
    "sg:city":"Hille",
    "sg:phone":"+49 571/649429",
    "sg:postcode":"32479",
    "sg:province":"Nordrhein-Westfalen",
    "wof:name":"Hildegard Fabig Steuerbevollm\u00e4chtigte",
    "wof:placetype":"venue"
},
  "geometry": {"coordinates":[8.8282213211,52.3179397583],"type":"Point"}
}