{
  "type": "Feature",
  "properties": {
    "iso:country":"DE",
    "sg:address":"Friedrichstr. 32",
    "sg:city":"Friedrichroda",
    "sg:phone":"+49 3623/304688",
    "sg:postcode":"99894",
    "sg:province":"Th\u00fcringen",
    "wof:name":"B. Stadler",
    "wof:placetype":"venue"
},
  "geometry": {"coordinates":[10.572826,50.857349],"type":"Point"}
}