{
  "type": "Feature",
  "properties": {
    "iso:country":"DE",
    "sg:address":"Gro\u00dfe Leege Str. 42b",
    "sg:city":"Berlin",
    "sg:phone":"+49 30/9716999",
    "sg:postcode":"13055",
    "sg:province":"Berlin",
    "wof:name":"Thomas Starck",
    "wof:placetype":"venue"
},
  "geometry": {"coordinates":[13.4907741547,52.5397109985],"type":"Point"}
}