{
  "type": "Feature",
  "properties": {
    "iso:country":"DE",
    "sg:address":"Pla\u00dfhofsbankstr. 10",
    "sg:city":"Essen",
    "sg:phone":"+49 201/556967",
    "sg:postcode":"45309",
    "sg:province":"Nordrhein-Westfalen",
    "wof:name":"David Busch Gmbh",
    "wof:placetype":"venue"
},
  "geometry": {"coordinates":[7.0806050301,51.482624054],"type":"Point"}
}