{
  "type": "Feature",
  "properties": {
    "iso:country":"DE",
    "sg:address":"Oberweidstr.",
    "sg:city":"Kriftel",
    "sg:postcode":"65830",
    "sg:province":"Hessen",
    "wof:name":"Aldi Gmbh & Co. Kg",
    "wof:placetype":"venue"
},
  "geometry": {"coordinates":[8.4584236145,50.0830154419],"type":"Point"}
}