{
  "type": "Feature",
  "properties": {
    "iso:country":"DE",
    "sg:address":"Wilhelm-K\u00fclz-Str. 29",
    "sg:city":"Cottbus",
    "sg:phone":"+49 355/795373",
    "sg:postcode":"03046",
    "sg:province":"Brandenburg",
    "wof:name":"A. Kluba Ingenieur",
    "wof:placetype":"venue"
},
  "geometry": {"coordinates":[14.3216991425,51.7540855408],"type":"Point"}
}