{
  "type": "Feature",
  "properties": {
    "iso:country":"DE",
    "sg:address":"Bl\u00fctenstr. 9",
    "sg:city":"L\u00fctzelbach",
    "sg:phone":"+49 9372/944756",
    "sg:postcode":"64750",
    "sg:province":"Hessen",
    "wof:name":"Vbm-kompakt",
    "wof:placetype":"venue"
},
  "geometry": {"coordinates":[9.125726,49.792366],"type":"Point"}
}