{
  "type": "Feature",
  "properties": {
    "iso:country":"DE",
    "sg:address":"Talstr. 40",
    "sg:city":"Notzingen",
    "sg:phone":"+49 7021/42567",
    "sg:postcode":"73274",
    "sg:province":"Baden-W\u00fcrttemberg",
    "wof:name":"Bieg & Seitz Tours Gmbh",
    "wof:placetype":"venue"
},
  "geometry": {"coordinates":[9.4506845474,48.6707801819],"type":"Point"}
}