{
  "type": "Feature",
  "properties": {
    "iso:country":"DE",
    "sg:address":"Allmandstr. 4",
    "sg:city":"Oberndorf",
    "sg:phone":"+49 7423/5168",
    "sg:postcode":"78727",
    "sg:province":"Baden-W\u00fcrttemberg",
    "wof:name":"Alwin Heinzelmann",
    "wof:placetype":"venue"
},
  "geometry": {"coordinates":[8.5966587067,48.302066803],"type":"Point"}
}