{
  "type": "Feature",
  "properties": {
    "iso:country":"DE",
    "sg:address":"Auenbruggerstr. 90a",
    "sg:city":"M\u00fcnchen",
    "sg:phone":"+49 89/8120421",
    "sg:postcode":"80999",
    "sg:province":"Bayern",
    "wof:name":"Bit B\u00fcro Informations Technik Schneider",
    "wof:placetype":"venue"
},
  "geometry": {"coordinates":[11.445457,48.179932],"type":"Point"}
}