{
  "type": "Feature",
  "properties": {
    "iso:country":"DE",
    "sg:address":"Kolpingstr. 5",
    "sg:city":"Hanau",
    "sg:phone":"+49 6181/60198",
    "sg:postcode":"63456",
    "sg:province":"Hessen",
    "wof:name":"J\u00fcrgen Paul",
    "wof:placetype":"venue"
},
  "geometry": {"coordinates":[8.930455,50.10236],"type":"Point"}
}