{
  "type": "Feature",
  "properties": {
    "iso:country":"DE",
    "sg:address":"F\u00f6hrenweg 4 a",
    "sg:city":"Pentling",
    "sg:phone":"+49 941/948106",
    "sg:postcode":"93080",
    "sg:province":"Bayern",
    "wof:name":"Bernhard Gruber Architekt",
    "wof:placetype":"venue"
},
  "geometry": {"coordinates":[12.059611,48.987309],"type":"Point"}
}