{
  "type": "Feature",
  "properties": {
    "iso:country":"DE",
    "sg:address":"Franz\u00f6sische Str. 1",
    "sg:city":"Saarlouis",
    "sg:phone":"+49 6831/2957",
    "sg:postcode":"66740",
    "sg:province":"Saarland",
    "wof:name":"Ludwigs-apotheke",
    "wof:placetype":"venue"
},
  "geometry": {"coordinates":[6.751377,49.315128],"type":"Point"}
}