{
  "type": "Feature",
  "properties": {
    "iso:country":"DE",
    "sg:address":"Lange Str. 36",
    "sg:city":"Braunschweig",
    "sg:phone":"+49 531/44297",
    "sg:postcode":"38100",
    "sg:province":"Niedersachsen",
    "wof:name":"St.-petri-apotheke",
    "wof:placetype":"venue"
},
  "geometry": {"coordinates":[10.515046,52.266766],"type":"Point"}
}