{
  "type": "Feature",
  "properties": {
    "iso:country":"DE",
    "sg:address":"Heuberg 2",
    "sg:city":"C\u00f6lbe",
    "sg:phone":"+49 6421/84656",
    "sg:postcode":"35091",
    "sg:province":"Hessen",
    "wof:name":"Thomas Rotarius",
    "wof:placetype":"venue"
},
  "geometry": {"coordinates":[8.7845802307,50.8490180969],"type":"Point"}
}