{
  "type": "Feature",
  "properties": {
    "iso:country":"DE",
    "sg:address":"Kamener Str. 62",
    "sg:city":"Unna",
    "sg:postcode":"59425",
    "sg:province":"Nordrhein-Westfalen",
    "wof:name":"Verbraucherkonzept Rafael Ciesla Und",
    "wof:placetype":"venue"
},
  "geometry": {"coordinates":[7.6812739372,51.559715271],"type":"Point"}
}