{
  "type": "Feature",
  "properties": {
    "iso:country":"DE",
    "sg:address":"R\u00f6ter Str. 23",
    "sg:city":"Baiersbronn",
    "sg:phone":"+49 7442/50386",
    "sg:postcode":"72270",
    "sg:province":"Baden-W\u00fcrttemberg",
    "wof:name":"Werner Rothfuss Architekt",
    "wof:placetype":"venue"
},
  "geometry": {"coordinates":[8.3987,48.528542],"type":"Point"}
}