{
  "type": "Feature",
  "properties": {
    "iso:country":"DE",
    "sg:address":"Benzstr. 4",
    "sg:city":"Kirchheim",
    "sg:phone":"+49 89/9915110",
    "sg:postcode":"85551",
    "sg:province":"Bayern",
    "wof:name":"Sirius Image Company Gesellschaft F. Bildmanagement",
    "wof:placetype":"venue"
},
  "geometry": {"coordinates":[11.7667856216,48.1783027649],"type":"Point"}
}