{
  "type": "Feature",
  "properties": {
    "iso:country":"DE",
    "sg:address":"Sophienstrasse 19",
    "sg:city":"Stuttgart",
    "sg:phone":"+49 711/62009630",
    "sg:postcode":"70178",
    "sg:province":"Baden-W\u00fcrttemberg",
    "wof:name":"Sophie 19 - Moderatoren F\u00fcr Events Und Tv",
    "wof:placetype":"venue"
},
  "geometry": {"coordinates":[9.174157,48.771458],"type":"Point"}
}