{
  "type": "Feature",
  "properties": {
    "iso:country":"DE",
    "sg:address":"Am M\u00fchlteich 12",
    "sg:city":"Krosigk",
    "sg:postcode":"06193",
    "sg:province":"Sachsen-Anhalt",
    "wof:name":"H. Kurth",
    "wof:placetype":"venue"
},
  "geometry": {"coordinates":[11.9326496124,51.6134605408],"type":"Point"}
}