{
  "type": "Feature",
  "properties": {
    "iso:country":"DE",
    "sg:address":"Pestalozzistr.",
    "sg:city":"Pasewalk",
    "sg:phone":"+49 3973/213615",
    "sg:postcode":"17309",
    "sg:province":"Mecklenburg-Vorpommern",
    "wof:name":"Schwedter Backwaren Gmbh",
    "wof:placetype":"venue"
},
  "geometry": {"coordinates":[14.00682,53.506451],"type":"Point"}
}