{
  "type": "Feature",
  "properties": {
    "iso:country":"DE",
    "sg:address":"Atenser Allee 117",
    "sg:city":"Nordenham",
    "sg:phone":"+49 4731/93990",
    "sg:postcode":"26954",
    "sg:province":"Niedersachsen",
    "wof:name":"Albers & Korn Beteiligungs Gmbh",
    "wof:placetype":"venue"
},
  "geometry": {"coordinates":[8.47763,53.500229],"type":"Point"}
}