{
  "type": "Feature",
  "properties": {
    "iso:country":"DE",
    "sg:address":"Boschstr 5",
    "sg:city":"Neustadt",
    "sg:phone":"+49 5032/2730",
    "sg:postcode":"31535",
    "sg:province":"Niedersachsen",
    "wof:name":"Nmt Metall Technik Gmbh & Co Kg",
    "wof:placetype":"venue"
},
  "geometry": {"coordinates":[9.3272628784,48.8577079773],"type":"Point"}
}