{
  "type": "Feature",
  "properties": {
    "iso:country":"DE",
    "sg:address":"Herriedener Str. 36",
    "sg:city":"N\u00fcrnberg",
    "sg:phone":"+49 911/674054",
    "sg:postcode":"90449",
    "sg:province":"Bayern",
    "wof:name":"Restaurant Akropolis",
    "wof:placetype":"venue"
},
  "geometry": {"coordinates":[11.0234413147,49.4199981689],"type":"Point"}
}