{
  "type": "Feature",
  "properties": {
    "iso:country":"DE",
    "sg:address":"Hagelgrundstr. 3",
    "sg:city":"Kaiserslautern",
    "sg:phone":"+49 631/72622",
    "sg:postcode":"67659",
    "sg:province":"Rheinland-Pfalz",
    "wof:name":"A. Reiss",
    "wof:placetype":"venue"
},
  "geometry": {"coordinates":[7.7880501747,49.469417572],"type":"Point"}
}