{
  "type": "Feature",
  "properties": {
    "iso:country":"DE",
    "sg:address":"Niederrotweil 13",
    "sg:city":"Vogtsburg",
    "sg:postcode":"79235",
    "sg:province":"Baden-W\u00fcrttemberg",
    "wof:name":"Egon Kaltenbach Vorm. Leo Baldinger",
    "wof:placetype":"venue"
},
  "geometry": {"coordinates":[7.6844778061,48.092918396],"type":"Point"}
}