{
  "type": "Feature",
  "properties": {
    "iso:country":"DE",
    "sg:address":"Leipziger Str. 3",
    "sg:city":"Apolda",
    "sg:phone":"+49 3644/50230",
    "sg:postcode":"99510",
    "sg:province":"Th\u00fcringen",
    "wof:name":"Autohaus Scholz Inh. Harald Scholz",
    "wof:placetype":"venue"
},
  "geometry": {"coordinates":[11.479627,51.019524],"type":"Point"}
}