{
  "type": "Feature",
  "properties": {
    "iso:country":"DE",
    "sg:address":"Wartenbergstr. 34",
    "sg:city":"Osnabr\u00fcck",
    "sg:phone":"+49 541/51601",
    "sg:postcode":"49082",
    "sg:province":"Niedersachsen",
    "wof:name":"Karl-heinz Knop",
    "wof:placetype":"venue"
},
  "geometry": {"coordinates":[8.0620565414,52.2580184937],"type":"Point"}
}