{
  "type": "Feature",
  "properties": {
    "iso:country":"DE",
    "sg:address":"Pestalozzistr. 17",
    "sg:city":"Rathmannsdorf",
    "sg:phone":"+49 35022/41768",
    "sg:postcode":"01814",
    "sg:province":"Sachsen",
    "wof:name":"Frank Sander",
    "wof:placetype":"venue"
},
  "geometry": {"coordinates":[14.1434602737,50.9291801453],"type":"Point"}
}