{
  "type": "Feature",
  "properties": {
    "iso:country":"DE",
    "sg:address":"Hans-Sachs-Str. 8",
    "sg:city":"M\u00fcnchen",
    "sg:phone":"+49 89/2609952",
    "sg:postcode":"80469",
    "sg:province":"Bayern",
    "wof:name":"Glockenbach Reisen",
    "wof:placetype":"venue"
},
  "geometry": {"coordinates":[11.569729805,48.1299362183],"type":"Point"}
}