{
  "type": "Feature",
  "properties": {
    "iso:country":"DE",
    "sg:address":"Gn\u00e4ditz 15 g",
    "sg:city":"Webau",
    "sg:phone":"+49 34441/29269",
    "sg:postcode":"06679",
    "sg:province":"Sachsen-Anhalt",
    "wof:name":"Walter D\u00f6rner",
    "wof:placetype":"venue"
},
  "geometry": {"coordinates":[12.0950546265,51.1687927246],"type":"Point"}
}