{
  "type": "Feature",
  "properties": {
    "iso:country":"DE",
    "sg:address":"Herrenstr 3-5",
    "sg:city":"Hannover",
    "sg:phone":"+49 511/126030",
    "sg:postcode":"30159",
    "sg:province":"Niedersachsen",
    "wof:name":"Union Beton Niedersachsen Gmbh & Co Kg",
    "wof:placetype":"venue"
},
  "geometry": {"coordinates":[9.7357549667,52.37733078],"type":"Point"}
}