{
  "type": "Feature",
  "properties": {
    "iso:country":"DE",
    "sg:address":"Luetkensallee 21",
    "sg:city":"Hamburg",
    "sg:phone":"+49 40/65687878",
    "sg:postcode":"22041",
    "sg:province":"Hamburg",
    "wof:name":"Joachim Zoellmer Gmbh",
    "wof:placetype":"venue"
},
  "geometry": {"coordinates":[10.0949411392,53.5773200989],"type":"Point"}
}