{
  "type": "Feature",
  "properties": {
    "iso:country":"DE",
    "sg:address":"Lippst\u00e4dter Str. 47",
    "sg:city":"Wadersloh",
    "sg:phone":"+49 2523/8395",
    "sg:postcode":"59329",
    "sg:province":"Nordrhein-Westfalen",
    "wof:name":"Karl Wulff",
    "wof:placetype":"venue"
},
  "geometry": {"coordinates":[8.267953,51.701118],"type":"Point"}
}