{
  "type": "Feature",
  "properties": {
    "iso:country":"DE",
    "sg:address":"Kirchplatz 1",
    "sg:city":"Meitingen",
    "sg:phone":"+49 8271/2141",
    "sg:postcode":"86405",
    "sg:province":"Bayern",
    "wof:name":"Josef Dreher",
    "wof:placetype":"venue"
},
  "geometry": {"coordinates":[10.8519105911,48.5284309387],"type":"Point"}
}