{
  "type": "Feature",
  "properties": {
    "iso:country":"DE",
    "sg:address":"Zerzabelshofstr. 5",
    "sg:city":"N\u00fcrnberg",
    "sg:phone":"+49 911/466864",
    "sg:postcode":"90478",
    "sg:province":"Bayern",
    "wof:name":"Boutique Barbara",
    "wof:placetype":"venue"
},
  "geometry": {"coordinates":[11.106686,49.445835],"type":"Point"}
}