{
  "type": "Feature",
  "properties": {
    "iso:country":"DE",
    "sg:address":"Abensberger Str. 36a",
    "sg:city":"Mainburg",
    "sg:phone":"+49 8751/810831",
    "sg:postcode":"84048",
    "sg:province":"Bayern",
    "wof:name":"E. H\u00f6sl",
    "wof:placetype":"venue"
},
  "geometry": {"coordinates":[11.7865400314,48.6449737549],"type":"Point"}
}