{
  "type": "Feature",
  "properties": {
    "iso:country":"DE",
    "sg:address":"Ottenberghalde 55",
    "sg:city":"Kressbronn",
    "sg:phone":"+49 7543/96030",
    "sg:postcode":"88079",
    "sg:province":"Baden-W\u00fcrttemberg",
    "wof:name":"Altenheim St. Konrad",
    "wof:placetype":"venue"
},
  "geometry": {"coordinates":[9.606893,47.591846],"type":"Point"}
}