{
  "type": "Feature",
  "properties": {
    "iso:country":"DE",
    "sg:address":"Reiffstr. 4",
    "sg:city":"Recklinghausen",
    "sg:postcode":"45659",
    "sg:province":"Nordrhein-Westfalen",
    "wof:name":"Planungsb\u00fcro Krahforst Gmbh",
    "wof:placetype":"venue"
},
  "geometry": {"coordinates":[7.190742,51.641495],"type":"Point"}
}