{
  "type": "Feature",
  "properties": {
    "iso:country":"DE",
    "sg:address":"Berliner Str. 39",
    "sg:city":"Lauenburg",
    "sg:phone":"+49 4153/4252",
    "sg:postcode":"21481",
    "sg:province":"Schleswig-Holstein",
    "wof:name":"Werner Kruse Inh. Heino Kruse",
    "wof:placetype":"venue"
},
  "geometry": {"coordinates":[10.5598583221,53.3744277954],"type":"Point"}
}