{
  "type": "Feature",
  "properties": {
    "iso:country":"DE",
    "sg:address":"Forststr. 9a",
    "sg:city":"Dresden",
    "sg:postcode":"01099",
    "sg:province":"Sachsen",
    "wof:name":"Werner Ehrlich",
    "wof:placetype":"venue"
},
  "geometry": {"coordinates":[13.7632131577,51.0656890869],"type":"Point"}
}