{
  "type": "Feature",
  "properties": {
    "iso:country":"DE",
    "sg:address":"Lindenhof 1 a",
    "sg:city":"Metschow",
    "sg:postcode":"17111",
    "sg:province":"Mecklenburg-Vorpommern",
    "wof:name":"Pension Bienenhof",
    "wof:placetype":"venue"
},
  "geometry": {"coordinates":[12.9651689529,53.9622688293],"type":"Point"}
}