{
  "type": "Feature",
  "properties": {
    "iso:country":"DE",
    "sg:address":"Burscheider Str. 154",
    "sg:city":"Leverkusen",
    "sg:phone":"+49 2171/32996",
    "sg:postcode":"51381",
    "sg:province":"Nordrhein-Westfalen",
    "wof:name":"D. Ley",
    "wof:placetype":"venue"
},
  "geometry": {"coordinates":[7.0377278328,51.0796546936],"type":"Point"}
}