{
  "type": "Feature",
  "properties": {
    "iso:country":"DE",
    "sg:address":"Wildensorger Str. 31",
    "sg:city":"Bamberg",
    "sg:phone":"+49 951/9570260",
    "sg:postcode":"96049",
    "sg:province":"Bayern",
    "wof:name":"Leonhard Ehrlich Ingenieur",
    "wof:placetype":"venue"
},
  "geometry": {"coordinates":[10.8670196533,49.8870201111],"type":"Point"}
}