{
  "type": "Feature",
  "properties": {
    "iso:country":"DE",
    "sg:address":"Hauptstr. 19",
    "sg:city":"Herborn",
    "sg:phone":"+49 2772/3371",
    "sg:postcode":"35745",
    "sg:province":"Hessen",
    "wof:name":"R\u00fcdiger Schwahn",
    "wof:placetype":"venue"
},
  "geometry": {"coordinates":[8.3028945923,50.6838912964],"type":"Point"}
}