{
  "type": "Feature",
  "properties": {
    "iso:country":"DE",
    "sg:address":"Burggraben 9-21",
    "sg:city":"Bergisch Gladbach",
    "sg:phone":"+49 2204/55559",
    "sg:postcode":"51429",
    "sg:province":"Nordrhein-Westfalen",
    "wof:name":"Bergisches Museum F. Bergbau Handwerk Und Gewerbe",
    "wof:placetype":"venue"
},
  "geometry": {"coordinates":[7.163572,50.965473],"type":"Point"}
}