{
  "type": "Feature",
  "properties": {
    "iso:country":"DE",
    "sg:address":"Stadtgartenstr. 42",
    "sg:city":"Ludwigshafen",
    "sg:phone":"+49 621/684754",
    "sg:postcode":"67071",
    "sg:province":"Rheinland-Pfalz",
    "wof:name":"Artur Schmidt Gmbh",
    "wof:placetype":"venue"
},
  "geometry": {"coordinates":[8.3781385422,49.4886245728],"type":"Point"}
}