{
  "type": "Feature",
  "properties": {
    "iso:country":"DE",
    "sg:address":"Werner-Siemens-Str. 29",
    "sg:city":"Hamburg",
    "sg:phone":"+49 40/75661930",
    "sg:postcode":"22113",
    "sg:province":"Schleswig-Holstein",
    "wof:name":"Hans-otto Saling",
    "wof:placetype":"venue"
},
  "geometry": {"coordinates":[10.088162,53.531006],"type":"Point"}
}