{
  "type": "Feature",
  "properties": {
    "iso:country":"DE",
    "sg:address":"Uferweg 7",
    "sg:city":"Drage",
    "sg:phone":"+49 4177/283",
    "sg:postcode":"21423",
    "sg:province":"Niedersachsen",
    "wof:name":"Pfaffenbach & Wenk Gmbh",
    "wof:placetype":"venue"
},
  "geometry": {"coordinates":[10.261713,53.414383],"type":"Point"}
}