{
  "type": "Feature",
  "properties": {
    "iso:country":"DE",
    "sg:address":"Stuttgarter Str. 63-65",
    "sg:city":"Metzingen",
    "sg:phone":"+49 7123/18080",
    "sg:postcode":"72555",
    "sg:province":"Baden-W\u00fcrttemberg",
    "wof:name":"M\u00fcller & Bauer Gmbh & Co.",
    "wof:placetype":"venue"
},
  "geometry": {"coordinates":[9.2755661011,48.5415420532],"type":"Point"}
}