{
  "type": "Feature",
  "properties": {
    "iso:country":"DE",
    "sg:address":"Kirchstr. 2",
    "sg:city":"Berod",
    "sg:phone":"+49 6435/6261",
    "sg:postcode":"56414",
    "sg:province":"Rheinland-Pfalz",
    "wof:name":"Heinz-josef Ehl",
    "wof:placetype":"venue"
},
  "geometry": {"coordinates":[7.937138,50.483921],"type":"Point"}
}