{
  "type": "Feature",
  "properties": {
    "iso:country":"DE",
    "sg:address":"Karlstr. 38",
    "sg:city":"Leinfelden-Echterdingen",
    "sg:phone":"+49 711/7542815",
    "sg:postcode":"70771",
    "sg:province":"Baden-W\u00fcrttemberg",
    "wof:name":"Peter Schaefer Ingenieur",
    "wof:placetype":"venue"
},
  "geometry": {"coordinates":[9.1236257553,48.6947364807],"type":"Point"}
}