{
  "type": "Feature",
  "properties": {
    "iso:country":"DE",
    "sg:address":"Unterm Moor 8",
    "sg:city":"Filsum",
    "sg:phone":"+49 4957/640",
    "sg:postcode":"26849",
    "sg:province":"Niedersachsen",
    "wof:name":"Dietrich Wattjes",
    "wof:placetype":"venue"
},
  "geometry": {"coordinates":[7.67507,53.251709],"type":"Point"}
}