{
  "type": "Feature",
  "properties": {
    "iso:country":"DE",
    "sg:address":"Josef-Reiss-Str. 13-15",
    "sg:city":"Tettnang",
    "sg:phone":"+49 7542/5050",
    "sg:postcode":"88069",
    "sg:province":"Baden-W\u00fcrttemberg",
    "wof:name":"Reiss International Gmbh",
    "wof:placetype":"venue"
},
  "geometry": {"coordinates":[9.58874,47.676842],"type":"Point"}
}