{
  "type": "Feature",
  "properties": {
    "iso:country":"DE",
    "sg:address":"Auf Dilgesh\u00f6h 14",
    "sg:city":"St. Wendel",
    "sg:phone":"+49 6856/279",
    "sg:postcode":"66606",
    "sg:province":"Saarland",
    "wof:name":"Heinz Schwarz Ingenieur",
    "wof:placetype":"venue"
},
  "geometry": {"coordinates":[7.2592301369,49.472568512],"type":"Point"}
}