{
  "type": "Feature",
  "properties": {
    "iso:country":"DE",
    "sg:address":"Marktstr. 1",
    "sg:city":"Bad Langensalza",
    "sg:phone":"+49 3603/6219",
    "sg:postcode":"99947",
    "sg:province":"Th\u00fcringen",
    "wof:name":"Stadtarchiv",
    "wof:placetype":"venue"
},
  "geometry": {"coordinates":[10.645123,51.108734],"type":"Point"}
}