{
  "type": "Feature",
  "properties": {
    "iso:country":"DE",
    "sg:address":"Bahnhofstr. 36",
    "sg:city":"Lotte",
    "sg:postcode":"49504",
    "sg:province":"Nordrhein-Westfalen",
    "wof:name":"B\u00fccherei Lotte",
    "wof:placetype":"venue"
},
  "geometry": {"coordinates":[7.919028,52.278118],"type":"Point"}
}