{
  "type": "Feature",
  "properties": {
    "iso:country":"DE",
    "sg:address":"Leintobelweg 21",
    "sg:city":"Scheidegg",
    "sg:phone":"+49 8381/7044",
    "sg:postcode":"88175",
    "sg:province":"Bayern",
    "wof:name":"Walter Langenmair Tennislehrer",
    "wof:placetype":"venue"
},
  "geometry": {"coordinates":[9.8607625961,47.5543861389],"type":"Point"}
}