{
  "type": "Feature",
  "properties": {
    "iso:country":"DE",
    "sg:address":"Karl-Holtz-Str. 16",
    "sg:city":"Berlin",
    "sg:phone":"+49 30/9324552",
    "sg:postcode":"12687",
    "sg:province":"Berlin",
    "wof:name":"Elisabeth Meinke",
    "wof:placetype":"venue"
},
  "geometry": {"coordinates":[13.5688171387,52.5526885986],"type":"Point"}
}