{
  "type": "Feature",
  "properties": {
    "iso:country":"DE",
    "sg:address":"Am H\u00fcgel 17",
    "sg:city":"Kulmbach",
    "sg:phone":"+49 9221/5336",
    "sg:postcode":"95326",
    "sg:province":"Bayern",
    "wof:name":"Lutz Immobilien Verwaltungs Gmbh",
    "wof:placetype":"venue"
},
  "geometry": {"coordinates":[11.4429302216,50.1218566895],"type":"Point"}
}