{
  "type": "Feature",
  "properties": {
    "iso:country":"DE",
    "sg:address":"Liebigstr 36/1",
    "sg:city":"Leingarten",
    "sg:phone":"+49 7131/174071",
    "sg:postcode":"74211",
    "sg:province":"Baden-W\u00fcrttemberg",
    "wof:name":"Geologistics Gmbh",
    "wof:placetype":"venue"
},
  "geometry": {"coordinates":[9.134894371,49.1474914551],"type":"Point"}
}