{
  "type": "Feature",
  "properties": {
    "iso:country":"DE",
    "sg:address":"Teutoburger Str. 10",
    "sg:city":"K\u00f6ln",
    "sg:phone":"+49 221/341311",
    "sg:postcode":"50678",
    "sg:province":"Nordrhein-Westfalen",
    "wof:name":"G\u00fcnter Berghaus Massagepraxis",
    "wof:placetype":"venue"
},
  "geometry": {"coordinates":[6.961326,50.9184],"type":"Point"}
}