{
  "type": "Feature",
  "properties": {
    "iso:country":"DE",
    "sg:address":"H\u00fcgel 3",
    "sg:city":"Altendambach",
    "sg:phone":"+49 3681/306902",
    "sg:postcode":"98553",
    "sg:province":"Th\u00fcringen",
    "wof:name":"Marion Brennecke Hebamme",
    "wof:placetype":"venue"
},
  "geometry": {"coordinates":[10.715529,50.559223],"type":"Point"}
}