{
  "type": "Feature",
  "properties": {
    "iso:country":"DE",
    "sg:address":"Industriestr 15",
    "sg:city":"Siegen",
    "sg:phone":"+49 271/772850",
    "sg:postcode":"57076",
    "sg:province":"Nordrhein-Westfalen",
    "wof:name":"Karl Theis Gmbh",
    "wof:placetype":"venue"
},
  "geometry": {"coordinates":[8.0356140137,50.9054069519],"type":"Point"}
}