{
  "type": "Feature",
  "properties": {
    "iso:country":"DE",
    "sg:address":"Niendorfer Str. 17",
    "sg:city":"Ratekau",
    "sg:phone":"+49 4502/3992",
    "sg:postcode":"23626",
    "sg:province":"Schleswig-Holstein",
    "wof:name":"J\u00f6rn Stoffers",
    "wof:placetype":"venue"
},
  "geometry": {"coordinates":[10.822337,53.970253],"type":"Point"}
}