{
  "type": "Feature",
  "properties": {
    "iso:country":"DE",
    "sg:address":"Karlstr. 12",
    "sg:city":"Falkenberg",
    "sg:phone":"+49 35365/34751",
    "sg:postcode":"04895",
    "sg:province":"Brandenburg",
    "wof:name":"Andreas Schmidt",
    "wof:placetype":"venue"
},
  "geometry": {"coordinates":[13.242528,51.586784],"type":"Point"}
}