{
  "type": "Feature",
  "properties": {
    "iso:country":"DE",
    "sg:address":"Coventrystr. 31",
    "sg:city":"Frankfurt",
    "sg:postcode":"65934",
    "sg:province":"Hessen",
    "wof:name":"Thc Pharm Gmbh",
    "wof:placetype":"venue"
},
  "geometry": {"coordinates":[8.5756263733,50.1021575928],"type":"Point"}
}