{
  "type": "Feature",
  "properties": {
    "iso:country":"DE",
    "sg:address":"Konrad-Celtis-Str. 33",
    "sg:city":"M\u00fcnchen",
    "sg:phone":"+49 171 5451678",
    "sg:postcode":"81369",
    "sg:province":"Bayern",
    "wof:name":"Antares Network",
    "wof:placetype":"venue"
},
  "geometry": {"coordinates":[11.5295619965,48.1108474731],"type":"Point"}
}