{
  "type": "Feature",
  "properties": {
    "iso:country":"DE",
    "sg:address":"An der Hart 40",
    "sg:city":"Weimar",
    "sg:phone":"+49 3643/401919",
    "sg:postcode":"99425",
    "sg:province":"Th\u00fcringen",
    "wof:name":"Waa Wasser- Und Abwasser- Anlagenbau Gmbh",
    "wof:placetype":"venue"
},
  "geometry": {"coordinates":[11.3531694412,50.963973999],"type":"Point"}
}