{
  "type": "Feature",
  "properties": {
    "iso:country":"DE",
    "sg:address":"Ortsstr. 12",
    "sg:city":"Aschau",
    "sg:phone":"+49 36738/42733",
    "sg:postcode":"07426",
    "sg:province":"Th\u00fcringen",
    "wof:name":"H. Schmidt",
    "wof:placetype":"venue"
},
  "geometry": {"coordinates":[11.132071,50.65469],"type":"Point"}
}