{
  "type": "Feature",
  "properties": {
    "iso:country":"DE",
    "sg:address":"Lange Trift 5",
    "sg:city":"Dransfeld",
    "sg:phone":"+49 172 9103181",
    "sg:postcode":"37127",
    "sg:province":"Niedersachsen",
    "wof:name":"Internet-service Fengewisch",
    "wof:placetype":"venue"
},
  "geometry": {"coordinates":[9.7574338913,51.4994735718],"type":"Point"}
}