{
  "type": "Feature",
  "properties": {
    "iso:country":"DE",
    "sg:address":"Hofstr. 20a",
    "sg:city":"Reinheim",
    "sg:phone":"+49 6162/81052",
    "sg:postcode":"64354",
    "sg:province":"Hessen",
    "wof:name":"Friedemann Mey",
    "wof:placetype":"venue"
},
  "geometry": {"coordinates":[8.824308,49.842125],"type":"Point"}
}