{
  "type": "Feature",
  "properties": {
    "iso:country":"DE",
    "sg:address":"Wolfsburger Str.",
    "sg:city":"Emden",
    "sg:postcode":"26723",
    "sg:province":"Niedersachsen",
    "wof:name":"Sil Steffens Industrie- Logistik Gmbh & Co. Kg",
    "wof:placetype":"venue"
},
  "geometry": {"coordinates":[7.1511449814,53.3613510132],"type":"Point"}
}