{
  "type": "Feature",
  "properties": {
    "iso:country":"DE",
    "sg:address":"Ketschendorfer Str. 84",
    "sg:city":"Coburg",
    "sg:postcode":"96450",
    "sg:province":"Bayern",
    "wof:name":"Aktiv Plus E. K.",
    "wof:placetype":"venue"
},
  "geometry": {"coordinates":[10.97103,50.247047],"type":"Point"}
}