{
  "type": "Feature",
  "properties": {
    "iso:country":"DE",
    "sg:address":"Erlenbruck 7",
    "sg:city":"Hinterzarten",
    "sg:phone":"+49 7652/753",
    "sg:postcode":"79856",
    "sg:province":"Baden-W\u00fcrttemberg",
    "wof:name":"Pension Hermine Dinger",
    "wof:placetype":"venue"
},
  "geometry": {"coordinates":[8.1100301743,47.8918380737],"type":"Point"}
}