{
  "type": "Feature",
  "properties": {
    "iso:country":"DE",
    "sg:address":"Seitschen 20",
    "sg:city":"G\u00f6da",
    "sg:phone":"+49 35930/51404",
    "sg:postcode":"02633",
    "sg:province":"Sachsen",
    "wof:name":"Blattin Mineralfutterwerk Seitschen Verwaltungs Gmbh",
    "wof:placetype":"venue"
},
  "geometry": {"coordinates":[14.321523,51.177536],"type":"Point"}
}