{
  "type": "Feature",
  "properties": {
    "iso:country":"DE",
    "sg:address":"Bergstr. 14",
    "sg:city":"Pfungstadt",
    "sg:phone":"+49 6157/5138",
    "sg:postcode":"64319",
    "sg:province":"Hessen",
    "wof:name":"Heinrich Darmst\u00e4dter",
    "wof:placetype":"venue"
},
  "geometry": {"coordinates":[8.598705,49.800873],"type":"Point"}
}