{
  "type": "Feature",
  "properties": {
    "iso:country":"DE",
    "sg:address":"Lindacher Feld 1",
    "sg:city":"Weichs",
    "sg:phone":"+49 8137/933501",
    "sg:postcode":"85258",
    "sg:province":"Bayern",
    "wof:name":"Seniorenwohnpark Ebersbach",
    "wof:placetype":"venue"
},
  "geometry": {"coordinates":[11.439893,48.390972],"type":"Point"}
}