{
  "type": "Feature",
  "properties": {
    "iso:country":"DE",
    "sg:address":"Am Deichdenkmal 11",
    "sg:city":"Hamburg",
    "sg:phone":"+49 40/7509625",
    "sg:postcode":"21109",
    "sg:province":"Hamburg",
    "wof:name":"Bernd Rosen\u00f6gger",
    "wof:placetype":"venue"
},
  "geometry": {"coordinates":[10.024178,53.493198],"type":"Point"}
}