{
  "type": "Feature",
  "properties": {
    "iso:country":"DE",
    "sg:address":"Nelkenweg 8",
    "sg:city":"Remscheid",
    "sg:phone":"+49 2191/55101",
    "sg:postcode":"42899",
    "sg:province":"Nordrhein-Westfalen",
    "wof:name":"J\u00fcrgen Petersen Ingenieur",
    "wof:placetype":"venue"
},
  "geometry": {"coordinates":[7.2395830154,51.2161026001],"type":"Point"}
}