{
  "type": "Feature",
  "properties": {
    "iso:country":"DE",
    "sg:address":"Nordbergstr. 13",
    "sg:city":"Obersulm",
    "sg:phone":"+49 7130/450541",
    "sg:postcode":"74182",
    "sg:province":"Baden-W\u00fcrttemberg",
    "wof:name":"Affaltracher Verlagsdruckerei Gmbh & Co. Kg",
    "wof:placetype":"venue"
},
  "geometry": {"coordinates":[9.3805294037,49.1372909546],"type":"Point"}
}