{
  "type": "Feature",
  "properties": {
    "iso:country":"DE",
    "sg:address":"Basler Stra\u00dfe 115",
    "sg:city":"Freiburg",
    "sg:phone":"+49 761",
    "sg:postcode":"79115",
    "sg:province":"Baden-W\u00fcrttemberg",
    "wof:name":"Vp - Verm\u00f6gensplanung - Mit Uns In Die Zukunft",
    "wof:placetype":"venue"
},
  "geometry": {"coordinates":[7.818853,47.984348],"type":"Point"}
}