{
  "type": "Feature",
  "properties": {
    "iso:country":"DE",
    "sg:address":"Vom-Berge-Weg 6 D",
    "sg:city":"Hamburg",
    "sg:phone":"+49 40/64539771",
    "sg:postcode":"22159",
    "sg:province":"Hamburg",
    "wof:name":"Teens/teens Einfach Nackte M\u00e4dchen.",
    "wof:placetype":"venue"
},
  "geometry": {"coordinates":[10.109298,53.605133],"type":"Point"}
}