{
  "type": "Feature",
  "properties": {
    "iso:country":"DE",
    "sg:address":"B\u00e4belitzer Weg 4",
    "sg:city":"Gnoien",
    "sg:phone":"+49 39971/12066",
    "sg:postcode":"17179",
    "sg:province":"Mecklenburg-Vorpommern",
    "wof:name":"Horst Wienh\u00f6ft",
    "wof:placetype":"venue"
},
  "geometry": {"coordinates":[12.7057409286,53.9731750488],"type":"Point"}
}