{
  "type": "Feature",
  "properties": {
    "iso:country":"DE",
    "sg:address":"Kirchgasse 2",
    "sg:city":"Schlo\u00dfvippach",
    "sg:phone":"+49 36371/52353",
    "sg:postcode":"99195",
    "sg:province":"Th\u00fcringen",
    "wof:name":"S\u00fcpke Und Horschkara Ohg",
    "wof:placetype":"venue"
},
  "geometry": {"coordinates":[11.141008,51.10535],"type":"Point"}
}