{
  "type": "Feature",
  "properties": {
    "iso:country":"DE",
    "sg:address":"Venusgasse 5",
    "sg:city":"Duisburg",
    "sg:phone":"+49 203/286280",
    "sg:postcode":"47051",
    "sg:province":"Nordrhein-Westfalen",
    "wof:name":"Nitz & Co. Speditions-kontor Gmbh",
    "wof:placetype":"venue"
},
  "geometry": {"coordinates":[6.7632961273,51.4332466125],"type":"Point"}
}