{
  "type": "Feature",
  "properties": {
    "iso:country":"DE",
    "sg:address":"Neustr. 5",
    "sg:city":"Laufeld",
    "sg:phone":"+49 6572/4323",
    "sg:postcode":"54533",
    "sg:province":"Rheinland-Pfalz",
    "wof:name":"T. Sartoris",
    "wof:placetype":"venue"
},
  "geometry": {"coordinates":[6.8666338921,50.0781974792],"type":"Point"}
}