{
  "type": "Feature",
  "properties": {
    "iso:country":"DE",
    "sg:address":"Wendentorwall 2a",
    "sg:city":"Braunschweig",
    "sg:phone":"+49 531/42798",
    "sg:postcode":"38100",
    "sg:province":"Niedersachsen",
    "wof:name":"Hoffmeister Gmbh",
    "wof:placetype":"venue"
},
  "geometry": {"coordinates":[10.5255022049,52.2719459534],"type":"Point"}
}