{
  "type": "Feature",
  "properties": {
    "iso:country":"DE",
    "sg:address":"Hugo-Viehoff-Str. 80",
    "sg:city":"D\u00fcsseldorf",
    "sg:phone":"+49 211/437731",
    "sg:postcode":"40468",
    "sg:province":"Nordrhein-Westfalen",
    "wof:name":"Katholisches Pfarramt St. Lukas",
    "wof:placetype":"venue"
},
  "geometry": {"coordinates":[6.7793450356,51.2565536499],"type":"Point"}
}