{
  "type": "Feature",
  "properties": {
    "iso:country":"DE",
    "sg:address":"Lindenthal 3",
    "sg:city":"Murnau",
    "sg:phone":"+49 8841/3987",
    "sg:postcode":"82418",
    "sg:province":"Bayern",
    "wof:name":"E. Kammerlocher",
    "wof:placetype":"venue"
},
  "geometry": {"coordinates":[11.205669,47.686268],"type":"Point"}
}