{
  "type": "Feature",
  "properties": {
    "iso:country":"DE",
    "sg:address":"Bahnhofstr. 7",
    "sg:city":"Schk\u00f6len",
    "sg:postcode":"07619",
    "sg:province":"Th\u00fcringen",
    "wof:name":"Bahnhofsgastst\u00e4tte",
    "wof:placetype":"venue"
},
  "geometry": {"coordinates":[11.823925972,51.0458106995],"type":"Point"}
}