{
  "type": "Feature",
  "properties": {
    "iso:country":"DE",
    "sg:address":"Stedinger Str. 246",
    "sg:city":"Delmenhorst",
    "sg:phone":"+49 4221/49900",
    "sg:postcode":"27753",
    "sg:province":"Niedersachsen",
    "wof:name":"G\u00fcnter Hedenkamp",
    "wof:placetype":"venue"
},
  "geometry": {"coordinates":[8.6402587891,53.0724601746],"type":"Point"}
}