{
  "type": "Feature",
  "properties": {
    "iso:country":"DE",
    "sg:address":"Am Markt 11",
    "sg:city":"Schwerte",
    "sg:postcode":"58239",
    "sg:province":"Nordrhein-Westfalen",
    "wof:name":"Mode Maximal Inh. Doris Hacheney",
    "wof:placetype":"venue"
},
  "geometry": {"coordinates":[7.56912,51.43977],"type":"Point"}
}