{
  "type": "Feature",
  "properties": {
    "iso:country":"DE",
    "sg:address":"Brunnenstr. 21",
    "sg:city":"Baldham",
    "sg:phone":"+49 8106/8652",
    "sg:postcode":"85598",
    "sg:province":"Bayern",
    "wof:name":"Max Lampert",
    "wof:placetype":"venue"
},
  "geometry": {"coordinates":[11.792847,48.096149],"type":"Point"}
}