{
  "type": "Feature",
  "properties": {
    "iso:country":"DE",
    "sg:address":"Im Holtkamp 78",
    "sg:city":"Duisburg",
    "sg:phone":"+49 203/593397",
    "sg:postcode":"47167",
    "sg:province":"Nordrhein-Westfalen",
    "wof:name":"Alfred Petri Gmbh",
    "wof:placetype":"venue"
},
  "geometry": {"coordinates":[6.777286,51.504013],"type":"Point"}
}