{
  "type": "Feature",
  "properties": {
    "iso:country":"DE",
    "sg:address":"Hohenhorst 67 a",
    "sg:city":"Altenberge",
    "sg:phone":"+49 2505/3433",
    "sg:postcode":"48341",
    "sg:province":"Nordrhein-Westfalen",
    "wof:name":"Heinze Planungen Gmbh",
    "wof:placetype":"venue"
},
  "geometry": {"coordinates":[7.498472,52.037533],"type":"Point"}
}