{
  "type": "Feature",
  "properties": {
    "iso:country":"DE",
    "sg:address":"Billerbecker Weg 94",
    "sg:city":"Berlin",
    "sg:phone":"+49 30/4326794",
    "sg:postcode":"13507",
    "sg:province":"Berlin",
    "wof:name":"Pizzeria Tartufo",
    "wof:placetype":"venue"
},
  "geometry": {"coordinates":[13.2782669067,52.5745697021],"type":"Point"}
}