{
  "type": "Feature",
  "properties": {
    "iso:country":"DE",
    "sg:address":"Grassauer Str. 2",
    "sg:city":"Grassau",
    "sg:phone":"+49 8641/2338",
    "sg:postcode":"83224",
    "sg:province":"Bayern",
    "wof:name":"Gnadl & Erb",
    "wof:placetype":"venue"
},
  "geometry": {"coordinates":[12.453502655,47.7673912048],"type":"Point"}
}