{
  "type": "Feature",
  "properties": {
    "iso:country":"DE",
    "sg:address":"Parkhofstr. 120",
    "sg:city":"H\u00fcckelhoven",
    "sg:phone":"+49 2433/86565",
    "sg:postcode":"41836",
    "sg:province":"Nordrhein-Westfalen",
    "wof:name":"Barbara-klause",
    "wof:placetype":"venue"
},
  "geometry": {"coordinates":[6.2216949463,51.056728363],"type":"Point"}
}