{
  "type": "Feature",
  "properties": {
    "iso:country":"DE",
    "sg:address":"Siemensring 18",
    "sg:city":"Willich",
    "sg:postcode":"47877",
    "sg:province":"Nordrhein-Westfalen",
    "wof:name":"United Parcel Service Deutschland Inc.",
    "wof:placetype":"venue"
},
  "geometry": {"coordinates":[6.5163068771,51.26770401],"type":"Point"}
}