{
  "type": "Feature",
  "properties": {
    "iso:country":"DE",
    "sg:address":"Gutenbergstr 4",
    "sg:city":"Ansbach",
    "sg:phone":"+49 981/95090",
    "sg:postcode":"91522",
    "sg:province":"Bayern",
    "wof:name":"Spit-impex Itw Befestigungssysteme Gmbh",
    "wof:placetype":"venue"
},
  "geometry": {"coordinates":[10.560606,49.301052],"type":"Point"}
}