{
  "type": "Feature",
  "properties": {
    "iso:country":"DE",
    "sg:address":"Waldstr. 30",
    "sg:city":"Gundelfingen",
    "sg:phone":"+49 761/580446",
    "sg:postcode":"79194",
    "sg:province":"Baden-W\u00fcrttemberg",
    "wof:name":"Reinhold Schneider",
    "wof:placetype":"venue"
},
  "geometry": {"coordinates":[7.87784,48.04388],"type":"Point"}
}