{
  "type": "Feature",
  "properties": {
    "iso:country":"DE",
    "sg:address":"Harschbacher Str. 9",
    "sg:city":"Raubach",
    "sg:phone":"+49 2684/5392",
    "sg:postcode":"56316",
    "sg:province":"Rheinland-Pfalz",
    "wof:name":"Ewald Marth",
    "wof:placetype":"venue"
},
  "geometry": {"coordinates":[7.6249098778,50.5751304626],"type":"Point"}
}