{
  "type": "Feature",
  "properties": {
    "iso:country":"DE",
    "sg:address":"R\u00fcsterweg 5",
    "sg:city":"Aschaffenburg",
    "sg:phone":"+49 6021/88580",
    "sg:postcode":"63741",
    "sg:province":"Bayern",
    "wof:name":"Fs Fernsprech Systeme Gmbh",
    "wof:placetype":"venue"
},
  "geometry": {"coordinates":[9.1221246719,49.9626312256],"type":"Point"}
}