{
  "type": "Feature",
  "properties": {
    "iso:country":"DE",
    "sg:address":"Im Rosengarten 4",
    "sg:city":"Schopfheim",
    "sg:phone":"+49 7622/668177",
    "sg:postcode":"79650",
    "sg:province":"Baden-W\u00fcrttemberg",
    "wof:name":"Dystar-textilfarben Gmbh",
    "wof:placetype":"venue"
},
  "geometry": {"coordinates":[7.8376698494,47.655040741],"type":"Point"}
}