{
  "type": "Feature",
  "properties": {
    "iso:country":"DE",
    "sg:address":"Buchenstr. 2",
    "sg:city":"G\u00f6ppingen",
    "sg:phone":"+49 7161/923965",
    "sg:postcode":"73035",
    "sg:province":"Baden-W\u00fcrttemberg",
    "wof:name":"Christine Puhane",
    "wof:placetype":"venue"
},
  "geometry": {"coordinates":[9.612487793,48.7145309448],"type":"Point"}
}