{
  "type": "Feature",
  "properties": {
    "iso:country":"DE",
    "sg:address":"Horber Str. 13",
    "sg:city":"Rottenburg",
    "sg:phone":"+49 7457/1353",
    "sg:postcode":"72108",
    "sg:province":"Baden-W\u00fcrttemberg",
    "wof:name":"Josef Baur",
    "wof:placetype":"venue"
},
  "geometry": {"coordinates":[8.932848,48.440033],"type":"Point"}
}