{
  "type": "Feature",
  "properties": {
    "iso:country":"DE",
    "sg:city":"Helsa",
    "sg:phone":"+49 5604/8785",
    "sg:postcode":"34298",
    "sg:province":"Hessen",
    "wof:name":"Pfb H\u00f6ller-bau Gmbh",
    "wof:placetype":"venue"
},
  "geometry": {"coordinates":[9.68787,51.257633],"type":"Point"}
}