{
  "type": "Feature",
  "properties": {
    "iso:country":"DE",
    "sg:address":"Schulzenweg 24",
    "sg:city":"Schwerin",
    "sg:phone":"+49 385/644000",
    "sg:postcode":"19061",
    "sg:province":"Mecklenburg-Vorpommern",
    "wof:name":"Schwarz & Grantz Beteiligungs- Gmbh",
    "wof:placetype":"venue"
},
  "geometry": {"coordinates":[11.39028,53.60651],"type":"Point"}
}