{
  "type": "Feature",
  "properties": {
    "iso:country":"DE",
    "sg:address":"Auf dem Bruch 70",
    "sg:city":"M\u00fclheim",
    "sg:phone":"+49 208/35021",
    "sg:postcode":"45475",
    "sg:province":"Nordrhein-Westfalen",
    "wof:name":"Alteneinrichtung Der Stadt M\u00fchlheim An Der Ruhr",
    "wof:placetype":"venue"
},
  "geometry": {"coordinates":[6.892853,51.464119],"type":"Point"}
}