{
  "type": "Feature",
  "properties": {
    "iso:country":"DE",
    "sg:address":"M\u00fchlheide 14",
    "sg:city":"Stemwede",
    "sg:postcode":"32351",
    "sg:province":"Nordrhein-Westfalen",
    "wof:name":"M\u00fchlenheider Energie- Anlagen Gmbh",
    "wof:placetype":"venue"
},
  "geometry": {"coordinates":[8.501637,52.450062],"type":"Point"}
}