{
  "type": "Feature",
  "properties": {
    "iso:country":"DE",
    "sg:address":"Hohenh\u00f6veler Str. 28",
    "sg:city":"Hamm",
    "sg:phone":"+49 2381/789711",
    "sg:postcode":"59075",
    "sg:province":"Nordrhein-Westfalen",
    "wof:name":"K. Bulhardt-radowsky",
    "wof:placetype":"venue"
},
  "geometry": {"coordinates":[7.7624912262,51.6963119507],"type":"Point"}
}