{
  "type": "Feature",
  "properties": {
    "iso:country":"DE",
    "sg:address":"Schiffbr\u00fcckstr. 3",
    "sg:city":"Flensburg",
    "sg:phone":"+49 461/17430",
    "sg:postcode":"24937",
    "sg:province":"Schleswig-Holstein",
    "wof:name":"Heino Zierk Masseur",
    "wof:placetype":"venue"
},
  "geometry": {"coordinates":[9.433675,54.789467],"type":"Point"}
}