{
  "type": "Feature",
  "properties": {
    "iso:country":"DE",
    "sg:address":"Gartenstr. 31",
    "sg:city":"Limburg",
    "sg:phone":"+49 6431/45239",
    "sg:postcode":"65549",
    "sg:province":"Hessen",
    "wof:name":"F & S Fleckner & Simon Informationstechnik Gmbh",
    "wof:placetype":"venue"
},
  "geometry": {"coordinates":[8.069393158,50.3814735413],"type":"Point"}
}