{
  "type": "Feature",
  "properties": {
    "iso:country":"DE",
    "sg:address":"Heimhuder Str. 81",
    "sg:city":"Hamburg",
    "sg:phone":"+49 40/4502470",
    "sg:postcode":"20148",
    "sg:province":"Hamburg",
    "wof:name":"F & P Marketingforschung Gmbh",
    "wof:placetype":"venue"
},
  "geometry": {"coordinates":[9.992688,53.570335],"type":"Point"}
}