{
  "type": "Feature",
  "properties": {
    "iso:country":"DE",
    "sg:address":"Koblenzer Str. 47",
    "sg:city":"Kaisersesch",
    "sg:phone":"+49 2653/99850",
    "sg:postcode":"56759",
    "sg:province":"Rheinland-Pfalz",
    "wof:name":"Adler-apotheke Johannes Hanhart",
    "wof:placetype":"venue"
},
  "geometry": {"coordinates":[7.141123,50.230358],"type":"Point"}
}