{
  "type": "Feature",
  "properties": {
    "iso:country":"DE",
    "sg:address":"Neue Burgkemnitzer Str. 20",
    "sg:city":"Muldenstein",
    "sg:phone":"+49 3493/56759",
    "sg:postcode":"06804",
    "sg:province":"Sachsen-Anhalt",
    "wof:name":"A. Reinisch",
    "wof:placetype":"venue"
},
  "geometry": {"coordinates":[12.345395,51.671429],"type":"Point"}
}