{
  "type": "Feature",
  "properties": {
    "iso:country":"DE",
    "sg:address":"Auf dem Reuterhamm 11",
    "sg:city":"Bremerhaven",
    "sg:phone":"+49 471/952510",
    "sg:postcode":"27576",
    "sg:province":"Bremen",
    "wof:name":"Heinrich Stender Gmbh & Co.",
    "wof:placetype":"venue"
},
  "geometry": {"coordinates":[8.595744,53.556854],"type":"Point"}
}