{
  "type": "Feature",
  "properties": {
    "iso:country":"DE",
    "sg:address":"Bennostr. 13",
    "sg:city":"Radebeul",
    "sg:phone":"+49 351/8301374",
    "sg:postcode":"01445",
    "sg:province":"Sachsen",
    "wof:name":"Werner Vetters",
    "wof:placetype":"venue"
},
  "geometry": {"coordinates":[13.66593,51.109169],"type":"Point"}
}