{
  "type": "Feature",
  "properties": {
    "iso:country":"DE",
    "sg:address":"Wilhelm-Pieck-Str. 1",
    "sg:city":"Bernburg",
    "sg:postcode":"06406",
    "sg:province":"Sachsen-Anhalt",
    "wof:name":"Buchhandlung Brendel Inh. Otto Brendel",
    "wof:placetype":"venue"
},
  "geometry": {"coordinates":[11.73456,51.793259],"type":"Point"}
}