{
  "type": "Feature",
  "properties": {
    "iso:country":"DE",
    "sg:address":"Augustastr. 4",
    "sg:city":"Hamburg",
    "sg:phone":"+49 40/7242429",
    "sg:postcode":"21029",
    "sg:province":"Hamburg",
    "wof:name":"Schwarz & Schott",
    "wof:placetype":"venue"
},
  "geometry": {"coordinates":[10.2161073685,53.4907684326],"type":"Point"}
}