{
  "type": "Feature",
  "properties": {
    "iso:country":"DE",
    "sg:address":"Uerdinger Str. 306",
    "sg:city":"Krefeld",
    "sg:phone":"+49 2151/597695",
    "sg:postcode":"47800",
    "sg:province":"Nordrhein-Westfalen",
    "wof:name":"Tiergarten-apotheke",
    "wof:placetype":"venue"
},
  "geometry": {"coordinates":[6.593637,51.340206],"type":"Point"}
}