{
  "type": "Feature",
  "properties": {
    "iso:country":"DE",
    "sg:address":"Heideweg 41a",
    "sg:city":"L\u00fctjensee",
    "sg:postcode":"22952",
    "sg:province":"Schleswig-Holstein",
    "wof:name":"A. Von Samson-himmelstjerna",
    "wof:placetype":"venue"
},
  "geometry": {"coordinates":[10.3688497543,53.6380844116],"type":"Point"}
}