{
  "type": "Feature",
  "properties": {
    "iso:country":"DE",
    "sg:address":"Marktstr. 44",
    "sg:city":"St. Leon-Rot",
    "sg:phone":"+49 6227/51374",
    "sg:postcode":"68789",
    "sg:province":"Baden-W\u00fcrttemberg",
    "wof:name":"Margot Leichmann",
    "wof:placetype":"venue"
},
  "geometry": {"coordinates":[8.600915,49.266838],"type":"Point"}
}