{
  "type": "Feature",
  "properties": {
    "iso:country":"DE",
    "sg:address":"Postweg 1",
    "sg:city":"Kerken",
    "sg:phone":"+49 2833/2281",
    "sg:postcode":"47647",
    "sg:province":"Nordrhein-Westfalen",
    "wof:name":"Hermann Kleinkuhnen",
    "wof:placetype":"venue"
},
  "geometry": {"coordinates":[6.3700480461,51.4567871094],"type":"Point"}
}