{
  "type": "Feature",
  "properties": {
    "iso:country":"DE",
    "sg:address":"Am Westendorp 10",
    "sg:city":"Olfen",
    "sg:phone":"+49 2595/5560",
    "sg:postcode":"59399",
    "sg:province":"Nordrhein-Westfalen",
    "wof:name":"Fliesen B\u00fcrgel Gmbh",
    "wof:placetype":"venue"
},
  "geometry": {"coordinates":[7.3753209114,51.7098617554],"type":"Point"}
}