{
  "type": "Feature",
  "properties": {
    "iso:country":"DE",
    "sg:address":"Alte K\u00f6lner Str. 20",
    "sg:city":"R\u00f6srath",
    "sg:phone":"+49 2205/3924",
    "sg:postcode":"51503",
    "sg:province":"Nordrhein-Westfalen",
    "wof:name":"Kurt Otto Architekt",
    "wof:placetype":"venue"
},
  "geometry": {"coordinates":[7.147991,50.90815],"type":"Point"}
}