{
  "type": "Feature",
  "properties": {
    "iso:country":"DE",
    "sg:address":"Frankfurter Str. 45a",
    "sg:city":"Gelnhausen",
    "sg:phone":"+49 6051/889339",
    "sg:postcode":"63571",
    "sg:province":"Hessen",
    "wof:name":"Etv Gmbh",
    "wof:placetype":"venue"
},
  "geometry": {"coordinates":[9.17953,50.20488],"type":"Point"}
}