{
  "type": "Feature",
  "properties": {
    "iso:country":"DE",
    "sg:address":"M\u00fchlenstr. 12",
    "sg:city":"Melle",
    "sg:phone":"+49 5422/49742",
    "sg:postcode":"49324",
    "sg:province":"Niedersachsen",
    "wof:name":"R. P\u00f6sse",
    "wof:placetype":"venue"
},
  "geometry": {"coordinates":[8.338841,52.203075],"type":"Point"}
}