{
  "type": "Feature",
  "properties": {
    "iso:country":"DE",
    "sg:address":"Dr.-D\u00fcrr-Str. 12",
    "sg:city":"Wildeshausen",
    "sg:postcode":"27793",
    "sg:province":"Niedersachsen",
    "wof:name":"Aldi Gmbh & Co. Kg",
    "wof:placetype":"venue"
},
  "geometry": {"coordinates":[8.4177598953,52.8981361389],"type":"Point"}
}