{
  "type": "Feature",
  "properties": {
    "iso:country":"DE",
    "sg:address":"Postfach 5621",
    "sg:city":"Wiesbaden",
    "sg:postcode":"65046",
    "sg:province":"Hessen",
    "wof:name":"Dieter Todte Steinbruch",
    "wof:placetype":"venue"
},
  "geometry": {"coordinates":[8.2383804321,50.0840682983],"type":"Point"}
}