{
  "type": "Feature",
  "properties": {
    "iso:country":"DE",
    "sg:address":"Im Gr\u00fcndchen 7",
    "sg:city":"Bessenbach",
    "sg:phone":"+49 6095/2608",
    "sg:postcode":"63856",
    "sg:province":"Bayern",
    "wof:name":"Roth-bau Gmbh",
    "wof:placetype":"venue"
},
  "geometry": {"coordinates":[9.250689,49.983006],"type":"Point"}
}