{
  "type": "Feature",
  "properties": {
    "iso:country":"DE",
    "sg:address":"Zeintlm\u00fchle 1",
    "sg:city":"Ruhstorf",
    "sg:postcode":"94099",
    "sg:province":"Bayern",
    "wof:name":"Holz H\u00f6sl Gmbh & Co. Kg",
    "wof:placetype":"venue"
},
  "geometry": {"coordinates":[13.3885812759,48.4530944824],"type":"Point"}
}