{
  "type": "Feature",
  "properties": {
    "iso:country":"DE",
    "sg:address":"S\u00fcdstr. 19",
    "sg:city":"Frauenwald",
    "sg:phone":"+49 36782/61833",
    "sg:postcode":"98711",
    "sg:province":"Th\u00fcringen",
    "wof:name":"Willy Spindler",
    "wof:placetype":"venue"
},
  "geometry": {"coordinates":[10.8595237732,50.5807914734],"type":"Point"}
}