{
  "type": "Feature",
  "properties": {
    "iso:country":"DE",
    "sg:address":"Ludwigstr. 23",
    "sg:city":"M\u00fcnchen",
    "sg:phone":"+49 89/282064",
    "sg:postcode":"80539",
    "sg:province":"Bayern",
    "wof:name":"Redaktion Sch\u00f6nere Heimat Verlag Sch\u00f6nere Heimat",
    "wof:placetype":"venue"
},
  "geometry": {"coordinates":[11.5798339844,48.1479034424],"type":"Point"}
}