{
  "type": "Feature",
  "properties": {
    "iso:country":"DE",
    "sg:address":"Boschetsrieder Str. 51a",
    "sg:city":"M\u00fcnchen",
    "sg:phone":"+49 89/7849910",
    "sg:postcode":"81379",
    "sg:province":"Bayern",
    "wof:name":"Alexandra Feine Architektin",
    "wof:placetype":"venue"
},
  "geometry": {"coordinates":[11.532216,48.0998],"type":"Point"}
}