{
  "type": "Feature",
  "properties": {
    "iso:country":"DE",
    "sg:address":"Niederstr. 2",
    "sg:city":"Trier",
    "sg:phone":"+49 651/630150",
    "sg:postcode":"54293",
    "sg:province":"Rheinland-Pfalz",
    "wof:name":"Bistro",
    "wof:placetype":"venue"
},
  "geometry": {"coordinates":[6.6852288246,49.8099365234],"type":"Point"}
}