{
  "type": "Feature",
  "properties": {
    "iso:country":"DE",
    "sg:address":"Senner Str. 77",
    "sg:city":"Bielefeld",
    "sg:phone":"+49 521/411949",
    "sg:postcode":"33647",
    "sg:province":"Nordrhein-Westfalen",
    "wof:name":"Meteora",
    "wof:placetype":"venue"
},
  "geometry": {"coordinates":[8.5095243454,51.9785842896],"type":"Point"}
}