{
  "type": "Feature",
  "properties": {
    "iso:country":"DE",
    "sg:address":"K\u00fchlweinstr. 103",
    "sg:city":"V\u00f6lklingen",
    "sg:phone":"+49 6898/170",
    "sg:postcode":"66333",
    "sg:province":"Saarland",
    "wof:name":"Kath. Krankenhausb\u00fccherei St. Michael-krankenhaus",
    "wof:placetype":"venue"
},
  "geometry": {"coordinates":[6.855899,49.261234],"type":"Point"}
}