{
  "type": "Feature",
  "properties": {
    "iso:country":"DE",
    "sg:address":"Schulstr. 1",
    "sg:city":"Garbsen",
    "sg:phone":"+49 5137/70156",
    "sg:postcode":"30823",
    "sg:province":"Niedersachsen",
    "wof:name":"Horst K\u00f6hne",
    "wof:placetype":"venue"
},
  "geometry": {"coordinates":[9.6095504761,52.4070549011],"type":"Point"}
}