{
  "type": "Feature",
  "properties": {
    "iso:country":"DE",
    "sg:address":"Heerstr. 112",
    "sg:city":"Runkel",
    "sg:phone":"+49 6482/918100",
    "sg:postcode":"65594",
    "sg:province":"Hessen",
    "wof:name":"Hedler Systemlicht Gmbh",
    "wof:placetype":"venue"
},
  "geometry": {"coordinates":[8.137859,50.403858],"type":"Point"}
}