{
  "type": "Feature",
  "properties": {
    "iso:country":"DE",
    "sg:address":"Sch\u00f6ttlestr. 34 c",
    "sg:city":"Stuttgart",
    "sg:phone":"+49 711/766003",
    "sg:postcode":"70597",
    "sg:province":"Baden-W\u00fcrttemberg",
    "wof:name":"Dr. Scholz Und Partner Wirtschaftsp\u00fcfungs- Steuer-",
    "wof:placetype":"venue"
},
  "geometry": {"coordinates":[9.1612462997,48.7442626953],"type":"Point"}
}