{
  "type": "Feature",
  "properties": {
    "iso:country":"DE",
    "sg:address":"Mindener Str. 78",
    "sg:city":"Herford",
    "sg:phone":"+49 5221/23494",
    "sg:postcode":"32049",
    "sg:province":"Nordrhein-Westfalen",
    "wof:name":"S. Y\u00fczbasi",
    "wof:placetype":"venue"
},
  "geometry": {"coordinates":[8.6836967468,52.1248054504],"type":"Point"}
}