{
  "type": "Feature",
  "properties": {
    "iso:country":"DE",
    "sg:address":"Widderstr. 51",
    "sg:city":"Augsburg",
    "sg:phone":"+49 821/715691",
    "sg:postcode":"86167",
    "sg:province":"Bayern",
    "wof:name":"Friedrich Wei\u00dfbeck",
    "wof:placetype":"venue"
},
  "geometry": {"coordinates":[10.916413,48.384819],"type":"Point"}
}