{
  "type": "Feature",
  "properties": {
    "iso:country":"DE",
    "sg:address":"Am Marstall 2",
    "sg:city":"Hannover",
    "sg:phone":"+49 511/363925",
    "sg:postcode":"30159",
    "sg:province":"Niedersachsen",
    "wof:name":"J\u00fcrgen Dohrau Steuerberatungsges. Mbh",
    "wof:placetype":"venue"
},
  "geometry": {"coordinates":[9.7332334518,52.3747177124],"type":"Point"}
}