{
  "type": "Feature",
  "properties": {
    "iso:country":"DE",
    "sg:address":"Schramberger Str. 24",
    "sg:city":"Rottweil",
    "sg:phone":"+49 741/7653",
    "sg:postcode":"78628",
    "sg:province":"Baden-W\u00fcrttemberg",
    "wof:name":"Hacon Electronic Vertriebs-gmbh",
    "wof:placetype":"venue"
},
  "geometry": {"coordinates":[8.6201839447,48.164642334],"type":"Point"}
}