{
  "type": "Feature",
  "properties": {
    "iso:country":"DE",
    "sg:address":"Heerstr. 18",
    "sg:city":"Berlin",
    "sg:postcode":"14052",
    "sg:province":"Berlin",
    "wof:name":"Hansa-beteiligungs- Und Besitzgesellschaft Mbh",
    "wof:placetype":"venue"
},
  "geometry": {"coordinates":[13.265879,52.5093],"type":"Point"}
}