{
  "type": "Feature",
  "properties": {
    "iso:country":"DE",
    "sg:address":"Lange Str. 3",
    "sg:city":"Ganderkesee",
    "sg:phone":"+49 4222/2055",
    "sg:postcode":"27777",
    "sg:province":"Niedersachsen",
    "wof:name":"Johann Fink Inh. J\u00f6rg Schmager",
    "wof:placetype":"venue"
},
  "geometry": {"coordinates":[8.548829,53.031971],"type":"Point"}
}