{
  "type": "Feature",
  "properties": {
    "iso:country":"DE",
    "sg:address":"Wilhelmstr. 7",
    "sg:city":"M\u00fcnchberg",
    "sg:phone":"+49 9251/92033",
    "sg:postcode":"95213",
    "sg:province":"Bayern",
    "wof:name":"Ladys",
    "wof:placetype":"venue"
},
  "geometry": {"coordinates":[11.79375,50.188091],"type":"Point"}
}