{
  "type": "Feature",
  "properties": {
    "iso:country":"DE",
    "sg:address":"Rauher Stich 2",
    "sg:city":"Talheim",
    "sg:phone":"+49 7133/5788",
    "sg:postcode":"74388",
    "sg:province":"Baden-W\u00fcrttemberg",
    "wof:name":"Friedrich Gro\u00df",
    "wof:placetype":"venue"
},
  "geometry": {"coordinates":[9.1950082779,49.084487915],"type":"Point"}
}