{
  "type": "Feature",
  "properties": {
    "iso:country":"DE",
    "sg:address":"Kaysersbergstr. 17",
    "sg:city":"Landau",
    "sg:phone":"+49 6341/32586",
    "sg:postcode":"76829",
    "sg:province":"Rheinland-Pfalz",
    "wof:name":"Unique Edv Marketing Gmbh",
    "wof:placetype":"venue"
},
  "geometry": {"coordinates":[8.0922660828,49.1896972656],"type":"Point"}
}