{
  "type": "Feature",
  "properties": {
    "iso:country":"DE",
    "sg:address":"Althofstr. 1 a",
    "sg:city":"M\u00fclheim",
    "sg:phone":"+49 208/380653",
    "sg:postcode":"45468",
    "sg:province":"Nordrhein-Westfalen",
    "wof:name":"Ev. Pfarramt Petrikirche",
    "wof:placetype":"venue"
},
  "geometry": {"coordinates":[6.8838100433,51.4265403748],"type":"Point"}
}