{
  "type": "Feature",
  "properties": {
    "iso:country":"DE",
    "sg:address":"S\u00f6hrestr. 10",
    "sg:city":"Guxhagen",
    "sg:phone":"+49 5665/2393",
    "sg:postcode":"34302",
    "sg:province":"Hessen",
    "wof:name":"Heinrich Reinbold",
    "wof:placetype":"venue"
},
  "geometry": {"coordinates":[9.5110168457,51.2048072815],"type":"Point"}
}