{
  "type": "Feature",
  "properties": {
    "iso:country":"DE",
    "sg:address":"Karlstr. 52",
    "sg:city":"Lauffen",
    "sg:phone":"+49 7133/16923",
    "sg:postcode":"74348",
    "sg:province":"Baden-W\u00fcrttemberg",
    "wof:name":"Karl-heinz Kirchner Finanzberater",
    "wof:placetype":"venue"
},
  "geometry": {"coordinates":[9.1483840942,49.0719528198],"type":"Point"}
}