{
  "type": "Feature",
  "properties": {
    "iso:country":"DE",
    "sg:address":"Frankenthaler Str. 2",
    "sg:city":"He\u00dfheim",
    "sg:phone":"+49 6233/71829",
    "sg:postcode":"67258",
    "sg:province":"Rheinland-Pfalz",
    "wof:name":"M. Meyer Und H. Prohaska Modewaren",
    "wof:placetype":"venue"
},
  "geometry": {"coordinates":[8.310051,49.553738],"type":"Point"}
}