{
  "type": "Feature",
  "properties": {
    "iso:country":"DE",
    "sg:address":"Stieffring 8",
    "sg:city":"Berlin",
    "sg:phone":"+49 30/3443093",
    "sg:postcode":"13627",
    "sg:province":"Berlin",
    "wof:name":"M. Und P. Schr\u00f6der Gmbh",
    "wof:placetype":"venue"
},
  "geometry": {"coordinates":[13.314027,52.545662],"type":"Point"}
}