{
  "type": "Feature",
  "properties": {
    "iso:country":"DE",
    "sg:address":"Am \u00d6lbachgraben 14",
    "sg:city":"Wittlingen",
    "sg:phone":"+49 7621/163421",
    "sg:postcode":"79599",
    "sg:province":"Baden-W\u00fcrttemberg",
    "wof:name":"Textilscout24.de - Warum Woanders Mehr Bezahlen ?",
    "wof:placetype":"venue"
},
  "geometry": {"coordinates":[7.650739,47.652973],"type":"Point"}
}