{
  "type": "Feature",
  "properties": {
    "iso:country":"DE",
    "sg:address":"Am Rebstock 4",
    "sg:city":"Gro\u00dfkugel",
    "sg:phone":"+49 34605",
    "sg:postcode":"06184",
    "sg:province":"Sachsen-Anhalt",
    "wof:name":"Subunternehmer",
    "wof:placetype":"venue"
},
  "geometry": {"coordinates":[12.1539649963,51.4175186157],"type":"Point"}
}