{
  "type": "Feature",
  "properties": {
    "iso:country":"DE",
    "sg:address":"In der M\u00f6rschgewanne 12",
    "sg:city":"Ludwigshafen",
    "sg:postcode":"67065",
    "sg:province":"Rheinland-Pfalz",
    "wof:name":"J\u00fcreg Schneider Gmbh",
    "wof:placetype":"venue"
},
  "geometry": {"coordinates":[8.4222297668,49.4515228271],"type":"Point"}
}