{
  "type": "Feature",
  "properties": {
    "iso:country":"DE",
    "sg:address":"Ostpreu\u00dfenring 45",
    "sg:city":"Schwetzingen",
    "sg:phone":"+49 6202/857614",
    "sg:postcode":"68723",
    "sg:province":"Baden-W\u00fcrttemberg",
    "wof:name":"N. Ersoy \u00dcbersetzungsb\u00fcro",
    "wof:placetype":"venue"
},
  "geometry": {"coordinates":[8.569423,49.395756],"type":"Point"}
}