{
  "type": "Feature",
  "properties": {
    "iso:country":"DE",
    "sg:address":"Grund 63",
    "sg:city":"Johannisberg",
    "sg:phone":"+49 6722/8216",
    "sg:postcode":"65366",
    "sg:province":"Hessen",
    "wof:name":"Weingut Johannishof",
    "wof:placetype":"venue"
},
  "geometry": {"coordinates":[7.97756,49.99966],"type":"Point"}
}