{
  "type": "Feature",
  "properties": {
    "iso:country":"DE",
    "sg:address":"D\u00fcrerstr. 14",
    "sg:city":"W\u00fcrzburg",
    "sg:phone":"+49 931/322310",
    "sg:postcode":"97072",
    "sg:province":"Bayern",
    "wof:name":"Wuekro-electronic Gmbh & Co. Kg",
    "wof:placetype":"venue"
},
  "geometry": {"coordinates":[9.946637,49.790588],"type":"Point"}
}