{
  "type": "Feature",
  "properties": {
    "iso:country":"DE",
    "sg:address":"Triberger Str. 18",
    "sg:city":"Stuttgart",
    "sg:phone":"+49 711/6770238",
    "sg:postcode":"70569",
    "sg:province":"Baden-W\u00fcrttemberg",
    "wof:name":"Die H\u00fctte",
    "wof:placetype":"venue"
},
  "geometry": {"coordinates":[9.1374797821,48.7395973206],"type":"Point"}
}