{
  "type": "Feature",
  "properties": {
    "iso:country":"DE",
    "sg:address":"Martin-Luther-Str. 73",
    "sg:city":"Berlin",
    "sg:postcode":"13467",
    "sg:province":"Berlin",
    "wof:name":"Aldi Gmbh & Co. Kg",
    "wof:placetype":"venue"
},
  "geometry": {"coordinates":[13.3009300232,52.6141014099],"type":"Point"}
}