{
  "type": "Feature",
  "properties": {
    "iso:country":"DE",
    "sg:address":"Wittenburger Str. 1",
    "sg:city":"Renzow",
    "sg:phone":"+49 38874/22049",
    "sg:postcode":"19209",
    "sg:province":"Mecklenburg-Vorpommern",
    "wof:name":"Helms Ger\u00e4tebau Gmbh",
    "wof:placetype":"venue"
},
  "geometry": {"coordinates":[11.159883,53.631351],"type":"Point"}
}