{
  "type": "Feature",
  "properties": {
    "iso:country":"DE",
    "sg:address":"Gartenfelder Str. 109",
    "sg:city":"Berlin",
    "sg:phone":"+49 30/3342367",
    "sg:postcode":"13599",
    "sg:province":"Berlin",
    "wof:name":"Haselhorster Apotheke",
    "wof:placetype":"venue"
},
  "geometry": {"coordinates":[13.239589,52.542706],"type":"Point"}
}