{
  "type": "Feature",
  "properties": {
    "iso:country":"DE",
    "sg:address":"Hohewardstr. 338 a",
    "sg:city":"Herten",
    "sg:phone":"+49 2366/37469",
    "sg:postcode":"45699",
    "sg:province":"Nordrhein-Westfalen",
    "wof:name":"Tischlerei Bernd K\u00fcchenhoff E. K.",
    "wof:placetype":"venue"
},
  "geometry": {"coordinates":[7.158336,51.557713],"type":"Point"}
}