{
  "type": "Feature",
  "properties": {
    "iso:country":"DE",
    "sg:address":"Axenhofen 1",
    "sg:city":"Mainburg",
    "sg:postcode":"84048",
    "sg:province":"Bayern",
    "wof:name":"Thomas Reitmeier",
    "wof:placetype":"venue"
},
  "geometry": {"coordinates":[11.788204,48.661133],"type":"Point"}
}