{
  "type": "Feature",
  "properties": {
    "iso:country":"DE",
    "sg:address":"Wiesener Str. 94",
    "sg:city":"Frammersbach",
    "sg:phone":"+49 9355/359",
    "sg:postcode":"97833",
    "sg:province":"Bayern",
    "wof:name":"Manfred Schleissinger Gmbh",
    "wof:placetype":"venue"
},
  "geometry": {"coordinates":[9.460272,50.062256],"type":"Point"}
}