{
  "type": "Feature",
  "properties": {
    "iso:country":"DE",
    "sg:address":"Grobestr. 12",
    "sg:city":"Saalfeld",
    "sg:postcode":"07318",
    "sg:province":"Th\u00fcringen",
    "wof:name":"Polytronik Gmbh",
    "wof:placetype":"venue"
},
  "geometry": {"coordinates":[11.3554153442,50.6422080994],"type":"Point"}
}