{
  "type": "Feature",
  "properties": {
    "iso:country":"DE",
    "sg:address":"M\u00fchlenflur 20",
    "sg:city":"Zerf",
    "sg:phone":"+49 6587/7064",
    "sg:postcode":"54314",
    "sg:province":"Rheinland-Pfalz",
    "wof:name":"International Trade Agency Kurt Rommelfanger Gmbh",
    "wof:placetype":"venue"
},
  "geometry": {"coordinates":[6.6910319328,49.6056671143],"type":"Point"}
}