{
  "type": "Feature",
  "properties": {
    "iso:country":"DE",
    "sg:address":"Franz-Gr\u00f6tz-Str. 12",
    "sg:city":"Gaggenau",
    "sg:phone":"+49 7225/72175",
    "sg:postcode":"76571",
    "sg:province":"Baden-W\u00fcrttemberg",
    "wof:name":"Hdw Bautr\u00e4ger Gmbh",
    "wof:placetype":"venue"
},
  "geometry": {"coordinates":[8.3214731216,48.8010063171],"type":"Point"}
}