{
  "type": "Feature",
  "properties": {
    "iso:country":"DE",
    "sg:address":"Kurf\u00fcrstenstr. 82",
    "sg:city":"Berlin",
    "sg:phone":"+49 30/7068430",
    "sg:postcode":"12105",
    "sg:province":"Berlin",
    "wof:name":"Reimex Import Export Gmbh",
    "wof:placetype":"venue"
},
  "geometry": {"coordinates":[13.3768119812,52.4481086731],"type":"Point"}
}