{
  "type": "Feature",
  "properties": {
    "iso:country":"DE",
    "sg:address":"Klausenh\u00f6fe",
    "sg:city":"Riegel",
    "sg:phone":"+49 7644/1685",
    "sg:postcode":"79359",
    "sg:province":"Baden-W\u00fcrttemberg",
    "wof:name":"Alexander Unglaube",
    "wof:placetype":"venue"
},
  "geometry": {"coordinates":[7.744527,48.179775],"type":"Point"}
}