{
  "type": "Feature",
  "properties": {
    "iso:country":"DE",
    "sg:address":"Potzhofer Str. 10",
    "sg:city":"Solingen",
    "sg:phone":"+49 212",
    "sg:postcode":"42697",
    "sg:province":"Nordrhein-Westfalen",
    "wof:name":"Def Prods",
    "wof:placetype":"venue"
},
  "geometry": {"coordinates":[6.993173,51.164211],"type":"Point"}
}