{
  "type": "Feature",
  "properties": {
    "iso:country":"DE",
    "sg:address":"Ringstr. 46",
    "sg:city":"Berlin",
    "sg:phone":"+49 30/8168740",
    "sg:postcode":"12205",
    "sg:province":"Berlin",
    "wof:name":"Peter Schunk Mechatronic Systeme Gesch\u00e4ftsf\u00fchrungs Gmbh",
    "wof:placetype":"venue"
},
  "geometry": {"coordinates":[13.28877,52.435181],"type":"Point"}
}