{
  "type": "Feature",
  "properties": {
    "iso:country":"DE",
    "sg:address":"An der Schnellstr. 5",
    "sg:city":"Maselheim",
    "sg:phone":"+49 7356/2289",
    "sg:postcode":"88437",
    "sg:province":"Baden-W\u00fcrttemberg",
    "wof:name":"W. Rehm",
    "wof:placetype":"venue"
},
  "geometry": {"coordinates":[9.852919,48.158047],"type":"Point"}
}