{
  "type": "Feature",
  "properties": {
    "iso:country":"DE",
    "sg:address":"Hans-Geiger-Str. 30",
    "sg:city":"Erlangen",
    "sg:phone":"+49 9131/13126",
    "sg:postcode":"91052",
    "sg:province":"Bayern",
    "wof:name":"Horst Adrian",
    "wof:placetype":"venue"
},
  "geometry": {"coordinates":[11.0123920441,49.5780982971],"type":"Point"}
}