{
  "type": "Feature",
  "properties": {
    "iso:country":"DE",
    "sg:address":"Seegutstrasse 3",
    "sg:city":"Weissach im Tal",
    "sg:phone":"+49 7191",
    "sg:postcode":"71554",
    "sg:province":"Baden-W\u00fcrttemberg",
    "wof:name":"Ellinger-schweisstechnik",
    "wof:placetype":"venue"
},
  "geometry": {"coordinates":[9.488129,48.918549],"type":"Point"}
}