{
  "type": "Feature",
  "properties": {
    "iso:country":"DE",
    "sg:address":"Hauptstr. 93a",
    "sg:city":"Viersen",
    "sg:phone":"+49 2162/249890",
    "sg:postcode":"41747",
    "sg:province":"Nordrhein-Westfalen",
    "wof:name":"Dr. K\u00f6nig & Partner Gmbh",
    "wof:placetype":"venue"
},
  "geometry": {"coordinates":[6.3909749985,51.2552680969],"type":"Point"}
}