{
  "type": "Feature",
  "properties": {
    "iso:country":"DE",
    "sg:address":"Kirchstr. 7",
    "sg:city":"Weibern",
    "sg:phone":"+49 2655/1208",
    "sg:postcode":"56745",
    "sg:province":"Rheinland-Pfalz",
    "wof:name":"Elisabeth-haus",
    "wof:placetype":"venue"
},
  "geometry": {"coordinates":[7.145723,50.405312],"type":"Point"}
}