{
  "type": "Feature",
  "properties": {
    "iso:country":"DE",
    "sg:address":"Sudetenstr. 1",
    "sg:city":"R\u00fcsselsheim",
    "sg:phone":"+49 6142/71878",
    "sg:postcode":"65428",
    "sg:province":"Hessen",
    "wof:name":"Dr. Wolfgang Keil Rechtsanwalt",
    "wof:placetype":"venue"
},
  "geometry": {"coordinates":[8.3853235245,49.9650764465],"type":"Point"}
}