{
  "type": "Feature",
  "properties": {
    "iso:country":"DE",
    "sg:address":"Luitpoldstr. 30a",
    "sg:city":"Landshut",
    "sg:phone":"+49 871/64669",
    "sg:postcode":"84034",
    "sg:province":"Bayern",
    "wof:name":"T. Brandes",
    "wof:placetype":"venue"
},
  "geometry": {"coordinates":[12.143075943,48.538684845],"type":"Point"}
}