{
  "type": "Feature",
  "properties": {
    "iso:country":"DE",
    "sg:address":"Breslauer Str. 15",
    "sg:city":"Warendorf",
    "sg:phone":"+49 2581/3947",
    "sg:postcode":"48231",
    "sg:province":"Nordrhein-Westfalen",
    "wof:name":"Erika Ressel",
    "wof:placetype":"venue"
},
  "geometry": {"coordinates":[7.9800281525,51.9449501038],"type":"Point"}
}