{
  "type": "Feature",
  "properties": {
    "iso:country":"DE",
    "sg:address":"Enge Str. 7",
    "sg:city":"Diepholz",
    "sg:phone":"+49 5441/4390",
    "sg:postcode":"49356",
    "sg:province":"Niedersachsen",
    "wof:name":"E. Lerche",
    "wof:placetype":"venue"
},
  "geometry": {"coordinates":[8.3675441742,52.5950889587],"type":"Point"}
}