{
  "type": "Feature",
  "properties": {
    "iso:country":"DE",
    "sg:address":"Hubertusallee 35",
    "sg:city":"Wuppertal",
    "sg:phone":"+49 202/740066",
    "sg:postcode":"42117",
    "sg:province":"Nordrhein-Westfalen",
    "wof:name":"Prof. Wolfgang Rathke",
    "wof:placetype":"venue"
},
  "geometry": {"coordinates":[7.109821,51.241714],"type":"Point"}
}