{
  "type": "Feature",
  "properties": {
    "iso:country":"DE",
    "sg:address":"Quagliostr. 16",
    "sg:city":"M\u00fcnchen",
    "sg:phone":"+49 89/655253",
    "sg:postcode":"81543",
    "sg:province":"Bayern",
    "wof:name":"Franz Breitsamer",
    "wof:placetype":"venue"
},
  "geometry": {"coordinates":[11.5604095459,48.1043205261],"type":"Point"}
}