{
  "type": "Feature",
  "properties": {
    "iso:country":"DE",
    "sg:address":"Dreik\u00f6nigstr. 16a",
    "sg:city":"Schwetzingen",
    "sg:phone":"+49 6202/14011",
    "sg:postcode":"68723",
    "sg:province":"Baden-W\u00fcrttemberg",
    "wof:name":"Herbert Frey",
    "wof:placetype":"venue"
},
  "geometry": {"coordinates":[8.5733718872,49.3861351013],"type":"Point"}
}