{
  "type": "Feature",
  "properties": {
    "iso:country":"DE",
    "sg:address":"Postfach 62",
    "sg:city":"Breitscheid",
    "sg:phone":"+49 2638/1418",
    "sg:postcode":"53547",
    "sg:province":"Rheinland-Pfalz",
    "wof:name":"Kr\u00e4uterversand Ciupek",
    "wof:placetype":"venue"
},
  "geometry": {"coordinates":[7.4426341057,50.5819282532],"type":"Point"}
}