{
  "type": "Feature",
  "properties": {
    "iso:country":"DE",
    "sg:address":"Hubstr. 1",
    "sg:city":"Berching",
    "sg:phone":"+49 8462/2145",
    "sg:postcode":"92334",
    "sg:province":"Bayern",
    "wof:name":"Paul Schaffrinna Masseur",
    "wof:placetype":"venue"
},
  "geometry": {"coordinates":[11.440274,49.106747],"type":"Point"}
}