{
  "type": "Feature",
  "properties": {
    "iso:country":"DE",
    "sg:address":"Bleichstrasse 33",
    "sg:city":"Herschbach",
    "sg:phone":"+49 2626",
    "sg:postcode":"56249",
    "sg:province":"Rheinland-Pfalz",
    "wof:name":"Leku Gmbh Lederwaren",
    "wof:placetype":"venue"
},
  "geometry": {"coordinates":[7.7333450317,50.5773200989],"type":"Point"}
}