{
  "type": "Feature",
  "properties": {
    "iso:country":"DE",
    "sg:address":"In der Breite 11",
    "sg:city":"Lahr",
    "sg:phone":"+49 7821/22539",
    "sg:postcode":"77933",
    "sg:province":"Baden-W\u00fcrttemberg",
    "wof:name":"Theodor Heydgen Architekt",
    "wof:placetype":"venue"
},
  "geometry": {"coordinates":[7.860601,48.343376],"type":"Point"}
}