{
  "type": "Feature",
  "properties": {
    "iso:country":"DE",
    "sg:address":"Gervinusstr. 4",
    "sg:city":"Berlin",
    "sg:phone":"+49 30/32765400",
    "sg:postcode":"10629",
    "sg:province":"Berlin",
    "wof:name":"Roger Karbe Architekt",
    "wof:placetype":"venue"
},
  "geometry": {"coordinates":[13.305726,52.504406],"type":"Point"}
}