{
  "type": "Feature",
  "properties": {
    "iso:country":"DE",
    "sg:address":"Kreuzeskirchstr. 8",
    "sg:city":"Essen",
    "sg:phone":"+49 201/225785",
    "sg:postcode":"45127",
    "sg:province":"Nordrhein-Westfalen",
    "wof:name":"Geers H\u00f6rakustik Ag & Co. Kg",
    "wof:placetype":"venue"
},
  "geometry": {"coordinates":[7.0123281479,51.4593315125],"type":"Point"}
}