{
  "type": "Feature",
  "properties": {
    "iso:country":"DE",
    "sg:address":"Bonbadener Str. 20a",
    "sg:city":"Braunfels",
    "sg:phone":"+49 6442/5677",
    "sg:postcode":"35619",
    "sg:province":"Hessen",
    "wof:name":"Kleintierzuchtverein H 190 Braunfels E. V.",
    "wof:placetype":"venue"
},
  "geometry": {"coordinates":[8.3843736649,50.4929199219],"type":"Point"}
}