{
  "type": "Feature",
  "properties": {
    "iso:country":"DE",
    "sg:address":"Bruchhauser Str. 2",
    "sg:city":"Ratingen",
    "sg:phone":"+49 2102/60540",
    "sg:postcode":"40883",
    "sg:province":"Nordrhein-Westfalen",
    "wof:name":"Kath. Pfarramt St. Bartholom\u00e4us",
    "wof:placetype":"venue"
},
  "geometry": {"coordinates":[6.908203125,51.3245658875],"type":"Point"}
}