{
  "type": "Feature",
  "properties": {
    "iso:country":"DE",
    "sg:address":"M\u00fchlstr. 2",
    "sg:city":"Auenwald",
    "sg:phone":"+49 7191/53636",
    "sg:postcode":"71549",
    "sg:province":"Baden-W\u00fcrttemberg",
    "wof:name":"R\u00f6ssle",
    "wof:placetype":"venue"
},
  "geometry": {"coordinates":[9.5028896332,48.9507904053],"type":"Point"}
}