{
  "type": "Feature",
  "properties": {
    "iso:country":"DE",
    "sg:address":"Bergmannstr. 11",
    "sg:city":"Leer",
    "sg:postcode":"26789",
    "sg:province":"Niedersachsen",
    "wof:name":"Save Anlagenvermittlungsges. Mbh",
    "wof:placetype":"venue"
},
  "geometry": {"coordinates":[7.4559869766,53.2310562134],"type":"Point"}
}