{
  "type": "Feature",
  "properties": {
    "iso:country":"DE",
    "sg:address":"Alte Reutstr. 141",
    "sg:city":"F\u00fcrth",
    "sg:phone":"+49 911/7906618",
    "sg:postcode":"90765",
    "sg:province":"Bayern",
    "wof:name":"G\u00fcnter Breer",
    "wof:placetype":"venue"
},
  "geometry": {"coordinates":[11.006132,49.489094],"type":"Point"}
}