{
  "type": "Feature",
  "properties": {
    "iso:country":"DE",
    "sg:address":"K\u00e4the-Kollwitz-Str. 4",
    "sg:city":"Grimma",
    "sg:phone":"+49 3437/910172",
    "sg:postcode":"04668",
    "sg:province":"Sachsen",
    "wof:name":"H\u00e4nsel",
    "wof:placetype":"venue"
},
  "geometry": {"coordinates":[12.722472,51.237942],"type":"Point"}
}