{
  "type": "Feature",
  "properties": {
    "iso:country":"DE",
    "sg:address":"Dieselstr. 1",
    "sg:city":"Augsburg",
    "sg:phone":"+49 821/413031",
    "sg:postcode":"86154",
    "sg:province":"Bayern",
    "wof:name":"Miehle Kg",
    "wof:placetype":"venue"
},
  "geometry": {"coordinates":[10.8811435699,48.3858070374],"type":"Point"}
}