{
  "type": "Feature",
  "properties": {
    "iso:country":"DE",
    "sg:address":"Dorfstr. 2",
    "sg:city":"Wennigsen",
    "sg:phone":"+49 5109/3148",
    "sg:postcode":"30974",
    "sg:province":"Niedersachsen",
    "wof:name":"Friedrich Wissel",
    "wof:placetype":"venue"
},
  "geometry": {"coordinates":[9.609647,52.279762],"type":"Point"}
}