{
  "type": "Feature",
  "properties": {
    "iso:country":"DE",
    "sg:address":"Kasseler Str. 6",
    "sg:city":"Eschwege",
    "sg:phone":"+49 5651/20664",
    "sg:postcode":"37269",
    "sg:province":"Hessen",
    "wof:name":"K\u00fchnemund Gmbh & Co. Kg",
    "wof:placetype":"venue"
},
  "geometry": {"coordinates":[10.0289821625,51.1790428162],"type":"Point"}
}