{
  "type": "Feature",
  "properties": {
    "iso:country":"DE",
    "sg:address":"Maarstr. 11",
    "sg:city":"Troisdorf",
    "sg:phone":"+49 2241/403513",
    "sg:postcode":"53842",
    "sg:province":"Nordrhein-Westfalen",
    "wof:name":"E. Sch\u00f6ne",
    "wof:placetype":"venue"
},
  "geometry": {"coordinates":[7.1107501984,50.8351898193],"type":"Point"}
}