{
  "type": "Feature",
  "properties": {
    "iso:country":"DE",
    "sg:address":"Spitalgasse 27",
    "sg:city":"Kulmbach",
    "sg:phone":"+49 9221/4435",
    "sg:postcode":"95326",
    "sg:province":"Bayern",
    "wof:name":"Anna Scheder Kg",
    "wof:placetype":"venue"
},
  "geometry": {"coordinates":[11.4586811066,50.1084022522],"type":"Point"}
}