{
  "type": "Feature",
  "properties": {
    "iso:country":"DE",
    "sg:address":"Stadtwaldstr. 27",
    "sg:city":"M\u00f6nchengladbach",
    "sg:phone":"+49 2161/588930",
    "sg:postcode":"41179",
    "sg:province":"Nordrhein-Westfalen",
    "wof:name":"Laptolex E. K.",
    "wof:placetype":"venue"
},
  "geometry": {"coordinates":[6.37175,51.14756],"type":"Point"}
}