{
  "type": "Feature",
  "properties": {
    "iso:country":"DE",
    "sg:address":"K\u00f6nigsmoorstr. 47",
    "sg:city":"Moormerland",
    "sg:phone":"+49 4954/4555",
    "sg:postcode":"26802",
    "sg:province":"Niedersachsen",
    "wof:name":"Menno Helmers",
    "wof:placetype":"venue"
},
  "geometry": {"coordinates":[7.504451,53.275654],"type":"Point"}
}