{
  "type": "Feature",
  "properties": {
    "iso:country":"DE",
    "sg:address":"Hubertusstr. 4",
    "sg:city":"Langenzenn",
    "sg:phone":"+49 9101/8740",
    "sg:postcode":"90579",
    "sg:province":"Bayern",
    "wof:name":"Albert Goos",
    "wof:placetype":"venue"
},
  "geometry": {"coordinates":[10.774526,49.467525],"type":"Point"}
}