{
  "type": "Feature",
  "properties": {
    "iso:country":"DE",
    "sg:address":"Hermann-Kolb-Str. 35 b",
    "sg:city":"N\u00fcrnberg",
    "sg:phone":"+49 911/836775",
    "sg:postcode":"90475",
    "sg:province":"Bayern",
    "wof:name":"Grundbesitzverwaltung Claus Merk",
    "wof:placetype":"venue"
},
  "geometry": {"coordinates":[11.1791658401,49.4022102356],"type":"Point"}
}