{
  "type": "Feature",
  "properties": {
    "iso:country":"DE",
    "sg:address":"Blumenstr. 10",
    "sg:city":"Rodgau",
    "sg:phone":"+49 6106/14125",
    "sg:postcode":"63110",
    "sg:province":"Hessen",
    "wof:name":"Karl-heinz Werner Architekt",
    "wof:placetype":"venue"
},
  "geometry": {"coordinates":[8.879732,50.024467],"type":"Point"}
}