{
  "type": "Feature",
  "properties": {
    "iso:country":"DE",
    "sg:address":"Lugstr. 5",
    "sg:city":"Pirna",
    "sg:phone":"+49 3501/523610",
    "sg:postcode":"01796",
    "sg:province":"Sachsen",
    "wof:name":"Peter Ullrich Ingenieur",
    "wof:placetype":"venue"
},
  "geometry": {"coordinates":[13.9412002563,50.9736213684],"type":"Point"}
}