{
  "type": "Feature",
  "properties": {
    "iso:country":"DE",
    "sg:address":"Sch\u00fcruferstr. 196",
    "sg:city":"Dortmund",
    "sg:phone":"+49 231/950560",
    "sg:postcode":"44269",
    "sg:province":"Nordrhein-Westfalen",
    "wof:name":"Logo Digital Werbeservice Gmbh",
    "wof:placetype":"venue"
},
  "geometry": {"coordinates":[7.537507,51.490616],"type":"Point"}
}