{
  "type": "Feature",
  "properties": {
    "iso:country":"DE",
    "sg:address":"Neckarstr. 54",
    "sg:city":"Esslingen",
    "sg:phone":"+49 711/352611",
    "sg:postcode":"73728",
    "sg:province":"Baden-W\u00fcrttemberg",
    "wof:name":"Gunter Geier Steuerberater",
    "wof:placetype":"venue"
},
  "geometry": {"coordinates":[9.3126945496,48.7367210388],"type":"Point"}
}