{
  "type": "Feature",
  "properties": {
    "iso:country":"DE",
    "sg:address":"Kleinschmitthauser Weg 20",
    "sg:city":"D\u00fcsseldorf",
    "sg:phone":"+49 211/419151",
    "sg:postcode":"40468",
    "sg:province":"Nordrhein-Westfalen",
    "wof:name":"Haus Jakobs",
    "wof:placetype":"venue"
},
  "geometry": {"coordinates":[6.7760710716,51.2692642212],"type":"Point"}
}