{
  "type": "Feature",
  "properties": {
    "iso:country":"DE",
    "sg:address":"Am Busbahnhof 1",
    "sg:city":"Neuhaus",
    "sg:phone":"+49 3679/720134",
    "sg:postcode":"98724",
    "sg:province":"Th\u00fcringen",
    "wof:name":"Personenverkehrsgesellschaft Neuhaus Am Rennweg Mbh",
    "wof:placetype":"venue"
},
  "geometry": {"coordinates":[11.1478796005,50.4973487854],"type":"Point"}
}