{
  "type": "Feature",
  "properties": {
    "iso:country":"DE",
    "sg:address":"Karl-Robiczek-Str.10",
    "sg:city":"F\u00fcrstenfeldbruck",
    "sg:phone":"+49 8141",
    "sg:postcode":"82256",
    "sg:province":"Bayern",
    "wof:name":"Private Informative Homepage",
    "wof:placetype":"venue"
},
  "geometry": {"coordinates":[11.26391,48.183147],"type":"Point"}
}