{
  "type": "Feature",
  "properties": {
    "iso:country":"DE",
    "sg:address":"Wilhelmstal 25",
    "sg:city":"Radevormwald",
    "sg:phone":"+49 2191/60143",
    "sg:postcode":"42477",
    "sg:province":"Nordrhein-Westfalen",
    "wof:name":"Prico Medizinisch-technische Beratungs-vertriebs-gmbh",
    "wof:placetype":"venue"
},
  "geometry": {"coordinates":[7.302915,51.205997],"type":"Point"}
}