{
  "type": "Feature",
  "properties": {
    "iso:country":"DE",
    "sg:address":"Berliner Str. 32",
    "sg:city":"Seelow",
    "sg:phone":"+49 3346/424",
    "sg:postcode":"15306",
    "sg:province":"Brandenburg",
    "wof:name":"H. Biering",
    "wof:placetype":"venue"
},
  "geometry": {"coordinates":[14.3763542175,52.5323448181],"type":"Point"}
}