{
  "type": "Feature",
  "properties": {
    "iso:country":"DE",
    "sg:address":"An der Linde 2",
    "sg:city":"K\u00f6ln",
    "sg:phone":"+49 221/1301774",
    "sg:postcode":"50668",
    "sg:province":"Nordrhein-Westfalen",
    "wof:name":"Gastst\u00e4tte Zur Linde",
    "wof:placetype":"venue"
},
  "geometry": {"coordinates":[6.9615068436,50.9461174011],"type":"Point"}
}