{
  "type": "Feature",
  "properties": {
    "iso:country":"DE",
    "sg:address":"Rupertstr. 10",
    "sg:city":"Ottobeuren",
    "sg:phone":"+49 8332/1033",
    "sg:postcode":"87724",
    "sg:province":"Bayern",
    "wof:name":"Klaus Prei\u00dfinger Notar",
    "wof:placetype":"venue"
},
  "geometry": {"coordinates":[10.297369957,47.942363739],"type":"Point"}
}