{
  "type": "Feature",
  "properties": {
    "iso:country":"DE",
    "sg:address":"Rolandstr. 26",
    "sg:city":"Bremen",
    "sg:phone":"+49 421/505631",
    "sg:postcode":"28199",
    "sg:province":"Bremen",
    "wof:name":"W. Bohlmann",
    "wof:placetype":"venue"
},
  "geometry": {"coordinates":[8.7996702194,53.0715522766],"type":"Point"}
}