{
  "type": "Feature",
  "properties": {
    "iso:country":"DE",
    "sg:address":"Schubertstr. 5",
    "sg:city":"Rheinstetten",
    "sg:phone":"+49 7242/700490",
    "sg:postcode":"76287",
    "sg:province":"Baden-W\u00fcrttemberg",
    "wof:name":"Reinhard Eich Fliesenverlegung Gmbh",
    "wof:placetype":"venue"
},
  "geometry": {"coordinates":[8.2655925751,48.9692344666],"type":"Point"}
}