{
  "type": "Feature",
  "properties": {
    "iso:country":"DE",
    "sg:address":"Bismarckstr. 2 a",
    "sg:city":"Pinneberg",
    "sg:phone":"+49 4101/23196",
    "sg:postcode":"25421",
    "sg:province":"Schleswig-Holstein",
    "wof:name":"Reformhaus D. F. Wulf Gmbh & Co.",
    "wof:placetype":"venue"
},
  "geometry": {"coordinates":[9.7967500687,53.6614761353],"type":"Point"}
}