{
  "type": "Feature",
  "properties": {
    "iso:country":"DE",
    "sg:address":"Fachenfelder Weg 125 B",
    "sg:city":"Seevetal",
    "sg:phone":"+49 4105/668195",
    "sg:postcode":"21220",
    "sg:province":"Niedersachsen",
    "wof:name":"Finanz Conzept Inh. Oliver Meister",
    "wof:placetype":"venue"
},
  "geometry": {"coordinates":[10.0608901978,53.3844108582],"type":"Point"}
}