{
  "type": "Feature",
  "properties": {
    "iso:country":"DE",
    "sg:address":"Springorumallee 2",
    "sg:city":"Bochum",
    "sg:phone":"+49 234",
    "sg:postcode":"44795",
    "sg:province":"Nordrhein-Westfalen",
    "wof:name":"Pantheon Compuser",
    "wof:placetype":"venue"
},
  "geometry": {"coordinates":[7.2089710236,51.4550209045],"type":"Point"}
}