{
  "type": "Feature",
  "properties": {
    "iso:country":"DE",
    "sg:address":"Kirchrather Str. 16",
    "sg:city":"Aachen",
    "sg:postcode":"52074",
    "sg:province":"Nordrhein-Westfalen",
    "wof:name":"Irta Software-systeme Gmbh",
    "wof:placetype":"venue"
},
  "geometry": {"coordinates":[6.0523309708,50.774974823],"type":"Point"}
}