{
  "type": "Feature",
  "properties": {
    "iso:country":"DE",
    "sg:address":"Kettenbr\u00fcckstr. 3",
    "sg:city":"Bamberg",
    "sg:phone":"+49 951/25044",
    "sg:postcode":"96052",
    "sg:province":"Bayern",
    "wof:name":"R. Fuchs",
    "wof:placetype":"venue"
},
  "geometry": {"coordinates":[10.89132,49.89679],"type":"Point"}
}