{
  "type": "Feature",
  "properties": {
    "iso:country":"DE",
    "sg:address":"R\u00f6merstr. 48",
    "sg:city":"Senden",
    "sg:phone":"+49 7307/22000",
    "sg:postcode":"89250",
    "sg:province":"Bayern",
    "wof:name":"R\u00f6mer-apotheke",
    "wof:placetype":"venue"
},
  "geometry": {"coordinates":[10.075744,48.31744],"type":"Point"}
}