{
  "type": "Feature",
  "properties": {
    "iso:country":"DE",
    "sg:address":"Dahlenburger Str. 6",
    "sg:city":"Bleckede",
    "sg:phone":"+49 5852/762",
    "sg:postcode":"21354",
    "sg:province":"Niedersachsen",
    "wof:name":"W. L\u00f6ffler",
    "wof:placetype":"venue"
},
  "geometry": {"coordinates":[10.74032,53.283577],"type":"Point"}
}