{
  "type": "Feature",
  "properties": {
    "iso:country":"DE",
    "sg:address":"Hinterer Buchenberg 10",
    "sg:city":"Ellwangen",
    "sg:phone":"+49 7961/3088",
    "sg:postcode":"73479",
    "sg:province":"Baden-W\u00fcrttemberg",
    "wof:name":"Dentalring Handels-gmbh",
    "wof:placetype":"venue"
},
  "geometry": {"coordinates":[10.139697,48.954308],"type":"Point"}
}