{
  "type": "Feature",
  "properties": {
    "iso:country":"DE",
    "sg:address":"Hatschekstr 22",
    "sg:city":"Heidelberg",
    "sg:phone":"+49 6221/302188",
    "sg:postcode":"69126",
    "sg:province":"Baden-W\u00fcrttemberg",
    "wof:name":"Autolackiererei Dittmer Gmbh",
    "wof:placetype":"venue"
},
  "geometry": {"coordinates":[8.681398,49.363121],"type":"Point"}
}