{
  "type": "Feature",
  "properties": {
    "iso:country":"DE",
    "sg:address":"Feldmannsweg 25",
    "sg:city":"Herzebrock-Clarholz",
    "sg:phone":"+49 5245/2374",
    "sg:postcode":"33442",
    "sg:province":"Nordrhein-Westfalen",
    "wof:name":"I. Schnitker",
    "wof:placetype":"venue"
},
  "geometry": {"coordinates":[8.23813,51.876873],"type":"Point"}
}