{
  "type": "Feature",
  "properties": {
    "iso:country":"DE",
    "sg:address":"Heuerstr. 18",
    "sg:city":"Mainz",
    "sg:phone":"+49 6131/959790",
    "sg:postcode":"55129",
    "sg:province":"Rheinland-Pfalz",
    "wof:name":"Hotel-restaurant Rhodos",
    "wof:placetype":"venue"
},
  "geometry": {"coordinates":[8.2781362534,49.9599113464],"type":"Point"}
}