{
  "type": "Feature",
  "properties": {
    "iso:country":"DE",
    "sg:address":"Ludgeriplatz 12",
    "sg:city":"M\u00fcnster",
    "sg:postcode":"48151",
    "sg:province":"Nordrhein-Westfalen",
    "wof:name":"Eins Ci-gesellschaft F\u00fcr Interaktive Kommunikations-",
    "wof:placetype":"venue"
},
  "geometry": {"coordinates":[7.6259260178,51.9560813904],"type":"Point"}
}