{
  "type": "Feature",
  "properties": {
    "iso:country":"DE",
    "sg:address":"Sch\u00f6ngeisinger Str. 29",
    "sg:city":"F\u00fcrstenfeldbruck",
    "sg:postcode":"82256",
    "sg:province":"Bayern",
    "wof:name":"Brille Und Akustik Gmbh",
    "wof:placetype":"venue"
},
  "geometry": {"coordinates":[11.2520103455,48.1765518188],"type":"Point"}
}