{
  "type": "Feature",
  "properties": {
    "iso:country":"DE",
    "sg:address":"K\u00f6lner Str. 107",
    "sg:city":"Solingen",
    "sg:phone":"+49 212/203851",
    "sg:postcode":"42651",
    "sg:province":"Nordrhein-Westfalen",
    "wof:name":"Eiscafe Vittorio Zammatteo",
    "wof:placetype":"venue"
},
  "geometry": {"coordinates":[7.082851,51.17178],"type":"Point"}
}