{
  "type": "Feature",
  "properties": {
    "iso:country":"DE",
    "sg:address":"Dr.-Martin-Luther-Str. 9",
    "sg:city":"Hemau",
    "sg:phone":"+49 9491/466",
    "sg:postcode":"93155",
    "sg:province":"Bayern",
    "wof:name":"Ev. Luth. Pfarramt",
    "wof:placetype":"venue"
},
  "geometry": {"coordinates":[11.7820863724,49.0588493347],"type":"Point"}
}