{
  "type": "Feature",
  "properties": {
    "iso:country":"DE",
    "sg:address":"Dorfstr. 34",
    "sg:city":"Christinenfeld",
    "sg:phone":"+49 38825/22484",
    "sg:postcode":"23948",
    "sg:province":"Mecklenburg-Vorpommern",
    "wof:name":"W. Deutsch",
    "wof:placetype":"venue"
},
  "geometry": {"coordinates":[11.1943950653,53.961894989],"type":"Point"}
}