{
  "type": "Feature",
  "properties": {
    "iso:country":"DE",
    "sg:address":"Leopoldring 1",
    "sg:city":"Freiburg",
    "sg:phone":"+49 761/319020",
    "sg:postcode":"79098",
    "sg:province":"Baden-W\u00fcrttemberg",
    "wof:name":"Oskar Schunck Kg",
    "wof:placetype":"venue"
},
  "geometry": {"coordinates":[7.8531050682,47.9982376099],"type":"Point"}
}