{
  "type": "Feature",
  "properties": {
    "iso:country":"DE",
    "sg:address":"Weststr. 7",
    "sg:city":"Ditfurt",
    "sg:phone":"+49 3946/4459",
    "sg:postcode":"06484",
    "sg:province":"Sachsen-Anhalt",
    "wof:name":"G. Wilkerling",
    "wof:placetype":"venue"
},
  "geometry": {"coordinates":[11.19304,51.82827],"type":"Point"}
}