{
  "type": "Feature",
  "properties": {
    "iso:country":"DE",
    "sg:address":"Bechlingen 9",
    "sg:city":"Tettnang",
    "sg:phone":"+49 7542/7580",
    "sg:postcode":"88069",
    "sg:province":"Baden-W\u00fcrttemberg",
    "wof:name":"A. Osswald",
    "wof:placetype":"venue"
},
  "geometry": {"coordinates":[9.587363,47.679523],"type":"Point"}
}