{
  "type": "Feature",
  "properties": {
    "iso:country":"DE",
    "sg:address":"Am Klingenweg 13",
    "sg:city":"Walluf",
    "sg:phone":"+49 6123/709870",
    "sg:postcode":"65396",
    "sg:province":"Hessen",
    "wof:name":"Intersero Gmbh",
    "wof:placetype":"venue"
},
  "geometry": {"coordinates":[8.164291,50.045399],"type":"Point"}
}