{
  "type": "Feature",
  "properties": {
    "iso:country":"DE",
    "sg:address":"Naundorf 2",
    "sg:city":"Kirchhasel",
    "sg:phone":"+49 3672/414826",
    "sg:postcode":"07407",
    "sg:province":"Th\u00fcringen",
    "wof:name":"Bender-bau Gmbh",
    "wof:placetype":"venue"
},
  "geometry": {"coordinates":[11.410091,50.709358],"type":"Point"}
}