{
  "type": "Feature",
  "properties": {
    "iso:country":"DE",
    "sg:address":"Graspergerstr. 19",
    "sg:city":"Stockdorf",
    "sg:phone":"+49 89/8574121",
    "sg:postcode":"82131",
    "sg:province":"Bayern",
    "wof:name":"Alois Baumgartner Innenarchitekt",
    "wof:placetype":"venue"
},
  "geometry": {"coordinates":[11.41258,48.089432],"type":"Point"}
}