{
  "type": "Feature",
  "properties": {
    "iso:country":"DE",
    "sg:address":"G\u00e4rtnerweg 7",
    "sg:city":"Neu-Isenburg",
    "sg:phone":"+49 6102/77873",
    "sg:postcode":"63263",
    "sg:province":"Hessen",
    "wof:name":"Adolf Leichum Gmbh & Co. Kg",
    "wof:placetype":"venue"
},
  "geometry": {"coordinates":[8.698496,50.052124],"type":"Point"}
}