{
  "type": "Feature",
  "properties": {
    "iso:country":"DE",
    "sg:address":"Kraftwerkstr. 28a",
    "sg:city":"Peitz",
    "sg:postcode":"03185",
    "sg:province":"Brandenburg",
    "wof:name":"Rts Gmbh",
    "wof:placetype":"venue"
},
  "geometry": {"coordinates":[14.4353265762,51.8522567749],"type":"Point"}
}