{
  "type": "Feature",
  "properties": {
    "iso:country":"DE",
    "sg:address":"Rahnstr. 9",
    "sg:city":"Mittenwald",
    "sg:phone":"+49 8823/5945",
    "sg:postcode":"82481",
    "sg:province":"Bayern",
    "wof:name":"G\u00e4stehaus G. Eisenschmid",
    "wof:placetype":"venue"
},
  "geometry": {"coordinates":[11.2596817017,47.4373588562],"type":"Point"}
}