{
  "type": "Feature",
  "properties": {
    "iso:country":"DE",
    "sg:address":"St.-Afra-Str. 18",
    "sg:city":"Todtenweis",
    "sg:phone":"+49 8237/5072",
    "sg:postcode":"86447",
    "sg:province":"Bayern",
    "wof:name":"Karlheinz Rehm Ingenieur",
    "wof:placetype":"venue"
},
  "geometry": {"coordinates":[10.9307184219,48.5166931152],"type":"Point"}
}