{
  "type": "Feature",
  "properties": {
    "iso:country":"DE",
    "sg:address":"Ernst-Th\u00e4lmann-Str. 15",
    "sg:city":"Strausberg",
    "sg:phone":"+49 3341/422502",
    "sg:postcode":"15344",
    "sg:province":"Brandenburg",
    "wof:name":"Flora Zierpflanzen Handels Gmbh",
    "wof:placetype":"venue"
},
  "geometry": {"coordinates":[13.845673,52.534122],"type":"Point"}
}