{
  "type": "Feature",
  "properties": {
    "iso:country":"DE",
    "sg:address":"Kornb\u00fchlweg 1",
    "sg:city":"Reutlingen",
    "sg:phone":"+49 7072/2371",
    "sg:postcode":"72770",
    "sg:province":"Baden-W\u00fcrttemberg",
    "wof:name":"Bejol Anlageberater",
    "wof:placetype":"venue"
},
  "geometry": {"coordinates":[9.1469564438,48.4391822815],"type":"Point"}
}