{
  "type": "Feature",
  "properties": {
    "iso:country":"DE",
    "sg:city":"Hofgeismar",
    "sg:postcode":"34369",
    "sg:province":"Hessen",
    "wof:name":"Der Modeladen Zeitlos Inh. Andrea Peters E. K.",
    "wof:placetype":"venue"
},
  "geometry": {"coordinates":[9.382879,51.492264],"type":"Point"}
}