{
  "type": "Feature",
  "properties": {
    "iso:country":"DE",
    "sg:address":"Gretchenstr. 9a",
    "sg:city":"Hannover",
    "sg:phone":"+49 511/313130",
    "sg:postcode":"30161",
    "sg:province":"Niedersachsen",
    "wof:name":"Bergsportzentrale Hannover Gmbh",
    "wof:placetype":"venue"
},
  "geometry": {"coordinates":[9.746757,52.38385],"type":"Point"}
}