{
  "type": "Feature",
  "properties": {
    "iso:country":"DE",
    "sg:address":"L\u00f6hrhof 2",
    "sg:city":"Recklinghausen",
    "sg:postcode":"45657",
    "sg:province":"Nordrhein-Westfalen",
    "wof:name":"Aldi Gmbh & Co. Kg",
    "wof:placetype":"venue"
},
  "geometry": {"coordinates":[7.1977081299,51.61302948],"type":"Point"}
}