{
  "type": "Feature",
  "properties": {
    "iso:country":"DE",
    "sg:address":"Berliner Str. 14a",
    "sg:city":"Kolkwitz",
    "sg:postcode":"03099",
    "sg:province":"Brandenburg",
    "wof:name":"Terrazzowaren Und Grabmale Eg",
    "wof:placetype":"venue"
},
  "geometry": {"coordinates":[14.2431678772,51.7497558594],"type":"Point"}
}