{
  "type": "Feature",
  "properties": {
    "iso:country":"DE",
    "sg:address":"Dantestr. 15",
    "sg:city":"Stuttgart",
    "sg:phone":"+49 8191/911921",
    "sg:postcode":"70197",
    "sg:province":"Baden-W\u00fcrttemberg",
    "wof:name":"Huttner Fahrzeugbau Gmbh",
    "wof:placetype":"venue"
},
  "geometry": {"coordinates":[10.8539495468,48.0664596558],"type":"Point"}
}