{
  "type": "Feature",
  "properties": {
    "iso:country":"DE",
    "sg:address":"Justus-von-Liebig-Str. 1",
    "sg:city":"Landsberg",
    "sg:phone":"+49 8191/1251",
    "sg:postcode":"86899",
    "sg:province":"Bayern",
    "wof:name":"Redaktion Reinigung",
    "wof:placetype":"venue"
},
  "geometry": {"coordinates":[10.8581056595,48.0671081543],"type":"Point"}
}