{
  "type": "Feature",
  "properties": {
    "iso:country":"DE",
    "sg:address":"\u00d6stliche Karl-Friedrich-Str. 1",
    "sg:city":"Pforzheim",
    "sg:phone":"+49 7231/354211",
    "sg:postcode":"75175",
    "sg:province":"Baden-W\u00fcrttemberg",
    "wof:name":"C & A Mode Kg",
    "wof:placetype":"venue"
},
  "geometry": {"coordinates":[8.702472,48.891571],"type":"Point"}
}