{
  "type": "Feature",
  "properties": {
    "iso:country":"DE",
    "sg:address":"Gschwendt 3",
    "sg:city":"Benediktbeuern",
    "sg:phone":"+49 8857/8534",
    "sg:postcode":"83671",
    "sg:province":"Bayern",
    "wof:name":"Therese Rieger",
    "wof:placetype":"venue"
},
  "geometry": {"coordinates":[11.416354,47.700085],"type":"Point"}
}