{
  "type": "Feature",
  "properties": {
    "iso:country":"DE",
    "sg:address":"Lokstedter Steindamm 69a",
    "sg:city":"Hamburg",
    "sg:phone":"+49 40/5604343",
    "sg:postcode":"22529",
    "sg:province":"Hamburg",
    "wof:name":"Gerhard K\u00e4\u00dfer",
    "wof:placetype":"venue"
},
  "geometry": {"coordinates":[9.9675283432,53.5911521912],"type":"Point"}
}