{
  "type": "Feature",
  "properties": {
    "iso:country":"DE",
    "sg:address":"Hauptstr. 236",
    "sg:city":"M\u00f6nchengladbach",
    "sg:phone":"+49 2166/619484",
    "sg:postcode":"41236",
    "sg:province":"Nordrhein-Westfalen",
    "wof:name":"T Und W Mobilfunk Computer Telekommunikation",
    "wof:placetype":"venue"
},
  "geometry": {"coordinates":[6.454349041,51.1694030762],"type":"Point"}
}