{
  "type": "Feature",
  "properties": {
    "iso:country":"DE",
    "sg:address":"Straubinger Str. 9",
    "sg:city":"W\u00f6rth",
    "sg:phone":"+49 9482/2167",
    "sg:postcode":"93086",
    "sg:province":"Bayern",
    "wof:name":"Maria Warmuth Hebamme",
    "wof:placetype":"venue"
},
  "geometry": {"coordinates":[12.404114,48.99897],"type":"Point"}
}