{
  "type": "Feature",
  "properties": {
    "iso:country":"DE",
    "sg:address":"Prenzlauer Promenade 149 - 152",
    "sg:city":"Berlin",
    "sg:phone":"+49 30/4797116",
    "sg:postcode":"13189",
    "sg:province":"Berlin",
    "wof:name":"Comitek B\u00fcrosysteme Hans Joachim Frodl",
    "wof:placetype":"venue"
},
  "geometry": {"coordinates":[13.4268398285,52.5625801086],"type":"Point"}
}