{
  "type": "Feature",
  "properties": {
    "iso:country":"DE",
    "sg:address":"Hauptstr. 87-89",
    "sg:city":"Langenfeld",
    "sg:phone":"+49 2173/91095",
    "sg:postcode":"40764",
    "sg:province":"Nordrhein-Westfalen",
    "wof:name":"Holterbosch E. K.",
    "wof:placetype":"venue"
},
  "geometry": {"coordinates":[6.948600769,51.1057739258],"type":"Point"}
}