{
  "type": "Feature",
  "properties": {
    "iso:country":"DE",
    "sg:address":"Hauptstr. 67",
    "sg:city":"R\u00f6deraue",
    "sg:phone":"+49 35263/68571",
    "sg:postcode":"01609",
    "sg:province":"Sachsen",
    "wof:name":"Christian Sachse",
    "wof:placetype":"venue"
},
  "geometry": {"coordinates":[13.471625,51.387474],"type":"Point"}
}