{
  "type": "Feature",
  "properties": {
    "iso:country":"DE",
    "sg:address":"Dorfstr. 51",
    "sg:city":"Ismaning",
    "sg:phone":"+49 89/968316",
    "sg:postcode":"85737",
    "sg:province":"Bayern",
    "wof:name":"Wilhelm R\u00fcck Gmbh",
    "wof:placetype":"venue"
},
  "geometry": {"coordinates":[11.6790704727,48.216583252],"type":"Point"}
}