{
  "type": "Feature",
  "properties": {
    "iso:country":"DE",
    "sg:address":"Moorhauser Landstr. 22",
    "sg:city":"Lilienthal",
    "sg:phone":"+49 4298/5595",
    "sg:postcode":"28865",
    "sg:province":"Niedersachsen",
    "wof:name":"Stephan Niemetz",
    "wof:placetype":"venue"
},
  "geometry": {"coordinates":[8.9126720428,53.1525688171],"type":"Point"}
}