{
  "type": "Feature",
  "properties": {
    "iso:country":"DE",
    "sg:address":"Weierbacher Str. 17",
    "sg:city":"Idar-Oberstein",
    "sg:phone":"+49 6784/2226",
    "sg:postcode":"55743",
    "sg:province":"Rheinland-Pfalz",
    "wof:name":"Karl-peter Mayer",
    "wof:placetype":"venue"
},
  "geometry": {"coordinates":[7.4021830559,49.7362251282],"type":"Point"}
}