{
  "type": "Feature",
  "properties": {
    "iso:country":"DE",
    "sg:address":"Lembacher Str. 6-8",
    "sg:city":"Mannheim",
    "sg:postcode":"68229",
    "sg:province":"Baden-W\u00fcrttemberg",
    "wof:name":"Umieg Waren Import-export Handels- Und Beteiligungs Kg",
    "wof:placetype":"venue"
},
  "geometry": {"coordinates":[8.5739431381,49.4462432861],"type":"Point"}
}