{
  "type": "Feature",
  "properties": {
    "iso:country":"DE",
    "sg:address":"Kurf\u00fcrstenstr. 1",
    "sg:city":"K\u00f6ln",
    "sg:phone":"+49 221/316155",
    "sg:postcode":"50678",
    "sg:province":"Nordrhein-Westfalen",
    "wof:name":"Christel Grigo-wenzel",
    "wof:placetype":"venue"
},
  "geometry": {"coordinates":[6.960103,50.919853],"type":"Point"}
}