{
  "type": "Feature",
  "properties": {
    "iso:country":"DE",
    "sg:address":"L\u00fctzowstr. 347",
    "sg:city":"Solingen",
    "sg:phone":"+49 212/591256",
    "sg:postcode":"42653",
    "sg:province":"Nordrhein-Westfalen",
    "wof:name":"Tierpark Fauna",
    "wof:placetype":"venue"
},
  "geometry": {"coordinates":[7.08387,51.213387],"type":"Point"}
}