{
  "type": "Feature",
  "properties": {
    "iso:country":"DE",
    "sg:address":"Ortsstr. 30",
    "sg:city":"H\u00f6ttingen",
    "sg:phone":"+49 9148/1231",
    "sg:postcode":"91798",
    "sg:province":"Bayern",
    "wof:name":"Georg F\u00fcrsich",
    "wof:placetype":"venue"
},
  "geometry": {"coordinates":[11.02363,49.074528],"type":"Point"}
}