{
  "type": "Feature",
  "properties": {
    "iso:country":"DE",
    "sg:address":"Zum Grauenstein 20",
    "sg:city":"Weilburg",
    "sg:phone":"+49 6442/6088",
    "sg:postcode":"35781",
    "sg:province":"Hessen",
    "wof:name":"Ludwig Feiling",
    "wof:placetype":"venue"
},
  "geometry": {"coordinates":[8.359055,50.482738],"type":"Point"}
}