{
  "type": "Feature",
  "properties": {
    "iso:country":"DE",
    "sg:address":"M\u00f6llinger Str. 1",
    "sg:city":"H\u00f6xter",
    "sg:postcode":"37671",
    "sg:province":"Nordrhein-Westfalen",
    "wof:name":"Immobilien Gmbh H\u00f6xter-beverungen",
    "wof:placetype":"venue"
},
  "geometry": {"coordinates":[9.3809728622,51.7752723694],"type":"Point"}
}