{
  "type": "Feature",
  "properties": {
    "iso:country":"DE",
    "sg:address":"August-L\u00f6sch-Str. 1",
    "sg:city":"Heidenheim",
    "sg:phone":"+49 7321/22081",
    "sg:postcode":"89522",
    "sg:province":"Baden-W\u00fcrttemberg",
    "wof:name":"C & A Brenninkmeyer",
    "wof:placetype":"venue"
},
  "geometry": {"coordinates":[10.152437,48.675159],"type":"Point"}
}