{
  "type": "Feature",
  "properties": {
    "iso:country":"DE",
    "sg:address":"Hamburger Str. 39",
    "sg:city":"L\u00fcbeck",
    "sg:phone":"+49 451/891696",
    "sg:postcode":"23558",
    "sg:province":"Schleswig-Holstein",
    "wof:name":"J. Westerveld",
    "wof:placetype":"venue"
},
  "geometry": {"coordinates":[10.637695,53.84967],"type":"Point"}
}