{
  "type": "Feature",
  "properties": {
    "iso:country":"DE",
    "sg:address":"Storcha 3",
    "sg:city":"G\u00f6da",
    "sg:phone":"+49 35937/86202",
    "sg:postcode":"02633",
    "sg:province":"Sachsen",
    "wof:name":"Tyschler Gmbh",
    "wof:placetype":"venue"
},
  "geometry": {"coordinates":[14.301422,51.222916],"type":"Point"}
}