{
  "type": "Feature",
  "properties": {
    "iso:country":"DE",
    "sg:address":"Industriestr. 26",
    "sg:city":"Lorsch",
    "sg:phone":"+49 6251/587289",
    "sg:postcode":"64653",
    "sg:province":"Hessen",
    "wof:name":"Kunststoffverarbeitung Richard Schumacher Gmbh",
    "wof:placetype":"venue"
},
  "geometry": {"coordinates":[8.571348,49.643875],"type":"Point"}
}