{
  "type": "Feature",
  "properties": {
    "iso:country":"DE",
    "sg:address":"Kaiserstr. 41",
    "sg:city":"Radevormwald",
    "sg:phone":"+49 2195/2317",
    "sg:postcode":"42477",
    "sg:province":"Nordrhein-Westfalen",
    "wof:name":"Bernhard Bangert U. Hoffmann Gmbh & Co. Kg",
    "wof:placetype":"venue"
},
  "geometry": {"coordinates":[7.3533411026,51.2034912109],"type":"Point"}
}