{
  "type": "Feature",
  "properties": {
    "iso:country":"DE",
    "sg:address":"Fu\u00dfsteigkoppel 21",
    "sg:city":"Kronshagen",
    "sg:phone":"+49 431/548456",
    "sg:postcode":"24119",
    "sg:province":"Schleswig-Holstein",
    "wof:name":"J\u00fcrgen Geest Architekt",
    "wof:placetype":"venue"
},
  "geometry": {"coordinates":[10.088012,54.340427],"type":"Point"}
}