{
  "type": "Feature",
  "properties": {
    "iso:country":"DE",
    "sg:address":"Rittersweg 23",
    "sg:city":"Kleinblittersdorf",
    "sg:phone":"+49 6805/4546",
    "sg:postcode":"66271",
    "sg:province":"Saarland",
    "wof:name":"G. M\u00f6rchen Heissmangel",
    "wof:placetype":"venue"
},
  "geometry": {"coordinates":[7.0637512207,49.1275978088],"type":"Point"}
}