{
  "type": "Feature",
  "properties": {
    "iso:country":"DE",
    "sg:address":"Feldweg 19",
    "sg:city":"Norderstedt",
    "sg:phone":"+49 40/5225261",
    "sg:postcode":"22844",
    "sg:province":"Schleswig-Holstein",
    "wof:name":"Eks-anlagen, Elektrische Korrosionsschutzanlagen",
    "wof:placetype":"venue"
},
  "geometry": {"coordinates":[9.97833,53.75378],"type":"Point"}
}