{
  "type": "Feature",
  "properties": {
    "iso:country":"DE",
    "sg:address":"Buchenl\u00e4nderhof 1",
    "sg:city":"Norheim",
    "sg:phone":"+49 671/31219",
    "sg:postcode":"55585",
    "sg:province":"Rheinland-Pfalz",
    "wof:name":"B. Butz",
    "wof:placetype":"venue"
},
  "geometry": {"coordinates":[7.8185791969,49.8104553223],"type":"Point"}
}