{
  "type": "Feature",
  "properties": {
    "iso:country":"DE",
    "sg:address":"Winser Baum 2",
    "sg:city":"Winsen",
    "sg:phone":"+49 4171/2770",
    "sg:postcode":"21423",
    "sg:province":"Niedersachsen",
    "wof:name":"Kath. Pfarramt Guter Hirt",
    "wof:placetype":"venue"
},
  "geometry": {"coordinates":[10.1960916519,53.3677902222],"type":"Point"}
}