{
  "type": "Feature",
  "properties": {
    "iso:country":"DE",
    "sg:address":"Lichtentaler Str. 77",
    "sg:city":"Baden-Baden",
    "sg:phone":"+49 7221/22739",
    "sg:postcode":"76530",
    "sg:province":"Baden-W\u00fcrttemberg",
    "wof:name":"F\u00e4ssl",
    "wof:placetype":"venue"
},
  "geometry": {"coordinates":[8.2443437576,48.7546043396],"type":"Point"}
}