{
  "type": "Feature",
  "properties": {
    "iso:country":"DE",
    "sg:address":"Eichelthalerm\u00fchle 4",
    "sg:city":"Neunkirchen",
    "sg:phone":"+49 6858/8901",
    "sg:postcode":"66540",
    "sg:province":"Saarland",
    "wof:name":"Eichelthalerm\u00fchle Schwappach Pflege Gmbh",
    "wof:placetype":"venue"
},
  "geometry": {"coordinates":[7.243812,49.403973],"type":"Point"}
}