{
  "type": "Feature",
  "properties": {
    "iso:country":"DE",
    "sg:address":"Schwanenweg 20",
    "sg:city":"Kiel",
    "sg:postcode":"24105",
    "sg:province":"Schleswig-Holstein",
    "wof:name":"Zentr. Konservat. Medizin Ii Abt. Kinderkardiologie",
    "wof:placetype":"venue"
},
  "geometry": {"coordinates":[10.145772934,54.3316497803],"type":"Point"}
}