{
  "type": "Feature",
  "properties": {
    "iso:country":"DE",
    "sg:address":"Maximilianstr. 29",
    "sg:city":"Traunstein",
    "sg:phone":"+49 861/2912",
    "sg:postcode":"83278",
    "sg:province":"Bayern",
    "wof:name":"Top-chic Mode-handels- Ohg",
    "wof:placetype":"venue"
},
  "geometry": {"coordinates":[12.644900322,47.867351532],"type":"Point"}
}