{
  "type": "Feature",
  "properties": {
    "iso:country":"DE",
    "sg:address":"Gerberstra\u00dfe 15",
    "sg:city":"Leipzig",
    "sg:phone":"+49 341/9880",
    "sg:postcode":"04105",
    "sg:province":"Sachsen",
    "wof:name":"Hotel Inter-continental-leipzig",
    "wof:placetype":"venue"
},
  "geometry": {"coordinates":[12.3762407303,51.3469467163],"type":"Point"}
}