{
  "type": "Feature",
  "properties": {
    "iso:country":"DE",
    "sg:address":"Pfaffenweg 36 B",
    "sg:city":"Stuttgart",
    "sg:postcode":"70180",
    "sg:province":"Baden-W\u00fcrttemberg",
    "wof:name":"Bagherpur & Windisch Gmbh",
    "wof:placetype":"venue"
},
  "geometry": {"coordinates":[9.1699209213,48.7596511841],"type":"Point"}
}