{
  "type": "Feature",
  "properties": {
    "iso:country":"DE",
    "sg:address":"Westenfelder Str. 95",
    "sg:city":"Bochum",
    "sg:postcode":"44867",
    "sg:province":"Nordrhein-Westfalen",
    "wof:name":"Christian-fleisch Gmbh",
    "wof:placetype":"venue"
},
  "geometry": {"coordinates":[7.1453781128,51.47315979],"type":"Point"}
}