{
  "type": "Feature",
  "properties": {
    "iso:country":"DE",
    "sg:address":"Reindorfer Landstr. 12",
    "sg:city":"Buchholz",
    "sg:phone":"+49 4181/7886",
    "sg:postcode":"21244",
    "sg:province":"Niedersachsen",
    "wof:name":"Rolf Brunkhorst",
    "wof:placetype":"venue"
},
  "geometry": {"coordinates":[9.9073724747,53.3131332397],"type":"Point"}
}