{
  "type": "Feature",
  "properties": {
    "iso:country":"DE",
    "sg:address":"Kreisauer Weg 22",
    "sg:city":"Ludwigsburg",
    "sg:phone":"+49 7141/52377",
    "sg:postcode":"71642",
    "sg:province":"Baden-W\u00fcrttemberg",
    "wof:name":"Skoufas Gmbh",
    "wof:placetype":"venue"
},
  "geometry": {"coordinates":[9.22499,48.91573],"type":"Point"}
}