{
  "type": "Feature",
  "properties": {
    "iso:country":"DE",
    "sg:address":"Altenhofstr. 39",
    "sg:city":"St. Ingbert",
    "sg:phone":"+49 6894/956130",
    "sg:postcode":"66386",
    "sg:province":"Saarland",
    "wof:name":"J. Walter",
    "wof:placetype":"venue"
},
  "geometry": {"coordinates":[7.15936,49.26265],"type":"Point"}
}