{
  "type": "Feature",
  "properties": {
    "iso:country":"DE",
    "sg:address":"Leopoldstr. 11",
    "sg:city":"Karlsruhe",
    "sg:phone":"+49 721/27749",
    "sg:postcode":"76133",
    "sg:province":"Baden-W\u00fcrttemberg",
    "wof:name":"Redaktion Kleine Karlsruher Theater-chronik",
    "wof:placetype":"venue"
},
  "geometry": {"coordinates":[8.3897285461,49.0080795288],"type":"Point"}
}