{
  "type": "Feature",
  "properties": {
    "iso:country":"DE",
    "sg:address":"Industriestr. 12",
    "sg:city":"Kinding",
    "sg:phone":"+49 8467/242",
    "sg:postcode":"85125",
    "sg:province":"Bayern",
    "wof:name":"Hafner Bauunternehmung Gmbh",
    "wof:placetype":"venue"
},
  "geometry": {"coordinates":[11.383654,48.998604],"type":"Point"}
}