{
  "type": "Feature",
  "properties": {
    "iso:country":"DE",
    "sg:address":"Sielenwangstr. 21",
    "sg:city":"Gruibingen",
    "sg:phone":"+49 7335/921521",
    "sg:postcode":"73344",
    "sg:province":"Baden-W\u00fcrttemberg",
    "wof:name":"Bs Bodensysteme Deutschland Gmbh",
    "wof:placetype":"venue"
},
  "geometry": {"coordinates":[9.6459474564,48.5906066895],"type":"Point"}
}