{
  "type": "Feature",
  "properties": {
    "iso:country":"DE",
    "sg:address":"Ludwig-Ganghofer-Str. 9",
    "sg:city":"Neumarkt-Sankt Veit",
    "sg:phone":"+49 8639/98350",
    "sg:postcode":"84494",
    "sg:province":"Bayern",
    "wof:name":"Ludwig Frischhut Gmbh",
    "wof:placetype":"venue"
},
  "geometry": {"coordinates":[12.510383606,48.3672142029],"type":"Point"}
}