{
  "type": "Feature",
  "properties": {
    "iso:country":"DE",
    "sg:address":"Hauptstr. 20",
    "sg:city":"Beltheim",
    "sg:phone":"+49 6762/93010",
    "sg:postcode":"56290",
    "sg:province":"Rheinland-Pfalz",
    "wof:name":"Zorn Gmbh",
    "wof:placetype":"venue"
},
  "geometry": {"coordinates":[7.46142,50.104954],"type":"Point"}
}