{
  "type": "Feature",
  "properties": {
    "iso:country":"DE",
    "sg:address":"Mihlaer Str. 1",
    "sg:city":"Bischofroda",
    "sg:phone":"+49 36924/42609",
    "sg:postcode":"99826",
    "sg:province":"Th\u00fcringen",
    "wof:name":"Panorama",
    "wof:placetype":"venue"
},
  "geometry": {"coordinates":[10.3671798706,51.0564918518],"type":"Point"}
}