{
  "type": "Feature",
  "properties": {
    "iso:country":"DE",
    "sg:address":"Br\u00fcsseler Str. 5",
    "sg:city":"Troisdorf",
    "sg:phone":"+49 2241/949020",
    "sg:postcode":"53842",
    "sg:province":"Nordrhein-Westfalen",
    "wof:name":"Fleischimporte Diercks Gmbh",
    "wof:placetype":"venue"
},
  "geometry": {"coordinates":[7.1091718674,50.8368530273],"type":"Point"}
}