{
  "type": "Feature",
  "properties": {
    "iso:country":"DE",
    "sg:address":"Esplanade 8 POSTFACH 101053",
    "sg:city":"Wesel",
    "sg:phone":"+49 281/3009644",
    "sg:postcode":"46470",
    "wof:name":"Andi Maschinenbau + Vertriebs-gesellschaft Berning Mbh",
    "wof:placetype":"venue"
},
  "geometry": {"coordinates":[6.61982,51.656113],"type":"Point"}
}