{
  "type": "Feature",
  "properties": {
    "iso:country":"DE",
    "sg:address":"Rennsteig 17",
    "sg:city":"Berlin",
    "sg:phone":"+49 30/7452677",
    "sg:postcode":"12309",
    "sg:province":"Berlin",
    "wof:name":"Werner Musch",
    "wof:placetype":"venue"
},
  "geometry": {"coordinates":[13.418713,52.395668],"type":"Point"}
}