{
  "type": "Feature",
  "properties": {
    "iso:country":"DE",
    "sg:address":"Halenseestr. 5",
    "sg:city":"Berlin",
    "sg:postcode":"10711",
    "sg:province":"Berlin",
    "wof:name":"Hotel Consulting Bubis Gmbh & Co. Kg",
    "wof:placetype":"venue"
},
  "geometry": {"coordinates":[13.2843856812,52.495262146],"type":"Point"}
}