{
  "type": "Feature",
  "properties": {
    "iso:country":"DE",
    "sg:address":"Deepenhorn 8",
    "sg:city":"Hamburg",
    "sg:phone":"+49 40/6791900",
    "sg:postcode":"22145",
    "sg:province":"Hamburg",
    "wof:name":"Peitsch Foto",
    "wof:placetype":"venue"
},
  "geometry": {"coordinates":[10.164185,53.629845],"type":"Point"}
}