{
  "type": "Feature",
  "properties": {
    "iso:country":"DE",
    "sg:address":"Strandallee 1",
    "sg:city":"Neustadt",
    "sg:phone":"+49 4561/71070",
    "sg:postcode":"23730",
    "sg:province":"Schleswig-Holstein",
    "wof:name":"Soziales Genesungswerk Pelzerhaken E. V.",
    "wof:placetype":"venue"
},
  "geometry": {"coordinates":[10.885068,54.134293],"type":"Point"}
}