{
  "type": "Feature",
  "properties": {
    "iso:country":"DE",
    "sg:address":"Varenholzstr. 112",
    "sg:city":"Bochum",
    "sg:phone":"+49 2327/97570",
    "sg:postcode":"44869",
    "sg:province":"Nordrhein-Westfalen",
    "wof:name":"Hotel Vahrenholt",
    "wof:placetype":"venue"
},
  "geometry": {"coordinates":[7.1388502121,51.4414100647],"type":"Point"}
}