{
  "type": "Feature",
  "properties": {
    "iso:country":"DE",
    "sg:address":"Holstenplatz",
    "sg:city":"Elmshorn",
    "sg:phone":"+49 4121/2361",
    "sg:postcode":"25335",
    "sg:province":"Schleswig-Holstein",
    "wof:name":"Deutsche Bahn Ag",
    "wof:placetype":"venue"
},
  "geometry": {"coordinates":[9.6576547623,53.7554092407],"type":"Point"}
}