{
  "type": "Feature",
  "properties": {
    "iso:country":"DE",
    "sg:address":"Isarstr. 1",
    "sg:city":"Rosenheim",
    "sg:phone":"+49 8031/33010",
    "sg:postcode":"83026",
    "sg:province":"Bayern",
    "wof:name":"Oberland Grundst\u00fccks- Vermietungs- Und Verm\u00f6gens-",
    "wof:placetype":"venue"
},
  "geometry": {"coordinates":[12.1248998642,47.8417282104],"type":"Point"}
}