{
  "type": "Feature",
  "properties": {
    "iso:country":"DE",
    "sg:address":"Kirchstr. 15",
    "sg:city":"Rosbach",
    "sg:phone":"+49 6003/1426",
    "sg:postcode":"61191",
    "sg:province":"Hessen",
    "wof:name":"Horst Heinemann Ingenieur",
    "wof:placetype":"venue"
},
  "geometry": {"coordinates":[8.6890983582,50.3049087524],"type":"Point"}
}