{
  "type": "Feature",
  "properties": {
    "iso:country":"DE",
    "sg:address":"Vogtstra\u00dfe 41",
    "sg:city":"Frankfurt/M",
    "sg:phone":"+49 69/5963680",
    "sg:postcode":"60322",
    "sg:province":"Hessen",
    "wof:name":"Viv-international E.v.",
    "wof:placetype":"venue"
},
  "geometry": {"coordinates":[8.673803,50.125706],"type":"Point"}
}