{
  "type": "Feature",
  "properties": {
    "iso:country":"DE",
    "sg:address":"Elverdisser Str. 62",
    "sg:city":"Herford",
    "sg:phone":"+49 5221/71015",
    "sg:postcode":"32052",
    "sg:province":"Nordrhein-Westfalen",
    "wof:name":"Norbert Linke",
    "wof:placetype":"venue"
},
  "geometry": {"coordinates":[8.6657066345,52.1071739197],"type":"Point"}
}