{
  "type": "Feature",
  "properties": {
    "iso:country":"DE",
    "sg:address":"Oberkasseler Str. 74",
    "sg:city":"K\u00f6nigswinter",
    "sg:phone":"+49 2223/92170",
    "sg:postcode":"53639",
    "sg:province":"Nordrhein-Westfalen",
    "wof:name":"Sach- Und Haftpflicht- Versicherung Des",
    "wof:placetype":"venue"
},
  "geometry": {"coordinates":[7.1760210991,50.7040138245],"type":"Point"}
}