{
  "type": "Feature",
  "properties": {
    "iso:country":"DE",
    "sg:address":"Fremersbergstra\u00dfe 125",
    "sg:city":"Baden-Baden",
    "sg:phone":"+49 7221/30150",
    "sg:postcode":"76530",
    "sg:province":"Baden-W\u00fcrttemberg",
    "wof:name":"Fairway Hotel Am Golfplatz - Baden-baden",
    "wof:placetype":"venue"
},
  "geometry": {"coordinates":[8.2130088806,48.746723175],"type":"Point"}
}