{
  "type": "Feature",
  "properties": {
    "iso:country":"DE",
    "sg:address":"Idarer Str. 10",
    "sg:city":"Idar-Oberstein",
    "sg:phone":"+49 6781/24583",
    "sg:postcode":"55743",
    "sg:province":"Rheinland-Pfalz",
    "wof:name":"Michael Vohl",
    "wof:placetype":"venue"
},
  "geometry": {"coordinates":[7.3328208923,49.7225418091],"type":"Point"}
}