{
  "type": "Feature",
  "properties": {
    "iso:country":"DE",
    "sg:address":"Meltewitzer Str. 17",
    "sg:city":"Meltewitz",
    "sg:postcode":"04808",
    "sg:province":"Sachsen",
    "wof:name":"Dieselmotorenwerk Leipzig",
    "wof:placetype":"venue"
},
  "geometry": {"coordinates":[12.7918653488,51.3923568726],"type":"Point"}
}