{
  "type": "Feature",
  "properties": {
    "iso:country":"DE",
    "sg:address":"Hauptstr. 7",
    "sg:city":"Graach",
    "sg:phone":"+49 6531/8591",
    "sg:postcode":"54470",
    "sg:province":"Rheinland-Pfalz",
    "wof:name":"Gottfried Kerpen",
    "wof:placetype":"venue"
},
  "geometry": {"coordinates":[7.0588560104,49.9390068054],"type":"Point"}
}