{
  "type": "Feature",
  "properties": {
    "iso:country":"DE",
    "sg:address":"Seltersweg 54",
    "sg:city":"Gie\u00dfen",
    "sg:postcode":"35390",
    "sg:province":"Hessen",
    "wof:name":"Kvb Beratungsgesellges. F\u00fcr Finanzierungen Mbh",
    "wof:placetype":"venue"
},
  "geometry": {"coordinates":[8.671462,50.583073],"type":"Point"}
}