{
  "type": "Feature",
  "properties": {
    "iso:country":"DE",
    "sg:address":"Weseler Str. 16",
    "sg:city":"M\u00fcnster",
    "sg:phone":"+49 251/524633",
    "sg:postcode":"48151",
    "sg:province":"Nordrhein-Westfalen",
    "wof:name":"Neckura Versicherungs- Ag",
    "wof:placetype":"venue"
},
  "geometry": {"coordinates":[7.6197929382,51.9547767639],"type":"Point"}
}