{
  "type": "Feature",
  "properties": {
    "iso:country":"DE",
    "sg:address":"Friedensstr 4",
    "sg:city":"Krostitz",
    "sg:phone":"+49 34295/71113",
    "sg:postcode":"04509",
    "sg:province":"Sachsen",
    "wof:name":"Dieter Lucinski Gmbh",
    "wof:placetype":"venue"
},
  "geometry": {"coordinates":[12.4586811066,51.4871253967],"type":"Point"}
}