{
  "type": "Feature",
  "properties": {
    "iso:country":"DE",
    "sg:address":"Aidenbachstr. 30",
    "sg:city":"M\u00fcnchen",
    "sg:phone":"+49 89/783209",
    "sg:postcode":"81379",
    "sg:province":"Bayern",
    "wof:name":"Dagmar R\u00f6sler Praxis F\u00fcr Krankengymnastik",
    "wof:placetype":"venue"
},
  "geometry": {"coordinates":[11.52345,48.099033],"type":"Point"}
}