{
  "type": "Feature",
  "properties": {
    "iso:country":"DE",
    "sg:address":"Neue Str. 25",
    "sg:city":"Wehrhain",
    "sg:phone":"+49 35361/80178",
    "sg:postcode":"04936",
    "sg:province":"Brandenburg",
    "wof:name":"Dz Transport & Handels Gmbh D.ziegner Internationaler Fernverkehr",
    "wof:placetype":"venue"
},
  "geometry": {"coordinates":[13.4061603546,51.7561683655],"type":"Point"}
}