{
  "type": "Feature",
  "properties": {
    "iso:country":"DE",
    "sg:address":"Delitzscher Str 73",
    "sg:city":"Halle",
    "sg:phone":"+49 345/564090",
    "sg:postcode":"06112",
    "sg:province":"Sachsen-Anhalt",
    "wof:name":"Abh H\u00e4\u00dfler Lift Hebeb\u00fchnen Inh. Thomas H\u00e4\u00dfler",
    "wof:placetype":"venue"
},
  "geometry": {"coordinates":[12.00387,51.478569],"type":"Point"}
}