{
  "type": "Feature",
  "properties": {
    "iso:country":"DE",
    "sg:address":"Hauptstr. 254",
    "sg:city":"Schwalbach",
    "sg:phone":"+49 6834/54612",
    "sg:postcode":"66773",
    "sg:province":"Saarland",
    "wof:name":"Restaurant Dorfkrug",
    "wof:placetype":"venue"
},
  "geometry": {"coordinates":[6.8196787834,49.3050346375],"type":"Point"}
}