{
  "type": "Feature",
  "properties": {
    "iso:country":"DE",
    "sg:address":"Clara-Zetkin-Str. 2",
    "sg:city":"Oschersleben",
    "sg:phone":"+49 3949/2433",
    "sg:postcode":"39387",
    "sg:province":"Sachsen-Anhalt",
    "wof:name":"Jens Helmecke",
    "wof:placetype":"venue"
},
  "geometry": {"coordinates":[11.218437,52.031834],"type":"Point"}
}