{
  "type": "Feature",
  "properties": {
    "iso:country":"DE",
    "sg:address":"Schulstr. 4",
    "sg:city":"Trebur",
    "sg:phone":"+49 6147/8431",
    "sg:postcode":"65468",
    "sg:province":"Hessen",
    "wof:name":"Katholisches Pfarramt St. Ulrich",
    "wof:placetype":"venue"
},
  "geometry": {"coordinates":[8.3980846405,49.8825111389],"type":"Point"}
}