{
  "type": "Feature",
  "properties": {
    "iso:country":"DE",
    "sg:address":"Ruhesteinstr. 499",
    "sg:city":"Baiersbronn",
    "sg:phone":"+49 7449/305",
    "sg:postcode":"72270",
    "sg:province":"Baden-W\u00fcrttemberg",
    "wof:name":"Helmut G\u00fcnter",
    "wof:placetype":"venue"
},
  "geometry": {"coordinates":[8.294681,48.532883],"type":"Point"}
}