{
  "type": "Feature",
  "properties": {
    "iso:country":"DE",
    "sg:address":"Holderweg 45",
    "sg:city":"Gie\u00dfen",
    "sg:phone":"+49 641/56453",
    "sg:postcode":"35390",
    "sg:province":"Hessen",
    "wof:name":"B\u00fcro F\u00fcr Kommunikation",
    "wof:placetype":"venue"
},
  "geometry": {"coordinates":[8.676334,50.586613],"type":"Point"}
}