{
  "type": "Feature",
  "properties": {
    "iso:country":"DE",
    "sg:address":"Ulrichweg 2",
    "sg:city":"Herrenberg",
    "sg:phone":"+49 7032/21822",
    "sg:postcode":"71083",
    "sg:province":"Baden-W\u00fcrttemberg",
    "wof:name":"Dr. Wilfried Hamel Tierarzt",
    "wof:placetype":"venue"
},
  "geometry": {"coordinates":[8.8820152283,48.5977973938],"type":"Point"}
}