{
  "type": "Feature",
  "properties": {
    "iso:country":"DE",
    "sg:address":"Parchimer Chaussee 1",
    "sg:city":"Tessenow",
    "sg:postcode":"19376",
    "sg:province":"Mecklenburg-Vorpommern",
    "wof:name":"Technische Instandhaltung Unser & Schwebke Gmbh",
    "wof:placetype":"venue"
},
  "geometry": {"coordinates":[11.884196,53.362553],"type":"Point"}
}