{
  "type": "Feature",
  "properties": {
    "iso:country":"DE",
    "sg:address":"M\u00fcnster 50a",
    "sg:city":"M\u00fcnstertal",
    "sg:phone":"+49 7636/77754",
    "sg:postcode":"79244",
    "sg:province":"Baden-W\u00fcrttemberg",
    "wof:name":"F. Pfefferle",
    "wof:placetype":"venue"
},
  "geometry": {"coordinates":[7.79615,47.859692],"type":"Point"}
}