{
  "type": "Feature",
  "properties": {
    "iso:country":"DE",
    "sg:address":"Mendener Str. 73",
    "sg:city":"Iserlohn",
    "sg:phone":"+49 2371/22695",
    "sg:postcode":"58636",
    "sg:province":"Nordrhein-Westfalen",
    "wof:name":"Friesendorf",
    "wof:placetype":"venue"
},
  "geometry": {"coordinates":[7.7083411217,51.3763504028],"type":"Point"}
}