{
  "type": "Feature",
  "properties": {
    "iso:country":"DE",
    "sg:address":"Lange Str. 30",
    "sg:city":"Waiblingen",
    "sg:phone":"+49 7151/562748",
    "sg:postcode":"71332",
    "sg:province":"Baden-W\u00fcrttemberg",
    "wof:name":"Daniel Bubeck",
    "wof:placetype":"venue"
},
  "geometry": {"coordinates":[9.3161497116,48.8328857422],"type":"Point"}
}