{
  "type": "Feature",
  "properties": {
    "iso:country":"DE",
    "sg:address":"Gartenstr. 9",
    "sg:city":"Limburg",
    "sg:phone":"+49 6431/45533",
    "sg:postcode":"65550",
    "sg:province":"Hessen",
    "wof:name":"Versorgungsberatung L. B\u00f6hm Gmbh",
    "wof:placetype":"venue"
},
  "geometry": {"coordinates":[8.088760376,50.3670692444],"type":"Point"}
}