{
  "type": "Feature",
  "properties": {
    "iso:country":"DE",
    "sg:address":"Im N\u00f6ckel 2",
    "sg:city":"Gummersbach",
    "sg:phone":"+49 2261/64888",
    "sg:postcode":"51647",
    "sg:province":"Nordrhein-Westfalen",
    "wof:name":"Stefan Haarhaus",
    "wof:placetype":"venue"
},
  "geometry": {"coordinates":[7.497646,51.036388],"type":"Point"}
}