{
  "type": "Feature",
  "properties": {
    "iso:country":"DE",
    "sg:address":"Rattenweiler 3",
    "sg:city":"Tettnang",
    "sg:postcode":"88069",
    "sg:province":"Baden-W\u00fcrttemberg",
    "wof:name":"Hans Schmid Gmbh",
    "wof:placetype":"venue"
},
  "geometry": {"coordinates":[9.63949,47.627823],"type":"Point"}
}