{
  "type": "Feature",
  "properties": {
    "iso:country":"DE",
    "sg:address":"Bu\u00dftr. 27 PF 5325",
    "sg:city":"Freiburg",
    "sg:phone":"+49 180 5 704010",
    "sg:postcode":"79020",
    "sg:province":"Niedersachsen",
    "wof:name":"Desomed Dr. Trippen Gmbh",
    "wof:placetype":"venue"
},
  "geometry": {"coordinates":[7.85376,47.997181],"type":"Point"}
}