{
  "type": "Feature",
  "properties": {
    "iso:country":"DE",
    "sg:address":"Georg-August-Zinn-Str. 1",
    "sg:city":"Felsberg",
    "sg:phone":"+49 5662/1348",
    "sg:postcode":"34587",
    "sg:province":"Hessen",
    "wof:name":"Erwin Klinger Architekt",
    "wof:placetype":"venue"
},
  "geometry": {"coordinates":[9.412906,51.140518],"type":"Point"}
}