{
  "type": "Feature",
  "properties": {
    "iso:country":"DE",
    "sg:address":"Am Rathaus 7",
    "sg:city":"Steinbach",
    "sg:phone":"+49 6171/700042",
    "sg:postcode":"61449",
    "sg:province":"Hessen",
    "wof:name":"Stadtb\u00fccherei",
    "wof:placetype":"venue"
},
  "geometry": {"coordinates":[8.577107,50.167656],"type":"Point"}
}