{
  "type": "Feature",
  "properties": {
    "iso:country":"DE",
    "sg:address":"Matthias-Claudius-Str. 5",
    "sg:city":"Wiesbaden",
    "sg:phone":"+49 611/375300",
    "sg:postcode":"65185",
    "sg:province":"Hessen",
    "wof:name":"Its Inter Technik &service Gesellschaft F\u00fcr Techni-",
    "wof:placetype":"venue"
},
  "geometry": {"coordinates":[8.2419424057,50.0732955933],"type":"Point"}
}