{
  "type": "Feature",
  "properties": {
    "iso:country":"DE",
    "sg:address":"Forsthausweg 4",
    "sg:city":"Achim",
    "sg:phone":"+49 4202/71382",
    "sg:postcode":"28832",
    "sg:province":"Niedersachsen",
    "wof:name":"Hartmut Klimanek",
    "wof:placetype":"venue"
},
  "geometry": {"coordinates":[9.0962247849,53.0130691528],"type":"Point"}
}