{
  "type": "Feature",
  "properties": {
    "iso:country":"DE",
    "sg:address":"An der Blutfinke 111",
    "sg:city":"Wuppertal",
    "sg:phone":"+49 202/4603724",
    "sg:postcode":"42369",
    "sg:province":"Nordrhein-Westfalen",
    "wof:name":"J\u00f6rg Reuter",
    "wof:placetype":"venue"
},
  "geometry": {"coordinates":[7.1917967796,51.2210273743],"type":"Point"}
}