{
  "type": "Feature",
  "properties": {
    "iso:country":"DE",
    "sg:address":"Grabenstr. 27",
    "sg:city":"Kalkar",
    "sg:phone":"+49 2824/80385",
    "sg:postcode":"47546",
    "sg:province":"Nordrhein-Westfalen",
    "wof:name":"H. Alpay",
    "wof:placetype":"venue"
},
  "geometry": {"coordinates":[6.2942218781,51.7370033264],"type":"Point"}
}