{
  "type": "Feature",
  "properties": {
    "iso:country":"DE",
    "sg:address":"Bierweg 15B",
    "sg:city":"N\u00fcrnberg",
    "sg:phone":"+49 911/5216080",
    "sg:postcode":"90411",
    "sg:province":"Bayern",
    "wof:name":"Omnibus Bruckdorfer",
    "wof:placetype":"venue"
},
  "geometry": {"coordinates":[11.108007431,49.4851837158],"type":"Point"}
}