{
  "type": "Feature",
  "properties": {
    "iso:country":"DE",
    "sg:address":"S\u00fcdliche Hafenstr. 3",
    "sg:city":"W\u00fcrzburg",
    "sg:phone":"+49 931/96634",
    "sg:postcode":"97080",
    "sg:province":"Bayern",
    "wof:name":"Irene Hufnagel Priska Hufnagel D. Hufnagel U. J. Hufnagel In",
    "wof:placetype":"venue"
},
  "geometry": {"coordinates":[9.895346,49.799923],"type":"Point"}
}