{
  "type": "Feature",
  "properties": {
    "iso:country":"DE",
    "sg:address":"Gro\u00dfer Spiegelberg",
    "sg:city":"Neustrelitz",
    "sg:phone":"+49 3981/440639",
    "sg:postcode":"17235",
    "sg:province":"Mecklenburg-Vorpommern",
    "wof:name":"Nord Elektro Handels Gmbh",
    "wof:placetype":"venue"
},
  "geometry": {"coordinates":[13.0862131119,53.3362121582],"type":"Point"}
}