{
  "type": "Feature",
  "properties": {
    "iso:country":"DE",
    "sg:address":"Bankstr.",
    "sg:city":"Moers",
    "sg:postcode":"47441",
    "sg:province":"Nordrhein-Westfalen",
    "wof:name":"Vertrauens\u00e4rztlicher-dienst D. Lva Rheinprovinz",
    "wof:placetype":"venue"
},
  "geometry": {"coordinates":[6.6386752129,51.4507331848],"type":"Point"}
}