{
  "type": "Feature",
  "properties": {
    "iso:country":"DE",
    "sg:address":"Westernmauer 5",
    "sg:city":"Paderborn",
    "sg:phone":"+49 5251/22482",
    "sg:postcode":"33098",
    "sg:province":"Nordrhein-Westfalen",
    "wof:name":"Pizzeria Pinocchio",
    "wof:placetype":"venue"
},
  "geometry": {"coordinates":[8.7470598221,51.7160835266],"type":"Point"}
}