{
  "type": "Feature",
  "properties": {
    "iso:country":"DE",
    "sg:address":"Nassauische Str. 17b",
    "sg:city":"Bad Marienberg",
    "sg:phone":"+49 2661/938729",
    "sg:postcode":"56470",
    "sg:province":"Rheinland-Pfalz",
    "wof:name":"Iwb Industriewarenhandels- Und Beratungsgesellschaft Mbh",
    "wof:placetype":"venue"
},
  "geometry": {"coordinates":[7.956979,50.64872],"type":"Point"}
}