{
  "type": "Feature",
  "properties": {
    "iso:country":"DE",
    "sg:address":"Hans-B\u00f6ckler-Str. 1",
    "sg:city":"L\u00fcbeck",
    "sg:phone":"+49 451/588275",
    "sg:postcode":"23560",
    "sg:province":"Schleswig-Holstein",
    "wof:name":"Fachvermittlung F\u00fcr Seeleute Heuerstelle L\u00fcbeck",
    "wof:placetype":"venue"
},
  "geometry": {"coordinates":[10.680013,53.851501],"type":"Point"}
}