{
  "type": "Feature",
  "properties": {
    "iso:country":"DE",
    "sg:address":"Bienenstr. 5",
    "sg:city":"Heidelberg",
    "sg:phone":"+49 6221/164141",
    "sg:postcode":"69117",
    "sg:province":"Baden-W\u00fcrttemberg",
    "wof:name":"Zentralarchiv Zur Erforschung Der Geschichte Der Juden In",
    "wof:placetype":"venue"
},
  "geometry": {"coordinates":[8.701364,49.411518],"type":"Point"}
}