{
  "type": "Feature",
  "properties": {
    "iso:country":"DE",
    "sg:address":"Haagstr. 33",
    "sg:city":"Friedberg",
    "sg:postcode":"61169",
    "sg:province":"Hessen",
    "wof:name":"Kath. \u00d6ffentliche Bibliothek St. Marien",
    "wof:placetype":"venue"
},
  "geometry": {"coordinates":[8.756755,50.336277],"type":"Point"}
}