{
  "type": "Feature",
  "properties": {
    "iso:country":"DE",
    "sg:address":"F\u00fcrstenauer Str. 12",
    "sg:city":"Voltlage",
    "sg:phone":"+49 5467/1210",
    "sg:postcode":"49599",
    "sg:province":"Niedersachsen",
    "wof:name":"Clemens Wulfern",
    "wof:placetype":"venue"
},
  "geometry": {"coordinates":[7.745127,52.452694],"type":"Point"}
}