{
  "type": "Feature",
  "properties": {
    "iso:country":"DE",
    "sg:address":"Horster Str. 15",
    "sg:city":"Bottrop",
    "sg:postcode":"46236",
    "sg:province":"Nordrhein-Westfalen",
    "wof:name":"Mediability Gmbh",
    "wof:placetype":"venue"
},
  "geometry": {"coordinates":[6.928421,51.523029],"type":"Point"}
}