{
  "type": "Feature",
  "properties": {
    "iso:country":"DE",
    "sg:address":"Templergraben 86-90",
    "sg:city":"Aachen",
    "sg:phone":"+49 241/801",
    "sg:postcode":"52062",
    "sg:province":"Nordrhein-Westfalen",
    "wof:name":"Institut F\u00fcr Kraftfahrwesen Und Kolbenmaschinen Der Th",
    "wof:placetype":"venue"
},
  "geometry": {"coordinates":[6.080545,50.778538],"type":"Point"}
}