{
  "type": "Feature",
  "properties": {
    "iso:country":"DE",
    "sg:address":"Am Sportpark 2",
    "sg:city":"Salzgitter",
    "sg:phone":"+49 5341/265697",
    "sg:postcode":"38239",
    "sg:province":"Niedersachsen",
    "wof:name":"Blumenhaus Am Sportpark",
    "wof:placetype":"venue"
},
  "geometry": {"coordinates":[10.480425,52.190651],"type":"Point"}
}