{
  "type": "Feature",
  "properties": {
    "iso:country":"DE",
    "sg:address":"Kaiserstr. 17",
    "sg:city":"L\u00fcbbecke",
    "sg:phone":"+49 5741/250986",
    "sg:postcode":"32312",
    "sg:province":"Nordrhein-Westfalen",
    "wof:name":"M\u00fchlengarten Service Gmbh",
    "wof:placetype":"venue"
},
  "geometry": {"coordinates":[8.6073904037,52.3039093018],"type":"Point"}
}