{
  "type": "Feature",
  "properties": {
    "iso:country":"DE",
    "sg:address":"Willaberg 3",
    "sg:city":"Bodenkirchen",
    "sg:phone":"+49 8745/1496",
    "sg:postcode":"84155",
    "sg:province":"Bayern",
    "wof:name":"Bia Vertrieb Und Marketing Gmbh",
    "wof:placetype":"venue"
},
  "geometry": {"coordinates":[12.432372,48.405373],"type":"Point"}
}