{
  "type": "Feature",
  "properties": {
    "iso:country":"DE",
    "sg:address":"Untere Grabenstr. 2",
    "sg:city":"Leutkirch",
    "sg:phone":"+49 7561/2686",
    "sg:postcode":"88299",
    "sg:province":"Baden-W\u00fcrttemberg",
    "wof:name":"Richard Wagenseil Haus- Und K\u00fcchenger\u00e4te",
    "wof:placetype":"venue"
},
  "geometry": {"coordinates":[10.0237197876,47.8250389099],"type":"Point"}
}