{
  "type": "Feature",
  "properties": {
    "iso:country":"DE",
    "sg:address":"Schlo\u00dfseeallee 28",
    "sg:city":"Salem",
    "sg:phone":"+49 7553/6627",
    "sg:postcode":"88682",
    "sg:province":"Baden-W\u00fcrttemberg",
    "wof:name":"H. Hasiwa",
    "wof:placetype":"venue"
},
  "geometry": {"coordinates":[9.2962875366,47.7676925659],"type":"Point"}
}