{
  "type": "Feature",
  "properties": {
    "iso:country":"DE",
    "sg:address":"Otto-Decker-Str. 4",
    "sg:city":"Idar-Oberstein",
    "sg:phone":"+49 6781/28044",
    "sg:postcode":"55743",
    "sg:province":"Rheinland-Pfalz",
    "wof:name":"Engel-apotheke",
    "wof:placetype":"venue"
},
  "geometry": {"coordinates":[7.323932,49.702122],"type":"Point"}
}