{
  "type": "Feature",
  "properties": {
    "iso:country":"DE",
    "sg:address":"Hansaring 45-47",
    "sg:city":"K\u00f6ln",
    "sg:phone":"+49 221/133818",
    "sg:postcode":"50670",
    "sg:province":"Nordrhein-Westfalen",
    "wof:name":"Mahlburg Haus- Und Verm\u00f6gensverwaltung Gmbh",
    "wof:placetype":"venue"
},
  "geometry": {"coordinates":[6.9463701248,50.9470100403],"type":"Point"}
}