{
  "type": "Feature",
  "properties": {
    "iso:country":"DE",
    "sg:address":"Mittelstr. 49",
    "sg:city":"Horn-Bad Meinberg",
    "sg:phone":"+49 5234/5544",
    "sg:postcode":"32805",
    "sg:province":"Nordrhein-Westfalen",
    "wof:name":"Reiseb\u00fcro Josef Gemke Inh. Franz Schuchard",
    "wof:placetype":"venue"
},
  "geometry": {"coordinates":[8.9422216415,51.8722229004],"type":"Point"}
}