{
  "type": "Feature",
  "properties": {
    "iso:country":"DE",
    "sg:address":"Lienlas 20",
    "sg:city":"Kirchenpingarten",
    "sg:phone":"+49 9278/348",
    "sg:postcode":"95466",
    "sg:province":"Bayern",
    "wof:name":"Georg Pirner",
    "wof:placetype":"venue"
},
  "geometry": {"coordinates":[11.821911,49.92234],"type":"Point"}
}