{
  "type": "Feature",
  "properties": {
    "iso:country":"DE",
    "sg:address":"Am Stutenanger 6",
    "sg:city":"Oberschlei\u00dfheim",
    "sg:phone":"+49 89/3155434",
    "sg:postcode":"85764",
    "sg:province":"Bayern",
    "wof:name":"Thomas Summerauer",
    "wof:placetype":"venue"
},
  "geometry": {"coordinates":[11.5511798859,48.2559394836],"type":"Point"}
}