{
  "type": "Feature",
  "properties": {
    "iso:country":"DE",
    "sg:address":"Kreuzstr. 289",
    "sg:city":"Marl",
    "sg:phone":"+49 2365/18686",
    "sg:postcode":"45770",
    "sg:province":"Nordrhein-Westfalen",
    "wof:name":"Bdn-biomed. Privatinstitut F\u00fcr Feinstoffliche Diagnostik",
    "wof:placetype":"venue"
},
  "geometry": {"coordinates":[7.0967588425,51.6489524841],"type":"Point"}
}