{
  "type": "Feature",
  "properties": {
    "iso:country":"DE",
    "sg:address":"Huyssenallee 87",
    "sg:city":"Essen",
    "sg:phone":"+49 201/821630",
    "sg:postcode":"45128",
    "sg:province":"Nordrhein-Westfalen",
    "wof:name":"Wolfgang Strau\u00df Und Dr. Wolf D. Sondermann",
    "wof:placetype":"venue"
},
  "geometry": {"coordinates":[7.0087752342,51.4447669983],"type":"Point"}
}