{
  "type": "Feature",
  "properties": {
    "iso:country":"DE",
    "sg:address":"Hachen 2",
    "sg:city":"Lennestadt",
    "sg:phone":"+49 2721/83041",
    "sg:postcode":"57368",
    "sg:province":"Nordrhein-Westfalen",
    "wof:name":"Holzbearbeitung Richard Gmbh",
    "wof:placetype":"venue"
},
  "geometry": {"coordinates":[8.060804,51.142212],"type":"Point"}
}