{
  "type": "Feature",
  "properties": {
    "iso:country":"DE",
    "sg:address":"B\u00fclowallee 6",
    "sg:city":"Norderney",
    "sg:phone":"+49 4932/880",
    "sg:postcode":"26548",
    "sg:province":"Niedersachsen",
    "wof:name":"Nordseeklinik Gmbh & Co. Kg Norderney",
    "wof:placetype":"venue"
},
  "geometry": {"coordinates":[7.146238,53.70451],"type":"Point"}
}