{
  "type": "Feature",
  "properties": {
    "iso:country":"DE",
    "sg:address":"Gronaustr. 8",
    "sg:city":"Troisdorf",
    "sg:phone":"+49 228/451707",
    "sg:postcode":"53844",
    "sg:province":"Nordrhein-Westfalen",
    "wof:name":"Dach & Wand-fachbuchversand Inh. Christel H\u00f6gemann",
    "wof:placetype":"venue"
},
  "geometry": {"coordinates":[7.1056199074,50.7789001465],"type":"Point"}
}