{
  "type": "Feature",
  "properties": {
    "iso:country":"DE",
    "sg:address":"Silberbergstr. 1",
    "sg:city":"Hof",
    "sg:phone":"+49 9281/65041",
    "sg:postcode":"95030",
    "sg:province":"Bayern",
    "wof:name":"Siegfried Schlegel Architekt",
    "wof:placetype":"venue"
},
  "geometry": {"coordinates":[11.893429,50.328011],"type":"Point"}
}