{
  "type": "Feature",
  "properties": {
    "iso:country":"DE",
    "sg:address":"Am Niedwald 21",
    "sg:city":"Frankfurt",
    "sg:phone":"+49 69/393410",
    "sg:postcode":"65933",
    "sg:province":"Hessen",
    "wof:name":"J\u00fcrgen M\u00e4hler",
    "wof:placetype":"venue"
},
  "geometry": {"coordinates":[8.595243,50.111298],"type":"Point"}
}