{
  "type": "Feature",
  "properties": {
    "iso:country":"DE",
    "sg:address":"Kasernenstr. 2",
    "sg:city":"Coburg",
    "sg:phone":"+49 9561/75557",
    "sg:postcode":"96450",
    "sg:province":"Bayern",
    "wof:name":"Hugo Uebel",
    "wof:placetype":"venue"
},
  "geometry": {"coordinates":[10.9651288986,50.2657356262],"type":"Point"}
}