{
  "type": "Feature",
  "properties": {
    "iso:country":"DE",
    "sg:address":"Meglingerstr. 64",
    "sg:city":"M\u00fcnchen",
    "sg:phone":"+49 89/7803",
    "sg:postcode":"81477",
    "sg:province":"Bayern",
    "wof:name":"Deutsche Industriewartung Gmbh",
    "wof:placetype":"venue"
},
  "geometry": {"coordinates":[11.506792,48.089256],"type":"Point"}
}