{
  "type": "Feature",
  "properties": {
    "iso:country":"DE",
    "sg:address":"Wildenreuth I 2",
    "sg:city":"Erbendorf",
    "sg:phone":"+49 9682/1783",
    "sg:postcode":"92681",
    "sg:province":"Bayern",
    "wof:name":"G. Frieser Elektroinstallation",
    "wof:placetype":"venue"
},
  "geometry": {"coordinates":[12.077357,49.798393],"type":"Point"}
}