{
  "type": "Feature",
  "properties": {
    "iso:country":"DE",
    "sg:address":"Sandweg 33",
    "sg:city":"Weener",
    "sg:phone":"+49 4951/2106",
    "sg:postcode":"26826",
    "sg:province":"Niedersachsen",
    "wof:name":"Hinderk Groenewold",
    "wof:placetype":"venue"
},
  "geometry": {"coordinates":[7.3211221695,53.1766700745],"type":"Point"}
}