{
  "type": "Feature",
  "properties": {
    "iso:country":"DE",
    "sg:address":"Walpurgisstr. 19",
    "sg:city":"Dresden",
    "sg:phone":"+49 351/4956782",
    "sg:postcode":"01069",
    "sg:province":"Sachsen",
    "wof:name":"Residenz Touristik",
    "wof:placetype":"venue"
},
  "geometry": {"coordinates":[13.7412385941,51.0422096252],"type":"Point"}
}