{
  "type": "Feature",
  "properties": {
    "iso:country":"DE",
    "sg:address":"Holzer Str. 64 - 66",
    "sg:city":"J\u00fcchen",
    "sg:phone":"+49 2164/2247",
    "sg:postcode":"41363",
    "sg:province":"Nordrhein-Westfalen",
    "wof:name":"Glen Saxon Textil Gmbh",
    "wof:placetype":"venue"
},
  "geometry": {"coordinates":[6.4552788734,51.0981750488],"type":"Point"}
}