{
  "type": "Feature",
  "properties": {
    "iso:country":"DE",
    "sg:address":"Am Deverhafen 15",
    "sg:city":"Papenburg",
    "sg:postcode":"26871",
    "sg:province":"Niedersachsen",
    "wof:name":"Deutsche Tailleur Papenburg Gmbh & Co. Kg",
    "wof:placetype":"venue"
},
  "geometry": {"coordinates":[7.377705,53.087486],"type":"Point"}
}