{
  "type": "Feature",
  "properties": {
    "iso:country":"DE",
    "sg:address":"Amtmannsweg 30",
    "sg:city":"Harpstedt",
    "sg:postcode":"27243",
    "sg:province":"Niedersachsen",
    "wof:name":"Art-design",
    "wof:placetype":"venue"
},
  "geometry": {"coordinates":[8.598198,52.912422],"type":"Point"}
}