{
  "type": "Feature",
  "properties": {
    "iso:country":"DE",
    "sg:address":"Talstr. 41",
    "sg:city":"Malsch",
    "sg:phone":"+49 7246/6258",
    "sg:postcode":"76316",
    "sg:province":"Baden-W\u00fcrttemberg",
    "wof:name":"Herbert J\u00e4ger",
    "wof:placetype":"venue"
},
  "geometry": {"coordinates":[8.3316116333,48.8576927185],"type":"Point"}
}