{
  "type": "Feature",
  "properties": {
    "iso:country":"DE",
    "sg:address":"Landsberger Str. 57",
    "sg:city":"Inning",
    "sg:phone":"+49 8143/997717",
    "sg:postcode":"82266",
    "sg:province":"Bayern",
    "wof:name":"Kino Im Brauhaus Stegen",
    "wof:placetype":"venue"
},
  "geometry": {"coordinates":[11.15244,48.07671],"type":"Point"}
}