{
  "type": "Feature",
  "properties": {
    "iso:country":"DE",
    "sg:address":"Am Ravelsberg 14",
    "sg:city":"Aachen",
    "sg:phone":"+49 241/163437",
    "sg:postcode":"52080",
    "sg:province":"Nordrhein-Westfalen",
    "wof:name":"Hans-gerd Koch Ingenieur",
    "wof:placetype":"venue"
},
  "geometry": {"coordinates":[6.1204199791,50.8019180298],"type":"Point"}
}