{
  "type": "Feature",
  "properties": {
    "iso:country":"DE",
    "sg:address":"Noldenkothen 13",
    "sg:city":"Ratingen",
    "sg:postcode":"40882",
    "sg:province":"Nordrhein-Westfalen",
    "wof:name":"Techsus Agentur F\u00fcr Direkt- Marketing Und Vertrieb Gmbh",
    "wof:placetype":"venue"
},
  "geometry": {"coordinates":[6.8769187927,51.3007202148],"type":"Point"}
}