{
  "type": "Feature",
  "properties": {
    "iso:country":"DE",
    "sg:address":"Brunsb\u00fctteler Damm 312",
    "sg:city":"Berlin",
    "sg:phone":"+49 30/3661007",
    "sg:postcode":"13591",
    "sg:province":"Berlin",
    "wof:name":"Ev. Pfarramt Dorf-gemeinde Staaken",
    "wof:placetype":"venue"
},
  "geometry": {"coordinates":[13.1494007111,52.5330200195],"type":"Point"}
}