{
  "type": "Feature",
  "properties": {
    "iso:country":"DE",
    "sg:address":"Falkenstr. 3",
    "sg:city":"Margetsh\u00f6chheim",
    "sg:phone":"+49 931/461079",
    "sg:postcode":"97276",
    "sg:province":"Bayern",
    "wof:name":"Oskar Flach",
    "wof:placetype":"venue"
},
  "geometry": {"coordinates":[9.8624649048,49.8403930664],"type":"Point"}
}