{
  "type": "Feature",
  "properties": {
    "iso:country":"DE",
    "sg:address":"Bebelstr. 9",
    "sg:city":"Wolfsburg",
    "sg:phone":"+49 5361/21677",
    "sg:postcode":"38440",
    "sg:province":"Niedersachsen",
    "wof:name":"Birgit Schreyer",
    "wof:placetype":"venue"
},
  "geometry": {"coordinates":[10.788328,52.417843],"type":"Point"}
}