{
  "type": "Feature",
  "properties": {
    "iso:country":"DE",
    "sg:address":"Im Stillen Eck 20",
    "sg:city":"Marl",
    "sg:phone":"+49 2365/96940",
    "sg:postcode":"45768",
    "sg:province":"Nordrhein-Westfalen",
    "wof:name":"Werner M. Tappe",
    "wof:placetype":"venue"
},
  "geometry": {"coordinates":[7.0751810074,51.6655883789],"type":"Point"}
}