{
  "type": "Feature",
  "properties": {
    "iso:country":"DE",
    "sg:address":"Heinrich-Bauer-Str. 8",
    "sg:city":"Dresden",
    "sg:phone":"+49 351/2005089",
    "sg:postcode":"01259",
    "sg:province":"Sachsen",
    "wof:name":"Dr. Martin Eckert Ingenieur",
    "wof:placetype":"venue"
},
  "geometry": {"coordinates":[13.8562173843,51.0026435852],"type":"Point"}
}