{
  "type": "Feature",
  "properties": {
    "iso:country":"DE",
    "sg:address":"Mauserstr. 17",
    "sg:city":"Ludwigsburg",
    "sg:phone":"+49 7141/86821",
    "sg:postcode":"71640",
    "sg:province":"Baden-W\u00fcrttemberg",
    "wof:name":"G\u00fcnter Dussling Gmbh",
    "wof:placetype":"venue"
},
  "geometry": {"coordinates":[9.236389,48.892208],"type":"Point"}
}