{
  "type": "Feature",
  "properties": {
    "iso:country":"DE",
    "sg:address":"Kaiserberg 7",
    "sg:city":"Erbendorf",
    "sg:phone":"+49 9682/2243",
    "sg:postcode":"92681",
    "sg:province":"Bayern",
    "wof:name":"Simon Mihl",
    "wof:placetype":"venue"
},
  "geometry": {"coordinates":[12.0473823547,49.8389892578],"type":"Point"}
}