{
  "type": "Feature",
  "properties": {
    "iso:country":"DE",
    "sg:address":"Halberst\u00e4dter Str. 15",
    "sg:city":"Goslar",
    "sg:phone":"+49 4922/0492690",
    "sg:postcode":"38644",
    "sg:province":"Niedersachsen",
    "wof:name":"Grindus Ag",
    "wof:placetype":"venue"
},
  "geometry": {"coordinates":[7.135161,50.958706],"type":"Point"}
}