{
  "type": "Feature",
  "properties": {
    "iso:country":"DE",
    "sg:address":"Nedensdorf 1",
    "sg:city":"Staffelstein",
    "sg:phone":"+49 9573/5729",
    "sg:postcode":"96231",
    "sg:province":"Bayern",
    "wof:name":"Fritz Leicht",
    "wof:placetype":"venue"
},
  "geometry": {"coordinates":[10.968542099,50.1152458191],"type":"Point"}
}