{
  "type": "Feature",
  "properties": {
    "iso:country":"DE",
    "sg:address":"Grombacher Str. 23",
    "sg:city":"Bad Rappenau",
    "sg:phone":"+49 7268/1353",
    "sg:postcode":"74906",
    "sg:province":"Baden-W\u00fcrttemberg",
    "wof:name":"Thai-fashion",
    "wof:placetype":"venue"
},
  "geometry": {"coordinates":[9.039081,49.253693],"type":"Point"}
}