{
  "type": "Feature",
  "properties": {
    "iso:country":"DE",
    "sg:address":"Pestalozzistr. 4523",
    "sg:city":"Pirmasens",
    "sg:postcode":"66953",
    "sg:province":"Rheinland-Pfalz",
    "wof:name":"Quasimoto Motorrad-zubeh\u00f6r Handel",
    "wof:placetype":"venue"
},
  "geometry": {"coordinates":[7.6082901955,49.2126808167],"type":"Point"}
}