{
  "type": "Feature",
  "properties": {
    "iso:country":"DE",
    "sg:address":"Kniebisstr. 28",
    "sg:city":"Ditzingen",
    "sg:phone":"+49 7156/8217",
    "sg:postcode":"71254",
    "sg:province":"Baden-W\u00fcrttemberg",
    "wof:name":"R. Hafner Gmbh",
    "wof:placetype":"venue"
},
  "geometry": {"coordinates":[9.0745096207,48.8206787109],"type":"Point"}
}