{
  "type": "Feature",
  "properties": {
    "iso:country":"DE",
    "sg:address":"Schumacherstr. 91",
    "sg:city":"Hamburg",
    "sg:phone":"+49 40/388158",
    "sg:postcode":"22767",
    "sg:province":"Hamburg",
    "wof:name":"Wolfgang Schmidt Und Wolfgang Naujok",
    "wof:placetype":"venue"
},
  "geometry": {"coordinates":[9.943339,53.554653],"type":"Point"}
}