{
  "type": "Feature",
  "properties": {
    "iso:country":"DE",
    "sg:address":"Genovevastr. 94",
    "sg:city":"K\u00f6ln",
    "sg:postcode":"51063",
    "sg:province":"Nordrhein-Westfalen",
    "wof:name":"Concepta Liegenschafts- Verwaltungsges. Mbh & Co. Kg",
    "wof:placetype":"venue"
},
  "geometry": {"coordinates":[7.0086131096,50.9658699036],"type":"Point"}
}