{
  "type": "Feature",
  "properties": {
    "iso:country":"DE",
    "sg:city":"Straubing",
    "sg:phone":"+49 9421/89710",
    "sg:postcode":"94315",
    "sg:province":"Bayern",
    "wof:name":"Incerto",
    "wof:placetype":"venue"
},
  "geometry": {"coordinates":[12.573706,48.881397],"type":"Point"}
}