{
  "type": "Feature",
  "properties": {
    "iso:country":"DE",
    "sg:address":"Thomastr. 7",
    "sg:city":"B\u00fcrgstadt",
    "sg:phone":"+49 9371/80475",
    "sg:postcode":"63927",
    "sg:province":"Bayern",
    "wof:name":"Eww Markt",
    "wof:placetype":"venue"
},
  "geometry": {"coordinates":[9.2746429443,49.7193336487],"type":"Point"}
}