{
  "type": "Feature",
  "properties": {
    "iso:country":"DE",
    "sg:address":"Savellistr. 10",
    "sg:city":"Rheinfelden",
    "sg:postcode":"79618",
    "sg:province":"Baden-W\u00fcrttemberg",
    "wof:name":"Flugschule Hochrhein-baar",
    "wof:placetype":"venue"
},
  "geometry": {"coordinates":[7.801669,47.580002],"type":"Point"}
}