{
  "type": "Feature",
  "properties": {
    "iso:country":"DE",
    "sg:address":"Walkm\u00fchlstr. 10",
    "sg:city":"Erfurt",
    "sg:phone":"+49 361/590160",
    "sg:postcode":"99084",
    "sg:province":"Th\u00fcringen",
    "wof:name":"Wirtschafts- Und Steuerberatungs Gmbh",
    "wof:placetype":"venue"
},
  "geometry": {"coordinates":[11.0216312408,50.9710159302],"type":"Point"}
}