{
  "type": "Feature",
  "properties": {
    "iso:country":"DE",
    "sg:address":"Mellinghausstr. 13",
    "sg:city":"Herdecke",
    "sg:phone":"+49 2330/3900",
    "sg:postcode":"58313",
    "sg:province":"Nordrhein-Westfalen",
    "wof:name":"Peter Klomp Architekt",
    "wof:placetype":"venue"
},
  "geometry": {"coordinates":[7.437128,51.401669],"type":"Point"}
}