{
  "type": "Feature",
  "properties": {
    "iso:country":"DE",
    "sg:address":"Bahnhofstr. 34",
    "sg:city":"K\u00f6ln",
    "sg:postcode":"51143",
    "sg:province":"Nordrhein-Westfalen",
    "wof:name":"City-hosen Goergens Gmbh",
    "wof:placetype":"venue"
},
  "geometry": {"coordinates":[7.058071,50.883533],"type":"Point"}
}