{
  "type": "Feature",
  "properties": {
    "iso:country":"DE",
    "sg:address":"Freiheitstr. 104",
    "sg:city":"Remscheid",
    "sg:phone":"+49 2191/41011",
    "sg:postcode":"42853",
    "sg:province":"Nordrhein-Westfalen",
    "wof:name":"Michael Grote",
    "wof:placetype":"venue"
},
  "geometry": {"coordinates":[7.1864509583,51.17760849],"type":"Point"}
}