{
  "type": "Feature",
  "properties": {
    "iso:country":"DE",
    "sg:address":"Visbeker Str. 9",
    "sg:city":"Visbek",
    "sg:postcode":"49429",
    "sg:province":"Niedersachsen",
    "wof:name":"Ir Unipork Gmbh",
    "wof:placetype":"venue"
},
  "geometry": {"coordinates":[8.3723716736,52.839214325],"type":"Point"}
}