{
  "type": "Feature",
  "properties": {
    "iso:country":"DE",
    "sg:address":"Irisweg 6",
    "sg:city":"D\u00fcren",
    "sg:phone":"+49 2421/81676",
    "sg:postcode":"52353",
    "sg:province":"Nordrhein-Westfalen",
    "wof:name":"P. Michels",
    "wof:placetype":"venue"
},
  "geometry": {"coordinates":[6.439781189,50.8157234192],"type":"Point"}
}