{
  "type": "Feature",
  "properties": {
    "iso:country":"DE",
    "sg:address":"Louisenstr. 89",
    "sg:city":"Bad Homburg",
    "sg:phone":"+49 6172/20360",
    "sg:postcode":"61348",
    "sg:province":"Hessen",
    "wof:name":"Frottee-boutique",
    "wof:placetype":"venue"
},
  "geometry": {"coordinates":[8.6191177368,50.2255554199],"type":"Point"}
}