{
  "type": "Feature",
  "properties": {
    "iso:country":"DE",
    "sg:address":"M\u00fcnchner Str. 2",
    "sg:city":"Berg",
    "sg:phone":"+49 8151/12834",
    "sg:postcode":"82335",
    "sg:province":"Bayern",
    "wof:name":"Monika Sedlmayr-groeger Und Edward Groeger",
    "wof:placetype":"venue"
},
  "geometry": {"coordinates":[11.3625259399,47.9837760925],"type":"Point"}
}