{
  "type": "Feature",
  "properties": {
    "iso:country":"DE",
    "sg:address":"Windausweg 2",
    "sg:city":"G\u00f6ttingen",
    "sg:phone":"+49 551/394910",
    "sg:postcode":"37073",
    "sg:province":"Niedersachsen",
    "wof:name":"Universit\u00e4t G\u00f6ttingen Abteilung Rechtsmedizin",
    "wof:placetype":"venue"
},
  "geometry": {"coordinates":[9.9299621582,51.5227661133],"type":"Point"}
}