{
  "type": "Feature",
  "properties": {
    "iso:country":"DE",
    "sg:address":"Hilpert 2",
    "sg:city":"Vellberg",
    "sg:phone":"+49 7907/1746",
    "sg:postcode":"74541",
    "sg:province":"Baden-W\u00fcrttemberg",
    "wof:name":"Belle Fleur Kosmetik - Natur E. K.",
    "wof:placetype":"venue"
},
  "geometry": {"coordinates":[9.908205,49.101665],"type":"Point"}
}