{
  "type": "Feature",
  "properties": {
    "iso:country":"DE",
    "sg:address":"Gro\u00dfe Rittergasse 75",
    "sg:city":"Frankfurt",
    "sg:phone":"+49 69/96202723",
    "sg:postcode":"60594",
    "sg:province":"Hessen",
    "wof:name":"Altes Haus",
    "wof:placetype":"venue"
},
  "geometry": {"coordinates":[8.6908054352,50.1059494019],"type":"Point"}
}