{
  "type": "Feature",
  "properties": {
    "iso:country":"DE",
    "sg:address":"Rosenheimer Str. 4",
    "sg:city":"Wasserburg",
    "sg:phone":"+49 8071/3070",
    "sg:postcode":"83512",
    "sg:province":"Bayern",
    "wof:name":"Bartsch Und Martin Notare",
    "wof:placetype":"venue"
},
  "geometry": {"coordinates":[12.2309055328,48.0582313538],"type":"Point"}
}