{
  "type": "Feature",
  "properties": {
    "iso:country":"DE",
    "sg:address":"S\u00e4chsische Str. 72",
    "sg:city":"Berlin",
    "sg:phone":"+49 30/88501080",
    "sg:postcode":"10707",
    "sg:province":"Berlin",
    "wof:name":"Klaus Mahlke & Partner Consulting Gmbh",
    "wof:placetype":"venue"
},
  "geometry": {"coordinates":[13.3190279007,52.4984588623],"type":"Point"}
}