{
  "type": "Feature",
  "properties": {
    "iso:country":"DE",
    "sg:address":"An der Kirche 6",
    "sg:city":"Lippetal",
    "sg:phone":"+49 2923/463",
    "sg:postcode":"59510",
    "sg:province":"Nordrhein-Westfalen",
    "wof:name":"Katholisches Pfarramt St. Stephanus",
    "wof:placetype":"venue"
},
  "geometry": {"coordinates":[8.0997219086,51.6337394714],"type":"Point"}
}