{
  "type": "Feature",
  "properties": {
    "iso:country":"DE",
    "sg:address":"Postfach 1254:: 49619 L\u00f6ningen:: Germany.^^Tabbenstr 20::",
    "sg:city":"L\u00f6ningen",
    "sg:phone":"+49 5432/840",
    "sg:postcode":"49624",
    "sg:province":"Niedersachsen",
    "wof:name":"Volksbank Eg L\u00f6ningen",
    "wof:placetype":"venue"
},
  "geometry": {"coordinates":[7.756497,52.733463],"type":"Point"}
}