{
  "type": "Feature",
  "properties": {
    "iso:country":"DE",
    "sg:address":"L\u00fcbecker Str. 10 a",
    "sg:city":"Ahrensburg",
    "sg:phone":"+49 4102/2300",
    "sg:postcode":"22926",
    "sg:province":"Schleswig-Holstein",
    "wof:name":"Park Hotel Ahrensburg Ohg",
    "wof:placetype":"venue"
},
  "geometry": {"coordinates":[10.2419700623,53.6814537048],"type":"Point"}
}