{
  "type": "Feature",
  "properties": {
    "iso:country":"DE",
    "sg:address":"Klinkertorplatz 1",
    "sg:city":"Augsburg",
    "sg:phone":"+49 821/346710",
    "sg:postcode":"86152",
    "sg:province":"Bayern",
    "wof:name":"Hansj\u00f6rg M\u00fcller Steuerberater",
    "wof:placetype":"venue"
},
  "geometry": {"coordinates":[10.8892412186,48.3713989258],"type":"Point"}
}