{
  "type": "Feature",
  "properties": {
    "iso:country":"DE",
    "sg:address":"Jakob-Faulhaber-Str. 6a",
    "sg:city":"Mannheim",
    "sg:phone":"+49 621/756552",
    "sg:postcode":"68305",
    "sg:province":"Baden-W\u00fcrttemberg",
    "wof:name":"Kl\u00e4 Amsel",
    "wof:placetype":"venue"
},
  "geometry": {"coordinates":[8.4807052612,49.5257301331],"type":"Point"}
}