{
  "type": "Feature",
  "properties": {
    "iso:country":"DE",
    "sg:address":"An der Lehmgrube 17",
    "sg:city":"\u00d6hringen",
    "sg:phone":"+49 7941/943310",
    "sg:postcode":"74613",
    "sg:province":"Baden-W\u00fcrttemberg",
    "wof:name":"Sporthotel \u00d6hringen Gmbh",
    "wof:placetype":"venue"
},
  "geometry": {"coordinates":[9.4837465286,49.1930160522],"type":"Point"}
}