{
  "type": "Feature",
  "properties": {
    "iso:country":"DE",
    "sg:address":"Stemmer Weingarten 46",
    "sg:city":"Minden",
    "sg:phone":"+49 4957/149116",
    "sg:postcode":"32425",
    "sg:province":"Nordrhein-Westfalen",
    "wof:name":"Stemmer Massivholzm\u00d6bel Kl\u00d6pper Gmbh",
    "wof:placetype":"venue"
},
  "geometry": {"coordinates":[8.8738775253,52.3260574341],"type":"Point"}
}