{
  "type": "Feature",
  "properties": {
    "iso:country":"DE",
    "sg:address":"Nord-West-Ring 27",
    "sg:city":"Augustdorf",
    "sg:phone":"+49 5237/96990",
    "sg:postcode":"32832",
    "sg:province":"Nordrhein-Westfalen",
    "wof:name":"Teuto-glasveredlung Gmbh & Co. Kg",
    "wof:placetype":"venue"
},
  "geometry": {"coordinates":[8.7041501999,51.9064598083],"type":"Point"}
}