{
  "type": "Feature",
  "properties": {
    "iso:country":"DE",
    "sg:address":"Sportweg 14",
    "sg:city":"Raschau",
    "sg:phone":"+49 3774/26237",
    "sg:postcode":"08352",
    "sg:province":"Sachsen",
    "wof:name":"Landfarm Pro Agrar Gmbh",
    "wof:placetype":"venue"
},
  "geometry": {"coordinates":[12.8420495987,50.5309181213],"type":"Point"}
}