{
  "type": "Feature",
  "properties": {
    "iso:country":"DE",
    "sg:address":"S\u00fcdstr. 23",
    "sg:city":"Donauw\u00f6rth",
    "sg:phone":"+49 906/6929",
    "sg:postcode":"86609",
    "sg:province":"Bayern",
    "wof:name":"Ev. Luth. Pfarramt",
    "wof:placetype":"venue"
},
  "geometry": {"coordinates":[10.7509155273,48.7213821411],"type":"Point"}
}