{
  "type": "Feature",
  "properties": {
    "iso:country":"DE",
    "sg:address":"G\u00f6rlitzer Str. 1",
    "sg:city":"Neuss",
    "sg:phone":"+49 2131/1740",
    "sg:postcode":"41460",
    "sg:province":"Nordrhein-Westfalen",
    "wof:name":"United Parcel Service Deutschland Inc.",
    "wof:placetype":"venue"
},
  "geometry": {"coordinates":[6.7202768326,51.2022781372],"type":"Point"}
}