{
  "type": "Feature",
  "properties": {
    "iso:country":"DE",
    "sg:address":"Karlshagener Weg 3",
    "sg:city":"Dresden",
    "sg:postcode":"01109",
    "sg:province":"Sachsen",
    "wof:name":"S\u00e4ugling- Und Kleinkinderheim",
    "wof:placetype":"venue"
},
  "geometry": {"coordinates":[13.7739057541,51.1171913147],"type":"Point"}
}