{
  "type": "Feature",
  "properties": {
    "iso:country":"DE",
    "sg:address":"Hafnerweg 5",
    "sg:city":"Baden-Baden",
    "sg:phone":"+49 7221/181931",
    "sg:postcode":"76532",
    "sg:province":"Baden-W\u00fcrttemberg",
    "wof:name":"Kehler Industriebau Gmbh",
    "wof:placetype":"venue"
},
  "geometry": {"coordinates":[8.221021,48.786926],"type":"Point"}
}