{
  "type": "Feature",
  "properties": {
    "iso:country":"DE",
    "sg:address":"Fuggerstr. 27",
    "sg:city":"Berlin",
    "sg:phone":"+49 30/2116642",
    "sg:postcode":"10777",
    "sg:province":"Berlin",
    "wof:name":"Trattoria A Muntagnola",
    "wof:placetype":"venue"
},
  "geometry": {"coordinates":[13.3439674377,52.4988555908],"type":"Point"}
}