{
  "type": "Feature",
  "properties": {
    "iso:country":"DE",
    "sg:address":"Banter Weg 24",
    "sg:city":"Wilhelmshaven",
    "sg:phone":"+49 4421/201020",
    "sg:postcode":"26389",
    "sg:province":"Niedersachsen",
    "wof:name":"Wsz Wilhelmshavener Stahlhandel Und Zuschnitt-",
    "wof:placetype":"venue"
},
  "geometry": {"coordinates":[8.0909023285,53.5176315308],"type":"Point"}
}