{
  "type": "Feature",
  "properties": {
    "iso:country":"DE",
    "sg:address":"Maria Trost 25",
    "sg:city":"Koblenz",
    "sg:phone":"+49 261/80700161",
    "sg:postcode":"56070",
    "sg:province":"Rheinland-Pfalz",
    "wof:name":"Infosoft Informations- U. Dokumentationssysteme Gmbh",
    "wof:placetype":"venue"
},
  "geometry": {"coordinates":[7.5796961784,50.3867073059],"type":"Point"}
}