{
  "type": "Feature",
  "properties": {
    "iso:country":"DE",
    "sg:address":"Stavener Str. 78",
    "sg:city":"Neubrandenburg",
    "sg:phone":"+49 395/4691364",
    "sg:postcode":"17034",
    "sg:province":"Mecklenburg-Vorpommern",
    "wof:name":"Ingenieurb\u00fcro Drews Elektrotechnik Gmbh",
    "wof:placetype":"venue"
},
  "geometry": {"coordinates":[13.2808647156,53.5685462952],"type":"Point"}
}