{
  "type": "Feature",
  "properties": {
    "iso:country":"DE",
    "sg:address":"Hiberniastr. 5",
    "sg:city":"Waltrop",
    "sg:postcode":"45731",
    "sg:province":"Nordrhein-Westfalen",
    "wof:name":"Manuscriptum Verlags- Buchhaltung Thomas Hoof Kg",
    "wof:placetype":"venue"
},
  "geometry": {"coordinates":[7.419254,51.618343],"type":"Point"}
}