{
  "type": "Feature",
  "properties": {
    "iso:country":"DE",
    "sg:address":"Mathias-Br\u00fcggen-Str. 148",
    "sg:city":"K\u00f6ln",
    "sg:phone":"+49 221/5948151",
    "sg:postcode":"50829",
    "sg:province":"Nordrhein-Westfalen",
    "wof:name":"Cnc-bearbeitungscenter B. Morawetz / K\u00f6ln",
    "wof:placetype":"venue"
},
  "geometry": {"coordinates":[6.882804,50.98695],"type":"Point"}
}