{
  "type": "Feature",
  "properties": {
    "iso:country":"DE",
    "sg:address":"Josefplatz 5",
    "sg:city":"D\u00fcsseldorf",
    "sg:phone":"+49 211/785119",
    "sg:postcode":"40227",
    "sg:province":"Nordrhein-Westfalen",
    "wof:name":"E. Bleiss",
    "wof:placetype":"venue"
},
  "geometry": {"coordinates":[6.803249,51.214226],"type":"Point"}
}