{
  "type": "Feature",
  "properties": {
    "iso:country":"DE",
    "sg:address":"Leutragraben 2-4",
    "sg:city":"Jena",
    "sg:phone":"+49 3641/89260",
    "sg:postcode":"07743",
    "sg:province":"Th\u00fcringen",
    "wof:name":"Uws Unternehmens- Beratung Gmbh",
    "wof:placetype":"venue"
},
  "geometry": {"coordinates":[11.583249,50.928215],"type":"Point"}
}