{
  "type": "Feature",
  "properties": {
    "iso:country":"DE",
    "sg:address":"Gundelsdorfer Str. 32",
    "sg:city":"Kronach",
    "sg:phone":"+49 9261/2528",
    "sg:postcode":"96317",
    "sg:province":"Bayern",
    "wof:name":"Konrad Welscher",
    "wof:placetype":"venue"
},
  "geometry": {"coordinates":[11.306632,50.26939],"type":"Point"}
}