{
  "type": "Feature",
  "properties": {
    "iso:country":"DE",
    "sg:address":"R\u00f6merstr. 5",
    "sg:city":"Trostberg",
    "sg:phone":"+49 8621/977623",
    "sg:postcode":"83308",
    "sg:province":"Bayern",
    "wof:name":"Alz Werbegrafik Kg",
    "wof:placetype":"venue"
},
  "geometry": {"coordinates":[12.5883207321,48.0465660095],"type":"Point"}
}