{
  "type": "Feature",
  "properties": {
    "iso:country":"DE",
    "sg:address":"Am Linder Kreuz 53",
    "sg:city":"K\u00f6ln",
    "sg:phone":"+49 2203/63711",
    "sg:postcode":"51147",
    "sg:province":"Nordrhein-Westfalen",
    "wof:name":"Karl Schenkelberg",
    "wof:placetype":"venue"
},
  "geometry": {"coordinates":[7.1005978584,50.8482513428],"type":"Point"}
}