{
  "type": "Feature",
  "properties": {
    "iso:country":"DE",
    "sg:address":"Clara-Zetkin-Str. 38",
    "sg:city":"Ludwigslust",
    "sg:phone":"+49 3874/29590",
    "sg:postcode":"19288",
    "sg:province":"Mecklenburg-Vorpommern",
    "wof:name":"Friedrich Lange",
    "wof:placetype":"venue"
},
  "geometry": {"coordinates":[11.4965391159,53.3226127625],"type":"Point"}
}