{
  "type": "Feature",
  "properties": {
    "iso:country":"DE",
    "sg:address":"Gro\u00dfe Gasse 367",
    "sg:city":"Badeborn",
    "sg:phone":"+49 39483/5920",
    "sg:postcode":"06493",
    "sg:province":"Sachsen-Anhalt",
    "wof:name":"Keunecke Feinkost Gmbh",
    "wof:placetype":"venue"
},
  "geometry": {"coordinates":[11.243181,51.765755],"type":"Point"}
}