{
  "type": "Feature",
  "properties": {
    "iso:country":"DE",
    "sg:address":"Magdeburger Str. 2",
    "sg:city":"Bad Sachsa",
    "sg:phone":"+49 5523/1288",
    "sg:postcode":"37441",
    "sg:province":"Niedersachsen",
    "wof:name":"Ingeburg Riebenstahl",
    "wof:placetype":"venue"
},
  "geometry": {"coordinates":[10.5639324188,51.5964355469],"type":"Point"}
}