{
  "type": "Feature",
  "properties": {
    "iso:country":"DE",
    "sg:address":"Steinheide 29",
    "sg:city":"T\u00f6nisvorst",
    "sg:phone":"+49 2151/798526",
    "sg:postcode":"47918",
    "sg:province":"Nordrhein-Westfalen",
    "wof:name":"Roulands Technischer Kundendienst Gmbh",
    "wof:placetype":"venue"
},
  "geometry": {"coordinates":[6.5037388802,51.338558197],"type":"Point"}
}