{
  "type": "Feature",
  "properties": {
    "iso:country":"DE",
    "sg:address":"Blumenstr. 5",
    "sg:city":"G\u00f6rlitz",
    "sg:phone":"+49 3581/42110",
    "sg:postcode":"02826",
    "sg:province":"Sachsen",
    "wof:name":"Philip J. O. Bernklau E. Kfm.",
    "wof:placetype":"venue"
},
  "geometry": {"coordinates":[14.988824,51.148655],"type":"Point"}
}