{
  "type": "Feature",
  "properties": {
    "iso:country":"DE",
    "sg:address":"Emilienstr. 14",
    "sg:city":"Essen",
    "sg:phone":"+49 201/8778630",
    "sg:postcode":"45128",
    "sg:province":"Nordrhein-Westfalen",
    "wof:name":"Lc-digitale Bildtechnik Bernd Armgart",
    "wof:placetype":"venue"
},
  "geometry": {"coordinates":[7.0148911476,51.4433555603],"type":"Point"}
}