{
  "type": "Feature",
  "properties": {
    "iso:country":"DE",
    "sg:address":"Wilhelm Bergnerstr. 1",
    "sg:city":"Glinde",
    "sg:phone":"+49 40/727402",
    "sg:postcode":"21509",
    "sg:province":"Schleswig-Holstein",
    "wof:name":"Tetra Pak Processing Gmbh",
    "wof:placetype":"venue"
},
  "geometry": {"coordinates":[10.2241249084,53.5294876099],"type":"Point"}
}