{
  "type": "Feature",
  "properties": {
    "iso:country":"DE",
    "sg:address":"Hauptstr. 12",
    "sg:city":"Geising",
    "sg:phone":"+49 35056/35418",
    "sg:postcode":"01778",
    "sg:province":"Sachsen",
    "wof:name":"Johannes Lehmann",
    "wof:placetype":"venue"
},
  "geometry": {"coordinates":[13.787399,50.761116],"type":"Point"}
}