{
  "type": "Feature",
  "properties": {
    "iso:country":"DE",
    "sg:address":"Schulstr. 24",
    "sg:city":"Theisbergstegen",
    "sg:phone":"+49 6381/3381",
    "sg:postcode":"66871",
    "sg:province":"Rheinland-Pfalz",
    "wof:name":"Friedrich Jung",
    "wof:placetype":"venue"
},
  "geometry": {"coordinates":[7.444012,49.516876],"type":"Point"}
}