{
  "type": "Feature",
  "properties": {
    "iso:country":"DE",
    "sg:address":"Togostr. 21",
    "sg:city":"Wuppertal",
    "sg:postcode":"42277",
    "sg:province":"Nordrhein-Westfalen",
    "wof:name":"Guido Giesler Gmbh",
    "wof:placetype":"venue"
},
  "geometry": {"coordinates":[7.235092,51.285484],"type":"Point"}
}