{
  "type": "Feature",
  "properties": {
    "iso:country":"DE",
    "sg:address":"An der Erftm\u00fcndung 1a",
    "sg:city":"Neuss",
    "sg:phone":"+49 2131/101524",
    "sg:postcode":"41468",
    "sg:province":"Nordrhein-Westfalen",
    "wof:name":"Great Cansiron Verm\u00f6gens- Verwaltung Gmbh",
    "wof:placetype":"venue"
},
  "geometry": {"coordinates":[6.7299389839,51.1808586121],"type":"Point"}
}