{
  "type": "Feature",
  "properties": {
    "iso:country":"DE",
    "sg:address":"Dampfm\u00fchlenstr. 18",
    "sg:city":"D\u00fcren",
    "sg:phone":"+49 2421/62551",
    "sg:postcode":"52355",
    "sg:province":"Nordrhein-Westfalen",
    "wof:name":"Multi Shop Versand Gmbh",
    "wof:placetype":"venue"
},
  "geometry": {"coordinates":[6.4362130165,50.7998352051],"type":"Point"}
}