{
  "type": "Feature",
  "properties": {
    "iso:country":"DE",
    "sg:address":"Herrenstr. 12",
    "sg:city":"Bad F\u00fcssing",
    "sg:phone":"+49 8537/278",
    "sg:postcode":"94072",
    "sg:province":"Bayern",
    "wof:name":"Katholisches Pfarramt St. Stephanus",
    "wof:placetype":"venue"
},
  "geometry": {"coordinates":[13.2595157623,48.3072853088],"type":"Point"}
}