{
  "type": "Feature",
  "properties": {
    "iso:country":"DE",
    "sg:address":"Bauschlotter Str. 29",
    "sg:city":"Pforzheim",
    "sg:phone":"+49 7231/52018",
    "sg:postcode":"75177",
    "sg:province":"Baden-W\u00fcrttemberg",
    "wof:name":"Schempf Gmbh",
    "wof:placetype":"venue"
},
  "geometry": {"coordinates":[8.711027,48.906986],"type":"Point"}
}