{
  "type": "Feature",
  "properties": {
    "iso:country":"DE",
    "sg:address":"Blumenstr. 30",
    "sg:city":"Dortmund",
    "sg:phone":"+49 231/821886",
    "sg:postcode":"44147",
    "sg:province":"Nordrhein-Westfalen",
    "wof:name":"A. Tempel",
    "wof:placetype":"venue"
},
  "geometry": {"coordinates":[7.4477548599,51.5185394287],"type":"Point"}
}