{
  "type": "Feature",
  "properties": {
    "iso:country":"DE",
    "sg:address":"Geisbachstr. 37",
    "sg:city":"Koblenz",
    "sg:phone":"+49 261/21589",
    "sg:postcode":"56072",
    "sg:province":"Rheinland-Pfalz",
    "wof:name":"Dr. Klaus-peter H\u00fcrter Tierarzt",
    "wof:placetype":"venue"
},
  "geometry": {"coordinates":[7.55539608,50.3582038879],"type":"Point"}
}