{
  "type": "Feature",
  "properties": {
    "iso:country":"DE",
    "sg:address":"Brauweilerstr. 62",
    "sg:city":"Bergheim",
    "sg:phone":"+49 2238/41412",
    "sg:postcode":"50129",
    "sg:province":"Nordrhein-Westfalen",
    "wof:name":"Berthold Klemann",
    "wof:placetype":"venue"
},
  "geometry": {"coordinates":[6.7541999817,50.9667701721],"type":"Point"}
}