{
  "type": "Feature",
  "properties": {
    "iso:country":"DE",
    "sg:address":"Erich-Klabunde-Str. 127",
    "sg:city":"Kassel",
    "sg:phone":"+49 561/23251",
    "sg:postcode":"34121",
    "sg:province":"Hessen",
    "wof:name":"Wolfgang Reinbold Architekt",
    "wof:placetype":"venue"
},
  "geometry": {"coordinates":[9.475647,51.303123],"type":"Point"}
}