{
  "type": "Feature",
  "properties": {
    "iso:country":"DE",
    "sg:address":"An der Elle 5",
    "sg:city":"Merzenich",
    "sg:phone":"+49 2421/36043",
    "sg:postcode":"52399",
    "sg:province":"Nordrhein-Westfalen",
    "wof:name":"Harald Walter",
    "wof:placetype":"venue"
},
  "geometry": {"coordinates":[6.523856163,50.8269195557],"type":"Point"}
}