{
  "type": "Feature",
  "properties": {
    "iso:country":"DE",
    "sg:address":"Hauptstr. 44",
    "sg:city":"Bruchk\u00f6bel",
    "sg:phone":"+49 6181/75850",
    "sg:postcode":"63486",
    "sg:province":"Hessen",
    "wof:name":"C. Und J. Dejdar",
    "wof:placetype":"venue"
},
  "geometry": {"coordinates":[8.9203119278,50.1789627075],"type":"Point"}
}