{
  "type": "Feature",
  "properties": {
    "iso:country":"DE",
    "sg:address":"Gabelsbergerstr. 1",
    "sg:city":"Regensburg",
    "sg:phone":"+49 941/798009",
    "sg:postcode":"93047",
    "sg:province":"Bayern",
    "wof:name":"Dr. Med. E. Lamby Arzt F\u00fcr Allgemeinmedizin",
    "wof:placetype":"venue"
},
  "geometry": {"coordinates":[12.1086769104,49.0176620483],"type":"Point"}
}