{
  "type": "Feature",
  "properties": {
    "iso:country":"DE",
    "sg:address":"Hofener Str. 56",
    "sg:city":"Fellbach",
    "sg:phone":"+49 711/5185753",
    "sg:postcode":"70736",
    "sg:province":"Baden-W\u00fcrttemberg",
    "wof:name":"Gr\u00fcnenthal Gmbh",
    "wof:placetype":"venue"
},
  "geometry": {"coordinates":[9.2548103333,48.8429832458],"type":"Point"}
}