{
  "type": "Feature",
  "properties": {
    "iso:country":"DE",
    "sg:address":"Franz-Galitz-Str. 8",
    "sg:city":"Allershausen",
    "sg:phone":"+49 8166/684440",
    "sg:postcode":"85391",
    "sg:province":"Bayern",
    "wof:name":"V\u00f6ba Massivhaus Gmbh",
    "wof:placetype":"venue"
},
  "geometry": {"coordinates":[11.5924949646,48.4341621399],"type":"Point"}
}