{
  "type": "Feature",
  "properties": {
    "iso:country":"DE",
    "sg:address":"Wohltkamp 10",
    "sg:city":"Schee\u00dfel",
    "sg:phone":"+49 4263/2890",
    "sg:postcode":"27383",
    "sg:province":"Niedersachsen",
    "wof:name":"Eurobowl Gerhard Lorch Gmbh",
    "wof:placetype":"venue"
},
  "geometry": {"coordinates":[9.459223,53.168865],"type":"Point"}
}