{
  "type": "Feature",
  "properties": {
    "iso:country":"DE",
    "sg:address":"Bahnstr. 46",
    "sg:city":"Mendig",
    "sg:phone":"+49 2652/1738",
    "sg:postcode":"56743",
    "sg:province":"Rheinland-Pfalz",
    "wof:name":"Kranz Gbr",
    "wof:placetype":"venue"
},
  "geometry": {"coordinates":[7.283777,50.370644],"type":"Point"}
}