{
  "type": "Feature",
  "properties": {
    "iso:country":"DE",
    "sg:address":"Carl-Zeiss-Str. 2",
    "sg:city":"Mainz",
    "sg:phone":"+49 6131/58020",
    "sg:postcode":"55129",
    "sg:province":"Rheinland-Pfalz",
    "wof:name":"Werkst\u00e4tten F\u00fcr Behinderte Mainz Ggmbh",
    "wof:placetype":"venue"
},
  "geometry": {"coordinates":[8.268256,49.962875],"type":"Point"}
}