{
  "type": "Feature",
  "properties": {
    "iso:country":"DE",
    "sg:address":"Bittelbronner Str. 44",
    "sg:city":"M\u00f6ckm\u00fchl",
    "sg:phone":"+49 6298/39116",
    "sg:postcode":"74219",
    "sg:province":"Baden-W\u00fcrttemberg",
    "wof:name":"Vz Verm\u00f6gensverwaltung Gmbh",
    "wof:placetype":"venue"
},
  "geometry": {"coordinates":[9.351956,49.326748],"type":"Point"}
}