{
  "type": "Feature",
  "properties": {
    "iso:country":"DE",
    "sg:address":"Birkenfelder Str. 1-3",
    "sg:city":"Keltern",
    "sg:phone":"+49 4972/367050",
    "sg:postcode":"75210",
    "sg:province":"Baden-W\u00fcrttemberg",
    "wof:name":"B + B Burkhardt + Bischoff Gmbh + Co",
    "wof:placetype":"venue"
},
  "geometry": {"coordinates":[8.6156406403,48.884021759],"type":"Point"}
}