{
  "type": "Feature",
  "properties": {
    "iso:country":"DE",
    "sg:address":"Oskar-Von-Miller-Str. 1a",
    "sg:city":"Eching",
    "sg:phone":"+49 8165/77346",
    "sg:postcode":"85386",
    "sg:province":"Bayern",
    "wof:name":"Jeol Germany Gmbh",
    "wof:placetype":"venue"
},
  "geometry": {"coordinates":[11.6474733353,48.3104057312],"type":"Point"}
}