{
  "type": "Feature",
  "properties": {
    "iso:country":"DE",
    "sg:address":"M\u00fchlrain 17",
    "sg:city":"Stuttgart",
    "sg:phone":"+49 711/244041",
    "sg:postcode":"70180",
    "sg:province":"Baden-W\u00fcrttemberg",
    "wof:name":"M. Von Poswig Architekt",
    "wof:placetype":"venue"
},
  "geometry": {"coordinates":[9.168147,48.761478],"type":"Point"}
}