{
  "type": "Feature",
  "properties": {
    "iso:country":"DE",
    "sg:address":"Schalksburgstr. 13",
    "sg:city":"Stra\u00dfberg",
    "sg:phone":"+49 7434/1537",
    "sg:postcode":"72479",
    "sg:province":"Baden-W\u00fcrttemberg",
    "wof:name":"J\u00fcrgen Koch",
    "wof:placetype":"venue"
},
  "geometry": {"coordinates":[9.097361,48.183926],"type":"Point"}
}