{
  "type": "Feature",
  "properties": {
    "iso:country":"DE",
    "sg:address":"Prager Str. 6",
    "sg:city":"Waldkraiburg",
    "sg:phone":"+49 8638/949888",
    "sg:postcode":"84478",
    "sg:province":"Bayern",
    "wof:name":"Linden-apotheke Inh. Maria Sommer E. Kfr.",
    "wof:placetype":"venue"
},
  "geometry": {"coordinates":[12.400013,48.20681],"type":"Point"}
}