{
  "type": "Feature",
  "properties": {
    "iso:country":"DE",
    "sg:address":"Taunusstr. 46",
    "sg:city":"Gro\u00dfkrotzenburg",
    "sg:phone":"+49 6186/657",
    "sg:postcode":"63538",
    "sg:province":"Hessen",
    "wof:name":"Taunusstube",
    "wof:placetype":"venue"
},
  "geometry": {"coordinates":[8.9738473892,50.0835723877],"type":"Point"}
}