{
  "type": "Feature",
  "properties": {
    "iso:country":"DE",
    "sg:address":"Harmoniestr. 22",
    "sg:city":"Duisburg",
    "sg:phone":"+49 203/82940",
    "sg:postcode":"47119",
    "sg:province":"Nordrhein-Westfalen",
    "wof:name":"Fair Play Spielhallen- Und Automaten-aufstell Gmbh",
    "wof:placetype":"venue"
},
  "geometry": {"coordinates":[6.7329092026,51.4532279968],"type":"Point"}
}