{
  "type": "Feature",
  "properties": {
    "iso:country":"DE",
    "sg:address":"H\u00e4nferstr. 29",
    "sg:city":"Baden-Baden",
    "sg:phone":"+49 7223/58989",
    "sg:postcode":"76534",
    "sg:province":"Baden-W\u00fcrttemberg",
    "wof:name":"Heinz Meyer",
    "wof:placetype":"venue"
},
  "geometry": {"coordinates":[8.155574,48.725128],"type":"Point"}
}