{
  "type": "Feature",
  "properties": {
    "iso:country":"DE",
    "sg:address":"T\u00fcbinger Str. 36",
    "sg:city":"Waldenbuch",
    "sg:phone":"+49 7157/88360",
    "sg:postcode":"71111",
    "sg:province":"Baden-W\u00fcrttemberg",
    "wof:name":"G\u00fcnter Fr\u00f6schle Ingenieur",
    "wof:placetype":"venue"
},
  "geometry": {"coordinates":[9.1316261292,48.6339988708],"type":"Point"}
}