{
  "type": "Feature",
  "properties": {
    "iso:country":"DE",
    "sg:address":"Huben 13",
    "sg:city":"Aschau",
    "sg:phone":"+49 8057/1024",
    "sg:postcode":"83229",
    "sg:province":"Bayern",
    "wof:name":"Wohnbau Sachrang Gmbh",
    "wof:placetype":"venue"
},
  "geometry": {"coordinates":[12.2604093552,47.6834716797],"type":"Point"}
}