{
  "type": "Feature",
  "properties": {
    "iso:country":"DE",
    "sg:address":"Ainmillerstr. 37",
    "sg:city":"M\u00fcnchen",
    "sg:phone":"+49 89/393138",
    "sg:postcode":"80801",
    "sg:province":"Bayern",
    "wof:name":"C. Hahn",
    "wof:placetype":"venue"
},
  "geometry": {"coordinates":[11.576565,48.158936],"type":"Point"}
}