{
  "type": "Feature",
  "properties": {
    "iso:country":"DE",
    "sg:address":"In der Hilbach 46",
    "sg:city":"Heimbach",
    "sg:phone":"+49 2446/245",
    "sg:postcode":"52396",
    "sg:province":"Nordrhein-Westfalen",
    "wof:name":"Hans Clermont",
    "wof:placetype":"venue"
},
  "geometry": {"coordinates":[6.4938,50.632641],"type":"Point"}
}