{
  "type": "Feature",
  "properties": {
    "iso:country":"DE",
    "sg:address":"Breitenfelder Str. 30",
    "sg:city":"Hamburg",
    "sg:phone":"+49 40/4803477",
    "sg:postcode":"20251",
    "sg:province":"Hamburg",
    "wof:name":"G. Mack",
    "wof:placetype":"venue"
},
  "geometry": {"coordinates":[9.9736118317,53.5859413147],"type":"Point"}
}