{
  "type": "Feature",
  "properties": {
    "iso:country":"DE",
    "sg:address":"F\u00e4rberstr. 1",
    "sg:city":"Hachenburg",
    "sg:phone":"+49 2662/1746",
    "sg:postcode":"57627",
    "sg:province":"Rheinland-Pfalz",
    "wof:name":"Karl-h. Christian",
    "wof:placetype":"venue"
},
  "geometry": {"coordinates":[7.824092,50.660061],"type":"Point"}
}