{
  "type": "Feature",
  "properties": {
    "iso:country":"DE",
    "sg:address":"Neumarkt 18",
    "sg:city":"Neuss",
    "sg:phone":"+49 2131/274192",
    "sg:postcode":"41460",
    "sg:province":"Nordrhein-Westfalen",
    "wof:name":"Physiotherapie,,krankengymnastik-praxis,r. Diepold,",
    "wof:placetype":"venue"
},
  "geometry": {"coordinates":[6.690502,51.197617],"type":"Point"}
}