{
  "type": "Feature",
  "properties": {
    "iso:country":"DE",
    "sg:address":"Ulmenweg 2",
    "sg:city":"K\u00f6nigslutter",
    "sg:phone":"+49 5353/2169",
    "sg:postcode":"38154",
    "sg:province":"Niedersachsen",
    "wof:name":"G\u00fcnter Rosnerski",
    "wof:placetype":"venue"
},
  "geometry": {"coordinates":[10.812603,52.262089],"type":"Point"}
}