{
  "type": "Feature",
  "properties": {
    "iso:country":"DE",
    "sg:address":"Margrefstr. 15",
    "sg:city":"Essen",
    "sg:phone":"+49 201/409319",
    "sg:postcode":"45239",
    "sg:province":"Nordrhein-Westfalen",
    "wof:name":"Biohof G\u00fcnter Maas",
    "wof:placetype":"venue"
},
  "geometry": {"coordinates":[7.053579,51.385803],"type":"Point"}
}