{
  "type": "Feature",
  "properties": {
    "iso:country":"DE",
    "sg:address":"Scheerengasse 3",
    "sg:city":"Frankfurt",
    "sg:phone":"+49 69/651226",
    "sg:postcode":"60599",
    "sg:province":"Hessen",
    "wof:name":"Willi Peez",
    "wof:placetype":"venue"
},
  "geometry": {"coordinates":[8.7165975571,50.0991668701],"type":"Point"}
}