{
  "type": "Feature",
  "properties": {
    "iso:country":"DE",
    "sg:address":"Unter den Paichen 42",
    "sg:city":"Pittenbach",
    "sg:phone":"+49 6556/7560",
    "sg:postcode":"54595",
    "sg:province":"Rheinland-Pfalz",
    "wof:name":"Pardeller Gmbh",
    "wof:placetype":"venue"
},
  "geometry": {"coordinates":[6.3427400589,50.1722717285],"type":"Point"}
}