{
  "type": "Feature",
  "properties": {
    "iso:country":"DE",
    "sg:address":"Professor-Carl-Reiser-Str. 40",
    "sg:city":"Garmisch-Partenkirchen",
    "sg:phone":"+49 8821/57773",
    "sg:postcode":"82467",
    "sg:province":"Bayern",
    "wof:name":"Gerhard Dettmann",
    "wof:placetype":"venue"
},
  "geometry": {"coordinates":[11.1016721725,47.5028877258],"type":"Point"}
}