{
  "type": "Feature",
  "properties": {
    "iso:country":"DE",
    "sg:address":"Niddastr. 64",
    "sg:city":"Frankfurt",
    "sg:phone":"+49 69/234012",
    "sg:postcode":"60329",
    "sg:province":"Hessen",
    "wof:name":"Hulla & Co. Human Dynamics Keg",
    "wof:placetype":"venue"
},
  "geometry": {"coordinates":[8.662779,50.109287],"type":"Point"}
}