{
  "type": "Feature",
  "properties": {
    "iso:country":"DE",
    "sg:address":"Kirchplatz 18",
    "sg:city":"R\u00f6ttingen",
    "sg:phone":"+49 9338/442",
    "sg:postcode":"97285",
    "sg:province":"Bayern",
    "wof:name":"Anton Engelhardt",
    "wof:placetype":"venue"
},
  "geometry": {"coordinates":[9.967811,49.509884],"type":"Point"}
}