{
  "type": "Feature",
  "properties": {
    "iso:country":"DE",
    "sg:address":"Sannentalstr. 39",
    "sg:city":"Metzingen",
    "sg:phone":"+49 7123/21725",
    "sg:postcode":"72555",
    "sg:province":"Baden-W\u00fcrttemberg",
    "wof:name":"P. Hilbert Hebamme",
    "wof:placetype":"venue"
},
  "geometry": {"coordinates":[9.272415,48.539272],"type":"Point"}
}