{
  "type": "Feature",
  "properties": {
    "iso:country":"DE",
    "sg:address":"Am Boten 15",
    "sg:city":"Kreuzau",
    "sg:phone":"+49 2421/951419",
    "sg:postcode":"52372",
    "sg:province":"Nordrhein-Westfalen",
    "wof:name":"E-technik Pikos Gmbh",
    "wof:placetype":"venue"
},
  "geometry": {"coordinates":[6.5342001915,50.7553787231],"type":"Point"}
}