{
  "type": "Feature",
  "properties": {
    "iso:country":"DE",
    "sg:address":"Bahnhofstr. 1",
    "sg:city":"Seeg",
    "sg:phone":"+49 8364/231",
    "sg:postcode":"87637",
    "sg:province":"Bayern",
    "wof:name":"R. Landerer & L. Frey",
    "wof:placetype":"venue"
},
  "geometry": {"coordinates":[10.608953476,47.6547546387],"type":"Point"}
}