{
  "type": "Feature",
  "properties": {
    "iso:country":"DE",
    "sg:address":"Leinbachstr. 2",
    "sg:city":"Leingarten",
    "sg:phone":"+49 7131/403373",
    "sg:postcode":"74211",
    "sg:province":"Baden-W\u00fcrttemberg",
    "wof:name":"Ahlborn & Co. Kunststoffe Gmbh",
    "wof:placetype":"venue"
},
  "geometry": {"coordinates":[9.12723,49.14389],"type":"Point"}
}