{
  "type": "Feature",
  "properties": {
    "iso:country":"DE",
    "sg:address":"Hainm\u00fchlenweg 4",
    "sg:city":"L\u00fcbben",
    "sg:phone":"+49 3546/3065",
    "sg:postcode":"15907",
    "sg:province":"Brandenburg",
    "wof:name":"Fred Weinack",
    "wof:placetype":"venue"
},
  "geometry": {"coordinates":[13.88111,51.936123],"type":"Point"}
}