{
  "type": "Feature",
  "properties": {
    "iso:country":"DE",
    "sg:address":"Sch\u00fctzenstrasse 18",
    "sg:city":"Bachhagel",
    "sg:phone":"+49 9077",
    "sg:postcode":"89429",
    "sg:province":"Bayern",
    "wof:name":"Schnepf Gmbh - Ihr Kompetenter Partner",
    "wof:placetype":"venue"
},
  "geometry": {"coordinates":[10.326975,48.631397],"type":"Point"}
}