{
  "type": "Feature",
  "properties": {
    "iso:country":"DE",
    "sg:address":"Viktor-von-Scheffel-Str. 53",
    "sg:city":"Langerringen",
    "sg:phone":"+49 8232/4859",
    "sg:postcode":"86853",
    "sg:province":"Bayern",
    "wof:name":"Karl Rittmayr",
    "wof:placetype":"venue"
},
  "geometry": {"coordinates":[10.760871,48.143875],"type":"Point"}
}