{
  "type": "Feature",
  "properties": {
    "iso:country":"DE",
    "sg:address":"Fellener Str. 25",
    "sg:city":"Burgsinn",
    "sg:phone":"+49 9356/932191",
    "sg:postcode":"97775",
    "sg:province":"Bayern",
    "wof:name":"Holzfachhandlung Barthel Gmbh",
    "wof:placetype":"venue"
},
  "geometry": {"coordinates":[9.64675,50.14666],"type":"Point"}
}