{
  "type": "Feature",
  "properties": {
    "iso:country":"DE",
    "sg:address":"Daimlerstr. 27",
    "sg:city":"Stuttgart",
    "sg:phone":"+49 711/560116",
    "sg:postcode":"70372",
    "sg:province":"Baden-W\u00fcrttemberg",
    "wof:name":"Back Grimm Und Partner",
    "wof:placetype":"venue"
},
  "geometry": {"coordinates":[9.219356,48.804974],"type":"Point"}
}