{
  "type": "Feature",
  "properties": {
    "iso:country":"DE",
    "sg:address":"Rosa-Luxemburg-Str. 35",
    "sg:city":"Wusterwitz",
    "sg:phone":"+49 33839/61505",
    "sg:postcode":"14789",
    "sg:province":"Brandenburg",
    "wof:name":"Restaurant Waldkater",
    "wof:placetype":"venue"
},
  "geometry": {"coordinates":[12.3881502151,52.3849372864],"type":"Point"}
}