{
  "type": "Feature",
  "properties": {
    "iso:country":"DE",
    "sg:address":"Schwenkstr. 5",
    "sg:city":"Allmendingen",
    "sg:phone":"+49 7391/52886",
    "sg:postcode":"89604",
    "sg:province":"Baden-W\u00fcrttemberg",
    "wof:name":"Klaus Zimmermann",
    "wof:placetype":"venue"
},
  "geometry": {"coordinates":[9.7250127792,48.3309211731],"type":"Point"}
}