{
  "type": "Feature",
  "properties": {
    "iso:country":"DE",
    "sg:address":"Klosterstr 27",
    "sg:city":"Osnabr\u00fcck",
    "sg:phone":"+49 541/682803",
    "sg:postcode":"49074",
    "sg:province":"Niedersachsen",
    "wof:name":"Ben-maschinenbau",
    "wof:placetype":"venue"
},
  "geometry": {"coordinates":[8.0515851974,52.2803955078],"type":"Point"}
}