{
  "type": "Feature",
  "properties": {
    "iso:country":"DE",
    "sg:address":"Konrad-Popp-Platz 1",
    "sg:city":"Mainleus",
    "sg:phone":"+49 9229/213",
    "sg:postcode":"95336",
    "sg:province":"Bayern",
    "wof:name":"Schwarzer Adler",
    "wof:placetype":"venue"
},
  "geometry": {"coordinates":[11.3751659393,50.1002807617],"type":"Point"}
}