{
  "type": "Feature",
  "properties": {
    "iso:country":"DE",
    "sg:address":"Klosterstr. 2",
    "sg:city":"Traunstein",
    "sg:phone":"+49 861/64443",
    "sg:postcode":"83278",
    "sg:province":"Bayern",
    "wof:name":"Kaisers Bettenmarkt Inh. Herbert Kaiser Kg",
    "wof:placetype":"venue"
},
  "geometry": {"coordinates":[12.6458082199,47.8700904846],"type":"Point"}
}