{
  "type": "Feature",
  "properties": {
    "iso:country":"DE",
    "sg:city":"\u00dcchtelhausen",
    "sg:phone":"+49 9720/247",
    "sg:postcode":"97532",
    "sg:province":"Bayern",
    "wof:name":"Raiffeisenbank Schonungen Eg",
    "wof:placetype":"venue"
},
  "geometry": {"coordinates":[10.271333,50.092178],"type":"Point"}
}