{
  "type": "Feature",
  "properties": {
    "iso:country":"DE",
    "sg:address":"Schmollerstr. 100a",
    "sg:city":"Stuttgart",
    "sg:phone":"+49 711/532102",
    "sg:postcode":"70378",
    "sg:province":"Baden-W\u00fcrttemberg",
    "wof:name":"Joachim Blendl",
    "wof:placetype":"venue"
},
  "geometry": {"coordinates":[9.23154,48.829033],"type":"Point"}
}