{
  "type": "Feature",
  "properties": {
    "iso:country":"DE",
    "sg:address":"F\u00fcchtenfelder Str. 26",
    "sg:city":"Wietmarschen",
    "sg:phone":"+49 5946/91330",
    "sg:postcode":"49835",
    "sg:province":"Niedersachsen",
    "wof:name":"Dif-organveredlung G. K\u00fcppers Gmbh & Co. Kg",
    "wof:placetype":"venue"
},
  "geometry": {"coordinates":[7.124019146,52.5535087585],"type":"Point"}
}