{
  "type": "Feature",
  "properties": {
    "iso:country":"DE",
    "sg:address":"Nickep\u00fctz 26",
    "sg:city":"D\u00fcren",
    "sg:phone":"+49 2421",
    "sg:postcode":"52349",
    "sg:province":"Nordrhein-Westfalen",
    "wof:name":"Autopfandhaus D\u00fcren",
    "wof:placetype":"venue"
},
  "geometry": {"coordinates":[6.458495,50.805717],"type":"Point"}
}