{
  "type": "Feature",
  "properties": {
    "iso:country":"DE",
    "sg:address":"Kornwestheimer Str. 127",
    "sg:city":"Korntal-M\u00fcnchingen",
    "sg:phone":"+49 7150/6386",
    "sg:postcode":"70825",
    "sg:province":"Baden-W\u00fcrttemberg",
    "wof:name":"Heinz Ludwig",
    "wof:placetype":"venue"
},
  "geometry": {"coordinates":[9.114808,48.854519],"type":"Point"}
}