{
  "type": "Feature",
  "properties": {
    "iso:country":"DE",
    "sg:address":"Emilienstr. 4",
    "sg:city":"\u00c2ugustdorf",
    "sg:phone":"+49 5237/890732",
    "sg:postcode":"32832",
    "sg:province":"Nordrhein-Westfalen",
    "wof:name":"Webdesign - Internetdienstleistung - Kay-uwe Jung",
    "wof:placetype":"venue"
},
  "geometry": {"coordinates":[8.743597,51.907169],"type":"Point"}
}