{
  "type": "Feature",
  "properties": {
    "iso:country":"DE",
    "sg:address":"Kamillenstr. 42A",
    "sg:city":"Berlin",
    "sg:phone":"+49 30/31505045",
    "sg:postcode":"12203",
    "sg:province":"Berlin",
    "wof:name":"Bartke Consulting Gmbh",
    "wof:placetype":"venue"
},
  "geometry": {"coordinates":[13.299401,52.45142],"type":"Point"}
}