{
  "type": "Feature",
  "properties": {
    "iso:country":"DE",
    "sg:address":"Allendorfer Str.",
    "sg:city":"Schwalmstadt",
    "sg:phone":"+49 6691/96110",
    "sg:postcode":"34613",
    "sg:province":"Hessen",
    "wof:name":"Az-modell Verwaltungs Gmbh",
    "wof:placetype":"venue"
},
  "geometry": {"coordinates":[9.18798,50.920887],"type":"Point"}
}