{
  "type": "Feature",
  "properties": {
    "iso:country":"DE",
    "sg:address":"Dr.-Von-Fromm-Str. 3::",
    "sg:city":"Weiden",
    "sg:phone":"+49 4969/973560",
    "sg:postcode":"92637",
    "sg:province":"Bayern",
    "wof:name":"W\u00dcrttenbergisch Badische Versicherungs Ag",
    "wof:placetype":"venue"
},
  "geometry": {"coordinates":[8.647744,50.107559],"type":"Point"}
}