{
  "type": "Feature",
  "properties": {
    "iso:country":"DE",
    "sg:address":"Orpethaler Str. 54",
    "sg:city":"Diemelstadt",
    "sg:phone":"+49 5642/790",
    "sg:postcode":"34474",
    "sg:province":"Hessen",
    "wof:name":"C.d. Haupt Papier- Und Pappenfabrik Gmbh & Co. Kg",
    "wof:placetype":"venue"
},
  "geometry": {"coordinates":[8.9794387817,51.5062065125],"type":"Point"}
}