{
  "type": "Feature",
  "properties": {
    "iso:country":"DE",
    "sg:address":"Manteuffelstr. 42",
    "sg:city":"Berlin",
    "sg:phone":"+49 30/7512038",
    "sg:postcode":"12103",
    "sg:province":"Berlin",
    "wof:name":"Tuscher Und Sohn",
    "wof:placetype":"venue"
},
  "geometry": {"coordinates":[13.376385,52.458157],"type":"Point"}
}