{
  "type": "Feature",
  "properties": {
    "iso:country":"DE",
    "sg:address":"H\u00fcbschstr. 19",
    "sg:city":"Karlsruhe",
    "sg:phone":"+49 721/828240",
    "sg:postcode":"76135",
    "sg:province":"Baden-W\u00fcrttemberg",
    "wof:name":"Gerhard Assem Architekt",
    "wof:placetype":"venue"
},
  "geometry": {"coordinates":[8.372771,49.005013],"type":"Point"}
}