{
  "type": "Feature",
  "properties": {
    "iso:country":"DE",
    "sg:address":"Urbacher Str. 12",
    "sg:city":"Menteroda",
    "sg:phone":"+49 36029/84241",
    "sg:postcode":"99996",
    "sg:province":"Th\u00fcringen",
    "wof:name":"Elsbeth Richter",
    "wof:placetype":"venue"
},
  "geometry": {"coordinates":[10.5654249191,51.3071327209],"type":"Point"}
}