{
  "type": "Feature",
  "properties": {
    "iso:country":"DE",
    "sg:address":"Ingelheimer Str. 11",
    "sg:city":"Stadecken-Elsheim",
    "sg:phone":"+49 6130/6388",
    "sg:postcode":"55271",
    "sg:province":"Rheinland-Pfalz",
    "wof:name":"Hugo Zimmer",
    "wof:placetype":"venue"
},
  "geometry": {"coordinates":[8.122710228,49.9169616699],"type":"Point"}
}