{
  "type": "Feature",
  "properties": {
    "iso:country":"DE",
    "sg:address":"Untere Vorstadt 11",
    "sg:city":"Albstadt",
    "sg:phone":"+49 7431/590442",
    "sg:postcode":"72458",
    "sg:province":"Baden-W\u00fcrttemberg",
    "wof:name":"Cafe Intermetzo",
    "wof:placetype":"venue"
},
  "geometry": {"coordinates":[9.028643,48.212711],"type":"Point"}
}