{
  "type": "Feature",
  "properties": {
    "iso:country":"DE",
    "sg:address":"Turmstr. 13",
    "sg:city":"Reutlingen",
    "sg:phone":"+49 7121/337785",
    "sg:postcode":"72770",
    "sg:province":"Baden-W\u00fcrttemberg",
    "wof:name":"Dr. Heinz W. Stadelmann",
    "wof:placetype":"venue"
},
  "geometry": {"coordinates":[9.1395664215,48.4785995483],"type":"Point"}
}