{
  "type": "Feature",
  "properties": {
    "iso:country":"DE",
    "sg:address":"Siemensstr. 9",
    "sg:city":"L\u00fcbbecke",
    "sg:phone":"+49 5741/3250",
    "sg:postcode":"32312",
    "sg:province":"Nordrhein-Westfalen",
    "wof:name":"Liberty Damenmoden Gmbh",
    "wof:placetype":"venue"
},
  "geometry": {"coordinates":[8.6275577545,52.3243751526],"type":"Point"}
}