{
  "type": "Feature",
  "properties": {
    "iso:country":"DE",
    "sg:address":"See\u00e4ckerstr. 11",
    "sg:city":"W\u00e4schenbeuren",
    "sg:phone":"+49 7172/22458",
    "sg:postcode":"73116",
    "sg:province":"Baden-W\u00fcrttemberg",
    "wof:name":"B. Messick",
    "wof:placetype":"venue"
},
  "geometry": {"coordinates":[9.690076,48.756763],"type":"Point"}
}