{
  "type": "Feature",
  "properties": {
    "iso:country":"DE",
    "sg:address":"Haldenstr 4",
    "sg:city":"Riedlingen",
    "sg:phone":"+49 7371/93720",
    "sg:postcode":"88499",
    "sg:province":"Baden-W\u00fcrttemberg",
    "wof:name":"Ulrich'sche Buchdruckerei Und Verlag Gmbh & Co Kg",
    "wof:placetype":"venue"
},
  "geometry": {"coordinates":[9.4759082794,48.153301239],"type":"Point"}
}