{
  "type": "Feature",
  "properties": {
    "iso:country":"DE",
    "sg:address":"Riedwasen 2",
    "sg:city":"Frankenhardt",
    "sg:phone":"+49 7959/2464",
    "sg:postcode":"74586",
    "sg:province":"Baden-W\u00fcrttemberg",
    "wof:name":"Helmut Abel Gmbh",
    "wof:placetype":"venue"
},
  "geometry": {"coordinates":[10.0342302322,49.0732116699],"type":"Point"}
}