{
  "type": "Feature",
  "properties": {
    "iso:country":"DE",
    "sg:address":"Nagoldstr. 15",
    "sg:city":"Sindelfingen",
    "sg:phone":"+49 7031/86680",
    "sg:postcode":"71065",
    "sg:province":"Baden-W\u00fcrttemberg",
    "wof:name":"Hotel-garni W. Raaf",
    "wof:placetype":"venue"
},
  "geometry": {"coordinates":[9.013094902,48.7055358887],"type":"Point"}
}