{
  "type": "Feature",
  "properties": {
    "iso:country":"DE",
    "sg:address":"Birkunger Str. 27",
    "sg:city":"Leinefelde",
    "sg:postcode":"37327",
    "sg:province":"Th\u00fcringen",
    "wof:name":"E & B Holding Management Gmbh",
    "wof:placetype":"venue"
},
  "geometry": {"coordinates":[10.330895,51.372704],"type":"Point"}
}