{
  "type": "Feature",
  "properties": {
    "iso:country":"DE",
    "sg:address":"Breite Herzogstr. 11",
    "sg:city":"Wolfenb\u00fcttel",
    "sg:phone":"+49 5331/1704",
    "sg:postcode":"38300",
    "sg:province":"Niedersachsen",
    "wof:name":"Altstadt - Taxi",
    "wof:placetype":"venue"
},
  "geometry": {"coordinates":[10.540495,52.163818],"type":"Point"}
}