{
  "type": "Feature",
  "properties": {
    "iso:country":"DE",
    "sg:address":"K\u00f6nigsberger Str. 13",
    "sg:city":"Barmstedt",
    "sg:phone":"+49 4123/7783",
    "sg:postcode":"25355",
    "sg:province":"Schleswig-Holstein",
    "wof:name":"Helge Johannsen",
    "wof:placetype":"venue"
},
  "geometry": {"coordinates":[9.7690391541,53.798740387],"type":"Point"}
}