{
  "type": "Feature",
  "properties": {
    "iso:country":"DE",
    "sg:address":"G\u00f6ttweiger Str. 5",
    "sg:city":"Buchen",
    "sg:postcode":"74722",
    "sg:province":"Baden-W\u00fcrttemberg",
    "wof:name":"Sadina Gmbh",
    "wof:placetype":"venue"
},
  "geometry": {"coordinates":[9.3118438721,49.5232048035],"type":"Point"}
}