{
  "type": "Feature",
  "properties": {
    "iso:country":"DE",
    "sg:address":"M\u00fchlenstr. 92",
    "sg:city":"T\u00f6nisvorst",
    "sg:phone":"+49 2151/994066",
    "sg:postcode":"47918",
    "sg:province":"Nordrhein-Westfalen",
    "wof:name":"Werner Gottwald",
    "wof:placetype":"venue"
},
  "geometry": {"coordinates":[6.506799221,51.3217582703],"type":"Point"}
}