{
  "type": "Feature",
  "properties": {
    "iso:country":"DE",
    "sg:address":"H\u00fcblerstr. 2",
    "sg:city":"Dresden",
    "sg:phone":"+49 351/3400700",
    "sg:postcode":"01309",
    "sg:province":"Sachsen",
    "wof:name":"Hampe Und H\u00f6bel Rechtsanw\u00e4lte",
    "wof:placetype":"venue"
},
  "geometry": {"coordinates":[13.8061294556,51.0519676208],"type":"Point"}
}