{
  "type": "Feature",
  "properties": {
    "iso:country":"DE",
    "sg:city":"stade",
    "sg:postcode":"21682",
    "sg:province":"Niedersachsen",
    "wof:name":"Well.come - Well Fit Entertainment: Fitness, Wellness & More",
    "wof:placetype":"venue"
},
  "geometry": {"coordinates":[9.478363,53.601963],"type":"Point"}
}