{
  "type": "Feature",
  "properties": {
    "iso:country":"DE",
    "sg:address":"Soldiner Str. 26",
    "sg:city":"Berlin",
    "sg:phone":"+49 30/4932985",
    "sg:postcode":"13359",
    "sg:province":"Berlin",
    "wof:name":"Pizzeria Da Mouin",
    "wof:placetype":"venue"
},
  "geometry": {"coordinates":[13.3858137131,52.5589790344],"type":"Point"}
}