{
  "type": "Feature",
  "properties": {
    "iso:country":"DE",
    "sg:address":"Falkenried 82",
    "sg:city":"Hamburg",
    "sg:phone":"+49 40/483469",
    "sg:postcode":"20251",
    "sg:province":"Hamburg",
    "wof:name":"Marianne Freese Inh. Marianne Krickow",
    "wof:placetype":"venue"
},
  "geometry": {"coordinates":[9.9726133347,53.5849151611],"type":"Point"}
}