{
  "type": "Feature",
  "properties": {
    "iso:country":"DE",
    "sg:address":"M\u00fchlweg 8",
    "sg:city":"Bogen",
    "sg:phone":"+49 9422/2567",
    "sg:postcode":"94327",
    "sg:province":"Bayern",
    "wof:name":"Cosmo-handelsges. Mbh",
    "wof:placetype":"venue"
},
  "geometry": {"coordinates":[12.6696081161,48.9269256592],"type":"Point"}
}