{
  "type": "Feature",
  "properties": {
    "iso:country":"DE",
    "sg:address":"Ahrensfelder Chaussee 18",
    "sg:city":"Eiche",
    "sg:phone":"+49 30/9375397",
    "sg:postcode":"16356",
    "sg:province":"Brandenburg",
    "wof:name":"Imbi\u00df Ilona Tannigel",
    "wof:placetype":"venue"
},
  "geometry": {"coordinates":[13.5899438858,52.569442749],"type":"Point"}
}