{
  "type": "Feature",
  "properties": {
    "iso:country":"DE",
    "sg:address":"Katzenbachstr. 32",
    "sg:city":"Stuttgart",
    "sg:phone":"+49 711/732490",
    "sg:postcode":"70563",
    "sg:province":"Baden-W\u00fcrttemberg",
    "wof:name":"Fliesen-koch Stefan Koch",
    "wof:placetype":"venue"
},
  "geometry": {"coordinates":[9.110326767,48.733001709],"type":"Point"}
}