{
  "type": "Feature",
  "properties": {
    "iso:country":"DE",
    "sg:address":"Baerler Str. 18",
    "sg:city":"Moers",
    "sg:phone":"+49 2841/98866",
    "sg:postcode":"47441",
    "sg:province":"Nordrhein-Westfalen",
    "wof:name":"Zws-zukunftsorientierte W\u00e4rme Systeme Gmbh",
    "wof:placetype":"venue"
},
  "geometry": {"coordinates":[6.6318068504,51.4569778442],"type":"Point"}
}