{
  "type": "Feature",
  "properties": {
    "iso:country":"DE",
    "sg:address":"Welsleber Str. 32",
    "sg:city":"Magdeburg",
    "sg:postcode":"39122",
    "sg:province":"Sachsen-Anhalt",
    "wof:name":"Gk Immobilien Gmbh",
    "wof:placetype":"venue"
},
  "geometry": {"coordinates":[11.6600856781,52.0603790283],"type":"Point"}
}