{
  "type": "Feature",
  "properties": {
    "iso:country":"DE",
    "sg:address":"Ratsstr. 6-8",
    "sg:city":"Langewiesen",
    "sg:phone":"+49 3677/800800",
    "sg:postcode":"98704",
    "sg:province":"Th\u00fcringen",
    "wof:name":"G. He\u00df",
    "wof:placetype":"venue"
},
  "geometry": {"coordinates":[10.9739761353,50.6717071533],"type":"Point"}
}