{
  "type": "Feature",
  "properties": {
    "iso:country":"DE",
    "sg:address":"Hermann-Burte-Str. 9",
    "sg:city":"Kandern",
    "sg:phone":"+49 7626/6887",
    "sg:postcode":"79400",
    "sg:province":"Baden-W\u00fcrttemberg",
    "wof:name":"S. Volz",
    "wof:placetype":"venue"
},
  "geometry": {"coordinates":[7.654528141,47.7138824463],"type":"Point"}
}