{
  "type": "Feature",
  "properties": {
    "iso:country":"DE",
    "sg:address":"Eldenstr. 29",
    "sg:city":"Plau",
    "sg:phone":"+49 38735/42451",
    "sg:postcode":"19395",
    "sg:province":"Mecklenburg-Vorpommern",
    "wof:name":"J\u00f6rg Harder",
    "wof:placetype":"venue"
},
  "geometry": {"coordinates":[12.1918888092,53.3706474304],"type":"Point"}
}