{
  "type": "Feature",
  "properties": {
    "iso:country":"DE",
    "sg:address":"Bamberger Str. 12",
    "sg:city":"H\u00f6chstadt",
    "sg:phone":"+49 9193/4732",
    "sg:postcode":"91315",
    "sg:province":"Bayern",
    "wof:name":"H. Wegel Masseur",
    "wof:placetype":"venue"
},
  "geometry": {"coordinates":[10.806965,49.70628],"type":"Point"}
}