{
  "type": "Feature",
  "properties": {
    "iso:country":"DE",
    "sg:address":"R\u00f6ntgenstr. 7",
    "sg:city":"Wolfsburg",
    "sg:phone":"+49 5361/48283",
    "sg:postcode":"38440",
    "sg:province":"Niedersachsen",
    "wof:name":"Tanzschule Giebel Adtv",
    "wof:placetype":"venue"
},
  "geometry": {"coordinates":[10.7781057358,52.4103507996],"type":"Point"}
}