{
  "type": "Feature",
  "properties": {
    "iso:country":"DE",
    "sg:address":"Unter den Eichen 6",
    "sg:city":"Burgstall",
    "sg:phone":"+49 39364/4452",
    "sg:postcode":"39517",
    "sg:province":"Sachsen-Anhalt",
    "wof:name":"Malerunternehmen Inh. Sven U. Uwe Prosowski Gbr",
    "wof:placetype":"venue"
},
  "geometry": {"coordinates":[11.698686,52.406818],"type":"Point"}
}