{
  "type": "Feature",
  "properties": {
    "iso:country":"DE",
    "sg:address":"Augsburger Str. 31",
    "sg:city":"Fischach",
    "sg:phone":"+49 8236/5655",
    "sg:postcode":"86850",
    "sg:province":"Bayern",
    "wof:name":"Klaus Weiske",
    "wof:placetype":"venue"
},
  "geometry": {"coordinates":[10.6599464417,48.2924041748],"type":"Point"}
}