{
  "type": "Feature",
  "properties": {
    "iso:country":"DE",
    "sg:address":"Luxemburger Ring 17",
    "sg:city":"Aachen",
    "sg:phone":"+49 241/63782",
    "sg:postcode":"52066",
    "sg:province":"Nordrhein-Westfalen",
    "wof:name":"Dr. Elke Trampen Rechtsanw\u00e4ltin",
    "wof:placetype":"venue"
},
  "geometry": {"coordinates":[6.0850682259,50.7504196167],"type":"Point"}
}