{
  "type": "Feature",
  "properties": {
    "iso:country":"DE",
    "sg:address":"Kapellenstr. 1 a",
    "sg:city":"Kriftel",
    "sg:phone":"+49 6192/7001",
    "sg:postcode":"65830",
    "sg:province":"Hessen",
    "wof:name":"Kath. \u00d6ffentliche Bibliothek",
    "wof:placetype":"venue"
},
  "geometry": {"coordinates":[8.466216,50.082039],"type":"Point"}
}