{
  "type": "Feature",
  "properties": {
    "iso:country":"DE",
    "sg:address":"Kreillerstr. 193",
    "sg:city":"M\u00fcnchen",
    "sg:phone":"+49 89/423248",
    "sg:postcode":"81825",
    "sg:province":"Bayern",
    "wof:name":"Walter Butzke Steuerberater",
    "wof:placetype":"venue"
},
  "geometry": {"coordinates":[11.6604728699,48.1230316162],"type":"Point"}
}