{
  "type": "Feature",
  "properties": {
    "iso:country":"DE",
    "sg:address":"Auf der Gaste 5",
    "sg:city":"Uplengen",
    "sg:phone":"+49 4956/781",
    "sg:postcode":"26670",
    "sg:province":"Niedersachsen",
    "wof:name":"Harm Ottersberg Binnenschiffahrt",
    "wof:placetype":"venue"
},
  "geometry": {"coordinates":[7.760921,53.307713],"type":"Point"}
}