{
  "type": "Feature",
  "properties": {
    "iso:country":"DE",
    "sg:address":"Goerdelerstr. 26",
    "sg:city":"Wuppertal",
    "sg:postcode":"42329",
    "sg:province":"Nordrhein-Westfalen",
    "wof:name":"Cvjm Wuppertal-sonnborn E. V.",
    "wof:placetype":"venue"
},
  "geometry": {"coordinates":[7.0794148445,51.2316818237],"type":"Point"}
}