{
  "type": "Feature",
  "properties": {
    "iso:country":"DE",
    "sg:address":"Stakendorfer Tor 15a",
    "sg:city":"Sch\u00f6nberg",
    "sg:postcode":"24217",
    "sg:province":"Schleswig-Holstein",
    "wof:name":"Hansa-bau B\u00fcdelsdorf Gmbh & Co. Kg",
    "wof:placetype":"venue"
},
  "geometry": {"coordinates":[10.3759832382,54.3951721191],"type":"Point"}
}