{
  "type": "Feature",
  "properties": {
    "iso:country":"DE",
    "sg:address":"Nikolaus-Otto-Str. 1",
    "sg:city":"Olching",
    "sg:phone":"+49 8142/418235",
    "sg:postcode":"82140",
    "sg:province":"Bayern",
    "wof:name":"Gbs-german Bartender Service Gmbh",
    "wof:placetype":"venue"
},
  "geometry": {"coordinates":[11.328154,48.207752],"type":"Point"}
}