{
  "type": "Feature",
  "properties": {
    "iso:country":"DE",
    "sg:address":"Im Waldring 35",
    "sg:city":"Wadern",
    "sg:phone":"+49 6874/376",
    "sg:postcode":"66687",
    "sg:province":"Saarland",
    "wof:name":"Peter Bollinger",
    "wof:placetype":"venue"
},
  "geometry": {"coordinates":[6.832288,49.493294],"type":"Point"}
}