{
  "type": "Feature",
  "properties": {
    "iso:country":"DE",
    "sg:address":"Goetjensorter Deich 5 a",
    "sg:city":"Hamburg",
    "sg:phone":"+49 40/7542268",
    "sg:postcode":"21109",
    "sg:province":"Hamburg",
    "wof:name":"Henry Reymers",
    "wof:placetype":"venue"
},
  "geometry": {"coordinates":[10.0481,53.490601],"type":"Point"}
}