{
  "type": "Feature",
  "properties": {
    "iso:country":"DE",
    "sg:address":"Fittingstr. 47",
    "sg:city":"Singen",
    "sg:postcode":"78224",
    "sg:province":"Baden-W\u00fcrttemberg",
    "wof:name":"Aldi Gmbh & Co. Kg",
    "wof:placetype":"venue"
},
  "geometry": {"coordinates":[8.852025032,47.7557106018],"type":"Point"}
}