{
  "type": "Feature",
  "properties": {
    "iso:country":"DE",
    "sg:address":"Dr.-Hermann-Bizer-Str. 45",
    "sg:city":"Albstadt",
    "sg:phone":"+49 7432/3628",
    "sg:postcode":"72461",
    "sg:province":"Baden-W\u00fcrttemberg",
    "wof:name":"Dieter Conzelmann Heissmangel",
    "wof:placetype":"venue"
},
  "geometry": {"coordinates":[9.0233879089,48.257019043],"type":"Point"}
}