{
  "type": "Feature",
  "properties": {
    "iso:country":"DE",
    "sg:address":"Ruhrstr. 11a",
    "sg:city":"Hamburg",
    "sg:phone":"+49 40/85370731",
    "sg:postcode":"22761",
    "sg:province":"Hamburg",
    "wof:name":"Eike Wiehe Architekt",
    "wof:placetype":"venue"
},
  "geometry": {"coordinates":[9.928006,53.561543],"type":"Point"}
}