{
  "type": "Feature",
  "properties": {
    "iso:country":"DE",
    "sg:address":"Am Anger 11",
    "sg:city":"Rodewisch",
    "sg:postcode":"08228",
    "sg:province":"Sachsen",
    "wof:name":"Ev.-methodistische Kirche Rodewisch",
    "wof:placetype":"venue"
},
  "geometry": {"coordinates":[12.4110002518,50.5317497253],"type":"Point"}
}