{
  "type": "Feature",
  "properties": {
    "iso:country":"DE",
    "sg:address":"T\u00fcbinger Str. 45",
    "sg:city":"Gomaringen",
    "sg:phone":"+49 7072/2837",
    "sg:postcode":"72810",
    "sg:province":"Baden-W\u00fcrttemberg",
    "wof:name":"Hans Kuttler",
    "wof:placetype":"venue"
},
  "geometry": {"coordinates":[9.0981626511,48.4510879517],"type":"Point"}
}