{
  "type": "Feature",
  "properties": {
    "iso:country":"DE",
    "sg:address":"Gr\u00fcnberger Str. 21",
    "sg:city":"Gie\u00dfen",
    "sg:phone":"+49 641/31155",
    "sg:postcode":"35390",
    "sg:province":"Hessen",
    "wof:name":"Harlekin",
    "wof:placetype":"venue"
},
  "geometry": {"coordinates":[8.6835412979,50.5836524963],"type":"Point"}
}