{
  "type": "Feature",
  "properties": {
    "iso:country":"DE",
    "sg:address":"Viktoriastr. 71",
    "sg:city":"L\u00fcnen",
    "sg:phone":"+49 2306/1611",
    "sg:postcode":"44532",
    "sg:province":"Nordrhein-Westfalen",
    "wof:name":"Adac-reiseb\u00fcro",
    "wof:placetype":"venue"
},
  "geometry": {"coordinates":[7.5090517998,51.6091842651],"type":"Point"}
}