{
  "type": "Feature",
  "properties": {
    "iso:country":"DE",
    "sg:address":"Stra\u00dfburger Weg 4",
    "sg:city":"Halle",
    "sg:phone":"+49 345/5507751",
    "sg:postcode":"06120",
    "sg:province":"Sachsen-Anhalt",
    "wof:name":"Dr. Med. Inge Von Rozycki",
    "wof:placetype":"venue"
},
  "geometry": {"coordinates":[11.938921,51.49894],"type":"Point"}
}