{
  "type": "Feature",
  "properties": {
    "iso:country":"DE",
    "sg:address":"Ritterstr. 2a::",
    "sg:city":"Berlin",
    "sg:phone":"+49 4930/6169040",
    "sg:postcode":"10969",
    "sg:province":"Berlin",
    "wof:name":"Consenta Treuhand Ag",
    "wof:placetype":"venue"
},
  "geometry": {"coordinates":[13.413521,52.500652],"type":"Point"}
}