{
  "type": "Feature",
  "properties": {
    "iso:country":"DE",
    "sg:address":"Schadenweilerstr. 52",
    "sg:city":"Hechingen",
    "sg:phone":"+49 7471/2494",
    "sg:postcode":"72379",
    "sg:province":"Baden-W\u00fcrttemberg",
    "wof:name":"Gambrinus",
    "wof:placetype":"venue"
},
  "geometry": {"coordinates":[8.968164444,48.354347229],"type":"Point"}
}