{
  "type": "Feature",
  "properties": {
    "iso:country":"DE",
    "sg:address":"Jasperallee 54",
    "sg:city":"Braunschweig",
    "sg:phone":"+49 531/341772",
    "sg:postcode":"38102",
    "sg:province":"Niedersachsen",
    "wof:name":"Stendel Immobilien Inhaber Klaus Stendel E. K.",
    "wof:placetype":"venue"
},
  "geometry": {"coordinates":[10.5427026749,52.2684364319],"type":"Point"}
}