{
  "type": "Feature",
  "properties": {
    "iso:country":"DE",
    "sg:address":"Deichstr. 25",
    "sg:city":"Uetersen",
    "sg:phone":"+49 4941/2271090",
    "sg:postcode":"25436",
    "sg:province":"Schleswig-Holstein",
    "wof:name":"Harles & Jentzsch Gmbh",
    "wof:placetype":"venue"
},
  "geometry": {"coordinates":[9.644562,53.679054],"type":"Point"}
}