{
  "type": "Feature",
  "properties": {
    "iso:country":"DE",
    "sg:address":"Mendener Str. 66",
    "sg:city":"Menden",
    "sg:phone":"+49 2373/81929",
    "sg:postcode":"58706",
    "sg:province":"Nordrhein-Westfalen",
    "wof:name":"Il Rugantino",
    "wof:placetype":"venue"
},
  "geometry": {"coordinates":[7.8180770874,51.4252624512],"type":"Point"}
}