{
  "type": "Feature",
  "properties": {
    "iso:country":"DE",
    "sg:address":"Rheinstr. 13",
    "sg:city":"Norden",
    "sg:phone":"+49 4931/167697",
    "sg:postcode":"26506",
    "sg:province":"Niedersachsen",
    "wof:name":"Johann Grensemann",
    "wof:placetype":"venue"
},
  "geometry": {"coordinates":[7.231938839,53.5937767029],"type":"Point"}
}