{
  "type": "Feature",
  "properties": {
    "iso:country":"DE",
    "sg:address":"Max-Maddalena-Str. 9",
    "sg:city":"Rostock",
    "sg:postcode":"18069",
    "sg:province":"Mecklenburg-Vorpommern",
    "wof:name":"Hanseback Rostocker Konditorei Und Backwaren Gmbh",
    "wof:placetype":"venue"
},
  "geometry": {"coordinates":[12.0681276321,54.099937439],"type":"Point"}
}