{
  "type": "Feature",
  "properties": {
    "iso:country":"DE",
    "sg:address":"Breite Str. 11a",
    "sg:city":"Buchholz",
    "sg:phone":"+49 4181/38444",
    "sg:postcode":"21244",
    "sg:province":"Niedersachsen",
    "wof:name":"Marianne Schr\u00f6der Taschenparadies",
    "wof:placetype":"venue"
},
  "geometry": {"coordinates":[9.880122,53.328281],"type":"Point"}
}