{
  "type": "Feature",
  "properties": {
    "iso:country":"DE",
    "sg:address":"Rosgartenstr. 28",
    "sg:city":"Konstanz",
    "sg:phone":"+49 7531/27022",
    "sg:postcode":"78462",
    "sg:province":"Baden-W\u00fcrttemberg",
    "wof:name":"Walter Marquardt Rechtsanwalt",
    "wof:placetype":"venue"
},
  "geometry": {"coordinates":[9.174495697,47.6590042114],"type":"Point"}
}