{
  "type": "Feature",
  "properties": {
    "iso:country":"DE",
    "sg:address":"Sch\u00f6nefelder Chaussee 29",
    "sg:city":"Berlin",
    "sg:phone":"+49 30/67989474",
    "sg:postcode":"12524",
    "sg:province":"Berlin",
    "wof:name":"Mittag",
    "wof:placetype":"venue"
},
  "geometry": {"coordinates":[13.5325746536,52.416217804],"type":"Point"}
}