{
  "type": "Feature",
  "properties": {
    "iso:country":"DE",
    "sg:address":"Von-Kellenbach-Str. 7",
    "sg:city":"Koblenz",
    "sg:phone":"+49 261/72200",
    "sg:postcode":"56076",
    "sg:province":"Rheinland-Pfalz",
    "wof:name":"Goese Ballettschule",
    "wof:placetype":"venue"
},
  "geometry": {"coordinates":[7.5936899185,50.3256874084],"type":"Point"}
}