{
  "type": "Feature",
  "properties": {
    "iso:country":"DE",
    "sg:address":"Birnbaumsm\u00fchle 65",
    "sg:city":"Frankfurt",
    "sg:postcode":"15234",
    "sg:province":"Brandenburg",
    "wof:name":"Gtm Bau Gmbh",
    "wof:placetype":"venue"
},
  "geometry": {"coordinates":[14.5014753342,52.3498802185],"type":"Point"}
}