{
  "type": "Feature",
  "properties": {
    "iso:country":"DE",
    "sg:address":"Halzenberg 25",
    "sg:city":"Wermelskirchen",
    "sg:phone":"+49 2196/1050",
    "sg:postcode":"42929",
    "sg:province":"Nordrhein-Westfalen",
    "wof:name":"Duratec Hartstoffe Gmbh",
    "wof:placetype":"venue"
},
  "geometry": {"coordinates":[7.27109,51.100384],"type":"Point"}
}