{
  "type": "Feature",
  "properties": {
    "iso:country":"DE",
    "sg:address":"Kanalstr. 120",
    "sg:city":"Viersen",
    "sg:phone":"+49 2162/12817",
    "sg:postcode":"41748",
    "sg:province":"Nordrhein-Westfalen",
    "wof:name":"Margit Sch\u00fcckes",
    "wof:placetype":"venue"
},
  "geometry": {"coordinates":[6.40257,51.263168],"type":"Point"}
}