{
  "type": "Feature",
  "properties": {
    "iso:country":"DE",
    "sg:address":"Braker Str. 27",
    "sg:city":"Bielefeld",
    "sg:phone":"+49 521/76949",
    "sg:postcode":"33729",
    "sg:province":"Nordrhein-Westfalen",
    "wof:name":"Rudi M\u00fcller",
    "wof:placetype":"venue"
},
  "geometry": {"coordinates":[8.6086330414,52.068901062],"type":"Point"}
}