{
  "type": "Feature",
  "properties": {
    "iso:country":"DE",
    "sg:address":"Maria-Hilf-Str. 17",
    "sg:city":"K\u00f6ln",
    "sg:phone":"+49 221/9320031",
    "sg:postcode":"50677",
    "sg:province":"Nordrhein-Westfalen",
    "wof:name":"Barke Und Partner B\u00fcro F\u00fcr Kommunikation Rufus B",
    "wof:placetype":"venue"
},
  "geometry": {"coordinates":[6.956486,50.919373],"type":"Point"}
}