{
  "type": "Feature",
  "properties": {
    "iso:country":"DE",
    "sg:address":"An der Marienkirche 5",
    "sg:city":"Rendsburg",
    "sg:phone":"+49 4331/22080",
    "sg:postcode":"24768",
    "sg:province":"Schleswig-Holstein",
    "wof:name":"Charleston",
    "wof:placetype":"venue"
},
  "geometry": {"coordinates":[9.6646471024,54.3051490784],"type":"Point"}
}