{
  "type": "Feature",
  "properties": {
    "iso:country":"DE",
    "sg:address":"Yburgstr.7",
    "sg:city":"Rheinm\u00fcnater",
    "sg:phone":"+49 7227/8571",
    "sg:postcode":"77836",
    "sg:province":"Baden-W\u00fcrttemberg",
    "wof:name":"Shop4you2000 Musik, Dvd, Videos Und B\u00fccher Von Jpc",
    "wof:placetype":"venue"
},
  "geometry": {"coordinates":[-96.70700100000001,30.525209],"type":"Point"}
}