{
  "type": "Feature",
  "properties": {
    "iso:country":"DE",
    "sg:address":"Ludwig-Thoma-Str. 4",
    "sg:city":"T\u00fcrkenfeld",
    "sg:phone":"+49 8193/1613",
    "sg:postcode":"82299",
    "sg:province":"Bayern",
    "wof:name":"Peter Schneller",
    "wof:placetype":"venue"
},
  "geometry": {"coordinates":[11.0885009766,48.1068534851],"type":"Point"}
}