{
  "type": "Feature",
  "properties": {
    "iso:country":"DE",
    "sg:address":"Weseler Str. 140",
    "sg:city":"Haltern",
    "sg:phone":"+49 2364/108259",
    "sg:postcode":"45721",
    "sg:province":"Nordrhein-Westfalen",
    "wof:name":"Karl-heinz Borgers",
    "wof:placetype":"venue"
},
  "geometry": {"coordinates":[7.1695981026,51.7380523682],"type":"Point"}
}