{
  "type": "Feature",
  "properties": {
    "iso:country":"DE",
    "sg:address":"Dinklager Str. 8",
    "sg:city":"Holdorf",
    "sg:phone":"+49 5494/8568",
    "sg:postcode":"49451",
    "sg:province":"Niedersachsen",
    "wof:name":"L & S M\u00f6bel Gmbh",
    "wof:placetype":"venue"
},
  "geometry": {"coordinates":[8.1268930435,52.5937309265],"type":"Point"}
}