{
  "type": "Feature",
  "properties": {
    "iso:country":"DE",
    "sg:address":"Am Langen Steg 7",
    "sg:city":"Weiden",
    "sg:postcode":"92637",
    "sg:province":"Bayern",
    "wof:name":"Zaxx Speed Communication Internet Gmbh",
    "wof:placetype":"venue"
},
  "geometry": {"coordinates":[12.1697587967,49.6820526123],"type":"Point"}
}