{
  "type": "Feature",
  "properties": {
    "iso:country":"DE",
    "sg:address":"Thomaestr. 9",
    "sg:city":"Braunschweig",
    "sg:phone":"+49 531/53969",
    "sg:postcode":"38118",
    "sg:province":"Niedersachsen",
    "wof:name":"Pizzeria Avcu",
    "wof:placetype":"venue"
},
  "geometry": {"coordinates":[10.5058250427,52.2687492371],"type":"Point"}
}