{
  "type": "Feature",
  "properties": {
    "iso:country":"DE",
    "sg:address":"Vorster Heidweg 12-14 Sevelen",
    "sg:city":"Issum",
    "sg:phone":"+49 4928/3595400",
    "sg:postcode":"47661",
    "sg:province":"Nordrhein-Westfalen",
    "wof:name":"Mathias Fronhoffs Gmbh & Co Kg",
    "wof:placetype":"venue"
},
  "geometry": {"coordinates":[6.426165,51.534786],"type":"Point"}
}