{
  "type": "Feature",
  "properties": {
    "iso:country":"DE",
    "sg:address":"Heerstr. 90",
    "sg:city":"St. Goar",
    "sg:phone":"+49 6741/7205",
    "sg:postcode":"56329",
    "sg:province":"Rheinland-Pfalz",
    "wof:name":"Junge Mode",
    "wof:placetype":"venue"
},
  "geometry": {"coordinates":[7.714147,50.151424],"type":"Point"}
}