{
  "type": "Feature",
  "properties": {
    "iso:country":"DE",
    "sg:address":"Ziegelstr. 167",
    "sg:city":"L\u00fcbeck",
    "sg:phone":"+49 451/8998080",
    "sg:postcode":"23556",
    "sg:province":"Schleswig-Holstein",
    "wof:name":"Dea Mineral\u00f6l Ag",
    "wof:placetype":"venue"
},
  "geometry": {"coordinates":[10.6465520859,53.8596191406],"type":"Point"}
}