{
  "type": "Feature",
  "properties": {
    "iso:country":"DE",
    "sg:address":"Frommannstr. 6",
    "sg:city":"Leipzig",
    "sg:phone":"+49 341/6880323",
    "sg:postcode":"04317",
    "sg:province":"Sachsen",
    "wof:name":"Junghanns & Kolosche Gmbh",
    "wof:placetype":"venue"
},
  "geometry": {"coordinates":[12.3976,51.337597],"type":"Point"}
}