{
  "type": "Feature",
  "properties": {
    "iso:country":"DE",
    "sg:address":"Friedberger Str. 89-91",
    "sg:city":"Bad Vilbel",
    "sg:phone":"+49 6101/409020",
    "sg:postcode":"61118",
    "sg:province":"Hessen",
    "wof:name":"Hessol Mineraloelvertrieb Gmbh",
    "wof:placetype":"venue"
},
  "geometry": {"coordinates":[8.7422819138,50.1897544861],"type":"Point"}
}