{
  "type": "Feature",
  "properties": {
    "iso:country":"DE",
    "sg:address":"Max-Greve-Str. 32",
    "sg:city":"Bochum",
    "sg:postcode":"44791",
    "sg:province":"Nordrhein-Westfalen",
    "wof:name":"Wirth & Partner Beteiligungs Ag",
    "wof:placetype":"venue"
},
  "geometry": {"coordinates":[7.23343,51.486263],"type":"Point"}
}