{
  "type": "Feature",
  "properties": {
    "iso:country":"DE",
    "sg:address":"Malchiner Str. 26",
    "sg:city":"Teterow",
    "sg:phone":"+49 3996/187014",
    "sg:postcode":"17166",
    "sg:province":"Mecklenburg-Vorpommern",
    "wof:name":"Einskaufscenter Leb. Gmbh",
    "wof:placetype":"venue"
},
  "geometry": {"coordinates":[12.576954,53.772198],"type":"Point"}
}