{
  "type": "Feature",
  "properties": {
    "iso:country":"DE",
    "sg:address":"Merckstr. 25",
    "sg:city":"Darmstadt",
    "sg:phone":"+49 6151/161",
    "sg:postcode":"64283",
    "sg:province":"Hessen",
    "wof:name":"Institut F\u00fcr Elektro- Mechanische Konstruktionen",
    "wof:placetype":"venue"
},
  "geometry": {"coordinates":[8.6611175537,49.8735694885],"type":"Point"}
}