{
  "type": "Feature",
  "properties": {
    "iso:country":"DE",
    "sg:address":"Barbarossastr. 31",
    "sg:city":"Sinzig",
    "sg:postcode":"53489",
    "sg:province":"Rheinland-Pfalz",
    "wof:name":"Meral",
    "wof:placetype":"venue"
},
  "geometry": {"coordinates":[7.251625,50.546108],"type":"Point"}
}