{
  "type": "Feature",
  "properties": {
    "iso:country":"DE",
    "sg:address":"Untere Str. 9",
    "sg:city":"Wipperf\u00fcrth",
    "sg:phone":"+49 2267/9456",
    "sg:postcode":"51688",
    "sg:province":"Nordrhein-Westfalen",
    "wof:name":"K. H. Riesener Augenoptiker",
    "wof:placetype":"venue"
},
  "geometry": {"coordinates":[7.3955860138,51.1167602539],"type":"Point"}
}