{
  "type": "Feature",
  "properties": {
    "iso:country":"DE",
    "sg:address":"Martin-Luther-Str. 16",
    "sg:city":"Bruchk\u00f6bel",
    "sg:phone":"+49 6181/709654",
    "sg:postcode":"63486",
    "sg:province":"Hessen",
    "wof:name":"Zen Line Dental Gmbh",
    "wof:placetype":"venue"
},
  "geometry": {"coordinates":[8.9213972092,50.1796188354],"type":"Point"}
}