{
  "type": "Feature",
  "properties": {
    "iso:country":"DE",
    "sg:address":"Maxstr 9",
    "sg:city":"Essen",
    "sg:phone":"+49 201/227912",
    "sg:postcode":"45127",
    "sg:province":"Nordrhein-Westfalen",
    "wof:name":"Fust Wever & Co Vertriebs Gmbh",
    "wof:placetype":"venue"
},
  "geometry": {"coordinates":[7.0089697838,51.4528884888],"type":"Point"}
}