{
  "type": "Feature",
  "properties": {
    "iso:country":"DE",
    "sg:address":"Entensumpfweg 5",
    "sg:city":"Uetze",
    "sg:phone":"+49 5147/8413",
    "sg:postcode":"31311",
    "sg:province":"Niedersachsen",
    "wof:name":"Bergmannsverein H\u00e4nigsen Werner Schubert",
    "wof:placetype":"venue"
},
  "geometry": {"coordinates":[10.1165151596,52.4912528992],"type":"Point"}
}