{
  "type": "Feature",
  "properties": {
    "iso:country":"DE",
    "sg:address":"Wallgasse",
    "sg:city":"Rinteln",
    "sg:phone":"+49 5751/44977",
    "sg:postcode":"31737",
    "sg:province":"Niedersachsen",
    "wof:name":"Ehleben Zeichen-service",
    "wof:placetype":"venue"
},
  "geometry": {"coordinates":[9.078765,52.187534],"type":"Point"}
}