{
  "type": "Feature",
  "properties": {
    "iso:country":"DE",
    "sg:address":"Engerser Landstr. 127 a",
    "sg:city":"Neuwied",
    "sg:phone":"+49 2631/20392",
    "sg:postcode":"56564",
    "sg:province":"Rheinland-Pfalz",
    "wof:name":"Roland Reinboth Architekt",
    "wof:placetype":"venue"
},
  "geometry": {"coordinates":[7.484121,50.429298],"type":"Point"}
}