{
  "type": "Feature",
  "properties": {
    "iso:country":"DE",
    "sg:address":"Brunnenstr. 5",
    "sg:city":"Leer",
    "sg:phone":"+49 491/61228",
    "sg:postcode":"26789",
    "sg:province":"Niedersachsen",
    "wof:name":"Restaurant Dionysos",
    "wof:placetype":"venue"
},
  "geometry": {"coordinates":[7.4503931999,53.2279777527],"type":"Point"}
}