{
  "type": "Feature",
  "properties": {
    "iso:country":"DE",
    "sg:address":"In den Wiesen 6",
    "sg:city":"Eisenberg",
    "sg:phone":"+49 36691/6330",
    "sg:postcode":"07607",
    "sg:province":"Th\u00fcringen",
    "wof:name":"Eisenberger Fenster- Und T\u00fcrenbau Gmbh & Co. Kg",
    "wof:placetype":"venue"
},
  "geometry": {"coordinates":[11.893661,50.970242],"type":"Point"}
}