{
  "type": "Feature",
  "properties": {
    "iso:country":"DE",
    "sg:address":"Max-Planck-Str. 12",
    "sg:city":"M\u00fcnchen",
    "sg:phone":"+49 89/4703879",
    "sg:postcode":"81675",
    "sg:province":"Bayern",
    "wof:name":"Irene Niewiem",
    "wof:placetype":"venue"
},
  "geometry": {"coordinates":[11.5976667404,48.1358451843],"type":"Point"}
}