{
  "type": "Feature",
  "properties": {
    "iso:country":"DE",
    "sg:address":"Kurf\u00fcrstendamm 131",
    "sg:city":"Berlin",
    "sg:phone":"+49 30/31423849",
    "sg:postcode":"10711",
    "sg:province":"Berlin",
    "wof:name":"Gutmann Kantinenbetriebe Gmbh",
    "wof:placetype":"venue"
},
  "geometry": {"coordinates":[13.2923021317,52.4971733093],"type":"Point"}
}