{
  "type": "Feature",
  "properties": {
    "iso:country":"DE",
    "sg:address":"S\u00fcderstr. 8-12",
    "sg:city":"Leck",
    "sg:phone":"+49 4662/878090",
    "sg:postcode":"25917",
    "sg:province":"Schleswig-Holstein",
    "wof:name":"Hagebaumarkt Friedrich Frenzel Gmbh",
    "wof:placetype":"venue"
},
  "geometry": {"coordinates":[8.9728593826,54.7714538574],"type":"Point"}
}