{
  "type": "Feature",
  "properties": {
    "iso:country":"DE",
    "sg:address":"Mittelweg 11",
    "sg:city":"Bernhardswald",
    "sg:phone":"+49 9407/3886",
    "sg:postcode":"93170",
    "sg:province":"Bayern",
    "wof:name":"Helmut Blindzellner Architekt",
    "wof:placetype":"venue"
},
  "geometry": {"coordinates":[12.244091,49.09164],"type":"Point"}
}