{
  "type": "Feature",
  "properties": {
    "iso:country":"DE",
    "sg:address":"Industriestr. 8",
    "sg:city":"Gr\u00fcnstadt",
    "sg:phone":"+49 6359/83006",
    "sg:postcode":"67269",
    "sg:province":"Rheinland-Pfalz",
    "wof:name":"Grulms-pneumatic Handelsgesellschaft Mbh",
    "wof:placetype":"venue"
},
  "geometry": {"coordinates":[8.1757898331,49.560962677],"type":"Point"}
}