{
  "type": "Feature",
  "properties": {
    "iso:country":"DE",
    "sg:address":"L\u00f6chgauer Str. 3",
    "sg:city":"Erligheim",
    "sg:phone":"+49 7143/21065",
    "sg:postcode":"74391",
    "sg:province":"Baden-W\u00fcrttemberg",
    "wof:name":"Helmut Umbach",
    "wof:placetype":"venue"
},
  "geometry": {"coordinates":[9.098837,49.019859],"type":"Point"}
}