{
  "type": "Feature",
  "properties": {
    "iso:country":"DE",
    "sg:address":"Hauptstr. 40",
    "sg:city":"Adenau",
    "sg:phone":"+49 2691/2380",
    "sg:postcode":"53518",
    "sg:province":"Rheinland-Pfalz",
    "wof:name":"S. Obliers",
    "wof:placetype":"venue"
},
  "geometry": {"coordinates":[6.9270339012,50.3829917908],"type":"Point"}
}