{
  "type": "Feature",
  "properties": {
    "iso:country":"DE",
    "sg:address":"Anton-Ulrich-Str. 47",
    "sg:city":"Meiningen",
    "sg:phone":"+49 3693/711489",
    "sg:postcode":"98617",
    "sg:province":"Th\u00fcringen",
    "wof:name":"Restaurant Plovdiv Inh. Kostadin Bosew",
    "wof:placetype":"venue"
},
  "geometry": {"coordinates":[10.4145727158,50.5646324158],"type":"Point"}
}