{
  "type": "Feature",
  "properties": {
    "iso:country":"DE",
    "sg:address":"Dahlhauser Str. 70",
    "sg:city":"Hattingen",
    "sg:phone":"+49 2324/81280",
    "sg:postcode":"45529",
    "sg:province":"Nordrhein-Westfalen",
    "wof:name":"Haus Benecken",
    "wof:placetype":"venue"
},
  "geometry": {"coordinates":[7.1635818481,51.4111747742],"type":"Point"}
}