{
  "type": "Feature",
  "properties": {
    "iso:country":"DE",
    "sg:address":"Parkstr. 4",
    "sg:city":"Balgst\u00e4dt",
    "sg:postcode":"06632",
    "sg:province":"Sachsen-Anhalt",
    "wof:name":"Evangelisches Pfarramt",
    "wof:placetype":"venue"
},
  "geometry": {"coordinates":[11.732790947,51.2062721252],"type":"Point"}
}