{
  "type": "Feature",
  "properties": {
    "iso:country":"DE",
    "sg:address":"Spielweg 8",
    "sg:city":"M\u00fcnstertal",
    "sg:phone":"+49 7636/280",
    "sg:postcode":"79244",
    "sg:province":"Baden-W\u00fcrttemberg",
    "wof:name":"J. Gutmann",
    "wof:placetype":"venue"
},
  "geometry": {"coordinates":[7.8345470428,47.8772697449],"type":"Point"}
}