{
  "type": "Feature",
  "properties": {
    "iso:country":"DE",
    "sg:address":"Birder Str. 37",
    "sg:city":"Selfkant",
    "sg:phone":"+49 2456/1238",
    "sg:postcode":"52538",
    "sg:province":"Nordrhein-Westfalen",
    "wof:name":"Leo Geradts",
    "wof:placetype":"venue"
},
  "geometry": {"coordinates":[5.899902,51.014378],"type":"Point"}
}