{
  "type": "Feature",
  "properties": {
    "iso:country":"DE",
    "sg:address":"Hohenzollernstr. 20",
    "sg:city":"B\u00fcsum",
    "sg:phone":"+49 4834/96110",
    "sg:postcode":"25761",
    "sg:province":"Schleswig-Holstein",
    "wof:name":"Hotel-restaurant Die Muschel",
    "wof:placetype":"venue"
},
  "geometry": {"coordinates":[8.8555135727,54.1295471191],"type":"Point"}
}