{
  "type": "Feature",
  "properties": {
    "iso:country":"DE",
    "sg:address":"Postfach 100318",
    "sg:city":"Siegen",
    "sg:postcode":"57003",
    "sg:province":"Nordrhein-Westfalen",
    "wof:name":"Institut F\u00fcr Wirtschaftsrecht",
    "wof:placetype":"venue"
},
  "geometry": {"coordinates":[8.02341,50.873798],"type":"Point"}
}