{
  "type": "Feature",
  "properties": {
    "iso:country":"DE",
    "sg:address":"Wolfenb\u00fctteler Str. 64",
    "sg:city":"Braunschweig",
    "sg:phone":"+49 531/73262",
    "sg:postcode":"38102",
    "sg:province":"Niedersachsen",
    "wof:name":"Walter Kelmereit",
    "wof:placetype":"venue"
},
  "geometry": {"coordinates":[10.5286626816,52.2519569397],"type":"Point"}
}