{
  "type": "Feature",
  "properties": {
    "iso:country":"DE",
    "sg:address":"Alter Sportplatz 16",
    "sg:city":"Heiden",
    "sg:phone":"+49 2867/90379",
    "sg:postcode":"46359",
    "sg:province":"Nordrhein-Westfalen",
    "wof:name":"G\u00fcnter Pels Architekt",
    "wof:placetype":"venue"
},
  "geometry": {"coordinates":[6.941488,51.823589],"type":"Point"}
}