{
  "type": "Feature",
  "properties": {
    "iso:country":"DE",
    "sg:address":"Kitzenhausweg 25",
    "sg:city":"Aachen",
    "sg:phone":"+49 2408/5260",
    "sg:postcode":"52076",
    "sg:province":"Nordrhein-Westfalen",
    "wof:name":"Alfons Kratzenberg",
    "wof:placetype":"venue"
},
  "geometry": {"coordinates":[6.195401,50.69397],"type":"Point"}
}