{
  "type": "Feature",
  "properties": {
    "iso:country":"DE",
    "sg:address":"Kochstr. 34",
    "sg:city":"Leipzig",
    "sg:phone":"+49 341/5647826",
    "sg:postcode":"04275",
    "sg:province":"Sachsen",
    "wof:name":"Saxonia Verm\u00f6gens- Und Immobilien Treuhand-gmbh",
    "wof:placetype":"venue"
},
  "geometry": {"coordinates":[12.371217,51.32048],"type":"Point"}
}