{
  "type": "Feature",
  "properties": {
    "iso:country":"DE",
    "sg:address":"Naumburger Str. 27",
    "sg:city":"Wei\u00dfenfels",
    "sg:postcode":"06667",
    "sg:province":"Sachsen-Anhalt",
    "wof:name":"Map-haus Gmbh",
    "wof:placetype":"venue"
},
  "geometry": {"coordinates":[11.9633407593,51.198600769],"type":"Point"}
}