{
  "type": "Feature",
  "properties": {
    "iso:country":"DE",
    "sg:address":"Metzer Str. 4",
    "sg:city":"Berlin",
    "sg:phone":"+49 30/4406461",
    "sg:postcode":"10405",
    "sg:province":"Berlin",
    "wof:name":"Abz Ambulantes Behandlungs- Zentrum Blumberger Damm Gmbh",
    "wof:placetype":"venue"
},
  "geometry": {"coordinates":[13.4266901016,52.5405197144],"type":"Point"}
}