{
  "type": "Feature",
  "properties": {
    "iso:country":"DE",
    "sg:address":"Flugplatz",
    "sg:city":"Ganderkesee",
    "sg:phone":"+49 4942/2270960",
    "sg:postcode":"27777",
    "sg:province":"Niedersachsen",
    "wof:name":"Fallschirmsportschule Ganderkesee",
    "wof:placetype":"venue"
},
  "geometry": {"coordinates":[8.5163669586,53.0301551819],"type":"Point"}
}