{
  "type": "Feature",
  "properties": {
    "iso:country":"DE",
    "sg:address":"Alte Bergstr. 400",
    "sg:city":"Landsberg",
    "sg:postcode":"86899",
    "sg:province":"Bayern",
    "wof:name":"Lauterbach Gmbh",
    "wof:placetype":"venue"
},
  "geometry": {"coordinates":[10.8786840439,48.0490989685],"type":"Point"}
}