{
  "type": "Feature",
  "properties": {
    "iso:country":"DE",
    "sg:address":"Gr\u00fcne 1",
    "sg:city":"Radevormwald",
    "sg:phone":"+49 2195/40319",
    "sg:postcode":"42477",
    "sg:province":"Nordrhein-Westfalen",
    "wof:name":"Pizzeria Zur Gr\u00fcne",
    "wof:placetype":"venue"
},
  "geometry": {"coordinates":[7.3895359039,51.2021369934],"type":"Point"}
}