{
  "type": "Feature",
  "properties": {
    "iso:country":"DE",
    "sg:address":"Neuh\u00e4user Str. 12",
    "sg:city":"Sonneberg",
    "sg:phone":"+49 3675/89260",
    "sg:postcode":"96515",
    "sg:province":"Th\u00fcringen",
    "wof:name":"Ads Sciherheitsdienste Gmbh",
    "wof:placetype":"venue"
},
  "geometry": {"coordinates":[11.2080097198,50.3536605835],"type":"Point"}
}