{
  "type": "Feature",
  "properties": {
    "iso:country":"DE",
    "sg:address":"Weidauer Str. 1",
    "sg:city":"Schwarzenberg",
    "sg:phone":"+49 3774/26102",
    "sg:postcode":"08340",
    "sg:province":"Sachsen",
    "wof:name":"Klaus Lentzen Rechtsanwalt",
    "wof:placetype":"venue"
},
  "geometry": {"coordinates":[12.7887983322,50.5454978943],"type":"Point"}
}