{
  "type": "Feature",
  "properties": {
    "iso:country":"DE",
    "sg:address":"Badhausstr. 26a",
    "sg:city":"Abensberg",
    "sg:phone":"+49 9443/7160",
    "sg:postcode":"93326",
    "sg:province":"Bayern",
    "wof:name":"Heinz Spitzbarth Architekt",
    "wof:placetype":"venue"
},
  "geometry": {"coordinates":[11.850087,48.812195],"type":"Point"}
}