{
  "type": "Feature",
  "properties": {
    "iso:country":"DE",
    "sg:address":"Burgstr 28::",
    "sg:city":"Berlin",
    "sg:phone":"+49 30/590011270",
    "sg:postcode":"10178",
    "sg:province":"Berlin",
    "wof:name":"Arbeitgeberverband Des Privaten Bankgewerbes Ev",
    "wof:placetype":"venue"
},
  "geometry": {"coordinates":[13.400986,52.520992],"type":"Point"}
}