{
  "type": "Feature",
  "properties": {
    "iso:country":"DE",
    "sg:address":"G\u00fcterbahnhofstr. 6",
    "sg:city":"Kamenz",
    "sg:phone":"+49 35783/01694",
    "sg:postcode":"01917",
    "sg:province":"Sachsen",
    "wof:name":"K & S Abholmarkt Gmbh",
    "wof:placetype":"venue"
},
  "geometry": {"coordinates":[14.0893421173,51.2746734619],"type":"Point"}
}