{
  "type": "Feature",
  "properties": {
    "iso:country":"DE",
    "sg:address":"Lutzhorner Landstr. 38",
    "sg:city":"Barmstedt",
    "sg:phone":"+49 4123/904920",
    "sg:postcode":"25355",
    "sg:province":"Schleswig-Holstein",
    "wof:name":"Wilhelm Ohrt Inh. Joachim Orth",
    "wof:placetype":"venue"
},
  "geometry": {"coordinates":[9.76982,53.811687],"type":"Point"}
}