{
  "type": "Feature",
  "properties": {
    "iso:country":"DE",
    "sg:address":"Mettmanner Str. 53-55",
    "sg:city":"Velbert",
    "sg:phone":"+49 2051/23079",
    "sg:postcode":"42549",
    "sg:province":"Nordrhein-Westfalen",
    "wof:name":"Helga Gries Kg",
    "wof:placetype":"venue"
},
  "geometry": {"coordinates":[7.0502758026,51.3317298889],"type":"Point"}
}