{
  "type": "Feature",
  "properties": {
    "iso:country":"DE",
    "sg:address":"Goethestr. 3",
    "sg:city":"Datteln",
    "sg:phone":"+49 2363/61780",
    "sg:postcode":"45711",
    "sg:province":"Nordrhein-Westfalen",
    "wof:name":"Hekatron Gmbh",
    "wof:placetype":"venue"
},
  "geometry": {"coordinates":[7.340435,51.658318],"type":"Point"}
}