{
  "type": "Feature",
  "properties": {
    "iso:country":"DE",
    "sg:address":"Schmiedestr. 52",
    "sg:city":"Wuppertal",
    "sg:phone":"+49 202/664052",
    "sg:postcode":"42279",
    "sg:province":"Nordrhein-Westfalen",
    "wof:name":"L. Hielscher",
    "wof:placetype":"venue"
},
  "geometry": {"coordinates":[7.2495498657,51.3141899109],"type":"Point"}
}