{
  "type": "Feature",
  "properties": {
    "iso:country":"DE",
    "sg:address":"Friedrichstr. 6",
    "sg:city":"Karlsdorf-Neuthard",
    "sg:postcode":"76689",
    "sg:province":"Baden-W\u00fcrttemberg",
    "wof:name":"Pars-verlag Gmbh",
    "wof:placetype":"venue"
},
  "geometry": {"coordinates":[8.5495100021,49.1379623413],"type":"Point"}
}