{
  "type": "Feature",
  "properties": {
    "iso:country":"DE",
    "sg:address":"Rudolst\u00e4dter Str. 145",
    "sg:city":"Erfurt",
    "sg:phone":"+49 361/3735320",
    "sg:postcode":"99099",
    "sg:province":"Th\u00fcringen",
    "wof:name":"Dipl.-ing. K. Zschiegner Ingenieur",
    "wof:placetype":"venue"
},
  "geometry": {"coordinates":[11.0803012848,50.964012146],"type":"Point"}
}