{
  "type": "Feature",
  "properties": {
    "iso:country":"DE",
    "sg:address":"Bergstr. 26",
    "sg:city":"Hamburg",
    "sg:phone":"+49 40/7679773",
    "sg:postcode":"20095",
    "sg:province":"Hamburg",
    "wof:name":"Deutsche Rhederei Versicherungs-ag",
    "wof:placetype":"venue"
},
  "geometry": {"coordinates":[9.9950227737,53.5514411926],"type":"Point"}
}