{
  "type": "Feature",
  "properties": {
    "iso:country":"DE",
    "sg:address":"Bleichstr. 8",
    "sg:city":"Pforzheim",
    "sg:phone":"+49 7231/25386",
    "sg:postcode":"75173",
    "sg:province":"Baden-W\u00fcrttemberg",
    "wof:name":"Safir",
    "wof:placetype":"venue"
},
  "geometry": {"coordinates":[8.6972675323,48.8879394531],"type":"Point"}
}