{
  "type": "Feature",
  "properties": {
    "iso:country":"DE",
    "sg:address":"Dunkelgasse 16",
    "sg:city":"Treuen",
    "sg:phone":"+49 37468/2431",
    "sg:postcode":"08233",
    "sg:province":"Sachsen",
    "wof:name":"M. Schrader",
    "wof:placetype":"venue"
},
  "geometry": {"coordinates":[12.3094778061,50.5406532288],"type":"Point"}
}