{
  "type": "Feature",
  "properties": {
    "iso:country":"DE",
    "sg:address":"In der Betz 21",
    "sg:city":"Leutesdorf",
    "sg:phone":"+49 2631/74980",
    "sg:postcode":"56599",
    "sg:province":"Rheinland-Pfalz",
    "wof:name":"Rolf Und Resi Sch\u00e4tzle",
    "wof:placetype":"venue"
},
  "geometry": {"coordinates":[7.377447,50.454185],"type":"Point"}
}