{
  "type": "Feature",
  "properties": {
    "iso:country":"DE",
    "sg:address":"Gr\u00f6mer 217",
    "sg:city":"Ha\u00dfleben",
    "sg:phone":"+49 36201/60512",
    "sg:postcode":"99189",
    "sg:province":"Th\u00fcringen",
    "wof:name":"K. Geske",
    "wof:placetype":"venue"
},
  "geometry": {"coordinates":[10.9945049286,51.1108474731],"type":"Point"}
}