{
  "type": "Feature",
  "properties": {
    "iso:country":"DE",
    "sg:address":"Stadtbahnbogen 593",
    "sg:city":"Berlin",
    "sg:phone":"+49 30/3186950",
    "sg:postcode":"10623",
    "sg:province":"Berlin",
    "wof:name":"Buecherbogen Am Savignyplatz Gmbh",
    "wof:placetype":"venue"
},
  "geometry": {"coordinates":[13.32804,52.508652],"type":"Point"}
}