{
  "type": "Feature",
  "properties": {
    "iso:country":"DE",
    "sg:address":"Moritzstr 7",
    "sg:city":"Wiesbaden",
    "sg:phone":"+49 611/305500",
    "sg:postcode":"65185",
    "sg:province":"Hessen",
    "wof:name":"Nass Gmbh",
    "wof:placetype":"venue"
},
  "geometry": {"coordinates":[8.23826,50.076572],"type":"Point"}
}