{
  "type": "Feature",
  "properties": {
    "iso:country":"DE",
    "sg:address":"Goethestr. 3",
    "sg:city":"Jena",
    "sg:phone":"+49 3641/890051",
    "sg:postcode":"07743",
    "sg:province":"Th\u00fcringen",
    "wof:name":"Rudolf Van Paridon",
    "wof:placetype":"venue"
},
  "geometry": {"coordinates":[11.581347,50.927639],"type":"Point"}
}