{
  "type": "Feature",
  "properties": {
    "iso:country":"DE",
    "sg:address":"Radeckestr 43",
    "sg:city":"M\u00fcnchen",
    "sg:phone":"+49 89/8346500",
    "sg:postcode":"81245",
    "sg:province":"Bayern",
    "wof:name":"Lugrama Graphische Maschinen Gro\u00dfhandel Gmbh",
    "wof:placetype":"venue"
},
  "geometry": {"coordinates":[11.47523,48.151871],"type":"Point"}
}