{
  "type": "Feature",
  "properties": {
    "iso:country":"DE",
    "sg:address":"Bahnhofstr. 16",
    "sg:city":"Suhl",
    "sg:phone":"+49 3681/722124",
    "sg:postcode":"98527",
    "sg:province":"Th\u00fcringen",
    "wof:name":"S. Kr\u00e4mer Immobilienmakler",
    "wof:placetype":"venue"
},
  "geometry": {"coordinates":[10.6867513657,50.6074981689],"type":"Point"}
}