{
  "type": "Feature",
  "properties": {
    "iso:country":"DE",
    "sg:address":"Grimbergstr 12b",
    "sg:city":"Gelsenkirchen",
    "sg:phone":"+49 209/980800",
    "sg:postcode":"45889",
    "sg:province":"Nordrhein-Westfalen",
    "wof:name":"Text Lite",
    "wof:placetype":"venue"
},
  "geometry": {"coordinates":[7.113332,51.540237],"type":"Point"}
}