{
  "type": "Feature",
  "properties": {
    "iso:country":"DE",
    "sg:address":"Keltenring 29",
    "sg:city":"Spiesheim",
    "sg:phone":"+49 6732/7045",
    "sg:postcode":"55288",
    "sg:province":"Rheinland-Pfalz",
    "wof:name":"Heribert Erbes",
    "wof:placetype":"venue"
},
  "geometry": {"coordinates":[8.1318874359,49.8131980896],"type":"Point"}
}