{
  "type": "Feature",
  "properties": {
    "iso:country":"DE",
    "sg:address":"Kellerbergstr. 38",
    "sg:city":"Steinach",
    "sg:postcode":"94377",
    "sg:province":"Bayern",
    "wof:name":"Imc Schroeder Gmbh",
    "wof:placetype":"venue"
},
  "geometry": {"coordinates":[12.6035547256,48.9506568909],"type":"Point"}
}