{
  "type": "Feature",
  "properties": {
    "iso:country":"DE",
    "sg:address":"Waldallee",
    "sg:city":"Remseck",
    "sg:postcode":"71686",
    "sg:province":"Baden-W\u00fcrttemberg",
    "wof:name":"Ortsb\u00fccherei Waldallee",
    "wof:placetype":"venue"
},
  "geometry": {"coordinates":[9.283075,48.886925],"type":"Point"}
}