{
  "type": "Feature",
  "properties": {
    "iso:country":"DE",
    "sg:address":"Wilhelmsh\u00f6her Allee 253",
    "sg:city":"Kassel",
    "sg:phone":"+49 561/3149469",
    "sg:postcode":"34131",
    "sg:province":"Hessen",
    "wof:name":"Fastmotion-tv",
    "wof:placetype":"venue"
},
  "geometry": {"coordinates":[9.44547,51.313488],"type":"Point"}
}