{
  "type": "Feature",
  "properties": {
    "iso:country":"DE",
    "sg:address":"P\u00fctzhecke 3",
    "sg:city":"Bonn",
    "sg:phone":"+49 228/484850",
    "sg:postcode":"53229",
    "sg:province":"Nordrhein-Westfalen",
    "wof:name":"Otto Seebode Min Rat",
    "wof:placetype":"venue"
},
  "geometry": {"coordinates":[7.1992402077,50.7382583618],"type":"Point"}
}