{
  "type": "Feature",
  "properties": {
    "iso:country":"DE",
    "sg:address":"Wallerfangerstr. 100",
    "sg:city":"Saarlouis",
    "sg:phone":"+49 6831/3063",
    "sg:postcode":"66740",
    "sg:province":"Saarland",
    "wof:name":"Autohaus Coerper, Saarlouis ( Opel )",
    "wof:placetype":"venue"
},
  "geometry": {"coordinates":[6.7367649078,49.3170890808],"type":"Point"}
}