{
  "type": "Feature",
  "properties": {
    "iso:country":"DE",
    "sg:address":"Bahnhofstr. 41",
    "sg:city":"Velbert",
    "sg:phone":"+49 2051/52293",
    "sg:postcode":"42551",
    "sg:province":"Nordrhein-Westfalen",
    "wof:name":"Winfried Krabbe",
    "wof:placetype":"venue"
},
  "geometry": {"coordinates":[7.0488228798,51.342010498],"type":"Point"}
}