{
  "type": "Feature",
  "properties": {
    "iso:country":"DE",
    "sg:address":"Suhrsweg 9",
    "sg:city":"Hamburg",
    "sg:phone":"+49 40/6918807",
    "sg:postcode":"22305",
    "sg:province":"Hamburg",
    "wof:name":"Harald Bremmer",
    "wof:placetype":"venue"
},
  "geometry": {"coordinates":[10.045992,53.592365],"type":"Point"}
}