{
  "type": "Feature",
  "properties": {
    "iso:country":"DE",
    "sg:address":"Hindenburgstr. 42",
    "sg:city":"B\u00fcnde",
    "sg:phone":"+49 5223/10494",
    "sg:postcode":"32257",
    "sg:province":"Nordrhein-Westfalen",
    "wof:name":"Weinstube Schnutetunker",
    "wof:placetype":"venue"
},
  "geometry": {"coordinates":[8.5921497345,52.1983528137],"type":"Point"}
}