{
  "type": "Feature",
  "properties": {
    "iso:country":"DE",
    "sg:address":"Laibstr. 26",
    "sg:city":"Dietingen",
    "sg:phone":"+49 7404/2877",
    "sg:postcode":"78661",
    "sg:province":"Baden-W\u00fcrttemberg",
    "wof:name":"Weinstube A. St\u00f6hr",
    "wof:placetype":"venue"
},
  "geometry": {"coordinates":[8.639040947,48.2325668335],"type":"Point"}
}