{
  "type": "Feature",
  "properties": {
    "iso:country":"DE",
    "sg:address":"Nentwigstr. 1",
    "sg:city":"Berlin",
    "sg:postcode":"12621",
    "sg:province":"Berlin",
    "wof:name":"Katholisches Pfarramt St. Martin",
    "wof:placetype":"venue"
},
  "geometry": {"coordinates":[13.6040096283,52.5148391724],"type":"Point"}
}