{
  "type": "Feature",
  "properties": {
    "iso:country":"DE",
    "sg:address":"Friedrich-Ebert-Str. 133",
    "sg:city":"Krefeld",
    "sg:phone":"+49 2151/502321",
    "sg:postcode":"47800",
    "sg:province":"Nordrhein-Westfalen",
    "wof:name":"Sch\u00fctz Bodenschutz Gmbh",
    "wof:placetype":"venue"
},
  "geometry": {"coordinates":[6.588071,51.343067],"type":"Point"}
}