{
  "type": "Feature",
  "properties": {
    "iso:country":"DE",
    "sg:address":"Rostocker Str. 7",
    "sg:city":"Horn-Bad Meinberg",
    "sg:phone":"+49 5234/98881",
    "sg:postcode":"32805",
    "sg:province":"Nordrhein-Westfalen",
    "wof:name":"Pension Haus Ostermann",
    "wof:placetype":"venue"
},
  "geometry": {"coordinates":[8.9880685806,51.8982009888],"type":"Point"}
}