{
  "type": "Feature",
  "properties": {
    "iso:country":"DE",
    "sg:address":"August-Kutterer-Str. 18",
    "sg:city":"Karlsruhe",
    "sg:phone":"+49 721/573468",
    "sg:postcode":"76189",
    "sg:province":"Baden-W\u00fcrttemberg",
    "wof:name":"Walter Neukirchen",
    "wof:placetype":"venue"
},
  "geometry": {"coordinates":[8.318525,49.008175],"type":"Point"}
}