{
  "type": "Feature",
  "properties": {
    "iso:country":"DE",
    "sg:address":"H\u00f6rlbach 22",
    "sg:city":"Ellingen",
    "sg:phone":"+49 9141/3373",
    "sg:postcode":"91792",
    "sg:province":"Bayern",
    "wof:name":"Kurt Beranovsky",
    "wof:placetype":"venue"
},
  "geometry": {"coordinates":[10.9413709641,49.0757827759],"type":"Point"}
}