{
  "type": "Feature",
  "properties": {
    "iso:country":"DE",
    "sg:address":"Brockeswalder Chaussee 52",
    "sg:city":"Cuxhaven",
    "sg:phone":"+49 4721/27919",
    "sg:postcode":"27474",
    "sg:province":"Niedersachsen",
    "wof:name":"Kleiderkur Engl Gmbh",
    "wof:placetype":"venue"
},
  "geometry": {"coordinates":[8.68301,53.8596],"type":"Point"}
}