{
  "type": "Feature",
  "properties": {
    "iso:country":"DE",
    "sg:address":"Bischofswerdaer Str. 36",
    "sg:city":"Gro\u00dfr\u00f6hrsdorf",
    "sg:phone":"+49 35952/56158",
    "sg:postcode":"01900",
    "sg:province":"Sachsen",
    "wof:name":"M. Rasch",
    "wof:placetype":"venue"
},
  "geometry": {"coordinates":[14.033290863,51.1429862976],"type":"Point"}
}