{
  "type": "Feature",
  "properties": {
    "iso:country":"DE",
    "sg:address":"Schollkamp 25",
    "sg:city":"Schermbeck",
    "sg:phone":"+49 2853/2659",
    "sg:postcode":"46514",
    "sg:province":"Nordrhein-Westfalen",
    "wof:name":"Hugo Meusel Architekt",
    "wof:placetype":"venue"
},
  "geometry": {"coordinates":[6.876379,51.687893],"type":"Point"}
}