{
  "type": "Feature",
  "properties": {
    "iso:country":"DE",
    "sg:address":"Oberholzweg",
    "sg:city":"Ochtendung",
    "sg:postcode":"56299",
    "sg:province":"Rheinland-Pfalz",
    "wof:name":"Hans M\u00fcller Gmbh",
    "wof:placetype":"venue"
},
  "geometry": {"coordinates":[7.4289431572,50.3549156189],"type":"Point"}
}