{
  "type": "Feature",
  "properties": {
    "iso:country":"DE",
    "sg:address":"Dorfstr. 17",
    "sg:city":"Ludwigsburg",
    "sg:phone":"+49 7141/464620",
    "sg:postcode":"71636",
    "sg:province":"Baden-W\u00fcrttemberg",
    "wof:name":"Drapalla",
    "wof:placetype":"venue"
},
  "geometry": {"coordinates":[9.1612119675,48.8849411011],"type":"Point"}
}