{
  "type": "Feature",
  "properties": {
    "iso:country":"DE",
    "sg:address":"Vichter Str. 48",
    "sg:city":"Stolberg",
    "sg:phone":"+49 2402/75832",
    "sg:postcode":"52224",
    "sg:province":"Nordrhein-Westfalen",
    "wof:name":"C. Delhey",
    "wof:placetype":"venue"
},
  "geometry": {"coordinates":[6.2775321007,50.7544555664],"type":"Point"}
}