{
  "type": "Feature",
  "properties": {
    "iso:country":"DE",
    "sg:address":"Potsdamer Stra\u00dfe 16",
    "sg:city":"Brandenburg",
    "sg:phone":"+49 3381/517160",
    "sg:postcode":"14776",
    "sg:province":"Brandenburg",
    "wof:name":"Ingenieurb\u00fcro Dipl.-ing. Ludwig Dathe",
    "wof:placetype":"venue"
},
  "geometry": {"coordinates":[12.575261,52.405811],"type":"Point"}
}