{
  "type": "Feature",
  "properties": {
    "iso:country":"DE",
    "sg:address":"Am Kilitzsch 1",
    "sg:city":"Salzm\u00fcnde",
    "sg:phone":"+49 34609/22090",
    "sg:postcode":"06198",
    "sg:province":"Sachsen-Anhalt",
    "wof:name":"All-flamm Heizservice",
    "wof:placetype":"venue"
},
  "geometry": {"coordinates":[11.8319816589,51.565826416],"type":"Point"}
}