{
  "type": "Feature",
  "properties": {
    "iso:country":"DE",
    "sg:address":"Agnes-Miegel-Str. 11",
    "sg:city":"Leonberg",
    "sg:phone":"+49 7152/25261",
    "sg:postcode":"71229",
    "sg:province":"Baden-W\u00fcrttemberg",
    "wof:name":"Walter Rentschler",
    "wof:placetype":"venue"
},
  "geometry": {"coordinates":[9.016618,48.803619],"type":"Point"}
}