{
  "type": "Feature",
  "properties": {
    "iso:country":"DE",
    "sg:address":"Gewerbegebiet 5",
    "sg:city":"K\u00f6nigsee",
    "sg:phone":"+49 36738/6030",
    "sg:postcode":"07426",
    "sg:province":"Th\u00fcringen",
    "wof:name":"Lattermann & Schreyer Lasertechnik Gmbh",
    "wof:placetype":"venue"
},
  "geometry": {"coordinates":[11.109466,50.653263],"type":"Point"}
}