{
  "type": "Feature",
  "properties": {
    "iso:country":"DE",
    "sg:address":"Crimmitschauer Str. 133",
    "sg:city":"Zwickau",
    "sg:phone":"+49 375/523736",
    "sg:postcode":"08058",
    "sg:province":"Sachsen",
    "wof:name":"Wolfgang Sonntag",
    "wof:placetype":"venue"
},
  "geometry": {"coordinates":[12.47241,50.735371],"type":"Point"}
}