{
  "type": "Feature",
  "properties": {
    "iso:country":"DE",
    "sg:address":"Vogelsang 8",
    "sg:city":"Damp",
    "sg:postcode":"24351",
    "sg:province":"Schleswig-Holstein",
    "wof:name":"Rainer Hansen B\u00e4ckerei",
    "wof:placetype":"venue"
},
  "geometry": {"coordinates":[9.956626,54.57066],"type":"Point"}
}