{
  "type": "Feature",
  "properties": {
    "iso:country":"DE",
    "sg:address":"Erbprinzenstr. 4 -12",
    "sg:city":"Karlsruhe",
    "sg:postcode":"76133",
    "sg:province":"Baden-W\u00fcrttemberg",
    "wof:name":"1 & 1 Pure Tec Gmbh",
    "wof:placetype":"venue"
},
  "geometry": {"coordinates":[8.4029064178,49.0072746277],"type":"Point"}
}