{
  "type": "Feature",
  "properties": {
    "iso:country":"DE",
    "sg:address":"Siegesstr 100",
    "sg:city":"Wuppertal",
    "sg:phone":"+49 202/81626",
    "sg:postcode":"42285",
    "sg:province":"Nordrhein-Westfalen",
    "wof:name":"Breidenbach-druck Kg",
    "wof:placetype":"venue"
},
  "geometry": {"coordinates":[7.1830911636,51.2629814148],"type":"Point"}
}