{
  "type": "Feature",
  "properties": {
    "iso:country":"DE",
    "sg:address":"torleystr. 13",
    "sg:city":"iserlohn",
    "sg:postcode":"58644",
    "sg:province":"Nordrhein-Westfalen",
    "wof:name":"B\u00f6rseninfo-shop!",
    "wof:placetype":"venue"
},
  "geometry": {"coordinates":[7.713216,51.368408],"type":"Point"}
}