{
  "type": "Feature",
  "properties": {
    "iso:country":"DE",
    "sg:address":"Gartenstr. 8",
    "sg:city":"Bad Wimpfen",
    "sg:phone":"+49 7063/471",
    "sg:postcode":"74206",
    "sg:province":"Baden-W\u00fcrttemberg",
    "wof:name":"K. Sch\u00f6ll",
    "wof:placetype":"venue"
},
  "geometry": {"coordinates":[9.158612,49.231651],"type":"Point"}
}