{
  "type": "Feature",
  "properties": {
    "iso:country":"DE",
    "sg:address":"D\u00fcrener Str. 182",
    "sg:city":"K\u00f6ln",
    "sg:phone":"+49 221/403123",
    "sg:postcode":"50931",
    "sg:province":"Nordrhein-Westfalen",
    "wof:name":"Melitta Weiss",
    "wof:placetype":"venue"
},
  "geometry": {"coordinates":[6.914401,50.929852],"type":"Point"}
}