{
  "type": "Feature",
  "properties": {
    "iso:country":"DE",
    "sg:address":"Benzstra\u00dfe 6",
    "sg:city":"Heddesheim",
    "sg:phone":"+49 6203/4897",
    "sg:postcode":"68542",
    "sg:province":"Baden-W\u00fcrttemberg",
    "wof:name":"Friedhelm Zei\u00df Gmbh",
    "wof:placetype":"venue"
},
  "geometry": {"coordinates":[8.6309089661,49.5108413696],"type":"Point"}
}