{
  "type": "Feature",
  "properties": {
    "iso:country":"DE",
    "sg:address":"Aachener Str. 1036",
    "sg:city":"K\u00f6ln",
    "sg:phone":"+49 221/48990",
    "sg:postcode":"50858",
    "sg:province":"Nordrhein-Westfalen",
    "wof:name":"Funny-frisch Snack Und Geb\u00e4ck Gmbh",
    "wof:placetype":"venue"
},
  "geometry": {"coordinates":[6.8588337898,50.9380836487],"type":"Point"}
}