{
  "type": "Feature",
  "properties": {
    "iso:country":"DE",
    "sg:address":"Karl-von-Drais-Str. 5a",
    "sg:city":"Frankfurt",
    "sg:phone":"+49 69/546040",
    "sg:postcode":"60435",
    "sg:province":"Hessen",
    "wof:name":"Chr. Keller-zeller Masseur",
    "wof:placetype":"venue"
},
  "geometry": {"coordinates":[8.681292,50.147552],"type":"Point"}
}