{
  "type": "Feature",
  "properties": {
    "iso:country":"DE",
    "sg:address":"Poststr.",
    "sg:city":"Guxhagen",
    "sg:postcode":"34302",
    "sg:province":"Hessen",
    "wof:name":"Gemeindeb\u00fccherei",
    "wof:placetype":"venue"
},
  "geometry": {"coordinates":[9.481416,51.202091],"type":"Point"}
}