{
  "type": "Feature",
  "properties": {
    "iso:country":"DE",
    "sg:address":"Schwedenstr. 56",
    "sg:city":"M\u00fcnchen",
    "sg:phone":"+49 89/3615814",
    "sg:postcode":"80805",
    "sg:province":"Bayern",
    "wof:name":"Michael Schumann Rechtsanwalt",
    "wof:placetype":"venue"
},
  "geometry": {"coordinates":[11.6029233932,48.1678352356],"type":"Point"}
}