{
  "type": "Feature",
  "properties": {
    "iso:country":"DE",
    "sg:address":"Hugenottenallee 22",
    "sg:city":"Neu-Isenburg",
    "sg:phone":"+49 6102/23000",
    "sg:postcode":"63263",
    "sg:province":"Hessen",
    "wof:name":"Kurt Br\u00f6r",
    "wof:placetype":"venue"
},
  "geometry": {"coordinates":[8.6888580322,50.0566673279],"type":"Point"}
}