{
  "type": "Feature",
  "properties": {
    "iso:country":"DE",
    "sg:address":"Weirachstr. 3",
    "sg:city":"Burgstetten",
    "sg:phone":"+49 7191/65974",
    "sg:postcode":"71576",
    "sg:province":"Baden-W\u00fcrttemberg",
    "wof:name":"Skg Erbstetten Karl Bohn",
    "wof:placetype":"venue"
},
  "geometry": {"coordinates":[9.3873462677,48.927318573],"type":"Point"}
}