{
  "type": "Feature",
  "properties": {
    "iso:country":"DE",
    "sg:address":"Rechbergstr. 31",
    "sg:city":"Waldstetten",
    "sg:phone":"+49 7171/498333",
    "sg:postcode":"73550",
    "sg:province":"Baden-W\u00fcrttemberg",
    "wof:name":"Markus Hofele Gmbh",
    "wof:placetype":"venue"
},
  "geometry": {"coordinates":[9.8136205673,48.7635231018],"type":"Point"}
}