{
  "type": "Feature",
  "properties": {
    "iso:country":"DE",
    "sg:address":"Am Sportplatz 8",
    "sg:city":"Tautenhain",
    "sg:phone":"+49 36601/8680",
    "sg:postcode":"07639",
    "sg:province":"Th\u00fcringen",
    "wof:name":"Sita Esr Gmbh & Co. Kg",
    "wof:placetype":"venue"
},
  "geometry": {"coordinates":[11.924093,50.921795],"type":"Point"}
}