{
  "type": "Feature",
  "properties": {
    "iso:country":"DE",
    "sg:address":"Schier\u00e4ckerstr. 7",
    "sg:city":"N\u00fcrnberg",
    "sg:phone":"+49 911/32170",
    "sg:postcode":"90431",
    "sg:province":"Bayern",
    "wof:name":"Gerbeth Gmbh",
    "wof:placetype":"venue"
},
  "geometry": {"coordinates":[11.015417,49.455429],"type":"Point"}
}