{
  "type": "Feature",
  "properties": {
    "iso:country":"DE",
    "sg:address":"Bahnhofstr. 14",
    "sg:city":"Nonnenhorn",
    "sg:phone":"+49 8382/8235",
    "sg:postcode":"88149",
    "sg:province":"Bayern",
    "wof:name":"G\u00fcnter Hirlinger",
    "wof:placetype":"venue"
},
  "geometry": {"coordinates":[9.613625,47.574203],"type":"Point"}
}