{
  "type": "Feature",
  "properties": {
    "iso:country":"DE",
    "sg:address":"Rader Str. 55 A",
    "sg:city":"Schwanewede",
    "sg:phone":"+49 4296/377",
    "sg:postcode":"28790",
    "sg:province":"Niedersachsen",
    "wof:name":"Hermann Morisse",
    "wof:placetype":"venue"
},
  "geometry": {"coordinates":[8.518001,53.268559],"type":"Point"}
}