{
  "type": "Feature",
  "properties": {
    "iso:country":"DE",
    "sg:address":"Halinger Dorfstr. 83",
    "sg:city":"Menden",
    "sg:phone":"+49 2378/2580",
    "sg:postcode":"58708",
    "sg:province":"Nordrhein-Westfalen",
    "wof:name":"G\u00fcnter Krumscheid Gmbh",
    "wof:placetype":"venue"
},
  "geometry": {"coordinates":[7.719162,51.460575],"type":"Point"}
}