{
  "type": "Feature",
  "properties": {
    "iso:country":"DE",
    "sg:address":"Mittelstr. 60",
    "sg:city":"Neuwied",
    "sg:phone":"+49 2631/29807",
    "sg:postcode":"56564",
    "sg:province":"Rheinland-Pfalz",
    "wof:name":"Dress Point Gmbh",
    "wof:placetype":"venue"
},
  "geometry": {"coordinates":[7.4607200623,50.4294433594],"type":"Point"}
}