{
  "type": "Feature",
  "properties": {
    "iso:country":"DE",
    "sg:address":"Breite Str. 12",
    "sg:city":"Saarbr\u00fccken",
    "sg:phone":"+49 681/49294",
    "sg:postcode":"66115",
    "sg:province":"Saarland",
    "wof:name":"Rita Niedermeier",
    "wof:placetype":"venue"
},
  "geometry": {"coordinates":[6.953655,49.241718],"type":"Point"}
}