{
  "type": "Feature",
  "properties": {
    "iso:country":"DE",
    "sg:address":"Markgrafenstr. 53",
    "sg:city":"Emmendingen",
    "sg:phone":"+49 7641/930680",
    "sg:postcode":"79312",
    "sg:province":"Baden-W\u00fcrttemberg",
    "wof:name":"Hotel Markgraf Gmbh",
    "wof:placetype":"venue"
},
  "geometry": {"coordinates":[7.8533420563,48.1177558899],"type":"Point"}
}