{
  "type": "Feature",
  "properties": {
    "iso:country":"DE",
    "sg:address":"Fischers Allee 91",
    "sg:city":"Hamburg",
    "sg:postcode":"22763",
    "sg:province":"Hamburg",
    "wof:name":"Das Aktuelle Xbox Forum",
    "wof:placetype":"venue"
},
  "geometry": {"coordinates":[9.922214,53.552811],"type":"Point"}
}