{
  "type": "Feature",
  "properties": {
    "iso:country":"DE",
    "sg:address":"Herzogenstr. 5",
    "sg:city":"W\u00fcrzburg",
    "sg:phone":"+49 931/18295",
    "sg:postcode":"97070",
    "sg:province":"Bayern",
    "wof:name":"Friedrich May Kunstmaler",
    "wof:placetype":"venue"
},
  "geometry": {"coordinates":[9.931627,49.795673],"type":"Point"}
}