{
  "type": "Feature",
  "properties": {
    "iso:country":"DE",
    "sg:address":"Neusser Str. 30",
    "sg:city":"K\u00f6ln",
    "sg:phone":"+49 221/7326888",
    "sg:postcode":"50670",
    "sg:province":"Nordrhein-Westfalen",
    "wof:name":"T. Miller Rechtsanwalt",
    "wof:placetype":"venue"
},
  "geometry": {"coordinates":[6.9574069977,50.9527816772],"type":"Point"}
}