{
  "type": "Feature",
  "properties": {
    "iso:country":"DE",
    "sg:address":"An der Bahn 36",
    "sg:city":"Ganderkesee",
    "sg:phone":"+49 4223/2328",
    "sg:postcode":"27777",
    "sg:province":"Niedersachsen",
    "wof:name":"Sandstrahlbetrieb Schl\u00fcter Gmbh",
    "wof:placetype":"venue"
},
  "geometry": {"coordinates":[8.519566,53.100185],"type":"Point"}
}