{
  "type": "Feature",
  "properties": {
    "iso:country":"DE",
    "sg:address":"B\u00fcrg 1",
    "sg:city":"Rattenkirchen",
    "sg:phone":"+49 8073/642",
    "sg:postcode":"84431",
    "sg:province":"Bayern",
    "wof:name":"Lorenz St\u00f6ckl",
    "wof:placetype":"venue"
},
  "geometry": {"coordinates":[12.2983,48.215645],"type":"Point"}
}