{
  "type": "Feature",
  "properties": {
    "iso:country":"DE",
    "sg:address":"Scherlebecker Str. 281",
    "sg:city":"Herten",
    "sg:phone":"+49 2366/42644",
    "sg:postcode":"45701",
    "sg:province":"Nordrhein-Westfalen",
    "wof:name":"Gertrudenau",
    "wof:placetype":"venue"
},
  "geometry": {"coordinates":[7.1417078972,51.6202926636],"type":"Point"}
}