{
  "type": "Feature",
  "properties": {
    "iso:country":"DE",
    "sg:address":"Girbigsdorfer Stra\u00dfe 17",
    "sg:city":"G\u00f6rlitz",
    "sg:phone":"+49 3581",
    "sg:postcode":"02828",
    "sg:province":"Sachsen",
    "wof:name":"Schweisstechnik Dieter Kluge",
    "wof:placetype":"venue"
},
  "geometry": {"coordinates":[14.9692,51.16291],"type":"Point"}
}