{
  "type": "Feature",
  "properties": {
    "iso:country":"DE",
    "sg:address":"Robert-Koch-Str. 3",
    "sg:city":"Goslar",
    "sg:postcode":"38642",
    "sg:province":"Niedersachsen",
    "wof:name":"Stadtb\u00fccherei Goslar Zweigst.j\u00fcrgenohl",
    "wof:placetype":"venue"
},
  "geometry": {"coordinates":[10.438773,51.921848],"type":"Point"}
}