{
  "type": "Feature",
  "properties": {
    "iso:country":"DE",
    "sg:address":"Burgstr. 24/26",
    "sg:city":"Krummh\u00f6rn",
    "sg:phone":"+49 4923/253",
    "sg:postcode":"26736",
    "sg:province":"Niedersachsen",
    "wof:name":"Burg-apotheke",
    "wof:placetype":"venue"
},
  "geometry": {"coordinates":[7.096821,53.435055],"type":"Point"}
}