{
  "type": "Feature",
  "properties": {
    "iso:country":"DE",
    "sg:address":"Carl-Theodor-Str. 7",
    "sg:city":"Schwetzingen",
    "sg:phone":"+49 6202/17533",
    "sg:postcode":"68723",
    "sg:province":"Baden-W\u00fcrttemberg",
    "wof:name":"China-restaurant Shanghai",
    "wof:placetype":"venue"
},
  "geometry": {"coordinates":[8.5746221542,49.384677887],"type":"Point"}
}