{
  "type": "Feature",
  "properties": {
    "iso:country":"DE",
    "sg:address":"Falkenbergstr. 190",
    "sg:city":"Norderstedt",
    "sg:phone":"+49 40/5223519",
    "sg:postcode":"22844",
    "sg:province":"Schleswig-Holstein",
    "wof:name":"Werner Grotherr",
    "wof:placetype":"venue"
},
  "geometry": {"coordinates":[10.012929,53.720432],"type":"Point"}
}