{
  "type": "Feature",
  "properties": {
    "iso:country":"DE",
    "sg:address":"Schernegg",
    "sg:city":"Massing",
    "sg:phone":"+49 8724/1382",
    "sg:postcode":"84323",
    "sg:province":"Bayern",
    "wof:name":"J. Enghuber",
    "wof:placetype":"venue"
},
  "geometry": {"coordinates":[12.617627,48.405586],"type":"Point"}
}