{
  "type": "Feature",
  "properties": {
    "iso:country":"DE",
    "sg:address":"Am Oelvebach 37",
    "sg:city":"Krefeld",
    "sg:phone":"+49 2151/570116",
    "sg:postcode":"47809",
    "sg:province":"Nordrhein-Westfalen",
    "wof:name":"Aengenvoort Gmbh",
    "wof:placetype":"venue"
},
  "geometry": {"coordinates":[6.664811,51.32869],"type":"Point"}
}