{
  "type": "Feature",
  "properties": {
    "iso:country":"DE",
    "sg:address":"Alt-Wittenau 95",
    "sg:city":"Berlin",
    "sg:phone":"+49 30/4117040",
    "sg:postcode":"13437",
    "sg:province":"Berlin",
    "wof:name":"Fliesen Junck Fachbaumarkt Gmbh",
    "wof:placetype":"venue"
},
  "geometry": {"coordinates":[13.3379583359,52.5892906189],"type":"Point"}
}