{
  "type": "Feature",
  "properties": {
    "iso:country":"DE",
    "sg:address":"Im Brunnenfeld 2",
    "sg:city":"Umkirch",
    "sg:phone":"+49 7665/6014",
    "sg:postcode":"79224",
    "sg:province":"Baden-W\u00fcrttemberg",
    "wof:name":"Badische Staatsbrauerei Rothaus Ag",
    "wof:placetype":"venue"
},
  "geometry": {"coordinates":[7.771899,48.029797],"type":"Point"}
}