{
  "type": "Feature",
  "properties": {
    "iso:country":"DE",
    "sg:address":"Hilsstr. 29",
    "sg:city":"Holzen",
    "sg:phone":"+49 5534/2362",
    "sg:postcode":"37632",
    "sg:province":"Niedersachsen",
    "wof:name":"Ernst-august Samsen",
    "wof:placetype":"venue"
},
  "geometry": {"coordinates":[9.668785,51.935085],"type":"Point"}
}