{
  "type": "Feature",
  "properties": {
    "iso:country":"DE",
    "sg:address":"Landstr. 16 B",
    "sg:city":"Miltzow",
    "sg:phone":"+49 38328/252",
    "sg:postcode":"18519",
    "sg:province":"Mecklenburg-Vorpommern",
    "wof:name":"Mastgut Engelswacht Gmbh",
    "wof:placetype":"venue"
},
  "geometry": {"coordinates":[13.169895,54.206226],"type":"Point"}
}