{
  "type": "Feature",
  "properties": {
    "iso:country":"DE",
    "sg:address":"Krahnendonk 119",
    "sg:city":"M\u00f6nchengladbach",
    "sg:phone":"+49 2161",
    "sg:postcode":"41066",
    "sg:province":"Nordrhein-Westfalen",
    "wof:name":"Fliesenhandel",
    "wof:placetype":"venue"
},
  "geometry": {"coordinates":[6.470512867,51.2292976379],"type":"Point"}
}