{
  "type": "Feature",
  "properties": {
    "iso:country":"DE",
    "sg:address":"Dornbusch 2",
    "sg:city":"Hamburg",
    "sg:postcode":"20095",
    "sg:province":"Hamburg",
    "wof:name":"Verwaltung S. I. T. Stegmann Informations Technologie Gmbh",
    "wof:placetype":"venue"
},
  "geometry": {"coordinates":[9.994006,53.549026],"type":"Point"}
}