{
  "type": "Feature",
  "properties": {
    "iso:country":"DE",
    "sg:address":"Westhofener Str. 1",
    "sg:city":"Dortmund",
    "sg:phone":"+49 4923/177450",
    "sg:postcode":"44265",
    "sg:province":"Nordrhein-Westfalen",
    "wof:name":"Hotel Merkure Landhaus Syburg",
    "wof:placetype":"venue"
},
  "geometry": {"coordinates":[7.49405,51.425838],"type":"Point"}
}