{
  "type": "Feature",
  "properties": {
    "iso:country":"DE",
    "sg:address":"Sophie-Charlotten-Str. 73",
    "sg:city":"Berlin",
    "sg:postcode":"14059",
    "sg:province":"Berlin",
    "wof:name":"Dfr Landhaus-bau Gmbh & Co. Canadien Homes Kg",
    "wof:placetype":"venue"
},
  "geometry": {"coordinates":[13.288957,52.512032],"type":"Point"}
}