{
  "type": "Feature",
  "properties": {
    "iso:country":"DE",
    "sg:address":"Lindenweg 12",
    "sg:city":"Halsbr\u00fccke",
    "sg:phone":"+49 3731/32717",
    "sg:postcode":"09633",
    "sg:province":"Sachsen",
    "wof:name":"H.-j. Frank",
    "wof:placetype":"venue"
},
  "geometry": {"coordinates":[13.3644552231,50.9393348694],"type":"Point"}
}