{
  "type": "Feature",
  "properties": {
    "iso:country":"DE",
    "sg:address":"Hart 6",
    "sg:city":"Edling",
    "sg:phone":"+49 8039/1774",
    "sg:postcode":"83533",
    "sg:province":"Bayern",
    "wof:name":"Harter Schlo\u00dfstuben",
    "wof:placetype":"venue"
},
  "geometry": {"coordinates":[12.1488199234,48.0373382568],"type":"Point"}
}