{
  "type": "Feature",
  "properties": {
    "iso:country":"DE",
    "sg:address":"Birsteiner Str. 5",
    "sg:city":"Gelnhausen",
    "sg:phone":"+49 6045/3386",
    "sg:postcode":"63571",
    "sg:province":"Hessen",
    "wof:name":"Thomas Otto",
    "wof:placetype":"venue"
},
  "geometry": {"coordinates":[9.223487854,50.2084960938],"type":"Point"}
}