{
  "type": "Feature",
  "properties": {
    "iso:country":"DE",
    "sg:address":"Tambacher Str. 13",
    "sg:city":"Floh-Seligenthal",
    "sg:phone":"+49 3683/604666",
    "sg:postcode":"98593",
    "sg:province":"Th\u00fcringen",
    "wof:name":"Hartmut Waitz",
    "wof:placetype":"venue"
},
  "geometry": {"coordinates":[10.4819898605,50.7543334961],"type":"Point"}
}