{
  "type": "Feature",
  "properties": {
    "iso:country":"DE",
    "sg:address":"Stettiner Str. 10",
    "sg:city":"L\u00f6hne",
    "sg:phone":"+49 5732/7980",
    "sg:postcode":"32584",
    "sg:province":"Nordrhein-Westfalen",
    "wof:name":"Eckhard Grummert Architekt",
    "wof:placetype":"venue"
},
  "geometry": {"coordinates":[8.708429,52.233246],"type":"Point"}
}