{
  "type": "Feature",
  "properties": {
    "iso:country":"DE",
    "sg:address":"Orlandostr. 8",
    "sg:city":"M\u00fcnchen",
    "sg:phone":"+49 89/29160602",
    "sg:postcode":"80331",
    "sg:province":"Bayern",
    "wof:name":"Franz Xaver Hafner Architekt",
    "wof:placetype":"venue"
},
  "geometry": {"coordinates":[11.57961,48.137444],"type":"Point"}
}