{
  "type": "Feature",
  "properties": {
    "iso:country":"DE",
    "sg:address":"Industriestr. 11",
    "sg:city":"Schwandorf",
    "sg:phone":"+49 9431/748710",
    "sg:postcode":"92421",
    "sg:province":"Bayern",
    "wof:name":"Wilczek Gmbh",
    "wof:placetype":"venue"
},
  "geometry": {"coordinates":[12.1006860733,49.3118133545],"type":"Point"}
}