{
  "type": "Feature",
  "properties": {
    "iso:country":"DE",
    "sg:address":"Hausbergweg 2",
    "sg:city":"Breidenbach",
    "sg:phone":"+49 6465",
    "sg:postcode":"35236",
    "sg:province":"Hessen",
    "wof:name":"Consult Team Ges. F. Unternehmens- U. Immobilienvermittlung",
    "wof:placetype":"venue"
},
  "geometry": {"coordinates":[8.4559412003,50.8873748779],"type":"Point"}
}