{
  "type": "Feature",
  "properties": {
    "iso:country":"DE",
    "sg:address":"Heckinghauser Str. 176",
    "sg:city":"Wuppertal",
    "sg:phone":"+49 202/625010",
    "sg:postcode":"42289",
    "sg:province":"Nordrhein-Westfalen",
    "wof:name":"Liebig-apotheke",
    "wof:placetype":"venue"
},
  "geometry": {"coordinates":[7.222597,51.270954],"type":"Point"}
}