{
  "type": "Feature",
  "properties": {
    "iso:country":"DE",
    "sg:address":"K\u00fcferstr.",
    "sg:city":"D\u00fcren-Hoven",
    "sg:phone":"+49 2421/85238",
    "sg:postcode":"52353",
    "sg:province":"Nordrhein-Westfalen",
    "wof:name":"Teich & Koi",
    "wof:placetype":"venue"
},
  "geometry": {"coordinates":[6.4377450943,50.8314743042],"type":"Point"}
}