{
  "type": "Feature",
  "properties": {
    "iso:country":"DE",
    "sg:address":"Dragonerweg 24",
    "sg:city":"Mannheim",
    "sg:phone":"+49 621/400090",
    "sg:postcode":"68163",
    "sg:province":"Baden-W\u00fcrttemberg",
    "wof:name":"L. Kahl",
    "wof:placetype":"venue"
},
  "geometry": {"coordinates":[8.5041694641,49.4675483704],"type":"Point"}
}