{
  "type": "Feature",
  "properties": {
    "iso:country":"DE",
    "sg:address":"Bruchweg 66a",
    "sg:city":"H\u00fcnxe",
    "sg:phone":"+49 2064/37010",
    "sg:postcode":"46569",
    "sg:province":"Nordrhein-Westfalen",
    "wof:name":"M. Walgenbach",
    "wof:placetype":"venue"
},
  "geometry": {"coordinates":[6.7196059227,51.6145706177],"type":"Point"}
}