{
  "type": "Feature",
  "properties": {
    "iso:country":"DE",
    "sg:address":"Hauptstr. 2a",
    "sg:city":"Hochdorf-Assenheim",
    "sg:phone":"+49 6231/7172",
    "sg:postcode":"67126",
    "sg:province":"Rheinland-Pfalz",
    "wof:name":"Esso Station",
    "wof:placetype":"venue"
},
  "geometry": {"coordinates":[8.2806949615,49.4185752869],"type":"Point"}
}