{
  "type": "Feature",
  "properties": {
    "iso:country":"DE",
    "sg:address":"Z\u00f6rbiger Str. 44",
    "sg:city":"Bitterfeld",
    "sg:phone":"+49 3493/21526",
    "sg:postcode":"06749",
    "sg:province":"Sachsen-Anhalt",
    "wof:name":"Gertec Gmbh",
    "wof:placetype":"venue"
},
  "geometry": {"coordinates":[12.2994041443,51.6242370605],"type":"Point"}
}