{
  "type": "Feature",
  "properties": {
    "iso:country":"DE",
    "sg:address":"Liskircherstr. 23",
    "sg:city":"Regensburg",
    "sg:phone":"+49 941/55089",
    "sg:postcode":"93049",
    "sg:province":"Bayern",
    "wof:name":"Gerhard Felhofer Und Franz Wittman",
    "wof:placetype":"venue"
},
  "geometry": {"coordinates":[12.0786981583,49.0148658752],"type":"Point"}
}