{
  "type": "Feature",
  "properties": {
    "iso:country":"DE",
    "sg:address":"Bismarckstr. 4-8",
    "sg:city":"B\u00fcsum",
    "sg:postcode":"25761",
    "sg:province":"Schleswig-Holstein",
    "wof:name":"Gem\u00e4lde Albrecht",
    "wof:placetype":"venue"
},
  "geometry": {"coordinates":[8.8652582169,54.1329307556],"type":"Point"}
}