{
  "type": "Feature",
  "properties": {
    "iso:country":"DE",
    "sg:address":"Amselweg 10",
    "sg:city":"Rosche",
    "sg:phone":"+49 5803/1299",
    "sg:postcode":"29571",
    "sg:province":"Niedersachsen",
    "wof:name":"Cordt-g\u00fcnther Schulz",
    "wof:placetype":"venue"
},
  "geometry": {"coordinates":[10.745192,52.987415],"type":"Point"}
}