{
  "type": "Feature",
  "properties": {
    "iso:country":"DE",
    "sg:address":"Hansaring 89",
    "sg:city":"K\u00f6ln",
    "sg:phone":"+49 221/136589",
    "sg:postcode":"50670",
    "sg:province":"Nordrhein-Westfalen",
    "wof:name":"H. Gregor",
    "wof:placetype":"venue"
},
  "geometry": {"coordinates":[6.950239,50.948536],"type":"Point"}
}