{
  "type": "Feature",
  "properties": {
    "iso:country":"DE",
    "sg:address":"Niederheide 5",
    "sg:city":"Neuenrade",
    "sg:phone":"+49 2392/61487",
    "sg:postcode":"58809",
    "sg:province":"Nordrhein-Westfalen",
    "wof:name":"Stadtb\u00fccherei",
    "wof:placetype":"venue"
},
  "geometry": {"coordinates":[7.788635,51.28249],"type":"Point"}
}