{
  "type": "Feature",
  "properties": {
    "iso:country":"DE",
    "sg:address":"Johann-Gottfried-Herder-Str.59",
    "sg:city":"Werne",
    "sg:phone":"+49 2389/537633",
    "sg:postcode":"59368",
    "sg:province":"Nordrhein-Westfalen",
    "wof:name":"S. Winter",
    "wof:placetype":"venue"
},
  "geometry": {"coordinates":[7.6155548096,51.6728477478],"type":"Point"}
}