{
  "type": "Feature",
  "properties": {
    "iso:country":"DE",
    "sg:address":"Retzerheide 5",
    "sg:city":"Bad Salzuflen",
    "sg:phone":"+49 5222/282269",
    "sg:postcode":"32108",
    "sg:province":"Nordrhein-Westfalen",
    "wof:name":"Helmut Schlo\u00dfhahn",
    "wof:placetype":"venue"
},
  "geometry": {"coordinates":[8.8050870895,52.0534324646],"type":"Point"}
}