{
  "type": "Feature",
  "properties": {
    "iso:country":"DE",
    "sg:address":"Hauptstr. 171-173",
    "sg:city":"Frechen",
    "sg:phone":"+49 2234/53867",
    "sg:postcode":"50226",
    "sg:province":"Nordrhein-Westfalen",
    "wof:name":"H. W. Elektroinstallation Gmbh",
    "wof:placetype":"venue"
},
  "geometry": {"coordinates":[6.803634,50.90926],"type":"Point"}
}