{
  "type": "Feature",
  "properties": {
    "iso:country":"DE",
    "sg:address":"Goethestr. 7",
    "sg:city":"Wei\u00dfensee",
    "sg:phone":"+49 36374/20265",
    "sg:postcode":"99631",
    "sg:province":"Th\u00fcringen",
    "wof:name":"Gerhard Debernitz Rolladenbau",
    "wof:placetype":"venue"
},
  "geometry": {"coordinates":[11.070769,51.197681],"type":"Point"}
}