{
  "type": "Feature",
  "properties": {
    "iso:country":"DE",
    "sg:address":"Ortsstr. 59",
    "sg:city":"Langenorla",
    "sg:phone":"+49 3647/412661",
    "sg:postcode":"07381",
    "sg:province":"Th\u00fcringen",
    "wof:name":"Hartwig Wuckelt",
    "wof:placetype":"venue"
},
  "geometry": {"coordinates":[11.575897,50.74147],"type":"Point"}
}