{
  "type": "Feature",
  "properties": {
    "iso:country":"DE",
    "sg:address":"Gr\u00fcntenseestr. 26",
    "sg:city":"Oy-Mittelberg",
    "sg:phone":"+49 8361/3330",
    "sg:postcode":"87466",
    "sg:province":"Bayern",
    "wof:name":"Titze Verlags Gmbh",
    "wof:placetype":"venue"
},
  "geometry": {"coordinates":[10.4613628387,47.6276855469],"type":"Point"}
}