{
  "type": "Feature",
  "properties": {
    "iso:country":"DE",
    "sg:address":"Kestenbergerweg 28",
    "sg:city":"Schifferstadt",
    "sg:postcode":"67105",
    "sg:province":"Rheinland-Pfalz",
    "wof:name":"A & B Gmbh",
    "wof:placetype":"venue"
},
  "geometry": {"coordinates":[8.368008,49.379295],"type":"Point"}
}