{
  "type": "Feature",
  "properties": {
    "iso:country":"DE",
    "sg:address":"Weisensteinstr. 10",
    "sg:city":"Alzenau",
    "sg:phone":"+49 6023/4883",
    "sg:postcode":"63755",
    "sg:province":"Bayern",
    "wof:name":"Deissler Gmbh",
    "wof:placetype":"venue"
},
  "geometry": {"coordinates":[9.0721988678,50.0707817078],"type":"Point"}
}