{
  "type": "Feature",
  "properties": {
    "iso:country":"DE",
    "sg:address":"Otto-Baer-Str. 6",
    "sg:city":"Magdeburg",
    "sg:postcode":"39118",
    "sg:province":"Sachsen-Anhalt",
    "wof:name":"Lady Cathrin Gmbh",
    "wof:placetype":"venue"
},
  "geometry": {"coordinates":[11.614313,52.089832],"type":"Point"}
}