{
  "type": "Feature",
  "properties": {
    "iso:country":"DE",
    "sg:address":"Mundschenkstr 5",
    "sg:city":"Kropst\u00e4dt",
    "sg:phone":"+49 34920/7010",
    "sg:postcode":"06895",
    "sg:province":"Sachsen-Anhalt",
    "wof:name":"Mundschenk Druck + Medien",
    "wof:placetype":"venue"
},
  "geometry": {"coordinates":[12.74522,51.957752],"type":"Point"}
}