{
  "type": "Feature",
  "properties": {
    "iso:country":"DE",
    "sg:address":"Jungbluthgasse 22",
    "sg:city":"K\u00f6ln",
    "sg:phone":"+49 221/484378",
    "sg:postcode":"50858",
    "sg:province":"Nordrhein-Westfalen",
    "wof:name":"Eu-trade Konsumg\u00fcter Grosshandels-gmbh",
    "wof:placetype":"venue"
},
  "geometry": {"coordinates":[6.8516769409,50.9311141968],"type":"Point"}
}