{
  "type": "Feature",
  "properties": {
    "iso:country":"DE",
    "sg:address":"S\u00e4gewerk",
    "sg:city":"Erbach",
    "sg:phone":"+49 6062/3114",
    "sg:postcode":"64711",
    "sg:province":"Hessen",
    "wof:name":"S\u00e4gewerk Seibert S\u00f6hne Gmbh",
    "wof:placetype":"venue"
},
  "geometry": {"coordinates":[8.9939556122,49.6222038269],"type":"Point"}
}