{
  "type": "Feature",
  "properties": {
    "iso:country":"DE",
    "sg:address":"Hinterberg 33",
    "sg:city":"Friesoythe",
    "sg:phone":"+49 4493/92150",
    "sg:postcode":"26169",
    "sg:province":"Niedersachsen",
    "wof:name":"R. Werner Viehhandel",
    "wof:placetype":"venue"
},
  "geometry": {"coordinates":[7.771731,52.978867],"type":"Point"}
}