{
  "type": "Feature",
  "properties": {
    "iso:country":"DE",
    "sg:address":"K\u00f6lner Str. 71",
    "sg:city":"M\u00fclheim",
    "sg:phone":"+49 208/485242",
    "sg:postcode":"45481",
    "sg:province":"Nordrhein-Westfalen",
    "wof:name":"Ganser Gmbh",
    "wof:placetype":"venue"
},
  "geometry": {"coordinates":[6.8755898476,51.3979225159],"type":"Point"}
}