{
  "type": "Feature",
  "properties": {
    "iso:country":"DE",
    "sg:address":"Alt Zeilsheim 25",
    "sg:city":"Frankfurt",
    "sg:postcode":"65931",
    "sg:province":"Hessen",
    "wof:name":"Selig & Kleinsorge Schreinerei Gmbh",
    "wof:placetype":"venue"
},
  "geometry": {"coordinates":[8.49212,50.095245],"type":"Point"}
}