{
  "type": "Feature",
  "properties": {
    "iso:country":"DE",
    "sg:address":"In der Vogelstang 1",
    "sg:city":"Heidelberg",
    "sg:phone":"+49 6221/22886",
    "sg:postcode":"69115",
    "sg:province":"Baden-W\u00fcrttemberg",
    "wof:name":"A. Knopf Immobilienmakler",
    "wof:placetype":"venue"
},
  "geometry": {"coordinates":[8.6829614639,49.3965911865],"type":"Point"}
}