{
  "type": "Feature",
  "properties": {
    "iso:country":"DE",
    "sg:address":"Max-Schmidt-Str. 3",
    "sg:city":"Finsterwalde",
    "sg:phone":"+49 3531/8884",
    "sg:postcode":"03238",
    "sg:province":"Brandenburg",
    "wof:name":"Dietmar Passolt",
    "wof:placetype":"venue"
},
  "geometry": {"coordinates":[13.7070579529,51.6330833435],"type":"Point"}
}