{
  "type": "Feature",
  "properties": {
    "iso:country":"DE",
    "sg:address":"Hagener Str. 22",
    "sg:city":"Hagen",
    "sg:phone":"+49 2331/631348",
    "sg:postcode":"58099",
    "sg:province":"Nordrhein-Westfalen",
    "wof:name":"Ms Brillenstudio Gmbh",
    "wof:placetype":"venue"
},
  "geometry": {"coordinates":[7.471613884,51.3939628601],"type":"Point"}
}