{
  "type": "Feature",
  "properties": {
    "iso:country":"DE",
    "sg:address":"Dorfstr. 128",
    "sg:city":"Klein Nordende",
    "sg:phone":"+49 4121/94967",
    "sg:postcode":"25336",
    "sg:province":"Schleswig-Holstein",
    "wof:name":"Wolfgang Sibbert",
    "wof:placetype":"venue"
},
  "geometry": {"coordinates":[9.6606025696,53.7213478088],"type":"Point"}
}