{
  "type": "Feature",
  "properties": {
    "iso:country":"DE",
    "sg:address":"Ludwig-H\u00fcttner-Str. 21",
    "sg:city":"Waldershof",
    "sg:postcode":"95679",
    "sg:province":"Bayern",
    "wof:name":"C & C-gro\u00dfmarkt",
    "wof:placetype":"venue"
},
  "geometry": {"coordinates":[12.07289505,49.98462677],"type":"Point"}
}