{
  "type": "Feature",
  "properties": {
    "iso:country":"DE",
    "sg:address":"Gro\u00dfgr\u00fcndlacher Hauptstr. 9",
    "sg:city":"N\u00fcrnberg",
    "sg:phone":"+49 911/301559",
    "sg:postcode":"90427",
    "sg:province":"Bayern",
    "wof:name":"H. B\u00f6hm",
    "wof:placetype":"venue"
},
  "geometry": {"coordinates":[11.0106840134,49.5272865295],"type":"Point"}
}