{
  "type": "Feature",
  "properties": {
    "iso:country":"DE",
    "sg:address":"Greifswalder Str. 9",
    "sg:city":"Paderborn",
    "sg:phone":"+49 5251/34014",
    "sg:postcode":"33106",
    "sg:province":"Nordrhein-Westfalen",
    "wof:name":"Werner Immig",
    "wof:placetype":"venue"
},
  "geometry": {"coordinates":[8.7263412476,51.7005004883],"type":"Point"}
}