{
  "type": "Feature",
  "properties": {
    "iso:country":"DE",
    "sg:address":"L\u00f6hrbacher Str. 8",
    "sg:city":"Abtsteinach",
    "sg:phone":"+49 6207/3031",
    "sg:postcode":"69518",
    "sg:province":"Hessen",
    "wof:name":"Ernst Hintenlang",
    "wof:placetype":"venue"
},
  "geometry": {"coordinates":[8.7848386765,49.5439186096],"type":"Point"}
}