{
  "type": "Feature",
  "properties": {
    "iso:country":"DE",
    "sg:address":"Ob dem Kusterdinger Weg 2",
    "sg:city":"T\u00fcbingen",
    "sg:phone":"+49 7071/93790",
    "sg:postcode":"72074",
    "sg:province":"Baden-W\u00fcrttemberg",
    "wof:name":"Bub Beton- Und Bau Gmbh & Co. Kg",
    "wof:placetype":"venue"
},
  "geometry": {"coordinates":[9.090234,48.521267],"type":"Point"}
}