{
  "type": "Feature",
  "properties": {
    "iso:country":"DE",
    "sg:address":"Treppenstr. 17",
    "sg:city":"Wuppertal",
    "sg:phone":"+49 202/3099674",
    "sg:postcode":"42115",
    "sg:province":"Nordrhein-Westfalen",
    "wof:name":"Wilhelm Innonovative Medien Gmbh",
    "wof:placetype":"venue"
},
  "geometry": {"coordinates":[7.127978,51.252052],"type":"Point"}
}