{
  "type": "Feature",
  "properties": {
    "iso:country":"DE",
    "sg:address":"Ahornweg 7",
    "sg:city":"Prieros",
    "sg:phone":"+49 33768/50743",
    "sg:postcode":"15752",
    "wof:name":"O. Trommler",
    "wof:placetype":"venue"
},
  "geometry": {"coordinates":[13.772299,52.224812],"type":"Point"}
}