{
  "type": "Feature",
  "properties": {
    "iso:country":"DE",
    "sg:address":"Von-Galen-Str. 2",
    "sg:city":"Heek",
    "sg:phone":"+49 2568/96067",
    "sg:postcode":"48619",
    "sg:province":"Nordrhein-Westfalen",
    "wof:name":"Tischlerei Gellenbeck",
    "wof:placetype":"venue"
},
  "geometry": {"coordinates":[7.1076440811,52.1187400818],"type":"Point"}
}