{
  "type": "Feature",
  "properties": {
    "iso:country":"DE",
    "sg:address":"Heubnerstr. 8",
    "sg:city":"Lutherstadt Wittenberg",
    "sg:phone":"+49 3491/414915",
    "sg:postcode":"06886",
    "sg:province":"Sachsen-Anhalt",
    "wof:name":"Lehmann & Leeseringen Gbr",
    "wof:placetype":"venue"
},
  "geometry": {"coordinates":[12.652472,51.869141],"type":"Point"}
}