{
  "type": "Feature",
  "properties": {
    "iso:country":"DE",
    "sg:address":"Ruhesteinstr. 349",
    "sg:city":"Baiersbronn",
    "sg:phone":"+49 4974/4284010",
    "sg:postcode":"72270",
    "sg:province":"Baden-W\u00fcrttemberg",
    "wof:name":"Morlock Pr\u00c4zisionstechnik E.k.",
    "wof:placetype":"venue"
},
  "geometry": {"coordinates":[8.314205,48.523769],"type":"Point"}
}