{
  "type": "Feature",
  "properties": {
    "iso:country":"DE",
    "sg:address":"72250",
    "sg:city":"Freudenstadt-Wittlensweiler",
    "sg:postcode":"72250",
    "sg:province":"Baden-W\u00fcrttemberg",
    "wof:name":"Raiffeisenbank Wittlensweiler Eg",
    "wof:placetype":"venue"
},
  "geometry": {"coordinates":[8.4504,48.471561],"type":"Point"}
}