{
  "type": "Feature",
  "properties": {
    "iso:country":"DE",
    "sg:address":"M\u00fchlenbachstr. 21",
    "sg:city":"Neuss",
    "sg:phone":"+49 2131/541371",
    "sg:postcode":"41462",
    "sg:province":"Nordrhein-Westfalen",
    "wof:name":"Bernhard Tihen",
    "wof:placetype":"venue"
},
  "geometry": {"coordinates":[6.659679,51.226006],"type":"Point"}
}