{
  "type": "Feature",
  "properties": {
    "iso:country":"DE",
    "sg:address":"Schmiedekoppelweg 11",
    "sg:city":"Handorf",
    "sg:phone":"+49 4133/6008",
    "sg:postcode":"21447",
    "sg:province":"Niedersachsen",
    "wof:name":"Erst-strahlpumpentechnik Egon R\u00f6sner",
    "wof:placetype":"venue"
},
  "geometry": {"coordinates":[10.3489217758,53.3441085815],"type":"Point"}
}