{
  "type": "Feature",
  "properties": {
    "iso:country":"DE",
    "sg:address":"Schleif 11",
    "sg:city":"Achern",
    "sg:phone":"+49 7841",
    "sg:postcode":"77855",
    "sg:province":"Baden-W\u00fcrttemberg",
    "wof:name":"Joco W\u00e4rme In Form",
    "wof:placetype":"venue"
},
  "geometry": {"coordinates":[8.0686445236,48.6384925842],"type":"Point"}
}