{
  "type": "Feature",
  "properties": {
    "iso:country":"DE",
    "sg:address":"Hopstener Str. 67",
    "sg:city":"H\u00f6rstel",
    "sg:phone":"+49 5978/770",
    "sg:postcode":"48477",
    "sg:province":"Nordrhein-Westfalen",
    "wof:name":"Helmut Kocks",
    "wof:placetype":"venue"
},
  "geometry": {"coordinates":[7.517732,52.346199],"type":"Point"}
}