{
  "type": "Feature",
  "properties": {
    "iso:country":"DE",
    "sg:address":"Friedrich-List-Str. 8",
    "sg:city":"Ki\u00dflegg",
    "sg:phone":"+49 7563/632",
    "sg:postcode":"88353",
    "sg:province":"Baden-W\u00fcrttemberg",
    "wof:name":"Endress Forst- Und Garten- Technik Vertriebs-gmbh",
    "wof:placetype":"venue"
},
  "geometry": {"coordinates":[9.891568,47.769718],"type":"Point"}
}