{
  "type": "Feature",
  "properties": {
    "iso:country":"DE",
    "sg:address":"Fuldaer Str. 28",
    "sg:city":"Dipperz",
    "sg:phone":"+49 6657/8084",
    "sg:postcode":"36160",
    "sg:province":"Hessen",
    "wof:name":"Restaurant Am Dorfbrunnen",
    "wof:placetype":"venue"
},
  "geometry": {"coordinates":[9.7961502075,50.5427398682],"type":"Point"}
}