{
  "type": "Feature",
  "properties": {
    "iso:country":"DE",
    "sg:city":"Immenreuth",
    "sg:phone":"+49 9642/7749",
    "sg:postcode":"95505",
    "sg:province":"Bayern",
    "wof:name":"Sparkasse Kemnath",
    "wof:placetype":"venue"
},
  "geometry": {"coordinates":[11.865163,49.90694],"type":"Point"}
}