{
  "type": "Feature",
  "properties": {
    "iso:country":"DE",
    "sg:address":"Marktplatz 4",
    "sg:city":"Langenhagen",
    "sg:postcode":"30853",
    "sg:province":"Niedersachsen",
    "wof:name":"Ahner & Odlozinski Beteiligungs- Gmbh",
    "wof:placetype":"venue"
},
  "geometry": {"coordinates":[9.740593,52.439255],"type":"Point"}
}