{
  "type": "Feature",
  "properties": {
    "iso:country":"DE",
    "sg:address":"Maximilianstr. 5",
    "sg:city":"Aschaffenburg",
    "sg:phone":"+49 6021/299790",
    "sg:postcode":"63739",
    "sg:province":"Bayern",
    "wof:name":"Imhof Historische Uniformen Manufaktur Gmbh",
    "wof:placetype":"venue"
},
  "geometry": {"coordinates":[9.138941,49.979626],"type":"Point"}
}