{
  "type": "Feature",
  "properties": {
    "iso:country":"DE",
    "sg:address":"S\u00fcdstr. 43",
    "sg:city":"Gotha",
    "sg:phone":"+49 3621/741068",
    "sg:postcode":"99867",
    "sg:province":"Th\u00fcringen",
    "wof:name":"Heinrich Luck",
    "wof:placetype":"venue"
},
  "geometry": {"coordinates":[10.7048072815,50.9362411499],"type":"Point"}
}