{
  "type": "Feature",
  "properties": {
    "iso:country":"DE",
    "sg:address":"Ziolkowskistr. 10",
    "sg:city":"Rostock",
    "sg:phone":"+49 381/448560",
    "sg:postcode":"18059",
    "sg:province":"Mecklenburg-Vorpommern",
    "wof:name":"Lvm",
    "wof:placetype":"venue"
},
  "geometry": {"coordinates":[12.1298313141,54.0362319946],"type":"Point"}
}