{
  "type": "Feature",
  "properties": {
    "iso:country":"DE",
    "sg:address":"Hauptstr. 15",
    "sg:city":"Nittenau",
    "sg:phone":"+49 9436/8206",
    "sg:postcode":"93149",
    "sg:province":"Bayern",
    "wof:name":"Wilhelm Loritz Ohg",
    "wof:placetype":"venue"
},
  "geometry": {"coordinates":[12.2716970444,49.1972732544],"type":"Point"}
}