{
  "type": "Feature",
  "properties": {
    "iso:country":"DE",
    "sg:address":"Am B\u00fcrgerberg 28",
    "sg:city":"Hennef",
    "sg:phone":"+49 2242/83727",
    "sg:postcode":"53773",
    "sg:province":"Nordrhein-Westfalen",
    "wof:name":"Dr. Hans-p. Kohlhaas Architekt",
    "wof:placetype":"venue"
},
  "geometry": {"coordinates":[7.302401,50.761566],"type":"Point"}
}