{
  "type": "Feature",
  "properties": {
    "iso:country":"DE",
    "sg:address":"Birkbuschstr. 87",
    "sg:city":"Berlin",
    "sg:phone":"+49 30/7919477",
    "sg:postcode":"12167",
    "sg:province":"Berlin",
    "wof:name":"Birkbusch-apotheke Christa Owoo E. Kfr.",
    "wof:placetype":"venue"
},
  "geometry": {"coordinates":[13.322696,52.45052],"type":"Point"}
}