{
  "type": "Feature",
  "properties": {
    "iso:country":"DE",
    "sg:address":"Industriepark 4 B",
    "sg:city":"Ganderkesee",
    "sg:phone":"+49 4222/9230",
    "sg:postcode":"27777",
    "sg:province":"Niedersachsen",
    "wof:name":"Teleworkingcenter",
    "wof:placetype":"venue"
},
  "geometry": {"coordinates":[8.5316648483,53.0285224915],"type":"Point"}
}