{
  "type": "Feature",
  "properties": {
    "iso:country":"DE",
    "sg:address":"Gutsblick 7",
    "sg:city":"Hennef",
    "sg:postcode":"53773",
    "sg:province":"Nordrhein-Westfalen",
    "wof:name":"Hut Und Mode Fuchs Gmbh",
    "wof:placetype":"venue"
},
  "geometry": {"coordinates":[7.2846450806,50.7737846375],"type":"Point"}
}