{
  "type": "Feature",
  "properties": {
    "iso:country":"DE",
    "sg:address":"Heinrich-Heine-Str 80",
    "sg:city":"Wei\u00dfwasser",
    "sg:phone":"+49 3576/28220",
    "sg:postcode":"02943",
    "sg:province":"Sachsen",
    "wof:name":"Olaf Fleisch- Und Wurstspezialit\u00e4ten Gmbh",
    "wof:placetype":"venue"
},
  "geometry": {"coordinates":[14.6567649841,51.4916687012],"type":"Point"}
}