{
  "type": "Feature",
  "properties": {
    "iso:country":"DE",
    "sg:address":"M\u00fchlenstr. 7",
    "sg:city":"L\u00fcnne",
    "sg:phone":"+49 5906/620",
    "sg:postcode":"48480",
    "sg:province":"Niedersachsen",
    "wof:name":"Tischlerei Dresselhaus Gmbh",
    "wof:placetype":"venue"
},
  "geometry": {"coordinates":[7.425454,52.434612],"type":"Point"}
}