{
  "type": "Feature",
  "properties": {
    "iso:country":"DE",
    "sg:address":"Kolpingstr. 24",
    "sg:city":"Pfronten",
    "sg:phone":"+49 8363/927610",
    "sg:postcode":"87459",
    "sg:province":"Bayern",
    "wof:name":"Mfs Dieter Hosmann E. K.",
    "wof:placetype":"venue"
},
  "geometry": {"coordinates":[10.561132431,47.6057128906],"type":"Point"}
}