{
  "type": "Feature",
  "properties": {
    "iso:country":"DE",
    "sg:address":"\u00d6sterholzstr 6b",
    "sg:city":"Nohra",
    "sg:phone":"+49 3643/825806",
    "sg:postcode":"99428",
    "sg:province":"Th\u00fcringen",
    "wof:name":"Tona",
    "wof:placetype":"venue"
},
  "geometry": {"coordinates":[11.256653,50.957748],"type":"Point"}
}