{
  "type": "Feature",
  "properties": {
    "iso:country":"DE",
    "sg:address":"Karwendelstr. 40",
    "sg:city":"Eichenau",
    "sg:phone":"+49 8141/818674",
    "sg:postcode":"82223",
    "sg:province":"Bayern",
    "wof:name":"Bruno B\u00fcrgerle Ingenieur",
    "wof:placetype":"venue"
},
  "geometry": {"coordinates":[11.321628,48.164089],"type":"Point"}
}