{
  "type": "Feature",
  "properties": {
    "iso:country":"DE",
    "sg:address":"Warrington-Platz 25",
    "sg:city":"Hilden",
    "sg:phone":"+49 2103/241212",
    "sg:postcode":"40721",
    "sg:province":"Nordrhein-Westfalen",
    "wof:name":"Dr. Med. K. Niknafs",
    "wof:placetype":"venue"
},
  "geometry": {"coordinates":[6.9348602295,51.1676902771],"type":"Point"}
}