{
  "type": "Feature",
  "properties": {
    "iso:country":"DE",
    "sg:address":"Steinweg 5",
    "sg:city":"Rotenburg",
    "sg:phone":"+49 6623/2283",
    "sg:postcode":"36199",
    "sg:province":"Hessen",
    "wof:name":"Lingenberg",
    "wof:placetype":"venue"
},
  "geometry": {"coordinates":[9.729124,50.997074],"type":"Point"}
}