{
  "type": "Feature",
  "properties": {
    "iso:country":"DE",
    "sg:address":"Wahlengasse 19",
    "sg:city":"Erftstadt",
    "sg:phone":"+49 2235/5146",
    "sg:postcode":"50374",
    "sg:province":"Nordrhein-Westfalen",
    "wof:name":"Josef Krudewig",
    "wof:placetype":"venue"
},
  "geometry": {"coordinates":[6.765531,50.799942],"type":"Point"}
}