{
  "type": "Feature",
  "properties": {
    "iso:country":"DE",
    "sg:address":"Roonstr. 17 - 19",
    "sg:city":"Solingen",
    "sg:phone":"+49 212/330983",
    "sg:postcode":"42699",
    "sg:province":"Nordrhein-Westfalen",
    "wof:name":"Skalpelle",
    "wof:placetype":"venue"
},
  "geometry": {"coordinates":[7.025943,51.16766],"type":"Point"}
}