{
  "type": "Feature",
  "properties": {
    "iso:country":"DE",
    "sg:address":"Hinterbacher Str. 12",
    "sg:city":"Rothenberg",
    "sg:phone":"+49 6068/2338",
    "sg:postcode":"64757",
    "sg:province":"Hessen",
    "wof:name":"Rolf Helm",
    "wof:placetype":"venue"
},
  "geometry": {"coordinates":[8.912119,49.536034],"type":"Point"}
}