{
  "type": "Feature",
  "properties": {
    "iso:country":"DE",
    "sg:address":"Langelohstr. 116e",
    "sg:city":"Hamburg",
    "sg:phone":"+49 40/80020525",
    "sg:postcode":"22609",
    "sg:province":"Hamburg",
    "wof:name":"Axel Steffen Rechtsanwalt",
    "wof:placetype":"venue"
},
  "geometry": {"coordinates":[9.8466072083,53.5700073242],"type":"Point"}
}