{
  "type": "Feature",
  "properties": {
    "iso:country":"DE",
    "sg:address":"Palmenweg 4",
    "sg:city":"Fritzlar",
    "sg:phone":"+49 5622/3175",
    "sg:postcode":"34560",
    "sg:province":"Hessen",
    "wof:name":"Adolf Gertenbach",
    "wof:placetype":"venue"
},
  "geometry": {"coordinates":[9.315074,51.129841],"type":"Point"}
}