{
  "type": "Feature",
  "properties": {
    "iso:country":"DE",
    "sg:address":"St.-Veit-Str. 1",
    "sg:city":"Kupferberg",
    "sg:phone":"+49 9227",
    "sg:postcode":"95362",
    "sg:province":"Bayern",
    "wof:name":"Kfz-center Huber",
    "wof:placetype":"venue"
},
  "geometry": {"coordinates":[11.5823402405,50.1390037537],"type":"Point"}
}