{
  "type": "Feature",
  "properties": {
    "iso:country":"DE",
    "sg:address":"Edisonstr. 83",
    "sg:city":"N\u00fcrnberg",
    "sg:phone":"+49 911/615561",
    "sg:postcode":"90431",
    "sg:province":"Bayern",
    "wof:name":"Weiss Trennw\u00e4nde Gmbh",
    "wof:placetype":"venue"
},
  "geometry": {"coordinates":[11.023551,49.433334],"type":"Point"}
}