{
  "type": "Feature",
  "properties": {
    "iso:country":"DE",
    "sg:address":"Manhagener Allee 76",
    "sg:city":"Ahrensburg",
    "sg:phone":"+49 4102/51171",
    "sg:postcode":"22926",
    "sg:province":"Schleswig-Holstein",
    "wof:name":"Schutz Marken Dienst Gmbh",
    "wof:placetype":"venue"
},
  "geometry": {"coordinates":[10.246974,53.666153],"type":"Point"}
}