{
  "type": "Feature",
  "properties": {
    "iso:country":"DE",
    "sg:address":"Oberperlm\u00fchle",
    "sg:city":"Baar",
    "sg:phone":"+49 8276/226",
    "sg:postcode":"86674",
    "sg:province":"Bayern",
    "wof:name":"E. Angerer",
    "wof:placetype":"venue"
},
  "geometry": {"coordinates":[10.9781627655,48.572467804],"type":"Point"}
}