{
  "type": "Feature",
  "properties": {
    "iso:country":"DE",
    "sg:address":"Friedrichstr. 9",
    "sg:city":"Herbolzheim",
    "sg:phone":"+49 7643/5150",
    "sg:postcode":"79336",
    "sg:province":"Baden-W\u00fcrttemberg",
    "wof:name":"Herbert Lehmann",
    "wof:placetype":"venue"
},
  "geometry": {"coordinates":[7.7732949257,48.2225646973],"type":"Point"}
}