{
  "type": "Feature",
  "properties": {
    "iso:country":"DE",
    "sg:address":"Schulstr. 5",
    "sg:city":"Wanzleben",
    "sg:phone":"+49 39209/3071",
    "sg:postcode":"39164",
    "sg:province":"Sachsen-Anhalt",
    "wof:name":"Antje Puchta",
    "wof:placetype":"venue"
},
  "geometry": {"coordinates":[11.4411687851,52.0611915588],"type":"Point"}
}