{
  "type": "Feature",
  "properties": {
    "iso:country":"DE",
    "sg:address":"K\u00f6rnerstr. 10 a",
    "sg:city":"Hannover",
    "sg:phone":"+49 511/1613501",
    "sg:postcode":"30159",
    "sg:province":"Niedersachsen",
    "wof:name":"Elis Communications Ohg",
    "wof:placetype":"venue"
},
  "geometry": {"coordinates":[9.7248497009,52.379737854],"type":"Point"}
}