{
  "type": "Feature",
  "properties": {
    "iso:country":"DE",
    "sg:address":"Am Holze 2",
    "sg:city":"Springe",
    "sg:phone":"+49 5044/985273",
    "sg:postcode":"31832",
    "sg:province":"Niedersachsen",
    "wof:name":"Final Fantasy Index",
    "wof:placetype":"venue"
},
  "geometry": {"coordinates":[9.656059,52.203468],"type":"Point"}
}