{
  "type": "Feature",
  "properties": {
    "iso:country":"DE",
    "sg:address":"Moormerlandstr. 45",
    "sg:city":"Moormerland",
    "sg:phone":"+49 4954/5143",
    "sg:postcode":"26802",
    "sg:province":"Niedersachsen",
    "wof:name":"Heinrich Voss",
    "wof:placetype":"venue"
},
  "geometry": {"coordinates":[7.482699,53.284912],"type":"Point"}
}