{
  "type": "Feature",
  "properties": {
    "iso:country":"DE",
    "sg:address":"Etzwiesenstr. 13",
    "sg:city":"M\u00fcnchen",
    "sg:phone":"+49 89/423454",
    "sg:postcode":"81735",
    "sg:province":"Bayern",
    "wof:name":"American Dental Supplies Gmbh",
    "wof:placetype":"venue"
},
  "geometry": {"coordinates":[11.658365,48.109734],"type":"Point"}
}