{
  "type": "Feature",
  "properties": {
    "iso:country":"DE",
    "sg:address":"Goethestr. 1",
    "sg:city":"Heilbronn",
    "sg:phone":"+49 7131/163598",
    "sg:postcode":"74076",
    "sg:province":"Baden-W\u00fcrttemberg",
    "wof:name":"Dietmar Sauer Krankengymnast",
    "wof:placetype":"venue"
},
  "geometry": {"coordinates":[9.2314,49.140205],"type":"Point"}
}