{
  "type": "Feature",
  "properties": {
    "iso:country":"DE",
    "sg:address":"Teichstr. 77",
    "sg:city":"Gro\u00dfenbrode",
    "sg:phone":"+49 4367/600",
    "sg:postcode":"23775",
    "sg:province":"Schleswig-Holstein",
    "wof:name":"Paracelsus-apotheke",
    "wof:placetype":"venue"
},
  "geometry": {"coordinates":[11.085226,54.370094],"type":"Point"}
}