{
  "type": "Feature",
  "properties": {
    "iso:country":"DE",
    "sg:address":"L\u00e4mlinstr 40",
    "sg:city":"Heilbronn",
    "sg:phone":"+49 7131/488550",
    "sg:postcode":"74080",
    "sg:province":"Baden-W\u00fcrttemberg",
    "wof:name":"G\u00fcnther Strecker",
    "wof:placetype":"venue"
},
  "geometry": {"coordinates":[9.157832,49.141392],"type":"Point"}
}