{
  "type": "Feature",
  "properties": {
    "iso:country":"DE",
    "sg:address":"H\u00e4userweg 22",
    "sg:city":"Ubstadt-Weiher",
    "sg:phone":"+49 7251/63411",
    "sg:postcode":"76698",
    "sg:province":"Baden-W\u00fcrttemberg",
    "wof:name":"G\u00fcnther Haberland",
    "wof:placetype":"venue"
},
  "geometry": {"coordinates":[8.6263551712,49.1664810181],"type":"Point"}
}