{
  "type": "Feature",
  "properties": {
    "iso:country":"DE",
    "sg:address":"Schw\u00e4blishauser Str. 5",
    "sg:city":"Pfullendorf",
    "sg:phone":"+49 7552/1637",
    "sg:postcode":"88630",
    "sg:province":"Baden-W\u00fcrttemberg",
    "wof:name":"R. Bosch",
    "wof:placetype":"venue"
},
  "geometry": {"coordinates":[9.285193,47.961338],"type":"Point"}
}