{
  "type": "Feature",
  "properties": {
    "iso:country":"DE",
    "sg:address":"Schreinerstr. 1- 3",
    "sg:city":"Breidenbach",
    "sg:phone":"+49 6465/897",
    "sg:postcode":"35236",
    "sg:province":"Hessen",
    "wof:name":"H.thom\u00e4 & S\u00f6hne Ohg",
    "wof:placetype":"venue"
},
  "geometry": {"coordinates":[8.4471073151,50.8884353638],"type":"Point"}
}