{
  "type": "Feature",
  "properties": {
    "iso:country":"DE",
    "sg:address":"Untermh\u00e4user Str. 5",
    "sg:city":"Gera",
    "sg:phone":"+49 365/8001550",
    "sg:postcode":"07548",
    "sg:province":"Th\u00fcringen",
    "wof:name":"Cafe Am Dix-haus",
    "wof:placetype":"venue"
},
  "geometry": {"coordinates":[12.063851,50.882622],"type":"Point"}
}