{
  "type": "Feature",
  "properties": {
    "iso:country":"DE",
    "sg:address":"Kaulbachstr. 46",
    "sg:city":"M\u00fcnchen",
    "sg:phone":"+49 89/397247",
    "sg:postcode":"80539",
    "sg:province":"Bayern",
    "wof:name":"Johann H\u00f6rner B\u00e4ckerei-konditorei",
    "wof:placetype":"venue"
},
  "geometry": {"coordinates":[11.584514,48.1511],"type":"Point"}
}