{
  "type": "Feature",
  "properties": {
    "iso:country":"DE",
    "sg:address":"Waldstr. 6",
    "sg:city":"Schefflenz",
    "sg:postcode":"74850",
    "sg:province":"Baden-W\u00fcrttemberg",
    "wof:name":"Ev. Pfarramt Gem. Mittelschefflenz",
    "wof:placetype":"venue"
},
  "geometry": {"coordinates":[9.2864704132,49.3987884521],"type":"Point"}
}