{
  "type": "Feature",
  "properties": {
    "iso:country":"DE",
    "sg:address":"Bahnhoffu\u00dfweg 16",
    "sg:city":"M\u00fchldorf",
    "sg:postcode":"84453",
    "sg:province":"Bayern",
    "wof:name":"Farmer Handels Gmbh",
    "wof:placetype":"venue"
},
  "geometry": {"coordinates":[12.5218801498,48.2442207336],"type":"Point"}
}