{
  "type": "Feature",
  "properties": {
    "iso:country":"DE",
    "sg:address":"Gallbergweg 23",
    "sg:city":"Brilon",
    "sg:phone":"+49 2961/2502",
    "sg:postcode":"59929",
    "sg:province":"Nordrhein-Westfalen",
    "wof:name":"R. Sommer Gmbh",
    "wof:placetype":"venue"
},
  "geometry": {"coordinates":[8.586392,51.402164],"type":"Point"}
}