{
  "type": "Feature",
  "properties": {
    "iso:country":"DE",
    "sg:address":"Bahnhofstr. 64",
    "sg:city":"Neu-Anspach",
    "sg:phone":"+49 6081/8310",
    "sg:postcode":"61267",
    "sg:province":"Hessen",
    "wof:name":"Erika Mundorff",
    "wof:placetype":"venue"
},
  "geometry": {"coordinates":[8.5138931274,50.2948760986],"type":"Point"}
}