{
  "type": "Feature",
  "properties": {
    "iso:country":"DE",
    "sg:address":"Steinweg 17",
    "sg:city":"Trendelburg",
    "sg:phone":"+49 5675/215",
    "sg:postcode":"34388",
    "sg:province":"Hessen",
    "wof:name":"Gerhard Go\u00dfmann",
    "wof:placetype":"venue"
},
  "geometry": {"coordinates":[9.426,51.57431],"type":"Point"}
}