{
  "type": "Feature",
  "properties": {
    "iso:country":"DE",
    "sg:address":"Ostermeedlandsweg 72-74",
    "sg:city":"Leer",
    "sg:phone":"+49 491/80030",
    "sg:postcode":"26789",
    "sg:province":"Niedersachsen",
    "wof:name":"M. Neemann Ohg",
    "wof:placetype":"venue"
},
  "geometry": {"coordinates":[7.47376,53.224361],"type":"Point"}
}