{
  "type": "Feature",
  "properties": {
    "iso:country":"DE",
    "sg:address":"Avendruper Str. 37",
    "sg:city":"M\u00fcnster",
    "sg:phone":"+49 251/141200",
    "sg:postcode":"48157",
    "sg:province":"Nordrhein-Westfalen",
    "wof:name":"Hk-tex Hans Kruchen Textilien",
    "wof:placetype":"venue"
},
  "geometry": {"coordinates":[7.7019181252,51.9990882874],"type":"Point"}
}