{
  "type": "Feature",
  "properties": {
    "iso:country":"DE",
    "sg:address":"Baumschulallee 5",
    "sg:city":"Bonn",
    "sg:phone":"+49 228/631647",
    "sg:postcode":"53115",
    "sg:province":"Nordrhein-Westfalen",
    "wof:name":"Cusanuswerk E. V.",
    "wof:placetype":"venue"
},
  "geometry": {"coordinates":[7.0969848633,50.729801178],"type":"Point"}
}