{
  "type": "Feature",
  "properties": {
    "iso:country":"DE",
    "sg:address":"Stettiner Str. 31",
    "sg:city":"Hattersheim",
    "sg:postcode":"65795",
    "sg:province":"Hessen",
    "wof:name":"Hot Plan Engineering- Consulting Gmbh",
    "wof:placetype":"venue"
},
  "geometry": {"coordinates":[8.492839,50.050884],"type":"Point"}
}