{
  "type": "Feature",
  "properties": {
    "iso:country":"DE",
    "sg:address":"K\u00f6mmlitzer Str. 9",
    "sg:city":"Rackwitz",
    "sg:postcode":"04519",
    "sg:province":"Sachsen",
    "wof:name":"Tha\u00dfler Kunststofftechnik Und Design Gmbh",
    "wof:placetype":"venue"
},
  "geometry": {"coordinates":[12.368753,51.430065],"type":"Point"}
}