{
  "type": "Feature",
  "properties": {
    "iso:country":"DE",
    "sg:address":"Kapellenstr. 18",
    "sg:city":"Unterhaching",
    "sg:phone":"+49 89/6650640",
    "sg:postcode":"82008",
    "sg:province":"Bayern",
    "wof:name":"Deka Textilfarben Gmbh",
    "wof:placetype":"venue"
},
  "geometry": {"coordinates":[11.6212644577,48.0665779114],"type":"Point"}
}