{
  "type": "Feature",
  "properties": {
    "iso:country":"DE",
    "sg:address":"Am Hirtenbrunnen 1",
    "sg:city":"Zweibr\u00fccken",
    "sg:phone":"+49 6337/8232",
    "sg:postcode":"66482",
    "sg:province":"Rheinland-Pfalz",
    "wof:name":"G. Adelfang",
    "wof:placetype":"venue"
},
  "geometry": {"coordinates":[7.421235,49.276657],"type":"Point"}
}