{
  "type": "Feature",
  "properties": {
    "iso:country":"DE",
    "sg:address":"Pfeuferstr. 42",
    "sg:city":"M\u00fcnchen",
    "sg:phone":"+49 89/72579573",
    "sg:postcode":"81373",
    "sg:province":"Bayern",
    "wof:name":"Frimmer & Ferreira",
    "wof:placetype":"venue"
},
  "geometry": {"coordinates":[11.5410814285,48.1220664978],"type":"Point"}
}