{
  "type": "Feature",
  "properties": {
    "iso:country":"DE",
    "sg:address":"Scheffelstr. 46",
    "sg:city":"Zwickau",
    "sg:phone":"+49 375/474413",
    "sg:postcode":"08066",
    "sg:province":"Sachsen",
    "wof:name":"Floribunda Gmbh",
    "wof:placetype":"venue"
},
  "geometry": {"coordinates":[12.506829,50.734032],"type":"Point"}
}