{
  "type": "Feature",
  "properties": {
    "iso:country":"DE",
    "sg:address":"Europark Fichtenhain A",
    "sg:city":"Krefeld",
    "sg:phone":"+49 2151/6200",
    "sg:postcode":"47807",
    "sg:province":"Nordrhein-Westfalen",
    "wof:name":"Incas Ag",
    "wof:placetype":"venue"
},
  "geometry": {"coordinates":[6.558927,51.292603],"type":"Point"}
}