{
  "type": "Feature",
  "properties": {
    "iso:country":"DE",
    "sg:address":"S\u00fcdstr. 26",
    "sg:city":"Enger",
    "sg:phone":"+49 5224/970359",
    "sg:postcode":"32130",
    "sg:province":"Nordrhein-Westfalen",
    "wof:name":"Coragent Dg Weber Christiane Weber E. K.",
    "wof:placetype":"venue"
},
  "geometry": {"coordinates":[8.5544424057,52.1115493774],"type":"Point"}
}