{
  "type": "Feature",
  "properties": {
    "iso:country":"DE",
    "sg:address":"Nidderstr. 19",
    "sg:city":"Bad Vilbel",
    "sg:phone":"+49 6101/32655",
    "sg:postcode":"61118",
    "sg:province":"Hessen",
    "wof:name":"Osswald Umlauf",
    "wof:placetype":"venue"
},
  "geometry": {"coordinates":[8.785474,50.19368],"type":"Point"}
}