{
  "type": "Feature",
  "properties": {
    "iso:country":"DE",
    "sg:address":"W\u00f6rthstr. 29",
    "sg:city":"M\u00fcnchen",
    "sg:phone":"+49 89/4483880",
    "sg:postcode":"81667",
    "sg:province":"Bayern",
    "wof:name":"Aventin-kellerei Herbert Prikryl",
    "wof:placetype":"venue"
},
  "geometry": {"coordinates":[11.601023674,48.1304130554],"type":"Point"}
}