{
  "type": "Feature",
  "properties": {
    "iso:country":"DE",
    "sg:address":"Hermannsdorfer Str. 11",
    "sg:city":"Burladingen",
    "sg:phone":"+49 7475/371",
    "sg:postcode":"72393",
    "sg:province":"Baden-W\u00fcrttemberg",
    "wof:name":"Adler",
    "wof:placetype":"venue"
},
  "geometry": {"coordinates":[9.1163892746,48.2887077332],"type":"Point"}
}