{
  "type": "Feature",
  "properties": {
    "iso:country":"DE",
    "sg:address":"Am Willerwald",
    "sg:city":"Obersimten",
    "sg:phone":"+49 6331/45454",
    "sg:postcode":"66957",
    "sg:province":"Rheinland-Pfalz",
    "wof:name":"Sv Obersimten Fu\u00dfballverein",
    "wof:placetype":"venue"
},
  "geometry": {"coordinates":[7.5836410522,49.1628646851],"type":"Point"}
}