{
  "type": "Feature",
  "properties": {
    "iso:country":"DE",
    "sg:address":"Am Streichen 12",
    "sg:city":"Bastheim",
    "sg:phone":"+49 9774/391",
    "sg:postcode":"97654",
    "sg:province":"Bayern",
    "wof:name":"Schmitt Schl\u00fcsselfertiges Bauen Mbh",
    "wof:placetype":"venue"
},
  "geometry": {"coordinates":[10.184111,50.426956],"type":"Point"}
}