{
  "type": "Feature",
  "properties": {
    "iso:country":"DE",
    "sg:address":"Z\u00fcrnweg 28",
    "sg:city":"Seevetal",
    "sg:postcode":"21217",
    "sg:province":"Niedersachsen",
    "wof:name":"Ems-gleisbau-betriebs Gmbh",
    "wof:placetype":"venue"
},
  "geometry": {"coordinates":[10.0385112762,53.4204216003],"type":"Point"}
}