{
  "type": "Feature",
  "properties": {
    "iso:country":"DE",
    "sg:address":"August-Bebel-Allee 33",
    "sg:city":"Eichwalde",
    "sg:phone":"+49 30/6756437",
    "sg:postcode":"15732",
    "sg:province":"Brandenburg",
    "wof:name":"Zimmerei Gebr. Sperling Gmbh",
    "wof:placetype":"venue"
},
  "geometry": {"coordinates":[13.618688,52.366413],"type":"Point"}
}