{
  "type": "Feature",
  "properties": {
    "iso:country":"DE",
    "sg:address":"Herzogsreuter Str. 76",
    "sg:city":"Hinterschmiding",
    "sg:phone":"+49 8551/96200",
    "sg:postcode":"94146",
    "sg:province":"Bayern",
    "wof:name":"Max Fuchs",
    "wof:placetype":"venue"
},
  "geometry": {"coordinates":[13.621544838,48.8249855042],"type":"Point"}
}