{
  "type": "Feature",
  "properties": {
    "iso:country":"DE",
    "sg:address":"Hauptstr. 96",
    "sg:city":"Wiedensahl",
    "sg:postcode":"31719",
    "sg:province":"Niedersachsen",
    "wof:name":"Landwirtschaftlicher Verein Adolf Peeck",
    "wof:placetype":"venue"
},
  "geometry": {"coordinates":[9.1198701859,52.3849334717],"type":"Point"}
}