{
  "type": "Feature",
  "properties": {
    "iso:country":"DE",
    "sg:address":"Feldstr. 12",
    "sg:city":"Plei\u00dfa",
    "sg:phone":"+49 3722/93104",
    "sg:postcode":"09246",
    "wof:name":"Wolfgang Schulz",
    "wof:placetype":"venue"
},
  "geometry": {"coordinates":[12.759368,50.830166],"type":"Point"}
}