{
  "type": "Feature",
  "properties": {
    "iso:country":"DE",
    "sg:address":"Hauptstr. 11",
    "sg:city":"B\u00f6bingen",
    "sg:phone":"+49 4971/7312499",
    "sg:postcode":"73560",
    "sg:province":"Baden-W\u00fcrttemberg",
    "wof:name":"Michael Franzl",
    "wof:placetype":"venue"
},
  "geometry": {"coordinates":[9.919132,48.821293],"type":"Point"}
}