{
  "type": "Feature",
  "properties": {
    "iso:country":"DE",
    "sg:address":"Rostocker Str. 55",
    "sg:city":"D\u00fcsseldorf",
    "sg:phone":"+49 211/705701",
    "sg:postcode":"40595",
    "sg:province":"Nordrhein-Westfalen",
    "wof:name":"Heinz Niehus",
    "wof:placetype":"venue"
},
  "geometry": {"coordinates":[6.89409,51.150658],"type":"Point"}
}