{
  "type": "Feature",
  "properties": {
    "iso:country":"DE",
    "sg:address":"Gustav-Ullrich-Str. 9",
    "sg:city":"Annweiler",
    "sg:phone":"+49 6346/8922",
    "sg:postcode":"76855",
    "sg:province":"Rheinland-Pfalz",
    "wof:name":"Emil Schwarz Kohlen-handlung",
    "wof:placetype":"venue"
},
  "geometry": {"coordinates":[7.9726719856,49.2047843933],"type":"Point"}
}