{
  "type": "Feature",
  "properties": {
    "iso:country":"DE",
    "sg:address":"Hochstr. 11",
    "sg:city":"Tiefenbach",
    "sg:phone":"+49 8709/672",
    "sg:postcode":"84184",
    "sg:province":"Bayern",
    "wof:name":"Siegfried Hacker Architekt",
    "wof:placetype":"venue"
},
  "geometry": {"coordinates":[12.089374,48.487572],"type":"Point"}
}