{
  "type": "Feature",
  "properties": {
    "iso:country":"DE",
    "sg:address":"Gretenbachstr. 15",
    "sg:city":"Bad Orb",
    "sg:phone":"+49 6052/2961",
    "sg:postcode":"63619",
    "sg:province":"Hessen",
    "wof:name":"Willi Schreiber",
    "wof:placetype":"venue"
},
  "geometry": {"coordinates":[9.349025,50.226482],"type":"Point"}
}