{
  "type": "Feature",
  "properties": {
    "iso:country":"DE",
    "sg:address":"Erlenhof 1",
    "sg:city":"Trier",
    "sg:phone":"+49 651/968880",
    "sg:postcode":"54293",
    "sg:province":"Rheinland-Pfalz",
    "wof:name":"Bagrat Bautenschutz Betonsanierung Gmbh",
    "wof:placetype":"venue"
},
  "geometry": {"coordinates":[6.630953,49.785622],"type":"Point"}
}