{
  "type": "Feature",
  "properties": {
    "iso:country":"DE",
    "sg:address":"L\u00e4rchenweg 14",
    "sg:city":"Balzheim",
    "sg:phone":"+49 7347/2993",
    "sg:postcode":"88481",
    "sg:province":"Baden-W\u00fcrttemberg",
    "wof:name":"Paul Hirtling",
    "wof:placetype":"venue"
},
  "geometry": {"coordinates":[10.074539,48.177166],"type":"Point"}
}