{
  "type": "Feature",
  "properties": {
    "iso:country":"DE",
    "sg:address":"Industriestr. 7",
    "sg:city":"Biebertal",
    "sg:phone":"+49 6409/7085",
    "sg:postcode":"35444",
    "sg:province":"Hessen",
    "wof:name":"Heinrich H\u00f6rr Gmbh",
    "wof:placetype":"venue"
},
  "geometry": {"coordinates":[8.5997343063,50.6442375183],"type":"Point"}
}