{
  "type": "Feature",
  "properties": {
    "iso:country":"DE",
    "sg:address":"Richard-Wagner-Str. 25",
    "sg:city":"Essen",
    "sg:phone":"+49 201/228424",
    "sg:postcode":"45128",
    "sg:province":"Nordrhein-Westfalen",
    "wof:name":"Heiming & Thomas Ohg",
    "wof:placetype":"venue"
},
  "geometry": {"coordinates":[7.0224270821,51.4441299438],"type":"Point"}
}