{
  "type": "Feature",
  "properties": {
    "iso:country":"DE",
    "sg:address":"Pfalzdorfer Str. 12",
    "sg:city":"Goch",
    "sg:phone":"+49 2823/3020",
    "sg:postcode":"47574",
    "sg:province":"Nordrhein-Westfalen",
    "wof:name":"Pfeffer-grill",
    "wof:placetype":"venue"
},
  "geometry": {"coordinates":[6.1619319916,51.6808929443],"type":"Point"}
}