{
  "type": "Feature",
  "properties": {
    "iso:country":"DE",
    "sg:address":"Luitpoldplatz 17",
    "sg:city":"Bayreuth",
    "sg:phone":"+49 921/24290",
    "sg:postcode":"95444",
    "sg:province":"Bayern",
    "wof:name":"Christa Ernst",
    "wof:placetype":"venue"
},
  "geometry": {"coordinates":[11.5770483017,49.9467163086],"type":"Point"}
}