{
  "type": "Feature",
  "properties": {
    "iso:country":"DE",
    "sg:address":"Apfelstr. 60",
    "sg:city":"Heinsberg",
    "sg:phone":"+49 2452/4085",
    "sg:postcode":"52525",
    "sg:province":"Nordrhein-Westfalen",
    "wof:name":"Heinsberger Volkszeitung",
    "wof:placetype":"venue"
},
  "geometry": {"coordinates":[6.09344,51.062111],"type":"Point"}
}