{
  "type": "Feature",
  "properties": {
    "iso:country":"DE",
    "sg:address":"Herchenstein",
    "sg:city":"Dillenburg",
    "sg:phone":"+49 2771/6567",
    "sg:postcode":"35688",
    "sg:province":"Hessen",
    "wof:name":"K.-h. Nickel",
    "wof:placetype":"venue"
},
  "geometry": {"coordinates":[8.3476343155,50.7413520813],"type":"Point"}
}