{
  "type": "Feature",
  "properties": {
    "iso:country":"DE",
    "sg:address":"Brooktor 11",
    "sg:city":"Hamburg",
    "sg:postcode":"20457",
    "sg:province":"Hamburg",
    "wof:name":"Schiffahrtsges. Puttgarden Mbh",
    "wof:placetype":"venue"
},
  "geometry": {"coordinates":[9.9992980957,53.5423622131],"type":"Point"}
}