{
  "type": "Feature",
  "properties": {
    "iso:country":"DE",
    "sg:address":"Bischofstr. 14",
    "sg:city":"Bischofswerda",
    "sg:phone":"+49 3594/703059",
    "sg:postcode":"01877",
    "sg:province":"Sachsen",
    "wof:name":"Wasserversorgung Bischofswerda Gmbh",
    "wof:placetype":"venue"
},
  "geometry": {"coordinates":[14.185833931,51.1274375916],"type":"Point"}
}