{
  "type": "Feature",
  "properties": {
    "iso:country":"DE",
    "sg:address":"Waldsiedlung",
    "sg:city":"Diedersdorf",
    "sg:postcode":"15306",
    "sg:province":"Brandenburg",
    "wof:name":"Hut Oderbau Gmbh",
    "wof:placetype":"venue"
},
  "geometry": {"coordinates":[14.38035,52.533703],"type":"Point"}
}