{
  "type": "Feature",
  "properties": {
    "iso:country":"DE",
    "sg:address":"Am K\u00f6bens 6",
    "sg:city":"Langwedel",
    "sg:phone":"+49 4232/7644",
    "sg:postcode":"27299",
    "sg:province":"Niedersachsen",
    "wof:name":"Johann Oetting",
    "wof:placetype":"venue"
},
  "geometry": {"coordinates":[9.17622,52.982227],"type":"Point"}
}