{
  "type": "Feature",
  "properties": {
    "iso:country":"DE",
    "sg:address":"Sonnenbichlstra\u00dfe 25",
    "sg:city":"Nonnenhorn/Bodensee",
    "sg:postcode":"88149",
    "sg:province":"Bayern",
    "wof:name":"Hsbc Trinkaus & Burkhardt - Bank Seit 1785",
    "wof:placetype":"venue"
},
  "geometry": {"coordinates":[-85.804489,38.265308],"type":"Point"}
}