{
  "type": "Feature",
  "properties": {
    "iso:country":"DE",
    "sg:address":"Kattwiehe 2",
    "sg:city":"Rahden",
    "sg:phone":"+49 5771/2128",
    "sg:postcode":"32369",
    "sg:province":"Nordrhein-Westfalen",
    "wof:name":"Adolf Baumbach",
    "wof:placetype":"venue"
},
  "geometry": {"coordinates":[8.591676,52.474731],"type":"Point"}
}