{
  "type": "Feature",
  "properties": {
    "iso:country":"DE",
    "sg:address":"Marktplatz 13",
    "sg:city":"Ohrdruf",
    "sg:phone":"+49 3624/313400",
    "sg:postcode":"99885",
    "sg:province":"Th\u00fcringen",
    "wof:name":"Brigitte Platz Anlageberater",
    "wof:placetype":"venue"
},
  "geometry": {"coordinates":[10.7329206467,50.8274421692],"type":"Point"}
}