{
  "type": "Feature",
  "properties": {
    "iso:country":"DE",
    "sg:address":"Hinter Mont",
    "sg:city":"Treis-Karden",
    "sg:phone":"+49 2672/7440",
    "sg:postcode":"56253",
    "sg:province":"Rheinland-Pfalz",
    "wof:name":"Donatelli Gmbh",
    "wof:placetype":"venue"
},
  "geometry": {"coordinates":[7.304496,50.173164],"type":"Point"}
}