{
  "type": "Feature",
  "properties": {
    "iso:country":"DE",
    "sg:address":"Paternusstr. 36",
    "sg:city":"Worms",
    "sg:phone":"+49 6247/313",
    "sg:postcode":"67551",
    "sg:province":"Rheinland-Pfalz",
    "wof:name":"Heinz Merker",
    "wof:placetype":"venue"
},
  "geometry": {"coordinates":[8.2751064301,49.637676239],"type":"Point"}
}