{
  "type": "Feature",
  "properties": {
    "iso:country":"DE",
    "sg:address":"\u00d6jendorfer Weg 39",
    "sg:city":"Hamburg",
    "sg:phone":"+49 40/7327584",
    "sg:postcode":"22119",
    "sg:province":"Hamburg",
    "wof:name":"\u00d6jendorfer Treff",
    "wof:placetype":"venue"
},
  "geometry": {"coordinates":[10.1111793518,53.5432548523],"type":"Point"}
}