{
  "type": "Feature",
  "properties": {
    "iso:country":"DE",
    "sg:address":"Memberg 54",
    "sg:city":"Malgersdorf",
    "sg:phone":"+49 9954/90210",
    "sg:postcode":"84333",
    "sg:province":"Bayern",
    "wof:name":"Soska Gmbh",
    "wof:placetype":"venue"
},
  "geometry": {"coordinates":[12.732374,48.540905],"type":"Point"}
}