{
  "type": "Feature",
  "properties": {
    "iso:country":"DE",
    "sg:address":"Obere Hauptstr. 10",
    "sg:city":"Lugau",
    "sg:postcode":"09385",
    "sg:province":"Sachsen",
    "wof:name":"Siegfried M\u00fcller",
    "wof:placetype":"venue"
},
  "geometry": {"coordinates":[12.746694,50.761078],"type":"Point"}
}