{
  "type": "Feature",
  "properties": {
    "iso:country":"DE",
    "sg:address":"Berliner Ring 41",
    "sg:city":"Wolfsburg",
    "sg:phone":"+49 5361/24004",
    "sg:postcode":"38440",
    "sg:province":"Niedersachsen",
    "wof:name":"Vw-bad",
    "wof:placetype":"venue"
},
  "geometry": {"coordinates":[10.7966709137,52.4163246155],"type":"Point"}
}