{
  "type": "Feature",
  "properties": {
    "iso:country":"DE",
    "sg:address":"H\u00fcnefeldstr. 5",
    "sg:city":"Hamburg",
    "sg:phone":"+49 40/661212",
    "sg:postcode":"22045",
    "sg:province":"Hamburg",
    "wof:name":"Heinrich Karow",
    "wof:placetype":"venue"
},
  "geometry": {"coordinates":[10.116211,53.586727],"type":"Point"}
}