{
  "type": "Feature",
  "properties": {
    "iso:country":"DE",
    "sg:address":"Industriestr. 14b",
    "sg:city":"Mettmann",
    "sg:phone":"+49 2104/25620",
    "sg:postcode":"40822",
    "sg:province":"Nordrhein-Westfalen",
    "wof:name":"R\u00fcdiger Heidenreich",
    "wof:placetype":"venue"
},
  "geometry": {"coordinates":[7.010464,51.250748],"type":"Point"}
}