{
  "type": "Feature",
  "properties": {
    "iso:country":"DE",
    "sg:address":"Amselweg 16",
    "sg:city":"Sprotta",
    "sg:phone":"+49 3423/602121",
    "sg:postcode":"04838",
    "sg:province":"Sachsen",
    "wof:name":"Udo G\u00e4belein",
    "wof:placetype":"venue"
},
  "geometry": {"coordinates":[12.6262254715,51.4936714172],"type":"Point"}
}