{
  "type": "Feature",
  "properties": {
    "iso:country":"DE",
    "sg:address":"L\u00fcbarserStr 25-27",
    "sg:city":"Berlin",
    "sg:phone":"+49 30",
    "sg:postcode":"13435",
    "sg:province":"Berlin",
    "wof:name":"Ios Gmbh",
    "wof:placetype":"venue"
},
  "geometry": {"coordinates":[13.3328323364,52.5985221863],"type":"Point"}
}