{
  "type": "Feature",
  "properties": {
    "iso:country":"DE",
    "sg:address":"Im Br\u00fcckle 4",
    "sg:city":"Bretten",
    "sg:phone":"+49 7252/2186",
    "sg:postcode":"75015",
    "sg:province":"Baden-W\u00fcrttemberg",
    "wof:name":"Siegfried Sartorius Gmbh",
    "wof:placetype":"venue"
},
  "geometry": {"coordinates":[8.7015600204,49.0304031372],"type":"Point"}
}