{
  "type": "Feature",
  "properties": {
    "iso:country":"DE",
    "sg:address":"Ohlm\u00fcllerstr. 2",
    "sg:city":"M\u00fcnchen",
    "sg:phone":"+49 89/669163",
    "sg:postcode":"81541",
    "sg:province":"Bayern",
    "wof:name":"Bei Schorschi",
    "wof:placetype":"venue"
},
  "geometry": {"coordinates":[11.578212738,48.1261940002],"type":"Point"}
}