{
  "type": "Feature",
  "properties": {
    "iso:country":"DE",
    "sg:address":"Weinbergsweg 28",
    "sg:city":"Adendorf",
    "sg:phone":"+49 4131/18393",
    "sg:postcode":"21365",
    "sg:province":"Niedersachsen",
    "wof:name":"Hochzeitsausstatter Peters",
    "wof:placetype":"venue"
},
  "geometry": {"coordinates":[10.4328804016,53.2837562561],"type":"Point"}
}