{
  "type": "Feature",
  "properties": {
    "iso:country":"DE",
    "sg:address":"Gottlieb-Daimler-Str 17",
    "sg:city":"Holzwickede",
    "sg:phone":"+49 2301/9470",
    "sg:postcode":"59439",
    "sg:province":"Nordrhein-Westfalen",
    "wof:name":"Wawin Gmbh",
    "wof:placetype":"venue"
},
  "geometry": {"coordinates":[7.615905,51.513241],"type":"Point"}
}