{
  "type": "Feature",
  "properties": {
    "iso:country":"DE",
    "sg:address":"Untere M\u00fchlewiesen 4",
    "sg:city":"Wut\u00f6schingen",
    "sg:phone":"+49 7746/2114",
    "sg:postcode":"79793",
    "sg:province":"Baden-W\u00fcrttemberg",
    "wof:name":"Walter Mutter",
    "wof:placetype":"venue"
},
  "geometry": {"coordinates":[8.379156,47.670879],"type":"Point"}
}