{
  "type": "Feature",
  "properties": {
    "iso:country":"DE",
    "sg:address":"Ringstr. 1",
    "sg:city":"Weilrod",
    "sg:phone":"+49 6084/5836",
    "sg:postcode":"61276",
    "sg:province":"Hessen",
    "wof:name":"Wolfgang Manier",
    "wof:placetype":"venue"
},
  "geometry": {"coordinates":[8.3983001709,50.2843132019],"type":"Point"}
}