{
  "type": "Feature",
  "properties": {
    "iso:country":"DE",
    "sg:address":"Triftstr. 107",
    "sg:city":"L\u00fcbeck",
    "sg:phone":"+49 451/401805",
    "sg:postcode":"23554",
    "sg:province":"Schleswig-Holstein",
    "wof:name":"P. Spandet Immobilienmakler Gmbh",
    "wof:placetype":"venue"
},
  "geometry": {"coordinates":[10.6787691116,53.8912467957],"type":"Point"}
}