{
  "type": "Feature",
  "properties": {
    "iso:country":"DE",
    "sg:address":"Diergardtplatz 12",
    "sg:city":"Viersen",
    "sg:phone":"+49 2162/358057",
    "sg:postcode":"41747",
    "sg:province":"Nordrhein-Westfalen",
    "wof:name":"Moderne Bauelemente Detlef Knechtel Gmbh & Co.",
    "wof:placetype":"venue"
},
  "geometry": {"coordinates":[6.391845,51.259506],"type":"Point"}
}