{
  "type": "Feature",
  "properties": {
    "iso:country":"DE",
    "sg:address":"Schumannstr. 9",
    "sg:city":"Siegburg",
    "sg:phone":"+49 2241/976200",
    "sg:postcode":"53721",
    "sg:province":"Nordrhein-Westfalen",
    "wof:name":"Robi Gmbh",
    "wof:placetype":"venue"
},
  "geometry": {"coordinates":[7.2097887993,50.7894897461],"type":"Point"}
}