{
  "type": "Feature",
  "properties": {
    "iso:country":"DE",
    "sg:address":"Hassenr\u00f6ther Str. 32",
    "sg:city":"H\u00f6chst",
    "sg:phone":"+49 6163/2457",
    "sg:postcode":"64739",
    "sg:province":"Hessen",
    "wof:name":"W. Fornott",
    "wof:placetype":"venue"
},
  "geometry": {"coordinates":[8.938412,49.781124],"type":"Point"}
}