{
  "type": "Feature",
  "properties": {
    "iso:country":"DE",
    "sg:address":"Kapellenstr. 20",
    "sg:city":"Hohenwart",
    "sg:phone":"+49 8443/522",
    "sg:postcode":"86558",
    "sg:province":"Bayern",
    "wof:name":"M. Brachmann",
    "wof:placetype":"venue"
},
  "geometry": {"coordinates":[11.380516,48.594326],"type":"Point"}
}