{
  "type": "Feature",
  "properties": {
    "iso:country":"DE",
    "sg:address":"Klabundstr. 15",
    "sg:city":"Frankfurt",
    "sg:phone":"+49 335/545690",
    "sg:postcode":"15232",
    "sg:province":"Brandenburg",
    "wof:name":"Frank Kania",
    "wof:placetype":"venue"
},
  "geometry": {"coordinates":[14.544634,52.323223],"type":"Point"}
}