{
  "type": "Feature",
  "properties": {
    "iso:country":"DE",
    "sg:address":"Schulstr. 6",
    "sg:city":"Baar-Ebenhausen",
    "sg:phone":"+49 8453/2779",
    "sg:postcode":"85107",
    "sg:province":"Bayern",
    "wof:name":"Bistro Schranner",
    "wof:placetype":"venue"
},
  "geometry": {"coordinates":[11.4736232758,48.6714172363],"type":"Point"}
}