{
  "type": "Feature",
  "properties": {
    "iso:country":"DE",
    "sg:address":"Freidankstr. 10",
    "sg:city":"M\u00fcnchen",
    "sg:phone":"+49 89/6019713",
    "sg:postcode":"81739",
    "sg:province":"Bayern",
    "wof:name":"Peter Schmid Kohlen- Und Brennstoffhandlung",
    "wof:placetype":"venue"
},
  "geometry": {"coordinates":[11.672375,48.084805],"type":"Point"}
}