{
  "type": "Feature",
  "properties": {
    "iso:country":"DE",
    "sg:address":"Hebelstr. 26",
    "sg:city":"Ketsch",
    "sg:phone":"+49 6202/61663",
    "sg:postcode":"68775",
    "sg:province":"Baden-W\u00fcrttemberg",
    "wof:name":"Wilhelm Baumann",
    "wof:placetype":"venue"
},
  "geometry": {"coordinates":[8.5287675858,49.36378479],"type":"Point"}
}