{
  "type": "Feature",
  "properties": {
    "iso:country":"DE",
    "sg:address":"Langensalzaer Landstr.",
    "sg:city":"M\u00fchlhausen",
    "sg:phone":"+49 36014/42422",
    "sg:postcode":"99974",
    "sg:province":"Th\u00fcringen",
    "wof:name":"Floristik Hamm",
    "wof:placetype":"venue"
},
  "geometry": {"coordinates":[10.478246,51.198933],"type":"Point"}
}