{
  "type": "Feature",
  "properties": {
    "iso:country":"DE",
    "sg:address":"Schulstr. 25",
    "sg:city":"Schiffweiler",
    "sg:phone":"+49 6821/6060",
    "sg:postcode":"66578",
    "sg:province":"Saarland",
    "wof:name":"Aktiv-markt",
    "wof:placetype":"venue"
},
  "geometry": {"coordinates":[7.0975317955,49.3561515808],"type":"Point"}
}