{
  "type": "Feature",
  "properties": {
    "iso:country":"DE",
    "sg:address":"Emilienstr. 3",
    "sg:city":"Zwickau",
    "sg:phone":"+49 375/241628",
    "sg:postcode":"08056",
    "sg:province":"Sachsen",
    "wof:name":"Frank Hartzendorf",
    "wof:placetype":"venue"
},
  "geometry": {"coordinates":[12.483189,50.71471],"type":"Point"}
}