{
  "type": "Feature",
  "properties": {
    "iso:country":"DE",
    "sg:address":"Elsetalstr. 6",
    "sg:city":"Herscheid",
    "sg:postcode":"58849",
    "sg:province":"Nordrhein-Westfalen",
    "wof:name":"Ernst W. Langenbach Gmbh",
    "wof:placetype":"venue"
},
  "geometry": {"coordinates":[7.801723,51.190361],"type":"Point"}
}