{
  "type": "Feature",
  "properties": {
    "iso:country":"DE",
    "sg:address":"Hauptstr. 135",
    "sg:city":"Miltenberg",
    "sg:phone":"+49 9371/2731",
    "sg:postcode":"63897",
    "sg:province":"Bayern",
    "wof:name":"Fritz Lang",
    "wof:placetype":"venue"
},
  "geometry": {"coordinates":[9.2532777786,49.6996612549],"type":"Point"}
}