{
  "type": "Feature",
  "properties": {
    "iso:country":"DE",
    "sg:address":"Untere Allee 2",
    "sg:city":"Hildburghausen",
    "sg:phone":"+49 3685/703719",
    "sg:postcode":"98646",
    "sg:province":"Th\u00fcringen",
    "wof:name":"Roland Halbig Rechtsanwalt",
    "wof:placetype":"venue"
},
  "geometry": {"coordinates":[10.7269582748,50.4268379211],"type":"Point"}
}