{
  "type": "Feature",
  "properties": {
    "iso:country":"DE",
    "sg:address":"Steimelstr. 8",
    "sg:city":"Bergneustadt",
    "sg:phone":"+49 2261/45497",
    "sg:postcode":"51702",
    "sg:province":"Nordrhein-Westfalen",
    "wof:name":"J\u00fcrgen Harens Ingenieur",
    "wof:placetype":"venue"
},
  "geometry": {"coordinates":[7.682682991,51.0276298523],"type":"Point"}
}