{
  "type": "Feature",
  "properties": {
    "iso:country":"DE",
    "sg:address":"Domstr. 20",
    "sg:city":"K\u00f6ln",
    "sg:phone":"+49 221/1490",
    "sg:postcode":"50668",
    "sg:province":"Nordrhein-Westfalen",
    "wof:name":"Rewe-handelsgesellschaft Rhein-schwarzwald Mbh",
    "wof:placetype":"venue"
},
  "geometry": {"coordinates":[6.9590039253,50.9457473755],"type":"Point"}
}