{
  "type": "Feature",
  "properties": {
    "iso:country":"DE",
    "sg:address":"Kurt-Schumacher-Str. 2",
    "sg:city":"Herten",
    "sg:phone":"+49 2366/36120",
    "sg:postcode":"45699",
    "sg:province":"Nordrhein-Westfalen",
    "wof:name":"Restaurant Ratskeller",
    "wof:placetype":"venue"
},
  "geometry": {"coordinates":[7.1352391243,51.5940628052],"type":"Point"}
}