{
  "type": "Feature",
  "properties": {
    "iso:country":"DE",
    "sg:address":"Planitzstr. 43",
    "sg:city":"Berlin",
    "sg:phone":"+49 30/5671521",
    "sg:postcode":"12621",
    "sg:province":"Berlin",
    "wof:name":"Katharina Woy",
    "wof:placetype":"venue"
},
  "geometry": {"coordinates":[13.591932,52.507645],"type":"Point"}
}