{
  "type": "Feature",
  "properties": {
    "iso:country":"DE",
    "sg:address":"Markt 6",
    "sg:city":"Holzminden",
    "sg:phone":"+49 5531/7614",
    "sg:postcode":"37603",
    "sg:province":"Niedersachsen",
    "wof:name":"Marktstube",
    "wof:placetype":"venue"
},
  "geometry": {"coordinates":[9.4470462799,51.8281822205],"type":"Point"}
}