{
  "type": "Feature",
  "properties": {
    "iso:country":"DE",
    "sg:address":"Ringstr. 13",
    "sg:city":"Malsch",
    "sg:phone":"+49 7253/21178",
    "sg:postcode":"69254",
    "sg:province":"Baden-W\u00fcrttemberg",
    "wof:name":"Armin Raddatz",
    "wof:placetype":"venue"
},
  "geometry": {"coordinates":[8.6796,49.24387],"type":"Point"}
}