{
  "type": "Feature",
  "properties": {
    "iso:country":"DE",
    "sg:address":"Oeverdieck",
    "sg:city":"Lensahn",
    "sg:phone":"+49 4363/1340",
    "sg:postcode":"23738",
    "sg:province":"Schleswig-Holstein",
    "wof:name":"Tsv Lensahn",
    "wof:placetype":"venue"
},
  "geometry": {"coordinates":[10.8913488388,54.2169914246],"type":"Point"}
}