{
  "type": "Feature",
  "properties": {
    "iso:country":"DE",
    "sg:address":"Taubenstr. 4",
    "sg:city":"Cottbus",
    "sg:postcode":"03046",
    "sg:province":"Brandenburg",
    "wof:name":"T\u00fc-service Ingenieur- Und Beratungs Gmbh",
    "wof:placetype":"venue"
},
  "geometry": {"coordinates":[14.332097,51.755337],"type":"Point"}
}