{
  "type": "Feature",
  "properties": {
    "iso:country":"DE",
    "sg:address":"Dortmunder Str. 12",
    "sg:city":"Schwetzingen",
    "sg:phone":"+49 4962/0210624",
    "sg:postcode":"68723",
    "sg:province":"Baden-W\u00fcrttemberg",
    "wof:name":"Schwetzinger Kartondruck Kiefer + Knapp Ohg",
    "wof:placetype":"venue"
},
  "geometry": {"coordinates":[8.5622339249,49.3995246887],"type":"Point"}
}