{
  "type": "Feature",
  "properties": {
    "iso:country":"DE",
    "sg:address":"Gelderner Str. 372",
    "sg:city":"Kevelaer",
    "sg:phone":"+49 2832/3839",
    "sg:postcode":"47623",
    "sg:province":"Nordrhein-Westfalen",
    "wof:name":"Helmut Peters",
    "wof:placetype":"venue"
},
  "geometry": {"coordinates":[6.26171,51.569992],"type":"Point"}
}