{
  "type": "Feature",
  "properties": {
    "iso:country":"DE",
    "sg:address":"Hans-Weigel-Str. 14",
    "sg:city":"Leipzig",
    "sg:phone":"+49 341/6515621",
    "sg:postcode":"04319",
    "sg:province":"Sachsen",
    "wof:name":"Mario Rei\u00dfmann",
    "wof:placetype":"venue"
},
  "geometry": {"coordinates":[12.4739589691,51.3385429382],"type":"Point"}
}