{
  "type": "Feature",
  "properties": {
    "iso:country":"DE",
    "sg:address":"Wilhelmstr. 107",
    "sg:city":"Klingenberg",
    "sg:phone":"+49 9372/2438",
    "sg:postcode":"63911",
    "sg:province":"Bayern",
    "wof:name":"Weingut Der Stadt Klingenberg",
    "wof:placetype":"venue"
},
  "geometry": {"coordinates":[9.1843595505,49.775062561],"type":"Point"}
}