{
  "type": "Feature",
  "properties": {
    "iso:country":"DE",
    "sg:address":"Hallerstr. 5f",
    "sg:city":"Hamburg",
    "sg:phone":"+49 40/4204679",
    "sg:postcode":"20146",
    "sg:province":"Hamburg",
    "wof:name":"Urte Fernandez",
    "wof:placetype":"venue"
},
  "geometry": {"coordinates":[9.980731,53.57312],"type":"Point"}
}