{
  "type": "Feature",
  "properties": {
    "iso:country":"DE",
    "sg:address":"Heinrichsallee 6",
    "sg:city":"Aachen",
    "sg:phone":"+49 241/504959",
    "sg:postcode":"52062",
    "sg:province":"Nordrhein-Westfalen",
    "wof:name":"Erika Plager Krankengymnastin",
    "wof:placetype":"venue"
},
  "geometry": {"coordinates":[6.096168,50.775188],"type":"Point"}
}