{
  "type": "Feature",
  "properties": {
    "iso:country":"DE",
    "sg:address":"Kanalstr. 19",
    "sg:city":"Rudersberg",
    "sg:phone":"+49 7183/6663",
    "sg:postcode":"73635",
    "sg:province":"Baden-W\u00fcrttemberg",
    "wof:name":"W. Munz",
    "wof:placetype":"venue"
},
  "geometry": {"coordinates":[9.5506887436,48.8599090576],"type":"Point"}
}