{
  "type": "Feature",
  "properties": {
    "iso:country":"DE",
    "sg:address":"Theodor-Heuss-Ring 9",
    "sg:city":"Iserlohn",
    "sg:phone":"+49 2371/14555",
    "sg:postcode":"58636",
    "sg:province":"Nordrhein-Westfalen",
    "wof:name":"Pizzeria Romantica",
    "wof:placetype":"venue"
},
  "geometry": {"coordinates":[7.6981039047,51.376499176],"type":"Point"}
}