{
  "type": "Feature",
  "properties": {
    "iso:country":"DE",
    "sg:address":"Im Hainzenthal 43",
    "sg:city":"Winnweiler",
    "sg:postcode":"67722",
    "sg:province":"Rheinland-Pfalz",
    "wof:name":"Aktiv-markt",
    "wof:placetype":"venue"
},
  "geometry": {"coordinates":[7.8365130424,49.5650444031],"type":"Point"}
}