{
  "type": "Feature",
  "properties": {
    "iso:country":"DE",
    "sg:address":"St.-Laurentius-Platz 1",
    "sg:city":"Schwandorf",
    "sg:phone":"+49 9431/1516",
    "sg:postcode":"92421",
    "sg:province":"Bayern",
    "wof:name":"Georg B\u00e4uml",
    "wof:placetype":"venue"
},
  "geometry": {"coordinates":[12.060099,49.307056],"type":"Point"}
}