{
  "type": "Feature",
  "properties": {
    "iso:country":"DE",
    "sg:address":"Zweibr\u00fccker Str. 57-59",
    "sg:city":"Pirmasens",
    "sg:phone":"+49 6331/511400",
    "sg:postcode":"66953",
    "sg:province":"Rheinland-Pfalz",
    "wof:name":"Johannes E. K\u00fchn Gmbh",
    "wof:placetype":"venue"
},
  "geometry": {"coordinates":[7.6007890701,49.2090148926],"type":"Point"}
}