{
  "type": "Feature",
  "properties": {
    "iso:country":"DE",
    "sg:address":"Hinter den Heidgruben 1",
    "sg:city":"Blender",
    "sg:postcode":"27337",
    "sg:province":"Niedersachsen",
    "wof:name":"Lignatur-haus Gmbh",
    "wof:placetype":"venue"
},
  "geometry": {"coordinates":[9.09735,52.915245],"type":"Point"}
}