{
  "type": "Feature",
  "properties": {
    "iso:country":"DE",
    "sg:address":"Im Gewerbegebiet 28",
    "sg:city":"Deggenhausertal",
    "sg:phone":"+49 7066/99200",
    "sg:postcode":"88693",
    "sg:province":"Baden-W\u00fcrttemberg",
    "wof:name":"Beck Gmbh",
    "wof:placetype":"venue"
},
  "geometry": {"coordinates":[9.103813,49.209812],"type":"Point"}
}