{
  "type": "Feature",
  "properties": {
    "iso:country":"DE",
    "sg:address":"Meisenweg 4",
    "sg:city":"Schwalmstadt",
    "sg:postcode":"34613",
    "sg:province":"Hessen",
    "wof:name":"Josef-alfred Pelz",
    "wof:placetype":"venue"
},
  "geometry": {"coordinates":[9.2058124542,50.92137146],"type":"Point"}
}