{
  "type": "Feature",
  "properties": {
    "iso:country":"DE",
    "sg:address":"Mittelstr. 28",
    "sg:city":"Braunfels",
    "sg:phone":"+49 6473/1543",
    "sg:postcode":"35619",
    "sg:province":"Hessen",
    "wof:name":"Rudolf Kahl",
    "wof:placetype":"venue"
},
  "geometry": {"coordinates":[8.335629,50.532394],"type":"Point"}
}