{
  "type": "Feature",
  "properties": {
    "iso:country":"DE",
    "sg:address":"Friedrich-Ludwig-Jahn-Str. 7",
    "sg:city":"Doberlug-Kirchhain",
    "sg:phone":"+49 35322/4276",
    "sg:postcode":"03253",
    "sg:province":"Brandenburg",
    "wof:name":"J\u00f6rg Treppe",
    "wof:placetype":"venue"
},
  "geometry": {"coordinates":[13.5560569763,51.6385421753],"type":"Point"}
}