{
  "type": "Feature",
  "properties": {
    "iso:country":"DE",
    "sg:address":"Brauerstr. 21",
    "sg:city":"Uelzen",
    "sg:phone":"+49 581/71036",
    "sg:postcode":"29525",
    "sg:province":"Niedersachsen",
    "wof:name":"Sanit\u00e4tshaus Dohrmann Friedhelm Talg Gmbh",
    "wof:placetype":"venue"
},
  "geometry": {"coordinates":[10.56056,52.968464],"type":"Point"}
}