{
  "type": "Feature",
  "properties": {
    "iso:country":"DE",
    "sg:address":"Weicheringer Str. 153",
    "sg:city":"Ingolstadt",
    "sg:phone":"+49 8450/381",
    "sg:postcode":"85051",
    "sg:province":"Bayern",
    "wof:name":"Karl Thaller",
    "wof:placetype":"venue"
},
  "geometry": {"coordinates":[11.426942,48.713902],"type":"Point"}
}