{
  "type": "Feature",
  "properties": {
    "iso:country":"DE",
    "sg:address":"Weidenbrinkstr. 1",
    "sg:city":"Espelkamp",
    "sg:phone":"+49 5743/920072",
    "sg:postcode":"32339",
    "sg:province":"Nordrhein-Westfalen",
    "wof:name":"Karl Halwe",
    "wof:placetype":"venue"
},
  "geometry": {"coordinates":[8.644211,52.342594],"type":"Point"}
}