{
  "type": "Feature",
  "properties": {
    "iso:country":"DE",
    "sg:address":"Rathausplatz 4",
    "sg:city":"Schierling",
    "sg:phone":"+49 9451",
    "sg:postcode":"84069",
    "sg:province":"Bayern",
    "wof:name":"Marktgemeinde Schierling",
    "wof:placetype":"venue"
},
  "geometry": {"coordinates":[12.138256073,48.8374099731],"type":"Point"}
}