{
  "type": "Feature",
  "properties": {
    "iso:country":"DE",
    "sg:address":"Velsdorfer Str. 16",
    "sg:city":"Calv\u00f6rde",
    "sg:phone":"+49 39051/375",
    "sg:postcode":"39359",
    "sg:province":"Sachsen-Anhalt",
    "wof:name":"U. R\u00f6hning",
    "wof:placetype":"venue"
},
  "geometry": {"coordinates":[11.285017,52.398857],"type":"Point"}
}