{
  "type": "Feature",
  "properties": {
    "iso:country":"DE",
    "sg:address":"Porschestr. 30",
    "sg:city":"Kaufbeuren",
    "sg:phone":"+49 8341/8571",
    "sg:postcode":"87600",
    "sg:province":"Bayern",
    "wof:name":"Werktachtal-werkst\u00e4tten Einrichtung Der Lebenshife",
    "wof:placetype":"venue"
},
  "geometry": {"coordinates":[10.639282,47.892433],"type":"Point"}
}