{
  "type": "Feature",
  "properties": {
    "iso:country":"DE",
    "sg:address":"Im Wechselfeld 27",
    "sg:city":"St. Peter",
    "sg:phone":"+49 7660/823",
    "sg:postcode":"79271",
    "sg:province":"Baden-W\u00fcrttemberg",
    "wof:name":"Horst F\u00e4skorn Heilpraktiker",
    "wof:placetype":"venue"
},
  "geometry": {"coordinates":[8.0306844711,48.0109710693],"type":"Point"}
}