{
  "type": "Feature",
  "properties": {
    "iso:country":"DE",
    "sg:address":"K\u00e4serm\u00fchl 2",
    "sg:city":"Bischofsmais",
    "sg:phone":"+49 9920/292",
    "sg:postcode":"94253",
    "sg:province":"Bayern",
    "wof:name":"Fr\u00fcchte K\u00f6lbl",
    "wof:placetype":"venue"
},
  "geometry": {"coordinates":[13.1180887222,48.9052734375],"type":"Point"}
}