{
  "type": "Feature",
  "properties": {
    "iso:country":"DE",
    "sg:address":"Horneburger Str. 27",
    "sg:city":"Datteln",
    "sg:phone":"+49 2363/62221",
    "sg:postcode":"45711",
    "sg:province":"Nordrhein-Westfalen",
    "wof:name":"Richard Zimmermann",
    "wof:placetype":"venue"
},
  "geometry": {"coordinates":[7.291104,51.632248],"type":"Point"}
}