{
  "type": "Feature",
  "properties": {
    "iso:country":"DE",
    "sg:address":"Subbelrather Str. 146 Ehrenfeld",
    "sg:city":"K\u00f6ln",
    "sg:phone":"+49 4922/1528088",
    "sg:postcode":"50823",
    "sg:province":"Nordrhein-Westfalen",
    "wof:name":"Eugen Bosch Gmbh & Co Kg",
    "wof:placetype":"venue"
},
  "geometry": {"coordinates":[6.91728,50.949825],"type":"Point"}
}