{
  "type": "Feature",
  "properties": {
    "iso:country":"DE",
    "sg:address":"Untere Ringstr. 14",
    "sg:city":"Schluchsee",
    "sg:phone":"+49 7656/449",
    "sg:postcode":"79859",
    "sg:province":"Baden-W\u00fcrttemberg",
    "wof:name":"Gertrud Isele Bootsvermietung",
    "wof:placetype":"venue"
},
  "geometry": {"coordinates":[8.1859951019,47.8189888],"type":"Point"}
}