{
  "type": "Feature",
  "properties": {
    "iso:country":"DE",
    "sg:address":"Berrenrather Str. 197",
    "sg:city":"H\u00fcrth",
    "sg:phone":"+49 2233/32563",
    "sg:postcode":"50354",
    "sg:province":"Nordrhein-Westfalen",
    "wof:name":"J. Metzger",
    "wof:placetype":"venue"
},
  "geometry": {"coordinates":[6.8675441742,50.894241333],"type":"Point"}
}