{
  "type": "Feature",
  "properties": {
    "iso:country":"DE",
    "sg:address":"Wilder Kamp 1 a",
    "sg:city":"Seevetal",
    "sg:phone":"+49 4105/682240",
    "sg:postcode":"21220",
    "sg:province":"Niedersachsen",
    "wof:name":"Ambulante Pflege Die Falken",
    "wof:placetype":"venue"
},
  "geometry": {"coordinates":[10.027393,53.381935],"type":"Point"}
}