{
  "type": "Feature",
  "properties": {
    "iso:country":"DE",
    "sg:address":"Berliner Ring 33",
    "sg:city":"Bad Bentheim",
    "sg:phone":"+49 5922/6710",
    "sg:postcode":"48455",
    "sg:province":"Niedersachsen",
    "wof:name":"H. Und I. Timmer",
    "wof:placetype":"venue"
},
  "geometry": {"coordinates":[7.1569638252,52.2948074341],"type":"Point"}
}