{
  "type": "Feature",
  "properties": {
    "iso:country":"DE",
    "sg:address":"Dorfstr. 15",
    "sg:city":"Reil",
    "sg:phone":"+49 6542/901439",
    "sg:postcode":"56861",
    "sg:province":"Rheinland-Pfalz",
    "wof:name":"Burg Itc Gmbh",
    "wof:placetype":"venue"
},
  "geometry": {"coordinates":[7.1172862053,50.0208740234],"type":"Point"}
}