{
  "type": "Feature",
  "properties": {
    "iso:country":"DE",
    "sg:address":"Torstr. 108",
    "sg:city":"Wenigenlupnitz",
    "sg:phone":"+49 36920/80654",
    "sg:postcode":"99819",
    "sg:province":"Th\u00fcringen",
    "wof:name":"Beate K\u00fchr",
    "wof:placetype":"venue"
},
  "geometry": {"coordinates":[10.428143,50.978081],"type":"Point"}
}