{
  "type": "Feature",
  "properties": {
    "iso:country":"DE",
    "sg:address":"Hauptstr. 32",
    "sg:city":"Kaarst",
    "sg:phone":"+49 2131/519526",
    "sg:postcode":"41564",
    "sg:province":"Nordrhein-Westfalen",
    "wof:name":"Doris Aue",
    "wof:placetype":"venue"
},
  "geometry": {"coordinates":[6.593038,51.207222],"type":"Point"}
}