{
  "type": "Feature",
  "properties": {
    "iso:country":"DE",
    "sg:address":"Rheinstr. 4",
    "sg:city":"Pfungstadt",
    "sg:phone":"+49 6157/91510",
    "sg:postcode":"64319",
    "sg:province":"Hessen",
    "wof:name":"F. Feldmann Finanzberater",
    "wof:placetype":"venue"
},
  "geometry": {"coordinates":[8.5959043503,49.8026351929],"type":"Point"}
}