{
  "type": "Feature",
  "properties": {
    "iso:country":"DE",
    "sg:address":"Durlacher Str. 18",
    "sg:city":"Ketsch",
    "sg:phone":"+49 6202/61893",
    "sg:postcode":"68775",
    "sg:province":"Baden-W\u00fcrttemberg",
    "wof:name":"Koll Gmbh",
    "wof:placetype":"venue"
},
  "geometry": {"coordinates":[8.543589592,49.3637504578],"type":"Point"}
}