{
  "type": "Feature",
  "properties": {
    "iso:country":"DE",
    "sg:address":"Hasenmeerweg 17",
    "sg:city":"Uplengen",
    "sg:phone":"+49 4956/912091",
    "sg:postcode":"26670",
    "sg:province":"Niedersachsen",
    "wof:name":"Sassen",
    "wof:placetype":"venue"
},
  "geometry": {"coordinates":[7.711094,53.332188],"type":"Point"}
}