{
  "type": "Feature",
  "properties": {
    "iso:country":"DE",
    "sg:address":"Parkstrasse 1",
    "sg:city":"Ilshofen",
    "sg:phone":"+49 7904/7010",
    "sg:postcode":"74532",
    "sg:province":"Baden-W\u00fcrttemberg",
    "wof:name":"Bausch Str\u00f6bel Maschinenfabrik Ilshofen",
    "wof:placetype":"venue"
},
  "geometry": {"coordinates":[9.9176054001,49.1724433899],"type":"Point"}
}