{
  "type": "Feature",
  "properties": {
    "iso:country":"DE",
    "sg:address":"Klosterstr. 23",
    "sg:city":"Bad Herrenalb",
    "sg:phone":"+49 7083/2479",
    "sg:postcode":"76332",
    "sg:province":"Baden-W\u00fcrttemberg",
    "wof:name":"Romoser",
    "wof:placetype":"venue"
},
  "geometry": {"coordinates":[8.4366903305,48.7960472107],"type":"Point"}
}