{
  "type": "Feature",
  "properties": {
    "iso:country":"DE",
    "sg:address":"Orkotten 59",
    "sg:city":"Telgte",
    "sg:phone":"+49 2504/1852",
    "sg:postcode":"48291",
    "sg:province":"Nordrhein-Westfalen",
    "wof:name":"Theodor Osthues Inh. Alfred Osthues",
    "wof:placetype":"venue"
},
  "geometry": {"coordinates":[7.7693791389,51.9789657593],"type":"Point"}
}