{
  "type": "Feature",
  "properties": {
    "iso:country":"DE",
    "sg:address":"Hausneindorfer Str. 1",
    "sg:city":"Hedersleben",
    "sg:phone":"+49 39481/81396",
    "sg:postcode":"06458",
    "sg:province":"Sachsen-Anhalt",
    "wof:name":"Walter Kuhn",
    "wof:placetype":"venue"
},
  "geometry": {"coordinates":[11.2579622269,51.8513221741],"type":"Point"}
}