{
  "type": "Feature",
  "properties": {
    "iso:country":"DE",
    "sg:address":"K\u00f6lner Str. 12",
    "sg:city":"Kerpen",
    "sg:phone":"+49 2237/54765",
    "sg:postcode":"50171",
    "sg:province":"Nordrhein-Westfalen",
    "wof:name":"M. Block Und F. Fa\u00dfbender",
    "wof:placetype":"venue"
},
  "geometry": {"coordinates":[6.6963419914,50.8703384399],"type":"Point"}
}