{
  "type": "Feature",
  "properties": {
    "iso:country":"DE",
    "sg:address":"Wiegenweg 2",
    "sg:city":"Dietfurt",
    "sg:phone":"+49 8464/605106",
    "sg:postcode":"92345",
    "sg:province":"Bayern",
    "wof:name":"H. M\u00fcller",
    "wof:placetype":"venue"
},
  "geometry": {"coordinates":[11.5587387085,49.0260429382],"type":"Point"}
}