{
  "type": "Feature",
  "properties": {
    "iso:country":"DE",
    "sg:address":"Am Hofanger 22",
    "sg:city":"Kaufbeuren",
    "sg:phone":"+49 8341/94530",
    "sg:postcode":"87600",
    "sg:province":"Bayern",
    "wof:name":"G. Nentwich",
    "wof:placetype":"venue"
},
  "geometry": {"coordinates":[10.6156930923,47.8896713257],"type":"Point"}
}