{
  "type": "Feature",
  "properties": {
    "iso:country":"DE",
    "sg:address":"Ostenhellweg 34",
    "sg:city":"Dortmund",
    "sg:phone":"+49 231/54395379",
    "sg:postcode":"44135",
    "sg:province":"Nordrhein-Westfalen",
    "wof:name":"Karstadt-reiseb\u00fcro",
    "wof:placetype":"venue"
},
  "geometry": {"coordinates":[7.4701209068,51.5144081116],"type":"Point"}
}