{
  "type": "Feature",
  "properties": {
    "iso:country":"DE",
    "sg:address":"Spekendorfer Kirchweg 24",
    "sg:city":"Aurich",
    "sg:phone":"+49 4947/830",
    "sg:postcode":"26607",
    "sg:province":"Niedersachsen",
    "wof:name":"Reiner B\u00fcnting",
    "wof:placetype":"venue"
},
  "geometry": {"coordinates":[7.619421,53.531322],"type":"Point"}
}