{
  "type": "Feature",
  "properties": {
    "iso:country":"DE",
    "sg:address":"Willstr. 8",
    "sg:city":"N\u00fcrnberg",
    "sg:phone":"+49 911/270577",
    "sg:postcode":"90429",
    "sg:province":"Bayern",
    "wof:name":"Mitsportzentrale",
    "wof:placetype":"venue"
},
  "geometry": {"coordinates":[11.05533,49.451962],"type":"Point"}
}