{
  "type": "Feature",
  "properties": {
    "iso:country":"DE",
    "sg:address":"Lemf\u00f6rder Str. 50",
    "sg:city":"Rahden",
    "sg:phone":"+49 5771/1545",
    "sg:postcode":"32369",
    "sg:province":"Nordrhein-Westfalen",
    "wof:name":"Wilh. Brockschmidt",
    "wof:placetype":"venue"
},
  "geometry": {"coordinates":[8.591598,52.443081],"type":"Point"}
}