{
  "type": "Feature",
  "properties": {
    "iso:country":"DE",
    "sg:address":"Kronprinzstr. 47-49",
    "sg:city":"Langenfeld",
    "sg:phone":"+49 2173/2810",
    "sg:postcode":"40764",
    "sg:province":"Nordrhein-Westfalen",
    "wof:name":"Peter Butz Gmbh",
    "wof:placetype":"venue"
},
  "geometry": {"coordinates":[6.9667668343,51.1199874878],"type":"Point"}
}