{
  "type": "Feature",
  "properties": {
    "iso:country":"DE",
    "sg:address":"Westfalenstr. 80",
    "sg:city":"H\u00f6rstel",
    "sg:phone":"+49 5459/6992",
    "sg:postcode":"48477",
    "sg:province":"Nordrhein-Westfalen",
    "wof:name":"Zur Schleuse",
    "wof:placetype":"venue"
},
  "geometry": {"coordinates":[7.5879201889,52.2825508118],"type":"Point"}
}