{
  "type": "Feature",
  "properties": {
    "iso:country":"DE",
    "sg:address":"Bolongarostr. 150",
    "sg:city":"Frankfurt",
    "sg:phone":"+49 69/306061",
    "sg:postcode":"65929",
    "sg:province":"Hessen",
    "wof:name":"Deutscher Detektiv Verband E. V.",
    "wof:placetype":"venue"
},
  "geometry": {"coordinates":[8.5487165451,50.099773407],"type":"Point"}
}