{
  "type": "Feature",
  "properties": {
    "iso:country":"DE",
    "sg:address":"Neckarstr. 22",
    "sg:city":"Mannheim",
    "sg:phone":"+49 621/792235",
    "sg:postcode":"68259",
    "sg:province":"Baden-W\u00fcrttemberg",
    "wof:name":"Walter Eiermann",
    "wof:placetype":"venue"
},
  "geometry": {"coordinates":[8.5312356949,49.4802398682],"type":"Point"}
}