{
  "type": "Feature",
  "properties": {
    "iso:country":"DE",
    "sg:address":"Linkenheimer Str. 31",
    "sg:city":"Stutensee",
    "sg:phone":"+49 7244/92288",
    "sg:postcode":"76297",
    "sg:province":"Baden-W\u00fcrttemberg",
    "wof:name":"Paul-gerhard Schunk Architekt",
    "wof:placetype":"venue"
},
  "geometry": {"coordinates":[8.468252,49.071239],"type":"Point"}
}