{
  "type": "Feature",
  "properties": {
    "iso:country":"DE",
    "sg:address":"Bahnhofstr. 2",
    "sg:city":"Bad Segeberg",
    "sg:postcode":"23795",
    "sg:province":"Schleswig-Holstein",
    "wof:name":"Kies-verkaufskontor Holstein Gmbh",
    "wof:placetype":"venue"
},
  "geometry": {"coordinates":[10.3108386993,53.9346351624],"type":"Point"}
}