{
  "type": "Feature",
  "properties": {
    "iso:country":"DE",
    "sg:address":"Gro\u00dfe Gasse 15",
    "sg:city":"Michelstadt",
    "sg:phone":"+49 6061/3495",
    "sg:postcode":"64720",
    "sg:province":"Hessen",
    "wof:name":"S&s Elektronik Vertriebs Gmbh",
    "wof:placetype":"venue"
},
  "geometry": {"coordinates":[9.0043382645,49.6796302795],"type":"Point"}
}