{
  "type": "Feature",
  "properties": {
    "iso:country":"DE",
    "sg:address":"Auf dem R\u00e4hden 36",
    "sg:city":"Auhagen",
    "sg:phone":"+49 5725/6631",
    "sg:postcode":"31553",
    "sg:province":"Niedersachsen",
    "wof:name":"W. Kruppa",
    "wof:placetype":"venue"
},
  "geometry": {"coordinates":[9.281271,52.390427],"type":"Point"}
}