{
  "type": "Feature",
  "properties": {
    "iso:country":"DE",
    "sg:address":"Hohenzollerndamm 88 a",
    "sg:city":"Berlin",
    "sg:phone":"+49 30/8258249",
    "sg:postcode":"14199",
    "sg:province":"Berlin",
    "wof:name":"Schielke",
    "wof:placetype":"venue"
},
  "geometry": {"coordinates":[13.283861,52.478966],"type":"Point"}
}