{
  "type": "Feature",
  "properties": {
    "iso:country":"DE",
    "sg:address":"Holveder Weg 11",
    "sg:city":"Sauensiek",
    "sg:phone":"+49 4169/1432",
    "sg:postcode":"21644",
    "sg:province":"Niedersachsen",
    "wof:name":"K. Penner",
    "wof:placetype":"venue"
},
  "geometry": {"coordinates":[9.6058979034,53.3766860962],"type":"Point"}
}