{
  "type": "Feature",
  "properties": {
    "iso:country":"DE",
    "sg:address":"Meininger Str. 132",
    "sg:city":"Suhl",
    "sg:phone":"+49 3681/720758",
    "sg:postcode":"98529",
    "sg:province":"Th\u00fcringen",
    "wof:name":"Elektro-josef",
    "wof:placetype":"venue"
},
  "geometry": {"coordinates":[10.656725,50.600014],"type":"Point"}
}