{
  "type": "Feature",
  "properties": {
    "iso:country":"DE",
    "sg:address":"Alsterblick 59",
    "sg:city":"Hamburg",
    "sg:phone":"+49 40/60761069",
    "sg:postcode":"22397",
    "sg:province":"Hamburg",
    "wof:name":"Gkg Ges. F\u00fcr Kommunikation Im Gesundheitswesen Mbh",
    "wof:placetype":"venue"
},
  "geometry": {"coordinates":[10.119938,53.702843],"type":"Point"}
}