{
  "type": "Feature",
  "properties": {
    "iso:country":"DE",
    "sg:address":"Vorderer Anger 286",
    "sg:city":"Landsberg",
    "sg:phone":"+49 8191/39277",
    "sg:postcode":"86899",
    "sg:province":"Bayern",
    "wof:name":"Jeans For You Gmbh",
    "wof:placetype":"venue"
},
  "geometry": {"coordinates":[10.876628,48.051411],"type":"Point"}
}