{
  "type": "Feature",
  "properties": {
    "iso:country":"DE",
    "sg:address":"Kamigstr. 23",
    "sg:city":"Ueckerm\u00fcnde",
    "sg:phone":"+49 39771/27785",
    "sg:postcode":"17373",
    "sg:province":"Mecklenburg-Vorpommern",
    "wof:name":"Avv Dienstleistungsges. Mbh",
    "wof:placetype":"venue"
},
  "geometry": {"coordinates":[14.0471096039,53.7429924011],"type":"Point"}
}