{
  "type": "Feature",
  "properties": {
    "iso:country":"DE",
    "sg:address":"Varresbecker Str. 123",
    "sg:city":"Wuppertal",
    "sg:phone":"+49 202/71910",
    "sg:postcode":"42115",
    "sg:province":"Nordrhein-Westfalen",
    "wof:name":"Daimler Chrysler Bank Gmbh",
    "wof:placetype":"venue"
},
  "geometry": {"coordinates":[7.103492,51.251236],"type":"Point"}
}