{
  "type": "Feature",
  "properties": {
    "iso:country":"DE",
    "sg:address":"Jungfernstr. 10",
    "sg:city":"B\u00fctzow",
    "sg:phone":"+49 4938/4616035",
    "sg:postcode":"18246",
    "sg:province":"Mecklenburg-Vorpommern",
    "wof:name":"Dankert",
    "wof:placetype":"venue"
},
  "geometry": {"coordinates":[11.9854669571,53.8478355408],"type":"Point"}
}