{
  "type": "Feature",
  "properties": {
    "iso:country":"DE",
    "sg:address":"Pinacher Str. 61",
    "sg:city":"M\u00fchlacker",
    "sg:phone":"+49 4976/8591070",
    "sg:postcode":"75417",
    "sg:province":"Baden-W\u00fcrttemberg",
    "wof:name":"Eugen Rold Gmbh",
    "wof:placetype":"venue"
},
  "geometry": {"coordinates":[8.010221,48.139545],"type":"Point"}
}