{
  "type": "Feature",
  "properties": {
    "iso:country":"DE",
    "sg:address":"Niedermattstr. 2",
    "sg:city":"Kehl",
    "sg:phone":"+49 7853/475",
    "sg:postcode":"77694",
    "sg:province":"Baden-W\u00fcrttemberg",
    "wof:name":"Michele Henke Masseurin",
    "wof:placetype":"venue"
},
  "geometry": {"coordinates":[7.868335,48.587082],"type":"Point"}
}