{
  "type": "Feature",
  "properties": {
    "iso:country":"DE",
    "sg:address":"Itzenb\u00fctteler M\u00fchlenweg 31",
    "sg:city":"Bendestorf",
    "sg:phone":"+49 4183/6024",
    "sg:postcode":"21227",
    "sg:province":"Niedersachsen",
    "wof:name":"Pan Americarne Handels Gmbh",
    "wof:placetype":"venue"
},
  "geometry": {"coordinates":[9.9660711288,53.3318099976],"type":"Point"}
}