{
  "type": "Feature",
  "properties": {
    "iso:country":"DE",
    "sg:address":"Coppistr. 1",
    "sg:city":"Eberswalde",
    "sg:phone":"+49 3334/287753",
    "sg:postcode":"16227",
    "sg:province":"Brandenburg",
    "wof:name":"Ww Wohnen Und Wohlf\u00fchlen Bauelemente-vertriebs Gmbh",
    "wof:placetype":"venue"
},
  "geometry": {"coordinates":[13.769597,52.845802],"type":"Point"}
}