{
  "type": "Feature",
  "properties": {
    "iso:country":"DE",
    "sg:address":"Egenhofenstr. 20 d",
    "sg:city":"Planegg",
    "sg:phone":"+49 89/8574633",
    "sg:postcode":"82152",
    "sg:province":"Bayern",
    "wof:name":"Prof. Christian Helfrich Ingenieur",
    "wof:placetype":"venue"
},
  "geometry": {"coordinates":[11.4213342667,48.1119728088],"type":"Point"}
}