{
  "type": "Feature",
  "properties": {
    "iso:country":"DE",
    "sg:address":"Steinkamp 2",
    "sg:city":"Laboe",
    "sg:postcode":"24235",
    "sg:province":"Schleswig-Holstein",
    "wof:name":"Ehrich Beteiligungs Gmbh & Co. Liegenschafts Kg",
    "wof:placetype":"venue"
},
  "geometry": {"coordinates":[10.2253923416,54.4010505676],"type":"Point"}
}