{
  "type": "Feature",
  "properties": {
    "iso:country":"DE",
    "sg:address":"Alte Korbacher Str. 5",
    "sg:city":"V\u00f6hl",
    "sg:phone":"+49 5631/61190",
    "sg:postcode":"34516",
    "sg:province":"Hessen",
    "wof:name":"Karl Hartwig",
    "wof:placetype":"venue"
},
  "geometry": {"coordinates":[8.890787,51.240101],"type":"Point"}
}