{
  "type": "Feature",
  "properties": {
    "iso:country":"DE",
    "sg:address":"Am K\u00fcbelweiher 3",
    "sg:city":"Heroldsbach",
    "sg:phone":"+49 9190/92900",
    "sg:postcode":"91336",
    "sg:province":"Bayern",
    "wof:name":"Dr. Augustin Studienreisen Gmbh",
    "wof:placetype":"venue"
},
  "geometry": {"coordinates":[11.0155220032,49.691696167],"type":"Point"}
}