{
  "type": "Feature",
  "properties": {
    "iso:country":"DE",
    "sg:address":"Alte Poststr. 8",
    "sg:city":"Stuttgart",
    "sg:phone":"+49 711/2261347",
    "sg:postcode":"70173",
    "sg:province":"Baden-W\u00fcrttemberg",
    "wof:name":"Kosmetikstudio M. Krafft",
    "wof:placetype":"venue"
},
  "geometry": {"coordinates":[9.17294,48.774933],"type":"Point"}
}