{
  "type": "Feature",
  "properties": {
    "iso:country":"DE",
    "sg:address":"Hagener Str. 465",
    "sg:city":"Kreuztal",
    "sg:phone":"+49 2732/82933",
    "sg:postcode":"57223",
    "sg:province":"Nordrhein-Westfalen",
    "wof:name":"Elo Gmbh",
    "wof:placetype":"venue"
},
  "geometry": {"coordinates":[7.9823269844,51.0081329346],"type":"Point"}
}