{
  "type": "Feature",
  "properties": {
    "iso:country":"DE",
    "sg:address":"S\u00fcdblick 4",
    "sg:city":"F\u00f6hren",
    "sg:phone":"+49 6502/8985",
    "sg:postcode":"54343",
    "sg:province":"Rheinland-Pfalz",
    "wof:name":"V. Bommes",
    "wof:placetype":"venue"
},
  "geometry": {"coordinates":[6.7568459511,49.854221344],"type":"Point"}
}