{
  "type": "Feature",
  "properties": {
    "iso:country":"DE",
    "sg:address":"Martinsfeld 30",
    "sg:city":"K\u00f6ln",
    "sg:phone":"+49 221/9322007",
    "sg:postcode":"50676",
    "sg:province":"Nordrhein-Westfalen",
    "wof:name":"Bau Art M\u00f6bel Und Interieur Gmbh",
    "wof:placetype":"venue"
},
  "geometry": {"coordinates":[6.9514107704,50.9285812378],"type":"Point"}
}