{
  "type": "Feature",
  "properties": {
    "iso:country":"DE",
    "sg:address":"Vahrenwalder Str. 89",
    "sg:city":"Hannover",
    "sg:phone":"+49 511/3506714",
    "sg:postcode":"30165",
    "sg:province":"Niedersachsen",
    "wof:name":"E. Majunke",
    "wof:placetype":"venue"
},
  "geometry": {"coordinates":[9.734827,52.393497],"type":"Point"}
}