{
  "type": "Feature",
  "properties": {
    "iso:country":"DE",
    "sg:address":"Oberhollerau",
    "sg:city":"Moosthenning",
    "sg:phone":"+49 8731/9629",
    "sg:postcode":"84164",
    "sg:province":"Bayern",
    "wof:name":"Rudolf Und Franz Peter",
    "wof:placetype":"venue"
},
  "geometry": {"coordinates":[12.4584350586,48.6763839722],"type":"Point"}
}