{
  "type": "Feature",
  "properties": {
    "iso:country":"DE",
    "sg:address":"Groner Str. 16",
    "sg:city":"G\u00f6ttingen",
    "sg:phone":"+49 551/54040",
    "sg:postcode":"37073",
    "sg:province":"Niedersachsen",
    "wof:name":"Brillen-opticum Augenoptik",
    "wof:placetype":"venue"
},
  "geometry": {"coordinates":[9.9323692322,51.5320472717],"type":"Point"}
}