{
  "type": "Feature",
  "properties": {
    "iso:country":"DE",
    "sg:address":"Ernst-Th\u00e4lmann-Str. 22",
    "sg:city":"Neugersdorf",
    "sg:phone":"+49 3586/702431",
    "sg:postcode":"02727",
    "sg:province":"Sachsen",
    "wof:name":"M. Bennewitz Inh. Martin Belger",
    "wof:placetype":"venue"
},
  "geometry": {"coordinates":[14.603267,50.983173],"type":"Point"}
}