{
  "type": "Feature",
  "properties": {
    "iso:country":"DE",
    "sg:address":"Harpener Str. 2a",
    "sg:city":"Bochum",
    "sg:phone":"+49 234/901820",
    "sg:postcode":"44791",
    "sg:province":"Nordrhein-Westfalen",
    "wof:name":"Joseph Hubert",
    "wof:placetype":"venue"
},
  "geometry": {"coordinates":[7.234273,51.483437],"type":"Point"}
}