{
  "type": "Feature",
  "properties": {
    "iso:country":"DE",
    "sg:address":"Postberg 2",
    "sg:city":"Rittersgr\u00fcn",
    "sg:phone":"+49 37757/7633",
    "sg:postcode":"08355",
    "wof:name":"Michael Kunz Ofen Und Fliesen Gmbh",
    "wof:placetype":"venue"
},
  "geometry": {"coordinates":[12.8029851913,50.4737319946],"type":"Point"}
}