{
  "type": "Feature",
  "properties": {
    "iso:country":"DE",
    "sg:address":"G\u00fcterbahnhofstr. 15b",
    "sg:city":"Villingen-Schwenningen",
    "sg:phone":"+49 7721/23124",
    "sg:postcode":"78048",
    "sg:province":"Baden-W\u00fcrttemberg",
    "wof:name":"Vereinsgastst\u00e4tte Eisenbahner- Sportverein Villingen E. V.",
    "wof:placetype":"venue"
},
  "geometry": {"coordinates":[8.4669675827,48.0564804077],"type":"Point"}
}