{
  "type": "Feature",
  "properties": {
    "iso:country":"DE",
    "sg:address":"Wallstr. 4",
    "sg:city":"L\u00fcneburg",
    "sg:phone":"+49 4131/7430",
    "sg:postcode":"21335",
    "sg:province":"Niedersachsen",
    "wof:name":"Landeszentralbank In Der Freien Hansestadt Bremen-",
    "wof:placetype":"venue"
},
  "geometry": {"coordinates":[10.4076910019,53.2458572388],"type":"Point"}
}