{
  "type": "Feature",
  "properties": {
    "iso:country":"DE",
    "sg:address":"Gartenstr./Albertstr.",
    "sg:city":"Glindow",
    "sg:phone":"+49 3327/42676",
    "sg:postcode":"14542",
    "sg:province":"Brandenburg",
    "wof:name":"Spedition Schmidt",
    "wof:placetype":"venue"
},
  "geometry": {"coordinates":[12.933676,52.376747],"type":"Point"}
}