{
  "type": "Feature",
  "properties": {
    "iso:country":"DE",
    "sg:address":"Marienplatz 63",
    "sg:city":"Ravensburg",
    "sg:postcode":"88212",
    "sg:province":"Baden-W\u00fcrttemberg",
    "wof:name":"Deutsche Telekom T-punkt",
    "wof:placetype":"venue"
},
  "geometry": {"coordinates":[9.6135587692,47.7831726074],"type":"Point"}
}