{
  "type": "Feature",
  "properties": {
    "iso:country":"DE",
    "sg:address":"Ottobeuren",
    "sg:city":"Ottobeuren",
    "sg:phone":"+49 8332/7776",
    "sg:postcode":"87724",
    "sg:province":"Bayern",
    "wof:name":"Raiffeisenbank Woringen-lachen Eg",
    "wof:placetype":"venue"
},
  "geometry": {"coordinates":[10.32418,47.937672],"type":"Point"}
}