{
  "type": "Feature",
  "properties": {
    "iso:country":"DE",
    "sg:address":"Griesstr. 91",
    "sg:city":"Hamburg",
    "sg:phone":"+49 40/618380",
    "sg:postcode":"20535",
    "sg:province":"Hamburg",
    "wof:name":"Manfred Brandt",
    "wof:placetype":"venue"
},
  "geometry": {"coordinates":[10.0597238541,53.5640678406],"type":"Point"}
}