{
  "type": "Feature",
  "properties": {
    "iso:country":"DE",
    "sg:address":"Bgm.-Schmid-Str. 16",
    "sg:city":"Burscheid",
    "sg:phone":"+49 4921/747825",
    "sg:postcode":"51399",
    "sg:province":"Nordrhein-Westfalen",
    "wof:name":"Awv Anzeigen-werbe-u. Verlags Gmbh",
    "wof:placetype":"venue"
},
  "geometry": {"coordinates":[7.1131138802,51.0837631226],"type":"Point"}
}