{
  "type": "Feature",
  "properties": {
    "iso:country":"DE",
    "sg:address":"Weidenweg 16",
    "sg:city":"Golzow",
    "sg:phone":"+49 3334/420250",
    "sg:postcode":"16230",
    "sg:province":"Brandenburg",
    "wof:name":"Reinhard Zittlau",
    "wof:placetype":"venue"
},
  "geometry": {"coordinates":[13.806992,52.913746],"type":"Point"}
}