{
  "type": "Feature",
  "properties": {
    "iso:country":"DE",
    "sg:address":"Muschau 5",
    "sg:city":"Loit",
    "sg:phone":"+49 4641/3094",
    "sg:postcode":"24888",
    "sg:province":"Schleswig-Holstein",
    "wof:name":"Autohaus Borghardt E. Kfm.",
    "wof:placetype":"venue"
},
  "geometry": {"coordinates":[9.702798,54.618294],"type":"Point"}
}