{
  "type": "Feature",
  "properties": {
    "iso:country":"DE",
    "sg:address":"Georgstr. 20",
    "sg:city":"Hannover",
    "sg:postcode":"30159",
    "sg:province":"Niedersachsen",
    "wof:name":"Heimstiftung In Hannover H. Gr\u00fcsch",
    "wof:placetype":"venue"
},
  "geometry": {"coordinates":[9.737101,52.374653],"type":"Point"}
}