{
  "type": "Feature",
  "properties": {
    "iso:country":"DE",
    "sg:address":"Otto-Nagel-Str. 15",
    "sg:city":"Berlin",
    "sg:postcode":"12683",
    "sg:province":"Berlin",
    "wof:name":"Dr. Med. J. Schulz",
    "wof:placetype":"venue"
},
  "geometry": {"coordinates":[13.551589,52.517258],"type":"Point"}
}