{
  "type": "Feature",
  "properties": {
    "iso:country":"DE",
    "sg:address":"Anton-Schranz-Str. 1",
    "sg:city":"Pfaffenhofen",
    "sg:phone":"+49 8441/2103",
    "sg:postcode":"85276",
    "sg:province":"Bayern",
    "wof:name":"Ilmtaler Transportbeton Gmbh & Co.",
    "wof:placetype":"venue"
},
  "geometry": {"coordinates":[11.5090532303,48.5463752747],"type":"Point"}
}