{
  "type": "Feature",
  "properties": {
    "iso:country":"DE",
    "sg:address":"Resedenweg 11",
    "sg:city":"Ettlingen",
    "sg:phone":"+49 7243/99533",
    "sg:postcode":"76275",
    "sg:province":"Baden-W\u00fcrttemberg",
    "wof:name":"Dr. Horst Dentz Rechtsanwalt",
    "wof:placetype":"venue"
},
  "geometry": {"coordinates":[8.3625612259,48.9241256714],"type":"Point"}
}