{
  "type": "Feature",
  "properties": {
    "iso:country":"DE",
    "sg:address":"Raiffeisenstr. 8",
    "sg:city":"Dudenhofen",
    "sg:phone":"+49 6232/65360",
    "sg:postcode":"67373",
    "sg:province":"Rheinland-Pfalz",
    "wof:name":"Gaspema Gastronomie-spezial- Maschinen Und Einrichtungs-",
    "wof:placetype":"venue"
},
  "geometry": {"coordinates":[8.39158,49.317505],"type":"Point"}
}