{
  "type": "Feature",
  "properties": {
    "iso:country":"DE",
    "sg:address":"Thorwaldsenstr. 43",
    "sg:city":"Frankfurt",
    "sg:phone":"+49 69/632772",
    "sg:postcode":"60596",
    "sg:province":"Hessen",
    "wof:name":"Mkm Vertriebsgesellschaft Mbh",
    "wof:placetype":"venue"
},
  "geometry": {"coordinates":[8.673741,50.098026],"type":"Point"}
}