{
  "type": "Feature",
  "properties": {
    "iso:country":"DE",
    "sg:address":"Kilian-Leib-Str. 48",
    "sg:city":"Eichst\u00e4tt",
    "sg:phone":"+49 8421/4355",
    "sg:postcode":"85072",
    "sg:province":"Bayern",
    "wof:name":"Bernhard Schleicher Steuerberater",
    "wof:placetype":"venue"
},
  "geometry": {"coordinates":[11.1662044525,48.882106781],"type":"Point"}
}