{
  "type": "Feature",
  "properties": {
    "iso:country":"DE",
    "sg:address":"Ponauer Str. 4",
    "sg:city":"Hengersberg",
    "sg:phone":"+49 9901/94920",
    "sg:postcode":"94491",
    "sg:province":"Bayern",
    "wof:name":"Josef M\u00dcller Werkzeug-undformenbau Gmbh",
    "wof:placetype":"venue"
},
  "geometry": {"coordinates":[13.054574,48.760426],"type":"Point"}
}