{
  "type": "Feature",
  "properties": {
    "iso:country":"DE",
    "sg:address":"Hasengasse 5 -7",
    "sg:city":"Frankfurt",
    "sg:phone":"+49 69/284309",
    "sg:postcode":"60311",
    "sg:province":"Hessen",
    "wof:name":"E. Keller",
    "wof:placetype":"venue"
},
  "geometry": {"coordinates":[8.683875,50.112762],"type":"Point"}
}