{
  "type": "Feature",
  "properties": {
    "iso:country":"DE",
    "sg:address":"Nikolaus-Otto-Str. 6",
    "sg:city":"Meerbusch",
    "sg:phone":"+49 2159/910760",
    "sg:postcode":"40670",
    "sg:province":"Nordrhein-Westfalen",
    "wof:name":"Willi Siegel E. K. Inh. Ralf Silz",
    "wof:placetype":"venue"
},
  "geometry": {"coordinates":[6.6164870262,51.2744064331],"type":"Point"}
}