{
  "type": "Feature",
  "properties": {
    "iso:country":"DE",
    "sg:address":"Solinger Str. 48",
    "sg:city":"Wuppertal",
    "sg:phone":"+49 202/473464",
    "sg:postcode":"42349",
    "sg:province":"Nordrhein-Westfalen",
    "wof:name":"G. Langensiepen",
    "wof:placetype":"venue"
},
  "geometry": {"coordinates":[7.1228289604,51.2044219971],"type":"Point"}
}