{
  "type": "Feature",
  "properties": {
    "iso:country":"DE",
    "sg:address":"Kl\u00f6sgeskamp 11",
    "sg:city":"Kaarst",
    "sg:phone":"+49 2131/601664",
    "sg:postcode":"41564",
    "sg:province":"Nordrhein-Westfalen",
    "wof:name":"Gerd Z\u00f6rb Gmbh",
    "wof:placetype":"venue"
},
  "geometry": {"coordinates":[6.587327,51.222023],"type":"Point"}
}