{
  "type": "Feature",
  "properties": {
    "iso:country":"DE",
    "sg:address":"Karmelitenstr. 36",
    "sg:city":"W\u00fcrzburg",
    "sg:postcode":"97070",
    "sg:province":"Bayern",
    "wof:name":"Eid Verwaltungsges. Mbh",
    "wof:placetype":"venue"
},
  "geometry": {"coordinates":[9.9271945953,49.7956161499],"type":"Point"}
}