{
  "type": "Feature",
  "properties": {
    "iso:country":"DE",
    "sg:address":"Nordel 5a",
    "sg:city":"Hilter",
    "sg:phone":"+49 5424/23400",
    "sg:postcode":"49176",
    "sg:province":"Niedersachsen",
    "wof:name":"Mev Elektronik Service Gmbh",
    "wof:placetype":"venue"
},
  "geometry": {"coordinates":[8.157466,52.131699],"type":"Point"}
}