{
  "type": "Feature",
  "properties": {
    "iso:country":"DE",
    "sg:address":"Haustenbecker Str. 3",
    "sg:city":"Isenb\u00fcttel",
    "sg:postcode":"38550",
    "sg:province":"Niedersachsen",
    "wof:name":"Pension Und Hofcafe Gehrenkamp Kg",
    "wof:placetype":"venue"
},
  "geometry": {"coordinates":[10.5928926468,52.4350624084],"type":"Point"}
}