{
  "type": "Feature",
  "properties": {
    "iso:country":"DE",
    "sg:address":"Breitestr. 10",
    "sg:city":"Engen",
    "sg:phone":"+49 7733/5999",
    "sg:postcode":"78234",
    "sg:province":"Baden-W\u00fcrttemberg",
    "wof:name":"Dietmar Wenin",
    "wof:placetype":"venue"
},
  "geometry": {"coordinates":[8.774140358,47.8556442261],"type":"Point"}
}