{
  "type": "Feature",
  "properties": {
    "iso:country":"DE",
    "sg:address":"Akademiestr. 46",
    "sg:city":"Karlsruhe",
    "sg:phone":"+49 721/9131415",
    "sg:postcode":"76133",
    "sg:province":"Baden-W\u00fcrttemberg",
    "wof:name":"Triton",
    "wof:placetype":"venue"
},
  "geometry": {"coordinates":[8.393203,49.010994],"type":"Point"}
}