{
  "type": "Feature",
  "properties": {
    "iso:country":"DE",
    "sg:address":"Loher Str. 1",
    "sg:city":"Schwelm",
    "sg:postcode":"58332",
    "sg:province":"Nordrhein-Westfalen",
    "wof:name":"Astram Anlagentechnik Gmbh",
    "wof:placetype":"venue"
},
  "geometry": {"coordinates":[7.29451,51.291283],"type":"Point"}
}