{
  "type": "Feature",
  "properties": {
    "iso:country":"DE",
    "sg:address":"Am Tannenw\u00e4ldchen 28",
    "sg:city":"Erfurt",
    "sg:phone":"+49 361/3733174",
    "sg:postcode":"99096",
    "sg:province":"Th\u00fcringen",
    "wof:name":"Hotel-gasthaus Am Bismarckturm",
    "wof:placetype":"venue"
},
  "geometry": {"coordinates":[11.0408639908,50.9506835938],"type":"Point"}
}