{
  "type": "Feature",
  "properties": {
    "iso:country":"DE",
    "sg:address":"Reichsstr. 23",
    "sg:city":"Freudenstadt",
    "sg:phone":"+49 7441/2186",
    "sg:postcode":"72250",
    "sg:province":"Baden-W\u00fcrttemberg",
    "wof:name":"M. Bleicher",
    "wof:placetype":"venue"
},
  "geometry": {"coordinates":[8.4141168594,48.462688446],"type":"Point"}
}