{
  "type": "Feature",
  "properties": {
    "iso:country":"DE",
    "sg:address":"Schillerstr. 5",
    "sg:city":"Wetzlar",
    "sg:phone":"+49 6441/33051",
    "sg:postcode":"35584",
    "sg:province":"Hessen",
    "wof:name":"Seconic Gmbh Fertigungstechnik F\u00fcr Die",
    "wof:placetype":"venue"
},
  "geometry": {"coordinates":[8.517647,50.585186],"type":"Point"}
}