{
  "type": "Feature",
  "properties": {
    "iso:country":"DE",
    "sg:address":"Johann-Sch\u00fctte-Str. 9",
    "sg:city":"Mannheim",
    "sg:phone":"+49 621/787440",
    "sg:postcode":"68307",
    "sg:province":"Baden-W\u00fcrttemberg",
    "wof:name":"Pizzeria Da Leo",
    "wof:placetype":"venue"
},
  "geometry": {"coordinates":[8.4750289917,49.5479621887],"type":"Point"}
}