{
  "type": "Feature",
  "properties": {
    "iso:country":"DE",
    "sg:address":"Weseler Str. 78",
    "sg:city":"D\u00fclmen",
    "sg:phone":"+49 2590/223",
    "sg:postcode":"48249",
    "sg:province":"Nordrhein-Westfalen",
    "wof:name":"Heinrich H\u00f6lscher",
    "wof:placetype":"venue"
},
  "geometry": {"coordinates":[7.37022686,51.865070343],"type":"Point"}
}