{
  "type": "Feature",
  "properties": {
    "iso:country":"DE",
    "sg:address":"Streitwalder Str. 4",
    "sg:city":"Frohburg",
    "sg:phone":"+49 34348/60760",
    "sg:postcode":"04654",
    "sg:province":"Sachsen",
    "wof:name":"H. Musch",
    "wof:placetype":"venue"
},
  "geometry": {"coordinates":[12.5568742752,51.0524711609],"type":"Point"}
}