{
  "type": "Feature",
  "properties": {
    "iso:country":"DE",
    "sg:address":"Ro\u00dfplan 17",
    "sg:city":"Altenburg",
    "sg:phone":"+49 3447/500626",
    "sg:postcode":"04600",
    "sg:province":"Th\u00fcringen",
    "wof:name":"Casino",
    "wof:placetype":"venue"
},
  "geometry": {"coordinates":[12.4327077866,50.9829673767],"type":"Point"}
}