{
  "type": "Feature",
  "properties": {
    "iso:country":"DE",
    "sg:address":"Dr.-Wilhelm-K\u00fclz-Str. 12",
    "sg:city":"P\u00f6\u00dfneck",
    "sg:phone":"+49 3647/421334",
    "sg:postcode":"07381",
    "sg:province":"Th\u00fcringen",
    "wof:name":"Horst Rehe Tischlerei",
    "wof:placetype":"venue"
},
  "geometry": {"coordinates":[11.589593,50.693047],"type":"Point"}
}