{
  "type": "Feature",
  "properties": {
    "iso:country":"DE",
    "sg:address":"Max-Eyth-Str. 55",
    "sg:city":"Kirchheim",
    "sg:phone":"+49 7021/44516",
    "sg:postcode":"73230",
    "sg:province":"Baden-W\u00fcrttemberg",
    "wof:name":"Autoteleshop Und Kommunika- Tions-organisation Und",
    "wof:placetype":"venue"
},
  "geometry": {"coordinates":[9.4533061981,48.6484375],"type":"Point"}
}