{
  "type": "Feature",
  "properties": {
    "iso:country":"DE",
    "sg:address":"Neue Ziegelh\u00fctte 4",
    "sg:city":"Waldm\u00fcnchen",
    "sg:phone":"+49 9972/517",
    "sg:postcode":"93449",
    "sg:province":"Bayern",
    "wof:name":"Josef Dietl",
    "wof:placetype":"venue"
},
  "geometry": {"coordinates":[12.6938743591,49.3922348022],"type":"Point"}
}