{
  "type": "Feature",
  "properties": {
    "iso:country":"DE",
    "sg:address":"Am Lerchenfeld 30",
    "sg:city":"Neukirchen-Vluyn",
    "sg:phone":"+49 2845/4774",
    "sg:postcode":"47506",
    "sg:province":"Nordrhein-Westfalen",
    "wof:name":"Oldtime Jazz",
    "wof:placetype":"venue"
},
  "geometry": {"coordinates":[6.5808358192,51.4560852051],"type":"Point"}
}