{
  "type": "Feature",
  "properties": {
    "iso:country":"DE",
    "sg:address":"Bahnhofstr. 10",
    "sg:city":"Bad Arolsen",
    "sg:phone":"+49 5691/3741",
    "sg:postcode":"34454",
    "sg:province":"Hessen",
    "wof:name":"Werner Panning",
    "wof:placetype":"venue"
},
  "geometry": {"coordinates":[9.014131546,51.3806152344],"type":"Point"}
}