{
  "type": "Feature",
  "properties": {
    "iso:country":"DE",
    "sg:address":"Gutenbergring 49B",
    "sg:city":"Norderstedt",
    "sg:phone":"+49 40/52886833",
    "sg:postcode":"22848",
    "sg:province":"Schleswig-Holstein",
    "wof:name":"Buga Schlie\u00dfsysteme Ag",
    "wof:placetype":"venue"
},
  "geometry": {"coordinates":[9.9874334335,53.6590805054],"type":"Point"}
}