{
  "type": "Feature",
  "properties": {
    "iso:country":"DE",
    "sg:address":"Allmersbacher Str.",
    "sg:city":"Allmersbach",
    "sg:phone":"+49 7191/56678",
    "sg:postcode":"71573",
    "sg:province":"Baden-W\u00fcrttemberg",
    "wof:name":"Penny Markt Gmbh",
    "wof:placetype":"venue"
},
  "geometry": {"coordinates":[9.4825849533,48.9082641602],"type":"Point"}
}