{
  "type": "Feature",
  "properties": {
    "iso:country":"DE",
    "sg:address":"Dorfstr. 3c",
    "sg:city":"Isernhagen",
    "sg:phone":"+49 5139/892570",
    "sg:postcode":"30916",
    "sg:province":"Niedersachsen",
    "wof:name":"Rolf Georg Krogmeyer Architekt",
    "wof:placetype":"venue"
},
  "geometry": {"coordinates":[9.832222,52.467312],"type":"Point"}
}