{
  "type": "Feature",
  "properties": {
    "iso:country":"DE",
    "sg:address":"Zum Schw\u00e4rmshof 15",
    "sg:city":"Neunkirchen-Seelscheid",
    "sg:phone":"+49 2247/1477",
    "sg:postcode":"53819",
    "sg:province":"Nordrhein-Westfalen",
    "wof:name":"M. Lemmen",
    "wof:placetype":"venue"
},
  "geometry": {"coordinates":[7.370457,50.869164],"type":"Point"}
}