{
  "type": "Feature",
  "properties": {
    "iso:country":"DE",
    "sg:address":"89567",
    "sg:city":"Sontheim",
    "sg:phone":"+49 7325/6095",
    "sg:postcode":"89567",
    "sg:province":"Baden-W\u00fcrttemberg",
    "wof:name":"Raiffeisenbank Brenztal Eg",
    "wof:placetype":"venue"
},
  "geometry": {"coordinates":[10.2731,48.552052],"type":"Point"}
}