{
  "type": "Feature",
  "properties": {
    "iso:country":"DE",
    "sg:address":"Ingolst\u00e4dter Str. 1",
    "sg:city":"Pfaffenhofen",
    "sg:phone":"+49 8441/9860",
    "sg:postcode":"85276",
    "sg:province":"Bayern",
    "wof:name":"Michael Weidner Kg",
    "wof:placetype":"venue"
},
  "geometry": {"coordinates":[11.5066404343,48.5302314758],"type":"Point"}
}