{
  "type": "Feature",
  "properties": {
    "iso:country":"DE",
    "sg:address":"Torfstr. 12",
    "sg:city":"Berlin",
    "sg:phone":"+49 30/45494655",
    "sg:postcode":"13353",
    "sg:province":"Berlin",
    "wof:name":"Mckb General\u00fcbernehmer- Leistungen Komplett Bau Gmbh",
    "wof:placetype":"venue"
},
  "geometry": {"coordinates":[13.35184,52.540657],"type":"Point"}
}