{
  "type": "Feature",
  "properties": {
    "iso:country":"DE",
    "sg:address":"Lindenstr. 5",
    "sg:city":"Ebeleben",
    "sg:phone":"+49 4938/4324050",
    "sg:postcode":"99713",
    "sg:province":"Th\u00fcringen",
    "wof:name":"Peter Harloff Rohrleitungs-, Behaelter- U. Apparatebau",
    "wof:placetype":"venue"
},
  "geometry": {"coordinates":[12.209052,53.819355],"type":"Point"}
}