{
  "type": "Feature",
  "properties": {
    "iso:country":"DE",
    "sg:address":"Hindenburgstr. 4",
    "sg:city":"Gronau",
    "sg:phone":"+49 2562/4584",
    "sg:postcode":"48599",
    "sg:province":"Nordrhein-Westfalen",
    "wof:name":"Heinrich Walfort",
    "wof:placetype":"venue"
},
  "geometry": {"coordinates":[7.0431871414,52.2216758728],"type":"Point"}
}