{
  "type": "Feature",
  "properties": {
    "iso:country":"DE",
    "sg:address":"Aachener Str. 181",
    "sg:city":"Baesweiler",
    "sg:phone":"+49 2401/2380",
    "sg:postcode":"52499",
    "sg:province":"Nordrhein-Westfalen",
    "wof:name":"Richard Und Hans-peter Lowis",
    "wof:placetype":"venue"
},
  "geometry": {"coordinates":[6.1887321472,50.9070777893],"type":"Point"}
}