{
  "type": "Feature",
  "properties": {
    "iso:country":"DE",
    "sg:address":"Gausekampweg 2",
    "sg:city":"Halle",
    "sg:phone":"+49 5201/816310",
    "sg:postcode":"33790",
    "sg:province":"Nordrhein-Westfalen",
    "wof:name":"Laibach Stuben",
    "wof:placetype":"venue"
},
  "geometry": {"coordinates":[8.3526926041,52.0624275208],"type":"Point"}
}