{
  "type": "Feature",
  "properties": {
    "iso:country":"DE",
    "sg:address":"Asholts Hof 1",
    "sg:city":"Bielefeld",
    "sg:phone":"+49 521/442394",
    "sg:postcode":"33649",
    "sg:province":"Nordrhein-Westfalen",
    "wof:name":"Friedrich Fischer",
    "wof:placetype":"venue"
},
  "geometry": {"coordinates":[8.477981,51.968178],"type":"Point"}
}