{
  "type": "Feature",
  "properties": {
    "iso:country":"DE",
    "sg:address":"Berlinerstr 42",
    "sg:city":"D - Asperg",
    "sg:phone":"+49 7141/661315",
    "sg:postcode":"71679",
    "sg:province":"Baden-W\u00fcrttemberg",
    "wof:name":"Ferienwohnungen Im Engadin",
    "wof:placetype":"venue"
},
  "geometry": {"coordinates":[9.1299667358,48.9015464783],"type":"Point"}
}