{
  "type": "Feature",
  "properties": {
    "iso:country":"DE",
    "sg:address":"Amselweg 14",
    "sg:city":"Isenb\u00fcttel",
    "sg:phone":"+49 5374/4481",
    "sg:postcode":"38550",
    "sg:province":"Niedersachsen",
    "wof:name":"H. Und G. Hanisch",
    "wof:placetype":"venue"
},
  "geometry": {"coordinates":[10.5817775726,52.4294319153],"type":"Point"}
}