{
  "type": "Feature",
  "properties": {
    "iso:country":"DE",
    "sg:address":"M\u00fcddersheimer Str. 4",
    "sg:city":"Weilerswist",
    "sg:phone":"+49 2254/2746",
    "sg:postcode":"53919",
    "sg:province":"Nordrhein-Westfalen",
    "wof:name":"Heinz Kastenholz",
    "wof:placetype":"venue"
},
  "geometry": {"coordinates":[6.8249921799,50.7406158447],"type":"Point"}
}