{
  "type": "Feature",
  "properties": {
    "iso:country":"DE",
    "sg:address":"Kirchstr. 3",
    "sg:city":"Steinach",
    "sg:phone":"+49 36762/32595",
    "sg:postcode":"96523",
    "sg:province":"Th\u00fcringen",
    "wof:name":"Manfred Otto",
    "wof:placetype":"venue"
},
  "geometry": {"coordinates":[11.1562862396,50.4318847656],"type":"Point"}
}