{
  "type": "Feature",
  "properties": {
    "iso:country":"DE",
    "sg:address":"Am M\u00fchlweg 13",
    "sg:city":"Haunetal",
    "sg:phone":"+49 6673/782",
    "sg:postcode":"36166",
    "sg:province":"Hessen",
    "wof:name":"W. Billing",
    "wof:placetype":"venue"
},
  "geometry": {"coordinates":[9.667640686,50.7396354675],"type":"Point"}
}