{
  "type": "Feature",
  "properties": {
    "iso:country":"DE",
    "sg:address":"Hauptstr. 36",
    "sg:city":"Hornburg",
    "sg:phone":"+49 34776/20367",
    "sg:postcode":"06295",
    "sg:province":"Sachsen-Anhalt",
    "wof:name":"T. Hendrich",
    "wof:placetype":"venue"
},
  "geometry": {"coordinates":[11.58778,51.454098],"type":"Point"}
}