{
  "type": "Feature",
  "properties": {
    "iso:country":"DE",
    "sg:address":"Josefstr. 1",
    "sg:city":"Heinsberg",
    "sg:postcode":"52525",
    "sg:province":"Nordrhein-Westfalen",
    "wof:name":"Lfg Rheinland Agrarversicherungsmakler Ohg",
    "wof:placetype":"venue"
},
  "geometry": {"coordinates":[6.0940852165,51.0608634949],"type":"Point"}
}