{
  "type": "Feature",
  "properties": {
    "iso:country":"DE",
    "sg:address":"Bergener Ring 37",
    "sg:city":"Ottendorf-Okrilla",
    "sg:phone":"+49 35205/6030",
    "sg:postcode":"01458",
    "sg:province":"Sachsen",
    "wof:name":"Klaus K\u00f6nig Gmbh",
    "wof:placetype":"venue"
},
  "geometry": {"coordinates":[13.839223,51.183147],"type":"Point"}
}