{
  "type": "Feature",
  "properties": {
    "iso:country":"DE",
    "sg:address":"Postfach",
    "sg:city":"Wendisch Rietz",
    "sg:phone":"+49 33679/401",
    "sg:postcode":"15861",
    "sg:province":"Brandenburg",
    "wof:name":"Camping Schwarzhorn",
    "wof:placetype":"venue"
},
  "geometry": {"coordinates":[-78.043617,41.36713],"type":"Point"}
}