{
  "type": "Feature",
  "properties": {
    "iso:country":"DE",
    "sg:address":"Regensburger Str. 3",
    "sg:city":"Berlin",
    "sg:phone":"+49 30/2351710",
    "sg:postcode":"10777",
    "sg:province":"Berlin",
    "wof:name":"Pauli Data Inh. Roswitha Pauli",
    "wof:placetype":"venue"
},
  "geometry": {"coordinates":[13.339784,52.49596],"type":"Point"}
}