{
  "type": "Feature",
  "properties": {
    "iso:country":"DE",
    "sg:address":"Bahnhofstr. 51",
    "sg:city":"Zossen",
    "sg:phone":"+49 3377/301101",
    "sg:postcode":"15806",
    "sg:province":"Brandenburg",
    "wof:name":"M. Kreher Rechtsanwalt",
    "wof:placetype":"venue"
},
  "geometry": {"coordinates":[13.444270134,52.2149353027],"type":"Point"}
}