{
  "type": "Feature",
  "properties": {
    "iso:country":"DE",
    "sg:address":"Teichstr. 20",
    "sg:city":"D\u00f6lbau",
    "sg:postcode":"06184",
    "sg:province":"Sachsen-Anhalt",
    "wof:name":"Harald Fischer",
    "wof:placetype":"venue"
},
  "geometry": {"coordinates":[12.098115,51.436375],"type":"Point"}
}