{
  "type": "Feature",
  "properties": {
    "iso:country":"DE",
    "sg:address":"Schleusinger Str. 77a",
    "sg:city":"Manebach",
    "sg:postcode":"98693",
    "sg:province":"Th\u00fcringen",
    "wof:name":"Dr. Med. Astrid Deber",
    "wof:placetype":"venue"
},
  "geometry": {"coordinates":[10.85944,50.675808],"type":"Point"}
}