{
  "type": "Feature",
  "properties": {
    "iso:country":"DE",
    "sg:address":"Herzog-Ludwig-Str. 24",
    "sg:city":"Neustadt",
    "sg:phone":"+49 9445/7066",
    "sg:postcode":"93333",
    "sg:province":"Bayern",
    "wof:name":"A. Hausd\u00f6rfer",
    "wof:placetype":"venue"
},
  "geometry": {"coordinates":[11.763924,48.809734],"type":"Point"}
}