{
  "type": "Feature",
  "properties": {
    "iso:country":"DE",
    "sg:address":"Graseweg 4",
    "sg:city":"Hann. M\u00fcnden",
    "sg:phone":"+49 5545/6090",
    "sg:postcode":"34346",
    "sg:province":"Niedersachsen",
    "wof:name":"Aldi Gmbh & Co. Kg",
    "wof:placetype":"venue"
},
  "geometry": {"coordinates":[9.7613143921,51.3927650452],"type":"Point"}
}