{
  "type": "Feature",
  "properties": {
    "iso:country":"DE",
    "sg:address":"Riedemannweg 58",
    "sg:city":"Berlin",
    "sg:phone":"+49 30/3497770",
    "sg:postcode":"13627",
    "sg:province":"Berlin",
    "wof:name":"Comtec Gmbh",
    "wof:placetype":"venue"
},
  "geometry": {"coordinates":[13.3163614273,52.5454330444],"type":"Point"}
}