{
  "type": "Feature",
  "properties": {
    "iso:country":"DE",
    "sg:address":"Barf\u00fc\u00dferstr. 5",
    "sg:city":"Nordhausen",
    "sg:phone":"+49 3631/972903",
    "sg:postcode":"99734",
    "sg:province":"Th\u00fcringen",
    "wof:name":"Udo Eidam",
    "wof:placetype":"venue"
},
  "geometry": {"coordinates":[10.792327,51.50428],"type":"Point"}
}