{
  "type": "Feature",
  "properties": {
    "iso:country":"DE",
    "sg:address":"Stephanskirchener Str. 16",
    "sg:city":"M\u00fcnchen",
    "sg:phone":"+49 89/6891651",
    "sg:postcode":"81669",
    "sg:province":"Bayern",
    "wof:name":"Huber Gmbh Elektro- Installation",
    "wof:placetype":"venue"
},
  "geometry": {"coordinates":[11.612929,48.113022],"type":"Point"}
}