{
  "type": "Feature",
  "properties": {
    "iso:country":"DE",
    "sg:address":"V\u00f6hrenbacher Str. 14a",
    "sg:city":"Villingen-Schwenningen",
    "sg:phone":"+49 7721/55138",
    "sg:postcode":"78050",
    "sg:province":"Baden-W\u00fcrttemberg",
    "wof:name":"Richard Kienzler",
    "wof:placetype":"venue"
},
  "geometry": {"coordinates":[8.4518508911,48.059589386],"type":"Point"}
}