{
  "type": "Feature",
  "properties": {
    "iso:country":"DE",
    "sg:address":"Vorstadtstr. 30",
    "sg:city":"Saarbr\u00fccken",
    "sg:phone":"+49 681/53388",
    "sg:postcode":"66117",
    "sg:province":"Saarland",
    "wof:name":"Arthur Hertel",
    "wof:placetype":"venue"
},
  "geometry": {"coordinates":[6.98553,49.231911],"type":"Point"}
}