{
  "type": "Feature",
  "properties": {
    "iso:country":"DE",
    "sg:address":"G\u00f6ddertzgarten 42",
    "sg:city":"Meckenheim",
    "sg:phone":"+49 2225/3588",
    "sg:postcode":"53340",
    "sg:province":"Nordrhein-Westfalen",
    "wof:name":"Urbs Et Orbis Klaus Semmel Buch-antiquariat",
    "wof:placetype":"venue"
},
  "geometry": {"coordinates":[7.051815033,50.6319847107],"type":"Point"}
}