{
  "type": "Feature",
  "properties": {
    "iso:country":"DE",
    "sg:address":"Br\u00fcckh\u00f6rn 18a",
    "sg:city":"Emden",
    "sg:phone":"+49 4921/25328",
    "sg:postcode":"26725",
    "sg:province":"Niedersachsen",
    "wof:name":"Diederike Andreesen",
    "wof:placetype":"venue"
},
  "geometry": {"coordinates":[7.254334,53.377892],"type":"Point"}
}