{
  "type": "Feature",
  "properties": {
    "iso:country":"DE",
    "sg:address":"Tilsiter Str. 4-6",
    "sg:city":"Sindelfingen",
    "sg:postcode":"71065",
    "sg:province":"Baden-W\u00fcrttemberg",
    "wof:name":"Genericom Software Gmbh",
    "wof:placetype":"venue"
},
  "geometry": {"coordinates":[9.028065,48.702423],"type":"Point"}
}