{
  "type": "Feature",
  "properties": {
    "iso:country":"DE",
    "sg:address":"Einsiedler Hauptstr. 30",
    "sg:city":"Chemnitz",
    "sg:postcode":"09123",
    "sg:province":"Sachsen",
    "wof:name":"Dw-vertriebs Ohg",
    "wof:placetype":"venue"
},
  "geometry": {"coordinates":[12.9725399017,50.7697105408],"type":"Point"}
}