{
  "type": "Feature",
  "properties": {
    "iso:country":"DE",
    "sg:address":"Hainstr. 86",
    "sg:city":"Biedenkopf",
    "sg:phone":"+49 6461/2467",
    "sg:postcode":"35216",
    "sg:province":"Hessen",
    "wof:name":"Kath. Pfarramt St. Josef",
    "wof:placetype":"venue"
},
  "geometry": {"coordinates":[8.5220947266,50.9150657654],"type":"Point"}
}