{
  "type": "Feature",
  "properties": {
    "iso:country":"DE",
    "sg:address":"Luisenstr. 1a",
    "sg:city":"Baden-Baden",
    "sg:phone":"+49 7221/22317",
    "sg:postcode":"76530",
    "sg:province":"Baden-W\u00fcrttemberg",
    "wof:name":"Tiffany",
    "wof:placetype":"venue"
},
  "geometry": {"coordinates":[8.238215,48.761673],"type":"Point"}
}