{
  "type": "Feature",
  "properties": {
    "iso:country":"DE",
    "sg:address":"Holzmarkt 16",
    "sg:city":"Bad Windsheim",
    "sg:phone":"+49 9841/5031",
    "sg:postcode":"91438",
    "sg:province":"Bayern",
    "wof:name":"Klug Ohg",
    "wof:placetype":"venue"
},
  "geometry": {"coordinates":[10.417154,49.500328],"type":"Point"}
}