{
  "type": "Feature",
  "properties": {
    "iso:country":"DE",
    "sg:address":"Steglitzer Damm 5",
    "sg:city":"Berlin",
    "sg:phone":"+49 30/7959468",
    "sg:postcode":"12169",
    "sg:province":"Berlin",
    "wof:name":"Dietmar Gielow",
    "wof:placetype":"venue"
},
  "geometry": {"coordinates":[13.336466,52.451332],"type":"Point"}
}