{
  "type": "Feature",
  "properties": {
    "iso:country":"DE",
    "sg:address":"Am Qualisch 24d",
    "sg:city":"Wei\u00dfwasser",
    "sg:phone":"+49 3576/208303",
    "sg:postcode":"02943",
    "sg:province":"Sachsen",
    "wof:name":"Dr. Med. Klaus-dieter Karg",
    "wof:placetype":"venue"
},
  "geometry": {"coordinates":[14.636171,51.515537],"type":"Point"}
}