{
  "type": "Feature",
  "properties": {
    "iso:country":"DE",
    "sg:address":"Bachstr. 6",
    "sg:city":"Winningen",
    "sg:phone":"+49 2606/499",
    "sg:postcode":"56333",
    "sg:province":"Rheinland-Pfalz",
    "wof:name":"Brunnenklause",
    "wof:placetype":"venue"
},
  "geometry": {"coordinates":[7.5196471214,50.3131141663],"type":"Point"}
}