{
  "type": "Feature",
  "properties": {
    "iso:country":"DE",
    "sg:address":"Merowingerstr. 15",
    "sg:city":"Mannheim",
    "sg:phone":"+49 621/716970",
    "sg:postcode":"68259",
    "sg:province":"Baden-W\u00fcrttemberg",
    "wof:name":"Deutsches Bau- Rechenzentrum Gmbh",
    "wof:placetype":"venue"
},
  "geometry": {"coordinates":[8.5566034317,49.4978599548],"type":"Point"}
}