{
  "type": "Feature",
  "properties": {
    "iso:country":"DE",
    "sg:address":"Am Kiefernschlag 9",
    "sg:city":"Schwabach",
    "sg:phone":"+49 9122/98890",
    "sg:postcode":"91126",
    "sg:province":"Bayern",
    "wof:name":"Bkm Pr\u00e4zisionswerkzeuge Stanz- Und Biegeteile Gmbh",
    "wof:placetype":"venue"
},
  "geometry": {"coordinates":[11.055918,49.318512],"type":"Point"}
}