{
  "type": "Feature",
  "properties": {
    "iso:country":"DE",
    "sg:address":"Siedlertrift 1",
    "sg:city":"Brandenburg",
    "sg:phone":"+49 3381/714736",
    "sg:postcode":"14772",
    "sg:province":"Brandenburg",
    "wof:name":"Kr\u00fcger Transport Gmbh",
    "wof:placetype":"venue"
},
  "geometry": {"coordinates":[12.5170602798,52.449760437],"type":"Point"}
}