{
  "type": "Feature",
  "properties": {
    "iso:country":"DE",
    "sg:address":"Danziger Str. 33",
    "sg:city":"Friedberg",
    "sg:phone":"+49 6031/3728",
    "sg:postcode":"61169",
    "sg:province":"Hessen",
    "wof:name":"J. Balcarek Steuerberater",
    "wof:placetype":"venue"
},
  "geometry": {"coordinates":[8.7589845657,50.3273353577],"type":"Point"}
}