{
  "type": "Feature",
  "properties": {
    "iso:country":"DE",
    "sg:address":"Hochk\u00f6nigweg 10a",
    "sg:city":"Berlin",
    "sg:phone":"+49 4930/7039696",
    "sg:postcode":"12349",
    "sg:province":"Berlin",
    "wof:name":"E F A Elektro-und Fernmeldeanlagen Gmbh",
    "wof:placetype":"venue"
},
  "geometry": {"coordinates":[13.4115085602,52.438243866],"type":"Point"}
}