{
  "type": "Feature",
  "properties": {
    "iso:country":"DE",
    "sg:address":"J\u00fcrgensplatz 46",
    "sg:city":"D\u00fcsseldorf",
    "sg:phone":"+49 211/390960",
    "sg:postcode":"40219",
    "sg:province":"Nordrhein-Westfalen",
    "wof:name":"Cic Cityimmobilien-contor Gmbh",
    "wof:placetype":"venue"
},
  "geometry": {"coordinates":[6.7686867714,51.2161140442],"type":"Point"}
}