{
  "type": "Feature",
  "properties": {
    "iso:country":"DE",
    "sg:address":"Stadtweg 5",
    "sg:city":"Berkatal",
    "sg:phone":"+49 5652/3151",
    "sg:postcode":"37297",
    "sg:province":"Hessen",
    "wof:name":"Dreyer & Koch Handelsvertretung Gmbh",
    "wof:placetype":"venue"
},
  "geometry": {"coordinates":[9.9619760513,51.2415161133],"type":"Point"}
}