{
  "type": "Feature",
  "properties": {
    "iso:country":"DE",
    "sg:address":"Auf dem Wellerskamp 24",
    "sg:city":"Witten",
    "sg:phone":"+49 2302/89373",
    "sg:postcode":"58454",
    "sg:province":"Nordrhein-Westfalen",
    "wof:name":"Leonardo-da-vinci",
    "wof:placetype":"venue"
},
  "geometry": {"coordinates":[7.4085359573,51.4540061951],"type":"Point"}
}