{
  "type": "Feature",
  "properties": {
    "iso:country":"DE",
    "sg:address":"Marktstr. 12",
    "sg:city":"Grabow",
    "sg:phone":"+49 38756/22436",
    "sg:postcode":"19300",
    "sg:province":"Mecklenburg-Vorpommern",
    "wof:name":"Manfred Gollnik",
    "wof:placetype":"venue"
},
  "geometry": {"coordinates":[11.5625610352,53.2798538208],"type":"Point"}
}