{
  "type": "Feature",
  "properties": {
    "iso:country":"DE",
    "sg:address":"Ringer Str. 5",
    "sg:city":"Emlichheim",
    "sg:phone":"+49 5943/1222",
    "sg:postcode":"49824",
    "sg:province":"Niedersachsen",
    "wof:name":"Ring-apotheke",
    "wof:placetype":"venue"
},
  "geometry": {"coordinates":[6.85331,52.606373],"type":"Point"}
}