{
  "type": "Feature",
  "properties": {
    "iso:country":"DE",
    "sg:address":"Gibitzenhofstr. 74",
    "sg:city":"N\u00fcrnberg",
    "sg:phone":"+49 911/411738",
    "sg:postcode":"90443",
    "sg:province":"Bayern",
    "wof:name":"Uncle Sam Shop",
    "wof:placetype":"venue"
},
  "geometry": {"coordinates":[11.067607,49.436813],"type":"Point"}
}