{
  "type": "Feature",
  "properties": {
    "iso:country":"DE",
    "sg:address":"Juliuspromenade 64",
    "sg:city":"W\u00fcrzburg",
    "sg:phone":"+49 931/18750",
    "sg:postcode":"97070",
    "sg:province":"Bayern",
    "wof:name":"Tl Boutique Tina Langer",
    "wof:placetype":"venue"
},
  "geometry": {"coordinates":[9.931637,49.797142],"type":"Point"}
}