{
  "type": "Feature",
  "properties": {
    "iso:country":"DE",
    "sg:address":"Prinzregentenufer 9",
    "sg:city":"N\u00fcrnberg",
    "sg:phone":"+49 911/533977",
    "sg:postcode":"90489",
    "sg:province":"Bayern",
    "wof:name":"Rochow Und Partner Gbr Rechtsanw\u00e4lte",
    "wof:placetype":"venue"
},
  "geometry": {"coordinates":[11.08867836,49.4524002075],"type":"Point"}
}