{
  "type": "Feature",
  "properties": {
    "iso:country":"DE",
    "sg:address":"H\u00f6rsterholz 1",
    "sg:city":"Bochum",
    "sg:phone":"+49 234/492727",
    "sg:postcode":"44879",
    "sg:province":"Nordrhein-Westfalen",
    "wof:name":"Gerlach Ingenieur Gmbh",
    "wof:placetype":"venue"
},
  "geometry": {"coordinates":[7.146135,51.439571],"type":"Point"}
}