{
  "type": "Feature",
  "properties": {
    "iso:country":"DE",
    "sg:address":"Krayer Str. 10",
    "sg:city":"Essen",
    "sg:phone":"+49 201/500912",
    "sg:postcode":"45276",
    "sg:province":"Nordrhein-Westfalen",
    "wof:name":"Schorsch",
    "wof:placetype":"venue"
},
  "geometry": {"coordinates":[7.0768527985,51.4511222839],"type":"Point"}
}