{
  "type": "Feature",
  "properties": {
    "iso:country":"DE",
    "sg:address":"Bramfelder Chaussee 54",
    "sg:city":"Hamburg",
    "sg:postcode":"22177",
    "sg:province":"Hamburg",
    "wof:name":"Lord Spielhallen Gmbh",
    "wof:placetype":"venue"
},
  "geometry": {"coordinates":[10.0633459091,53.5964775085],"type":"Point"}
}