{
  "type": "Feature",
  "properties": {
    "iso:country":"DE",
    "sg:address":"M\u00fchlenstr. 7",
    "sg:city":"Bad Wildungen",
    "sg:phone":"+49 5621/960924",
    "sg:postcode":"34537",
    "sg:province":"Hessen",
    "wof:name":"Tanz Caf\u00e9 Bolero",
    "wof:placetype":"venue"
},
  "geometry": {"coordinates":[9.073592,51.112297],"type":"Point"}
}