{
  "type": "Feature",
  "properties": {
    "iso:country":"DE",
    "sg:address":"Oberpforte 13",
    "sg:city":"Buseck",
    "sg:phone":"+49 6408/2962",
    "sg:postcode":"35418",
    "sg:province":"Hessen",
    "wof:name":"Pizzeria Il Gabbiano",
    "wof:placetype":"venue"
},
  "geometry": {"coordinates":[8.7889156342,50.6085739136],"type":"Point"}
}