{
  "type": "Feature",
  "properties": {
    "iso:country":"DE",
    "sg:address":"Mangerstr. 37",
    "sg:city":"Potsdam",
    "sg:postcode":"14467",
    "sg:province":"Brandenburg",
    "wof:name":"Plus-planb\u00fcro F\u00fcr Umwelt- Technik Und -sanierung Gmbh",
    "wof:placetype":"venue"
},
  "geometry": {"coordinates":[13.0707807541,52.4076004028],"type":"Point"}
}