{
  "type": "Feature",
  "properties": {
    "iso:country":"DE",
    "sg:address":"Ludwigstr. 88-92",
    "sg:city":"Neu\u00f6tting",
    "sg:phone":"+49 8671/99470",
    "sg:postcode":"84524",
    "sg:province":"Bayern",
    "wof:name":"Ganzbeck Verwaltungs- Gmbh",
    "wof:placetype":"venue"
},
  "geometry": {"coordinates":[12.6882352829,48.2401847839],"type":"Point"}
}