{
  "type": "Feature",
  "properties": {
    "iso:country":"DE",
    "sg:address":"Zum Schieferstein 10",
    "sg:city":"Marienheide",
    "sg:postcode":"51709",
    "sg:province":"Nordrhein-Westfalen",
    "wof:name":"B\u00fcro F\u00fcr Bauplanung Und Messebau",
    "wof:placetype":"venue"
},
  "geometry": {"coordinates":[7.514245,51.060101],"type":"Point"}
}