{
  "type": "Feature",
  "properties": {
    "iso:country":"DE",
    "sg:address":"Planiger Str. 158",
    "sg:city":"Bad Kreuznach",
    "sg:phone":"+49 671/894440",
    "sg:postcode":"55543",
    "sg:province":"Rheinland-Pfalz",
    "wof:name":"C Und C",
    "wof:placetype":"venue"
},
  "geometry": {"coordinates":[7.8802118301,49.8512535095],"type":"Point"}
}