{
  "type": "Feature",
  "properties": {
    "iso:country":"DE",
    "sg:address":"Am Anger 1",
    "sg:city":"Remagen",
    "sg:phone":"+49 2642/280",
    "sg:postcode":"53424",
    "sg:province":"Rheinland-Pfalz",
    "wof:name":"Kath. Krankenhausb\u00fccherei Krankenhaus Maria Stern",
    "wof:placetype":"venue"
},
  "geometry": {"coordinates":[7.231655,50.575054],"type":"Point"}
}