{
  "type": "Feature",
  "properties": {
    "iso:country":"DE",
    "sg:address":"Siersburger Str. 8",
    "sg:city":"Wallerfangen",
    "sg:phone":"+49 6831/61152",
    "sg:postcode":"66798",
    "sg:province":"Saarland",
    "wof:name":"Hotellerie Waldesruh",
    "wof:placetype":"venue"
},
  "geometry": {"coordinates":[6.6760702133,49.3437652588],"type":"Point"}
}