{
  "type": "Feature",
  "properties": {
    "iso:country":"DE",
    "sg:address":"Lehmbrookweg 3",
    "sg:city":"Hamburg",
    "sg:phone":"+49 40/6684554",
    "sg:postcode":"22159",
    "sg:province":"Hamburg",
    "wof:name":"I. Markert",
    "wof:placetype":"venue"
},
  "geometry": {"coordinates":[10.1092290878,53.5946006775],"type":"Point"}
}