{
  "type": "Feature",
  "properties": {
    "iso:country":"DE",
    "sg:address":"Lehmgrubenweg 24",
    "sg:city":"Ha\u00dfloch",
    "sg:phone":"+49 6324/91036",
    "sg:postcode":"67454",
    "sg:province":"Rheinland-Pfalz",
    "wof:name":"Heinrich Kling",
    "wof:placetype":"venue"
},
  "geometry": {"coordinates":[8.250746,49.372341],"type":"Point"}
}