{
  "type": "Feature",
  "properties": {
    "iso:country":"DE",
    "sg:address":"M\u00fchlbachstr. 19",
    "sg:city":"\u00dcberlingen",
    "sg:phone":"+49 7551/7033",
    "sg:postcode":"88662",
    "sg:province":"Baden-W\u00fcrttemberg",
    "wof:name":"Thuringia Versicherungs-ag",
    "wof:placetype":"venue"
},
  "geometry": {"coordinates":[9.1731939316,47.7633895874],"type":"Point"}
}