{
  "type": "Feature",
  "properties": {
    "iso:country":"DE",
    "sg:address":"Uhlandstr. 28",
    "sg:city":"Geislingen",
    "sg:postcode":"72351",
    "sg:province":"Baden-W\u00fcrttemberg",
    "wof:name":"Dtg Design Und Technik Mit Glas Gmbh",
    "wof:placetype":"venue"
},
  "geometry": {"coordinates":[8.816717,48.286732],"type":"Point"}
}