{
  "type": "Feature",
  "properties": {
    "iso:country":"DE",
    "sg:address":"Hallesche Str. 14d",
    "sg:city":"Lieskau",
    "sg:phone":"+49 345/5511666",
    "sg:postcode":"06120",
    "sg:province":"Sachsen-Anhalt",
    "wof:name":"G. Wagner",
    "wof:placetype":"venue"
},
  "geometry": {"coordinates":[11.8677310944,51.5023765564],"type":"Point"}
}