{
  "type": "Feature",
  "properties": {
    "iso:country":"DE",
    "sg:address":"Bensheimer Str. 65",
    "sg:city":"Viernheim",
    "sg:phone":"+49 6204/8387",
    "sg:postcode":"68519",
    "sg:province":"Hessen",
    "wof:name":"H. Lang",
    "wof:placetype":"venue"
},
  "geometry": {"coordinates":[8.592948,49.543362],"type":"Point"}
}