{
  "type": "Feature",
  "properties": {
    "iso:country":"DE",
    "sg:address":"Mosbacher Str. 75 POSTFACH 2130",
    "sg:city":"Mosbach",
    "sg:phone":"+49 6261/643660",
    "sg:postcode":"74812",
    "sg:province":"Baden-W\u00fcrttemberg",
    "wof:name":"Eisengie\u00dferei Gl\u00dcckauf Gmbh",
    "wof:placetype":"venue"
},
  "geometry": {"coordinates":[9.119575,49.340569],"type":"Point"}
}