{
  "type": "Feature",
  "properties": {
    "iso:country":"DE",
    "sg:address":"F\u00fcnfminutenweg-S\u00fcd 11",
    "sg:city":"Windischleuba",
    "sg:phone":"+49 3447/85290",
    "sg:postcode":"04603",
    "sg:province":"Th\u00fcringen",
    "wof:name":"Lebenshilfe Altenburg E. V.",
    "wof:placetype":"venue"
},
  "geometry": {"coordinates":[12.461197,51.011784],"type":"Point"}
}