{
  "type": "Feature",
  "properties": {
    "iso:country":"DE",
    "sg:address":"Graf-Rantzau-Str. 17",
    "sg:city":"Breitenburg",
    "sg:phone":"+49 4821/82478",
    "sg:postcode":"25524",
    "sg:province":"Schleswig-Holstein",
    "wof:name":"Peter Matthiesen",
    "wof:placetype":"venue"
},
  "geometry": {"coordinates":[9.5046319962,53.9052734375],"type":"Point"}
}