{
  "type": "Feature",
  "properties": {
    "iso:country":"DE",
    "sg:address":"Babbergerstr. 21",
    "sg:city":"Karlsruhe",
    "sg:phone":"+49 4972/1950350",
    "sg:postcode":"76189",
    "sg:province":"Baden-W\u00fcrttemberg",
    "wof:name":"K\u00dchn Elektrotechnik Gmbh",
    "wof:placetype":"venue"
},
  "geometry": {"coordinates":[8.317582,49.005848],"type":"Point"}
}