{
  "type": "Feature",
  "properties": {
    "iso:country":"DE",
    "sg:address":"Bliesransbacher Str. 43",
    "sg:city":"Saarbr\u00fccken",
    "sg:phone":"+49 6893/2410",
    "sg:postcode":"66130",
    "sg:province":"Saarland",
    "wof:name":"Kurt Witte",
    "wof:placetype":"venue"
},
  "geometry": {"coordinates":[7.065071,49.196754],"type":"Point"}
}