{
  "type": "Feature",
  "properties": {
    "iso:country":"DE",
    "sg:address":"Gattingerstr.20",
    "sg:city":"W\u00fcrzburg",
    "sg:phone":"+49 931/619050",
    "sg:postcode":"97076",
    "sg:province":"Bayern",
    "wof:name":"Euro-friwa Gmbh",
    "wof:placetype":"venue"
},
  "geometry": {"coordinates":[9.9913578033,49.7940368652],"type":"Point"}
}