{
  "type": "Feature",
  "properties": {
    "iso:country":"DE",
    "sg:address":"Bahnhofplatz 6",
    "sg:city":"Utting",
    "sg:phone":"+49 8806/92040",
    "sg:postcode":"86919",
    "sg:province":"Bayern",
    "wof:name":"Hotel-restaurant Wittelsbacher Hof",
    "wof:placetype":"venue"
},
  "geometry": {"coordinates":[11.0934228897,48.0229568481],"type":"Point"}
}