{
  "type": "Feature",
  "properties": {
    "iso:country":"DE",
    "sg:address":"Heinzestr. 5",
    "sg:city":"Alfeld",
    "sg:phone":"+49 5181/3822",
    "sg:postcode":"31061",
    "sg:province":"Niedersachsen",
    "wof:name":"G\u00fcnter Heinrich",
    "wof:placetype":"venue"
},
  "geometry": {"coordinates":[9.832587,51.985409],"type":"Point"}
}