{
  "type": "Feature",
  "properties": {
    "iso:country":"DE",
    "sg:address":"August-Horch-Str. 2-4",
    "sg:city":"Koblenz",
    "sg:postcode":"56070",
    "sg:province":"Rheinland-Pfalz",
    "wof:name":"Dpd Denkhaus Verwaltungsgesellschaft Mbh",
    "wof:placetype":"venue"
},
  "geometry": {"coordinates":[7.5644168854,50.3862686157],"type":"Point"}
}