{
  "type": "Feature",
  "properties": {
    "iso:country":"DE",
    "sg:address":"Fritz-Reuter-Str. 30",
    "sg:city":"Norderstedt",
    "sg:phone":"+49 40/5255404",
    "sg:postcode":"22844",
    "sg:province":"Schleswig-Holstein",
    "wof:name":"Ingeborg Siemoneit Krankengymnastin",
    "wof:placetype":"venue"
},
  "geometry": {"coordinates":[10.013398,53.709579],"type":"Point"}
}