{
  "type": "Feature",
  "properties": {
    "iso:country":"DE",
    "sg:address":"Am Ellernfeld 14",
    "sg:city":"Aurich",
    "sg:phone":"+49 4941/2827",
    "sg:postcode":"26603",
    "sg:province":"Niedersachsen",
    "wof:name":"Jugendherberge Aurich",
    "wof:placetype":"venue"
},
  "geometry": {"coordinates":[7.4799480438,53.4638290405],"type":"Point"}
}