{
  "type": "Feature",
  "properties": {
    "iso:country":"DE",
    "sg:address":"Falkenweg 6",
    "sg:city":"Niedernhausen",
    "sg:postcode":"65527",
    "sg:province":"Hessen",
    "wof:name":"Osiris Media Filmproduktion 2 Gmbh",
    "wof:placetype":"venue"
},
  "geometry": {"coordinates":[8.2380475998,50.1657867432],"type":"Point"}
}