{
  "type": "Feature",
  "properties": {
    "iso:country":"DE",
    "sg:address":"In der Loh 13",
    "sg:city":"Meerbusch-Lank",
    "sg:postcode":"40668",
    "sg:province":"Nordrhein-Westfalen",
    "wof:name":"Pooch Klimatechnik",
    "wof:placetype":"venue"
},
  "geometry": {"coordinates":[6.6817860603,51.3129882812],"type":"Point"}
}