{
  "type": "Feature",
  "properties": {
    "iso:country":"DE",
    "sg:address":"L\u00fcbecker Str. 11",
    "sg:city":"Gladbeck",
    "sg:phone":"+49 2043/72897",
    "sg:postcode":"45968",
    "sg:province":"Nordrhein-Westfalen",
    "wof:name":"Dr. H.-h. Und Heide. Schneider",
    "wof:placetype":"venue"
},
  "geometry": {"coordinates":[7.0242462158,51.5466003418],"type":"Point"}
}