{
  "type": "Feature",
  "properties": {
    "iso:country":"DE",
    "sg:address":"Fuhlsb\u00fcttler Str. 737",
    "sg:city":"Hamburg",
    "sg:phone":"+49 40/591861",
    "sg:postcode":"22337",
    "sg:province":"Hamburg",
    "wof:name":"Beerdigungsb\u00fcro Beck St. Anschar Gmbh",
    "wof:placetype":"venue"
},
  "geometry": {"coordinates":[10.033855,53.619076],"type":"Point"}
}