{
  "type": "Feature",
  "properties": {
    "iso:country":"DE",
    "sg:address":"Dorfstr. 3",
    "sg:city":"Hageb\u00f6k",
    "sg:phone":"+49 38426/20246",
    "sg:postcode":"23974",
    "sg:province":"Mecklenburg-Vorpommern",
    "wof:name":"Agrargenossenschaft Hageb\u00f6k Eg",
    "wof:placetype":"venue"
},
  "geometry": {"coordinates":[11.6089,53.960442],"type":"Point"}
}