{
  "type": "Feature",
  "properties": {
    "iso:country":"DE",
    "sg:address":"Brombach 39",
    "sg:city":"Schramberg",
    "sg:phone":"+49 7422/96266",
    "sg:postcode":"78713",
    "sg:province":"Baden-W\u00fcrttemberg",
    "wof:name":"H\u00e4berle Laser- Und Feinwerktechnik Gmbh",
    "wof:placetype":"venue"
},
  "geometry": {"coordinates":[8.436246,48.244507],"type":"Point"}
}