{
  "type": "Feature",
  "properties": {
    "iso:country":"DE",
    "sg:address":"Gausebrink 66",
    "sg:city":"Ochtrup",
    "sg:phone":"+49 2553/6061",
    "sg:postcode":"48607",
    "sg:province":"Nordrhein-Westfalen",
    "wof:name":"R. B. M. Armaturen Gmbh",
    "wof:placetype":"venue"
},
  "geometry": {"coordinates":[7.175594,52.203129],"type":"Point"}
}