{
  "type": "Feature",
  "properties": {
    "iso:country":"DE",
    "sg:address":"Daimlerstr. 6",
    "sg:city":"Kirchheim",
    "sg:phone":"+49 89/9034152",
    "sg:postcode":"85551",
    "sg:province":"Bayern",
    "wof:name":"Eisen-wolf Gmbh",
    "wof:placetype":"venue"
},
  "geometry": {"coordinates":[11.765073,48.177464],"type":"Point"}
}