{
  "type": "Feature",
  "properties": {
    "iso:country":"DE",
    "sg:address":"Netphener Weg 7",
    "sg:city":"Netphen",
    "sg:phone":"+49 2738/6185",
    "sg:postcode":"57250",
    "sg:province":"Nordrhein-Westfalen",
    "wof:name":"Pizzeria Franco",
    "wof:placetype":"venue"
},
  "geometry": {"coordinates":[8.1300106049,50.9132766724],"type":"Point"}
}