{
  "type": "Feature",
  "properties": {
    "iso:country":"DE",
    "sg:address":"Bahnhofstr. 55",
    "sg:city":"Zerbst",
    "sg:postcode":"39261",
    "sg:province":"Sachsen-Anhalt",
    "wof:name":"G\u00f6hring Waffen Gmbh",
    "wof:placetype":"venue"
},
  "geometry": {"coordinates":[12.0911598206,51.9550933838],"type":"Point"}
}