{
  "type": "Feature",
  "properties": {
    "iso:country":"DE",
    "sg:address":"Bischofsgr\u00fcner Weg 54",
    "sg:city":"Berlin",
    "sg:phone":"+49 30/7746047",
    "sg:postcode":"12247",
    "sg:province":"Berlin",
    "wof:name":"Elpro- W. Zieger E. K.",
    "wof:placetype":"venue"
},
  "geometry": {"coordinates":[13.3612937927,52.4401550293],"type":"Point"}
}