{
  "type": "Feature",
  "properties": {
    "iso:country":"DE",
    "sg:address":"Sch\u00f6nbergstr. 44",
    "sg:city":"Wiesbaden",
    "sg:phone":"+49 611/425656",
    "sg:postcode":"65199",
    "sg:province":"Hessen",
    "wof:name":"Sch\u00f6nberg-apotheke",
    "wof:placetype":"venue"
},
  "geometry": {"coordinates":[8.200477,50.07885],"type":"Point"}
}