{
  "type": "Feature",
  "properties": {
    "iso:country":"DE",
    "sg:address":"Staudenfeldweg 1",
    "sg:city":"Otterfing",
    "sg:postcode":"83624",
    "sg:province":"Bayern",
    "wof:name":"Franz Heigl Gmbh",
    "wof:placetype":"venue"
},
  "geometry": {"coordinates":[11.6817998886,47.9135398865],"type":"Point"}
}