{
  "type": "Feature",
  "properties": {
    "iso:country":"DE",
    "sg:address":"Erftstr. 100",
    "sg:city":"Neuss",
    "sg:phone":"+49 2131/92480",
    "sg:postcode":"41460",
    "sg:province":"Nordrhein-Westfalen",
    "wof:name":"Sozialdienst Kath. M\u00e4nner",
    "wof:placetype":"venue"
},
  "geometry": {"coordinates":[6.6910381317,51.1959075928],"type":"Point"}
}