{
  "type": "Feature",
  "properties": {
    "iso:country":"DE",
    "sg:address":"Wasserburger Landstr. 204 a",
    "sg:city":"M\u00fcnchen",
    "sg:phone":"+49 89/4391939",
    "sg:postcode":"81827",
    "sg:province":"Bayern",
    "wof:name":"Wollersberger Gmbh",
    "wof:placetype":"venue"
},
  "geometry": {"coordinates":[11.6997213364,48.1134719849],"type":"Point"}
}