{
  "type": "Feature",
  "properties": {
    "iso:country":"DE",
    "sg:address":"Gerlingweg 86",
    "sg:city":"Elmshorn",
    "sg:phone":"+49 4121/80060",
    "sg:postcode":"25335",
    "sg:province":"Schleswig-Holstein",
    "wof:name":"Hk Hydraulik Kontor Gmbh",
    "wof:placetype":"venue"
},
  "geometry": {"coordinates":[9.658138,53.772408],"type":"Point"}
}