{
  "type": "Feature",
  "properties": {
    "iso:country":"DE",
    "sg:address":"Am Bahnhof 2",
    "sg:city":"Gro\u00dfrosseln",
    "sg:phone":"+49 6898/94130",
    "sg:postcode":"66352",
    "sg:province":"Saarland",
    "wof:name":"Arthur Meyer M\u00fchle- Und Megro- Kraftfutterf. Grossh. In Getr.",
    "wof:placetype":"venue"
},
  "geometry": {"coordinates":[6.84074,49.208019],"type":"Point"}
}