{
  "type": "Feature",
  "properties": {
    "iso:country":"DE",
    "sg:address":"Mallinckrodtstr. 320",
    "sg:city":"Dortmund",
    "sg:postcode":"44147",
    "sg:province":"Nordrhein-Westfalen",
    "wof:name":"Werftunion Verwaltungs-gmbh",
    "wof:placetype":"venue"
},
  "geometry": {"coordinates":[7.444855,51.523899],"type":"Point"}
}