{
  "type": "Feature",
  "properties": {
    "iso:country":"DE",
    "sg:address":"Raiffeisenstr. 3",
    "sg:city":"Laufen",
    "sg:phone":"+49 8682/1514",
    "sg:postcode":"83410",
    "sg:province":"Bayern",
    "wof:name":"Georg Garschhammer Kunststoffverarbeitung",
    "wof:placetype":"venue"
},
  "geometry": {"coordinates":[12.921729,47.936817],"type":"Point"}
}