{
  "type": "Feature",
  "properties": {
    "iso:country":"DE",
    "sg:address":"Wallstr. 15",
    "sg:city":"Rehau",
    "sg:phone":"+49 9283/1609",
    "sg:postcode":"95111",
    "sg:province":"Bayern",
    "wof:name":"K. Hopperdietzel Inh. Wilhelm Hopperdietzel",
    "wof:placetype":"venue"
},
  "geometry": {"coordinates":[12.037862,50.249428],"type":"Point"}
}