{
  "type": "Feature",
  "properties": {
    "iso:country":"DE",
    "sg:address":"Hildesheimer Str. 182",
    "sg:city":"Laatzen",
    "sg:phone":"+49 511/821550",
    "sg:postcode":"30880",
    "sg:province":"Niedersachsen",
    "wof:name":"L. Lerchenberger Jun.",
    "wof:placetype":"venue"
},
  "geometry": {"coordinates":[9.8012247086,52.3049468994],"type":"Point"}
}