{
  "type": "Feature",
  "properties": {
    "iso:country":"DE",
    "sg:address":"Elisabethenstra\u00dfe 39",
    "sg:city":"Darmstadt",
    "sg:phone":"+49 6151/1774290",
    "sg:postcode":"64283",
    "sg:province":"Hessen",
    "wof:name":"A Bis Z Textildruck + Werbemittel Gmbh",
    "wof:placetype":"venue"
},
  "geometry": {"coordinates":[8.6480360031,49.8699302673],"type":"Point"}
}