{
  "type": "Feature",
  "properties": {
    "iso:country":"DE",
    "sg:address":"Hartmannstr. 50",
    "sg:city":"Albstadt",
    "sg:phone":"+49 7431/71331",
    "sg:postcode":"72458",
    "sg:province":"Baden-W\u00fcrttemberg",
    "wof:name":"R\u00fcdiger Lang",
    "wof:placetype":"venue"
},
  "geometry": {"coordinates":[9.004986,48.209038],"type":"Point"}
}