{
  "type": "Feature",
  "properties": {
    "iso:country":"DE",
    "sg:address":"Auf R\u00fctt 12",
    "sg:city":"Feusdorf",
    "sg:phone":"+49 6597/4565",
    "sg:postcode":"54584",
    "sg:province":"Rheinland-Pfalz",
    "wof:name":"Adolf Schmitz",
    "wof:placetype":"venue"
},
  "geometry": {"coordinates":[6.596333,50.341488],"type":"Point"}
}