{
  "type": "Feature",
  "properties": {
    "iso:country":"DE",
    "sg:address":"Robert-Bosch-Str. 26",
    "sg:city":"Frickenhausen",
    "sg:postcode":"72636",
    "sg:province":"Baden-W\u00fcrttemberg",
    "wof:name":"H. H\u00e4hnel Kunstmaler",
    "wof:placetype":"venue"
},
  "geometry": {"coordinates":[9.347069,48.590717],"type":"Point"}
}