{
  "type": "Feature",
  "properties": {
    "iso:country":"DE",
    "sg:address":"Gartenstr. 6",
    "sg:city":"Spenge",
    "sg:phone":"+49 5225/5859",
    "sg:postcode":"32139",
    "sg:province":"Nordrhein-Westfalen",
    "wof:name":"Karl-heinz Tiemeyer",
    "wof:placetype":"venue"
},
  "geometry": {"coordinates":[8.4813642502,52.1353530884],"type":"Point"}
}