{
  "type": "Feature",
  "properties": {
    "iso:country":"DE",
    "sg:address":"Am Hillernsen Hamm 3",
    "sg:city":"Jever",
    "sg:phone":"+49 4461/3327",
    "sg:postcode":"26441",
    "sg:province":"Niedersachsen",
    "wof:name":"Heiko F\u00f6rster Elektromeister",
    "wof:placetype":"venue"
},
  "geometry": {"coordinates":[7.905331,53.57933],"type":"Point"}
}