{
  "type": "Feature",
  "properties": {
    "iso:country":"DE",
    "sg:address":"Ringstr. 36",
    "sg:city":"L\u00f6hne",
    "sg:phone":"+49 5731/3512",
    "sg:postcode":"32584",
    "sg:province":"Nordrhein-Westfalen",
    "wof:name":"A. Treusch Immobilienmakler",
    "wof:placetype":"venue"
},
  "geometry": {"coordinates":[8.7827978134,52.2056617737],"type":"Point"}
}