{
  "type": "Feature",
  "properties": {
    "iso:country":"DE",
    "sg:address":"Borsigstr 18",
    "sg:city":"Wolfsburg",
    "sg:phone":"+49 5361/557183",
    "sg:postcode":"38446",
    "sg:province":"Niedersachsen",
    "wof:name":"Fit-umwelttechnik Gmbh",
    "wof:placetype":"venue"
},
  "geometry": {"coordinates":[10.816979,52.427776],"type":"Point"}
}