{
  "type": "Feature",
  "properties": {
    "iso:country":"DE",
    "sg:address":"Wielandstr. 20",
    "sg:city":"Neumarkt",
    "sg:phone":"+49 9181/460170",
    "sg:postcode":"92318",
    "sg:province":"Bayern",
    "wof:name":"Mathi Hoffer Fassadenbau Gmbh",
    "wof:placetype":"venue"
},
  "geometry": {"coordinates":[11.482872,49.288239],"type":"Point"}
}