{
  "type": "Feature",
  "properties": {
    "iso:country":"DE",
    "sg:address":"St. Georgen 60",
    "sg:city":"Bayreuth",
    "sg:phone":"+49 921/27031",
    "sg:postcode":"95448",
    "sg:province":"Bayern",
    "wof:name":"Bayerische Vereinsbank Ag",
    "wof:placetype":"venue"
},
  "geometry": {"coordinates":[11.593138,49.954891],"type":"Point"}
}