{
  "type": "Feature",
  "properties": {
    "iso:country":"DE",
    "sg:address":"Bergstr. 15c",
    "sg:city":"Deisenhofen",
    "sg:postcode":"82041",
    "sg:province":"Bayern",
    "wof:name":"Arena 21 Wohnbau Gmbh & Co. Kg",
    "wof:placetype":"venue"
},
  "geometry": {"coordinates":[11.595409,48.018669],"type":"Point"}
}