{
  "type": "Feature",
  "properties": {
    "iso:country":"DE",
    "sg:address":"Bachgasse 10",
    "sg:city":"Geisingen",
    "sg:phone":"+49 7704/6777",
    "sg:postcode":"78187",
    "sg:province":"Baden-W\u00fcrttemberg",
    "wof:name":"Beate B\u00f6schet-weber Rechtsanw\u00e4ltin",
    "wof:placetype":"venue"
},
  "geometry": {"coordinates":[8.6443367004,47.9226303101],"type":"Point"}
}