{
  "type": "Feature",
  "properties": {
    "iso:country":"DE",
    "sg:address":"Brinkstr. 8",
    "sg:city":"Drebber",
    "sg:phone":"+49 5445/1622",
    "sg:postcode":"49457",
    "sg:province":"Niedersachsen",
    "wof:name":"Helmut Muhle",
    "wof:placetype":"venue"
},
  "geometry": {"coordinates":[8.446872,52.672993],"type":"Point"}
}