{
  "type": "Feature",
  "properties": {
    "iso:country":"DE",
    "sg:address":"Kaldenhausener Str. 58",
    "sg:city":"Moers",
    "sg:phone":"+49 2841/64767",
    "sg:postcode":"47447",
    "sg:province":"Nordrhein-Westfalen",
    "wof:name":"A. Meimers",
    "wof:placetype":"venue"
},
  "geometry": {"coordinates":[6.617993,51.396477],"type":"Point"}
}