{
  "type": "Feature",
  "properties": {
    "iso:country":"DE",
    "sg:address":"Th\u00fcngersheimer Str. 8",
    "sg:city":"Veitsh\u00f6chheim",
    "sg:phone":"+49 931/980600",
    "sg:postcode":"97209",
    "sg:province":"Bayern",
    "wof:name":"Hotel-cafe M\u00fcller",
    "wof:placetype":"venue"
},
  "geometry": {"coordinates":[9.872546196,49.833404541],"type":"Point"}
}