{
  "type": "Feature",
  "properties": {
    "iso:country":"DE",
    "sg:address":"Mazmannstr. 49",
    "sg:city":"Albstadt",
    "sg:phone":"+49 7431/3185",
    "sg:postcode":"72458",
    "sg:province":"Baden-W\u00fcrttemberg",
    "wof:name":"F. Eppler",
    "wof:placetype":"venue"
},
  "geometry": {"coordinates":[9.0290431976,48.2208557129],"type":"Point"}
}