{
  "type": "Feature",
  "properties": {
    "iso:country":"DE",
    "sg:address":"Danziger Str. 10a",
    "sg:city":"Bergneustadt",
    "sg:phone":"+49 2261/42649",
    "sg:postcode":"51702",
    "sg:province":"Nordrhein-Westfalen",
    "wof:name":"Vhb Grundst\u00fccksverwaltungsges. Haus- Und Boden-fonds Mbh",
    "wof:placetype":"venue"
},
  "geometry": {"coordinates":[7.6410541534,51.0369644165],"type":"Point"}
}