{
  "type": "Feature",
  "properties": {
    "iso:country":"DE",
    "sg:address":"Derner Str. 499",
    "sg:city":"Dortmund",
    "sg:phone":"+49 231/859800",
    "sg:postcode":"44329",
    "sg:province":"Nordrhein-Westfalen",
    "wof:name":"Riag Handwerks-zentrum Ges. F\u00fcr Innenausbau Und",
    "wof:placetype":"venue"
},
  "geometry": {"coordinates":[7.520405,51.571678],"type":"Point"}
}