{
  "type": "Feature",
  "properties": {
    "iso:country":"DE",
    "sg:address":"Wartburgstr. 19",
    "sg:city":"Berlin",
    "sg:phone":"+49 30/78708870",
    "sg:postcode":"10825",
    "sg:province":"Berlin",
    "wof:name":"Dr. Dieter Greiner Rechtsanwalt",
    "wof:placetype":"venue"
},
  "geometry": {"coordinates":[13.3421964645,52.4867515564],"type":"Point"}
}