{
  "type": "Feature",
  "properties": {
    "iso:country":"DE",
    "sg:address":"M\u00fchlweg 13",
    "sg:city":"Dieskau",
    "sg:phone":"+49 345/5800344",
    "sg:postcode":"06184",
    "sg:province":"Sachsen-Anhalt",
    "wof:name":"Ursula Fessel",
    "wof:placetype":"venue"
},
  "geometry": {"coordinates":[12.036339,51.431133],"type":"Point"}
}