{
  "type": "Feature",
  "properties": {
    "iso:country":"DE",
    "sg:address":"Rheingaublick 17",
    "sg:city":"Geisenheim",
    "sg:phone":"+49 6722/5836",
    "sg:postcode":"65366",
    "sg:province":"Hessen",
    "wof:name":"H. J\u00e4ger Gmbh",
    "wof:placetype":"venue"
},
  "geometry": {"coordinates":[7.966988,50.00922],"type":"Point"}
}