{
  "type": "Feature",
  "properties": {
    "iso:country":"DE",
    "sg:address":"Bahnhofstr. 14",
    "sg:city":"Bad Eilsen",
    "sg:phone":"+49 5722/84849",
    "sg:postcode":"31707",
    "sg:province":"Niedersachsen",
    "wof:name":"Maschmeier",
    "wof:placetype":"venue"
},
  "geometry": {"coordinates":[9.106274,52.239697],"type":"Point"}
}