{
  "type": "Feature",
  "properties": {
    "iso:country":"DE",
    "sg:address":"Reitzebergstr. 6",
    "sg:city":"Gr\u00fcndau",
    "sg:phone":"+49 6058/2789",
    "sg:postcode":"63584",
    "sg:province":"Hessen",
    "wof:name":"Brambier Verwaltung Gmbh",
    "wof:placetype":"venue"
},
  "geometry": {"coordinates":[9.0993242264,50.2431411743],"type":"Point"}
}