{
  "type": "Feature",
  "properties": {
    "iso:country":"DE",
    "sg:address":"Edlinger Str 68",
    "sg:city":"Stephanskirchen",
    "sg:phone":"+49 8036/9088261",
    "sg:postcode":"83071",
    "sg:province":"Bayern",
    "wof:name":"Turnpoint Fastline Gmbh",
    "wof:placetype":"venue"
},
  "geometry": {"coordinates":[12.2086467743,47.8630561829],"type":"Point"}
}