{
  "type": "Feature",
  "properties": {
    "iso:country":"DE",
    "sg:address":"An der Maar 28",
    "sg:city":"Pulheim",
    "sg:phone":"+49 2234/82224",
    "sg:postcode":"50259",
    "sg:province":"Nordrhein-Westfalen",
    "wof:name":"Fliesen Keramik Schmitz Handelsagentur E. K.",
    "wof:placetype":"venue"
},
  "geometry": {"coordinates":[6.7623929977,50.95545578],"type":"Point"}
}