{
  "type": "Feature",
  "properties": {
    "iso:country":"DE",
    "sg:address":"Trierer Str. 133",
    "sg:city":"Merzig",
    "sg:phone":"+49 6861/4163",
    "sg:postcode":"66663",
    "sg:province":"Saarland",
    "wof:name":"Dental-studio Merzig H. & H. Scheid Gmbh",
    "wof:placetype":"venue"
},
  "geometry": {"coordinates":[6.6368451118,49.4477157593],"type":"Point"}
}