{
  "type": "Feature",
  "properties": {
    "iso:country":"DE",
    "sg:address":"Hubertusstr. 19",
    "sg:city":"Thale",
    "sg:phone":"+49 3947/3378",
    "sg:postcode":"06502",
    "sg:province":"Sachsen-Anhalt",
    "wof:name":"B. Golla",
    "wof:placetype":"venue"
},
  "geometry": {"coordinates":[11.033371,51.744236],"type":"Point"}
}