{
  "type": "Feature",
  "properties": {
    "iso:country":"DE",
    "sg:address":"Ulmer Str. 13",
    "sg:city":"Neus\u00e4\u00df",
    "sg:phone":"+49 821/489479",
    "sg:postcode":"86356",
    "sg:province":"Bayern",
    "wof:name":"C. Meyer",
    "wof:placetype":"venue"
},
  "geometry": {"coordinates":[10.828252,48.376648],"type":"Point"}
}