{
  "type": "Feature",
  "properties": {
    "iso:country":"DE",
    "sg:address":"Fl\u00f6\u00dferstr. 22",
    "sg:city":"Lechbruck",
    "sg:phone":"+49 8862/8526",
    "sg:postcode":"86983",
    "sg:province":"Bayern",
    "wof:name":"Sparkasse Ostallg\u00e4u",
    "wof:placetype":"venue"
},
  "geometry": {"coordinates":[10.797508,47.69648],"type":"Point"}
}