{
  "type": "Feature",
  "properties": {
    "iso:country":"DE",
    "sg:address":"Wilhelmstr. 42",
    "sg:city":"Merchweiler",
    "sg:phone":"+49 6825/41365",
    "sg:postcode":"66589",
    "sg:province":"Saarland",
    "wof:name":"Robert Heimes",
    "wof:placetype":"venue"
},
  "geometry": {"coordinates":[7.0938792229,49.3699645996],"type":"Point"}
}