{
  "type": "Feature",
  "properties": {
    "iso:country":"DE",
    "sg:address":"Weiherwiese 27",
    "sg:city":"Idstein",
    "sg:phone":"+49 6126/8807",
    "sg:postcode":"65510",
    "sg:province":"Hessen",
    "wof:name":"Verein Sch\u00fclerhilfe J\u00fcrgen Lenhart",
    "wof:placetype":"venue"
},
  "geometry": {"coordinates":[8.2726583481,50.220703125],"type":"Point"}
}