{
  "type": "Feature",
  "properties": {
    "iso:country":"DE",
    "sg:address":"Berliner Freiheit 1d",
    "sg:city":"Bremen",
    "sg:phone":"+49 421/464488",
    "sg:postcode":"28327",
    "sg:province":"Bremen",
    "wof:name":"Ludger Rohde Rechtsanwalt",
    "wof:placetype":"venue"
},
  "geometry": {"coordinates":[8.8926782608,53.0810661316],"type":"Point"}
}