{
  "type": "Feature",
  "properties": {
    "iso:country":"DE",
    "sg:address":"Geraer Str. 13",
    "sg:city":"Stadtroda",
    "sg:postcode":"07646",
    "sg:province":"Th\u00fcringen",
    "wof:name":"Cwb Compakt Wohnen Und Bauen Gmbh",
    "wof:placetype":"venue"
},
  "geometry": {"coordinates":[11.731177,50.857494],"type":"Point"}
}