{
  "type": "Feature",
  "properties": {
    "iso:country":"DE",
    "sg:address":"Stufenweg 14",
    "sg:city":"Moers",
    "sg:phone":"+49 2841/30745",
    "sg:postcode":"47447",
    "sg:province":"Nordrhein-Westfalen",
    "wof:name":"Hans Hamann",
    "wof:placetype":"venue"
},
  "geometry": {"coordinates":[6.6466741562,51.4267616272],"type":"Point"}
}