{
  "type": "Feature",
  "properties": {
    "iso:country":"DE",
    "sg:address":"Am Dorn 27",
    "sg:city":"L\u00fcdinghausen",
    "sg:phone":"+49 2591/8393",
    "sg:postcode":"59348",
    "sg:province":"Nordrhein-Westfalen",
    "wof:name":"Wittkemper Bautr\u00e4ger Gmbh",
    "wof:placetype":"venue"
},
  "geometry": {"coordinates":[7.400476,51.762337],"type":"Point"}
}