{
  "type": "Feature",
  "properties": {
    "iso:country":"DE",
    "sg:address":"Moltkestr. 7",
    "sg:city":"Offenburg",
    "sg:phone":"+49 781/41488",
    "sg:postcode":"77654",
    "sg:province":"Baden-W\u00fcrttemberg",
    "wof:name":"Br\u00fcnnele",
    "wof:placetype":"venue"
},
  "geometry": {"coordinates":[7.9533600807,48.4752197266],"type":"Point"}
}