{
  "type": "Feature",
  "properties": {
    "iso:country":"DE",
    "sg:address":"Wiesenstr. 3 a",
    "sg:city":"Sulzbach",
    "sg:phone":"+49 6196/73310",
    "sg:postcode":"65843",
    "sg:province":"Hessen",
    "wof:name":"Steiner Fliesen Gmbh",
    "wof:placetype":"venue"
},
  "geometry": {"coordinates":[8.5295505524,50.1298675537],"type":"Point"}
}