{
  "type": "Feature",
  "properties": {
    "iso:country":"DE",
    "sg:address":"Schubertstr. 35",
    "sg:city":"Friedrichshafen",
    "sg:phone":"+49 7541/72960",
    "sg:postcode":"88046",
    "sg:province":"Baden-W\u00fcrttemberg",
    "wof:name":"Franz Blaser Immobilien-b\u00fcro",
    "wof:placetype":"venue"
},
  "geometry": {"coordinates":[9.494301796,47.6544761658],"type":"Point"}
}