{
  "type": "Feature",
  "properties": {
    "iso:country":"DE",
    "sg:address":"Breiteicher Str. 7",
    "sg:city":"Raubling",
    "sg:phone":"+49 8035/2829",
    "sg:postcode":"83064",
    "sg:province":"Bayern",
    "wof:name":"I. Enzinger Heissmangel",
    "wof:placetype":"venue"
},
  "geometry": {"coordinates":[12.1170396805,47.8058128357],"type":"Point"}
}