{
  "type": "Feature",
  "properties": {
    "iso:country":"DE",
    "sg:address":"Lieberoser Str. 23",
    "sg:city":"L\u00fcbben",
    "sg:postcode":"15907",
    "sg:province":"Brandenburg",
    "wof:name":"Fuchs & Nietz",
    "wof:placetype":"venue"
},
  "geometry": {"coordinates":[13.917166,51.941162],"type":"Point"}
}