{
  "type": "Feature",
  "properties": {
    "iso:country":"DE",
    "sg:address":"Langg. 95",
    "sg:city":"Ha\u00dfloch",
    "sg:phone":"+49 4971/712318",
    "sg:postcode":"67454",
    "sg:province":"Rheinland-Pfalz",
    "wof:name":"K. C. Kern Kg",
    "wof:placetype":"venue"
},
  "geometry": {"coordinates":[9.8005180359,48.7949028015],"type":"Point"}
}