{
  "type": "Feature",
  "properties": {
    "iso:country":"DE",
    "sg:address":"Warschauer Str. 5",
    "sg:city":"Torgau",
    "sg:phone":"+49 3421/710119",
    "sg:postcode":"04860",
    "sg:province":"Sachsen",
    "wof:name":"Holzelementebau Thielemann Gmbh",
    "wof:placetype":"venue"
},
  "geometry": {"coordinates":[12.988917,51.559109],"type":"Point"}
}