{
  "type": "Feature",
  "properties": {
    "iso:country":"DE",
    "sg:address":"Sporker Str. 30",
    "sg:city":"Detmold",
    "sg:phone":"+49 5231/58671",
    "sg:postcode":"32760",
    "sg:province":"Nordrhein-Westfalen",
    "wof:name":"Ernst-hermann Zeckei Steuerberater",
    "wof:placetype":"venue"
},
  "geometry": {"coordinates":[8.909620285,51.9178504944],"type":"Point"}
}