{
  "type": "Feature",
  "properties": {
    "iso:country":"DE",
    "sg:address":"Eligiuspassage 2",
    "sg:city":"V\u00f6lklingen",
    "sg:phone":"+49 6898/50230",
    "sg:postcode":"66333",
    "sg:province":"Saarland",
    "wof:name":"Einrichtungshaus Storch Gmbh",
    "wof:placetype":"venue"
},
  "geometry": {"coordinates":[6.854065,49.249447],"type":"Point"}
}