{
  "type": "Feature",
  "properties": {
    "iso:country":"DE",
    "sg:address":"Ihmer Tor 14",
    "sg:city":"Ronnenberg",
    "sg:phone":"+49 5109/9661",
    "sg:postcode":"30952",
    "sg:province":"Niedersachsen",
    "wof:name":"Heinrich Rosemeier Gmbh",
    "wof:placetype":"venue"
},
  "geometry": {"coordinates":[9.661726,52.316601],"type":"Point"}
}