{
  "type": "Feature",
  "properties": {
    "iso:country":"DE",
    "sg:address":"Hammerwasen 15",
    "sg:city":"Rottenburg",
    "sg:phone":"+49 7472/93740",
    "sg:postcode":"72108",
    "sg:province":"Baden-W\u00fcrttemberg",
    "wof:name":"Artur Kroll Gmbh & Co Kg",
    "wof:placetype":"venue"
},
  "geometry": {"coordinates":[8.9176979065,48.4667549133],"type":"Point"}
}