{
  "type": "Feature",
  "properties": {
    "iso:country":"DE",
    "sg:address":"N\u00fcrnberger Str. 57",
    "sg:city":"Zirndorf",
    "sg:phone":"+49 911/9602356",
    "sg:postcode":"90513",
    "sg:province":"Bayern",
    "wof:name":"D2 Shop Zirndorf",
    "wof:placetype":"venue"
},
  "geometry": {"coordinates":[10.9663047791,49.4380836487],"type":"Point"}
}