{
  "type": "Feature",
  "properties": {
    "iso:country":"DE",
    "sg:address":"Annemarie-Nutzhorn-Weg 4",
    "sg:city":"Wedemark",
    "sg:postcode":"30900",
    "sg:province":"Niedersachsen",
    "wof:name":"Allucando Gmbh",
    "wof:placetype":"venue"
},
  "geometry": {"coordinates":[9.73929,52.524273],"type":"Point"}
}