{
  "type": "Feature",
  "properties": {
    "iso:country":"DE",
    "sg:address":"Ewaldstr. 9",
    "sg:city":"Herten",
    "sg:phone":"+49 2366/35490",
    "sg:postcode":"45699",
    "sg:province":"Nordrhein-Westfalen",
    "wof:name":"W\u00e4sche-moden Martin R.lenz",
    "wof:placetype":"venue"
},
  "geometry": {"coordinates":[7.1396389008,51.5929908752],"type":"Point"}
}