{
  "type": "Feature",
  "properties": {
    "iso:country":"DE",
    "sg:address":"H\u00fcgelsheimer Str. 10",
    "sg:city":"Iffezheim",
    "sg:phone":"+49 7229/2220",
    "sg:postcode":"76473",
    "sg:province":"Baden-W\u00fcrttemberg",
    "wof:name":"Elektro Sch\u00e4fer Gmbh",
    "wof:placetype":"venue"
},
  "geometry": {"coordinates":[8.1401185989,48.8228721619],"type":"Point"}
}