{
  "type": "Feature",
  "properties": {
    "iso:country":"DE",
    "sg:address":"Ulmenstr. 98",
    "sg:city":"D\u00fcsseldorf",
    "sg:phone":"+49 211/484027",
    "sg:postcode":"40476",
    "sg:province":"Nordrhein-Westfalen",
    "wof:name":"L. O. G. Lotterie- Organisations Gmbh",
    "wof:placetype":"venue"
},
  "geometry": {"coordinates":[6.782782,51.248341],"type":"Point"}
}