{
  "type": "Feature",
  "properties": {
    "iso:country":"DE",
    "sg:address":"Wei\u00dfkreuzstr. 12",
    "sg:city":"Saarlouis",
    "sg:phone":"+49 6831/121232",
    "sg:postcode":"66740",
    "sg:province":"Saarland",
    "wof:name":"Manfred Klein",
    "wof:placetype":"venue"
},
  "geometry": {"coordinates":[6.7518339157,49.3136787415],"type":"Point"}
}