{
  "type": "Feature",
  "properties": {
    "iso:country":"DE",
    "sg:address":"Schwarzer Weg 109",
    "sg:city":"Peine",
    "sg:phone":"+49 5171/17275",
    "sg:postcode":"31224",
    "sg:province":"Niedersachsen",
    "wof:name":"Jet-tankstelle",
    "wof:placetype":"venue"
},
  "geometry": {"coordinates":[10.2366504669,52.3338661194],"type":"Point"}
}