{
  "type": "Feature",
  "properties": {
    "iso:country":"DE",
    "sg:address":"Meessen 10",
    "sg:city":"Oststeinbek",
    "sg:postcode":"22113",
    "sg:province":"Schleswig-Holstein",
    "wof:name":"Sonne Mond Und Sterne Verlag Gmbh",
    "wof:placetype":"venue"
},
  "geometry": {"coordinates":[10.16127491,53.5492477417],"type":"Point"}
}