{
  "type": "Feature",
  "properties": {
    "iso:country":"DE",
    "sg:address":"Amelandstr. 8",
    "sg:city":"Recklinghausen",
    "sg:phone":"+49 2361/488333",
    "sg:postcode":"45665",
    "sg:province":"Nordrhein-Westfalen",
    "wof:name":"Hildegard Bootz",
    "wof:placetype":"venue"
},
  "geometry": {"coordinates":[7.219522953,51.608833313],"type":"Point"}
}