{
  "type": "Feature",
  "properties": {
    "iso:country":"DE",
    "sg:address":"T\u00e4ubchenstr. 2e",
    "sg:city":"Berlin",
    "sg:phone":"+49 30/8133816",
    "sg:postcode":"14163",
    "sg:province":"Berlin",
    "wof:name":"Manu Kunst Und Antiquit\u00e4ten Gmbh",
    "wof:placetype":"venue"
},
  "geometry": {"coordinates":[13.2352619171,52.4466171265],"type":"Point"}
}