{
  "type": "Feature",
  "properties": {
    "iso:country":"DE",
    "sg:address":"Breiter Weg 19",
    "sg:city":"Bondorf",
    "sg:phone":"+49 7457/1089",
    "sg:postcode":"71149",
    "sg:province":"Baden-W\u00fcrttemberg",
    "wof:name":"Willy Wanner",
    "wof:placetype":"venue"
},
  "geometry": {"coordinates":[8.822476387,48.5194664001],"type":"Point"}
}