{
  "type": "Feature",
  "properties": {
    "iso:country":"DE",
    "sg:address":"Sonsbecker Str. 40-44",
    "sg:city":"Xanten",
    "sg:phone":"+49 2801/71430",
    "sg:postcode":"46509",
    "sg:province":"Nordrhein-Westfalen",
    "wof:name":"Shipconsulting & Manage- Ment Gmbh",
    "wof:placetype":"venue"
},
  "geometry": {"coordinates":[6.435737133,51.6534004211],"type":"Point"}
}