{
  "type": "Feature",
  "properties": {
    "iso:country":"DE",
    "sg:address":"Porschestr. 13",
    "sg:city":"Salzgitter",
    "sg:phone":"+49 5341/811210",
    "sg:postcode":"38259",
    "sg:province":"Niedersachsen",
    "wof:name":"A. Mendrock",
    "wof:placetype":"venue"
},
  "geometry": {"coordinates":[10.384936,52.057678],"type":"Point"}
}