{
  "type": "Feature",
  "properties": {
    "iso:country":"DE",
    "sg:address":"Maierhofstr. 34",
    "sg:city":"Albstadt",
    "sg:phone":"+49 7432/21732",
    "sg:postcode":"72461",
    "sg:province":"Baden-W\u00fcrttemberg",
    "wof:name":"G\u00fcnter Haasis",
    "wof:placetype":"venue"
},
  "geometry": {"coordinates":[8.998433,48.284264],"type":"Point"}
}