{
  "type": "Feature",
  "properties": {
    "iso:country":"DE",
    "sg:address":"Beim Strohhause 24",
    "sg:city":"Hamburg",
    "sg:phone":"+49 40/241671",
    "sg:postcode":"20097",
    "sg:province":"Hamburg",
    "wof:name":"Alpha Dent Abdol-hamid Lebaschi",
    "wof:placetype":"venue"
},
  "geometry": {"coordinates":[10.022429,53.55307],"type":"Point"}
}