{
  "type": "Feature",
  "properties": {
    "iso:country":"DE",
    "sg:address":"Kirchplatz 9",
    "sg:city":"Bad Essen",
    "sg:phone":"+49 5472/94480",
    "sg:postcode":"49152",
    "sg:province":"Niedersachsen",
    "wof:name":"Capitalia Treuhand Ohg Steuerberatungsgesellschaft",
    "wof:placetype":"venue"
},
  "geometry": {"coordinates":[8.3399801254,52.3200111389],"type":"Point"}
}