{
  "type": "Feature",
  "properties": {
    "iso:country":"DE",
    "sg:address":"Pfaderstr. 22",
    "sg:city":"Wassenberg",
    "sg:postcode":"41849",
    "sg:province":"Nordrhein-Westfalen",
    "wof:name":"K\u00fcppers Innenausbau Gmbh",
    "wof:placetype":"venue"
},
  "geometry": {"coordinates":[6.099262,51.114143],"type":"Point"}
}