{
  "type": "Feature",
  "properties": {
    "iso:country":"DE",
    "sg:address":"Theisseil 12",
    "sg:city":"Theisseil",
    "sg:phone":"+49 961/32477",
    "sg:postcode":"92637",
    "sg:province":"Bayern",
    "wof:name":"Georg Schmau\u00df",
    "wof:placetype":"venue"
},
  "geometry": {"coordinates":[12.225725,49.690598],"type":"Point"}
}