{
  "type": "Feature",
  "properties": {
    "iso:country":"DE",
    "sg:address":"Hauptstr. 15",
    "sg:city":"Metterich",
    "sg:phone":"+49 6565/2207",
    "sg:postcode":"54634",
    "sg:province":"Rheinland-Pfalz",
    "wof:name":"M. Molitor",
    "wof:placetype":"venue"
},
  "geometry": {"coordinates":[6.5875630379,49.9785346985],"type":"Point"}
}