{
  "type": "Feature",
  "properties": {
    "iso:country":"DE",
    "sg:address":"Cuxhavener Str. 63",
    "sg:city":"N\u00fcrnberg",
    "sg:phone":"+49 911/346822",
    "sg:postcode":"90425",
    "sg:province":"Bayern",
    "wof:name":"Carins Friseurboutique",
    "wof:placetype":"venue"
},
  "geometry": {"coordinates":[11.0675344467,49.4773368835],"type":"Point"}
}