{
  "type": "Feature",
  "properties": {
    "iso:country":"DE",
    "sg:address":"10 rue de la paix",
    "sg:city":"PARIS",
    "sg:phone":"+49 169852415",
    "sg:postcode":"75002",
    "wof:name":"D\u00e9veloppement Des Ressources Humaines Assist\u00e9 Par http://ww",
    "wof:placetype":"venue"
},
  "geometry": {"coordinates":[2.331142,48.868942],"type":"Point"}
}