{
  "type": "Feature",
  "properties": {
    "iso:country":"DE",
    "sg:address":"Sendlinger Str. 12",
    "sg:city":"M\u00fcnchen",
    "sg:phone":"+49 89/2609076",
    "sg:postcode":"80331",
    "sg:province":"Bayern",
    "wof:name":"Wilhelm Neubert",
    "wof:placetype":"venue"
},
  "geometry": {"coordinates":[11.5715837479,48.1356658936],"type":"Point"}
}