{
  "type": "Feature",
  "properties": {
    "iso:country":"DE",
    "sg:address":"Judenstr. 3 - 4",
    "sg:city":"Zeitz",
    "sg:postcode":"06712",
    "sg:province":"Sachsen-Anhalt",
    "wof:name":"Ufa Filmtheater Capitol",
    "wof:placetype":"venue"
},
  "geometry": {"coordinates":[12.136507988,51.0497665405],"type":"Point"}
}