{
  "type": "Feature",
  "properties": {
    "iso:country":"DE",
    "sg:address":"Buxtehuder Str. 7",
    "sg:city":"Apensen",
    "sg:phone":"+49 4167/436",
    "sg:postcode":"21641",
    "sg:province":"Niedersachsen",
    "wof:name":"G. Zygla",
    "wof:placetype":"venue"
},
  "geometry": {"coordinates":[9.615463,53.434315],"type":"Point"}
}