{
  "type": "Feature",
  "properties": {
    "iso:country":"DE",
    "sg:address":"Westf\u00e4lische Str. 41",
    "sg:city":"Berlin",
    "sg:phone":"+49 30/8924663",
    "sg:postcode":"10711",
    "sg:province":"Berlin",
    "wof:name":"Anna Schneider Gmbh",
    "wof:placetype":"venue"
},
  "geometry": {"coordinates":[13.294219,52.496441],"type":"Point"}
}