{
  "type": "Feature",
  "properties": {
    "iso:country":"DE",
    "sg:address":"B\u00e4renthal 1a",
    "sg:city":"Egloffstein",
    "sg:phone":"+49 9197/326",
    "sg:postcode":"91349",
    "sg:province":"Bayern",
    "wof:name":"Holzbau Singer",
    "wof:placetype":"venue"
},
  "geometry": {"coordinates":[11.2705726624,49.693397522],"type":"Point"}
}