{
  "type": "Feature",
  "properties": {
    "iso:country":"DE",
    "sg:address":"M\u00fchlenweg 27",
    "sg:city":"Schwante",
    "sg:phone":"+49 33055/70984",
    "sg:postcode":"16727",
    "sg:province":"Brandenburg",
    "wof:name":"Raiffeisen Handels- Genossenschaft Oranienburg Eg",
    "wof:placetype":"venue"
},
  "geometry": {"coordinates":[13.088073,52.729282],"type":"Point"}
}