{
  "type": "Feature",
  "properties": {
    "iso:country":"DE",
    "sg:address":"Schillerstr. 19",
    "sg:city":"Sinsheim",
    "sg:phone":"+49 7261/3020",
    "sg:postcode":"74889",
    "sg:province":"Baden-W\u00fcrttemberg",
    "wof:name":"Giancarlo Salvia",
    "wof:placetype":"venue"
},
  "geometry": {"coordinates":[8.907119751,49.2560958862],"type":"Point"}
}