{
  "type": "Feature",
  "properties": {
    "iso:country":"DE",
    "sg:address":"Regensburger Str.",
    "sg:city":"Burglengenfeld",
    "sg:postcode":"93133",
    "sg:province":"Bayern",
    "wof:name":"Stinnes Baumarkt Ag",
    "wof:placetype":"venue"
},
  "geometry": {"coordinates":[12.0446376801,49.2039222717],"type":"Point"}
}