{
  "type": "Feature",
  "properties": {
    "iso:country":"DE",
    "sg:address":"Axel-Springer-Platz 1",
    "sg:city":"Hamburg",
    "sg:postcode":"20355",
    "sg:province":"Hamburg",
    "wof:name":"Vm & Tm Verlag Verwaltungs Gmbh",
    "wof:placetype":"venue"
},
  "geometry": {"coordinates":[9.9850349426,53.5526275635],"type":"Point"}
}