{
  "type": "Feature",
  "properties": {
    "iso:country":"DE",
    "sg:address":"Steinstra\u00dfe 8",
    "sg:city":"Nordwalde",
    "sg:phone":"+49 2573/98711",
    "sg:postcode":"48356",
    "sg:province":"Nordrhein-Westfalen",
    "wof:name":"Suchmeldung.de",
    "wof:placetype":"venue"
},
  "geometry": {"coordinates":[7.478926,52.080334],"type":"Point"}
}