{
  "type": "Feature",
  "properties": {
    "iso:country":"DE",
    "sg:address":"Hauptstr. 2",
    "sg:city":"Luckau",
    "sg:phone":"+49 3544/6155",
    "sg:postcode":"15926",
    "sg:province":"Brandenburg",
    "wof:name":"U. Wieczorek",
    "wof:placetype":"venue"
},
  "geometry": {"coordinates":[13.713905,51.852882],"type":"Point"}
}