{
  "type": "Feature",
  "properties": {
    "iso:country":"DE",
    "sg:address":"Am Werk 7",
    "sg:city":"Webau",
    "sg:phone":"+49 34441/910",
    "sg:postcode":"06679",
    "sg:province":"Sachsen-Anhalt",
    "wof:name":"Paraffinwerk Webau Gmbh",
    "wof:placetype":"venue"
},
  "geometry": {"coordinates":[12.0948553085,51.1687698364],"type":"Point"}
}