{
  "type": "Feature",
  "properties": {
    "iso:country":"DE",
    "sg:address":"Drei\u00dfigackerer Str. 1",
    "sg:city":"Meiningen",
    "sg:phone":"+49 3693/503531",
    "sg:postcode":"98617",
    "sg:province":"Th\u00fcringen",
    "wof:name":"Kreuzbergschenke",
    "wof:placetype":"venue"
},
  "geometry": {"coordinates":[10.4072847366,50.5611190796],"type":"Point"}
}