{
  "type": "Feature",
  "properties": {
    "iso:country":"DE",
    "sg:address":"Friesenwall 24 d",
    "sg:city":"K\u00f6ln",
    "sg:phone":"+49 221/2573239",
    "sg:postcode":"50672",
    "sg:province":"Nordrhein-Westfalen",
    "wof:name":"Barflo Brasserie",
    "wof:placetype":"venue"
},
  "geometry": {"coordinates":[6.940652,50.937363],"type":"Point"}
}