{
  "type": "Feature",
  "properties": {
    "iso:country":"DE",
    "sg:address":"Bismarckstr. 57",
    "sg:city":"Tangerh\u00fctte",
    "sg:phone":"+49 3935/212167",
    "sg:postcode":"39517",
    "sg:province":"Sachsen-Anhalt",
    "wof:name":"W. Roloff Ingenieur",
    "wof:placetype":"venue"
},
  "geometry": {"coordinates":[11.8165855408,52.4341392517],"type":"Point"}
}