{
  "type": "Feature",
  "properties": {
    "iso:country":"DE",
    "sg:address":"Schulstr. 10",
    "sg:city":"St\u00fctzengr\u00fcn",
    "sg:phone":"+49 37462/5024",
    "sg:postcode":"08328",
    "sg:province":"Sachsen",
    "wof:name":"Rainer Weck",
    "wof:placetype":"venue"
},
  "geometry": {"coordinates":[12.52049,50.525013],"type":"Point"}
}