{
  "type": "Feature",
  "properties": {
    "iso:country":"DE",
    "sg:address":"Blumenstr. 4",
    "sg:city":"B\u00fchl",
    "sg:phone":"+49 7223/93130",
    "sg:postcode":"77815",
    "sg:province":"Baden-W\u00fcrttemberg",
    "wof:name":"Hotel-restaurant Gr\u00fcne Bettlad",
    "wof:placetype":"venue"
},
  "geometry": {"coordinates":[8.1391372681,48.6963233948],"type":"Point"}
}