{
  "type": "Feature",
  "properties": {
    "iso:country":"DE",
    "sg:address":"Stadtweg 3",
    "sg:city":"Darmstadt",
    "sg:phone":"+49 6151/373450",
    "sg:postcode":"64291",
    "sg:province":"Hessen",
    "wof:name":"Schampera",
    "wof:placetype":"venue"
},
  "geometry": {"coordinates":[8.6604633331,49.9103317261],"type":"Point"}
}