{
  "type": "Feature",
  "properties": {
    "iso:country":"DE",
    "sg:address":"Wilhelm-Reuter-Str. 13",
    "sg:city":"Eppstein",
    "sg:phone":"+49 6195/911168",
    "sg:postcode":"65817",
    "sg:province":"Hessen",
    "wof:name":"B. Christoffers Steuerberater",
    "wof:placetype":"venue"
},
  "geometry": {"coordinates":[8.3622159958,50.1388511658],"type":"Point"}
}