{
  "type": "Feature",
  "properties": {
    "iso:country":"DE",
    "sg:address":"Hausinger Str 6",
    "sg:city":"Langenfeld",
    "sg:phone":"+49 2173/3991630",
    "sg:postcode":"40764",
    "sg:province":"Nordrhein-Westfalen",
    "wof:name":"Fetra Aluminium Profiltechnik Gmbh",
    "wof:placetype":"venue"
},
  "geometry": {"coordinates":[6.948959,51.094257],"type":"Point"}
}