{
  "type": "Feature",
  "properties": {
    "iso:country":"DE",
    "sg:address":"Kirchplatz 5",
    "sg:city":"Bad Arolsen",
    "sg:phone":"+49 5691/40231",
    "sg:postcode":"34454",
    "sg:province":"Hessen",
    "wof:name":"H. Isenberg",
    "wof:placetype":"venue"
},
  "geometry": {"coordinates":[9.01502,51.380238],"type":"Point"}
}