{
  "type": "Feature",
  "properties": {
    "iso:country":"DE",
    "sg:address":"Robert-Koch-Str. 8",
    "sg:city":"Winsen",
    "sg:postcode":"21423",
    "sg:province":"Niedersachsen",
    "wof:name":"Marathon Technischer Fachhandel Gmbh",
    "wof:placetype":"venue"
},
  "geometry": {"coordinates":[10.228846,53.341545],"type":"Point"}
}