{
  "type": "Feature",
  "properties": {
    "iso:country":"DE",
    "sg:address":"Behlertstr. 28",
    "sg:city":"Potsdam",
    "sg:phone":"+49 331/279201",
    "sg:postcode":"14469",
    "sg:province":"Brandenburg",
    "wof:name":"Victoria Versicherung",
    "wof:placetype":"venue"
},
  "geometry": {"coordinates":[13.0631008148,52.4061698914],"type":"Point"}
}