{
  "type": "Feature",
  "properties": {
    "iso:country":"DE",
    "sg:address":"Theresienstr. 83",
    "sg:city":"M\u00fcnchen",
    "sg:phone":"+49 89/527684",
    "sg:postcode":"80333",
    "sg:province":"Bayern",
    "wof:name":"Claudia Fa\u00dfrainer",
    "wof:placetype":"venue"
},
  "geometry": {"coordinates":[11.5615148544,48.1517486572],"type":"Point"}
}