{
  "type": "Feature",
  "properties": {
    "iso:country":"DE",
    "sg:address":"Homberger Str. 2",
    "sg:city":"Malsfeld",
    "sg:phone":"+49 5662/3280",
    "sg:postcode":"34323",
    "sg:province":"Hessen",
    "wof:name":"Landffleischerei Hain Gmbh",
    "wof:placetype":"venue"
},
  "geometry": {"coordinates":[9.5092000961,51.0802841187],"type":"Point"}
}