{
  "type": "Feature",
  "properties": {
    "iso:country":"DE",
    "sg:address":"Martin-Luther-Str. 4",
    "sg:city":"Soltau",
    "sg:phone":"+49 5191/5624",
    "sg:postcode":"29614",
    "sg:province":"Niedersachsen",
    "wof:name":"Lions-club L\u00fcneburger Heide J\u00fcrgen Dransfeld",
    "wof:placetype":"venue"
},
  "geometry": {"coordinates":[9.8474826813,52.9875221252],"type":"Point"}
}