{
  "type": "Feature",
  "properties": {
    "iso:country":"DE",
    "sg:address":"Frankfurter Str. 21 b",
    "sg:city":"Kronberg",
    "sg:postcode":"61476",
    "sg:province":"Hessen",
    "wof:name":"Foxx Software Gmbh",
    "wof:placetype":"venue"
},
  "geometry": {"coordinates":[8.5150299072,50.1788978577],"type":"Point"}
}