{
  "type": "Feature",
  "properties": {
    "iso:country":"DE",
    "sg:address":"Weststr. 54",
    "sg:city":"Walchum",
    "sg:phone":"+49 5939/414",
    "sg:postcode":"26907",
    "sg:province":"Niedersachsen",
    "wof:name":"Heinrich M\u00fcter",
    "wof:placetype":"venue"
},
  "geometry": {"coordinates":[7.177449,52.923473],"type":"Point"}
}