{
  "type": "Feature",
  "properties": {
    "iso:country":"DE",
    "sg:address":"Klosterstr. 11",
    "sg:city":"Marienheide",
    "sg:phone":"+49 2264/8120",
    "sg:postcode":"51709",
    "sg:province":"Nordrhein-Westfalen",
    "wof:name":"Reinhard Scheffer",
    "wof:placetype":"venue"
},
  "geometry": {"coordinates":[7.532546,51.085304],"type":"Point"}
}