{
  "type": "Feature",
  "properties": {
    "iso:country":"DE",
    "sg:address":"Joseph-von-Eichendorff-Str. 11",
    "sg:city":"Nordstemmen",
    "sg:phone":"+49 5069/2129",
    "sg:postcode":"31171",
    "sg:province":"Niedersachsen",
    "wof:name":"I. Frankenberg",
    "wof:placetype":"venue"
},
  "geometry": {"coordinates":[9.7913751602,52.1605186462],"type":"Point"}
}