{
  "type": "Feature",
  "properties": {
    "iso:country":"DE",
    "sg:address":"M\u00fcnsterstr. 69",
    "sg:city":"D\u00fcsseldorf",
    "sg:phone":"+49 211/282866",
    "sg:postcode":"40476",
    "sg:province":"Nordrhein-Westfalen",
    "wof:name":"Cera-line Gmbh",
    "wof:placetype":"venue"
},
  "geometry": {"coordinates":[6.785885,51.243164],"type":"Point"}
}