{
  "type": "Feature",
  "properties": {
    "iso:country":"DE",
    "sg:address":"F\u00e4rberstr. 14",
    "sg:city":"Eggenfelden",
    "sg:phone":"+49 8721/96000",
    "sg:postcode":"84307",
    "sg:province":"Bayern",
    "wof:name":"Irl Planungs- Und Ingenieur- Gesellschaft Mbh",
    "wof:placetype":"venue"
},
  "geometry": {"coordinates":[12.7769966125,48.4066162109],"type":"Point"}
}