{
  "type": "Feature",
  "properties": {
    "iso:country":"DE",
    "sg:address":"Lengerser Str.",
    "sg:city":"Heringen",
    "sg:phone":"+49 6624/8066",
    "sg:postcode":"36266",
    "sg:province":"Hessen",
    "wof:name":"Vs Verbundschalungen Verwaltungs Gmbh",
    "wof:placetype":"venue"
},
  "geometry": {"coordinates":[10.003141,50.885204],"type":"Point"}
}