{
  "type": "Feature",
  "properties": {
    "iso:country":"DE",
    "sg:address":"Goldammerweg 19",
    "sg:city":"Bottrop",
    "sg:phone":"+49 2041/58620",
    "sg:postcode":"46242",
    "sg:province":"Nordrhein-Westfalen",
    "wof:name":"Hans Und Anette Asch",
    "wof:placetype":"venue"
},
  "geometry": {"coordinates":[6.886919,51.545567],"type":"Point"}
}