{
  "type": "Feature",
  "properties": {
    "iso:country":"DE",
    "sg:address":"Klaus-Groth-Str. 25",
    "sg:city":"Hamburg",
    "sg:phone":"+49 40/4105702",
    "sg:postcode":"20535",
    "sg:province":"Hamburg",
    "wof:name":"Buchstaben-center K\u00f6ppe Gmbh",
    "wof:placetype":"venue"
},
  "geometry": {"coordinates":[10.030976,53.555492],"type":"Point"}
}