{
  "type": "Feature",
  "properties": {
    "iso:country":"DE",
    "sg:address":"Seumestr. 10",
    "sg:city":"Hamburg",
    "sg:phone":"+49 40/208971",
    "sg:postcode":"22089",
    "sg:province":"Hamburg",
    "wof:name":"Bierland Getr\u00e4nke Siegbert Zilz",
    "wof:placetype":"venue"
},
  "geometry": {"coordinates":[10.056134,53.570156],"type":"Point"}
}