{
  "type": "Feature",
  "properties": {
    "iso:country":"DE",
    "sg:address":"Oberstr. 92",
    "sg:city":"Grevenbroich",
    "sg:phone":"+49 2181/296700",
    "sg:postcode":"41516",
    "sg:province":"Nordrhein-Westfalen",
    "wof:name":"Rudolf Gehlen Verwaltungs-gmbh",
    "wof:placetype":"venue"
},
  "geometry": {"coordinates":[6.6142988205,51.1001739502],"type":"Point"}
}