{
  "type": "Feature",
  "properties": {
    "iso:country":"DE",
    "sg:address":"Zedersdorf 19",
    "sg:city":"Sonnefeld",
    "sg:phone":"+49 9562/8771",
    "sg:postcode":"96242",
    "sg:province":"Bayern",
    "wof:name":"E. Baudler",
    "wof:placetype":"venue"
},
  "geometry": {"coordinates":[11.151302,50.247894],"type":"Point"}
}