{
  "type": "Feature",
  "properties": {
    "iso:country":"DE",
    "sg:address":"Erchanbertstr. 13",
    "sg:city":"M\u00fcnchen",
    "sg:phone":"+49 89/933330",
    "sg:postcode":"81929",
    "sg:province":"Bayern",
    "wof:name":"Wilhelm Kuchenbauer Gmbh",
    "wof:placetype":"venue"
},
  "geometry": {"coordinates":[11.658652,48.150494],"type":"Point"}
}