{
  "type": "Feature",
  "properties": {
    "iso:country":"DE",
    "sg:address":"Bruchwiesenstr. 15",
    "sg:city":"Saarbr\u00fccken",
    "sg:phone":"+49 681/9385990",
    "sg:postcode":"66111",
    "sg:province":"Saarland",
    "wof:name":"Karin Rolshoven Ergotherapiepraxis",
    "wof:placetype":"venue"
},
  "geometry": {"coordinates":[7.002958,49.23484],"type":"Point"}
}