{
  "type": "Feature",
  "properties": {
    "iso:country":"DE",
    "sg:address":"Schillerstr. 15",
    "sg:city":"Edingen-Neckarhausen",
    "sg:phone":"+49 6203/85637",
    "sg:postcode":"68535",
    "sg:province":"Baden-W\u00fcrttemberg",
    "wof:name":"Georg Ott",
    "wof:placetype":"venue"
},
  "geometry": {"coordinates":[8.616879,49.441433],"type":"Point"}
}