{
  "type": "Feature",
  "properties": {
    "iso:country":"DE",
    "sg:address":"Heutingsheimer Str. 1",
    "sg:city":"Stuttgart",
    "sg:phone":"+49 711/8263380",
    "sg:postcode":"70439",
    "sg:province":"Baden-W\u00fcrttemberg",
    "wof:name":"Linde-grill",
    "wof:placetype":"venue"
},
  "geometry": {"coordinates":[9.1593437195,48.8429527283],"type":"Point"}
}