{
  "type": "Feature",
  "properties": {
    "iso:country":"DE",
    "sg:address":"Dorfstr. 14",
    "sg:city":"Bad Schandau",
    "sg:phone":"+49 35022/42408",
    "sg:postcode":"01814",
    "sg:province":"Sachsen",
    "wof:name":"Jugendherberge Bad Schandau",
    "wof:placetype":"venue"
},
  "geometry": {"coordinates":[14.1754655838,50.921749115],"type":"Point"}
}