{
  "type": "Feature",
  "properties": {
    "iso:country":"DE",
    "sg:address":"Garreler Str. 18",
    "sg:city":"B\u00f6sel",
    "sg:phone":"+49 4494/251",
    "sg:postcode":"26219",
    "sg:province":"Niedersachsen",
    "wof:name":"J. Preuth",
    "wof:placetype":"venue"
},
  "geometry": {"coordinates":[7.96917,53.004459],"type":"Point"}
}