{
  "type": "Feature",
  "properties": {
    "iso:country":"DE",
    "sg:address":"Schubertstr. 3",
    "sg:city":"Malsch",
    "sg:phone":"+49 7253/21826",
    "sg:postcode":"69254",
    "sg:province":"Baden-W\u00fcrttemberg",
    "wof:name":"Wilfried Hemberger",
    "wof:placetype":"venue"
},
  "geometry": {"coordinates":[8.6878032684,49.2456207275],"type":"Point"}
}