{
  "type": "Feature",
  "properties": {
    "iso:country":"DE",
    "sg:address":"Hartigstr. 3",
    "sg:city":"Zittau",
    "sg:phone":"+49 3583/510041",
    "sg:postcode":"02763",
    "sg:province":"Sachsen",
    "wof:name":"Wolfgang Menzel",
    "wof:placetype":"venue"
},
  "geometry": {"coordinates":[14.7873277664,50.9003677368],"type":"Point"}
}