{
  "type": "Feature",
  "properties": {
    "iso:country":"DE",
    "sg:address":"Karl-Pfaff-Siedlung 135",
    "sg:city":"Kaiserslautern",
    "sg:phone":"+49 631/26211",
    "sg:postcode":"67663",
    "sg:province":"Rheinland-Pfalz",
    "wof:name":"Sonnenbrillen-shop Www.sun66.com",
    "wof:placetype":"venue"
},
  "geometry": {"coordinates":[7.744332,49.434383],"type":"Point"}
}