{
  "type": "Feature",
  "properties": {
    "iso:country":"DE",
    "sg:address":"Ernst-Th\u00e4lmann-Str. 33",
    "sg:city":"Hainichen",
    "sg:phone":"+49 37207/2853",
    "sg:postcode":"09661",
    "sg:province":"Sachsen",
    "wof:name":"Reinhard Lippmann",
    "wof:placetype":"venue"
},
  "geometry": {"coordinates":[13.123533,50.965012],"type":"Point"}
}