{
  "type": "Feature",
  "properties": {
    "iso:country":"DE",
    "sg:address":"Bergstr. 4",
    "sg:city":"Bodenkirchen",
    "sg:phone":"+49 8741/6734",
    "sg:postcode":"84155",
    "sg:province":"Bayern",
    "wof:name":"Katholisches Pfarramt Mari\u00e4 Heimsuchung",
    "wof:placetype":"venue"
},
  "geometry": {"coordinates":[12.4275941849,48.4385147095],"type":"Point"}
}