{
  "type": "Feature",
  "properties": {
    "iso:country":"DE",
    "sg:address":"Frankenstr. 4",
    "sg:city":"H\u00f6chberg",
    "sg:phone":"+49 931/400321",
    "sg:postcode":"97204",
    "sg:province":"Bayern",
    "wof:name":"Dr. Michael Hilgenstock Rechtsanwalt",
    "wof:placetype":"venue"
},
  "geometry": {"coordinates":[9.8850650787,49.7877426147],"type":"Point"}
}