{
  "type": "Feature",
  "properties": {
    "iso:country":"DE",
    "sg:address":"Kaiserstr. 20",
    "sg:city":"W\u00fcrzburg",
    "sg:phone":"+49 931/57018",
    "sg:postcode":"97070",
    "sg:province":"Bayern",
    "wof:name":"Kiliansb\u00e4ck",
    "wof:placetype":"venue"
},
  "geometry": {"coordinates":[9.934499,49.79911],"type":"Point"}
}