{
  "type": "Feature",
  "properties": {
    "iso:country":"DE",
    "sg:address":"Petersh\u00e4userhof 2",
    "sg:city":"Zilshausen",
    "sg:phone":"+49 6762/1772",
    "sg:postcode":"56288",
    "sg:province":"Rheinland-Pfalz",
    "wof:name":"Karl-josef Pulger",
    "wof:placetype":"venue"
},
  "geometry": {"coordinates":[7.381161,50.121593],"type":"Point"}
}