{
  "type": "Feature",
  "properties": {
    "iso:country":"DE",
    "sg:address":"Neuer Weg 13",
    "sg:city":"S\u00fclfeld",
    "sg:phone":"+49 4537/230",
    "sg:postcode":"23867",
    "sg:province":"Schleswig-Holstein",
    "wof:name":"Rudolf Rupprecht",
    "wof:placetype":"venue"
},
  "geometry": {"coordinates":[10.227023,53.802013],"type":"Point"}
}