{
  "type": "Feature",
  "properties": {
    "iso:country":"DE",
    "sg:address":"Gro\u00dfschmiedestr. 4",
    "sg:city":"Wismar",
    "sg:phone":"+49 3841/259484",
    "sg:postcode":"23966",
    "sg:province":"Mecklenburg-Vorpommern",
    "wof:name":"G. K\u00f6hn",
    "wof:placetype":"venue"
},
  "geometry": {"coordinates":[11.467651,53.891518],"type":"Point"}
}