{
  "type": "Feature",
  "properties": {
    "iso:country":"DE",
    "sg:address":"Im Dorfe 5",
    "sg:city":"Hamb\u00fchren",
    "sg:phone":"+49 5084/5260",
    "sg:postcode":"29313",
    "sg:province":"Niedersachsen",
    "wof:name":"Erich L\u00fcders",
    "wof:placetype":"venue"
},
  "geometry": {"coordinates":[9.984944,52.637711],"type":"Point"}
}