{
  "type": "Feature",
  "properties": {
    "iso:country":"DE",
    "sg:address":"M\u00fchlenbergstr. 17 a",
    "sg:city":"Calden",
    "sg:phone":"+49 5677/1533",
    "sg:postcode":"34379",
    "sg:province":"Hessen",
    "wof:name":"F. H\u00fcbl",
    "wof:placetype":"venue"
},
  "geometry": {"coordinates":[9.322905,51.440014],"type":"Point"}
}