{
  "type": "Feature",
  "properties": {
    "iso:country":"DE",
    "sg:address":"Hofener Str 10c",
    "sg:city":"Sonthofen",
    "sg:phone":"+49 8321/4103",
    "sg:postcode":"87527",
    "sg:province":"Bayern",
    "wof:name":"Mh-hoteleinrichtungsgesellschaft Gmbh",
    "wof:placetype":"venue"
},
  "geometry": {"coordinates":[10.287304,47.50935],"type":"Point"}
}