{
  "type": "Feature",
  "properties": {
    "iso:country":"DE",
    "sg:address":"Marienburger Platz 22",
    "sg:city":"Hildesheim",
    "sg:postcode":"31141",
    "sg:province":"Niedersachsen",
    "wof:name":"Institut F\u00fcr Angewandte Sprachwissenschaft",
    "wof:placetype":"venue"
},
  "geometry": {"coordinates":[9.9750947952,52.1334609985],"type":"Point"}
}