{
  "type": "Feature",
  "properties": {
    "iso:country":"DE",
    "sg:address":"Flie\u00dfe 1",
    "sg:city":"L\u00f6bej\u00fcn",
    "sg:phone":"+49 34603/77201",
    "sg:postcode":"06193",
    "sg:province":"Sachsen-Anhalt",
    "wof:name":"H. Harzer",
    "wof:placetype":"venue"
},
  "geometry": {"coordinates":[11.900644,51.638577],"type":"Point"}
}