{
  "type": "Feature",
  "properties": {
    "iso:country":"DE",
    "sg:address":"Adenauerallee 133",
    "sg:city":"Bonn",
    "sg:phone":"+49 228/241218",
    "sg:postcode":"53113",
    "sg:province":"Nordrhein-Westfalen",
    "wof:name":"Dr. Hans G\u00fcnther Axe Assekuranz",
    "wof:placetype":"venue"
},
  "geometry": {"coordinates":[7.1144452095,50.7220039368],"type":"Point"}
}