{
  "type": "Feature",
  "properties": {
    "iso:country":"DE",
    "sg:address":"Holter Hauptstr. 5",
    "sg:city":"L\u00e4hden",
    "sg:phone":"+49 5964/272",
    "sg:postcode":"49774",
    "sg:province":"Niedersachsen",
    "wof:name":"Gastst\u00e4tte Rolfes",
    "wof:placetype":"venue"
},
  "geometry": {"coordinates":[7.6209340096,52.736114502],"type":"Point"}
}