{
  "type": "Feature",
  "properties": {
    "iso:country":"DE",
    "sg:address":"Nadorster Str. 60-62",
    "sg:city":"Oldenburg",
    "sg:phone":"+49 441/81015",
    "sg:postcode":"26123",
    "sg:province":"Niedersachsen",
    "wof:name":"Martin Eilers Gmbh",
    "wof:placetype":"venue"
},
  "geometry": {"coordinates":[8.217549,53.151402],"type":"Point"}
}