{
  "type": "Feature",
  "properties": {
    "iso:country":"DE",
    "sg:address":"K\u00f6nigsstr.60",
    "sg:city":"M\u00fcnster",
    "sg:phone":"+49 251/415",
    "sg:postcode":"48143",
    "sg:province":"Nordrhein-Westfalen",
    "wof:name":"Dresdner Bank",
    "wof:placetype":"venue"
},
  "geometry": {"coordinates":[7.625976,51.960506],"type":"Point"}
}