{
  "type": "Feature",
  "properties": {
    "iso:country":"DE",
    "sg:address":"\u00c4u\u00dfere Waldstr 32",
    "sg:city":"Greppin",
    "sg:phone":"+49 3493/400534",
    "sg:postcode":"06803",
    "sg:province":"Sachsen-Anhalt",
    "wof:name":"Rukom",
    "wof:placetype":"venue"
},
  "geometry": {"coordinates":[12.302471,51.651749],"type":"Point"}
}