{
  "type": "Feature",
  "properties": {
    "iso:country":"DE",
    "sg:address":"Am Wacholder 86",
    "sg:city":"Herzogenrath",
    "sg:phone":"+49 2407/96054",
    "sg:postcode":"52134",
    "sg:province":"Nordrhein-Westfalen",
    "wof:name":"Multi Immobilien Beteiligungs Gmbh",
    "wof:placetype":"venue"
},
  "geometry": {"coordinates":[6.09648,50.833462],"type":"Point"}
}