{
  "type": "Feature",
  "properties": {
    "iso:country":"DE",
    "sg:address":"Schlo\u00dfstr. 79",
    "sg:city":"Berlin",
    "sg:phone":"+49 30/7926296",
    "sg:postcode":"12165",
    "sg:province":"Berlin",
    "wof:name":"Heinrich Scheuermann",
    "wof:placetype":"venue"
},
  "geometry": {"coordinates":[13.3198680878,52.4555740356],"type":"Point"}
}