{
  "type": "Feature",
  "properties": {
    "iso:country":"DE",
    "sg:address":"Dankwardweg 5",
    "sg:city":"Wiesbaden",
    "sg:phone":"+49 611/309462",
    "sg:postcode":"65189",
    "sg:province":"Hessen",
    "wof:name":"Die Nageltante",
    "wof:placetype":"venue"
},
  "geometry": {"coordinates":[8.2682733536,50.063835144],"type":"Point"}
}