{
  "type": "Feature",
  "properties": {
    "iso:country":"DE",
    "sg:address":"Frentzenhofstr. 2",
    "sg:city":"H\u00fcrth",
    "sg:phone":"+49 2233/943178",
    "sg:postcode":"50354",
    "sg:province":"Nordrhein-Westfalen",
    "wof:name":"Eichrodt Chemie Gmbh",
    "wof:placetype":"venue"
},
  "geometry": {"coordinates":[6.88651,50.865086],"type":"Point"}
}