{
  "type": "Feature",
  "properties": {
    "iso:country":"DE",
    "sg:address":"Schwaber Str. 3",
    "sg:city":"Jevenstedt",
    "sg:phone":"+49 4337/865",
    "sg:postcode":"24808",
    "sg:province":"Schleswig-Holstein",
    "wof:name":"Napoleons Grill",
    "wof:placetype":"venue"
},
  "geometry": {"coordinates":[9.6696977615,54.2348747253],"type":"Point"}
}