{
  "type": "Feature",
  "properties": {
    "iso:country":"DE",
    "sg:address":"Weichselstr. 6",
    "sg:city":"Wiesbaden",
    "sg:phone":"+49 611/564588",
    "sg:postcode":"65191",
    "sg:province":"Hessen",
    "wof:name":"Barbara Bleckert Masseurin",
    "wof:placetype":"venue"
},
  "geometry": {"coordinates":[8.266568,50.094505],"type":"Point"}
}