{
  "type": "Feature",
  "properties": {
    "iso:country":"DE",
    "sg:address":"Am Klosterbach 2",
    "sg:city":"Marsberg",
    "sg:phone":"+49 2991/6206",
    "sg:postcode":"34431",
    "sg:province":"Nordrhein-Westfalen",
    "wof:name":"Hans-josef Reiermann",
    "wof:placetype":"venue"
},
  "geometry": {"coordinates":[8.763446,51.410614],"type":"Point"}
}