{
  "type": "Feature",
  "properties": {
    "iso:country":"DE",
    "sg:address":"Weddigenstr. 42",
    "sg:city":"Wuppertal",
    "sg:phone":"+49 202/607407",
    "sg:postcode":"42389",
    "sg:province":"Nordrhein-Westfalen",
    "wof:name":"G\u00fcnter Petig Steuerberater",
    "wof:placetype":"venue"
},
  "geometry": {"coordinates":[7.2427740097,51.2700042725],"type":"Point"}
}