{
  "type": "Feature",
  "properties": {
    "iso:country":"DE",
    "sg:address":"Im Konvent 12",
    "sg:city":"Krefeld",
    "sg:phone":"+49 2151/735991",
    "sg:postcode":"47839",
    "sg:province":"Nordrhein-Westfalen",
    "wof:name":"Antiquit\u00e4ten Des Klassizismus Geller & T\u00f6lke Gmbh",
    "wof:placetype":"venue"
},
  "geometry": {"coordinates":[6.508563,51.374062],"type":"Point"}
}