{
  "type": "Feature",
  "properties": {
    "iso:country":"DE",
    "sg:address":"Goslarsche Str. 29",
    "sg:city":"Salzgitter",
    "sg:phone":"+49 5341/33589",
    "sg:postcode":"38259",
    "sg:province":"Niedersachsen",
    "wof:name":"Helga Lersch",
    "wof:placetype":"venue"
},
  "geometry": {"coordinates":[10.324922,52.033722],"type":"Point"}
}