{
  "type": "Feature",
  "properties": {
    "iso:country":"DE",
    "sg:address":"Breite Str. 91",
    "sg:city":"Niederstotzingen",
    "sg:phone":"+49 7325/8746",
    "sg:postcode":"89168",
    "sg:province":"Baden-W\u00fcrttemberg",
    "wof:name":"Fritz Noller",
    "wof:placetype":"venue"
},
  "geometry": {"coordinates":[10.229887,48.528866],"type":"Point"}
}