{
  "type": "Feature",
  "properties": {
    "iso:country":"DE",
    "sg:address":"Markt 8a",
    "sg:city":"Ruhland",
    "sg:phone":"+49 35752/2531",
    "sg:postcode":"01945",
    "sg:province":"Brandenburg",
    "wof:name":"B. Pathe",
    "wof:placetype":"venue"
},
  "geometry": {"coordinates":[13.8739356995,51.4304428101],"type":"Point"}
}