{
  "type": "Feature",
  "properties": {
    "iso:country":"DE",
    "sg:address":"Im Osterfeld 56",
    "sg:city":"Badbergen",
    "sg:postcode":"49635",
    "sg:province":"Niedersachsen",
    "wof:name":"Seelig Trans-cont Gmbh",
    "wof:placetype":"venue"
},
  "geometry": {"coordinates":[7.961160183,52.6149482727],"type":"Point"}
}