{
  "type": "Feature",
  "properties": {
    "iso:country":"DE",
    "sg:address":"An der Wattenheimer Br\u00fccke",
    "sg:city":"Lorsch",
    "sg:phone":"+49 6251/51659",
    "sg:postcode":"64653",
    "sg:province":"Hessen",
    "wof:name":"Karl H. Kasten",
    "wof:placetype":"venue"
},
  "geometry": {"coordinates":[8.568782,49.672466],"type":"Point"}
}