{
  "type": "Feature",
  "properties": {
    "iso:country":"DE",
    "sg:address":"Sch\u00fctzenstr. 31",
    "sg:city":"Freudenberg",
    "sg:phone":"+49 2734/4670",
    "sg:postcode":"57258",
    "sg:province":"Nordrhein-Westfalen",
    "wof:name":"Gottfried K\u00f6hler Hotel Gmbh",
    "wof:placetype":"venue"
},
  "geometry": {"coordinates":[7.8687558174,50.8921661377],"type":"Point"}
}