{
  "type": "Feature",
  "properties": {
    "iso:country":"DE",
    "sg:address":"Hellenpfad 109",
    "sg:city":"Bendorf",
    "sg:phone":"+49 2622/6445",
    "sg:postcode":"56170",
    "sg:province":"Rheinland-Pfalz",
    "wof:name":"Peter Heuft",
    "wof:placetype":"venue"
},
  "geometry": {"coordinates":[7.5769910812,50.4371604919],"type":"Point"}
}