{
  "type": "Feature",
  "properties": {
    "iso:country":"DE",
    "sg:address":"Luitpoldstr. 27",
    "sg:city":"Krailling",
    "sg:phone":"+49 89/8599525",
    "sg:postcode":"82152",
    "sg:province":"Bayern",
    "wof:name":"Lilo Friepan",
    "wof:placetype":"venue"
},
  "geometry": {"coordinates":[11.414786,48.10009],"type":"Point"}
}