{
  "type": "Feature",
  "properties": {
    "iso:country":"DE",
    "sg:address":"Am Stadtbrunnen 1",
    "sg:city":"Dietzenbach",
    "sg:phone":"+49 6074/23117",
    "sg:postcode":"63128",
    "sg:province":"Hessen",
    "wof:name":"Heberer & Echternach Textilien",
    "wof:placetype":"venue"
},
  "geometry": {"coordinates":[8.778875351,50.0089302063],"type":"Point"}
}