{
  "type": "Feature",
  "properties": {
    "iso:country":"DE",
    "sg:address":"Frankenallee 125-127",
    "sg:city":"Frankfurt",
    "sg:phone":"+49 69/75809943",
    "sg:postcode":"60326",
    "sg:province":"Hessen",
    "wof:name":"Aerovias Nacionales De Colombia S.a. Avianca",
    "wof:placetype":"venue"
},
  "geometry": {"coordinates":[8.640116,50.104294],"type":"Point"}
}