{
  "type": "Feature",
  "properties": {
    "iso:country":"DE",
    "sg:address":"Flintholm 13",
    "sg:city":"Waabs",
    "sg:phone":"+49 4352/2642",
    "sg:postcode":"24369",
    "sg:province":"Schleswig-Holstein",
    "wof:name":"Wolfgang Petersen",
    "wof:placetype":"venue"
},
  "geometry": {"coordinates":[9.991758,54.530102],"type":"Point"}
}