{
  "type": "Feature",
  "properties": {
    "iso:country":"DE",
    "sg:address":"Volksgartenstr. 10",
    "sg:city":"K\u00f6ln",
    "sg:phone":"+49 221/319254",
    "sg:postcode":"50677",
    "sg:province":"Nordrhein-Westfalen",
    "wof:name":"Rivet",
    "wof:placetype":"venue"
},
  "geometry": {"coordinates":[6.953123,50.920334],"type":"Point"}
}