{
  "type": "Feature",
  "properties": {
    "iso:country":"DE",
    "sg:address":"Husumer Str. 94",
    "sg:city":"Bielefeld",
    "sg:postcode":"33729",
    "sg:province":"Nordrhein-Westfalen",
    "wof:name":"Drei-stern-berufsmode Gmbh",
    "wof:placetype":"venue"
},
  "geometry": {"coordinates":[8.598458,52.078457],"type":"Point"}
}