{
  "type": "Feature",
  "properties": {
    "iso:country":"DE",
    "sg:address":"Overwegstr. 79",
    "sg:city":"Gelsenkirchen",
    "sg:phone":"+49 209/44444",
    "sg:postcode":"45881",
    "sg:province":"Nordrhein-Westfalen",
    "wof:name":"Kuhnert-werbung Werbegeschenke",
    "wof:placetype":"venue"
},
  "geometry": {"coordinates":[7.0805301666,51.5193214417],"type":"Point"}
}