{
  "type": "Feature",
  "properties": {
    "iso:country":"DE",
    "sg:address":"Oderstr. 4",
    "sg:city":"Twistringen",
    "sg:phone":"+49 4246/95053",
    "sg:postcode":"27239",
    "sg:province":"Niedersachsen",
    "wof:name":"Praxis Dr. Med. Mann Und Vetter",
    "wof:placetype":"venue"
},
  "geometry": {"coordinates":[8.556022644,52.7695274353],"type":"Point"}
}