{
  "type": "Feature",
  "properties": {
    "iso:country":"DE",
    "sg:address":"Sebastian-Bach-Str. 52",
    "sg:city":"Fellbach",
    "sg:phone":"+49 711/573135",
    "sg:postcode":"70734",
    "sg:province":"Baden-W\u00fcrttemberg",
    "wof:name":"F\u00fcrst",
    "wof:placetype":"venue"
},
  "geometry": {"coordinates":[9.2711954117,48.812412262],"type":"Point"}
}