{
  "type": "Feature",
  "properties": {
    "iso:country":"DE",
    "sg:address":"Woltersdorfer Landstr. 19",
    "sg:city":"Erkner",
    "sg:phone":"+49 3362/75053",
    "sg:postcode":"15537",
    "sg:province":"Brandenburg",
    "wof:name":"Extra",
    "wof:placetype":"venue"
},
  "geometry": {"coordinates":[13.7545995712,52.4361381531],"type":"Point"}
}