{
  "type": "Feature",
  "properties": {
    "iso:country":"DE",
    "sg:address":"Gro\u00dfenhainer Str. 22",
    "sg:city":"Dresden",
    "sg:postcode":"01097",
    "sg:province":"Sachsen",
    "wof:name":"Egbert Heinze",
    "wof:placetype":"venue"
},
  "geometry": {"coordinates":[13.736667,51.071941],"type":"Point"}
}