{
  "type": "Feature",
  "properties": {
    "iso:country":"DE",
    "sg:address":"Kronwinkler Str. 45B",
    "sg:city":"M\u00fcnchen",
    "sg:phone":"+49 89/8643143",
    "sg:postcode":"81245",
    "sg:province":"Bayern",
    "wof:name":"Eberhard Voigt Ingenuieur",
    "wof:placetype":"venue"
},
  "geometry": {"coordinates":[11.4229459763,48.1614532471],"type":"Point"}
}