{
  "type": "Feature",
  "properties": {
    "iso:country":"DE",
    "sg:address":"Bergstr. 10 a",
    "sg:city":"Idstein",
    "sg:phone":"+49 6434/5553",
    "sg:postcode":"65510",
    "sg:province":"Hessen",
    "wof:name":"Lydoxa Gmbh",
    "wof:placetype":"venue"
},
  "geometry": {"coordinates":[8.281738,50.269775],"type":"Point"}
}