{
  "type": "Feature",
  "properties": {
    "iso:country":"DE",
    "sg:address":"S\u00fcder Markt 5",
    "sg:city":"Herten",
    "sg:phone":"+49 2366/37380",
    "sg:postcode":"45699",
    "sg:province":"Nordrhein-Westfalen",
    "wof:name":"M. Karkowski",
    "wof:placetype":"venue"
},
  "geometry": {"coordinates":[7.145946,51.583855],"type":"Point"}
}