{
  "type": "Feature",
  "properties": {
    "iso:country":"DE",
    "sg:address":"Industriestr. 5",
    "sg:city":"Burscheid",
    "sg:phone":"+49 2174/679253",
    "sg:postcode":"51399",
    "sg:province":"Nordrhein-Westfalen",
    "wof:name":"Tara Teppichhandels- Vertriebs Gmbh",
    "wof:placetype":"venue"
},
  "geometry": {"coordinates":[7.0997738838,51.0874710083],"type":"Point"}
}