{
  "type": "Feature",
  "properties": {
    "iso:country":"DE",
    "sg:address":"Hauptstr. 315",
    "sg:city":"Hemer",
    "sg:phone":"+49 2372/10873",
    "sg:postcode":"58675",
    "sg:province":"Nordrhein-Westfalen",
    "wof:name":"A. Simon",
    "wof:placetype":"venue"
},
  "geometry": {"coordinates":[7.760969162,51.392288208],"type":"Point"}
}