{
  "type": "Feature",
  "properties": {
    "iso:country":"DE",
    "sg:address":"Am Brand 4",
    "sg:city":"T\u00fcrkenfeld",
    "sg:phone":"+49 8193/272",
    "sg:postcode":"82299",
    "sg:province":"Bayern",
    "wof:name":"Ernst Buckl",
    "wof:placetype":"venue"
},
  "geometry": {"coordinates":[11.0811471939,48.0986862183],"type":"Point"}
}