{
  "type": "Feature",
  "properties": {
    "iso:country":"DE",
    "sg:address":"Ostra-Allee 35",
    "sg:city":"Dresden",
    "sg:phone":"+49 351/4906063",
    "sg:postcode":"01067",
    "sg:province":"Sachsen",
    "wof:name":"Immobilienkontor Wiedemann & Co. Gmbh",
    "wof:placetype":"venue"
},
  "geometry": {"coordinates":[13.7273902893,51.0576171875],"type":"Point"}
}