{
  "type": "Feature",
  "properties": {
    "iso:country":"DE",
    "sg:address":"Waldstr. 6",
    "sg:city":"Lubmin",
    "sg:phone":"+49 38354/22337",
    "sg:postcode":"17509",
    "sg:province":"Mecklenburg-Vorpommern",
    "wof:name":"H. Ladwig",
    "wof:placetype":"venue"
},
  "geometry": {"coordinates":[13.613462,54.135963],"type":"Point"}
}