{
  "type": "Feature",
  "properties": {
    "iso:country":"DE",
    "sg:address":"Bruchweg 21 a",
    "sg:city":"Emersleben",
    "sg:phone":"+49 39424/9590",
    "sg:postcode":"38822",
    "sg:province":"Sachsen-Anhalt",
    "wof:name":"Melle Dachbaustoffe Gmbh",
    "wof:placetype":"venue"
},
  "geometry": {"coordinates":[11.143634,51.925602],"type":"Point"}
}