{
  "type": "Feature",
  "properties": {
    "iso:country":"DE",
    "sg:address":"Otto-Roelen-Str. 1",
    "sg:city":"Oberhausen",
    "sg:phone":"+49 208/6215286",
    "sg:postcode":"46147",
    "sg:province":"Nordrhein-Westfalen",
    "wof:name":"Citec Gmbh",
    "wof:placetype":"venue"
},
  "geometry": {"coordinates":[6.8188948631,51.5417251587],"type":"Point"}
}