{
  "type": "Feature",
  "properties": {
    "iso:country":"DE",
    "sg:address":"Falkenstr. 12",
    "sg:city":"Beratzhausen",
    "sg:phone":"+49 9493/800",
    "sg:postcode":"93176",
    "sg:province":"Bayern",
    "wof:name":"Fritz Spangler",
    "wof:placetype":"venue"
},
  "geometry": {"coordinates":[11.8041753769,49.0974884033],"type":"Point"}
}