{
  "type": "Feature",
  "properties": {
    "iso:country":"DE",
    "sg:address":"Gro\u00dfe Bergstr. 13",
    "sg:city":"Gehrden",
    "sg:phone":"+49 5108/5231",
    "sg:postcode":"30989",
    "sg:province":"Niedersachsen",
    "wof:name":"Elke Pusch",
    "wof:placetype":"venue"
},
  "geometry": {"coordinates":[9.596696,52.313339],"type":"Point"}
}