{
  "type": "Feature",
  "properties": {
    "iso:country":"DE",
    "sg:address":"Friederikenstr. 33",
    "sg:city":"Coswig",
    "sg:phone":"+49 34903/65665",
    "sg:postcode":"06869",
    "sg:province":"Sachsen-Anhalt",
    "wof:name":"Renate Pude",
    "wof:placetype":"venue"
},
  "geometry": {"coordinates":[12.457036972,51.8842964172],"type":"Point"}
}