{
  "type": "Feature",
  "properties": {
    "iso:country":"DE",
    "sg:address":"Wernesgr\u00fcner Str. 64b",
    "sg:city":"Rodewisch",
    "sg:phone":"+49 3744/48115",
    "sg:postcode":"08228",
    "sg:province":"Sachsen",
    "wof:name":"Denkinger Haustechnik Gmbh",
    "wof:placetype":"venue"
},
  "geometry": {"coordinates":[12.4236822128,50.5316925049],"type":"Point"}
}