{
  "type": "Feature",
  "properties": {
    "iso:country":"DE",
    "sg:address":"J\u00e4gerheimstr. 10",
    "sg:city":"Gr\u00f6benzell",
    "sg:phone":"+49 8142/570362",
    "sg:postcode":"82194",
    "sg:province":"Bayern",
    "wof:name":"Stephan Schweighart",
    "wof:placetype":"venue"
},
  "geometry": {"coordinates":[11.3813438416,48.1822280884],"type":"Point"}
}