{
  "type": "Feature",
  "properties": {
    "iso:country":"DE",
    "sg:address":"Siemensstr 15",
    "sg:city":"Velbert",
    "sg:phone":"+49 2051/21008",
    "sg:postcode":"42551",
    "sg:province":"Nordrhein-Westfalen",
    "wof:name":"Joh. Fr. M\u00fcller Gmbh & Co Kg",
    "wof:placetype":"venue"
},
  "geometry": {"coordinates":[7.0661540031,51.3492851257],"type":"Point"}
}