{
  "type": "Feature",
  "properties": {
    "iso:country":"DE",
    "sg:address":"Philipp-Reis-Str. 42 a",
    "sg:city":"Springe",
    "sg:phone":"+49 5041/5363",
    "sg:postcode":"31832",
    "sg:province":"Niedersachsen",
    "wof:name":"Klaus Motz",
    "wof:placetype":"venue"
},
  "geometry": {"coordinates":[9.571983,52.217209],"type":"Point"}
}