{
  "type": "Feature",
  "properties": {
    "iso:country":"DE",
    "sg:address":"Isareck 1",
    "sg:city":"Wang",
    "sg:postcode":"85368",
    "sg:province":"Bayern",
    "wof:name":"Forstservice Isar-harz Gmbh & Co. Kg",
    "wof:placetype":"venue"
},
  "geometry": {"coordinates":[11.938757,48.498146],"type":"Point"}
}