{
  "type": "Feature",
  "properties": {
    "iso:country":"DE",
    "sg:address":"Bahnhofstr. 46 A",
    "sg:city":"Neuwied",
    "sg:phone":"+49 2631/83650",
    "sg:postcode":"56564",
    "sg:province":"Rheinland-Pfalz",
    "wof:name":"Dr. Franz-josef Rheinspitz Rechtsanwalt",
    "wof:placetype":"venue"
},
  "geometry": {"coordinates":[7.4691557884,50.4301719666],"type":"Point"}
}