{
  "type": "Feature",
  "properties": {
    "iso:country":"DE",
    "sg:address":"Danziger Str. 21",
    "sg:city":"\u00d6hringen",
    "sg:phone":"+49 7941/7755",
    "sg:postcode":"74613",
    "sg:province":"Baden-W\u00fcrttemberg",
    "wof:name":"Robert Klimak Tenniscenter",
    "wof:placetype":"venue"
},
  "geometry": {"coordinates":[9.4918136597,49.1950798035],"type":"Point"}
}