{
  "type": "Feature",
  "properties": {
    "iso:country":"DE",
    "sg:address":"Sodenkamp 59",
    "sg:city":"Hamburg",
    "sg:postcode":"22337",
    "sg:province":"Hamburg",
    "wof:name":"Chiron Gmbh & Co. Kg",
    "wof:placetype":"venue"
},
  "geometry": {"coordinates":[10.0575971603,53.631401062],"type":"Point"}
}