{
  "type": "Feature",
  "properties": {
    "iso:country":"DE",
    "sg:address":"Hinter dem Bahnhof 4",
    "sg:city":"Weimar",
    "sg:phone":"+49 3643/420169",
    "sg:postcode":"99427",
    "sg:province":"Th\u00fcringen",
    "wof:name":"Ernst Kraus",
    "wof:placetype":"venue"
},
  "geometry": {"coordinates":[11.3295698166,50.9918212891],"type":"Point"}
}