{
  "type": "Feature",
  "properties": {
    "iso:country":"DE",
    "sg:address":"Industriestr.",
    "sg:city":"Trappenkamp",
    "sg:postcode":"24610",
    "sg:province":"Schleswig-Holstein",
    "wof:name":"Wir Drei Beteiligungs- Gmbh",
    "wof:placetype":"venue"
},
  "geometry": {"coordinates":[10.216901,54.045593],"type":"Point"}
}