{
  "type": "Feature",
  "properties": {
    "iso:country":"DE",
    "sg:address":"F\u00fcssener Str 1",
    "sg:city":"Biessenhofen",
    "sg:phone":"+49 8341/4390",
    "sg:postcode":"87640",
    "sg:province":"Bayern",
    "wof:name":"Nestl\u00e9 Deutschland Ag",
    "wof:placetype":"venue"
},
  "geometry": {"coordinates":[10.642246,47.831879],"type":"Point"}
}