{
  "type": "Feature",
  "properties": {
    "iso:country":"DE",
    "sg:address":"Rheinkaistr. 1",
    "sg:city":"Mannheim",
    "sg:phone":"+49 621/516621",
    "sg:postcode":"68159",
    "sg:province":"Baden-W\u00fcrttemberg",
    "wof:name":"Heinfried Raab",
    "wof:placetype":"venue"
},
  "geometry": {"coordinates":[8.4541044235,49.4854660034],"type":"Point"}
}