{
  "type": "Feature",
  "properties": {
    "iso:country":"DE",
    "sg:address":"Hauptstr. 24",
    "sg:city":"Lehmen",
    "sg:phone":"+49 2607/4031",
    "sg:postcode":"56332",
    "sg:province":"Rheinland-Pfalz",
    "wof:name":"Pension Karl Beginen",
    "wof:placetype":"venue"
},
  "geometry": {"coordinates":[7.4541869164,50.2843742371],"type":"Point"}
}