{
  "type": "Feature",
  "properties": {
    "iso:country":"DE",
    "sg:address":"Glockengasse 2",
    "sg:city":"Burgthann",
    "sg:phone":"+49 9183/1877",
    "sg:postcode":"90559",
    "sg:province":"Bayern",
    "wof:name":"Hans Sch\u00f6nwei\u00df",
    "wof:placetype":"venue"
},
  "geometry": {"coordinates":[11.34291,49.351768],"type":"Point"}
}