{
  "type": "Feature",
  "properties": {
    "iso:country":"DE",
    "sg:address":"Portsloger Damm 9",
    "sg:city":"Edewecht",
    "sg:phone":"+49 4486/1437",
    "sg:postcode":"26188",
    "sg:province":"Niedersachsen",
    "wof:name":"Johann Jan\u00dfen",
    "wof:placetype":"venue"
},
  "geometry": {"coordinates":[7.999323,53.145786],"type":"Point"}
}