{
  "type": "Feature",
  "properties": {
    "iso:country":"DE",
    "sg:address":"Damaschkestr. 7",
    "sg:city":"Ettlingen",
    "sg:phone":"+49 7243/14500",
    "sg:postcode":"76275",
    "sg:province":"Baden-W\u00fcrttemberg",
    "wof:name":"Chr. Dinklage Inh. Krischan Dinklage",
    "wof:placetype":"venue"
},
  "geometry": {"coordinates":[8.3942222595,48.9494285583],"type":"Point"}
}