{
  "type": "Feature",
  "properties": {
    "iso:country":"DE",
    "sg:address":"Funkenburgstr. 1",
    "sg:city":"Leipzig",
    "sg:phone":"+49 341/9832020",
    "sg:postcode":"04105",
    "sg:province":"Sachsen",
    "wof:name":"Reiseb\u00fcro Windrose Gmbh",
    "wof:placetype":"venue"
},
  "geometry": {"coordinates":[12.3630228043,51.3430633545],"type":"Point"}
}