{
  "type": "Feature",
  "properties": {
    "iso:country":"DE",
    "sg:address":"Hof Eich",
    "sg:city":"Linsengericht",
    "sg:phone":"+49 6051/73343",
    "sg:postcode":"63589",
    "sg:province":"Hessen",
    "wof:name":"F. Und K. Scholz",
    "wof:placetype":"venue"
},
  "geometry": {"coordinates":[9.20985,50.16692],"type":"Point"}
}