{
  "type": "Feature",
  "properties": {
    "iso:country":"DE",
    "sg:address":"Arthur-Soltau-Weg 10",
    "sg:city":"Tangstedt",
    "sg:postcode":"22889",
    "sg:province":"Schleswig-Holstein",
    "wof:name":"Schomacker Aktuelle Mode Gmbh & Co. Kg",
    "wof:placetype":"venue"
},
  "geometry": {"coordinates":[10.139465332,53.7526283264],"type":"Point"}
}