{
  "type": "Feature",
  "properties": {
    "iso:country":"DE",
    "sg:address":"Heribertstr 71",
    "sg:city":"Kerpen",
    "sg:phone":"+49 2275/911330",
    "sg:postcode":"50170",
    "sg:province":"Nordrhein-Westfalen",
    "wof:name":"Esm Mertens",
    "wof:placetype":"venue"
},
  "geometry": {"coordinates":[6.584707,50.865871],"type":"Point"}
}