{
  "type": "Feature",
  "properties": {
    "iso:country":"DE",
    "sg:address":"Rolfsb\u00fctteler Str. 8",
    "sg:city":"Hillerse",
    "sg:phone":"+49 5373/2357",
    "sg:postcode":"38543",
    "sg:province":"Niedersachsen",
    "wof:name":"Rolf Busse",
    "wof:placetype":"venue"
},
  "geometry": {"coordinates":[10.402136,52.410236],"type":"Point"}
}