{
  "type": "Feature",
  "properties": {
    "iso:country":"DE",
    "sg:address":"Ruhrstr. 27 a",
    "sg:city":"Arnsberg",
    "sg:phone":"+49 2931/3006",
    "sg:postcode":"59821",
    "sg:province":"Nordrhein-Westfalen",
    "wof:name":"Rainer Finke",
    "wof:placetype":"venue"
},
  "geometry": {"coordinates":[8.065523,51.398232],"type":"Point"}
}