{
  "type": "Feature",
  "properties": {
    "iso:country":"DE",
    "sg:address":"Hafenringstr 1",
    "sg:city":"Osnabr\u00fcck",
    "sg:phone":"+49 541/91410",
    "sg:postcode":"49090",
    "sg:province":"Niedersachsen",
    "wof:name":"Huntsman (germany) Gmbh Osnabr\u00fcck Betriebsst\u00e4tte",
    "wof:placetype":"venue"
},
  "geometry": {"coordinates":[8.0029468536,52.3040962219],"type":"Point"}
}