{
  "type": "Feature",
  "properties": {
    "iso:country":"DE",
    "sg:address":"Turmstr. 1",
    "sg:city":"Hattingen",
    "sg:phone":"+49 2324/42648",
    "sg:postcode":"45529",
    "sg:province":"Nordrhein-Westfalen",
    "wof:name":"Peter Thies",
    "wof:placetype":"venue"
},
  "geometry": {"coordinates":[7.1326599121,51.4036483765],"type":"Point"}
}