{
  "type": "Feature",
  "properties": {
    "iso:country":"DE",
    "sg:address":"Bahnhofstr. 16",
    "sg:city":"Berlin",
    "sg:phone":"+49 30/65260450",
    "sg:postcode":"12555",
    "sg:province":"Berlin",
    "wof:name":"Handycap Bahnhofstr.",
    "wof:placetype":"venue"
},
  "geometry": {"coordinates":[13.5778636932,52.4565124512],"type":"Point"}
}