{
  "type": "Feature",
  "properties": {
    "iso:country":"DE",
    "sg:address":"Valpichlerstr. 29",
    "sg:city":"M\u00fcnchen",
    "sg:phone":"+49 89/586144",
    "sg:postcode":"80686",
    "sg:province":"Bayern",
    "wof:name":"K. Schmidt-winkelhofer Steuerberater",
    "wof:placetype":"venue"
},
  "geometry": {"coordinates":[11.5063562393,48.137096405],"type":"Point"}
}