{
  "type": "Feature",
  "properties": {
    "iso:country":"DE",
    "sg:address":"Bachweg 36",
    "sg:city":"Blaufelden",
    "sg:phone":"+49 7936/204",
    "sg:postcode":"74572",
    "sg:province":"Baden-W\u00fcrttemberg",
    "wof:name":"O. Bauer",
    "wof:placetype":"venue"
},
  "geometry": {"coordinates":[9.892798,49.327942],"type":"Point"}
}