{
  "type": "Feature",
  "properties": {
    "iso:country":"DE",
    "sg:address":"Schulstr. 6",
    "sg:city":"Bad Saulgau",
    "sg:phone":"+49 7581/8739",
    "sg:postcode":"88348",
    "sg:province":"Baden-W\u00fcrttemberg",
    "wof:name":"St\u00e4dt. Galerie Die F\u00e4hre",
    "wof:placetype":"venue"
},
  "geometry": {"coordinates":[9.503259,48.018494],"type":"Point"}
}