{
  "type": "Feature",
  "properties": {
    "iso:country":"DE",
    "sg:address":"Haselnu\u00dfweg 2",
    "sg:city":"Goldenstedt",
    "sg:phone":"+49 4444/96300",
    "sg:postcode":"49424",
    "sg:province":"Niedersachsen",
    "wof:name":"Berding Beton Gmbh",
    "wof:placetype":"venue"
},
  "geometry": {"coordinates":[8.4315338135,52.7845878601],"type":"Point"}
}