{
  "type": "Feature",
  "properties": {
    "iso:country":"DE",
    "sg:address":"Kurt-Schumacher-Str. 80",
    "sg:city":"Mainz",
    "sg:phone":"+49 6131/44486",
    "sg:postcode":"55124",
    "sg:province":"Rheinland-Pfalz",
    "wof:name":"Hans Walter",
    "wof:placetype":"venue"
},
  "geometry": {"coordinates":[8.213401,50.006092],"type":"Point"}
}