{
  "type": "Feature",
  "properties": {
    "iso:country":"DE",
    "sg:address":"Widerholdstr. 39",
    "sg:city":"Singen",
    "sg:phone":"+49 7731/48558",
    "sg:postcode":"78224",
    "sg:province":"Baden-W\u00fcrttemberg",
    "wof:name":"M. Graf",
    "wof:placetype":"venue"
},
  "geometry": {"coordinates":[8.843065,47.76696],"type":"Point"}
}