{
  "type": "Feature",
  "properties": {
    "iso:country":"DE",
    "sg:address":"Buchenstr. 1",
    "sg:city":"Andernach",
    "sg:phone":"+49 2632/30361",
    "sg:postcode":"56626",
    "sg:province":"Rheinland-Pfalz",
    "wof:name":"Plus Gmbh & Co. Ohg",
    "wof:placetype":"venue"
},
  "geometry": {"coordinates":[7.4059400558,50.4203071594],"type":"Point"}
}