{
  "type": "Feature",
  "properties": {
    "iso:country":"DE",
    "sg:address":"Kronenstr. 8",
    "sg:city":"Schwetzingen",
    "sg:phone":"+49 6202/22482",
    "sg:postcode":"68723",
    "sg:province":"Baden-W\u00fcrttemberg",
    "wof:name":"Viet-vo Dao",
    "wof:placetype":"venue"
},
  "geometry": {"coordinates":[8.5688552856,49.3862266541],"type":"Point"}
}