{
  "type": "Feature",
  "properties": {
    "iso:country":"DE",
    "sg:address":"Ringstr. 22a",
    "sg:city":"Liebenburg",
    "sg:postcode":"38704",
    "sg:province":"Niedersachsen",
    "wof:name":"Volksb\u00fccherei",
    "wof:placetype":"venue"
},
  "geometry": {"coordinates":[10.3998,51.97567],"type":"Point"}
}