{
  "type": "Feature",
  "properties": {
    "iso:country":"DE",
    "sg:address":"K\u00fcstenkanalstr. 61",
    "sg:city":"Edewecht",
    "sg:phone":"+49 4405/5698",
    "sg:postcode":"26188",
    "sg:province":"Niedersachsen",
    "wof:name":"Enno Friedrichs",
    "wof:placetype":"venue"
},
  "geometry": {"coordinates":[8.065587,53.090126],"type":"Point"}
}