{
  "type": "Feature",
  "properties": {
    "iso:country":"DE",
    "sg:address":"Marienstr. 88",
    "sg:city":"Minden",
    "sg:phone":"+49 571/40460",
    "sg:postcode":"32425",
    "sg:province":"Nordrhein-Westfalen",
    "wof:name":"Melitta-bentz Kg",
    "wof:placetype":"venue"
},
  "geometry": {"coordinates":[8.916639328,52.3024673462],"type":"Point"}
}