{
  "type": "Feature",
  "properties": {
    "iso:country":"DE",
    "sg:address":"Gerhart-Hauptmann-Str. 17",
    "sg:city":"Gera",
    "sg:phone":"+49 365/23196",
    "sg:postcode":"07546",
    "sg:province":"Th\u00fcringen",
    "wof:name":"T. Ho\u00dfbach",
    "wof:placetype":"venue"
},
  "geometry": {"coordinates":[12.09582901,50.8887863159],"type":"Point"}
}