{
  "type": "Feature",
  "properties": {
    "iso:country":"DE",
    "sg:address":"Kantstr. 5",
    "sg:city":"Bautzen",
    "sg:phone":"+49 3591/603386",
    "sg:postcode":"02625",
    "sg:province":"Sachsen",
    "wof:name":"Enrico Albert",
    "wof:placetype":"venue"
},
  "geometry": {"coordinates":[14.4423828125,51.1825828552],"type":"Point"}
}