{
  "type": "Feature",
  "properties": {
    "iso:country":"DE",
    "sg:address":"Ringstr. 27",
    "sg:city":"Reich",
    "sg:phone":"+49 6761/2735",
    "sg:postcode":"55471",
    "sg:province":"Rheinland-Pfalz",
    "wof:name":"H. P. Kr\u00e4mer Gmbh & Co. Kg",
    "wof:placetype":"venue"
},
  "geometry": {"coordinates":[7.430071,50.000885],"type":"Point"}
}