{
  "type": "Feature",
  "properties": {
    "iso:country":"DE",
    "sg:address":"Kriegsstr. 13",
    "sg:city":"Karlsruhe",
    "sg:postcode":"76137",
    "sg:province":"Baden-W\u00fcrttemberg",
    "wof:name":"Krehl Verwaltungs Gmbh",
    "wof:placetype":"venue"
},
  "geometry": {"coordinates":[8.4000597,49.0053596497],"type":"Point"}
}