{
  "type": "Feature",
  "properties": {
    "iso:country":"DE",
    "sg:address":"Hauptstr. 3",
    "sg:city":"Edewecht",
    "sg:phone":"+49 4405/4319",
    "sg:postcode":"26188",
    "sg:province":"Niedersachsen",
    "wof:name":"Richard Hedemann",
    "wof:placetype":"venue"
},
  "geometry": {"coordinates":[7.987906,53.138096],"type":"Point"}
}