{
  "type": "Feature",
  "properties": {
    "iso:country":"DE",
    "sg:address":"Franz-Kissing-Str 5",
    "sg:city":"Menden",
    "sg:phone":"+49 2373/914797",
    "sg:postcode":"58706",
    "sg:province":"Nordrhein-Westfalen",
    "wof:name":"Inalco Aluminium Gmbh",
    "wof:placetype":"venue"
},
  "geometry": {"coordinates":[7.78445,51.451286],"type":"Point"}
}