{
  "type": "Feature",
  "properties": {
    "iso:country":"DE",
    "sg:address":"Viersener Str. 75",
    "sg:city":"Viersen",
    "sg:postcode":"41751",
    "sg:province":"Nordrhein-Westfalen",
    "wof:name":"Plan Tec Bau Gmbh",
    "wof:placetype":"venue"
},
  "geometry": {"coordinates":[6.34707,51.254581],"type":"Point"}
}