{
  "type": "Feature",
  "properties": {
    "iso:country":"DE",
    "sg:address":"S\u00fc\u00dflingswiesenweg 6",
    "sg:city":"M\u00fchltal",
    "sg:phone":"+49 6151/50910",
    "sg:postcode":"64367",
    "sg:province":"Hessen",
    "wof:name":"Gct Gesellschaft F\u00fcr Computer- Und Netzwerktechnik Mbh",
    "wof:placetype":"venue"
},
  "geometry": {"coordinates":[8.6825323105,49.795539856],"type":"Point"}
}