{
  "type": "Feature",
  "properties": {
    "iso:country":"DE",
    "sg:address":"Viktoriastr. 100",
    "sg:city":"Nordenham",
    "sg:phone":"+49 4731/5845",
    "sg:postcode":"26954",
    "sg:province":"Niedersachsen",
    "wof:name":"B. Grahn",
    "wof:placetype":"venue"
},
  "geometry": {"coordinates":[8.475774,53.497227],"type":"Point"}
}