{
  "type": "Feature",
  "properties": {
    "iso:country":"DE",
    "sg:address":"Schillerstr 55",
    "sg:city":"Zeuthen",
    "sg:phone":"+49 33762/70396",
    "sg:postcode":"15738",
    "sg:province":"Brandenburg",
    "wof:name":"Str\u00fcbing & Braun",
    "wof:placetype":"venue"
},
  "geometry": {"coordinates":[13.6230392456,52.3611602783],"type":"Point"}
}