{
  "type": "Feature",
  "properties": {
    "iso:country":"DE",
    "sg:address":"Bonner Str. 236",
    "sg:city":"K\u00f6ln",
    "sg:phone":"+49 221/3761970",
    "sg:postcode":"50968",
    "sg:province":"Nordrhein-Westfalen",
    "wof:name":"W. Hoffmann",
    "wof:placetype":"venue"
},
  "geometry": {"coordinates":[6.9628200531,50.9092025757],"type":"Point"}
}