{
  "type": "Feature",
  "properties": {
    "iso:country":"DE",
    "sg:address":"Hauptstr. 6",
    "sg:city":"Missen-Wilhams",
    "sg:phone":"+49 8320/346",
    "sg:postcode":"87547",
    "sg:province":"Bayern",
    "wof:name":"G\u00e4stehaus Felix Hold",
    "wof:placetype":"venue"
},
  "geometry": {"coordinates":[10.128531456,47.5964698792],"type":"Point"}
}