{
  "type": "Feature",
  "properties": {
    "iso:country":"DE",
    "sg:address":"Bischofswerdaer Str. 117",
    "sg:city":"Bretnig-Hauswalde",
    "sg:postcode":"01900",
    "sg:province":"Sachsen",
    "wof:name":"Drogerie Kunschmann Inh. I. Stangler",
    "wof:placetype":"venue"
},
  "geometry": {"coordinates":[14.062371,51.148613],"type":"Point"}
}