{
  "type": "Feature",
  "properties": {
    "iso:country":"DE",
    "sg:address":"Oberer Ristchenweg 18-20",
    "sg:city":"Osterode",
    "sg:phone":"+49 5522/4031",
    "sg:postcode":"37520",
    "sg:province":"Niedersachsen",
    "wof:name":"Rolf Markgraf Steuerberater",
    "wof:placetype":"venue"
},
  "geometry": {"coordinates":[10.2594108582,51.7111625671],"type":"Point"}
}