{
  "type": "Feature",
  "properties": {
    "iso:country":"DE",
    "sg:address":"Gro\u00dfe Gartenstr.",
    "sg:city":"Wanzleben",
    "sg:phone":"+49 39209/2308",
    "sg:postcode":"39164",
    "sg:province":"Sachsen-Anhalt",
    "wof:name":"Spa\u00dfbad",
    "wof:placetype":"venue"
},
  "geometry": {"coordinates":[11.4403505325,52.0587005615],"type":"Point"}
}