{
  "type": "Feature",
  "properties": {
    "iso:country":"DE",
    "sg:address":"K\u00f6lner Str. 217",
    "sg:city":"K\u00fcrten",
    "sg:phone":"+49 2268/6359",
    "sg:postcode":"51515",
    "sg:province":"Nordrhein-Westfalen",
    "wof:name":"Arno Zielke",
    "wof:placetype":"venue"
},
  "geometry": {"coordinates":[7.2332601547,51.0520248413],"type":"Point"}
}