{
  "type": "Feature",
  "properties": {
    "iso:country":"DE",
    "sg:address":"Zum Kuhseifen 2",
    "sg:city":"Schleiden",
    "sg:phone":"+49 2445/5651",
    "sg:postcode":"53937",
    "sg:province":"Nordrhein-Westfalen",
    "wof:name":"Max H\u00f6rnchen Gmbh",
    "wof:placetype":"venue"
},
  "geometry": {"coordinates":[6.4679708481,50.5156288147],"type":"Point"}
}