{
  "type": "Feature",
  "properties": {
    "iso:country":"DE",
    "sg:address":"Elisabethstr. 22",
    "sg:city":"D\u00fcsseldorf",
    "sg:phone":"+49 211/386280",
    "sg:postcode":"40217",
    "sg:province":"Nordrhein-Westfalen",
    "wof:name":"Maredo Gastst\u00e4tten Gmbh",
    "wof:placetype":"venue"
},
  "geometry": {"coordinates":[6.7754969597,51.2161178589],"type":"Point"}
}