{
  "type": "Feature",
  "properties": {
    "iso:country":"DE",
    "sg:address":"Johannesstr. 26",
    "sg:city":"Bonn",
    "sg:phone":"+49 228/475621",
    "sg:postcode":"53225",
    "sg:province":"Nordrhein-Westfalen",
    "wof:name":"Osman Karadag",
    "wof:placetype":"venue"
},
  "geometry": {"coordinates":[7.1186599731,50.7340316772],"type":"Point"}
}