{
  "type": "Feature",
  "properties": {
    "iso:country":"DE",
    "sg:address":"Markt 25",
    "sg:city":"Reichenbach",
    "sg:phone":"+49 35828/72926",
    "sg:postcode":"02894",
    "sg:province":"Sachsen",
    "wof:name":"Herbert Kluttig",
    "wof:placetype":"venue"
},
  "geometry": {"coordinates":[14.800544,51.140984],"type":"Point"}
}