{
  "type": "Feature",
  "properties": {
    "iso:country":"DE",
    "sg:address":"Uhlenflucht 17",
    "sg:city":"Holzminden",
    "sg:phone":"+49 5531/7902",
    "sg:postcode":"37603",
    "sg:province":"Niedersachsen",
    "wof:name":"Eberhard Rauls Ingenieur",
    "wof:placetype":"venue"
},
  "geometry": {"coordinates":[9.4511041641,51.8325462341],"type":"Point"}
}