{
  "type": "Feature",
  "properties": {
    "iso:country":"DE",
    "sg:address":"Oderbruchstr. 24a",
    "sg:city":"Neuhardenberg",
    "sg:phone":"+49 33476/566",
    "sg:postcode":"15320",
    "sg:province":"Brandenburg",
    "wof:name":"Flugplatz Wriezen Gmbh",
    "wof:placetype":"venue"
},
  "geometry": {"coordinates":[14.242456,52.603592],"type":"Point"}
}