{
  "type": "Feature",
  "properties": {
    "iso:country":"DE",
    "sg:address":"Tannenweg 11 a",
    "sg:city":"Walldorf",
    "sg:phone":"+49 6227/63044",
    "sg:postcode":"69190",
    "sg:province":"Baden-W\u00fcrttemberg",
    "wof:name":"Haluk \u00d6zden",
    "wof:placetype":"venue"
},
  "geometry": {"coordinates":[8.633603096,49.3106307983],"type":"Point"}
}