{
  "type": "Feature",
  "properties": {
    "iso:country":"DE",
    "sg:address":"Kolpingstr. 5",
    "sg:city":"Breisach",
    "sg:phone":"+49 7667/6600",
    "sg:postcode":"79206",
    "sg:province":"Baden-W\u00fcrttemberg",
    "wof:name":"Orpheus Entertainment Gmbh",
    "wof:placetype":"venue"
},
  "geometry": {"coordinates":[7.589442,48.02985],"type":"Point"}
}