{
  "type": "Feature",
  "properties": {
    "iso:country":"DE",
    "sg:address":"Bernhardstr. 3",
    "sg:city":"Steinen",
    "sg:phone":"+49 7627/8863",
    "sg:postcode":"79585",
    "sg:province":"Baden-W\u00fcrttemberg",
    "wof:name":"Klaus Keller",
    "wof:placetype":"venue"
},
  "geometry": {"coordinates":[7.749454,47.641811],"type":"Point"}
}