{
  "type": "Feature",
  "properties": {
    "iso:country":"DE",
    "sg:address":"Mohn\u00e4ckerstr. 8",
    "sg:city":"Mannheim",
    "sg:postcode":"68259",
    "sg:province":"Baden-W\u00fcrttemberg",
    "wof:name":"Schmidt & Lambio Baugesellschaft Mbh",
    "wof:placetype":"venue"
},
  "geometry": {"coordinates":[8.5468864441,49.4891815186],"type":"Point"}
}