{
  "type": "Feature",
  "properties": {
    "iso:country":"DE",
    "sg:address":"Hauptstr. 88",
    "sg:city":"Merzen",
    "sg:phone":"+49 5466/7220",
    "sg:postcode":"49586",
    "sg:province":"Niedersachsen",
    "wof:name":"Harry E. Baumgart Heilpraktiker",
    "wof:placetype":"venue"
},
  "geometry": {"coordinates":[7.7722821236,52.5041694641],"type":"Point"}
}