{
  "type": "Feature",
  "properties": {
    "iso:country":"DE",
    "sg:address":"K\u00f6nigstr. 19",
    "sg:city":"Torgelow",
    "sg:phone":"+49 3976/202245",
    "sg:postcode":"17358",
    "sg:province":"Mecklenburg-Vorpommern",
    "wof:name":"Gustav-adolf Diekmann",
    "wof:placetype":"venue"
},
  "geometry": {"coordinates":[14.0071144104,53.6307182312],"type":"Point"}
}