{
  "type": "Feature",
  "properties": {
    "iso:country":"DE",
    "sg:address":"Schlo\u00dfstr. 8",
    "sg:city":"Dachau",
    "sg:phone":"+49 8131/4063",
    "sg:postcode":"85221",
    "sg:province":"Bayern",
    "wof:name":"Brauerei Schlossberg Dachau Zweigb. Der Gabriel Sedlmayr",
    "wof:placetype":"venue"
},
  "geometry": {"coordinates":[11.431575,48.259323],"type":"Point"}
}