{
  "type": "Feature",
  "properties": {
    "iso:country":"DE",
    "sg:address":"B\u00e4ckerstr. 6",
    "sg:city":"Schadeleben",
    "sg:postcode":"06449",
    "sg:province":"Sachsen-Anhalt",
    "wof:name":"Compuls Systemhaus Gmbh",
    "wof:placetype":"venue"
},
  "geometry": {"coordinates":[11.3602466583,51.836971283],"type":"Point"}
}