{
  "type": "Feature",
  "properties": {
    "iso:country":"DE",
    "sg:address":"Apostelstr. 12",
    "sg:city":"Sundern",
    "sg:phone":"+49 2393/359",
    "sg:postcode":"59846",
    "sg:province":"Nordrhein-Westfalen",
    "wof:name":"Katholisches Pfarramt St. Antonius Eins.",
    "wof:placetype":"venue"
},
  "geometry": {"coordinates":[7.9521780014,51.2830429077],"type":"Point"}
}