{
  "type": "Feature",
  "properties": {
    "iso:country":"DE",
    "sg:address":"Christian-Keimann-Str. 1a",
    "sg:city":"Zittau",
    "sg:phone":"+49 3583/700260",
    "sg:postcode":"02763",
    "sg:province":"Sachsen",
    "wof:name":"H. Thomas",
    "wof:placetype":"venue"
},
  "geometry": {"coordinates":[14.811976,50.892216],"type":"Point"}
}