{
  "type": "Feature",
  "properties": {
    "iso:country":"DE",
    "sg:address":"Kornbergweg 35",
    "sg:city":"Peine",
    "sg:phone":"+49 5171/6842",
    "sg:postcode":"31224",
    "sg:province":"Niedersachsen",
    "wof:name":"H. Luttkus Rechtsanwalt Und Notar",
    "wof:placetype":"venue"
},
  "geometry": {"coordinates":[10.2270097733,52.3303337097],"type":"Point"}
}