{
  "type": "Feature",
  "properties": {
    "iso:country":"DE",
    "sg:address":"Tostergloper Str. 19",
    "sg:city":"Bleckede",
    "sg:phone":"+49 5854/1053",
    "sg:postcode":"21354",
    "sg:province":"Niedersachsen",
    "wof:name":"Hans-heinrich Schulz",
    "wof:placetype":"venue"
},
  "geometry": {"coordinates":[10.788112,53.240986],"type":"Point"}
}