{
  "type": "Feature",
  "properties": {
    "iso:country":"DE",
    "sg:address":"Engollinger Str. 5",
    "sg:city":"Auerbach",
    "sg:phone":"+49 9901/6497",
    "sg:postcode":"94530",
    "sg:province":"Bayern",
    "wof:name":"Eberhard Hamm Ingenieur",
    "wof:placetype":"venue"
},
  "geometry": {"coordinates":[13.1003437042,48.8026695251],"type":"Point"}
}