{
  "type": "Feature",
  "properties": {
    "iso:country":"DE",
    "sg:address":"Tanneneckweg 13",
    "sg:city":"Ellerau",
    "sg:postcode":"25479",
    "sg:province":"Schleswig-Holstein",
    "wof:name":"Braun & Behrmann Offsetdruck Gmbh",
    "wof:placetype":"venue"
},
  "geometry": {"coordinates":[9.946914,53.759659],"type":"Point"}
}