{
  "type": "Feature",
  "properties": {
    "iso:country":"DE",
    "sg:address":"Wittenberger Str. 25",
    "sg:city":"Torgau",
    "sg:phone":"+49 3421/739097",
    "sg:postcode":"04860",
    "sg:province":"Sachsen",
    "wof:name":"Kampka Rechtsanw\u00e4lte",
    "wof:placetype":"venue"
},
  "geometry": {"coordinates":[12.9994106293,51.560508728],"type":"Point"}
}