{
  "type": "Feature",
  "properties": {
    "iso:country":"DE",
    "sg:address":"Rudolfplatz 8",
    "sg:city":"K\u00f6ln",
    "sg:phone":"+49 221/2573211",
    "sg:postcode":"50674",
    "sg:province":"Nordrhein-Westfalen",
    "wof:name":"Mc Donalds Deutschland",
    "wof:placetype":"venue"
},
  "geometry": {"coordinates":[6.9397721291,50.9368209839],"type":"Point"}
}