{
  "type": "Feature",
  "properties": {
    "iso:country":"DE",
    "sg:address":"Karl-Kotzenberg-Str. 82a",
    "sg:city":"Frankfurt",
    "sg:postcode":"60431",
    "sg:province":"Hessen",
    "wof:name":"Mainperle Verwaltungs- Ag",
    "wof:placetype":"venue"
},
  "geometry": {"coordinates":[8.6488199234,50.1449050903],"type":"Point"}
}