{
  "type": "Feature",
  "properties": {
    "iso:country":"DE",
    "sg:address":"Tammer Str.",
    "sg:city":"Ludwigsburg",
    "sg:phone":"+49 7141/374046",
    "sg:postcode":"71634",
    "sg:province":"Baden-W\u00fcrttemberg",
    "wof:name":"Hettlage Kg",
    "wof:placetype":"venue"
},
  "geometry": {"coordinates":[9.156231,48.911098],"type":"Point"}
}