{
  "type": "Feature",
  "properties": {
    "iso:country":"DE",
    "sg:address":"Bahnhofstr. 40",
    "sg:city":"Ahaus",
    "sg:phone":"+49 2561/40730",
    "sg:postcode":"48683",
    "sg:province":"Nordrhein-Westfalen",
    "wof:name":"Maxim",
    "wof:placetype":"venue"
},
  "geometry": {"coordinates":[7.0107450485,52.078868866],"type":"Point"}
}