{
  "type": "Feature",
  "properties": {
    "iso:country":"DE",
    "sg:address":"Hauptstr. 3",
    "sg:city":"Sonnen",
    "sg:phone":"+49 8584/271",
    "sg:postcode":"94164",
    "sg:province":"Bayern",
    "wof:name":"Kohl & Sohn Gmbh",
    "wof:placetype":"venue"
},
  "geometry": {"coordinates":[13.724587,48.685226],"type":"Point"}
}