{
  "type": "Feature",
  "properties": {
    "iso:country":"DE",
    "sg:address":"Laurentiusstr. 2",
    "sg:city":"Mengerskirchen",
    "sg:phone":"+49 6476/1601",
    "sg:postcode":"35794",
    "sg:province":"Hessen",
    "wof:name":"Johann Jung",
    "wof:placetype":"venue"
},
  "geometry": {"coordinates":[8.2139148712,50.5489997864],"type":"Point"}
}