{
  "type": "Feature",
  "properties": {
    "iso:country":"DE",
    "sg:address":"funspass 1",
    "sg:city":"Wurz",
    "sg:phone":"+49 3525/5555",
    "sg:postcode":"04347",
    "sg:province":"Sachsen",
    "wof:name":"Spiele - Gewinnspiele: Kostenlose Onlinegames",
    "wof:placetype":"venue"
},
  "geometry": {"coordinates":[-69.829277,44.282188],"type":"Point"}
}