{
  "type": "Feature",
  "properties": {
    "iso:country":"DE",
    "sg:address":"Hainstr. 1",
    "sg:city":"Lollar",
    "sg:postcode":"35457",
    "sg:province":"Hessen",
    "wof:name":"Lenze-mobil Verwaltungsges. Mbh",
    "wof:placetype":"venue"
},
  "geometry": {"coordinates":[8.684756,50.683968],"type":"Point"}
}