{
  "type": "Feature",
  "properties": {
    "iso:country":"DE",
    "sg:address":"Kirchplatz 7",
    "sg:city":"Durbach",
    "sg:phone":"+49 781/41366",
    "sg:postcode":"77770",
    "sg:province":"Baden-W\u00fcrttemberg",
    "wof:name":"Kath. Pfarramt St. Heinrich",
    "wof:placetype":"venue"
},
  "geometry": {"coordinates":[8.0160560608,48.4957008362],"type":"Point"}
}