{
  "type": "Feature",
  "properties": {
    "iso:country":"DE",
    "sg:address":"Biberweg 5",
    "sg:city":"Troisdorf",
    "sg:phone":"+49 2241/402012",
    "sg:postcode":"53842",
    "sg:province":"Nordrhein-Westfalen",
    "wof:name":"Gebr. Ridder Gmbh",
    "wof:placetype":"venue"
},
  "geometry": {"coordinates":[7.1088781357,50.8287162781],"type":"Point"}
}