{
  "type": "Feature",
  "properties": {
    "iso:country":"DE",
    "sg:address":"Ringstr 31",
    "sg:city":"Wut\u00f6schingen",
    "sg:phone":"+49 7746/91155",
    "sg:postcode":"79793",
    "sg:province":"Baden-W\u00fcrttemberg",
    "wof:name":"Eu Con Unternehmensberatung Gmbh",
    "wof:placetype":"venue"
},
  "geometry": {"coordinates":[8.371859,47.665279],"type":"Point"}
}