{
  "type": "Feature",
  "properties": {
    "iso:country":"DE",
    "sg:address":"Goorsdorferstr.61",
    "sg:city":"Rostock",
    "sg:phone":"+49 381/2005208",
    "sg:postcode":"18146",
    "sg:province":"Mecklenburg-Vorpommern",
    "wof:name":"Der 1. Kscr Begr\u00fc\u00dft Alle User",
    "wof:placetype":"venue"
},
  "geometry": {"coordinates":[12.16817,54.121368],"type":"Point"}
}