{
  "type": "Feature",
  "properties": {
    "iso:country":"DE",
    "sg:address":"K\u00f6nigstr. 11",
    "sg:city":"Ehningen",
    "sg:phone":"+49 7034/7539",
    "sg:postcode":"71139",
    "sg:province":"Baden-W\u00fcrttemberg",
    "wof:name":"E. Stahl",
    "wof:placetype":"venue"
},
  "geometry": {"coordinates":[8.945494,48.660625],"type":"Point"}
}