{
  "type": "Feature",
  "properties": {
    "iso:country":"DE",
    "sg:address":"Bahnhofstr. 3",
    "sg:city":"Wedemark",
    "sg:phone":"+49 5130/79712",
    "sg:postcode":"30900",
    "sg:province":"Niedersachsen",
    "wof:name":"Restaurant Syrtaki",
    "wof:placetype":"venue"
},
  "geometry": {"coordinates":[9.7543354034,52.5221214294],"type":"Point"}
}