{
  "type": "Feature",
  "properties": {
    "iso:country":"DE",
    "sg:address":"Hafenstr. 10a",
    "sg:city":"N\u00fcrnberg",
    "sg:phone":"+49 911/6427383",
    "sg:postcode":"90451",
    "sg:province":"Bayern",
    "wof:name":"S\u00fc\u00dfer Laden S\u00fc\u00dfwaren Und Spirituosen Gmbh",
    "wof:placetype":"venue"
},
  "geometry": {"coordinates":[11.036866188,49.4077072144],"type":"Point"}
}