{
  "type": "Feature",
  "properties": {
    "iso:country":"DE",
    "sg:address":"Parkallee 36",
    "sg:city":"Bremen",
    "sg:phone":"+49 421/341347",
    "sg:postcode":"28209",
    "sg:province":"Bremen",
    "wof:name":"Ernst Matzke",
    "wof:placetype":"venue"
},
  "geometry": {"coordinates":[8.822931,53.083237],"type":"Point"}
}