{
  "type": "Feature",
  "properties": {
    "iso:country":"DE",
    "sg:address":"Windscheidstr. 16",
    "sg:city":"Berlin",
    "sg:phone":"+49 30/3237827",
    "sg:postcode":"10627",
    "sg:province":"Berlin",
    "wof:name":"Dr. Med. Eva Plewa \u00c4rztin F\u00fcr Allgemeinmedizin",
    "wof:placetype":"venue"
},
  "geometry": {"coordinates":[13.2993297577,52.5058021545],"type":"Point"}
}