{
  "type": "Feature",
  "properties": {
    "iso:country":"DE",
    "sg:address":"Daimlerstr. 11",
    "sg:city":"Steinen",
    "sg:phone":"+49 7627/2330",
    "sg:postcode":"79585",
    "sg:province":"Baden-W\u00fcrttemberg",
    "wof:name":"Langehein Frisch-men\u00fc- Party-service Gmbh",
    "wof:placetype":"venue"
},
  "geometry": {"coordinates":[7.731061,47.640499],"type":"Point"}
}