{
  "type": "Feature",
  "properties": {
    "iso:country":"DE",
    "sg:address":"Markgr\u00f6ninger Str. 136",
    "sg:city":"Ludwigsburg",
    "sg:phone":"+49 7141/31892",
    "sg:postcode":"71634",
    "sg:province":"Baden-W\u00fcrttemberg",
    "wof:name":"Walter Kohler",
    "wof:placetype":"venue"
},
  "geometry": {"coordinates":[9.1565217972,48.9047966003],"type":"Point"}
}