{
  "type": "Feature",
  "properties": {
    "iso:country":"DE",
    "sg:address":"Forststr. 39",
    "sg:city":"Braunschweig",
    "sg:phone":"+49 531/351178",
    "sg:postcode":"38108",
    "sg:province":"Niedersachsen",
    "wof:name":"Hans Sandbrink",
    "wof:placetype":"venue"
},
  "geometry": {"coordinates":[10.5485229492,52.3020057678],"type":"Point"}
}