{
  "type": "Feature",
  "properties": {
    "iso:country":"DE",
    "sg:address":"Staffelhof 15",
    "sg:city":"Petersberg",
    "sg:phone":"+49 6331/97451",
    "sg:postcode":"66989",
    "sg:province":"Rheinland-Pfalz",
    "wof:name":"Waltraud Dinies",
    "wof:placetype":"venue"
},
  "geometry": {"coordinates":[7.5794239044,49.2323684692],"type":"Point"}
}