{
  "type": "Feature",
  "properties": {
    "iso:country":"DE",
    "sg:address":"Hermannstr. 4",
    "sg:city":"Melle",
    "sg:phone":"+49 5429/1555",
    "sg:postcode":"49326",
    "sg:province":"Niedersachsen",
    "wof:name":"C. Und Rosy Grothaus",
    "wof:placetype":"venue"
},
  "geometry": {"coordinates":[8.264501,52.163246],"type":"Point"}
}