{
  "type": "Feature",
  "properties": {
    "iso:country":"DE",
    "sg:address":"Am Kocherberg 3",
    "sg:city":"Neuenstadt",
    "sg:phone":"+49 7139/453464",
    "sg:postcode":"74196",
    "sg:province":"Baden-W\u00fcrttemberg",
    "wof:name":"Katharina Horvath",
    "wof:placetype":"venue"
},
  "geometry": {"coordinates":[9.30376,49.242538],"type":"Point"}
}