{
  "type": "Feature",
  "properties": {
    "iso:country":"DE",
    "sg:address":"Adam-Hoffmann-Str. 1",
    "sg:city":"Kaiserslautern",
    "sg:phone":"+49 631/3609317",
    "sg:postcode":"67657",
    "sg:province":"Rheinland-Pfalz",
    "wof:name":"Werbung, Webdesign, Firmenausstattungen",
    "wof:placetype":"venue"
},
  "geometry": {"coordinates":[7.7848,49.454308],"type":"Point"}
}