{
  "type": "Feature",
  "properties": {
    "iso:country":"DE",
    "sg:address":"Hochstr. 36",
    "sg:city":"Herbstein",
    "sg:phone":"+49 6647/374",
    "sg:postcode":"36358",
    "sg:province":"Hessen",
    "wof:name":"Medico Laborservice Peter Kinkel",
    "wof:placetype":"venue"
},
  "geometry": {"coordinates":[9.4525928497,50.5645294189],"type":"Point"}
}