{
  "type": "Feature",
  "properties": {
    "iso:country":"DE",
    "sg:address":"Eichenallee 24",
    "sg:city":"Gr\u00fcnheide",
    "sg:phone":"+49 3362/6139",
    "sg:postcode":"15537",
    "sg:province":"Brandenburg",
    "wof:name":"G. Lehmann",
    "wof:placetype":"venue"
},
  "geometry": {"coordinates":[13.802091,52.417164],"type":"Point"}
}