{
  "type": "Feature",
  "properties": {
    "iso:country":"DE",
    "sg:address":"Markt 15",
    "sg:city":"Eltville",
    "sg:phone":"+49 6123/899462",
    "sg:postcode":"65346",
    "sg:province":"Hessen",
    "wof:name":"Schantl Pharma Service Gmbh",
    "wof:placetype":"venue"
},
  "geometry": {"coordinates":[8.0946083069,50.0201950073],"type":"Point"}
}