{
  "type": "Feature",
  "properties": {
    "iso:country":"DE",
    "sg:address":"Humboldtstr. 3",
    "sg:city":"Leverkusen",
    "sg:phone":"+49 2171/44095",
    "sg:postcode":"51379",
    "sg:province":"Nordrhein-Westfalen",
    "wof:name":"Rainer Diele Finanzberater",
    "wof:placetype":"venue"
},
  "geometry": {"coordinates":[7.0056810379,51.0664100647],"type":"Point"}
}