{
  "type": "Feature",
  "properties": {
    "iso:country":"DE",
    "sg:address":"Eichendorffstr. 34",
    "sg:city":"Olpe",
    "sg:phone":"+49 2761/4545",
    "sg:postcode":"57462",
    "sg:province":"Nordrhein-Westfalen",
    "wof:name":"Otto Grebe",
    "wof:placetype":"venue"
},
  "geometry": {"coordinates":[7.844482,51.020161],"type":"Point"}
}