{
  "type": "Feature",
  "properties": {
    "iso:country":"DE",
    "sg:address":"Kasinostr. 35",
    "sg:city":"Frankfurt",
    "sg:phone":"+49 69/301072",
    "sg:postcode":"65929",
    "sg:province":"Hessen",
    "wof:name":"David Court Rechtsanwalt",
    "wof:placetype":"venue"
},
  "geometry": {"coordinates":[8.5483369827,50.1025314331],"type":"Point"}
}