{
  "type": "Feature",
  "properties": {
    "iso:country":"DE",
    "sg:address":"Grenzm\u00fchle 2",
    "sg:city":"Marquartstein",
    "sg:phone":"+49 8641/8225",
    "sg:postcode":"83250",
    "sg:province":"Bayern",
    "wof:name":"Elektrizit\u00e4tswerk Gr\u00e4nzm\u00fchle",
    "wof:placetype":"venue"
},
  "geometry": {"coordinates":[12.46753,47.754959],"type":"Point"}
}