{
  "type": "Feature",
  "properties": {
    "iso:country":"DE",
    "sg:address":"Nelkenweg 16",
    "sg:city":"Kamp-Lintfort",
    "sg:phone":"+49 2842/81993",
    "sg:postcode":"47475",
    "sg:province":"Nordrhein-Westfalen",
    "wof:name":"F. M\u00f6lders Immobilienmakler",
    "wof:placetype":"venue"
},
  "geometry": {"coordinates":[6.519797802,51.4989891052],"type":"Point"}
}