{
  "type": "Feature",
  "properties": {
    "iso:country":"DE",
    "sg:address":"Burgh\u00f6lzli 12",
    "sg:city":"Weil am Rhein",
    "sg:phone":"+49 7621/62184",
    "sg:postcode":"79576",
    "sg:province":"Baden-W\u00fcrttemberg",
    "wof:name":"Vereins- Sportgastst\u00e4tte Fv",
    "wof:placetype":"venue"
},
  "geometry": {"coordinates":[7.6044211388,47.6053390503],"type":"Point"}
}