{
  "type": "Feature",
  "properties": {
    "iso:country":"DE",
    "sg:address":"Daubaer Str. 7",
    "sg:city":"Lohmen",
    "sg:phone":"+49 3501/588169",
    "sg:postcode":"01847",
    "sg:province":"Sachsen",
    "wof:name":"Rekobau Pirna Gmbh",
    "wof:placetype":"venue"
},
  "geometry": {"coordinates":[13.989417,50.992222],"type":"Point"}
}