{
  "type": "Feature",
  "properties": {
    "iso:country":"DE",
    "sg:address":"Paul-Neumann-Str. 52",
    "sg:city":"Potsdam",
    "sg:postcode":"14482",
    "sg:province":"Brandenburg",
    "wof:name":"Besucher- Und Touristenservice Inh. Gabriele Tober",
    "wof:placetype":"venue"
},
  "geometry": {"coordinates":[13.1078062057,52.3877220154],"type":"Point"}
}