{
  "type": "Feature",
  "properties": {
    "iso:country":"DE",
    "sg:address":"Karlshafener Str. 12",
    "sg:city":"Reinhardshagen",
    "sg:phone":"+49 5544/95030",
    "sg:postcode":"34359",
    "sg:province":"Hessen",
    "wof:name":"K. Sallwey",
    "wof:placetype":"venue"
},
  "geometry": {"coordinates":[9.6023845673,51.4942932129],"type":"Point"}
}