{
  "type": "Feature",
  "properties": {
    "iso:country":"DE",
    "sg:address":"Schaftrift 4",
    "sg:city":"Geschwenda",
    "sg:postcode":"98716",
    "sg:province":"Th\u00fcringen",
    "wof:name":"Rolands Homepage",
    "wof:placetype":"venue"
},
  "geometry": {"coordinates":[10.823349,50.731796],"type":"Point"}
}