{
  "type": "Feature",
  "properties": {
    "iso:country":"DE",
    "sg:address":"Friedrichstr. 16",
    "sg:city":"Bad Steben",
    "sg:phone":"+49 9288/6494",
    "sg:postcode":"95138",
    "sg:province":"Bayern",
    "wof:name":"Zur Tenne",
    "wof:placetype":"venue"
},
  "geometry": {"coordinates":[11.642865181,50.365524292],"type":"Point"}
}