{
  "type": "Feature",
  "properties": {
    "iso:country":"DE",
    "sg:address":"Bahnhofstr. 25",
    "sg:city":"G\u00f6ppingen",
    "sg:phone":"+49 7161/70456",
    "sg:postcode":"73033",
    "sg:province":"Baden-W\u00fcrttemberg",
    "wof:name":"Parkhaus G\u00f6ppingen Gmbh & Co.",
    "wof:placetype":"venue"
},
  "geometry": {"coordinates":[9.649274826,48.7022018433],"type":"Point"}
}