{
  "type": "Feature",
  "properties": {
    "iso:country":"DE",
    "sg:address":"Karl-Marx-Str. 6 a",
    "sg:city":"Plaidt",
    "sg:phone":"+49 2632/5750",
    "sg:postcode":"56637",
    "sg:province":"Rheinland-Pfalz",
    "wof:name":"Betti Pauli",
    "wof:placetype":"venue"
},
  "geometry": {"coordinates":[7.3984627724,50.3914489746],"type":"Point"}
}