{
  "type": "Feature",
  "properties": {
    "iso:country":"DE",
    "sg:address":"Industriestr. 11",
    "sg:city":"Ergolding",
    "sg:phone":"+49 871/79552",
    "sg:postcode":"84030",
    "sg:province":"Bayern",
    "wof:name":"Hess Baby Und Kind Happy Lady E. K.",
    "wof:placetype":"venue"
},
  "geometry": {"coordinates":[12.1633605957,48.5634231567],"type":"Point"}
}