{
  "type": "Feature",
  "properties": {
    "iso:country":"DE",
    "sg:address":"Augustastr. 20",
    "sg:city":"Siegburg",
    "sg:phone":"+49 2241/62288",
    "sg:postcode":"53721",
    "sg:province":"Nordrhein-Westfalen",
    "wof:name":"Movie Kino",
    "wof:placetype":"venue"
},
  "geometry": {"coordinates":[7.2008638382,50.802822113],"type":"Point"}
}