{
  "type": "Feature",
  "properties": {
    "iso:country":"DE",
    "sg:address":"Olgastrasse",
    "sg:city":"Bad Wildbad",
    "sg:postcode":"75323",
    "sg:province":"Baden-W\u00fcrttemberg",
    "wof:name":"Synergie",
    "wof:placetype":"venue"
},
  "geometry": {"coordinates":[8.5483617783,48.7438354492],"type":"Point"}
}