{
  "type": "Feature",
  "properties": {
    "iso:country":"DE",
    "sg:address":"Danziger Str. 5",
    "sg:city":"Bruck",
    "sg:phone":"+49 9434/2090",
    "sg:postcode":"92436",
    "sg:province":"Bayern",
    "wof:name":"Altenheim St. Elisabeth",
    "wof:placetype":"venue"
},
  "geometry": {"coordinates":[12.302344,49.24958],"type":"Point"}
}