{
  "type": "Feature",
  "properties": {
    "iso:country":"DE",
    "sg:address":"Max-Stromeyer-Str. 170 d",
    "sg:city":"Konstanz",
    "sg:phone":"+49 7531/9920",
    "sg:postcode":"78467",
    "sg:province":"Baden-W\u00fcrttemberg",
    "wof:name":"Henry Schein-dentina Gmbh",
    "wof:placetype":"venue"
},
  "geometry": {"coordinates":[9.152188,47.679462],"type":"Point"}
}