{
  "type": "Feature",
  "properties": {
    "iso:country":"DE",
    "sg:address":"Bienerstr. 51",
    "sg:city":"Hofheim",
    "sg:postcode":"65719",
    "sg:province":"Hessen",
    "wof:name":"Creaktiv - Modedesign Bramm Gmbh",
    "wof:placetype":"venue"
},
  "geometry": {"coordinates":[8.4533519745,50.0952835083],"type":"Point"}
}