{
  "type": "Feature",
  "properties": {
    "iso:country":"DE",
    "sg:address":"Josefstr. 18",
    "sg:city":"Herten",
    "sg:phone":"+49 2366/88028",
    "sg:postcode":"45699",
    "sg:province":"Nordrhein-Westfalen",
    "wof:name":"Peter Wernitz Rechtsanwalt",
    "wof:placetype":"venue"
},
  "geometry": {"coordinates":[7.1529259682,51.6025428772],"type":"Point"}
}