{
  "type": "Feature",
  "properties": {
    "iso:country":"DE",
    "sg:address":"Elleringhauser Str. 57",
    "sg:city":"Olsberg",
    "sg:phone":"+49 2962/2451",
    "sg:postcode":"59939",
    "sg:province":"Nordrhein-Westfalen",
    "wof:name":"Haus Keuthen",
    "wof:placetype":"venue"
},
  "geometry": {"coordinates":[8.5339202881,51.34765625],"type":"Point"}
}