{
  "type": "Feature",
  "properties": {
    "iso:country":"DE",
    "sg:address":"Am Bahnhof 34a",
    "sg:city":"Heldrungen",
    "sg:postcode":"06577",
    "sg:province":"Th\u00fcringen",
    "wof:name":"Wohnungsgenossenschaft Thomas M\u00fcntzer Eg",
    "wof:placetype":"venue"
},
  "geometry": {"coordinates":[11.188659668,51.2996788025],"type":"Point"}
}