{
  "type": "Feature",
  "properties": {
    "iso:country":"DE",
    "sg:address":"Markt 18",
    "sg:city":"Ahaus",
    "sg:phone":"+49 2561/2127",
    "sg:postcode":"48683",
    "sg:province":"Nordrhein-Westfalen",
    "wof:name":"Modissa Moden",
    "wof:placetype":"venue"
},
  "geometry": {"coordinates":[7.006804,52.075783],"type":"Point"}
}