{
  "type": "Feature",
  "properties": {
    "iso:country":"DE",
    "sg:address":"Morkener Str. 62",
    "sg:city":"Bedburg",
    "sg:phone":"+49 2272/2570",
    "sg:postcode":"50181",
    "sg:province":"Nordrhein-Westfalen",
    "wof:name":"Willibert Granderath",
    "wof:placetype":"venue"
},
  "geometry": {"coordinates":[6.5459971428,51.0011520386],"type":"Point"}
}