{
  "type": "Feature",
  "properties": {
    "iso:country":"DE",
    "sg:address":"R\u00f6dingsmarkt 52",
    "sg:city":"Hamburg",
    "sg:postcode":"20459",
    "sg:province":"Hamburg",
    "wof:name":"Poldergesellschaft Neum\u00fchlen-westkai Mbh",
    "wof:placetype":"venue"
},
  "geometry": {"coordinates":[9.984285,53.545628],"type":"Point"}
}