{
  "type": "Feature",
  "properties": {
    "iso:country":"DE",
    "sg:address":"Georgenstr. 38",
    "sg:city":"M\u00fcnchen",
    "sg:phone":"+49 89/3899910",
    "sg:postcode":"80799",
    "sg:province":"Bayern",
    "wof:name":"Corsica & Sardinia Ferries Gmbh",
    "wof:placetype":"venue"
},
  "geometry": {"coordinates":[11.577378273,48.1550254822],"type":"Point"}
}