{
  "type": "Feature",
  "properties": {
    "iso:country":"DE",
    "sg:address":"Im Wei\u00dfen Moor 19",
    "sg:city":"Seth",
    "sg:phone":"+49 4194/7036",
    "sg:postcode":"23845",
    "sg:province":"Schleswig-Holstein",
    "wof:name":"H. J\u00fcrgen Muu\u00df",
    "wof:placetype":"venue"
},
  "geometry": {"coordinates":[10.165854454,53.85131073],"type":"Point"}
}