{
  "type": "Feature",
  "properties": {
    "iso:country":"DE",
    "sg:address":"Bahnhofstr. 10",
    "sg:city":"Platten",
    "sg:phone":"+49 6535/7103",
    "sg:postcode":"54518",
    "sg:province":"Rheinland-Pfalz",
    "wof:name":"Ludwig Becker",
    "wof:placetype":"venue"
},
  "geometry": {"coordinates":[6.950416,49.950642],"type":"Point"}
}