{
  "type": "Feature",
  "properties": {
    "iso:country":"DE",
    "sg:address":"Aum\u00fchle 3",
    "sg:city":"\u00dcbersee",
    "sg:phone":"+49 8642/5000",
    "sg:postcode":"83236",
    "sg:province":"Bayern",
    "wof:name":"Weyerer Immobilienmakler",
    "wof:placetype":"venue"
},
  "geometry": {"coordinates":[12.4814291,47.8119430542],"type":"Point"}
}