{
  "type": "Feature",
  "properties": {
    "iso:country":"DE",
    "sg:address":"Postfach 3080:: 24029 Kiel:: Germany.^^Muhliusstrasse 38::",
    "sg:city":"Kiel",
    "sg:postcode":"24103",
    "sg:province":"Schleswig-Holstein",
    "wof:name":"Business Angel Venture Gmbh",
    "wof:placetype":"venue"
},
  "geometry": {"coordinates":[8.68342,50.112041],"type":"Point"}
}