{
  "type": "Feature",
  "properties": {
    "iso:country":"DE",
    "sg:address":"Schule",
    "sg:city":"Reilingen",
    "sg:postcode":"68799",
    "sg:province":"Baden-W\u00fcrttemberg",
    "wof:name":"Gemeindebibliothek",
    "wof:placetype":"venue"
},
  "geometry": {"coordinates":[8.571835,49.2948],"type":"Point"}
}