{
  "type": "Feature",
  "properties": {
    "iso:country":"DE",
    "sg:address":"Castroper Str. 154",
    "sg:city":"Datteln",
    "sg:phone":"+49 2363/62211",
    "sg:postcode":"45711",
    "sg:province":"Nordrhein-Westfalen",
    "wof:name":"A. Schmidt",
    "wof:placetype":"venue"
},
  "geometry": {"coordinates":[7.334373951,51.6412277222],"type":"Point"}
}