{
  "type": "Feature",
  "properties": {
    "iso:country":"DE",
    "sg:address":"Wahlener Str. 69",
    "sg:city":"Losheim",
    "sg:phone":"+49 6872/4744",
    "sg:postcode":"66679",
    "sg:province":"Saarland",
    "wof:name":"Elke Biehl",
    "wof:placetype":"venue"
},
  "geometry": {"coordinates":[6.7770757675,49.4881401062],"type":"Point"}
}