{
  "type": "Feature",
  "properties": {
    "iso:country":"DE",
    "sg:address":"Rastdorfer Str. 100",
    "sg:city":"Spahnharrenst\u00e4tte",
    "sg:phone":"+49 5956/1257",
    "sg:postcode":"49751",
    "sg:province":"Niedersachsen",
    "wof:name":"Johann Heitmann",
    "wof:placetype":"venue"
},
  "geometry": {"coordinates":[7.51968,52.841091],"type":"Point"}
}