{
  "type": "Feature",
  "properties": {
    "iso:country":"DE",
    "sg:address":"Kaiserstr. 50",
    "sg:city":"Frankfurt",
    "sg:phone":"+49 69/230498",
    "sg:postcode":"60329",
    "sg:province":"Hessen",
    "wof:name":"Union Tours Gmbh",
    "wof:placetype":"venue"
},
  "geometry": {"coordinates":[8.6689720154,50.1086807251],"type":"Point"}
}