{
  "type": "Feature",
  "properties": {
    "iso:country":"DE",
    "sg:address":"Pf\u00e4hlerstr. 26",
    "sg:city":"Saarbr\u00fccken",
    "sg:phone":"+49 681/700111",
    "sg:postcode":"66128",
    "sg:province":"Saarland",
    "wof:name":"Dr. Med. Eberhard Herrmann",
    "wof:placetype":"venue"
},
  "geometry": {"coordinates":[6.9213728905,49.2330169678],"type":"Point"}
}