{
  "type": "Feature",
  "properties": {
    "iso:country":"DE",
    "sg:address":"Raabstr. 10",
    "sg:city":"N\u00fcrnberg",
    "sg:phone":"+49 911/3262153",
    "sg:postcode":"90429",
    "sg:province":"Bayern",
    "wof:name":"G\u00fcnther Hoinka",
    "wof:placetype":"venue"
},
  "geometry": {"coordinates":[11.0323991776,49.4592819214],"type":"Point"}
}