{
  "type": "Feature",
  "properties": {
    "iso:country":"DE",
    "sg:address":"Gartenstr. 4",
    "sg:city":"Sch\u00f6ffengrund",
    "sg:phone":"+49 6445/5648",
    "sg:postcode":"35641",
    "sg:province":"Hessen",
    "wof:name":"Isofloc-fachbetrieb",
    "wof:placetype":"venue"
},
  "geometry": {"coordinates":[8.495465,50.487968],"type":"Point"}
}