{
  "type": "Feature",
  "properties": {
    "iso:country":"DE",
    "sg:address":"Bachstr 6",
    "sg:city":"Hanau",
    "sg:phone":"+49 6181/98620",
    "sg:postcode":"63452",
    "sg:province":"Hessen",
    "wof:name":"Fcc Financial & Corporate Communications Gmbh",
    "wof:placetype":"venue"
},
  "geometry": {"coordinates":[8.897088,50.142361],"type":"Point"}
}