{
  "type": "Feature",
  "properties": {
    "iso:country":"DE",
    "sg:address":"Eisenh\u00e4user Str. 67",
    "sg:city":"Steffenberg",
    "sg:phone":"+49 6464/5555",
    "sg:postcode":"35239",
    "sg:province":"Hessen",
    "wof:name":"Bz Therapie- Wohn- Und Pflegegruppen Gmbh",
    "wof:placetype":"venue"
},
  "geometry": {"coordinates":[8.480253,50.832161],"type":"Point"}
}