{
  "type": "Feature",
  "properties": {
    "iso:country":"DE",
    "sg:address":"Wolfschartstr. 2",
    "sg:city":"Langenweddingen",
    "sg:phone":"+49 39205/23002",
    "sg:postcode":"39171",
    "sg:province":"Sachsen-Anhalt",
    "wof:name":"Hannes Bierstube",
    "wof:placetype":"venue"
},
  "geometry": {"coordinates":[11.5270738602,52.0368041992],"type":"Point"}
}