{
  "type": "Feature",
  "properties": {
    "iso:country":"DE",
    "sg:address":"Telgweg 14",
    "sg:city":"Geeste",
    "sg:phone":"+49 5937/390",
    "sg:postcode":"49744",
    "sg:province":"Niedersachsen",
    "wof:name":"Heinrich Coppenrath",
    "wof:placetype":"venue"
},
  "geometry": {"coordinates":[7.233181,52.622353],"type":"Point"}
}