{
  "type": "Feature",
  "properties": {
    "iso:country":"DE",
    "sg:address":"Nolteweg 12",
    "sg:city":"Hunderdorf",
    "sg:phone":"+49 9422/6211",
    "sg:postcode":"94336",
    "sg:province":"Bayern",
    "wof:name":"Ks Komfort Schlaf",
    "wof:placetype":"venue"
},
  "geometry": {"coordinates":[12.729852,48.947628],"type":"Point"}
}