{
  "type": "Feature",
  "properties": {
    "iso:country":"DE",
    "sg:address":"Lucknerstr. 8",
    "sg:city":"Leipzig",
    "sg:phone":"+49 341/4616650",
    "sg:postcode":"04159",
    "sg:province":"Sachsen",
    "wof:name":"Helmut Hoffmann",
    "wof:placetype":"venue"
},
  "geometry": {"coordinates":[12.326171,51.373554],"type":"Point"}
}