{
  "type": "Feature",
  "properties": {
    "iso:country":"DE",
    "sg:address":"Aphovener Str. 15",
    "sg:city":"Heinsberg",
    "sg:phone":"+49 2452/7492",
    "sg:postcode":"52525",
    "sg:province":"Nordrhein-Westfalen",
    "wof:name":"Laurenz Jenni\u00dfen",
    "wof:placetype":"venue"
},
  "geometry": {"coordinates":[6.083383,51.06786],"type":"Point"}
}