{
  "type": "Feature",
  "properties": {
    "iso:country":"DE",
    "sg:address":"Kirchenallee 34-36",
    "sg:city":"Hamburg",
    "sg:phone":"+49 40/2801201",
    "sg:postcode":"20099",
    "sg:province":"Hamburg",
    "wof:name":"Hertz Gmbh",
    "wof:placetype":"venue"
},
  "geometry": {"coordinates":[10.008255,53.554951],"type":"Point"}
}