{
  "type": "Feature",
  "properties": {
    "iso:country":"DE",
    "sg:address":"Sybelstr. 73",
    "sg:city":"Essen",
    "sg:phone":"+49 201/705617",
    "sg:postcode":"45145",
    "sg:province":"Nordrhein-Westfalen",
    "wof:name":"Sybelsch\u00e4nke",
    "wof:placetype":"venue"
},
  "geometry": {"coordinates":[6.9752459526,51.4485168457],"type":"Point"}
}