{
  "type": "Feature",
  "properties": {
    "iso:country":"DE",
    "sg:address":"Dr.-B\u00f6ckler-Str. 1",
    "sg:city":"Kirchheim",
    "sg:phone":"+49 9366/1867",
    "sg:postcode":"97268",
    "sg:province":"Bayern",
    "wof:name":"Erich Heinzmann Elektroinstallation",
    "wof:placetype":"venue"
},
  "geometry": {"coordinates":[9.853805,49.655785],"type":"Point"}
}