{
  "type": "Feature",
  "properties": {
    "iso:country":"DE",
    "sg:address":"Friedhofstr. 10",
    "sg:city":"Oberhausen",
    "sg:phone":"+49 6362/8779",
    "sg:postcode":"67822",
    "sg:province":"Rheinland-Pfalz",
    "wof:name":"Klaus Klock",
    "wof:placetype":"venue"
},
  "geometry": {"coordinates":[7.8029808998,49.6955604553],"type":"Point"}
}