{
  "type": "Feature",
  "properties": {
    "iso:country":"DE",
    "sg:address":"Burgstr 9",
    "sg:city":"M\u00fclheim-K\u00e4rlich",
    "sg:phone":"+49 2630/94410",
    "sg:postcode":"56218",
    "sg:province":"Rheinland-Pfalz",
    "wof:name":"K\u00e4rlicher Ton- Und Schamotte-werk Mannheim & Co Kg",
    "wof:placetype":"venue"
},
  "geometry": {"coordinates":[7.48563,50.388538],"type":"Point"}
}