{
  "type": "Feature",
  "properties": {
    "iso:country":"DE",
    "sg:address":"Dorf-Hauptstr. 14",
    "sg:city":"Bernau",
    "sg:phone":"+49 7675/383",
    "sg:postcode":"79872",
    "sg:province":"Baden-W\u00fcrttemberg",
    "wof:name":"M. Paulus",
    "wof:placetype":"venue"
},
  "geometry": {"coordinates":[8.0321321487,47.8088645935],"type":"Point"}
}