{
  "type": "Feature",
  "properties": {
    "iso:country":"DE",
    "sg:address":"Archstr. 15",
    "sg:city":"Garmisch-Partenkirchen",
    "sg:phone":"+49 8821/93390",
    "sg:postcode":"82467",
    "sg:province":"Bayern",
    "wof:name":"Monika Riesch Riga-plast",
    "wof:placetype":"venue"
},
  "geometry": {"coordinates":[11.0675420761,47.4885177612],"type":"Point"}
}