{
  "type": "Feature",
  "properties": {
    "iso:country":"DE",
    "sg:address":"Herrntrop 46",
    "sg:city":"Kirchhundem",
    "sg:phone":"+49 2723/929050",
    "sg:postcode":"57399",
    "sg:province":"Nordrhein-Westfalen",
    "wof:name":"Kaiser Ventilatorenbau Kg",
    "wof:placetype":"venue"
},
  "geometry": {"coordinates":[8.105056,51.088104],"type":"Point"}
}