{
  "type": "Feature",
  "properties": {
    "iso:country":"DE",
    "sg:address":"Hans-Wilhelm-Kirst-Str. 1-4",
    "sg:city":"Irmenach",
    "sg:phone":"+49 6541/6045",
    "sg:postcode":"56843",
    "sg:province":"Rheinland-Pfalz",
    "wof:name":"Hans Kirst Kg",
    "wof:placetype":"venue"
},
  "geometry": {"coordinates":[7.1915597916,49.9260749817],"type":"Point"}
}