{
  "type": "Feature",
  "properties": {
    "iso:country":"DE",
    "sg:address":"Hermelinweg 6",
    "sg:city":"Lingen",
    "sg:phone":"+49 591/74059",
    "sg:postcode":"49811",
    "sg:province":"Niedersachsen",
    "wof:name":"Wilhelm Loch Tierarzt",
    "wof:placetype":"venue"
},
  "geometry": {"coordinates":[7.3741469383,52.525806427],"type":"Point"}
}