{
  "type": "Feature",
  "properties": {
    "iso:country":"DE",
    "sg:address":"Jean-Pierre-Jungels-Str. 36",
    "sg:city":"Mainz",
    "sg:phone":"+49 6131/947660",
    "sg:postcode":"55126",
    "sg:province":"Rheinland-Pfalz",
    "wof:name":"Kr\u00f6ber & Partner",
    "wof:placetype":"venue"
},
  "geometry": {"coordinates":[8.1673898697,49.9813079834],"type":"Point"}
}