{
  "type": "Feature",
  "properties": {
    "iso:country":"DE",
    "sg:address":"Letterhausstr. 22",
    "sg:city":"Wallenhorst",
    "sg:postcode":"49134",
    "sg:province":"Niedersachsen",
    "wof:name":"Horst M\u00fcller Verlagsvertreter",
    "wof:placetype":"venue"
},
  "geometry": {"coordinates":[8.012318,52.345318],"type":"Point"}
}