{
  "type": "Feature",
  "properties": {
    "iso:country":"DE",
    "sg:address":"Kettelerstr. 57",
    "sg:city":"Dieburg",
    "sg:phone":"+49 6071/25307",
    "sg:postcode":"64807",
    "sg:province":"Hessen",
    "wof:name":"Hilde Thomas-zoth Rechtsanw\u00e4ltin",
    "wof:placetype":"venue"
},
  "geometry": {"coordinates":[8.8427362442,49.8929023743],"type":"Point"}
}