{
  "type": "Feature",
  "properties": {
    "iso:country":"DE",
    "sg:address":"Halskestr. 8",
    "sg:city":"N\u00fcrnberg",
    "sg:phone":"+49 911/613230",
    "sg:postcode":"90459",
    "sg:province":"Bayern",
    "wof:name":"Hans Klimke",
    "wof:placetype":"venue"
},
  "geometry": {"coordinates":[11.082801,49.435169],"type":"Point"}
}