{
  "type": "Feature",
  "properties": {
    "iso:country":"DE",
    "sg:address":"Rolandstr. 9",
    "sg:city":"Essen",
    "sg:phone":"+49 201/200990",
    "sg:postcode":"45128",
    "sg:province":"Nordrhein-Westfalen",
    "wof:name":"Wasag-chemie Ag",
    "wof:placetype":"venue"
},
  "geometry": {"coordinates":[7.012551,51.44804],"type":"Point"}
}