{
  "type": "Feature",
  "properties": {
    "iso:country":"DE",
    "sg:address":"Pelmanstr. 59",
    "sg:city":"Essen",
    "sg:phone":"+49 201/255237",
    "sg:postcode":"45131",
    "sg:province":"Nordrhein-Westfalen",
    "wof:name":"Dezabu Im- Und Export Gmbh",
    "wof:placetype":"venue"
},
  "geometry": {"coordinates":[6.996805191,51.432636261],"type":"Point"}
}