{
  "type": "Feature",
  "properties": {
    "iso:country":"DE",
    "sg:address":"Venloer Str. 308d",
    "sg:city":"K\u00f6ln",
    "sg:phone":"+49 221/518755",
    "sg:postcode":"50823",
    "sg:province":"Nordrhein-Westfalen",
    "wof:name":"Blumen-risse Gmbh & Co. Kg",
    "wof:placetype":"venue"
},
  "geometry": {"coordinates":[6.919245,50.948929],"type":"Point"}
}