{
  "type": "Feature",
  "properties": {
    "iso:country":"DE",
    "sg:address":"Hauptstr. 2",
    "sg:city":"Ankum",
    "sg:phone":"+49 5462/596",
    "sg:postcode":"49577",
    "sg:province":"Niedersachsen",
    "wof:name":"H. Billenkamp",
    "wof:placetype":"venue"
},
  "geometry": {"coordinates":[7.8748297691,52.541557312],"type":"Point"}
}