{
  "type": "Feature",
  "properties": {
    "iso:country":"DE",
    "sg:address":"Wiesentalstr. 31",
    "sg:city":"Meckenbeuren",
    "sg:phone":"+49 7542/94490",
    "sg:postcode":"88074",
    "sg:province":"Baden-W\u00fcrttemberg",
    "wof:name":"Sauter Holding Ag",
    "wof:placetype":"venue"
},
  "geometry": {"coordinates":[9.564392,47.691097],"type":"Point"}
}