{
  "type": "Feature",
  "properties": {
    "iso:country":"DE",
    "sg:address":"Wartburgstr. 1",
    "sg:city":"Berlin",
    "sg:phone":"+49 30/7847780",
    "sg:postcode":"10823",
    "sg:province":"Berlin",
    "wof:name":"Dietmar Schmidt",
    "wof:placetype":"venue"
},
  "geometry": {"coordinates":[13.35202,52.487659],"type":"Point"}
}