{
  "type": "Feature",
  "properties": {
    "iso:country":"DE",
    "sg:address":"Stiftsgasse 3",
    "sg:city":"D\u00fcsseldorf",
    "sg:phone":"+49 211/407448",
    "sg:postcode":"40489",
    "sg:province":"Nordrhein-Westfalen",
    "wof:name":"R. Weyergraf",
    "wof:placetype":"venue"
},
  "geometry": {"coordinates":[6.734149,51.300575],"type":"Point"}
}