{
  "type": "Feature",
  "properties": {
    "iso:country":"DE",
    "sg:address":"Am Freiheitsplatz 3",
    "sg:city":"Hanau",
    "sg:phone":"+49 6181/21264",
    "sg:postcode":"63450",
    "sg:province":"Hessen",
    "wof:name":"Sauberland Textilpflege",
    "wof:placetype":"venue"
},
  "geometry": {"coordinates":[8.918337,50.134373],"type":"Point"}
}