{
  "type": "Feature",
  "properties": {
    "iso:country":"DE",
    "sg:address":"Koyne 2",
    "sg:city":"Lauchhammer",
    "sg:phone":"+49 3574/124238",
    "sg:postcode":"01979",
    "sg:province":"Brandenburg",
    "wof:name":"Harry Reisewitz",
    "wof:placetype":"venue"
},
  "geometry": {"coordinates":[13.736921,51.521778],"type":"Point"}
}