{
  "type": "Feature",
  "properties": {
    "iso:country":"DE",
    "sg:address":"Nuschelberger Hauptstr. 1",
    "sg:city":"Lauf",
    "sg:phone":"+49 9123/3396",
    "sg:postcode":"91207",
    "sg:province":"Bayern",
    "wof:name":"Hallerschl\u00f6\u00dfchen",
    "wof:placetype":"venue"
},
  "geometry": {"coordinates":[11.2335395813,49.5377197266],"type":"Point"}
}