{
  "type": "Feature",
  "properties": {
    "iso:country":"DE",
    "sg:address":"Kaiserstr. 42",
    "sg:city":"Herne",
    "sg:phone":"+49 2323/23649",
    "sg:postcode":"44629",
    "sg:province":"Nordrhein-Westfalen",
    "wof:name":"Karl-heinz Basler Steuerberater",
    "wof:placetype":"venue"
},
  "geometry": {"coordinates":[7.2046961784,51.5472297668],"type":"Point"}
}