{
  "type": "Feature",
  "properties": {
    "iso:country":"DE",
    "sg:address":"Mindener Str. 115",
    "sg:city":"Herford",
    "sg:phone":"+49 5221/25061",
    "sg:postcode":"32049",
    "sg:province":"Nordrhein-Westfalen",
    "wof:name":"Sieker",
    "wof:placetype":"venue"
},
  "geometry": {"coordinates":[8.6870927811,52.1292266846],"type":"Point"}
}