{
  "type": "Feature",
  "properties": {
    "iso:country":"DE",
    "sg:address":"Kluser Stra\u00dfe 62",
    "sg:city":"Neub\u00f6rger",
    "sg:phone":"+49 4966/436",
    "sg:postcode":"26909",
    "sg:province":"Niedersachsen",
    "wof:name":"Gvi Globalvillage Internet Gmbh",
    "wof:placetype":"venue"
},
  "geometry": {"coordinates":[7.4340810776,52.9497146606],"type":"Point"}
}