{
  "type": "Feature",
  "properties": {
    "iso:country":"DE",
    "sg:address":"Neum\u00fchle 1",
    "sg:city":"Kronach",
    "sg:postcode":"96317",
    "sg:province":"Bayern",
    "wof:name":"Georg Geiger Ohg",
    "wof:placetype":"venue"
},
  "geometry": {"coordinates":[11.3633680344,50.272895813],"type":"Point"}
}