{
  "type": "Feature",
  "properties": {
    "iso:country":"DE",
    "sg:address":"Lohholzweg 4",
    "sg:city":"Hof",
    "sg:phone":"+49 9281/61375",
    "sg:postcode":"95030",
    "sg:province":"Bayern",
    "wof:name":"Knopf-hartmann",
    "wof:placetype":"venue"
},
  "geometry": {"coordinates":[11.843994,50.305946],"type":"Point"}
}