{
  "type": "Feature",
  "properties": {
    "iso:country":"DE",
    "sg:address":"Sachsenberger Str. 3",
    "sg:city":"Frankenberg",
    "sg:phone":"+49 6451/713290",
    "sg:postcode":"35066",
    "sg:province":"Hessen",
    "wof:name":"Akquitel Termin Service Christioph Meyer Ohg",
    "wof:placetype":"venue"
},
  "geometry": {"coordinates":[8.8061466217,51.0789413452],"type":"Point"}
}