{
  "type": "Feature",
  "properties": {
    "iso:country":"DE",
    "sg:address":"Eschenauer Hauptstr. 43",
    "sg:city":"Eckental",
    "sg:phone":"+49 9126/281271",
    "sg:postcode":"90542",
    "sg:province":"Bayern",
    "wof:name":"Anja Wernicke Rechtsanw\u00e4ltin",
    "wof:placetype":"venue"
},
  "geometry": {"coordinates":[11.1992549896,49.5744132996],"type":"Point"}
}