{
  "type": "Feature",
  "properties": {
    "iso:country":"DE",
    "sg:address":"R\u00f6testr. 16",
    "sg:city":"Bietigheim-Bissingen",
    "sg:phone":"+49 4971/425810",
    "sg:postcode":"74321",
    "sg:province":"Baden-W\u00fcrttemberg",
    "wof:name":"Rieger Beh\u00c4lterbau Gmbh",
    "wof:placetype":"venue"
},
  "geometry": {"coordinates":[9.1512403488,48.9515533447],"type":"Point"}
}