{
  "type": "Feature",
  "properties": {
    "iso:country":"DE",
    "sg:address":"Kieler Weg 16",
    "sg:city":"Delmenhorst",
    "sg:phone":"+49 4221/70761",
    "sg:postcode":"27751",
    "sg:province":"Niedersachsen",
    "wof:name":"Christa Bohmhoff",
    "wof:placetype":"venue"
},
  "geometry": {"coordinates":[8.662557,53.051865],"type":"Point"}
}