{
  "type": "Feature",
  "properties": {
    "iso:country":"DE",
    "sg:address":"Marktstr. 8",
    "sg:city":"Bad T\u00f6lz",
    "sg:phone":"+49 8041/6091",
    "sg:postcode":"83646",
    "sg:province":"Bayern",
    "wof:name":"Gr\u00fcnerbr\u00e4u",
    "wof:placetype":"venue"
},
  "geometry": {"coordinates":[11.5578536987,47.760635376],"type":"Point"}
}