{
  "type": "Feature",
  "properties": {
    "iso:country":"DE",
    "sg:address":"Gro\u00df Ch\u00fcdener Weg 3",
    "sg:city":"Pretzier",
    "sg:postcode":"29416",
    "sg:province":"Sachsen-Anhalt",
    "wof:name":"Peb - Bauplanungs - Gmbh",
    "wof:placetype":"venue"
},
  "geometry": {"coordinates":[11.259011,52.834656],"type":"Point"}
}