{
  "type": "Feature",
  "properties": {
    "iso:country":"DE",
    "sg:address":"Dr.-Kurt-Schumacher-Str. 15",
    "sg:city":"Kirchheimbolanden",
    "sg:postcode":"67292",
    "sg:province":"Rheinland-Pfalz",
    "wof:name":"Wiwi Windkraft Beteiligungs- Gmbh",
    "wof:placetype":"venue"
},
  "geometry": {"coordinates":[7.994491,49.670059],"type":"Point"}
}