{
  "type": "Feature",
  "properties": {
    "iso:country":"DE",
    "sg:address":"Josefstr. 5",
    "sg:city":"Hanau",
    "sg:phone":"+49 6181/81616",
    "sg:postcode":"63452",
    "sg:province":"Hessen",
    "wof:name":"Michael Bos Steuerberater",
    "wof:placetype":"venue"
},
  "geometry": {"coordinates":[8.9079856873,50.1431312561],"type":"Point"}
}