{
  "type": "Feature",
  "properties": {
    "iso:country":"DE",
    "sg:address":"Tannenweg 5",
    "sg:city":"Hausen",
    "sg:postcode":"97262",
    "sg:province":"Bayern",
    "wof:name":"Hotel Am Wiesenweg Gmbh",
    "wof:placetype":"venue"
},
  "geometry": {"coordinates":[10.017534256,49.907535553],"type":"Point"}
}