{
  "type": "Feature",
  "properties": {
    "iso:country":"DE",
    "sg:address":"Gartenstr. 6a",
    "sg:city":"Salzm\u00fcnde",
    "sg:phone":"+49 34609/22343",
    "sg:postcode":"06198",
    "sg:province":"Sachsen-Anhalt",
    "wof:name":"Vsf Verkehrstechnik Gmbh",
    "wof:placetype":"venue"
},
  "geometry": {"coordinates":[11.8514242172,51.5269927979],"type":"Point"}
}