{
  "type": "Feature",
  "properties": {
    "iso:country":"DE",
    "sg:address":"Sachsenring 18",
    "sg:city":"Vellmar",
    "sg:phone":"+49 561/823177",
    "sg:postcode":"34246",
    "sg:province":"Hessen",
    "wof:name":"A. Kreiz-bruder",
    "wof:placetype":"venue"
},
  "geometry": {"coordinates":[9.462463,51.347485],"type":"Point"}
}