{
  "type": "Feature",
  "properties": {
    "iso:country":"DE",
    "sg:address":"Spitalstr. 11",
    "sg:city":"Zell",
    "sg:phone":"+49 7835/1522",
    "sg:postcode":"77736",
    "sg:province":"Baden-W\u00fcrttemberg",
    "wof:name":"Gabriele Allgaier Masseurin",
    "wof:placetype":"venue"
},
  "geometry": {"coordinates":[8.067036,48.3465],"type":"Point"}
}