{
  "type": "Feature",
  "properties": {
    "iso:country":"DE",
    "sg:address":"Freudenbergstr. 14",
    "sg:city":"Weinheim",
    "sg:phone":"+49 6201/16868",
    "sg:postcode":"69469",
    "sg:province":"Baden-W\u00fcrttemberg",
    "wof:name":"Stefan Kochs Masseur",
    "wof:placetype":"venue"
},
  "geometry": {"coordinates":[8.66754,49.546089],"type":"Point"}
}