{
  "type": "Feature",
  "properties": {
    "iso:country":"DE",
    "sg:address":"Hohenstaufenstr. 4",
    "sg:city":"G\u00f6ppingen",
    "sg:phone":"+49 7161/67260",
    "sg:postcode":"73033",
    "sg:province":"Baden-W\u00fcrttemberg",
    "wof:name":"Wilhelmshilfe-bad G\u00f6ppingen",
    "wof:placetype":"venue"
},
  "geometry": {"coordinates":[9.6611,48.70298],"type":"Point"}
}