{
  "type": "Feature",
  "properties": {
    "iso:country":"DE",
    "sg:address":"Weinheimer Str. 22",
    "sg:city":"K\u00f6ln",
    "sg:phone":"+49 221/891137",
    "sg:postcode":"51107",
    "sg:province":"Nordrhein-Westfalen",
    "wof:name":"Richard Golombek Architekt",
    "wof:placetype":"venue"
},
  "geometry": {"coordinates":[7.0463,50.928001],"type":"Point"}
}