{
  "type": "Feature",
  "properties": {
    "iso:country":"DE",
    "sg:address":"Benrather Str. 58",
    "sg:city":"Hilden",
    "sg:phone":"+49 2103/910710",
    "sg:postcode":"40721",
    "sg:province":"Nordrhein-Westfalen",
    "wof:name":"Dkv Hilden Karin H\u00e4u\u00dfler Und",
    "wof:placetype":"venue"
},
  "geometry": {"coordinates":[6.9255838394,51.1667785645],"type":"Point"}
}