{
  "type": "Feature",
  "properties": {
    "iso:country":"DE",
    "sg:address":"Provinzialstr. 25",
    "sg:city":"Saarbr\u00fccken",
    "sg:phone":"+49 6898/81800",
    "sg:postcode":"66126",
    "sg:province":"Saarland",
    "wof:name":"Edel Ri-tec Gmbh",
    "wof:placetype":"venue"
},
  "geometry": {"coordinates":[6.9115109444,49.2470741272],"type":"Point"}
}