{
  "type": "Feature",
  "properties": {
    "iso:country":"DE",
    "sg:address":"Anton-Ulrich-Str. 37",
    "sg:city":"Meiningen",
    "sg:phone":"+49 3693/503115",
    "sg:postcode":"98617",
    "sg:province":"Th\u00fcringen",
    "wof:name":"Nikolaus Gro\u00df",
    "wof:placetype":"venue"
},
  "geometry": {"coordinates":[10.414341,50.565529],"type":"Point"}
}