{
  "type": "Feature",
  "properties": {
    "iso:country":"DE",
    "sg:address":"Goerdelerstr. 22",
    "sg:city":"Apolda",
    "sg:postcode":"99510",
    "sg:province":"Th\u00fcringen",
    "wof:name":"Boutique F\u00fcr Kopfbekleidung Und Modisches Zubeh\u00f6r",
    "wof:placetype":"venue"
},
  "geometry": {"coordinates":[11.513319,51.024437],"type":"Point"}
}