{
  "type": "Feature",
  "properties": {
    "iso:country":"DE",
    "sg:address":"Dresdener Str. 65",
    "sg:city":"Luckau",
    "sg:phone":"+49 3544/2041",
    "sg:postcode":"15926",
    "sg:province":"Brandenburg",
    "wof:name":"Thomas Schulze",
    "wof:placetype":"venue"
},
  "geometry": {"coordinates":[13.699577,51.845188],"type":"Point"}
}