{
  "type": "Feature",
  "properties": {
    "iso:country":"DE",
    "sg:address":"Eickenscheidter Fuhr 53",
    "sg:city":"Essen",
    "sg:phone":"+49 201/281479",
    "sg:postcode":"45139",
    "sg:province":"Nordrhein-Westfalen",
    "wof:name":"Alfred Schumacher",
    "wof:placetype":"venue"
},
  "geometry": {"coordinates":[7.027326,51.453667],"type":"Point"}
}