{
  "type": "Feature",
  "properties": {
    "iso:country":"DE",
    "sg:address":"Schlesische Str. 20",
    "sg:city":"Berlin",
    "sg:phone":"+49 30/6179140",
    "sg:postcode":"10997",
    "sg:province":"Berlin",
    "wof:name":"Enno Maa\u00df Architekt",
    "wof:placetype":"venue"
},
  "geometry": {"coordinates":[13.446463,52.498505],"type":"Point"}
}