{
  "type": "Feature",
  "properties": {
    "iso:country":"DE",
    "sg:address":"Ziolkowskistr. 11",
    "sg:city":"Rostock",
    "sg:phone":"+49 381/405620",
    "sg:postcode":"18059",
    "sg:province":"Mecklenburg-Vorpommern",
    "wof:name":"Wohnungs-genossenschaft Rostock-s\u00fcd Eg",
    "wof:placetype":"venue"
},
  "geometry": {"coordinates":[12.1188354492,54.0712585449],"type":"Point"}
}