{
  "type": "Feature",
  "properties": {
    "iso:country":"DE",
    "sg:address":"Alte Walserstr. 20",
    "sg:city":"Oberstdorf",
    "sg:phone":"+49 8322/4061",
    "sg:postcode":"87561",
    "sg:province":"Bayern",
    "wof:name":"Naturhotel-restaurant-caf\u00e9- Waldesruh Brutscher E. K.",
    "wof:placetype":"venue"
},
  "geometry": {"coordinates":[10.2593336105,47.4063606262],"type":"Point"}
}