{
  "type": "Feature",
  "properties": {
    "iso:country":"DE",
    "sg:address":"Marktstr. 18",
    "sg:city":"Hindelang",
    "sg:phone":"+49 8324/564",
    "sg:postcode":"87541",
    "sg:province":"Bayern",
    "wof:name":"Willi Gai\u00dfer",
    "wof:placetype":"venue"
},
  "geometry": {"coordinates":[10.3697919846,47.506187439],"type":"Point"}
}