{
  "type": "Feature",
  "properties": {
    "iso:country":"DE",
    "sg:address":"Schlo\u00dfstr. 30",
    "sg:city":"Ludwigsburg",
    "sg:phone":"+49 7141/975040",
    "sg:postcode":"71634",
    "sg:province":"Baden-W\u00fcrttemberg",
    "wof:name":"Porzellan-manufaktur Ludwigsburg Gmbh",
    "wof:placetype":"venue"
},
  "geometry": {"coordinates":[9.1941404343,48.9001235962],"type":"Point"}
}