{
  "type": "Feature",
  "properties": {
    "iso:country":"DE",
    "sg:address":"Magdeburger Str. 33",
    "sg:city":"Krefeld",
    "sg:phone":"+49 2151/20640",
    "sg:postcode":"47800",
    "sg:province":"Nordrhein-Westfalen",
    "wof:name":"S\u00fcsswaren-verkaufs-kg",
    "wof:placetype":"venue"
},
  "geometry": {"coordinates":[6.6208410263,51.3596305847],"type":"Point"}
}