{
  "type": "Feature",
  "properties": {
    "iso:country":"DE",
    "sg:address":"Rehgrabenstr. 1",
    "sg:city":"Saarbr\u00fccken",
    "sg:phone":"+49 6897/761428",
    "sg:postcode":"66125",
    "sg:province":"Saarland",
    "wof:name":"Alexander Karwat & Sohn Gmbh",
    "wof:placetype":"venue"
},
  "geometry": {"coordinates":[7.0333662033,49.2870903015],"type":"Point"}
}