{
  "type": "Feature",
  "properties": {
    "iso:country":"DE",
    "sg:address":"Am Inzerfeld 91",
    "sg:city":"Duisburg",
    "sg:phone":"+49 203/584215",
    "sg:postcode":"47167",
    "sg:province":"Nordrhein-Westfalen",
    "wof:name":"G. Feustel",
    "wof:placetype":"venue"
},
  "geometry": {"coordinates":[6.7959198952,51.4911117554],"type":"Point"}
}