{
  "type": "Feature",
  "properties": {
    "iso:country":"DE",
    "sg:address":"Windelsbleicher Str. 43",
    "sg:city":"Bielefeld",
    "sg:phone":"+49 521/9429140",
    "sg:postcode":"33647",
    "sg:province":"Nordrhein-Westfalen",
    "wof:name":"Das Isses Papierhandel Und Mehr Gmbh",
    "wof:placetype":"venue"
},
  "geometry": {"coordinates":[8.5180196762,51.9819335938],"type":"Point"}
}