{
  "type": "Feature",
  "properties": {
    "iso:country":"DE",
    "sg:address":"Agricolaplatz 11",
    "sg:city":"M\u00fcnchen",
    "sg:phone":"+49 89/561491",
    "sg:postcode":"80687",
    "sg:province":"Bayern",
    "wof:name":"Achim Eichler Architekt",
    "wof:placetype":"venue"
},
  "geometry": {"coordinates":[11.49329,48.141216],"type":"Point"}
}