{
  "type": "Feature",
  "properties": {
    "iso:country":"DE",
    "sg:address":"Grimnitzstr. 6 a",
    "sg:city":"Berlin",
    "sg:phone":"+49 30/36281929",
    "sg:postcode":"13595",
    "sg:province":"Berlin",
    "wof:name":"Burkhard Gericke Steuerberater",
    "wof:placetype":"venue"
},
  "geometry": {"coordinates":[13.1951131821,52.5162277222],"type":"Point"}
}