{
  "type": "Feature",
  "properties": {
    "iso:country":"DE",
    "sg:address":"Fischereiweg 13",
    "sg:city":"Dessau",
    "sg:phone":"+49 340/615127",
    "sg:postcode":"06846",
    "sg:province":"Sachsen-Anhalt",
    "wof:name":"Dr. Med. Dieter Ullrich",
    "wof:placetype":"venue"
},
  "geometry": {"coordinates":[12.224009,51.839127],"type":"Point"}
}