{
  "type": "Feature",
  "properties": {
    "iso:country":"DE",
    "sg:address":"Im Bruch 82",
    "sg:city":"Weyhe",
    "sg:phone":"+49 4942/038893",
    "sg:postcode":"28844",
    "sg:province":"Niedersachsen",
    "wof:name":"Holzbau Glinka",
    "wof:placetype":"venue"
},
  "geometry": {"coordinates":[8.8521022797,52.9942779541],"type":"Point"}
}