{
  "type": "Feature",
  "properties": {
    "iso:country":"DE",
    "sg:address":"Freimanner Bahnhofstr. 23",
    "sg:city":"M\u00fcnchen",
    "sg:phone":"+49 89/3232169",
    "sg:postcode":"80807",
    "sg:province":"Bayern",
    "wof:name":"Tkd Trocken Eis Und Kohlen- S\u00e4ure Distribution Gmbh",
    "wof:placetype":"venue"
},
  "geometry": {"coordinates":[11.607962,48.188206],"type":"Point"}
}