{
  "type": "Feature",
  "properties": {
    "iso:country":"DE",
    "sg:address":"Altengammer Elbdeich 38",
    "sg:city":"Hamburg",
    "sg:phone":"+49 40/7235233",
    "sg:postcode":"21039",
    "sg:province":"Hamburg",
    "wof:name":"Claus Harden",
    "wof:placetype":"venue"
},
  "geometry": {"coordinates":[10.292522,53.430008],"type":"Point"}
}