{
  "type": "Feature",
  "properties": {
    "iso:country":"DE",
    "sg:address":"Am Silberber 43",
    "sg:city":"Seelze",
    "sg:postcode":"30926",
    "sg:province":"Niedersachsen",
    "wof:name":"Werbeagentur-deja-service-seelze",
    "wof:placetype":"venue"
},
  "geometry": {"coordinates":[9.565345,52.400551],"type":"Point"}
}