{
  "type": "Feature",
  "properties": {
    "iso:country":"DE",
    "sg:address":"Im Ohl 85",
    "sg:city":"Arnsberg",
    "sg:phone":"+49 2932/21011",
    "sg:postcode":"59757",
    "sg:province":"Nordrhein-Westfalen",
    "wof:name":"Schulte Gmbh",
    "wof:placetype":"venue"
},
  "geometry": {"coordinates":[7.9427399635,51.466709137],"type":"Point"}
}