{
  "type": "Feature",
  "properties": {
    "iso:country":"DE",
    "sg:address":"Am F\u00fcrstberg 21",
    "sg:city":"Obernzell",
    "sg:phone":"+49 8591/574",
    "sg:postcode":"94130",
    "sg:province":"Bayern",
    "wof:name":"Heinz Greiner",
    "wof:placetype":"venue"
},
  "geometry": {"coordinates":[13.576333046,48.563583374],"type":"Point"}
}