{
  "type": "Feature",
  "properties": {
    "iso:country":"DE",
    "sg:address":"Celsiusstr. 102",
    "sg:city":"Bonn",
    "sg:phone":"+49 228/257349",
    "sg:postcode":"53125",
    "sg:province":"Nordrhein-Westfalen",
    "wof:name":"Stanislaus Burjan",
    "wof:placetype":"venue"
},
  "geometry": {"coordinates":[7.0563869476,50.6996383667],"type":"Point"}
}