{
  "type": "Feature",
  "properties": {
    "iso:country":"DE",
    "sg:city":"Roth",
    "sg:phone":"+49 9171/87661",
    "sg:postcode":"91154",
    "sg:province":"Bayern",
    "wof:name":"Beatclub Collo Rock",
    "wof:placetype":"venue"
},
  "geometry": {"coordinates":[11.090575,49.246204],"type":"Point"}
}