{
  "type": "Feature",
  "properties": {
    "iso:country":"DE",
    "sg:address":"Schenefelder Landstr. 160",
    "sg:city":"Hamburg",
    "sg:phone":"+49 40/871061",
    "sg:postcode":"22589",
    "sg:province":"Hamburg",
    "wof:name":"Beg B\u00dcro-einrichtungs Gmbh & Co",
    "wof:placetype":"venue"
},
  "geometry": {"coordinates":[9.823884964,53.5745735168],"type":"Point"}
}