{
  "type": "Feature",
  "properties": {
    "iso:country":"DE",
    "sg:address":"Ahornstr. 9",
    "sg:city":"Friesoythe",
    "sg:phone":"+49 4497/291",
    "sg:postcode":"26169",
    "sg:province":"Niedersachsen",
    "wof:name":"Brodale Gmbh",
    "wof:placetype":"venue"
},
  "geometry": {"coordinates":[7.8055100441,53.0836296082],"type":"Point"}
}