{
  "type": "Feature",
  "properties": {
    "iso:country":"DE",
    "sg:address":"Schmiedestr. 1",
    "sg:city":"Bad Harzburg",
    "sg:phone":"+49 4953/222095",
    "sg:postcode":"38667",
    "sg:province":"Niedersachsen",
    "wof:name":"Deutsche Bank Ag",
    "wof:placetype":"venue"
},
  "geometry": {"coordinates":[10.560425,51.879795],"type":"Point"}
}