{
  "type": "Feature",
  "properties": {
    "iso:country":"DE",
    "sg:address":"Dammstr. 14",
    "sg:city":"Unterensingen",
    "sg:phone":"+49 7022/262166",
    "sg:postcode":"72669",
    "sg:province":"Baden-W\u00fcrttemberg",
    "wof:name":"Heike Renke",
    "wof:placetype":"venue"
},
  "geometry": {"coordinates":[9.3591966629,48.6553077698],"type":"Point"}
}