{
  "type": "Feature",
  "properties": {
    "iso:country":"DE",
    "sg:address":"Geraer Str. 47b",
    "sg:city":"Berlin",
    "sg:phone":"+49 30/7723328",
    "sg:postcode":"12209",
    "sg:province":"Berlin",
    "wof:name":"Moresco Immobilien- Management Gmbh",
    "wof:placetype":"venue"
},
  "geometry": {"coordinates":[13.3360176086,52.421421051],"type":"Point"}
}