{
  "type": "Feature",
  "properties": {
    "iso:country":"DE",
    "sg:address":"Gerichtstr. 25",
    "sg:city":"Berlin",
    "sg:phone":"+49 30/4652735",
    "sg:postcode":"13347",
    "sg:province":"Berlin",
    "wof:name":"Horst Freund",
    "wof:placetype":"venue"
},
  "geometry": {"coordinates":[13.3716602325,52.5444564819],"type":"Point"}
}