{
  "type": "Feature",
  "properties": {
    "iso:country":"DE",
    "sg:address":"Bebelstr. 60",
    "sg:city":"Stuttgart",
    "sg:phone":"+49 711/6365580",
    "sg:postcode":"70193",
    "sg:province":"Baden-W\u00fcrttemberg",
    "wof:name":"Abf Entsorgung Gmbh",
    "wof:placetype":"venue"
},
  "geometry": {"coordinates":[9.1490354538,48.7749671936],"type":"Point"}
}