{
  "type": "Feature",
  "properties": {
    "iso:country":"DE",
    "sg:address":"Breedenstr. 3",
    "sg:city":"Ladbergen",
    "sg:phone":"+49 5485/1249",
    "sg:postcode":"49549",
    "sg:province":"Nordrhein-Westfalen",
    "wof:name":"Friedrich Oelrich",
    "wof:placetype":"venue"
},
  "geometry": {"coordinates":[7.735185,52.136253],"type":"Point"}
}