{
  "type": "Feature",
  "properties": {
    "iso:country":"DE",
    "sg:address":"Im Dachlet 9",
    "sg:city":"Heilbronn",
    "sg:phone":"+49 7066/5454",
    "sg:postcode":"74078",
    "sg:province":"Baden-W\u00fcrttemberg",
    "wof:name":"H. Kilper Immobilienmakler",
    "wof:placetype":"venue"
},
  "geometry": {"coordinates":[9.1358757019,49.1974601746],"type":"Point"}
}