{
  "type": "Feature",
  "properties": {
    "iso:country":"DE",
    "sg:address":"Hauptstr. 122",
    "sg:city":"Schw\u00f6rstadt",
    "sg:phone":"+49 4977/628571",
    "sg:postcode":"79739",
    "sg:province":"Baden-W\u00fcrttemberg",
    "wof:name":"Volksbank Rhein-wehra Eg",
    "wof:placetype":"venue"
},
  "geometry": {"coordinates":[7.872123,47.592087],"type":"Point"}
}