{
  "type": "Feature",
  "properties": {
    "iso:country":"DE",
    "sg:address":"Eisenbahnstr. 3",
    "sg:city":"Mahlberg",
    "sg:phone":"+49 4978/251728",
    "sg:postcode":"77972",
    "sg:province":"Baden-W\u00fcrttemberg",
    "wof:name":"Stephan Kiesel",
    "wof:placetype":"venue"
},
  "geometry": {"coordinates":[7.81001091,48.2886199951],"type":"Point"}
}