{
  "type": "Feature",
  "properties": {
    "iso:country":"DE",
    "sg:address":"Fischersteg 6",
    "sg:city":"K\u00f6nigslutter",
    "sg:phone":"+49 5353/2784",
    "sg:postcode":"38154",
    "sg:province":"Niedersachsen",
    "wof:name":"L. Skottki Heissmangel",
    "wof:placetype":"venue"
},
  "geometry": {"coordinates":[10.8221321106,52.2600059509],"type":"Point"}
}