{
  "type": "Feature",
  "properties": {
    "iso:country":"DE",
    "sg:address":"Papenwisch 20",
    "sg:city":"M\u00fchlen Eichsen",
    "sg:phone":"+49 38821/60570",
    "sg:postcode":"19205",
    "sg:province":"Mecklenburg-Vorpommern",
    "wof:name":"B. Streit",
    "wof:placetype":"venue"
},
  "geometry": {"coordinates":[11.245782,53.761093],"type":"Point"}
}