{
  "type": "Feature",
  "properties": {
    "iso:country":"DE",
    "sg:address":"Sophienstr. 97",
    "sg:city":"Erbach",
    "sg:phone":"+49 6061/675",
    "sg:postcode":"64711",
    "sg:province":"Hessen",
    "wof:name":"A-z Immobilien Rainer Skarke",
    "wof:placetype":"venue"
},
  "geometry": {"coordinates":[8.9845819473,49.6654434204],"type":"Point"}
}