{
  "type": "Feature",
  "properties": {
    "iso:country":"DE",
    "sg:address":"Geyersche Str. 3",
    "sg:city":"Thum-Jahnsbach",
    "sg:phone":"+49 37297/4447",
    "sg:postcode":"09419",
    "sg:province":"Sachsen",
    "wof:name":"Heinz Kraft",
    "wof:placetype":"venue"
},
  "geometry": {"coordinates":[12.9498,50.674431],"type":"Point"}
}