{
  "type": "Feature",
  "properties": {
    "iso:country":"DE",
    "sg:address":"Sophienstr. 33",
    "sg:city":"Braunschweig",
    "sg:phone":"+49 531/82313",
    "sg:postcode":"38118",
    "sg:province":"Niedersachsen",
    "wof:name":"Siedle Ausstellungs- Und Schulungszentrum",
    "wof:placetype":"venue"
},
  "geometry": {"coordinates":[10.510617,52.258595],"type":"Point"}
}