{
  "type": "Feature",
  "properties": {
    "iso:country":"DE",
    "sg:address":"H\u00fcding 23",
    "sg:city":"R\u00fcthen",
    "sg:phone":"+49 2952/3675",
    "sg:postcode":"59602",
    "sg:province":"Nordrhein-Westfalen",
    "wof:name":"Hb Transportanlagenbau Gmbh",
    "wof:placetype":"venue"
},
  "geometry": {"coordinates":[8.426391,51.495434],"type":"Point"}
}