{
  "type": "Feature",
  "properties": {
    "iso:country":"DE",
    "sg:address":"Ederweg 10",
    "sg:city":"Felsberg",
    "sg:postcode":"34587",
    "sg:province":"Hessen",
    "wof:name":"Bkb B\u00fcro F\u00fcr Kommunale Baubetreuung Gmbh",
    "wof:placetype":"venue"
},
  "geometry": {"coordinates":[9.428461,51.131084],"type":"Point"}
}