{
  "type": "Feature",
  "properties": {
    "iso:country":"DE",
    "sg:address":"Am Bahnhof",
    "sg:city":"Halberstadt",
    "sg:postcode":"38820",
    "sg:province":"Sachsen-Anhalt",
    "wof:name":"Taxiruf Gmbh",
    "wof:placetype":"venue"
},
  "geometry": {"coordinates":[11.1209936142,51.9258956909],"type":"Point"}
}