{
  "type": "Feature",
  "properties": {
    "iso:country":"DE",
    "sg:address":"Knollenkamp 7",
    "sg:city":"Emsdetten",
    "sg:phone":"+49 2572/7717",
    "sg:postcode":"48282",
    "sg:province":"Nordrhein-Westfalen",
    "wof:name":"Hans Kassens",
    "wof:placetype":"venue"
},
  "geometry": {"coordinates":[7.53662,52.171303],"type":"Point"}
}