{
  "type": "Feature",
  "properties": {
    "iso:country":"DE",
    "sg:address":"Schulstr. 17",
    "sg:city":"Ahnatal",
    "sg:phone":"+49 5609/9331",
    "sg:postcode":"34292",
    "sg:province":"Hessen",
    "wof:name":"Ekkehard Heuser",
    "wof:placetype":"venue"
},
  "geometry": {"coordinates":[9.398095,51.363682],"type":"Point"}
}