{
  "type": "Feature",
  "properties": {
    "iso:country":"DE",
    "sg:address":"Hoevermannskamp 47",
    "sg:city":"Uelzen",
    "sg:phone":"+49 581/14151",
    "sg:postcode":"29525",
    "sg:province":"Niedersachsen",
    "wof:name":"Heinz-joachim Martens Architekt",
    "wof:placetype":"venue"
},
  "geometry": {"coordinates":[10.570505,52.960678],"type":"Point"}
}