{
  "type": "Feature",
  "properties": {
    "iso:country":"DE",
    "sg:address":"Amorbacher Str. 36",
    "sg:city":"Ilvesheim",
    "sg:phone":"+49 621/493604",
    "sg:postcode":"68549",
    "sg:province":"Baden-W\u00fcrttemberg",
    "wof:name":"Paul Klay",
    "wof:placetype":"venue"
},
  "geometry": {"coordinates":[8.5521297455,49.4836616516],"type":"Point"}
}