{
  "type": "Feature",
  "properties": {
    "iso:country":"DE",
    "sg:address":"Sahrstr. 4",
    "sg:city":"Kirchsahr",
    "sg:phone":"+49 2643/1477",
    "sg:postcode":"53505",
    "sg:province":"Rheinland-Pfalz",
    "wof:name":"Skylab",
    "wof:placetype":"venue"
},
  "geometry": {"coordinates":[6.905269,50.517757],"type":"Point"}
}