{
  "type": "Feature",
  "properties": {
    "iso:country":"DE",
    "sg:address":"Kleinrheinfelder Weg 30",
    "sg:city":"Donnersdorf",
    "sg:phone":"+49 9528/528",
    "sg:postcode":"97499",
    "sg:province":"Bayern",
    "wof:name":"Michael Feller",
    "wof:placetype":"venue"
},
  "geometry": {"coordinates":[10.415137,49.968899],"type":"Point"}
}