{
  "type": "Feature",
  "properties": {
    "iso:country":"DE",
    "sg:address":"Karlsruher Str. 89",
    "sg:city":"Pforzheim",
    "sg:phone":"+49 7231/106074",
    "sg:postcode":"75179",
    "sg:province":"Baden-W\u00fcrttemberg",
    "wof:name":"Hans Heimerdinger",
    "wof:placetype":"venue"
},
  "geometry": {"coordinates":[8.654455,48.904438],"type":"Point"}
}