{
  "type": "Feature",
  "properties": {
    "iso:country":"DE",
    "sg:address":"Freiherr-vom-Stein-Str. 3",
    "sg:city":"Nordhausen",
    "sg:phone":"+49 3631/988368",
    "sg:postcode":"99734",
    "sg:province":"Th\u00fcringen",
    "wof:name":"Friedrichs & Partner Rechtsanw\u00e4lte",
    "wof:placetype":"venue"
},
  "geometry": {"coordinates":[10.7863435745,51.497631073],"type":"Point"}
}