{
  "type": "Feature",
  "properties": {
    "iso:country":"DE",
    "sg:address":"Auf'm Kettgert 10",
    "sg:city":"Neuwied",
    "sg:phone":"+49 2631/71244",
    "sg:postcode":"56567",
    "sg:province":"Rheinland-Pfalz",
    "wof:name":"H. Sujatta Dolmetscherin",
    "wof:placetype":"venue"
},
  "geometry": {"coordinates":[7.439684,50.44915],"type":"Point"}
}