{
  "type": "Feature",
  "properties": {
    "iso:country":"DE",
    "sg:address":"Halterner Str. 51",
    "sg:city":"Recklinghausen",
    "sg:phone":"+49 2361/24678",
    "sg:postcode":"45657",
    "sg:province":"Nordrhein-Westfalen",
    "wof:name":"Immobilien Und Anlagenberatung Banach Kg",
    "wof:placetype":"venue"
},
  "geometry": {"coordinates":[7.1950941086,51.6220397949],"type":"Point"}
}