{
  "type": "Feature",
  "properties": {
    "iso:country":"DE",
    "sg:address":"Am Sch\u00e4ferpfad 1",
    "sg:city":"Saarwellingen",
    "sg:phone":"+49 6838/2696",
    "sg:postcode":"66793",
    "sg:province":"Saarland",
    "wof:name":"Anton Laub Architekt",
    "wof:placetype":"venue"
},
  "geometry": {"coordinates":[6.801838,49.36113],"type":"Point"}
}