{
  "type": "Feature",
  "properties": {
    "iso:country":"DE",
    "sg:address":"Bitburger Str. 38",
    "sg:city":"Bitburg",
    "sg:phone":"+49 6561/8139",
    "sg:postcode":"54634",
    "sg:province":"Rheinland-Pfalz",
    "wof:name":"T. Und P. Gansen",
    "wof:placetype":"venue"
},
  "geometry": {"coordinates":[6.544284,49.961044],"type":"Point"}
}