{
  "type": "Feature",
  "properties": {
    "iso:country":"DE",
    "sg:address":"Adalbertstra\u00dfe 20",
    "sg:city":"Berlin - Kreuzberg",
    "sg:phone":"+49 30/61694910",
    "sg:postcode":"10997",
    "sg:province":"Berlin",
    "wof:name":"Heimann Messebau",
    "wof:placetype":"venue"
},
  "geometry": {"coordinates":[13.420408,52.502529],"type":"Point"}
}