{
  "type": "Feature",
  "properties": {
    "iso:country":"DE",
    "sg:address":"Schluchtweg 13",
    "sg:city":"P\u00f6cking",
    "sg:phone":"+49 8151/911234",
    "sg:postcode":"82343",
    "sg:province":"Bayern",
    "wof:name":"Karl Lense Architekt",
    "wof:placetype":"venue"
},
  "geometry": {"coordinates":[11.294781,47.987579],"type":"Point"}
}