{
  "type": "Feature",
  "properties": {
    "iso:country":"DE",
    "sg:address":"Arnswaldtstr. 18",
    "sg:city":"Hannover",
    "sg:phone":"+49 511/363930",
    "sg:postcode":"30159",
    "sg:province":"Niedersachsen",
    "wof:name":"Landesverband Der Maschinen- Ringe Niedersachsen E. V.",
    "wof:placetype":"venue"
},
  "geometry": {"coordinates":[9.746376,52.369888],"type":"Point"}
}