{
  "type": "Feature",
  "properties": {
    "iso:country":"DE",
    "sg:address":"Garnkorb 8",
    "sg:city":"Preetz",
    "sg:phone":"+49 190864702",
    "sg:postcode":"24211",
    "sg:province":"Schleswig-Holstein",
    "wof:name":"Terminzentrum Die Veranstaltungssuchmaschine",
    "wof:placetype":"venue"
},
  "geometry": {"coordinates":[10.283364,54.235924],"type":"Point"}
}