{
  "type": "Feature",
  "properties": {
    "iso:country":"DE",
    "sg:address":"Magdeburger Str. 79",
    "sg:city":"Calbe",
    "sg:phone":"+49 39291/2141",
    "sg:postcode":"39240",
    "sg:province":"Sachsen-Anhalt",
    "wof:name":"Klaus Wenzlawe Ingenieur",
    "wof:placetype":"venue"
},
  "geometry": {"coordinates":[11.8869018555,51.915763855],"type":"Point"}
}