{
  "type": "Feature",
  "properties": {
    "iso:country":"DE",
    "sg:address":"Westbahnhofstr. 60",
    "sg:city":"T\u00fcbingen",
    "sg:phone":"+49 7071/793737",
    "sg:postcode":"72070",
    "sg:province":"Baden-W\u00fcrttemberg",
    "wof:name":"Arnold Conrad",
    "wof:placetype":"venue"
},
  "geometry": {"coordinates":[9.039952,48.520882],"type":"Point"}
}