{
  "type": "Feature",
  "properties": {
    "iso:country":"DE",
    "sg:address":"Akazienweg 24a",
    "sg:city":"Baiersdorf",
    "sg:postcode":"91083",
    "sg:province":"Bayern",
    "wof:name":"Hausverkauf In Spanien",
    "wof:placetype":"venue"
},
  "geometry": {"coordinates":[11.03914,49.653568],"type":"Point"}
}