{
  "type": "Feature",
  "properties": {
    "iso:country":"DE",
    "sg:address":"Wahlenpfad 52",
    "sg:city":"Elsdorf",
    "sg:phone":"+49 2274/81158",
    "sg:postcode":"50189",
    "sg:province":"Nordrhein-Westfalen",
    "wof:name":"D. Boekers Heilpraktiker",
    "wof:placetype":"venue"
},
  "geometry": {"coordinates":[6.5476050377,50.9434814453],"type":"Point"}
}