{
  "type": "Feature",
  "properties": {
    "iso:country":"DE",
    "sg:address":"Parkstr. 39",
    "sg:city":"Horn-Bad Meinberg",
    "sg:phone":"+49 5234/2910",
    "sg:postcode":"32805",
    "sg:province":"Nordrhein-Westfalen",
    "wof:name":"Horst Br\u00f6tzmann",
    "wof:placetype":"venue"
},
  "geometry": {"coordinates":[8.9853696823,51.8951797485],"type":"Point"}
}