{
  "type": "Feature",
  "properties": {
    "iso:country":"DE",
    "sg:address":"Rothenbaumchausee 76b",
    "sg:city":"Hamburg",
    "sg:phone":"+49 40/41351240",
    "sg:postcode":"20148",
    "sg:province":"Hamburg",
    "wof:name":"D\u00f6rner Architekten",
    "wof:placetype":"venue"
},
  "geometry": {"coordinates":[9.988442,53.567169],"type":"Point"}
}