{
  "type": "Feature",
  "properties": {
    "iso:country":"DE",
    "sg:address":"Rudolf-Diesel-Str. 12",
    "sg:city":"Sandhausen",
    "sg:phone":"+49 4962/2454061",
    "sg:postcode":"69207",
    "sg:province":"Baden-W\u00fcrttemberg",
    "wof:name":"Pasco Gmbh",
    "wof:placetype":"venue"
},
  "geometry": {"coordinates":[8.658372,49.342365],"type":"Point"}
}