{
  "type": "Feature",
  "properties": {
    "iso:country":"DE",
    "sg:address":"Freie Bauernstr. 5",
    "sg:city":"Argenb\u00fchl",
    "sg:phone":"+49 7566/91201",
    "sg:postcode":"88260",
    "sg:province":"Baden-W\u00fcrttemberg",
    "wof:name":"Emil Geiger",
    "wof:placetype":"venue"
},
  "geometry": {"coordinates":[9.929476738,47.6628684998],"type":"Point"}
}