{
  "type": "Feature",
  "properties": {
    "iso:country":"DE",
    "sg:address":"Stenney 3",
    "sg:city":"Hagen",
    "sg:phone":"+49 2331/42007",
    "sg:postcode":"58135",
    "sg:province":"Nordrhein-Westfalen",
    "wof:name":"Indusriebedarf Sch\u00f6nfeld Gmbh",
    "wof:placetype":"venue"
},
  "geometry": {"coordinates":[7.422423,51.34811],"type":"Point"}
}