{
  "type": "Feature",
  "properties": {
    "iso:country":"DE",
    "sg:address":"Linggplatz 13",
    "sg:city":"Bad Hersfeld",
    "sg:phone":"+49 6621/2882",
    "sg:postcode":"36251",
    "sg:province":"Hessen",
    "wof:name":"Peter Klingelh\u00f6fer",
    "wof:placetype":"venue"
},
  "geometry": {"coordinates":[9.705598,50.867626],"type":"Point"}
}