{
  "type": "Feature",
  "properties": {
    "iso:country":"DE",
    "sg:address":"Schulterblatt 58",
    "sg:city":"Hamburg",
    "sg:phone":"+49 40/43252620",
    "sg:postcode":"20357",
    "sg:province":"Hamburg",
    "wof:name":"Medienagentur Peter Stertz Gmbh",
    "wof:placetype":"venue"
},
  "geometry": {"coordinates":[9.9628009796,53.5612716675],"type":"Point"}
}