{
  "type": "Feature",
  "properties": {
    "iso:country":"DE",
    "sg:address":"Ossenpa\u00df 15",
    "sg:city":"Kevelaer",
    "sg:phone":"+49 2832/4544",
    "sg:postcode":"47623",
    "sg:province":"Nordrhein-Westfalen",
    "wof:name":"Hendrix",
    "wof:placetype":"venue"
},
  "geometry": {"coordinates":[6.262779,51.582848],"type":"Point"}
}