{
  "type": "Feature",
  "properties": {
    "iso:country":"DE",
    "sg:address":"Bismarckstr. 1",
    "sg:city":"Bad Oeynhausen",
    "sg:phone":"+49 5731/20187",
    "sg:postcode":"32545",
    "sg:province":"Nordrhein-Westfalen",
    "wof:name":"Alten- Und Pflegeheim Pust",
    "wof:placetype":"venue"
},
  "geometry": {"coordinates":[8.798922,52.200981],"type":"Point"}
}