{
  "type": "Feature",
  "properties": {
    "iso:country":"DE",
    "sg:address":"Altenberger Str. 9d",
    "sg:city":"Hermsdorf",
    "sg:postcode":"01776",
    "sg:province":"Sachsen",
    "wof:name":"Karl-heinz Schmieder",
    "wof:placetype":"venue"
},
  "geometry": {"coordinates":[13.65759,50.735722],"type":"Point"}
}