{
  "type": "Feature",
  "properties": {
    "iso:country":"DE",
    "sg:address":"Friedl\u00e4nder Landstr. 16",
    "sg:city":"Anklam",
    "sg:phone":"+49 3971/5962",
    "sg:postcode":"17389",
    "sg:province":"Mecklenburg-Vorpommern",
    "wof:name":"Karl Und Reinhard Teske",
    "wof:placetype":"venue"
},
  "geometry": {"coordinates":[13.686622,53.845707],"type":"Point"}
}