{
  "type": "Feature",
  "properties": {
    "iso:country":"DE",
    "sg:address":"Daimlerstr. 18",
    "sg:city":"Neus\u00e4\u00df",
    "sg:phone":"+49 821/469163",
    "sg:postcode":"86356",
    "sg:province":"Bayern",
    "wof:name":"Dorner",
    "wof:placetype":"venue"
},
  "geometry": {"coordinates":[10.824837,48.393593],"type":"Point"}
}