{
  "type": "Feature",
  "properties": {
    "iso:country":"DE",
    "sg:address":"Jesinger Hauptstr. 51",
    "sg:city":"T\u00fcbingen",
    "sg:postcode":"72070",
    "sg:province":"Baden-W\u00fcrttemberg",
    "wof:name":"Technoass Verwaltungs-und Beteiligungs- Gmbh",
    "wof:placetype":"venue"
},
  "geometry": {"coordinates":[8.978524,48.526691],"type":"Point"}
}