{
  "type": "Feature",
  "properties": {
    "iso:country":"DE",
    "sg:address":"Winterberg 8",
    "sg:city":"Kalletal",
    "sg:phone":"+49 5733/2696",
    "sg:postcode":"32689",
    "sg:province":"Nordrhein-Westfalen",
    "wof:name":"H. Westhoff",
    "wof:placetype":"venue"
},
  "geometry": {"coordinates":[8.902067,52.157043],"type":"Point"}
}