{
  "type": "Feature",
  "properties": {
    "iso:country":"DE",
    "sg:address":"Br\u00fcggener Stra\u00dfe",
    "sg:city":"Br\u00fcggen",
    "sg:phone":"+49 2157/909497",
    "sg:postcode":"41379",
    "sg:province":"Nordrhein-Westfalen",
    "wof:name":"Die Seite Der Region Viersen",
    "wof:placetype":"venue"
},
  "geometry": {"coordinates":[6.190205,51.274204],"type":"Point"}
}