{
  "type": "Feature",
  "properties": {
    "iso:country":"DE",
    "sg:address":"Stuttgarter Str. 28",
    "sg:city":"Herrenberg",
    "sg:phone":"+49 7032/24930",
    "sg:postcode":"71083",
    "sg:province":"Baden-W\u00fcrttemberg",
    "wof:name":"Siner",
    "wof:placetype":"venue"
},
  "geometry": {"coordinates":[8.8709526062,48.5976829529],"type":"Point"}
}