{
  "type": "Feature",
  "properties": {
    "iso:country":"DE",
    "sg:address":"Dolomitenstr. 11",
    "sg:city":"Berlin",
    "sg:phone":"+49 30/4711089",
    "sg:postcode":"13187",
    "sg:province":"Berlin",
    "wof:name":"Michael Hentschel Patentanwalt",
    "wof:placetype":"venue"
},
  "geometry": {"coordinates":[13.4004478455,52.5591049194],"type":"Point"}
}