{
  "type": "Feature",
  "properties": {
    "iso:country":"DE",
    "sg:address":"Maria-Neide-Str 2",
    "sg:city":"Magdeburg",
    "sg:phone":"+49 391/625640",
    "sg:postcode":"39120",
    "sg:province":"Sachsen-Anhalt",
    "wof:name":"Lvq-wp Pr\u00fcflabor Gmbh",
    "wof:placetype":"venue"
},
  "geometry": {"coordinates":[11.639877,52.085785],"type":"Point"}
}