{
  "type": "Feature",
  "properties": {
    "iso:country":"DE",
    "sg:address":"Kaiserstr. 167",
    "sg:city":"Herten",
    "sg:phone":"+49 2366/37262",
    "sg:postcode":"45699",
    "sg:province":"Nordrhein-Westfalen",
    "wof:name":"Ev. Pfarramt Disteln Scherlebeck",
    "wof:placetype":"venue"
},
  "geometry": {"coordinates":[7.1508789062,51.6005096436],"type":"Point"}
}