{
  "type": "Feature",
  "properties": {
    "iso:country":"DE",
    "sg:address":"Stradower Weg",
    "sg:city":"Vetschau",
    "sg:phone":"+49 35433/7700",
    "sg:postcode":"03226",
    "sg:province":"Brandenburg",
    "wof:name":"Bay Wa Ag",
    "wof:placetype":"venue"
},
  "geometry": {"coordinates":[14.0933761597,51.78673172],"type":"Point"}
}