{
  "type": "Feature",
  "properties": {
    "iso:country":"DE",
    "sg:address":"Bahnhofstr. 15",
    "sg:city":"M\u00fcnster",
    "sg:phone":"+49 251/56265",
    "sg:postcode":"48143",
    "sg:province":"Nordrhein-Westfalen",
    "wof:name":"Wilhelm Hagemann",
    "wof:placetype":"venue"
},
  "geometry": {"coordinates":[7.6347680092,51.9578437805],"type":"Point"}
}