{
  "type": "Feature",
  "properties": {
    "iso:country":"DE",
    "sg:address":"Normannenstr. 47",
    "sg:city":"Wuppertal",
    "sg:phone":"+49 202/266190",
    "sg:postcode":"42277",
    "sg:province":"Nordrhein-Westfalen",
    "wof:name":"Hilmo Hildesheim & Mosblech Gmbh",
    "wof:placetype":"venue"
},
  "geometry": {"coordinates":[7.2187771797,51.2766227722],"type":"Point"}
}