{
  "type": "Feature",
  "properties": {
    "iso:country":"DE",
    "sg:address":"Eberhardstr. 19",
    "sg:city":"Trier",
    "sg:phone":"+49 651/141548",
    "sg:postcode":"54290",
    "sg:province":"Rheinland-Pfalz",
    "wof:name":"Dpa Deutsche Presse Agentur Gmbh",
    "wof:placetype":"venue"
},
  "geometry": {"coordinates":[6.6349310875,49.7489776611],"type":"Point"}
}