{
  "type": "Feature",
  "properties": {
    "iso:country":"DE",
    "sg:address":"Friedrichplatz 19::",
    "sg:city":"Mannheim",
    "sg:phone":"+49 4962/1816036",
    "sg:postcode":"68165",
    "sg:province":"Baden-W\u00fcrttemberg",
    "wof:name":"Dr. Weber & Partner Leasing-gesellschaftmbh",
    "wof:placetype":"venue"
},
  "geometry": {"coordinates":[8.478332,49.48341],"type":"Point"}
}