{
  "type": "Feature",
  "properties": {
    "iso:country":"DE",
    "sg:address":"Steinbacher Str. 22",
    "sg:city":"St. Wendel",
    "sg:phone":"+49 6851/5263",
    "sg:postcode":"66606",
    "sg:province":"Saarland",
    "wof:name":"Willi W\u00f6lflinger",
    "wof:placetype":"venue"
},
  "geometry": {"coordinates":[7.163632,49.432484],"type":"Point"}
}