{
  "type": "Feature",
  "properties": {
    "iso:country":"DE",
    "sg:address":"Wiesk\u00e4mper Weg 22",
    "sg:city":"Marl",
    "sg:phone":"+49 2365/71424",
    "sg:postcode":"45768",
    "sg:province":"Nordrhein-Westfalen",
    "wof:name":"Klaus H\u00f6nig Steureberater",
    "wof:placetype":"venue"
},
  "geometry": {"coordinates":[7.043443203,51.6266136169],"type":"Point"}
}