{
  "type": "Feature",
  "properties": {
    "iso:country":"DE",
    "sg:address":"B\u00e4renallee 34",
    "sg:city":"Hamburg",
    "sg:phone":"+49 40/6521401",
    "sg:postcode":"22041",
    "sg:province":"Hamburg",
    "wof:name":"J. Kumolka Immobilienmakler",
    "wof:placetype":"venue"
},
  "geometry": {"coordinates":[10.0663919449,53.569934845],"type":"Point"}
}