{
  "type": "Feature",
  "properties": {
    "iso:country":"DE",
    "sg:address":"Ebstorfer Str. 4",
    "sg:city":"Melbeck",
    "sg:phone":"+49 4134/910995",
    "sg:postcode":"21406",
    "sg:province":"Niedersachsen",
    "wof:name":"Michael Raasch E. K.",
    "wof:placetype":"venue"
},
  "geometry": {"coordinates":[10.405620575,53.1798286438],"type":"Point"}
}