{
  "type": "Feature",
  "properties": {
    "iso:country":"DE",
    "sg:address":"Holzdorfer Str. 18",
    "sg:city":"Annaburg",
    "sg:phone":"+49 35385/20218",
    "sg:postcode":"06925",
    "sg:province":"Sachsen-Anhalt",
    "wof:name":"Horst Lohmann",
    "wof:placetype":"venue"
},
  "geometry": {"coordinates":[13.0501365662,51.7320327759],"type":"Point"}
}