{
  "type": "Feature",
  "properties": {
    "iso:country":"DE",
    "sg:address":"Am Lomberg 1",
    "sg:city":"Velbert",
    "sg:phone":"+49 2052/4504",
    "sg:postcode":"42555",
    "sg:province":"Nordrhein-Westfalen",
    "wof:name":"Schaltbau Holding Ag",
    "wof:placetype":"venue"
},
  "geometry": {"coordinates":[7.1036810875,51.3498497009],"type":"Point"}
}