{
  "type": "Feature",
  "properties": {
    "iso:country":"DE",
    "sg:address":"Malteserstr. 11",
    "sg:city":"Reutlingen",
    "sg:phone":"+49 7121/57190",
    "sg:postcode":"72770",
    "sg:province":"Baden-W\u00fcrttemberg",
    "wof:name":"W. Kurz",
    "wof:placetype":"venue"
},
  "geometry": {"coordinates":[9.1730918884,48.4955940247],"type":"Point"}
}