{
  "type": "Feature",
  "properties": {
    "iso:country":"DE",
    "sg:address":"Papenstr. 6",
    "sg:city":"Wismar",
    "sg:phone":"+49 3841/258490",
    "sg:postcode":"23966",
    "sg:province":"Mecklenburg-Vorpommern",
    "wof:name":"Wismar Immobilien",
    "wof:placetype":"venue"
},
  "geometry": {"coordinates":[11.4616775513,53.8895454407],"type":"Point"}
}