{
  "type": "Feature",
  "properties": {
    "iso:country":"DE",
    "sg:address":"S\u00fcskindstr. 4",
    "sg:city":"M\u00fcnchen",
    "sg:phone":"+49 89/936096",
    "sg:postcode":"81929",
    "sg:province":"Bayern",
    "wof:name":"Messecard Besucher- Und Aussteller-informations-",
    "wof:placetype":"venue"
},
  "geometry": {"coordinates":[11.6483325958,48.1400756836],"type":"Point"}
}