{
  "type": "Feature",
  "properties": {
    "iso:country":"DE",
    "sg:address":"Hagelkreuzstr. 5",
    "sg:city":"Hilden",
    "sg:phone":"+49 2103/8520",
    "sg:postcode":"40721",
    "sg:province":"Nordrhein-Westfalen",
    "wof:name":"Else De Fries",
    "wof:placetype":"venue"
},
  "geometry": {"coordinates":[6.935936,51.164822],"type":"Point"}
}