{
  "type": "Feature",
  "properties": {
    "iso:country":"DE",
    "sg:city":"Bad Marienberg",
    "sg:postcode":"56470",
    "sg:province":"Rheinland-Pfalz",
    "wof:name":"Drk Senioreneinrichtungen In Bad Marienberg Im Westerwald",
    "wof:placetype":"venue"
},
  "geometry": {"coordinates":[7.951052,50.650074],"type":"Point"}
}