{
  "type": "Feature",
  "properties": {
    "iso:country":"DE",
    "sg:address":"Holser Str. 16",
    "sg:city":"B\u00fcnde",
    "sg:phone":"+49 5223/61389",
    "sg:postcode":"32257",
    "sg:province":"Nordrhein-Westfalen",
    "wof:name":"Erich L\u00f6ffler",
    "wof:placetype":"venue"
},
  "geometry": {"coordinates":[8.56541,52.203533],"type":"Point"}
}