{
  "type": "Feature",
  "properties": {
    "iso:country":"DE",
    "sg:address":"Hochriesweg 5",
    "sg:city":"Nu\u00dfdorf",
    "sg:phone":"+49 8034/4839",
    "sg:postcode":"83131",
    "sg:province":"Bayern",
    "wof:name":"Haus St. Benedikt Wohn- Und Pflegeheim F\u00fcr \u00e4ltere Menschen",
    "wof:placetype":"venue"
},
  "geometry": {"coordinates":[12.1583032608,47.7422676086],"type":"Point"}
}