{
  "type": "Feature",
  "properties": {
    "iso:country":"DE",
    "sg:address":"Walther-Rathenau-Str. 14 a",
    "sg:city":"Gro\u00df-Gerau",
    "sg:phone":"+49 6152/83814",
    "sg:postcode":"64521",
    "sg:province":"Hessen",
    "wof:name":"L\u00fchrs",
    "wof:placetype":"venue"
},
  "geometry": {"coordinates":[8.4823789597,49.9193840027],"type":"Point"}
}