{
  "type": "Feature",
  "properties": {
    "iso:country":"DE",
    "sg:address":"Am Zehnthof 100",
    "sg:city":"Essen",
    "sg:phone":"+49 4920/189830",
    "sg:postcode":"45307",
    "sg:province":"Nordrhein-Westfalen",
    "wof:name":"Kolping-berufsbildungswerk Essen Gemeinn\u00dctzige Gesellschaft6",
    "wof:placetype":"venue"
},
  "geometry": {"coordinates":[7.059827,51.458054],"type":"Point"}
}