{
  "type": "Feature",
  "properties": {
    "iso:country":"DE",
    "sg:address":"Obere Krautgasse 24",
    "sg:city":"Laucha",
    "sg:phone":"+49 34462/21644",
    "sg:postcode":"06636",
    "sg:province":"Sachsen-Anhalt",
    "wof:name":"Frank Bothe Gmbh",
    "wof:placetype":"venue"
},
  "geometry": {"coordinates":[11.681876,51.225048],"type":"Point"}
}