{
  "type": "Feature",
  "properties": {
    "iso:country":"DE",
    "sg:address":"Stadtveener Str. 66",
    "sg:city":"Sonsbeck",
    "sg:phone":"+49 2838/3825",
    "sg:postcode":"47665",
    "sg:province":"Nordrhein-Westfalen",
    "wof:name":"Heinrich Eberhard",
    "wof:placetype":"venue"
},
  "geometry": {"coordinates":[6.417185,51.602699],"type":"Point"}
}