{
  "type": "Feature",
  "properties": {
    "iso:country":"DE",
    "sg:address":"Frankenstr. 43",
    "sg:city":"Bubenreuth",
    "sg:phone":"+49 9131/89560",
    "sg:postcode":"91088",
    "sg:province":"Bayern",
    "wof:name":"Josef Teller Ohg",
    "wof:placetype":"venue"
},
  "geometry": {"coordinates":[11.0089063644,49.6253967285],"type":"Point"}
}