{
  "type": "Feature",
  "properties": {
    "iso:country":"DE",
    "sg:address":"Am Hofteich 6",
    "sg:city":"Pfaffroda-Sch\u00f6nfeld",
    "sg:phone":"+49 37360/6170",
    "sg:postcode":"09526",
    "sg:province":"Sachsen",
    "wof:name":"Martin Zschorn",
    "wof:placetype":"venue"
},
  "geometry": {"coordinates":[13.3568983078,50.6962623596],"type":"Point"}
}