{
  "type": "Feature",
  "properties": {
    "iso:country":"DE",
    "sg:address":"Averdiekstr. 2",
    "sg:city":"Osnabr\u00fcck",
    "sg:phone":"+49 541/440430",
    "sg:postcode":"49078",
    "sg:province":"Niedersachsen",
    "wof:name":"Bohlen & Sohn Gmbh & Co. Kg",
    "wof:placetype":"venue"
},
  "geometry": {"coordinates":[7.976,52.267277],"type":"Point"}
}