{
  "type": "Feature",
  "properties": {
    "iso:country":"DE",
    "sg:address":"Hagener Str. 65",
    "sg:city":"Iserlohn",
    "sg:phone":"+49 2374/10424",
    "sg:postcode":"58642",
    "sg:province":"Nordrhein-Westfalen",
    "wof:name":"Sanit\u00e4tshaus H. Enneper",
    "wof:placetype":"venue"
},
  "geometry": {"coordinates":[7.6115221977,51.3651313782],"type":"Point"}
}