{
  "type": "Feature",
  "properties": {
    "iso:country":"DE",
    "sg:address":"Gangolfsweg 12",
    "sg:city":"Aachen",
    "sg:phone":"+49 2408/3117",
    "sg:postcode":"52076",
    "sg:province":"Nordrhein-Westfalen",
    "wof:name":"E. Rombach Heissmangel",
    "wof:placetype":"venue"
},
  "geometry": {"coordinates":[6.1782531738,50.7265052795],"type":"Point"}
}