{
  "type": "Feature",
  "properties": {
    "iso:country":"DE",
    "sg:address":"Spartanerstr. 7",
    "sg:city":"Hannover",
    "sg:phone":"+49 511/8441688",
    "sg:postcode":"30519",
    "sg:province":"Niedersachsen",
    "wof:name":"Cbs Konzepte Ges. F\u00fcr Coaching Beratung Und",
    "wof:placetype":"venue"
},
  "geometry": {"coordinates":[9.76287,52.342121],"type":"Point"}
}