{
  "type": "Feature",
  "properties": {
    "iso:country":"DE",
    "sg:address":"Kiesstr. 111",
    "sg:city":"Darmstadt",
    "sg:phone":"+49 6151/47055",
    "sg:postcode":"64287",
    "sg:province":"Hessen",
    "wof:name":"J. Koch Finanzberater",
    "wof:placetype":"venue"
},
  "geometry": {"coordinates":[8.666893959,49.8685150146],"type":"Point"}
}