{
  "type": "Feature",
  "properties": {
    "iso:country":"DE",
    "sg:address":"Pfarrgasse 4",
    "sg:city":"Sulzbach-Rosenberg",
    "sg:phone":"+49 9661/3407",
    "sg:postcode":"92237",
    "sg:province":"Bayern",
    "wof:name":"Sozialberatung F. Werdende M\u00fctter",
    "wof:placetype":"venue"
},
  "geometry": {"coordinates":[11.738922,49.506069],"type":"Point"}
}