{
  "type": "Feature",
  "properties": {
    "iso:country":"DE",
    "sg:address":"Bruchtannenstr.1",
    "sg:city":"Kleinostheim",
    "sg:phone":"+49 6027",
    "sg:postcode":"63801",
    "sg:province":"Bayern",
    "wof:name":"Be-schu-plast",
    "wof:placetype":"venue"
},
  "geometry": {"coordinates":[9.062551,50.010654],"type":"Point"}
}