{
  "type": "Feature",
  "properties": {
    "iso:country":"DE",
    "sg:address":"Dorfstr. 84",
    "sg:city":"Selbitz",
    "sg:phone":"+49 34928/60107",
    "sg:postcode":"06773",
    "sg:province":"Sachsen-Anhalt",
    "wof:name":"Landwirtschaftsbetrieb E.g.",
    "wof:placetype":"venue"
},
  "geometry": {"coordinates":[12.537664,51.812405],"type":"Point"}
}