{
  "type": "Feature",
  "properties": {
    "iso:country":"DE",
    "sg:address":"Barthelsm\u00fchlring 24",
    "sg:city":"Kandel",
    "sg:phone":"+49 7275/8673",
    "sg:postcode":"76870",
    "sg:province":"Rheinland-Pfalz",
    "wof:name":"\u00d6\u00dfwein Gmbh",
    "wof:placetype":"venue"
},
  "geometry": {"coordinates":[8.1795940399,49.0997772217],"type":"Point"}
}