{
  "type": "Feature",
  "properties": {
    "iso:country":"DE",
    "sg:address":"M\u00f6rikestr 3",
    "sg:city":"Mandelbachtal",
    "sg:phone":"+49 6893/2951",
    "sg:postcode":"66399",
    "sg:province":"Saarland",
    "wof:name":"Schmich Schweisstechnik Gmbh",
    "wof:placetype":"venue"
},
  "geometry": {"coordinates":[7.1467218399,49.1945495605],"type":"Point"}
}