{
  "type": "Feature",
  "properties": {
    "iso:country":"DE",
    "sg:address":"R\u00fcckersh\u00e4user Str. 4",
    "sg:city":"Burgschwalbach",
    "sg:phone":"+49 6430/7853",
    "sg:postcode":"65558",
    "sg:province":"Rheinland-Pfalz",
    "wof:name":"Albert Poths",
    "wof:placetype":"venue"
},
  "geometry": {"coordinates":[8.078405,50.282284],"type":"Point"}
}