{
  "type": "Feature",
  "properties": {
    "iso:country":"DE",
    "sg:address":"Paetowstr. 11",
    "sg:city":"Potsdam",
    "sg:phone":"+49 331/2805710",
    "sg:postcode":"14473",
    "sg:province":"Brandenburg",
    "wof:name":"Heinz Schlegelmilch Ingenieur",
    "wof:placetype":"venue"
},
  "geometry": {"coordinates":[13.0527448654,52.3822555542],"type":"Point"}
}