{
  "type": "Feature",
  "properties": {
    "iso:country":"DE",
    "sg:address":"Am Friedensberg 27",
    "sg:city":"Klingenthal",
    "sg:phone":"+49 37467/22873",
    "sg:postcode":"08248",
    "sg:province":"Sachsen",
    "wof:name":"Erhard G\u00fcndel",
    "wof:placetype":"venue"
},
  "geometry": {"coordinates":[12.475718,50.359779],"type":"Point"}
}