{
  "type": "Feature",
  "properties": {
    "iso:country":"DE",
    "sg:address":"Otto-von-Guericke-Str. 54",
    "sg:city":"Magdeburg",
    "sg:postcode":"39104",
    "sg:province":"Sachsen-Anhalt",
    "wof:name":"Christine Ebeling",
    "wof:placetype":"venue"
},
  "geometry": {"coordinates":[11.6272640228,52.1211242676],"type":"Point"}
}