{
  "type": "Feature",
  "properties": {
    "iso:country":"DE",
    "sg:address":"Fliederweg 8",
    "sg:city":"Melsungen",
    "sg:phone":"+49 5661/1641",
    "sg:postcode":"34212",
    "sg:province":"Hessen",
    "wof:name":"Thomas Krug Ingenieur",
    "wof:placetype":"venue"
},
  "geometry": {"coordinates":[9.5511646271,51.1324882507],"type":"Point"}
}