{
  "type": "Feature",
  "properties": {
    "iso:country":"DE",
    "sg:address":"Benzstr. 3",
    "sg:city":"W\u00fcrzburg",
    "sg:phone":"+49 931/450690",
    "sg:postcode":"97082",
    "sg:province":"Bayern",
    "wof:name":"Schumacher & Gr\u00c4f Gmbh & Co Kg",
    "wof:placetype":"venue"
},
  "geometry": {"coordinates":[9.909855,49.798618],"type":"Point"}
}