{
  "type": "Feature",
  "properties": {
    "iso:country":"DE",
    "sg:address":"Augustenstr. 5 a",
    "sg:city":"Regensburg",
    "sg:phone":"+49 941/22442",
    "sg:postcode":"93049",
    "sg:province":"Bayern",
    "wof:name":"Richard F\u00fcrbacher",
    "wof:placetype":"venue"
},
  "geometry": {"coordinates":[12.0874090195,49.0144233704],"type":"Point"}
}