{
  "type": "Feature",
  "properties": {
    "iso:country":"DE",
    "sg:address":"Bessemerstr. 15",
    "sg:city":"Frankfurt",
    "sg:phone":"+49 6109/36867",
    "sg:postcode":"60388",
    "sg:province":"Hessen",
    "wof:name":"Rotex Werkzeugmaschinen- Handel Gmbh",
    "wof:placetype":"venue"
},
  "geometry": {"coordinates":[8.749282,50.142944],"type":"Point"}
}