{
  "type": "Feature",
  "properties": {
    "iso:country":"DE",
    "sg:address":"\u00d6lm\u00fchle 40",
    "sg:city":"Langerwehe",
    "sg:phone":"+49 2423/901933",
    "sg:postcode":"52379",
    "sg:province":"Nordrhein-Westfalen",
    "wof:name":"Christian Baum",
    "wof:placetype":"venue"
},
  "geometry": {"coordinates":[6.373009,50.822231],"type":"Point"}
}