{
  "type": "Feature",
  "properties": {
    "iso:country":"DE",
    "sg:address":"Braunschweiger Str. 12",
    "sg:city":"Gifhorn",
    "sg:phone":"+49 5371/140429",
    "sg:postcode":"38518",
    "sg:province":"Niedersachsen",
    "wof:name":"Jordan-bolzmann-hirschfeld Gbr",
    "wof:placetype":"venue"
},
  "geometry": {"coordinates":[10.5442152023,52.480632782],"type":"Point"}
}