{
  "type": "Feature",
  "properties": {
    "iso:country":"DE",
    "sg:address":"Kortumstr. 66",
    "sg:city":"Bochum",
    "sg:phone":"+49 234/683009",
    "sg:postcode":"44787",
    "sg:province":"Nordrhein-Westfalen",
    "wof:name":"Dagmar Schramm Krankengymnastin",
    "wof:placetype":"venue"
},
  "geometry": {"coordinates":[7.217327,51.480122],"type":"Point"}
}