{
  "type": "Feature",
  "properties": {
    "iso:country":"DE",
    "sg:address":"Industriestr. 22",
    "sg:city":"Rotenburg",
    "sg:phone":"+49 4261/94940",
    "sg:postcode":"27356",
    "sg:province":"Niedersachsen",
    "wof:name":"Multi Gastronomietechnik Gmbh",
    "wof:placetype":"venue"
},
  "geometry": {"coordinates":[9.427618,53.12392],"type":"Point"}
}