{
  "type": "Feature",
  "properties": {
    "iso:country":"DE",
    "sg:address":"Hermann-Lingg-Str. 2",
    "sg:city":"M\u00fcnchen",
    "sg:phone":"+49 89/54466333",
    "sg:postcode":"80336",
    "sg:province":"Bayern",
    "wof:name":"Kpd.de",
    "wof:placetype":"venue"
},
  "geometry": {"coordinates":[11.5515041351,48.1387863159],"type":"Point"}
}