{
  "type": "Feature",
  "properties": {
    "iso:country":"DE",
    "sg:address":"M\u00fcndelheimer Weg 48",
    "sg:city":"D\u00fcsseldorf",
    "sg:phone":"+49 211/941030",
    "sg:postcode":"40472",
    "sg:province":"Nordrhein-Westfalen",
    "wof:name":"Berendsen Textilservice Gmbh",
    "wof:placetype":"venue"
},
  "geometry": {"coordinates":[6.797726,51.288597],"type":"Point"}
}