{
  "type": "Feature",
  "properties": {
    "iso:country":"DE",
    "sg:address":"Ludwigsgraben 22",
    "sg:city":"K\u00f6sching",
    "sg:phone":"+49 8456/7662",
    "sg:postcode":"85092",
    "sg:province":"Bayern",
    "wof:name":"Franz Liepold",
    "wof:placetype":"venue"
},
  "geometry": {"coordinates":[11.502503,48.809875],"type":"Point"}
}