{
  "type": "Feature",
  "properties": {
    "iso:country":"DE",
    "sg:address":"V\u00f6rfken 18",
    "sg:city":"Schwelm",
    "sg:phone":"+49 2336/12574",
    "sg:postcode":"58332",
    "sg:province":"Nordrhein-Westfalen",
    "wof:name":"Scolari Gmbh",
    "wof:placetype":"venue"
},
  "geometry": {"coordinates":[7.265285,51.289143],"type":"Point"}
}