{
  "type": "Feature",
  "properties": {
    "iso:country":"DE",
    "sg:address":"Nadorster Weg 15",
    "sg:city":"Cloppenburg",
    "sg:postcode":"49661",
    "sg:province":"Niedersachsen",
    "wof:name":"Um Die Welt Reisen Inh. Gerhard Hoppe",
    "wof:placetype":"venue"
},
  "geometry": {"coordinates":[8.0474424362,52.8477363586],"type":"Point"}
}