{
  "type": "Feature",
  "properties": {
    "iso:country":"DE",
    "sg:address":"Hauptstr. 93",
    "sg:city":"\u00d6stringen",
    "sg:phone":"+49 7253/21082",
    "sg:postcode":"76684",
    "sg:province":"Baden-W\u00fcrttemberg",
    "wof:name":"Reiseb\u00fcro Die Reise",
    "wof:placetype":"venue"
},
  "geometry": {"coordinates":[8.7092638016,49.218460083],"type":"Point"}
}