{
  "type": "Feature",
  "properties": {
    "iso:country":"DE",
    "sg:address":"Thalkirchner Str. 288",
    "sg:city":"M\u00fcnchen",
    "sg:phone":"+49 89/7232122",
    "sg:postcode":"81371",
    "sg:province":"Bayern",
    "wof:name":"Guido Pretzl",
    "wof:placetype":"venue"
},
  "geometry": {"coordinates":[11.5449409485,48.1056251526],"type":"Point"}
}