{
  "type": "Feature",
  "properties": {
    "iso:country":"DE",
    "sg:address":"Krenmoosstr. 6",
    "sg:city":"Karlsfeld",
    "sg:phone":"+49 8131/92353",
    "sg:postcode":"85757",
    "sg:province":"Bayern",
    "wof:name":"Josef Bayerl",
    "wof:placetype":"venue"
},
  "geometry": {"coordinates":[11.47348,48.224419],"type":"Point"}
}