{
  "type": "Feature",
  "properties": {
    "iso:country":"DE",
    "sg:address":"Kirchstr. 31",
    "sg:city":"Friesoythe",
    "sg:phone":"+49 4491/2306",
    "sg:postcode":"26169",
    "sg:province":"Niedersachsen",
    "wof:name":"Lampenhaus Roter Inh. Lucie Roter",
    "wof:placetype":"venue"
},
  "geometry": {"coordinates":[7.8610401154,53.0214118958],"type":"Point"}
}