{
  "type": "Feature",
  "properties": {
    "iso:country":"DE",
    "sg:address":"Seffenter Weg 8",
    "sg:city":"Aachen",
    "sg:phone":"+49 241/801",
    "sg:postcode":"52074",
    "sg:province":"Nordrhein-Westfalen",
    "wof:name":"Wiss. Institut Lehrstuhl Und Institut F\u00fcr",
    "wof:placetype":"venue"
},
  "geometry": {"coordinates":[6.0677690506,50.7809791565],"type":"Point"}
}