{
  "type": "Feature",
  "properties": {
    "iso:country":"DE",
    "sg:address":"Schwarzh\u00f6lzlstr. 30",
    "sg:city":"M\u00fcnchen",
    "sg:phone":"+49 89/3141021",
    "sg:postcode":"80995",
    "sg:province":"Bayern",
    "wof:name":"G. Waldherr",
    "wof:placetype":"venue"
},
  "geometry": {"coordinates":[11.521150589,48.2219200134],"type":"Point"}
}