{
  "type": "Feature",
  "properties": {
    "iso:country":"DE",
    "sg:address":"Ortsstr. 1c",
    "sg:city":"Wutha-Farnroda",
    "sg:phone":"+49 36921/90943",
    "sg:postcode":"99848",
    "sg:province":"Th\u00fcringen",
    "wof:name":"Prof. Dr. M. Eichel Heilprakiker",
    "wof:placetype":"venue"
},
  "geometry": {"coordinates":[10.432299614,50.9464302063],"type":"Point"}
}