{
  "type": "Feature",
  "properties": {
    "iso:country":"DE",
    "sg:address":"Gillbachstr. 111",
    "sg:city":"Neuss",
    "sg:phone":"+49 2131/471583",
    "sg:postcode":"41466",
    "sg:province":"Nordrhein-Westfalen",
    "wof:name":"Reinhold Kaltenberg",
    "wof:placetype":"venue"
},
  "geometry": {"coordinates":[6.6881461143,51.1535987854],"type":"Point"}
}