{
  "type": "Feature",
  "properties": {
    "iso:country":"DE",
    "sg:address":"Ladestr. 2",
    "sg:city":"Landstuhl",
    "sg:phone":"+49 6371/63509",
    "sg:postcode":"66849",
    "sg:province":"Rheinland-Pfalz",
    "wof:name":"Daniele Und Familie",
    "wof:placetype":"venue"
},
  "geometry": {"coordinates":[7.5728697777,49.4165115356],"type":"Point"}
}