{
  "type": "Feature",
  "properties": {
    "iso:country":"DE",
    "sg:address":"Ringstr. 6",
    "sg:city":"Homburg",
    "sg:phone":"+49 4968/411323",
    "sg:postcode":"66424",
    "sg:province":"Saarland",
    "wof:name":"Deutsche Apotheker-und \u00c4rzte Bank",
    "wof:placetype":"venue"
},
  "geometry": {"coordinates":[7.335706,49.31245],"type":"Point"}
}