{
  "type": "Feature",
  "properties": {
    "iso:country":"DE",
    "sg:address":"Boderitzer Str. 17",
    "sg:city":"Dresden",
    "sg:phone":"+49 351/4711634",
    "sg:postcode":"01217",
    "sg:province":"Sachsen",
    "wof:name":"Oswald Rudolphs Blumenland Ohg",
    "wof:placetype":"venue"
},
  "geometry": {"coordinates":[13.749791,51.014603],"type":"Point"}
}