{
  "type": "Feature",
  "properties": {
    "iso:country":"DE",
    "sg:address":"Wollmarkt 17",
    "sg:city":"Arnstadt",
    "sg:phone":"+49 3628/48834",
    "sg:postcode":"99310",
    "sg:province":"Th\u00fcringen",
    "wof:name":"Andis Stube",
    "wof:placetype":"venue"
},
  "geometry": {"coordinates":[10.9548635483,50.8343467712],"type":"Point"}
}