{
  "type": "Feature",
  "properties": {
    "iso:country":"DE",
    "sg:address":"Trebishainer Weg 34",
    "sg:city":"Elbisbach",
    "sg:phone":"+49 34345/22550",
    "sg:postcode":"04651",
    "sg:province":"Sachsen",
    "wof:name":"Gasthof Trebishain",
    "wof:placetype":"venue"
},
  "geometry": {"coordinates":[12.6398649216,51.1047058105],"type":"Point"}
}