{
  "type": "Feature",
  "properties": {
    "iso:country":"DE",
    "sg:address":"Bergstr. 36",
    "sg:city":"Odenthal",
    "sg:postcode":"51519",
    "sg:province":"Nordrhein-Westfalen",
    "wof:name":"K\u00fchner Informations- Technologie Gmbh",
    "wof:placetype":"venue"
},
  "geometry": {"coordinates":[7.1187539101,51.0411567688],"type":"Point"}
}