{
  "type": "Feature",
  "properties": {
    "iso:country":"DE",
    "sg:address":"Sophienblatt 48a",
    "sg:city":"Kiel",
    "sg:phone":"+49 33703/77090",
    "sg:postcode":"24114",
    "sg:province":"Schleswig-Holstein",
    "wof:name":"Buchbindereiservice Gmbh",
    "wof:placetype":"venue"
},
  "geometry": {"coordinates":[13.40193,52.168114],"type":"Point"}
}