{
  "type": "Feature",
  "properties": {
    "iso:country":"DE",
    "sg:address":"Robert-Perthel-Str. 17",
    "sg:city":"K\u00f6ln",
    "sg:phone":"+49 221/174500",
    "sg:postcode":"50739",
    "sg:province":"Nordrhein-Westfalen",
    "wof:name":"Castiglione Gmbh",
    "wof:placetype":"venue"
},
  "geometry": {"coordinates":[6.918610096,50.9803009033],"type":"Point"}
}