{
  "type": "Feature",
  "properties": {
    "iso:country":"DE",
    "sg:address":"Heinrich-Osthus-Str. 34",
    "sg:city":"Bielefeld",
    "sg:phone":"+49 5209/980302",
    "sg:postcode":"33659",
    "sg:province":"Nordrhein-Westfalen",
    "wof:name":"A. Krause",
    "wof:placetype":"venue"
},
  "geometry": {"coordinates":[8.5028533936,51.9512786865],"type":"Point"}
}