{
  "type": "Feature",
  "properties": {
    "iso:country":"DE",
    "sg:address":"Schleinitzstr. 1",
    "sg:city":"Braunschweig",
    "sg:phone":"+49 531/330242",
    "sg:postcode":"38106",
    "sg:province":"Niedersachsen",
    "wof:name":"Anno 1826",
    "wof:placetype":"venue"
},
  "geometry": {"coordinates":[10.5251159668,52.2737083435],"type":"Point"}
}