{
  "type": "Feature",
  "properties": {
    "iso:country":"DE",
    "sg:address":"Lessenstr. 9 A",
    "sg:city":"Goslar",
    "sg:phone":"+49 5321/34455",
    "sg:postcode":"38640",
    "sg:province":"Niedersachsen",
    "wof:name":"Burckhard Und Ulrich M\u00fcller Steuerberater",
    "wof:placetype":"venue"
},
  "geometry": {"coordinates":[10.4187631607,51.9186401367],"type":"Point"}
}