{
  "type": "Feature",
  "properties": {
    "iso:country":"DE",
    "sg:address":"Feldstr. 16",
    "sg:city":"Eltville",
    "sg:phone":"+49 6123/2855",
    "sg:postcode":"65343",
    "sg:province":"Hessen",
    "wof:name":"Klaus Neuhoff Architekt",
    "wof:placetype":"venue"
},
  "geometry": {"coordinates":[8.120841,50.030869],"type":"Point"}
}