{
  "type": "Feature",
  "properties": {
    "iso:country":"DE",
    "sg:address":"Engelbertstr. 47",
    "sg:city":"K\u00f6ln",
    "sg:phone":"+49 4922/1230305",
    "sg:postcode":"50674",
    "sg:province":"Nordrhein-Westfalen",
    "wof:name":"L. Wenzel",
    "wof:placetype":"venue"
},
  "geometry": {"coordinates":[6.938025,50.93396],"type":"Point"}
}