{
  "type": "Feature",
  "properties": {
    "iso:country":"DE",
    "sg:address":"Sandweg 11",
    "sg:city":"Flieden",
    "sg:phone":"+49 6655/2420",
    "sg:postcode":"36103",
    "sg:province":"Hessen",
    "wof:name":"Fridolin Sauer Ohg",
    "wof:placetype":"venue"
},
  "geometry": {"coordinates":[9.5782489777,50.4109230042],"type":"Point"}
}