{
  "type": "Feature",
  "properties": {
    "iso:country":"DE",
    "sg:address":"Am Strom 64",
    "sg:city":"Rostock",
    "sg:postcode":"18119",
    "sg:province":"Mecklenburg-Vorpommern",
    "wof:name":"Hbl Gmbh",
    "wof:placetype":"venue"
},
  "geometry": {"coordinates":[12.087857,54.177429],"type":"Point"}
}