{
  "type": "Feature",
  "properties": {
    "iso:country":"DE",
    "sg:address":"Hermann-K\u00f6hl-Str. 3 a",
    "sg:city":"Regensburg",
    "sg:phone":"+49 941/58420",
    "sg:postcode":"93049",
    "sg:province":"Bayern",
    "wof:name":"Verwaltungs Gmbh Der Carlson Kg",
    "wof:placetype":"venue"
},
  "geometry": {"coordinates":[12.0607128143,49.020111084],"type":"Point"}
}