{
  "type": "Feature",
  "properties": {
    "iso:country":"DE",
    "sg:address":"M\u00f6tzower Landstr. 33",
    "sg:city":"Brandenburg",
    "sg:postcode":"14776",
    "sg:province":"Brandenburg",
    "wof:name":"B. B. - Brandenburger Brunnenbau Gmbh",
    "wof:placetype":"venue"
},
  "geometry": {"coordinates":[12.57586,52.424221],"type":"Point"}
}