{
  "type": "Feature",
  "properties": {
    "iso:country":"DE",
    "sg:address":"Sebastistr. 10",
    "sg:city":"Kipfenberg",
    "sg:phone":"+49 8465/279",
    "sg:postcode":"85110",
    "sg:province":"Bayern",
    "wof:name":"Gastst\u00e4tte Konrad Sedlmeier",
    "wof:placetype":"venue"
},
  "geometry": {"coordinates":[11.4326229095,48.9644050598],"type":"Point"}
}