{
  "type": "Feature",
  "properties": {
    "iso:country":"DE",
    "sg:address":"Donauw\u00f6rther Str. 25",
    "sg:city":"H\u00f6chst\u00e4dt",
    "sg:phone":"+49 9074/4041",
    "sg:postcode":"89420",
    "sg:province":"Bayern",
    "wof:name":"Anton Schindele Steinmetz",
    "wof:placetype":"venue"
},
  "geometry": {"coordinates":[10.5673770905,48.6182327271],"type":"Point"}
}