{
  "type": "Feature",
  "properties": {
    "iso:country":"DE",
    "sg:address":"Weinstr. 48",
    "sg:city":"Wachenheim",
    "sg:postcode":"67157",
    "sg:province":"Rheinland-Pfalz",
    "wof:name":"Appelrath Marketing Consulting Gmbh",
    "wof:placetype":"venue"
},
  "geometry": {"coordinates":[8.1811723709,49.4392814636],"type":"Point"}
}