{
  "type": "Feature",
  "properties": {
    "iso:country":"DE",
    "sg:address":"Alleenstr. 83",
    "sg:city":"Kirchheim",
    "sg:phone":"+49 7021/735753",
    "sg:postcode":"73230",
    "sg:province":"Baden-W\u00fcrttemberg",
    "wof:name":"Thuringia Versicherung",
    "wof:placetype":"venue"
},
  "geometry": {"coordinates":[9.4536657333,48.6466903687],"type":"Point"}
}