{
  "type": "Feature",
  "properties": {
    "iso:country":"DE",
    "sg:address":"Bernauer Str. 92",
    "sg:city":"Oranienburg",
    "sg:postcode":"16515",
    "sg:province":"Brandenburg",
    "wof:name":"Mgn Maler Gmbh",
    "wof:placetype":"venue"
},
  "geometry": {"coordinates":[13.2515,52.757912],"type":"Point"}
}