{
  "type": "Feature",
  "properties": {
    "iso:country":"DE",
    "sg:address":"Am Fl\u00fcgelbahnhof 4",
    "sg:city":"Kronach",
    "sg:phone":"+49 9261/627824",
    "sg:postcode":"96317",
    "sg:province":"Bayern",
    "wof:name":"Diepreisfrage.de - Erste Regionale Preisagentur",
    "wof:placetype":"venue"
},
  "geometry": {"coordinates":[11.322917,50.234024],"type":"Point"}
}