{
  "type": "Feature",
  "properties": {
    "iso:country":"DE",
    "sg:address":"Stra\u00dfe R 19",
    "sg:city":"Berlin",
    "sg:phone":"+49 30/3342632",
    "sg:postcode":"13629",
    "sg:province":"Berlin",
    "wof:name":"Karin Kamischke Steuerberaterin",
    "wof:placetype":"venue"
},
  "geometry": {"coordinates":[13.244395256,52.5558738708],"type":"Point"}
}