{
  "type": "Feature",
  "properties": {
    "iso:country":"DE",
    "sg:address":"Schulweg 26",
    "sg:city":"Hamburg",
    "sg:phone":"+49 40/400090",
    "sg:postcode":"20259",
    "sg:province":"Hamburg",
    "wof:name":"Achim Deimling-ostrinsky",
    "wof:placetype":"venue"
},
  "geometry": {"coordinates":[9.9590387344,53.5736961365],"type":"Point"}
}