{
  "type": "Feature",
  "properties": {
    "iso:country":"DE",
    "sg:address":"Buckower Damm 221",
    "sg:city":"Berlin",
    "sg:phone":"+49 30/6044800",
    "sg:postcode":"12349",
    "sg:province":"Berlin",
    "wof:name":"Quickis Fleisch-und Wurstwaren Handels Gmbh",
    "wof:placetype":"venue"
},
  "geometry": {"coordinates":[13.4364652634,52.423992157],"type":"Point"}
}