{
  "type": "Feature",
  "properties": {
    "iso:country":"DE",
    "sg:address":"Meininger Str. 2",
    "sg:city":"Meiningen",
    "sg:phone":"+49 3693/974114",
    "sg:postcode":"98617",
    "sg:province":"Th\u00fcringen",
    "wof:name":"Elena Dietz",
    "wof:placetype":"venue"
},
  "geometry": {"coordinates":[10.38838,50.55946],"type":"Point"}
}