{
  "type": "Feature",
  "properties": {
    "iso:country":"DE",
    "sg:address":"Tannenstr. 2",
    "sg:city":"Langenargen",
    "sg:phone":"+49 7543/2697",
    "sg:postcode":"88085",
    "sg:province":"Baden-W\u00fcrttemberg",
    "wof:name":"Anton Zodel",
    "wof:placetype":"venue"
},
  "geometry": {"coordinates":[9.5422420502,47.6123657227],"type":"Point"}
}