{
  "type": "Feature",
  "properties": {
    "iso:country":"DE",
    "sg:address":"Bahnhofstr. 47",
    "sg:city":"Kempten",
    "sg:phone":"+49 831/26329",
    "sg:postcode":"87435",
    "sg:province":"Bayern",
    "wof:name":"Cafe College",
    "wof:placetype":"venue"
},
  "geometry": {"coordinates":[10.314339,47.718929],"type":"Point"}
}