{
  "type": "Feature",
  "properties": {
    "iso:country":"DE",
    "sg:address":"Hauptstr. 79",
    "sg:city":"M\u00f6nchengladbach",
    "sg:phone":"+49 2166/43321",
    "sg:postcode":"41236",
    "sg:province":"Nordrhein-Westfalen",
    "wof:name":"Henry's Sportswear",
    "wof:placetype":"venue"
},
  "geometry": {"coordinates":[6.445429,51.168552],"type":"Point"}
}