{
  "type": "Feature",
  "properties": {
    "iso:country":"DE",
    "sg:address":"Ferdinand-Zwack-Str. 3",
    "sg:city":"Freising",
    "sg:phone":"+49 8161/3457",
    "sg:postcode":"85354",
    "sg:province":"Bayern",
    "wof:name":"Interessengemeinschaft Goldberg E. V.",
    "wof:placetype":"venue"
},
  "geometry": {"coordinates":[11.7347326279,48.3996887207],"type":"Point"}
}