{
  "type": "Feature",
  "properties": {
    "iso:country":"DE",
    "sg:address":"Trillbach 17-19",
    "sg:city":"Koblenz",
    "sg:phone":"+49 261/81544",
    "sg:postcode":"56070",
    "sg:province":"Rheinland-Pfalz",
    "wof:name":"G. Rickhey",
    "wof:placetype":"venue"
},
  "geometry": {"coordinates":[7.583238,50.394722],"type":"Point"}
}