{
  "type": "Feature",
  "properties": {
    "iso:country":"DE",
    "sg:address":"Am Petroleumhafen 2",
    "sg:city":"L\u00fcbeck",
    "sg:phone":"+49 451/879400",
    "sg:postcode":"23554",
    "sg:province":"Schleswig-Holstein",
    "wof:name":"Ex Franchise System Gmbh",
    "wof:placetype":"venue"
},
  "geometry": {"coordinates":[10.6908798218,53.9034385681],"type":"Point"}
}