{
  "type": "Feature",
  "properties": {
    "iso:country":"DE",
    "sg:address":"Marktstr. 8",
    "sg:city":"J\u00fclich",
    "sg:phone":"+49 2461/55018",
    "sg:postcode":"52428",
    "sg:province":"Nordrhein-Westfalen",
    "wof:name":"Ph. Meessen Ohg",
    "wof:placetype":"venue"
},
  "geometry": {"coordinates":[6.3578748703,50.9211845398],"type":"Point"}
}