{
  "type": "Feature",
  "properties": {
    "iso:country":"DE",
    "sg:address":"Reuterallee 21",
    "sg:city":"Darmstadt",
    "sg:phone":"+49 6151/943323",
    "sg:postcode":"64297",
    "sg:province":"Hessen",
    "wof:name":"Praxis Dr. Med. B\u00f6hmer Und Dr. Med. Schreiber",
    "wof:placetype":"venue"
},
  "geometry": {"coordinates":[8.6378984451,49.8190422058],"type":"Point"}
}