{
  "type": "Feature",
  "properties": {
    "iso:country":"DE",
    "sg:address":"Tornower Str. 14",
    "sg:city":"Blumenow",
    "sg:postcode":"16775",
    "sg:province":"Brandenburg",
    "wof:name":"E. Und K. Otto",
    "wof:placetype":"venue"
},
  "geometry": {"coordinates":[13.2512893677,53.0999565125],"type":"Point"}
}