{
  "type": "Feature",
  "properties": {
    "iso:country":"DE",
    "sg:address":"Schiede 31",
    "sg:city":"Limburg",
    "sg:phone":"+49 6431/281100",
    "sg:postcode":"65549",
    "sg:province":"Hessen",
    "wof:name":"J\u00fcrgen Arnold Rechtsanwalt",
    "wof:placetype":"venue"
},
  "geometry": {"coordinates":[8.0593967438,50.3880691528],"type":"Point"}
}