{
  "type": "Feature",
  "properties": {
    "iso:country":"DE",
    "sg:address":"Comeniusstr. 2",
    "sg:city":"Herrnhut",
    "sg:phone":"+49 35873/2253",
    "sg:postcode":"02747",
    "sg:province":"Sachsen",
    "wof:name":"Comenius-buchhandlung Gmbh",
    "wof:placetype":"venue"
},
  "geometry": {"coordinates":[14.746155,51.016453],"type":"Point"}
}