{
  "type": "Feature",
  "properties": {
    "iso:country":"DE",
    "sg:address":"Markt 6",
    "sg:city":"Querfurt",
    "sg:postcode":"06268",
    "sg:province":"Sachsen-Anhalt",
    "wof:name":"Ckc Edv Und Tele- Kommunikationsges. Mbh",
    "wof:placetype":"venue"
},
  "geometry": {"coordinates":[11.597533226,51.3783378601],"type":"Point"}
}