{
  "type": "Feature",
  "properties": {
    "iso:country":"DE",
    "sg:address":"Breite Str. 4",
    "sg:city":"Wernigerode",
    "sg:phone":"+49 3943/632409",
    "sg:postcode":"38855",
    "sg:province":"Sachsen-Anhalt",
    "wof:name":"Cafe Wien",
    "wof:placetype":"venue"
},
  "geometry": {"coordinates":[10.785137,51.833496],"type":"Point"}
}