{
  "type": "Feature",
  "properties": {
    "iso:country":"DE",
    "sg:address":"Dillstr. 19",
    "sg:city":"Hamburg",
    "sg:phone":"+49 40/45037913",
    "sg:postcode":"20146",
    "sg:province":"Hamburg",
    "wof:name":"Beteiligungs A.m.f. Aircraftleasing",
    "wof:placetype":"venue"
},
  "geometry": {"coordinates":[9.982453,53.570122],"type":"Point"}
}