{
  "type": "Feature",
  "properties": {
    "iso:country":"DE",
    "sg:address":"Fregestr. 4",
    "sg:city":"Leipzig",
    "sg:phone":"+49 341/9800065",
    "sg:postcode":"04105",
    "sg:province":"Sachsen",
    "wof:name":"J. Junge",
    "wof:placetype":"venue"
},
  "geometry": {"coordinates":[12.355594,51.344536],"type":"Point"}
}