{
  "type": "Feature",
  "properties": {
    "iso:country":"DE",
    "sg:address":"Hangstr. 25",
    "sg:city":"Kiel",
    "sg:phone":"+49 431/723088",
    "sg:postcode":"24148",
    "sg:province":"Schleswig-Holstein",
    "wof:name":"Otto Becker Gmbh & Co. Kg",
    "wof:placetype":"venue"
},
  "geometry": {"coordinates":[10.1724443436,54.3170776367],"type":"Point"}
}