{
  "type": "Feature",
  "properties": {
    "iso:country":"DE",
    "sg:address":"Saturnstr 63",
    "sg:city":"Aschheim",
    "sg:phone":"+49 89/9915510",
    "sg:postcode":"85609",
    "sg:province":"Bayern",
    "wof:name":"Steico Ag",
    "wof:placetype":"venue"
},
  "geometry": {"coordinates":[11.719111,48.175331],"type":"Point"}
}