{
  "type": "Feature",
  "properties": {
    "iso:country":"DE",
    "sg:address":"Saalfelder Str. 17",
    "sg:city":"Unterwirbach",
    "sg:phone":"+49 36741/2913",
    "sg:postcode":"07422",
    "sg:province":"Th\u00fcringen",
    "wof:name":"Trabagg Transport Abri\u00df Baggerbetrieb Gmbh",
    "wof:placetype":"venue"
},
  "geometry": {"coordinates":[11.297065,50.667744],"type":"Point"}
}