{
  "type": "Feature",
  "properties": {
    "iso:country":"DE",
    "sg:address":"Krefelder Str. 8",
    "sg:city":"T\u00f6nisvorst",
    "sg:phone":"+49 2151/797888",
    "sg:postcode":"47918",
    "sg:province":"Nordrhein-Westfalen",
    "wof:name":"Reiseb\u00fcro Striewisch",
    "wof:placetype":"venue"
},
  "geometry": {"coordinates":[6.4795098305,51.3457756042],"type":"Point"}
}