{
  "type": "Feature",
  "properties": {
    "iso:country":"DE",
    "sg:address":"Schubertstr. 3",
    "sg:city":"Ahlen",
    "sg:phone":"+49 2382/3883",
    "sg:postcode":"59227",
    "sg:province":"Nordrhein-Westfalen",
    "wof:name":"Willi Weigel",
    "wof:placetype":"venue"
},
  "geometry": {"coordinates":[7.8771190643,51.7634544373],"type":"Point"}
}