{
  "type": "Feature",
  "properties": {
    "iso:country":"DE",
    "sg:address":"Horner Weg 68",
    "sg:city":"Hamburg",
    "sg:phone":"+49 40/21981827",
    "sg:postcode":"20535",
    "sg:province":"Hamburg",
    "wof:name":"Jamada Gmbh Thomitzek Horla Gowin",
    "wof:placetype":"venue"
},
  "geometry": {"coordinates":[10.0633869171,53.5557136536],"type":"Point"}
}