{
  "type": "Feature",
  "properties": {
    "iso:country":"DE",
    "sg:address":"Dorfstr. 7",
    "sg:city":"Eppishausen",
    "sg:phone":"+49 8266/352",
    "sg:postcode":"87745",
    "sg:province":"Bayern",
    "wof:name":"U. Kleiber",
    "wof:placetype":"venue"
},
  "geometry": {"coordinates":[10.5078964233,48.2030525208],"type":"Point"}
}