{
  "type": "Feature",
  "properties": {
    "iso:country":"DE",
    "sg:address":"Mindener Str. 21",
    "sg:city":"Bad Oeynhausen",
    "sg:postcode":"32545",
    "sg:province":"Nordrhein-Westfalen",
    "wof:name":"Global Immobilien Gmbh",
    "wof:placetype":"venue"
},
  "geometry": {"coordinates":[8.8036336899,52.2077140808],"type":"Point"}
}