{
  "type": "Feature",
  "properties": {
    "iso:country":"DE",
    "sg:address":"Hauptstr. 7",
    "sg:city":"Brechen",
    "sg:phone":"+49 6438/2758",
    "sg:postcode":"65611",
    "sg:province":"Hessen",
    "wof:name":"Robert H\u00f6hler",
    "wof:placetype":"venue"
},
  "geometry": {"coordinates":[8.162385,50.348049],"type":"Point"}
}