{
  "type": "Feature",
  "properties": {
    "iso:country":"DE",
    "sg:address":"Forststr. 1",
    "sg:city":"Eckersdorf",
    "sg:phone":"+49 921/39620",
    "sg:postcode":"95488",
    "sg:province":"Bayern",
    "wof:name":"M. H\u00fcbner",
    "wof:placetype":"venue"
},
  "geometry": {"coordinates":[11.508347,49.93449],"type":"Point"}
}