{
  "type": "Feature",
  "properties": {
    "iso:country":"DE",
    "sg:address":"Hirtenstr. 2 b",
    "sg:city":"Oberhausen",
    "sg:phone":"+49 208/6352804",
    "sg:postcode":"46145",
    "sg:province":"Nordrhein-Westfalen",
    "wof:name":"Amine Gmbh",
    "wof:placetype":"venue"
},
  "geometry": {"coordinates":[6.8598017693,51.5178833008],"type":"Point"}
}