{
  "type": "Feature",
  "properties": {
    "iso:country":"DE",
    "sg:address":"Schmollerstr. 19",
    "sg:city":"Schw\u00e4bisch Hall",
    "sg:phone":"+49 791/939971",
    "sg:postcode":"74523",
    "sg:province":"Baden-W\u00fcrttemberg",
    "wof:name":"H. Und K. Starke",
    "wof:placetype":"venue"
},
  "geometry": {"coordinates":[9.7860746384,49.1102561951],"type":"Point"}
}