{
  "type": "Feature",
  "properties": {
    "iso:country":"DE",
    "sg:address":"G\u00fcrtelstr. 5",
    "sg:city":"Unna",
    "sg:phone":"+49 2303/14691",
    "sg:postcode":"59423",
    "sg:province":"Nordrhein-Westfalen",
    "wof:name":"Uwe Weitkamp Rechtsanwalt",
    "wof:placetype":"venue"
},
  "geometry": {"coordinates":[7.6868739128,51.5339546204],"type":"Point"}
}