{
  "type": "Feature",
  "properties": {
    "iso:country":"DE",
    "sg:address":"Nelkenstr. 2a",
    "sg:city":"Edewecht",
    "sg:phone":"+49 4405/49034",
    "sg:postcode":"26188",
    "sg:province":"Niedersachsen",
    "wof:name":"Frank Gerdes",
    "wof:placetype":"venue"
},
  "geometry": {"coordinates":[7.9772849083,53.1166381836],"type":"Point"}
}