{
  "type": "Feature",
  "properties": {
    "iso:country":"DE",
    "sg:address":"Grenzallee 44",
    "sg:city":"Berlin",
    "sg:phone":"+49 30/6127087",
    "sg:postcode":"12057",
    "sg:province":"Berlin",
    "wof:name":"Lehe Planen- Und Zeltverleih",
    "wof:placetype":"venue"
},
  "geometry": {"coordinates":[13.4542217255,52.4654083252],"type":"Point"}
}