{
  "type": "Feature",
  "properties": {
    "iso:country":"DE",
    "sg:address":"K\u00f6nigstr. 58",
    "sg:city":"Rottenburg",
    "sg:phone":"+49 7472/981717",
    "sg:postcode":"72108",
    "sg:province":"Baden-W\u00fcrttemberg",
    "wof:name":"Heiner Norz",
    "wof:placetype":"venue"
},
  "geometry": {"coordinates":[8.9315681458,48.4752197266],"type":"Point"}
}