{
  "type": "Feature",
  "properties": {
    "iso:country":"DE",
    "sg:address":"Geschwister-Scholl-Str. 2",
    "sg:city":"Gera",
    "sg:phone":"+49 365/22050",
    "sg:postcode":"07545",
    "sg:province":"Th\u00fcringen",
    "wof:name":"Paul Tischendorf",
    "wof:placetype":"venue"
},
  "geometry": {"coordinates":[12.0847969055,50.8717536926],"type":"Point"}
}