{
  "type": "Feature",
  "properties": {
    "iso:country":"DE",
    "sg:address":"Talstr. 8",
    "sg:city":"Aspach",
    "sg:phone":"+49 7191/22378",
    "sg:postcode":"71546",
    "sg:province":"Baden-W\u00fcrttemberg",
    "wof:name":"H. Jonas",
    "wof:placetype":"venue"
},
  "geometry": {"coordinates":[9.399471,48.971676],"type":"Point"}
}