{
  "type": "Feature",
  "properties": {
    "iso:country":"DE",
    "sg:address":"Kirchplatz 4",
    "sg:city":"Castell",
    "sg:phone":"+49 9325/461",
    "sg:postcode":"97355",
    "sg:province":"Bayern",
    "wof:name":"Gr\u00fcner Baum",
    "wof:placetype":"venue"
},
  "geometry": {"coordinates":[10.3518161774,49.7400512695],"type":"Point"}
}