{
  "type": "Feature",
  "properties": {
    "iso:country":"DE",
    "sg:address":"Am Rott 1 Grabow",
    "sg:city":"L\u00fcchow",
    "sg:phone":"+49 4958/6498790",
    "sg:postcode":"29439",
    "sg:province":"Niedersachsen",
    "wof:name":"Moebel Wolfrath Gmbh Einrichtungshaus",
    "wof:placetype":"venue"
},
  "geometry": {"coordinates":[11.1013698578,53.0119590759],"type":"Point"}
}