{
  "type": "Feature",
  "properties": {
    "iso:country":"DE",
    "sg:address":"Jurastr. 46",
    "sg:city":"Albstadt",
    "sg:phone":"+49 7432/97710",
    "sg:postcode":"72461",
    "sg:province":"Baden-W\u00fcrttemberg",
    "wof:name":"Tailfinger Druckerei Heinrich Weidle Kg",
    "wof:placetype":"venue"
},
  "geometry": {"coordinates":[9.0294055939,48.2354431152],"type":"Point"}
}