{
  "type": "Feature",
  "properties": {
    "iso:country":"DE",
    "sg:address":"Gro\u00dfe Ziegelstr. 35",
    "sg:city":"Pfullingen",
    "sg:phone":"+49 7121/790185",
    "sg:postcode":"72793",
    "sg:province":"Baden-W\u00fcrttemberg",
    "wof:name":"F. Schwarz Ingenieur",
    "wof:placetype":"venue"
},
  "geometry": {"coordinates":[9.2239122391,48.462802887],"type":"Point"}
}