{
  "type": "Feature",
  "properties": {
    "iso:country":"DE",
    "sg:address":"Rie\u00dfnerstr. 12",
    "sg:city":"Weimar",
    "sg:postcode":"99427",
    "sg:province":"Th\u00fcringen",
    "wof:name":"Block 6 Modeteam Gmbh",
    "wof:placetype":"venue"
},
  "geometry": {"coordinates":[11.3265542984,50.9936027527],"type":"Point"}
}