{
  "type": "Feature",
  "properties": {
    "iso:country":"DE",
    "sg:address":"Barthelsm\u00fchlrg. 16",
    "sg:city":"Kandel",
    "sg:phone":"+49 4972/7598830",
    "sg:postcode":"76870",
    "sg:province":"Rheinland-Pfalz",
    "wof:name":"Celsa Messger\u00c4te Gmbh",
    "wof:placetype":"venue"
},
  "geometry": {"coordinates":[8.177838,49.099735],"type":"Point"}
}