{
  "type": "Feature",
  "properties": {
    "iso:country":"DE",
    "sg:address":"Noorderloog 3",
    "sg:city":"Spiekeroog",
    "sg:phone":"+49 4976/1428",
    "sg:postcode":"26474",
    "sg:province":"Niedersachsen",
    "wof:name":"S. Trabitsch-willms",
    "wof:placetype":"venue"
},
  "geometry": {"coordinates":[7.694589138,53.7706642151],"type":"Point"}
}