{
  "type": "Feature",
  "properties": {
    "iso:country":"DE",
    "sg:address":"Sachsenstr. 8",
    "sg:city":"Hamburg",
    "sg:phone":"+49 40/237170",
    "sg:postcode":"20097",
    "sg:province":"Hamburg",
    "wof:name":"J\u00fcrgen Rickertsen Gmbh",
    "wof:placetype":"venue"
},
  "geometry": {"coordinates":[10.0259475708,53.5458641052],"type":"Point"}
}