{
  "type": "Feature",
  "properties": {
    "iso:country":"DE",
    "sg:address":"Im Weidenbruch 14",
    "sg:city":"K\u00f6ln",
    "sg:phone":"+49 221/641041",
    "sg:postcode":"51061",
    "sg:province":"Nordrhein-Westfalen",
    "wof:name":"Jean Kloeppel Gmbh & Co. Kg",
    "wof:placetype":"venue"
},
  "geometry": {"coordinates":[7.024406,50.979843],"type":"Point"}
}