{
  "type": "Feature",
  "properties": {
    "iso:country":"DE",
    "sg:address":"Hagelberger Str. 45",
    "sg:city":"Berlin",
    "sg:postcode":"10965",
    "sg:province":"Berlin",
    "wof:name":"Maritim Yachting Vermietungs- Und Ver-",
    "wof:placetype":"venue"
},
  "geometry": {"coordinates":[13.3838596344,52.4913673401],"type":"Point"}
}