{
  "type": "Feature",
  "properties": {
    "iso:country":"DE",
    "sg:address":"Nebenstr. 21",
    "sg:city":"Thurm",
    "sg:phone":"+49 37601/25212",
    "sg:postcode":"08138",
    "wof:name":"Motor Flurf\u00f6rdertechnik Gmbh",
    "wof:placetype":"venue"
},
  "geometry": {"coordinates":[12.5533847809,50.765007019],"type":"Point"}
}