{
  "type": "Feature",
  "properties": {
    "iso:country":"DE",
    "sg:address":"Wermbachstr. 50",
    "sg:city":"Aschaffenburg",
    "sg:phone":"+49 6021/30150",
    "sg:postcode":"63739",
    "sg:province":"Bayern",
    "wof:name":"Wohnconcept Planungs- Und Vertriebs Gmbh",
    "wof:placetype":"venue"
},
  "geometry": {"coordinates":[9.1489896774,49.9730300903],"type":"Point"}
}