{
  "type": "Feature",
  "properties": {
    "iso:country":"DE",
    "sg:address":"Zehlendorfer Str. 13",
    "sg:city":"Hagen",
    "sg:phone":"+49 2331/28767",
    "sg:postcode":"58097",
    "sg:province":"Nordrhein-Westfalen",
    "wof:name":"Ing. Axel Feldscher",
    "wof:placetype":"venue"
},
  "geometry": {"coordinates":[7.474937,51.363323],"type":"Point"}
}