{
  "type": "Feature",
  "properties": {
    "iso:country":"DE",
    "sg:address":"Eremitagestr. 32",
    "sg:city":"Bayreuth",
    "sg:phone":"+49 921/9800959",
    "sg:postcode":"95448",
    "sg:province":"Bayern",
    "wof:name":"Gerhard Thurn",
    "wof:placetype":"venue"
},
  "geometry": {"coordinates":[11.6167869568,49.9471626282],"type":"Point"}
}