{
  "type": "Feature",
  "properties": {
    "iso:country":"DE",
    "sg:address":"Wildbachstr. 9",
    "sg:city":"Aachen",
    "sg:phone":"+49 241/176572",
    "sg:postcode":"52074",
    "sg:province":"Nordrhein-Westfalen",
    "wof:name":"Logiconcept Verwaltungs Gmbh",
    "wof:placetype":"venue"
},
  "geometry": {"coordinates":[6.061603,50.795277],"type":"Point"}
}