{
  "type": "Feature",
  "properties": {
    "iso:country":"DE",
    "sg:address":"Ob der Wanne 28",
    "sg:city":"Brigachtal",
    "sg:postcode":"78086",
    "sg:province":"Baden-W\u00fcrttemberg",
    "wof:name":"S. Trewer",
    "wof:placetype":"venue"
},
  "geometry": {"coordinates":[8.4718885422,48.0080528259],"type":"Point"}
}