{
  "type": "Feature",
  "properties": {
    "iso:country":"DE",
    "sg:address":"Elfenweg 12",
    "sg:city":"Karlsruhe",
    "sg:phone":"+49 721/882088",
    "sg:postcode":"76199",
    "sg:province":"Baden-W\u00fcrttemberg",
    "wof:name":"K. H. Frob\u00f6se",
    "wof:placetype":"venue"
},
  "geometry": {"coordinates":[8.419960022,48.969997406],"type":"Point"}
}