{
  "type": "Feature",
  "properties": {
    "iso:country":"DE",
    "sg:address":"Max-Eyth-Str. 51",
    "sg:city":"Sch\u00f6naich",
    "sg:phone":"+49 7031/655631",
    "sg:postcode":"71101",
    "sg:province":"Baden-W\u00fcrttemberg",
    "wof:name":"Theo Schimpf",
    "wof:placetype":"venue"
},
  "geometry": {"coordinates":[9.0559053421,48.6612091064],"type":"Point"}
}