{
  "type": "Feature",
  "properties": {
    "iso:country":"DE",
    "sg:address":"Beethovenstr. 60",
    "sg:city":"Solingen",
    "sg:phone":"+49 212/18822",
    "sg:postcode":"42655",
    "sg:province":"Nordrhein-Westfalen",
    "wof:name":"Peter Schnittmann",
    "wof:placetype":"venue"
},
  "geometry": {"coordinates":[7.0679512024,51.1773071289],"type":"Point"}
}