{
  "type": "Feature",
  "properties": {
    "iso:country":"DE",
    "sg:address":"Hagedornstr. 22",
    "sg:city":"Hamburg",
    "sg:phone":"+49 40/38610601",
    "sg:postcode":"20149",
    "sg:province":"Hamburg",
    "wof:name":"Oldenburg Gmbh",
    "wof:placetype":"venue"
},
  "geometry": {"coordinates":[9.9907817841,53.5790290833],"type":"Point"}
}