{
  "type": "Feature",
  "properties": {
    "iso:country":"DE",
    "sg:address":"Karl-von-Hahn-Str. 30",
    "sg:city":"Freudenstadt",
    "sg:phone":"+49 7441/91650",
    "sg:postcode":"72250",
    "sg:province":"Baden-W\u00fcrttemberg",
    "wof:name":"Baugemeinschaft Herrenhof Gmbh & Co. Kg",
    "wof:placetype":"venue"
},
  "geometry": {"coordinates":[8.408318,48.470627],"type":"Point"}
}