{
  "type": "Feature",
  "properties": {
    "iso:country":"DE",
    "sg:address":"Brautstr. 7",
    "sg:city":"M\u00fccke",
    "sg:phone":"+49 6400/90101",
    "sg:postcode":"35325",
    "sg:province":"Hessen",
    "wof:name":"A. Lambrecht Architekt",
    "wof:placetype":"venue"
},
  "geometry": {"coordinates":[9.114679,50.619175],"type":"Point"}
}