{
  "type": "Feature",
  "properties": {
    "iso:country":"DE",
    "sg:address":"Wittgensteiner Str. 147",
    "sg:city":"Hilchenbach",
    "sg:phone":"+49 2733/51168",
    "sg:postcode":"57271",
    "sg:province":"Nordrhein-Westfalen",
    "wof:name":"Langenbach Transporte- Baustoffe Gmbh",
    "wof:placetype":"venue"
},
  "geometry": {"coordinates":[8.0633831024,50.9757919312],"type":"Point"}
}