{
  "type": "Feature",
  "properties": {
    "iso:country":"DE",
    "sg:address":"Calwer Str. 4",
    "sg:city":"Tamm",
    "sg:phone":"+49 7141/603580",
    "sg:postcode":"71732",
    "sg:province":"Baden-W\u00fcrttemberg",
    "wof:name":"Hans-peter Pfeiffer",
    "wof:placetype":"venue"
},
  "geometry": {"coordinates":[9.1349992752,48.9275665283],"type":"Point"}
}