{
  "type": "Feature",
  "properties": {
    "iso:country":"DE",
    "sg:address":"Silostr. 25",
    "sg:city":"Krefeld",
    "sg:postcode":"47809",
    "sg:province":"Nordrhein-Westfalen",
    "wof:name":"Schou-verwaltungs Gmbh",
    "wof:placetype":"venue"
},
  "geometry": {"coordinates":[6.66068,51.342552],"type":"Point"}
}