{
  "type": "Feature",
  "properties": {
    "iso:country":"DE",
    "sg:address":"Kloppenheimer Str. 20",
    "sg:city":"Wiesbaden",
    "sg:phone":"+49 611/9505800",
    "sg:postcode":"65191",
    "sg:province":"Hessen",
    "wof:name":"Rsg Casino",
    "wof:placetype":"venue"
},
  "geometry": {"coordinates":[8.2898349762,50.0840759277],"type":"Point"}
}