{
  "type": "Feature",
  "properties": {
    "iso:country":"DE",
    "sg:address":"Georg-Fr\u00f6ba-Str. 3",
    "sg:city":"Alsbach-H\u00e4hnlein",
    "sg:phone":"+49 6257/68310",
    "sg:postcode":"64665",
    "sg:province":"Hessen",
    "wof:name":"Antike M\u00f6bel Und Aufbereitung Robert Lei\u00df",
    "wof:placetype":"venue"
},
  "geometry": {"coordinates":[8.5771284103,49.7372703552],"type":"Point"}
}