{
  "type": "Feature",
  "properties": {
    "iso:country":"DE",
    "sg:address":"Hauptstr. 303",
    "sg:city":"V\u00f6lklingen",
    "sg:phone":"+49 6802/1022",
    "sg:postcode":"66333",
    "sg:province":"Saarland",
    "wof:name":"J\u00fcrgen Sch\u00e4fer",
    "wof:placetype":"venue"
},
  "geometry": {"coordinates":[6.7308578491,49.1753883362],"type":"Point"}
}