{
  "type": "Feature",
  "properties": {
    "iso:country":"DE",
    "sg:address":"Feuerhausstr. 19",
    "sg:city":"F\u00fcrstenfeldbruck",
    "sg:phone":"+49 8141/512086",
    "sg:postcode":"82256",
    "sg:province":"Bayern",
    "wof:name":"Anton Hoch Architekt",
    "wof:placetype":"venue"
},
  "geometry": {"coordinates":[11.255933,48.183395],"type":"Point"}
}