{
  "type": "Feature",
  "properties": {
    "iso:country":"DE",
    "sg:address":"Bl\u00fccherstr. 98b",
    "sg:city":"Augsburg",
    "sg:phone":"+49 821/721404",
    "sg:postcode":"86165",
    "sg:province":"Bayern",
    "wof:name":"Arno Hannig Heilpraktiker",
    "wof:placetype":"venue"
},
  "geometry": {"coordinates":[10.9276075363,48.3751869202],"type":"Point"}
}