{
  "type": "Feature",
  "properties": {
    "iso:country":"DE",
    "sg:address":"99610",
    "sg:city":"S\u00f6mmerda",
    "sg:postcode":"99610",
    "sg:province":"Th\u00fcringen",
    "wof:name":"Volksbank S\u00f6mmerda-sondershausen Eg",
    "wof:placetype":"venue"
},
  "geometry": {"coordinates":[11.19563,51.158501],"type":"Point"}
}