{
  "type": "Feature",
  "properties": {
    "iso:country":"DE",
    "sg:address":"Ehrenstr. 1-3",
    "sg:city":"K\u00f6ln",
    "sg:phone":"+49 221/2583124",
    "sg:postcode":"50672",
    "sg:province":"Nordrhein-Westfalen",
    "wof:name":"Parf\u00fcmerie Douglas West Gmbh & Co. Kg",
    "wof:placetype":"venue"
},
  "geometry": {"coordinates":[6.944808,50.938416],"type":"Point"}
}