{
  "type": "Feature",
  "properties": {
    "iso:country":"DE",
    "sg:address":"Br\u00fcckenstr. 9",
    "sg:city":"Grimma",
    "sg:phone":"+49 3437/92260",
    "sg:postcode":"04668",
    "sg:province":"Sachsen",
    "wof:name":"Heinz Manfred Schulze Rechtsanwalt",
    "wof:placetype":"venue"
},
  "geometry": {"coordinates":[12.7304592133,51.2373161316],"type":"Point"}
}