{
  "type": "Feature",
  "properties": {
    "iso:country":"DE",
    "sg:address":"Zeilharder Str. 15",
    "sg:city":"Messel",
    "sg:phone":"+49 6159/5775",
    "sg:postcode":"64409",
    "sg:province":"Hessen",
    "wof:name":"Stan Messebau Gmbh",
    "wof:placetype":"venue"
},
  "geometry": {"coordinates":[8.7453346252,49.9241294861],"type":"Point"}
}