{
  "type": "Feature",
  "properties": {
    "iso:country":"DE",
    "sg:address":"Lindwurmstr. 203",
    "sg:city":"M\u00fcnchen",
    "sg:phone":"+49 89/777719",
    "sg:postcode":"80337",
    "sg:province":"Bayern",
    "wof:name":"Rabe Fahrradhandel Gmbh",
    "wof:placetype":"venue"
},
  "geometry": {"coordinates":[11.544391,48.122147],"type":"Point"}
}