{
  "type": "Feature",
  "properties": {
    "iso:country":"DE",
    "sg:address":"Altdorfer Str. 49",
    "sg:city":"Lauf",
    "sg:phone":"+49 9123/2439",
    "sg:postcode":"91207",
    "sg:province":"Bayern",
    "wof:name":"Perls",
    "wof:placetype":"venue"
},
  "geometry": {"coordinates":[11.284084,49.50597],"type":"Point"}
}