{
  "type": "Feature",
  "properties": {
    "iso:country":"DE",
    "sg:address":"Langensoll 34",
    "sg:city":"Laboe",
    "sg:postcode":"24235",
    "sg:province":"Schleswig-Holstein",
    "wof:name":"Siems Verm\u00f6gensverwaltung Gmbh",
    "wof:placetype":"venue"
},
  "geometry": {"coordinates":[10.2321147919,54.3969764709],"type":"Point"}
}