{
  "type": "Feature",
  "properties": {
    "iso:country":"DE",
    "sg:address":"Fellbacher Str. 95",
    "sg:city":"Fellbach",
    "sg:phone":"+49 711/588911",
    "sg:postcode":"70736",
    "sg:province":"Baden-W\u00fcrttemberg",
    "wof:name":"R. W\u00f6lfle",
    "wof:placetype":"venue"
},
  "geometry": {"coordinates":[9.2676334381,48.8272476196],"type":"Point"}
}