{
  "type": "Feature",
  "properties": {
    "iso:country":"DE",
    "sg:address":"Aisinger Str. 98",
    "sg:city":"Rosenheim",
    "sg:postcode":"83026",
    "sg:province":"Bayern",
    "wof:name":"Steingraber Verwaltung Gmbh",
    "wof:placetype":"venue"
},
  "geometry": {"coordinates":[12.1127414703,47.8341407776],"type":"Point"}
}