{
  "type": "Feature",
  "properties": {
    "iso:country":"DE",
    "sg:address":"Dorfstr. 23",
    "sg:city":"Reinst\u00e4dt",
    "sg:phone":"+49 36422/6990",
    "sg:postcode":"07768",
    "sg:province":"Th\u00fcringen",
    "wof:name":"Taxis Th\u00fcringen Veranstaltungen",
    "wof:placetype":"venue"
},
  "geometry": {"coordinates":[11.474713,50.808617],"type":"Point"}
}