{
  "type": "Feature",
  "properties": {
    "iso:country":"DE",
    "sg:address":"Im Uelenbend 5",
    "sg:city":"Roetgen",
    "sg:phone":"+49 2471/4750",
    "sg:postcode":"52159",
    "sg:province":"Nordrhein-Westfalen",
    "wof:name":"Maria Und Hans Maraite",
    "wof:placetype":"venue"
},
  "geometry": {"coordinates":[6.203445,50.680244],"type":"Point"}
}