{
  "type": "Feature",
  "properties": {
    "iso:country":"DE",
    "sg:address":"Sonnenbrede 14",
    "sg:city":"Warburg",
    "sg:postcode":"34414",
    "sg:province":"Nordrhein-Westfalen",
    "wof:name":"Astorga Fritz Lange Gmbh",
    "wof:placetype":"venue"
},
  "geometry": {"coordinates":[9.156793,51.491272],"type":"Point"}
}