{
  "type": "Feature",
  "properties": {
    "iso:country":"DE",
    "sg:address":"Wilhelmstr. 53",
    "sg:city":"Lampertheim",
    "sg:phone":"+49 6206/56341",
    "sg:postcode":"68623",
    "sg:province":"Hessen",
    "wof:name":"Players Palace",
    "wof:placetype":"venue"
},
  "geometry": {"coordinates":[8.4693565369,49.5947341919],"type":"Point"}
}