{
  "type": "Feature",
  "properties": {
    "iso:country":"DE",
    "sg:address":"Rote Reihe 6",
    "sg:city":"Hannover",
    "sg:phone":"+49 511/12410",
    "sg:postcode":"30169",
    "sg:province":"Niedersachsen",
    "wof:name":"Landeskirchenamt",
    "wof:placetype":"venue"
},
  "geometry": {"coordinates":[9.727973938,52.3716087341],"type":"Point"}
}