{
  "type": "Feature",
  "properties": {
    "iso:country":"DE",
    "sg:address":"Waldweg 31",
    "sg:city":"Hamburg",
    "sg:phone":"+49 40/6014914",
    "sg:postcode":"22393",
    "sg:province":"Hamburg",
    "wof:name":"Hatru Bau Gmbh",
    "wof:placetype":"venue"
},
  "geometry": {"coordinates":[10.117714,53.654884],"type":"Point"}
}