{
  "type": "Feature",
  "properties": {
    "iso:country":"DE",
    "sg:address":"Westerntorstr. 29",
    "sg:city":"Wolfenb\u00fcttel",
    "sg:postcode":"38304",
    "sg:province":"Niedersachsen",
    "wof:name":"Tanjas Eil- Und Kleintransporte Gmbh",
    "wof:placetype":"venue"
},
  "geometry": {"coordinates":[10.46012,52.144714],"type":"Point"}
}