{
  "type": "Feature",
  "properties": {
    "iso:country":"DE",
    "sg:address":"Bleichstr. 4",
    "sg:city":"Pforzheim",
    "sg:phone":"+49 7231/23663",
    "sg:postcode":"75173",
    "sg:province":"Baden-W\u00fcrttemberg",
    "wof:name":"St\u00e4hle & Co. Gmbh",
    "wof:placetype":"venue"
},
  "geometry": {"coordinates":[8.697468,48.888203],"type":"Point"}
}