{
  "type": "Feature",
  "properties": {
    "iso:country":"DE",
    "sg:address":"Emmishofer Str. 3",
    "sg:city":"Konstanz",
    "sg:phone":"+49 7531/189566",
    "sg:postcode":"78462",
    "sg:province":"Baden-W\u00fcrttemberg",
    "wof:name":"Mz Moderne Zahntechnik Gmbh",
    "wof:placetype":"venue"
},
  "geometry": {"coordinates":[9.170791,47.657143],"type":"Point"}
}