{
  "type": "Feature",
  "properties": {
    "iso:country":"DE",
    "sg:address":"Malsenstr. 51",
    "sg:city":"M\u00fcnchen",
    "sg:postcode":"80638",
    "sg:province":"Bayern",
    "wof:name":"Grand Vin De Bordeux E. K.",
    "wof:placetype":"venue"
},
  "geometry": {"coordinates":[11.5235261917,48.1601753235],"type":"Point"}
}