{
  "type": "Feature",
  "properties": {
    "iso:country":"DE",
    "sg:address":"Lotter Str. 30",
    "sg:city":"Osnabr\u00fcck",
    "sg:phone":"+49 541/409120",
    "sg:postcode":"49078",
    "sg:province":"Niedersachsen",
    "wof:name":"Hotel Klute",
    "wof:placetype":"venue"
},
  "geometry": {"coordinates":[8.0316476822,52.274597168],"type":"Point"}
}