{
  "type": "Feature",
  "properties": {
    "iso:country":"DE",
    "sg:address":"Hohlweg 3",
    "sg:city":"Weilbach",
    "sg:postcode":"63937",
    "sg:province":"Bayern",
    "wof:name":"Diepraxis Planungs- Und Einricht.gmbh",
    "wof:placetype":"venue"
},
  "geometry": {"coordinates":[9.218549,49.66703],"type":"Point"}
}