{
  "type": "Feature",
  "properties": {
    "iso:country":"DE",
    "sg:address":"Welluckenweg 4",
    "sg:city":"Neunkirchen",
    "sg:phone":"+49 9134/997940",
    "sg:postcode":"91077",
    "sg:province":"Bayern",
    "wof:name":"H. S\u00fcss Elektroinstallation",
    "wof:placetype":"venue"
},
  "geometry": {"coordinates":[11.121998,49.614918],"type":"Point"}
}