{
  "type": "Feature",
  "properties": {
    "iso:country":"DE",
    "sg:address":"Schwaneweder Str. 2",
    "sg:city":"Bremen",
    "sg:phone":"+49 421/605794",
    "sg:postcode":"28779",
    "sg:province":"Bremen",
    "wof:name":"Schumann",
    "wof:placetype":"venue"
},
  "geometry": {"coordinates":[8.572032,53.196693],"type":"Point"}
}