{
  "type": "Feature",
  "properties": {
    "iso:country":"DE",
    "sg:address":"Am Gro\u00dfmarkt 1",
    "sg:city":"Herne",
    "sg:phone":"+49 2323/25510",
    "sg:postcode":"44653",
    "sg:province":"Nordrhein-Westfalen",
    "wof:name":"Am Gro\u00dfmarkt",
    "wof:placetype":"venue"
},
  "geometry": {"coordinates":[7.1908969879,51.5417709351],"type":"Point"}
}