{
  "type": "Feature",
  "properties": {
    "iso:country":"DE",
    "sg:address":"Schulstr. 26",
    "sg:city":"M\u00fcnsing",
    "sg:phone":"+49 8171/26678",
    "sg:postcode":"82541",
    "sg:province":"Bayern",
    "wof:name":"Katholisches Pfarramt St. Michael",
    "wof:placetype":"venue"
},
  "geometry": {"coordinates":[11.3782863617,47.8783760071],"type":"Point"}
}