{
  "type": "Feature",
  "properties": {
    "iso:country":"DE",
    "sg:address":"Am Sonnenhang 8",
    "sg:city":"M\u00f6hnesee",
    "sg:phone":"+49 2924/7065",
    "sg:postcode":"59519",
    "sg:province":"Nordrhein-Westfalen",
    "wof:name":"Dietrich Sch\u00e4fer Rechtsanwalt",
    "wof:placetype":"venue"
},
  "geometry": {"coordinates":[8.0867586136,51.493888855],"type":"Point"}
}