{
  "type": "Feature",
  "properties": {
    "iso:country":"DE",
    "sg:address":"Hauptstr. 10",
    "sg:city":"Aachen",
    "sg:phone":"+49 241/602176",
    "sg:postcode":"52066",
    "sg:province":"Nordrhein-Westfalen",
    "wof:name":"Dieter Neustra\u00df",
    "wof:placetype":"venue"
},
  "geometry": {"coordinates":[6.0921821594,50.7637405396],"type":"Point"}
}