{
  "type": "Feature",
  "properties": {
    "iso:country":"DE",
    "sg:address":"Auf der Heide 6",
    "sg:city":"Nettersheim",
    "sg:phone":"+49 2486/1661",
    "sg:postcode":"53947",
    "sg:province":"Nordrhein-Westfalen",
    "wof:name":"Scan-schleifmittel Gmbh",
    "wof:placetype":"venue"
},
  "geometry": {"coordinates":[6.657261,50.50679],"type":"Point"}
}