{
  "type": "Feature",
  "properties": {
    "iso:country":"DE",
    "sg:address":"Gartenstr. 3",
    "sg:city":"Neuruppin",
    "sg:phone":"+49 3391/2806",
    "sg:postcode":"16816",
    "sg:province":"Brandenburg",
    "wof:name":"Drei Linden",
    "wof:placetype":"venue"
},
  "geometry": {"coordinates":[12.8139257431,52.9316482544],"type":"Point"}
}