{
  "type": "Feature",
  "properties": {
    "iso:country":"DE",
    "sg:address":"Husarenstr. 2",
    "sg:city":"Sankt Augustin",
    "sg:phone":"+49 2241/2361",
    "sg:postcode":"53757",
    "sg:province":"Nordrhein-Westfalen",
    "wof:name":"Caritas-altenheim St. Monika",
    "wof:placetype":"venue"
},
  "geometry": {"coordinates":[7.179815,50.770535],"type":"Point"}
}