{
  "type": "Feature",
  "properties": {
    "iso:country":"DE",
    "sg:address":"Ischlestr. 20",
    "sg:city":"Rottweil",
    "sg:phone":"+49 4974/122746",
    "sg:postcode":"78628",
    "sg:province":"Baden-W\u00fcrttemberg",
    "wof:name":"Gustav Kuon Lackfabrik",
    "wof:placetype":"venue"
},
  "geometry": {"coordinates":[8.6275,48.167858],"type":"Point"}
}