{
  "type": "Feature",
  "properties": {
    "iso:country":"DE",
    "sg:address":"Chemnitztalstr. 169",
    "sg:city":"Chemnitz",
    "sg:postcode":"09114",
    "sg:province":"Sachsen",
    "wof:name":"Winfried Nerger",
    "wof:placetype":"venue"
},
  "geometry": {"coordinates":[12.909711,50.870735],"type":"Point"}
}