{
  "type": "Feature",
  "properties": {
    "iso:country":"DE",
    "sg:address":"Burgstr. 108",
    "sg:city":"K\u00f6ln",
    "sg:phone":"+49 221/872304",
    "sg:postcode":"51103",
    "sg:province":"Nordrhein-Westfalen",
    "wof:name":"Herta Diedrich",
    "wof:placetype":"venue"
},
  "geometry": {"coordinates":[7.0245480537,50.9374847412],"type":"Point"}
}