{
  "type": "Feature",
  "properties": {
    "iso:country":"DE",
    "sg:address":"Johann-Sebastian-Bach-Ring 25",
    "sg:city":"Windsbach",
    "sg:phone":"+49 9871/7711",
    "sg:postcode":"91575",
    "sg:province":"Bayern",
    "wof:name":"Viering Werkzeuge Maschinen Gmbh",
    "wof:placetype":"venue"
},
  "geometry": {"coordinates":[10.8376607895,49.2452850342],"type":"Point"}
}