{
  "type": "Feature",
  "properties": {
    "iso:country":"DE",
    "sg:address":"Klosterstr. 9",
    "sg:city":"Schwandorf",
    "sg:phone":"+49 9431/1342",
    "sg:postcode":"92421",
    "sg:province":"Bayern",
    "wof:name":"Meixner Reiseb\u00fcro",
    "wof:placetype":"venue"
},
  "geometry": {"coordinates":[12.1061220169,49.3279914856],"type":"Point"}
}