{
  "type": "Feature",
  "properties": {
    "iso:country":"DE",
    "sg:address":"Bergsonstr. 106",
    "sg:city":"M\u00fcnchen",
    "sg:phone":"+49 89/89711081",
    "sg:postcode":"81245",
    "sg:province":"Bayern",
    "wof:name":"Barmaneter & Seibert Gmbh",
    "wof:placetype":"venue"
},
  "geometry": {"coordinates":[11.428628,48.1642],"type":"Point"}
}