{
  "type": "Feature",
  "properties": {
    "iso:country":"DE",
    "sg:address":"Hauptstr. 24",
    "sg:city":"Brome",
    "sg:phone":"+49 5833/979844",
    "sg:postcode":"38465",
    "sg:province":"Niedersachsen",
    "wof:name":"Restaurante Roma",
    "wof:placetype":"venue"
},
  "geometry": {"coordinates":[10.9443016052,52.6020736694],"type":"Point"}
}