{
  "type": "Feature",
  "properties": {
    "iso:country":"DE",
    "sg:address":"Ridderstr. 23",
    "sg:city":"Ahaus",
    "sg:phone":"+49 2561/3087",
    "sg:postcode":"48683",
    "sg:province":"Nordrhein-Westfalen",
    "wof:name":"Ossendorf Gmbh",
    "wof:placetype":"venue"
},
  "geometry": {"coordinates":[7.018887,52.080475],"type":"Point"}
}