{
  "type": "Feature",
  "properties": {
    "iso:country":"DE",
    "sg:address":"Lotzstr. 12",
    "sg:city":"Nettetal",
    "sg:phone":"+49 2153/72784",
    "sg:postcode":"41334",
    "sg:province":"Nordrhein-Westfalen",
    "wof:name":"Willy Friedhoff",
    "wof:placetype":"venue"
},
  "geometry": {"coordinates":[6.247491,51.296318],"type":"Point"}
}