{
  "type": "Feature",
  "properties": {
    "iso:country":"DE",
    "sg:address":"Rathausstr. 2",
    "sg:city":"Ranis",
    "sg:phone":"+49 3647/422573",
    "sg:postcode":"07389",
    "sg:province":"Th\u00fcringen",
    "wof:name":"H. Beyer",
    "wof:placetype":"venue"
},
  "geometry": {"coordinates":[11.566248,50.662457],"type":"Point"}
}