{
  "type": "Feature",
  "properties": {
    "iso:country":"DE",
    "sg:address":"Scharzfelder Str.",
    "sg:city":"Bad Lauterberg",
    "sg:phone":"+49 5524/6612",
    "sg:postcode":"37431",
    "sg:province":"Niedersachsen",
    "wof:name":"Burgruine Scharzfels",
    "wof:placetype":"venue"
},
  "geometry": {"coordinates":[10.4344997406,51.6222991943],"type":"Point"}
}