{
  "type": "Feature",
  "properties": {
    "iso:country":"DE",
    "sg:address":"Minslebener Str. 26",
    "sg:city":"Derenburg",
    "sg:phone":"+49 39453/50526",
    "sg:postcode":"38895",
    "sg:province":"Sachsen-Anhalt",
    "wof:name":"Iris Jacob",
    "wof:placetype":"venue"
},
  "geometry": {"coordinates":[10.904299736,51.8704719543],"type":"Point"}
}