{
  "type": "Feature",
  "properties": {
    "iso:country":"DE",
    "sg:address":"Heisiusstr. 18",
    "sg:city":"Bremen",
    "sg:phone":"+49 421/480445",
    "sg:postcode":"28307",
    "sg:province":"Bremen",
    "wof:name":"H. K\u00f6nsen",
    "wof:placetype":"venue"
},
  "geometry": {"coordinates":[8.9177856445,53.0406112671],"type":"Point"}
}