{
  "type": "Feature",
  "properties": {
    "iso:country":"DE",
    "sg:address":"Lange Str. 17",
    "sg:city":"Hann. M\u00fcnden",
    "sg:phone":"+49 5541/2180",
    "sg:postcode":"34346",
    "sg:province":"Niedersachsen",
    "wof:name":"Rehberg Fachgesch\u00e4ft F\u00fcr Handarbeiten",
    "wof:placetype":"venue"
},
  "geometry": {"coordinates":[9.652213,51.418125],"type":"Point"}
}