{
  "type": "Feature",
  "properties": {
    "iso:country":"DE",
    "sg:address":"Heuss-Str. 23",
    "sg:city":"Aachen",
    "sg:phone":"+49 241/5859306",
    "sg:postcode":"52078",
    "sg:province":"Nordrhein-Westfalen",
    "wof:name":"Articult Gmbh",
    "wof:placetype":"venue"
},
  "geometry": {"coordinates":[6.1564202309,50.7514305115],"type":"Point"}
}