{
  "type": "Feature",
  "properties": {
    "iso:country":"DE",
    "sg:address":"Zinnkrautweg 42",
    "sg:city":"Hamburg",
    "sg:phone":"+49 40/6016149",
    "sg:postcode":"22395",
    "sg:province":"Hamburg",
    "wof:name":"Wolfgang Thieme",
    "wof:placetype":"venue"
},
  "geometry": {"coordinates":[10.1112098694,53.6598815918],"type":"Point"}
}