{
  "type": "Feature",
  "properties": {
    "iso:country":"DE",
    "sg:address":"Ostenstr. 1",
    "sg:city":"Schwerte",
    "sg:phone":"+49 2304/16735",
    "sg:postcode":"58239",
    "sg:province":"Nordrhein-Westfalen",
    "wof:name":"Aydin",
    "wof:placetype":"venue"
},
  "geometry": {"coordinates":[7.5691738129,51.4411239624],"type":"Point"}
}