{
  "type": "Feature",
  "properties": {
    "iso:country":"DE",
    "sg:address":"Rh\u00f6nstr. 2",
    "sg:city":"Hofheim",
    "sg:phone":"+49 6192/99650",
    "sg:postcode":"65719",
    "sg:province":"Hessen",
    "wof:name":"Wilhelm Pier Process Analytical",
    "wof:placetype":"venue"
},
  "geometry": {"coordinates":[8.4189958572,50.059337616],"type":"Point"}
}