{
  "type": "Feature",
  "properties": {
    "iso:country":"DE",
    "sg:address":"Dornstetter Str. 43",
    "sg:city":"Waldachtal",
    "sg:phone":"+49 7443/5210",
    "sg:postcode":"72178",
    "sg:province":"Baden-W\u00fcrttemberg",
    "wof:name":"Richard Schmelzle Ingenieur",
    "wof:placetype":"venue"
},
  "geometry": {"coordinates":[8.55389,48.479305],"type":"Point"}
}