{
  "type": "Feature",
  "properties": {
    "iso:country":"DE",
    "sg:address":"Bahnhofstr. 11",
    "sg:city":"Nordhorn",
    "sg:phone":"+49 5921/98261",
    "sg:postcode":"48529",
    "sg:province":"Niedersachsen",
    "wof:name":"Sparkassenstiftung F\u00fcr Die Grafschaft Bentheim",
    "wof:placetype":"venue"
},
  "geometry": {"coordinates":[7.0644412041,52.4322052002],"type":"Point"}
}