{
  "type": "Feature",
  "properties": {
    "iso:country":"DE",
    "sg:address":"Altenstadter Str. 18-20",
    "sg:city":"Schongau",
    "sg:phone":"+49 8861/8064",
    "sg:postcode":"86956",
    "sg:province":"Bayern",
    "wof:name":"W. Kurt Gnettner",
    "wof:placetype":"venue"
},
  "geometry": {"coordinates":[10.890203476,47.8180122375],"type":"Point"}
}