{
  "type": "Feature",
  "properties": {
    "iso:country":"DE",
    "sg:address":"Buchenhofener Str. 23",
    "sg:city":"Wuppertal",
    "sg:phone":"+49 202/780815",
    "sg:postcode":"42329",
    "sg:province":"Nordrhein-Westfalen",
    "wof:name":"Herminghaus & Co. Gmbh",
    "wof:placetype":"venue"
},
  "geometry": {"coordinates":[7.1084899902,51.2267723083],"type":"Point"}
}