{
  "type": "Feature",
  "properties": {
    "iso:country":"DE",
    "sg:address":"Hauptstr. 35",
    "sg:city":"Gr\u00e4fendorf",
    "sg:phone":"+49 3535/23660",
    "sg:postcode":"04916",
    "sg:province":"Brandenburg",
    "wof:name":"Preu\u00df Bau Gmbh",
    "wof:placetype":"venue"
},
  "geometry": {"coordinates":[9.7414073944,50.1225204468],"type":"Point"}
}