{
  "type": "Feature",
  "properties": {
    "iso:country":"DE",
    "sg:address":"Hauptstr. 24",
    "sg:city":"Lichtenau",
    "sg:phone":"+49 7227/8401",
    "sg:postcode":"77839",
    "sg:province":"Baden-W\u00fcrttemberg",
    "wof:name":"Doris Kl\u00f6pfer Gmbh",
    "wof:placetype":"venue"
},
  "geometry": {"coordinates":[8.007789,48.726246],"type":"Point"}
}