{
  "type": "Feature",
  "properties": {
    "iso:country":"DE",
    "sg:address":"Franz-Marc-Weg 66",
    "sg:city":"M\u00fcnster",
    "sg:phone":"+49 2501/6997",
    "sg:postcode":"48165",
    "sg:province":"Nordrhein-Westfalen",
    "wof:name":"H. Feldkamp",
    "wof:placetype":"venue"
},
  "geometry": {"coordinates":[7.668407917,51.9002838135],"type":"Point"}
}