{
  "type": "Feature",
  "properties": {
    "iso:country":"DE",
    "sg:address":"Parsickstr. 19",
    "sg:city":"Moers",
    "sg:phone":"+49 2841/27210",
    "sg:postcode":"47441",
    "sg:province":"Nordrhein-Westfalen",
    "wof:name":"Hans Slomka",
    "wof:placetype":"venue"
},
  "geometry": {"coordinates":[6.605670929,51.4480895996],"type":"Point"}
}