{
  "type": "Feature",
  "properties": {
    "iso:country":"DE",
    "sg:address":"Am Fort Schaar 14",
    "sg:city":"Wilhelmshaven",
    "sg:phone":"+49 4421/83566",
    "sg:postcode":"26389",
    "sg:province":"Niedersachsen",
    "wof:name":"Bfb B\u00fcro F\u00fcr Baupublikationen Inh. Evelyn Koch",
    "wof:placetype":"venue"
},
  "geometry": {"coordinates":[8.072447,53.543217],"type":"Point"}
}