{
  "type": "Feature",
  "properties": {
    "iso:country":"DE",
    "sg:address":"Am Lunedeich 37",
    "sg:city":"Bremerhaven",
    "sg:phone":"+49 471/76051",
    "sg:postcode":"27572",
    "sg:province":"Bremen",
    "wof:name":"Meynstapler Vertriebs Und Service Gmbh",
    "wof:placetype":"venue"
},
  "geometry": {"coordinates":[8.5834312439,53.5171394348],"type":"Point"}
}