{
  "type": "Feature",
  "properties": {
    "iso:country":"DE",
    "sg:address":"Stedefreunder Str. 168",
    "sg:city":"Herford",
    "sg:phone":"+49 5221/3774",
    "sg:postcode":"32051",
    "sg:province":"Nordrhein-Westfalen",
    "wof:name":"August St\u00f6rmer",
    "wof:placetype":"venue"
},
  "geometry": {"coordinates":[8.58533,52.107182],"type":"Point"}
}