{
  "type": "Feature",
  "properties": {
    "iso:country":"DE",
    "sg:address":"Am Brink 9",
    "sg:city":"Klein Ber\u00dfen",
    "sg:phone":"+49 5965/651",
    "sg:postcode":"49777",
    "sg:province":"Niedersachsen",
    "wof:name":"Heinrich Brockmann",
    "wof:placetype":"venue"
},
  "geometry": {"coordinates":[7.463766,52.767448],"type":"Point"}
}