{
  "type": "Feature",
  "properties": {
    "iso:country":"DE",
    "sg:address":"Frauenalber Str. 5",
    "sg:city":"Marxzell",
    "sg:phone":"+49 7248/5578",
    "sg:postcode":"76359",
    "sg:province":"Baden-W\u00fcrttemberg",
    "wof:name":"Eckert Pension",
    "wof:placetype":"venue"
},
  "geometry": {"coordinates":[8.4498157501,48.8431472778],"type":"Point"}
}