{
  "type": "Feature",
  "properties": {
    "iso:country":"DE",
    "sg:address":"Paul-Keller-Str. 5",
    "sg:city":"Pocking",
    "sg:phone":"+49 8531/912110",
    "sg:postcode":"94060",
    "sg:province":"Bayern",
    "wof:name":"Siegfried H\u00f6fer Immobilien Gmbh",
    "wof:placetype":"venue"
},
  "geometry": {"coordinates":[13.3291950226,48.4080429077],"type":"Point"}
}