{
  "type": "Feature",
  "properties": {
    "iso:country":"DE",
    "sg:address":"Weidenauer Str. 167",
    "sg:city":"Siegen",
    "sg:phone":"+49 271/76092",
    "sg:postcode":"57076",
    "sg:province":"Nordrhein-Westfalen",
    "wof:name":"Bernd Erich Kill Architekt",
    "wof:placetype":"venue"
},
  "geometry": {"coordinates":[8.027706,50.897938],"type":"Point"}
}