{
  "type": "Feature",
  "properties": {
    "iso:country":"DE",
    "sg:address":"Kremelstr. 20",
    "sg:city":"Baumholder",
    "sg:phone":"+49 6783/981222",
    "sg:postcode":"55774",
    "sg:province":"Rheinland-Pfalz",
    "wof:name":"P. R. Pallasch",
    "wof:placetype":"venue"
},
  "geometry": {"coordinates":[7.3333377838,49.6146469116],"type":"Point"}
}