{
  "type": "Feature",
  "properties": {
    "iso:country":"DE",
    "sg:address":"Griesenbalken 3",
    "sg:city":"Overath",
    "sg:phone":"+49 2206/2357",
    "sg:postcode":"51491",
    "sg:province":"Nordrhein-Westfalen",
    "wof:name":"Franz Mester",
    "wof:placetype":"venue"
},
  "geometry": {"coordinates":[7.276756,50.952393],"type":"Point"}
}