{
  "type": "Feature",
  "properties": {
    "iso:country":"DE",
    "sg:address":"Licher Strasse 16",
    "sg:city":"Pohlheim",
    "sg:phone":"+49 6404",
    "sg:postcode":"35415",
    "sg:province":"Hessen",
    "wof:name":"Clown Ichmael",
    "wof:placetype":"venue"
},
  "geometry": {"coordinates":[8.751501,50.537811],"type":"Point"}
}