{
  "type": "Feature",
  "properties": {
    "iso:country":"DE",
    "sg:address":"Sonnenberg 3",
    "sg:city":"Schweigen-Rechtenbach",
    "sg:phone":"+49 6342/7879",
    "sg:postcode":"76889",
    "sg:province":"Rheinland-Pfalz",
    "wof:name":"Restaurant Sonnenberg",
    "wof:placetype":"venue"
},
  "geometry": {"coordinates":[7.9489607811,49.0513801575],"type":"Point"}
}