{
  "type": "Feature",
  "properties": {
    "iso:country":"DE",
    "sg:address":"Schulstr. 13",
    "sg:city":"Friedrichsdorf",
    "sg:phone":"+49 6175/93300",
    "sg:postcode":"61381",
    "sg:province":"Hessen",
    "wof:name":"Lissmeier Design",
    "wof:placetype":"venue"
},
  "geometry": {"coordinates":[8.653947,50.276875],"type":"Point"}
}