{
  "type": "Feature",
  "properties": {
    "iso:country":"DE",
    "sg:address":"Kantstr. 2",
    "sg:city":"Weimar",
    "sg:postcode":"99425",
    "sg:province":"Th\u00fcringen",
    "wof:name":"Ing.-b\u00fcro R\u00f6sler & Partner Gmbh",
    "wof:placetype":"venue"
},
  "geometry": {"coordinates":[11.3339853287,50.9699249268],"type":"Point"}
}