{
  "type": "Feature",
  "properties": {
    "iso:country":"DE",
    "sg:address":"Haringstr. 25",
    "sg:city":"H\u00f6henkirchen-Siegertbrn",
    "sg:phone":"+49 8102/71824",
    "sg:postcode":"85635",
    "sg:province":"Bayern",
    "wof:name":"Helmut Sperka Architekt",
    "wof:placetype":"venue"
},
  "geometry": {"coordinates":[11.720812,48.022564],"type":"Point"}
}