{
  "type": "Feature",
  "properties": {
    "iso:country":"DE",
    "sg:address":"Carl-Sonnenschein-Str. 30",
    "sg:city":"L\u00fcdinghausen",
    "sg:phone":"+49 2591/5041",
    "sg:postcode":"59348",
    "sg:province":"Nordrhein-Westfalen",
    "wof:name":"Cordial-produktions- Und Warenvertriebs Gmbh",
    "wof:placetype":"venue"
},
  "geometry": {"coordinates":[7.4317989349,51.7580795288],"type":"Point"}
}