{
  "type": "Feature",
  "properties": {
    "iso:country":"DE",
    "sg:address":"Putlitzer Str. 50",
    "sg:city":"Parchim",
    "sg:phone":"+49 3871/226103",
    "sg:postcode":"19370",
    "sg:province":"Mecklenburg-Vorpommern",
    "wof:name":"Sabrina Steinbring-gatz Rechtsanw\u00e4ltin",
    "wof:placetype":"venue"
},
  "geometry": {"coordinates":[11.8462591171,53.4236984253],"type":"Point"}
}