{
  "type": "Feature",
  "properties": {
    "iso:country":"DE",
    "sg:address":"Hauptstr. 8A",
    "sg:city":"Salzgitter",
    "sg:phone":"+49 5300/261",
    "sg:postcode":"38239",
    "sg:province":"Niedersachsen",
    "wof:name":"Karl Cordes",
    "wof:placetype":"venue"
},
  "geometry": {"coordinates":[10.411542,52.198963],"type":"Point"}
}