{
  "type": "Feature",
  "properties": {
    "iso:country":"DE",
    "sg:address":"Mozartstr. 26",
    "sg:city":"Wiesenbach",
    "sg:phone":"+49 6223/970101",
    "sg:postcode":"69257",
    "sg:province":"Baden-W\u00fcrttemberg",
    "wof:name":"I. W\u00f6lfelschneider Rechtsanwalt",
    "wof:placetype":"venue"
},
  "geometry": {"coordinates":[8.7983980179,49.361995697],"type":"Point"}
}