{
  "type": "Feature",
  "properties": {
    "iso:country":"DE",
    "sg:address":"Auf dem \u00d6wer 2",
    "sg:city":"Leer",
    "sg:phone":"+49 491/3505",
    "sg:postcode":"26789",
    "sg:province":"Niedersachsen",
    "wof:name":"Lammert Battermann",
    "wof:placetype":"venue"
},
  "geometry": {"coordinates":[7.413895,53.221985],"type":"Point"}
}