{
  "type": "Feature",
  "properties": {
    "iso:country":"DE",
    "sg:address":"Grabenstr. 32",
    "sg:city":"Neuwied",
    "sg:phone":"+49 2631/31749",
    "sg:postcode":"56564",
    "sg:province":"Rheinland-Pfalz",
    "wof:name":"J\u00fcrgen H\u00f6ppner Garten- Und",
    "wof:placetype":"venue"
},
  "geometry": {"coordinates":[7.470838,50.441792],"type":"Point"}
}