{
  "type": "Feature",
  "properties": {
    "iso:country":"DE",
    "sg:address":"Ostpassage 7",
    "sg:city":"Langenhagen",
    "sg:phone":"+49 511/733058",
    "sg:postcode":"30853",
    "sg:province":"Niedersachsen",
    "wof:name":"Gesellschaft F\u00fcr Den Vertrieb Hochwert. Medizin.-techn. Pro-",
    "wof:placetype":"venue"
},
  "geometry": {"coordinates":[9.741558,52.439377],"type":"Point"}
}