{
  "type": "Feature",
  "properties": {
    "iso:country":"DE",
    "sg:address":"Colmener Str. 7",
    "sg:city":"Rehlingen-Siersburg",
    "sg:phone":"+49 6835/67056",
    "sg:postcode":"66780",
    "sg:province":"Saarland",
    "wof:name":"Berthold Ohlmann",
    "wof:placetype":"venue"
},
  "geometry": {"coordinates":[6.681455,49.376942],"type":"Point"}
}