{
  "type": "Feature",
  "properties": {
    "iso:country":"DE",
    "sg:address":"Rosterstr. 49",
    "sg:city":"Siegen",
    "sg:phone":"+49 271/236030",
    "sg:postcode":"57074",
    "sg:province":"Nordrhein-Westfalen",
    "wof:name":"Bernd Donath Rechtsanwalt",
    "wof:placetype":"venue"
},
  "geometry": {"coordinates":[8.0155277252,50.866569519],"type":"Point"}
}