{
  "type": "Feature",
  "properties": {
    "iso:country":"DE",
    "sg:address":"Am Brunnen 16",
    "sg:city":"Potsdam",
    "sg:postcode":"14473",
    "sg:province":"Brandenburg",
    "wof:name":"Dr. Med. Erika Fischer",
    "wof:placetype":"venue"
},
  "geometry": {"coordinates":[13.076992,52.378342],"type":"Point"}
}