{
  "type": "Feature",
  "properties": {
    "iso:country":"DE",
    "sg:address":"Gutenbergstr. 10 POSTFACH 600163",
    "sg:city":"Sindelfingen",
    "sg:phone":"+49 4970/3173930",
    "sg:postcode":"71050",
    "sg:province":"Baden-W\u00fcrttemberg",
    "wof:name":"K\u00d6rner Rotationsdruck",
    "wof:placetype":"venue"
},
  "geometry": {"coordinates":[8.9751281738,48.7283363342],"type":"Point"}
}