{
  "type": "Feature",
  "properties": {
    "iso:country":"DE",
    "sg:address":"Kaltenweide 17",
    "sg:city":"Elmshorn",
    "sg:phone":"+49 4121/81515",
    "sg:postcode":"25335",
    "sg:province":"Schleswig-Holstein",
    "wof:name":"Uwe Oeding",
    "wof:placetype":"venue"
},
  "geometry": {"coordinates":[9.665763,53.756805],"type":"Point"}
}