{
  "type": "Feature",
  "properties": {
    "iso:country":"DE",
    "sg:address":"Behaimstr. 9",
    "sg:city":"Weiden",
    "sg:phone":"+49 961/61234",
    "sg:postcode":"92637",
    "sg:province":"Bayern",
    "wof:name":"Max Scharnagl",
    "wof:placetype":"venue"
},
  "geometry": {"coordinates":[12.152387619,49.682559967],"type":"Point"}
}