{
  "type": "Feature",
  "properties": {
    "iso:country":"DE",
    "sg:address":"Lindenstr. 45",
    "sg:city":"Crimmitschau",
    "sg:phone":"+49 3762/2735",
    "sg:postcode":"08451",
    "sg:province":"Sachsen",
    "wof:name":"Liselotte J\u00e4hnig Hebamme",
    "wof:placetype":"venue"
},
  "geometry": {"coordinates":[12.31945,50.794048],"type":"Point"}
}