{
  "type": "Feature",
  "properties": {
    "iso:country":"DE",
    "sg:address":"Gro\u00dfenhainer Str. 70",
    "sg:city":"Pr\u00f6sen",
    "sg:phone":"+49 3533/811117",
    "sg:postcode":"04932",
    "sg:province":"Brandenburg",
    "wof:name":"Ute Schmidtchen",
    "wof:placetype":"venue"
},
  "geometry": {"coordinates":[13.500905,51.427467],"type":"Point"}
}