{
  "type": "Feature",
  "properties": {
    "iso:country":"DE",
    "sg:address":"Frankfurter Str. 21",
    "sg:city":"Kelkheim",
    "sg:phone":"+49 6195/2000",
    "sg:postcode":"65779",
    "sg:province":"Hessen",
    "wof:name":"Sigrun Horn Antiquit\u00e4ten",
    "wof:placetype":"venue"
},
  "geometry": {"coordinates":[8.451334,50.13562],"type":"Point"}
}