{
  "type": "Feature",
  "properties": {
    "iso:country":"DE",
    "sg:address":"St.-Georg-Str. 10",
    "sg:city":"Dasing",
    "sg:phone":"+49 8205/7327",
    "sg:postcode":"86453",
    "sg:province":"Bayern",
    "wof:name":"Leonhard R\u00f6mmelt",
    "wof:placetype":"venue"
},
  "geometry": {"coordinates":[11.089633,48.388374],"type":"Point"}
}