{
  "type": "Feature",
  "properties": {
    "iso:country":"DE",
    "sg:address":"Lindenh\u00f6he 19",
    "sg:city":"Durach",
    "sg:phone":"+49 831/564290",
    "sg:postcode":"87471",
    "sg:province":"Bayern",
    "wof:name":"Dipl.-ing. Dieter Pestel",
    "wof:placetype":"venue"
},
  "geometry": {"coordinates":[10.339935,47.700405],"type":"Point"}
}