{
  "type": "Feature",
  "properties": {
    "iso:country":"DE",
    "sg:address":"Hausdorffstr. 160",
    "sg:city":"Bonn",
    "sg:phone":"+49 228/232881",
    "sg:postcode":"53129",
    "sg:province":"Nordrhein-Westfalen",
    "wof:name":"Adolf Simon",
    "wof:placetype":"venue"
},
  "geometry": {"coordinates":[7.108487,50.712296],"type":"Point"}
}