{
  "type": "Feature",
  "properties": {
    "iso:country":"DE",
    "sg:address":"Alte Kirchstr. 47",
    "sg:city":"Rahden",
    "sg:phone":"+49 5776/380",
    "sg:postcode":"32369",
    "sg:province":"Nordrhein-Westfalen",
    "wof:name":"Friedr. Tinnemeier",
    "wof:placetype":"venue"
},
  "geometry": {"coordinates":[8.679676,52.483677],"type":"Point"}
}