{
  "type": "Feature",
  "properties": {
    "iso:country":"DE",
    "sg:address":"B\u00fcrgermeister-Bohl-Str. 66d",
    "sg:city":"Augsburg",
    "sg:phone":"+49 821/2292044",
    "sg:postcode":"86157",
    "sg:province":"Bayern",
    "wof:name":"Josef Und Maria Pauli",
    "wof:placetype":"venue"
},
  "geometry": {"coordinates":[10.861237,48.356934],"type":"Point"}
}