{
  "type": "Feature",
  "properties": {
    "iso:country":"DE",
    "sg:address":"Richard-Strau\u00df-Str. 32",
    "sg:city":"Freilassing",
    "sg:phone":"+49 8654/9179",
    "sg:postcode":"83395",
    "sg:province":"Bayern",
    "wof:name":"Peter Krug",
    "wof:placetype":"venue"
},
  "geometry": {"coordinates":[12.9742269516,47.8469047546],"type":"Point"}
}