{
  "type": "Feature",
  "properties": {
    "iso:country":"DE",
    "sg:address":"Johann-Tongers-Pad 5",
    "sg:city":"Langeoog",
    "sg:phone":"+49 4972/6154",
    "sg:postcode":"26465",
    "sg:province":"Niedersachsen",
    "wof:name":"G\u00e4stehaus M. Leweck",
    "wof:placetype":"venue"
},
  "geometry": {"coordinates":[7.4810352325,53.7467765808],"type":"Point"}
}