{
  "type": "Feature",
  "properties": {
    "iso:country":"DE",
    "sg:address":"Prager Str. 1b/102",
    "sg:city":"Weimar",
    "sg:phone":"+49 3643/403579",
    "sg:postcode":"99427",
    "sg:province":"Th\u00fcringen",
    "wof:name":"Hygiene Kleinert E. K.",
    "wof:placetype":"venue"
},
  "geometry": {"coordinates":[11.309374,50.988647],"type":"Point"}
}