{
  "type": "Feature",
  "properties": {
    "iso:country":"DE",
    "sg:address":"Bahnhofstr. 15",
    "sg:city":"Bad K\u00f6nig",
    "sg:phone":"+49 4960/632071",
    "sg:postcode":"64732",
    "sg:province":"Hessen",
    "wof:name":"Sparkasse Odenwaldkreis",
    "wof:placetype":"venue"
},
  "geometry": {"coordinates":[9.003945,49.741127],"type":"Point"}
}