{
  "type": "Feature",
  "properties": {
    "iso:country":"DE",
    "sg:address":"Neumarkt",
    "sg:city":"Schleiz",
    "sg:phone":"+49 3663/2438",
    "sg:postcode":"07907",
    "sg:province":"Th\u00fcringen",
    "wof:name":"Johann-friedrich-b\u00f6ttger- Gedenkst\u00e4tte",
    "wof:placetype":"venue"
},
  "geometry": {"coordinates":[11.809585,50.576778],"type":"Point"}
}