{
  "type": "Feature",
  "properties": {
    "iso:country":"DE",
    "sg:address":"Sassenberg 18",
    "sg:city":"S\u00f6gel",
    "sg:phone":"+49 5952/93330",
    "sg:postcode":"49751",
    "sg:province":"Niedersachsen",
    "wof:name":"K. H. Rolfes Steuerbevollm\u00e4chtigter",
    "wof:placetype":"venue"
},
  "geometry": {"coordinates":[7.5160279274,52.8410758972],"type":"Point"}
}