{
  "type": "Feature",
  "properties": {
    "iso:country":"DE",
    "sg:address":"Markusstr. 18",
    "sg:city":"Reutlingen",
    "sg:phone":"+49 7121/330475",
    "sg:postcode":"72760",
    "sg:province":"Baden-W\u00fcrttemberg",
    "wof:name":"Hans-joachim K\u00f6lle",
    "wof:placetype":"venue"
},
  "geometry": {"coordinates":[9.205465,48.499847],"type":"Point"}
}