{
  "type": "Feature",
  "properties": {
    "iso:country":"DE",
    "sg:address":"Boeselagerstr. 20",
    "sg:city":"M\u00fcnster",
    "sg:phone":"+49 251/73826",
    "sg:postcode":"48163",
    "sg:province":"Nordrhein-Westfalen",
    "wof:name":"Blumenhalle Dreyer",
    "wof:placetype":"venue"
},
  "geometry": {"coordinates":[7.598642,51.93581],"type":"Point"}
}