{
  "type": "Feature",
  "properties": {
    "iso:country":"DE",
    "sg:address":"Mathildenstr 12",
    "sg:city":"M\u00fcnchen",
    "sg:phone":"+49 89/5387",
    "sg:postcode":"80336",
    "sg:province":"Bayern",
    "wof:name":"M\u00fcnchener Hypothekenbank Eg",
    "wof:placetype":"venue"
},
  "geometry": {"coordinates":[11.563447,48.133781],"type":"Point"}
}