{
  "type": "Feature",
  "properties": {
    "iso:country":"DE",
    "sg:address":"Gr\u00fcnberger Str. 54",
    "sg:city":"Alsfeld",
    "sg:phone":"+49 6631/5015",
    "sg:postcode":"36304",
    "sg:province":"Hessen",
    "wof:name":"Raiffeisen Waren-zentrale Rhein-main Eg",
    "wof:placetype":"venue"
},
  "geometry": {"coordinates":[9.263452,50.745831],"type":"Point"}
}