{
  "type": "Feature",
  "properties": {
    "iso:country":"DE",
    "sg:address":"Tenter Weg 1",
    "sg:city":"Remscheid",
    "sg:postcode":"42897",
    "sg:province":"Nordrhein-Westfalen",
    "wof:name":"Voba Beteiligungsges. Mbh",
    "wof:placetype":"venue"
},
  "geometry": {"coordinates":[7.24444,51.177269],"type":"Point"}
}