{
  "type": "Feature",
  "properties": {
    "iso:country":"DE",
    "sg:address":"An Haus Bruch 10",
    "sg:city":"Grefrath",
    "sg:phone":"+49 2158/2133",
    "sg:postcode":"47929",
    "sg:province":"Nordrhein-Westfalen",
    "wof:name":"Haus Bruch",
    "wof:placetype":"venue"
},
  "geometry": {"coordinates":[6.3548998833,51.3307647705],"type":"Point"}
}