{
  "type": "Feature",
  "properties": {
    "iso:country":"DE",
    "sg:address":"Maybachweg 9",
    "sg:city":"Wolfsburg",
    "sg:phone":"+49 5361/85410",
    "sg:postcode":"38446",
    "sg:province":"Niedersachsen",
    "wof:name":"Naturstein-billen Die Grabmalberatung Gmbh",
    "wof:placetype":"venue"
},
  "geometry": {"coordinates":[10.8010101318,52.4297294617],"type":"Point"}
}