{
  "type": "Feature",
  "properties": {
    "iso:country":"DE",
    "sg:address":"H\u00fcxstr. 57",
    "sg:city":"L\u00fcbeck",
    "sg:phone":"+49 451/77212",
    "sg:postcode":"23552",
    "sg:province":"Schleswig-Holstein",
    "wof:name":"Aubergine",
    "wof:placetype":"venue"
},
  "geometry": {"coordinates":[10.6891860962,53.8658981323],"type":"Point"}
}