{
  "type": "Feature",
  "properties": {
    "iso:country":"DE",
    "sg:address":"Sandweg 14",
    "sg:city":"Frankfurt",
    "sg:phone":"+49 69/40353871",
    "sg:postcode":"60316",
    "sg:province":"Hessen",
    "wof:name":"It Models - Wir Bringen Sie Ins Internet",
    "wof:placetype":"venue"
},
  "geometry": {"coordinates":[8.696047,50.116795],"type":"Point"}
}