{
  "type": "Feature",
  "properties": {
    "iso:country":"DE",
    "sg:address":"Rother Str. 9",
    "sg:city":"Sauldorf",
    "sg:phone":"+49 7578/9220",
    "sg:postcode":"88605",
    "sg:province":"Baden-W\u00fcrttemberg",
    "wof:name":"Gabele Gmbh",
    "wof:placetype":"venue"
},
  "geometry": {"coordinates":[9.105742,47.941574],"type":"Point"}
}