{
  "type": "Feature",
  "properties": {
    "iso:country":"DE",
    "sg:address":"Burgstr. 12",
    "sg:city":"Rheinfelden",
    "sg:phone":"+49 7623/5564",
    "sg:postcode":"79618",
    "sg:province":"Baden-W\u00fcrttemberg",
    "wof:name":"Heinz Frank",
    "wof:placetype":"venue"
},
  "geometry": {"coordinates":[7.81383,47.587181],"type":"Point"}
}