{
  "type": "Feature",
  "properties": {
    "iso:country":"DE",
    "sg:address":"L\u00fcneburger Str. 105",
    "sg:city":"Soltau",
    "sg:phone":"+49 5191/98980",
    "sg:postcode":"29614",
    "sg:province":"Niedersachsen",
    "wof:name":"Milchzentrale Soltau Eg",
    "wof:placetype":"venue"
},
  "geometry": {"coordinates":[9.8622303009,52.9868202209],"type":"Point"}
}