{
  "type": "Feature",
  "properties": {
    "iso:country":"DE",
    "sg:address":"Violinenweg 3",
    "sg:city":"Waldeck",
    "sg:phone":"+49 5634/7208",
    "sg:postcode":"34513",
    "sg:province":"Hessen",
    "wof:name":"Fritz Becker",
    "wof:placetype":"venue"
},
  "geometry": {"coordinates":[8.985501,51.274643],"type":"Point"}
}