{
  "type": "Feature",
  "properties": {
    "iso:country":"DE",
    "sg:address":"Hochstr. 1",
    "sg:city":"Wiesbaden",
    "sg:postcode":"65195",
    "sg:province":"Hessen",
    "wof:name":"Can Altbausanierungen Und Baudekorationen Gmbh",
    "wof:placetype":"venue"
},
  "geometry": {"coordinates":[8.231424,50.087143],"type":"Point"}
}