{
  "type": "Feature",
  "properties": {
    "iso:country":"DE",
    "sg:address":"Skalitzer Str. 106",
    "sg:city":"Berlin",
    "sg:phone":"+49 30/6124010",
    "sg:postcode":"10997",
    "sg:province":"Berlin",
    "wof:name":"Bizim Tur-vermittlung",
    "wof:placetype":"venue"
},
  "geometry": {"coordinates":[13.4267673492,52.4994087219],"type":"Point"}
}