{
  "type": "Feature",
  "properties": {
    "iso:country":"DE",
    "sg:address":"Ludwigstr. 4",
    "sg:city":"Cham",
    "sg:phone":"+49 9971/1401",
    "sg:postcode":"93413",
    "sg:province":"Bayern",
    "wof:name":"E. Ehrl",
    "wof:placetype":"venue"
},
  "geometry": {"coordinates":[12.6639461517,49.2201004028],"type":"Point"}
}