{
  "type": "Feature",
  "properties": {
    "iso:country":"DE",
    "sg:address":"Turnerstr. 42",
    "sg:city":"Schkeuditz",
    "sg:phone":"+49 34204/14136",
    "sg:postcode":"04435",
    "sg:province":"Sachsen",
    "wof:name":"T\u00e4nzer Und Schwarz Rechtsanw\u00e4lte",
    "wof:placetype":"venue"
},
  "geometry": {"coordinates":[12.2178535461,51.3999938965],"type":"Point"}
}