{
  "type": "Feature",
  "properties": {
    "iso:country":"DE",
    "sg:address":"Lange Gasse 5",
    "sg:city":"Amberg",
    "sg:phone":"+49 9621/15327",
    "sg:postcode":"92224",
    "sg:province":"Bayern",
    "wof:name":"L. Zweck",
    "wof:placetype":"venue"
},
  "geometry": {"coordinates":[11.8521909714,49.4447746277],"type":"Point"}
}