{
  "type": "Feature",
  "properties": {
    "iso:country":"DE",
    "sg:address":"Donnerberg 90 b",
    "sg:city":"Essen",
    "sg:phone":"+49 201/697678",
    "sg:postcode":"45357",
    "sg:province":"Nordrhein-Westfalen",
    "wof:name":"Bernhard Terboven",
    "wof:placetype":"venue"
},
  "geometry": {"coordinates":[6.921772,51.481441],"type":"Point"}
}