{
  "type": "Feature",
  "properties": {
    "iso:country":"DE",
    "sg:address":"Bodestr 27-29",
    "sg:city":"Hamburg",
    "sg:phone":"+49 2603/96000",
    "sg:postcode":"21031",
    "sg:province":"Hamburg",
    "wof:name":"Heinen & L\u00f6wenstein Medizintechnik Gmbh",
    "wof:placetype":"venue"
},
  "geometry": {"coordinates":[7.72059,50.349819],"type":"Point"}
}