{
  "type": "Feature",
  "properties": {
    "iso:country":"DE",
    "sg:address":"Longericher Hauptstr. 70",
    "sg:city":"K\u00f6ln",
    "sg:phone":"+49 221/9574030",
    "sg:postcode":"50739",
    "sg:province":"Nordrhein-Westfalen",
    "wof:name":"Longericher Reiseb\u00fcro Gmbh",
    "wof:placetype":"venue"
},
  "geometry": {"coordinates":[6.9060258865,50.9971122742],"type":"Point"}
}