{
  "type": "Feature",
  "properties": {
    "iso:country":"DE",
    "sg:address":"Schulstr. 12",
    "sg:city":"Tuttlingen",
    "sg:phone":"+49 7461/4788",
    "sg:postcode":"78532",
    "sg:province":"Baden-W\u00fcrttemberg",
    "wof:name":"D. Kohler Ingenieur",
    "wof:placetype":"venue"
},
  "geometry": {"coordinates":[8.8169441223,47.9832496643],"type":"Point"}
}