{
  "type": "Feature",
  "properties": {
    "iso:country":"DE",
    "sg:address":"Melanchthonstr. 17",
    "sg:city":"Stuttgart",
    "sg:phone":"+49 711/5282515",
    "sg:postcode":"70374",
    "sg:province":"Baden-W\u00fcrttemberg",
    "wof:name":"Erwin B\u00e4chle",
    "wof:placetype":"venue"
},
  "geometry": {"coordinates":[9.2317399979,48.8069801331],"type":"Point"}
}