{
  "type": "Feature",
  "properties": {
    "iso:country":"DE",
    "sg:address":"Bierfelder Str. 8",
    "sg:city":"Gusenburg",
    "sg:phone":"+49 6503/7929",
    "sg:postcode":"54413",
    "sg:province":"Rheinland-Pfalz",
    "wof:name":"Bbl Malerbetrieb Gmbh",
    "wof:placetype":"venue"
},
  "geometry": {"coordinates":[6.902613,49.634056],"type":"Point"}
}