{
  "type": "Feature",
  "properties": {
    "iso:country":"DE",
    "sg:address":"Schwarzanger 21",
    "sg:city":"M\u00fcnchen",
    "sg:phone":"+49 89/3111011",
    "sg:postcode":"80939",
    "sg:province":"Bayern",
    "wof:name":"Asia Kunstblumen Gmbh",
    "wof:placetype":"venue"
},
  "geometry": {"coordinates":[11.594799,48.202789],"type":"Point"}
}