{
  "type": "Feature",
  "properties": {
    "iso:country":"DE",
    "sg:address":"Pohlstr. 20",
    "sg:city":"Berlin",
    "sg:phone":"+49 30/254440",
    "sg:postcode":"10785",
    "sg:province":"Berlin",
    "wof:name":"R & S Allgemeine Gesch\u00e4fts- F\u00fchrungs Gmbh & Co.",
    "wof:placetype":"venue"
},
  "geometry": {"coordinates":[13.368347168,52.5003890991],"type":"Point"}
}