{
  "type": "Feature",
  "properties": {
    "iso:country":"DE",
    "sg:address":"Hamburger Str. 45",
    "sg:city":"Ahrensburg",
    "sg:phone":"+49 4102/56161",
    "sg:postcode":"22926",
    "sg:province":"Schleswig-Holstein",
    "wof:name":"Esso Deutschland Gmbh",
    "wof:placetype":"venue"
},
  "geometry": {"coordinates":[10.2326412201,53.6696281433],"type":"Point"}
}