{
  "type": "Feature",
  "properties": {
    "iso:country":"DE",
    "sg:address":"Hauptstr. 7",
    "sg:city":"Gro\u00dfpostwitz",
    "sg:phone":"+49 35938/50018",
    "sg:postcode":"02692",
    "sg:province":"Sachsen",
    "wof:name":"Doris Wetzko",
    "wof:placetype":"venue"
},
  "geometry": {"coordinates":[14.4402399063,51.1204528809],"type":"Point"}
}