{
  "type": "Feature",
  "properties": {
    "iso:country":"DE",
    "sg:address":"Dorfstr. 12",
    "sg:city":"Winkelstedt",
    "sg:phone":"+49 39081/273",
    "sg:postcode":"39624",
    "sg:province":"Sachsen-Anhalt",
    "wof:name":"Wernecke Tiefbau Gmbh",
    "wof:placetype":"venue"
},
  "geometry": {"coordinates":[11.3174285889,52.6781845093],"type":"Point"}
}