{
  "type": "Feature",
  "properties": {
    "iso:country":"DE",
    "sg:address":"Gutower Str. 12",
    "sg:city":"Damshagen",
    "sg:phone":"+49 38825/22913",
    "sg:postcode":"23948",
    "sg:province":"Mecklenburg-Vorpommern",
    "wof:name":"C. J\u00e4ger",
    "wof:placetype":"venue"
},
  "geometry": {"coordinates":[11.1514472961,53.9231910706],"type":"Point"}
}