{
  "type": "Feature",
  "properties": {
    "iso:country":"DE",
    "sg:address":"Schertlinstra\u00dfe 21",
    "sg:city":"Augsburg",
    "sg:phone":"+49 821",
    "sg:postcode":"86159",
    "sg:province":"Bayern",
    "wof:name":"V.g.i. - Vertriebsgesellschaft Internet Mbh",
    "wof:placetype":"venue"
},
  "geometry": {"coordinates":[10.895395,48.353123],"type":"Point"}
}