{
  "type": "Feature",
  "properties": {
    "iso:country":"DE",
    "sg:address":"Am Zipfelbach 10",
    "sg:city":"Waiblingen",
    "sg:phone":"+49 7146/42119",
    "sg:postcode":"71336",
    "sg:province":"Baden-W\u00fcrttemberg",
    "wof:name":"Musikverein",
    "wof:placetype":"venue"
},
  "geometry": {"coordinates":[9.3109741211,48.8900871277],"type":"Point"}
}