{
  "type": "Feature",
  "properties": {
    "iso:country":"DE",
    "sg:address":"Bachstr. 40",
    "sg:city":"Langenfeld",
    "sg:phone":"+49 2173/76777",
    "sg:postcode":"40764",
    "sg:province":"Nordrhein-Westfalen",
    "wof:name":"Gottfried Wagner Heilpraktiker",
    "wof:placetype":"venue"
},
  "geometry": {"coordinates":[6.9451889992,51.109413147],"type":"Point"}
}