{
  "type": "Feature",
  "properties": {
    "iso:country":"DE",
    "sg:address":"Sterndamm 53",
    "sg:city":"Berlin",
    "sg:phone":"+49 30/6312002",
    "sg:postcode":"12487",
    "sg:province":"Berlin",
    "wof:name":"G\u00fcnter Wernicke Gmbh",
    "wof:placetype":"venue"
},
  "geometry": {"coordinates":[13.5077266693,52.4485549927],"type":"Point"}
}