{
  "type": "Feature",
  "properties": {
    "iso:country":"DE",
    "sg:address":"Querstr. 31",
    "sg:city":"D\u00f6brichau",
    "sg:phone":"+49 35365/35308",
    "sg:postcode":"04886",
    "sg:province":"Sachsen",
    "wof:name":"Ingo Rathsack",
    "wof:placetype":"venue"
},
  "geometry": {"coordinates":[13.134251,51.595184],"type":"Point"}
}