{
  "type": "Feature",
  "properties": {
    "iso:country":"DE",
    "sg:address":"Portweg 24",
    "sg:city":"Osnabr\u00fcck",
    "sg:phone":"+49 541/126061",
    "sg:postcode":"49076",
    "sg:province":"Niedersachsen",
    "wof:name":"Alfred Walle Elektroinstallation",
    "wof:placetype":"venue"
},
  "geometry": {"coordinates":[7.985948,52.293667],"type":"Point"}
}