{
  "type": "Feature",
  "properties": {
    "iso:country":"DE",
    "sg:address":"Untere Breite Str. 39",
    "sg:city":"Ravensburg",
    "sg:phone":"+49 751/31888",
    "sg:postcode":"88212",
    "sg:province":"Baden-W\u00fcrttemberg",
    "wof:name":"Strauss Gmbh & Co. Kg",
    "wof:placetype":"venue"
},
  "geometry": {"coordinates":[9.610449791,47.7830047607],"type":"Point"}
}