{
  "type": "Feature",
  "properties": {
    "iso:country":"DE",
    "sg:address":"Centroall. 283",
    "sg:city":"Oberhausen",
    "sg:phone":"+49 208/6254320",
    "sg:postcode":"46047",
    "sg:province":"Nordrhein-Westfalen",
    "wof:name":"Iko-minerals Gmbh",
    "wof:placetype":"venue"
},
  "geometry": {"coordinates":[6.87923,51.48785],"type":"Point"}
}