{
  "type": "Feature",
  "properties": {
    "iso:country":"DE",
    "sg:address":"Beselerallee 69a",
    "sg:city":"Kiel",
    "sg:phone":"+49 431/5789979",
    "sg:postcode":"24105",
    "sg:province":"Schleswig-Holstein",
    "wof:name":"Dr Carsten Heidemann Rechtsanwalt",
    "wof:placetype":"venue"
},
  "geometry": {"coordinates":[10.1324977875,54.3364334106],"type":"Point"}
}