{
  "type": "Feature",
  "properties": {
    "iso:country":"DE",
    "sg:address":"Nordseestr. 6",
    "sg:city":"Wittmund",
    "sg:phone":"+49 4464/303",
    "sg:postcode":"26409",
    "sg:province":"Niedersachsen",
    "wof:name":"Pension I. Knauer",
    "wof:placetype":"venue"
},
  "geometry": {"coordinates":[7.8028430939,53.6955299377],"type":"Point"}
}