{
  "type": "Feature",
  "properties": {
    "iso:country":"DE",
    "sg:address":"Altenessener Str. 374",
    "sg:city":"Essen",
    "sg:phone":"+49 201/340114",
    "sg:postcode":"45326",
    "sg:province":"Nordrhein-Westfalen",
    "wof:name":"Ludwig Peters",
    "wof:placetype":"venue"
},
  "geometry": {"coordinates":[7.008375,51.496273],"type":"Point"}
}