{
  "type": "Feature",
  "properties": {
    "iso:country":"DE",
    "sg:address":"Heidend 24",
    "sg:city":"Schwalmtal",
    "sg:phone":"+49 4921/631699",
    "sg:postcode":"41366",
    "sg:province":"Nordrhein-Westfalen",
    "wof:name":"Uwe Hein Transport- U. Speditionsunternehmen Ohg",
    "wof:placetype":"venue"
},
  "geometry": {"coordinates":[6.2611098289,51.2615394592],"type":"Point"}
}