{
  "type": "Feature",
  "properties": {
    "iso:country":"DE",
    "sg:address":"Bornheimer Landwehr 50",
    "sg:city":"Frankfurt",
    "sg:phone":"+49 69/444747",
    "sg:postcode":"60385",
    "sg:province":"Hessen",
    "wof:name":"Eva-maria Lauter",
    "wof:placetype":"venue"
},
  "geometry": {"coordinates":[8.7092170715,50.1225318909],"type":"Point"}
}