{
  "type": "Feature",
  "properties": {
    "iso:country":"DE",
    "sg:address":"Potshauser Str 12",
    "sg:city":"Solingen",
    "sg:phone":"+49 212/2541610",
    "sg:postcode":"42651",
    "sg:province":"Nordrhein-Westfalen",
    "wof:name":"Wingenbach & Piekhardt Gmbh",
    "wof:placetype":"venue"
},
  "geometry": {"coordinates":[7.089957,51.177856],"type":"Point"}
}