{
  "type": "Feature",
  "properties": {
    "iso:country":"DE",
    "sg:address":"Carl-Schurz-Str. 68",
    "sg:city":"Erftstadt",
    "sg:phone":"+49 2235/45565",
    "sg:postcode":"50374",
    "sg:province":"Nordrhein-Westfalen",
    "wof:name":"Ristorante Pizzeria Toto",
    "wof:placetype":"venue"
},
  "geometry": {"coordinates":[6.814991951,50.8149147034],"type":"Point"}
}