{
  "type": "Feature",
  "properties": {
    "iso:country":"DE",
    "sg:address":"Roermonder Str. 12",
    "sg:city":"H\u00fcckelhoven",
    "sg:phone":"+49 2433/4850",
    "sg:postcode":"41836",
    "sg:province":"Nordrhein-Westfalen",
    "wof:name":"Erna Noelte Hanolith Betonsteinwerk",
    "wof:placetype":"venue"
},
  "geometry": {"coordinates":[6.2187662125,51.0519485474],"type":"Point"}
}