{
  "type": "Feature",
  "properties": {
    "iso:country":"DE",
    "sg:address":"Horstlooge 15",
    "sg:city":"Hamburg",
    "sg:phone":"+49 40/6031326",
    "sg:postcode":"22359",
    "sg:province":"Hamburg",
    "wof:name":"Ursula Moik",
    "wof:placetype":"venue"
},
  "geometry": {"coordinates":[10.1561317444,53.6572952271],"type":"Point"}
}