{
  "type": "Feature",
  "properties": {
    "iso:country":"DE",
    "sg:address":"Stift 27",
    "sg:city":"Tecklenburg",
    "sg:phone":"+49 5481/3623",
    "sg:postcode":"49545",
    "sg:province":"Nordrhein-Westfalen",
    "wof:name":"Helmut Rogowsky Textilien",
    "wof:placetype":"venue"
},
  "geometry": {"coordinates":[7.8846859932,52.2143096924],"type":"Point"}
}