{
  "type": "Feature",
  "properties": {
    "iso:country":"DE",
    "sg:address":"L\u00fcneburger Str. 65",
    "sg:city":"Winsen",
    "sg:phone":"+49 4171/3211",
    "sg:postcode":"21423",
    "sg:province":"Niedersachsen",
    "wof:name":"Hausverwaltung Vollbrecht Inh. Silke Schauer E. K.",
    "wof:placetype":"venue"
},
  "geometry": {"coordinates":[10.2149648666,53.354724884],"type":"Point"}
}