{
  "type": "Feature",
  "properties": {
    "iso:country":"DE",
    "sg:address":"S\u00fcdstr. 4",
    "sg:city":"Neuferchau",
    "sg:phone":"+49 39008/375",
    "sg:postcode":"38486",
    "sg:province":"Sachsen-Anhalt",
    "wof:name":"Hans-j\u00fcrgen L\u00fcder",
    "wof:placetype":"venue"
},
  "geometry": {"coordinates":[11.066675,52.573151],"type":"Point"}
}