{
  "type": "Feature",
  "properties": {
    "iso:country":"DE",
    "sg:address":"Gartenstr. 7",
    "sg:city":"Schramberg",
    "sg:phone":"+49 7422/96222",
    "sg:postcode":"78713",
    "sg:province":"Baden-W\u00fcrttemberg",
    "wof:name":"Dr. Med. Ulrich Knebel",
    "wof:placetype":"venue"
},
  "geometry": {"coordinates":[8.4195308685,48.225528717],"type":"Point"}
}