{
  "type": "Feature",
  "properties": {
    "iso:country":"DE",
    "sg:address":"Wilhelmstr. 47",
    "sg:city":"Hamm",
    "sg:phone":"+49 2381/430890",
    "sg:postcode":"59067",
    "sg:province":"Nordrhein-Westfalen",
    "wof:name":"Songuel Bahcekapili",
    "wof:placetype":"venue"
},
  "geometry": {"coordinates":[7.8022770882,51.6728248596],"type":"Point"}
}