{
  "type": "Feature",
  "properties": {
    "iso:country":"DE",
    "sg:address":"S\u00fc\u00dfenborner Weg 43",
    "sg:city":"Kromsdorf",
    "sg:phone":"+49 3643/426430",
    "sg:postcode":"99441",
    "sg:province":"Th\u00fcringen",
    "wof:name":"M. Unrein",
    "wof:placetype":"venue"
},
  "geometry": {"coordinates":[11.3782043457,50.9961967468],"type":"Point"}
}