{
  "type": "Feature",
  "properties": {
    "iso:country":"DE",
    "sg:address":"Gauthierstra\u00dfe 45",
    "sg:city":"Bad Wildbad",
    "sg:phone":"+49 7231/313399",
    "sg:postcode":"75323",
    "sg:province":"Baden-W\u00fcrttemberg",
    "wof:name":"Webdesign Von Ihrem Internet-partner Web-z",
    "wof:placetype":"venue"
},
  "geometry": {"coordinates":[8.58629,48.77441],"type":"Point"}
}