{
  "type": "Feature",
  "properties": {
    "iso:country":"DE",
    "sg:address":"Lange Str. 34",
    "sg:city":"Grimma",
    "sg:phone":"+49 3437/919831",
    "sg:postcode":"04668",
    "sg:province":"Sachsen",
    "wof:name":"Ines Richter",
    "wof:placetype":"venue"
},
  "geometry": {"coordinates":[12.727152,51.234516],"type":"Point"}
}