{
  "type": "Feature",
  "properties": {
    "iso:country":"DE",
    "sg:address":"Br\u00fcsseler Platz 6",
    "sg:city":"K\u00f6ln",
    "sg:phone":"+49 221/511859",
    "sg:postcode":"50672",
    "sg:province":"Nordrhein-Westfalen",
    "wof:name":"Eiscafe Forum",
    "wof:placetype":"venue"
},
  "geometry": {"coordinates":[6.935041,50.938732],"type":"Point"}
}