{
  "type": "Feature",
  "properties": {
    "iso:country":"DE",
    "sg:address":"Berliner Str. 24",
    "sg:city":"Langenselbold",
    "sg:phone":"+49 6184/2713",
    "sg:postcode":"63505",
    "sg:province":"Hessen",
    "wof:name":"Friedh. Benz",
    "wof:placetype":"venue"
},
  "geometry": {"coordinates":[9.057636261,50.1796417236],"type":"Point"}
}