{
  "type": "Feature",
  "properties": {
    "iso:country":"DE",
    "sg:address":"Bahnhofstr. 7",
    "sg:city":"Kordel",
    "sg:phone":"+49 6505/95088",
    "sg:postcode":"54306",
    "sg:province":"Rheinland-Pfalz",
    "wof:name":"D. Schaan",
    "wof:placetype":"venue"
},
  "geometry": {"coordinates":[6.6339578629,49.8382453918],"type":"Point"}
}