{
  "type": "Feature",
  "properties": {
    "iso:country":"DE",
    "sg:address":"Hauptstr. 35",
    "sg:city":"Haimhausen",
    "sg:phone":"+49 8133/711",
    "sg:postcode":"85778",
    "sg:province":"Bayern",
    "wof:name":"O. Danhofer",
    "wof:placetype":"venue"
},
  "geometry": {"coordinates":[11.5545120239,48.317237854],"type":"Point"}
}