{
  "type": "Feature",
  "properties": {
    "iso:country":"DE",
    "sg:address":"Richard-Strauss-Str. 27",
    "sg:city":"M\u00fcnchen",
    "sg:phone":"+49 89/52310910",
    "sg:postcode":"81677",
    "sg:province":"Bayern",
    "wof:name":"Fischer",
    "wof:placetype":"venue"
},
  "geometry": {"coordinates":[11.614918,48.141598],"type":"Point"}
}