{
  "type": "Feature",
  "properties": {
    "iso:country":"DE",
    "sg:address":"Hirzgasse 1",
    "sg:city":"M\u00fccke",
    "sg:phone":"+49 6401/7636",
    "sg:postcode":"35325",
    "sg:province":"Hessen",
    "wof:name":"W. Hessler",
    "wof:placetype":"venue"
},
  "geometry": {"coordinates":[8.9780130386,50.6357727051],"type":"Point"}
}