{
  "type": "Feature",
  "properties": {
    "iso:country":"DE",
    "sg:address":"Flugplatzstr.",
    "sg:city":"Nordhorn",
    "sg:phone":"+49 5921/36733",
    "sg:postcode":"48531",
    "sg:province":"Niedersachsen",
    "wof:name":"Flugplatz Nordhorn-lingen Gmbh",
    "wof:placetype":"venue"
},
  "geometry": {"coordinates":[7.16248703,52.4579124451],"type":"Point"}
}