{
  "type": "Feature",
  "properties": {
    "iso:country":"DE",
    "sg:address":"Alte Landstr. 8",
    "sg:city":"Ottobrunn",
    "sg:phone":"+49 89/6096572",
    "sg:postcode":"85521",
    "sg:province":"Bayern",
    "wof:name":"Br\u00fcckner Gmbh",
    "wof:placetype":"venue"
},
  "geometry": {"coordinates":[11.655506134,48.0722618103],"type":"Point"}
}