{
  "type": "Feature",
  "properties": {
    "iso:country":"DE",
    "sg:address":"Dotzheimer Str. 72",
    "sg:city":"Wiesbaden",
    "sg:phone":"+49 611/47474",
    "sg:postcode":"65197",
    "sg:province":"Hessen",
    "wof:name":"Klosterhof",
    "wof:placetype":"venue"
},
  "geometry": {"coordinates":[8.226348877,50.0778236389],"type":"Point"}
}