{
  "type": "Feature",
  "properties": {
    "iso:country":"DE",
    "sg:address":"Stuttgarter Str. 61",
    "sg:city":"Aalen",
    "sg:phone":"+49 7361/61176",
    "sg:postcode":"73430",
    "sg:province":"Baden-W\u00fcrttemberg",
    "wof:name":"Forelle",
    "wof:placetype":"venue"
},
  "geometry": {"coordinates":[10.0902690887,48.8337898254],"type":"Point"}
}