{
  "type": "Feature",
  "properties": {
    "iso:country":"DE",
    "sg:address":"34326",
    "sg:city":"Morschen",
    "sg:phone":"+49 5664/354",
    "sg:postcode":"34326",
    "sg:province":"Hessen",
    "wof:name":"Klostersch\u00e4nke",
    "wof:placetype":"venue"
},
  "geometry": {"coordinates":[9.6170501709,51.0600318909],"type":"Point"}
}