{
  "type": "Feature",
  "properties": {
    "iso:country":"DE",
    "sg:address":"Hagener Str. 293",
    "sg:city":"Gevelsberg",
    "sg:phone":"+49 2332/60267",
    "sg:postcode":"58285",
    "sg:province":"Nordrhein-Westfalen",
    "wof:name":"W. Marcegalia",
    "wof:placetype":"venue"
},
  "geometry": {"coordinates":[7.374792099,51.3322067261],"type":"Point"}
}