{
  "type": "Feature",
  "properties": {
    "iso:country":"DE",
    "sg:address":"Oderberger Str. 20",
    "sg:city":"Berlin",
    "sg:postcode":"10435",
    "sg:province":"Berlin",
    "wof:name":"1000 Digital - Ges. F\u00fcr Multi- Media- Und E-commerce Mbh",
    "wof:placetype":"venue"
},
  "geometry": {"coordinates":[13.4071731567,52.5396347046],"type":"Point"}
}