{
  "type": "Feature",
  "properties": {
    "iso:country":"DE",
    "sg:address":"Oldenburger Str. 23 A",
    "sg:city":"Nordenham",
    "sg:phone":"+49 4731/6366",
    "sg:postcode":"26954",
    "sg:province":"Niedersachsen",
    "wof:name":"Werner Fuchs Masseur",
    "wof:placetype":"venue"
},
  "geometry": {"coordinates":[8.466725,53.489693],"type":"Point"}
}