{
  "type": "Feature",
  "properties": {
    "iso:country":"DE",
    "sg:address":"B\u00f6ningergasse 7",
    "sg:city":"Br\u00fchl",
    "sg:postcode":"50321",
    "sg:province":"Nordrhein-Westfalen",
    "wof:name":"Verein Griechischer Eltern Und Erziehungsber. Aristoteles",
    "wof:placetype":"venue"
},
  "geometry": {"coordinates":[6.9035749435,50.8261985779],"type":"Point"}
}