{
  "type": "Feature",
  "properties": {
    "iso:country":"DE",
    "sg:address":"Neufferstr. 14",
    "sg:city":"Speyer",
    "sg:phone":"+49 6232/79208",
    "sg:postcode":"67346",
    "sg:province":"Rheinland-Pfalz",
    "wof:name":"D\u00f6lling Und K\u00fchn",
    "wof:placetype":"venue"
},
  "geometry": {"coordinates":[8.4333162308,49.3138465881],"type":"Point"}
}