{
  "type": "Feature",
  "properties": {
    "iso:country":"DE",
    "sg:address":"Pfl\u00fcmerweg 7",
    "sg:city":"Hameln",
    "sg:phone":"+49 5151/65783",
    "sg:postcode":"31787",
    "sg:province":"Niedersachsen",
    "wof:name":"Fliesen Tack Gmbh Kg",
    "wof:placetype":"venue"
},
  "geometry": {"coordinates":[9.3482913971,52.0994758606],"type":"Point"}
}