{
  "type": "Feature",
  "properties": {
    "iso:country":"DE",
    "sg:address":"Cunsdorfer Str. 67c",
    "sg:city":"Reichenbach",
    "sg:phone":"+49 3765/16062",
    "sg:postcode":"08468",
    "sg:province":"Sachsen",
    "wof:name":"Thomas Schmidt",
    "wof:placetype":"venue"
},
  "geometry": {"coordinates":[12.3579301834,50.6177520752],"type":"Point"}
}