{
  "type": "Feature",
  "properties": {
    "iso:country":"DE",
    "sg:address":"Karl-Huber-Str. 7",
    "sg:city":"Hahnbach",
    "sg:phone":"+49 9664/225",
    "sg:postcode":"92256",
    "sg:province":"Bayern",
    "wof:name":"Heinrich Krusche Ingenieur",
    "wof:placetype":"venue"
},
  "geometry": {"coordinates":[11.8083810806,49.5380821228],"type":"Point"}
}