{
  "type": "Feature",
  "properties": {
    "iso:country":"DE",
    "sg:address":"Lehenstr. 31",
    "sg:city":"Stuttgart",
    "sg:phone":"+49 711/6402061",
    "sg:postcode":"70180",
    "sg:province":"Baden-W\u00fcrttemberg",
    "wof:name":"Red. Lr Literatur-report Verband Kath. Verleger",
    "wof:placetype":"venue"
},
  "geometry": {"coordinates":[9.1721963882,48.7617607117],"type":"Point"}
}