{
  "type": "Feature",
  "properties": {
    "iso:country":"DE",
    "sg:address":"Landshuter Str. 16",
    "sg:city":"Rottenburg",
    "sg:phone":"+49 8781/92442",
    "sg:postcode":"84056",
    "sg:province":"Bayern",
    "wof:name":"Musikkneipe Namenlos",
    "wof:placetype":"venue"
},
  "geometry": {"coordinates":[12.0260047913,48.7016906738],"type":"Point"}
}