{
  "type": "Feature",
  "properties": {
    "iso:country":"DE",
    "sg:address":"Theodor-Heuss-Str. 20",
    "sg:city":"Ha\u00dfmersheim",
    "sg:phone":"+49 6266/95000",
    "sg:postcode":"74855",
    "sg:province":"Baden-W\u00fcrttemberg",
    "wof:name":"Rolf Frey",
    "wof:placetype":"venue"
},
  "geometry": {"coordinates":[9.1498746872,49.3016929626],"type":"Point"}
}