{
  "type": "Feature",
  "properties": {
    "iso:country":"DE",
    "sg:address":"Hermann-Veit-Str. 7",
    "sg:city":"Karlsruhe",
    "sg:phone":"+49 721/814020",
    "sg:postcode":"76135",
    "sg:province":"Baden-W\u00fcrttemberg",
    "wof:name":"Sportkreis Karlsruhe",
    "wof:placetype":"venue"
},
  "geometry": {"coordinates":[8.3773460388,48.9970092773],"type":"Point"}
}