{
  "type": "Feature",
  "properties": {
    "iso:country":"DE",
    "sg:address":"Von-Einem-Stra\u00dfe 31",
    "sg:city":"Essen",
    "sg:phone":"+49 201/8777330",
    "sg:postcode":"45130",
    "sg:province":"Nordrhein-Westfalen",
    "wof:name":"R\u00fcw\u00e4rts Online: Infos F\u00fcr Essen R\u00fcttenscheid",
    "wof:placetype":"venue"
},
  "geometry": {"coordinates":[7.018081,51.439548],"type":"Point"}
}