{
  "type": "Feature",
  "properties": {
    "iso:country":"DE",
    "sg:address":"Eppendorfer Weg 219",
    "sg:city":"Hamburg",
    "sg:phone":"+49 40/4206100",
    "sg:postcode":"20253",
    "sg:province":"Hamburg",
    "wof:name":"Ab. Schnitt",
    "wof:placetype":"venue"
},
  "geometry": {"coordinates":[9.971452713,53.5819396973],"type":"Point"}
}