{
  "type": "Feature",
  "properties": {
    "iso:country":"DE",
    "sg:address":"Kleink\u00fchnauer Str. 48",
    "sg:city":"Dessau",
    "sg:phone":"+49 340/613604",
    "sg:postcode":"06846",
    "sg:province":"Sachsen-Anhalt",
    "wof:name":"Sandner Dachbau Gmbh",
    "wof:placetype":"venue"
},
  "geometry": {"coordinates":[12.176725,51.8461],"type":"Point"}
}