{
  "type": "Feature",
  "properties": {
    "iso:country":"DE",
    "sg:address":"Buchenauer Str. 28",
    "sg:city":"Biedenkopf",
    "sg:phone":"+49 6461/5258",
    "sg:postcode":"35216",
    "sg:province":"Hessen",
    "wof:name":"K. H. Sauerwald",
    "wof:placetype":"venue"
},
  "geometry": {"coordinates":[8.561516,50.875153],"type":"Point"}
}