{
  "type": "Feature",
  "properties": {
    "iso:country":"DE",
    "sg:address":"Bahnhofstr. 34",
    "sg:city":"Waiblingen",
    "sg:phone":"+49 7151/59777",
    "sg:postcode":"71332",
    "sg:province":"Baden-W\u00fcrttemberg",
    "wof:name":"Dietrich Eckhardt",
    "wof:placetype":"venue"
},
  "geometry": {"coordinates":[9.30937,48.829578],"type":"Point"}
}