{
  "type": "Feature",
  "properties": {
    "iso:country":"DE",
    "sg:address":"Scheffelstr. 20",
    "sg:city":"Zwickau",
    "sg:phone":"+49 375/475631",
    "sg:postcode":"08066",
    "sg:province":"Sachsen",
    "wof:name":"Raimund Gro\u00df Ingenieur",
    "wof:placetype":"venue"
},
  "geometry": {"coordinates":[12.5000228882,50.7302627563],"type":"Point"}
}