{
  "type": "Feature",
  "properties": {
    "iso:country":"DE",
    "sg:address":"Dietenh\u00e4user Str. 9",
    "sg:city":"Weilm\u00fcnster",
    "sg:phone":"+49 6472/91680",
    "sg:postcode":"35789",
    "sg:province":"Hessen",
    "wof:name":"Dienst Und R\u00fchl Rechtsanw\u00e4lte Und Notare",
    "wof:placetype":"venue"
},
  "geometry": {"coordinates":[8.3774528503,50.4320983887],"type":"Point"}
}