{
  "type": "Feature",
  "properties": {
    "iso:country":"DE",
    "sg:address":"Kortumstr. 91",
    "sg:city":"Bochum",
    "sg:postcode":"44787",
    "sg:province":"Nordrhein-Westfalen",
    "wof:name":"Premion Ag",
    "wof:placetype":"venue"
},
  "geometry": {"coordinates":[7.217031002,51.4825325012],"type":"Point"}
}