{
  "type": "Feature",
  "properties": {
    "iso:country":"DE",
    "sg:address":"Friedhofstr. 6",
    "sg:city":"Leipzig",
    "sg:phone":"+49 34297/45003",
    "sg:postcode":"04288",
    "sg:province":"Sachsen",
    "wof:name":"Roth-bau",
    "wof:placetype":"venue"
},
  "geometry": {"coordinates":[12.4605731964,51.2816505432],"type":"Point"}
}