{
  "type": "Feature",
  "properties": {
    "iso:country":"DE",
    "sg:address":"Rabenecksheide 10",
    "sg:city":"Bielefeld",
    "sg:phone":"+49 521/48245",
    "sg:postcode":"33649",
    "sg:province":"Nordrhein-Westfalen",
    "wof:name":"Max Groetschel",
    "wof:placetype":"venue"
},
  "geometry": {"coordinates":[8.4556,51.968613],"type":"Point"}
}