{
  "type": "Feature",
  "properties": {
    "iso:country":"DE",
    "sg:address":"Feuerbachstr 4",
    "sg:city":"Leipzig",
    "sg:phone":"+49 341/589220",
    "sg:postcode":"04105",
    "sg:province":"Sachsen",
    "wof:name":"Werbeagentur Feuerbach 4",
    "wof:placetype":"venue"
},
  "geometry": {"coordinates":[12.359013,51.34671],"type":"Point"}
}