{
  "type": "Feature",
  "properties": {
    "iso:country":"DE",
    "sg:address":"Waldstr. 17",
    "sg:city":"Emskirchen",
    "sg:phone":"+49 9104/588",
    "sg:postcode":"91448",
    "sg:province":"Bayern",
    "wof:name":"Speer Verwaltungs Gmbh",
    "wof:placetype":"venue"
},
  "geometry": {"coordinates":[10.7019472122,49.5546760559],"type":"Point"}
}