{
  "type": "Feature",
  "properties": {
    "iso:country":"DE",
    "sg:address":"Ulmenallee 5",
    "sg:city":"G\u00f6hren",
    "sg:phone":"+49 38308/5430",
    "sg:postcode":"18586",
    "sg:province":"Mecklenburg-Vorpommern",
    "wof:name":"Flair-hotel Albatros",
    "wof:placetype":"venue"
},
  "geometry": {"coordinates":[13.7357721329,54.3441200256],"type":"Point"}
}