{
  "type": "Feature",
  "properties": {
    "iso:country":"DE",
    "sg:address":"Malmedyer Str. 17a",
    "sg:city":"Hannover",
    "sg:phone":"+49 511/841147",
    "sg:postcode":"30519",
    "sg:province":"Niedersachsen",
    "wof:name":"Hans Hermann Cronimus",
    "wof:placetype":"venue"
},
  "geometry": {"coordinates":[9.78134,52.342079],"type":"Point"}
}