{
  "type": "Feature",
  "properties": {
    "iso:country":"DE",
    "sg:address":"Poststr. 20",
    "sg:city":"Grevenbroich",
    "sg:phone":"+49 2181/74546",
    "sg:postcode":"41516",
    "sg:province":"Nordrhein-Westfalen",
    "wof:name":"Frostis",
    "wof:placetype":"venue"
},
  "geometry": {"coordinates":[6.624709,51.108814],"type":"Point"}
}