{
  "type": "Feature",
  "properties": {
    "iso:country":"DE",
    "sg:address":"Paschenburg 12",
    "sg:city":"Barenburg",
    "sg:phone":"+49 4273/208",
    "sg:postcode":"27245",
    "sg:province":"Niedersachsen",
    "wof:name":"Hermann Symkenberg",
    "wof:placetype":"venue"
},
  "geometry": {"coordinates":[8.785255,52.624722],"type":"Point"}
}