{
  "type": "Feature",
  "properties": {
    "iso:country":"DE",
    "sg:address":"Beestener Str. 7",
    "sg:city":"L\u00fcnne",
    "sg:phone":"+49 5906/7200",
    "sg:postcode":"48480",
    "sg:province":"Niedersachsen",
    "wof:name":"Bernhard Schr\u00f6der",
    "wof:placetype":"venue"
},
  "geometry": {"coordinates":[7.434688,52.422287],"type":"Point"}
}