{
  "type": "Feature",
  "properties": {
    "iso:country":"DE",
    "sg:address":"Kreuzstr. 19",
    "sg:city":"Triberg",
    "sg:phone":"+49 7722/4557",
    "sg:postcode":"78098",
    "sg:province":"Baden-W\u00fcrttemberg",
    "wof:name":"Christa Greguletz-moser",
    "wof:placetype":"venue"
},
  "geometry": {"coordinates":[8.23024,48.12965],"type":"Point"}
}