{
  "type": "Feature",
  "properties": {
    "iso:country":"DE",
    "sg:address":"L\u00e4rchenstr. 5",
    "sg:city":"Frankfurt",
    "sg:phone":"+49 69/384300",
    "sg:postcode":"65933",
    "sg:province":"Hessen",
    "wof:name":"Vladimir Cesljar Gmbh",
    "wof:placetype":"venue"
},
  "geometry": {"coordinates":[8.6064748764,50.0963592529],"type":"Point"}
}