{
  "type": "Feature",
  "properties": {
    "iso:country":"DE",
    "sg:address":"Burgstr. 12",
    "sg:city":"Altenburg",
    "sg:phone":"+49 3447/315177",
    "sg:postcode":"04600",
    "sg:province":"Th\u00fcringen",
    "wof:name":"Pagel Und Schilder Rechtsanw\u00e4lte",
    "wof:placetype":"venue"
},
  "geometry": {"coordinates":[12.4368371964,50.9865951538],"type":"Point"}
}