{
  "type": "Feature",
  "properties": {
    "iso:country":"DE",
    "sg:address":"Kirchweg 6",
    "sg:city":"Wiesent",
    "sg:phone":"+49 9482/1706",
    "sg:postcode":"93109",
    "sg:province":"Bayern",
    "wof:name":"Kath. Pfarramt Mari\u00e4 Himmelfahrt",
    "wof:placetype":"venue"
},
  "geometry": {"coordinates":[12.3780899048,49.007358551],"type":"Point"}
}