{
  "type": "Feature",
  "properties": {
    "iso:country":"DE",
    "sg:address":"Mozartstr. 27",
    "sg:city":"Bonn",
    "sg:postcode":"53115",
    "sg:province":"Nordrhein-Westfalen",
    "wof:name":"Vk Vereinigte Kieswerke Gmbh",
    "wof:placetype":"venue"
},
  "geometry": {"coordinates":[7.0885248184,50.7331733704],"type":"Point"}
}