{
  "type": "Feature",
  "properties": {
    "iso:country":"DE",
    "sg:address":"Am Rathaus 1a",
    "sg:city":"Fredersdorf",
    "sg:phone":"+49 33439/337",
    "sg:postcode":"15370",
    "sg:province":"Brandenburg",
    "wof:name":"Gvvs Grundst\u00fccks- Verwaltungs Gmbh",
    "wof:placetype":"venue"
},
  "geometry": {"coordinates":[13.7561836243,52.5282936096],"type":"Point"}
}