{
  "type": "Feature",
  "properties": {
    "iso:country":"DE",
    "sg:address":"Berliner Str. 7a",
    "sg:city":"Hemsbach",
    "sg:phone":"+49 6201/7685",
    "sg:postcode":"69502",
    "sg:province":"Baden-W\u00fcrttemberg",
    "wof:name":"A. A. Hilsberg Gmbh",
    "wof:placetype":"venue"
},
  "geometry": {"coordinates":[8.6453647614,49.5951690674],"type":"Point"}
}