{
  "type": "Feature",
  "properties": {
    "iso:country":"DE",
    "sg:address":"F\u00fcrther Str. 15",
    "sg:city":"M\u00f6rlenbach",
    "sg:phone":"+49 6209/4243",
    "sg:postcode":"69509",
    "sg:province":"Hessen",
    "wof:name":"Peter Sch\u00fctz",
    "wof:placetype":"venue"
},
  "geometry": {"coordinates":[8.7380504608,49.5988540649],"type":"Point"}
}