{
  "type": "Feature",
  "properties": {
    "iso:country":"DE",
    "sg:address":"Neue Bahnhofstr. 63",
    "sg:city":"St. Ingbert",
    "sg:phone":"+49 6894/870893",
    "sg:postcode":"66386",
    "sg:province":"Saarland",
    "wof:name":"Gd Express Worldwide Gmbh",
    "wof:placetype":"venue"
},
  "geometry": {"coordinates":[7.10914,49.273788],"type":"Point"}
}