{
  "type": "Feature",
  "properties": {
    "iso:country":"DE",
    "sg:address":"Alte Zollstr. 38",
    "sg:city":"Niederkr\u00fcchten",
    "sg:phone":"+49 2163/8429",
    "sg:postcode":"41372",
    "sg:province":"Nordrhein-Westfalen",
    "wof:name":"Tteguma Gmbh",
    "wof:placetype":"venue"
},
  "geometry": {"coordinates":[6.126242,51.215023],"type":"Point"}
}