{
  "type": "Feature",
  "properties": {
    "iso:country":"DE",
    "sg:address":"Am Bahndamm 34",
    "sg:city":"Ahaus",
    "sg:phone":"+49 2561/971816",
    "sg:postcode":"48683",
    "sg:province":"Nordrhein-Westfalen",
    "wof:name":"Haveloh Gmbh",
    "wof:placetype":"venue"
},
  "geometry": {"coordinates":[6.984925,52.105453],"type":"Point"}
}