{
  "type": "Feature",
  "properties": {
    "iso:country":"DE",
    "sg:address":"Alte R\u00f6merstr. 81 a",
    "sg:city":"K\u00f6ln",
    "sg:phone":"+49 221/7087197",
    "sg:postcode":"50769",
    "sg:province":"Nordrhein-Westfalen",
    "wof:name":"Nahtrans Transport Gmbh",
    "wof:placetype":"venue"
},
  "geometry": {"coordinates":[6.9402298927,51.0363197327],"type":"Point"}
}