{
  "type": "Feature",
  "properties": {
    "iso:country":"DE",
    "sg:address":"Raiffeisenstr. 6",
    "sg:city":"Rehling",
    "sg:phone":"+49 8237/364",
    "sg:postcode":"86508",
    "sg:province":"Bayern",
    "wof:name":"Martin Jakob",
    "wof:placetype":"venue"
},
  "geometry": {"coordinates":[10.932795,48.485058],"type":"Point"}
}