{
  "type": "Feature",
  "properties": {
    "iso:country":"DE",
    "sg:city":"Dresden",
    "sg:postcode":"01309",
    "sg:province":"Sachsen",
    "wof:name":"Sachsenhandball",
    "wof:placetype":"venue"
},
  "geometry": {"coordinates":[13.788579,51.046448],"type":"Point"}
}