{
  "type": "Feature",
  "properties": {
    "iso:country":"DE",
    "sg:address":"Wettersteinstr. 7",
    "sg:city":"Garmisch-Partenkirchen",
    "sg:phone":"+49 8821/93220",
    "sg:postcode":"82467",
    "sg:province":"Bayern",
    "wof:name":"Dr. Bollig Gmbh Steuerberatungsges.",
    "wof:placetype":"venue"
},
  "geometry": {"coordinates":[11.0992174149,47.4953613281],"type":"Point"}
}