{
  "type": "Feature",
  "properties": {
    "iso:country":"DE",
    "sg:address":"Nienhagener Str.",
    "sg:city":"Gr\u00f6ningen",
    "sg:phone":"+49 39403/9213",
    "sg:postcode":"39397",
    "sg:province":"Sachsen-Anhalt",
    "wof:name":"Betonkies Gr\u00f6ningen Gmbh & Co. Kg",
    "wof:placetype":"venue"
},
  "geometry": {"coordinates":[11.1787576675,51.9496688843],"type":"Point"}
}