{
  "type": "Feature",
  "properties": {
    "iso:country":"DE",
    "sg:address":"Georg-Benjamin-Str. 15",
    "sg:city":"Berlin",
    "sg:phone":"+49 30/9496071",
    "sg:postcode":"13125",
    "sg:province":"Berlin",
    "wof:name":"Dr. Med. Wolfgang R\u00fcchel",
    "wof:placetype":"venue"
},
  "geometry": {"coordinates":[13.499321,52.629364],"type":"Point"}
}