{
  "type": "Feature",
  "properties": {
    "iso:country":"DE",
    "sg:address":"Marktstr. 41",
    "sg:city":"Pritzwalk",
    "sg:phone":"+49 3395/2881",
    "sg:postcode":"16928",
    "sg:province":"Brandenburg",
    "wof:name":"Vivi-ann Fashion",
    "wof:placetype":"venue"
},
  "geometry": {"coordinates":[12.17609,53.149681],"type":"Point"}
}