{
  "type": "Feature",
  "properties": {
    "iso:country":"DE",
    "sg:address":"Obere Str. 28",
    "sg:city":"Schweinfurt",
    "sg:phone":"+49 9721/22858",
    "sg:postcode":"97421",
    "sg:province":"Bayern",
    "wof:name":"Bernhard Wansch",
    "wof:placetype":"venue"
},
  "geometry": {"coordinates":[10.233433,50.047195],"type":"Point"}
}