{
  "type": "Feature",
  "properties": {
    "iso:country":"DE",
    "sg:address":"Althausweg 48",
    "sg:city":"M\u00fcnster",
    "sg:phone":"+49 251/262330",
    "sg:postcode":"48159",
    "sg:province":"Nordrhein-Westfalen",
    "wof:name":"Christa Fugel Steuerberaterin",
    "wof:placetype":"venue"
},
  "geometry": {"coordinates":[7.6062498093,51.9906997681],"type":"Point"}
}