{
  "type": "Feature",
  "properties": {
    "iso:country":"DE",
    "sg:address":"Am Markt 18",
    "sg:city":"Castrop-Rauxel",
    "sg:phone":"+49 2305/922113",
    "sg:postcode":"44575",
    "sg:province":"Nordrhein-Westfalen",
    "wof:name":"Altstadt-apotheke Winfried Radinger E. Kfm.",
    "wof:placetype":"venue"
},
  "geometry": {"coordinates":[7.311068,51.547131],"type":"Point"}
}