{
  "type": "Feature",
  "properties": {
    "iso:country":"DE",
    "sg:address":"Elper Weg 70",
    "sg:city":"Recklinghausen",
    "sg:phone":"+49 2361/17037",
    "sg:postcode":"45657",
    "sg:province":"Nordrhein-Westfalen",
    "wof:name":"Ruth Jansen Gmbh",
    "wof:placetype":"venue"
},
  "geometry": {"coordinates":[7.18529,51.617668],"type":"Point"}
}