{
  "type": "Feature",
  "properties": {
    "iso:country":"DE",
    "sg:address":"Eschenstrutherstr. 2",
    "sg:city":"Kaufungen",
    "sg:phone":"+49 5605/9290556",
    "sg:postcode":"34260",
    "sg:province":"Hessen",
    "wof:name":"Aktivity.net - Wir F\u00f6rdern Ehrenamt",
    "wof:placetype":"venue"
},
  "geometry": {"coordinates":[9.617537,51.282684],"type":"Point"}
}