{
  "type": "Feature",
  "properties": {
    "iso:country":"DE",
    "sg:address":"Busdorfwall 39",
    "sg:city":"Paderborn",
    "sg:phone":"+49 5251/25486",
    "sg:postcode":"33098",
    "sg:province":"Nordrhein-Westfalen",
    "wof:name":"Bittermann Kunstmaler",
    "wof:placetype":"venue"
},
  "geometry": {"coordinates":[8.75204,51.718143],"type":"Point"}
}