{
  "type": "Feature",
  "properties": {
    "iso:country":"DE",
    "sg:address":"Hindenburgstr. 90",
    "sg:city":"Gingen",
    "sg:phone":"+49 7162/7253",
    "sg:postcode":"73333",
    "sg:province":"Baden-W\u00fcrttemberg",
    "wof:name":"Eberhard Renftle",
    "wof:placetype":"venue"
},
  "geometry": {"coordinates":[9.7780599594,48.6581726074],"type":"Point"}
}