{
  "type": "Feature",
  "properties": {
    "iso:country":"DE",
    "sg:address":"Spitalgasse 27",
    "sg:city":"Coburg",
    "sg:phone":"+49 9561/90389",
    "sg:postcode":"96450",
    "sg:province":"Bayern",
    "wof:name":"Willemer & Praue Das Photohaus",
    "wof:placetype":"venue"
},
  "geometry": {"coordinates":[10.9648790359,50.2598381042],"type":"Point"}
}