{
  "type": "Feature",
  "properties": {
    "iso:country":"DE",
    "sg:address":"Nu\u00dfbaumweg 4",
    "sg:city":"Taufkirchen",
    "sg:phone":"+49 89/6122725",
    "sg:postcode":"82024",
    "sg:province":"Bayern",
    "wof:name":"Heinz Gebhard Ingenieur",
    "wof:placetype":"venue"
},
  "geometry": {"coordinates":[11.5986118317,48.046672821],"type":"Point"}
}