{
  "type": "Feature",
  "properties": {
    "iso:country":"DE",
    "sg:address":"Ernst-Barlach-Str. 107",
    "sg:city":"Taucha",
    "sg:phone":"+49 34298/63720",
    "sg:postcode":"04425",
    "sg:province":"Sachsen",
    "wof:name":"Oekologische Produkte Und Produzenten",
    "wof:placetype":"venue"
},
  "geometry": {"coordinates":[12.490324,51.370167],"type":"Point"}
}