{
  "type": "Feature",
  "properties": {
    "iso:country":"DE",
    "sg:address":"Wilhelmstr. 75",
    "sg:city":"Aachen",
    "sg:phone":"+49 241/949290",
    "sg:postcode":"52070",
    "sg:province":"Nordrhein-Westfalen",
    "wof:name":"Pro Consult Gesellschaft F\u00fcr Verm\u00f6gensaufbau Mbh",
    "wof:placetype":"venue"
},
  "geometry": {"coordinates":[6.0958127975,50.7713165283],"type":"Point"}
}