{
  "type": "Feature",
  "properties": {
    "iso:country":"DE",
    "sg:address":"Markt 27",
    "sg:city":"Kalkar",
    "sg:phone":"+49 2824/2211",
    "sg:postcode":"47546",
    "sg:province":"Nordrhein-Westfalen",
    "wof:name":"Markt-apotheke",
    "wof:placetype":"venue"
},
  "geometry": {"coordinates":[6.292266,51.73827],"type":"Point"}
}