{
  "type": "Feature",
  "properties": {
    "iso:country":"DE",
    "sg:address":"Jupiterstr. 3",
    "sg:city":"Leipzig",
    "sg:phone":"+49 341/4127474",
    "sg:postcode":"04205",
    "sg:province":"Sachsen",
    "wof:name":"Helga Kleinschmidt",
    "wof:placetype":"venue"
},
  "geometry": {"coordinates":[12.273803,51.319275],"type":"Point"}
}