{
  "type": "Feature",
  "properties": {
    "iso:country":"DE",
    "sg:address":"Norderhafen 12",
    "sg:city":"Nordstrand",
    "sg:phone":"+49 4842/8512",
    "sg:postcode":"25845",
    "sg:province":"Schleswig-Holstein",
    "wof:name":"Pension Anneliese Andresen",
    "wof:placetype":"venue"
},
  "geometry": {"coordinates":[8.8313808441,54.5074272156],"type":"Point"}
}