{
  "type": "Feature",
  "properties": {
    "iso:country":"DE",
    "sg:address":"Karl-Marx-Str. 23",
    "sg:city":"Dresden",
    "sg:phone":"+49 4935/1887180",
    "sg:postcode":"01109",
    "sg:province":"Sachsen",
    "wof:name":"Siegle + Epple Gmbh & Co. Kg",
    "wof:placetype":"venue"
},
  "geometry": {"coordinates":[13.77343,51.113186],"type":"Point"}
}