{
  "type": "Feature",
  "properties": {
    "iso:country":"DE",
    "sg:address":"Hauptstr. 76",
    "sg:city":"Zell",
    "sg:phone":"+49 931/461243",
    "sg:postcode":"97299",
    "sg:province":"Bayern",
    "wof:name":"L. St\u00fctzel",
    "wof:placetype":"venue"
},
  "geometry": {"coordinates":[9.873535,49.807583],"type":"Point"}
}