{
  "type": "Feature",
  "properties": {
    "iso:country":"DE",
    "sg:address":"Klinikstr. 36",
    "sg:city":"Gie\u00dfen",
    "sg:postcode":"35392",
    "sg:province":"Hessen",
    "wof:name":"Institut F\u00fcr Klinische Chemie Und Pathobiologie",
    "wof:placetype":"venue"
},
  "geometry": {"coordinates":[8.665017128,50.5750961304],"type":"Point"}
}