{
  "type": "Feature",
  "properties": {
    "iso:country":"DE",
    "sg:address":"Preysingstr. 54",
    "sg:city":"Wolnzach",
    "sg:phone":"+49 8442/924950",
    "sg:postcode":"85283",
    "sg:province":"Bayern",
    "wof:name":"Wallner Gmbh",
    "wof:placetype":"venue"
},
  "geometry": {"coordinates":[11.629616,48.598274],"type":"Point"}
}