{
  "type": "Feature",
  "properties": {
    "iso:country":"DE",
    "sg:address":"Edisonstr.17",
    "sg:city":"Bautzen",
    "sg:phone":"+49 4935/914840",
    "sg:postcode":"02625",
    "sg:province":"Sachsen",
    "wof:name":"L\u00d6blein Fleisch & Wurst- Spezialit\u00c4ten Gmbh",
    "wof:placetype":"venue"
},
  "geometry": {"coordinates":[14.4269685745,51.1633529663],"type":"Point"}
}