{
  "type": "Feature",
  "properties": {
    "iso:country":"DE",
    "sg:address":"Hafenstr. 73",
    "sg:city":"Bremerhaven",
    "sg:phone":"+49 471/9413673",
    "sg:postcode":"27576",
    "sg:province":"Bremen",
    "wof:name":"Columbus-apotheke",
    "wof:placetype":"venue"
},
  "geometry": {"coordinates":[8.583327,53.554909],"type":"Point"}
}