{
  "type": "Feature",
  "properties": {
    "iso:country":"DE",
    "sg:address":"Ruhrstr.14",
    "sg:city":"erfurt",
    "sg:phone":"+49 361/5660393",
    "sg:postcode":"99089",
    "sg:province":"Th\u00fcringen",
    "wof:name":"Sonnenstudio L\u00f6cher",
    "wof:placetype":"venue"
},
  "geometry": {"coordinates":[11.045928,50.977455],"type":"Point"}
}