{
  "type": "Feature",
  "properties": {
    "iso:country":"DE",
    "sg:address":"M\u00fcnchnerstr. 115",
    "sg:city":"Unterf\u00f6hring",
    "sg:postcode":"85774",
    "sg:province":"Bayern",
    "wof:name":"1a-geb\u00e4udeservice Kg",
    "wof:placetype":"venue"
},
  "geometry": {"coordinates":[11.646382,48.196995],"type":"Point"}
}