{
  "type": "Feature",
  "properties": {
    "iso:country":"DE",
    "sg:address":"Ringstr. 11",
    "sg:city":"Zachenberg",
    "sg:postcode":"94239",
    "sg:province":"Bayern",
    "wof:name":"W & K Sieb- Und Brachtechnik Gmbh",
    "wof:placetype":"venue"
},
  "geometry": {"coordinates":[13.000283,48.96944],"type":"Point"}
}