{
  "type": "Feature",
  "properties": {
    "iso:country":"DE",
    "sg:address":"Feldstr. 66",
    "sg:city":"Bergholz-Rehbr\u00fccke",
    "sg:phone":"+49 33200/85712",
    "sg:postcode":"14558",
    "sg:province":"Brandenburg",
    "wof:name":"Horst Frohberg",
    "wof:placetype":"venue"
},
  "geometry": {"coordinates":[13.114671,52.352074],"type":"Point"}
}