{
  "type": "Feature",
  "properties": {
    "iso:country":"DE",
    "sg:address":"Mehner M\u00fchle 9",
    "sg:city":"L\u00fcbbecke",
    "sg:phone":"+49 5741/8104",
    "sg:postcode":"32312",
    "sg:province":"Nordrhein-Westfalen",
    "wof:name":"Willi Schmale",
    "wof:placetype":"venue"
},
  "geometry": {"coordinates":[8.5787343979,52.2856407166],"type":"Point"}
}