{
  "type": "Feature",
  "properties": {
    "iso:country":"DE",
    "sg:address":"Carl-Zeiss-Str. 2",
    "sg:city":"Quickborn",
    "sg:postcode":"25451",
    "sg:province":"Schleswig-Holstein",
    "wof:name":"Daz Immobilien Und Anlagen Gmbh & Co. Kg",
    "wof:placetype":"venue"
},
  "geometry": {"coordinates":[9.9314470291,53.747127533],"type":"Point"}
}