{
  "type": "Feature",
  "properties": {
    "iso:country":"DE",
    "sg:address":"Hohenerxlebener Str. 93",
    "sg:city":"Sta\u00dffurt",
    "sg:postcode":"39418",
    "sg:province":"Sachsen-Anhalt",
    "wof:name":"Fritz Wiest",
    "wof:placetype":"venue"
},
  "geometry": {"coordinates":[11.59288,51.850704],"type":"Point"}
}