{
  "type": "Feature",
  "properties": {
    "iso:country":"DE",
    "sg:address":"Heinrich-Rau-Str. 37",
    "sg:city":"Eberswalde",
    "sg:phone":"+49 3334/32585",
    "sg:postcode":"16227",
    "sg:province":"Brandenburg",
    "wof:name":"J\u00f6rg Hoffmann",
    "wof:placetype":"venue"
},
  "geometry": {"coordinates":[13.7187757492,52.8421630859],"type":"Point"}
}