{
  "type": "Feature",
  "properties": {
    "iso:country":"DE",
    "sg:address":"Hauptstr. 55",
    "sg:city":"Overath",
    "sg:phone":"+49 2206/6255",
    "sg:postcode":"51491",
    "sg:province":"Nordrhein-Westfalen",
    "wof:name":"Christel Hundler Heilpraktikerin",
    "wof:placetype":"venue"
},
  "geometry": {"coordinates":[7.2858381271,50.9328956604],"type":"Point"}
}