{
  "type": "Feature",
  "properties": {
    "iso:country":"DE",
    "sg:address":"Schadowstr. 93",
    "sg:city":"D\u00fcsseldorf",
    "sg:phone":"+49 211/36860",
    "sg:postcode":"40212",
    "sg:province":"Nordrhein-Westfalen",
    "wof:name":"Karstadt Warenhaus Ag",
    "wof:placetype":"venue"
},
  "geometry": {"coordinates":[6.78317,51.226471],"type":"Point"}
}