{
  "type": "Feature",
  "properties": {
    "iso:country":"DE",
    "sg:address":"Herrengartenstr. 15",
    "sg:city":"Donzdorf",
    "sg:phone":"+49 7162/25501",
    "sg:postcode":"73072",
    "sg:province":"Baden-W\u00fcrttemberg",
    "wof:name":"F. Steiner",
    "wof:placetype":"venue"
},
  "geometry": {"coordinates":[9.806483,48.684872],"type":"Point"}
}