{
  "type": "Feature",
  "properties": {
    "iso:country":"DE",
    "sg:address":"Kirchstr. 37",
    "sg:city":"Leichlingen",
    "sg:phone":"+49 2175/98869",
    "sg:postcode":"42799",
    "sg:province":"Nordrhein-Westfalen",
    "wof:name":"Josef Remmert",
    "wof:placetype":"venue"
},
  "geometry": {"coordinates":[7.0209188461,51.1083145142],"type":"Point"}
}