{
  "type": "Feature",
  "properties": {
    "iso:country":"DE",
    "sg:address":"Amtsstr. 7",
    "sg:city":"S\u00f6gel",
    "sg:phone":"+49 5952/1867",
    "sg:postcode":"49751",
    "sg:province":"Niedersachsen",
    "wof:name":"M. Schrand",
    "wof:placetype":"venue"
},
  "geometry": {"coordinates":[7.518561,52.840027],"type":"Point"}
}