{
  "type": "Feature",
  "properties": {
    "iso:country":"DE",
    "sg:address":"Paul-Trunetz-Str. 8",
    "sg:city":"B\u00f6rtlingen",
    "sg:phone":"+49 7161/57134",
    "sg:postcode":"73104",
    "sg:province":"Baden-W\u00fcrttemberg",
    "wof:name":"Krankenpflegeverein",
    "wof:placetype":"venue"
},
  "geometry": {"coordinates":[9.632853,48.754253],"type":"Point"}
}