{
  "type": "Feature",
  "properties": {
    "iso:country":"DE",
    "sg:address":"Im Esch 17 u. 18",
    "sg:city":"Witten",
    "sg:phone":"+49 2302/2060",
    "sg:postcode":"58455",
    "sg:province":"Nordrhein-Westfalen",
    "wof:name":"Gallad\u00e9 Holding Gmbh & Co. Kg",
    "wof:placetype":"venue"
},
  "geometry": {"coordinates":[7.295358181,51.4362411499],"type":"Point"}
}