{
  "type": "Feature",
  "properties": {
    "iso:country":"DE",
    "sg:address":"Zum Kaiserblick 25",
    "sg:city":"Feldkirchen-Westerham",
    "sg:phone":"+49 8063/9935",
    "sg:postcode":"83620",
    "sg:province":"Bayern",
    "wof:name":"Fastron Ges. F. Elektronic & Bauelemente",
    "wof:placetype":"venue"
},
  "geometry": {"coordinates":[11.82985,47.905521],"type":"Point"}
}