{
  "type": "Feature",
  "properties": {
    "iso:country":"DE",
    "sg:address":"Deviller Str. 14",
    "sg:city":"Bargteheide",
    "sg:phone":"+49 4532/24640",
    "sg:postcode":"22941",
    "sg:province":"Schleswig-Holstein",
    "wof:name":"Sabine Meyer",
    "wof:placetype":"venue"
},
  "geometry": {"coordinates":[10.28441,53.733047],"type":"Point"}
}