{
  "type": "Feature",
  "properties": {
    "iso:country":"DE",
    "sg:address":"Br\u00fcckenstr. 1",
    "sg:city":"Marsberg",
    "sg:phone":"+49 2993/228",
    "sg:postcode":"34431",
    "sg:province":"Nordrhein-Westfalen",
    "wof:name":"F.-j. M\u00fcller",
    "wof:placetype":"venue"
},
  "geometry": {"coordinates":[8.942604,51.41938],"type":"Point"}
}