{
  "type": "Feature",
  "properties": {
    "iso:country":"DE",
    "sg:address":"Gutenbergstr. 8",
    "sg:city":"Braunschweig",
    "sg:phone":"+49 531/81122",
    "sg:postcode":"38118",
    "sg:province":"Niedersachsen",
    "wof:name":"G\u00fcnter Bartels",
    "wof:placetype":"venue"
},
  "geometry": {"coordinates":[10.5024251938,52.2585792542],"type":"Point"}
}