{
  "type": "Feature",
  "properties": {
    "iso:country":"DE",
    "sg:address":"Raasdorfer Stra\u00dfe 4",
    "sg:city":"Mohlsdorf",
    "sg:phone":"+49 3661",
    "sg:postcode":"07987",
    "sg:province":"Th\u00fcringen",
    "wof:name":"M S Metalltechnik Gmbh",
    "wof:placetype":"venue"
},
  "geometry": {"coordinates":[12.2535982132,50.6709861755],"type":"Point"}
}