{
  "type": "Feature",
  "properties": {
    "iso:country":"DE",
    "sg:address":"Friedloser Str. 28",
    "sg:city":"Bad Hersfeld",
    "sg:phone":"+49 6621/917645",
    "sg:postcode":"36251",
    "sg:province":"Hessen",
    "wof:name":"Druck-store Digital-print- Erzeugnisse Gmbh",
    "wof:placetype":"venue"
},
  "geometry": {"coordinates":[9.7173833847,50.8727645874],"type":"Point"}
}