{
  "type": "Feature",
  "properties": {
    "iso:country":"DE",
    "sg:address":"Altenwall 21",
    "sg:city":"Bremen",
    "sg:phone":"+49 421/335000",
    "sg:postcode":"28195",
    "sg:province":"Bremen",
    "wof:name":"Vinnen Beteiligungsges. Mbh",
    "wof:placetype":"venue"
},
  "geometry": {"coordinates":[8.810323,53.072311],"type":"Point"}
}