{
  "type": "Feature",
  "properties": {
    "iso:country":"DE",
    "sg:address":"St\u00f6ckmannstr. 177",
    "sg:city":"Oberhausen",
    "sg:phone":"+49 208/24081",
    "sg:postcode":"46045",
    "sg:province":"Nordrhein-Westfalen",
    "wof:name":"Besa-hydraulik- Und Armaturen Berghem & Salber",
    "wof:placetype":"venue"
},
  "geometry": {"coordinates":[6.84897,51.46368],"type":"Point"}
}