{
  "type": "Feature",
  "properties": {
    "iso:country":"DE",
    "sg:address":"Gartenkamp 17",
    "sg:city":"Celle",
    "sg:phone":"+49 5141/31005",
    "sg:postcode":"29229",
    "sg:province":"Niedersachsen",
    "wof:name":"Kfz-sachverst\u00e4ndigenb\u00fcro Uecker Gmbh",
    "wof:placetype":"venue"
},
  "geometry": {"coordinates":[10.1359729767,52.6449890137],"type":"Point"}
}