{
  "type": "Feature",
  "properties": {
    "iso:country":"DE",
    "sg:address":"Gro\u00dfe Gartenstr 3",
    "sg:city":"Brandenburg",
    "sg:phone":"+49 3381/524127",
    "sg:postcode":"14776",
    "sg:province":"Brandenburg",
    "wof:name":"Hoffmann-jalousien Gmbh",
    "wof:placetype":"venue"
},
  "geometry": {"coordinates":[12.5593185425,52.4038314819],"type":"Point"}
}