{
  "type": "Feature",
  "properties": {
    "iso:country":"DE",
    "sg:address":"St.-Wendel-Str. 4",
    "sg:city":"Oberkirch",
    "sg:phone":"+49 7802/4807",
    "sg:postcode":"77704",
    "sg:province":"Baden-W\u00fcrttemberg",
    "wof:name":"Franz Streif",
    "wof:placetype":"venue"
},
  "geometry": {"coordinates":[8.0453424454,48.5269165039],"type":"Point"}
}