{
  "type": "Feature",
  "properties": {
    "iso:country":"DE",
    "sg:address":"Neue Str. 3",
    "sg:city":"Varel",
    "sg:phone":"+49 4451/85424",
    "sg:postcode":"26316",
    "sg:province":"Niedersachsen",
    "wof:name":"Trend-line Shm Modevertrieb Gmbh",
    "wof:placetype":"venue"
},
  "geometry": {"coordinates":[8.139492,53.395168],"type":"Point"}
}