{
  "type": "Feature",
  "properties": {
    "iso:country":"DE",
    "sg:address":"Brunnengasse 2",
    "sg:city":"Bad Br\u00fcckenau",
    "sg:phone":"+49 9741/2449",
    "sg:postcode":"97769",
    "sg:province":"Bayern",
    "wof:name":"Friedrich Messler Immobilienmakler",
    "wof:placetype":"venue"
},
  "geometry": {"coordinates":[9.7907752991,50.3097381592],"type":"Point"}
}