{
  "type": "Feature",
  "properties": {
    "iso:country":"DE",
    "sg:address":"Bahnhofstr. 9",
    "sg:city":"Gelnhausen",
    "sg:phone":"+49 6051/3341",
    "sg:postcode":"63571",
    "sg:province":"Hessen",
    "wof:name":"Kebab Station",
    "wof:placetype":"venue"
},
  "geometry": {"coordinates":[9.1896295547,50.1968688965],"type":"Point"}
}