{
  "type": "Feature",
  "properties": {
    "iso:country":"DE",
    "sg:address":"Forststr. 30",
    "sg:city":"Ostfildern",
    "sg:phone":"+49 711/412234",
    "sg:postcode":"73760",
    "sg:province":"Baden-W\u00fcrttemberg",
    "wof:name":"T. Till",
    "wof:placetype":"venue"
},
  "geometry": {"coordinates":[9.258890152,48.7303657532],"type":"Point"}
}