{
  "type": "Feature",
  "properties": {
    "iso:country":"DE",
    "sg:address":"Lonauer Str. 48",
    "sg:city":"Herzberg",
    "sg:phone":"+49 5521/2871",
    "sg:postcode":"37412",
    "sg:province":"Niedersachsen",
    "wof:name":"G\u00fcnter Garbode Steuerberater",
    "wof:placetype":"venue"
},
  "geometry": {"coordinates":[10.2875213623,51.6688423157],"type":"Point"}
}