{
  "type": "Feature",
  "properties": {
    "iso:country":"DE",
    "sg:address":"Kaltm\u00fchlweg 36",
    "sg:city":"Rosenheim",
    "sg:phone":"+49 8031/63539",
    "sg:postcode":"83026",
    "sg:province":"Bayern",
    "wof:name":"Orca Software Gmbh",
    "wof:placetype":"venue"
},
  "geometry": {"coordinates":[12.1180438995,47.8367271423],"type":"Point"}
}