{
  "type": "Feature",
  "properties": {
    "iso:country":"DE",
    "sg:address":"W\u00fcrttemberger Str. 7",
    "sg:city":"Eggenstein-Leopoldshafen",
    "sg:phone":"+49 7247/2390",
    "sg:postcode":"76344",
    "sg:province":"Baden-W\u00fcrttemberg",
    "wof:name":"Beatrice Zappe Heilpraktiker",
    "wof:placetype":"venue"
},
  "geometry": {"coordinates":[8.3969602585,49.0949134827],"type":"Point"}
}