{
  "type": "Feature",
  "properties": {
    "iso:country":"DE",
    "sg:address":"Lehrenweg 32",
    "sg:city":"Meersburg",
    "sg:phone":"+49 7532/414901",
    "sg:postcode":"88709",
    "sg:province":"Baden-W\u00fcrttemberg",
    "wof:name":"Ferienwohnungen Und Zimmer Benz/steidle, Meersburg",
    "wof:placetype":"venue"
},
  "geometry": {"coordinates":[9.276369,47.696793],"type":"Point"}
}