{
  "type": "Feature",
  "properties": {
    "iso:country":"DE",
    "sg:address":"Sch\u00fctzenhausstr. 26",
    "sg:city":"Schlettau",
    "sg:phone":"+49 3733/66301",
    "sg:postcode":"09487",
    "sg:province":"Sachsen",
    "wof:name":"Afs Agrarfarm Gmbh Schlettau",
    "wof:placetype":"venue"
},
  "geometry": {"coordinates":[12.9445400238,50.5584411621],"type":"Point"}
}