{
  "type": "Feature",
  "properties": {
    "iso:country":"DE",
    "sg:address":"M\u00e4rkische Allee 408",
    "sg:city":"Berlin",
    "sg:phone":"+49 30/9335505",
    "sg:postcode":"12689",
    "sg:province":"Berlin",
    "wof:name":"Ristorante Pizzeria",
    "wof:placetype":"venue"
},
  "geometry": {"coordinates":[13.5679922104,52.5712051392],"type":"Point"}
}