{
  "type": "Feature",
  "properties": {
    "iso:country":"DE",
    "sg:address":"N\u00fcrnberger Str. 20",
    "sg:city":"Seubersdorf",
    "sg:phone":"+49 9497/244",
    "sg:postcode":"92358",
    "sg:province":"Bayern",
    "wof:name":"H. Wittl",
    "wof:placetype":"venue"
},
  "geometry": {"coordinates":[11.623838,49.167786],"type":"Point"}
}