{
  "type": "Feature",
  "properties": {
    "iso:country":"DE",
    "sg:address":"Robert-Koch-Str. 3",
    "sg:city":"Schwerin",
    "sg:phone":"+49 385/5812943",
    "sg:postcode":"19055",
    "sg:province":"Mecklenburg-Vorpommern",
    "wof:name":"Dieter Schwarz",
    "wof:placetype":"venue"
},
  "geometry": {"coordinates":[11.426896,53.635548],"type":"Point"}
}