{
  "type": "Feature",
  "properties": {
    "iso:country":"DE",
    "sg:address":"Bruckwiesreuth",
    "sg:city":"Saldenburg",
    "sg:phone":"+49 8504/8239",
    "sg:postcode":"94163",
    "sg:province":"Bayern",
    "wof:name":"Gasthaus L. Klessinger",
    "wof:placetype":"venue"
},
  "geometry": {"coordinates":[13.3436145782,48.7630386353],"type":"Point"}
}