{
  "type": "Feature",
  "properties": {
    "iso:country":"DE",
    "sg:address":"Bethlehemer Str. 28",
    "sg:city":"Bergheim",
    "sg:phone":"+49 2271/44660",
    "sg:postcode":"50126",
    "sg:province":"Nordrhein-Westfalen",
    "wof:name":"R. C. E. Baubetreuungs- Gmbh",
    "wof:placetype":"venue"
},
  "geometry": {"coordinates":[6.644853,50.955055],"type":"Point"}
}