{
  "type": "Feature",
  "properties": {
    "iso:country":"DE",
    "sg:address":"Industriestr. 4-6",
    "sg:city":"Pressig",
    "sg:phone":"+49 9265/913333",
    "sg:postcode":"96332",
    "sg:province":"Bayern",
    "wof:name":"Fertigteilwerk Pressig Gmbh",
    "wof:placetype":"venue"
},
  "geometry": {"coordinates":[11.2969427109,50.3472557068],"type":"Point"}
}