{
  "type": "Feature",
  "properties": {
    "iso:country":"DE",
    "sg:address":"Sarnowstr. 27",
    "sg:city":"Stralsund",
    "sg:phone":"+49 3831/310353",
    "sg:postcode":"18435",
    "sg:province":"Mecklenburg-Vorpommern",
    "wof:name":"S. G\u00e4rtner",
    "wof:placetype":"venue"
},
  "geometry": {"coordinates":[13.082386,54.32209],"type":"Point"}
}