{
  "type": "Feature",
  "properties": {
    "iso:country":"DE",
    "sg:address":"Neuer Weg 30",
    "sg:city":"Waldenbuch",
    "sg:phone":"+49 7157/20374",
    "sg:postcode":"71111",
    "sg:province":"Baden-W\u00fcrttemberg",
    "wof:name":"Leonhardt",
    "wof:placetype":"venue"
},
  "geometry": {"coordinates":[9.131994,48.636135],"type":"Point"}
}