{
  "type": "Feature",
  "properties": {
    "iso:country":"DE",
    "sg:address":"Ziegelstr. 2",
    "sg:city":"Kirchheim",
    "sg:phone":"+49 7021/43633",
    "sg:postcode":"73230",
    "sg:province":"Baden-W\u00fcrttemberg",
    "wof:name":"Gunter Geier Steuerberater",
    "wof:placetype":"venue"
},
  "geometry": {"coordinates":[9.4515237808,48.6438217163],"type":"Point"}
}