{
  "type": "Feature",
  "properties": {
    "iso:country":"DE",
    "sg:address":"Iranische Str. 6",
    "sg:city":"Berlin",
    "sg:phone":"+49 30/4924044",
    "sg:postcode":"13347",
    "sg:province":"Berlin",
    "wof:name":"B\u00fcrgermeister-reuter-stiftung",
    "wof:placetype":"venue"
},
  "geometry": {"coordinates":[13.3683986664,52.5548171997],"type":"Point"}
}