{
  "type": "Feature",
  "properties": {
    "iso:country":"DE",
    "sg:address":"Zenettistr 11",
    "sg:city":"M\u00fcnchen",
    "sg:phone":"+49 89/777923",
    "sg:postcode":"80337",
    "sg:province":"Bayern",
    "wof:name":"Planen Mayr",
    "wof:placetype":"venue"
},
  "geometry": {"coordinates":[11.558024,48.123158],"type":"Point"}
}