{
  "type": "Feature",
  "properties": {
    "iso:country":"DE",
    "sg:address":"Hofst\u00fcckerweg 9",
    "sg:city":"Schellweiler",
    "sg:phone":"+49 671/61046",
    "sg:postcode":"66869",
    "sg:province":"Rheinland-Pfalz",
    "wof:name":"Scheidweiler",
    "wof:placetype":"venue"
},
  "geometry": {"coordinates":[7.8628549576,49.823802948],"type":"Point"}
}