{
  "type": "Feature",
  "properties": {
    "iso:country":"DE",
    "sg:address":"Baderstr. 1A",
    "sg:city":"Marienberg",
    "sg:phone":"+49 3735/23139",
    "sg:postcode":"09496",
    "sg:province":"Sachsen",
    "wof:name":"Rossmann Drogeriemarkt",
    "wof:placetype":"venue"
},
  "geometry": {"coordinates":[13.164388,50.65023],"type":"Point"}
}