{
  "type": "Feature",
  "properties": {
    "iso:country":"DE",
    "sg:address":"Hauberg 2",
    "sg:city":"Emmerich",
    "sg:postcode":"46446",
    "sg:province":"Nordrhein-Westfalen",
    "wof:name":"Meyer Diamant-, Bohr- Und S\u00e4getechnik Gmbh",
    "wof:placetype":"venue"
},
  "geometry": {"coordinates":[6.1462569237,51.8744430542],"type":"Point"}
}