{
  "type": "Feature",
  "properties": {
    "iso:country":"DE",
    "sg:address":"Lichtenauer Str. 109",
    "sg:city":"Melsungen",
    "sg:phone":"+49 5602/3481",
    "sg:postcode":"34212",
    "sg:province":"Hessen",
    "wof:name":"R. Alscher",
    "wof:placetype":"venue"
},
  "geometry": {"coordinates":[9.6658964157,51.1717681885],"type":"Point"}
}