{
  "type": "Feature",
  "properties": {
    "iso:country":"DE",
    "sg:address":"fliederstrasse 5a",
    "sg:city":"westerstede",
    "sg:phone":"+49 4488/8629061",
    "sg:postcode":"26655",
    "sg:province":"Niedersachsen",
    "wof:name":"The Inner Temple Network",
    "wof:placetype":"venue"
},
  "geometry": {"coordinates":[7.915813,53.263042],"type":"Point"}
}