{
  "type": "Feature",
  "properties": {
    "iso:country":"DE",
    "sg:address":"Zum Frenser Feld 18 B",
    "sg:city":"Bergheim",
    "sg:postcode":"50127",
    "sg:province":"Nordrhein-Westfalen",
    "wof:name":"Kik Dekorations- Und Objektservice Gmbh",
    "wof:placetype":"venue"
},
  "geometry": {"coordinates":[6.699914,50.930367],"type":"Point"}
}