{
  "type": "Feature",
  "properties": {
    "iso:country":"DE",
    "sg:address":"Weg beim J\u00e4ger 193",
    "sg:city":"Hamburg",
    "sg:phone":"+49 40/5005930",
    "sg:postcode":"22335",
    "sg:province":"Hamburg",
    "wof:name":"Lufthansa Technik Ag",
    "wof:placetype":"venue"
},
  "geometry": {"coordinates":[9.997053,53.621593],"type":"Point"}
}