{
  "type": "Feature",
  "properties": {
    "iso:country":"DE",
    "sg:address":"Siechenstr. 24",
    "sg:city":"Bamberg",
    "sg:phone":"+49 951/63118",
    "sg:postcode":"96052",
    "sg:province":"Bayern",
    "wof:name":"M\u00fcnchner Hofbr\u00e4ust\u00fcbl",
    "wof:placetype":"venue"
},
  "geometry": {"coordinates":[10.8894119263,49.8991127014],"type":"Point"}
}