{
  "type": "Feature",
  "properties": {
    "iso:country":"DE",
    "sg:address":"Landshuter Allee 73",
    "sg:city":"M\u00fcnchen",
    "sg:phone":"+49 89/1675607",
    "sg:postcode":"80637",
    "sg:province":"Bayern",
    "wof:name":"H. R. Grasmeier Heilpraktiker",
    "wof:placetype":"venue"
},
  "geometry": {"coordinates":[11.536804,48.155586],"type":"Point"}
}