{
  "type": "Feature",
  "properties": {
    "iso:country":"DE",
    "sg:address":"Dorfplatz 6",
    "sg:city":"Parsdorf",
    "sg:phone":"+49 89/9043177",
    "sg:postcode":"85599",
    "sg:province":"Bayern",
    "wof:name":"Pizzeria Salotto",
    "wof:placetype":"venue"
},
  "geometry": {"coordinates":[11.7876901627,48.1418380737],"type":"Point"}
}