{
  "type": "Feature",
  "properties": {
    "iso:country":"DE",
    "sg:address":"Rethobergstr. 9",
    "sg:city":"Northeim",
    "sg:postcode":"37154",
    "sg:province":"Niedersachsen",
    "wof:name":"Handwerker Union Northeim Gmbh",
    "wof:placetype":"venue"
},
  "geometry": {"coordinates":[10.042935,51.738548],"type":"Point"}
}