{
  "type": "Feature",
  "properties": {
    "iso:country":"DE",
    "sg:address":"Am Hohlebrunnen 3",
    "sg:city":"Bad Homburg",
    "sg:phone":"+49 6172/450917",
    "sg:postcode":"61352",
    "sg:province":"Hessen",
    "wof:name":"Wilfried Empter",
    "wof:placetype":"venue"
},
  "geometry": {"coordinates":[8.6256847382,50.2210388184],"type":"Point"}
}