{
  "type": "Feature",
  "properties": {
    "iso:country":"DE",
    "sg:address":"Wendlerstr. 1",
    "sg:city":"N\u00fcrnberg",
    "sg:phone":"+49 911/442002",
    "sg:postcode":"90459",
    "sg:province":"Bayern",
    "wof:name":"Max Morlock Wettannahme",
    "wof:placetype":"venue"
},
  "geometry": {"coordinates":[11.081666,49.441933],"type":"Point"}
}