{
  "type": "Feature",
  "properties": {
    "iso:country":"DE",
    "sg:address":"Gitterseestr. 1",
    "sg:city":"Dresden",
    "sg:phone":"+49 351/4030963",
    "sg:postcode":"01187",
    "sg:province":"Sachsen",
    "wof:name":"Brennstoffhandel Hans Holfert",
    "wof:placetype":"venue"
},
  "geometry": {"coordinates":[13.707372,51.027977],"type":"Point"}
}