{
  "type": "Feature",
  "properties": {
    "iso:country":"DE",
    "sg:address":"Am Steinbruch 1",
    "sg:city":"Oberstaufen",
    "sg:phone":"+49 8386/1224",
    "sg:postcode":"87534",
    "sg:province":"Bayern",
    "wof:name":"Hans N\u00e4gele",
    "wof:placetype":"venue"
},
  "geometry": {"coordinates":[10.01844,47.545097],"type":"Point"}
}