{
  "type": "Feature",
  "properties": {
    "iso:country":"DE",
    "sg:address":"In den Twieten 14",
    "sg:city":"Suderburg",
    "sg:postcode":"29556",
    "sg:province":"Niedersachsen",
    "wof:name":"Hotel Zum Lindenheim",
    "wof:placetype":"venue"
},
  "geometry": {"coordinates":[10.4422664642,52.8986320496],"type":"Point"}
}