{
  "type": "Feature",
  "properties": {
    "iso:country":"DE",
    "sg:address":"Borchelhof 59",
    "sg:city":"Rotenburg",
    "sg:phone":"+49 4286/1072",
    "sg:postcode":"27356",
    "sg:province":"Niedersachsen",
    "wof:name":"Paul Jaletzky",
    "wof:placetype":"venue"
},
  "geometry": {"coordinates":[9.349555,53.17609],"type":"Point"}
}