{
  "type": "Feature",
  "properties": {
    "iso:country":"DE",
    "sg:address":"Seigertsh\u00e4user Str. 13",
    "sg:city":"Neukirchen",
    "sg:phone":"+49 6694/210",
    "sg:postcode":"34626",
    "sg:province":"Hessen",
    "wof:name":"Mario Kaniut",
    "wof:placetype":"venue"
},
  "geometry": {"coordinates":[9.3437891006,50.8700294495],"type":"Point"}
}