{
  "type": "Feature",
  "properties": {
    "iso:country":"DE",
    "sg:address":"Mindelheimer Str. 1",
    "sg:city":"Pfaffenhausen",
    "sg:phone":"+49 8265/1250",
    "sg:postcode":"87772",
    "sg:province":"Bayern",
    "wof:name":"Kreuz",
    "wof:placetype":"venue"
},
  "geometry": {"coordinates":[10.4574613571,48.1207466125],"type":"Point"}
}