{
  "type": "Feature",
  "properties": {
    "iso:country":"DE",
    "sg:address":"Remchinger Str. 1",
    "sg:city":"Remchingen",
    "sg:phone":"+49 7232/72700",
    "sg:postcode":"75196",
    "sg:province":"Baden-W\u00fcrttemberg",
    "wof:name":"Vk Konception Werbe-gmbh",
    "wof:placetype":"venue"
},
  "geometry": {"coordinates":[8.5715036392,48.9528045654],"type":"Point"}
}