{
  "type": "Feature",
  "properties": {
    "iso:country":"DE",
    "sg:address":"Waldb\u00fchnenweg 1",
    "sg:city":"Seebad Heringsdorf",
    "sg:phone":"+49 38378/30522",
    "sg:postcode":"17424",
    "sg:province":"Mecklenburg-Vorpommern",
    "wof:name":"H. Widmer",
    "wof:placetype":"venue"
},
  "geometry": {"coordinates":[14.165813446,53.9508666992],"type":"Point"}
}