{
  "type": "Feature",
  "properties": {
    "iso:country":"DE",
    "sg:address":"Kirchberg 1a",
    "sg:city":"Steinbach",
    "sg:postcode":"36448",
    "sg:province":"Th\u00fcringen",
    "wof:name":"Konsumgenossenschaft S\u00fcdth\u00fcringen Eg",
    "wof:placetype":"venue"
},
  "geometry": {"coordinates":[10.3612670898,50.8329315186],"type":"Point"}
}