{
  "type": "Feature",
  "properties": {
    "iso:country":"DE",
    "sg:address":"Rainfarnstr. 36",
    "sg:city":"M\u00fcnchen",
    "sg:phone":"+49 89/3142995",
    "sg:postcode":"80935",
    "sg:province":"Bayern",
    "wof:name":"Rainfarn-apotheke",
    "wof:placetype":"venue"
},
  "geometry": {"coordinates":[11.552559,48.207649],"type":"Point"}
}