{
  "type": "Feature",
  "properties": {
    "iso:country":"DE",
    "sg:address":"Lohweg 3",
    "sg:city":"Brand",
    "sg:phone":"+49 9236/278",
    "sg:postcode":"95682",
    "sg:province":"Bayern",
    "wof:name":"Trutterstube",
    "wof:placetype":"venue"
},
  "geometry": {"coordinates":[11.9111051559,49.9689559937],"type":"Point"}
}