{
  "type": "Feature",
  "properties": {
    "iso:country":"DE",
    "sg:address":"Siemensstr. 2",
    "sg:city":"Metzingen",
    "sg:phone":"+49 7123/41385",
    "sg:postcode":"72555",
    "sg:province":"Baden-W\u00fcrttemberg",
    "wof:name":"W. Zumbruch",
    "wof:placetype":"venue"
},
  "geometry": {"coordinates":[9.2799949646,48.5451202393],"type":"Point"}
}