{
  "type": "Feature",
  "properties": {
    "iso:country":"DE",
    "sg:address":"Gl\u00f6rfeld 15",
    "sg:city":"Halver",
    "sg:phone":"+49 4923/533862",
    "sg:postcode":"58553",
    "sg:province":"Nordrhein-Westfalen",
    "wof:name":"S\u00d6hnchen, Friedr Karl, Inh A Schnippering",
    "wof:placetype":"venue"
},
  "geometry": {"coordinates":[7.49667,51.226299],"type":"Point"}
}