{
  "type": "Feature",
  "properties": {
    "iso:country":"DE",
    "sg:address":"Sch\u00f6nhauser Allee 172",
    "sg:city":"Berlin",
    "sg:phone":"+49 30/4468670",
    "sg:postcode":"10435",
    "sg:province":"Berlin",
    "wof:name":"Vamed Krankenhausmanagement Und Betriebsf\u00fchrungsges. Mbh",
    "wof:placetype":"venue"
},
  "geometry": {"coordinates":[13.4122781754,52.5329246521],"type":"Point"}
}