{
  "type": "Feature",
  "properties": {
    "iso:country":"DE",
    "sg:address":"Hagenaustr. 7",
    "sg:city":"Langenbach",
    "sg:postcode":"85416",
    "sg:province":"Bayern",
    "wof:name":"Generation Planners Verwaltungs Gmbh",
    "wof:placetype":"venue"
},
  "geometry": {"coordinates":[11.8532018661,48.4440116882],"type":"Point"}
}