{
  "type": "Feature",
  "properties": {
    "iso:country":"DE",
    "sg:address":"Quelkhorner Landstr. 6",
    "sg:city":"Ottersberg",
    "sg:phone":"+49 4293/7159",
    "sg:postcode":"28870",
    "sg:province":"Niedersachsen",
    "wof:name":"Herbert Wurthmann",
    "wof:placetype":"venue"
},
  "geometry": {"coordinates":[9.082944,53.133945],"type":"Point"}
}