{
  "type": "Feature",
  "properties": {
    "iso:country":"DE",
    "sg:address":"Seestr. 9",
    "sg:city":"Neubrandenburg",
    "sg:phone":"+49 395/2952",
    "sg:postcode":"17033",
    "sg:province":"Mecklenburg-Vorpommern",
    "wof:name":"Bbn Beratungs- Und B\u00fcroservicegesellschaft Mbh",
    "wof:placetype":"venue"
},
  "geometry": {"coordinates":[13.238607,53.5499],"type":"Point"}
}