{
  "type": "Feature",
  "properties": {
    "iso:country":"DE",
    "sg:address":"Ludwig-Erhard-Str. 12",
    "sg:city":"Bergheim",
    "sg:phone":"+49 2238/942647",
    "sg:postcode":"50129",
    "sg:province":"Nordrhein-Westfalen",
    "wof:name":"Josef Herget Gmbh",
    "wof:placetype":"venue"
},
  "geometry": {"coordinates":[6.7566018105,50.9685707092],"type":"Point"}
}