{
  "type": "Feature",
  "properties": {
    "iso:country":"DE",
    "sg:address":"Kirchstr. 4",
    "sg:city":"Niederwiesa",
    "sg:postcode":"09577",
    "sg:province":"Sachsen",
    "wof:name":"Ev.-luth. Kirche Niederwiesa",
    "wof:placetype":"venue"
},
  "geometry": {"coordinates":[13.0166082382,50.8626327515],"type":"Point"}
}