{
  "type": "Feature",
  "properties": {
    "iso:country":"DE",
    "sg:address":"Schlo\u00dfk\u00fcchenweg 15",
    "sg:city":"Schmalkalden",
    "sg:phone":"+49 3683/682350",
    "sg:postcode":"98574",
    "sg:province":"Th\u00fcringen",
    "wof:name":"Kreis- Und Stadtarchiv Au\u00dfenstelle Schmalkalden",
    "wof:placetype":"venue"
},
  "geometry": {"coordinates":[10.457218,50.726318],"type":"Point"}
}