{
  "type": "Feature",
  "properties": {
    "iso:country":"DE",
    "sg:address":"Himmelsruh 14",
    "sg:city":"G\u00f6ttingen",
    "sg:phone":"+49 551/792344",
    "sg:postcode":"37085",
    "sg:province":"Niedersachsen",
    "wof:name":"J. Gekel",
    "wof:placetype":"venue"
},
  "geometry": {"coordinates":[9.958531,51.517891],"type":"Point"}
}