{
  "type": "Feature",
  "properties": {
    "iso:country":"DE",
    "sg:address":"Meerfeldstr. 48",
    "sg:city":"Mannheim",
    "sg:phone":"+49 621/8321450",
    "sg:postcode":"68163",
    "sg:province":"Baden-W\u00fcrttemberg",
    "wof:name":"Tchibo Frisch-r\u00f6st-kaffee Gmbh",
    "wof:placetype":"venue"
},
  "geometry": {"coordinates":[8.4686098099,49.4739685059],"type":"Point"}
}