{
  "type": "Feature",
  "properties": {
    "iso:country":"DE",
    "sg:address":"Weisserlenstr. 11",
    "sg:city":"Freiburg",
    "sg:phone":"+49 4976/1130330",
    "sg:postcode":"79108",
    "sg:province":"Baden-W\u00fcrttemberg",
    "wof:name":"Reimann Holzoptimierung Gmbh & Co. Kg",
    "wof:placetype":"venue"
},
  "geometry": {"coordinates":[7.809123,48.039989],"type":"Point"}
}