{
  "type": "Feature",
  "properties": {
    "iso:country":"DE",
    "sg:address":"Parkhofstr. 55",
    "sg:city":"H\u00fcckelhoven",
    "sg:phone":"+49 2433/84755",
    "sg:postcode":"41836",
    "sg:province":"Nordrhein-Westfalen",
    "wof:name":"Diana Discothek",
    "wof:placetype":"venue"
},
  "geometry": {"coordinates":[6.223236,51.053097],"type":"Point"}
}