{
  "type": "Feature",
  "properties": {
    "iso:country":"DE",
    "sg:address":"Karolinenstr. 108",
    "sg:city":"F\u00fcrth",
    "sg:phone":"+49 911/729022",
    "sg:postcode":"90763",
    "sg:province":"Bayern",
    "wof:name":"Kind Und Eltern Fr\u00fchf\u00f6rder. -gemeinn\u00fctzige Gmbh",
    "wof:placetype":"venue"
},
  "geometry": {"coordinates":[10.998167038,49.4673271179],"type":"Point"}
}