{
  "type": "Feature",
  "properties": {
    "iso:country":"DE",
    "sg:address":"Holdersteige 8",
    "sg:city":"Ostrach",
    "sg:phone":"+49 7585/932900",
    "sg:postcode":"88356",
    "sg:province":"Baden-W\u00fcrttemberg",
    "wof:name":"Urbschat Wohn- Und Gewerbebau Gmbh",
    "wof:placetype":"venue"
},
  "geometry": {"coordinates":[9.3855075836,47.9552650452],"type":"Point"}
}