{
  "type": "Feature",
  "properties": {
    "iso:country":"DE",
    "sg:address":"Ernst-Th\u00e4lmann-Str. 19",
    "sg:city":"Ostseebad Wustrow",
    "sg:phone":"+49 38220/80344",
    "sg:postcode":"18347",
    "sg:province":"Mecklenburg-Vorpommern",
    "wof:name":"D\u00e4hn Und Thum Immobilienmakler",
    "wof:placetype":"venue"
},
  "geometry": {"coordinates":[12.3983078003,54.3475341797],"type":"Point"}
}