{
  "type": "Feature",
  "properties": {
    "iso:country":"DE",
    "sg:address":"Ringstr. 1",
    "sg:city":"Siershahn",
    "sg:phone":"+49 2623/5384",
    "sg:postcode":"56427",
    "sg:province":"Rheinland-Pfalz",
    "wof:name":"Udo Plaug",
    "wof:placetype":"venue"
},
  "geometry": {"coordinates":[7.773787,50.484291],"type":"Point"}
}