{
  "type": "Feature",
  "properties": {
    "iso:country":"DE",
    "sg:address":"Ivendorfer Landstr. 62",
    "sg:city":"L\u00fcbeck",
    "sg:phone":"+49 4502/2679",
    "sg:postcode":"23570",
    "sg:province":"Schleswig-Holstein",
    "wof:name":"Hans-j\u00fcrgen Fr\u00e4hmcke",
    "wof:placetype":"venue"
},
  "geometry": {"coordinates":[10.83841,53.935112],"type":"Point"}
}