{
  "type": "Feature",
  "properties": {
    "iso:country":"DE",
    "sg:address":"Semmeringstr. 11",
    "sg:city":"Duisburg",
    "sg:phone":"+49 203/724696",
    "sg:postcode":"47249",
    "sg:province":"Nordrhein-Westfalen",
    "wof:name":"Kath. Pfarramt Heilig Geist",
    "wof:placetype":"venue"
},
  "geometry": {"coordinates":[6.7788939476,51.3847579956],"type":"Point"}
}