{
  "type": "Feature",
  "properties": {
    "iso:country":"DE",
    "sg:address":"Alexandrastr. 3",
    "sg:city":"Wiesbaden",
    "sg:phone":"+49 611/88090",
    "sg:postcode":"65187",
    "sg:province":"Hessen",
    "wof:name":"Panthus Deutschland Gmbh",
    "wof:placetype":"venue"
},
  "geometry": {"coordinates":[8.239442,50.068954],"type":"Point"}
}