{
  "type": "Feature",
  "properties": {
    "iso:country":"DE",
    "sg:address":"B\u00fcrgerstr. 2",
    "sg:city":"Hof",
    "sg:phone":"+49 9281/819490",
    "sg:postcode":"95028",
    "sg:province":"Bayern",
    "wof:name":"Benecke Und Gross Von Trockau Rechtsanw\u00e4lte",
    "wof:placetype":"venue"
},
  "geometry": {"coordinates":[11.9181137085,50.3214111328],"type":"Point"}
}