{
  "type": "Feature",
  "properties": {
    "iso:country":"DE",
    "sg:address":"Holtmar 8",
    "sg:city":"Beckum",
    "sg:phone":"+49 2521/4376",
    "sg:postcode":"59269",
    "sg:province":"Nordrhein-Westfalen",
    "wof:name":"Franz L\u00fcdeke",
    "wof:placetype":"venue"
},
  "geometry": {"coordinates":[7.998785,51.747581],"type":"Point"}
}