{
  "type": "Feature",
  "properties": {
    "iso:country":"DE",
    "sg:address":"Ulmer Str. 60",
    "sg:city":"Augsburg",
    "sg:phone":"+49 821/240910",
    "sg:postcode":"86156",
    "sg:province":"Bayern",
    "wof:name":"Gtb Gewerblich-technisches Bildungszentrum Gmbh",
    "wof:placetype":"venue"
},
  "geometry": {"coordinates":[10.871026,48.381474],"type":"Point"}
}