{
  "type": "Feature",
  "properties": {
    "iso:country":"DE",
    "sg:address":"Richrather Str. 88",
    "sg:city":"Hilden",
    "sg:phone":"+49 2103/336058",
    "sg:postcode":"40723",
    "sg:province":"Nordrhein-Westfalen",
    "wof:name":"Medikus",
    "wof:placetype":"venue"
},
  "geometry": {"coordinates":[6.938046,51.159939],"type":"Point"}
}