{
  "type": "Feature",
  "properties": {
    "iso:country":"DE",
    "sg:address":"Karcherstr. 32",
    "sg:city":"Neunkirchen",
    "sg:phone":"+49 6821/31326",
    "sg:postcode":"66539",
    "sg:province":"Saarland",
    "wof:name":"B. Hein\u00df Und Holm",
    "wof:placetype":"venue"
},
  "geometry": {"coordinates":[7.2158689499,49.3259315491],"type":"Point"}
}