{
  "type": "Feature",
  "properties": {
    "iso:country":"DE",
    "sg:address":"Landgrafenstr. 100",
    "sg:city":"Worms",
    "sg:phone":"+49 6241/76685",
    "sg:postcode":"67549",
    "sg:province":"Rheinland-Pfalz",
    "wof:name":"Ludwig Mehlmann",
    "wof:placetype":"venue"
},
  "geometry": {"coordinates":[8.317811,49.633057],"type":"Point"}
}