{
  "type": "Feature",
  "properties": {
    "iso:country":"DE",
    "sg:address":"Hauptstr. 44",
    "sg:city":"Pirmasens",
    "sg:phone":"+49 6331/64248",
    "sg:postcode":"66953",
    "sg:province":"Rheinland-Pfalz",
    "wof:name":"Gregor Griesser Nachf.",
    "wof:placetype":"venue"
},
  "geometry": {"coordinates":[7.6045417786,49.1990623474],"type":"Point"}
}