{
  "type": "Feature",
  "properties": {
    "iso:country":"DE",
    "sg:address":"Timotheusplatz 2",
    "sg:city":"Hildesheim",
    "sg:phone":"+49 5121/83793",
    "sg:postcode":"31141",
    "sg:province":"Niedersachsen",
    "wof:name":"Ev. Pfarramt St. Tomotheus",
    "wof:placetype":"venue"
},
  "geometry": {"coordinates":[9.9674968719,52.1347351074],"type":"Point"}
}