{
  "type": "Feature",
  "properties": {
    "iso:country":"DE",
    "sg:address":"Berliner Str. 114",
    "sg:city":"Berlin",
    "sg:phone":"+49 30/8115466",
    "sg:postcode":"14169",
    "sg:province":"Berlin",
    "wof:name":"Ruth Bast",
    "wof:placetype":"venue"
},
  "geometry": {"coordinates":[13.282132,52.441456],"type":"Point"}
}