{
  "type": "Feature",
  "properties": {
    "iso:country":"DE",
    "sg:address":"Neugasse 11",
    "sg:city":"Heidelberg",
    "sg:phone":"+49 6221/25010",
    "sg:postcode":"69117",
    "sg:province":"Baden-W\u00fcrttemberg",
    "wof:name":"A. Strubel",
    "wof:placetype":"venue"
},
  "geometry": {"coordinates":[8.695552,49.409527],"type":"Point"}
}