{
  "type": "Feature",
  "properties": {
    "iso:country":"DE",
    "sg:address":"Rudolf-Diesel-Str. 5",
    "sg:city":"Emsdetten",
    "sg:phone":"+49 2572/220",
    "sg:postcode":"48282",
    "sg:province":"Nordrhein-Westfalen",
    "wof:name":"Vw Audi Vertriebszentrum Nord-west Gmbh",
    "wof:placetype":"venue"
},
  "geometry": {"coordinates":[7.550378,52.155239],"type":"Point"}
}