{
  "type": "Feature",
  "properties": {
    "iso:country":"DE",
    "sg:address":"Wilhelmstr. 20",
    "sg:city":"Glauchau",
    "sg:phone":"+49 3763/3500",
    "sg:postcode":"08371",
    "sg:province":"Sachsen",
    "wof:name":"P. Wehrmann",
    "wof:placetype":"venue"
},
  "geometry": {"coordinates":[12.537859,50.820732],"type":"Point"}
}