{
  "type": "Feature",
  "properties": {
    "iso:country":"DE",
    "sg:address":"Hahler Str. 24",
    "sg:city":"Minden",
    "sg:phone":"+49 571/23098",
    "sg:postcode":"32427",
    "sg:province":"Nordrhein-Westfalen",
    "wof:name":"Henner Benkert Rechtsanwalt Und Notar",
    "wof:placetype":"venue"
},
  "geometry": {"coordinates":[8.9092941284,52.2928161621],"type":"Point"}
}