{
  "type": "Feature",
  "properties": {
    "iso:country":"DE",
    "sg:address":"Nickerner Platz 2",
    "sg:city":"Dresden",
    "sg:postcode":"01257",
    "sg:province":"Sachsen",
    "wof:name":"Wsb Energie Gmbh & Co. Windpark Brandenburg Erste Kg",
    "wof:placetype":"venue"
},
  "geometry": {"coordinates":[13.802332,50.990143],"type":"Point"}
}