{
  "type": "Feature",
  "properties": {
    "iso:country":"DE",
    "sg:address":"Orffweg 1",
    "sg:city":"Allmersbach",
    "sg:phone":"+49 7191/310310",
    "sg:postcode":"71573",
    "sg:province":"Baden-W\u00fcrttemberg",
    "wof:name":"M. Seilnacht",
    "wof:placetype":"venue"
},
  "geometry": {"coordinates":[9.479811,48.908203],"type":"Point"}
}