{
  "type": "Feature",
  "properties": {
    "iso:country":"DE",
    "sg:address":"J\u00e4gerstr. 25",
    "sg:city":"Apolda",
    "sg:phone":"+49 3644/555350",
    "sg:postcode":"99510",
    "sg:province":"Th\u00fcringen",
    "wof:name":"Eva-maria Wand Hebamme",
    "wof:placetype":"venue"
},
  "geometry": {"coordinates":[11.511999,51.027802],"type":"Point"}
}