{
  "type": "Feature",
  "properties": {
    "iso:country":"DE",
    "sg:address":"Mozartstr. 47",
    "sg:city":"Heiden",
    "sg:phone":"+49 2867/8800",
    "sg:postcode":"46359",
    "sg:province":"Nordrhein-Westfalen",
    "wof:name":"Dr. Godehard Bartmann Tierarzt",
    "wof:placetype":"venue"
},
  "geometry": {"coordinates":[6.929268837,51.8292770386],"type":"Point"}
}