{
  "type": "Feature",
  "properties": {
    "iso:country":"DE",
    "sg:address":"S\u00fcdstr. 4",
    "sg:city":"Warendorf",
    "sg:phone":"+49 2581/2345",
    "sg:postcode":"48231",
    "sg:province":"Nordrhein-Westfalen",
    "wof:name":"Ad. R\u00f6ttger",
    "wof:placetype":"venue"
},
  "geometry": {"coordinates":[7.9783802032,51.9537353516],"type":"Point"}
}