{
  "type": "Feature",
  "properties": {
    "iso:country":"DE",
    "sg:address":"Wengestr. 17",
    "sg:city":"Essen",
    "sg:phone":"+49 201/211598",
    "sg:postcode":"45309",
    "sg:province":"Nordrhein-Westfalen",
    "wof:name":"R. Waltering",
    "wof:placetype":"venue"
},
  "geometry": {"coordinates":[7.0667629242,51.4789352417],"type":"Point"}
}