{
  "type": "Feature",
  "properties": {
    "iso:country":"DE",
    "sg:address":"Eilveser Hauptstr. 106",
    "sg:city":"Neustadt",
    "sg:phone":"+49 5034/92300",
    "sg:postcode":"31535",
    "sg:province":"Niedersachsen",
    "wof:name":"Werner",
    "wof:placetype":"venue"
},
  "geometry": {"coordinates":[9.4006128311,52.5381889343],"type":"Point"}
}