{
  "type": "Feature",
  "properties": {
    "iso:country":"DE",
    "sg:address":"Kirchplatz 4",
    "sg:city":"Schwanau",
    "sg:phone":"+49 7824/2347",
    "sg:postcode":"77963",
    "sg:province":"Baden-W\u00fcrttemberg",
    "wof:name":"Ev. Pfarramt Allmannsweier",
    "wof:placetype":"venue"
},
  "geometry": {"coordinates":[7.7825231552,48.366897583],"type":"Point"}
}