{
  "type": "Feature",
  "properties": {
    "iso:country":"DE",
    "sg:address":"Am M\u00fchlenberg 27",
    "sg:city":"Northeim",
    "sg:phone":"+49 5551/2664",
    "sg:postcode":"37154",
    "sg:province":"Niedersachsen",
    "wof:name":"Gwf",
    "wof:placetype":"venue"
},
  "geometry": {"coordinates":[10.0532932281,51.6936264038],"type":"Point"}
}