{
  "type": "Feature",
  "properties": {
    "iso:country":"DE",
    "sg:address":"Egglhauser Str. 7",
    "sg:city":"Pfeffenhausen",
    "sg:phone":"+49 8782/353",
    "sg:postcode":"84076",
    "sg:province":"Bayern",
    "wof:name":"J. Schrott",
    "wof:placetype":"venue"
},
  "geometry": {"coordinates":[11.961435318,48.663684845],"type":"Point"}
}