{
  "type": "Feature",
  "properties": {
    "iso:country":"DE",
    "sg:address":"Eldeblick",
    "sg:city":"Matzlow-Garwitz",
    "sg:phone":"+49 38722/2270",
    "sg:postcode":"19372",
    "sg:province":"Mecklenburg-Vorpommern",
    "wof:name":"Kremke",
    "wof:placetype":"venue"
},
  "geometry": {"coordinates":[11.69643,53.450802],"type":"Point"}
}