{
  "type": "Feature",
  "properties": {
    "iso:country":"DE",
    "sg:address":"Lu\u00dfstr. 2",
    "sg:city":"Puchheim",
    "sg:phone":"+49 89/806815",
    "sg:postcode":"82178",
    "sg:province":"Bayern",
    "wof:name":"Ingrid K\u00f6llnberger",
    "wof:placetype":"venue"
},
  "geometry": {"coordinates":[11.350616,48.173309],"type":"Point"}
}