{
  "type": "Feature",
  "properties": {
    "iso:country":"DE",
    "sg:address":"Willmanndamm 15",
    "sg:city":"Berlin",
    "sg:phone":"+49 30/7811293",
    "sg:postcode":"10827",
    "sg:province":"Berlin",
    "wof:name":"Luckys Pizzeria",
    "wof:placetype":"venue"
},
  "geometry": {"coordinates":[13.3618307114,52.4902458191],"type":"Point"}
}