{
  "type": "Feature",
  "properties": {
    "iso:country":"DE",
    "sg:address":"Traunring 4",
    "sg:city":"Traunreut",
    "sg:phone":"+49 8669/2168",
    "sg:postcode":"83301",
    "sg:province":"Bayern",
    "wof:name":"Wolfgang Und Brigitte H\u00fcbner",
    "wof:placetype":"venue"
},
  "geometry": {"coordinates":[12.5864839554,47.9641418457],"type":"Point"}
}