{
  "type": "Feature",
  "properties": {
    "iso:country":"DE",
    "sg:address":"Adolf-Meyer-Str. 19",
    "sg:city":"Nienburg",
    "sg:phone":"+49 34721/22693",
    "sg:postcode":"06429",
    "sg:province":"Sachsen-Anhalt",
    "wof:name":"M. Koch",
    "wof:placetype":"venue"
},
  "geometry": {"coordinates":[11.766303,51.836674],"type":"Point"}
}