{
  "type": "Feature",
  "properties": {
    "iso:country":"DE",
    "sg:address":"Am S\u00fcdhang 14",
    "sg:city":"Oststeinbek",
    "sg:phone":"+49 40/7122871",
    "sg:postcode":"22113",
    "sg:province":"Schleswig-Holstein",
    "wof:name":"Il Mondo Gmbh",
    "wof:placetype":"venue"
},
  "geometry": {"coordinates":[10.1699237823,53.5386734009],"type":"Point"}
}