{
  "type": "Feature",
  "properties": {
    "iso:country":"DE",
    "sg:address":"Kapellstr. 38a",
    "sg:city":"Donauw\u00f6rth",
    "sg:phone":"+49 906/240112",
    "sg:postcode":"86609",
    "sg:province":"Bayern",
    "wof:name":"M. Scheis & Sohn Gmbh & Co. Kg",
    "wof:placetype":"venue"
},
  "geometry": {"coordinates":[10.783908844,48.7165107727],"type":"Point"}
}