{
  "type": "Feature",
  "properties": {
    "iso:country":"DE",
    "sg:address":"Dagobertweg 3",
    "sg:city":"Stuttgart",
    "sg:phone":"+49 711/332787",
    "sg:postcode":"70327",
    "sg:province":"Baden-W\u00fcrttemberg",
    "wof:name":"Friedinger",
    "wof:placetype":"venue"
},
  "geometry": {"coordinates":[9.2573890686,48.7884292603],"type":"Point"}
}