{
  "type": "Feature",
  "properties": {
    "iso:country":"DE",
    "sg:address":"Neust\u00e4dter Str. 1",
    "sg:city":"R\u00fcgland",
    "sg:phone":"+49 9828/230",
    "sg:postcode":"91622",
    "sg:province":"Bayern",
    "wof:name":"Ev. Luth. Pfarramt",
    "wof:placetype":"venue"
},
  "geometry": {"coordinates":[10.5864067078,49.4011573792],"type":"Point"}
}