{
  "type": "Feature",
  "properties": {
    "iso:country":"DE",
    "sg:address":"Seiferitzer Str. 1",
    "sg:city":"Dennheritz",
    "sg:phone":"+49 3763/78102",
    "sg:postcode":"08393",
    "sg:province":"Sachsen",
    "wof:name":"Verwaltungsgesellschaft Dennheritzer Agrarproduktion",
    "wof:placetype":"venue"
},
  "geometry": {"coordinates":[12.4861488342,50.8189315796],"type":"Point"}
}