{
  "type": "Feature",
  "properties": {
    "iso:country":"DE",
    "sg:address":"Ostenfelder Str. 104",
    "sg:city":"Husum",
    "sg:phone":"+49 4841/66500",
    "sg:postcode":"25813",
    "sg:province":"Schleswig-Holstein",
    "wof:name":"Hansen & Detlefsen Leimholz Gmbh",
    "wof:placetype":"venue"
},
  "geometry": {"coordinates":[9.0935163498,54.4707260132],"type":"Point"}
}