{
  "type": "Feature",
  "properties": {
    "iso:country":"DE",
    "sg:address":"Markusstr. 4",
    "sg:city":"Gro\u00dfenhain",
    "sg:phone":"+49 3522/62174",
    "sg:postcode":"01558",
    "sg:province":"Sachsen",
    "wof:name":"B. G\u00fcnther",
    "wof:placetype":"venue"
},
  "geometry": {"coordinates":[13.5371236801,51.2862892151],"type":"Point"}
}