{
  "type": "Feature",
  "properties": {
    "iso:country":"DE",
    "sg:address":"Adolf-Reichwein-Str. 9",
    "sg:city":"Frankfurt",
    "sg:phone":"+49 69/563421",
    "sg:postcode":"60320",
    "sg:province":"Hessen",
    "wof:name":"Heinz G\u00fcnter Grein",
    "wof:placetype":"venue"
},
  "geometry": {"coordinates":[8.6734657288,50.1434173584],"type":"Point"}
}