{
  "type": "Feature",
  "properties": {
    "iso:country":"DE",
    "sg:address":"Lerchenstr. 62",
    "sg:city":"Winterbach",
    "sg:phone":"+49 7181/73082",
    "sg:postcode":"73650",
    "sg:province":"Baden-W\u00fcrttemberg",
    "wof:name":"S. Piernikaczyk Hebamme",
    "wof:placetype":"venue"
},
  "geometry": {"coordinates":[9.486725,48.797417],"type":"Point"}
}