{
  "type": "Feature",
  "properties": {
    "iso:country":"DE",
    "sg:address":"Am Alten Stauwehr 12",
    "sg:city":"Meckenheim",
    "sg:phone":"+49 2225/94240",
    "sg:postcode":"53340",
    "sg:province":"Nordrhein-Westfalen",
    "wof:name":"Karl-heinz Mrusek",
    "wof:placetype":"venue"
},
  "geometry": {"coordinates":[7.0195798874,50.6348609924],"type":"Point"}
}