{
  "type": "Feature",
  "properties": {
    "iso:country":"DE",
    "sg:address":"Wiesenstr. 24",
    "sg:city":"Neu-Isenburg",
    "sg:phone":"+49 6102/34193",
    "sg:postcode":"63263",
    "sg:province":"Hessen",
    "wof:name":"G. Sporket",
    "wof:placetype":"venue"
},
  "geometry": {"coordinates":[8.699109,50.056007],"type":"Point"}
}