{
  "type": "Feature",
  "properties": {
    "iso:country":"DE",
    "sg:address":"St. Georgener Str. 74",
    "sg:city":"Hardt",
    "sg:phone":"+49 7422/20728",
    "sg:postcode":"78739",
    "sg:province":"Baden-W\u00fcrttemberg",
    "wof:name":"Helmut Laufer",
    "wof:placetype":"venue"
},
  "geometry": {"coordinates":[8.4105396271,48.1839408875],"type":"Point"}
}