{
  "type": "Feature",
  "properties": {
    "iso:country":"DE",
    "sg:address":"Neuwiesenstr. 20",
    "sg:city":"Frankfurt",
    "sg:phone":"+49 69/672871",
    "sg:postcode":"60528",
    "sg:province":"Hessen",
    "wof:name":"Walter Und Wolfram Nicol Architekten",
    "wof:placetype":"venue"
},
  "geometry": {"coordinates":[8.651145,50.079967],"type":"Point"}
}