{
  "type": "Feature",
  "properties": {
    "iso:country":"DE",
    "sg:address":"Reginastr. 8",
    "sg:city":"G\u00fctersloh",
    "sg:phone":"+49 5241/79841",
    "sg:postcode":"33335",
    "sg:province":"Nordrhein-Westfalen",
    "wof:name":"G\u00fcnther Schubert Architekt",
    "wof:placetype":"venue"
},
  "geometry": {"coordinates":[8.428237,51.90741],"type":"Point"}
}