{
  "type": "Feature",
  "properties": {
    "iso:country":"DE",
    "sg:address":"Pferdemarkt 8",
    "sg:city":"Stade",
    "sg:phone":"+49 4141/3610",
    "sg:postcode":"21682",
    "sg:province":"Niedersachsen",
    "wof:name":"Gwu Gewerbe- Und Wohnungs- Bau Unterelbe Gmbh + Co. Kg",
    "wof:placetype":"venue"
},
  "geometry": {"coordinates":[9.475457,53.599739],"type":"Point"}
}