{
  "type": "Feature",
  "properties": {
    "iso:country":"DE",
    "sg:address":"Kasseler Str. 53",
    "sg:city":"Kirchhain",
    "sg:postcode":"35274",
    "sg:province":"Hessen",
    "wof:name":"Baumbach-verwaltungs Gmbh",
    "wof:placetype":"venue"
},
  "geometry": {"coordinates":[8.920583,50.830605],"type":"Point"}
}