{
  "type": "Feature",
  "properties": {
    "iso:country":"DE",
    "sg:address":"Wilhelm-Hauff-Str. 2-4",
    "sg:city":"Frankfurt",
    "sg:postcode":"60325",
    "sg:province":"Hessen",
    "wof:name":"Belmaks Infotech Gmbh",
    "wof:placetype":"venue"
},
  "geometry": {"coordinates":[8.65505,50.112598],"type":"Point"}
}