{
  "type": "Feature",
  "properties": {
    "iso:country":"DE",
    "sg:address":"Siegburger Str. 143",
    "sg:city":"Bonn",
    "sg:phone":"+49 228/421170",
    "sg:postcode":"53229",
    "sg:province":"Nordrhein-Westfalen",
    "wof:name":"Farnschl\u00e4der Assekuranz Versicherungsbetreuungs- Und",
    "wof:placetype":"venue"
},
  "geometry": {"coordinates":[7.1396708488,50.7446098328],"type":"Point"}
}