{
  "type": "Feature",
  "properties": {
    "iso:country":"DE",
    "sg:address":"Gro\u00dfe Str. 26",
    "sg:city":"Dissen",
    "sg:phone":"+49 5421/2654",
    "sg:postcode":"49201",
    "sg:province":"Niedersachsen",
    "wof:name":"Erich Rannacher Elektro Rundfunkmech. Meister",
    "wof:placetype":"venue"
},
  "geometry": {"coordinates":[8.203049,52.115082],"type":"Point"}
}