{
  "type": "Feature",
  "properties": {
    "iso:country":"DE",
    "sg:address":"Jahnstr. 6",
    "sg:city":"Idar-Oberstein",
    "sg:phone":"+49 6781/27759",
    "sg:postcode":"55743",
    "sg:province":"Rheinland-Pfalz",
    "wof:name":"Jahnklause",
    "wof:placetype":"venue"
},
  "geometry": {"coordinates":[7.3295311928,49.7023544312],"type":"Point"}
}