{
  "type": "Feature",
  "properties": {
    "iso:country":"DE",
    "sg:address":"Marktstr. 15",
    "sg:city":"Rheine",
    "sg:postcode":"48431",
    "sg:province":"Nordrhein-Westfalen",
    "wof:name":"J. Fernandes Gmbh",
    "wof:placetype":"venue"
},
  "geometry": {"coordinates":[7.436621,52.279091],"type":"Point"}
}