{
  "type": "Feature",
  "properties": {
    "iso:country":"DE",
    "sg:address":"Hauptstr.",
    "sg:city":"Hohenleipisch",
    "sg:postcode":"04934",
    "sg:province":"Brandenburg",
    "wof:name":"Allianz Dvag G. Neustadt",
    "wof:placetype":"venue"
},
  "geometry": {"coordinates":[13.5447187424,51.4865112305],"type":"Point"}
}