{
  "type": "Feature",
  "properties": {
    "iso:country":"DE",
    "sg:address":"Hannoversche Stra\u00dfe 144",
    "sg:city":"G\u00f6ttingen",
    "sg:phone":"+49 551/55041",
    "sg:postcode":"37077",
    "sg:province":"Niedersachsen",
    "wof:name":"Atelier Timm",
    "wof:placetype":"venue"
},
  "geometry": {"coordinates":[9.932005,51.563995],"type":"Point"}
}