{
  "type": "Feature",
  "properties": {
    "iso:country":"DE",
    "sg:address":"Maubes 3a",
    "sg:city":"Solingen",
    "sg:phone":"+49 212",
    "sg:postcode":"42697",
    "sg:province":"Nordrhein-Westfalen",
    "wof:name":"Spanien Immobilien H.oberstrahs",
    "wof:placetype":"venue"
},
  "geometry": {"coordinates":[7.0013608932,51.1728248596],"type":"Point"}
}