{
  "type": "Feature",
  "properties": {
    "iso:country":"DE",
    "sg:address":"Mauritiusweg 4",
    "sg:city":"Rottenburg",
    "sg:phone":"+49 8785/1002",
    "sg:postcode":"84056",
    "sg:province":"Bayern",
    "wof:name":"E. Zeller",
    "wof:placetype":"venue"
},
  "geometry": {"coordinates":[12.086143,48.74144],"type":"Point"}
}