{
  "type": "Feature",
  "properties": {
    "iso:country":"DE",
    "sg:address":"Eckstr. 8",
    "sg:city":"Erftstadt",
    "sg:phone":"+49 2235/955650",
    "sg:postcode":"50374",
    "sg:province":"Nordrhein-Westfalen",
    "wof:name":"Rape- Handelsvertretung Gmbh",
    "wof:placetype":"venue"
},
  "geometry": {"coordinates":[6.7705850601,50.7379989624],"type":"Point"}
}