{
  "type": "Feature",
  "properties": {
    "iso:country":"DE",
    "sg:address":"Dudweilerstr. 2 a",
    "sg:city":"Saarbr\u00fccken",
    "sg:phone":"+49 681/34318",
    "sg:postcode":"66111",
    "sg:province":"Saarland",
    "wof:name":"E. Cremer Ballettschule",
    "wof:placetype":"venue"
},
  "geometry": {"coordinates":[6.9945287704,49.2351379395],"type":"Point"}
}