{
  "type": "Feature",
  "properties": {
    "iso:country":"DE",
    "sg:address":"Rietburgstr. 30",
    "sg:city":"Dannstadt-Schauernheim",
    "sg:phone":"+49 6231/2703",
    "sg:postcode":"67125",
    "sg:province":"Rheinland-Pfalz",
    "wof:name":"Ria Friedrich",
    "wof:placetype":"venue"
},
  "geometry": {"coordinates":[8.315978,49.422436],"type":"Point"}
}