{
  "type": "Feature",
  "properties": {
    "iso:country":"DE",
    "sg:address":"Laerer Str. 27",
    "sg:city":"Sassenberg",
    "sg:phone":"+49 5426/2319",
    "sg:postcode":"48336",
    "sg:province":"Nordrhein-Westfalen",
    "wof:name":"Willi Und Angela Buddenkotte",
    "wof:placetype":"venue"
},
  "geometry": {"coordinates":[8.0607118607,52.0643806458],"type":"Point"}
}