{
  "type": "Feature",
  "properties": {
    "iso:country":"DE",
    "sg:address":"Bahnhofstr. 23",
    "sg:city":"Speichersdorf",
    "sg:phone":"+49 9275/1237",
    "sg:postcode":"95469",
    "sg:province":"Bayern",
    "wof:name":"Gerdas Gaststube",
    "wof:placetype":"venue"
},
  "geometry": {"coordinates":[11.776049614,49.8705062866],"type":"Point"}
}