{
  "type": "Feature",
  "properties": {
    "iso:country":"DE",
    "sg:address":"Soester Str. 11 a",
    "sg:city":"Kleve",
    "sg:phone":"+49 2821/505704",
    "sg:postcode":"47533",
    "sg:province":"Nordrhein-Westfalen",
    "wof:name":"Thomas Karow Heilpraktiker",
    "wof:placetype":"venue"
},
  "geometry": {"coordinates":[6.1372442245,51.7761726379],"type":"Point"}
}