{
  "type": "Feature",
  "properties": {
    "iso:country":"DE",
    "sg:address":"Marktplatz 24",
    "sg:city":"B\u00f6blingen",
    "sg:postcode":"71032",
    "sg:province":"Baden-W\u00fcrttemberg",
    "wof:name":"Usb Prohaska E. K.",
    "wof:placetype":"venue"
},
  "geometry": {"coordinates":[9.0118532181,48.6848297119],"type":"Point"}
}