{
  "type": "Feature",
  "properties": {
    "iso:country":"DE",
    "sg:address":"Tittmoninger Str. 21",
    "sg:city":"Burghausen",
    "sg:phone":"+49 8677/7034",
    "sg:postcode":"84489",
    "sg:province":"Bayern",
    "wof:name":"Oberbayern Gmbh & Co. Kg",
    "wof:placetype":"venue"
},
  "geometry": {"coordinates":[12.8328838348,48.1583557129],"type":"Point"}
}