{
  "type": "Feature",
  "properties": {
    "iso:country":"DE",
    "sg:address":"Neukrug 1",
    "sg:city":"Schuby",
    "sg:phone":"+49 4621/4793",
    "sg:postcode":"24850",
    "sg:province":"Schleswig-Holstein",
    "wof:name":"Bent Jensen-nissen",
    "wof:placetype":"venue"
},
  "geometry": {"coordinates":[9.508037,54.527588],"type":"Point"}
}