{
  "type": "Feature",
  "properties": {
    "iso:country":"DE",
    "sg:address":"Dorfstr. 5",
    "sg:city":"Bolsterlang",
    "sg:phone":"+49 8326/36260",
    "sg:postcode":"87538",
    "sg:province":"Bayern",
    "wof:name":"Hermann Schmid",
    "wof:placetype":"venue"
},
  "geometry": {"coordinates":[10.232862,47.460869],"type":"Point"}
}