{
  "type": "Feature",
  "properties": {
    "iso:country":"DE",
    "sg:address":"Kaiserstr. 57",
    "sg:city":"M\u00fclheim",
    "sg:phone":"+49 208/32722",
    "sg:postcode":"45468",
    "sg:province":"Nordrhein-Westfalen",
    "wof:name":"Kaiser-friedrich-apotheke",
    "wof:placetype":"venue"
},
  "geometry": {"coordinates":[6.888572,51.426132],"type":"Point"}
}