{
  "type": "Feature",
  "properties": {
    "iso:country":"DE",
    "sg:address":"Rehbockstr. 24",
    "sg:city":"Celle",
    "sg:postcode":"29225",
    "sg:province":"Niedersachsen",
    "wof:name":"E. B. S. Erdgas Betankungs Systeme Gmbh & Co. Kg",
    "wof:placetype":"venue"
},
  "geometry": {"coordinates":[10.046527,52.606079],"type":"Point"}
}