{
  "type": "Feature",
  "properties": {
    "iso:country":"DE",
    "sg:address":"Metzstr. 18",
    "sg:city":"K\u00f6tzting",
    "sg:phone":"+49 9941/904813",
    "sg:postcode":"93444",
    "sg:province":"Bayern",
    "wof:name":"H. Wolf",
    "wof:placetype":"venue"
},
  "geometry": {"coordinates":[12.856164,49.177261],"type":"Point"}
}