{
  "type": "Feature",
  "properties": {
    "iso:country":"DE",
    "sg:address":"Heerdter Lohweg 226b",
    "sg:city":"D\u00fcsseldorf",
    "sg:phone":"+49 211/5374750",
    "sg:postcode":"40549",
    "sg:province":"Nordrhein-Westfalen",
    "wof:name":"Norbert Sch\u00e4fer",
    "wof:placetype":"venue"
},
  "geometry": {"coordinates":[6.7278289795,51.2379722595],"type":"Point"}
}