{
  "type": "Feature",
  "properties": {
    "iso:country":"DE",
    "sg:address":"Fennastr. 69",
    "sg:city":"Nordhorn",
    "sg:phone":"+49 4959/2171000",
    "sg:postcode":"48529",
    "sg:province":"Niedersachsen",
    "wof:name":"Peters Nahrungsmittel Gmbh",
    "wof:placetype":"venue"
},
  "geometry": {"coordinates":[7.059601,52.40575],"type":"Point"}
}