{
  "type": "Feature",
  "properties": {
    "iso:country":"DE",
    "sg:address":"Klaushager Weg 22",
    "sg:city":"Berlin",
    "sg:phone":"+49 30/4043273",
    "sg:postcode":"13467",
    "sg:province":"Berlin",
    "wof:name":"Almut Eickhoff",
    "wof:placetype":"venue"
},
  "geometry": {"coordinates":[13.2964038849,52.6185874939],"type":"Point"}
}