{
  "type": "Feature",
  "properties": {
    "iso:country":"DE",
    "sg:address":"An der Mangfall 2",
    "sg:city":"Rosenheim",
    "sg:postcode":"83026",
    "sg:province":"Bayern",
    "wof:name":"Hauser Naturstein Gmbh",
    "wof:placetype":"venue"
},
  "geometry": {"coordinates":[12.086153,47.844055],"type":"Point"}
}