{
  "type": "Feature",
  "properties": {
    "iso:country":"DE",
    "sg:address":"Bahnhofstr 55",
    "sg:city":"Rietberg",
    "sg:phone":"+49 5244/983331",
    "sg:postcode":"33397",
    "sg:province":"Nordrhein-Westfalen",
    "wof:name":"Rietbergwerke Gmbh & Co. Kg Beh\u00e4ltertechnik",
    "wof:placetype":"venue"
},
  "geometry": {"coordinates":[8.429479,51.816742],"type":"Point"}
}