{
  "type": "Feature",
  "properties": {
    "iso:country":"DE",
    "sg:address":"Bielefelder Str 7",
    "sg:city":"Hilter",
    "sg:phone":"+49 4954/2437584",
    "sg:postcode":"49176",
    "sg:province":"Niedersachsen",
    "wof:name":"Kreissparkasse Osnabr\u00fcck",
    "wof:placetype":"venue"
},
  "geometry": {"coordinates":[8.147061,52.138214],"type":"Point"}
}