{
  "type": "Feature",
  "properties": {
    "iso:country":"DE",
    "sg:address":"Paul-Lincke-Str. 6",
    "sg:city":"Neu-Ulm",
    "sg:phone":"+49 731/78963",
    "sg:postcode":"89231",
    "sg:province":"Bayern",
    "wof:name":"Resa-transport Gmbh",
    "wof:placetype":"venue"
},
  "geometry": {"coordinates":[10.0217752457,48.4049453735],"type":"Point"}
}