{
  "type": "Feature",
  "properties": {
    "iso:country":"DE",
    "sg:address":"Fuchshofstr. 36",
    "sg:city":"Ludwigsburg",
    "sg:phone":"+49 7141/81475",
    "sg:postcode":"71638",
    "sg:province":"Baden-W\u00fcrttemberg",
    "wof:name":"Ruth Seidenspinner",
    "wof:placetype":"venue"
},
  "geometry": {"coordinates":[9.2065229416,48.8941116333],"type":"Point"}
}