{
  "type": "Feature",
  "properties": {
    "iso:country":"DE",
    "sg:address":"Saalfelder Str. 87",
    "sg:city":"Schmiedefeld",
    "sg:phone":"+49 36701/61597",
    "sg:postcode":"98739",
    "sg:province":"Th\u00fcringen",
    "wof:name":"G. Walther",
    "wof:placetype":"venue"
},
  "geometry": {"coordinates":[11.2169103622,50.5363540649],"type":"Point"}
}