{
  "type": "Feature",
  "properties": {
    "iso:country":"DE",
    "sg:address":"St. Johanner Str. 58",
    "sg:city":"Saarbr\u00fccken",
    "sg:postcode":"66125",
    "sg:province":"Saarland",
    "wof:name":"Gfm Ges. F\u00fcr Mittel- Standsberatung Mbh",
    "wof:placetype":"venue"
},
  "geometry": {"coordinates":[7.009349,49.267666],"type":"Point"}
}