{
  "type": "Feature",
  "properties": {
    "iso:country":"DE",
    "sg:address":"Rawiestr. 7",
    "sg:city":"Osnabr\u00fcck",
    "sg:phone":"+49 541/707646",
    "sg:postcode":"49084",
    "sg:province":"Niedersachsen",
    "wof:name":"Interdomus Heimtex Gmbh",
    "wof:placetype":"venue"
},
  "geometry": {"coordinates":[8.086995,52.270382],"type":"Point"}
}