{
  "type": "Feature",
  "properties": {
    "iso:country":"DE",
    "sg:address":"Georgstr. 9",
    "sg:city":"Twist",
    "sg:phone":"+49 5936/6981",
    "sg:postcode":"49767",
    "sg:province":"Niedersachsen",
    "wof:name":"Gerhard Schnieders",
    "wof:placetype":"venue"
},
  "geometry": {"coordinates":[7.058768,52.633129],"type":"Point"}
}