{
  "type": "Feature",
  "properties": {
    "iso:country":"DE",
    "sg:address":"Wessobrunner Str. 20",
    "sg:city":"Gauting",
    "sg:phone":"+49 89/89890759",
    "sg:postcode":"82131",
    "sg:province":"Bayern",
    "wof:name":"Werkstatt Gmbh",
    "wof:placetype":"venue"
},
  "geometry": {"coordinates":[11.361836,48.068546],"type":"Point"}
}