{
  "type": "Feature",
  "properties": {
    "iso:country":"DE",
    "sg:address":"Allerm\u00f6her Deich 401",
    "sg:city":"Hamburg",
    "sg:phone":"+49 40/7231267",
    "sg:postcode":"21037",
    "sg:province":"Hamburg",
    "wof:name":"Ingo M\u00fcller",
    "wof:placetype":"venue"
},
  "geometry": {"coordinates":[10.1709699631,53.4724121094],"type":"Point"}
}