{
  "type": "Feature",
  "properties": {
    "iso:country":"DE",
    "sg:address":"Kelterstr. 41",
    "sg:city":"Birkenfeld",
    "sg:phone":"+49 7082/2229",
    "sg:postcode":"75217",
    "sg:province":"Baden-W\u00fcrttemberg",
    "wof:name":"G. Kull",
    "wof:placetype":"venue"
},
  "geometry": {"coordinates":[8.586195,48.873863],"type":"Point"}
}