{
  "type": "Feature",
  "properties": {
    "iso:country":"DE",
    "sg:address":"Dufkampstr. 55",
    "sg:city":"Stadtlohn",
    "sg:phone":"+49 2563/6679",
    "sg:postcode":"48703",
    "sg:province":"Nordrhein-Westfalen",
    "wof:name":"Marlies Wirtz",
    "wof:placetype":"venue"
},
  "geometry": {"coordinates":[6.923839,51.993256],"type":"Point"}
}