{
  "type": "Feature",
  "properties": {
    "iso:country":"DE",
    "sg:address":"Auenstr. 10",
    "sg:city":"K\u00fchbach",
    "sg:phone":"+49 8251/87990",
    "sg:postcode":"86556",
    "sg:province":"Bayern",
    "wof:name":"Heinrich Ballas",
    "wof:placetype":"venue"
},
  "geometry": {"coordinates":[11.190561,48.494267],"type":"Point"}
}