{
  "type": "Feature",
  "properties": {
    "iso:country":"DE",
    "sg:address":"Poststr. 18",
    "sg:city":"Bad Berleburg",
    "sg:phone":"+49 2751/928000",
    "sg:postcode":"57319",
    "sg:province":"Nordrhein-Westfalen",
    "wof:name":"Heka-textilvertrieb Nkd-gmbh",
    "wof:placetype":"venue"
},
  "geometry": {"coordinates":[8.392408371,51.050743103],"type":"Point"}
}