{
  "type": "Feature",
  "properties": {
    "iso:country":"DE",
    "sg:address":"Isargestade 737",
    "sg:city":"Landshut",
    "sg:phone":"+49 871/89378",
    "sg:postcode":"84028",
    "sg:province":"Bayern",
    "wof:name":"G. St\u00e4rz Immobilienmakler",
    "wof:placetype":"venue"
},
  "geometry": {"coordinates":[12.1527080536,48.5400733948],"type":"Point"}
}