{
  "type": "Feature",
  "properties": {
    "iso:country":"DE",
    "sg:address":"Naglerstr. 2b",
    "sg:city":"Pforzheim",
    "sg:phone":"+49 4972/3151066",
    "sg:postcode":"75175",
    "sg:province":"Baden-W\u00fcrttemberg",
    "wof:name":"Yabi-spirit Creative Brillen Gmbh",
    "wof:placetype":"venue"
},
  "geometry": {"coordinates":[8.7231760025,48.8977279663],"type":"Point"}
}