{
  "type": "Feature",
  "properties": {
    "iso:country":"DE",
    "sg:address":"Bahnhofstr. 21",
    "sg:city":"Trittau",
    "sg:phone":"+49 4154/2500",
    "sg:postcode":"22946",
    "sg:province":"Schleswig-Holstein",
    "wof:name":"Schmidt Und Neitzel Rechtsanw\u00e4lte Und Notar",
    "wof:placetype":"venue"
},
  "geometry": {"coordinates":[10.4030151367,53.6176261902],"type":"Point"}
}