{
  "type": "Feature",
  "properties": {
    "iso:country":"DE",
    "sg:address":"Steinbach 8",
    "sg:city":"Rothenburg",
    "sg:phone":"+49 9861/8350",
    "sg:postcode":"91541",
    "sg:province":"Bayern",
    "wof:name":"Schneider Gartengestaltung",
    "wof:placetype":"venue"
},
  "geometry": {"coordinates":[10.162492,49.403622],"type":"Point"}
}