{
  "type": "Feature",
  "properties": {
    "iso:country":"DE",
    "sg:address":"Ludwigstr. 11",
    "sg:city":"Garmisch-Partenkirchen",
    "sg:phone":"+49 8821/2652",
    "sg:postcode":"82467",
    "sg:province":"Bayern",
    "wof:name":"Georg Neuner",
    "wof:placetype":"venue"
},
  "geometry": {"coordinates":[11.112951,47.492207],"type":"Point"}
}