{
  "type": "Feature",
  "properties": {
    "iso:country":"DE",
    "sg:address":"Wachtstr. 17-24",
    "sg:city":"Bremen",
    "sg:phone":"+49 421/363280",
    "sg:postcode":"28195",
    "sg:province":"Bremen",
    "wof:name":"Global Assekuranz Vermittlungsges. Mbh",
    "wof:placetype":"venue"
},
  "geometry": {"coordinates":[8.8068180084,53.07472229],"type":"Point"}
}