{
  "type": "Feature",
  "properties": {
    "iso:country":"DE",
    "sg:address":"Greifensteinstr. 22",
    "sg:city":"Thum",
    "sg:phone":"+49 37297/2629",
    "sg:postcode":"09419",
    "sg:province":"Sachsen",
    "wof:name":"Baldaufs Einkehr",
    "wof:placetype":"venue"
},
  "geometry": {"coordinates":[12.9471750259,50.6687164307],"type":"Point"}
}