{
  "type": "Feature",
  "properties": {
    "iso:country":"DE",
    "sg:address":"Bahnhofstr. 4",
    "sg:city":"Karlsruhe",
    "sg:postcode":"76137",
    "sg:province":"Baden-W\u00fcrttemberg",
    "wof:name":"Petra Lindig Gmbh",
    "wof:placetype":"venue"
},
  "geometry": {"coordinates":[8.394696,49.000443],"type":"Point"}
}