{
  "type": "Feature",
  "properties": {
    "iso:country":"DE",
    "sg:address":"Zossener Str. 24",
    "sg:city":"Glienick",
    "sg:phone":"+49 3377/30460",
    "sg:postcode":"15806",
    "sg:province":"Brandenburg",
    "wof:name":"Engelbrecht Spielplatz- Ger\u00e4te Gmbh",
    "wof:placetype":"venue"
},
  "geometry": {"coordinates":[13.3829278946,52.2469177246],"type":"Point"}
}