{
  "type": "Feature",
  "properties": {
    "iso:country":"DE",
    "sg:address":"Kirchgasse 4",
    "sg:city":"Seckach",
    "sg:phone":"+49 6293/370",
    "sg:postcode":"74743",
    "sg:province":"Baden-W\u00fcrttemberg",
    "wof:name":"Ev. Pfarramt Gem. Grosseicholzheim",
    "wof:placetype":"venue"
},
  "geometry": {"coordinates":[9.2906980515,49.4444046021],"type":"Point"}
}