{
  "type": "Feature",
  "properties": {
    "iso:country":"DE",
    "sg:address":"Berliner Str. 30",
    "sg:city":"Wusterhausen",
    "sg:phone":"+49 33979/14619",
    "sg:postcode":"16868",
    "sg:province":"Brandenburg",
    "wof:name":"M. Opitz",
    "wof:placetype":"venue"
},
  "geometry": {"coordinates":[12.462755,52.885155],"type":"Point"}
}