{
  "type": "Feature",
  "properties": {
    "iso:country":"DE",
    "sg:address":"Praterinsel 5",
    "sg:city":"M\u00fcnchen",
    "sg:phone":"+49 89/23509053",
    "sg:postcode":"80538",
    "sg:province":"Bayern",
    "wof:name":"Alpenvereins-b\u00fccherei",
    "wof:placetype":"venue"
},
  "geometry": {"coordinates":[11.589003,48.135147],"type":"Point"}
}