{
  "type": "Feature",
  "properties": {
    "iso:country":"DE",
    "sg:address":"Solla",
    "sg:city":"Waldkirchen",
    "sg:phone":"+49 8581/4129",
    "sg:postcode":"94065",
    "sg:province":"Bayern",
    "wof:name":"Stockinger",
    "wof:placetype":"venue"
},
  "geometry": {"coordinates":[13.64112,48.755054],"type":"Point"}
}