{
  "type": "Feature",
  "properties": {
    "iso:country":"DE",
    "sg:address":"Rheinallee 24",
    "sg:city":"Mainz",
    "sg:phone":"+49 6131/611854",
    "sg:postcode":"55118",
    "sg:province":"Rheinland-Pfalz",
    "wof:name":"Rheinklause",
    "wof:placetype":"venue"
},
  "geometry": {"coordinates":[8.2656345367,50.0103111267],"type":"Point"}
}