{
  "type": "Feature",
  "properties": {
    "iso:country":"DE",
    "sg:address":"Altenessener Str. 589",
    "sg:city":"Essen",
    "sg:phone":"+49 201/342288",
    "sg:postcode":"45329",
    "sg:province":"Nordrhein-Westfalen",
    "wof:name":"K. H. Eicker",
    "wof:placetype":"venue"
},
  "geometry": {"coordinates":[7.006931,51.509644],"type":"Point"}
}