{
  "type": "Feature",
  "properties": {
    "iso:country":"DE",
    "sg:address":"M\u00fcnchener Str. 11",
    "sg:city":"Mering",
    "sg:phone":"+49 8233/3880",
    "sg:postcode":"86415",
    "sg:province":"Bayern",
    "wof:name":"Kissing - Mering Eg",
    "wof:placetype":"venue"
},
  "geometry": {"coordinates":[10.986537,48.266544],"type":"Point"}
}