{
  "type": "Feature",
  "properties": {
    "iso:country":"DE",
    "sg:address":"Erlenstr. 10",
    "sg:city":"Gai\u00dfach",
    "sg:phone":"+49 8041/78040",
    "sg:postcode":"83674",
    "sg:province":"Bayern",
    "wof:name":"Precupa Pr\u00c4zisions & Kunsttechnik Znl. Mewag Gmbh",
    "wof:placetype":"venue"
},
  "geometry": {"coordinates":[11.580109,47.747829],"type":"Point"}
}