{
  "type": "Feature",
  "properties": {
    "iso:country":"DE",
    "sg:address":"Rathausstr. 6",
    "sg:city":"Waldmohr",
    "sg:phone":"+49 6373/9322",
    "sg:postcode":"66914",
    "sg:province":"Rheinland-Pfalz",
    "wof:name":"Collmar & Co. Kg",
    "wof:placetype":"venue"
},
  "geometry": {"coordinates":[7.3330597878,49.3871040344],"type":"Point"}
}