{
  "type": "Feature",
  "properties": {
    "iso:country":"DE",
    "sg:address":"Am Krankenhaus 5-7",
    "sg:city":"Stadthagen",
    "sg:phone":"+49 5721/74091",
    "sg:postcode":"31655",
    "sg:province":"Niedersachsen",
    "wof:name":"Kreisaltenzentrum",
    "wof:placetype":"venue"
},
  "geometry": {"coordinates":[9.211817,52.320564],"type":"Point"}
}