{
  "type": "Feature",
  "properties": {
    "iso:country":"DE",
    "sg:address":"An der Bastion 44",
    "sg:city":"Berlin",
    "sg:phone":"+49 30/3652404",
    "sg:postcode":"14089",
    "sg:province":"Berlin",
    "wof:name":"J\u00fcrgen Herhold",
    "wof:placetype":"venue"
},
  "geometry": {"coordinates":[13.1327314377,52.4640464783],"type":"Point"}
}