{
  "type": "Feature",
  "properties": {
    "iso:country":"DE",
    "sg:address":"Forchenstr 12",
    "sg:city":"Wurmberg",
    "sg:phone":"+49 7044/940681",
    "sg:postcode":"75449",
    "sg:province":"Baden-W\u00fcrttemberg",
    "wof:name":"Rain Electronics Gmbh",
    "wof:placetype":"venue"
},
  "geometry": {"coordinates":[8.795839,48.878628],"type":"Point"}
}