{
  "type": "Feature",
  "properties": {
    "iso:country":"DE",
    "sg:address":"Achterdeich 45",
    "sg:city":"Stelle",
    "sg:phone":"+49 4174/2447",
    "sg:postcode":"21435",
    "sg:province":"Niedersachsen",
    "wof:name":"Peter Meyer",
    "wof:placetype":"venue"
},
  "geometry": {"coordinates":[10.119671,53.384476],"type":"Point"}
}