{
  "type": "Feature",
  "properties": {
    "iso:country":"DE",
    "sg:address":"Rheinstr. 22",
    "sg:city":"Neu-Isenburg",
    "sg:phone":"+49 6102/800081",
    "sg:postcode":"63263",
    "sg:province":"Hessen",
    "wof:name":"Ingo-lutz Stra\u00dfburger Rechtsanwalt Und Notar",
    "wof:placetype":"venue"
},
  "geometry": {"coordinates":[8.689002037,50.0542564392],"type":"Point"}
}