{
  "type": "Feature",
  "properties": {
    "iso:country":"DE",
    "sg:address":"Ubierstr. 9 - 11",
    "sg:city":"Emden",
    "sg:postcode":"26723",
    "sg:province":"Niedersachsen",
    "wof:name":"Hummerich Verwaltungsges. Mbh",
    "wof:placetype":"venue"
},
  "geometry": {"coordinates":[7.18974,53.369621],"type":"Point"}
}