{
  "type": "Feature",
  "properties": {
    "iso:country":"DE",
    "sg:address":"Hauptstr 68",
    "sg:city":"Hofheim",
    "sg:phone":"+49 6192/28801",
    "sg:postcode":"65719",
    "sg:province":"Hessen",
    "wof:name":"Hofheimer Zeitung Verlagsges. Mbh",
    "wof:placetype":"venue"
},
  "geometry": {"coordinates":[8.443421,50.086201],"type":"Point"}
}