{
  "type": "Feature",
  "properties": {
    "iso:country":"DE",
    "sg:address":"Ritterstr. 1",
    "sg:city":"Bad Sch\u00f6nborn",
    "sg:phone":"+49 7253/4184",
    "sg:postcode":"76669",
    "sg:province":"Baden-W\u00fcrttemberg",
    "wof:name":"T. Gander",
    "wof:placetype":"venue"
},
  "geometry": {"coordinates":[8.6541795731,49.2208900452],"type":"Point"}
}