{
  "type": "Feature",
  "properties": {
    "iso:country":"DE",
    "sg:address":"Lindenstr. 32",
    "sg:city":"Bramsche",
    "sg:phone":"+49 5461/4366",
    "sg:postcode":"49565",
    "sg:province":"Niedersachsen",
    "wof:name":"Kath. Pfarrb\u00fccherei St. Martinus",
    "wof:placetype":"venue"
},
  "geometry": {"coordinates":[7.976696,52.414303],"type":"Point"}
}