{
  "type": "Feature",
  "properties": {
    "iso:country":"DE",
    "sg:address":"Bizetstr. 24",
    "sg:city":"Berlin",
    "sg:postcode":"13088",
    "sg:province":"Berlin",
    "wof:name":"Ram Consult Gmbh",
    "wof:placetype":"venue"
},
  "geometry": {"coordinates":[13.451625,52.547192],"type":"Point"}
}