{
  "type": "Feature",
  "properties": {
    "iso:country":"DE",
    "sg:address":"Ostpreu\u00dfenstr. 10",
    "sg:city":"Burgau",
    "sg:phone":"+49 8222/90060",
    "sg:postcode":"89331",
    "sg:province":"Bayern",
    "wof:name":"W. St\u00fctz",
    "wof:placetype":"venue"
},
  "geometry": {"coordinates":[10.4218196869,48.4266929626],"type":"Point"}
}