{
  "type": "Feature",
  "properties": {
    "iso:country":"DE",
    "sg:address":"Binger Gasse 18",
    "sg:city":"Boppard",
    "sg:phone":"+49 6742/4430",
    "sg:postcode":"56154",
    "sg:province":"Rheinland-Pfalz",
    "wof:name":"Adolf Kutzler",
    "wof:placetype":"venue"
},
  "geometry": {"coordinates":[7.5961561203,50.2308311462],"type":"Point"}
}