{
  "type": "Feature",
  "properties": {
    "iso:country":"DE",
    "sg:address":"Kuckucksweg 44",
    "sg:city":"Wietzen",
    "sg:phone":"+49 5022/1666",
    "sg:postcode":"31613",
    "sg:province":"Niedersachsen",
    "wof:name":"Horsemans Home",
    "wof:placetype":"venue"
},
  "geometry": {"coordinates":[9.076712,52.719826],"type":"Point"}
}