{
  "type": "Feature",
  "properties": {
    "iso:country":"DE",
    "sg:address":"Juliusstr. 14",
    "sg:city":"Siegen",
    "sg:phone":"+49 271/51886",
    "sg:postcode":"57072",
    "sg:province":"Nordrhein-Westfalen",
    "wof:name":"Helmut Klahr",
    "wof:placetype":"venue"
},
  "geometry": {"coordinates":[8.023597,50.876392],"type":"Point"}
}