{
  "type": "Feature",
  "properties": {
    "iso:country":"DE",
    "sg:address":"Blustenweg 5",
    "sg:city":"Ottenh\u00f6fen",
    "sg:phone":"+49 7842/2175",
    "sg:postcode":"77883",
    "sg:province":"Baden-W\u00fcrttemberg",
    "wof:name":"Erwin Knapp Architekt",
    "wof:placetype":"venue"
},
  "geometry": {"coordinates":[8.153116,48.564766],"type":"Point"}
}