{
  "type": "Feature",
  "properties": {
    "iso:country":"DE",
    "sg:address":"Hans-Weigel-Str. 10b",
    "sg:city":"Leipzig",
    "sg:phone":"+49 341/6891073",
    "sg:postcode":"04319",
    "sg:province":"Sachsen",
    "wof:name":"Huppmann Immobilien Gmbh",
    "wof:placetype":"venue"
},
  "geometry": {"coordinates":[12.473942,51.3386],"type":"Point"}
}