{
  "type": "Feature",
  "properties": {
    "iso:country":"DE",
    "sg:address":"Grabenstr. 7",
    "sg:city":"Bernkastel-Kues",
    "sg:phone":"+49 6531/6762",
    "sg:postcode":"54470",
    "sg:province":"Rheinland-Pfalz",
    "wof:name":"Castel-pub",
    "wof:placetype":"venue"
},
  "geometry": {"coordinates":[7.075322,49.916676],"type":"Point"}
}