{
  "type": "Feature",
  "properties": {
    "iso:country":"DE",
    "sg:address":"Kapfb\u00fchlstr. 49",
    "sg:city":"Rheinfelden",
    "sg:phone":"+49 7623/59502",
    "sg:postcode":"79618",
    "sg:province":"Baden-W\u00fcrttemberg",
    "wof:name":"Ruth Maria Wagner Heilpraktikerin",
    "wof:placetype":"venue"
},
  "geometry": {"coordinates":[7.8069629669,47.5848007202],"type":"Point"}
}