{
  "type": "Feature",
  "properties": {
    "iso:country":"DE",
    "sg:address":"Paulinenweg 12",
    "sg:city":"Halle",
    "sg:phone":"+49 5201/120",
    "sg:postcode":"33790",
    "sg:province":"Nordrhein-Westfalen",
    "wof:name":"Storck Beteiligungen Gmbh",
    "wof:placetype":"venue"
},
  "geometry": {"coordinates":[8.338533,52.059189],"type":"Point"}
}