{
  "type": "Feature",
  "properties": {
    "iso:country":"DE",
    "sg:address":"Peterstr. 7",
    "sg:city":"H\u00fcckeswagen",
    "sg:phone":"+49 2192/3711",
    "sg:postcode":"42499",
    "sg:province":"Nordrhein-Westfalen",
    "wof:name":"Oberbergische Apotheke Inh. Klaus Zaehlke",
    "wof:placetype":"venue"
},
  "geometry": {"coordinates":[7.34377,51.149715],"type":"Point"}
}