{
  "type": "Feature",
  "properties": {
    "iso:country":"DE",
    "sg:address":"Milchgrund 49",
    "sg:city":"Hamburg",
    "sg:phone":"+49 40/7904966",
    "sg:postcode":"21075",
    "sg:province":"Hamburg",
    "wof:name":"Ev. Pfarramt Ii Petrus-gemeinde",
    "wof:placetype":"venue"
},
  "geometry": {"coordinates":[9.9511823654,53.468044281],"type":"Point"}
}