{
  "type": "Feature",
  "properties": {
    "iso:country":"DE",
    "sg:address":"Daimlerstr. 12",
    "sg:city":"Langenau",
    "sg:phone":"+49 7345/7603",
    "sg:postcode":"89129",
    "sg:province":"Baden-W\u00fcrttemberg",
    "wof:name":"Kassen-h\u00e4ge Gmbh",
    "wof:placetype":"venue"
},
  "geometry": {"coordinates":[10.121427536,48.494392395],"type":"Point"}
}