{
  "type": "Feature",
  "properties": {
    "iso:country":"DE",
    "sg:address":"Kreuzotterweg 5",
    "sg:city":"Stuttgart",
    "sg:phone":"+49 711/864866",
    "sg:postcode":"70499",
    "sg:province":"Baden-W\u00fcrttemberg",
    "wof:name":"Druckerei Albrecht Gmbh & Co. Kg Druck Papierverarbeitung",
    "wof:placetype":"venue"
},
  "geometry": {"coordinates":[9.086178,48.801525],"type":"Point"}
}