{
  "type": "Feature",
  "properties": {
    "iso:country":"DE",
    "sg:address":"Estenfelder Str. 49d",
    "sg:city":"W\u00fcrzburg",
    "sg:phone":"+49 931/286305",
    "sg:postcode":"97078",
    "sg:province":"Bayern",
    "wof:name":"J. Kremser Ingenieur",
    "wof:placetype":"venue"
},
  "geometry": {"coordinates":[9.9708843231,49.8230285645],"type":"Point"}
}