{
  "type": "Feature",
  "properties": {
    "iso:country":"DE",
    "sg:address":"Theodor-Heuss-Str. 2",
    "sg:city":"Sulzbach",
    "sg:phone":"+49 6028/996904",
    "sg:postcode":"63834",
    "sg:province":"Bayern",
    "wof:name":"Christian Nitsche",
    "wof:placetype":"venue"
},
  "geometry": {"coordinates":[9.1541728973,49.9136619568],"type":"Point"}
}