{
  "type": "Feature",
  "properties": {
    "iso:country":"DE",
    "sg:address":"Rossertstr. 27",
    "sg:city":"Kelkheim",
    "sg:postcode":"65779",
    "sg:province":"Hessen",
    "wof:name":"Merlin Corporate Services Gmbh",
    "wof:placetype":"venue"
},
  "geometry": {"coordinates":[8.3933029175,50.1667098999],"type":"Point"}
}