{
  "type": "Feature",
  "properties": {
    "iso:country":"DE",
    "sg:address":"Wendelsteinstr. 13",
    "sg:city":"Gilching",
    "sg:phone":"+49 8105/23819",
    "sg:postcode":"82205",
    "sg:province":"Bayern",
    "wof:name":"Klaus Frisch",
    "wof:placetype":"venue"
},
  "geometry": {"coordinates":[11.2878055573,48.1143531799],"type":"Point"}
}