{
  "type": "Feature",
  "properties": {
    "iso:country":"DE",
    "sg:address":"Destouchesstr. 19",
    "sg:city":"M\u00fcnchen",
    "sg:phone":"+49 89/396334",
    "sg:postcode":"80803",
    "sg:province":"Bayern",
    "wof:name":"Wessling Verm\u00f6gens- Verwaltung Gmbh",
    "wof:placetype":"venue"
},
  "geometry": {"coordinates":[11.5812950134,48.1648979187],"type":"Point"}
}