{
  "type": "Feature",
  "properties": {
    "iso:country":"DE",
    "sg:address":"Ganghoferstr. 29",
    "sg:city":"Maisach",
    "sg:phone":"+49 8142/48121",
    "sg:postcode":"82216",
    "sg:province":"Bayern",
    "wof:name":"Hofmann & Co. Au\u00dfenhandels Gmbh",
    "wof:placetype":"venue"
},
  "geometry": {"coordinates":[11.2564601898,48.2191696167],"type":"Point"}
}