{
  "type": "Feature",
  "properties": {
    "iso:country":"DE",
    "sg:address":"Sonnenhang 4",
    "sg:city":"Vlotho",
    "sg:phone":"+49 5733/8636",
    "sg:postcode":"32602",
    "sg:province":"Nordrhein-Westfalen",
    "wof:name":"L. Gehring Sen.",
    "wof:placetype":"venue"
},
  "geometry": {"coordinates":[8.876893,52.177155],"type":"Point"}
}