{
  "type": "Feature",
  "properties": {
    "iso:country":"DE",
    "sg:address":"Marktplatz 4",
    "sg:city":"Pyrbaum",
    "sg:phone":"+49 9180/722",
    "sg:postcode":"90602",
    "sg:province":"Bayern",
    "wof:name":"Ev. Luth. Pfarramt",
    "wof:placetype":"venue"
},
  "geometry": {"coordinates":[11.2848558426,49.2964515686],"type":"Point"}
}