{
  "type": "Feature",
  "properties": {
    "iso:country":"DE",
    "sg:city":"Hamburg",
    "sg:postcode":"20357",
    "sg:province":"Hamburg",
    "wof:name":"Andreas Herzau Fotografie",
    "wof:placetype":"venue"
},
  "geometry": {"coordinates":[9.96583,53.562263],"type":"Point"}
}