{
  "type": "Feature",
  "properties": {
    "iso:country":"DE",
    "sg:address":"Gondolfstr. 39",
    "sg:city":"W\u00f6llstadt",
    "sg:phone":"+49 6034/4454",
    "sg:postcode":"61206",
    "sg:province":"Hessen",
    "wof:name":"Heinrich U. Claudia Roskoni",
    "wof:placetype":"venue"
},
  "geometry": {"coordinates":[8.755490303,50.2946624756],"type":"Point"}
}