{
  "type": "Feature",
  "properties": {
    "iso:country":"DE",
    "sg:address":"Am Felde 38",
    "sg:city":"Seevetal",
    "sg:phone":"+49 40/7687611",
    "sg:postcode":"21217",
    "sg:province":"Niedersachsen",
    "wof:name":"Klaus Rasmus",
    "wof:placetype":"venue"
},
  "geometry": {"coordinates":[10.0280637741,53.4214477539],"type":"Point"}
}