{
  "type": "Feature",
  "properties": {
    "iso:country":"DE",
    "sg:address":"Bergstr. 3",
    "sg:city":"Alsenz",
    "sg:phone":"+49 6362/636",
    "sg:postcode":"67821",
    "sg:province":"Rheinland-Pfalz",
    "wof:name":"Fritz Staab",
    "wof:placetype":"venue"
},
  "geometry": {"coordinates":[7.811919,49.721096],"type":"Point"}
}