{
  "type": "Feature",
  "properties": {
    "iso:country":"DE",
    "sg:address":"B\u00fcrgermeister-P\u00fctz-Str 123-125",
    "sg:city":"Duisburg",
    "sg:phone":"+49 203/445464",
    "sg:postcode":"47137",
    "sg:province":"Nordrhein-Westfalen",
    "wof:name":"Sprengkraft",
    "wof:placetype":"venue"
},
  "geometry": {"coordinates":[6.7615861893,51.4604530334],"type":"Point"}
}