{
  "type": "Feature",
  "properties": {
    "iso:country":"DE",
    "sg:address":"Bussardstr. 27",
    "sg:city":"Recklinghausen",
    "sg:phone":"+49 2361/83838",
    "sg:postcode":"45665",
    "sg:province":"Nordrhein-Westfalen",
    "wof:name":"Horst Jeuken Steuerberater",
    "wof:placetype":"venue"
},
  "geometry": {"coordinates":[7.2722477913,51.6010971069],"type":"Point"}
}