{
  "type": "Feature",
  "properties": {
    "iso:country":"DE",
    "sg:address":"Lange Str. 100",
    "sg:city":"Castrop-Rauxel",
    "sg:phone":"+49 2305/75880",
    "sg:postcode":"44579",
    "sg:province":"Nordrhein-Westfalen",
    "wof:name":"Emil Galautz",
    "wof:placetype":"venue"
},
  "geometry": {"coordinates":[7.3177661896,51.5855064392],"type":"Point"}
}