{
  "type": "Feature",
  "properties": {
    "iso:country":"DE",
    "sg:address":"Am Herrenfeld 18",
    "sg:city":"Marburg",
    "sg:phone":"+49 6421/34636",
    "sg:postcode":"35037",
    "sg:province":"Hessen",
    "wof:name":"Heinrich Henkel",
    "wof:placetype":"venue"
},
  "geometry": {"coordinates":[8.7529153824,50.796672821],"type":"Point"}
}