{
  "type": "Feature",
  "properties": {
    "iso:country":"DE",
    "sg:address":"Salinenstr. 13",
    "sg:city":"Stotternheim",
    "sg:phone":"+49 36201/86258",
    "sg:postcode":"99195",
    "sg:province":"Th\u00fcringen",
    "wof:name":"Kraus Baugesellschaft Mbh",
    "wof:placetype":"venue"
},
  "geometry": {"coordinates":[11.0467233658,51.0508918762],"type":"Point"}
}