{
  "type": "Feature",
  "properties": {
    "iso:country":"DE",
    "sg:address":"Mittelstr. 2",
    "sg:city":"Calden",
    "sg:phone":"+49 5674/1888",
    "sg:postcode":"34379",
    "sg:province":"Hessen",
    "wof:name":"Gudrun Eckert",
    "wof:placetype":"venue"
},
  "geometry": {"coordinates":[9.4036941528,51.409236908],"type":"Point"}
}