{
  "type": "Feature",
  "properties": {
    "iso:country":"DE",
    "sg:address":"Friedrichstr. 125",
    "sg:city":"D\u00fcsseldorf",
    "sg:phone":"+49 211/9345141",
    "sg:postcode":"40217",
    "sg:province":"Nordrhein-Westfalen",
    "wof:name":"Panico-azevedo Gmbh",
    "wof:placetype":"venue"
},
  "geometry": {"coordinates":[6.7766819,51.2098770142],"type":"Point"}
}