{
  "type": "Feature",
  "properties": {
    "iso:country":"DE",
    "sg:address":"B\u00fcrgweg 16",
    "sg:city":"N\u00fcrnberg",
    "sg:phone":"+49 911/5430164",
    "sg:postcode":"90482",
    "sg:province":"Bayern",
    "wof:name":"Schreinerei Seger Gmbh",
    "wof:placetype":"venue"
},
  "geometry": {"coordinates":[11.136264,49.462521],"type":"Point"}
}