{
  "type": "Feature",
  "properties": {
    "iso:country":"DE",
    "sg:address":"Lange Str. 27",
    "sg:city":"Hagenburg",
    "sg:phone":"+49 5033/7618",
    "sg:postcode":"31558",
    "sg:province":"Niedersachsen",
    "wof:name":"Ratskeller",
    "wof:placetype":"venue"
},
  "geometry": {"coordinates":[9.322728157,52.4331130981],"type":"Point"}
}