{
  "type": "Feature",
  "properties": {
    "iso:country":"DE",
    "sg:address":"Rolshover Str 526",
    "sg:city":"K\u00f6ln",
    "sg:phone":"+49 221/98390",
    "sg:postcode":"51105",
    "sg:province":"Nordrhein-Westfalen",
    "wof:name":"J\u00e4ger + Schmitter Dialog Gesellschaft F\u00fcr Informationslogistik Mbh",
    "wof:placetype":"venue"
},
  "geometry": {"coordinates":[6.995965004,50.9179382324],"type":"Point"}
}