{
  "type": "Feature",
  "properties": {
    "iso:country":"DE",
    "sg:address":"Kriegsstr. 100",
    "sg:city":"Karlsruhe",
    "sg:phone":"+49 721/9300",
    "sg:postcode":"76133",
    "sg:province":"Baden-W\u00fcrttemberg",
    "wof:name":"Deutsche Postbank Ag",
    "wof:placetype":"venue"
},
  "geometry": {"coordinates":[8.4051427841,49.0057258606],"type":"Point"}
}