{
  "type": "Feature",
  "properties": {
    "iso:country":"DE",
    "sg:address":"Steinhart 21",
    "sg:city":"Pfaffing",
    "sg:postcode":"83539",
    "sg:province":"Bayern",
    "wof:name":"Zollner Verwaltungs Gmbh",
    "wof:placetype":"venue"
},
  "geometry": {"coordinates":[12.1161365509,48.0411758423],"type":"Point"}
}