{
  "type": "Feature",
  "properties": {
    "iso:country":"DE",
    "sg:address":"Bahnhofstr. 18",
    "sg:city":"Eisenberg",
    "sg:phone":"+49 36691/43608",
    "sg:postcode":"07607",
    "sg:province":"Th\u00fcringen",
    "wof:name":"Eberhard Schmenner",
    "wof:placetype":"venue"
},
  "geometry": {"coordinates":[11.891807,50.973801],"type":"Point"}
}