{
  "type": "Feature",
  "properties": {
    "iso:country":"DE",
    "sg:address":"Am Umweltpark 4",
    "sg:city":"Bochum",
    "sg:phone":"+49 234/91140",
    "sg:postcode":"44793",
    "sg:province":"Nordrhein-Westfalen",
    "wof:name":"Tyssenkrupp Weichenbau Gmbh",
    "wof:placetype":"venue"
},
  "geometry": {"coordinates":[7.1954989433,51.4714736938],"type":"Point"}
}