{
  "type": "Feature",
  "properties": {
    "iso:country":"DE",
    "sg:address":"Grubenstr. 42",
    "sg:city":"Rostock",
    "sg:phone":"+49 381/453308",
    "sg:postcode":"18055",
    "sg:province":"Mecklenburg-Vorpommern",
    "wof:name":"Wolter Bad Und K\u00fcche Gmbh",
    "wof:placetype":"venue"
},
  "geometry": {"coordinates":[12.143649,54.090145],"type":"Point"}
}