{
  "type": "Feature",
  "properties": {
    "iso:country":"DE",
    "sg:address":"Markt 39",
    "sg:city":"W\u00fcrselen",
    "sg:phone":"+49 2405/3883",
    "sg:postcode":"52146",
    "sg:province":"Nordrhein-Westfalen",
    "wof:name":"Sport Radermacher",
    "wof:placetype":"venue"
},
  "geometry": {"coordinates":[6.1325831413,50.8181190491],"type":"Point"}
}