{
  "type": "Feature",
  "properties": {
    "iso:country":"DE",
    "sg:address":"Am Gewerbering 3",
    "sg:city":"Burgstein",
    "sg:phone":"+49 37436/2420",
    "sg:postcode":"08538",
    "sg:province":"Sachsen",
    "wof:name":"Kemnitz-tal Bau Gmbh",
    "wof:placetype":"venue"
},
  "geometry": {"coordinates":[12.036052,50.425224],"type":"Point"}
}