{
  "type": "Feature",
  "properties": {
    "iso:country":"DE",
    "sg:address":"Kaiserstr. 9",
    "sg:city":"Bad Sassendorf",
    "sg:phone":"+49 2921/55321",
    "sg:postcode":"59505",
    "sg:province":"Nordrhein-Westfalen",
    "wof:name":"Fischer Feinuhrmacher- Juwelier-augenoptiker Gmbh",
    "wof:placetype":"venue"
},
  "geometry": {"coordinates":[8.1692485809,51.5859375],"type":"Point"}
}