{
  "type": "Feature",
  "properties": {
    "iso:country":"DE",
    "sg:address":"Van-Gogh-Str. 43",
    "sg:city":"Mainz",
    "sg:phone":"+49 6131/73950",
    "sg:postcode":"55127",
    "sg:province":"Rheinland-Pfalz",
    "wof:name":"Hans-j\u00fcrgen Schlamp Architekt",
    "wof:placetype":"venue"
},
  "geometry": {"coordinates":[8.184852,49.962437],"type":"Point"}
}