{
  "type": "Feature",
  "properties": {
    "iso:country":"DE",
    "sg:address":"Bahnhofstr. 25",
    "sg:city":"Voerde",
    "sg:phone":"+49 2855/850171",
    "sg:postcode":"46562",
    "sg:province":"Nordrhein-Westfalen",
    "wof:name":"Christiane Und Achim L\u00f6ll",
    "wof:placetype":"venue"
},
  "geometry": {"coordinates":[6.6742491722,51.5964584351],"type":"Point"}
}