{
  "type": "Feature",
  "properties": {
    "iso:country":"DE",
    "sg:address":"Hauptstr. 429",
    "sg:city":"K\u00f6ln",
    "sg:phone":"+49 2203/53110",
    "sg:postcode":"51143",
    "sg:province":"Nordrhein-Westfalen",
    "wof:name":"Liebeck",
    "wof:placetype":"venue"
},
  "geometry": {"coordinates":[7.0548,50.887909],"type":"Point"}
}