{
  "type": "Feature",
  "properties": {
    "iso:country":"DE",
    "sg:address":"Erntehof",
    "sg:city":"Neidenbach",
    "sg:phone":"+49 6565/7636",
    "sg:postcode":"54657",
    "sg:province":"Rheinland-Pfalz",
    "wof:name":"Hermann Grosdidier",
    "wof:placetype":"venue"
},
  "geometry": {"coordinates":[6.575593,50.109337],"type":"Point"}
}