{
  "type": "Feature",
  "properties": {
    "iso:country":"DE",
    "sg:address":"Hutfilterstr. 9-13",
    "sg:city":"Bremen",
    "sg:phone":"+49 421/30540",
    "sg:postcode":"28195",
    "sg:province":"Bremen",
    "wof:name":"Dcp Dettmer Container Packing Gmbh & Co. Kg",
    "wof:placetype":"venue"
},
  "geometry": {"coordinates":[8.802202,53.078766],"type":"Point"}
}