{
  "type": "Feature",
  "properties": {
    "iso:country":"DE",
    "sg:address":"Herrmannstr. 8a",
    "sg:city":"Bredstedt",
    "sg:phone":"+49 4671/2968",
    "sg:postcode":"25821",
    "sg:province":"Schleswig-Holstein",
    "wof:name":"Kinderheim Dansk Bornehave",
    "wof:placetype":"venue"
},
  "geometry": {"coordinates":[8.9651384354,54.6196517944],"type":"Point"}
}