{
  "type": "Feature",
  "properties": {
    "iso:country":"DE",
    "sg:address":"G\u00f6rgesheideweg 141",
    "sg:city":"Meerbusch",
    "sg:phone":"+49 2159/4794",
    "sg:postcode":"40670",
    "sg:province":"Nordrhein-Westfalen",
    "wof:name":"M. Hoppe",
    "wof:placetype":"venue"
},
  "geometry": {"coordinates":[6.616804,51.283382],"type":"Point"}
}