{
  "type": "Feature",
  "properties": {
    "iso:country":"DE",
    "sg:address":"Rather Str. 9",
    "sg:city":"Krefeld",
    "sg:phone":"+49 2151/561404",
    "sg:postcode":"47802",
    "sg:province":"Nordrhein-Westfalen",
    "wof:name":"Manfred Rexforth",
    "wof:placetype":"venue"
},
  "geometry": {"coordinates":[6.5857310295,51.3740119934],"type":"Point"}
}