{
  "type": "Feature",
  "properties": {
    "iso:country":"DE",
    "sg:address":"Am K\u00f6rnerplatz 2",
    "sg:city":"Frankenberg",
    "sg:phone":"+49 37206/75456",
    "sg:postcode":"09669",
    "sg:province":"Sachsen",
    "wof:name":"C. Hanke-\u00d6zmenn",
    "wof:placetype":"venue"
},
  "geometry": {"coordinates":[13.0331640244,50.9126319885],"type":"Point"}
}