{
  "type": "Feature",
  "properties": {
    "iso:country":"DE",
    "sg:address":"Waldhausener Str.101",
    "sg:city":"M\u00f6nchengladbach",
    "sg:phone":"+49 2161/309904",
    "sg:postcode":"41061",
    "sg:province":"Nordrhein-Westfalen",
    "wof:name":"O.hasse Dienstleistungen",
    "wof:placetype":"venue"
},
  "geometry": {"coordinates":[6.425056,51.195873],"type":"Point"}
}