{
  "type": "Feature",
  "properties": {
    "iso:country":"DE",
    "sg:address":"Hauptstr. 45",
    "sg:city":"\u00d6stringen",
    "sg:phone":"+49 7253/21556",
    "sg:postcode":"76684",
    "sg:province":"Baden-W\u00fcrttemberg",
    "wof:name":"Heger",
    "wof:placetype":"venue"
},
  "geometry": {"coordinates":[8.7043848038,49.2175254822],"type":"Point"}
}