{
  "type": "Feature",
  "properties": {
    "iso:country":"DE",
    "sg:address":"Karl-Rolle-Str. 13",
    "sg:city":"Eggenfelden",
    "sg:postcode":"84307",
    "sg:province":"Bayern",
    "wof:name":"Promedia E. K.",
    "wof:placetype":"venue"
},
  "geometry": {"coordinates":[12.7566919327,48.4046592712],"type":"Point"}
}