{
  "type": "Feature",
  "properties": {
    "iso:country":"DE",
    "sg:address":"Hauptwachstr 28",
    "sg:city":"Bamberg",
    "sg:phone":"+49 951/26641",
    "sg:postcode":"96047",
    "sg:province":"Bayern",
    "wof:name":"B\u00fcro & Schule",
    "wof:placetype":"venue"
},
  "geometry": {"coordinates":[10.890630722,49.8949279785],"type":"Point"}
}