{
  "type": "Feature",
  "properties": {
    "iso:country":"DE",
    "sg:address":"Kamener Str. 248",
    "sg:city":"Hamm",
    "sg:phone":"+49 2307/12634",
    "sg:postcode":"59077",
    "sg:province":"Nordrhein-Westfalen",
    "wof:name":"G. Hiddemann",
    "wof:placetype":"venue"
},
  "geometry": {"coordinates":[7.7086458206,51.6214981079],"type":"Point"}
}