{
  "type": "Feature",
  "properties": {
    "iso:country":"DE",
    "sg:address":"Schadowplatz 11",
    "sg:city":"D\u00fcsseldorf",
    "sg:phone":"+49 211/3238305",
    "sg:postcode":"40212",
    "sg:province":"Nordrhein-Westfalen",
    "wof:name":"Erdos Chashmere Textilhandels Gmbh",
    "wof:placetype":"venue"
},
  "geometry": {"coordinates":[6.7804970741,51.2260093689],"type":"Point"}
}