{
  "type": "Feature",
  "properties": {
    "iso:country":"DE",
    "sg:address":"Gollstr. 13",
    "sg:city":"Hannover",
    "sg:phone":"+49 511/526895",
    "sg:postcode":"30559",
    "sg:province":"Niedersachsen",
    "wof:name":"Armin Schmidt",
    "wof:placetype":"venue"
},
  "geometry": {"coordinates":[9.8584651947,52.3608894348],"type":"Point"}
}