{
  "type": "Feature",
  "properties": {
    "iso:country":"DE",
    "sg:address":"Kolbenstr. 8",
    "sg:city":"Windsbach",
    "sg:phone":"+49 9871/309",
    "sg:postcode":"91575",
    "sg:province":"Bayern",
    "wof:name":"Ev. Luth. Pfarramt Ii",
    "wof:placetype":"venue"
},
  "geometry": {"coordinates":[10.82609272,49.2459411621],"type":"Point"}
}