{
  "type": "Feature",
  "properties": {
    "iso:country":"DE",
    "sg:address":"Wilhelm-Bertelsmann-Str. 1",
    "sg:city":"Bielefeld",
    "sg:phone":"+49 521/521105",
    "sg:postcode":"33602",
    "sg:province":"Nordrhein-Westfalen",
    "wof:name":"Wilhelm Schneider Gmbh & Co. Kg",
    "wof:placetype":"venue"
},
  "geometry": {"coordinates":[8.5478887558,52.0282363892],"type":"Point"}
}