{
  "type": "Feature",
  "properties": {
    "iso:country":"DE",
    "sg:address":"Frankfurter Str. 38",
    "sg:city":"Kelkheim",
    "sg:phone":"+49 6195/2071",
    "sg:postcode":"65779",
    "sg:province":"Hessen",
    "wof:name":"Wilhelm Rodeck Gmbh & Co.",
    "wof:placetype":"venue"
},
  "geometry": {"coordinates":[8.4482746124,50.1406517029],"type":"Point"}
}