{
  "type": "Feature",
  "properties": {
    "iso:country":"DE",
    "sg:address":"Deutsch-Luxemburger-Str. 44",
    "sg:city":"Dortmund",
    "sg:phone":"+49 231/7922280",
    "sg:postcode":"44225",
    "sg:province":"Nordrhein-Westfalen",
    "wof:name":"Gr\u00fcne Druckerei Und Verlag Ohg",
    "wof:placetype":"venue"
},
  "geometry": {"coordinates":[7.435885,51.473675],"type":"Point"}
}