{
  "type": "Feature",
  "properties": {
    "iso:country":"DE",
    "sg:address":"Gorlerweg 7",
    "sg:city":"Rottenbuch",
    "sg:phone":"+49 8867/1394",
    "sg:postcode":"82401",
    "sg:province":"Bayern",
    "wof:name":"Georg Speer",
    "wof:placetype":"venue"
},
  "geometry": {"coordinates":[10.94695,47.744781],"type":"Point"}
}