{
  "type": "Feature",
  "properties": {
    "iso:country":"DE",
    "sg:address":"Hagenbacher Str. 37",
    "sg:city":"M\u00fcnchen",
    "sg:postcode":"81243",
    "sg:province":"Bayern",
    "wof:name":"Kloeppelladen.de - Der Kl\u00f6ppelladen",
    "wof:placetype":"venue"
},
  "geometry": {"coordinates":[11.426297,48.150375],"type":"Point"}
}