{
  "type": "Feature",
  "properties": {
    "iso:country":"DE",
    "sg:address":"Palaisplatz 2a",
    "sg:city":"Dresden",
    "sg:phone":"+49 351/5022533",
    "sg:postcode":"01097",
    "sg:province":"Sachsen",
    "wof:name":"Dwt Treuhand Gmbh",
    "wof:placetype":"venue"
},
  "geometry": {"coordinates":[13.7389640808,51.0610656738],"type":"Point"}
}