{
  "type": "Feature",
  "properties": {
    "iso:country":"DE",
    "sg:address":"Sandgasse 54",
    "sg:city":"Aschaffenburg",
    "sg:phone":"+49 6021/22752",
    "sg:postcode":"63739",
    "sg:province":"Bayern",
    "wof:name":"Silke Mayerh\u00f6fer Rechtsanw\u00e4ltin",
    "wof:placetype":"venue"
},
  "geometry": {"coordinates":[9.1501998901,49.9741363525],"type":"Point"}
}