{
  "type": "Feature",
  "properties": {
    "iso:country":"DE",
    "sg:address":"Schwalbenweg 1",
    "sg:city":"Stegaurach",
    "sg:phone":"+49 951/290630",
    "sg:postcode":"96135",
    "sg:province":"Bayern",
    "wof:name":"Dr. Elisabeth Geber-vogel Tier\u00e4rztin",
    "wof:placetype":"venue"
},
  "geometry": {"coordinates":[10.8445234299,49.8676528931],"type":"Point"}
}