{
  "type": "Feature",
  "properties": {
    "iso:country":"DE",
    "sg:address":"Vorstadt 21",
    "sg:city":"Mitterteich",
    "sg:phone":"+49 9633/1657",
    "sg:postcode":"95666",
    "sg:province":"Bayern",
    "wof:name":"Leonhard Zintl",
    "wof:placetype":"venue"
},
  "geometry": {"coordinates":[12.240412,49.949638],"type":"Point"}
}