{
  "type": "Feature",
  "properties": {
    "iso:country":"DE",
    "sg:address":"M\u00fcnsterstr. 5",
    "sg:city":"L\u00fcnen",
    "sg:phone":"+49 2306/50697",
    "sg:postcode":"44534",
    "sg:province":"Nordrhein-Westfalen",
    "wof:name":"Vertrauens\u00e4rztlicher-dienst D. Lva Westfalen",
    "wof:placetype":"venue"
},
  "geometry": {"coordinates":[7.5242080688,51.6159896851],"type":"Point"}
}