{
  "type": "Feature",
  "properties": {
    "iso:country":"DE",
    "sg:address":"Thomas-M\u00fcntzer-Str. 2",
    "sg:city":"Pratau",
    "sg:phone":"+49 3491/450701",
    "sg:postcode":"06888",
    "sg:province":"Sachsen-Anhalt",
    "wof:name":"Elbauen-apotheke E. K. Inh. Ilse Wieland",
    "wof:placetype":"venue"
},
  "geometry": {"coordinates":[-73.358521,41.141499],"type":"Point"}
}