{
  "type": "Feature",
  "properties": {
    "iso:country":"DE",
    "sg:address":"Kleine Rittergasse 11",
    "sg:city":"Frankfurt",
    "sg:phone":"+49 69/615986",
    "sg:postcode":"60594",
    "sg:province":"Hessen",
    "wof:name":"Irish Pub",
    "wof:placetype":"venue"
},
  "geometry": {"coordinates":[8.6904659271,50.1056556702],"type":"Point"}
}