{
  "type": "Feature",
  "properties": {
    "iso:country":"DE",
    "sg:address":"Dichtelbacher Str. 5",
    "sg:city":"Rheinb\u00f6llen",
    "sg:phone":"+49 6764/960220",
    "sg:postcode":"55494",
    "sg:province":"Rheinland-Pfalz",
    "wof:name":"W. Spreitzer",
    "wof:placetype":"venue"
},
  "geometry": {"coordinates":[7.676821,50.010899],"type":"Point"}
}