{
  "type": "Feature",
  "properties": {
    "iso:country":"DE",
    "sg:address":"Lippst\u00e4dter Str. 25",
    "sg:city":"Delbr\u00fcck",
    "sg:phone":"+49 5250/6913",
    "sg:postcode":"33129",
    "sg:province":"Nordrhein-Westfalen",
    "wof:name":"Johannes Wecker",
    "wof:placetype":"venue"
},
  "geometry": {"coordinates":[8.545408,51.752014],"type":"Point"}
}