{
  "type": "Feature",
  "properties": {
    "iso:country":"DE",
    "sg:address":"Waldmannshauser Str. 8",
    "sg:city":"Elbtal",
    "sg:phone":"+49 6436/4314",
    "sg:postcode":"65627",
    "sg:province":"Hessen",
    "wof:name":"Albert Heftrich Textilwaren",
    "wof:placetype":"venue"
},
  "geometry": {"coordinates":[8.0633535385,50.5040435791],"type":"Point"}
}