{
  "type": "Feature",
  "properties": {
    "iso:country":"DE",
    "sg:address":"D\u00fcsseldorfer Str. 30",
    "sg:city":"Solingen",
    "sg:phone":"+49 212/75603",
    "sg:postcode":"42697",
    "sg:province":"Nordrhein-Westfalen",
    "wof:name":"Organa Versicherungs- Vermittlungsgesellschaft Mbh",
    "wof:placetype":"venue"
},
  "geometry": {"coordinates":[7.0011281967,51.1613845825],"type":"Point"}
}