{
  "type": "Feature",
  "properties": {
    "iso:country":"DE",
    "sg:address":"Hausener Str. 10",
    "sg:city":"Gauting",
    "sg:phone":"+49 89/89340973",
    "sg:postcode":"82131",
    "sg:province":"Bayern",
    "wof:name":"Softmade E. K.",
    "wof:placetype":"venue"
},
  "geometry": {"coordinates":[11.32617,48.03133],"type":"Point"}
}