{
  "type": "Feature",
  "properties": {
    "iso:country":"DE",
    "sg:address":"Ernst-Th\u00e4lmann-Str. 2",
    "sg:city":"Wachow",
    "sg:phone":"+49 33239/70328",
    "sg:postcode":"14641",
    "sg:province":"Brandenburg",
    "wof:name":"Peter Gresch",
    "wof:placetype":"venue"
},
  "geometry": {"coordinates":[12.756002,52.533012],"type":"Point"}
}