{
  "type": "Feature",
  "properties": {
    "iso:country":"DE",
    "sg:address":"Am Anschlag 14",
    "sg:city":"Halver",
    "sg:phone":"+49 2353/5121",
    "sg:postcode":"58553",
    "sg:province":"Nordrhein-Westfalen",
    "wof:name":"Herbert B\u00fcrger",
    "wof:placetype":"venue"
},
  "geometry": {"coordinates":[7.471217,51.169147],"type":"Point"}
}