{
  "type": "Feature",
  "properties": {
    "iso:country":"DE",
    "sg:address":"K\u00f6lner Str. 52",
    "sg:city":"Mechernich",
    "sg:phone":"+49 2443/7201",
    "sg:postcode":"53894",
    "sg:province":"Nordrhein-Westfalen",
    "wof:name":"Stratmanns Men\u00fc-st\u00fcbchen",
    "wof:placetype":"venue"
},
  "geometry": {"coordinates":[6.6481389999,50.6126976013],"type":"Point"}
}