{
  "type": "Feature",
  "properties": {
    "iso:country":"DE",
    "sg:address":"Marktplatz 1",
    "sg:city":"Neustadt",
    "sg:phone":"+49 9568/5690",
    "sg:postcode":"96465",
    "sg:province":"Bayern",
    "wof:name":"Eckstein",
    "wof:placetype":"venue"
},
  "geometry": {"coordinates":[11.1235570908,50.3271942139],"type":"Point"}
}