{
  "type": "Feature",
  "properties": {
    "iso:country":"DE",
    "sg:address":"T\u00f6lzer Str. 26a",
    "sg:city":"Egling",
    "sg:phone":"+49 8176/421",
    "sg:postcode":"82544",
    "sg:province":"Bayern",
    "wof:name":"J\u00fcrgen Bail",
    "wof:placetype":"venue"
},
  "geometry": {"coordinates":[11.511238,47.914902],"type":"Point"}
}