{
  "type": "Feature",
  "properties": {
    "iso:country":"DE",
    "sg:address":"Im Urfftal 9",
    "sg:city":"Bad Wildungen",
    "sg:phone":"+49 5626/343",
    "sg:postcode":"34537",
    "sg:province":"Hessen",
    "wof:name":"Lange",
    "wof:placetype":"venue"
},
  "geometry": {"coordinates":[9.103922,51.049541],"type":"Point"}
}