{
  "type": "Feature",
  "properties": {
    "iso:country":"DE",
    "sg:address":"T\u00fcrkenstr. 52",
    "sg:city":"M\u00fcnchen",
    "sg:phone":"+49 89/2805180",
    "sg:postcode":"80799",
    "sg:province":"Bayern",
    "wof:name":"D. Bauer Und W. Serf",
    "wof:placetype":"venue"
},
  "geometry": {"coordinates":[11.5754985809,48.1492233276],"type":"Point"}
}