{
  "type": "Feature",
  "properties": {
    "iso:country":"DE",
    "sg:city":"Stockdorf",
    "sg:phone":"+49 89/856010",
    "sg:postcode":"82131",
    "sg:province":"Bayern",
    "wof:name":"Call Center Projekt Gmbh",
    "wof:placetype":"venue"
},
  "geometry": {"coordinates":[11.40744,48.091599],"type":"Point"}
}