{
  "type": "Feature",
  "properties": {
    "iso:country":"DE",
    "sg:address":"Am Hammerkloth 20",
    "sg:city":"Wuppertal",
    "sg:phone":"+49 202/708536",
    "sg:postcode":"42111",
    "sg:province":"Nordrhein-Westfalen",
    "wof:name":"Dieter Und Sabine Haarhaus",
    "wof:placetype":"venue"
},
  "geometry": {"coordinates":[7.164068,51.285061],"type":"Point"}
}