{
  "type": "Feature",
  "properties": {
    "iso:country":"DE",
    "sg:address":"Auf der Welle 5-7",
    "sg:city":"Rahden",
    "sg:phone":"+49 5771/9180",
    "sg:postcode":"32369",
    "sg:province":"Nordrhein-Westfalen",
    "wof:name":"Heinrich Meier Eisengie\u00dferei Beteilgungsgesellschaft Mbh",
    "wof:placetype":"venue"
},
  "geometry": {"coordinates":[8.625096,52.434795],"type":"Point"}
}