{
  "type": "Feature",
  "properties": {
    "iso:country":"DE",
    "sg:address":"K\u00f6nneritzstr. 98",
    "sg:city":"Leipzig",
    "sg:phone":"+49 341/4802053",
    "sg:postcode":"04229",
    "sg:province":"Sachsen",
    "wof:name":"Gerhard Kretzschmar",
    "wof:placetype":"venue"
},
  "geometry": {"coordinates":[12.341345,51.319813],"type":"Point"}
}