{
  "type": "Feature",
  "properties": {
    "iso:country":"DE",
    "sg:address":"Klausdorfer str. 104",
    "sg:city":"Altenholz",
    "sg:phone":"+49 431/324583",
    "sg:postcode":"24161",
    "sg:province":"Schleswig-Holstein",
    "wof:name":"Orpheon Musikwaren",
    "wof:placetype":"venue"
},
  "geometry": {"coordinates":[10.1214923859,54.4032936096],"type":"Point"}
}