{
  "type": "Feature",
  "properties": {
    "iso:country":"DE",
    "sg:address":"Johannes-Flintrop-Str. 121",
    "sg:city":"Mettmann",
    "sg:postcode":"40822",
    "sg:province":"Nordrhein-Westfalen",
    "wof:name":"Echterhagen Autoservice Gmbh",
    "wof:placetype":"venue"
},
  "geometry": {"coordinates":[6.9859271049,51.2557144165],"type":"Point"}
}