{
  "type": "Feature",
  "properties": {
    "iso:country":"DE",
    "sg:address":"Neutorgraben 1",
    "sg:city":"N\u00fcrnberg",
    "sg:phone":"+49 911/93120",
    "sg:postcode":"90419",
    "sg:province":"Bayern",
    "wof:name":"T & A N\u00fcrnberger Technologie- Zentrum Management",
    "wof:placetype":"venue"
},
  "geometry": {"coordinates":[11.070041,49.455593],"type":"Point"}
}