{
  "type": "Feature",
  "properties": {
    "iso:country":"DE",
    "sg:address":"An der Liebfrauenkirche 4",
    "sg:city":"Koblenz",
    "sg:phone":"+49 261/34393",
    "sg:postcode":"56068",
    "sg:province":"Rheinland-Pfalz",
    "wof:name":"Max Und Moritz",
    "wof:placetype":"venue"
},
  "geometry": {"coordinates":[7.5948371887,50.360912323],"type":"Point"}
}