{
  "type": "Feature",
  "properties": {
    "iso:country":"DE",
    "sg:address":"Gutenbergstr. 9",
    "sg:city":"Eppelheim",
    "sg:phone":"+49 6221/766961",
    "sg:postcode":"69214",
    "sg:province":"Baden-W\u00fcrttemberg",
    "wof:name":"Monika Billerbeck",
    "wof:placetype":"venue"
},
  "geometry": {"coordinates":[8.6256494522,49.4094200134],"type":"Point"}
}