{
  "type": "Feature",
  "properties": {
    "iso:country":"DE",
    "sg:address":"Rathausstr. 20a",
    "sg:city":"Regis-Breitingen",
    "sg:postcode":"04565",
    "sg:province":"Sachsen",
    "wof:name":"Hds Hausdienste Sachsen Gmbh",
    "wof:placetype":"venue"
},
  "geometry": {"coordinates":[12.4467821121,51.0893592834],"type":"Point"}
}