{
  "type": "Feature",
  "properties": {
    "iso:country":"DE",
    "sg:address":"Brahmsstr. 33",
    "sg:city":"Gaggenau",
    "sg:phone":"+49 7225/3692",
    "sg:postcode":"76571",
    "sg:province":"Baden-W\u00fcrttemberg",
    "wof:name":"P. Merkel",
    "wof:placetype":"venue"
},
  "geometry": {"coordinates":[8.32921,48.78878],"type":"Point"}
}