{
  "type": "Feature",
  "properties": {
    "iso:country":"DE",
    "sg:address":"Hauptstr. 14",
    "sg:city":"Nohn",
    "sg:phone":"+49 2696/203",
    "sg:postcode":"54578",
    "sg:province":"Rheinland-Pfalz",
    "wof:name":"Nikolaus Hahn",
    "wof:placetype":"venue"
},
  "geometry": {"coordinates":[6.786245,50.3297],"type":"Point"}
}