{
  "type": "Feature",
  "properties": {
    "iso:country":"DE",
    "sg:address":"Max-von-M\u00fcller-Str. 52",
    "sg:city":"Rottenburg",
    "sg:phone":"+49 8781/2640",
    "sg:postcode":"84056",
    "sg:province":"Bayern",
    "wof:name":"C. Angermann",
    "wof:placetype":"venue"
},
  "geometry": {"coordinates":[12.0248947144,48.7066841125],"type":"Point"}
}