{
  "type": "Feature",
  "properties": {
    "iso:country":"DE",
    "sg:address":"Gr Eschenheimer Str 14",
    "sg:city":"Frankfurt",
    "sg:postcode":"60313",
    "sg:province":"Hessen",
    "wof:name":"Sireo Real Estate Asset Management Gmbh",
    "wof:placetype":"venue"
},
  "geometry": {"coordinates":[8.6797142029,50.1153755188],"type":"Point"}
}