{
  "type": "Feature",
  "properties": {
    "iso:country":"DE",
    "sg:address":"Werdenbergweg 26",
    "sg:city":"Ulm",
    "sg:phone":"+49 731/23181",
    "sg:postcode":"89075",
    "sg:province":"Baden-W\u00fcrttemberg",
    "wof:name":"J\u00f6rg Riedle Architekt",
    "wof:placetype":"venue"
},
  "geometry": {"coordinates":[10.005162,48.412823],"type":"Point"}
}