{
  "type": "Feature",
  "properties": {
    "iso:country":"DE",
    "sg:address":"Darwinstr. 19",
    "sg:city":"Dresden",
    "sg:postcode":"01109",
    "sg:province":"Sachsen",
    "wof:name":"Katholisches Pfarramt Hl. Kreuz",
    "wof:placetype":"venue"
},
  "geometry": {"coordinates":[13.7826042175,51.1186218262],"type":"Point"}
}