{
  "type": "Feature",
  "properties": {
    "iso:country":"DE",
    "sg:address":"Am Scheid 22",
    "sg:city":"Obermaiselstein",
    "sg:postcode":"87538",
    "sg:province":"Bayern",
    "wof:name":"Ferienwohnung Andrea",
    "wof:placetype":"venue"
},
  "geometry": {"coordinates":[10.238933,47.445621],"type":"Point"}
}