{
  "type": "Feature",
  "properties": {
    "iso:country":"DE",
    "sg:address":"Jakobsbergstr. 6",
    "sg:city":"Mainz",
    "sg:phone":"+49 6131/226681",
    "sg:postcode":"55116",
    "sg:province":"Rheinland-Pfalz",
    "wof:name":"Sine Ausr\u00fcstung Und Bekleidung F\u00fcr Ruck-",
    "wof:placetype":"venue"
},
  "geometry": {"coordinates":[8.276699,49.99522],"type":"Point"}
}