{
  "type": "Feature",
  "properties": {
    "iso:country":"DE",
    "sg:address":"Hillesheimstr. 22",
    "sg:city":"K\u00f6ln",
    "sg:phone":"+49 221/7127614",
    "sg:postcode":"50735",
    "sg:province":"Nordrhein-Westfalen",
    "wof:name":"Haus Hillesheim",
    "wof:placetype":"venue"
},
  "geometry": {"coordinates":[6.9637460709,50.9862709045],"type":"Point"}
}