{
  "type": "Feature",
  "properties": {
    "iso:country":"DE",
    "sg:address":"Calenberger Esplanade 3",
    "sg:city":"Hannover",
    "sg:phone":"+49 511/3945600",
    "sg:postcode":"30169",
    "sg:province":"Niedersachsen",
    "wof:name":"Talicom Gmbh",
    "wof:placetype":"venue"
},
  "geometry": {"coordinates":[9.7242021561,52.36951828],"type":"Point"}
}