{
  "type": "Feature",
  "properties": {
    "iso:country":"DE",
    "sg:city":"Holzheim",
    "sg:phone":"+49 9075/270",
    "sg:postcode":"89438",
    "sg:province":"Bayern",
    "wof:name":"Georg Breunig",
    "wof:placetype":"venue"
},
  "geometry": {"coordinates":[10.528782,48.512287],"type":"Point"}
}