{
  "type": "Feature",
  "properties": {
    "iso:country":"DE",
    "sg:address":"Bahnhofstr. 22",
    "sg:city":"Hofheim",
    "sg:phone":"+49 9523/263",
    "sg:postcode":"97461",
    "sg:province":"Bayern",
    "wof:name":"Bay Wa Ag",
    "wof:placetype":"venue"
},
  "geometry": {"coordinates":[10.5208921432,50.1353149414],"type":"Point"}
}