{
  "type": "Feature",
  "properties": {
    "iso:country":"DE",
    "sg:address":"Borsigstr 2",
    "sg:city":"Hamburg",
    "sg:phone":"+49 40/733510",
    "sg:postcode":"22113",
    "sg:province":"Schleswig-Holstein",
    "wof:name":"Avg Abfall-verwertungs-gesellschaft Mbh",
    "wof:placetype":"venue"
},
  "geometry": {"coordinates":[10.1656427383,53.542137146],"type":"Point"}
}