{
  "type": "Feature",
  "properties": {
    "iso:country":"DE",
    "sg:address":"Neust\u00e4dter Str. 14",
    "sg:city":"Cottbus",
    "sg:phone":"+49 355/24636",
    "sg:postcode":"03046",
    "sg:province":"Brandenburg",
    "wof:name":"Alexander Grommel",
    "wof:placetype":"venue"
},
  "geometry": {"coordinates":[14.3353433609,51.7595901489],"type":"Point"}
}