{
  "type": "Feature",
  "properties": {
    "iso:country":"DE",
    "sg:address":"Heringer Fahrweg 18",
    "sg:city":"H\u00fcnfelden",
    "sg:phone":"+49 6438/923530",
    "sg:postcode":"65597",
    "sg:province":"Hessen",
    "wof:name":"Manuela Wei\u00df",
    "wof:placetype":"venue"
},
  "geometry": {"coordinates":[8.151439,50.31168],"type":"Point"}
}