{
  "type": "Feature",
  "properties": {
    "iso:country":"DE",
    "sg:address":"Frankenheimer Str. 1",
    "sg:city":"Oberweid",
    "sg:phone":"+49 36946/26111",
    "sg:postcode":"98634",
    "sg:province":"Th\u00fcringen",
    "wof:name":"Dieter Lange",
    "wof:placetype":"venue"
},
  "geometry": {"coordinates":[10.063852,50.590237],"type":"Point"}
}