{
  "type": "Feature",
  "properties": {
    "iso:country":"DE",
    "sg:address":"Neuer Weg 6",
    "sg:city":"F\u00fcrstenwerder",
    "sg:postcode":"17291",
    "sg:province":"Brandenburg",
    "wof:name":"Viktoria B\u00fcroservice E. K.",
    "wof:placetype":"venue"
},
  "geometry": {"coordinates":[13.5923299789,53.3910217285],"type":"Point"}
}