{
  "type": "Feature",
  "properties": {
    "iso:country":"DE",
    "sg:address":"Eidelstedter Weg 88",
    "sg:city":"Hamburg",
    "sg:phone":"+49 40/406886",
    "sg:postcode":"20255",
    "sg:province":"Hamburg",
    "wof:name":"Herber & Sohn Gmbh",
    "wof:placetype":"venue"
},
  "geometry": {"coordinates":[9.946415,53.582481],"type":"Point"}
}