{
  "type": "Feature",
  "properties": {
    "iso:country":"DE",
    "sg:address":"Zehntstr. 3-5",
    "sg:city":"Karlsruhe",
    "sg:phone":"+49 721/494463",
    "sg:postcode":"76227",
    "sg:province":"Baden-W\u00fcrttemberg",
    "wof:name":"Ofo-verlag Gmbh",
    "wof:placetype":"venue"
},
  "geometry": {"coordinates":[8.4699077606,48.9996185303],"type":"Point"}
}