{
  "type": "Feature",
  "properties": {
    "iso:country":"DE",
    "sg:address":"Richard-Lenk-Str. 8",
    "sg:city":"Kappelrodeck",
    "sg:phone":"+49 7842/1860",
    "sg:postcode":"77876",
    "sg:province":"Baden-W\u00fcrttemberg",
    "wof:name":"Leppert Mineral\u00f6le Gmbh",
    "wof:placetype":"venue"
},
  "geometry": {"coordinates":[8.1153774261,48.5945167542],"type":"Point"}
}