{
  "type": "Feature",
  "properties": {
    "iso:country":"DE",
    "sg:address":"Schwarzenbergstr. 15",
    "sg:city":"Rosenheim",
    "sg:phone":"+49 8031/269838",
    "sg:postcode":"83026",
    "sg:province":"Bayern",
    "wof:name":"Natura Et Patria Verlag Horst G.w. Gleiss",
    "wof:placetype":"venue"
},
  "geometry": {"coordinates":[12.0871973038,47.8254013062],"type":"Point"}
}