{
  "type": "Feature",
  "properties": {
    "iso:country":"DE",
    "sg:address":"Alte Ruhrorter Str. 11",
    "sg:city":"Duisburg",
    "sg:phone":"+49 203/809050",
    "sg:postcode":"47119",
    "sg:province":"Nordrhein-Westfalen",
    "wof:name":"Pkv Planungsgesellschaft Kombinierter Verkehr",
    "wof:placetype":"venue"
},
  "geometry": {"coordinates":[6.7487092018,51.4514122009],"type":"Point"}
}