{
  "type": "Feature",
  "properties": {
    "iso:country":"DE",
    "sg:address":"M\u00fcllerhartungstr. 8",
    "sg:city":"Bad Sulza",
    "sg:phone":"+49 36461/20497",
    "sg:postcode":"99518",
    "sg:province":"Th\u00fcringen",
    "wof:name":"D. Fuchs Und E. Krippendorf Masseure",
    "wof:placetype":"venue"
},
  "geometry": {"coordinates":[11.622868,51.086838],"type":"Point"}
}