{
  "type": "Feature",
  "properties": {
    "iso:country":"DE",
    "sg:address":"Oststr. 22",
    "sg:city":"Ahlen",
    "sg:phone":"+49 2382/84251",
    "sg:postcode":"59227",
    "sg:province":"Nordrhein-Westfalen",
    "wof:name":"Mode F\u00fcr M\u00e4nner Mit Dem Besonderen Geschmack",
    "wof:placetype":"venue"
},
  "geometry": {"coordinates":[7.8947281837,51.7631263733],"type":"Point"}
}