{
  "type": "Feature",
  "properties": {
    "iso:country":"DE",
    "sg:address":"Soltauer Str. 2 a",
    "sg:city":"Hannover",
    "sg:phone":"+49 511/576620",
    "sg:postcode":"30625",
    "sg:province":"Niedersachsen",
    "wof:name":"Dieter Knackstedt",
    "wof:placetype":"venue"
},
  "geometry": {"coordinates":[9.8175468445,52.3807220459],"type":"Point"}
}