{
  "type": "Feature",
  "properties": {
    "iso:country":"DE",
    "sg:address":"Lanterstr. 31",
    "sg:city":"Dinslaken",
    "sg:phone":"+49 2064/98088",
    "sg:postcode":"46539",
    "sg:province":"Nordrhein-Westfalen",
    "wof:name":"Sahmel Isolierungen Gmbh",
    "wof:placetype":"venue"
},
  "geometry": {"coordinates":[6.802275,51.563232],"type":"Point"}
}