{
  "type": "Feature",
  "properties": {
    "iso:country":"DE",
    "sg:address":"Hugenottenallee 25",
    "sg:city":"Neu-Isenburg",
    "sg:phone":"+49 6102/25718",
    "sg:postcode":"63263",
    "sg:province":"Hessen",
    "wof:name":"R. Weiss",
    "wof:placetype":"venue"
},
  "geometry": {"coordinates":[8.688335,50.056492],"type":"Point"}
}