{
  "type": "Feature",
  "properties": {
    "iso:country":"DE",
    "sg:address":"Markt 9",
    "sg:city":"Werne",
    "sg:phone":"+49 2389/3639",
    "sg:postcode":"59368",
    "sg:province":"Nordrhein-Westfalen",
    "wof:name":"Rathauscafe",
    "wof:placetype":"venue"
},
  "geometry": {"coordinates":[7.636588,51.662617],"type":"Point"}
}