{
  "type": "Feature",
  "properties": {
    "iso:country":"DE",
    "sg:address":"Gartenfeldstr. 7a",
    "sg:city":"Friedberg",
    "sg:phone":"+49 6031/91123",
    "sg:postcode":"61169",
    "sg:province":"Hessen",
    "wof:name":"Wolfgang Hopp",
    "wof:placetype":"venue"
},
  "geometry": {"coordinates":[8.7481069565,50.3333511353],"type":"Point"}
}