{
  "type": "Feature",
  "properties": {
    "iso:country":"DE",
    "sg:address":"Kleine Masch 1",
    "sg:city":"Braunschweig",
    "sg:phone":"+49 5307/6452",
    "sg:postcode":"38110",
    "sg:province":"Niedersachsen",
    "wof:name":"Bernhard Koschate",
    "wof:placetype":"venue"
},
  "geometry": {"coordinates":[10.532206,52.318085],"type":"Point"}
}