{
  "type": "Feature",
  "properties": {
    "iso:country":"DE",
    "sg:address":"Sch\u00f6nblick 5",
    "sg:city":"Haiger",
    "sg:phone":"+49 2771/32238",
    "sg:postcode":"35708",
    "sg:province":"Hessen",
    "wof:name":"Gefl\u00fcgelzuchtverein Sechshelden",
    "wof:placetype":"venue"
},
  "geometry": {"coordinates":[8.2489042282,50.7501754761],"type":"Point"}
}