{
  "type": "Feature",
  "properties": {
    "iso:country":"DE",
    "sg:address":"M\u00fcggenburg 2",
    "sg:city":"Hamburg",
    "sg:phone":"+49 40",
    "sg:postcode":"21129",
    "sg:province":"Hamburg",
    "wof:name":"Tv-videoservice Peter Gerdau",
    "wof:placetype":"venue"
},
  "geometry": {"coordinates":[9.880937,53.531998],"type":"Point"}
}