{
  "type": "Feature",
  "properties": {
    "iso:country":"DE",
    "sg:address":"Eysseneckstr. 56",
    "sg:city":"Frankfurt",
    "sg:postcode":"60322",
    "sg:province":"Hessen",
    "wof:name":"Lionya Beteiligungs Gmbh",
    "wof:placetype":"venue"
},
  "geometry": {"coordinates":[8.6752061844,50.1316452026],"type":"Point"}
}