{
  "type": "Feature",
  "properties": {
    "iso:country":"DE",
    "sg:address":"Auf der L\u00fctzelbach 14",
    "sg:city":"Weilburg",
    "sg:postcode":"35781",
    "sg:province":"Hessen",
    "wof:name":"Niedree Verwaltungs-gmbh",
    "wof:placetype":"venue"
},
  "geometry": {"coordinates":[8.2655248642,50.4920043945],"type":"Point"}
}