{
  "type": "Feature",
  "properties": {
    "iso:country":"DE",
    "sg:address":"Sophienstr. 18",
    "sg:city":"Stuttgart",
    "sg:phone":"+49 711/6408940",
    "sg:postcode":"70178",
    "sg:province":"Baden-W\u00fcrttemberg",
    "wof:name":"Rainer Bischof Rechtsanwalt",
    "wof:placetype":"venue"
},
  "geometry": {"coordinates":[9.1747608185,48.771396637],"type":"Point"}
}