{
  "type": "Feature",
  "properties": {
    "iso:country":"DE",
    "sg:address":"Grosse Muenzstr. 6::",
    "sg:city":"Magdeburg",
    "sg:phone":"+49 4939/159110",
    "sg:postcode":"39104",
    "sg:province":"Sachsen-Anhalt",
    "wof:name":"Stadtsparkasse Magdeburg",
    "wof:placetype":"venue"
},
  "geometry": {"coordinates":[11.634721,52.132275],"type":"Point"}
}