{
  "type": "Feature",
  "properties": {
    "iso:country":"DE",
    "sg:address":"Herchersgarten 2 b",
    "sg:city":"Merzhausen",
    "sg:phone":"+49 761/403943",
    "sg:postcode":"79249",
    "sg:province":"Baden-W\u00fcrttemberg",
    "wof:name":"H. Imberi Architekt",
    "wof:placetype":"venue"
},
  "geometry": {"coordinates":[7.824658,47.964394],"type":"Point"}
}