{
  "type": "Feature",
  "properties": {
    "iso:country":"DE",
    "sg:address":"August-Ruf-Str. 8",
    "sg:city":"Singen",
    "sg:phone":"+49 4977/318260",
    "sg:postcode":"78224",
    "sg:province":"Baden-W\u00fcrttemberg",
    "wof:name":"Deutsche Bank Ag",
    "wof:placetype":"venue"
},
  "geometry": {"coordinates":[8.839865,47.760349],"type":"Point"}
}