{
  "type": "Feature",
  "properties": {
    "iso:country":"DE",
    "sg:city":"Merzig",
    "sg:postcode":"66663",
    "sg:province":"Saarland",
    "wof:name":"Schulbibliothek An Der Volksschule Besseringen",
    "wof:placetype":"venue"
},
  "geometry": {"coordinates":[6.63651,49.442039],"type":"Point"}
}