{
  "type": "Feature",
  "properties": {
    "iso:country":"DE",
    "sg:address":"Kl\u00f6tzleweg 4",
    "sg:city":"Hartheim",
    "sg:phone":"+49 7633/406633",
    "sg:postcode":"79258",
    "sg:province":"Baden-W\u00fcrttemberg",
    "wof:name":"O. Krau\u00df",
    "wof:placetype":"venue"
},
  "geometry": {"coordinates":[7.6234331131,47.9327278137],"type":"Point"}
}