{
  "type": "Feature",
  "properties": {
    "iso:country":"DE",
    "sg:address":"Heggerstr. 70",
    "sg:city":"Hattingen",
    "sg:postcode":"45525",
    "sg:province":"Nordrhein-Westfalen",
    "wof:name":"Jutta Hogr\u00e4ve Beteiligungs Gmbh",
    "wof:placetype":"venue"
},
  "geometry": {"coordinates":[7.187984,51.401581],"type":"Point"}
}