{
  "type": "Feature",
  "properties": {
    "iso:country":"DE",
    "sg:address":"Schmollerstr. 5",
    "sg:city":"Schw\u00e4bisch Hall",
    "sg:phone":"+49 791/47900",
    "sg:postcode":"74523",
    "sg:province":"Baden-W\u00fcrttemberg",
    "wof:name":"Futterkiste",
    "wof:placetype":"venue"
},
  "geometry": {"coordinates":[9.782728,49.109035],"type":"Point"}
}