{
  "type": "Feature",
  "properties": {
    "iso:country":"DE",
    "sg:address":"Oberpframmerner Str. 25a",
    "sg:city":"Egmating",
    "sg:postcode":"85658",
    "sg:province":"Bayern",
    "wof:name":"Bavaria Marketingtechnik Gmbh",
    "wof:placetype":"venue"
},
  "geometry": {"coordinates":[11.799955368,48.006816864],"type":"Point"}
}