{
  "type": "Feature",
  "properties": {
    "iso:country":"DE",
    "sg:address":"Rottfeldstr. 11",
    "sg:city":"Meerbusch",
    "sg:postcode":"40670",
    "sg:province":"Nordrhein-Westfalen",
    "wof:name":"Theomail Kommunikations- Tionsdienst Gmbh",
    "wof:placetype":"venue"
},
  "geometry": {"coordinates":[6.6399030685,51.2835121155],"type":"Point"}
}