{
  "type": "Feature",
  "properties": {
    "iso:country":"DE",
    "sg:address":"Zimmermannstr. 29",
    "sg:city":"Berlin",
    "sg:phone":"+49 30/7912222",
    "sg:postcode":"12163",
    "sg:province":"Berlin",
    "wof:name":"Hedda Gerbert Steuerberaterin",
    "wof:placetype":"venue"
},
  "geometry": {"coordinates":[13.3194646835,52.4604797363],"type":"Point"}
}