{
  "type": "Feature",
  "properties": {
    "iso:country":"DE",
    "sg:address":"Isoldenstr. 30",
    "sg:city":"Gelsenkirchen",
    "sg:phone":"+49 209/1656393",
    "sg:postcode":"45892",
    "sg:province":"Nordrhein-Westfalen",
    "wof:name":"Lebensr\u00e4ume Hausbau & Bautr\u00e4ger Gmbh",
    "wof:placetype":"venue"
},
  "geometry": {"coordinates":[7.11431,51.583801],"type":"Point"}
}