{
  "type": "Feature",
  "properties": {
    "iso:country":"DE",
    "sg:address":"Hauptstr. 44-46",
    "sg:city":"Much",
    "sg:phone":"+49 2245/5313",
    "sg:postcode":"53804",
    "sg:province":"Nordrhein-Westfalen",
    "wof:name":"U. Didszuweit Damen- Und Kindermoden",
    "wof:placetype":"venue"
},
  "geometry": {"coordinates":[7.40433,50.905441],"type":"Point"}
}