{
  "type": "Feature",
  "properties": {
    "iso:country":"DE",
    "sg:address":"Friedrich-Back-Str. 19",
    "sg:city":"Kastellaun",
    "sg:phone":"+49 6762/4459",
    "sg:postcode":"56288",
    "sg:province":"Rheinland-Pfalz",
    "wof:name":"Alfa Holzspielwaren",
    "wof:placetype":"venue"
},
  "geometry": {"coordinates":[7.4416542053,50.0741653442],"type":"Point"}
}