{
  "type": "Feature",
  "properties": {
    "iso:country":"DE",
    "sg:address":"Helbeeck 2",
    "sg:city":"Greu\u00dfen",
    "sg:phone":"+49 3636/700726",
    "sg:postcode":"99718",
    "sg:province":"Th\u00fcringen",
    "wof:name":"Becker Und Fa\u00dfhauer Steuerberater",
    "wof:placetype":"venue"
},
  "geometry": {"coordinates":[10.9517698288,51.2285118103],"type":"Point"}
}