{
  "type": "Feature",
  "properties": {
    "iso:country":"DE",
    "sg:address":"Schierker Str. 30",
    "sg:city":"Berlin",
    "sg:phone":"+49 30",
    "sg:postcode":"12051",
    "sg:province":"Berlin",
    "wof:name":"Euraac",
    "wof:placetype":"venue"
},
  "geometry": {"coordinates":[13.43242,52.470139],"type":"Point"}
}