{
  "type": "Feature",
  "properties": {
    "iso:country":"DE",
    "sg:address":"Steinacker 34",
    "sg:city":"Bad Honnef",
    "sg:phone":"+49 2224/972177",
    "sg:postcode":"53604",
    "sg:province":"Nordrhein-Westfalen",
    "wof:name":"G & T Medizintechnik Gmbh",
    "wof:placetype":"venue"
},
  "geometry": {"coordinates":[7.329253,50.660767],"type":"Point"}
}