{
  "type": "Feature",
  "properties": {
    "iso:country":"DE",
    "sg:address":"Dorfstr. 39",
    "sg:city":"Beucha",
    "sg:phone":"+49 34292/73448",
    "sg:postcode":"04824",
    "sg:province":"Sachsen",
    "wof:name":"Elisabeth M\u00fcller",
    "wof:placetype":"venue"
},
  "geometry": {"coordinates":[12.561999,51.325703],"type":"Point"}
}