{
  "type": "Feature",
  "properties": {
    "iso:country":"DE",
    "sg:address":"Marienterrasse 3",
    "sg:city":"Hamburg",
    "sg:postcode":"22085",
    "sg:province":"Hamburg",
    "wof:name":"Carl C. Petersen Monopol-vertrieb",
    "wof:placetype":"venue"
},
  "geometry": {"coordinates":[10.0130119324,53.5762367249],"type":"Point"}
}