{
  "type": "Feature",
  "properties": {
    "iso:country":"DE",
    "sg:address":"Duesseldorfer Str. 56",
    "sg:city":"Moenchengladbach",
    "sg:phone":"+49 2166",
    "sg:postcode":"41238",
    "sg:province":"Nordrhein-Westfalen",
    "wof:name":"Partyservice Ralf Peltzer - M\u00f6nchengladbach",
    "wof:placetype":"venue"
},
  "geometry": {"coordinates":[6.490575,51.155842],"type":"Point"}
}