{
  "type": "Feature",
  "properties": {
    "iso:country":"DE",
    "sg:address":"Bahnhofstr. 32",
    "sg:city":"Wetter",
    "sg:phone":"+49 6423/963033",
    "sg:postcode":"35083",
    "sg:province":"Hessen",
    "wof:name":"G\u00fcnter Sawikowsky",
    "wof:placetype":"venue"
},
  "geometry": {"coordinates":[8.7282953262,50.9046630859],"type":"Point"}
}