{
  "type": "Feature",
  "properties": {
    "iso:country":"DE",
    "sg:address":"Dieselstr. 5",
    "sg:city":"Hameln",
    "sg:phone":"+49 5151/7640",
    "sg:postcode":"31789",
    "sg:province":"Niedersachsen",
    "wof:name":"Adolf Wehrhahn Kartonagenfabrik Gmbh",
    "wof:placetype":"venue"
},
  "geometry": {"coordinates":[9.3694086075,52.0967559814],"type":"Point"}
}