{
  "type": "Feature",
  "properties": {
    "iso:country":"DE",
    "sg:address":"Holtwicker Str. 51",
    "sg:city":"Haltern",
    "sg:phone":"+49 2364/12595",
    "sg:postcode":"45721",
    "sg:province":"Nordrhein-Westfalen",
    "wof:name":"J. Letzing",
    "wof:placetype":"venue"
},
  "geometry": {"coordinates":[7.1786980629,51.7445983887],"type":"Point"}
}