{
  "type": "Feature",
  "properties": {
    "iso:country":"DE",
    "sg:address":"Brandenburger Str. 39",
    "sg:city":"Offenbach",
    "sg:phone":"+49 69/868055",
    "sg:postcode":"63075",
    "sg:province":"Hessen",
    "wof:name":"Tegema Marketing Gmbh",
    "wof:placetype":"venue"
},
  "geometry": {"coordinates":[8.787311554,50.1258773804],"type":"Point"}
}