{
  "type": "Feature",
  "properties": {
    "iso:country":"DE",
    "sg:address":"M\u00f6ckm\u00fchler Str. 18",
    "sg:city":"Widdern",
    "sg:phone":"+49 6298/7303",
    "sg:postcode":"74259",
    "sg:province":"Baden-W\u00fcrttemberg",
    "wof:name":"Ev. Pfarramt",
    "wof:placetype":"venue"
},
  "geometry": {"coordinates":[9.4187088013,49.3164787292],"type":"Point"}
}