{
  "type": "Feature",
  "properties": {
    "iso:country":"DE",
    "sg:address":"Alt-Moabit 62-63",
    "sg:city":"Berlin",
    "sg:phone":"+49 30/3992530",
    "sg:postcode":"10555",
    "sg:province":"Berlin",
    "wof:name":"Kognito Visuelle Gestaltung",
    "wof:placetype":"venue"
},
  "geometry": {"coordinates":[13.32826,52.524017],"type":"Point"}
}