{
  "type": "Feature",
  "properties": {
    "iso:country":"DE",
    "sg:address":"Naheweg 23",
    "sg:city":"Erkrath",
    "sg:phone":"+49 2104/27402",
    "sg:postcode":"40699",
    "sg:province":"Nordrhein-Westfalen",
    "wof:name":"G.i.c. Hardware Engineering-produktion",
    "wof:placetype":"venue"
},
  "geometry": {"coordinates":[6.9697399139,51.2059211731],"type":"Point"}
}