{
  "type": "Feature",
  "properties": {
    "iso:country":"DE",
    "sg:address":"Bergstr. 7",
    "sg:city":"Bissingen",
    "sg:phone":"+49 7023/6512",
    "sg:postcode":"73266",
    "sg:province":"Baden-W\u00fcrttemberg",
    "wof:name":"R. Seifert",
    "wof:placetype":"venue"
},
  "geometry": {"coordinates":[9.512195,48.579529],"type":"Point"}
}