{
  "type": "Feature",
  "properties": {
    "iso:country":"DE",
    "sg:address":"Clara-Zetkin-Str. 104",
    "sg:city":"Erfurt",
    "sg:phone":"+49 361/3459294",
    "sg:postcode":"99099",
    "sg:province":"Th\u00fcringen",
    "wof:name":"Kappel Und L\u00fcftner Architekten",
    "wof:placetype":"venue"
},
  "geometry": {"coordinates":[11.042401,50.969971],"type":"Point"}
}