{
  "type": "Feature",
  "properties": {
    "iso:country":"DE",
    "sg:address":"In der Eck 8",
    "sg:city":"Schwalmtal",
    "sg:phone":"+49 6638/1591",
    "sg:postcode":"36318",
    "sg:province":"Hessen",
    "wof:name":"Nobis Verlags- Und Veran- Staltungs Gmbh & Co. Kg",
    "wof:placetype":"venue"
},
  "geometry": {"coordinates":[9.3332948685,50.7157287598],"type":"Point"}
}