{
  "type": "Feature",
  "properties": {
    "iso:country":"DE",
    "sg:address":"Pastor-Franke-Str. 6",
    "sg:city":"Gelsenkirchen",
    "sg:phone":"+49 209/35163",
    "sg:postcode":"45894",
    "sg:province":"Nordrhein-Westfalen",
    "wof:name":"Rudolf Sch\u00e4fer",
    "wof:placetype":"venue"
},
  "geometry": {"coordinates":[7.050434,51.574585],"type":"Point"}
}