{
  "type": "Feature",
  "properties": {
    "iso:country":"DE",
    "sg:address":"Lindenstr. 24",
    "sg:city":"Seitingen-Oberflacht",
    "sg:phone":"+49 7464/1663",
    "sg:postcode":"78606",
    "sg:province":"Baden-W\u00fcrttemberg",
    "wof:name":"Johann Seifried",
    "wof:placetype":"venue"
},
  "geometry": {"coordinates":[8.7135972977,48.0155296326],"type":"Point"}
}