{
  "type": "Feature",
  "properties": {
    "iso:country":"DE",
    "sg:address":"Fliederweg 9",
    "sg:city":"Kassel",
    "sg:phone":"+49 561/872383",
    "sg:postcode":"34125",
    "sg:province":"Hessen",
    "wof:name":"M. Br\u00f6cker Architekt",
    "wof:placetype":"venue"
},
  "geometry": {"coordinates":[9.529497,51.332001],"type":"Point"}
}