{
  "type": "Feature",
  "properties": {
    "iso:country":"DE",
    "sg:address":"Karl-Robiczek-Str. 8",
    "sg:city":"F\u00fcrstenfeldbruck",
    "sg:phone":"+49 8141/51310",
    "sg:postcode":"82256",
    "sg:province":"Bayern",
    "wof:name":"Cwr Werbevermittlungs Gmbh",
    "wof:placetype":"venue"
},
  "geometry": {"coordinates":[11.2640590668,48.1829147339],"type":"Point"}
}