{
  "type": "Feature",
  "properties": {
    "iso:country":"DE",
    "sg:address":"Friedrich-Engels-Ring 9",
    "sg:city":"Seebach",
    "sg:phone":"+49 36929/62350",
    "sg:postcode":"99846",
    "sg:province":"Th\u00fcringen",
    "wof:name":"J\u00fcrgen Feix",
    "wof:placetype":"venue"
},
  "geometry": {"coordinates":[10.427251,50.91156],"type":"Point"}
}