{
  "type": "Feature",
  "properties": {
    "iso:country":"DE",
    "sg:address":"Osteroder Str. 10",
    "sg:city":"Katlenburg-Lindau",
    "sg:phone":"+49 5552/356",
    "sg:postcode":"37191",
    "sg:province":"Niedersachsen",
    "wof:name":"G. Schlemme",
    "wof:placetype":"venue"
},
  "geometry": {"coordinates":[10.1009454727,51.6819610596],"type":"Point"}
}