{
  "type": "Feature",
  "properties": {
    "iso:country":"DE",
    "sg:address":"Hans-Thoma-Str. 5",
    "sg:city":"Rastatt",
    "sg:phone":"+49 4972/2253691",
    "sg:postcode":"76437",
    "sg:province":"Baden-W\u00fcrttemberg",
    "wof:name":"Volksbank Muggensturm Eg",
    "wof:placetype":"venue"
},
  "geometry": {"coordinates":[8.218575,48.842762],"type":"Point"}
}