{
  "type": "Feature",
  "properties": {
    "iso:country":"DE",
    "sg:address":"Wuppertaler Str. 20",
    "sg:city":"Braunschweig",
    "sg:phone":"+49 531/377130",
    "sg:postcode":"38108",
    "sg:province":"Niedersachsen",
    "wof:name":"Helmut L\u00f6hr",
    "wof:placetype":"venue"
},
  "geometry": {"coordinates":[10.555231,52.288204],"type":"Point"}
}