{
  "type": "Feature",
  "properties": {
    "iso:country":"DE",
    "sg:address":"Harrasser Str. 8",
    "sg:city":"Prien",
    "sg:phone":"+49 8051/1013",
    "sg:postcode":"83209",
    "sg:province":"Bayern",
    "wof:name":"Hotel-restaurant Villa Am See",
    "wof:placetype":"venue"
},
  "geometry": {"coordinates":[12.3642263412,47.8596382141],"type":"Point"}
}