{
  "type": "Feature",
  "properties": {
    "iso:country":"DE",
    "sg:address":"Dorfstr. 128",
    "sg:city":"L\u00f6wenberg",
    "sg:phone":"+49 33094/51162",
    "sg:postcode":"16775",
    "sg:province":"Brandenburg",
    "wof:name":"L. Adameck",
    "wof:placetype":"venue"
},
  "geometry": {"coordinates":[13.05299,52.90044],"type":"Point"}
}