{
  "type": "Feature",
  "properties": {
    "iso:country":"DE",
    "sg:address":"Siemensstr. 15",
    "sg:city":"Verl",
    "sg:phone":"+49 5246/2565",
    "sg:postcode":"33415",
    "sg:province":"Nordrhein-Westfalen",
    "wof:name":"Isoliertechnik Ewald Illies Gmbh",
    "wof:placetype":"venue"
},
  "geometry": {"coordinates":[8.558264,51.864429],"type":"Point"}
}