{
  "type": "Feature",
  "properties": {
    "iso:country":"DE",
    "sg:address":"Feldstr. 49",
    "sg:city":"Bokel",
    "sg:phone":"+49 4748/2261",
    "sg:postcode":"27616",
    "sg:province":"Niedersachsen",
    "wof:name":"Hinrich Grotheer",
    "wof:placetype":"venue"
},
  "geometry": {"coordinates":[8.7127056122,53.3817901611],"type":"Point"}
}