{
  "type": "Feature",
  "properties": {
    "iso:country":"DE",
    "sg:address":"Zum Pionierpark",
    "sg:city":"Bad Zwischenahn",
    "sg:phone":"+49 4403/7877",
    "sg:postcode":"26160",
    "sg:province":"Niedersachsen",
    "wof:name":"Isolierglasgesellschaft Bad Zwischenahn Mbh",
    "wof:placetype":"venue"
},
  "geometry": {"coordinates":[7.9765210152,53.1870803833],"type":"Point"}
}