{
  "type": "Feature",
  "properties": {
    "iso:country":"DE",
    "sg:address":"Am Weiheracker 34",
    "sg:city":"Neutraubling",
    "sg:postcode":"93073",
    "sg:province":"Bayern",
    "wof:name":"Barbara-moden",
    "wof:placetype":"venue"
},
  "geometry": {"coordinates":[12.206007,48.981853],"type":"Point"}
}