{
  "type": "Feature",
  "properties": {
    "iso:country":"DE",
    "sg:address":"Homburger Hohl 10",
    "sg:city":"Frankfurt",
    "sg:postcode":"60437",
    "sg:province":"Hessen",
    "wof:name":"Geb\u00e4udemanagement & Service - Esegovic Ohg",
    "wof:placetype":"venue"
},
  "geometry": {"coordinates":[8.6645336151,50.1841049194],"type":"Point"}
}