{
  "type": "Feature",
  "properties": {
    "iso:country":"DE",
    "sg:address":"Blumhardtstr. 18",
    "sg:city":"Heilbronn",
    "sg:phone":"+49 7131/380266",
    "sg:postcode":"74080",
    "sg:province":"Baden-W\u00fcrttemberg",
    "wof:name":"Futterer-lonhard Architekt",
    "wof:placetype":"venue"
},
  "geometry": {"coordinates":[9.192842,49.134983],"type":"Point"}
}