{
  "type": "Feature",
  "properties": {
    "iso:country":"DE",
    "sg:address":"St. Johanner Markt 13",
    "sg:city":"Saarbr\u00fccken",
    "sg:phone":"+49 681/33586",
    "sg:postcode":"66111",
    "sg:province":"Saarland",
    "wof:name":"Breininger Moden",
    "wof:placetype":"venue"
},
  "geometry": {"coordinates":[6.9957909584,49.2328643799],"type":"Point"}
}