{
  "type": "Feature",
  "properties": {
    "iso:country":"DE",
    "sg:address":"Lange Str. 12",
    "sg:city":"Uetze",
    "sg:phone":"+49 5173/1067",
    "sg:postcode":"31311",
    "sg:province":"Niedersachsen",
    "wof:name":"Bernhard Sprenger",
    "wof:placetype":"venue"
},
  "geometry": {"coordinates":[10.197895,52.46611],"type":"Point"}
}