{
  "type": "Feature",
  "properties": {
    "iso:country":"DE",
    "sg:address":"Lindenstr. 5",
    "sg:city":"Gundelfingen",
    "sg:phone":"+49 761/583245",
    "sg:postcode":"79194",
    "sg:province":"Baden-W\u00fcrttemberg",
    "wof:name":"Dietmar M\u00fchl",
    "wof:placetype":"venue"
},
  "geometry": {"coordinates":[7.8657112122,48.0468902588],"type":"Point"}
}