{
  "type": "Feature",
  "properties": {
    "iso:country":"DE",
    "sg:address":"Spechtstr. 1",
    "sg:city":"Berlin",
    "sg:phone":"+49 30/8418800",
    "sg:postcode":"14195",
    "sg:province":"Berlin",
    "wof:name":"Hansa Chemie Cosmetic Gmbh",
    "wof:placetype":"venue"
},
  "geometry": {"coordinates":[13.277691,52.460213],"type":"Point"}
}