{
  "type": "Feature",
  "properties": {
    "iso:country":"DE",
    "sg:address":"Merowingerstr. 37",
    "sg:city":"D\u00fcsseldorf",
    "sg:phone":"+49 211/334120",
    "sg:postcode":"40223",
    "sg:province":"Nordrhein-Westfalen",
    "wof:name":"Haus Kirschniok",
    "wof:placetype":"venue"
},
  "geometry": {"coordinates":[6.7766098976,51.2049980164],"type":"Point"}
}