{
  "type": "Feature",
  "properties": {
    "iso:country":"DE",
    "sg:address":"Kurpfalzring 106",
    "sg:city":"Heidelberg",
    "sg:phone":"+49 6221/779204",
    "sg:postcode":"69123",
    "sg:province":"Baden-W\u00fcrttemberg",
    "wof:name":"Zorn",
    "wof:placetype":"venue"
},
  "geometry": {"coordinates":[8.6402425766,49.4069023132],"type":"Point"}
}