{
  "type": "Feature",
  "properties": {
    "iso:country":"DE",
    "sg:address":"Burgstr. 19",
    "sg:city":"Aurich",
    "sg:phone":"+49 4941/2131",
    "sg:postcode":"26603",
    "sg:province":"Niedersachsen",
    "wof:name":"Ihr Platz Drogeriemarkt",
    "wof:placetype":"venue"
},
  "geometry": {"coordinates":[7.480795,53.469173],"type":"Point"}
}