{
  "type": "Feature",
  "properties": {
    "iso:country":"DE",
    "sg:address":"Lederergasse 43",
    "sg:city":"Passau",
    "sg:phone":"+49 851/34769",
    "sg:postcode":"94032",
    "sg:province":"Bayern",
    "wof:name":"R\u00f6mermuseum Kastel Biotro",
    "wof:placetype":"venue"
},
  "geometry": {"coordinates":[13.462213,48.570049],"type":"Point"}
}