{
  "type": "Feature",
  "properties": {
    "iso:country":"DE",
    "sg:address":"Hermannstr. 66",
    "sg:city":"Berlin",
    "sg:phone":"+49 30/6212059",
    "sg:postcode":"12049",
    "sg:province":"Berlin",
    "wof:name":"Lichteck Neuk\u00f6lln Ursula Trautenhahn",
    "wof:placetype":"venue"
},
  "geometry": {"coordinates":[13.42719,52.475086],"type":"Point"}
}