{
  "type": "Feature",
  "properties": {
    "iso:country":"DE",
    "sg:address":"Niedersteinbacher Str. 13",
    "sg:city":"M\u00f6mbris",
    "sg:phone":"+49 6029/99099",
    "sg:postcode":"63776",
    "sg:province":"Bayern",
    "wof:name":"Hubert R\u00f6ll",
    "wof:placetype":"venue"
},
  "geometry": {"coordinates":[9.174657,50.090576],"type":"Point"}
}