{
  "type": "Feature",
  "properties": {
    "iso:country":"DE",
    "sg:address":"Orsoyer Str. 36",
    "sg:city":"Rheinberg",
    "sg:postcode":"47495",
    "sg:province":"Nordrhein-Westfalen",
    "wof:name":"Alten- Und Pflegeheim Am Kattewald Gmbh",
    "wof:placetype":"venue"
},
  "geometry": {"coordinates":[6.604646,51.544003],"type":"Point"}
}