{
  "type": "Feature",
  "properties": {
    "iso:country":"DE",
    "sg:address":"Erlhof 19",
    "sg:city":"Erfurt-Stotternheim",
    "sg:phone":"+49 36204/77770",
    "sg:postcode":"99195",
    "sg:province":"Th\u00fcringen",
    "wof:name":"Bauzeichenb\u00fcro Kathrin Epperlein",
    "wof:placetype":"venue"
},
  "geometry": {"coordinates":[11.0451889038,51.0606803894],"type":"Point"}
}