{
  "type": "Feature",
  "properties": {
    "iso:country":"DE",
    "sg:address":"Lange Str. 94",
    "sg:city":"Greifswald",
    "sg:phone":"+49 3834/897808",
    "sg:postcode":"17489",
    "sg:province":"Mecklenburg-Vorpommern",
    "wof:name":"Leiendecker Und Homberg Rechtsanw\u00e4lte",
    "wof:placetype":"venue"
},
  "geometry": {"coordinates":[13.3808336258,54.0962104797],"type":"Point"}
}