{
  "type": "Feature",
  "properties": {
    "iso:country":"DE",
    "sg:address":"Werrestr. 2",
    "sg:city":"Herford",
    "sg:phone":"+49 5221/83153",
    "sg:postcode":"32049",
    "sg:province":"Nordrhein-Westfalen",
    "wof:name":"E. H\u00f6lling",
    "wof:placetype":"venue"
},
  "geometry": {"coordinates":[8.6772041321,52.118598938],"type":"Point"}
}