{
  "type": "Feature",
  "properties": {
    "iso:country":"DE",
    "sg:address":"Haidauer Str. 38",
    "sg:city":"Pfatter",
    "sg:phone":"+49 9481/264",
    "sg:postcode":"93102",
    "sg:province":"Bayern",
    "wof:name":"Karl Herwicht",
    "wof:placetype":"venue"
},
  "geometry": {"coordinates":[12.384008,48.965134],"type":"Point"}
}