{
  "type": "Feature",
  "properties": {
    "iso:country":"DE",
    "sg:address":"Klockner Str.",
    "sg:city":"Alt Zachun",
    "sg:postcode":"19230",
    "sg:province":"Mecklenburg-Vorpommern",
    "wof:name":"Kl\u00f6ckner Fl\u00fcssiggaslager Alt Zachun Gmbh & Co. Kg",
    "wof:placetype":"venue"
},
  "geometry": {"coordinates":[11.319632,53.501354],"type":"Point"}
}