{
  "type": "Feature",
  "properties": {
    "iso:country":"DE",
    "sg:address":"Grubholzer Str. 16-18",
    "sg:city":"Rosenheim",
    "sg:phone":"+49 8031/46485",
    "sg:postcode":"83026",
    "sg:province":"Bayern",
    "wof:name":"Ihr Schuhpartner Gmbh",
    "wof:placetype":"venue"
},
  "geometry": {"coordinates":[12.088985,47.849957],"type":"Point"}
}