{
  "type": "Feature",
  "properties": {
    "iso:country":"DE",
    "sg:address":"Rielingsh\u00e4user Str. 42",
    "sg:city":"Marbach",
    "sg:phone":"+49 7144/15790",
    "sg:postcode":"71672",
    "sg:province":"Baden-W\u00fcrttemberg",
    "wof:name":"Sb-car-wash Gmbh",
    "wof:placetype":"venue"
},
  "geometry": {"coordinates":[9.271709,48.944454],"type":"Point"}
}