{
  "type": "Feature",
  "properties": {
    "iso:country":"DE",
    "sg:address":"Hauptstr. 321",
    "sg:city":"Gaienhofen",
    "sg:phone":"+49 7735/774",
    "sg:postcode":"78343",
    "sg:province":"Baden-W\u00fcrttemberg",
    "wof:name":"Dr. Friedrich Rau Rechtsanwalt",
    "wof:placetype":"venue"
},
  "geometry": {"coordinates":[8.972530365,47.6765518188],"type":"Point"}
}