{
  "type": "Feature",
  "properties": {
    "iso:country":"DE",
    "sg:address":"Bruckfelder Str.",
    "sg:city":"Frickingen",
    "sg:phone":"+49 7554/8879",
    "sg:postcode":"88699",
    "sg:province":"Baden-W\u00fcrttemberg",
    "wof:name":"Friedrich Hodapp",
    "wof:placetype":"venue"
},
  "geometry": {"coordinates":[9.266186,47.808208],"type":"Point"}
}