{
  "type": "Feature",
  "properties": {
    "iso:country":"DE",
    "sg:address":"Grundsch\u00f6tteler Str.",
    "sg:city":"Wetter",
    "sg:phone":"+49 2335/6521",
    "sg:postcode":"58300",
    "sg:province":"Nordrhein-Westfalen",
    "wof:name":"H. Br\u00fchne Gmbh & Co. Kg",
    "wof:placetype":"venue"
},
  "geometry": {"coordinates":[7.3684029579,51.3695526123],"type":"Point"}
}