{
  "type": "Feature",
  "properties": {
    "iso:country":"DE",
    "sg:address":"Hauptstr. 24",
    "sg:city":"Schweitenkirchen",
    "sg:phone":"+49 8444/7921",
    "sg:postcode":"85301",
    "sg:province":"Bayern",
    "wof:name":"Karl Wiesender",
    "wof:placetype":"venue"
},
  "geometry": {"coordinates":[11.604443,48.50494],"type":"Point"}
}