{
  "type": "Feature",
  "properties": {
    "iso:country":"DE",
    "sg:address":"Wismarsche Str. 270",
    "sg:city":"Schwerin",
    "sg:phone":"+49 385/558480",
    "sg:postcode":"19053",
    "sg:province":"Mecklenburg-Vorpommern",
    "wof:name":"Bestattungsunternehmen J\u00fcrgen M\u00fcller Gmbh",
    "wof:placetype":"venue"
},
  "geometry": {"coordinates":[11.40206,53.633808],"type":"Point"}
}