{
  "type": "Feature",
  "properties": {
    "iso:country":"DE",
    "sg:address":"Kaiserstr. 112",
    "sg:city":"Lahr",
    "sg:phone":"+49 7821/22335",
    "sg:postcode":"77933",
    "sg:province":"Baden-W\u00fcrttemberg",
    "wof:name":"Heinz Pottiez",
    "wof:placetype":"venue"
},
  "geometry": {"coordinates":[7.8596448898,48.3407478333],"type":"Point"}
}