{
  "type": "Feature",
  "properties": {
    "iso:country":"DE",
    "sg:address":"Hauptstr. 57",
    "sg:city":"Quierschied",
    "sg:phone":"+49 6825/7446",
    "sg:postcode":"66287",
    "sg:province":"Saarland",
    "wof:name":"S. Guth\u00f6rl Hebamme",
    "wof:placetype":"venue"
},
  "geometry": {"coordinates":[7.037945,49.346481],"type":"Point"}
}