{
  "type": "Feature",
  "properties": {
    "iso:country":"DE",
    "sg:address":"Sindringer Str. 12",
    "sg:city":"Forchtenberg",
    "sg:phone":"+49 7947/324",
    "sg:postcode":"74670",
    "sg:province":"Baden-W\u00fcrttemberg",
    "wof:name":"Christian Gundel",
    "wof:placetype":"venue"
},
  "geometry": {"coordinates":[9.51266,49.291389],"type":"Point"}
}