{
  "type": "Feature",
  "properties": {
    "iso:country":"DE",
    "sg:address":"Kirchgasse 21",
    "sg:city":"Strehla",
    "sg:phone":"+49 35264/90715",
    "sg:postcode":"01616",
    "sg:province":"Sachsen",
    "wof:name":"Otto G\u00f6pel Architekten",
    "wof:placetype":"venue"
},
  "geometry": {"coordinates":[13.223749,51.352577],"type":"Point"}
}