{
  "type": "Feature",
  "properties": {
    "iso:country":"DE",
    "sg:address":"Sp\u00fclinsel",
    "sg:city":"Havelberg",
    "sg:postcode":"39539",
    "sg:province":"Sachsen-Anhalt",
    "wof:name":"Campingplatz Havelberg",
    "wof:placetype":"venue"
},
  "geometry": {"coordinates":[12.066934,52.829765],"type":"Point"}
}