{
  "type": "Feature",
  "properties": {
    "iso:country":"DE",
    "sg:address":"Schillerstr. 15",
    "sg:city":"Ulm",
    "sg:phone":"+49 731/66051",
    "sg:postcode":"89077",
    "sg:province":"Baden-W\u00fcrttemberg",
    "wof:name":"Emil Herbst",
    "wof:placetype":"venue"
},
  "geometry": {"coordinates":[9.981801,48.394512],"type":"Point"}
}