{
  "type": "Feature",
  "properties": {
    "iso:country":"DE",
    "sg:address":"Berliner Str. 2",
    "sg:city":"Offenbach",
    "sg:postcode":"63065",
    "sg:province":"Hessen",
    "wof:name":"Kermeta Gmbh",
    "wof:placetype":"venue"
},
  "geometry": {"coordinates":[8.7665548325,50.1052932739],"type":"Point"}
}