{
  "type": "Feature",
  "properties": {
    "iso:country":"DE",
    "sg:address":"Gewerbering 12",
    "sg:city":"G\u00e4gelow",
    "sg:postcode":"23968",
    "sg:province":"Mecklenburg-Vorpommern",
    "wof:name":"Mehe Bau Gmbh",
    "wof:placetype":"venue"
},
  "geometry": {"coordinates":[11.388498,53.902699],"type":"Point"}
}