{
  "type": "Feature",
  "properties": {
    "iso:country":"DE",
    "sg:address":"Feldstr. 6",
    "sg:city":"Idstein",
    "sg:phone":"+49 6126/52228",
    "sg:postcode":"65510",
    "sg:province":"Hessen",
    "wof:name":"Pfeiffer Gmbh",
    "wof:placetype":"venue"
},
  "geometry": {"coordinates":[8.3311920166,50.2197761536],"type":"Point"}
}