{
  "type": "Feature",
  "properties": {
    "iso:country":"DE",
    "sg:address":"Spitzerdorfstr. 22",
    "sg:city":"Wedel",
    "sg:phone":"+49 4103/3995",
    "sg:postcode":"22880",
    "sg:province":"Schleswig-Holstein",
    "wof:name":"C.-h. Bambowsky Ofensetzerei",
    "wof:placetype":"venue"
},
  "geometry": {"coordinates":[9.7057800293,53.5760383606],"type":"Point"}
}