{
  "type": "Feature",
  "properties": {
    "iso:country":"DE",
    "sg:address":"Huchenfelder Hauptstr. 102",
    "sg:city":"Pforzheim",
    "sg:phone":"+49 7231/70419",
    "sg:postcode":"75181",
    "sg:province":"Baden-W\u00fcrttemberg",
    "wof:name":"Karl-heinz Lechler",
    "wof:placetype":"venue"
},
  "geometry": {"coordinates":[8.6962299347,48.8534355164],"type":"Point"}
}