{
  "type": "Feature",
  "properties": {
    "iso:country":"DE",
    "sg:address":"Kantstr. 10",
    "sg:city":"Hirschberg",
    "sg:postcode":"69493",
    "sg:province":"Baden-W\u00fcrttemberg",
    "wof:name":"Meddent Gmbh",
    "wof:placetype":"venue"
},
  "geometry": {"coordinates":[8.661583,49.51268],"type":"Point"}
}