{
  "type": "Feature",
  "properties": {
    "iso:country":"DE",
    "sg:address":"Wiltinger Weg 44",
    "sg:city":"Saarbr\u00fccken",
    "sg:phone":"+49 681/72866",
    "sg:postcode":"66113",
    "sg:province":"Saarland",
    "wof:name":"Georg Krapp Ingenieur",
    "wof:placetype":"venue"
},
  "geometry": {"coordinates":[6.9577879906,49.2581481934],"type":"Point"}
}