{
  "type": "Feature",
  "properties": {
    "iso:country":"DE",
    "sg:address":"Ratzeburger Allee 108a",
    "sg:city":"L\u00fcbeck",
    "sg:phone":"+49 451/502510",
    "sg:postcode":"23562",
    "sg:province":"Schleswig-Holstein",
    "wof:name":"Olympic Auto Gmbh",
    "wof:placetype":"venue"
},
  "geometry": {"coordinates":[10.7078819275,53.8425979614],"type":"Point"}
}