{
  "type": "Feature",
  "properties": {
    "iso:country":"DE",
    "sg:address":"L\u00fctzowstr. 7",
    "sg:city":"K\u00f6ln",
    "sg:phone":"+49 221/212230",
    "sg:postcode":"50674",
    "sg:province":"Nordrhein-Westfalen",
    "wof:name":"Orgafest Organisationsges. Von Veranstaltungen Aller Art Mbh",
    "wof:placetype":"venue"
},
  "geometry": {"coordinates":[6.932303,50.932404],"type":"Point"}
}