{
  "type": "Feature",
  "properties": {
    "iso:country":"DE",
    "sg:address":"Sonnenweg 1",
    "sg:city":"Elchingen",
    "sg:phone":"+49 731/268741",
    "sg:postcode":"89275",
    "sg:province":"Bayern",
    "wof:name":"Josef W\u00f6hrle Steuerberater",
    "wof:placetype":"venue"
},
  "geometry": {"coordinates":[10.0448360443,48.4345016479],"type":"Point"}
}