{
  "type": "Feature",
  "properties": {
    "iso:country":"DE",
    "sg:address":"Walter-K\u00f6hn-Str.1b",
    "sg:city":"Leipzig",
    "sg:phone":"+49 341/5285150",
    "sg:postcode":"04356",
    "sg:province":"Sachsen",
    "wof:name":"Helm Ag",
    "wof:placetype":"venue"
},
  "geometry": {"coordinates":[12.4026222229,51.4010391235],"type":"Point"}
}