{
  "type": "Feature",
  "properties": {
    "iso:country":"DE",
    "sg:address":"Gl\u00f6ther Weg",
    "sg:city":"Atzendorf",
    "sg:phone":"+49 39266/51530",
    "sg:postcode":"39443",
    "sg:province":"Sachsen-Anhalt",
    "wof:name":"Bierstube Inh. Eckehardt Seewitz",
    "wof:placetype":"venue"
},
  "geometry": {"coordinates":[11.6017789841,51.9160423279],"type":"Point"}
}