{
  "type": "Feature",
  "properties": {
    "iso:country":"DE",
    "sg:address":"Karl-Marx-Str. 1",
    "sg:city":"Schwerz",
    "sg:phone":"+49 34604/20434",
    "sg:postcode":"06188",
    "sg:province":"Sachsen-Anhalt",
    "wof:name":"G. Sauer",
    "wof:placetype":"venue"
},
  "geometry": {"coordinates":[12.130526,51.562981],"type":"Point"}
}