{
  "type": "Feature",
  "properties": {
    "iso:country":"DE",
    "sg:address":"Etzhorner Weg 18",
    "sg:city":"Oldenburg",
    "sg:phone":"+49 441/302896",
    "sg:postcode":"26125",
    "sg:province":"Niedersachsen",
    "wof:name":"J\u00fcrgen Heick Architekt",
    "wof:placetype":"venue"
},
  "geometry": {"coordinates":[8.231897,53.171696],"type":"Point"}
}