{
  "type": "Feature",
  "properties": {
    "iso:country":"DE",
    "sg:address":"Ridbacher Str. 67",
    "sg:city":"Berlin",
    "sg:phone":"+49 30/5626293",
    "sg:postcode":"12621",
    "sg:province":"Berlin",
    "wof:name":"Pink Planet",
    "wof:placetype":"venue"
},
  "geometry": {"coordinates":[13.6059532166,52.520526886],"type":"Point"}
}