{
  "type": "Feature",
  "properties": {
    "iso:country":"DE",
    "sg:address":"Auf'm Kolm 25a",
    "sg:city":"Herne",
    "sg:phone":"+49 2323/687060",
    "sg:postcode":"44627",
    "sg:province":"Nordrhein-Westfalen",
    "wof:name":"K. Laufs Steuerberater",
    "wof:placetype":"venue"
},
  "geometry": {"coordinates":[7.2657599449,51.537940979],"type":"Point"}
}