{
  "type": "Feature",
  "properties": {
    "iso:country":"DE",
    "sg:address":"Dorfplatz 3",
    "sg:city":"H\u00f6xter",
    "sg:phone":"+49 5275/1493",
    "sg:postcode":"37671",
    "sg:province":"Nordrhein-Westfalen",
    "wof:name":"Josef Schl\u00fcter",
    "wof:placetype":"venue"
},
  "geometry": {"coordinates":[9.305442,51.707333],"type":"Point"}
}