{
  "type": "Feature",
  "properties": {
    "iso:country":"DE",
    "sg:address":"Am Neumarkt 49",
    "sg:city":"Solingen",
    "sg:phone":"+49 212/204695",
    "sg:postcode":"42651",
    "sg:province":"Nordrhein-Westfalen",
    "wof:name":"Matthias Becker",
    "wof:placetype":"venue"
},
  "geometry": {"coordinates":[7.078825,51.168697],"type":"Point"}
}