{
  "type": "Feature",
  "properties": {
    "iso:country":"DE",
    "sg:address":"Bohmter Str. 1",
    "sg:city":"Osnabr\u00fcck",
    "sg:phone":"+49 541/2022791",
    "sg:postcode":"49074",
    "sg:province":"Niedersachsen",
    "wof:name":"Akjp - Akademie F\u00fcr Kinder- Und Jugendlichen-",
    "wof:placetype":"venue"
},
  "geometry": {"coordinates":[8.0554132462,52.2764472961],"type":"Point"}
}