{
  "type": "Feature",
  "properties": {
    "iso:country":"DE",
    "sg:address":"Neuhof 4",
    "sg:city":"Zenting",
    "sg:phone":"+49 9907/925",
    "sg:postcode":"94579",
    "sg:province":"Bayern",
    "wof:name":"Hotel Neuhof",
    "wof:placetype":"venue"
},
  "geometry": {"coordinates":[13.2801055908,48.7685241699],"type":"Point"}
}