{
  "type": "Feature",
  "properties": {
    "iso:country":"DE",
    "sg:address":"Dessauer Str. 94",
    "sg:city":"Je\u00dfnitz",
    "sg:phone":"+49 3494/34139",
    "sg:postcode":"06800",
    "sg:province":"Sachsen-Anhalt",
    "wof:name":"Jozsef Karsai",
    "wof:placetype":"venue"
},
  "geometry": {"coordinates":[12.2846603394,51.6818885803],"type":"Point"}
}