{
  "type": "Feature",
  "properties": {
    "iso:country":"DE",
    "sg:address":"Eigene Scholle 55",
    "sg:city":"Mannheim",
    "sg:phone":"+49 621/756705",
    "sg:postcode":"68305",
    "sg:province":"Baden-W\u00fcrttemberg",
    "wof:name":"Bruno Differt",
    "wof:placetype":"venue"
},
  "geometry": {"coordinates":[8.498993,49.51812],"type":"Point"}
}