{
  "type": "Feature",
  "properties": {
    "iso:country":"DE",
    "sg:address":"Rupprechtstr. 3 1/2",
    "sg:city":"F\u00fcssen",
    "sg:phone":"+49 8362/93660",
    "sg:postcode":"87629",
    "sg:province":"Bayern",
    "wof:name":"Anton Paulsteiner Steuerberater",
    "wof:placetype":"venue"
},
  "geometry": {"coordinates":[10.6989965439,47.5693893433],"type":"Point"}
}