{
  "type": "Feature",
  "properties": {
    "iso:country":"DE",
    "sg:address":"Langemarckstr. 5",
    "sg:city":"Bonn",
    "sg:phone":"+49 228/441812",
    "sg:postcode":"53227",
    "sg:province":"Nordrhein-Westfalen",
    "wof:name":"H. Hardt",
    "wof:placetype":"venue"
},
  "geometry": {"coordinates":[7.170577,50.710583],"type":"Point"}
}