{
  "type": "Feature",
  "properties": {
    "iso:country":"DE",
    "sg:address":"Neufriedrichsdorfer Str. 50b",
    "sg:city":"Rathenow",
    "sg:phone":"+49 3385/513447",
    "sg:postcode":"14712",
    "sg:province":"Brandenburg",
    "wof:name":"Hans Zimmermann",
    "wof:placetype":"venue"
},
  "geometry": {"coordinates":[12.374523,52.602367],"type":"Point"}
}