{
  "type": "Feature",
  "properties": {
    "iso:country":"DE",
    "sg:address":"Schramberger Str. 48",
    "sg:city":"Eschbronn",
    "sg:phone":"+49 7403/1085",
    "sg:postcode":"78664",
    "sg:province":"Baden-W\u00fcrttemberg",
    "wof:name":"Eugen Jauch",
    "wof:placetype":"venue"
},
  "geometry": {"coordinates":[8.456136,48.188232],"type":"Point"}
}