{
  "type": "Feature",
  "properties": {
    "iso:country":"DE",
    "sg:address":"Engertstr. 2",
    "sg:city":"Stockdorf",
    "sg:phone":"+49 89/8576750",
    "sg:postcode":"82131",
    "sg:province":"Bayern",
    "wof:name":"Walter Ortmann Landschaftsarchitekt",
    "wof:placetype":"venue"
},
  "geometry": {"coordinates":[11.398437,48.092838],"type":"Point"}
}