{
  "type": "Feature",
  "properties": {
    "iso:country":"DE",
    "sg:address":"Offenbacher Str. 46",
    "sg:city":"M\u00fchlheim",
    "sg:phone":"+49 6108/72501",
    "sg:postcode":"63165",
    "sg:province":"Hessen",
    "wof:name":"Bkm Gmbh",
    "wof:placetype":"venue"
},
  "geometry": {"coordinates":[8.82764,50.123173],"type":"Point"}
}