{
  "type": "Feature",
  "properties": {
    "iso:country":"DE",
    "sg:address":"Fl\u00fcgeldamm 13",
    "sg:city":"Hannover",
    "sg:postcode":"30419",
    "sg:province":"Niedersachsen",
    "wof:name":"Sozialwerk Vinnhorst E. V.",
    "wof:placetype":"venue"
},
  "geometry": {"coordinates":[9.7006101608,52.4185371399],"type":"Point"}
}