{
  "type": "Feature",
  "properties": {
    "iso:country":"DE",
    "sg:address":"Dr.-Rudolf-Eberle-Str. 2 Steinbach",
    "sg:city":"Baden-Baden",
    "sg:phone":"+49 4972/2396360",
    "sg:postcode":"76534",
    "sg:province":"Baden-W\u00fcrttemberg",
    "wof:name":"Schulz Electronic Gmbh",
    "wof:placetype":"venue"
},
  "geometry": {"coordinates":[8.17941,48.735222],"type":"Point"}
}