{
  "type": "Feature",
  "properties": {
    "iso:country":"DE",
    "sg:address":"Bandwirkerstr. 34",
    "sg:city":"Hamburg",
    "sg:phone":"+49 40/6570880",
    "sg:postcode":"22041",
    "sg:province":"Hamburg",
    "wof:name":"Tosun Baugesellschaft Mbh",
    "wof:placetype":"venue"
},
  "geometry": {"coordinates":[10.0643,53.576683],"type":"Point"}
}