{
  "type": "Feature",
  "properties": {
    "iso:country":"DE",
    "sg:address":"Krickelberg 195",
    "sg:city":"H\u00fcckelhoven",
    "sg:phone":"+49 2433/958686",
    "sg:postcode":"41836",
    "sg:province":"Nordrhein-Westfalen",
    "wof:name":"Rs Parfumwelt",
    "wof:placetype":"venue"
},
  "geometry": {"coordinates":[6.1660070419,51.0734672546],"type":"Point"}
}