{
  "type": "Feature",
  "properties": {
    "iso:country":"DE",
    "sg:address":"Karl-Marx-Str. 2",
    "sg:city":"Hohenziatz",
    "sg:phone":"+49 39226/230",
    "sg:postcode":"39291",
    "sg:province":"Sachsen-Anhalt",
    "wof:name":"Lutz Zimmermann",
    "wof:placetype":"venue"
},
  "geometry": {"coordinates":[12.046949,52.179329],"type":"Point"}
}