{
  "type": "Feature",
  "properties": {
    "iso:country":"DE",
    "sg:address":"Barbarastr. 73",
    "sg:city":"Bleicherode",
    "sg:phone":"+49 36338/42822",
    "sg:postcode":"99752",
    "sg:province":"Th\u00fcringen",
    "wof:name":"Freibad",
    "wof:placetype":"venue"
},
  "geometry": {"coordinates":[10.5669898987,51.442325592],"type":"Point"}
}