{
  "type": "Feature",
  "properties": {
    "iso:country":"DE",
    "sg:address":"Gartenweg 9 b",
    "sg:city":"Schongau",
    "sg:phone":"+49 8861/200459",
    "sg:postcode":"86956",
    "sg:province":"Bayern",
    "wof:name":"Anton Wieland",
    "wof:placetype":"venue"
},
  "geometry": {"coordinates":[10.889283,47.811333],"type":"Point"}
}