{
  "type": "Feature",
  "properties": {
    "iso:country":"DE",
    "sg:address":"Altgruland 7",
    "sg:city":"Iserlohn",
    "sg:phone":"+49 2378/3222",
    "sg:postcode":"58640",
    "sg:province":"Nordrhein-Westfalen",
    "wof:name":"Gustav Schrader",
    "wof:placetype":"venue"
},
  "geometry": {"coordinates":[7.69181,51.457657],"type":"Point"}
}