{
  "type": "Feature",
  "properties": {
    "iso:country":"DE",
    "sg:address":"Koiserweg 3",
    "sg:city":"Schorndorf",
    "sg:phone":"+49 9971/30209",
    "sg:postcode":"93489",
    "sg:province":"Bayern",
    "wof:name":"Franz Fischer",
    "wof:placetype":"venue"
},
  "geometry": {"coordinates":[12.609434,49.189369],"type":"Point"}
}