{
  "type": "Feature",
  "properties": {
    "iso:country":"DE",
    "sg:address":"Wilhelmstr. 3",
    "sg:city":"Furtwangen",
    "sg:phone":"+49 7723/5592",
    "sg:postcode":"78120",
    "sg:province":"Baden-W\u00fcrttemberg",
    "wof:name":"Rutschmann Optik",
    "wof:placetype":"venue"
},
  "geometry": {"coordinates":[8.2058124542,48.0505638123],"type":"Point"}
}