{
  "type": "Feature",
  "properties": {
    "iso:country":"DE",
    "sg:address":"Colonnaden 72 II",
    "sg:city":"Hamburg",
    "sg:postcode":"20354",
    "sg:province":"Hamburg",
    "wof:name":"Ter\u00e4sjousi Deutschland Gmbh",
    "wof:placetype":"venue"
},
  "geometry": {"coordinates":[9.9924449921,53.5533447266],"type":"Point"}
}