{
  "type": "Feature",
  "properties": {
    "iso:country":"DE",
    "sg:address":"K\u00fckenbrink 5",
    "sg:city":"Porta Westfalica",
    "sg:phone":"+49 5751/8221",
    "sg:postcode":"32457",
    "sg:province":"Nordrhein-Westfalen",
    "wof:name":"Wilhelm Ostermeier",
    "wof:placetype":"venue"
},
  "geometry": {"coordinates":[9.0119400024,52.2033805847],"type":"Point"}
}