{
  "type": "Feature",
  "properties": {
    "iso:country":"DE",
    "sg:address":"W\u00fcrzburger Str. 43",
    "sg:city":"Bad Neustadt",
    "sg:phone":"+49 9771/3039",
    "sg:postcode":"97616",
    "sg:province":"Bayern",
    "wof:name":"Anni Zschiesche",
    "wof:placetype":"venue"
},
  "geometry": {"coordinates":[10.1923427582,50.3226890564],"type":"Point"}
}