{
  "type": "Feature",
  "properties": {
    "iso:country":"DE",
    "sg:address":"Talstr. 37",
    "sg:city":"Quierschied",
    "sg:phone":"+49 6897/64583",
    "sg:postcode":"66287",
    "sg:province":"Saarland",
    "wof:name":"M. Paries Gmbh",
    "wof:placetype":"venue"
},
  "geometry": {"coordinates":[7.0259919167,49.3033256531],"type":"Point"}
}