{
  "type": "Feature",
  "properties": {
    "iso:country":"DE",
    "sg:address":"Abtsleitenweg 4",
    "sg:city":"W\u00fcrzburg",
    "sg:phone":"+49 931/74307",
    "sg:postcode":"97074",
    "sg:province":"Bayern",
    "wof:name":"Helmuth Weber Bildhauer",
    "wof:placetype":"venue"
},
  "geometry": {"coordinates":[9.957349,49.7771],"type":"Point"}
}