{
  "type": "Feature",
  "properties": {
    "iso:country":"DE",
    "sg:address":"Ballengasse 4",
    "sg:city":"Garmisch-Partenkirchen",
    "sg:phone":"+49 8821/3271",
    "sg:postcode":"82467",
    "sg:province":"Bayern",
    "wof:name":"G\u00e4stehaus Utzschneider",
    "wof:placetype":"venue"
},
  "geometry": {"coordinates":[11.1125602722,47.4934005737],"type":"Point"}
}