{
  "type": "Feature",
  "properties": {
    "iso:country":"DE",
    "sg:address":"Stadelgasse 12",
    "sg:city":"Neuried",
    "sg:phone":"+49 7807/2303",
    "sg:postcode":"77743",
    "sg:province":"Baden-W\u00fcrttemberg",
    "wof:name":"Christian Fischer",
    "wof:placetype":"venue"
},
  "geometry": {"coordinates":[7.8163809776,48.4663505554],"type":"Point"}
}