{
  "type": "Feature",
  "properties": {
    "iso:country":"DE",
    "sg:address":"Im Gewerbegebiet 3",
    "sg:city":"He\u00dfdorf",
    "sg:phone":"+49 9135/6717",
    "sg:postcode":"91093",
    "sg:province":"Bayern",
    "wof:name":"Kurt Hilbinger K\u00e4ltetechnik Gmbh",
    "wof:placetype":"venue"
},
  "geometry": {"coordinates":[10.905789,49.623417],"type":"Point"}
}