{
  "type": "Feature",
  "properties": {
    "iso:country":"DE",
    "sg:address":"Inselstr. 5",
    "sg:city":"Wittd\u00fcn",
    "sg:phone":"+49 4682/4115",
    "sg:postcode":"25946",
    "sg:province":"Schleswig-Holstein",
    "wof:name":"Jens Quedens",
    "wof:placetype":"venue"
},
  "geometry": {"coordinates":[8.3977527618,54.6269264221],"type":"Point"}
}