{
  "type": "Feature",
  "properties": {
    "iso:country":"DE",
    "sg:address":"Lange Str. 1 a",
    "sg:city":"Ganderkesee",
    "sg:phone":"+49 4222/93250",
    "sg:postcode":"27777",
    "sg:province":"Niedersachsen",
    "wof:name":"Storch Industrie- Anlagen Gmbh",
    "wof:placetype":"venue"
},
  "geometry": {"coordinates":[8.54852,53.032162],"type":"Point"}
}