{
  "type": "Feature",
  "properties": {
    "iso:country":"DE",
    "sg:address":"Hohenbudberger Str. 1",
    "sg:city":"Krefeld",
    "sg:phone":"+49 2151/46058",
    "sg:postcode":"47829",
    "sg:province":"Nordrhein-Westfalen",
    "wof:name":"Pizzeria Romana",
    "wof:placetype":"venue"
},
  "geometry": {"coordinates":[6.6489739418,51.3583488464],"type":"Point"}
}