{
  "type": "Feature",
  "properties": {
    "iso:country":"DE",
    "sg:address":"St\u00fcbbenhauser Str. 46",
    "sg:city":"Mettmann",
    "sg:phone":"+49 2104/97130",
    "sg:postcode":"40822",
    "sg:province":"Nordrhein-Westfalen",
    "wof:name":"Becker Systemtechnik Gmbh",
    "wof:placetype":"venue"
},
  "geometry": {"coordinates":[6.959556,51.255493],"type":"Point"}
}