{
  "type": "Feature",
  "properties": {
    "iso:country":"DE",
    "sg:address":"Kabelweg 29",
    "sg:city":"Dessau",
    "sg:postcode":"06842",
    "sg:province":"Sachsen-Anhalt",
    "wof:name":"Osc Optical Sealing Control Gmbh",
    "wof:placetype":"venue"
},
  "geometry": {"coordinates":[12.238409,51.817947],"type":"Point"}
}