{
  "type": "Feature",
  "properties": {
    "iso:country":"DE",
    "sg:address":"Adalbert-Stifter-Str. 3",
    "sg:city":"Ratingen",
    "sg:phone":"+49 2102/31226",
    "sg:postcode":"40885",
    "sg:province":"Nordrhein-Westfalen",
    "wof:name":"Dr. Matthias Eschricht Rechtsanwalt",
    "wof:placetype":"venue"
},
  "geometry": {"coordinates":[6.8218050003,51.3279762268],"type":"Point"}
}