{
  "type": "Feature",
  "properties": {
    "iso:country":"DE",
    "sg:address":"Fliederweg 9",
    "sg:city":"Hitzhofen",
    "sg:phone":"+49 841/26418",
    "sg:postcode":"85122",
    "sg:province":"Bayern",
    "wof:name":"In-kart Gmbh",
    "wof:placetype":"venue"
},
  "geometry": {"coordinates":[11.315863,48.848701],"type":"Point"}
}