{
  "type": "Feature",
  "properties": {
    "iso:country":"DE",
    "sg:address":"Neustadt 2",
    "sg:city":"Lehesten",
    "sg:phone":"+49 36653/22213",
    "sg:postcode":"07349",
    "sg:province":"Th\u00fcringen",
    "wof:name":"Gl\u00fcckauf-apotheke Ingeborg Rimpel",
    "wof:placetype":"venue"
},
  "geometry": {"coordinates":[11.453017,50.474812],"type":"Point"}
}