{
  "type": "Feature",
  "properties": {
    "iso:country":"DE",
    "sg:address":"Hochfeldstr. 9",
    "sg:city":"Evenhausen",
    "sg:phone":"+49 8075/1543",
    "sg:postcode":"83552",
    "sg:province":"Bayern",
    "wof:name":"G. Reiser",
    "wof:placetype":"venue"
},
  "geometry": {"coordinates":[12.287074,48.027046],"type":"Point"}
}