{
  "type": "Feature",
  "properties": {
    "iso:country":"DE",
    "sg:address":"Bl\u00fccherstr. 5 a",
    "sg:city":"Edenkoben",
    "sg:phone":"+49 6323/7129",
    "sg:postcode":"67480",
    "sg:province":"Rheinland-Pfalz",
    "wof:name":"Brigitte Poth",
    "wof:placetype":"venue"
},
  "geometry": {"coordinates":[8.127938,49.278385],"type":"Point"}
}