{
  "type": "Feature",
  "properties": {
    "iso:country":"DE",
    "sg:address":"Ansbacher Str. 19",
    "sg:city":"Flachslanden",
    "sg:phone":"+49 9829/276",
    "sg:postcode":"91604",
    "sg:province":"Bayern",
    "wof:name":"Martin Volkert",
    "wof:placetype":"venue"
},
  "geometry": {"coordinates":[10.5123243332,49.3970184326],"type":"Point"}
}