{
  "type": "Feature",
  "properties": {
    "iso:country":"DE",
    "sg:address":"Huckarder Str. 14",
    "sg:city":"Essen",
    "sg:phone":"+49 201/282754",
    "sg:postcode":"45139",
    "sg:province":"Nordrhein-Westfalen",
    "wof:name":"Werner Olschewski",
    "wof:placetype":"venue"
},
  "geometry": {"coordinates":[7.047137,51.456657],"type":"Point"}
}