{
  "type": "Feature",
  "properties": {
    "iso:country":"DE",
    "sg:address":"Sengbergstr. 6",
    "sg:city":"Wiehl",
    "sg:phone":"+49 2262/93763",
    "sg:postcode":"51674",
    "sg:province":"Nordrhein-Westfalen",
    "wof:name":"Wilfried Nierstenh\u00f6fer",
    "wof:placetype":"venue"
},
  "geometry": {"coordinates":[7.585443,50.950298],"type":"Point"}
}