{
  "type": "Feature",
  "properties": {
    "iso:country":"DE",
    "sg:address":"Gewerbegebiet 6",
    "sg:city":"Schleife",
    "sg:phone":"+49 35773/76932",
    "sg:postcode":"02959",
    "sg:province":"Sachsen",
    "wof:name":"Zatt Hoch-tiefbau Gmbh",
    "wof:placetype":"venue"
},
  "geometry": {"coordinates":[14.533072,51.52895],"type":"Point"}
}