{
  "type": "Feature",
  "properties": {
    "iso:country":"DE",
    "sg:address":"Am Gerbersberg 9",
    "sg:city":"Rothenburg",
    "sg:phone":"+49 9861/86499",
    "sg:postcode":"91541",
    "sg:province":"Bayern",
    "wof:name":"Dr. Med. Gerhard Sauer",
    "wof:placetype":"venue"
},
  "geometry": {"coordinates":[10.1727838516,49.3841247559],"type":"Point"}
}