{
  "type": "Feature",
  "properties": {
    "iso:country":"DE",
    "sg:address":"Rheinstra\u00dfe 27",
    "sg:city":"Linz",
    "sg:phone":"+49 2644/80480",
    "sg:postcode":"53545",
    "sg:province":"Rheinland-Pfalz",
    "wof:name":"Schmitz Dessous-die W\u00e4sche Der Besonderen Art",
    "wof:placetype":"venue"
},
  "geometry": {"coordinates":[7.280432,50.566067],"type":"Point"}
}