{
  "type": "Feature",
  "properties": {
    "iso:country":"DE",
    "sg:address":"Sparbrod 18",
    "sg:city":"Gersfeld",
    "sg:phone":"+49 6654/7714",
    "sg:postcode":"36129",
    "sg:province":"Hessen",
    "wof:name":"C. Gro\u00df Hebamme",
    "wof:placetype":"venue"
},
  "geometry": {"coordinates":[9.913216,50.438763],"type":"Point"}
}