{
  "type": "Feature",
  "properties": {
    "iso:country":"DE",
    "sg:address":"Freiheitsring 44",
    "sg:city":"Frechen",
    "sg:phone":"+49 2234/53643",
    "sg:postcode":"50226",
    "sg:province":"Nordrhein-Westfalen",
    "wof:name":"Ulrich M\u00fcller",
    "wof:placetype":"venue"
},
  "geometry": {"coordinates":[6.810416,50.912827],"type":"Point"}
}