{
  "type": "Feature",
  "properties": {
    "iso:country":"DE",
    "sg:address":"B\u00fcnder Str. 49",
    "sg:city":"Hiddenhausen",
    "sg:phone":"+49 5221/61550",
    "sg:postcode":"32120",
    "sg:province":"Nordrhein-Westfalen",
    "wof:name":"Wehmeyer & Strunck Gmbh & Co. Kg",
    "wof:placetype":"venue"
},
  "geometry": {"coordinates":[8.64839,52.142105],"type":"Point"}
}