{
  "type": "Feature",
  "properties": {
    "iso:country":"DE",
    "sg:address":"Kaiserstr. 21",
    "sg:city":"Auerbach",
    "sg:phone":"+49 3744/215283",
    "sg:postcode":"08209",
    "sg:province":"Sachsen",
    "wof:name":"W\u00fcstenrot",
    "wof:placetype":"venue"
},
  "geometry": {"coordinates":[12.3932151794,50.5079612732],"type":"Point"}
}