{
  "type": "Feature",
  "properties": {
    "iso:country":"DE",
    "sg:address":"Ruhrfelder Str. 39",
    "sg:city":"M\u00f6nchengladbach",
    "sg:phone":"+49 2166/961468",
    "sg:postcode":"41199",
    "sg:province":"Nordrhein-Westfalen",
    "wof:name":"Barx",
    "wof:placetype":"venue"
},
  "geometry": {"coordinates":[6.447891,51.136192],"type":"Point"}
}