{
  "type": "Feature",
  "properties": {
    "iso:country":"DE",
    "sg:address":"D\u00fcrerstr. 4d",
    "sg:city":"Bad Nauheim",
    "sg:phone":"+49 6032/85133",
    "sg:postcode":"61231",
    "sg:province":"Hessen",
    "wof:name":"Dr. Med. Michael Klemm Arzt F. Frauenheilkunde",
    "wof:placetype":"venue"
},
  "geometry": {"coordinates":[8.7269001007,50.3844184875],"type":"Point"}
}