{
  "type": "Feature",
  "properties": {
    "iso:country":"DE",
    "sg:address":"Hauptstr. 29",
    "sg:city":"Steimke",
    "sg:phone":"+49 39008/253",
    "sg:postcode":"38486",
    "sg:province":"Sachsen-Anhalt",
    "wof:name":"Siegfried Jungnickel",
    "wof:placetype":"venue"
},
  "geometry": {"coordinates":[10.967306,52.589943],"type":"Point"}
}