{
  "type": "Feature",
  "properties": {
    "iso:country":"DE",
    "sg:address":"Mittelstr. 4",
    "sg:city":"H\u00f6gel",
    "sg:phone":"+49 4673/556",
    "sg:postcode":"25858",
    "sg:province":"Schleswig-Holstein",
    "wof:name":"Frank Diewald Heilpraktiker",
    "wof:placetype":"venue"
},
  "geometry": {"coordinates":[9.0601377487,54.6430244446],"type":"Point"}
}