{
  "type": "Feature",
  "properties": {
    "iso:country":"DE",
    "sg:address":"Hauptstr. 38",
    "sg:city":"Triberg",
    "sg:phone":"+49 7722/4489",
    "sg:postcode":"78098",
    "sg:province":"Baden-W\u00fcrttemberg",
    "wof:name":"Charlotte Reiner",
    "wof:placetype":"venue"
},
  "geometry": {"coordinates":[8.2329349518,48.1319694519],"type":"Point"}
}