{
  "type": "Feature",
  "properties": {
    "iso:country":"DE",
    "sg:address":"Schlo\u00dfberg 35",
    "sg:city":"Riedlingen",
    "sg:phone":"+49 7371/6539",
    "sg:postcode":"88499",
    "sg:province":"Baden-W\u00fcrttemberg",
    "wof:name":"Paul Braun",
    "wof:placetype":"venue"
},
  "geometry": {"coordinates":[9.476842,48.124783],"type":"Point"}
}