{
  "type": "Feature",
  "properties": {
    "iso:country":"DE",
    "sg:address":"Moltkestr. 28a",
    "sg:city":"L\u00fcnen",
    "sg:phone":"+49 2306/12486",
    "sg:postcode":"44536",
    "sg:province":"Nordrhein-Westfalen",
    "wof:name":"Horst Hohen",
    "wof:placetype":"venue"
},
  "geometry": {"coordinates":[7.508878231,51.6139717102],"type":"Point"}
}