{
  "type": "Feature",
  "properties": {
    "iso:country":"DE",
    "sg:address":"Nossener Str. 50",
    "sg:city":"Siebenlehn",
    "sg:phone":"+49 35242/43543",
    "sg:postcode":"09634",
    "sg:province":"Sachsen",
    "wof:name":"Elite Maschinenbau Siebenlehn Gmbh",
    "wof:placetype":"venue"
},
  "geometry": {"coordinates":[13.3034505844,51.0336952209],"type":"Point"}
}