{
  "type": "Feature",
  "properties": {
    "iso:country":"DE",
    "sg:address":"Kirchsteinstr. 2",
    "sg:city":"Sindelsdorf",
    "sg:phone":"+49 8856/3900",
    "sg:postcode":"82404",
    "sg:province":"Bayern",
    "wof:name":"Kath. Pfarramt St. Georg",
    "wof:placetype":"venue"
},
  "geometry": {"coordinates":[11.332570076,47.7225227356],"type":"Point"}
}