{
  "type": "Feature",
  "properties": {
    "iso:country":"DE",
    "sg:address":"Fasanenhain 3",
    "sg:city":"Hamburg",
    "sg:phone":"+49 40/6404449",
    "sg:postcode":"22391",
    "sg:province":"Hamburg",
    "wof:name":"Birgit Pilz-jenssen",
    "wof:placetype":"venue"
},
  "geometry": {"coordinates":[10.098052,53.635303],"type":"Point"}
}