{
  "type": "Feature",
  "properties": {
    "iso:country":"DE",
    "sg:address":"Fichtestra\u00dfe 25",
    "sg:city":"Offenbach",
    "sg:postcode":"63071",
    "sg:province":"Hessen",
    "wof:name":"Biopry - Wissenschaft Und Kommunikation",
    "wof:placetype":"venue"
},
  "geometry": {"coordinates":[8.791938,50.092976],"type":"Point"}
}