{
  "type": "Feature",
  "properties": {
    "iso:country":"DE",
    "sg:address":"Delitzscher Str 23",
    "sg:city":"L\u00f6bnitz",
    "sg:phone":"+49 34208/74230",
    "sg:postcode":"04509",
    "sg:province":"Sachsen",
    "wof:name":"Heka Fenster Gmbh & Co Kg",
    "wof:placetype":"venue"
},
  "geometry": {"coordinates":[12.353228569,51.5111045837],"type":"Point"}
}