{
  "type": "Feature",
  "properties": {
    "iso:country":"DE",
    "sg:address":"Hauptstr. 36",
    "sg:city":"Brombachtal",
    "sg:phone":"+49 6063/2380",
    "sg:postcode":"64753",
    "sg:province":"Hessen",
    "wof:name":"Emil B\u00fchler",
    "wof:placetype":"venue"
},
  "geometry": {"coordinates":[8.9532442093,49.7352561951],"type":"Point"}
}