{
  "type": "Feature",
  "properties": {
    "iso:country":"DE",
    "sg:address":"Miesenbacher Str. 10a",
    "sg:city":"Kottweiler-Schwanden",
    "sg:postcode":"66879",
    "sg:province":"Rheinland-Pfalz",
    "wof:name":"Knappenverein August Lehnhart",
    "wof:placetype":"venue"
},
  "geometry": {"coordinates":[7.5297751427,49.4563980103],"type":"Point"}
}