{
  "type": "Feature",
  "properties": {
    "iso:country":"DE",
    "sg:address":"Karl-Martell-Str. 33",
    "sg:city":"N\u00fcrnberg",
    "sg:phone":"+49 911/993100",
    "sg:postcode":"90431",
    "sg:province":"Bayern",
    "wof:name":"Max Weishaupt Gmbh",
    "wof:placetype":"venue"
},
  "geometry": {"coordinates":[11.012157,49.457676],"type":"Point"}
}