{
  "type": "Feature",
  "properties": {
    "iso:country":"DE",
    "sg:address":"Berliner Platz 9",
    "sg:city":"Sindelfingen",
    "sg:phone":"+49 7031/812233",
    "sg:postcode":"71065",
    "sg:province":"Baden-W\u00fcrttemberg",
    "wof:name":"Mayer",
    "wof:placetype":"venue"
},
  "geometry": {"coordinates":[9.016303,48.70026],"type":"Point"}
}