{
  "type": "Feature",
  "properties": {
    "iso:country":"DE",
    "sg:address":"Mittagsteinstr. 11",
    "sg:city":"Arrach",
    "sg:phone":"+49 9943/1382",
    "sg:postcode":"93474",
    "sg:province":"Bayern",
    "wof:name":"Hermann Zapf",
    "wof:placetype":"venue"
},
  "geometry": {"coordinates":[12.991908,49.206959],"type":"Point"}
}