{
  "type": "Feature",
  "properties": {
    "iso:country":"DE",
    "sg:address":"Rostocker Str. 5",
    "sg:city":"Wismar",
    "sg:phone":"+49 3841/25550",
    "sg:postcode":"23970",
    "sg:province":"Mecklenburg-Vorpommern",
    "wof:name":"Autohaus Bumann Gmbh",
    "wof:placetype":"venue"
},
  "geometry": {"coordinates":[11.483986,53.894459],"type":"Point"}
}