{
  "type": "Feature",
  "properties": {
    "iso:country":"DE",
    "sg:address":"Drosselweg 10",
    "sg:city":"Landau",
    "sg:phone":"+49 9951/8558",
    "sg:postcode":"94405",
    "sg:province":"Bayern",
    "wof:name":"Xaver N\u00fcrnberger",
    "wof:placetype":"venue"
},
  "geometry": {"coordinates":[12.760923,48.696987],"type":"Point"}
}