{
  "type": "Feature",
  "properties": {
    "iso:country":"DE",
    "sg:address":"Bahnhofstr. 33",
    "sg:city":"Berlin",
    "sg:phone":"+49 30/2155463",
    "sg:postcode":"12555",
    "sg:province":"Berlin",
    "wof:name":"Box Office Theaterkassen Gmbh",
    "wof:placetype":"venue"
},
  "geometry": {"coordinates":[13.579173,52.458618],"type":"Point"}
}