{
  "type": "Feature",
  "properties": {
    "iso:country":"DE",
    "sg:address":"Glash\u00fcttenstr. 57",
    "sg:city":"D\u00fcsseldorf",
    "sg:phone":"+49 211/278061",
    "sg:postcode":"40627",
    "sg:province":"Nordrhein-Westfalen",
    "wof:name":"Ngz Geldz\u00e4hlmaschinengesellschaft",
    "wof:placetype":"venue"
},
  "geometry": {"coordinates":[6.8662657738,51.2163734436],"type":"Point"}
}