{
  "type": "Feature",
  "properties": {
    "iso:country":"DE",
    "sg:address":"Leopoldstr. 27",
    "sg:city":"Berlin",
    "sg:phone":"+49 30/5665702",
    "sg:postcode":"12621",
    "sg:province":"Berlin",
    "wof:name":"Ingenieur B\u00fcro F\u00fcr Projekt- Management Heising Gmbh",
    "wof:placetype":"venue"
},
  "geometry": {"coordinates":[13.5922832489,52.5096359253],"type":"Point"}
}