{
  "type": "Feature",
  "properties": {
    "iso:country":"DE",
    "sg:address":"Tillmannsweg 9a",
    "sg:city":"Berlin",
    "sg:phone":"+49 30/80588251",
    "sg:postcode":"14109",
    "sg:province":"Berlin",
    "wof:name":"Boston Haus Baumanagement Gmbh",
    "wof:placetype":"venue"
},
  "geometry": {"coordinates":[13.1837835312,52.4257888794],"type":"Point"}
}