{
  "type": "Feature",
  "properties": {
    "iso:country":"DE",
    "sg:address":"Bahnhofstr. 4",
    "sg:city":"Wiesau",
    "sg:phone":"+49 9634/1684",
    "sg:postcode":"95676",
    "sg:province":"Bayern",
    "wof:name":"Thomas Schiml",
    "wof:placetype":"venue"
},
  "geometry": {"coordinates":[12.1807346344,49.909866333],"type":"Point"}
}