{
  "type": "Feature",
  "properties": {
    "iso:country":"DE",
    "sg:address":"Schallbruch 10",
    "sg:city":"Haan",
    "sg:phone":"+49 6172/457555",
    "sg:postcode":"42781",
    "sg:province":"Nordrhein-Westfalen",
    "wof:name":"Michael Alois Sch\u00c4fer Dachbedeckung Gmbh",
    "wof:placetype":"venue"
},
  "geometry": {"coordinates":[8.666316,50.232643],"type":"Point"}
}