{
  "type": "Feature",
  "properties": {
    "iso:country":"DE",
    "sg:address":"Im Schollengarten 1",
    "sg:city":"Bruchsal",
    "sg:phone":"+49 7257/1278",
    "sg:postcode":"76646",
    "sg:province":"Baden-W\u00fcrttemberg",
    "wof:name":"Squash-point Fitness-treff",
    "wof:placetype":"venue"
},
  "geometry": {"coordinates":[8.5592212677,49.0938568115],"type":"Point"}
}