{
  "type": "Feature",
  "properties": {
    "iso:country":"DE",
    "sg:address":"Sendenhorster Str. 10",
    "sg:city":"Sendenhorst",
    "sg:phone":"+49 2535/280",
    "sg:postcode":"48324",
    "sg:province":"Nordrhein-Westfalen",
    "wof:name":"Engel-apotheke",
    "wof:placetype":"venue"
},
  "geometry": {"coordinates":[7.829749,51.806767],"type":"Point"}
}