{
  "type": "Feature",
  "properties": {
    "iso:country":"DE",
    "sg:address":"Borsigallee 40",
    "sg:city":"Frankfurt",
    "sg:phone":"+49 6109/32552",
    "sg:postcode":"60388",
    "sg:province":"Hessen",
    "wof:name":"Volkshaus Enkheim",
    "wof:placetype":"venue"
},
  "geometry": {"coordinates":[8.7543382645,50.1424102783],"type":"Point"}
}