{
  "type": "Feature",
  "properties": {
    "iso:country":"DE",
    "sg:address":"Siemensallee 10",
    "sg:city":"Maintal",
    "sg:phone":"+49 6181/491892",
    "sg:postcode":"63477",
    "sg:province":"Hessen",
    "wof:name":"Arnold-optik Inh. Wolfgang Ludwig",
    "wof:placetype":"venue"
},
  "geometry": {"coordinates":[8.842305,50.13776],"type":"Point"}
}