{
  "type": "Feature",
  "properties": {
    "iso:country":"DE",
    "sg:address":"W\u00f6llnitzer Str. 75",
    "sg:city":"Jena",
    "sg:phone":"+49 3641/380343",
    "sg:postcode":"07749",
    "sg:province":"Th\u00fcringen",
    "wof:name":"Kr\u00f6ber Gmbh",
    "wof:placetype":"venue"
},
  "geometry": {"coordinates":[11.589221,50.909046],"type":"Point"}
}