{
  "type": "Feature",
  "properties": {
    "iso:country":"DE",
    "sg:address":"Beckerstr. 4 a",
    "sg:city":"Willich",
    "sg:phone":"+49 2154",
    "sg:postcode":"47877",
    "sg:province":"Nordrhein-Westfalen",
    "wof:name":"Tele/energie Beratungs-service",
    "wof:placetype":"venue"
},
  "geometry": {"coordinates":[6.53617,51.266575],"type":"Point"}
}