{
  "type": "Feature",
  "properties": {
    "iso:country":"DE",
    "sg:address":"Hildesheimer Str. 10",
    "sg:city":"Holle",
    "sg:phone":"+49 5062/1834",
    "sg:postcode":"31188",
    "sg:province":"Niedersachsen",
    "wof:name":"Kath. Pfarramt Unbefl. Empf. Mari\u00e4",
    "wof:placetype":"venue"
},
  "geometry": {"coordinates":[10.1631183624,52.1073532104],"type":"Point"}
}