{
  "type": "Feature",
  "properties": {
    "iso:country":"DE",
    "sg:address":"Karl-Ziegler-Str. 23",
    "sg:city":"Waiblingen",
    "sg:phone":"+49 7151/987883",
    "sg:postcode":"71336",
    "sg:province":"Baden-W\u00fcrttemberg",
    "wof:name":"M. Mergenthaler",
    "wof:placetype":"venue"
},
  "geometry": {"coordinates":[9.32724,48.861382],"type":"Point"}
}