{
  "type": "Feature",
  "properties": {
    "iso:country":"DE",
    "sg:address":"K\u00fcthestr. 14",
    "sg:city":"Coppenbr\u00fcgge",
    "sg:phone":"+49 5159/558",
    "sg:postcode":"31863",
    "sg:province":"Niedersachsen",
    "wof:name":"Friedrich Daues",
    "wof:placetype":"venue"
},
  "geometry": {"coordinates":[9.499513,52.087627],"type":"Point"}
}