{
  "type": "Feature",
  "properties": {
    "iso:country":"DE",
    "sg:address":"Dorfstr. 13",
    "sg:city":"Kobbeln",
    "sg:phone":"+49 33652/6660",
    "sg:postcode":"15890",
    "sg:province":"Brandenburg",
    "wof:name":"P. Thierbach",
    "wof:placetype":"venue"
},
  "geometry": {"coordinates":[14.635067,52.139763],"type":"Point"}
}