{
  "type": "Feature",
  "properties": {
    "iso:country":"DE",
    "sg:address":"Am Knick 10-16",
    "sg:city":"Oststeinbek",
    "sg:phone":"+49 40/713080",
    "sg:postcode":"22113",
    "sg:province":"Schleswig-Holstein",
    "wof:name":"B\u00fcro-bedarf-balke Gmbh",
    "wof:placetype":"venue"
},
  "geometry": {"coordinates":[10.15982,53.550507],"type":"Point"}
}