{
  "type": "Feature",
  "properties": {
    "iso:country":"DE",
    "sg:address":"Obenketzberg 9",
    "sg:city":"Solingen",
    "sg:phone":"+49 212",
    "sg:postcode":"42653",
    "sg:province":"Nordrhein-Westfalen",
    "wof:name":"R.m.s.--das Repetitorium Der Mathematik Und Statistik",
    "wof:placetype":"venue"
},
  "geometry": {"coordinates":[7.089352,51.197567],"type":"Point"}
}