{
  "type": "Feature",
  "properties": {
    "iso:country":"DE",
    "sg:address":"Weesower Str. 9a",
    "sg:city":"Sch\u00f6nfeld",
    "sg:phone":"+49 33398/7315",
    "sg:postcode":"16356",
    "sg:province":"Brandenburg",
    "wof:name":"Bernd Schoel",
    "wof:placetype":"venue"
},
  "geometry": {"coordinates":[13.73773,52.680706],"type":"Point"}
}