{
  "type": "Feature",
  "properties": {
    "iso:country":"DE",
    "sg:address":"Panjestr. 2a",
    "sg:city":"Elmshorn",
    "sg:phone":"+49 4121/482080",
    "sg:postcode":"25335",
    "sg:province":"Schleswig-Holstein",
    "wof:name":"Br\u00f6cker Bauelemente Gmbh",
    "wof:placetype":"venue"
},
  "geometry": {"coordinates":[9.660174,53.75494],"type":"Point"}
}