{
  "type": "Feature",
  "properties": {
    "iso:country":"DE",
    "sg:address":"D\u00fclkener Str. 89",
    "sg:city":"Wegberg",
    "sg:phone":"+49 2434/4792",
    "sg:postcode":"41844",
    "sg:province":"Nordrhein-Westfalen",
    "wof:name":"Heidehaus Rickelrath",
    "wof:placetype":"venue"
},
  "geometry": {"coordinates":[6.2879281044,51.1732292175],"type":"Point"}
}