{
  "type": "Feature",
  "properties": {
    "iso:country":"DE",
    "sg:address":"Schellhorner Str. 6",
    "sg:city":"Preetz",
    "sg:phone":"+49 4342/81122",
    "sg:postcode":"24211",
    "sg:province":"Schleswig-Holstein",
    "wof:name":"Hannss Sport",
    "wof:placetype":"venue"
},
  "geometry": {"coordinates":[10.2854633331,54.2348632812],"type":"Point"}
}