{
  "type": "Feature",
  "properties": {
    "iso:country":"DE",
    "sg:address":"Tossens B\u00fcschken 1",
    "sg:city":"Essen",
    "sg:phone":"+49 201/530297",
    "sg:postcode":"45279",
    "sg:province":"Nordrhein-Westfalen",
    "wof:name":"Katholisches Pfarramt St. Joseph",
    "wof:placetype":"venue"
},
  "geometry": {"coordinates":[7.100921154,51.4375343323],"type":"Point"}
}