{
  "type": "Feature",
  "properties": {
    "iso:country":"DE",
    "sg:address":"Georg-Schlesinger-Str. 9",
    "sg:city":"Cottbus",
    "sg:phone":"+49 355/723811",
    "sg:postcode":"03042",
    "sg:province":"Brandenburg",
    "wof:name":"F. Langner",
    "wof:placetype":"venue"
},
  "geometry": {"coordinates":[14.348477,51.756706],"type":"Point"}
}