{
  "type": "Feature",
  "properties": {
    "iso:country":"DE",
    "sg:address":"Bismarckstr. 34",
    "sg:city":"Seesen",
    "sg:phone":"+49 5381/1010",
    "sg:postcode":"38723",
    "sg:province":"Niedersachsen",
    "wof:name":"Thiele Baustoffe Gmbh",
    "wof:placetype":"venue"
},
  "geometry": {"coordinates":[10.176352,51.887375],"type":"Point"}
}