{
  "type": "Feature",
  "properties": {
    "iso:country":"DE",
    "sg:address":"Karl-Friedrich-Str. 3",
    "sg:city":"Emmendingen",
    "sg:phone":"+49 7641/49868",
    "sg:postcode":"79312",
    "sg:province":"Baden-W\u00fcrttemberg",
    "wof:name":"S. K. U. B. Fotostudio Gmbh",
    "wof:placetype":"venue"
},
  "geometry": {"coordinates":[7.8473749161,48.1218299866],"type":"Point"}
}