{
  "type": "Feature",
  "properties": {
    "iso:country":"DE",
    "sg:address":"Tonkuhlenweg 10",
    "sg:city":"Hamburg",
    "sg:phone":"+49 40/7389933",
    "sg:postcode":"21031",
    "sg:province":"Hamburg",
    "wof:name":"Inkodatec Gmbh",
    "wof:placetype":"venue"
},
  "geometry": {"coordinates":[10.207781,53.512218],"type":"Point"}
}