{
  "type": "Feature",
  "properties": {
    "iso:country":"DE",
    "sg:address":"Bahnhofstr. 31",
    "sg:city":"Neu-Isenburg",
    "sg:phone":"+49 6102/21981",
    "sg:postcode":"63263",
    "sg:province":"Hessen",
    "wof:name":"Pizzeria San Remo",
    "wof:placetype":"venue"
},
  "geometry": {"coordinates":[8.6920814514,50.0532875061],"type":"Point"}
}