{
  "type": "Feature",
  "properties": {
    "iso:country":"DE",
    "sg:address":"Donatusstr. 39-41",
    "sg:city":"Pulheim",
    "sg:phone":"+49 2234/82058",
    "sg:postcode":"50259",
    "sg:province":"Nordrhein-Westfalen",
    "wof:name":"Rheinische Schule F\u00fcr K\u00f6rperbehinderte",
    "wof:placetype":"venue"
},
  "geometry": {"coordinates":[6.7955698967,50.9597511292],"type":"Point"}
}