{
  "type": "Feature",
  "properties": {
    "iso:country":"DE",
    "sg:address":"Lange Reihe 29",
    "sg:city":"Hamburg",
    "sg:phone":"+49 40/2801383",
    "sg:postcode":"20099",
    "sg:province":"Hamburg",
    "wof:name":"Visum Fotoreportagen Gmbh",
    "wof:placetype":"venue"
},
  "geometry": {"coordinates":[10.0100574493,53.5567016602],"type":"Point"}
}