{
  "type": "Feature",
  "properties": {
    "iso:country":"DE",
    "sg:address":"Kolpingstr. 22",
    "sg:city":"Nittenau",
    "sg:phone":"+49 9436/1277",
    "sg:postcode":"93149",
    "sg:province":"Bayern",
    "wof:name":"Edmund Bachhuber Med. B\u00e4der",
    "wof:placetype":"venue"
},
  "geometry": {"coordinates":[12.273078,49.196083],"type":"Point"}
}