{
  "type": "Feature",
  "properties": {
    "iso:country":"DE",
    "sg:address":"Aylenstr. 6 - 1",
    "sg:city":"Dettingen",
    "sg:postcode":"73265",
    "sg:province":"Baden-W\u00fcrttemberg",
    "wof:name":"Mwt Heer Gmbh",
    "wof:placetype":"venue"
},
  "geometry": {"coordinates":[9.450579,48.612263],"type":"Point"}
}