{
  "type": "Feature",
  "properties": {
    "iso:country":"DE",
    "sg:address":"Martin-Luther-King-Platz 6",
    "sg:city":"Hamburg",
    "sg:postcode":"20146",
    "sg:province":"Hamburg",
    "wof:name":"Institut F\u00fcr Biochemie U. Lebensmittelchemie",
    "wof:placetype":"venue"
},
  "geometry": {"coordinates":[9.9795236588,53.5682525635],"type":"Point"}
}