{
  "type": "Feature",
  "properties": {
    "iso:country":"DE",
    "sg:address":"Hamburger Str. 55",
    "sg:city":"Dortmund",
    "sg:phone":"+49 231/8632341",
    "sg:postcode":"44135",
    "sg:province":"Nordrhein-Westfalen",
    "wof:name":"Ata Steuerberatungsges. Mbh",
    "wof:placetype":"venue"
},
  "geometry": {"coordinates":[7.4802651405,51.5140037537],"type":"Point"}
}