{
  "type": "Feature",
  "properties": {
    "iso:country":"DE",
    "sg:address":"Hauptstr. 25",
    "sg:city":"Behringen",
    "sg:phone":"+49 36254/71493",
    "sg:postcode":"99947",
    "sg:province":"Th\u00fcringen",
    "wof:name":"Erwin Jung",
    "wof:placetype":"venue"
},
  "geometry": {"coordinates":[10.528586,51.0224],"type":"Point"}
}