{
  "type": "Feature",
  "properties": {
    "iso:country":"DE",
    "sg:address":"Steintwiete 16",
    "sg:city":"Hamburg",
    "sg:phone":"+49 40/372229",
    "sg:postcode":"20459",
    "sg:province":"Hamburg",
    "wof:name":"Nvg Norddeutsche Verwaltung F\u00fcr Haus- Und Grund-",
    "wof:placetype":"venue"
},
  "geometry": {"coordinates":[9.9860754013,53.5467071533],"type":"Point"}
}