{
  "type": "Feature",
  "properties": {
    "iso:country":"DE",
    "sg:address":"Hanselaerstr. 36",
    "sg:city":"Kalkar",
    "sg:phone":"+49 2824/2205",
    "sg:postcode":"47546",
    "sg:province":"Nordrhein-Westfalen",
    "wof:name":"Bestattungen G\u00f6rtzen-heynen E. Kfr.",
    "wof:placetype":"venue"
},
  "geometry": {"coordinates":[6.295622,51.738941],"type":"Point"}
}