{
  "type": "Feature",
  "properties": {
    "iso:country":"DE",
    "sg:address":"Kirchstr. 6",
    "sg:city":"Saarbr\u00fccken",
    "sg:postcode":"66129",
    "sg:province":"Saarland",
    "wof:name":"M. Egler",
    "wof:placetype":"venue"
},
  "geometry": {"coordinates":[7.036392,49.178864],"type":"Point"}
}