{
  "type": "Feature",
  "properties": {
    "iso:country":"DE",
    "sg:address":"M\u00fcnsterweg 16",
    "sg:city":"Koblenz",
    "sg:phone":"+49 261/27855",
    "sg:postcode":"56070",
    "sg:province":"Rheinland-Pfalz",
    "wof:name":"Kuno Fiedler",
    "wof:placetype":"venue"
},
  "geometry": {"coordinates":[7.532673,50.371323],"type":"Point"}
}