{
  "type": "Feature",
  "properties": {
    "iso:country":"DE",
    "sg:address":"Hauptstr. 59",
    "sg:city":"Stadtprozelten",
    "sg:phone":"+49 9392/7089",
    "sg:postcode":"97909",
    "sg:province":"Bayern",
    "wof:name":"Cafe Wolz",
    "wof:placetype":"venue"
},
  "geometry": {"coordinates":[9.411048,49.784431],"type":"Point"}
}