{
  "type": "Feature",
  "properties": {
    "iso:country":"DE",
    "sg:address":"Sofienstr. 12",
    "sg:city":"Heidelberg",
    "sg:phone":"+49 6221/60730",
    "sg:postcode":"69115",
    "sg:province":"Baden-W\u00fcrttemberg",
    "wof:name":"Deutsch-amerikanisches Institut",
    "wof:placetype":"venue"
},
  "geometry": {"coordinates":[8.694003,49.407799],"type":"Point"}
}