{
  "type": "Feature",
  "properties": {
    "iso:country":"DE",
    "sg:address":"Homburger Str. 25",
    "sg:city":"Bexbach",
    "sg:phone":"+49 6826/3061",
    "sg:postcode":"66450",
    "sg:province":"Saarland",
    "wof:name":"Werner Kiefer Gmbh",
    "wof:placetype":"venue"
},
  "geometry": {"coordinates":[7.295088,49.343922],"type":"Point"}
}