{
  "type": "Feature",
  "properties": {
    "iso:country":"DE",
    "sg:address":"Paul-Schneider-Str. 9",
    "sg:city":"Trier",
    "sg:phone":"+49 651/12982",
    "sg:postcode":"54292",
    "sg:province":"Rheinland-Pfalz",
    "wof:name":"Roger Malvil",
    "wof:placetype":"venue"
},
  "geometry": {"coordinates":[6.6611299515,49.7687110901],"type":"Point"}
}