{
  "type": "Feature",
  "properties": {
    "iso:country":"DE",
    "sg:address":"Burgstr. 9",
    "sg:city":"Leinfelden-Echterdingen",
    "sg:phone":"+49 711/795172",
    "sg:postcode":"70771",
    "sg:province":"Baden-W\u00fcrttemberg",
    "wof:name":"Vertrauens\u00e4rztlicher-dienst Der Lva W\u00fcrttemberg",
    "wof:placetype":"venue"
},
  "geometry": {"coordinates":[9.1695537567,48.6898155212],"type":"Point"}
}