{
  "type": "Feature",
  "properties": {
    "iso:country":"DE",
    "sg:address":"Motzstr. 45",
    "sg:city":"Berlin",
    "sg:phone":"+49 30/2187625",
    "sg:postcode":"10777",
    "sg:province":"Berlin",
    "wof:name":"Kalabona",
    "wof:placetype":"venue"
},
  "geometry": {"coordinates":[13.3443241119,52.4963874817],"type":"Point"}
}