{
  "type": "Feature",
  "properties": {
    "iso:country":"DE",
    "sg:address":"Kufsteiner Str. 4",
    "sg:city":"Rosenheim",
    "sg:phone":"+49 8031/30010",
    "sg:postcode":"83022",
    "sg:province":"Bayern",
    "wof:name":"Stadthalle Rosenheim",
    "wof:placetype":"venue"
},
  "geometry": {"coordinates":[12.125632,47.853432],"type":"Point"}
}