{
  "type": "Feature",
  "properties": {
    "iso:country":"DE",
    "sg:address":"Am Roseng\u00e4rtchen 26",
    "sg:city":"Geisenheim",
    "sg:phone":"+49 6722/971179",
    "sg:postcode":"65366",
    "sg:province":"Hessen",
    "wof:name":"Nordstern",
    "wof:placetype":"venue"
},
  "geometry": {"coordinates":[7.959569931,50.003490448],"type":"Point"}
}