{
  "type": "Feature",
  "properties": {
    "iso:country":"DE",
    "sg:address":"Hauptstr. 51",
    "sg:city":"Obers\u00fc\u00dfbach",
    "sg:phone":"+49 8708/921060",
    "sg:postcode":"84101",
    "sg:province":"Bayern",
    "wof:name":"Silvia Und Simon Rank",
    "wof:placetype":"venue"
},
  "geometry": {"coordinates":[11.9447612762,48.6140594482],"type":"Point"}
}