{
  "type": "Feature",
  "properties": {
    "iso:country":"DE",
    "sg:address":"Armsener Str. 17",
    "sg:city":"Bremen",
    "sg:phone":"+49 421/429120",
    "sg:postcode":"28325",
    "sg:province":"Bremen",
    "wof:name":"W. Fuss",
    "wof:placetype":"venue"
},
  "geometry": {"coordinates":[8.9392280579,53.0594177246],"type":"Point"}
}