{
  "type": "Feature",
  "properties": {
    "iso:country":"DE",
    "sg:address":"Mittelweg 5",
    "sg:city":"Hille",
    "sg:phone":"+49 5734/7714",
    "sg:postcode":"32479",
    "sg:province":"Nordrhein-Westfalen",
    "wof:name":"F. Kuhlmann",
    "wof:placetype":"venue"
},
  "geometry": {"coordinates":[8.7844800949,52.276058197],"type":"Point"}
}