{
  "type": "Feature",
  "properties": {
    "iso:country":"DE",
    "sg:address":"Liebigstr. 25",
    "sg:city":"Osnabr\u00fcck",
    "sg:phone":"+49 4954/125075",
    "sg:postcode":"49074",
    "sg:province":"Niedersachsen",
    "wof:name":"Carl Weymann Gmbh",
    "wof:placetype":"venue"
},
  "geometry": {"coordinates":[8.052316,52.28006],"type":"Point"}
}