{
  "type": "Feature",
  "properties": {
    "iso:country":"DE",
    "sg:address":"Hufelandstr. 55",
    "sg:city":"Essen",
    "sg:phone":"+49 201/7230",
    "sg:postcode":"45122",
    "sg:province":"Niedersachsen",
    "wof:name":"Abteilung F\u00fcr Tumortherapie Und Forschung, Uniklinikum Essen",
    "wof:placetype":"venue"
},
  "geometry": {"coordinates":[6.989695,51.436268],"type":"Point"}
}