{
  "type": "Feature",
  "properties": {
    "iso:country":"DE",
    "sg:address":"Lauterbacher Str. 121",
    "sg:city":"V\u00f6lklingen",
    "sg:phone":"+49 6898/41529",
    "sg:postcode":"66333",
    "sg:province":"Saarland",
    "wof:name":"Werner Huppert Architekt",
    "wof:placetype":"venue"
},
  "geometry": {"coordinates":[6.799877,49.214634],"type":"Point"}
}