{
  "type": "Feature",
  "properties": {
    "iso:country":"DE",
    "sg:address":"Hindenburgstr. 2",
    "sg:city":"Altheim",
    "sg:phone":"+49 7340/591",
    "sg:postcode":"89174",
    "sg:province":"Baden-W\u00fcrttemberg",
    "wof:name":"Heinz Walter",
    "wof:placetype":"venue"
},
  "geometry": {"coordinates":[10.0256576538,48.5806846619],"type":"Point"}
}