{
  "type": "Feature",
  "properties": {
    "iso:country":"DE",
    "sg:address":"Jungbrunnenstr. 7",
    "sg:city":"Rottweil",
    "sg:phone":"+49 741/21847",
    "sg:postcode":"78628",
    "sg:province":"Baden-W\u00fcrttemberg",
    "wof:name":"Delta-werk-kern",
    "wof:placetype":"venue"
},
  "geometry": {"coordinates":[8.658362,48.16346],"type":"Point"}
}