{
  "type": "Feature",
  "properties": {
    "iso:country":"DE",
    "sg:address":"Am R\u00f6merbrunnen 5",
    "sg:city":"Schwalbach",
    "sg:phone":"+49 6834/51757",
    "sg:postcode":"66773",
    "sg:province":"Saarland",
    "wof:name":"Pohl",
    "wof:placetype":"venue"
},
  "geometry": {"coordinates":[6.816259,49.287987],"type":"Point"}
}