{
  "type": "Feature",
  "properties": {
    "iso:country":"DE",
    "sg:address":"Garzauer Str. 8",
    "sg:city":"Berlin",
    "sg:phone":"+49 30/56498938",
    "sg:postcode":"12683",
    "sg:province":"Berlin",
    "wof:name":"Monika Fiedler",
    "wof:placetype":"venue"
},
  "geometry": {"coordinates":[13.570896,52.527424],"type":"Point"}
}