{
  "type": "Feature",
  "properties": {
    "iso:country":"DE",
    "sg:address":"Hafenstr. 65",
    "sg:city":"Kassel",
    "sg:phone":"+49 561/572378",
    "sg:postcode":"34125",
    "sg:province":"Hessen",
    "wof:name":"Ralf Wollenhaupt",
    "wof:placetype":"venue"
},
  "geometry": {"coordinates":[9.518673,51.317017],"type":"Point"}
}