{
  "type": "Feature",
  "properties": {
    "iso:country":"DE",
    "sg:address":"Ulmenstr. 7",
    "sg:city":"Niedernhausen",
    "sg:phone":"+49 6127/5387",
    "sg:postcode":"65527",
    "sg:province":"Hessen",
    "wof:name":"Dr. Marion Strelitz \u00c4rztin F\u00fcr Allgemeinmedizin",
    "wof:placetype":"venue"
},
  "geometry": {"coordinates":[8.3157444,50.1669387817],"type":"Point"}
}