{
  "type": "Feature",
  "properties": {
    "iso:country":"DE",
    "sg:address":"Johannish\u00f6he 3",
    "sg:city":"Kottgeisering",
    "sg:phone":"+49 8144/8228",
    "sg:postcode":"82288",
    "sg:province":"Bayern",
    "wof:name":"C. Kronenbitter Architekt",
    "wof:placetype":"venue"
},
  "geometry": {"coordinates":[11.131452,48.124657],"type":"Point"}
}