{
  "type": "Feature",
  "properties": {
    "iso:country":"DE",
    "sg:address":"Korngasse 13",
    "sg:city":"Butzbach",
    "sg:phone":"+49 6033/65131",
    "sg:postcode":"35510",
    "sg:province":"Hessen",
    "wof:name":"G\u00fcnther Will Autolackiererei",
    "wof:placetype":"venue"
},
  "geometry": {"coordinates":[8.672418,50.435272],"type":"Point"}
}