{
  "type": "Feature",
  "properties": {
    "iso:country":"DE",
    "sg:address":"Wittener Str. 97",
    "sg:city":"Witten",
    "sg:phone":"+49 2302/77316",
    "sg:postcode":"58456",
    "sg:province":"Nordrhein-Westfalen",
    "wof:name":"Ingrid Bandmann",
    "wof:placetype":"venue"
},
  "geometry": {"coordinates":[7.271686,51.417061],"type":"Point"}
}