{
  "type": "Feature",
  "properties": {
    "iso:country":"DE",
    "sg:address":"Grubenstr. 39",
    "sg:city":"P\u00fcttlingen",
    "sg:phone":"+49 6806/48484",
    "sg:postcode":"66346",
    "sg:province":"Saarland",
    "wof:name":"Georg Kammer Gmbh",
    "wof:placetype":"venue"
},
  "geometry": {"coordinates":[6.9023199081,49.2948913574],"type":"Point"}
}