{
  "type": "Feature",
  "properties": {
    "iso:country":"DE",
    "sg:address":"Heinrich-Heine-Str. 86",
    "sg:city":"Schneeberg",
    "sg:postcode":"08289",
    "sg:province":"Sachsen",
    "wof:name":"W. Schnorrbusch",
    "wof:placetype":"venue"
},
  "geometry": {"coordinates":[12.64783,50.602001],"type":"Point"}
}