{
  "type": "Feature",
  "properties": {
    "iso:country":"DE",
    "sg:address":"Heulesheimer Str. 2",
    "sg:city":"Krefeld",
    "sg:phone":"+49 2151/573037",
    "sg:postcode":"47809",
    "sg:province":"Nordrhein-Westfalen",
    "wof:name":"Rudolf Honerkamp & Co.",
    "wof:placetype":"venue"
},
  "geometry": {"coordinates":[6.6641759872,51.3253593445],"type":"Point"}
}