{
  "type": "Feature",
  "properties": {
    "iso:country":"DE",
    "sg:address":"Wilh-Theo-R\u00f6mheld-Str 32",
    "sg:city":"Mainz",
    "sg:phone":"+49 6131/830900",
    "sg:postcode":"55130",
    "sg:province":"Rheinland-Pfalz",
    "wof:name":"Astron Hallen Und Bausysteme",
    "wof:placetype":"venue"
},
  "geometry": {"coordinates":[8.289516449,49.9823036194],"type":"Point"}
}