{
  "type": "Feature",
  "properties": {
    "iso:country":"DE",
    "sg:address":"kanalstr.17",
    "sg:city":"Weingarten",
    "sg:phone":"+49 7244/706644",
    "sg:postcode":"76356",
    "sg:province":"Baden-W\u00fcrttemberg",
    "wof:name":"De Giorgio Garten- Und Landschaftspflege",
    "wof:placetype":"venue"
},
  "geometry": {"coordinates":[8.5257587433,49.0522346497],"type":"Point"}
}