{
  "type": "Feature",
  "properties": {
    "iso:country":"DE",
    "sg:address":"Neue Str. 15",
    "sg:city":"Kellinghusen",
    "sg:phone":"+49 4822/2243",
    "sg:postcode":"25548",
    "sg:province":"Schleswig-Holstein",
    "wof:name":"Uwe B\u00f6ge",
    "wof:placetype":"venue"
},
  "geometry": {"coordinates":[9.7257738113,53.949634552],"type":"Point"}
}