{
  "type": "Feature",
  "properties": {
    "iso:country":"DE",
    "sg:address":"Am Rebst\u00f6ckel 3",
    "sg:city":"Edesheim",
    "sg:phone":"+49 6323/989448",
    "sg:postcode":"67483",
    "sg:province":"Rheinland-Pfalz",
    "wof:name":"Karin Hoffmann",
    "wof:placetype":"venue"
},
  "geometry": {"coordinates":[8.135616,49.261795],"type":"Point"}
}