{
  "type": "Feature",
  "properties": {
    "iso:country":"DE",
    "sg:address":"Im Amtshof 3",
    "sg:city":"Bad Krozingen",
    "sg:phone":"+49 7633/15197",
    "sg:postcode":"79189",
    "sg:province":"Baden-W\u00fcrttemberg",
    "wof:name":"Peter U. Hannelore Huetter",
    "wof:placetype":"venue"
},
  "geometry": {"coordinates":[7.7060608864,47.9071807861],"type":"Point"}
}