{
  "type": "Feature",
  "properties": {
    "iso:country":"DE",
    "sg:address":"Am Rollberg 10",
    "sg:city":"Berlin",
    "sg:postcode":"13158",
    "sg:province":"Berlin",
    "wof:name":"Dr. Med. Ilse Limberg",
    "wof:placetype":"venue"
},
  "geometry": {"coordinates":[13.398346,52.596104],"type":"Point"}
}