{
  "type": "Feature",
  "properties": {
    "iso:country":"DE",
    "sg:address":"Kreuzlinger Str. 25",
    "sg:city":"Konstanz",
    "sg:phone":"+49 7531/23119",
    "sg:postcode":"78462",
    "sg:province":"Baden-W\u00fcrttemberg",
    "wof:name":"Schreinerei Beuter",
    "wof:placetype":"venue"
},
  "geometry": {"coordinates":[9.172056,47.657063],"type":"Point"}
}