{
  "type": "Feature",
  "properties": {
    "iso:country":"DE",
    "sg:address":"Oststr. 33",
    "sg:city":"Hamm",
    "sg:phone":"+49 2381/12015",
    "sg:postcode":"59065",
    "sg:province":"Nordrhein-Westfalen",
    "wof:name":"Reiseb\u00fcro Effert Gmbh",
    "wof:placetype":"venue"
},
  "geometry": {"coordinates":[7.8222928047,51.6824684143],"type":"Point"}
}