{
  "type": "Feature",
  "properties": {
    "iso:country":"DE",
    "sg:address":"Kasseler Str.",
    "sg:city":"Niedenstein",
    "sg:phone":"+49 5624/925620",
    "sg:postcode":"34305",
    "sg:province":"Hessen",
    "wof:name":"Ritter Und Schaub Architekten",
    "wof:placetype":"venue"
},
  "geometry": {"coordinates":[9.313599,51.233662],"type":"Point"}
}