{
  "type": "Feature",
  "properties": {
    "iso:country":"DE",
    "sg:address":"Oberlinder Str 84",
    "sg:city":"Sonneberg",
    "sg:phone":"+49 3675/81900",
    "sg:postcode":"96515",
    "sg:province":"Th\u00fcringen",
    "wof:name":"Hero Soft Gesellschaft F\u00fcr Softwareentwicklung Mbh",
    "wof:placetype":"venue"
},
  "geometry": {"coordinates":[11.1784000397,50.3474197388],"type":"Point"}
}