{
  "type": "Feature",
  "properties": {
    "iso:country":"DE",
    "sg:address":"Schmidhausen 16",
    "sg:city":"Tuntenhausen",
    "sg:phone":"+49 8067/575",
    "sg:postcode":"83104",
    "sg:province":"Bayern",
    "wof:name":"Anton Hochmuth Gmbh",
    "wof:placetype":"venue"
},
  "geometry": {"coordinates":[12.00954,47.919754],"type":"Point"}
}