{
  "type": "Feature",
  "properties": {
    "iso:country":"DE",
    "sg:address":"Bamberger Str. 50",
    "sg:city":"Diespeck",
    "sg:postcode":"91456",
    "sg:province":"Bayern",
    "wof:name":"Tipo-sport E. K.",
    "wof:placetype":"venue"
},
  "geometry": {"coordinates":[10.6264295578,49.5993995667],"type":"Point"}
}