{
  "type": "Feature",
  "properties": {
    "iso:country":"DE",
    "sg:address":"Kloschinskystr. 81",
    "sg:city":"Trier",
    "sg:phone":"+49 651/29325",
    "sg:postcode":"54292",
    "sg:province":"Rheinland-Pfalz",
    "wof:name":"Franke Gmbh",
    "wof:placetype":"venue"
},
  "geometry": {"coordinates":[6.6469497681,49.7663726807],"type":"Point"}
}