{
  "type": "Feature",
  "properties": {
    "iso:country":"DE",
    "sg:address":"H\u00fcnegr\u00e4ben 28:: IG Lake II",
    "sg:city":"Schmallenberg",
    "sg:phone":"+49 2972/47875",
    "sg:postcode":"57392",
    "sg:province":"Nordrhein-Westfalen",
    "wof:name":"Blum Gbr",
    "wof:placetype":"venue"
},
  "geometry": {"coordinates":[8.2858181,51.154045105],"type":"Point"}
}