{
  "type": "Feature",
  "properties": {
    "iso:country":"DE",
    "sg:address":"Vorstadt 4",
    "sg:city":"Weilburg",
    "sg:phone":"+49 6471/2327",
    "sg:postcode":"35781",
    "sg:province":"Hessen",
    "wof:name":"Bodo Czypionka Augenoptiker",
    "wof:placetype":"venue"
},
  "geometry": {"coordinates":[8.2616167068,50.4834518433],"type":"Point"}
}