{
  "type": "Feature",
  "properties": {
    "iso:country":"DE",
    "sg:address":"Diezer Str. 17 - 19",
    "sg:city":"Limburg",
    "sg:phone":"+49 6431/8628",
    "sg:postcode":"65549",
    "sg:province":"Hessen",
    "wof:name":"Europa",
    "wof:placetype":"venue"
},
  "geometry": {"coordinates":[8.0610647202,50.3873138428],"type":"Point"}
}