{
  "type": "Feature",
  "properties": {
    "iso:country":"DE",
    "sg:address":"Lupinenweg 7",
    "sg:city":"Niedenstein",
    "sg:phone":"+49 5624/8008",
    "sg:postcode":"34305",
    "sg:province":"Hessen",
    "wof:name":"Karl Schaub Architekt",
    "wof:placetype":"venue"
},
  "geometry": {"coordinates":[9.317219,51.235966],"type":"Point"}
}