{
  "type": "Feature",
  "properties": {
    "iso:country":"DE",
    "sg:address":"Lessingstr. 23",
    "sg:city":"Bremen",
    "sg:phone":"+49 421/72844",
    "sg:postcode":"28203",
    "sg:province":"Bremen",
    "wof:name":"Rolf L\u00fcttich",
    "wof:placetype":"venue"
},
  "geometry": {"coordinates":[8.8334846497,53.0727081299],"type":"Point"}
}