{
  "type": "Feature",
  "properties": {
    "iso:country":"DE",
    "sg:address":"Freiherr-vom-Stein-Str. 14 a",
    "sg:city":"L\u00fcdenscheid",
    "sg:phone":"+49 2351/3171",
    "sg:postcode":"58511",
    "sg:province":"Nordrhein-Westfalen",
    "wof:name":"H. Pendel Und N. Schreiter Rechtsanw\u00e4lte",
    "wof:placetype":"venue"
},
  "geometry": {"coordinates":[7.6324901581,51.215057373],"type":"Point"}
}