{
  "type": "Feature",
  "properties": {
    "iso:country":"DE",
    "sg:address":"Kronprinzenstr. 57 a",
    "sg:city":"Netphen",
    "sg:phone":"+49 2738/2326",
    "sg:postcode":"57250",
    "sg:province":"Nordrhein-Westfalen",
    "wof:name":"Volker Z\u00f6ller Heilpraktiker",
    "wof:placetype":"venue"
},
  "geometry": {"coordinates":[8.1008090973,50.9152984619],"type":"Point"}
}