{
  "type": "Feature",
  "properties": {
    "iso:country":"DE",
    "sg:address":"K\u00f6lner Str. 102",
    "sg:city":"Bergneustadt",
    "sg:phone":"+49 2261/40910",
    "sg:postcode":"51702",
    "sg:province":"Nordrhein-Westfalen",
    "wof:name":"Bindler Technologie Verwaltungs Gmbh",
    "wof:placetype":"venue"
},
  "geometry": {"coordinates":[7.6378531456,51.0157775879],"type":"Point"}
}