{
  "type": "Feature",
  "properties": {
    "iso:country":"DE",
    "sg:address":"Hauptstr. 65",
    "sg:city":"Drebber",
    "sg:phone":"+49 5445/799",
    "sg:postcode":"49457",
    "sg:province":"Niedersachsen",
    "wof:name":"Heinrich Weber-bockhop",
    "wof:placetype":"venue"
},
  "geometry": {"coordinates":[8.408074,52.653515],"type":"Point"}
}