{
  "type": "Feature",
  "properties": {
    "iso:country":"DE",
    "sg:address":"Vogelsang 19",
    "sg:city":"Hameln",
    "sg:phone":"+49 5151/12409",
    "sg:postcode":"31789",
    "sg:province":"Niedersachsen",
    "wof:name":"Manfred Bartels Baulemente Gmbh",
    "wof:placetype":"venue"
},
  "geometry": {"coordinates":[9.412859,52.102413],"type":"Point"}
}