{
  "type": "Feature",
  "properties": {
    "iso:country":"DE",
    "sg:address":"Schanzenring 1",
    "sg:city":"Winsen",
    "sg:postcode":"21423",
    "sg:province":"Niedersachsen",
    "wof:name":"Claudia Meyer Gmbh",
    "wof:placetype":"venue"
},
  "geometry": {"coordinates":[10.2092237473,53.3631820679],"type":"Point"}
}