{
  "type": "Feature",
  "properties": {
    "iso:country":"DE",
    "sg:address":"Otto-Beck-Str. 14",
    "sg:city":"Mannheim",
    "sg:phone":"+49 621/4314160",
    "sg:postcode":"68165",
    "sg:province":"Baden-W\u00fcrttemberg",
    "wof:name":"Kurt F. M\u00fcller Architekt",
    "wof:placetype":"venue"
},
  "geometry": {"coordinates":[8.483618,49.480015],"type":"Point"}
}