{
  "type": "Feature",
  "properties": {
    "iso:country":"DE",
    "sg:address":"Zehma 7 A",
    "sg:city":"Saara",
    "sg:phone":"+49 34493/21523",
    "sg:postcode":"04603",
    "sg:province":"Th\u00fcringen",
    "wof:name":"Siegfried Leutzsch",
    "wof:placetype":"venue"
},
  "geometry": {"coordinates":[12.445602,50.924255],"type":"Point"}
}