{
  "type": "Feature",
  "properties": {
    "iso:country":"DE",
    "sg:city":"Eschershausen",
    "sg:phone":"+49 5534/2945",
    "sg:postcode":"37632",
    "sg:province":"Niedersachsen",
    "wof:name":"H. Kopp",
    "wof:placetype":"venue"
},
  "geometry": {"coordinates":[9.636475,51.927666],"type":"Point"}
}