{
  "type": "Feature",
  "properties": {
    "iso:country":"DE",
    "sg:address":"Bahnhofstr. 12",
    "sg:city":"Bobingen",
    "sg:phone":"+49 8234/3639",
    "sg:postcode":"86399",
    "sg:province":"Bayern",
    "wof:name":"A. Gohm Inh. Edith Irrgang",
    "wof:placetype":"venue"
},
  "geometry": {"coordinates":[10.831829071,48.2676696777],"type":"Point"}
}