{
  "type": "Feature",
  "properties": {
    "iso:country":"DE",
    "sg:address":"Helmholtzstr. 5",
    "sg:city":"Bremerhaven",
    "sg:phone":"+49 471/21590",
    "sg:postcode":"27574",
    "sg:province":"Bremen",
    "wof:name":"Manfred Warmbold",
    "wof:placetype":"venue"
},
  "geometry": {"coordinates":[8.608625,53.533974],"type":"Point"}
}