{
  "type": "Feature",
  "properties": {
    "iso:country":"DE",
    "sg:address":"Wickerer Str. 7",
    "sg:city":"Fl\u00f6rsheim",
    "sg:phone":"+49 6145/6526",
    "sg:postcode":"65439",
    "sg:province":"Hessen",
    "wof:name":"Scharfenbaum",
    "wof:placetype":"venue"
},
  "geometry": {"coordinates":[8.4296512604,50.0143013],"type":"Point"}
}