{
  "type": "Feature",
  "properties": {
    "iso:country":"DE",
    "sg:address":"Bahnstr. 2",
    "sg:city":"Erbach",
    "sg:phone":"+49 6062/1415",
    "sg:postcode":"64711",
    "sg:province":"Hessen",
    "wof:name":"Bierstube",
    "wof:placetype":"venue"
},
  "geometry": {"coordinates":[8.993262291,49.6565208435],"type":"Point"}
}