{
  "type": "Feature",
  "properties": {
    "iso:country":"DE",
    "sg:address":"Hohe Eich 3a",
    "sg:city":"Stutensee",
    "sg:phone":"+49 7244/945193",
    "sg:postcode":"76297",
    "sg:province":"Baden-W\u00fcrttemberg",
    "wof:name":"Peter Baumstark",
    "wof:placetype":"venue"
},
  "geometry": {"coordinates":[8.4676275253,49.0572967529],"type":"Point"}
}