{
  "type": "Feature",
  "properties": {
    "iso:country":"DE",
    "sg:address":"heinrich-heine-stra\u00dfe 7",
    "sg:city":"mainz",
    "sg:phone":"+49 6131/616702",
    "sg:postcode":"55118",
    "sg:province":"Rheinland-Pfalz",
    "wof:name":"Planungsb\u00fcro Englisch",
    "wof:placetype":"venue"
},
  "geometry": {"coordinates":[8.257713,50.010193],"type":"Point"}
}