{
  "type": "Feature",
  "properties": {
    "iso:country":"DE",
    "sg:address":"Weierhofweg 43",
    "sg:city":"Wiehl",
    "sg:phone":"+49 2262/2304",
    "sg:postcode":"51674",
    "sg:province":"Nordrhein-Westfalen",
    "wof:name":"Elektro Thiedecke Inh. Stefan Kapp",
    "wof:placetype":"venue"
},
  "geometry": {"coordinates":[7.5131092072,50.9677886963],"type":"Point"}
}