{
  "type": "Feature",
  "properties": {
    "iso:country":"DE",
    "sg:address":"L\u00fcnener Str. 176",
    "sg:city":"Kamen",
    "sg:phone":"+49 2307/10781",
    "sg:postcode":"59174",
    "sg:province":"Nordrhein-Westfalen",
    "wof:name":"Ernst Wienke",
    "wof:placetype":"venue"
},
  "geometry": {"coordinates":[7.6403617859,51.5891227722],"type":"Point"}
}