{
  "type": "Feature",
  "properties": {
    "iso:country":"DE",
    "sg:address":"Kommrat-Zimmermann-Str 6c",
    "sg:city":"Zirndorf",
    "sg:phone":"+49 911/606616",
    "sg:postcode":"90513",
    "sg:province":"Bayern",
    "wof:name":"Edelthalhammer Und Kollegen Rechtsanw\u00e4lte",
    "wof:placetype":"venue"
},
  "geometry": {"coordinates":[10.9531106949,49.4511604309],"type":"Point"}
}