{
  "type": "Feature",
  "properties": {
    "iso:country":"DE",
    "sg:address":"S\u00fcd-Nord-Str. 27",
    "sg:city":"Walchum",
    "sg:phone":"+49 5939/533",
    "sg:postcode":"26907",
    "sg:province":"Niedersachsen",
    "wof:name":"Richard Knurr",
    "wof:placetype":"venue"
},
  "geometry": {"coordinates":[7.208351,52.929733],"type":"Point"}
}