{
  "type": "Feature",
  "properties": {
    "iso:country":"DE",
    "sg:address":"Am Grund 7",
    "sg:city":"Bielefeld",
    "sg:phone":"+49 5205/7787",
    "sg:postcode":"33689",
    "sg:province":"Nordrhein-Westfalen",
    "wof:name":"K. H. Hagemann Gmbh",
    "wof:placetype":"venue"
},
  "geometry": {"coordinates":[8.605538,51.929516],"type":"Point"}
}