{
  "type": "Feature",
  "properties": {
    "iso:country":"DE",
    "sg:address":"Reuterstr. 43",
    "sg:city":"Lippstadt",
    "sg:phone":"+49 2941/61062",
    "sg:postcode":"59558",
    "sg:province":"Nordrhein-Westfalen",
    "wof:name":"Baugesch\u00e4ft Schewe Gmbh",
    "wof:placetype":"venue"
},
  "geometry": {"coordinates":[8.378004,51.701622],"type":"Point"}
}