{
  "type": "Feature",
  "properties": {
    "iso:country":"DE",
    "sg:address":"Lenneper Str. 2",
    "sg:city":"Remscheid",
    "sg:phone":"+49 2191/385538",
    "sg:postcode":"42855",
    "sg:province":"Nordrhein-Westfalen",
    "wof:name":"Kosmetikstudio Soika",
    "wof:placetype":"venue"
},
  "geometry": {"coordinates":[7.22202,51.178341],"type":"Point"}
}