{
  "type": "Feature",
  "properties": {
    "iso:country":"DE",
    "sg:address":"Hauptstr. 40",
    "sg:city":"Hollenbach",
    "sg:phone":"+49 8257/526",
    "sg:postcode":"86568",
    "sg:province":"Bayern",
    "wof:name":"Xaver Aechter",
    "wof:placetype":"venue"
},
  "geometry": {"coordinates":[11.07344,48.488121],"type":"Point"}
}