{
  "type": "Feature",
  "properties": {
    "iso:country":"DE",
    "sg:city":"Ebrach",
    "sg:phone":"+49 9553/319",
    "sg:postcode":"96157",
    "sg:province":"Bayern",
    "wof:name":"Fritz Schaller & Sohn",
    "wof:placetype":"venue"
},
  "geometry": {"coordinates":[10.493269,49.847843],"type":"Point"}
}