{
  "type": "Feature",
  "properties": {
    "iso:country":"DE",
    "sg:address":"Hermann-L\u00f6ns-Weg 33",
    "sg:city":"Telgte",
    "sg:phone":"+49 2504/4196",
    "sg:postcode":"48291",
    "sg:province":"Nordrhein-Westfalen",
    "wof:name":"G. Herwig",
    "wof:placetype":"venue"
},
  "geometry": {"coordinates":[7.785264,51.974293],"type":"Point"}
}