{
  "type": "Feature",
  "properties": {
    "iso:country":"DE",
    "sg:address":"Waldkircher Str. 12",
    "sg:city":"Elzach",
    "sg:phone":"+49 7682/1287",
    "sg:postcode":"79215",
    "sg:province":"Baden-W\u00fcrttemberg",
    "wof:name":"F. Pleuler B\u00e4ckerei",
    "wof:placetype":"venue"
},
  "geometry": {"coordinates":[8.138955,48.213196],"type":"Point"}
}