{
  "type": "Feature",
  "properties": {
    "iso:country":"DE",
    "sg:address":"Walter-Bruch-Str. 1",
    "sg:city":"Pattensen",
    "sg:phone":"+49 5101/99990",
    "sg:postcode":"30982",
    "sg:province":"Niedersachsen",
    "wof:name":"Hadakon Kommunikations- Systeme Gmbh",
    "wof:placetype":"venue"
},
  "geometry": {"coordinates":[9.773976326,52.2632637024],"type":"Point"}
}