{
  "type": "Feature",
  "properties": {
    "iso:country":"DE",
    "sg:address":"Bahnstr. 67",
    "sg:city":"Grevenbroich",
    "sg:phone":"+49 2181/3394",
    "sg:postcode":"41515",
    "sg:province":"Nordrhein-Westfalen",
    "wof:name":"Grillhaus Akcay",
    "wof:placetype":"venue"
},
  "geometry": {"coordinates":[6.5831179619,51.0915718079],"type":"Point"}
}