{
  "type": "Feature",
  "properties": {
    "iso:country":"DE",
    "sg:address":"Hundekehlestr. 4",
    "sg:city":"Berlin",
    "sg:phone":"+49 30/8256023",
    "sg:postcode":"14199",
    "sg:province":"Berlin",
    "wof:name":"Bernd Kaiser",
    "wof:placetype":"venue"
},
  "geometry": {"coordinates":[13.2891931534,52.4757156372],"type":"Point"}
}