{
  "type": "Feature",
  "properties": {
    "iso:country":"DE",
    "sg:address":"Marktplatz 1",
    "sg:city":"Euerdorf",
    "sg:phone":"+49 9704/1553",
    "sg:postcode":"97717",
    "sg:province":"Bayern",
    "wof:name":"Otto Baur",
    "wof:placetype":"venue"
},
  "geometry": {"coordinates":[10.0232963562,50.1489601135],"type":"Point"}
}