{
  "type": "Feature",
  "properties": {
    "iso:country":"DE",
    "sg:address":"Zwehrener Weg 6",
    "sg:city":"Kassel",
    "sg:phone":"+49 561/22176",
    "sg:postcode":"34121",
    "sg:province":"Hessen",
    "wof:name":"Restaurant D\u00fcsseldorfer Hof",
    "wof:placetype":"venue"
},
  "geometry": {"coordinates":[9.4687948227,51.305847168],"type":"Point"}
}