{
  "type": "Feature",
  "properties": {
    "iso:country":"DE",
    "sg:address":"Am Lauterberg 29",
    "sg:city":"Berod",
    "sg:phone":"+49 2680/1437",
    "sg:postcode":"57614",
    "sg:province":"Rheinland-Pfalz",
    "wof:name":"Christ Gmbh",
    "wof:placetype":"venue"
},
  "geometry": {"coordinates":[7.689182,50.642712],"type":"Point"}
}