{
  "type": "Feature",
  "properties": {
    "iso:country":"DE",
    "sg:address":"Rudolf-Breitscheid-Str.",
    "sg:city":"Masserberg",
    "sg:postcode":"98666",
    "sg:province":"Th\u00fcringen",
    "wof:name":"Ev.-luth. Kirche Heubach",
    "wof:placetype":"venue"
},
  "geometry": {"coordinates":[10.9317913055,50.5060462952],"type":"Point"}
}