{
  "type": "Feature",
  "properties": {
    "iso:country":"DE",
    "sg:address":"Friedrichstr. 9 A",
    "sg:city":"Stuttgart",
    "sg:postcode":"70174",
    "sg:province":"Baden-W\u00fcrttemberg",
    "wof:name":"Optik - Partner Ag",
    "wof:placetype":"venue"
},
  "geometry": {"coordinates":[9.1776685715,48.7828292847],"type":"Point"}
}