{
  "type": "Feature",
  "properties": {
    "iso:country":"DE",
    "sg:address":"Breite Str. 48",
    "sg:city":"Quedlinburg",
    "sg:phone":"+49 3946/2241",
    "sg:postcode":"06484",
    "sg:province":"Sachsen-Anhalt",
    "wof:name":"Modehaus Hulsch",
    "wof:placetype":"venue"
},
  "geometry": {"coordinates":[11.1428899765,51.7900390625],"type":"Point"}
}