{
  "type": "Feature",
  "properties": {
    "iso:country":"DE",
    "sg:address":"Obermarkt 26",
    "sg:city":"D\u00f6beln",
    "sg:phone":"+49 3431/710584",
    "sg:postcode":"04720",
    "sg:province":"Sachsen",
    "wof:name":"Central Friseur-gesellschaft D\u00f6beln Gmbh",
    "wof:placetype":"venue"
},
  "geometry": {"coordinates":[13.1227550507,51.1219711304],"type":"Point"}
}