{
  "type": "Feature",
  "properties": {
    "iso:country":"DE",
    "sg:address":"Vennebecker-Bruch-Str. 6 a",
    "sg:city":"Porta Westfalica",
    "sg:phone":"+49 5706/2252",
    "sg:postcode":"32457",
    "sg:province":"Nordrhein-Westfalen",
    "wof:name":"Werner Baumann",
    "wof:placetype":"venue"
},
  "geometry": {"coordinates":[8.896159,52.202545],"type":"Point"}
}