{
  "type": "Feature",
  "properties": {
    "iso:country":"DE",
    "sg:address":"Benquestr 58",
    "sg:city":"Bremen",
    "sg:phone":"+49 421/344488",
    "sg:postcode":"28209",
    "sg:province":"Bremen",
    "wof:name":"Hegeler & S\u00f6hne Gmbh & Co Kg",
    "wof:placetype":"venue"
},
  "geometry": {"coordinates":[8.8329868317,53.086605072],"type":"Point"}
}