{
  "type": "Feature",
  "properties": {
    "iso:country":"DE",
    "sg:address":"Blumenstr. 1",
    "sg:city":"Velbert",
    "sg:phone":"+49 2051/55595",
    "sg:postcode":"42551",
    "sg:province":"Nordrhein-Westfalen",
    "wof:name":"G. Pintaudi",
    "wof:placetype":"venue"
},
  "geometry": {"coordinates":[7.045899868,51.338218689],"type":"Point"}
}