{
  "type": "Feature",
  "properties": {
    "iso:country":"DE",
    "sg:address":"Hauptstr. 29",
    "sg:city":"Kirchheim",
    "sg:phone":"+49 6625/5358",
    "sg:postcode":"36275",
    "sg:province":"Hessen",
    "wof:name":"K. Scheidemantel",
    "wof:placetype":"venue"
},
  "geometry": {"coordinates":[9.5743989944,50.8389205933],"type":"Point"}
}