{
  "type": "Feature",
  "properties": {
    "iso:country":"DE",
    "sg:address":"Jahnstr.",
    "sg:city":"Bad Marienberg",
    "sg:phone":"+49 2661/95520",
    "sg:postcode":"56470",
    "sg:province":"Rheinland-Pfalz",
    "wof:name":"Holz-gross Gmbh",
    "wof:placetype":"venue"
},
  "geometry": {"coordinates":[7.956269,50.655712],"type":"Point"}
}