{
  "type": "Feature",
  "properties": {
    "iso:country":"DE",
    "sg:address":"Muckenschopfer Str. 6",
    "sg:city":"Rheinau",
    "sg:phone":"+49 7844/7305",
    "sg:postcode":"77866",
    "sg:province":"Baden-W\u00fcrttemberg",
    "wof:name":"Dieter Vogler",
    "wof:placetype":"venue"
},
  "geometry": {"coordinates":[7.9876022339,48.6816062927],"type":"Point"}
}