{
  "type": "Feature",
  "properties": {
    "iso:country":"DE",
    "sg:address":"Friesenstr. 16",
    "sg:city":"L\u00fcdenscheid",
    "sg:phone":"+49 2351/24932",
    "sg:postcode":"58509",
    "sg:province":"Nordrhein-Westfalen",
    "wof:name":"Nohn & S\u00f6hne Ohg",
    "wof:placetype":"venue"
},
  "geometry": {"coordinates":[7.6152219772,51.2211074829],"type":"Point"}
}