{
  "type": "Feature",
  "properties": {
    "iso:country":"DE",
    "sg:address":"Auricher Str. 37",
    "sg:city":"Stuttgart",
    "sg:phone":"+49 711/847474",
    "sg:postcode":"70437",
    "sg:province":"Baden-W\u00fcrttemberg",
    "wof:name":"Heinz Wanneck",
    "wof:placetype":"venue"
},
  "geometry": {"coordinates":[9.189138,48.830734],"type":"Point"}
}