{
  "type": "Feature",
  "properties": {
    "iso:country":"DE",
    "sg:address":"Reutlinger Str. 1a",
    "sg:city":"Berlin",
    "sg:phone":"+49 30/7742190",
    "sg:postcode":"12247",
    "sg:province":"Berlin",
    "wof:name":"J\u00fcrgen Wilisch",
    "wof:placetype":"venue"
},
  "geometry": {"coordinates":[13.3605709076,52.4463500977],"type":"Point"}
}