{
  "type": "Feature",
  "properties": {
    "iso:country":"DE",
    "sg:address":"Dinghartinger Str. 8",
    "sg:city":"Stra\u00dflach-Dingharting",
    "sg:phone":"+49 8170/7556",
    "sg:postcode":"82064",
    "sg:province":"Bayern",
    "wof:name":"M. Gr\u00f6bmair",
    "wof:placetype":"venue"
},
  "geometry": {"coordinates":[11.5358896255,47.9615440369],"type":"Point"}
}