{
  "type": "Feature",
  "properties": {
    "iso:country":"DE",
    "sg:address":"Hauptstr. 4",
    "sg:city":"Velden",
    "sg:phone":"+49 8742/732",
    "sg:postcode":"84149",
    "sg:province":"Bayern",
    "wof:name":"Erich Thalmeier Architekt",
    "wof:placetype":"venue"
},
  "geometry": {"coordinates":[12.255141,48.365257],"type":"Point"}
}