{
  "type": "Feature",
  "properties": {
    "iso:country":"DE",
    "sg:address":"Ehrengutstr. 1",
    "sg:city":"M\u00fcnchen",
    "sg:phone":"+49 89/7210960",
    "sg:postcode":"80469",
    "sg:province":"Bayern",
    "wof:name":"Psl & P Publishing Service Leuthel & Partner Gmbh",
    "wof:placetype":"venue"
},
  "geometry": {"coordinates":[11.5579442978,48.1215057373],"type":"Point"}
}