{
  "type": "Feature",
  "properties": {
    "iso:country":"DE",
    "sg:address":"Anne-Frank-Anger 15",
    "sg:city":"M\u00fcnchen",
    "sg:phone":"+49 89/6804676",
    "sg:postcode":"81673",
    "sg:province":"Bayern",
    "wof:name":"Robert Heinrich Architekt",
    "wof:placetype":"venue"
},
  "geometry": {"coordinates":[11.639226,48.12389],"type":"Point"}
}