{
  "type": "Feature",
  "properties": {
    "iso:country":"DE",
    "sg:address":"Gewerbepark 20",
    "sg:city":"Malschwitz",
    "sg:phone":"+49 3591/607874",
    "sg:postcode":"02694",
    "sg:province":"Sachsen",
    "wof:name":"Betonbohr- Und S\u00e4geservice Gmbh",
    "wof:placetype":"venue"
},
  "geometry": {"coordinates":[14.473777771,51.2211227417],"type":"Point"}
}