{
  "type": "Feature",
  "properties": {
    "iso:country":"DE",
    "sg:address":"Wiesenbrede 6",
    "sg:city":"Lage",
    "sg:phone":"+49 5232/4627",
    "sg:postcode":"32791",
    "sg:province":"Nordrhein-Westfalen",
    "wof:name":"Gerd W. M\u00f6ller",
    "wof:placetype":"venue"
},
  "geometry": {"coordinates":[8.841843605,51.982334137],"type":"Point"}
}