{
  "type": "Feature",
  "properties": {
    "iso:country":"DE",
    "sg:address":"R\u00fcschendorfer Str. 17",
    "sg:city":"Damme",
    "sg:phone":"+49 5491/2376",
    "sg:postcode":"49401",
    "sg:province":"Niedersachsen",
    "wof:name":"Dr. Helmut-gerd Vogelsang Tierarzt",
    "wof:placetype":"venue"
},
  "geometry": {"coordinates":[8.202132225,52.522693634],"type":"Point"}
}