{
  "type": "Feature",
  "properties": {
    "iso:country":"DE",
    "sg:address":"Am Egelsee 2",
    "sg:city":"P\u00fcrgen",
    "sg:phone":"+49 8196/591",
    "sg:postcode":"86932",
    "sg:province":"Bayern",
    "wof:name":"Marian Prei\u00dfer Hebamme",
    "wof:placetype":"venue"
},
  "geometry": {"coordinates":[10.921386,48.025455],"type":"Point"}
}