{
  "type": "Feature",
  "properties": {
    "iso:country":"DE",
    "sg:address":"Ludenberger Str. 5",
    "sg:city":"D\u00fcsseldorf",
    "sg:phone":"+49 211/6986896",
    "sg:postcode":"40629",
    "sg:province":"Nordrhein-Westfalen",
    "wof:name":"K & S Gesellschaft F\u00fcr Objektbetreuung Mbh",
    "wof:placetype":"venue"
},
  "geometry": {"coordinates":[6.8307762146,51.2412948608],"type":"Point"}
}