{
  "type": "Feature",
  "properties": {
    "iso:country":"DE",
    "sg:address":"Lothringer Str 36b",
    "sg:city":"Bochum",
    "sg:phone":"+49 234/9535970",
    "sg:postcode":"44805",
    "sg:province":"Nordrhein-Westfalen",
    "wof:name":"Volto Gmbh",
    "wof:placetype":"venue"
},
  "geometry": {"coordinates":[7.282001,51.519691],"type":"Point"}
}