{
  "type": "Feature",
  "properties": {
    "iso:country":"DE",
    "sg:address":"Helenenstr. 11",
    "sg:city":"Hannover",
    "sg:phone":"+49 511/839081",
    "sg:postcode":"30519",
    "sg:province":"Niedersachsen",
    "wof:name":"Verlag Wolfgang Hoffmann",
    "wof:placetype":"venue"
},
  "geometry": {"coordinates":[9.7629375458,52.3384666443],"type":"Point"}
}