{
  "type": "Feature",
  "properties": {
    "iso:country":"DE",
    "sg:address":"Bismarkstrasse 14",
    "sg:city":"Ludwigsburg",
    "sg:phone":"+49 7141/8929042",
    "sg:postcode":"71634",
    "sg:province":"Baden-W\u00fcrttemberg",
    "wof:name":"Lauterbach & Grimm Gmbh",
    "wof:placetype":"venue"
},
  "geometry": {"coordinates":[9.182421,48.89716],"type":"Point"}
}