{
  "type": "Feature",
  "properties": {
    "iso:country":"DE",
    "sg:address":"In der Helle 9",
    "sg:city":"Kierspe",
    "sg:phone":"+49 2359/91490",
    "sg:postcode":"58566",
    "sg:province":"Nordrhein-Westfalen",
    "wof:name":"M\u00e4rkum All Plast Service Gmbh",
    "wof:placetype":"venue"
},
  "geometry": {"coordinates":[7.588484,51.122177],"type":"Point"}
}