{
  "type": "Feature",
  "properties": {
    "iso:country":"DE",
    "sg:address":"S\u00fcderstr. 18",
    "sg:city":"Heide",
    "sg:phone":"+49 481/63528",
    "sg:postcode":"25746",
    "sg:province":"Schleswig-Holstein",
    "wof:name":"K.-h. Gust",
    "wof:placetype":"venue"
},
  "geometry": {"coordinates":[9.0907974243,54.1931877136],"type":"Point"}
}