{
  "type": "Feature",
  "properties": {
    "iso:country":"DE",
    "sg:address":"Vorderreihe 28",
    "sg:city":"L\u00fcbeck",
    "sg:phone":"+49 4502/6885",
    "sg:postcode":"23570",
    "sg:province":"Schleswig-Holstein",
    "wof:name":"Danke Warenhandels Gmbh",
    "wof:placetype":"venue"
},
  "geometry": {"coordinates":[10.8688373566,53.9568138123],"type":"Point"}
}