{
  "type": "Feature",
  "properties": {
    "iso:country":"DE",
    "sg:address":"Birkenweg 8",
    "sg:city":"Laupheim",
    "sg:phone":"+49 7392/4768",
    "sg:postcode":"88471",
    "sg:province":"Baden-W\u00fcrttemberg",
    "wof:name":"Karl-heinz Schiffer Steuerberater",
    "wof:placetype":"venue"
},
  "geometry": {"coordinates":[9.892531395,48.2271270752],"type":"Point"}
}