{
  "type": "Feature",
  "properties": {
    "iso:country":"DE",
    "sg:address":"Barer Str. 86 A",
    "sg:city":"M\u00fcnchen",
    "sg:phone":"+49 89/2720162",
    "sg:postcode":"80799",
    "sg:province":"Bayern",
    "wof:name":"Alois Hutter Masseur",
    "wof:placetype":"venue"
},
  "geometry": {"coordinates":[11.57499,48.153416],"type":"Point"}
}