{
  "type": "Feature",
  "properties": {
    "iso:country":"DE",
    "sg:address":"Rosenstr. 18",
    "sg:city":"Furth im Wald",
    "sg:phone":"+49 9973/1246",
    "sg:postcode":"93437",
    "sg:province":"Bayern",
    "wof:name":"Bestattungen E. Schiessl",
    "wof:placetype":"venue"
},
  "geometry": {"coordinates":[12.846132,49.308617],"type":"Point"}
}