{
  "type": "Feature",
  "properties": {
    "iso:country":"DE",
    "sg:address":"Auf dem Sandberg 4",
    "sg:city":"K\u00f6ln",
    "sg:phone":"+49 221/8307742",
    "sg:postcode":"51105",
    "sg:province":"Nordrhein-Westfalen",
    "wof:name":"Heinz Thelen Architekt",
    "wof:placetype":"venue"
},
  "geometry": {"coordinates":[6.993487,50.912167],"type":"Point"}
}