{
  "type": "Feature",
  "properties": {
    "iso:country":"DE",
    "sg:address":"Iggelheimer Str. 17",
    "sg:city":"Speyer",
    "sg:phone":"+49 6232/42187",
    "sg:postcode":"67346",
    "sg:province":"Rheinland-Pfalz",
    "wof:name":"Zimmermann",
    "wof:placetype":"venue"
},
  "geometry": {"coordinates":[8.431081,49.319332],"type":"Point"}
}