{
  "type": "Feature",
  "properties": {
    "iso:country":"DE",
    "sg:address":"Hauptstr. 118",
    "sg:city":"Herschweiler-Pettersheim",
    "sg:phone":"+49 6384/361",
    "sg:postcode":"66909",
    "sg:province":"Rheinland-Pfalz",
    "wof:name":"Richard Leixner",
    "wof:placetype":"venue"
},
  "geometry": {"coordinates":[7.3473348618,49.4801254272],"type":"Point"}
}