{
  "type": "Feature",
  "properties": {
    "iso:country":"DE",
    "sg:address":"Grafweg 18",
    "sg:city":"Attendorn",
    "sg:phone":"+49 2722/2423",
    "sg:postcode":"57439",
    "sg:province":"Nordrhein-Westfalen",
    "wof:name":"Rudolf Pompe Gmbh",
    "wof:placetype":"venue"
},
  "geometry": {"coordinates":[7.909204,51.127159],"type":"Point"}
}