{
  "type": "Feature",
  "properties": {
    "iso:country":"DE",
    "sg:address":"Hebbergstr. 17",
    "sg:city":"Filderstadt",
    "sg:postcode":"70794",
    "sg:province":"Baden-W\u00fcrttemberg",
    "wof:name":"Sch\u00f6llkopf Stukkateur Meisterbetrieb E. K.",
    "wof:placetype":"venue"
},
  "geometry": {"coordinates":[9.19294,48.65807],"type":"Point"}
}