{
  "type": "Feature",
  "properties": {
    "iso:country":"DE",
    "sg:address":"Br\u00fchlstr.",
    "sg:city":"Me\u00dfstetten",
    "sg:phone":"+49 7436/205",
    "sg:postcode":"72469",
    "sg:province":"Baden-W\u00fcrttemberg",
    "wof:name":"Gerhard K\u00e4stle",
    "wof:placetype":"venue"
},
  "geometry": {"coordinates":[8.877397,48.198708],"type":"Point"}
}