{
  "type": "Feature",
  "properties": {
    "iso:country":"DE",
    "sg:address":"Schwemannstr. 4",
    "sg:city":"Hildesheim",
    "sg:phone":"+49 5121/157157",
    "sg:postcode":"31134",
    "sg:province":"Niedersachsen",
    "wof:name":"Michael Erdmann",
    "wof:placetype":"venue"
},
  "geometry": {"coordinates":[9.9532012939,52.1509094238],"type":"Point"}
}