{
  "type": "Feature",
  "properties": {
    "iso:country":"DE",
    "sg:address":"M\u00fchlenstr. 6",
    "sg:city":"Jemgum",
    "sg:phone":"+49 4902/912932",
    "sg:postcode":"26844",
    "sg:province":"Niedersachsen",
    "wof:name":"Johann Duin",
    "wof:placetype":"venue"
},
  "geometry": {"coordinates":[7.2791519165,53.3155899048],"type":"Point"}
}