{
  "type": "Feature",
  "properties": {
    "iso:country":"DE",
    "sg:address":"Fuggerstr. 6",
    "sg:city":"K\u00f6ln",
    "sg:phone":"+49 2203/93490",
    "sg:postcode":"51149",
    "sg:province":"Nordrhein-Westfalen",
    "wof:name":"Kienle Gmbh",
    "wof:placetype":"venue"
},
  "geometry": {"coordinates":[7.0756731033,50.9046516418],"type":"Point"}
}