{
  "type": "Feature",
  "properties": {
    "iso:country":"DE",
    "sg:address":"S\u00fcdstr. 25",
    "sg:city":"Kamp-Lintfort",
    "sg:phone":"+49 2842/3310",
    "sg:postcode":"47475",
    "sg:province":"Nordrhein-Westfalen",
    "wof:name":"Tms Norbert Neuhaus E. K.",
    "wof:placetype":"venue"
},
  "geometry": {"coordinates":[6.542473793,51.4872169495],"type":"Point"}
}