{
  "type": "Feature",
  "properties": {
    "iso:country":"DE",
    "sg:address":"August-Schmidt-Str. 4",
    "sg:city":"Dortmund",
    "sg:phone":"+49 231/7551",
    "sg:postcode":"44227",
    "sg:province":"Nordrhein-Westfalen",
    "wof:name":"Universit\u00e4t Lehrgebiet Baupl. U. Architekturtheorie",
    "wof:placetype":"venue"
},
  "geometry": {"coordinates":[7.413602829,51.4846954346],"type":"Point"}
}