{
  "type": "Feature",
  "properties": {
    "iso:country":"DE",
    "sg:address":"Gartenstr. 13",
    "sg:city":"Ebenhausen",
    "sg:postcode":"82067",
    "sg:province":"Bayern",
    "wof:name":"Bo-da Betriebsorganisation Und Datenverarbeitungs Gmbh",
    "wof:placetype":"venue"
},
  "geometry": {"coordinates":[11.4531984329,47.9790420532],"type":"Point"}
}