{
  "type": "Feature",
  "properties": {
    "iso:country":"DE",
    "sg:address":"Markt 71",
    "sg:city":"Sankt Augustin",
    "sg:postcode":"53757",
    "sg:province":"Nordrhein-Westfalen",
    "wof:name":"Y\u00fc Fong Import-export Warenhandels Gmbh",
    "wof:placetype":"venue"
},
  "geometry": {"coordinates":[7.1867809296,50.7768287659],"type":"Point"}
}