{
  "type": "Feature",
  "properties": {
    "iso:country":"DE",
    "sg:address":"Hammer 28",
    "sg:city":"Schwarzenfeld",
    "sg:phone":"+49 9435/2251",
    "sg:postcode":"92521",
    "sg:province":"Bayern",
    "wof:name":"Allkofer Gmbh & Co. Bauzentrum Kg",
    "wof:placetype":"venue"
},
  "geometry": {"coordinates":[12.1463832855,49.3874015808],"type":"Point"}
}