{
  "type": "Feature",
  "properties": {
    "iso:country":"DE",
    "sg:address":"Jurastr. 50",
    "sg:city":"Esslingen",
    "sg:phone":"+49 711/3456770",
    "sg:postcode":"73734",
    "sg:province":"Baden-W\u00fcrttemberg",
    "wof:name":"Hans-ulrich Kr\u00f6mer Architekt",
    "wof:placetype":"venue"
},
  "geometry": {"coordinates":[9.312219,48.720753],"type":"Point"}
}