{
  "type": "Feature",
  "properties": {
    "iso:country":"DE",
    "sg:address":"Hauptstr. 28",
    "sg:city":"Untersteinach",
    "sg:phone":"+49 9225/8209",
    "sg:postcode":"95369",
    "sg:province":"Bayern",
    "wof:name":"B. Dressel",
    "wof:placetype":"venue"
},
  "geometry": {"coordinates":[11.52983,50.132359],"type":"Point"}
}