{
  "type": "Feature",
  "properties": {
    "iso:country":"DE",
    "sg:address":"Im Buchholz",
    "sg:city":"L\u00f6rrach",
    "sg:phone":"+49 7621/53555",
    "sg:postcode":"79541",
    "sg:province":"Baden-W\u00fcrttemberg",
    "wof:name":"Karl Friedlin",
    "wof:placetype":"venue"
},
  "geometry": {"coordinates":[7.692363,47.633957],"type":"Point"}
}