{
  "type": "Feature",
  "properties": {
    "iso:country":"DE",
    "sg:address":"R\u00f6merstr. 46",
    "sg:city":"Kehl",
    "sg:phone":"+49 7854/370",
    "sg:postcode":"77694",
    "sg:province":"Baden-W\u00fcrttemberg",
    "wof:name":"Hermann Ritt",
    "wof:placetype":"venue"
},
  "geometry": {"coordinates":[7.820652,48.508018],"type":"Point"}
}