{
  "type": "Feature",
  "properties": {
    "iso:country":"DE",
    "sg:address":"Dorfstr. 35b",
    "sg:city":"Je\u00dfnigk",
    "sg:phone":"+49 3535/3036",
    "sg:postcode":"04916",
    "sg:province":"Brandenburg",
    "wof:name":"Je\u00dfnigker Agrar Gmbh",
    "wof:placetype":"venue"
},
  "geometry": {"coordinates":[13.231134,51.727943],"type":"Point"}
}