{
  "type": "Feature",
  "properties": {
    "iso:country":"DE",
    "sg:address":"Kapellenweg 14",
    "sg:city":"K\u00f6nigsdorf",
    "sg:phone":"+49 8179/8457",
    "sg:postcode":"82549",
    "sg:province":"Bayern",
    "wof:name":"Josef St\u00f6ger",
    "wof:placetype":"venue"
},
  "geometry": {"coordinates":[11.494282,47.819504],"type":"Point"}
}