{
  "type": "Feature",
  "properties": {
    "iso:country":"DE",
    "sg:address":"B\u00fcschers Kamp 18",
    "sg:city":"G\u00fctersloh",
    "sg:phone":"+49 5241/54212",
    "sg:postcode":"33332",
    "sg:province":"Nordrhein-Westfalen",
    "wof:name":"Gisela Granzin",
    "wof:placetype":"venue"
},
  "geometry": {"coordinates":[8.3664703369,51.8895492554],"type":"Point"}
}