{
  "type": "Feature",
  "properties": {
    "iso:country":"DE",
    "sg:address":"Dorfstr. 8",
    "sg:city":"K\u00f6rbitz",
    "sg:phone":"+49 33746/72465",
    "sg:postcode":"14913",
    "sg:province":"Brandenburg",
    "wof:name":"T. No\u00dfmann",
    "wof:placetype":"venue"
},
  "geometry": {"coordinates":[13.1142625809,51.8978767395],"type":"Point"}
}