{
  "type": "Feature",
  "properties": {
    "iso:country":"DE",
    "sg:address":"Eisenbahnstr. 8",
    "sg:city":"Sonneberg",
    "sg:postcode":"96515",
    "sg:province":"Th\u00fcringen",
    "wof:name":"Karl K\u00f6hler",
    "wof:placetype":"venue"
},
  "geometry": {"coordinates":[11.1822690964,50.354183197],"type":"Point"}
}