{
  "type": "Feature",
  "properties": {
    "iso:country":"DE",
    "sg:address":"Hospitalstr. 86",
    "sg:city":"Wallerfangen",
    "sg:phone":"+49 6831/61459",
    "sg:postcode":"66798",
    "sg:province":"Saarland",
    "wof:name":"Richard Schmitt",
    "wof:placetype":"venue"
},
  "geometry": {"coordinates":[6.70573,49.324059],"type":"Point"}
}