{
  "type": "Feature",
  "properties": {
    "iso:country":"DE",
    "sg:address":"Richard-Wagner-Str. 35",
    "sg:city":"Bayreuth",
    "sg:phone":"+49 921/65234",
    "sg:postcode":"95444",
    "sg:province":"Bayern",
    "wof:name":"Hendrik B\u00e4rwald",
    "wof:placetype":"venue"
},
  "geometry": {"coordinates":[11.5818576813,49.9421882629],"type":"Point"}
}