{
  "type": "Feature",
  "properties": {
    "iso:country":"DE",
    "sg:address":"Bahnhofstr 10a",
    "sg:city":"Igel/Trier",
    "sg:phone":"+49 6501",
    "sg:postcode":"54298",
    "sg:province":"Rheinland-Pfalz",
    "wof:name":"Igel-design Schausbreitner & Schlicker Gmbh: Hauptseite",
    "wof:placetype":"venue"
},
  "geometry": {"coordinates":[6.5519490242,49.7076148987],"type":"Point"}
}