{
  "type": "Feature",
  "properties": {
    "iso:country":"DE",
    "sg:address":"\u00c4u\u00dfere Leipziger Str. 52",
    "sg:city":"Schkeuditz",
    "sg:phone":"+49 34204/62209",
    "sg:postcode":"04435",
    "sg:province":"Sachsen",
    "wof:name":"Axel Schult",
    "wof:placetype":"venue"
},
  "geometry": {"coordinates":[12.250235,51.387531],"type":"Point"}
}