{
  "type": "Feature",
  "properties": {
    "iso:country":"DE",
    "sg:address":"Hauptstr. 30",
    "sg:city":"Tr\u00f6glitz",
    "sg:postcode":"06729",
    "sg:province":"Sachsen-Anhalt",
    "wof:name":"Technologie- Und Gr\u00fcnderzentrum Elsteraue Gmbh",
    "wof:placetype":"venue"
},
  "geometry": {"coordinates":[12.213760376,51.0623703003],"type":"Point"}
}