{
  "type": "Feature",
  "properties": {
    "iso:country":"DE",
    "sg:address":"Wei\u00dfkugelweg 11",
    "sg:city":"Berlin",
    "sg:phone":"+49 30/7040980",
    "sg:postcode":"12107",
    "sg:province":"Berlin",
    "wof:name":"Brenck & Klimek Gmbh",
    "wof:placetype":"venue"
},
  "geometry": {"coordinates":[13.403775,52.433548],"type":"Point"}
}