{
  "type": "Feature",
  "properties": {
    "iso:country":"DE",
    "sg:address":"Lohmarstr. 2",
    "sg:city":"Bad Honnef",
    "sg:phone":"+49 2224/3353",
    "sg:postcode":"53604",
    "sg:province":"Nordrhein-Westfalen",
    "wof:name":"N. Verwegen Gmbh",
    "wof:placetype":"venue"
},
  "geometry": {"coordinates":[7.230047226,50.644203186],"type":"Point"}
}