{
  "type": "Feature",
  "properties": {
    "iso:country":"DE",
    "sg:address":"Berliner Str. 24",
    "sg:city":"Salzgitter",
    "sg:phone":"+49 5341/16050",
    "sg:postcode":"38226",
    "sg:province":"Niedersachsen",
    "wof:name":"B & S Video- Medien- Vertriebs- Gmbh",
    "wof:placetype":"venue"
},
  "geometry": {"coordinates":[10.3338127136,52.154296875],"type":"Point"}
}