{
  "type": "Feature",
  "properties": {
    "iso:country":"DE",
    "sg:address":"Koskauer Str. 73",
    "sg:city":"Tanna",
    "sg:phone":"+49 36646/22593",
    "sg:postcode":"07922",
    "sg:province":"Th\u00fcringen",
    "wof:name":"Peter Schmidt Gmbh",
    "wof:placetype":"venue"
},
  "geometry": {"coordinates":[11.8638772964,50.4947280884],"type":"Point"}
}