{
  "type": "Feature",
  "properties": {
    "iso:country":"DE",
    "sg:address":"Kanalstr. 22",
    "sg:city":"Hamburg",
    "sg:phone":"+49 40/224224",
    "sg:postcode":"22085",
    "sg:province":"Hamburg",
    "wof:name":"Trotzdem",
    "wof:placetype":"venue"
},
  "geometry": {"coordinates":[10.018242836,53.5730705261],"type":"Point"}
}