{
  "type": "Feature",
  "properties": {
    "iso:country":"DE",
    "sg:address":"Kerkrader Str. 11",
    "sg:city":"Gie\u00dfen",
    "sg:phone":"+49 641/9433155",
    "sg:postcode":"35394",
    "sg:province":"Hessen",
    "wof:name":"Anwaltskanzlei Peter Kath",
    "wof:placetype":"venue"
},
  "geometry": {"coordinates":[8.728448,50.574806],"type":"Point"}
}