{
  "type": "Feature",
  "properties": {
    "iso:country":"DE",
    "sg:address":"Untergasse 58",
    "sg:city":"Bingen",
    "sg:phone":"+49 6725/1816",
    "sg:postcode":"55411",
    "sg:province":"Rheinland-Pfalz",
    "wof:name":"K.-h. Weyerh\u00e4user Immobilienmakler",
    "wof:placetype":"venue"
},
  "geometry": {"coordinates":[7.9595131874,49.9228744507],"type":"Point"}
}