{
  "type": "Feature",
  "properties": {
    "iso:country":"DE",
    "sg:address":"Hildenweg 22",
    "sg:city":"Eningen",
    "sg:phone":"+49 4971/2188582",
    "sg:postcode":"72800",
    "sg:province":"Baden-W\u00fcrttemberg",
    "wof:name":"Roland Kromer",
    "wof:placetype":"venue"
},
  "geometry": {"coordinates":[9.261836,48.483395],"type":"Point"}
}