{
  "type": "Feature",
  "properties": {
    "iso:country":"DE",
    "sg:address":"Viktoriastr. 8",
    "sg:city":"Karlsruhe",
    "sg:phone":"+49 721/20012",
    "sg:postcode":"76133",
    "sg:province":"Baden-W\u00fcrttemberg",
    "wof:name":"Medici Fotodesign Uwe Janke",
    "wof:placetype":"venue"
},
  "geometry": {"coordinates":[8.3886489868,49.0066947937],"type":"Point"}
}