{
  "type": "Feature",
  "properties": {
    "iso:country":"DE",
    "sg:address":"Seelingst\u00e4dter Str. 25",
    "sg:city":"Hameln",
    "sg:phone":"+49 5151/56385",
    "sg:postcode":"31789",
    "sg:province":"Niedersachsen",
    "wof:name":"Procon Projektmanagement Und Consulting Gmbh",
    "wof:placetype":"venue"
},
  "geometry": {"coordinates":[9.4003238678,52.093585968],"type":"Point"}
}