{
  "type": "Feature",
  "properties": {
    "iso:country":"DE",
    "sg:address":"Berliner Str. 11",
    "sg:city":"Vellmar",
    "sg:phone":"+49 561/8200486",
    "sg:postcode":"34246",
    "sg:province":"Hessen",
    "wof:name":"Karo-lack Karosseriebau Und Lackier Gmbh",
    "wof:placetype":"venue"
},
  "geometry": {"coordinates":[9.475966,51.347633],"type":"Point"}
}