{
  "type": "Feature",
  "properties": {
    "iso:country":"DE",
    "sg:address":"Lindenstr. 8",
    "sg:city":"P\u00f6rnbach",
    "sg:phone":"+49 8446/382",
    "sg:postcode":"85309",
    "sg:province":"Bayern",
    "wof:name":"Golden Tandoori",
    "wof:placetype":"venue"
},
  "geometry": {"coordinates":[11.4640054703,48.6137771606],"type":"Point"}
}