{
  "type": "Feature",
  "properties": {
    "iso:country":"DE",
    "sg:address":"Dorfstr. 23",
    "sg:city":"Germering",
    "sg:phone":"+49 89/844311",
    "sg:postcode":"82110",
    "sg:province":"Bayern",
    "wof:name":"Sebastian Reger",
    "wof:placetype":"venue"
},
  "geometry": {"coordinates":[11.356171,48.136524],"type":"Point"}
}