{
  "type": "Feature",
  "properties": {
    "iso:country":"DE",
    "sg:address":"Balz 6",
    "sg:city":"Westerburg",
    "sg:phone":"+49 2663/4171",
    "sg:postcode":"56457",
    "sg:province":"Rheinland-Pfalz",
    "wof:name":"D. Krusche",
    "wof:placetype":"venue"
},
  "geometry": {"coordinates":[7.9598150253,50.5555839539],"type":"Point"}
}