{
  "type": "Feature",
  "properties": {
    "iso:country":"DE",
    "sg:address":"Friedrich-Engelhorn-Str. 7",
    "sg:city":"Mannheim",
    "sg:phone":"+49 621/3363580",
    "sg:postcode":"68167",
    "sg:province":"Baden-W\u00fcrttemberg",
    "wof:name":"Signum Versicherung Gmbh",
    "wof:placetype":"venue"
},
  "geometry": {"coordinates":[8.495724678,49.5006141663],"type":"Point"}
}