{
  "type": "Feature",
  "properties": {
    "iso:country":"DE",
    "sg:address":"Dorner Weg 4",
    "sg:city":"Reichshof",
    "sg:phone":"+49 2261/52917",
    "sg:postcode":"51580",
    "sg:province":"Nordrhein-Westfalen",
    "wof:name":"Ulrich Ay",
    "wof:placetype":"venue"
},
  "geometry": {"coordinates":[7.611202,50.983547],"type":"Point"}
}