{
  "type": "Feature",
  "properties": {
    "iso:country":"DE",
    "sg:address":"Nordstr. 56",
    "sg:city":"Werther",
    "sg:postcode":"33824",
    "sg:province":"Nordrhein-Westfalen",
    "wof:name":"Rzr Netzwerk Innovative Finanzplanung E. K.",
    "wof:placetype":"venue"
},
  "geometry": {"coordinates":[8.4104881287,52.0791358948],"type":"Point"}
}