{
  "type": "Feature",
  "properties": {
    "iso:country":"DE",
    "sg:address":"Eichenweg 4",
    "sg:city":"Weener",
    "sg:phone":"+49 4951/578",
    "sg:postcode":"26826",
    "sg:province":"Niedersachsen",
    "wof:name":"Ev. Pfarramt Ev. Freikirchl. Gemeinde",
    "wof:placetype":"venue"
},
  "geometry": {"coordinates":[7.3440117836,53.1597633362],"type":"Point"}
}