{
  "type": "Feature",
  "properties": {
    "iso:country":"DE",
    "sg:address":"Maybachstr. 27",
    "sg:city":"L\u00f6wenstein",
    "sg:phone":"+49 4971/301251",
    "sg:postcode":"74245",
    "sg:province":"Baden-W\u00fcrttemberg",
    "wof:name":"Kreissparkasse Heilbronn",
    "wof:placetype":"venue"
},
  "geometry": {"coordinates":[9.380612,49.095295],"type":"Point"}
}