{
  "type": "Feature",
  "properties": {
    "iso:country":"DE",
    "sg:address":"R\u00f6merstr. 26",
    "sg:city":"Obernburg",
    "sg:phone":"+49 6022/9177",
    "sg:postcode":"63785",
    "sg:province":"Bayern",
    "wof:name":"Theodor Vad",
    "wof:placetype":"venue"
},
  "geometry": {"coordinates":[9.1466083527,49.8407669067],"type":"Point"}
}