{
  "type": "Feature",
  "properties": {
    "iso:country":"DE",
    "sg:address":"Oberpleiser Str. 19 b",
    "sg:city":"Hennef",
    "sg:phone":"+49 2242/85892",
    "sg:postcode":"53773",
    "sg:province":"Nordrhein-Westfalen",
    "wof:name":"D. Camesino",
    "wof:placetype":"venue"
},
  "geometry": {"coordinates":[7.282023,50.749489],"type":"Point"}
}