{
  "type": "Feature",
  "properties": {
    "iso:country":"DE",
    "sg:address":"Benzstr. 17",
    "sg:city":"Ulm",
    "sg:phone":"+49 731/9214872",
    "sg:postcode":"89079",
    "sg:province":"Baden-W\u00fcrttemberg",
    "wof:name":"Ipu Immobilien- Und Projekt- Entwicklungsgesellschaft",
    "wof:placetype":"venue"
},
  "geometry": {"coordinates":[9.942284,48.365147],"type":"Point"}
}