{
  "type": "Feature",
  "properties": {
    "iso:country":"DE",
    "sg:address":"Jacob-Burckhardt-Str. 15",
    "sg:city":"Grenzach-Wyhlen",
    "sg:postcode":"79639",
    "sg:province":"Baden-W\u00fcrttemberg",
    "wof:name":"Reiseb\u00fcro B\u00fcrgin",
    "wof:placetype":"venue"
},
  "geometry": {"coordinates":[7.660782814,47.5512619019],"type":"Point"}
}