{
  "type": "Feature",
  "properties": {
    "iso:country":"DE",
    "sg:address":"Wiesenstr. 1",
    "sg:city":"Bensheim",
    "sg:phone":"+49 6251/3633",
    "sg:postcode":"64625",
    "sg:province":"Hessen",
    "wof:name":"Asphaltbau Heinz J. Dziura Gmbh",
    "wof:placetype":"venue"
},
  "geometry": {"coordinates":[8.5912542343,49.6849708557],"type":"Point"}
}