{
  "type": "Feature",
  "properties": {
    "iso:country":"DE",
    "sg:address":"Kaiserstr. 11",
    "sg:city":"Vienenburg",
    "sg:phone":"+49 5324/1500",
    "sg:postcode":"38690",
    "sg:province":"Niedersachsen",
    "wof:name":"W\u00e4schehaus Hans-gerhard Tolle Kg",
    "wof:placetype":"venue"
},
  "geometry": {"coordinates":[10.5640897751,51.9528083801],"type":"Point"}
}