{
  "type": "Feature",
  "properties": {
    "iso:country":"DE",
    "sg:address":"Weberstr. 8",
    "sg:city":"Karlsruhe",
    "sg:phone":"+49 4929/5798120",
    "sg:postcode":"76133",
    "sg:province":"Baden-W\u00fcrttemberg",
    "wof:name":"W\u00c4chter Packautomatik Gmbh & Co Kg",
    "wof:placetype":"venue"
},
  "geometry": {"coordinates":[8.721837,51.5751],"type":"Point"}
}