{
  "type": "Feature",
  "properties": {
    "iso:country":"DE",
    "sg:address":"Friedrich-Ebert-Str. 1",
    "sg:city":"Weida",
    "sg:phone":"+49 36603/67271",
    "sg:postcode":"07570",
    "sg:province":"Th\u00fcringen",
    "wof:name":"M. Starke",
    "wof:placetype":"venue"
},
  "geometry": {"coordinates":[12.0434093475,50.7740516663],"type":"Point"}
}