{
  "type": "Feature",
  "properties": {
    "iso:country":"DE",
    "sg:address":"Hildegardstr. 2",
    "sg:city":"Kaiserslautern",
    "sg:phone":"+49 631/58652",
    "sg:postcode":"67661",
    "sg:province":"Rheinland-Pfalz",
    "wof:name":"R. Schneider",
    "wof:placetype":"venue"
},
  "geometry": {"coordinates":[7.699719,49.412064],"type":"Point"}
}