{
  "type": "Feature",
  "properties": {
    "iso:country":"DE",
    "sg:address":"Schubertstr. 1",
    "sg:city":"Volkach",
    "sg:phone":"+49 9381/1567",
    "sg:postcode":"97332",
    "sg:province":"Bayern",
    "wof:name":"N. Und I. Dressler",
    "wof:placetype":"venue"
},
  "geometry": {"coordinates":[10.232964,49.865028],"type":"Point"}
}