{
  "type": "Feature",
  "properties": {
    "iso:country":"DE",
    "sg:address":"Wittelsbacherh\u00f6he 50-52",
    "sg:city":"Straubing",
    "sg:phone":"+49 9421/864178",
    "sg:postcode":"94315",
    "sg:province":"Bayern",
    "wof:name":"Frei- Und Hallenbad",
    "wof:placetype":"venue"
},
  "geometry": {"coordinates":[12.5603570938,48.8732032776],"type":"Point"}
}