{
  "type": "Feature",
  "properties": {
    "iso:country":"DE",
    "sg:address":"Mittelstr. 12",
    "sg:city":"B\u00f6hlen",
    "sg:postcode":"04564",
    "sg:province":"Sachsen",
    "wof:name":"B\u00f6hlener Verm\u00f6gensverwaltungs Gmbh",
    "wof:placetype":"venue"
},
  "geometry": {"coordinates":[12.3864736557,51.2303237915],"type":"Point"}
}