{
  "type": "Feature",
  "properties": {
    "iso:country":"DE",
    "sg:address":"Bahnhofstr. 22",
    "sg:city":"Sulzheim",
    "sg:phone":"+49 6732/5951",
    "sg:postcode":"55286",
    "sg:province":"Rheinland-Pfalz",
    "wof:name":"H. Und M. Dreibus Weingut",
    "wof:placetype":"venue"
},
  "geometry": {"coordinates":[8.096159935,49.8423843384],"type":"Point"}
}