{
  "type": "Feature",
  "properties": {
    "iso:country":"DE",
    "sg:address":"Rieblingstr. 12",
    "sg:city":"Parchim",
    "sg:phone":"+49 3871/212914",
    "sg:postcode":"19370",
    "sg:province":"Mecklenburg-Vorpommern",
    "wof:name":"Dachdeckermeister Udo Kr\u00fcger",
    "wof:placetype":"venue"
},
  "geometry": {"coordinates":[11.836791,53.416298],"type":"Point"}
}