{
  "type": "Feature",
  "properties": {
    "iso:country":"DE",
    "sg:address":"B\u00fcchlring 41",
    "sg:city":"Hohenthann",
    "sg:phone":"+49 8784/1635",
    "sg:postcode":"84098",
    "sg:province":"Bayern",
    "wof:name":"Christa J\u00f6chle",
    "wof:placetype":"venue"
},
  "geometry": {"coordinates":[12.0907478333,48.6649932861],"type":"Point"}
}