{
  "type": "Feature",
  "properties": {
    "iso:country":"DE",
    "sg:address":"Friedrich-Ebert-Anlage 2",
    "sg:city":"Frankfurt",
    "sg:phone":"+49 69/744701",
    "sg:postcode":"60325",
    "sg:province":"Hessen",
    "wof:name":"Bgo-beteiligungsgesellschaft Ost Mbh & Co. Kg",
    "wof:placetype":"venue"
},
  "geometry": {"coordinates":[8.659504,50.110268],"type":"Point"}
}