{
  "type": "Feature",
  "properties": {
    "iso:country":"DE",
    "sg:address":"Maiburger Str. 38",
    "sg:city":"Leer",
    "sg:phone":"+49 491/73808",
    "sg:postcode":"26789",
    "sg:province":"Niedersachsen",
    "wof:name":"Spanienimport Rieger Gro\u00dfhandel-import-export",
    "wof:placetype":"venue"
},
  "geometry": {"coordinates":[7.5239062309,53.2438659668],"type":"Point"}
}