{
  "type": "Feature",
  "properties": {
    "iso:country":"DE",
    "sg:address":"Goethestr. 8",
    "sg:city":"Freiburg",
    "sg:phone":"+49 761/703620",
    "sg:postcode":"79100",
    "sg:province":"Baden-W\u00fcrttemberg",
    "wof:name":"Karl-heinz Oellers Rechtsanwalt",
    "wof:placetype":"venue"
},
  "geometry": {"coordinates":[7.8443880081,47.9891281128],"type":"Point"}
}