{
  "type": "Feature",
  "properties": {
    "iso:country":"DE",
    "sg:address":"Haberstr. 12",
    "sg:city":"Heidelberg",
    "sg:phone":"+49 6221/300035",
    "sg:postcode":"69126",
    "sg:province":"Baden-W\u00fcrttemberg",
    "wof:name":"L. & H. Hochstein Gmbh & Co. Kg",
    "wof:placetype":"venue"
},
  "geometry": {"coordinates":[8.680875,49.365177],"type":"Point"}
}