{
  "type": "Feature",
  "properties": {
    "iso:country":"DE",
    "sg:address":"Ritterstr. 18",
    "sg:city":"Weiherhammer",
    "sg:phone":"+49 9605/1204",
    "sg:postcode":"92729",
    "sg:province":"Bayern",
    "wof:name":"A. Krapf",
    "wof:placetype":"venue"
},
  "geometry": {"coordinates":[12.053166,49.633324],"type":"Point"}
}