{
  "type": "Feature",
  "properties": {
    "iso:country":"DE",
    "sg:city":"Hannover",
    "sg:phone":"+49 511/6101950",
    "sg:postcode":"30179",
    "sg:province":"Niedersachsen",
    "wof:name":"Intouch - Gesellschaft F\u00fcr Telemarketing Und Consulting Mbh",
    "wof:placetype":"venue"
},
  "geometry": {"coordinates":[9.750585,52.410606],"type":"Point"}
}