{
  "type": "Feature",
  "properties": {
    "iso:country":"DE",
    "sg:address":"Bahnhofstr. 1-1",
    "sg:city":"Herrenberg",
    "sg:phone":"+49 7032/23952",
    "sg:postcode":"71083",
    "sg:province":"Baden-W\u00fcrttemberg",
    "wof:name":"Thessaloniki",
    "wof:placetype":"venue"
},
  "geometry": {"coordinates":[8.8658952713,48.5943183899],"type":"Point"}
}