{
  "type": "Feature",
  "properties": {
    "iso:country":"DE",
    "sg:address":"Westring 291",
    "sg:city":"Mainz",
    "sg:phone":"+49 6131/682590",
    "sg:postcode":"55120",
    "sg:province":"Rheinland-Pfalz",
    "wof:name":"P. K\u00f6hler",
    "wof:placetype":"venue"
},
  "geometry": {"coordinates":[8.2151222229,50.0164146423],"type":"Point"}
}