{
  "type": "Feature",
  "properties": {
    "iso:country":"DE",
    "sg:address":"Vaerstenberg 28a",
    "sg:city":"Herdecke",
    "sg:phone":"+49 2330/8166",
    "sg:postcode":"58313",
    "sg:province":"Nordrhein-Westfalen",
    "wof:name":"Andreas Latussek",
    "wof:placetype":"venue"
},
  "geometry": {"coordinates":[7.44084692,51.4316520691],"type":"Point"}
}