{
  "type": "Feature",
  "properties": {
    "iso:country":"DE",
    "sg:address":"Brauweg 38",
    "sg:city":"G\u00f6ttingen",
    "sg:phone":"+49 551/70730",
    "sg:postcode":"37073",
    "sg:province":"Niedersachsen",
    "wof:name":"Carl Mahr Holding Gmbh",
    "wof:placetype":"venue"
},
  "geometry": {"coordinates":[9.926795,51.524906],"type":"Point"}
}