{
  "type": "Feature",
  "properties": {
    "iso:country":"DE",
    "sg:address":"Marktstr. 47",
    "sg:city":"Ravensburg",
    "sg:phone":"+49 751/25698",
    "sg:postcode":"88212",
    "sg:province":"Baden-W\u00fcrttemberg",
    "wof:name":"Restaurant Humpisgastst\u00e4tte",
    "wof:placetype":"venue"
},
  "geometry": {"coordinates":[9.6158208847,47.7803993225],"type":"Point"}
}