{
  "type": "Feature",
  "properties": {
    "iso:country":"DE",
    "sg:address":"Grille 1a",
    "sg:city":"Minden",
    "sg:phone":"+49 571/30251",
    "sg:postcode":"32423",
    "sg:province":"Nordrhein-Westfalen",
    "wof:name":"Viktoria Apotheke Minden",
    "wof:placetype":"venue"
},
  "geometry": {"coordinates":[8.949556,52.284637],"type":"Point"}
}