{
  "type": "Feature",
  "properties": {
    "iso:country":"DE",
    "sg:address":"Kornstr. 3",
    "sg:city":"Ingolstadt",
    "sg:phone":"+49 841/87704",
    "sg:postcode":"85049",
    "sg:province":"Bayern",
    "wof:name":"Schuster Gmbh",
    "wof:placetype":"venue"
},
  "geometry": {"coordinates":[11.3492326736,48.7587051392],"type":"Point"}
}