{
  "type": "Feature",
  "properties": {
    "iso:country":"DE",
    "sg:address":"Getzelauer Str. 2",
    "sg:city":"Leipzig",
    "sg:postcode":"04279",
    "sg:province":"Sachsen",
    "wof:name":"Levatio Steuer- Beratungsges. Mbh",
    "wof:placetype":"venue"
},
  "geometry": {"coordinates":[12.4023427963,51.2866325378],"type":"Point"}
}