{
  "type": "Feature",
  "properties": {
    "iso:country":"DE",
    "sg:address":"Runenweg",
    "sg:city":"Reichertshofen",
    "sg:phone":"+49 8453/1803",
    "sg:postcode":"85084",
    "sg:province":"Bayern",
    "wof:name":"S. Niedermeir",
    "wof:placetype":"venue"
},
  "geometry": {"coordinates":[11.5164709091,48.6407394409],"type":"Point"}
}