{
  "type": "Feature",
  "properties": {
    "iso:country":"DE",
    "sg:address":"Fritz-Overbeck-Weg 4",
    "sg:city":"Worpswede",
    "sg:phone":"+49 4792/1400",
    "sg:postcode":"27726",
    "sg:province":"Niedersachsen",
    "wof:name":"Verlag Haus Am Weyerberg Gmbh",
    "wof:placetype":"venue"
},
  "geometry": {"coordinates":[8.9232368469,53.2176704407],"type":"Point"}
}