{
  "type": "Feature",
  "properties": {
    "iso:country":"DE",
    "sg:address":"Strandstr. 10",
    "sg:city":"Borkum",
    "sg:phone":"+49 4922/558",
    "sg:postcode":"26757",
    "sg:province":"Niedersachsen",
    "wof:name":"Pension Haus Wybrands-lange",
    "wof:placetype":"venue"
},
  "geometry": {"coordinates":[6.6645507812,53.588180542],"type":"Point"}
}