{
  "type": "Feature",
  "properties": {
    "iso:country":"DE",
    "sg:address":"An der Zeche Heinrich 45",
    "sg:city":"Essen",
    "sg:phone":"+49 201/585461",
    "sg:postcode":"45277",
    "sg:province":"Nordrhein-Westfalen",
    "wof:name":"Sport Stefan",
    "wof:placetype":"venue"
},
  "geometry": {"coordinates":[7.0764808655,51.4171333313],"type":"Point"}
}