{
  "type": "Feature",
  "properties": {
    "iso:country":"DE",
    "sg:address":"Industriestr. 18",
    "sg:city":"Lage",
    "sg:phone":"+49 5232/62065",
    "sg:postcode":"32791",
    "sg:province":"Nordrhein-Westfalen",
    "wof:name":"G\u00fcnter Hofherr",
    "wof:placetype":"venue"
},
  "geometry": {"coordinates":[8.816755,51.992729],"type":"Point"}
}