{
  "type": "Feature",
  "properties": {
    "iso:country":"DE",
    "sg:address":"Karl-Marx-Str. 37",
    "sg:city":"Crawinkel",
    "sg:phone":"+49 3624/401971",
    "sg:postcode":"99330",
    "sg:province":"Th\u00fcringen",
    "wof:name":"E. He\u00df",
    "wof:placetype":"venue"
},
  "geometry": {"coordinates":[10.788189888,50.7809104919],"type":"Point"}
}