{
  "type": "Feature",
  "properties": {
    "iso:country":"DE",
    "sg:address":"Mittelfeldstr. 4",
    "sg:city":"Haiger",
    "sg:phone":"+49 2773/2785",
    "sg:postcode":"35708",
    "sg:province":"Hessen",
    "wof:name":"Henrik Verkerk Steuerberater",
    "wof:placetype":"venue"
},
  "geometry": {"coordinates":[8.1853990555,50.7494697571],"type":"Point"}
}