{
  "type": "Feature",
  "properties": {
    "iso:country":"DE",
    "sg:address":"G\u00f6rresstr. 31",
    "sg:city":"M\u00fcnchen",
    "sg:phone":"+49 89/524502",
    "sg:postcode":"80798",
    "sg:province":"Bayern",
    "wof:name":"Bekir Hakverdi",
    "wof:placetype":"venue"
},
  "geometry": {"coordinates":[11.5629816055,48.155620575],"type":"Point"}
}