{
  "type": "Feature",
  "properties": {
    "iso:country":"DE",
    "sg:address":"Eigelstein 66",
    "sg:city":"K\u00f6ln",
    "sg:phone":"+49 221/135858",
    "sg:postcode":"50668",
    "sg:province":"Nordrhein-Westfalen",
    "wof:name":"Theodor Krall",
    "wof:placetype":"venue"
},
  "geometry": {"coordinates":[6.9568829536,50.9478302002],"type":"Point"}
}