{
  "type": "Feature",
  "properties": {
    "iso:country":"DE",
    "sg:address":"Am Tiefenbach 10",
    "sg:city":"Bayerisch Eisenstein",
    "sg:phone":"+49 9925/320",
    "sg:postcode":"94252",
    "sg:province":"Bayern",
    "wof:name":"G\u00e4stehaus Ersnt Kuchler",
    "wof:placetype":"venue"
},
  "geometry": {"coordinates":[13.1879720688,49.1190490723],"type":"Point"}
}