{
  "type": "Feature",
  "properties": {
    "iso:country":"DE",
    "sg:address":"Forsthaus 5",
    "sg:city":"Kolkwitz",
    "sg:postcode":"03099",
    "sg:province":"Brandenburg",
    "wof:name":"Dr. H. J. Matschke",
    "wof:placetype":"venue"
},
  "geometry": {"coordinates":[14.14818,51.728889],"type":"Point"}
}