{
  "type": "Feature",
  "properties": {
    "iso:country":"DE",
    "sg:address":"Chamer Str. 24",
    "sg:city":"Arnschwang",
    "sg:phone":"+49 9977/226",
    "sg:postcode":"93473",
    "sg:province":"Bayern",
    "wof:name":"O. M\u00fchlbauer",
    "wof:placetype":"venue"
},
  "geometry": {"coordinates":[12.811079,49.27417],"type":"Point"}
}