{
  "type": "Feature",
  "properties": {
    "iso:country":"DE",
    "sg:address":"Brunnenstr. 19",
    "sg:city":"Niedernw\u00f6hren",
    "sg:phone":"+49 5721/2909",
    "sg:postcode":"31712",
    "sg:province":"Niedersachsen",
    "wof:name":"Heinz Fahlbusch Fleischerei Gmbh",
    "wof:placetype":"venue"
},
  "geometry": {"coordinates":[9.1396951675,52.3514862061],"type":"Point"}
}