{
  "type": "Feature",
  "properties": {
    "iso:country":"DE",
    "sg:address":"In Katzem 5 a",
    "sg:city":"Erkelenz",
    "sg:phone":"+49 2435/2973",
    "sg:postcode":"41812",
    "sg:province":"Nordrhein-Westfalen",
    "wof:name":"Lothar Heimen",
    "wof:placetype":"venue"
},
  "geometry": {"coordinates":[6.33943,51.033379],"type":"Point"}
}