{
  "type": "Feature",
  "properties": {
    "iso:country":"DE",
    "sg:address":"Schillerstr. 9",
    "sg:city":"Lauda-K\u00f6nigshofen",
    "sg:phone":"+49 9343/1296",
    "sg:postcode":"97922",
    "sg:province":"Baden-W\u00fcrttemberg",
    "wof:name":"Horst Hempel",
    "wof:placetype":"venue"
},
  "geometry": {"coordinates":[9.703843,49.566738],"type":"Point"}
}