{
  "type": "Feature",
  "properties": {
    "iso:country":"DE",
    "sg:address":"Matthiasplatz",
    "sg:city":"J\u00fclich",
    "sg:postcode":"52428",
    "sg:province":"Nordrhein-Westfalen",
    "wof:name":"B\u00fcrgerhalle Lich-steinstrass",
    "wof:placetype":"venue"
},
  "geometry": {"coordinates":[6.37733,50.92997],"type":"Point"}
}