{
  "type": "Feature",
  "properties": {
    "iso:country":"DE",
    "sg:address":"Hauptstr. 39",
    "sg:city":"Pirmasens",
    "sg:phone":"+49 6331/31607",
    "sg:postcode":"66953",
    "sg:province":"Rheinland-Pfalz",
    "wof:name":"Fielman Ag & Co.",
    "wof:placetype":"venue"
},
  "geometry": {"coordinates":[7.6050539017,49.1986236572],"type":"Point"}
}