{
  "type": "Feature",
  "properties": {
    "iso:country":"DE",
    "sg:address":"Obernstr. 38",
    "sg:city":"Bielefeld",
    "sg:phone":"+49 521/178745",
    "sg:postcode":"33602",
    "sg:province":"Nordrhein-Westfalen",
    "wof:name":"Bogner",
    "wof:placetype":"venue"
},
  "geometry": {"coordinates":[8.528455,52.019901],"type":"Point"}
}