{
  "type": "Feature",
  "properties": {
    "iso:country":"DE",
    "sg:address":"Pilgrim 5",
    "sg:city":"Holzminden",
    "sg:phone":"+49 5536/578",
    "sg:postcode":"37603",
    "sg:province":"Niedersachsen",
    "wof:name":"Marlies L\u00fcthje Ot Neuhaus Im Solling",
    "wof:placetype":"venue"
},
  "geometry": {"coordinates":[9.5208806992,51.7559356689],"type":"Point"}
}