{
  "type": "Feature",
  "properties": {
    "iso:country":"DE",
    "sg:address":"Gustav-Ricker-Str. 50",
    "sg:city":"Magdeburg",
    "sg:phone":"+49 391/6227753",
    "sg:postcode":"39120",
    "sg:province":"Sachsen-Anhalt",
    "wof:name":"Willy Mewes",
    "wof:placetype":"venue"
},
  "geometry": {"coordinates":[11.635596,52.080101],"type":"Point"}
}