{
  "type": "Feature",
  "properties": {
    "iso:country":"DE",
    "sg:address":"Kronenstr 17",
    "sg:city":"Ettlingen",
    "sg:phone":"+49 7243/58090",
    "sg:postcode":"76275",
    "sg:province":"Baden-W\u00fcrttemberg",
    "wof:name":"Megapolymers Kunststoffhandel Gmbh & Co Kg",
    "wof:placetype":"venue"
},
  "geometry": {"coordinates":[8.4089488983,48.9423065186],"type":"Point"}
}