{
  "type": "Feature",
  "properties": {
    "iso:country":"DE",
    "sg:address":"St.-Osdag-Str. 2",
    "sg:city":"Neustadt",
    "sg:phone":"+49 5072/1217",
    "sg:postcode":"31535",
    "sg:province":"Niedersachsen",
    "wof:name":"Paul Kl\u00fcnder",
    "wof:placetype":"venue"
},
  "geometry": {"coordinates":[9.569013,52.599663],"type":"Point"}
}