{
  "type": "Feature",
  "properties": {
    "iso:country":"DE",
    "sg:address":"Elisabethstr. 4",
    "sg:city":"Oldenburg",
    "sg:phone":"+49 441/9266468",
    "sg:postcode":"26135",
    "sg:province":"Niedersachsen",
    "wof:name":"C. W\u00fclfrath-klatt Rechtsanwalt",
    "wof:placetype":"venue"
},
  "geometry": {"coordinates":[8.2132034302,53.1337890625],"type":"Point"}
}