{
  "type": "Feature",
  "properties": {
    "iso:country":"DE",
    "sg:address":"Lange Str. 39",
    "sg:city":"Petershagen",
    "sg:phone":"+49 5702/2217",
    "sg:postcode":"32469",
    "sg:province":"Nordrhein-Westfalen",
    "wof:name":"Reiner Steinh\u00e4user Anlageberater",
    "wof:placetype":"venue"
},
  "geometry": {"coordinates":[8.970700264,52.3773231506],"type":"Point"}
}