{
  "type": "Feature",
  "properties": {
    "iso:country":"DE",
    "sg:address":"D\u00fcsseldorfer Str. 1c",
    "sg:city":"Marktheidenfeld",
    "sg:phone":"+49 9391/98540",
    "sg:postcode":"97828",
    "sg:province":"Bayern",
    "wof:name":"Taurus B\u00f6rsenhandelsges. Mbh",
    "wof:placetype":"venue"
},
  "geometry": {"coordinates":[9.6006803513,49.8498497009],"type":"Point"}
}