{
  "type": "Feature",
  "properties": {
    "iso:country":"DE",
    "sg:address":"H\u00f6fgensweg 8",
    "sg:city":"Selfkant",
    "sg:phone":"+49 2456/925",
    "sg:postcode":"52538",
    "sg:province":"Nordrhein-Westfalen",
    "wof:name":"Salmocid R Gmbh Patentverwertungen",
    "wof:placetype":"venue"
},
  "geometry": {"coordinates":[5.904032,51.01387],"type":"Point"}
}