{
  "type": "Feature",
  "properties": {
    "iso:country":"DE",
    "sg:address":"Vollrathstr. 40",
    "sg:city":"Frechen",
    "sg:phone":"+49 2234/962977",
    "sg:postcode":"50226",
    "sg:province":"Nordrhein-Westfalen",
    "wof:name":"M. Rinke Rechtsanwalt",
    "wof:placetype":"venue"
},
  "geometry": {"coordinates":[6.7664699554,50.9408798218],"type":"Point"}
}