{
  "type": "Feature",
  "properties": {
    "iso:country":"DE",
    "sg:address":"Eschenallee 38",
    "sg:city":"M\u00fchlenbeck",
    "sg:phone":"+49 33056/21415",
    "sg:postcode":"16567",
    "sg:province":"Brandenburg",
    "wof:name":"I. Wegner",
    "wof:placetype":"venue"
},
  "geometry": {"coordinates":[13.393448,52.648327],"type":"Point"}
}