{
  "type": "Feature",
  "properties": {
    "iso:country":"DE",
    "sg:address":"Annaberger Str. 96",
    "sg:city":"Raschau",
    "sg:phone":"+49 3774/86760",
    "sg:postcode":"08352",
    "sg:province":"Sachsen",
    "wof:name":"Karl Neukirchner",
    "wof:placetype":"venue"
},
  "geometry": {"coordinates":[12.823348,50.529854],"type":"Point"}
}