{
  "type": "Feature",
  "properties": {
    "iso:country":"DE",
    "sg:address":"Rudolf-Breitscheid-Str. 3",
    "sg:city":"Hartenstein",
    "sg:phone":"+49 37605/5370",
    "sg:postcode":"08118",
    "sg:province":"Sachsen",
    "wof:name":"R. Hasse",
    "wof:placetype":"venue"
},
  "geometry": {"coordinates":[12.67024,50.66209],"type":"Point"}
}