{
  "type": "Feature",
  "properties": {
    "iso:country":"DE",
    "sg:address":"Hospitalstr. 22",
    "sg:city":"Biedenkopf",
    "sg:phone":"+49 6461/923004",
    "sg:postcode":"35216",
    "sg:province":"Hessen",
    "wof:name":"Peter Schmitt",
    "wof:placetype":"venue"
},
  "geometry": {"coordinates":[8.530625,50.91045],"type":"Point"}
}