{
  "type": "Feature",
  "properties": {
    "iso:country":"DE",
    "sg:address":"Hauptstr. 54",
    "sg:city":"Freystadt",
    "sg:phone":"+49 9179/5482",
    "sg:postcode":"92342",
    "sg:province":"Bayern",
    "wof:name":"Fuchs",
    "wof:placetype":"venue"
},
  "geometry": {"coordinates":[11.36215,49.16785],"type":"Point"}
}