{
  "type": "Feature",
  "properties": {
    "iso:country":"DE",
    "sg:address":"Brunnenstr. 10",
    "sg:city":"Schwarzerden",
    "sg:phone":"+49 6765/7436",
    "sg:postcode":"55629",
    "sg:province":"Rheinland-Pfalz",
    "wof:name":"R. Diener",
    "wof:placetype":"venue"
},
  "geometry": {"coordinates":[7.511332,49.860741],"type":"Point"}
}