{
  "type": "Feature",
  "properties": {
    "iso:country":"DE",
    "sg:address":"Simonspike 7",
    "sg:city":"Drolshagen",
    "sg:phone":"+49 2763/6118",
    "sg:postcode":"57489",
    "sg:province":"Nordrhein-Westfalen",
    "wof:name":"Johannes Ackerschott",
    "wof:placetype":"venue"
},
  "geometry": {"coordinates":[7.7232499123,51.0630760193],"type":"Point"}
}