{
  "type": "Feature",
  "properties": {
    "iso:country":"DE",
    "sg:address":"Dorfstr. 3",
    "sg:city":"Bristow",
    "sg:phone":"+49 3996/120336",
    "sg:postcode":"17166",
    "sg:province":"Mecklenburg-Vorpommern",
    "wof:name":"Ergo Versicherungsgruppe Ag",
    "wof:placetype":"venue"
},
  "geometry": {"coordinates":[12.6232995987,53.7141685486],"type":"Point"}
}