{
  "type": "Feature",
  "properties": {
    "iso:country":"DE",
    "sg:address":"Siedlerstr. 2a",
    "sg:city":"Sinsheim",
    "sg:phone":"+49 7265/7579",
    "sg:postcode":"74889",
    "sg:province":"Baden-W\u00fcrttemberg",
    "wof:name":"Bauelemente Hartmann & Leucht",
    "wof:placetype":"venue"
},
  "geometry": {"coordinates":[8.7883358002,49.2481956482],"type":"Point"}
}