{
  "type": "Feature",
  "properties": {
    "iso:country":"DE",
    "sg:address":"Planiger Str. 62",
    "sg:city":"Bad Kreuznach",
    "sg:phone":"+49 671/67411",
    "sg:postcode":"55543",
    "sg:province":"Rheinland-Pfalz",
    "wof:name":"Deco-schwarz Inh. Heinz Dieter Schwarz",
    "wof:placetype":"venue"
},
  "geometry": {"coordinates":[7.8683848381,49.8462181091],"type":"Point"}
}