{
  "type": "Feature",
  "properties": {
    "iso:country":"DE",
    "sg:address":"Schlo\u00dfweg 13",
    "sg:city":"Herrstein",
    "sg:phone":"+49 6785/1658",
    "sg:postcode":"55756",
    "sg:province":"Rheinland-Pfalz",
    "wof:name":"Cafe In Der Zehntscheune",
    "wof:placetype":"venue"
},
  "geometry": {"coordinates":[7.337303,49.781048],"type":"Point"}
}