{
  "type": "Feature",
  "properties": {
    "iso:country":"DE",
    "sg:address":"Eisenbahnstr. 30",
    "sg:city":"Friedrichshafen",
    "sg:phone":"+49 7541/4911",
    "sg:postcode":"88048",
    "sg:province":"Baden-W\u00fcrttemberg",
    "wof:name":"A. Welsch Mineral\u00f6l-grosshandel",
    "wof:placetype":"venue"
},
  "geometry": {"coordinates":[9.4193525314,47.6705474854],"type":"Point"}
}