{
  "type": "Feature",
  "properties": {
    "iso:country":"DE",
    "sg:address":"Hochwaldstr. 9",
    "sg:city":"Niederhambach",
    "sg:phone":"+49 6787/8219",
    "sg:postcode":"55767",
    "sg:province":"Rheinland-Pfalz",
    "wof:name":"Rudi Lauer",
    "wof:placetype":"venue"
},
  "geometry": {"coordinates":[7.19482,49.684349],"type":"Point"}
}