{
  "type": "Feature",
  "properties": {
    "iso:country":"DE",
    "sg:address":"F\u00fcrstenrieder Str. 74",
    "sg:city":"M\u00fcnchen",
    "sg:phone":"+49 89/565784",
    "sg:postcode":"80686",
    "sg:province":"Bayern",
    "wof:name":"E. Eberlein",
    "wof:placetype":"venue"
},
  "geometry": {"coordinates":[11.5026731491,48.1347427368],"type":"Point"}
}