{
  "type": "Feature",
  "properties": {
    "iso:country":"DE",
    "sg:address":"Sch\u00fctzenstr. 3",
    "sg:city":"Lamstedt",
    "sg:phone":"+49 4773/7471",
    "sg:postcode":"21769",
    "sg:province":"Niedersachsen",
    "wof:name":"K. Blanck",
    "wof:placetype":"venue"
},
  "geometry": {"coordinates":[9.098586,53.634003],"type":"Point"}
}