{
  "type": "Feature",
  "properties": {
    "iso:country":"DE",
    "sg:address":"Schellingstr. 44",
    "sg:city":"Hamburg",
    "sg:postcode":"22089",
    "sg:province":"Hamburg",
    "wof:name":"Carl Lunau Gmbh & Co.",
    "wof:placetype":"venue"
},
  "geometry": {"coordinates":[10.048283577,53.5692367554],"type":"Point"}
}