{
  "type": "Feature",
  "properties": {
    "iso:country":"DE",
    "sg:address":"Franz-Josef-Faller-Str. 2",
    "sg:city":"Todtnau",
    "sg:phone":"+49 7671/8993",
    "sg:postcode":"79674",
    "sg:province":"Baden-W\u00fcrttemberg",
    "wof:name":"Schwarzwald-apotheke J\u00fcrgen Franz Krumpholz E. Kfm.",
    "wof:placetype":"venue"
},
  "geometry": {"coordinates":[7.945244,47.828606],"type":"Point"}
}