{
  "type": "Feature",
  "properties": {
    "iso:country":"DE",
    "sg:address":"Zum Sch\u00fctzenhof 1",
    "sg:city":"Arnsberg",
    "sg:phone":"+49 2931/22906",
    "sg:postcode":"59821",
    "sg:province":"Nordrhein-Westfalen",
    "wof:name":"Mihail T\u00fcrkoglu",
    "wof:placetype":"venue"
},
  "geometry": {"coordinates":[8.0699138641,51.3955993652],"type":"Point"}
}