{
  "type": "Feature",
  "properties": {
    "iso:country":"DE",
    "sg:address":"Freiheitsplatz 1",
    "sg:city":"Langelsheim",
    "sg:phone":"+49 5326/1426",
    "sg:postcode":"38685",
    "sg:province":"Niedersachsen",
    "wof:name":"Hans-j. Koch Rechtsanwalt Und Notar",
    "wof:placetype":"venue"
},
  "geometry": {"coordinates":[10.335524559,51.9363136292],"type":"Point"}
}