{
  "type": "Feature",
  "properties": {
    "iso:country":"DE",
    "sg:address":"Sch\u00f6nberger Landstr. 67",
    "sg:city":"Sch\u00f6nkirchen",
    "sg:phone":"+49 4348/8425",
    "sg:postcode":"24232",
    "sg:province":"Schleswig-Holstein",
    "wof:name":"Beratung F\u00fcr Psychisch Kranke",
    "wof:placetype":"venue"
},
  "geometry": {"coordinates":[10.212611,54.335201],"type":"Point"}
}