{
  "type": "Feature",
  "properties": {
    "iso:country":"DE",
    "sg:address":"F\u00fcssener Str. 26",
    "sg:city":"Marktoberdorf",
    "sg:phone":"+49 4922/2493300",
    "sg:postcode":"87616",
    "sg:province":"Bayern",
    "wof:name":"Induflex Ing. B\u00dcrohans Lamsfuss Gmbh",
    "wof:placetype":"venue"
},
  "geometry": {"coordinates":[7.2350988388,50.6468391418],"type":"Point"}
}