{
  "type": "Feature",
  "properties": {
    "iso:country":"DE",
    "sg:address":"Togostr. 11",
    "sg:city":"Duisburg",
    "sg:phone":"+49 203/704232",
    "sg:postcode":"47249",
    "sg:province":"Nordrhein-Westfalen",
    "wof:name":"O & K Messeservice Gmbh",
    "wof:placetype":"venue"
},
  "geometry": {"coordinates":[6.765279,51.372879],"type":"Point"}
}