{
  "type": "Feature",
  "properties": {
    "iso:country":"DE",
    "sg:address":"Bismarckstr 18-20",
    "sg:city":"Heilbronn",
    "sg:phone":"+49 7131/68291",
    "sg:postcode":"74072",
    "sg:province":"Baden-W\u00fcrttemberg",
    "wof:name":"Lws-technik Hermann Eisele Gmbh & Co",
    "wof:placetype":"venue"
},
  "geometry": {"coordinates":[9.2277793884,49.1399688721],"type":"Point"}
}