{
  "type": "Feature",
  "properties": {
    "iso:country":"DE",
    "sg:address":"Kahlenweide 2",
    "sg:city":"Winsen",
    "sg:phone":"+49 5143/8511",
    "sg:postcode":"29308",
    "sg:province":"Niedersachsen",
    "wof:name":"Hans H. Behrens",
    "wof:placetype":"venue"
},
  "geometry": {"coordinates":[9.911111,52.683666],"type":"Point"}
}