{
  "type": "Feature",
  "properties": {
    "iso:country":"DE",
    "sg:address":"Schulstr. 24",
    "sg:city":"Bischofsheim",
    "sg:phone":"+49 6144/7534",
    "sg:postcode":"65474",
    "sg:province":"Hessen",
    "wof:name":"Reweda Gmbh",
    "wof:placetype":"venue"
},
  "geometry": {"coordinates":[8.35993,49.987995],"type":"Point"}
}