{
  "type": "Feature",
  "properties": {
    "iso:country":"DE",
    "sg:address":"Beuthener Str. 1a",
    "sg:city":"Gladbeck",
    "sg:phone":"+49 2043/41974",
    "sg:postcode":"45966",
    "sg:province":"Nordrhein-Westfalen",
    "wof:name":"Rassegefl\u00fcgelzuchtverein Gladbeck-rentfort",
    "wof:placetype":"venue"
},
  "geometry": {"coordinates":[6.9576182365,51.5764541626],"type":"Point"}
}