{
  "type": "Feature",
  "properties": {
    "iso:country":"DE",
    "sg:address":"Molberger Str. 3",
    "sg:city":"Cloppenburg",
    "sg:phone":"+49 4471/957779",
    "sg:postcode":"49661",
    "sg:province":"Niedersachsen",
    "wof:name":"Moin Moin",
    "wof:placetype":"venue"
},
  "geometry": {"coordinates":[8.0322055817,52.8425941467],"type":"Point"}
}