{
  "type": "Feature",
  "properties": {
    "iso:country":"DE",
    "sg:address":"Franz-Bl\u00e4si-Str. 19",
    "sg:city":"Bruchsal",
    "sg:phone":"+49 7251/71290",
    "sg:postcode":"76646",
    "sg:province":"Baden-W\u00fcrttemberg",
    "wof:name":"Cara Immobilien Vermittlung Gmbh",
    "wof:placetype":"venue"
},
  "geometry": {"coordinates":[8.5940799713,49.1285476685],"type":"Point"}
}