{
  "type": "Feature",
  "properties": {
    "iso:country":"DE",
    "sg:address":"Hauptstr. 26",
    "sg:city":"Kirchzarten",
    "sg:phone":"+49 7661/3350",
    "sg:postcode":"79199",
    "sg:province":"Baden-W\u00fcrttemberg",
    "wof:name":"K. Hauser",
    "wof:placetype":"venue"
},
  "geometry": {"coordinates":[7.9528632164,47.9637031555],"type":"Point"}
}