{
  "type": "Feature",
  "properties": {
    "iso:country":"DE",
    "sg:address":"Herzogstr. 22",
    "sg:city":"Mehring",
    "sg:phone":"+49 8677/96890",
    "sg:postcode":"84561",
    "sg:province":"Bayern",
    "wof:name":"Techno-projekt Handels Gmbh",
    "wof:placetype":"venue"
},
  "geometry": {"coordinates":[12.7869682312,48.1922607422],"type":"Point"}
}