{
  "type": "Feature",
  "properties": {
    "iso:country":"DE",
    "sg:address":"Mevissenstr. 16",
    "sg:city":"K\u00f6ln",
    "sg:phone":"+49 221/7326646",
    "sg:postcode":"50668",
    "sg:province":"Nordrhein-Westfalen",
    "wof:name":"Kamani Handelsgesellschaft Mbh",
    "wof:placetype":"venue"
},
  "geometry": {"coordinates":[6.9682230949,50.9524879456],"type":"Point"}
}