{
  "type": "Feature",
  "properties": {
    "iso:country":"DE",
    "sg:address":"Schulstr. 2",
    "sg:city":"Auetal",
    "sg:phone":"+49 5752/828",
    "sg:postcode":"31749",
    "sg:province":"Niedersachsen",
    "wof:name":"G\u00fcnter Hanke",
    "wof:placetype":"venue"
},
  "geometry": {"coordinates":[9.233986,52.234261],"type":"Point"}
}