{
  "type": "Feature",
  "properties": {
    "iso:country":"DE",
    "sg:address":"Dieselstr. 32",
    "sg:city":"Coesfeld",
    "sg:phone":"+49 2541/4086",
    "sg:postcode":"48653",
    "sg:province":"Nordrhein-Westfalen",
    "wof:name":"Helmut Grabowsky",
    "wof:placetype":"venue"
},
  "geometry": {"coordinates":[7.1780891418,51.9197540283],"type":"Point"}
}