{
  "type": "Feature",
  "properties": {
    "iso:country":"DE",
    "sg:address":"Auf der Wiese 20",
    "sg:city":"Kaarst",
    "sg:phone":"+49 2131/511709",
    "sg:postcode":"41564",
    "sg:province":"Nordrhein-Westfalen",
    "wof:name":"Kurt Opper Architekt",
    "wof:placetype":"venue"
},
  "geometry": {"coordinates":[6.589554,51.207092],"type":"Point"}
}