{
  "type": "Feature",
  "properties": {
    "iso:country":"DE",
    "sg:address":"Luckauer Chaussee 13",
    "sg:city":"Dahme",
    "sg:phone":"+49 35451/90781",
    "sg:postcode":"15936",
    "sg:province":"Brandenburg",
    "wof:name":"Frank Weigmann Gmbh",
    "wof:placetype":"venue"
},
  "geometry": {"coordinates":[13.436362,51.865967],"type":"Point"}
}