{
  "type": "Feature",
  "properties": {
    "iso:country":"DE",
    "sg:address":"Ostendstr. 70",
    "sg:city":"Stuttgart",
    "sg:phone":"+49 711/264242",
    "sg:postcode":"70188",
    "sg:province":"Baden-W\u00fcrttemberg",
    "wof:name":"Angelos Pizza Taxi",
    "wof:placetype":"venue"
},
  "geometry": {"coordinates":[9.207676,48.785252],"type":"Point"}
}