{
  "type": "Feature",
  "properties": {
    "iso:country":"DE",
    "sg:address":"Kleinried 8",
    "sg:city":"Bechhofen",
    "sg:postcode":"91572",
    "sg:province":"Bayern",
    "wof:name":"Bauunternehmen Gessler",
    "wof:placetype":"venue"
},
  "geometry": {"coordinates":[10.5840349197,49.1923370361],"type":"Point"}
}