{
  "type": "Feature",
  "properties": {
    "iso:country":"DE",
    "sg:address":"Lange Str. 77",
    "sg:city":"Lage",
    "sg:phone":"+49 5232/62815",
    "sg:postcode":"32791",
    "sg:province":"Nordrhein-Westfalen",
    "wof:name":"Schuhe & Sport Sprenger Gmbh",
    "wof:placetype":"venue"
},
  "geometry": {"coordinates":[8.793615,51.990376],"type":"Point"}
}