{
  "type": "Feature",
  "properties": {
    "iso:country":"DE",
    "sg:address":"Fleetplatz 2-4",
    "sg:city":"Hamburg",
    "sg:phone":"+49 40/7359300",
    "sg:postcode":"21035",
    "sg:province":"Hamburg",
    "wof:name":"Fleethaus Apotheke Heike Huhn Und Elisabethtimmermann Ohg",
    "wof:placetype":"venue"
},
  "geometry": {"coordinates":[10.15808,53.489323],"type":"Point"}
}