{
  "type": "Feature",
  "properties": {
    "iso:country":"DE",
    "sg:address":"Gerhart-Hauptmann-Str. 5",
    "sg:city":"Delitzsch",
    "sg:phone":"+49 34202/90686",
    "sg:postcode":"04509",
    "sg:province":"Sachsen",
    "wof:name":"Harry Schweda",
    "wof:placetype":"venue"
},
  "geometry": {"coordinates":[12.3581113815,51.524646759],"type":"Point"}
}