{
  "type": "Feature",
  "properties": {
    "iso:country":"DE",
    "sg:address":"Bahnhofstr. 30",
    "sg:city":"Kahla",
    "sg:phone":"+49 36424/22028",
    "sg:postcode":"07768",
    "sg:province":"Th\u00fcringen",
    "wof:name":"Nether",
    "wof:placetype":"venue"
},
  "geometry": {"coordinates":[11.5890722275,50.8087081909],"type":"Point"}
}