{
  "type": "Feature",
  "properties": {
    "iso:country":"DE",
    "sg:address":"M\u00fchlentalweg",
    "sg:city":"H\u00f6chstenbach",
    "sg:phone":"+49 2680/8077",
    "sg:postcode":"57629",
    "sg:province":"Rheinland-Pfalz",
    "wof:name":"Ingenieurb\u00fcro W. Burens Vdi",
    "wof:placetype":"venue"
},
  "geometry": {"coordinates":[7.7459,50.633266],"type":"Point"}
}