{
  "type": "Feature",
  "properties": {
    "iso:country":"DE",
    "sg:address":"Markstr. 2 / B\u00f6rsenhof B",
    "sg:city":"Bremen",
    "sg:phone":"+49 421/360840",
    "sg:postcode":"28195",
    "sg:province":"Bremen",
    "wof:name":"Dav Deutsche Au\u00dfenhandels- Und Verkehrs-akademie",
    "wof:placetype":"venue"
},
  "geometry": {"coordinates":[8.804667,53.075165],"type":"Point"}
}