{
  "type": "Feature",
  "properties": {
    "iso:country":"DE",
    "sg:address":"Turnitzstr. 26-28",
    "sg:city":"Ansbach",
    "sg:phone":"+49 981/9770777",
    "sg:postcode":"91522",
    "sg:province":"Bayern",
    "wof:name":"Digicomp Gmbh & Co. Praxiseinrichtungen Kg",
    "wof:placetype":"venue"
},
  "geometry": {"coordinates":[10.575269,49.298622],"type":"Point"}
}