{
  "type": "Feature",
  "properties": {
    "iso:country":"DE",
    "sg:address":"Birkenweg 2",
    "sg:city":"Waldbr\u00f6l",
    "sg:phone":"+49 2291/1557",
    "sg:postcode":"51545",
    "sg:province":"Nordrhein-Westfalen",
    "wof:name":"K. Klemmer Anlageberater",
    "wof:placetype":"venue"
},
  "geometry": {"coordinates":[7.6186900139,50.887588501],"type":"Point"}
}