{
  "type": "Feature",
  "properties": {
    "iso:country":"DE",
    "sg:address":"Weckenhofstr. 4",
    "sg:city":"Kaarst",
    "sg:phone":"+49 2131/601497",
    "sg:postcode":"41564",
    "sg:province":"Nordrhein-Westfalen",
    "wof:name":"Heinrich Seip Ohg",
    "wof:placetype":"venue"
},
  "geometry": {"coordinates":[6.6317749023,51.2185134888],"type":"Point"}
}