{
  "type": "Feature",
  "properties": {
    "iso:country":"DE",
    "sg:address":"Schl\u00fcterstr. 5",
    "sg:city":"Brilon",
    "sg:phone":"+49 2963/1851",
    "sg:postcode":"59929",
    "sg:province":"Nordrhein-Westfalen",
    "wof:name":"J. Vonnahme",
    "wof:placetype":"venue"
},
  "geometry": {"coordinates":[8.643684,51.417572],"type":"Point"}
}