{
  "type": "Feature",
  "properties": {
    "iso:country":"DE",
    "sg:address":"Cranger Str. 37",
    "sg:city":"Gelsenkirchen",
    "sg:phone":"+49 209/399068",
    "sg:postcode":"45894",
    "sg:province":"Nordrhein-Westfalen",
    "wof:name":"Thomas J\u00fcrgensen Architekt",
    "wof:placetype":"venue"
},
  "geometry": {"coordinates":[7.06091,51.575489],"type":"Point"}
}