{
  "type": "Feature",
  "properties": {
    "iso:country":"DE",
    "sg:address":"Bergstr. 173",
    "sg:city":"Marl",
    "sg:postcode":"45770",
    "sg:province":"Nordrhein-Westfalen",
    "wof:name":"Angelkiste A. Goralski Kg",
    "wof:placetype":"venue"
},
  "geometry": {"coordinates":[7.110814,51.659966],"type":"Point"}
}