{
  "type": "Feature",
  "properties": {
    "iso:country":"DE",
    "sg:address":"Bergg\u00e4rtenstr. 21",
    "sg:city":"Neuwied",
    "sg:postcode":"56564",
    "sg:province":"Rheinland-Pfalz",
    "wof:name":"Rico Bau Innen- Und Au\u00dfenputz Gmbh",
    "wof:placetype":"venue"
},
  "geometry": {"coordinates":[7.470871,50.442883],"type":"Point"}
}