{
  "type": "Feature",
  "properties": {
    "iso:country":"DE",
    "sg:address":"Wilhelmstr. 20d",
    "sg:city":"Remscheid",
    "sg:phone":"+49 2191/26883",
    "sg:postcode":"42853",
    "sg:province":"Nordrhein-Westfalen",
    "wof:name":"Kath. Pfarramt St. Marien",
    "wof:placetype":"venue"
},
  "geometry": {"coordinates":[7.1811819077,51.1875076294],"type":"Point"}
}