{
  "type": "Feature",
  "properties": {
    "iso:country":"DE",
    "sg:address":"Lollfu\u00df 98 a",
    "sg:city":"Schleswig",
    "sg:phone":"+49 4621/21008",
    "sg:postcode":"24837",
    "sg:province":"Schleswig-Holstein",
    "wof:name":"Beer Und Speeldeel",
    "wof:placetype":"venue"
},
  "geometry": {"coordinates":[9.548034668,54.5129013062],"type":"Point"}
}