{
  "type": "Feature",
  "properties": {
    "iso:country":"DE",
    "sg:address":"Germersheimer Landstr. 2",
    "sg:city":"Philippsburg",
    "sg:phone":"+49 7256/6041",
    "sg:postcode":"76661",
    "sg:province":"Baden-W\u00fcrttemberg",
    "wof:name":"Iba Aqua-pflege-produkte Gmbh",
    "wof:placetype":"venue"
},
  "geometry": {"coordinates":[8.452011,49.201656],"type":"Point"}
}