{
  "type": "Feature",
  "properties": {
    "iso:country":"DE",
    "sg:address":"Treppenstr. 55 a",
    "sg:city":"Wadgassen",
    "sg:phone":"+49 6834/4416",
    "sg:postcode":"66787",
    "sg:province":"Saarland",
    "wof:name":"C\u00f6nen Gmbh",
    "wof:placetype":"venue"
},
  "geometry": {"coordinates":[6.797211,49.262798],"type":"Point"}
}