{
  "type": "Feature",
  "properties": {
    "iso:country":"DE",
    "sg:address":"Hauffstr. 5",
    "sg:city":"Bretzfeld",
    "sg:postcode":"74626",
    "sg:province":"Baden-W\u00fcrttemberg",
    "wof:name":"N. G. Metall- Und Fensterbau Gmbh",
    "wof:placetype":"venue"
},
  "geometry": {"coordinates":[9.402828,49.160641],"type":"Point"}
}