{
  "type": "Feature",
  "properties": {
    "iso:country":"DE",
    "sg:address":"H\u00f6rder Str. 8",
    "sg:city":"Dortmund",
    "sg:phone":"+49 231/259906",
    "sg:postcode":"44309",
    "sg:province":"Nordrhein-Westfalen",
    "wof:name":"Madame Karin",
    "wof:placetype":"venue"
},
  "geometry": {"coordinates":[7.546192,51.522766],"type":"Point"}
}