{
  "type": "Feature",
  "properties": {
    "iso:country":"DE",
    "sg:address":"Friesengasse 20a",
    "sg:city":"Frankfurt",
    "sg:phone":"+49 69/7074277",
    "sg:postcode":"60487",
    "sg:province":"Hessen",
    "wof:name":"K. Heinrich H. Wallat R. Hansmann Und B. Heise",
    "wof:placetype":"venue"
},
  "geometry": {"coordinates":[8.637734,50.123802],"type":"Point"}
}