{
  "type": "Feature",
  "properties": {
    "iso:country":"DE",
    "sg:address":"Sch\u00f6nhauser Allee 40 a",
    "sg:city":"Berlin",
    "sg:phone":"+49 30/4406258",
    "sg:postcode":"10435",
    "sg:province":"Berlin",
    "wof:name":"Petra Staht",
    "wof:placetype":"venue"
},
  "geometry": {"coordinates":[13.412614,52.53973],"type":"Point"}
}