{
  "type": "Feature",
  "properties": {
    "iso:country":"DE",
    "sg:address":"Steinberger Str. 15",
    "sg:city":"Waldweiler",
    "sg:phone":"+49 4965/891465",
    "sg:postcode":"54429",
    "sg:province":"Rheinland-Pfalz",
    "wof:name":"Hans-joachim Donie U. Ute Thomas",
    "wof:placetype":"venue"
},
  "geometry": {"coordinates":[6.805524,49.609505],"type":"Point"}
}