{
  "type": "Feature",
  "properties": {
    "iso:country":"DE",
    "sg:address":"Heidelbeergasse 4",
    "sg:city":"Dassel",
    "sg:phone":"+49 5564/91047",
    "sg:postcode":"37586",
    "sg:province":"Niedersachsen",
    "wof:name":"W. Dreyer",
    "wof:placetype":"venue"
},
  "geometry": {"coordinates":[9.72203,51.773167],"type":"Point"}
}