{
  "type": "Feature",
  "properties": {
    "iso:country":"DE",
    "sg:address":"Emserstr. 27",
    "sg:city":"St Martin",
    "sg:phone":"+49 6323/7759",
    "sg:postcode":"67487",
    "sg:province":"Rheinland-Pfalz",
    "wof:name":"K. Herold",
    "wof:placetype":"venue"
},
  "geometry": {"coordinates":[8.100323,49.298817],"type":"Point"}
}