{
  "type": "Feature",
  "properties": {
    "iso:country":"DE",
    "sg:address":"Wilhelmstr. 109",
    "sg:city":"Aachen",
    "sg:phone":"+49 241/507051",
    "sg:postcode":"52070",
    "sg:province":"Nordrhein-Westfalen",
    "wof:name":"B\u00e4der Mohr Gmbh Bad Und Wohnen",
    "wof:placetype":"venue"
},
  "geometry": {"coordinates":[6.095424,50.769936],"type":"Point"}
}