{
  "type": "Feature",
  "properties": {
    "iso:country":"DE",
    "sg:address":"Lorenzweg 42 Haus 3",
    "sg:city":"Magdeburg",
    "sg:postcode":"39124",
    "sg:province":"Sachsen-Anhalt",
    "wof:name":"Fgs Systemhaus Gmbh",
    "wof:placetype":"venue"
},
  "geometry": {"coordinates":[11.6369895935,52.1571159363],"type":"Point"}
}