{
  "type": "Feature",
  "properties": {
    "iso:country":"DE",
    "sg:address":"Rheinstr. 26",
    "sg:city":"Nierstein",
    "sg:phone":"+49 6133/59398",
    "sg:postcode":"55283",
    "sg:province":"Rheinland-Pfalz",
    "wof:name":"Heil Immobilien",
    "wof:placetype":"venue"
},
  "geometry": {"coordinates":[8.3395967484,49.8746032715],"type":"Point"}
}