{
  "type": "Feature",
  "properties": {
    "iso:country":"DE",
    "sg:address":"Riedweg 4",
    "sg:city":"Halle",
    "sg:phone":"+49 345/7702660",
    "sg:postcode":"06132",
    "sg:province":"Sachsen-Anhalt",
    "wof:name":"Konzept Zwischenerwerb Gmbh & Co. Objekt 4 Kg",
    "wof:placetype":"venue"
},
  "geometry": {"coordinates":[11.9871902466,51.4247512817],"type":"Point"}
}