{
  "type": "Feature",
  "properties": {
    "iso:country":"DE",
    "sg:address":"Theaterstr12",
    "sg:city":"Oberammergau",
    "sg:postcode":"82487",
    "sg:province":"Bayern",
    "wof:name":"Hiking Biking & Fishing - Norwegian Tourist Board",
    "wof:placetype":"venue"
},
  "geometry": {"coordinates":[9.9732999802,53.5498313904],"type":"Point"}
}