{
  "type": "Feature",
  "properties": {
    "iso:country":"DE",
    "sg:address":"Br\u00fcsseler Ring 20",
    "sg:city":"Aachen",
    "sg:postcode":"52074",
    "sg:province":"Nordrhein-Westfalen",
    "wof:name":"Aix-leasing Gmbh",
    "wof:placetype":"venue"
},
  "geometry": {"coordinates":[6.070497036,50.752204895],"type":"Point"}
}