{
  "type": "Feature",
  "properties": {
    "iso:country":"DE",
    "sg:address":"Foppenkamp 14",
    "sg:city":"Lengerich",
    "sg:phone":"+49 5904/94455",
    "sg:postcode":"49838",
    "sg:province":"Niedersachsen",
    "wof:name":"Westermann Gmbh & Co. Kg",
    "wof:placetype":"venue"
},
  "geometry": {"coordinates":[7.538522,52.538029],"type":"Point"}
}