{
  "type": "Feature",
  "properties": {
    "iso:country":"DE",
    "sg:address":"Seidenweberstr. 9",
    "sg:city":"Langenfeld",
    "sg:phone":"+49 2173/900991",
    "sg:postcode":"40764",
    "sg:province":"Nordrhein-Westfalen",
    "wof:name":"F. Kremer",
    "wof:placetype":"venue"
},
  "geometry": {"coordinates":[6.948068,51.096649],"type":"Point"}
}