{
  "type": "Feature",
  "properties": {
    "iso:country":"DE",
    "sg:address":"Steinstr. 5",
    "sg:city":"Moers",
    "sg:phone":"+49 2841/24092",
    "sg:postcode":"47441",
    "sg:province":"Nordrhein-Westfalen",
    "wof:name":"Der Teeladen Christel Zsian Kg",
    "wof:placetype":"venue"
},
  "geometry": {"coordinates":[6.6260437965,51.451499939],"type":"Point"}
}