{
  "type": "Feature",
  "properties": {
    "iso:country":"DE",
    "sg:address":"Osterwalder Weg 19",
    "sg:city":"Hoogstede",
    "sg:phone":"+49 5944/1529",
    "sg:postcode":"49846",
    "sg:province":"Niedersachsen",
    "wof:name":"Windau Modestoffe Gmbh",
    "wof:placetype":"venue"
},
  "geometry": {"coordinates":[6.982214,52.563808],"type":"Point"}
}