{
  "type": "Feature",
  "properties": {
    "iso:country":"DE",
    "sg:address":"Schwackendorf 37",
    "sg:city":"Hasselberg",
    "sg:phone":"+49 4642/6134",
    "sg:postcode":"24376",
    "sg:province":"Schleswig-Holstein",
    "wof:name":"Ernst H. Claussen",
    "wof:placetype":"venue"
},
  "geometry": {"coordinates":[9.93392,54.659939],"type":"Point"}
}