{
  "type": "Feature",
  "properties": {
    "iso:country":"DE",
    "sg:address":"Elisabeth-Selbert-Str. 9",
    "sg:city":"Langenfeld",
    "sg:phone":"+49 2173/91510",
    "sg:postcode":"40764",
    "sg:province":"Nordrhein-Westfalen",
    "wof:name":"P\u00e4schke Gmbh",
    "wof:placetype":"venue"
},
  "geometry": {"coordinates":[6.9341239929,51.1237373352],"type":"Point"}
}