{
  "type": "Feature",
  "properties": {
    "iso:country":"DE",
    "sg:address":"Friedrich-Engels-Str. 6",
    "sg:city":"Tarthun",
    "sg:phone":"+49 39268/2254",
    "sg:postcode":"39435",
    "sg:province":"Sachsen-Anhalt",
    "wof:name":"Hydraulik Tarthun Gmbh",
    "wof:placetype":"venue"
},
  "geometry": {"coordinates":[11.482431,51.922546],"type":"Point"}
}