{
  "type": "Feature",
  "properties": {
    "iso:country":"DE",
    "sg:address":"Neue Kasseler Str. 16",
    "sg:city":"Marburg",
    "sg:phone":"+49 6421/65714",
    "sg:postcode":"35039",
    "sg:province":"Hessen",
    "wof:name":"Karl-heinz Kraul",
    "wof:placetype":"venue"
},
  "geometry": {"coordinates":[8.7720890045,50.8228797913],"type":"Point"}
}