{
  "type": "Feature",
  "properties": {
    "iso:country":"DE",
    "sg:address":"Siemensstr. 6",
    "sg:city":"Kelkheim",
    "sg:phone":"+49 6195/99080",
    "sg:postcode":"65779",
    "sg:province":"Hessen",
    "wof:name":"G\u00fcnter Horn & Co. Gmbh",
    "wof:placetype":"venue"
},
  "geometry": {"coordinates":[8.467282,50.121536],"type":"Point"}
}