{
  "type": "Feature",
  "properties": {
    "iso:country":"DE",
    "sg:address":"Stolzestr. 2",
    "sg:city":"Halle",
    "sg:phone":"+49 345/5200025",
    "sg:postcode":"06118",
    "sg:province":"Sachsen-Anhalt",
    "wof:name":"Apotheke Am Landrain",
    "wof:placetype":"venue"
},
  "geometry": {"coordinates":[11.977857,51.503464],"type":"Point"}
}