{
  "type": "Feature",
  "properties": {
    "iso:country":"DE",
    "sg:address":"Bechhofen 31",
    "sg:city":"Neuendettelsau",
    "sg:phone":"+49 9874/67891",
    "sg:postcode":"91564",
    "sg:province":"Bayern",
    "wof:name":"Datacut Meyer",
    "wof:placetype":"venue"
},
  "geometry": {"coordinates":[10.7902126312,49.2607383728],"type":"Point"}
}