{
  "type": "Feature",
  "properties": {
    "iso:country":"DE",
    "sg:address":"L\u00f6hberg 9",
    "sg:city":"M\u00fclheim",
    "sg:phone":"+49 208/471007",
    "sg:postcode":"45468",
    "sg:province":"Nordrhein-Westfalen",
    "wof:name":"Gebr. Vehar Gmbh & Co. Kg",
    "wof:placetype":"venue"
},
  "geometry": {"coordinates":[6.882598877,51.4277801514],"type":"Point"}
}