{
  "type": "Feature",
  "properties": {
    "iso:country":"DE",
    "sg:address":"Amsbergstr. 7",
    "sg:city":"Bad Harzburg",
    "sg:phone":"+49 5322/2040",
    "sg:postcode":"38667",
    "sg:province":"Niedersachsen",
    "wof:name":"Dagmar Kieslich Heilpraktikerin",
    "wof:placetype":"venue"
},
  "geometry": {"coordinates":[10.5564937592,51.8778305054],"type":"Point"}
}