{
  "type": "Feature",
  "properties": {
    "iso:country":"DE",
    "sg:address":"K\u00f6nigstr. 83-87",
    "sg:city":"N\u00fcrnberg",
    "sg:phone":"+49 911/24970",
    "sg:postcode":"90402",
    "sg:province":"Bayern",
    "wof:name":"Ims-midoc Medizinische Informations-dokumentations-",
    "wof:placetype":"venue"
},
  "geometry": {"coordinates":[11.081124,49.448227],"type":"Point"}
}