{
  "type": "Feature",
  "properties": {
    "iso:country":"DE",
    "sg:address":"Hindenburgstr. 1",
    "sg:city":"Deggendorf",
    "sg:phone":"+49 991/3792570",
    "sg:postcode":"94469",
    "sg:province":"Bayern",
    "wof:name":"B & S Bielmeier & Sagstetter B\u00fcrosysteme Gmbh",
    "wof:placetype":"venue"
},
  "geometry": {"coordinates":[12.9551334381,48.8361358643],"type":"Point"}
}