{
  "type": "Feature",
  "properties": {
    "iso:country":"DE",
    "sg:address":"Robert-Koch-Str. 6",
    "sg:city":"St. Georgen",
    "sg:phone":"+49 7724/7850",
    "sg:postcode":"78112",
    "sg:province":"Baden-W\u00fcrttemberg",
    "wof:name":"Richard Zsch\u00e4bitz Ingenieur",
    "wof:placetype":"venue"
},
  "geometry": {"coordinates":[8.3156223297,48.1277885437],"type":"Point"}
}