{
  "type": "Feature",
  "properties": {
    "iso:country":"DE",
    "sg:address":"M\u00fcnchinger Str. 32",
    "sg:city":"Stuttgart",
    "sg:phone":"+49 711/801091",
    "sg:postcode":"70439",
    "sg:province":"Baden-W\u00fcrttemberg",
    "wof:name":"Arthur Schmid Steuerberater",
    "wof:placetype":"venue"
},
  "geometry": {"coordinates":[9.1492204666,48.8497772217],"type":"Point"}
}