{
  "type": "Feature",
  "properties": {
    "iso:country":"DE",
    "sg:address":"D\u00f6rnchen 2",
    "sg:city":"Herten",
    "sg:phone":"+49 209/62579",
    "sg:postcode":"45701",
    "sg:province":"Nordrhein-Westfalen",
    "wof:name":"Consysas International Gmbh",
    "wof:placetype":"venue"
},
  "geometry": {"coordinates":[7.0951328278,51.608127594],"type":"Point"}
}