{
  "type": "Feature",
  "properties": {
    "iso:country":"DE",
    "sg:address":"Karolingerstr. 83",
    "sg:city":"Bocholt",
    "sg:phone":"+49 2871/182367",
    "sg:postcode":"46395",
    "sg:province":"Nordrhein-Westfalen",
    "wof:name":"U. Sommers",
    "wof:placetype":"venue"
},
  "geometry": {"coordinates":[6.603296,51.830589],"type":"Point"}
}