{
  "type": "Feature",
  "properties": {
    "iso:country":"DE",
    "sg:address":"Albertusstr. 47-49",
    "sg:city":"K\u00f6ln",
    "sg:phone":"+49 221/254938",
    "sg:postcode":"50667",
    "sg:province":"Nordrhein-Westfalen",
    "wof:name":"Ingrid Roth Architektin",
    "wof:placetype":"venue"
},
  "geometry": {"coordinates":[6.943937,50.940323],"type":"Point"}
}