{
  "type": "Feature",
  "properties": {
    "iso:country":"DE",
    "sg:address":"Bahnhofstr. 141",
    "sg:city":"Warmensteinach",
    "sg:postcode":"95485",
    "sg:province":"Bayern",
    "wof:name":"Gardinen-stube Warmensteinach Gmbh",
    "wof:placetype":"venue"
},
  "geometry": {"coordinates":[11.7787561417,49.9958343506],"type":"Point"}
}