{
  "type": "Feature",
  "properties": {
    "iso:country":"DE",
    "sg:address":"Johann-Reis-Str. 21",
    "sg:city":"Wei\u00dfenfels",
    "sg:phone":"+49 3443/441546",
    "sg:postcode":"06667",
    "sg:province":"Sachsen-Anhalt",
    "wof:name":"Bio Komp-sas Gmbh",
    "wof:placetype":"venue"
},
  "geometry": {"coordinates":[11.9858798981,51.1860389709],"type":"Point"}
}