{
  "type": "Feature",
  "properties": {
    "iso:country":"DE",
    "sg:address":"K\u00f6lner Str. 68",
    "sg:city":"Remscheid",
    "sg:phone":"+49 2191/963676",
    "sg:postcode":"42897",
    "sg:province":"Nordrhein-Westfalen",
    "wof:name":"Holger Albermann Steuerberater",
    "wof:placetype":"venue"
},
  "geometry": {"coordinates":[7.2559690475,51.188457489],"type":"Point"}
}