{
  "type": "Feature",
  "properties": {
    "iso:country":"DE",
    "sg:address":"65 rue de Lancry",
    "sg:city":"Paris",
    "sg:postcode":"75010",
    "wof:name":"Jean Claude Dewaele",
    "wof:placetype":"venue"
},
  "geometry": {"coordinates":[2.362959,48.872494],"type":"Point"}
}