{
  "type": "Feature",
  "properties": {
    "iso:country":"DE",
    "sg:address":"Cokturhof",
    "sg:city":"Sch\u00f6nebeck",
    "sg:phone":"+49 3928/780678",
    "sg:postcode":"39218",
    "sg:province":"Sachsen-Anhalt",
    "wof:name":"Kreisarchiv Landkreis Sch\u00f6nebeck-elbe",
    "wof:placetype":"venue"
},
  "geometry": {"coordinates":[11.745505,52.019325],"type":"Point"}
}