{
  "type": "Feature",
  "properties": {
    "iso:country":"DE",
    "sg:address":"Am Stadion",
    "sg:city":"Seelow",
    "sg:postcode":"15306",
    "sg:province":"Brandenburg",
    "wof:name":"Religion",
    "wof:placetype":"venue"
},
  "geometry": {"coordinates":[14.39098,52.534481],"type":"Point"}
}