{
  "type": "Feature",
  "properties": {
    "iso:country":"DE",
    "sg:address":"Ahornweg 2",
    "sg:city":"Beckingen",
    "sg:phone":"+49 6835/2316",
    "sg:postcode":"66701",
    "sg:province":"Saarland",
    "wof:name":"Toni Rech Immobilienmakler",
    "wof:placetype":"venue"
},
  "geometry": {"coordinates":[6.7518920898,49.4305953979],"type":"Point"}
}