{
  "type": "Feature",
  "properties": {
    "iso:country":"DE",
    "sg:address":"Obentrautstra\u00dfe 62",
    "sg:city":"Berlin",
    "sg:phone":"+49 30/23550070",
    "sg:postcode":"10963",
    "sg:province":"Berlin",
    "wof:name":"Messenger Transport Logistik Gmbh",
    "wof:placetype":"venue"
},
  "geometry": {"coordinates":[13.3816728592,52.4972381592],"type":"Point"}
}