{
  "type": "Feature",
  "properties": {
    "iso:country":"DE",
    "sg:address":"Eglishalde 6",
    "sg:city":"Trossingen",
    "sg:phone":"+49 4974/252280",
    "sg:postcode":"78647",
    "sg:province":"Baden-W\u00fcrttemberg",
    "wof:name":"Tr-electronic Gmbh",
    "wof:placetype":"venue"
},
  "geometry": {"coordinates":[8.608064,48.078136],"type":"Point"}
}