{
  "type": "Feature",
  "properties": {
    "iso:country":"DE",
    "sg:address":"Triftstr. 15",
    "sg:city":"Kadenbach",
    "sg:phone":"+49 2620/8410",
    "sg:postcode":"56337",
    "sg:province":"Rheinland-Pfalz",
    "wof:name":"Hermann J\u00e4ger Ingenieur",
    "wof:placetype":"venue"
},
  "geometry": {"coordinates":[7.7264909744,50.388092041],"type":"Point"}
}