{
  "type": "Feature",
  "properties": {
    "iso:country":"DE",
    "sg:address":"Am Spreedeplacken 8",
    "sg:city":"Lengerich",
    "sg:phone":"+49 4954/8180060",
    "sg:postcode":"49525",
    "sg:province":"Nordrhein-Westfalen",
    "wof:name":"Ernst Dunkel Gmbh & Co. Kg",
    "wof:placetype":"venue"
},
  "geometry": {"coordinates":[7.866747,52.188583],"type":"Point"}
}