{
  "type": "Feature",
  "properties": {
    "iso:country":"DE",
    "sg:address":"Herbert-Hinnendahl-Str. 23",
    "sg:city":"Bielefeld",
    "sg:phone":"+49 521/965840",
    "sg:postcode":"33602",
    "sg:province":"Nordrhein-Westfalen",
    "wof:name":"Vereinigte Haftpflicht",
    "wof:placetype":"venue"
},
  "geometry": {"coordinates":[8.5337638855,52.0282669067],"type":"Point"}
}