{
  "type": "Feature",
  "properties": {
    "iso:country":"DE",
    "sg:address":"Alemannenstr. 27",
    "sg:city":"Senden",
    "sg:phone":"+49 7307/94920",
    "sg:postcode":"89250",
    "sg:province":"Bayern",
    "wof:name":"K\u00e4\u00dfmeyer F\u00f6rdertechnik Vertriebs Gmbh",
    "wof:placetype":"venue"
},
  "geometry": {"coordinates":[10.0332174301,48.3320007324],"type":"Point"}
}