{
  "type": "Feature",
  "properties": {
    "iso:country":"DE",
    "sg:address":"Widenmayerstr. 29",
    "sg:city":"M\u00fcnchen",
    "sg:phone":"+49 89/299062",
    "sg:postcode":"80538",
    "sg:province":"Bayern",
    "wof:name":"Robert Keupert",
    "wof:placetype":"venue"
},
  "geometry": {"coordinates":[11.5949239731,48.1436271667],"type":"Point"}
}