{
  "type": "Feature",
  "properties": {
    "iso:country":"DE",
    "sg:address":"Ahlmannstr. 29",
    "sg:city":"Rendsburg",
    "sg:phone":"+49 4331/789587",
    "sg:postcode":"24768",
    "sg:province":"Schleswig-Holstein",
    "wof:name":"Brocke",
    "wof:placetype":"venue"
},
  "geometry": {"coordinates":[9.637843132,54.3132133484],"type":"Point"}
}