{
  "type": "Feature",
  "properties": {
    "iso:country":"DE",
    "sg:address":"Seltrisa Ring 34",
    "sg:city":"Selters",
    "sg:phone":"+49 6483/7863",
    "sg:postcode":"65618",
    "sg:province":"Hessen",
    "wof:name":"Steinheimer Gmbh",
    "wof:placetype":"venue"
},
  "geometry": {"coordinates":[8.227703,50.335537],"type":"Point"}
}