{
  "type": "Feature",
  "properties": {
    "iso:country":"DE",
    "sg:address":"An der Aue 3",
    "sg:city":"Radeberg",
    "sg:postcode":"01454",
    "sg:province":"Sachsen",
    "wof:name":"Robert Albrecht Anlageberater",
    "wof:placetype":"venue"
},
  "geometry": {"coordinates":[13.9128627777,51.0956611633],"type":"Point"}
}