{
  "type": "Feature",
  "properties": {
    "iso:country":"DE",
    "sg:address":"Hohenzollernstr. 11 Borghorst",
    "sg:city":"Steinfurt",
    "sg:phone":"+49 4925/5293890",
    "sg:postcode":"48565",
    "sg:province":"Nordrhein-Westfalen",
    "wof:name":"Fehmer Gmbh",
    "wof:placetype":"venue"
},
  "geometry": {"coordinates":[7.3389511108,52.150100708],"type":"Point"}
}