{
  "type": "Feature",
  "properties": {
    "iso:country":"DE",
    "sg:address":"Wanheimer Str. 66",
    "sg:city":"Duisburg",
    "sg:phone":"+49 203/660455",
    "sg:postcode":"47053",
    "sg:province":"Nordrhein-Westfalen",
    "wof:name":"Brigitte Hagedorn",
    "wof:placetype":"venue"
},
  "geometry": {"coordinates":[6.7540440559,51.419593811],"type":"Point"}
}