{
  "type": "Feature",
  "properties": {
    "iso:country":"DE",
    "sg:address":"Biewerer Str. 192",
    "sg:city":"Trier",
    "sg:phone":"+49 651/9680015",
    "sg:postcode":"54293",
    "sg:province":"Rheinland-Pfalz",
    "wof:name":"Trimobil Immobilien Gmbh & Co.",
    "wof:placetype":"venue"
},
  "geometry": {"coordinates":[6.6704378128,49.7831497192],"type":"Point"}
}