{
  "type": "Feature",
  "properties": {
    "iso:country":"DE",
    "sg:address":"Pr\u00e4lat-Hartl-Str. 9",
    "sg:city":"Adelshofen",
    "sg:phone":"+49 8145/6905",
    "sg:postcode":"82276",
    "sg:province":"Bayern",
    "wof:name":"H. Hartl",
    "wof:placetype":"venue"
},
  "geometry": {"coordinates":[11.115397,48.199238],"type":"Point"}
}