{
  "type": "Feature",
  "properties": {
    "iso:country":"DE",
    "sg:address":"Eriagstr. 34",
    "sg:city":"Ingolstadt",
    "sg:postcode":"85053",
    "sg:province":"Bayern",
    "wof:name":"Raffineriegesellschaft Vohburg Ingolstadt Mbh",
    "wof:placetype":"venue"
},
  "geometry": {"coordinates":[11.4771547318,48.7495956421],"type":"Point"}
}