{
  "type": "Feature",
  "properties": {
    "iso:country":"DE",
    "sg:address":"Bismarckstr. 24",
    "sg:city":"Memmingen",
    "sg:phone":"+49 8331/74347",
    "sg:postcode":"87700",
    "sg:province":"Bayern",
    "wof:name":"Dr. Med. Erwin Kratzer",
    "wof:placetype":"venue"
},
  "geometry": {"coordinates":[10.1694412231,47.9837150574],"type":"Point"}
}