{
  "type": "Feature",
  "properties": {
    "iso:country":"DE",
    "sg:address":"Eisenacher Str. 7",
    "sg:city":"Schwetzingen",
    "sg:phone":"+49 6202/4445",
    "sg:postcode":"68723",
    "sg:province":"Baden-W\u00fcrttemberg",
    "wof:name":"Immoverwaltung Gmbh",
    "wof:placetype":"venue"
},
  "geometry": {"coordinates":[8.565952301,49.39270401],"type":"Point"}
}