{
  "type": "Feature",
  "properties": {
    "iso:country":"DE",
    "sg:address":"Am Schmiedebruch 15",
    "sg:city":"Meerbeck",
    "sg:phone":"+49 5721/2985",
    "sg:postcode":"31715",
    "sg:province":"Niedersachsen",
    "wof:name":"Friedrich Nolte",
    "wof:placetype":"venue"
},
  "geometry": {"coordinates":[9.1424694061,52.3433113098],"type":"Point"}
}