{
  "type": "Feature",
  "properties": {
    "iso:country":"DE",
    "sg:address":"Grillparzerstr. 34",
    "sg:city":"Hamburg",
    "sg:phone":"+49 40/22944694",
    "sg:postcode":"22085",
    "sg:province":"Hamburg",
    "wof:name":"Terrahe Und Bonert Rechtsanw\u00e4lte",
    "wof:placetype":"venue"
},
  "geometry": {"coordinates":[10.0172805786,53.5795478821],"type":"Point"}
}