{
  "type": "Feature",
  "properties": {
    "iso:country":"DE",
    "sg:address":"Pillham 2",
    "sg:city":"Ruhstorf",
    "sg:phone":"+49 8531/229",
    "sg:postcode":"94099",
    "sg:province":"Bayern",
    "wof:name":"G. Pimiskern Ingenieur",
    "wof:placetype":"venue"
},
  "geometry": {"coordinates":[13.3228416443,48.4516487122],"type":"Point"}
}