{
  "type": "Feature",
  "properties": {
    "iso:country":"DE",
    "sg:address":"Jeddeloher Damm 1",
    "sg:city":"Edewecht",
    "sg:phone":"+49 4405/5667",
    "sg:postcode":"26188",
    "sg:province":"Niedersachsen",
    "wof:name":"O. Von Aschwege",
    "wof:placetype":"venue"
},
  "geometry": {"coordinates":[8.0207395554,53.1215591431],"type":"Point"}
}