{
  "type": "Feature",
  "properties": {
    "iso:country":"DE",
    "sg:address":"Willst\u00e4tterstr. 7",
    "sg:city":"D\u00fcsseldorf",
    "sg:phone":"+49 211/53770",
    "sg:postcode":"40549",
    "sg:province":"Nordrhein-Westfalen",
    "wof:name":"Sigma System Audio-visuell Gmbh",
    "wof:placetype":"venue"
},
  "geometry": {"coordinates":[6.7134342194,51.2402572632],"type":"Point"}
}