{
  "type": "Feature",
  "properties": {
    "iso:country":"DE",
    "sg:address":"Frankfurter Str. 3a",
    "sg:city":"Braunschweig",
    "sg:phone":"+49 531/8863355",
    "sg:postcode":"38122",
    "sg:province":"Niedersachsen",
    "wof:name":"Mpp Studios Gmbh",
    "wof:placetype":"venue"
},
  "geometry": {"coordinates":[10.513874,52.256462],"type":"Point"}
}