{
  "type": "Feature",
  "properties": {
    "iso:country":"DE",
    "sg:address":"Juliuspromenade 46",
    "sg:city":"W\u00fcrzburg",
    "sg:phone":"+49 931/51182",
    "sg:postcode":"97070",
    "sg:province":"Bayern",
    "wof:name":"Dr. Med. W. Parussel",
    "wof:placetype":"venue"
},
  "geometry": {"coordinates":[9.9295806885,49.7966346741],"type":"Point"}
}