{
  "type": "Feature",
  "properties": {
    "iso:country":"DE",
    "sg:address":"Bahnhofstr. 17a",
    "sg:city":"Lehrte",
    "sg:phone":"+49 5132/825150",
    "sg:postcode":"31275",
    "sg:province":"Niedersachsen",
    "wof:name":"Fips Gmbh",
    "wof:placetype":"venue"
},
  "geometry": {"coordinates":[9.973701,52.375648],"type":"Point"}
}