{
  "type": "Feature",
  "properties": {
    "iso:country":"DE",
    "sg:address":"Ettaler Strasse 2",
    "sg:city":"Oberammergau",
    "sg:postcode":"82487",
    "sg:province":"Bayern",
    "wof:name":"Hotel Turmwirt In Oberammergau",
    "wof:placetype":"venue"
},
  "geometry": {"coordinates":[11.0653495789,47.5958900452],"type":"Point"}
}