{
  "type": "Feature",
  "properties": {
    "iso:country":"DE",
    "sg:address":"\u00d6lhafendamm 35",
    "sg:city":"Wilhelmshaven",
    "sg:phone":"+49 4421/305050",
    "sg:postcode":"26384",
    "sg:province":"Niedersachsen",
    "wof:name":"Vogelers Bayernhaus",
    "wof:placetype":"venue"
},
  "geometry": {"coordinates":[8.1357889175,53.531703949],"type":"Point"}
}