{
  "type": "Feature",
  "properties": {
    "iso:country":"DE",
    "sg:address":"S\u00fcrther Hauptstr. 190a",
    "sg:city":"K\u00f6ln",
    "sg:phone":"+49 2236/322188",
    "sg:postcode":"50999",
    "sg:province":"Nordrhein-Westfalen",
    "wof:name":"S. Albrecht Rechtsanwalt",
    "wof:placetype":"venue"
},
  "geometry": {"coordinates":[7.0188579559,50.8680534363],"type":"Point"}
}