{
  "type": "Feature",
  "properties": {
    "iso:country":"DE",
    "sg:address":"Bahnhofstr. 9-11",
    "sg:city":"Cloppenburg",
    "sg:phone":"+49 4471/92200",
    "sg:postcode":"49661",
    "sg:province":"Niedersachsen",
    "wof:name":"Georg Werrelmann Gro\u00df- U. Einzelhandel In Tex-",
    "wof:placetype":"venue"
},
  "geometry": {"coordinates":[8.0446023941,52.8454017639],"type":"Point"}
}