{
  "type": "Feature",
  "properties": {
    "iso:country":"DE",
    "sg:address":"Hainbundstr. 17",
    "sg:city":"G\u00f6ttingen",
    "sg:phone":"+49 551/41709",
    "sg:postcode":"37085",
    "sg:province":"Niedersachsen",
    "wof:name":"Arkana Verlag Tete B\u00f6ttger Rainer Wunderlich Gmbh",
    "wof:placetype":"venue"
},
  "geometry": {"coordinates":[9.9593343735,51.5387763977],"type":"Point"}
}