{
  "type": "Feature",
  "properties": {
    "iso:country":"DE",
    "sg:address":"Bergstr. 16",
    "sg:city":"Sinzheim",
    "sg:phone":"+49 7221/81694",
    "sg:postcode":"76547",
    "sg:province":"Baden-W\u00fcrttemberg",
    "wof:name":"Peter Steinel",
    "wof:placetype":"venue"
},
  "geometry": {"coordinates":[8.170457,48.763557],"type":"Point"}
}