{
  "type": "Feature",
  "properties": {
    "iso:country":"DE",
    "sg:address":"Schwarzwaldstr 2",
    "sg:city":"Ettenheim",
    "sg:phone":"+49 7822/896546",
    "sg:postcode":"77955",
    "sg:province":"Baden-W\u00fcrttemberg",
    "wof:name":"Zt-zerspanung",
    "wof:placetype":"venue"
},
  "geometry": {"coordinates":[7.809961,48.255932],"type":"Point"}
}