{
  "type": "Feature",
  "properties": {
    "iso:country":"DE",
    "sg:address":"Feldstr. 3",
    "sg:city":"M\u00fchlheim",
    "sg:postcode":"63165",
    "sg:province":"Hessen",
    "wof:name":"Tronje Otten Ohg",
    "wof:placetype":"venue"
},
  "geometry": {"coordinates":[8.8351612091,50.1240577698],"type":"Point"}
}