{
  "type": "Feature",
  "properties": {
    "iso:country":"DE",
    "sg:address":"Am Kurzen Holze 31",
    "sg:city":"Wolfenb\u00fcttel",
    "sg:phone":"+49 5331/71371",
    "sg:postcode":"38302",
    "sg:province":"Niedersachsen",
    "wof:name":"Helmut Ritterbusch Steuerberater",
    "wof:placetype":"venue"
},
  "geometry": {"coordinates":[10.5521087646,52.177066803],"type":"Point"}
}