{
  "type": "Feature",
  "properties": {
    "iso:country":"DE",
    "sg:address":"Julius-Brecht-Str. 7",
    "sg:city":"Freiburg",
    "sg:phone":"+49 761/484999",
    "sg:postcode":"79115",
    "sg:province":"Baden-W\u00fcrttemberg",
    "wof:name":"Manfred Els\u00e4sser Fotograf",
    "wof:placetype":"venue"
},
  "geometry": {"coordinates":[7.8192939758,47.9943618774],"type":"Point"}
}