{
  "type": "Feature",
  "properties": {
    "iso:country":"DE",
    "sg:address":"Odendorfer Weg 5",
    "sg:city":"Euskirchen",
    "sg:phone":"+49 2255/950909",
    "sg:postcode":"53881",
    "sg:province":"Nordrhein-Westfalen",
    "wof:name":"Optivers-versicherungs- Und Finanzoptimierung",
    "wof:placetype":"venue"
},
  "geometry": {"coordinates":[6.86416,50.638531],"type":"Point"}
}