{
  "type": "Feature",
  "properties": {
    "iso:country":"DE",
    "sg:address":"Lagerhausstr. 8",
    "sg:city":"Gr\u00fcnsfeld",
    "sg:phone":"+49 9346/95100",
    "sg:postcode":"97947",
    "sg:province":"Baden-W\u00fcrttemberg",
    "wof:name":"Raiffeisenbank B\u00fctthard- Gauk\u00f6nigshofen Eg",
    "wof:placetype":"venue"
},
  "geometry": {"coordinates":[9.78731,49.594761],"type":"Point"}
}