{
  "type": "Feature",
  "properties": {
    "iso:country":"DE",
    "sg:address":"Hansastr. 17",
    "sg:city":"Essen",
    "sg:phone":"+49 201/511136",
    "sg:postcode":"45276",
    "sg:province":"Nordrhein-Westfalen",
    "wof:name":"F. Kappert",
    "wof:placetype":"venue"
},
  "geometry": {"coordinates":[7.0756969452,51.4470748901],"type":"Point"}
}