{
  "type": "Feature",
  "properties": {
    "iso:country":"DE",
    "sg:address":"Warschauer Str. 6",
    "sg:city":"Berlin",
    "sg:phone":"+49 30/2946828",
    "sg:postcode":"10243",
    "sg:province":"Berlin",
    "wof:name":"Barbara Ankiewicz",
    "wof:placetype":"venue"
},
  "geometry": {"coordinates":[13.4530153275,52.5144424438],"type":"Point"}
}