{
  "type": "Feature",
  "properties": {
    "iso:country":"DE",
    "sg:address":"Rabensham 1",
    "sg:city":"Triftern",
    "sg:phone":"+49 8574/822",
    "sg:postcode":"84371",
    "sg:province":"Bayern",
    "wof:name":"K. Pechaigner",
    "wof:placetype":"venue"
},
  "geometry": {"coordinates":[12.955848,48.360958],"type":"Point"}
}