{
  "type": "Feature",
  "properties": {
    "iso:country":"DE",
    "sg:address":"Schlachthausstr. 10",
    "sg:city":"Amberg",
    "sg:phone":"+49 9621/22447",
    "sg:postcode":"92224",
    "sg:province":"Bayern",
    "wof:name":"H\u00f6nle Verwaltungs Gmbh",
    "wof:placetype":"venue"
},
  "geometry": {"coordinates":[11.864982,49.442986],"type":"Point"}
}