{
  "type": "Feature",
  "properties": {
    "iso:country":"DE",
    "sg:address":"Am Stadthafen 40",
    "sg:city":"Essen",
    "sg:phone":"+49 201/834550",
    "sg:postcode":"45356",
    "sg:province":"Nordrhein-Westfalen",
    "wof:name":"Ralf Teichmann Gmbh",
    "wof:placetype":"venue"
},
  "geometry": {"coordinates":[6.964483,51.499126],"type":"Point"}
}