{
  "type": "Feature",
  "properties": {
    "iso:country":"DE",
    "sg:address":"G\u00fcntzelstr. 14",
    "sg:city":"Berlin",
    "sg:phone":"+49 30/868860",
    "sg:postcode":"10717",
    "sg:province":"Berlin",
    "wof:name":"Queens Hotel Berlin",
    "wof:placetype":"venue"
},
  "geometry": {"coordinates":[13.329120636,52.4910240173],"type":"Point"}
}