{
  "type": "Feature",
  "properties": {
    "iso:country":"DE",
    "sg:address":"Innsbrucker Str. 2-4",
    "sg:city":"Mainz-Kostheim",
    "sg:phone":"+49 6134/61598",
    "sg:postcode":"55246",
    "sg:province":"Hessen",
    "wof:name":"Konditorei Und B\u00e4ckerei Schmitt Gmbh",
    "wof:placetype":"venue"
},
  "geometry": {"coordinates":[8.292556,50.006615],"type":"Point"}
}