{
  "type": "Feature",
  "properties": {
    "iso:country":"DE",
    "sg:address":"Landstr. 31",
    "sg:city":"Gaggenau",
    "sg:phone":"+49 7224/3156",
    "sg:postcode":"76571",
    "sg:province":"Baden-W\u00fcrttemberg",
    "wof:name":"Dieter Pierow Heilpraktiker",
    "wof:placetype":"venue"
},
  "geometry": {"coordinates":[8.3444261551,48.7879905701],"type":"Point"}
}