{
  "type": "Feature",
  "properties": {
    "iso:country":"DE",
    "sg:address":"Stolkgasse 25-45",
    "sg:city":"K\u00f6ln",
    "sg:postcode":"50667",
    "sg:province":"Nordrhein-Westfalen",
    "wof:name":"Imt Media Trading Und Verlags Verwaltungs Gmbh",
    "wof:placetype":"venue"
},
  "geometry": {"coordinates":[6.953528,50.944115],"type":"Point"}
}