{
  "type": "Feature",
  "properties": {
    "iso:country":"DE",
    "sg:address":"Roonstr. 69",
    "sg:city":"Oberhausen",
    "sg:phone":"+49 208/842207",
    "sg:postcode":"46049",
    "sg:province":"Nordrhein-Westfalen",
    "wof:name":"Ingenieurb\u00fcro H. Lindermann Gmbh",
    "wof:placetype":"venue"
},
  "geometry": {"coordinates":[6.839042,51.468075],"type":"Point"}
}