{
  "type": "Feature",
  "properties": {
    "iso:country":"DE",
    "sg:address":"Homberger Str. 142",
    "sg:city":"Bad Hersfeld",
    "sg:phone":"+49 6621/919315",
    "sg:postcode":"36251",
    "sg:province":"Hessen",
    "wof:name":"Okay-kauf",
    "wof:placetype":"venue"
},
  "geometry": {"coordinates":[9.6878728867,50.8801193237],"type":"Point"}
}