{
  "type": "Feature",
  "properties": {
    "iso:country":"DE",
    "sg:address":"Carl-Christ-Str. 2a",
    "sg:city":"Buxtehude",
    "sg:postcode":"21614",
    "sg:province":"Niedersachsen",
    "wof:name":"Marina Twielenfleth Gmbh & Co. Kg",
    "wof:placetype":"venue"
},
  "geometry": {"coordinates":[9.6837902069,53.4691848755],"type":"Point"}
}