{
  "type": "Feature",
  "properties": {
    "iso:country":"DE",
    "sg:address":"Am Waldschl\u00f6\u00dfchen 4",
    "sg:city":"Langelsheim",
    "sg:phone":"+49 5325/591234",
    "sg:postcode":"38685",
    "sg:province":"Niedersachsen",
    "wof:name":"Ambulanter Pflegedienst Lauenthal Inhaber Stefan",
    "wof:placetype":"venue"
},
  "geometry": {"coordinates":[10.277879,51.861092],"type":"Point"}
}