{
  "type": "Feature",
  "properties": {
    "iso:country":"DE",
    "sg:address":"Auf der Winzerer H\u00f6he 27a",
    "sg:city":"Regensburg",
    "sg:phone":"+49 941/86670",
    "sg:postcode":"93059",
    "sg:province":"Bayern",
    "wof:name":"Rosenthal-roth",
    "wof:placetype":"venue"
},
  "geometry": {"coordinates":[12.0903110504,49.0328826904],"type":"Point"}
}