{
  "type": "Feature",
  "properties": {
    "iso:country":"DE",
    "sg:address":"Klosterstr. 35",
    "sg:city":"Langenargen",
    "sg:phone":"+49 7543/1270",
    "sg:postcode":"88085",
    "sg:province":"Baden-W\u00fcrttemberg",
    "wof:name":"Sozialstation St. Martin",
    "wof:placetype":"venue"
},
  "geometry": {"coordinates":[9.538715,47.598286],"type":"Point"}
}