{
  "type": "Feature",
  "properties": {
    "iso:country":"DE",
    "sg:address":"Zavelsteiner Str.",
    "sg:city":"Bad Teinach-Zavelstein",
    "sg:phone":"+49 7053/8831",
    "sg:postcode":"75385",
    "sg:province":"Baden-W\u00fcrttemberg",
    "wof:name":"Gastst\u00e4tte Schwarzwaldverein Calw",
    "wof:placetype":"venue"
},
  "geometry": {"coordinates":[8.6803655624,48.696269989],"type":"Point"}
}