{
  "type": "Feature",
  "properties": {
    "iso:country":"DE",
    "sg:address":"Breitstr. 54",
    "sg:city":"Pegau",
    "sg:phone":"+49 34296/72018",
    "sg:postcode":"04523",
    "sg:province":"Sachsen",
    "wof:name":"Christine Becker Rechtsanw\u00e4ltin",
    "wof:placetype":"venue"
},
  "geometry": {"coordinates":[12.2486953735,51.1677322388],"type":"Point"}
}