{
  "type": "Feature",
  "properties": {
    "iso:country":"DE",
    "sg:address":"Bayreuther Str. 31",
    "sg:city":"Dresden",
    "sg:phone":"+49 351/3100000",
    "sg:postcode":"01187",
    "sg:province":"Sachsen",
    "wof:name":"Triat Hausverwaltungs Gmbh",
    "wof:placetype":"venue"
},
  "geometry": {"coordinates":[13.720998764,51.0325126648],"type":"Point"}
}