{
  "type": "Feature",
  "properties": {
    "iso:country":"DE",
    "sg:address":"Ulrichstr. 77 b",
    "sg:city":"Alpen",
    "sg:phone":"+49 2802/6810",
    "sg:postcode":"46519",
    "sg:province":"Nordrhein-Westfalen",
    "wof:name":"Johannes Polm",
    "wof:placetype":"venue"
},
  "geometry": {"coordinates":[6.503037,51.582531],"type":"Point"}
}