{
  "type": "Feature",
  "properties": {
    "iso:country":"DE",
    "sg:address":"M\u00fchlenstr. 24",
    "sg:city":"Schleiz",
    "sg:phone":"+49 3663/403518",
    "sg:postcode":"07907",
    "sg:province":"Th\u00fcringen",
    "wof:name":"Uta Keller",
    "wof:placetype":"venue"
},
  "geometry": {"coordinates":[11.730219841,50.5711402893],"type":"Point"}
}