{
  "type": "Feature",
  "properties": {
    "iso:country":"DE",
    "sg:address":"Ellmendinger Str. 23",
    "sg:city":"Karlsruhe",
    "sg:phone":"+49 721/943920",
    "sg:postcode":"76227",
    "sg:province":"Baden-W\u00fcrttemberg",
    "wof:name":"Roland Eberhardt Steuerberater",
    "wof:placetype":"venue"
},
  "geometry": {"coordinates":[8.4585161209,48.9938774109],"type":"Point"}
}