{
  "type": "Feature",
  "properties": {
    "iso:country":"DE",
    "sg:address":"Wiesbadener Str. 37",
    "sg:city":"Taunusstein",
    "sg:phone":"+49 6128/934832",
    "sg:postcode":"65232",
    "sg:province":"Hessen",
    "wof:name":"Hans-peter Trottner",
    "wof:placetype":"venue"
},
  "geometry": {"coordinates":[8.160572052,50.1401367188],"type":"Point"}
}