{
  "type": "Feature",
  "properties": {
    "iso:country":"DE",
    "sg:address":"Flensbergstr. 10",
    "sg:city":"Twist",
    "sg:phone":"+49 5936/904434",
    "sg:postcode":"49767",
    "sg:province":"Niedersachsen",
    "wof:name":"Twister Rats-apotheke Apotheker Edmund Wermes E. K.",
    "wof:placetype":"venue"
},
  "geometry": {"coordinates":[7.095507,52.646908],"type":"Point"}
}