{
  "type": "Feature",
  "properties": {
    "iso:country":"DE",
    "sg:address":"Amtsstr. 6",
    "sg:city":"Rodenberg",
    "sg:phone":"+49 5723/74407",
    "sg:postcode":"31552",
    "sg:province":"Niedersachsen",
    "wof:name":"M. Kretschmann",
    "wof:placetype":"venue"
},
  "geometry": {"coordinates":[9.355405,52.312401],"type":"Point"}
}