{
  "type": "Feature",
  "properties": {
    "iso:country":"DE",
    "sg:address":"S\u00fcderstr. 20",
    "sg:city":"Kronprinzenkoog",
    "sg:phone":"+49 4851/3201",
    "sg:postcode":"25709",
    "sg:province":"Schleswig-Holstein",
    "wof:name":"Biohof Rolf Hell",
    "wof:placetype":"venue"
},
  "geometry": {"coordinates":[8.986385,53.94104],"type":"Point"}
}