{
  "type": "Feature",
  "properties": {
    "iso:country":"DE",
    "sg:address":"Frauensteinstr. 8",
    "sg:city":"Frankfurt",
    "sg:phone":"+49 69/554026",
    "sg:postcode":"60322",
    "sg:province":"Hessen",
    "wof:name":"G\u00e4stehaus Stella",
    "wof:placetype":"venue"
},
  "geometry": {"coordinates":[8.6800613403,50.1310806274],"type":"Point"}
}