{
  "type": "Feature",
  "properties": {
    "iso:country":"DE",
    "sg:address":"Am Bergwald 41",
    "sg:city":"Stuttgart",
    "sg:phone":"+49 711/4201880",
    "sg:postcode":"70329",
    "sg:province":"Baden-W\u00fcrttemberg",
    "wof:name":"Ernst Prechter",
    "wof:placetype":"venue"
},
  "geometry": {"coordinates":[9.2437801361,48.7571296692],"type":"Point"}
}