{
  "type": "Feature",
  "properties": {
    "iso:country":"DE",
    "sg:address":"Thiersheimer Str.",
    "sg:city":"Arzberg",
    "sg:phone":"+49 9233/5906",
    "sg:postcode":"95659",
    "sg:province":"Bayern",
    "wof:name":"Wertstoffhof",
    "wof:placetype":"venue"
},
  "geometry": {"coordinates":[12.183538,50.058392],"type":"Point"}
}