{
  "type": "Feature",
  "properties": {
    "iso:country":"DE",
    "sg:address":"Koschendorfer Str. 37",
    "sg:city":"Kolkwitz",
    "sg:phone":"+49 355/287377",
    "sg:postcode":"03099",
    "sg:province":"Brandenburg",
    "wof:name":"G. Mewes Steuerberater",
    "wof:placetype":"venue"
},
  "geometry": {"coordinates":[14.249704361,51.7370147705],"type":"Point"}
}