{
  "type": "Feature",
  "properties": {
    "iso:country":"DE",
    "sg:address":"Weihersm\u00fchle 1",
    "sg:city":"Zapfendorf",
    "sg:postcode":"96199",
    "sg:province":"Bayern",
    "wof:name":"Dietmar Dierauf",
    "wof:placetype":"venue"
},
  "geometry": {"coordinates":[10.932383,50.019951],"type":"Point"}
}