{
  "type": "Feature",
  "properties": {
    "iso:country":"DE",
    "sg:address":"Lechtenbergweg 25",
    "sg:city":"M\u00fcnster",
    "sg:phone":"+49 251/784353",
    "sg:postcode":"48165",
    "sg:province":"Nordrhein-Westfalen",
    "wof:name":"Michael Hoppermann",
    "wof:placetype":"venue"
},
  "geometry": {"coordinates":[7.638509,51.922173],"type":"Point"}
}