{
  "type": "Feature",
  "properties": {
    "iso:country":"DE",
    "sg:address":"Hauptstr. 50",
    "sg:city":"Beckum",
    "sg:phone":"+49 2525/1756",
    "sg:postcode":"59269",
    "sg:province":"Nordrhein-Westfalen",
    "wof:name":"A. Liekenbr\u00f6cker",
    "wof:placetype":"venue"
},
  "geometry": {"coordinates":[8.03108,51.787312],"type":"Point"}
}