{
  "type": "Feature",
  "properties": {
    "iso:country":"DE",
    "sg:address":"St. Ottilier Weg 69",
    "sg:city":"Helsa",
    "sg:phone":"+49 5602/1665",
    "sg:postcode":"34298",
    "sg:province":"Hessen",
    "wof:name":"Manfred Br\u00fcbach",
    "wof:placetype":"venue"
},
  "geometry": {"coordinates":[9.656543,51.225887],"type":"Point"}
}