{
  "type": "Feature",
  "properties": {
    "iso:country":"DE",
    "sg:address":"Lipschitzallee 63",
    "sg:city":"Berlin",
    "sg:phone":"+49 30/6034217",
    "sg:postcode":"12353",
    "sg:province":"Berlin",
    "wof:name":"Dieter Jacobi Ingenieur",
    "wof:placetype":"venue"
},
  "geometry": {"coordinates":[13.4647264481,52.4253463745],"type":"Point"}
}