{
  "type": "Feature",
  "properties": {
    "iso:country":"DE",
    "sg:address":"Kirchbachstr. 53",
    "sg:city":"Bremen",
    "sg:phone":"+49 421/444917",
    "sg:postcode":"28211",
    "sg:province":"Bremen",
    "wof:name":"Ulrich Zacher Architekt",
    "wof:placetype":"venue"
},
  "geometry": {"coordinates":[8.854824,53.076866],"type":"Point"}
}