{
  "type": "Feature",
  "properties": {
    "iso:country":"DE",
    "sg:address":"Ludwigstr. 15",
    "sg:city":"Rudolstadt",
    "sg:phone":"+49 3672/422722",
    "sg:postcode":"07407",
    "sg:province":"Th\u00fcringen",
    "wof:name":"R. Wedemann",
    "wof:placetype":"venue"
},
  "geometry": {"coordinates":[11.34364,50.721401],"type":"Point"}
}