{
  "type": "Feature",
  "properties": {
    "iso:country":"DE",
    "sg:address":"Mailar 12",
    "sg:city":"Schmallenberg",
    "sg:phone":"+49 2971/86558",
    "sg:postcode":"57392",
    "sg:province":"Nordrhein-Westfalen",
    "wof:name":"Friedhelm Schmitte",
    "wof:placetype":"venue"
},
  "geometry": {"coordinates":[8.250473,51.207664],"type":"Point"}
}