{
  "type": "Feature",
  "properties": {
    "iso:country":"DE",
    "sg:address":"Waldburgstr. 1",
    "sg:city":"B\u00f6blingen",
    "sg:phone":"+49 7031/223491",
    "sg:postcode":"71032",
    "sg:province":"Baden-W\u00fcrttemberg",
    "wof:name":"Ev. Heimstiftung E. V.",
    "wof:placetype":"venue"
},
  "geometry": {"coordinates":[9.019707,48.686481],"type":"Point"}
}