{
  "type": "Feature",
  "properties": {
    "iso:country":"DE",
    "sg:address":"Georgstr. 17",
    "sg:city":"Bremerhaven",
    "sg:phone":"+49 471/21964",
    "sg:postcode":"27570",
    "sg:province":"Bremen",
    "wof:name":"Parf\u00fcmerie Kr\u00f6mer Gmbh",
    "wof:placetype":"venue"
},
  "geometry": {"coordinates":[8.589284,53.53355],"type":"Point"}
}