{
  "type": "Feature",
  "properties": {
    "iso:country":"DE",
    "sg:address":"An der Stadtkirche 17-19",
    "sg:city":"Darmstadt",
    "sg:phone":"+49 6151/20707",
    "sg:postcode":"64283",
    "sg:province":"Hessen",
    "wof:name":"Zoo-haus Lindenstruth",
    "wof:placetype":"venue"
},
  "geometry": {"coordinates":[8.655928,49.871094],"type":"Point"}
}