{
  "type": "Feature",
  "properties": {
    "iso:country":"DE",
    "sg:address":"Siemensstr. 1-5",
    "sg:city":"Pulheim",
    "sg:phone":"+49 2238/7017",
    "sg:postcode":"50259",
    "sg:province":"Nordrhein-Westfalen",
    "wof:name":"Stohrer Druck Gmbh",
    "wof:placetype":"venue"
},
  "geometry": {"coordinates":[6.8182067871,50.9915542603],"type":"Point"}
}