{
  "type": "Feature",
  "properties": {
    "iso:country":"DE",
    "sg:address":"Geyersche Str. 13",
    "sg:city":"Thum",
    "sg:postcode":"09419",
    "sg:province":"Sachsen",
    "wof:name":"Erhard Haaase",
    "wof:placetype":"venue"
},
  "geometry": {"coordinates":[12.926632,50.663551],"type":"Point"}
}