{
  "type": "Feature",
  "properties": {
    "iso:country":"DE",
    "sg:address":"Oberspreestr. 57 g",
    "sg:city":"Berlin",
    "sg:phone":"+49 30/6716781",
    "sg:postcode":"12439",
    "sg:province":"Berlin",
    "wof:name":"Gottfried Riedel",
    "wof:placetype":"venue"
},
  "geometry": {"coordinates":[13.51329,52.455505],"type":"Point"}
}