{
  "type": "Feature",
  "properties": {
    "iso:country":"DE",
    "sg:address":"Vellwigstr. 8",
    "sg:city":"Herne",
    "sg:postcode":"44628",
    "sg:province":"Nordrhein-Westfalen",
    "wof:name":"Evangelisch-lutherischer Gebetsverein B\u00f6rnig",
    "wof:placetype":"venue"
},
  "geometry": {"coordinates":[7.2664937973,51.549446106],"type":"Point"}
}