{
  "type": "Feature",
  "properties": {
    "iso:country":"DE",
    "sg:address":"Am M\u00fchlgraben 7",
    "sg:city":"Erding",
    "sg:phone":"+49 8122/85859",
    "sg:postcode":"85435",
    "sg:province":"Bayern",
    "wof:name":"Cafe Cest La Vie",
    "wof:placetype":"venue"
},
  "geometry": {"coordinates":[11.910164,48.306366],"type":"Point"}
}