{
  "type": "Feature",
  "properties": {
    "iso:country":"DE",
    "sg:address":"Uhlandstrasse 56",
    "sg:city":"Bochum",
    "sg:phone":"+49 234/5844596",
    "sg:postcode":"44791",
    "sg:province":"Nordrhein-Westfalen",
    "wof:name":"Jarod Multimedia-agentur - Kommunikations-design",
    "wof:placetype":"venue"
},
  "geometry": {"coordinates":[7.220138,51.490803],"type":"Point"}
}