{
  "type": "Feature",
  "properties": {
    "iso:country":"DE",
    "sg:address":"Hellerweg 15",
    "sg:city":"Esslingen",
    "sg:phone":"+49 711/356805",
    "sg:postcode":"73728",
    "sg:province":"Baden-W\u00fcrttemberg",
    "wof:name":"H. Fuchslocher",
    "wof:placetype":"venue"
},
  "geometry": {"coordinates":[9.3026800156,48.7499198914],"type":"Point"}
}