{
  "type": "Feature",
  "properties": {
    "iso:country":"DE",
    "sg:address":"Lichtenberger Str. 40-42",
    "sg:city":"Rheinau",
    "sg:postcode":"77866",
    "sg:province":"Baden-W\u00fcrttemberg",
    "wof:name":"Poddington Peas Gmbh",
    "wof:placetype":"venue"
},
  "geometry": {"coordinates":[7.9352087975,48.6540145874],"type":"Point"}
}