{
  "type": "Feature",
  "properties": {
    "iso:country":"DE",
    "sg:address":"Kirchenpfad 5",
    "sg:city":"Pluwig",
    "sg:phone":"+49 6588/7100",
    "sg:postcode":"54316",
    "sg:province":"Rheinland-Pfalz",
    "wof:name":"Gebr. Lambertz",
    "wof:placetype":"venue"
},
  "geometry": {"coordinates":[6.717732,49.67971],"type":"Point"}
}