{
  "type": "Feature",
  "properties": {
    "iso:country":"DE",
    "sg:address":"Kirchweg 57",
    "sg:city":"Barver",
    "sg:phone":"+49 5448/266",
    "sg:postcode":"49453",
    "sg:province":"Niedersachsen",
    "wof:name":"Ev. Pfarramt Barver",
    "wof:placetype":"venue"
},
  "geometry": {"coordinates":[8.595375061,52.6212348938],"type":"Point"}
}