{
  "type": "Feature",
  "properties": {
    "iso:country":"DE",
    "sg:address":"Bahnstr. 11",
    "sg:city":"Baesweiler",
    "sg:phone":"+49 2401/51451",
    "sg:postcode":"52499",
    "sg:province":"Nordrhein-Westfalen",
    "wof:name":"Heinz Schr\u00f6ders",
    "wof:placetype":"venue"
},
  "geometry": {"coordinates":[6.200321,50.922298],"type":"Point"}
}