{
  "type": "Feature",
  "properties": {
    "iso:country":"DE",
    "sg:address":"Wandalenweg 8-10",
    "sg:city":"Hamburg",
    "sg:phone":"+49 40/236040",
    "sg:postcode":"20097",
    "sg:province":"Hamburg",
    "wof:name":"Creditreform Hamburg",
    "wof:placetype":"venue"
},
  "geometry": {"coordinates":[10.023024,53.549587],"type":"Point"}
}