{
  "type": "Feature",
  "properties": {
    "iso:country":"DE",
    "sg:address":"Engesserstr. 6",
    "sg:city":"Freiburg",
    "sg:phone":"+49 761/52088",
    "sg:postcode":"79108",
    "sg:province":"Baden-W\u00fcrttemberg",
    "wof:name":"Jakob Glaser Gmbh & Co. Kg",
    "wof:placetype":"venue"
},
  "geometry": {"coordinates":[7.8473191261,48.0210227966],"type":"Point"}
}