{
  "type": "Feature",
  "properties": {
    "iso:country":"DE",
    "sg:address":"Oberstr. 22",
    "sg:city":"Krefeld",
    "sg:postcode":"47829",
    "sg:province":"Nordrhein-Westfalen",
    "wof:name":"Fashion Line Mode Gmbh",
    "wof:placetype":"venue"
},
  "geometry": {"coordinates":[6.6496090889,51.3528289795],"type":"Point"}
}