{
  "type": "Feature",
  "properties": {
    "iso:country":"DE",
    "sg:address":"Marktstr. 34",
    "sg:city":"Neckarsulm",
    "sg:phone":"+49 7132/922244",
    "sg:postcode":"74172",
    "sg:province":"Baden-W\u00fcrttemberg",
    "wof:name":"Herbert Dech Rechtsanwalt",
    "wof:placetype":"venue"
},
  "geometry": {"coordinates":[9.22544384,49.1927337646],"type":"Point"}
}