{
  "type": "Feature",
  "properties": {
    "iso:country":"DE",
    "sg:address":"Goseriede 4",
    "sg:city":"Hannover",
    "sg:postcode":"30159",
    "sg:province":"Niedersachsen",
    "wof:name":"Cyberhub Ag",
    "wof:placetype":"venue"
},
  "geometry": {"coordinates":[9.7323951721,52.3772773743],"type":"Point"}
}