{
  "type": "Feature",
  "properties": {
    "iso:country":"DE",
    "sg:address":"Franklebener Str 5",
    "sg:city":"Spergau",
    "sg:phone":"+49 3462/80273",
    "sg:postcode":"06237",
    "sg:province":"Sachsen-Anhalt",
    "wof:name":"Metallbau Scheffler",
    "wof:placetype":"venue"
},
  "geometry": {"coordinates":[12.064779,51.299618],"type":"Point"}
}