{
  "type": "Feature",
  "properties": {
    "iso:country":"DE",
    "sg:address":"G\u00fcnzburger Str. 71",
    "sg:city":"Gundelfingen",
    "sg:phone":"+49 9073/8080",
    "sg:postcode":"89423",
    "sg:province":"Bayern",
    "wof:name":"Hildenbrand-bekleidungs Gmbh",
    "wof:placetype":"venue"
},
  "geometry": {"coordinates":[10.3674945831,48.5397758484],"type":"Point"}
}