{
  "type": "Feature",
  "properties": {
    "iso:country":"DE",
    "sg:address":"Auf der H\u00fctte 5",
    "sg:city":"Schmallenberg",
    "sg:phone":"+49 2977/351",
    "sg:postcode":"57392",
    "sg:province":"Nordrhein-Westfalen",
    "wof:name":"Wilhelm Adelmann Verlag",
    "wof:placetype":"venue"
},
  "geometry": {"coordinates":[8.3939657211,51.2401618958],"type":"Point"}
}