{
  "type": "Feature",
  "properties": {
    "iso:country":"DE",
    "sg:address":"Memelstr. 8",
    "sg:city":"Bottrop",
    "sg:phone":"+49 2041/730154",
    "sg:postcode":"46238",
    "sg:province":"Nordrhein-Westfalen",
    "wof:name":"Petra Skowronek",
    "wof:placetype":"venue"
},
  "geometry": {"coordinates":[6.944942,51.537262],"type":"Point"}
}