{
  "type": "Feature",
  "properties": {
    "iso:country":"DE",
    "sg:address":"\u00dcblherstr. 2",
    "sg:city":"Kempten",
    "sg:phone":"+49 831/21418",
    "sg:postcode":"87435",
    "sg:province":"Bayern",
    "wof:name":"Dr. Elmar Schraudy Tierarzt",
    "wof:placetype":"venue"
},
  "geometry": {"coordinates":[10.307970047,47.7161712646],"type":"Point"}
}