{
  "type": "Feature",
  "properties": {
    "iso:country":"DE",
    "sg:address":"Auf den Schrederwiesen 23",
    "sg:city":"M\u00fcnchen",
    "sg:phone":"+49 89/1502628",
    "sg:postcode":"80995",
    "sg:province":"Bayern",
    "wof:name":"Impex-elektro Schuster",
    "wof:placetype":"venue"
},
  "geometry": {"coordinates":[11.4973077774,48.1987495422],"type":"Point"}
}