{
  "type": "Feature",
  "properties": {
    "iso:country":"DE",
    "sg:address":"Kammerer Str. 11",
    "sg:city":"Fahrenzhausen",
    "sg:phone":"+49 8137/539954",
    "sg:postcode":"85777",
    "sg:province":"Bayern",
    "wof:name":"Gastst\u00e4tte Wirtshaus Inh. Franz Fund",
    "wof:placetype":"venue"
},
  "geometry": {"coordinates":[11.5403003693,48.3818588257],"type":"Point"}
}