{
  "type": "Feature",
  "properties": {
    "iso:country":"DE",
    "sg:address":"Bernardstr. 19",
    "sg:city":"Offenbach",
    "sg:phone":"+49 69/816008",
    "sg:postcode":"63067",
    "sg:province":"Hessen",
    "wof:name":"Itz",
    "wof:placetype":"venue"
},
  "geometry": {"coordinates":[8.7553796768,50.1080169678],"type":"Point"}
}