{
  "type": "Feature",
  "properties": {
    "iso:country":"DE",
    "sg:address":"Bruchen 1",
    "sg:city":"Birken-Honigsessen",
    "sg:phone":"+49 2294/493",
    "sg:postcode":"57587",
    "sg:province":"Rheinland-Pfalz",
    "wof:name":"Alois B\u00e4hner",
    "wof:placetype":"venue"
},
  "geometry": {"coordinates":[7.724324,50.83812],"type":"Point"}
}