{
  "type": "Feature",
  "properties": {
    "iso:country":"DE",
    "sg:address":"Brunnenstr. 8",
    "sg:city":"Kirschweiler",
    "sg:phone":"+49 6781/31111",
    "sg:postcode":"55743",
    "sg:province":"Rheinland-Pfalz",
    "wof:name":"H. Doll",
    "wof:placetype":"venue"
},
  "geometry": {"coordinates":[7.23889,49.75404],"type":"Point"}
}