{
  "type": "Feature",
  "properties": {
    "iso:country":"DE",
    "sg:address":"Karl-Ehmann-Str. 27",
    "sg:city":"Schelklingen",
    "sg:phone":"+49 7384/585",
    "sg:postcode":"89601",
    "sg:province":"Baden-W\u00fcrttemberg",
    "wof:name":"Xaver Sontheimer",
    "wof:placetype":"venue"
},
  "geometry": {"coordinates":[9.6454572678,48.3960113525],"type":"Point"}
}