{
  "type": "Feature",
  "properties": {
    "iso:country":"DE",
    "sg:address":"Winzler Str. 56",
    "sg:city":"Pirmasens",
    "sg:phone":"+49 6331/75596",
    "sg:postcode":"66955",
    "sg:province":"Rheinland-Pfalz",
    "wof:name":"Erwin Martz",
    "wof:placetype":"venue"
},
  "geometry": {"coordinates":[7.6016569138,49.1968269348],"type":"Point"}
}