{
  "type": "Feature",
  "properties": {
    "iso:country":"DE",
    "sg:address":"Von-Moeller-Str. 9",
    "sg:city":"Bad Oeynhausen",
    "sg:postcode":"32545",
    "sg:province":"Nordrhein-Westfalen",
    "wof:name":"Stadtb\u00fccherei Bad Oeynhausen Hauptstelle",
    "wof:placetype":"venue"
},
  "geometry": {"coordinates":[8.801019,52.20248],"type":"Point"}
}