{
  "type": "Feature",
  "properties": {
    "iso:country":"DE",
    "sg:address":"Feldpfad 86",
    "sg:city":"Norden",
    "sg:phone":"+49 4931/5533",
    "sg:postcode":"26506",
    "sg:province":"Niedersachsen",
    "wof:name":"Elly Dehne",
    "wof:placetype":"venue"
},
  "geometry": {"coordinates":[7.1923317909,53.5945053101],"type":"Point"}
}