{
  "type": "Feature",
  "properties": {
    "iso:country":"DE",
    "sg:address":"Schwalbenweg 1",
    "sg:city":"Peine",
    "sg:phone":"+49 5171/82407",
    "sg:postcode":"31226",
    "sg:province":"Niedersachsen",
    "wof:name":"Gef\u00c4ller Elektrotechnik Gmbh",
    "wof:placetype":"venue"
},
  "geometry": {"coordinates":[10.269957,52.294731],"type":"Point"}
}