{
  "type": "Feature",
  "properties": {
    "iso:country":"DE",
    "sg:address":"Eichenplatz 5",
    "sg:city":"K\u00f6nigsbrunn",
    "sg:phone":"+49 8231/4246",
    "sg:postcode":"86343",
    "sg:province":"Bayern",
    "wof:name":"T. Linder Heissmangel",
    "wof:placetype":"venue"
},
  "geometry": {"coordinates":[10.895731926,48.2552146912],"type":"Point"}
}