{
  "type": "Feature",
  "properties": {
    "iso:country":"DE",
    "sg:address":"Sengerweg 11",
    "sg:city":"K\u00f6ln",
    "sg:postcode":"51107",
    "sg:province":"Nordrhein-Westfalen",
    "wof:name":"Schluer Immobilien Service Gmbh",
    "wof:placetype":"venue"
},
  "geometry": {"coordinates":[7.07655,50.923134],"type":"Point"}
}