{
  "type": "Feature",
  "properties": {
    "iso:country":"DE",
    "sg:address":"Schillerstr. 21",
    "sg:city":"Kirchheim",
    "sg:phone":"+49 7143/33710",
    "sg:postcode":"74366",
    "sg:province":"Baden-W\u00fcrttemberg",
    "wof:name":"H. Hoff",
    "wof:placetype":"venue"
},
  "geometry": {"coordinates":[9.147948,49.039448],"type":"Point"}
}