{
  "type": "Feature",
  "properties": {
    "iso:country":"DE",
    "sg:address":"Clara-Zetkin-Str. 3",
    "sg:city":"Birkenwerder",
    "sg:phone":"+49 3303/402563",
    "sg:postcode":"16547",
    "sg:province":"Brandenburg",
    "wof:name":"M. Ziemann",
    "wof:placetype":"venue"
},
  "geometry": {"coordinates":[13.284515,52.688351],"type":"Point"}
}