{
  "type": "Feature",
  "properties": {
    "iso:country":"DE",
    "sg:address":"K\u00f6lner Str. 343a",
    "sg:city":"Bergneustadt",
    "sg:phone":"+49 2261/45527",
    "sg:postcode":"51702",
    "sg:province":"Nordrhein-Westfalen",
    "wof:name":"Artemis",
    "wof:placetype":"venue"
},
  "geometry": {"coordinates":[7.6652231216,51.0227203369],"type":"Point"}
}