{
  "type": "Feature",
  "properties": {
    "iso:country":"DE",
    "sg:address":"Gewerbestr. 1-5",
    "sg:city":"Pasewalk",
    "sg:phone":"+49 4939/7320530",
    "sg:postcode":"17309",
    "sg:province":"Mecklenburg-Vorpommern",
    "wof:name":"M\u00dchlenback Gmbh - B\u00c4ckerei - Konditorei",
    "wof:placetype":"venue"
},
  "geometry": {"coordinates":[14.00695,53.51524],"type":"Point"}
}