{
  "type": "Feature",
  "properties": {
    "iso:country":"DE",
    "sg:address":"Ockenheimer Str. 10",
    "sg:city":"Gau-Algesheim",
    "sg:phone":"+49 6725/2462",
    "sg:postcode":"55435",
    "sg:province":"Rheinland-Pfalz",
    "wof:name":"Kl\u00f6tzchen",
    "wof:placetype":"venue"
},
  "geometry": {"coordinates":[8.012736,49.959084],"type":"Point"}
}