{
  "type": "Feature",
  "properties": {
    "iso:country":"DE",
    "sg:address":"Schwarzh\u00f6ring 14",
    "sg:city":"Schwarzh\u00f6ring",
    "sg:phone":"+49 8541/8293",
    "sg:postcode":"94565",
    "wof:name":"Gastwirtschaft J. Feilmeier",
    "wof:placetype":"venue"
},
  "geometry": {"coordinates":[13.2242031097,48.6694755554],"type":"Point"}
}