{
  "type": "Feature",
  "properties": {
    "iso:country":"DE",
    "sg:address":"Nietzschestr. 30",
    "sg:city":"M\u00fcnchen",
    "sg:phone":"+49 89/3508360",
    "sg:postcode":"80807",
    "sg:province":"Bayern",
    "wof:name":"Baumanagement Seelhoff Gmbh",
    "wof:placetype":"venue"
},
  "geometry": {"coordinates":[11.570725441,48.1789321899],"type":"Point"}
}