{
  "type": "Feature",
  "properties": {
    "iso:country":"DE",
    "sg:address":"Albuchweg 59",
    "sg:city":"Bartholom\u00e4",
    "sg:phone":"+49 7173/7471",
    "sg:postcode":"73566",
    "sg:province":"Baden-W\u00fcrttemberg",
    "wof:name":"Reinhard Kreisel Anlageberater",
    "wof:placetype":"venue"
},
  "geometry": {"coordinates":[9.9819450378,48.7522468567],"type":"Point"}
}