{
  "type": "Feature",
  "properties": {
    "iso:country":"DE",
    "sg:address":"Ahlener Weg 16",
    "sg:city":"Drensteinfurt",
    "sg:phone":"+49 2508/337",
    "sg:postcode":"48317",
    "sg:province":"Nordrhein-Westfalen",
    "wof:name":"Bedachungen Kortendieck & Sohn Gmbh",
    "wof:placetype":"venue"
},
  "geometry": {"coordinates":[7.749369,51.795155],"type":"Point"}
}