{
  "type": "Feature",
  "properties": {
    "iso:country":"DE",
    "sg:address":"Meersburger Str. 1",
    "sg:city":"Friedrichshafen",
    "sg:phone":"+49 7541/94002",
    "sg:postcode":"88048",
    "sg:province":"Baden-W\u00fcrttemberg",
    "wof:name":"R. Moosbacher",
    "wof:placetype":"venue"
},
  "geometry": {"coordinates":[9.412049,47.670258],"type":"Point"}
}