{
  "type": "Feature",
  "properties": {
    "iso:country":"DE",
    "sg:address":"Schwetzinger Str. 103",
    "sg:city":"Hockenheim",
    "sg:phone":"+49 6205/20090",
    "sg:postcode":"68766",
    "sg:province":"Baden-W\u00fcrttemberg",
    "wof:name":"Epc Elreha Leiterplatten - Technik Gmbh",
    "wof:placetype":"venue"
},
  "geometry": {"coordinates":[8.547912,49.329575],"type":"Point"}
}