{
  "type": "Feature",
  "properties": {
    "iso:country":"DE",
    "sg:address":"Salmorth 5",
    "sg:city":"Kleve",
    "sg:phone":"+49 2821/93446",
    "sg:postcode":"47533",
    "sg:province":"Nordrhein-Westfalen",
    "wof:name":"August B\u00f6hling",
    "wof:placetype":"venue"
},
  "geometry": {"coordinates":[6.14291,51.831379],"type":"Point"}
}