{
  "type": "Feature",
  "properties": {
    "iso:country":"DE",
    "sg:address":"Hainstr. 95",
    "sg:city":"Chemnitz",
    "sg:phone":"+49 371/4012861",
    "sg:postcode":"09130",
    "sg:province":"Sachsen",
    "wof:name":"Katrin Patzig",
    "wof:placetype":"venue"
},
  "geometry": {"coordinates":[12.935285,50.839798],"type":"Point"}
}