{
  "type": "Feature",
  "properties": {
    "iso:country":"DE",
    "sg:address":"Hauptstr. 114",
    "sg:city":"Appenweier",
    "sg:phone":"+49 7805/3333",
    "sg:postcode":"77767",
    "sg:province":"Baden-W\u00fcrttemberg",
    "wof:name":"Mina M\u00fcller",
    "wof:placetype":"venue"
},
  "geometry": {"coordinates":[7.9679341316,48.5567588806],"type":"Point"}
}