{
  "type": "Feature",
  "properties": {
    "iso:country":"DE",
    "sg:address":"Breite Herzogstr. 5",
    "sg:city":"Wolfenb\u00fcttel",
    "sg:phone":"+49 5331/2564",
    "sg:postcode":"38300",
    "sg:province":"Niedersachsen",
    "wof:name":"J. Bosse",
    "wof:placetype":"venue"
},
  "geometry": {"coordinates":[10.5404529572,52.1630935669],"type":"Point"}
}