{
  "type": "Feature",
  "properties": {
    "iso:country":"DE",
    "sg:address":"M\u00fchlenredder 2",
    "sg:city":"Kuddew\u00f6rde",
    "sg:phone":"+49 4154/81614",
    "sg:postcode":"22958",
    "sg:province":"Schleswig-Holstein",
    "wof:name":"Sch\u00f6nheitsfarm Clau\u00dfen Gmbh",
    "wof:placetype":"venue"
},
  "geometry": {"coordinates":[10.389579,53.577244],"type":"Point"}
}