{
  "type": "Feature",
  "properties": {
    "iso:country":"DE",
    "sg:address":"Germersheimer Str. 54",
    "sg:city":"N\u00fcrnberg",
    "sg:phone":"+49 911/483220",
    "sg:postcode":"90469",
    "sg:province":"Bayern",
    "wof:name":"Udo Pawlik",
    "wof:placetype":"venue"
},
  "geometry": {"coordinates":[11.09792,49.403671],"type":"Point"}
}