{
  "type": "Feature",
  "properties": {
    "iso:country":"DE",
    "sg:address":"Bundschuhstr. 7",
    "sg:city":"Heilbronn",
    "sg:phone":"+49 7131/254534",
    "sg:postcode":"74081",
    "sg:province":"Baden-W\u00fcrttemberg",
    "wof:name":"Kleintierz\u00fcchterverein B\u00f6ckingen 1899 E. V.",
    "wof:placetype":"venue"
},
  "geometry": {"coordinates":[9.1879806519,49.1189117432],"type":"Point"}
}