{
  "type": "Feature",
  "properties": {
    "iso:country":"DE",
    "sg:address":"Heerstr. 31a",
    "sg:city":"Niederkassel",
    "sg:phone":"+49 2208/759241",
    "sg:postcode":"53859",
    "sg:province":"Nordrhein-Westfalen",
    "wof:name":"Elbero Gmbh",
    "wof:placetype":"venue"
},
  "geometry": {"coordinates":[7.067085,50.820278],"type":"Point"}
}