{
  "type": "Feature",
  "properties": {
    "iso:country":"DE",
    "sg:address":"Am Eberb\u00fchl 3",
    "sg:city":"Heltersberg",
    "sg:phone":"+49 6333/63526",
    "sg:postcode":"67716",
    "sg:province":"Rheinland-Pfalz",
    "wof:name":"E. Getta",
    "wof:placetype":"venue"
},
  "geometry": {"coordinates":[7.7165851593,49.3145446777],"type":"Point"}
}