{
  "type": "Feature",
  "properties": {
    "iso:country":"DE",
    "sg:address":"Friedenstr. 65",
    "sg:city":"Pforzheim",
    "sg:phone":"+49 7231/63526",
    "sg:postcode":"75173",
    "sg:province":"Baden-W\u00fcrttemberg",
    "wof:name":"Kurt M\u00fcller Architekt",
    "wof:placetype":"venue"
},
  "geometry": {"coordinates":[8.69521,48.879124],"type":"Point"}
}