{
  "type": "Feature",
  "properties": {
    "iso:country":"DE",
    "sg:address":"Schuhmacherwoog 15",
    "sg:city":"Kaiserslautern",
    "sg:phone":"+49 631/95697",
    "sg:postcode":"67661",
    "sg:province":"Rheinland-Pfalz",
    "wof:name":"Provinzial Versicherung Rohfleisch",
    "wof:placetype":"venue"
},
  "geometry": {"coordinates":[7.65955019,49.43126297],"type":"Point"}
}