{
  "type": "Feature",
  "properties": {
    "iso:country":"DE",
    "sg:address":"Am Neuen Markt 7",
    "sg:city":"Ramstein-Miesenbach",
    "sg:phone":"+49 6371/953054",
    "sg:postcode":"66877",
    "sg:province":"Rheinland-Pfalz",
    "wof:name":"G & W Eurowohnbau Gmbh",
    "wof:placetype":"venue"
},
  "geometry": {"coordinates":[7.554956913,49.4479408264],"type":"Point"}
}