{
  "type": "Feature",
  "properties": {
    "iso:country":"DE",
    "sg:address":"B\u00e4rentalstr. 11",
    "sg:city":"D\u00f6beln",
    "sg:phone":"+49 3431/611058",
    "sg:postcode":"04720",
    "sg:province":"Sachsen",
    "wof:name":"K. Fricke",
    "wof:placetype":"venue"
},
  "geometry": {"coordinates":[13.110005,51.116283],"type":"Point"}
}