{
  "type": "Feature",
  "properties": {
    "iso:country":"DE",
    "sg:address":"Heinrich-Heine-Str. 60",
    "sg:city":"Storkow",
    "sg:phone":"+49 33678/72214",
    "sg:postcode":"15859",
    "sg:province":"Brandenburg",
    "wof:name":"H. Obenhaupt",
    "wof:placetype":"venue"
},
  "geometry": {"coordinates":[13.935026,52.258301],"type":"Point"}
}