{
  "type": "Feature",
  "properties": {
    "iso:country":"DE",
    "sg:address":"Mannheimer Str. 81-",
    "sg:city":"Frankfurt",
    "sg:phone":"+49 69/71641",
    "sg:postcode":"60327",
    "sg:province":"Hessen",
    "wof:name":"Rbg Reisebetreuungs Gmbh",
    "wof:placetype":"venue"
},
  "geometry": {"coordinates":[8.6567735672,50.1027183533],"type":"Point"}
}