{
  "type": "Feature",
  "properties": {
    "iso:country":"DE",
    "sg:address":"Feldstr. 1",
    "sg:city":"Halstenbek",
    "sg:phone":"+49 4101/473307",
    "sg:postcode":"25469",
    "sg:province":"Schleswig-Holstein",
    "wof:name":"Arthur Senger Ingenieur",
    "wof:placetype":"venue"
},
  "geometry": {"coordinates":[9.8377275467,53.6335105896],"type":"Point"}
}