{
  "type": "Feature",
  "properties": {
    "iso:country":"DE",
    "sg:address":"Goethestr. 6",
    "sg:city":"R\u00f6srath",
    "sg:phone":"+49 2205/4481",
    "sg:postcode":"51503",
    "sg:province":"Nordrhein-Westfalen",
    "wof:name":"P. P\u00fctz",
    "wof:placetype":"venue"
},
  "geometry": {"coordinates":[7.1790342331,50.9014282227],"type":"Point"}
}