{
  "type": "Feature",
  "properties": {
    "iso:country":"DE",
    "sg:address":"Nonnenstra\u00dfe 5b",
    "sg:city":"Leipzig",
    "sg:phone":"+49 341/486660",
    "sg:postcode":"04229",
    "sg:province":"Sachsen",
    "wof:name":"Hps Werkskundendienst- Und Servicegesellschaft Mbh",
    "wof:placetype":"venue"
},
  "geometry": {"coordinates":[12.34652,51.330406],"type":"Point"}
}