{
  "type": "Feature",
  "properties": {
    "iso:country":"DE",
    "sg:address":"Wemberweg 4",
    "sg:city":"Erwitte",
    "sg:phone":"+49 2943/49830",
    "sg:postcode":"59597",
    "sg:province":"Nordrhein-Westfalen",
    "wof:name":"Combi",
    "wof:placetype":"venue"
},
  "geometry": {"coordinates":[8.3514556885,51.6136398315],"type":"Point"}
}