{
  "type": "Feature",
  "properties": {
    "iso:country":"DE",
    "sg:address":"Kaiserstr. 30",
    "sg:city":"Kitzingen",
    "sg:phone":"+49 9321/22972",
    "sg:postcode":"97318",
    "sg:province":"Bayern",
    "wof:name":"Gertrud Haberberger Heilpraktiker",
    "wof:placetype":"venue"
},
  "geometry": {"coordinates":[10.1595420837,49.7380485535],"type":"Point"}
}