{
  "type": "Feature",
  "properties": {
    "iso:country":"DE",
    "sg:address":"Tituscorso",
    "sg:city":"Frankfurt",
    "sg:phone":"+49 69/571031",
    "sg:postcode":"60439",
    "sg:province":"Hessen",
    "wof:name":"C. & A.",
    "wof:placetype":"venue"
},
  "geometry": {"coordinates":[8.634725,50.157341],"type":"Point"}
}