{
  "type": "Feature",
  "properties": {
    "iso:country":"DE",
    "sg:address":"Osterheck 12",
    "sg:city":"Winnert",
    "sg:phone":"+49 4845/1358",
    "sg:postcode":"25887",
    "sg:province":"Schleswig-Holstein",
    "wof:name":"Michael Rese",
    "wof:placetype":"venue"
},
  "geometry": {"coordinates":[9.211648941,54.4325866699],"type":"Point"}
}