{
  "type": "Feature",
  "properties": {
    "iso:country":"DE",
    "sg:address":"Hauptstr. 10",
    "sg:city":"Illmensee",
    "sg:phone":"+49 7558/252",
    "sg:postcode":"88636",
    "sg:province":"Baden-W\u00fcrttemberg",
    "wof:name":"Seehof",
    "wof:placetype":"venue"
},
  "geometry": {"coordinates":[9.3735761642,47.8610496521],"type":"Point"}
}