{
  "type": "Feature",
  "properties": {
    "iso:country":"DE",
    "sg:address":"Friedrichsgaber Weg 465",
    "sg:city":"Norderstedt",
    "sg:phone":"+49 40/5227058",
    "sg:postcode":"22846",
    "sg:province":"Schleswig-Holstein",
    "wof:name":"Kiebitz-apotheke",
    "wof:placetype":"venue"
},
  "geometry": {"coordinates":[9.987404,53.718559],"type":"Point"}
}