{
  "type": "Feature",
  "properties": {
    "iso:country":"DE",
    "sg:address":"Kastanienweg 2",
    "sg:city":"Michelbach",
    "sg:phone":"+49 6761/5002",
    "sg:postcode":"56288",
    "sg:province":"Rheinland-Pfalz",
    "wof:name":"Heinz Br\u00fcck",
    "wof:placetype":"venue"
},
  "geometry": {"coordinates":[7.454564,50.014999],"type":"Point"}
}