{
  "type": "Feature",
  "properties": {
    "iso:country":"DE",
    "sg:address":"Josefstr. 19",
    "sg:city":"Sundern",
    "sg:phone":"+49 2935/2766",
    "sg:postcode":"59846",
    "sg:province":"Nordrhein-Westfalen",
    "wof:name":"Wolfgang Westermann",
    "wof:placetype":"venue"
},
  "geometry": {"coordinates":[7.9832310677,51.3711967468],"type":"Point"}
}