{
  "type": "Feature",
  "properties": {
    "iso:country":"DE",
    "sg:address":"Fr\u00fchlingstr. 1",
    "sg:city":"Herdecke",
    "sg:phone":"+49 2330/916829",
    "sg:postcode":"58313",
    "sg:province":"Nordrhein-Westfalen",
    "wof:name":"Viktoria Versicherungen David Wolfien",
    "wof:placetype":"venue"
},
  "geometry": {"coordinates":[7.430729866,51.3990097046],"type":"Point"}
}