{
  "type": "Feature",
  "properties": {
    "iso:country":"DE",
    "sg:address":"Schlo\u00df Weyhern",
    "sg:city":"Egenhofen",
    "sg:postcode":"82281",
    "sg:province":"Bayern",
    "wof:name":"Err - Syndicus Verm\u00f6gensverwaltungs- Ag",
    "wof:placetype":"venue"
},
  "geometry": {"coordinates":[11.1608400345,48.2832794189],"type":"Point"}
}