{
  "type": "Feature",
  "properties": {
    "iso:country":"DE",
    "sg:address":"Sedanstr 16d",
    "sg:city":"Kiel",
    "sg:phone":"+49 431/979130",
    "sg:postcode":"24116",
    "sg:province":"Schleswig-Holstein",
    "wof:name":"Elmatic Gmbh",
    "wof:placetype":"venue"
},
  "geometry": {"coordinates":[10.1085033417,54.3281288147],"type":"Point"}
}