{
  "type": "Feature",
  "properties": {
    "iso:country":"DE",
    "sg:address":"Nordstr. 6",
    "sg:city":"Bersenbr\u00fcck",
    "sg:phone":"+49 5439/3737",
    "sg:postcode":"49593",
    "sg:province":"Niedersachsen",
    "wof:name":"Lohbeck & Lohbeck",
    "wof:placetype":"venue"
},
  "geometry": {"coordinates":[7.945503,52.55545],"type":"Point"}
}