{
  "type": "Feature",
  "properties": {
    "iso:country":"DE",
    "sg:address":"Goethestr. 2",
    "sg:city":"Maintal",
    "sg:phone":"+49 6109/64186",
    "sg:postcode":"63477",
    "sg:province":"Hessen",
    "wof:name":"Idea Die Gr\u00fcne Drogerie Gmbh",
    "wof:placetype":"venue"
},
  "geometry": {"coordinates":[8.817065,50.149803],"type":"Point"}
}