{
  "type": "Feature",
  "properties": {
    "iso:country":"DE",
    "sg:address":"Feringastr. 14",
    "sg:city":"Unterf\u00f6hring",
    "sg:phone":"+49 89/9926990",
    "sg:postcode":"85774",
    "sg:province":"Bayern",
    "wof:name":"Aic - Reglo Plas Fertig Gmbh",
    "wof:placetype":"venue"
},
  "geometry": {"coordinates":[11.636066,48.178043],"type":"Point"}
}