{
  "type": "Feature",
  "properties": {
    "iso:country":"DE",
    "sg:address":"August-Bebel-Str. 9",
    "sg:city":"Torgau",
    "sg:phone":"+49 3421/903552",
    "sg:postcode":"04860",
    "sg:province":"Sachsen",
    "wof:name":"Dentallabor Raschke & Heider Gmbh",
    "wof:placetype":"venue"
},
  "geometry": {"coordinates":[12.9954280853,51.5592880249],"type":"Point"}
}