{
  "type": "Feature",
  "properties": {
    "iso:country":"DE",
    "sg:address":"Trivastr. 24",
    "sg:city":"M\u00fcnchen",
    "sg:phone":"+49 89/151404",
    "sg:postcode":"80637",
    "sg:province":"Bayern",
    "wof:name":"K. Kagermaier",
    "wof:placetype":"venue"
},
  "geometry": {"coordinates":[11.5403280258,48.1621208191],"type":"Point"}
}