{
  "type": "Feature",
  "properties": {
    "iso:country":"DE",
    "sg:address":"Aufgang zum Kalvarienberg 4",
    "sg:city":"Bad T\u00f6lz",
    "sg:phone":"+49 8041/2918",
    "sg:postcode":"83646",
    "sg:province":"Bayern",
    "wof:name":"Simon Und Max Schneider Gmbh",
    "wof:placetype":"venue"
},
  "geometry": {"coordinates":[11.559209,47.762657],"type":"Point"}
}