{
  "type": "Feature",
  "properties": {
    "iso:country":"DE",
    "sg:address":"Liebigstr. 16",
    "sg:city":"Heppenheim",
    "sg:phone":"+49 6252/910100",
    "sg:postcode":"64646",
    "sg:province":"Hessen",
    "wof:name":"Optisolv Pharma Gmbh",
    "wof:placetype":"venue"
},
  "geometry": {"coordinates":[8.635798,49.640896],"type":"Point"}
}