{
  "type": "Feature",
  "properties": {
    "iso:country":"DE",
    "sg:address":"Zur Wiesethquelle 7",
    "sg:city":"Aurach",
    "sg:phone":"+49 9804/427",
    "sg:postcode":"91589",
    "sg:province":"Bayern",
    "wof:name":"August Griesser Elektroinstallation",
    "wof:placetype":"venue"
},
  "geometry": {"coordinates":[10.360661,49.233292],"type":"Point"}
}