{
  "type": "Feature",
  "properties": {
    "iso:country":"DE",
    "sg:address":"Wolfegger Str. 2",
    "sg:city":"Weingarten",
    "sg:phone":"+49 751/52348",
    "sg:postcode":"88250",
    "sg:province":"Baden-W\u00fcrttemberg",
    "wof:name":"Bernd Metz Ingenieur",
    "wof:placetype":"venue"
},
  "geometry": {"coordinates":[9.6482048035,47.8079109192],"type":"Point"}
}