{
  "type": "Feature",
  "properties": {
    "iso:country":"DE",
    "sg:address":"Fessenbacher Str. 120",
    "sg:city":"Offenburg",
    "sg:phone":"+49 781/31558",
    "sg:postcode":"77654",
    "sg:province":"Baden-W\u00fcrttemberg",
    "wof:name":"Paul B\u00e4chle",
    "wof:placetype":"venue"
},
  "geometry": {"coordinates":[7.9781289101,48.4641723633],"type":"Point"}
}