{
  "type": "Feature",
  "properties": {
    "iso:country":"DE",
    "sg:address":"Gabelsbergerstr. 30",
    "sg:city":"Traunstein",
    "sg:phone":"+49 861/9869638",
    "sg:postcode":"83278",
    "sg:province":"Bayern",
    "wof:name":"Color Service Ohg",
    "wof:placetype":"venue"
},
  "geometry": {"coordinates":[12.6338129044,47.8699493408],"type":"Point"}
}