{
  "type": "Feature",
  "properties": {
    "iso:country":"DE",
    "sg:address":"Hermann-Bo\u00dfdorf-Str. 3",
    "sg:city":"Wiesenburg",
    "sg:phone":"+49 33849/50259",
    "sg:postcode":"14827",
    "sg:province":"Brandenburg",
    "wof:name":"Paul Richter",
    "wof:placetype":"venue"
},
  "geometry": {"coordinates":[12.454347,52.113552],"type":"Point"}
}