{
  "type": "Feature",
  "properties": {
    "iso:country":"DE",
    "sg:address":"Sch\u00e4ftlarnstr. 136",
    "sg:city":"M\u00fcnchen",
    "sg:phone":"+49 89/7231953",
    "sg:postcode":"81371",
    "sg:province":"Bayern",
    "wof:name":"Hagen Sydow",
    "wof:placetype":"venue"
},
  "geometry": {"coordinates":[11.5486745834,48.1053504944],"type":"Point"}
}