{
  "type": "Feature",
  "properties": {
    "iso:country":"DE",
    "sg:address":"Adolf-Kolping-Str. 14",
    "sg:city":"Walld\u00fcrn",
    "sg:phone":"+49 4962/82690",
    "sg:postcode":"74731",
    "sg:province":"Baden-W\u00fcrttemberg",
    "wof:name":"Volksbank Walld\u00fcrn Eg, -spar- Und Kreditbank-",
    "wof:placetype":"venue"
},
  "geometry": {"coordinates":[9.367718,49.581566],"type":"Point"}
}