{
  "type": "Feature",
  "properties": {
    "iso:country":"DE",
    "sg:address":"Oswald-Meder-Str 23",
    "sg:city":"Villingen-Schwenningen",
    "sg:phone":"+49 7721/21598",
    "sg:postcode":"78052",
    "sg:province":"Baden-W\u00fcrttemberg",
    "wof:name":"Glatz Formenbau Gmbh & Co Kg",
    "wof:placetype":"venue"
},
  "geometry": {"coordinates":[8.4595937729,48.031791687],"type":"Point"}
}