{
  "type": "Feature",
  "properties": {
    "iso:country":"DE",
    "sg:address":"Jugendheimstr. 13",
    "sg:city":"Bernkastel-Kues",
    "sg:phone":"+49 6531/8051",
    "sg:postcode":"54470",
    "sg:province":"Rheinland-Pfalz",
    "wof:name":"Jugend- Und Touristenheim",
    "wof:placetype":"venue"
},
  "geometry": {"coordinates":[7.0649371147,49.9130249023],"type":"Point"}
}