{
  "type": "Feature",
  "properties": {
    "iso:country":"DE",
    "sg:address":"Vahrenwalder Str. 9",
    "sg:city":"Hannover",
    "sg:postcode":"30165",
    "sg:province":"Niedersachsen",
    "wof:name":"Cas-one Holdingges. Mbh",
    "wof:placetype":"venue"
},
  "geometry": {"coordinates":[9.73377,52.387016],"type":"Point"}
}