{
  "type": "Feature",
  "properties": {
    "iso:country":"DE",
    "sg:address":"Kapellenstr. 28",
    "sg:city":"Osterwieck",
    "sg:phone":"+49 39421/74857",
    "sg:postcode":"38835",
    "sg:province":"Sachsen-Anhalt",
    "wof:name":"Besthorn",
    "wof:placetype":"venue"
},
  "geometry": {"coordinates":[10.713797,51.970512],"type":"Point"}
}