{
  "type": "Feature",
  "properties": {
    "iso:country":"DE",
    "sg:address":"Ulmenweg 8",
    "sg:city":"Wegberg",
    "sg:phone":"+49 2434/1053",
    "sg:postcode":"41844",
    "sg:province":"Nordrhein-Westfalen",
    "wof:name":"Horst Jansen Immobilienmakler",
    "wof:placetype":"venue"
},
  "geometry": {"coordinates":[6.2991871834,51.1426773071],"type":"Point"}
}