{
  "type": "Feature",
  "properties": {
    "iso:country":"DE",
    "sg:address":"Hauptstr. 134",
    "sg:city":"Bielefeld",
    "sg:phone":"+49 521/4329053",
    "sg:postcode":"33647",
    "sg:province":"Nordrhein-Westfalen",
    "wof:name":"Terra-tours",
    "wof:placetype":"venue"
},
  "geometry": {"coordinates":[8.5071220398,51.9938812256],"type":"Point"}
}