{
  "type": "Feature",
  "properties": {
    "iso:country":"DE",
    "sg:address":"Nieder-M\u00f6rler-Str. 31",
    "sg:city":"Bad Nauheim",
    "sg:phone":"+49 6032/82830",
    "sg:postcode":"61231",
    "sg:province":"Hessen",
    "wof:name":"Carbonara",
    "wof:placetype":"venue"
},
  "geometry": {"coordinates":[8.7192382812,50.3810195923],"type":"Point"}
}