{
  "type": "Feature",
  "properties": {
    "iso:country":"DE",
    "sg:address":"Am Schelprieth 10",
    "sg:city":"Lachendorf",
    "sg:postcode":"29331",
    "sg:province":"Niedersachsen",
    "wof:name":"Nater Gmbh",
    "wof:placetype":"venue"
},
  "geometry": {"coordinates":[10.2489213943,52.61378479],"type":"Point"}
}