{
  "type": "Feature",
  "properties": {
    "iso:country":"DE",
    "sg:address":"Hademareplatz 6",
    "sg:city":"Hemer",
    "sg:phone":"+49 2372/12485",
    "sg:postcode":"58675",
    "sg:province":"Nordrhein-Westfalen",
    "wof:name":"L\u00f6wen Play Gmbh",
    "wof:placetype":"venue"
},
  "geometry": {"coordinates":[7.7669658661,51.3849945068],"type":"Point"}
}