{
  "type": "Feature",
  "properties": {
    "iso:country":"DE",
    "sg:address":"Mozartstr. 2",
    "sg:city":"K\u00f6ln",
    "sg:phone":"+49 221/311450",
    "sg:postcode":"50999",
    "sg:province":"Nordrhein-Westfalen",
    "wof:name":"Sandro Einsiedel Und Haeffner Architekten",
    "wof:placetype":"venue"
},
  "geometry": {"coordinates":[7.011235,50.881065],"type":"Point"}
}