{
  "type": "Feature",
  "properties": {
    "iso:country":"DE",
    "sg:address":"Burgeffstr. 26",
    "sg:city":"Hochheim",
    "sg:phone":"+49 6146/2287",
    "sg:postcode":"65239",
    "sg:province":"Hessen",
    "wof:name":"Fritz Weilb\u00e4cher Elektroinstallation",
    "wof:placetype":"venue"
},
  "geometry": {"coordinates":[8.350493,50.012566],"type":"Point"}
}