{
  "type": "Feature",
  "properties": {
    "iso:country":"DE",
    "sg:address":"Am Merzenb\u00e4chle 30",
    "sg:city":"Pfedelbach",
    "sg:phone":"+49 7941/2676",
    "sg:postcode":"74629",
    "sg:province":"Baden-W\u00fcrttemberg",
    "wof:name":"H. Skribanek-schaaf",
    "wof:placetype":"venue"
},
  "geometry": {"coordinates":[9.5064840317,49.1718025208],"type":"Point"}
}