{
  "type": "Feature",
  "properties": {
    "iso:country":"DE",
    "sg:address":"S\u00fcrenheider Str. 322",
    "sg:city":"Verl",
    "sg:phone":"+49 5246/2578",
    "sg:postcode":"33415",
    "sg:province":"Nordrhein-Westfalen",
    "wof:name":"Edmund Klinke",
    "wof:placetype":"venue"
},
  "geometry": {"coordinates":[8.457417,51.894348],"type":"Point"}
}