{
  "type": "Feature",
  "properties": {
    "iso:country":"DE",
    "sg:address":"Zum Steinberg 3",
    "sg:city":"Bredstedt",
    "sg:phone":"+49 4671/930944",
    "sg:postcode":"25821",
    "sg:province":"Schleswig-Holstein",
    "wof:name":"Georg F. Petersen",
    "wof:placetype":"venue"
},
  "geometry": {"coordinates":[8.964313,54.623486],"type":"Point"}
}