{
  "type": "Feature",
  "properties": {
    "iso:country":"DE",
    "sg:address":"Kapellenring 3",
    "sg:city":"Heinsberg",
    "sg:phone":"+49 2452/61316",
    "sg:postcode":"52525",
    "sg:province":"Nordrhein-Westfalen",
    "wof:name":"M. K\u00fcppers Und H. Lambertz",
    "wof:placetype":"venue"
},
  "geometry": {"coordinates":[6.0894451141,51.059387207],"type":"Point"}
}