{
  "type": "Feature",
  "properties": {
    "iso:country":"DE",
    "sg:address":"Alfred-Brodauf-Str. 2",
    "sg:city":"Aue",
    "sg:phone":"+49 3771/26923",
    "sg:postcode":"08280",
    "sg:province":"Sachsen",
    "wof:name":"D. Schmitt",
    "wof:placetype":"venue"
},
  "geometry": {"coordinates":[12.7023286819,50.5858840942],"type":"Point"}
}