{
  "type": "Feature",
  "properties": {
    "iso:country":"DE",
    "sg:address":"Weinbergweg 1",
    "sg:city":"Lehnin",
    "sg:phone":"+49 3382/681",
    "sg:postcode":"14797",
    "sg:province":"Brandenburg",
    "wof:name":"Kurt Meyer",
    "wof:placetype":"venue"
},
  "geometry": {"coordinates":[12.7438249588,52.3184089661],"type":"Point"}
}