{
  "type": "Feature",
  "properties": {
    "iso:country":"DE",
    "sg:address":"Am Bogen 6",
    "sg:city":"Augsburg",
    "sg:phone":"+49 821/36666",
    "sg:postcode":"86152",
    "sg:province":"Bayern",
    "wof:name":"Walter Meile Gmbh",
    "wof:placetype":"venue"
},
  "geometry": {"coordinates":[10.901892,48.371044],"type":"Point"}
}