{
  "type": "Feature",
  "properties": {
    "iso:country":"DE",
    "sg:address":"Almsfeld 6",
    "sg:city":"Altenbrak",
    "sg:phone":"+49 39456/936",
    "sg:postcode":"38889",
    "sg:province":"Sachsen-Anhalt",
    "wof:name":"Frank Schierhorn Disco 6",
    "wof:placetype":"venue"
},
  "geometry": {"coordinates":[10.935282,51.748989],"type":"Point"}
}