{
  "type": "Feature",
  "properties": {
    "iso:country":"DE",
    "sg:address":"Josef-Otto-Kolb-Str. 4",
    "sg:city":"Hausen",
    "sg:phone":"+49 9191/4595",
    "sg:postcode":"91353",
    "sg:province":"Bayern",
    "wof:name":"Renker Ingenieur",
    "wof:placetype":"venue"
},
  "geometry": {"coordinates":[11.030962944,49.691368103],"type":"Point"}
}