{
  "type": "Feature",
  "properties": {
    "iso:country":"DE",
    "sg:address":"Adelshofer Str. 10",
    "sg:city":"Eppingen",
    "sg:phone":"+49 7262/7999",
    "sg:postcode":"75031",
    "sg:province":"Baden-W\u00fcrttemberg",
    "wof:name":"Martin-ziegler Gmbh",
    "wof:placetype":"venue"
},
  "geometry": {"coordinates":[8.9086828232,49.1386947632],"type":"Point"}
}