{
  "type": "Feature",
  "properties": {
    "iso:country":"DE",
    "sg:address":"Hauptstr. 50",
    "sg:city":"Sande",
    "sg:phone":"+49 4422/986913",
    "sg:postcode":"26452",
    "sg:province":"Niedersachsen",
    "wof:name":"Cockpit Schnellrestaurant",
    "wof:placetype":"venue"
},
  "geometry": {"coordinates":[8.017370224,53.4991912842],"type":"Point"}
}