{
  "type": "Feature",
  "properties": {
    "iso:country":"DE",
    "sg:address":"Obernstr. 8",
    "sg:city":"Varel",
    "sg:phone":"+49 4451/862666",
    "sg:postcode":"26316",
    "sg:province":"Niedersachsen",
    "wof:name":"K\u00fcchen-traum",
    "wof:placetype":"venue"
},
  "geometry": {"coordinates":[8.1397895813,53.3953666687],"type":"Point"}
}