{
  "type": "Feature",
  "properties": {
    "iso:country":"DE",
    "sg:address":"Tulpenstr. 33",
    "sg:city":"Krummennaab",
    "sg:postcode":"92703",
    "sg:province":"Bayern",
    "wof:name":"Funkerclub Wiesau Josef H\u00e4rtl",
    "wof:placetype":"venue"
},
  "geometry": {"coordinates":[12.1072177887,49.8352355957],"type":"Point"}
}