{
  "type": "Feature",
  "properties": {
    "iso:country":"DE",
    "sg:address":"Stublang 2",
    "sg:city":"Staffelstein",
    "sg:phone":"+49 9573/6304",
    "sg:postcode":"96231",
    "sg:province":"Bayern",
    "wof:name":"B. Reichert",
    "wof:placetype":"venue"
},
  "geometry": {"coordinates":[10.9991750717,50.1024131775],"type":"Point"}
}