{
  "type": "Feature",
  "properties": {
    "iso:country":"DE",
    "sg:address":"Talweg 1",
    "sg:city":"Ebhausen",
    "sg:postcode":"72224",
    "sg:province":"Baden-W\u00fcrttemberg",
    "wof:name":"J.-u. Rothfu\u00df Gmbh",
    "wof:placetype":"venue"
},
  "geometry": {"coordinates":[8.6957807541,48.6064186096],"type":"Point"}
}