{
  "type": "Feature",
  "properties": {
    "iso:country":"DE",
    "sg:address":"Heiligbrunnenstr. 22",
    "sg:city":"Titisee-Neustadt",
    "sg:phone":"+49 7652/91150",
    "sg:postcode":"79822",
    "sg:province":"Baden-W\u00fcrttemberg",
    "wof:name":"Pension Haus Lindenh\u00f6he",
    "wof:placetype":"venue"
},
  "geometry": {"coordinates":[8.1155185699,47.918132782],"type":"Point"}
}