{
  "type": "Feature",
  "properties": {
    "iso:country":"DE",
    "sg:address":"In der Hegge 8",
    "sg:city":"Bohmte",
    "sg:phone":"+49 5471/2970",
    "sg:postcode":"49163",
    "sg:province":"Niedersachsen",
    "wof:name":"Ulrich Alscher",
    "wof:placetype":"venue"
},
  "geometry": {"coordinates":[8.259968,52.347374],"type":"Point"}
}