{
  "type": "Feature",
  "properties": {
    "iso:country":"DE",
    "sg:address":"M\u00e4rkische Allee 276",
    "sg:city":"Berlin",
    "sg:phone":"+49 30/93770016",
    "sg:postcode":"12679",
    "sg:province":"Berlin",
    "wof:name":"Kaisers Markt",
    "wof:placetype":"venue"
},
  "geometry": {"coordinates":[13.5547637939,52.5565681458],"type":"Point"}
}