{
  "type": "Feature",
  "properties": {
    "iso:country":"DE",
    "sg:address":"Neupfarrplatz 8",
    "sg:city":"Regensburg",
    "sg:phone":"+49 941/563111",
    "sg:postcode":"93047",
    "sg:province":"Bayern",
    "wof:name":"Geber Intertabaco Gmbh",
    "wof:placetype":"venue"
},
  "geometry": {"coordinates":[12.0970163345,49.018283844],"type":"Point"}
}