{
  "type": "Feature",
  "properties": {
    "iso:country":"DE",
    "sg:address":"Gotenstra\u00dfe 4",
    "sg:city":"Hamburg",
    "sg:phone":"+49 40",
    "sg:postcode":"20097",
    "sg:province":"Hamburg",
    "wof:name":"Dr. R. Wienberg",
    "wof:placetype":"venue"
},
  "geometry": {"coordinates":[10.022851,53.548706],"type":"Point"}
}