{
  "type": "Feature",
  "properties": {
    "iso:country":"DE",
    "sg:address":"Unterdorfstr. 16",
    "sg:city":"K\u00f6ngen",
    "sg:phone":"+49 7024/82411",
    "sg:postcode":"73257",
    "sg:province":"Baden-W\u00fcrttemberg",
    "wof:name":"R. Deutsch",
    "wof:placetype":"venue"
},
  "geometry": {"coordinates":[9.363346,48.683907],"type":"Point"}
}