{
  "type": "Feature",
  "properties": {
    "iso:country":"DE",
    "sg:address":"Im Wieschen 10",
    "sg:city":"Homburg/Einoed",
    "sg:phone":"+49 6848/72180",
    "sg:postcode":"66424",
    "sg:province":"Saarland",
    "wof:name":"Ht-computer Website",
    "wof:placetype":"venue"
},
  "geometry": {"coordinates":[7.321242,49.270988],"type":"Point"}
}