{
  "type": "Feature",
  "properties": {
    "iso:country":"DE",
    "sg:address":"Baiersbronner Str. 60",
    "sg:city":"Freudenstadt",
    "sg:phone":"+49 7442/4309",
    "sg:postcode":"72250",
    "sg:province":"Baden-W\u00fcrttemberg",
    "wof:name":"Gretel Arnold",
    "wof:placetype":"venue"
},
  "geometry": {"coordinates":[8.4127998352,48.4642601013],"type":"Point"}
}