{
  "type": "Feature",
  "properties": {
    "iso:country":"DE",
    "sg:address":"Fuchslochweg 2",
    "sg:city":"Neidenstein",
    "sg:postcode":"74933",
    "sg:province":"Baden-W\u00fcrttemberg",
    "wof:name":"Verlag Lokalpresse Gmbh",
    "wof:placetype":"venue"
},
  "geometry": {"coordinates":[8.8933753967,49.3177642822],"type":"Point"}
}