{
  "type": "Feature",
  "properties": {
    "iso:country":"DE",
    "sg:address":"Erlenweg 7a",
    "sg:city":"Geretsried",
    "sg:phone":"+49 8171/32916",
    "sg:postcode":"82538",
    "sg:province":"Bayern",
    "wof:name":"Michael Klein Makler",
    "wof:placetype":"venue"
},
  "geometry": {"coordinates":[11.4778146744,47.8666954041],"type":"Point"}
}