{
  "type": "Feature",
  "properties": {
    "iso:country":"DE",
    "sg:address":"Regerstr. 23",
    "sg:city":"Dresden",
    "sg:phone":"+49 351/3104402",
    "sg:postcode":"01309",
    "sg:province":"Sachsen",
    "wof:name":"Dietrich Und Helga Peter",
    "wof:placetype":"venue"
},
  "geometry": {"coordinates":[13.799719,51.051674],"type":"Point"}
}