{
  "type": "Feature",
  "properties": {
    "iso:country":"DE",
    "sg:address":"Bozener Str. 23",
    "sg:city":"Hechingen",
    "sg:phone":"+49 7471/5967",
    "sg:postcode":"72379",
    "sg:province":"Baden-W\u00fcrttemberg",
    "wof:name":"Otto G\u00f6hner",
    "wof:placetype":"venue"
},
  "geometry": {"coordinates":[8.9673633575,48.3469352722],"type":"Point"}
}