{
  "type": "Feature",
  "properties": {
    "iso:country":"DE",
    "sg:address":"Am Zankwald 12",
    "sg:city":"Spiesen-Elversberg",
    "sg:postcode":"66583",
    "sg:province":"Saarland",
    "wof:name":"Pcs-professional Coating Solutions Gmbh",
    "wof:placetype":"venue"
},
  "geometry": {"coordinates":[7.140193,49.310795],"type":"Point"}
}