{
  "type": "Feature",
  "properties": {
    "iso:country":"DE",
    "sg:address":"Stadionstr. 19",
    "sg:city":"Sch\u00f6nebeck",
    "sg:phone":"+49 391/7318766",
    "sg:postcode":"39218",
    "sg:province":"Sachsen-Anhalt",
    "wof:name":"Cangoo Freizeitpark Gmbh",
    "wof:placetype":"venue"
},
  "geometry": {"coordinates":[11.7161960602,52.0135993958],"type":"Point"}
}