{
  "type": "Feature",
  "properties": {
    "iso:country":"DE",
    "sg:address":"Elisabethstr. 19 b",
    "sg:city":"T\u00fc\u00dfling",
    "sg:phone":"+49 8633/1492",
    "sg:postcode":"84577",
    "sg:province":"Bayern",
    "wof:name":"Pilspub Monaco",
    "wof:placetype":"venue"
},
  "geometry": {"coordinates":[12.6010713577,48.2110061646],"type":"Point"}
}