{
  "type": "Feature",
  "properties": {
    "iso:country":"DE",
    "sg:address":"Leonhard-Boldt-Str. 19",
    "sg:city":"Eutin",
    "sg:phone":"+49 4521/8050",
    "sg:postcode":"23701",
    "sg:province":"Schleswig-Holstein",
    "wof:name":"Hotel Seeschlo\u00df Am Kellersee",
    "wof:placetype":"venue"
},
  "geometry": {"coordinates":[10.6047897339,54.1556167603],"type":"Point"}
}