{
  "type": "Feature",
  "properties": {
    "iso:country":"DE",
    "sg:city":"Hankensb\u00fcttel",
    "sg:phone":"+49 5832/980828",
    "sg:postcode":"29386",
    "sg:province":"Niedersachsen",
    "wof:name":"Otter-zentrum Hankensb\u00fcttel",
    "wof:placetype":"venue"
},
  "geometry": {"coordinates":[10.604063,52.731651],"type":"Point"}
}