{
  "type": "Feature",
  "properties": {
    "iso:country":"DE",
    "sg:address":"Lerchenweg 13",
    "sg:city":"Brande-H\u00f6rnerkirchen",
    "sg:phone":"+49 4127/9620",
    "sg:postcode":"25364",
    "sg:province":"Schleswig-Holstein",
    "wof:name":"T. Pahl",
    "wof:placetype":"venue"
},
  "geometry": {"coordinates":[9.700895,53.855507],"type":"Point"}
}