{
  "type": "Feature",
  "properties": {
    "iso:country":"DE",
    "sg:address":"M\u00f6nchweg 29",
    "sg:city":"Rottenburg",
    "sg:phone":"+49 7457/5541",
    "sg:postcode":"72108",
    "sg:province":"Baden-W\u00fcrttemberg",
    "wof:name":"Andrea Renz",
    "wof:placetype":"venue"
},
  "geometry": {"coordinates":[8.8059072495,48.4913825989],"type":"Point"}
}