{
  "type": "Feature",
  "properties": {
    "iso:country":"DE",
    "sg:address":"Koogstr. 15",
    "sg:city":"Karolinenkoog",
    "sg:phone":"+49 4882/65000",
    "sg:postcode":"25774",
    "sg:province":"Schleswig-Holstein",
    "wof:name":"Hotel-restaurant Pfahlershof",
    "wof:placetype":"venue"
},
  "geometry": {"coordinates":[8.9676418304,54.2985267639],"type":"Point"}
}