{
  "type": "Feature",
  "properties": {
    "iso:country":"DE",
    "sg:address":"Postfach 4",
    "sg:city":"Witzmannsberg",
    "sg:postcode":"94104",
    "sg:province":"Bayern",
    "wof:name":"Mehrzweckhalle Enzersdorf",
    "wof:placetype":"venue"
},
  "geometry": {"coordinates":[13.412831,48.714691],"type":"Point"}
}