{
  "type": "Feature",
  "properties": {
    "iso:country":"DE",
    "sg:address":"Rellinghauser Str. 126",
    "sg:city":"Essen",
    "sg:phone":"+49 201/772693",
    "sg:postcode":"45128",
    "sg:province":"Nordrhein-Westfalen",
    "wof:name":"Wesseling",
    "wof:placetype":"venue"
},
  "geometry": {"coordinates":[7.018274,51.442055],"type":"Point"}
}