{
  "type": "Feature",
  "properties": {
    "iso:country":"DE",
    "sg:address":"Peterstaler Str. 31",
    "sg:city":"Heidelberg",
    "sg:phone":"+49 6221/809228",
    "sg:postcode":"69118",
    "sg:province":"Baden-W\u00fcrttemberg",
    "wof:name":"Video-ecke Merklinger",
    "wof:placetype":"venue"
},
  "geometry": {"coordinates":[8.7559328079,49.4211082458],"type":"Point"}
}