{
  "type": "Feature",
  "properties": {
    "iso:country":"DE",
    "sg:address":"Neunkircher Str. 56",
    "sg:city":"Spiesen-Elversberg",
    "sg:phone":"+49 6821/97010",
    "sg:postcode":"66583",
    "sg:province":"Saarland",
    "wof:name":"Volker Werny Ingenieur",
    "wof:placetype":"venue"
},
  "geometry": {"coordinates":[7.1318798065,49.3165473938],"type":"Point"}
}