{
  "type": "Feature",
  "properties": {
    "iso:country":"DE",
    "sg:address":"Gr\u00fcndelweg 65",
    "sg:city":"Haiterbach",
    "sg:phone":"+49 7456/1053",
    "sg:postcode":"72221",
    "sg:province":"Baden-W\u00fcrttemberg",
    "wof:name":"Ernst St\u00f6hr",
    "wof:placetype":"venue"
},
  "geometry": {"coordinates":[8.63630867,48.5474052429],"type":"Point"}
}