{
  "type": "Feature",
  "properties": {
    "iso:country":"DE",
    "sg:address":"Osterstr. 31",
    "sg:city":"Norden",
    "sg:phone":"+49 4931/5202",
    "sg:postcode":"26506",
    "sg:province":"Niedersachsen",
    "wof:name":"B. Kretzmer",
    "wof:placetype":"venue"
},
  "geometry": {"coordinates":[7.2101039886,53.5972213745],"type":"Point"}
}