{
  "type": "Feature",
  "properties": {
    "iso:country":"DE",
    "sg:address":"Bergring 4",
    "sg:city":"Marburg",
    "sg:phone":"+49 6421/31143",
    "sg:postcode":"35041",
    "sg:province":"Hessen",
    "wof:name":"J. Bamberger",
    "wof:placetype":"venue"
},
  "geometry": {"coordinates":[8.74818,50.817364],"type":"Point"}
}