{
  "type": "Feature",
  "properties": {
    "iso:country":"DE",
    "sg:address":"Bernecker Str. 14",
    "sg:city":"Himmelkron",
    "sg:phone":"+49 9227/4545",
    "sg:postcode":"95502",
    "sg:province":"Bayern",
    "wof:name":"Eckbert P\u00f6hlmann Architekt",
    "wof:placetype":"venue"
},
  "geometry": {"coordinates":[11.597942,50.060707],"type":"Point"}
}