{
  "type": "Feature",
  "properties": {
    "iso:country":"DE",
    "sg:address":"Heiseder Str. 11",
    "sg:city":"Sarstedt",
    "sg:phone":"+49 5066/3802",
    "sg:postcode":"31157",
    "sg:province":"Niedersachsen",
    "wof:name":"Gasthaus Konrad Dormeier Inh. W. Deckert",
    "wof:placetype":"venue"
},
  "geometry": {"coordinates":[9.8525762558,52.2597732544],"type":"Point"}
}