{
  "type": "Feature",
  "properties": {
    "iso:country":"DE",
    "sg:address":"Baumstr. 2",
    "sg:city":"M\u00fcnchen",
    "sg:phone":"+49 89/20239093",
    "sg:postcode":"80469",
    "sg:province":"Bayern",
    "wof:name":"Stefan Henrich Rechtsanwalt",
    "wof:placetype":"venue"
},
  "geometry": {"coordinates":[11.5716762543,48.1269187927],"type":"Point"}
}