{
  "type": "Feature",
  "properties": {
    "iso:country":"DE",
    "sg:address":"Obersteiner Weg 45",
    "sg:city":"Berlin",
    "sg:phone":"+49 30/4714465",
    "sg:postcode":"13086",
    "sg:province":"Berlin",
    "wof:name":"Walter Jahnke",
    "wof:placetype":"venue"
},
  "geometry": {"coordinates":[13.450956,52.561249],"type":"Point"}
}