{
  "type": "Feature",
  "properties": {
    "iso:country":"DE",
    "sg:address":"Robert-Bosch-Str. 2",
    "sg:city":"Ichenhausen",
    "sg:phone":"+49 8223/3093",
    "sg:postcode":"89335",
    "sg:province":"Bayern",
    "wof:name":"Stumb\u00f6ck Kg",
    "wof:placetype":"venue"
},
  "geometry": {"coordinates":[10.309565,48.376934],"type":"Point"}
}