{
  "type": "Feature",
  "properties": {
    "iso:country":"DE",
    "sg:address":"Ernst-Heinrich-Geist-Str. 5",
    "sg:city":"Frechen",
    "sg:phone":"+49 2234/954550",
    "sg:postcode":"50226",
    "sg:province":"Nordrhein-Westfalen",
    "wof:name":"1. Fc K\u00f6ln Marketing Und Vertriebs Gmbh",
    "wof:placetype":"venue"
},
  "geometry": {"coordinates":[6.817837,50.908085],"type":"Point"}
}