{
  "type": "Feature",
  "properties": {
    "iso:country":"DE",
    "sg:address":"Nu\u00dfanger 4",
    "sg:city":"Goslar",
    "sg:phone":"+49 5321/318688",
    "sg:postcode":"38640",
    "sg:province":"Niedersachsen",
    "wof:name":"Gastst\u00e4tte Gl\u00fcck-auf",
    "wof:placetype":"venue"
},
  "geometry": {"coordinates":[10.461180687,51.9171524048],"type":"Point"}
}