{
  "type": "Feature",
  "properties": {
    "iso:country":"DE",
    "sg:address":"Lange Str. 47",
    "sg:city":"Beverungen",
    "sg:phone":"+49 5273/1308",
    "sg:postcode":"37688",
    "sg:province":"Nordrhein-Westfalen",
    "wof:name":"J\u00fcrgen Knipping Fleischerfachgesch\u00e4ft E. K.",
    "wof:placetype":"venue"
},
  "geometry": {"coordinates":[9.3736629486,51.6651649475],"type":"Point"}
}