{
  "type": "Feature",
  "properties": {
    "iso:country":"DE",
    "sg:address":"M\u00f6rfelder Landstr. 117",
    "sg:city":"Frankfurt",
    "sg:phone":"+49 69/9636480",
    "sg:postcode":"60598",
    "sg:province":"Hessen",
    "wof:name":"Gebser & Partner Ag",
    "wof:placetype":"venue"
},
  "geometry": {"coordinates":[8.6832580566,50.0958862305],"type":"Point"}
}