{
  "type": "Feature",
  "properties": {
    "iso:country":"DE",
    "sg:address":"Halstenbeker Chaussee 11",
    "sg:city":"Schenefeld",
    "sg:postcode":"22869",
    "sg:province":"Schleswig-Holstein",
    "wof:name":"Basis Bau Gmbh",
    "wof:placetype":"venue"
},
  "geometry": {"coordinates":[9.816394,53.60495],"type":"Point"}
}