{
  "type": "Feature",
  "properties": {
    "iso:country":"DE",
    "sg:address":"Seminarweg 1",
    "sg:city":"Pfaffenhausen",
    "sg:phone":"+49 8265/202",
    "sg:postcode":"87772",
    "sg:province":"Bayern",
    "wof:name":"Xaver Schl\u00f6gel Kg Steinmetz",
    "wof:placetype":"venue"
},
  "geometry": {"coordinates":[10.4567470551,48.1201286316],"type":"Point"}
}