{
  "type": "Feature",
  "properties": {
    "iso:country":"DE",
    "sg:address":"Stiller Tor 3",
    "sg:city":"Schmalkalden",
    "sg:phone":"+49 3683/603527",
    "sg:postcode":"98574",
    "sg:province":"Th\u00fcringen",
    "wof:name":"Martin Giel",
    "wof:placetype":"venue"
},
  "geometry": {"coordinates":[10.455384,50.720711],"type":"Point"}
}