{
  "type": "Feature",
  "properties": {
    "iso:country":"DE",
    "sg:address":"Tiefer Weg 9",
    "sg:city":"Goldenstedt",
    "sg:phone":"+49 4444/505",
    "sg:postcode":"49424",
    "sg:province":"Niedersachsen",
    "wof:name":"Stephanus Marischen",
    "wof:placetype":"venue"
},
  "geometry": {"coordinates":[8.436653,52.79081],"type":"Point"}
}