{
  "type": "Feature",
  "properties": {
    "iso:country":"DE",
    "sg:address":"Insinger Str. 6",
    "sg:city":"Wettringen",
    "sg:phone":"+49 9869/255",
    "sg:postcode":"91631",
    "sg:province":"Bayern",
    "wof:name":"P. Stahl",
    "wof:placetype":"venue"
},
  "geometry": {"coordinates":[10.1587028503,49.2596168518],"type":"Point"}
}