{
  "type": "Feature",
  "properties": {
    "iso:country":"DE",
    "sg:address":"M\u00fcnsterstr. 31",
    "sg:city":"Lengerich",
    "sg:phone":"+49 5481/37030",
    "sg:postcode":"49525",
    "sg:province":"Nordrhein-Westfalen",
    "wof:name":"Hasret-reisen",
    "wof:placetype":"venue"
},
  "geometry": {"coordinates":[7.8501648903,52.1860542297],"type":"Point"}
}