{
  "type": "Feature",
  "properties": {
    "iso:country":"DE",
    "sg:address":"Logaer Weg 94",
    "sg:city":"Leer",
    "sg:phone":"+49 491/73320",
    "sg:postcode":"26789",
    "sg:province":"Niedersachsen",
    "wof:name":"Wolfgang Rau",
    "wof:placetype":"venue"
},
  "geometry": {"coordinates":[7.4883379936,53.2400512695],"type":"Point"}
}