{
  "type": "Feature",
  "properties": {
    "iso:country":"DE",
    "sg:address":"Breitscheidstr. 103",
    "sg:city":"Rudolstadt",
    "sg:phone":"+49 3672/52010",
    "sg:postcode":"07407",
    "sg:province":"Th\u00fcringen",
    "wof:name":"Alceru Schwarza Gmbh- Alternative Celluloseverfahren",
    "wof:placetype":"venue"
},
  "geometry": {"coordinates":[11.3284330368,50.7015838623],"type":"Point"}
}