{
  "type": "Feature",
  "properties": {
    "iso:country":"DE",
    "sg:address":"Waldh\u00f6fe 12",
    "sg:city":"S\u00f6gel",
    "sg:phone":"+49 5952/1229",
    "sg:postcode":"49751",
    "sg:province":"Niedersachsen",
    "wof:name":"Hotel Alfons T\u00e4lkers",
    "wof:placetype":"venue"
},
  "geometry": {"coordinates":[7.5609898567,52.8271827698],"type":"Point"}
}