{
  "type": "Feature",
  "properties": {
    "iso:country":"DE",
    "sg:address":"Im Dorfe 16a",
    "sg:city":"Heist",
    "sg:phone":"+49 4122/83401",
    "sg:postcode":"25492",
    "sg:province":"Schleswig-Holstein",
    "wof:name":"V.-h. Both",
    "wof:placetype":"venue"
},
  "geometry": {"coordinates":[9.6680469513,53.6538276672],"type":"Point"}
}