{
  "type": "Feature",
  "properties": {
    "iso:country":"DE",
    "sg:address":"74424",
    "sg:city":"B\u00fchlertann",
    "sg:phone":"+49 7973/6011",
    "sg:postcode":"74424",
    "sg:province":"Baden-W\u00fcrttemberg",
    "wof:name":"Raiffeisenbank Oberes B\u00fchertal Eg",
    "wof:placetype":"venue"
},
  "geometry": {"coordinates":[9.90913,49.040886],"type":"Point"}
}