{
  "type": "Feature",
  "properties": {
    "iso:country":"DE",
    "sg:address":"Martinistr. 4",
    "sg:city":"Geisenfeld",
    "sg:phone":"+49 8452/2977",
    "sg:postcode":"85290",
    "sg:province":"Bayern",
    "wof:name":"Karl Maier",
    "wof:placetype":"venue"
},
  "geometry": {"coordinates":[11.672565,48.645287],"type":"Point"}
}