{
  "type": "Feature",
  "properties": {
    "iso:country":"DE",
    "sg:address":"Schwaige",
    "sg:city":"Starnberg",
    "sg:phone":"+49 8151/8342",
    "sg:postcode":"82319",
    "sg:province":"Bayern",
    "wof:name":"Hans Hauser",
    "wof:placetype":"venue"
},
  "geometry": {"coordinates":[11.349459,48.010548],"type":"Point"}
}