{
  "type": "Feature",
  "properties": {
    "iso:country":"DE",
    "sg:address":"Im W\u00f6rth 3",
    "sg:city":"Rockenhausen",
    "sg:phone":"+49 6361/7430",
    "sg:postcode":"67806",
    "sg:province":"Rheinland-Pfalz",
    "wof:name":"Rittmann",
    "wof:placetype":"venue"
},
  "geometry": {"coordinates":[7.820871,49.633144],"type":"Point"}
}