{
  "type": "Feature",
  "properties": {
    "iso:country":"DE",
    "sg:address":"Hafenmarkt 1",
    "sg:city":"Kaufbeuren",
    "sg:phone":"+49 8341/14904",
    "sg:postcode":"87600",
    "sg:province":"Bayern",
    "wof:name":"Hefele Orthop\u00e4die-technik Gmbh",
    "wof:placetype":"venue"
},
  "geometry": {"coordinates":[10.6211881638,47.8806724548],"type":"Point"}
}