{
  "type": "Feature",
  "properties": {
    "iso:country":"DE",
    "sg:address":"Steinbruchstr. 20",
    "sg:city":"Polling",
    "sg:phone":"+49 881/40245",
    "sg:postcode":"82398",
    "sg:province":"Bayern",
    "wof:name":"Eberhard G\u00fcnther & Sohn Fu\u00dfbodentechnik Gmbh & Co. Kg",
    "wof:placetype":"venue"
},
  "geometry": {"coordinates":[11.143475,47.8088],"type":"Point"}
}