{
  "type": "Feature",
  "properties": {
    "iso:country":"DE",
    "sg:address":"Eisinger Str. 11",
    "sg:city":"K\u00f6nigsbach-Stein",
    "sg:phone":"+49 7232/9815",
    "sg:postcode":"75203",
    "sg:province":"Baden-W\u00fcrttemberg",
    "wof:name":"Helmut Vollmer",
    "wof:placetype":"venue"
},
  "geometry": {"coordinates":[8.644604,48.961418],"type":"Point"}
}