{
  "type": "Feature",
  "properties": {
    "iso:country":"DE",
    "sg:address":"Marianne-Heese-Str. 22",
    "sg:city":"Werl",
    "sg:phone":"+49 2922/97050",
    "sg:postcode":"59457",
    "sg:province":"Nordrhein-Westfalen",
    "wof:name":"Christa Sodenkamp-heine Steuerberaterin",
    "wof:placetype":"venue"
},
  "geometry": {"coordinates":[7.9027891159,51.5540313721],"type":"Point"}
}