{
  "type": "Feature",
  "properties": {
    "iso:country":"DE",
    "sg:address":"Wilhelmstr. 22",
    "sg:city":"Ulm",
    "sg:phone":"+49 731/15530",
    "sg:postcode":"89073",
    "sg:province":"Baden-W\u00fcrttemberg",
    "wof:name":"Open Shop Holding Ag",
    "wof:placetype":"venue"
},
  "geometry": {"coordinates":[9.988476,48.405422],"type":"Point"}
}