{
  "type": "Feature",
  "properties": {
    "iso:country":"DE",
    "sg:address":"Birkenweg 3",
    "sg:city":"L\u00fcbstorf",
    "sg:phone":"+49 3867/202",
    "sg:postcode":"19069",
    "sg:province":"Mecklenburg-Vorpommern",
    "wof:name":"G\u00fcnter Kr\u00fcger Finanzberater",
    "wof:placetype":"venue"
},
  "geometry": {"coordinates":[11.4093818665,53.7274665833],"type":"Point"}
}