{
  "type": "Feature",
  "properties": {
    "iso:country":"DE",
    "sg:address":"Sch\u00f6nstr. 12",
    "sg:city":"M\u00fcnchen",
    "sg:postcode":"81543",
    "sg:province":"Bayern",
    "wof:name":"S.& P. Consult - Stein & Part. Verm\u00f6gv. Sow. Gastron.- U. Int",
    "wof:placetype":"venue"
},
  "geometry": {"coordinates":[11.5675468445,48.1106948853],"type":"Point"}
}