{
  "type": "Feature",
  "properties": {
    "iso:country":"DE",
    "sg:address":"Bollmannsruh 12a",
    "sg:city":"Bollmannsruh",
    "sg:postcode":"14778",
    "sg:province":"Brandenburg",
    "wof:name":"C. Schulz Ingenieur",
    "wof:placetype":"venue"
},
  "geometry": {"coordinates":[12.681139946,52.5077667236],"type":"Point"}
}