{
  "type": "Feature",
  "properties": {
    "iso:country":"DE",
    "sg:address":"Marktstr. 8",
    "sg:city":"Marktbreit",
    "sg:phone":"+49 9332/50540",
    "sg:postcode":"97340",
    "sg:province":"Bayern",
    "wof:name":"Hotel Zum L\u00f6wen",
    "wof:placetype":"venue"
},
  "geometry": {"coordinates":[10.1436367035,49.6676864624],"type":"Point"}
}