{
  "type": "Feature",
  "properties": {
    "iso:country":"DE",
    "sg:address":"Rappenauer Str. 40-44",
    "sg:city":"Kirchardt",
    "sg:phone":"+49 7266/91400",
    "sg:postcode":"74912",
    "sg:province":"Baden-W\u00fcrttemberg",
    "wof:name":"Dietz Grabmale Und Natursteinwerk Gmbh",
    "wof:placetype":"venue"
},
  "geometry": {"coordinates":[8.9986600876,49.2077903748],"type":"Point"}
}