{
  "type": "Feature",
  "properties": {
    "iso:country":"DE",
    "sg:address":"S\u00fcdring 3",
    "sg:city":"Raesfeld",
    "sg:phone":"+49 2865/1306",
    "sg:postcode":"46348",
    "sg:province":"Nordrhein-Westfalen",
    "wof:name":"Reinhard G. Nie\u00dfling",
    "wof:placetype":"venue"
},
  "geometry": {"coordinates":[6.8464331627,51.7671546936],"type":"Point"}
}