{
  "type": "Feature",
  "properties": {
    "iso:country":"DE",
    "sg:address":"Gr\u00fcnbacher Str. 33",
    "sg:city":"Moosinning",
    "sg:phone":"+49 8123/1895",
    "sg:postcode":"85452",
    "sg:province":"Bayern",
    "wof:name":"Michael Nebauer",
    "wof:placetype":"venue"
},
  "geometry": {"coordinates":[11.780688,48.287727],"type":"Point"}
}