{
  "type": "Feature",
  "properties": {
    "iso:country":"DE",
    "sg:address":"Firmungstr. 44-46",
    "sg:city":"Koblenz",
    "sg:phone":"+49 261/34615",
    "sg:postcode":"56068",
    "sg:province":"Rheinland-Pfalz",
    "wof:name":"Antica Anny Poeschmann",
    "wof:placetype":"venue"
},
  "geometry": {"coordinates":[7.5977120399,50.3608932495],"type":"Point"}
}