{
  "type": "Feature",
  "properties": {
    "iso:country":"DE",
    "sg:address":"Am Binzelberg 10",
    "sg:city":"Heusweiler",
    "sg:phone":"+49 6806/78828",
    "sg:postcode":"66265",
    "sg:province":"Saarland",
    "wof:name":"R. U. M. Schr\u00f6ck Architekten",
    "wof:placetype":"venue"
},
  "geometry": {"coordinates":[6.951442,49.328674],"type":"Point"}
}