{
  "type": "Feature",
  "properties": {
    "iso:country":"DE",
    "sg:address":"Haarenufer 34",
    "sg:city":"Oldenburg",
    "sg:phone":"+49 441/971770",
    "sg:postcode":"26122",
    "sg:province":"Niedersachsen",
    "wof:name":"Senkowski",
    "wof:placetype":"venue"
},
  "geometry": {"coordinates":[8.1968078613,53.1416511536],"type":"Point"}
}