{
  "type": "Feature",
  "properties": {
    "iso:country":"DE",
    "sg:address":"M\u00fchlbachring 37",
    "sg:city":"Oberthulba",
    "sg:phone":"+49 9736/9491",
    "sg:postcode":"97723",
    "sg:province":"Bayern",
    "wof:name":"Mergenthal",
    "wof:placetype":"venue"
},
  "geometry": {"coordinates":[9.924568,50.180988],"type":"Point"}
}