{
  "type": "Feature",
  "properties": {
    "iso:country":"DE",
    "sg:address":"Hauptstr. 20",
    "sg:city":"Herdorf",
    "sg:phone":"+49 2744/269",
    "sg:postcode":"57562",
    "sg:province":"Rheinland-Pfalz",
    "wof:name":"Johannes Lehmann",
    "wof:placetype":"venue"
},
  "geometry": {"coordinates":[7.9495692253,50.7779655457],"type":"Point"}
}