{
  "type": "Feature",
  "properties": {
    "iso:country":"DE",
    "sg:address":"L\u00fcbecker Str. 34",
    "sg:city":"Ammersbek",
    "sg:phone":"+49 40/6050646",
    "sg:postcode":"22949",
    "sg:province":"Schleswig-Holstein",
    "wof:name":"Hoisb\u00fctteler M\u00fchle Backwaren-vertriebs Gmbh",
    "wof:placetype":"venue"
},
  "geometry": {"coordinates":[10.177823,53.694256],"type":"Point"}
}