{
  "type": "Feature",
  "properties": {
    "iso:country":"DE",
    "sg:address":"Necklenbroicher Str. 74",
    "sg:city":"Meerbusch",
    "sg:phone":"+49 2132/6999",
    "sg:postcode":"40667",
    "sg:province":"Nordrhein-Westfalen",
    "wof:name":"Werner Weiers",
    "wof:placetype":"venue"
},
  "geometry": {"coordinates":[6.6797881126,51.2506408691],"type":"Point"}
}