{
  "type": "Feature",
  "properties": {
    "iso:country":"DE",
    "sg:address":"Kanzlerstr. 4",
    "sg:city":"D\u00fcsseldorf",
    "sg:postcode":"40472",
    "sg:province":"Nordrhein-Westfalen",
    "wof:name":"Immo Project Gmbh",
    "wof:placetype":"venue"
},
  "geometry": {"coordinates":[6.82305,51.263287],"type":"Point"}
}