{
  "type": "Feature",
  "properties": {
    "iso:country":"DE",
    "sg:address":"Regendorfer Str. 35",
    "sg:city":"Regenstauf",
    "sg:phone":"+49 9402/70586",
    "sg:postcode":"93128",
    "sg:province":"Bayern",
    "wof:name":"Ebv Makler-kontor Gmbh",
    "wof:placetype":"venue"
},
  "geometry": {"coordinates":[12.1176519394,49.1226272583],"type":"Point"}
}