{
  "type": "Feature",
  "properties": {
    "iso:country":"DE",
    "sg:address":"St.-Georgen-Str. 16",
    "sg:city":"Ingoldingen",
    "sg:phone":"+49 7355/547",
    "sg:postcode":"88456",
    "sg:province":"Baden-W\u00fcrttemberg",
    "wof:name":"Anton Sproll",
    "wof:placetype":"venue"
},
  "geometry": {"coordinates":[9.738899,48.025604],"type":"Point"}
}