{
  "type": "Feature",
  "properties": {
    "iso:country":"DE",
    "sg:address":"Schlo\u00dfstr. 4",
    "sg:city":"W\u00fcrselen",
    "sg:phone":"+49 2405/88473",
    "sg:postcode":"52146",
    "sg:province":"Nordrhein-Westfalen",
    "wof:name":"Wilfried Gorgels",
    "wof:placetype":"venue"
},
  "geometry": {"coordinates":[6.113961,50.818478],"type":"Point"}
}