{
  "type": "Feature",
  "properties": {
    "iso:country":"DE",
    "sg:address":"S\u00e4gm\u00fchlweg 4",
    "sg:city":"Bad Schussenried",
    "sg:phone":"+49 7583/2500",
    "sg:postcode":"88427",
    "sg:province":"Baden-W\u00fcrttemberg",
    "wof:name":"Waliso A. Walser",
    "wof:placetype":"venue"
},
  "geometry": {"coordinates":[9.6639041901,47.9968757629],"type":"Point"}
}