{
  "type": "Feature",
  "properties": {
    "iso:country":"DE",
    "sg:address":"Welfenstra\u00dfe 10",
    "sg:city":"Steingaden",
    "sg:postcode":"86989",
    "sg:province":"Bayern",
    "wof:name":"Gasthof Klosterbr\u00e4ust\u00fcberl Steingaden",
    "wof:placetype":"venue"
},
  "geometry": {"coordinates":[10.8617172241,47.7009315491],"type":"Point"}
}