{
  "type": "Feature",
  "properties": {
    "iso:country":"DE",
    "sg:address":"Relingenstra\u00dfe 4",
    "sg:city":"Augsburg",
    "sg:phone":"+49 821/5030530",
    "sg:postcode":"86153",
    "sg:province":"Bayern",
    "wof:name":"Augsburger Panther Eishokey Gmbh",
    "wof:placetype":"venue"
},
  "geometry": {"coordinates":[10.8857183456,48.3746833801],"type":"Point"}
}