{
  "type": "Feature",
  "properties": {
    "iso:country":"DE",
    "sg:address":"Lindenallee 18",
    "sg:city":"G\u00f6ttingen",
    "sg:phone":"+49 5502/1538",
    "sg:postcode":"37079",
    "sg:province":"Niedersachsen",
    "wof:name":"Fredi Wieneke Steuerberater",
    "wof:placetype":"venue"
},
  "geometry": {"coordinates":[9.8203449249,51.5393714905],"type":"Point"}
}