{
  "type": "Feature",
  "properties": {
    "iso:country":"DE",
    "sg:address":"Karl-Marx-Str. 9",
    "sg:city":"Kaiserslautern",
    "sg:phone":"+49 631/64444",
    "sg:postcode":"67655",
    "sg:province":"Rheinland-Pfalz",
    "wof:name":"Berthold Becht Rechtsanwalt",
    "wof:placetype":"venue"
},
  "geometry": {"coordinates":[7.7727179527,49.4434432983],"type":"Point"}
}