{
  "type": "Feature",
  "properties": {
    "iso:country":"DE",
    "sg:address":"Adalbertsteinweg 44",
    "sg:city":"Aachen",
    "sg:phone":"+49 241/542036",
    "sg:postcode":"52070",
    "sg:province":"Nordrhein-Westfalen",
    "wof:name":"Rosa Hansen",
    "wof:placetype":"venue"
},
  "geometry": {"coordinates":[6.100313,50.774395],"type":"Point"}
}