{
  "type": "Feature",
  "properties": {
    "iso:country":"DE",
    "sg:address":"Westf\u00e4lische Str. 63",
    "sg:city":"Berlin",
    "sg:phone":"+49 30/5144862",
    "sg:postcode":"10709",
    "sg:province":"Berlin",
    "wof:name":"K. Fowler & Peter Janke Gbr",
    "wof:placetype":"venue"
},
  "geometry": {"coordinates":[13.2969331741,52.4955635071],"type":"Point"}
}