{
  "type": "Feature",
  "properties": {
    "iso:country":"DE",
    "sg:address":"Zaininger Str. 13",
    "sg:city":"R\u00f6merstein",
    "sg:phone":"+49 4973/8293730",
    "sg:postcode":"72587",
    "sg:province":"Baden-W\u00fcrttemberg",
    "wof:name":"Rueckle Gmbh",
    "wof:placetype":"venue"
},
  "geometry": {"coordinates":[9.5148830414,48.4916610718],"type":"Point"}
}