{
  "type": "Feature",
  "properties": {
    "iso:country":"DE",
    "sg:address":"Bodenseestr. 84",
    "sg:city":"M\u00fcnchen",
    "sg:phone":"+49 89/835717",
    "sg:postcode":"81243",
    "sg:province":"Bayern",
    "wof:name":"D.w. Druck & Werbeservice Gmbh",
    "wof:placetype":"venue"
},
  "geometry": {"coordinates":[11.4450788498,48.1459121704],"type":"Point"}
}