{
  "type": "Feature",
  "properties": {
    "iso:country":"DE",
    "sg:address":"Albstr 8",
    "sg:city":"Neuhausen",
    "sg:phone":"+49 7158/9560690",
    "sg:postcode":"73765",
    "sg:province":"Baden-W\u00fcrttemberg",
    "wof:name":"Eberhard Bolz",
    "wof:placetype":"venue"
},
  "geometry": {"coordinates":[8.775779,48.79483],"type":"Point"}
}