{
  "type": "Feature",
  "properties": {
    "iso:country":"DE",
    "sg:address":"Schmalenend 14",
    "sg:city":"Viersen",
    "sg:phone":"+49 2153/3094",
    "sg:postcode":"41751",
    "sg:province":"Nordrhein-Westfalen",
    "wof:name":"Erich Wilms Werbeatelier Gmbh",
    "wof:placetype":"venue"
},
  "geometry": {"coordinates":[6.2740721703,51.2678337097],"type":"Point"}
}