{
  "type": "Feature",
  "properties": {
    "iso:country":"DE",
    "sg:address":"Kirchplatz 2",
    "sg:city":"Weingarten",
    "sg:postcode":"88250",
    "sg:province":"Baden-W\u00fcrttemberg",
    "wof:name":"Arbeitsstelle F. Wirtschafts- Didaktik",
    "wof:placetype":"venue"
},
  "geometry": {"coordinates":[9.6458721161,47.80909729],"type":"Point"}
}