{
  "type": "Feature",
  "properties": {
    "iso:country":"DE",
    "sg:address":"Grasgasse 332",
    "sg:city":"Landshut",
    "sg:phone":"+49 871/28200",
    "sg:postcode":"84028",
    "sg:province":"Bayern",
    "wof:name":"Trachtenstubn Am Rathaus Ruth Vogl",
    "wof:placetype":"venue"
},
  "geometry": {"coordinates":[12.1524620056,48.5364532471],"type":"Point"}
}