{
  "type": "Feature",
  "properties": {
    "iso:country":"DE",
    "sg:address":"Wilhelmstr. 2",
    "sg:city":"Hameln",
    "sg:phone":"+49 5151/958755",
    "sg:postcode":"31785",
    "sg:province":"Niedersachsen",
    "wof:name":"Matthias Schmitz Architekt",
    "wof:placetype":"venue"
},
  "geometry": {"coordinates":[9.361476,52.102882],"type":"Point"}
}