{
  "type": "Feature",
  "properties": {
    "iso:country":"DE",
    "sg:address":"Landsberger Allee 131a",
    "sg:city":"Berlin",
    "sg:phone":"+49 30/9710890",
    "sg:postcode":"10369",
    "sg:province":"Berlin",
    "wof:name":"Agt Partner Gmbh",
    "wof:placetype":"venue"
},
  "geometry": {"coordinates":[13.462245,52.530167],"type":"Point"}
}