{
  "type": "Feature",
  "properties": {
    "iso:country":"DE",
    "sg:address":"Gagarinstr. 11",
    "sg:city":"Schwerin",
    "sg:phone":"+49 385/2013940",
    "sg:postcode":"19063",
    "sg:province":"Mecklenburg-Vorpommern",
    "wof:name":"Carl H. Gressmann Inh. Manfred Thur",
    "wof:placetype":"venue"
},
  "geometry": {"coordinates":[11.458785,53.59523],"type":"Point"}
}