{
  "type": "Feature",
  "properties": {
    "iso:country":"DE",
    "sg:address":"Nagelstr. 14",
    "sg:city":"Eberswalde",
    "sg:phone":"+49 3334/22825",
    "sg:postcode":"16225",
    "sg:province":"Brandenburg",
    "wof:name":"Klaus Conrad",
    "wof:placetype":"venue"
},
  "geometry": {"coordinates":[13.824001,52.833633],"type":"Point"}
}