{
  "type": "Feature",
  "properties": {
    "iso:country":"DE",
    "sg:address":"Heinrich-Lanz-Str. 24",
    "sg:city":"Markt Indersdorf",
    "sg:phone":"+49 8136/1018",
    "sg:postcode":"85229",
    "sg:province":"Bayern",
    "wof:name":"Hans Fischer",
    "wof:placetype":"venue"
},
  "geometry": {"coordinates":[11.37596035,48.3503036499],"type":"Point"}
}