{
  "type": "Feature",
  "properties": {
    "iso:country":"DE",
    "sg:address":"Bahnstr. 38",
    "sg:city":"D\u00fcsseldorf",
    "sg:phone":"+49 211/866360",
    "sg:postcode":"40210",
    "sg:province":"Nordrhein-Westfalen",
    "wof:name":"Westf\u00e4lische Hypothekenbank Ag",
    "wof:placetype":"venue"
},
  "geometry": {"coordinates":[6.7824249268,51.219871521],"type":"Point"}
}