{
  "type": "Feature",
  "properties": {
    "iso:country":"DE",
    "sg:address":"Kalkweg 17",
    "sg:city":"D\u00fcsseldorf",
    "sg:phone":"+49 203/997980",
    "sg:postcode":"40489",
    "sg:province":"Nordrhein-Westfalen",
    "wof:name":"Peter Peiffer Steuerberater",
    "wof:placetype":"venue"
},
  "geometry": {"coordinates":[6.7828798294,51.3392906189],"type":"Point"}
}