{
  "type": "Feature",
  "properties": {
    "iso:country":"DE",
    "sg:address":"Klein Feldhus 1",
    "sg:city":"Rastede",
    "sg:postcode":"26180",
    "sg:province":"Niedersachsen",
    "wof:name":"In Vento Beteiligungs- Gmbh",
    "wof:placetype":"venue"
},
  "geometry": {"coordinates":[8.222292,53.214916],"type":"Point"}
}