{
  "type": "Feature",
  "properties": {
    "iso:country":"DE",
    "sg:address":"Ausschl\u00e4ger Weg 37-39",
    "sg:city":"Hamburg",
    "sg:phone":"+49 40/259074",
    "sg:postcode":"20537",
    "sg:province":"Hamburg",
    "wof:name":"Brink Gmbh",
    "wof:placetype":"venue"
},
  "geometry": {"coordinates":[10.0355520248,53.5515441895],"type":"Point"}
}