{
  "type": "Feature",
  "properties": {
    "iso:country":"DE",
    "sg:address":"Ostdeutsche Str. 19",
    "sg:city":"Sehnde",
    "sg:phone":"+49 5132/866386",
    "sg:postcode":"31319",
    "sg:province":"Niedersachsen",
    "wof:name":"Andre Meyer Architekt",
    "wof:placetype":"venue"
},
  "geometry": {"coordinates":[9.893176,52.346413],"type":"Point"}
}