{
  "type": "Feature",
  "properties": {
    "iso:country":"DE",
    "sg:address":"Klaus-Groth-Str. 9",
    "sg:city":"Eutin",
    "sg:phone":"+49 4521/9585",
    "sg:postcode":"23701",
    "sg:province":"Schleswig-Holstein",
    "wof:name":"Dieter Ullrich",
    "wof:placetype":"venue"
},
  "geometry": {"coordinates":[10.612008,54.129429],"type":"Point"}
}