{
  "type": "Feature",
  "properties": {
    "iso:country":"DE",
    "sg:address":"Heimhuder Str. 16",
    "sg:city":"Hamburg",
    "sg:phone":"+49 40/445239",
    "sg:postcode":"20148",
    "sg:province":"Hamburg",
    "wof:name":"Pension Haus Heimhude",
    "wof:placetype":"venue"
},
  "geometry": {"coordinates":[9.9929237366,53.5650672913],"type":"Point"}
}