{
  "type": "Feature",
  "properties": {
    "iso:country":"DE",
    "sg:address":"K\u00fcstriner Str. 1",
    "sg:city":"Seelow",
    "sg:phone":"+49 3346/844344",
    "sg:postcode":"15306",
    "sg:province":"Brandenburg",
    "wof:name":"Pension Centrum Am Markt",
    "wof:placetype":"venue"
},
  "geometry": {"coordinates":[14.3820819855,52.5338897705],"type":"Point"}
}