{
  "type": "Feature",
  "properties": {
    "iso:country":"DE",
    "sg:address":"St.-Michael-Str. 3",
    "sg:city":"Schwalmtal",
    "sg:phone":"+49 2163/943030",
    "sg:postcode":"41366",
    "sg:province":"Nordrhein-Westfalen",
    "wof:name":"Br\u00fcggener Reiseb\u00fcro Richter Gmbh",
    "wof:placetype":"venue"
},
  "geometry": {"coordinates":[6.2739491463,51.2143669128],"type":"Point"}
}