{
  "type": "Feature",
  "properties": {
    "iso:country":"DE",
    "sg:address":"Stresemannallee 35",
    "sg:city":"Frankfurt",
    "sg:phone":"+49 69/639536",
    "sg:postcode":"60596",
    "sg:province":"Hessen",
    "wof:name":"Heinrich Freitag Rechtsanwalt",
    "wof:placetype":"venue"
},
  "geometry": {"coordinates":[8.6710596085,50.0966796875],"type":"Point"}
}