{
  "type": "Feature",
  "properties": {
    "iso:country":"DE",
    "sg:address":"Wildpfad 7",
    "sg:city":"Berlin",
    "sg:phone":"+49 30812",
    "sg:postcode":"14193",
    "sg:province":"Berlin",
    "wof:name":"H\u00e4user Makler Berlin",
    "wof:placetype":"venue"
},
  "geometry": {"coordinates":[13.2747297287,52.4772071838],"type":"Point"}
}