{
  "type": "Feature",
  "properties": {
    "iso:country":"DE",
    "sg:address":"Odfeldstr. 15",
    "sg:city":"Eschershausen",
    "sg:phone":"+49 5534/999841",
    "sg:postcode":"37632",
    "sg:province":"Niedersachsen",
    "wof:name":"Marcus Sievers",
    "wof:placetype":"venue"
},
  "geometry": {"coordinates":[9.629986763,51.9289703369],"type":"Point"}
}