{
  "type": "Feature",
  "properties": {
    "iso:country":"DE",
    "sg:address":"Druckereistr.",
    "sg:city":"Leipzig",
    "sg:phone":"+49 341/4618888",
    "sg:postcode":"04159",
    "sg:province":"Sachsen",
    "wof:name":"Theisen Baumaschinen",
    "wof:placetype":"venue"
},
  "geometry": {"coordinates":[12.312211,51.37862],"type":"Point"}
}