{
  "type": "Feature",
  "properties": {
    "iso:country":"DE",
    "sg:address":"Frankfurter Str. 1",
    "sg:city":"Brechen",
    "sg:phone":"+49 6483/7000",
    "sg:postcode":"65611",
    "sg:province":"Hessen",
    "wof:name":"Trost Isolierungen W\u00e4rme- K\u00e4lte- Schallschutz- Und",
    "wof:placetype":"venue"
},
  "geometry": {"coordinates":[8.1981935501,50.3490371704],"type":"Point"}
}