{
  "type": "Feature",
  "properties": {
    "iso:country":"DE",
    "sg:address":"K\u00e4the-Niederkirchner-Str. 21",
    "sg:city":"Berlin",
    "sg:phone":"+49 30/4252062",
    "sg:postcode":"10407",
    "sg:province":"Berlin",
    "wof:name":"Rolf Lindemann",
    "wof:placetype":"venue"
},
  "geometry": {"coordinates":[13.43372,52.529564],"type":"Point"}
}