{
  "type": "Feature",
  "properties": {
    "iso:country":"DE",
    "sg:address":"Breslauer Str. 5",
    "sg:city":"Meschede",
    "sg:phone":"+49 291/82254",
    "sg:postcode":"59872",
    "sg:province":"Nordrhein-Westfalen",
    "wof:name":"R. Eichler",
    "wof:placetype":"venue"
},
  "geometry": {"coordinates":[8.2735443115,51.3592567444],"type":"Point"}
}