{
  "type": "Feature",
  "properties": {
    "iso:country":"DE",
    "sg:address":"Appenzeller Str. 6",
    "sg:city":"N\u00fcrnberg",
    "sg:phone":"+49 911/615600",
    "sg:postcode":"90431",
    "sg:province":"Bayern",
    "wof:name":"Robert H. Braun Gmbh",
    "wof:placetype":"venue"
},
  "geometry": {"coordinates":[11.0222358704,49.4395942688],"type":"Point"}
}