{
  "type": "Feature",
  "properties": {
    "iso:country":"DE",
    "sg:address":"Gausekamp 5",
    "sg:city":"Meinersen",
    "sg:phone":"+49 5372/6931",
    "sg:postcode":"38536",
    "sg:province":"Niedersachsen",
    "wof:name":"August Meinecke",
    "wof:placetype":"venue"
},
  "geometry": {"coordinates":[10.334895,52.465946],"type":"Point"}
}