{
  "type": "Feature",
  "properties": {
    "iso:country":"DE",
    "sg:address":"Rettershof",
    "sg:city":"Kelkheim",
    "sg:phone":"+49 6174/21541",
    "sg:postcode":"65779",
    "sg:province":"Hessen",
    "wof:name":"Restaurant Fr\u00f6hlicher Landmann",
    "wof:placetype":"venue"
},
  "geometry": {"coordinates":[8.4287033081,50.1684379578],"type":"Point"}
}