{
  "type": "Feature",
  "properties": {
    "iso:country":"DE",
    "sg:address":"Niederhofer Weg 1",
    "sg:city":"B\u00f6nen",
    "sg:phone":"+49 2383/8249",
    "sg:postcode":"59199",
    "sg:province":"Nordrhein-Westfalen",
    "wof:name":"Otto Isenbeck",
    "wof:placetype":"venue"
},
  "geometry": {"coordinates":[7.801357,51.612698],"type":"Point"}
}