{
  "type": "Feature",
  "properties": {
    "iso:country":"DE",
    "sg:address":"Stromstr. 41",
    "sg:city":"D\u00fcssseldorf",
    "sg:phone":"+49 211/9023467",
    "sg:postcode":"40221",
    "sg:province":"Nordrhein-Westfalen",
    "wof:name":"Public-vision Tv Und Video Ohg",
    "wof:placetype":"venue"
},
  "geometry": {"coordinates":[-85.766357,38.25489],"type":"Point"}
}