{
  "type": "Feature",
  "properties": {
    "iso:country":"DE",
    "sg:address":"Oranienstr. 39",
    "sg:city":"Wiesbaden",
    "sg:phone":"+49 611/309273",
    "sg:postcode":"65185",
    "sg:province":"Hessen",
    "wof:name":"M. Schaaf",
    "wof:placetype":"venue"
},
  "geometry": {"coordinates":[8.237103,50.07346],"type":"Point"}
}