{
  "type": "Feature",
  "properties": {
    "iso:country":"DE",
    "sg:address":"Heidelberger Str. 49",
    "sg:city":"Sch\u00f6nbrunn",
    "sg:phone":"+49 6262/6894",
    "sg:postcode":"69436",
    "sg:province":"Baden-W\u00fcrttemberg",
    "wof:name":"Hermann Wesch Gmbh",
    "wof:placetype":"venue"
},
  "geometry": {"coordinates":[8.927085,49.393169],"type":"Point"}
}