{
  "type": "Feature",
  "properties": {
    "iso:country":"DE",
    "sg:address":"Edzardstr 85",
    "sg:city":"Leer",
    "sg:phone":"+49 491/63097",
    "sg:postcode":"26789",
    "sg:province":"Niedersachsen",
    "wof:name":"Bgk Industrieservice Gmbh",
    "wof:placetype":"venue"
},
  "geometry": {"coordinates":[7.44007,53.235741],"type":"Point"}
}