{
  "type": "Feature",
  "properties": {
    "iso:country":"DE",
    "sg:address":"Bahnhofstr. 33",
    "sg:city":"Osterholz-Scharmbeck",
    "sg:phone":"+49 4791/4454",
    "sg:postcode":"27711",
    "sg:province":"Niedersachsen",
    "wof:name":"Bahnhofshotel",
    "wof:placetype":"venue"
},
  "geometry": {"coordinates":[8.7972345352,53.2241783142],"type":"Point"}
}