{
  "type": "Feature",
  "properties": {
    "iso:country":"DE",
    "sg:address":"Im Niederfeld 9",
    "sg:city":"V\u00f6hl",
    "sg:phone":"+49 5635/8379",
    "sg:postcode":"34516",
    "sg:province":"Hessen",
    "wof:name":"Markus Knauer",
    "wof:placetype":"venue"
},
  "geometry": {"coordinates":[8.903674,51.154087],"type":"Point"}
}