{
  "type": "Feature",
  "properties": {
    "iso:country":"DE",
    "sg:address":"Bonner Str 211",
    "sg:city":"K\u00f6ln",
    "sg:phone":"+49 221/934988182",
    "sg:postcode":"50968",
    "sg:province":"Nordrhein-Westfalen",
    "wof:name":"Agentur F\u00fcr Werbung Kochlowski Gmbh",
    "wof:placetype":"venue"
},
  "geometry": {"coordinates":[6.967305,50.89299],"type":"Point"}
}