{
  "type": "Feature",
  "properties": {
    "iso:country":"DE",
    "sg:address":"Fasaneneck 3",
    "sg:city":"Gr\u00f6mitz",
    "sg:phone":"+49 4562/22163",
    "sg:postcode":"23743",
    "sg:province":"Schleswig-Holstein",
    "wof:name":"R. Wachholz",
    "wof:placetype":"venue"
},
  "geometry": {"coordinates":[10.971829,54.153679],"type":"Point"}
}