{
  "type": "Feature",
  "properties": {
    "iso:country":"DE",
    "sg:address":"Kampstr. 2",
    "sg:city":"Hagen",
    "sg:phone":"+49 2331/15900",
    "sg:postcode":"58095",
    "sg:province":"Nordrhein-Westfalen",
    "wof:name":"Hanni Andree Immobilienmaklerin",
    "wof:placetype":"venue"
},
  "geometry": {"coordinates":[7.472743988,51.3583145142],"type":"Point"}
}