{
  "type": "Feature",
  "properties": {
    "iso:country":"DE",
    "sg:address":"Landwehrstr. 33",
    "sg:city":"M\u00fcnchen",
    "sg:phone":"+49 89/5525560",
    "sg:postcode":"80336",
    "sg:province":"Bayern",
    "wof:name":"Hotel Garni Andi",
    "wof:placetype":"venue"
},
  "geometry": {"coordinates":[11.5603494644,48.1362075806],"type":"Point"}
}