{
  "type": "Feature",
  "properties": {
    "iso:country":"DE",
    "sg:address":"Parreutstr. 9",
    "sg:city":"Ingolstadt",
    "sg:phone":"+49 841/86747",
    "sg:postcode":"85049",
    "sg:province":"Bayern",
    "wof:name":"Huttenlocher Gmbh",
    "wof:placetype":"venue"
},
  "geometry": {"coordinates":[11.375238,48.772636],"type":"Point"}
}