{
  "type": "Feature",
  "properties": {
    "iso:country":"DE",
    "sg:address":"Hauptlehrer-Lang-Str. 6",
    "sg:city":"Mindelheim",
    "sg:phone":"+49 8261/1409",
    "sg:postcode":"87719",
    "sg:province":"Bayern",
    "wof:name":"Susanne Bauer-dollinger",
    "wof:placetype":"venue"
},
  "geometry": {"coordinates":[10.490437,48.038727],"type":"Point"}
}