{
  "type": "Feature",
  "properties": {
    "iso:country":"DE",
    "sg:address":"Emmertsgrundpassage 4",
    "sg:city":"Heidelberg",
    "sg:phone":"+49 6221/380396",
    "sg:postcode":"69126",
    "sg:province":"Baden-W\u00fcrttemberg",
    "wof:name":"R\u00dcdiger Eggert",
    "wof:placetype":"venue"
},
  "geometry": {"coordinates":[8.6985330582,49.3690719604],"type":"Point"}
}