{
  "type": "Feature",
  "properties": {
    "iso:country":"DE",
    "sg:address":"Leonhardstr. 1",
    "sg:city":"Kipfenberg",
    "sg:phone":"+49 4923/771762",
    "sg:postcode":"85110",
    "sg:province":"Bayern",
    "wof:name":"Re-pak Verpackungs Gmbh",
    "wof:placetype":"venue"
},
  "geometry": {"coordinates":[7.8708930016,51.5084877014],"type":"Point"}
}