{
  "type": "Feature",
  "properties": {
    "iso:country":"DE",
    "sg:address":"Bahnhofstr. 26",
    "sg:city":"Leuben-Schleinitz",
    "sg:phone":"+49 35241/58552",
    "sg:postcode":"01623",
    "sg:province":"Sachsen",
    "wof:name":"P. M\u00fcller",
    "wof:placetype":"venue"
},
  "geometry": {"coordinates":[13.3136720657,51.1949005127],"type":"Point"}
}