{
  "type": "Feature",
  "properties": {
    "iso:country":"DE",
    "sg:address":"Maximilianstr. 12",
    "sg:city":"Ansbach",
    "sg:phone":"+49 981/17722",
    "sg:postcode":"91522",
    "sg:province":"Bayern",
    "wof:name":"T. Fliegner",
    "wof:placetype":"venue"
},
  "geometry": {"coordinates":[10.571271,49.300259],"type":"Point"}
}