{
  "type": "Feature",
  "properties": {
    "iso:country":"DE",
    "sg:address":"Am Brauhaus 4",
    "sg:city":"Sebnitz",
    "sg:phone":"+49 35971/53791",
    "sg:postcode":"01855",
    "sg:province":"Sachsen",
    "wof:name":"H. Loesel Immobilienmakler",
    "wof:placetype":"venue"
},
  "geometry": {"coordinates":[14.2724227905,50.9732551575],"type":"Point"}
}