{
  "type": "Feature",
  "properties": {
    "iso:country":"DE",
    "sg:address":"Wilmersdorfer Str. 153",
    "sg:city":"Berlin",
    "sg:phone":"+49 30/3428593",
    "sg:postcode":"10585",
    "sg:province":"Berlin",
    "wof:name":"Pappzerapp Inh. S. Fritz",
    "wof:placetype":"venue"
},
  "geometry": {"coordinates":[13.3050107956,52.5149383545],"type":"Point"}
}