{
  "type": "Feature",
  "properties": {
    "iso:country":"DE",
    "sg:address":"Volkartstr. 4 a",
    "sg:city":"M\u00fcnchen",
    "sg:phone":"+49 89/134822",
    "sg:postcode":"80634",
    "sg:province":"Bayern",
    "wof:name":"Hans Hartinger Architekt",
    "wof:placetype":"venue"
},
  "geometry": {"coordinates":[11.530836,48.154617],"type":"Point"}
}