{
  "type": "Feature",
  "properties": {
    "iso:country":"DE",
    "sg:address":"Feldstr. 16",
    "sg:city":"Riedstadt",
    "sg:phone":"+49 6158/72914",
    "sg:postcode":"64560",
    "sg:province":"Hessen",
    "wof:name":"Elke Hofmann",
    "wof:placetype":"venue"
},
  "geometry": {"coordinates":[8.43836689,49.8571739197],"type":"Point"}
}