{
  "type": "Feature",
  "properties": {
    "iso:country":"DE",
    "sg:address":"Kaiser Friedrich Ring 53",
    "sg:city":"Wiesbaden",
    "sg:postcode":"65185",
    "sg:province":"Hessen",
    "wof:name":"Buzz - Die Low-cost Fluglinie",
    "wof:placetype":"venue"
},
  "geometry": {"coordinates":[8.2334051132,50.0727996826],"type":"Point"}
}