{
  "type": "Feature",
  "properties": {
    "iso:country":"DE",
    "sg:address":"Holl\u00e4ndische Str. 152",
    "sg:city":"Kassel",
    "sg:phone":"+49 561/899631",
    "sg:postcode":"34127",
    "sg:province":"Hessen",
    "wof:name":"Ellis Pintchen",
    "wof:placetype":"venue"
},
  "geometry": {"coordinates":[9.4946918488,51.3344154358],"type":"Point"}
}