{
  "type": "Feature",
  "properties": {
    "iso:country":"DE",
    "sg:address":"Rahmer Str. 35",
    "sg:city":"Dortmund",
    "sg:phone":"+49 231/393125",
    "sg:postcode":"44369",
    "sg:province":"Nordrhein-Westfalen",
    "wof:name":"Startex",
    "wof:placetype":"venue"
},
  "geometry": {"coordinates":[7.412779808,51.5294799805],"type":"Point"}
}