{
  "type": "Feature",
  "properties": {
    "iso:country":"DE",
    "sg:address":"Xantener Str. 129",
    "sg:city":"Alpen",
    "sg:postcode":"46519",
    "sg:province":"Nordrhein-Westfalen",
    "wof:name":"Its-injektionstechnik Scheuten Gmbh",
    "wof:placetype":"venue"
},
  "geometry": {"coordinates":[6.517546,51.607487],"type":"Point"}
}