{
  "type": "Feature",
  "properties": {
    "iso:country":"DE",
    "sg:address":"Schillerstr. 3",
    "sg:city":"M\u00fcllheim",
    "sg:phone":"+49 7631/4572",
    "sg:postcode":"79379",
    "sg:province":"Baden-W\u00fcrttemberg",
    "wof:name":"Gudrun Argast Krankengymnastin",
    "wof:placetype":"venue"
},
  "geometry": {"coordinates":[7.623689,47.810314],"type":"Point"}
}