{
  "type": "Feature",
  "properties": {
    "iso:country":"DE",
    "sg:address":"Neuenhauser Str. 22",
    "sg:city":"Uelsen",
    "sg:phone":"+49 5942/822",
    "sg:postcode":"49843",
    "sg:province":"Niedersachsen",
    "wof:name":"Zonneveld",
    "wof:placetype":"venue"
},
  "geometry": {"coordinates":[6.891303,52.494484],"type":"Point"}
}