{
  "type": "Feature",
  "properties": {
    "iso:country":"DE",
    "sg:address":"Steinkirchen",
    "sg:city":"Obertaufkirchen",
    "sg:phone":"+49 8082/367",
    "sg:postcode":"84419",
    "sg:province":"Bayern",
    "wof:name":"J. Maurer",
    "wof:placetype":"venue"
},
  "geometry": {"coordinates":[12.26613,48.23774],"type":"Point"}
}