{
  "type": "Feature",
  "properties": {
    "iso:country":"DE",
    "sg:address":"Bahnhofstr. 17",
    "sg:city":"Kirchhain",
    "sg:phone":"+49 6422/6636",
    "sg:postcode":"35274",
    "sg:province":"Hessen",
    "wof:name":"Wilhelm Damm",
    "wof:placetype":"venue"
},
  "geometry": {"coordinates":[8.9210166931,50.8230171204],"type":"Point"}
}