{
  "type": "Feature",
  "properties": {
    "iso:country":"DE",
    "sg:address":"Eppendorfer Landstr. 7",
    "sg:city":"Hamburg",
    "sg:phone":"+49 40/4602220",
    "sg:postcode":"20249",
    "sg:province":"Hamburg",
    "wof:name":"Schuster",
    "wof:placetype":"venue"
},
  "geometry": {"coordinates":[9.982995,53.586334],"type":"Point"}
}