{
  "type": "Feature",
  "properties": {
    "iso:country":"DE",
    "sg:address":"Bockhorst 58",
    "sg:city":"Hamburg",
    "sg:phone":"+49 40/875570",
    "sg:postcode":"22589",
    "sg:province":"Hamburg",
    "wof:name":"Dr. Med. Sven Meenen",
    "wof:placetype":"venue"
},
  "geometry": {"coordinates":[9.8342256546,53.5683479309],"type":"Point"}
}