{
  "type": "Feature",
  "properties": {
    "iso:country":"DE",
    "sg:address":"Hattinger Str. 777",
    "sg:city":"Bochum",
    "sg:postcode":"44879",
    "sg:province":"Nordrhein-Westfalen",
    "wof:name":"Co Op-center",
    "wof:placetype":"venue"
},
  "geometry": {"coordinates":[7.1657547951,51.429069519],"type":"Point"}
}