{
  "type": "Feature",
  "properties": {
    "iso:country":"DE",
    "sg:address":"Kieler Str. 407-415",
    "sg:city":"Hamburg",
    "sg:phone":"+49 40/54767167",
    "sg:postcode":"22525",
    "sg:province":"Hamburg",
    "wof:name":"Reha-fit",
    "wof:placetype":"venue"
},
  "geometry": {"coordinates":[9.930425,53.590721],"type":"Point"}
}