{
  "type": "Feature",
  "properties": {
    "iso:country":"DE",
    "sg:address":"Dr.-Schleyer-Str. 12",
    "sg:city":"Rastatt",
    "sg:phone":"+49 7222/69980",
    "sg:postcode":"76437",
    "sg:province":"Baden-W\u00fcrttemberg",
    "wof:name":"Hotel Ph\u00f6nix",
    "wof:placetype":"venue"
},
  "geometry": {"coordinates":[8.190325737,48.8677749634],"type":"Point"}
}