{
  "type": "Feature",
  "properties": {
    "iso:country":"DE",
    "sg:address":"Carl-Benz-Str. 4",
    "sg:city":"Reilingen",
    "sg:phone":"+49 6205/7770",
    "sg:postcode":"68799",
    "sg:province":"Baden-W\u00fcrttemberg",
    "wof:name":"G\u00fcnter Sensbach",
    "wof:placetype":"venue"
},
  "geometry": {"coordinates":[8.558848381,49.2957611084],"type":"Point"}
}