{
  "type": "Feature",
  "properties": {
    "iso:country":"DE",
    "sg:address":"Wollersumer Str. 17",
    "sg:city":"Lunden",
    "sg:postcode":"25774",
    "sg:province":"Schleswig-Holstein",
    "wof:name":"Agentur P&k - Erovents",
    "wof:placetype":"venue"
},
  "geometry": {"coordinates":[9.019219,54.332504],"type":"Point"}
}