{
  "type": "Feature",
  "properties": {
    "iso:country":"DE",
    "sg:address":"Rehgebirgsstr. 3",
    "sg:city":"Schw\u00e4bisch Gm\u00fcnd",
    "sg:phone":"+49 7171/43177",
    "sg:postcode":"73529",
    "sg:province":"Baden-W\u00fcrttemberg",
    "wof:name":"Anton Wahl",
    "wof:placetype":"venue"
},
  "geometry": {"coordinates":[9.793197,48.751259],"type":"Point"}
}