{
  "type": "Feature",
  "properties": {
    "iso:country":"DE",
    "sg:address":"Im Rod 1",
    "sg:city":"Kirchheim",
    "sg:postcode":"36275",
    "sg:province":"Hessen",
    "wof:name":"Deks Gmbh Daten-elektro-kommunikations-",
    "wof:placetype":"venue"
},
  "geometry": {"coordinates":[9.559902,50.850243],"type":"Point"}
}