{
  "type": "Feature",
  "properties": {
    "iso:country":"DE",
    "sg:address":"Weinstr. 15",
    "sg:city":"L\u00f6chgau",
    "sg:phone":"+49 7143/18399",
    "sg:postcode":"74369",
    "sg:province":"Baden-W\u00fcrttemberg",
    "wof:name":"Ewald Ruoff Landwirt. Lohnbetrieb",
    "wof:placetype":"venue"
},
  "geometry": {"coordinates":[9.106606,49.003101],"type":"Point"}
}