{
  "type": "Feature",
  "properties": {
    "iso:country":"DE",
    "sg:address":"Reiherstr. 8",
    "sg:city":"K\u00f6ln",
    "sg:phone":"+49 2233/22409",
    "sg:postcode":"50997",
    "sg:province":"Nordrhein-Westfalen",
    "wof:name":"Heinrich Richter",
    "wof:placetype":"venue"
},
  "geometry": {"coordinates":[6.961071,50.876598],"type":"Point"}
}