{
  "type": "Feature",
  "properties": {
    "iso:country":"DE",
    "sg:address":"Hauptstr. 6",
    "sg:city":"Balve",
    "sg:phone":"+49 2375/2146",
    "sg:postcode":"58802",
    "sg:province":"Nordrhein-Westfalen",
    "wof:name":"Haus Drei K\u00f6nige",
    "wof:placetype":"venue"
},
  "geometry": {"coordinates":[7.8635139465,51.3313713074],"type":"Point"}
}