{
  "type": "Feature",
  "properties": {
    "iso:country":"DE",
    "sg:address":"Lindenthalg\u00fcrtel 72",
    "sg:city":"K\u00f6ln",
    "sg:phone":"+49 221/404939",
    "sg:postcode":"50935",
    "sg:province":"Nordrhein-Westfalen",
    "wof:name":"G\u00fcrtelsch\u00e4nke",
    "wof:placetype":"venue"
},
  "geometry": {"coordinates":[6.9111142159,50.9253158569],"type":"Point"}
}