{
  "type": "Feature",
  "properties": {
    "iso:country":"DE",
    "sg:address":"Im Kloster 4",
    "sg:city":"Tholey",
    "sg:phone":"+49 6853/2001",
    "sg:postcode":"66636",
    "sg:province":"Saarland",
    "wof:name":"Abtei St. Mauritius Bibliothek",
    "wof:placetype":"venue"
},
  "geometry": {"coordinates":[7.03207,49.481869],"type":"Point"}
}