{
  "type": "Feature",
  "properties": {
    "iso:country":"DE",
    "sg:address":"Postfach",
    "sg:city":"Halbemond",
    "sg:postcode":"26524",
    "sg:province":"Niedersachsen",
    "wof:name":"Sebi Verbrauchermarkt Gmbh",
    "wof:placetype":"venue"
},
  "geometry": {"coordinates":[7.2828397751,53.6028137207],"type":"Point"}
}