{
  "type": "Feature",
  "properties": {
    "iso:country":"DE",
    "sg:address":"Am Sportplatz 1",
    "sg:city":"Reitzenhain",
    "sg:phone":"+49 6771/599564",
    "sg:postcode":"56357",
    "sg:province":"Rheinland-Pfalz",
    "wof:name":"Albert Gebaudemanagment Gmbh",
    "wof:placetype":"venue"
},
  "geometry": {"coordinates":[7.7844958305,50.1533813477],"type":"Point"}
}