{
  "type": "Feature",
  "properties": {
    "iso:country":"DE",
    "sg:address":"Stedtfelder Str. 1",
    "sg:city":"Krauthausen",
    "sg:phone":"+49 3691/611801",
    "sg:postcode":"99819",
    "sg:province":"Th\u00fcringen",
    "wof:name":"Holzbau Justin Fend Gmbh",
    "wof:placetype":"venue"
},
  "geometry": {"coordinates":[10.202863,50.912926],"type":"Point"}
}