{
  "type": "Feature",
  "properties": {
    "iso:country":"DE",
    "sg:address":"Spielbergsweg 2",
    "sg:city":"Velbert",
    "sg:phone":"+49 2052/4103",
    "sg:postcode":"42555",
    "sg:province":"Nordrhein-Westfalen",
    "wof:name":"Willi Fuchs",
    "wof:placetype":"venue"
},
  "geometry": {"coordinates":[7.116493,51.342358],"type":"Point"}
}