{
  "type": "Feature",
  "properties": {
    "iso:country":"DE",
    "sg:address":"Leunaer Str.",
    "sg:city":"Merseburg",
    "sg:phone":"+49 3461/214173",
    "sg:postcode":"06217",
    "sg:province":"Sachsen-Anhalt",
    "wof:name":"Schwimmhalle",
    "wof:placetype":"venue"
},
  "geometry": {"coordinates":[11.9976072311,51.3508605957],"type":"Point"}
}