{
  "type": "Feature",
  "properties": {
    "iso:country":"DE",
    "sg:address":"Magdalenenweg 44",
    "sg:city":"Kirchheim",
    "sg:phone":"+49 89/9039761",
    "sg:postcode":"85551",
    "sg:province":"Bayern",
    "wof:name":"Joachim Rex",
    "wof:placetype":"venue"
},
  "geometry": {"coordinates":[11.7607183456,48.1734352112],"type":"Point"}
}