{
  "type": "Feature",
  "properties": {
    "iso:country":"DE",
    "sg:address":"Vorstadtstr. 35",
    "sg:city":"Saarbr\u00fccken",
    "sg:phone":"+49 681/5898241",
    "sg:postcode":"66117",
    "sg:province":"Saarland",
    "wof:name":"Hamburg-mannheimer Versicherungsgesellschaften",
    "wof:placetype":"venue"
},
  "geometry": {"coordinates":[6.9866600037,49.2314910889],"type":"Point"}
}