{
  "type": "Feature",
  "properties": {
    "iso:country":"DE",
    "sg:address":"B\u00f6ttchergasse 9-11",
    "sg:city":"Gera",
    "sg:phone":"+49 365/26050",
    "sg:postcode":"07545",
    "sg:province":"Th\u00fcringen",
    "wof:name":"Raiffeisenbank Und Handelsgenossen-, Schaft Gera E. G.",
    "wof:placetype":"venue"
},
  "geometry": {"coordinates":[12.085611,50.875332],"type":"Point"}
}