{
  "type": "Feature",
  "properties": {
    "iso:country":"DE",
    "sg:address":"Siegufer 1",
    "sg:city":"Eitorf",
    "sg:phone":"+49 2243/91810",
    "sg:postcode":"53783",
    "sg:province":"Nordrhein-Westfalen",
    "wof:name":"Iris Verwaltungs Gmbh",
    "wof:placetype":"venue"
},
  "geometry": {"coordinates":[7.4415512085,50.7762870789],"type":"Point"}
}