{
  "type": "Feature",
  "properties": {
    "iso:country":"DE",
    "sg:address":"Valkenierstr. 26",
    "sg:city":"Neu-Isenburg",
    "sg:phone":"+49 6102/6149",
    "sg:postcode":"63263",
    "sg:province":"Hessen",
    "wof:name":"Klaus Koch",
    "wof:placetype":"venue"
},
  "geometry": {"coordinates":[8.6796979904,50.0548820496],"type":"Point"}
}