{
  "type": "Feature",
  "properties": {
    "iso:country":"DE",
    "sg:address":"Garbenstr. 15",
    "sg:city":"Stuttgart",
    "sg:phone":"+49 711/4592097",
    "sg:postcode":"70599",
    "sg:province":"Baden-W\u00fcrttemberg",
    "wof:name":"Universit\u00e4t Hohenheim Universit\u00e4tsb. Hohenheim",
    "wof:placetype":"venue"
},
  "geometry": {"coordinates":[9.207856,48.711205],"type":"Point"}
}