{
  "type": "Feature",
  "properties": {
    "iso:country":"DE",
    "sg:address":"Am Perlenberg 1c",
    "sg:city":"Gonbach",
    "sg:phone":"+49 6302/4308",
    "sg:postcode":"67724",
    "sg:province":"Rheinland-Pfalz",
    "wof:name":"R\u00fcdiger Portz Finanzberater",
    "wof:placetype":"venue"
},
  "geometry": {"coordinates":[7.9063668251,49.5463790894],"type":"Point"}
}