{
  "type": "Feature",
  "properties": {
    "iso:country":"DE",
    "sg:address":"Am Anger 20",
    "sg:city":"Dresden",
    "sg:phone":"+49 351/2843303",
    "sg:postcode":"01237",
    "sg:province":"Sachsen",
    "wof:name":"J\u00f6rg Israel",
    "wof:placetype":"venue"
},
  "geometry": {"coordinates":[13.7920179367,51.0086784363],"type":"Point"}
}