{
  "type": "Feature",
  "properties": {
    "iso:country":"DE",
    "sg:address":"\u00c4u\u00dfere Wiener Str 17",
    "sg:city":"Regensburg",
    "sg:phone":"+49 941/603870",
    "sg:postcode":"93055",
    "sg:province":"Bayern",
    "wof:name":"K\u00fchne & Nagel Ag & Co Kg",
    "wof:placetype":"venue"
},
  "geometry": {"coordinates":[12.1506500244,49.0168380737],"type":"Point"}
}