{
  "type": "Feature",
  "properties": {
    "iso:country":"DE",
    "sg:address":"Hub\u00e4ckerstrasse 44",
    "sg:city":"Schw\u00e4bisch Gm\u00fcnd",
    "sg:phone":"+49 7171/495708",
    "sg:postcode":"73529",
    "sg:province":"Baden-W\u00fcrttemberg",
    "wof:name":"Dominik Bauer",
    "wof:placetype":"venue"
},
  "geometry": {"coordinates":[9.799873,48.783131],"type":"Point"}
}