{
  "type": "Feature",
  "properties": {
    "iso:country":"DE",
    "sg:address":"Hauptstr. 323",
    "sg:city":"Idar-Oberstein",
    "sg:postcode":"55743",
    "sg:province":"Rheinland-Pfalz",
    "wof:name":"Ralf Kranz",
    "wof:placetype":"venue"
},
  "geometry": {"coordinates":[7.3194799423,49.7037162781],"type":"Point"}
}