{
  "type": "Feature",
  "properties": {
    "iso:country":"DE",
    "sg:address":"Industriestr. 2",
    "sg:city":"Pommersfelden",
    "sg:phone":"+49 9548/1376",
    "sg:postcode":"96178",
    "sg:province":"Bayern",
    "wof:name":"Gamperling Demontagen Und Tankreinigungs Gmbh",
    "wof:placetype":"venue"
},
  "geometry": {"coordinates":[10.8233089447,49.7660484314],"type":"Point"}
}