{
  "type": "Feature",
  "properties": {
    "iso:country":"DE",
    "sg:address":"Wanninger Str. 9",
    "sg:city":"Obing",
    "sg:phone":"+49 8624/875630",
    "sg:postcode":"83119",
    "sg:province":"Bayern",
    "wof:name":"Stephan Hofmeister",
    "wof:placetype":"venue"
},
  "geometry": {"coordinates":[12.4095964432,47.9975166321],"type":"Point"}
}