{
  "type": "Feature",
  "properties": {
    "iso:country":"DE",
    "sg:address":"Von-Rechberg-Str. 21",
    "sg:city":"Villingen-Schwenningen",
    "sg:phone":"+49 7721/4658",
    "sg:postcode":"78050",
    "sg:province":"Baden-W\u00fcrttemberg",
    "wof:name":"Helmut R\u00e4uber",
    "wof:placetype":"venue"
},
  "geometry": {"coordinates":[8.459168,48.053192],"type":"Point"}
}