{
  "type": "Feature",
  "properties": {
    "iso:country":"DE",
    "sg:address":"Postfach",
    "sg:city":"Porta Westfalica",
    "sg:phone":"+49 571/71667",
    "sg:postcode":"32437",
    "sg:province":"Nordrhein-Westfalen",
    "wof:name":"Berghotel Wittekindsburg",
    "wof:placetype":"venue"
},
  "geometry": {"coordinates":[8.9225902557,52.239490509],"type":"Point"}
}