{
  "type": "Feature",
  "properties": {
    "iso:country":"DE",
    "sg:address":"Hindenburgweg 2",
    "sg:city":"Mosbach",
    "sg:phone":"+49 6261/971111",
    "sg:postcode":"74821",
    "sg:province":"Baden-W\u00fcrttemberg",
    "wof:name":"Leo Herrmann",
    "wof:placetype":"venue"
},
  "geometry": {"coordinates":[9.115384,49.347668],"type":"Point"}
}