{
  "type": "Feature",
  "properties": {
    "iso:country":"DE",
    "sg:address":"Waldschmidtstr. 4",
    "sg:city":"Miltach",
    "sg:phone":"+49 9944/9356",
    "sg:postcode":"93468",
    "sg:province":"Bayern",
    "wof:name":"Pension Maria Lommer",
    "wof:placetype":"venue"
},
  "geometry": {"coordinates":[12.7689447403,49.1570320129],"type":"Point"}
}