{
  "type": "Feature",
  "properties": {
    "iso:country":"DE",
    "sg:address":"Sachsenbr\u00fccke",
    "sg:city":"Hamburg",
    "sg:phone":"+49 40/78071418",
    "sg:postcode":"20457",
    "sg:province":"Hamburg",
    "wof:name":"Unikai Lagerei- Und Speditionsges. Mbh",
    "wof:placetype":"venue"
},
  "geometry": {"coordinates":[10.015016,53.528049],"type":"Point"}
}