{
  "type": "Feature",
  "properties": {
    "iso:country":"DE",
    "sg:address":"G\u00e4nsestr. 4",
    "sg:city":"Warendorf",
    "sg:phone":"+49 2581/4732",
    "sg:postcode":"48231",
    "sg:province":"Nordrhein-Westfalen",
    "wof:name":"G. Und U. Rheme Versicherungsb\u00fcro",
    "wof:placetype":"venue"
},
  "geometry": {"coordinates":[7.967607975,51.9229164124],"type":"Point"}
}