{
  "type": "Feature",
  "properties": {
    "iso:country":"DE",
    "sg:address":"Kienmoorweg 112",
    "sg:city":"Oberlangen",
    "sg:phone":"+49 5939/439",
    "sg:postcode":"49779",
    "sg:province":"Niedersachsen",
    "wof:name":"Heinrich Decks",
    "wof:placetype":"venue"
},
  "geometry": {"coordinates":[7.15494,52.860851],"type":"Point"}
}