{
  "type": "Feature",
  "properties": {
    "iso:country":"DE",
    "sg:address":"Fl\u00f6zlinger Str. 43",
    "sg:city":"Zimmern",
    "sg:phone":"+49 741/31595",
    "sg:postcode":"78658",
    "sg:province":"Baden-W\u00fcrttemberg",
    "wof:name":"Vereinsgastst\u00e4tte Sportverein Zimmern",
    "wof:placetype":"venue"
},
  "geometry": {"coordinates":[8.5762472153,48.1688079834],"type":"Point"}
}