{
  "type": "Feature",
  "properties": {
    "iso:country":"DE",
    "sg:address":"Feldstr. 7",
    "sg:city":"Hofheim",
    "sg:phone":"+49 6192/26733",
    "sg:postcode":"65719",
    "sg:province":"Hessen",
    "wof:name":"Sb Gro\u00dfmarkt F\u00fcr Tiernahrung",
    "wof:placetype":"venue"
},
  "geometry": {"coordinates":[8.449978,50.090675],"type":"Point"}
}