{
  "type": "Feature",
  "properties": {
    "iso:country":"DE",
    "sg:address":"Jakobstr. 16",
    "sg:city":"G\u00f6rlitz",
    "sg:phone":"+49 3581/408379",
    "sg:postcode":"02826",
    "sg:province":"Sachsen",
    "wof:name":"Musikkneipe Trichter",
    "wof:placetype":"venue"
},
  "geometry": {"coordinates":[14.9826068878,51.1470603943],"type":"Point"}
}