{
  "type": "Feature",
  "properties": {
    "iso:country":"DE",
    "sg:address":"Luisenstr. 16",
    "sg:city":"Solms",
    "sg:phone":"+49 6442/23995",
    "sg:postcode":"35606",
    "sg:province":"Hessen",
    "wof:name":"Michael Freyle Rechtsanwalt",
    "wof:placetype":"venue"
},
  "geometry": {"coordinates":[8.399148941,50.5417251587],"type":"Point"}
}