{
  "type": "Feature",
  "properties": {
    "iso:country":"DE",
    "sg:address":"Karl-Marx-Str. 12",
    "sg:city":"Berlin",
    "sg:phone":"+49 30/6241044",
    "sg:postcode":"12043",
    "sg:province":"Berlin",
    "wof:name":"Arlt Ohg B\u00fcromaschinen",
    "wof:placetype":"venue"
},
  "geometry": {"coordinates":[13.4259634018,52.4853858948],"type":"Point"}
}