{
  "type": "Feature",
  "properties": {
    "iso:country":"DE",
    "sg:address":"Freier Platz 2",
    "sg:city":"Selters",
    "sg:phone":"+49 6475/433",
    "sg:postcode":"65618",
    "sg:province":"Hessen",
    "wof:name":"Alfons Krickau",
    "wof:placetype":"venue"
},
  "geometry": {"coordinates":[8.3175601959,50.3595199585],"type":"Point"}
}