{
  "type": "Feature",
  "properties": {
    "iso:country":"DE",
    "sg:address":"Heinrich-Lanz-Str. 9",
    "sg:city":"Beindersheim",
    "sg:phone":"+49 4962/3337620",
    "sg:postcode":"67259",
    "sg:province":"Rheinland-Pfalz",
    "wof:name":"Karl Wieser Gmbh",
    "wof:placetype":"venue"
},
  "geometry": {"coordinates":[8.326656,49.556759],"type":"Point"}
}