{
  "type": "Feature",
  "properties": {
    "iso:country":"DE",
    "sg:address":"Moosfeldstr. 39",
    "sg:city":"Ergolding",
    "sg:phone":"+49 871/73693",
    "sg:postcode":"84030",
    "sg:province":"Bayern",
    "wof:name":"Alfons Hitl",
    "wof:placetype":"venue"
},
  "geometry": {"coordinates":[12.1570997238,48.5607414246],"type":"Point"}
}