{
  "type": "Feature",
  "properties": {
    "iso:country":"DE",
    "sg:address":"Am Lindenberg 4",
    "sg:city":"Friedland",
    "sg:phone":"+49 5504/456",
    "sg:postcode":"37133",
    "sg:province":"Niedersachsen",
    "wof:name":"Richard Deppe",
    "wof:placetype":"venue"
},
  "geometry": {"coordinates":[9.9595880508,51.3985939026],"type":"Point"}
}