{
  "type": "Feature",
  "properties": {
    "iso:country":"DE",
    "sg:address":"Hennersgasse 14-18",
    "sg:city":"Steinach",
    "sg:phone":"+49 36762/32507",
    "sg:postcode":"96523",
    "sg:province":"Th\u00fcringen",
    "wof:name":"Heinz Stephan Kg",
    "wof:placetype":"venue"
},
  "geometry": {"coordinates":[11.156782,50.434074],"type":"Point"}
}