{
  "type": "Feature",
  "properties": {
    "iso:country":"DE",
    "sg:address":"Wilhelm-Kuhnert-Str. 26",
    "sg:city":"M\u00fcnchen",
    "sg:phone":"+49 89/663388",
    "sg:postcode":"81543",
    "sg:province":"Bayern",
    "wof:name":"Holzbau Heinrich Gmbh",
    "wof:placetype":"venue"
},
  "geometry": {"coordinates":[11.5595169067,48.1048545837],"type":"Point"}
}