{
  "type": "Feature",
  "properties": {
    "iso:country":"DE",
    "sg:address":"Huller Weg 20",
    "sg:city":"Wallenhorst",
    "sg:phone":"+49 5407",
    "sg:postcode":"49134",
    "sg:province":"Niedersachsen",
    "wof:name":"Hilge-vertriebsb\u00fcro Nord",
    "wof:placetype":"venue"
},
  "geometry": {"coordinates":[7.9706478119,52.3527069092],"type":"Point"}
}