{
  "type": "Feature",
  "properties": {
    "iso:country":"DE",
    "sg:address":"Pfingstweider Str. 32",
    "sg:city":"Meckenbeuren",
    "sg:phone":"+49 7542/4860",
    "sg:postcode":"88074",
    "sg:province":"Baden-W\u00fcrttemberg",
    "wof:name":"Heinrich Weishaupt",
    "wof:placetype":"venue"
},
  "geometry": {"coordinates":[9.5547790527,47.6794776917],"type":"Point"}
}