{
  "type": "Feature",
  "properties": {
    "iso:country":"DE",
    "sg:address":"Admiralstr. 96",
    "sg:city":"Bremen",
    "sg:phone":"+49 421/353021",
    "sg:postcode":"28215",
    "sg:province":"Bremen",
    "wof:name":"Bremer Polster Handels Gmbh & Co. Kg",
    "wof:placetype":"venue"
},
  "geometry": {"coordinates":[8.8056001663,53.0906791687],"type":"Point"}
}