{
  "type": "Feature",
  "properties": {
    "iso:country":"DE",
    "sg:address":"Auf dem Hohm 10",
    "sg:city":"Langen",
    "sg:phone":"+49 4742/1011",
    "sg:postcode":"27607",
    "sg:province":"Niedersachsen",
    "wof:name":"Klaus Scheper",
    "wof:placetype":"venue"
},
  "geometry": {"coordinates":[8.614514,53.683468],"type":"Point"}
}