{
  "type": "Feature",
  "properties": {
    "iso:country":"DE",
    "sg:address":"Steinbeisstr. 20",
    "sg:city":"Kornwestheim",
    "sg:phone":"+49 7154/13170",
    "sg:postcode":"70806",
    "sg:province":"Baden-W\u00fcrttemberg",
    "wof:name":"Hoberg & Driesch Gmbh Eisen- Und R\u00f6hrengrosshdl.",
    "wof:placetype":"venue"
},
  "geometry": {"coordinates":[9.180315,48.876858],"type":"Point"}
}