{
  "type": "Feature",
  "properties": {
    "iso:country":"DE",
    "sg:address":"Egelseestr 16",
    "sg:city":"Windach",
    "sg:phone":"+49 8193/950163",
    "sg:postcode":"86949",
    "sg:province":"Bayern",
    "wof:name":"Graf Consultings Gmbh",
    "wof:placetype":"venue"
},
  "geometry": {"coordinates":[11.0386981964,48.0589256287],"type":"Point"}
}