{
  "type": "Feature",
  "properties": {
    "iso:country":"DE",
    "sg:address":"Po.- Box 21 33",
    "sg:city":"Grefrath",
    "sg:phone":"+49 4902/158",
    "sg:postcode":"47929",
    "sg:province":"Nordrhein-Westfalen",
    "wof:name":"Earthpool.net - The Virtual Brainfactory Worldwide",
    "wof:placetype":"venue"
},
  "geometry": {"coordinates":[6.34382,51.337299],"type":"Point"}
}