{
  "type": "Feature",
  "properties": {
    "iso:country":"DE",
    "sg:address":"Schehnberger Weg 1",
    "sg:city":"Wardenburg",
    "sg:phone":"+49 4407/718763",
    "sg:postcode":"26203",
    "sg:province":"Niedersachsen",
    "wof:name":"F\u00f6rster Metall-team Ges. F\u00fcr Metallbauarbeiten Mbh",
    "wof:placetype":"venue"
},
  "geometry": {"coordinates":[8.210887,53.051323],"type":"Point"}
}