{
  "type": "Feature",
  "properties": {
    "iso:country":"DE",
    "sg:address":"E.-T.-A.-Hoffmann-Str. 16",
    "sg:city":"Bonn",
    "sg:phone":"+49 228/231633",
    "sg:postcode":"53113",
    "sg:province":"Nordrhein-Westfalen",
    "wof:name":"H. M. Stodieck",
    "wof:placetype":"venue"
},
  "geometry": {"coordinates":[7.1316480637,50.7094306946],"type":"Point"}
}