{
  "type": "Feature",
  "properties": {
    "iso:country":"DE",
    "sg:address":"Industriestr. 17",
    "sg:city":"Simbach",
    "sg:phone":"+49 8571/7744",
    "sg:postcode":"84359",
    "sg:province":"Bayern",
    "wof:name":"Huber Wohnbau Gmbh",
    "wof:placetype":"venue"
},
  "geometry": {"coordinates":[13.006591,48.258919],"type":"Point"}
}