{
  "type": "Feature",
  "properties": {
    "iso:country":"DE",
    "sg:address":"Brodm\u00fchlweg 14 1/2",
    "sg:city":"Ingolstadt",
    "sg:postcode":"85049",
    "sg:province":"Bayern",
    "wof:name":"Schmidt Gmbh",
    "wof:placetype":"venue"
},
  "geometry": {"coordinates":[11.4252300262,48.7623634338],"type":"Point"}
}