{
  "type": "Feature",
  "properties": {
    "iso:country":"DE",
    "sg:address":"Neue Str. 6",
    "sg:city":"Oberhof",
    "sg:phone":"+49 36842/22455",
    "sg:postcode":"98559",
    "sg:province":"Th\u00fcringen",
    "wof:name":"Marion Kreuzau",
    "wof:placetype":"venue"
},
  "geometry": {"coordinates":[10.7239246368,50.7034454346],"type":"Point"}
}