{
  "type": "Feature",
  "properties": {
    "iso:country":"DE",
    "sg:address":"Donatusstr. 99",
    "sg:city":"K\u00f6ln",
    "sg:phone":"+49 221/5903508",
    "sg:postcode":"50767",
    "sg:province":"Nordrhein-Westfalen",
    "wof:name":"Meurer Transporte Gmbh & Co. Kg",
    "wof:placetype":"venue"
},
  "geometry": {"coordinates":[6.8714370728,51.0049095154],"type":"Point"}
}