{
  "type": "Feature",
  "properties": {
    "iso:country":"DE",
    "sg:address":"Sonnenbichlstr. 15",
    "sg:city":"Nonnenhorn",
    "sg:phone":"+49 8382/8271",
    "sg:postcode":"88149",
    "sg:province":"Bayern",
    "wof:name":"Otto Kapfhammer",
    "wof:placetype":"venue"
},
  "geometry": {"coordinates":[9.6121549606,47.5767440796],"type":"Point"}
}