{
  "type": "Feature",
  "properties": {
    "iso:country":"DE",
    "sg:address":"Fleischstr. 62",
    "sg:city":"Trier",
    "sg:phone":"+49 651/75978",
    "sg:postcode":"54290",
    "sg:province":"Rheinland-Pfalz",
    "wof:name":"Akademische Buchhandlung Interbook Gmbh",
    "wof:placetype":"venue"
},
  "geometry": {"coordinates":[6.6388401985,49.7557678223],"type":"Point"}
}