{
  "type": "Feature",
  "properties": {
    "iso:country":"DE",
    "sg:address":"Kronenstr. 41",
    "sg:city":"Waldbronn",
    "sg:phone":"+49 7243/63382",
    "sg:postcode":"76337",
    "sg:province":"Baden-W\u00fcrttemberg",
    "wof:name":"Heiwoh Bautr\u00e4ger Gmbh & Co.",
    "wof:placetype":"venue"
},
  "geometry": {"coordinates":[8.479326,48.921852],"type":"Point"}
}