{
  "type": "Feature",
  "properties": {
    "iso:country":"DE",
    "sg:address":"Dorflage 22",
    "sg:city":"Kretzschau",
    "sg:phone":"+49 3441/860104",
    "sg:postcode":"06712",
    "sg:province":"Sachsen-Anhalt",
    "wof:name":"Sieglinde Eckardt",
    "wof:placetype":"venue"
},
  "geometry": {"coordinates":[12.083864,51.061852],"type":"Point"}
}