{
  "type": "Feature",
  "properties": {
    "iso:country":"DE",
    "sg:address":"Berger Str. 5",
    "sg:city":"Starnberg",
    "sg:postcode":"82319",
    "sg:province":"Bayern",
    "wof:name":"Mehrzweckhalle Percha",
    "wof:placetype":"venue"
},
  "geometry": {"coordinates":[11.342172,47.999592],"type":"Point"}
}