{
  "type": "Feature",
  "properties": {
    "iso:country":"DE",
    "sg:address":"Hesser\u00f6der Str. 25",
    "sg:city":"Nordhausen",
    "sg:phone":"+49 3631/900323",
    "sg:postcode":"99734",
    "sg:province":"Th\u00fcringen",
    "wof:name":"Roland-apotheke E. Kfr. Inh. Heike Worbes",
    "wof:placetype":"venue"
},
  "geometry": {"coordinates":[10.781936,51.502033],"type":"Point"}
}