{
  "type": "Feature",
  "properties": {
    "iso:country":"DE",
    "sg:address":"Stadtplatz 14",
    "sg:city":"Aichach",
    "sg:phone":"+49 8251/2231",
    "sg:postcode":"86551",
    "sg:province":"Bayern",
    "wof:name":"Helios Wohnungs- Und Eigenheimbau Gmbh",
    "wof:placetype":"venue"
},
  "geometry": {"coordinates":[11.1316022873,48.459903717],"type":"Point"}
}