{
  "type": "Feature",
  "properties": {
    "iso:country":"DE",
    "sg:address":"S\u00fcdstr. 4",
    "sg:city":"Sankt Johann",
    "sg:phone":"+49 2651/3467",
    "sg:postcode":"56727",
    "sg:province":"Rheinland-Pfalz",
    "wof:name":"Hilger Verwaltungs-gmbh",
    "wof:placetype":"venue"
},
  "geometry": {"coordinates":[7.1978788376,50.3459358215],"type":"Point"}
}