{
  "type": "Feature",
  "properties": {
    "iso:country":"DE",
    "sg:address":"Fr\u00fchlingsaustr. 1",
    "sg:city":"Rodgau",
    "sg:phone":"+49 6106/69990",
    "sg:postcode":"63110",
    "sg:province":"Hessen",
    "wof:name":"Hotel Haingraben",
    "wof:placetype":"venue"
},
  "geometry": {"coordinates":[8.8884401321,50.0206794739],"type":"Point"}
}