{
  "type": "Feature",
  "properties": {
    "iso:country":"DE",
    "sg:address":"Hamburger Str. 141",
    "sg:city":"Elmshorn",
    "sg:phone":"+49 4121/439714",
    "sg:postcode":"25337",
    "sg:province":"Schleswig-Holstein",
    "wof:name":"Das Futterhaus Verwaltung Und Gro\u00dfhandel",
    "wof:placetype":"venue"
},
  "geometry": {"coordinates":[9.681453,53.74979],"type":"Point"}
}