{
  "type": "Feature",
  "properties": {
    "iso:country":"DE",
    "sg:address":"Kesselsdorfer Str. 55",
    "sg:city":"Dresden",
    "sg:phone":"+49 351/4162304",
    "sg:postcode":"01159",
    "sg:province":"Sachsen",
    "wof:name":"H. Spallek",
    "wof:placetype":"venue"
},
  "geometry": {"coordinates":[13.688185,51.042381],"type":"Point"}
}