{
  "type": "Feature",
  "properties": {
    "iso:country":"DE",
    "sg:address":"An der Bahn 4",
    "sg:city":"Sch\u00f6ppenstedt",
    "sg:phone":"+49 5332/3234",
    "sg:postcode":"38170",
    "sg:province":"Niedersachsen",
    "wof:name":"Joachim Meyer Bearbeitungs-gmbh",
    "wof:placetype":"venue"
},
  "geometry": {"coordinates":[10.777993,52.141148],"type":"Point"}
}