{
  "type": "Feature",
  "properties": {
    "iso:country":"DE",
    "sg:address":"B\u00fchlstr. 5",
    "sg:city":"Pfinztal",
    "sg:phone":"+49 7240/224",
    "sg:postcode":"76327",
    "sg:province":"Baden-W\u00fcrttemberg",
    "wof:name":"Kath. Pfarramt St. Pius X",
    "wof:placetype":"venue"
},
  "geometry": {"coordinates":[8.5425329208,48.9862594604],"type":"Point"}
}