{
  "type": "Feature",
  "properties": {
    "iso:country":"DE",
    "sg:address":"Am Bahnhof 19",
    "sg:city":"Hohenbucko",
    "sg:phone":"+49 35364/226",
    "sg:postcode":"04936",
    "sg:province":"Brandenburg",
    "wof:name":"G\u00f6tz Weisbrodt",
    "wof:placetype":"venue"
},
  "geometry": {"coordinates":[13.4561729431,51.7759399414],"type":"Point"}
}