{
  "type": "Feature",
  "properties": {
    "iso:country":"DE",
    "sg:address":"Elisabethstr. 14",
    "sg:city":"Salzgitter",
    "sg:phone":"+49 5341/37610",
    "sg:postcode":"38259",
    "sg:province":"Niedersachsen",
    "wof:name":"Fuchsbau",
    "wof:placetype":"venue"
},
  "geometry": {"coordinates":[10.3665323257,52.0524406433],"type":"Point"}
}