{
  "type": "Feature",
  "properties": {
    "iso:country":"DE",
    "sg:address":"Alte Mainzer Landstr. 32",
    "sg:city":"Dieburg",
    "sg:phone":"+49 6071/74408",
    "sg:postcode":"64807",
    "sg:province":"Hessen",
    "wof:name":"Oliver Kl\u00fcmper Rechtsanwalt",
    "wof:placetype":"venue"
},
  "geometry": {"coordinates":[8.826751709,49.8975028992],"type":"Point"}
}