{
  "type": "Feature",
  "properties": {
    "iso:country":"DE",
    "sg:address":"Kirchstr. 11",
    "sg:city":"Bilshausen",
    "sg:phone":"+49 5528/533",
    "sg:postcode":"37434",
    "sg:province":"Niedersachsen",
    "wof:name":"Wilhelm Bringmann Architekt",
    "wof:placetype":"venue"
},
  "geometry": {"coordinates":[10.15959,51.631866],"type":"Point"}
}