{
  "type": "Feature",
  "properties": {
    "iso:country":"DE",
    "sg:address":"Johann-Sebastian-Bach-Str. 4",
    "sg:city":"Vaterstetten",
    "sg:phone":"+49 8106/6071",
    "sg:postcode":"85591",
    "sg:province":"Bayern",
    "wof:name":"Adolf H\u00f6nninger Architekt",
    "wof:placetype":"venue"
},
  "geometry": {"coordinates":[11.774868,48.106007],"type":"Point"}
}