{
  "type": "Feature",
  "properties": {
    "iso:country":"DE",
    "sg:address":"Zum Tal 61",
    "sg:city":"Wuppertal",
    "sg:phone":"+49 202/473601",
    "sg:postcode":"42349",
    "sg:province":"Nordrhein-Westfalen",
    "wof:name":"Ernst Haas E. K.",
    "wof:placetype":"venue"
},
  "geometry": {"coordinates":[7.1391501427,51.2022590637],"type":"Point"}
}