{
  "type": "Feature",
  "properties": {
    "iso:country":"DE",
    "sg:address":"B\u00fcrgermeister-St\u00f6ckle-Str. 4",
    "sg:city":"Bad W\u00f6rishofen",
    "sg:phone":"+49 8247/2561",
    "sg:postcode":"86825",
    "sg:province":"Bayern",
    "wof:name":"Wolf",
    "wof:placetype":"venue"
},
  "geometry": {"coordinates":[10.591989,48.003216],"type":"Point"}
}