{
  "type": "Feature",
  "properties": {
    "iso:country":"DE",
    "sg:address":"Thea-B\u00e4hnisch-Weg 32",
    "sg:city":"Hannover",
    "sg:phone":"+49 511/6045553",
    "sg:postcode":"30657",
    "sg:province":"Niedersachsen",
    "wof:name":"Weidemann Ohg",
    "wof:placetype":"venue"
},
  "geometry": {"coordinates":[9.787906,52.426064],"type":"Point"}
}