{
  "type": "Feature",
  "properties": {
    "iso:country":"DE",
    "sg:city":"Sch\u00f6naich",
    "sg:phone":"+49 7031/650731",
    "sg:postcode":"71101",
    "sg:province":"Baden-W\u00fcrttemberg",
    "wof:name":"Jugendb\u00fccherei Joh.-br\u00fccker-schule",
    "wof:placetype":"venue"
},
  "geometry": {"coordinates":[9.059769,48.660175],"type":"Point"}
}