{
  "type": "Feature",
  "properties": {
    "iso:country":"DE",
    "sg:address":"Forststr. 14",
    "sg:city":"Rosenheim",
    "sg:postcode":"83026",
    "sg:province":"Bayern",
    "wof:name":"Dittmann & Forstner Private Wohnbauges. Mbh",
    "wof:placetype":"venue"
},
  "geometry": {"coordinates":[12.1126890182,47.8457832336],"type":"Point"}
}