{
  "type": "Feature",
  "properties": {
    "iso:country":"DE",
    "sg:address":"Arnst\u00e4dter Str. 11b",
    "sg:city":"Gehren",
    "sg:phone":"+49 36783/86690",
    "sg:postcode":"98708",
    "sg:province":"Th\u00fcringen",
    "wof:name":"Klaus Fickenscher",
    "wof:placetype":"venue"
},
  "geometry": {"coordinates":[11.0083637238,50.6583976746],"type":"Point"}
}