{
  "type": "Feature",
  "properties": {
    "iso:country":"DE",
    "sg:address":"Feldschl\u00f6\u00dfchenweg",
    "sg:city":"Merseburg",
    "sg:phone":"+49 3461/525471",
    "sg:postcode":"06217",
    "sg:province":"Sachsen-Anhalt",
    "wof:name":"Naherholungsgastst\u00e4tte S\u00fcdpark",
    "wof:placetype":"venue"
},
  "geometry": {"coordinates":[11.9869432449,51.3468017578],"type":"Point"}
}