{
  "type": "Feature",
  "properties": {
    "iso:country":"DE",
    "sg:address":"Dr.-Robert-Koch-Str. 26",
    "sg:city":"Burgst\u00e4dt",
    "sg:phone":"+49 3724/3030",
    "sg:postcode":"09217",
    "sg:province":"Sachsen",
    "wof:name":"J\u00fcrgen Munke",
    "wof:placetype":"venue"
},
  "geometry": {"coordinates":[12.806846,50.918892],"type":"Point"}
}