{
  "type": "Feature",
  "properties": {
    "iso:country":"DE",
    "sg:address":"An der Wei\u00dfen Mauer 13-15",
    "sg:city":"G\u00f6rlitz",
    "sg:postcode":"02826",
    "sg:province":"Sachsen",
    "wof:name":"B\u00e4uerliche Handelsgenossen- Schaft Raiffeisen G\u00f6rlitz Eg",
    "wof:placetype":"venue"
},
  "geometry": {"coordinates":[14.9670886993,51.1542816162],"type":"Point"}
}