{
  "type": "Feature",
  "properties": {
    "iso:country":"DE",
    "sg:address":"Am Katzenberg 19",
    "sg:city":"Aitrang",
    "sg:postcode":"87648",
    "sg:province":"Bayern",
    "wof:name":"Lkb Luftkanalbau Gmbh",
    "wof:placetype":"venue"
},
  "geometry": {"coordinates":[10.5317430496,47.8235664368],"type":"Point"}
}