{
  "type": "Feature",
  "properties": {
    "iso:country":"DE",
    "sg:address":"Naringer Str. 27",
    "sg:city":"Feldkirchen-Westerham",
    "sg:phone":"+49 8063/9527",
    "sg:postcode":"83620",
    "sg:province":"Bayern",
    "wof:name":"Siegried Andreas Wolfram Architekt",
    "wof:placetype":"venue"
},
  "geometry": {"coordinates":[11.831606,47.894653],"type":"Point"}
}