{
  "type": "Feature",
  "properties": {
    "iso:country":"DE",
    "sg:address":"Apollinarisstr. 2",
    "sg:city":"Kreuzau",
    "sg:phone":"+49 2422/7495",
    "sg:postcode":"52372",
    "sg:province":"Nordrhein-Westfalen",
    "wof:name":"Ria Dre\u00dfen",
    "wof:placetype":"venue"
},
  "geometry": {"coordinates":[6.447167,50.718124],"type":"Point"}
}