{
  "type": "Feature",
  "properties": {
    "iso:country":"DE",
    "sg:address":"Leopoldstr. 16",
    "sg:city":"Kraichtal",
    "sg:phone":"+49 7251/60055",
    "sg:postcode":"76703",
    "sg:province":"Baden-W\u00fcrttemberg",
    "wof:name":"Eugen Deuchler Rechtsanwalt",
    "wof:placetype":"venue"
},
  "geometry": {"coordinates":[8.6710357666,49.1439056396],"type":"Point"}
}