{
  "type": "Feature",
  "properties": {
    "iso:country":"DE",
    "sg:address":"K\u00f6nigst\u00e4dter Str. 37",
    "sg:city":"Nauheim",
    "sg:phone":"+49 6152/6529",
    "sg:postcode":"64569",
    "sg:province":"Hessen",
    "wof:name":"Jakob Schmau\u00df",
    "wof:placetype":"venue"
},
  "geometry": {"coordinates":[8.4514369965,49.9470252991],"type":"Point"}
}