{
  "type": "Feature",
  "properties": {
    "iso:country":"DE",
    "sg:address":"Postfach 1161",
    "sg:city":"We\u00dfling",
    "sg:phone":"+49 8153/916000",
    "sg:postcode":"82230",
    "sg:province":"Bayern",
    "wof:name":"Blue Calvin Classics - Musiklabel",
    "wof:placetype":"venue"
},
  "geometry": {"coordinates":[11.2503824234,48.0759315491],"type":"Point"}
}