{
  "type": "Feature",
  "properties": {
    "iso:country":"DE",
    "sg:address":"K\u00f6lner Str. 244",
    "sg:city":"K\u00f6ln",
    "sg:phone":"+49 4922/0312321",
    "sg:postcode":"51149",
    "sg:province":"Nordrhein-Westfalen",
    "wof:name":"H C Service Ges Fuer Werbemittel M B H",
    "wof:placetype":"venue"
},
  "geometry": {"coordinates":[7.011312,50.907108],"type":"Point"}
}