{
  "type": "Feature",
  "properties": {
    "iso:country":"DE",
    "sg:address":"Doormannsweg 45",
    "sg:city":"Hamburg",
    "sg:phone":"+49 40/434419",
    "sg:postcode":"20259",
    "sg:province":"Hamburg",
    "wof:name":"Volkmar K. Demuth",
    "wof:placetype":"venue"
},
  "geometry": {"coordinates":[9.9530191422,53.5679016113],"type":"Point"}
}