{
  "type": "Feature",
  "properties": {
    "iso:country":"DE",
    "sg:city":"Esgrus",
    "sg:phone":"+49 4637/315",
    "sg:postcode":"24402",
    "sg:province":"Schleswig-Holstein",
    "wof:name":"Volker Hansen B\u00e4ckerei",
    "wof:placetype":"venue"
},
  "geometry": {"coordinates":[9.781583,54.723434],"type":"Point"}
}