{
  "type": "Feature",
  "properties": {
    "iso:country":"DE",
    "sg:address":"Hauptst\u00e4tter Str. 152",
    "sg:city":"Stuttgart",
    "sg:phone":"+49 711/638088",
    "sg:postcode":"70178",
    "sg:province":"Baden-W\u00fcrttemberg",
    "wof:name":"City-kurier- Transport-agentur Gmbh",
    "wof:placetype":"venue"
},
  "geometry": {"coordinates":[9.1693477631,48.764755249],"type":"Point"}
}