{
  "type": "Feature",
  "properties": {
    "iso:country":"DE",
    "sg:address":"Monbachtal",
    "sg:city":"Bad Liebenzell",
    "sg:phone":"+49 7052/170",
    "sg:postcode":"75378",
    "sg:province":"Baden-W\u00fcrttemberg",
    "wof:name":"Liebenzeller Mission Freizeiten Und Reisen Gmbh",
    "wof:placetype":"venue"
},
  "geometry": {"coordinates":[8.7441549301,48.7938461304],"type":"Point"}
}