{
  "type": "Feature",
  "properties": {
    "iso:country":"DE",
    "sg:address":"K\u00f6nigstr. 24",
    "sg:city":"Hof",
    "sg:phone":"+49 9281/84400",
    "sg:postcode":"95028",
    "sg:province":"Bayern",
    "wof:name":"Wg Wohn- Und Grundbesitz Gmbh",
    "wof:placetype":"venue"
},
  "geometry": {"coordinates":[11.9214754105,50.3110198975],"type":"Point"}
}