{
  "type": "Feature",
  "properties": {
    "iso:country":"DE",
    "sg:address":"Hauptstr. 448",
    "sg:city":"K\u00f6nigswinter",
    "sg:phone":"+49 2223/23447",
    "sg:postcode":"53639",
    "sg:province":"Nordrhein-Westfalen",
    "wof:name":"Peter Glander",
    "wof:placetype":"venue"
},
  "geometry": {"coordinates":[7.194748,50.672363],"type":"Point"}
}