{
  "type": "Feature",
  "properties": {
    "iso:country":"DE",
    "sg:address":"Im D\u00fcrrloh 7",
    "sg:city":"M\u00fchlhausen",
    "sg:postcode":"92360",
    "sg:province":"Bayern",
    "wof:name":"Einkaufspool Freier H\u00e4ndler Gmbh",
    "wof:placetype":"venue"
},
  "geometry": {"coordinates":[11.4452352524,49.159828186],"type":"Point"}
}