{
  "type": "Feature",
  "properties": {
    "iso:country":"DE",
    "sg:address":"Erkertshofen",
    "sg:city":"Titting",
    "sg:phone":"+49 8423/420",
    "sg:postcode":"85135",
    "sg:province":"Bayern",
    "wof:name":"Juma Verwaltungs Gmbh & Co. Natursteinwerke Kg",
    "wof:placetype":"venue"
},
  "geometry": {"coordinates":[11.2229700089,48.9785995483],"type":"Point"}
}