{
  "type": "Feature",
  "properties": {
    "iso:country":"DE",
    "sg:address":"Dornberger Str. 21",
    "sg:city":"Bielefeld",
    "sg:phone":"+49 521/122325",
    "sg:postcode":"33615",
    "sg:province":"Nordrhein-Westfalen",
    "wof:name":"C. F. Eickmeyer",
    "wof:placetype":"venue"
},
  "geometry": {"coordinates":[8.5185346603,52.0215148926],"type":"Point"}
}