{
  "type": "Feature",
  "properties": {
    "iso:country":"DE",
    "sg:address":"D\u00fcrener Str. 177",
    "sg:city":"K\u00f6ln",
    "sg:postcode":"50931",
    "sg:province":"Nordrhein-Westfalen",
    "wof:name":"Trans Form Gesellschaft F\u00fcr Sprachen- Und Medien-",
    "wof:placetype":"venue"
},
  "geometry": {"coordinates":[6.915593,50.930634],"type":"Point"}
}