{
  "type": "Feature",
  "properties": {
    "iso:country":"DE",
    "sg:city":"Stuttgart",
    "sg:postcode":"70469",
    "sg:province":"Baden-W\u00fcrttemberg",
    "wof:name":"Heike Scherer Qualifizierte Fach\u00fcbersetzungen - Schwedisch-d",
    "wof:placetype":"venue"
},
  "geometry": {"coordinates":[9.158804,48.811352],"type":"Point"}
}