{
  "type": "Feature",
  "properties": {
    "iso:country":"DE",
    "sg:address":"Storchenplatz 1",
    "sg:city":"Neunkirchen",
    "sg:phone":"+49 6821/13211",
    "sg:postcode":"66538",
    "sg:province":"Saarland",
    "wof:name":"Gondoliere",
    "wof:placetype":"venue"
},
  "geometry": {"coordinates":[7.2006258965,49.3427734375],"type":"Point"}
}