{
  "type": "Feature",
  "properties": {
    "iso:country":"DE",
    "sg:address":"Burger Hauptstr. 49",
    "sg:city":"Herborn",
    "sg:phone":"+49 2772/42776",
    "sg:postcode":"35745",
    "sg:province":"Hessen",
    "wof:name":"Norbert N\u00fcrnberg",
    "wof:placetype":"venue"
},
  "geometry": {"coordinates":[8.3021860123,50.7051849365],"type":"Point"}
}