{
  "type": "Feature",
  "properties": {
    "iso:country":"DE",
    "sg:address":"Weimarer Str. 49",
    "sg:city":"Karlsruhe",
    "sg:postcode":"76139",
    "sg:province":"Baden-W\u00fcrttemberg",
    "wof:name":"Eisenmann Translations - German Translators",
    "wof:placetype":"venue"
},
  "geometry": {"coordinates":[8.453173,49.030754],"type":"Point"}
}