{
  "type": "Feature",
  "properties": {
    "iso:country":"DE",
    "sg:address":"Spessartstr. 8",
    "sg:city":"Aschaffenburg",
    "sg:phone":"+49 6021/93949",
    "sg:postcode":"63743",
    "sg:province":"Bayern",
    "wof:name":"Bistro To Steki",
    "wof:placetype":"venue"
},
  "geometry": {"coordinates":[9.1510877609,49.9647598267],"type":"Point"}
}