{
  "type": "Feature",
  "properties": {
    "iso:country":"DE",
    "sg:address":"Turnerstr. 25",
    "sg:city":"Bielefeld",
    "sg:phone":"+49 521/62359",
    "sg:postcode":"33602",
    "sg:province":"Nordrhein-Westfalen",
    "wof:name":"Fritz Beeck",
    "wof:placetype":"venue"
},
  "geometry": {"coordinates":[8.537122,52.020016],"type":"Point"}
}