{
  "type": "Feature",
  "properties": {
    "iso:country":"DE",
    "sg:address":"Heppenser Str. 37",
    "sg:city":"Wilhelmshaven",
    "sg:phone":"+49 4421/302271",
    "sg:postcode":"26384",
    "sg:province":"Niedersachsen",
    "wof:name":"Manfred Brunken",
    "wof:placetype":"venue"
},
  "geometry": {"coordinates":[8.136206,53.529369],"type":"Point"}
}