{
  "type": "Feature",
  "properties": {
    "iso:country":"DE",
    "sg:address":"Segeberger Str. 29",
    "sg:city":"Nahe",
    "sg:postcode":"23866",
    "sg:province":"Schleswig-Holstein",
    "wof:name":"Gunnar Lassen E. K.",
    "wof:placetype":"venue"
},
  "geometry": {"coordinates":[10.1407747269,53.7955131531],"type":"Point"}
}