{
  "type": "Feature",
  "properties": {
    "iso:country":"DE",
    "sg:address":"Vilsbiburg",
    "sg:city":"Vilsbiburg",
    "sg:phone":"+49 8741/3020",
    "sg:postcode":"84137",
    "sg:province":"Bayern",
    "wof:name":"Volksbank Eg",
    "wof:placetype":"venue"
},
  "geometry": {"coordinates":[12.35121,48.438808],"type":"Point"}
}