{
  "type": "Feature",
  "properties": {
    "iso:country":"DE",
    "sg:address":"Untergruppenbacher Str. 1",
    "sg:city":"Talheim",
    "sg:phone":"+49 7133/7890",
    "sg:postcode":"74388",
    "sg:province":"Baden-W\u00fcrttemberg",
    "wof:name":"Kath. Pfarramt Mari\u00e4 Himmelfahrt",
    "wof:placetype":"venue"
},
  "geometry": {"coordinates":[9.1987953186,49.0837974548],"type":"Point"}
}