{
  "type": "Feature",
  "properties": {
    "iso:country":"DE",
    "sg:address":"Koblenzer Str. 2",
    "sg:city":"Berlin",
    "sg:phone":"+49 30/8532963",
    "sg:postcode":"10715",
    "sg:province":"Berlin",
    "wof:name":"Angelika Walgenbach-priegnitz Ergotherapiepraxis",
    "wof:placetype":"venue"
},
  "geometry": {"coordinates":[13.321474,52.481274],"type":"Point"}
}