{
  "type": "Feature",
  "properties": {
    "iso:country":"DE",
    "sg:address":"Alte Dorfstr. 6",
    "sg:city":"Schossin",
    "sg:phone":"+49 3869/7244",
    "sg:postcode":"19073",
    "sg:province":"Mecklenburg-Vorpommern",
    "wof:name":"Landwirtschaftliche Erzeuger- Gemeinschaft Schossin Gmbh",
    "wof:placetype":"venue"
},
  "geometry": {"coordinates":[11.218451,53.541027],"type":"Point"}
}