{
  "type": "Feature",
  "properties": {
    "iso:country":"DE",
    "sg:address":"Markt 29",
    "sg:city":"Bernkastel-Kues",
    "sg:phone":"+49 6531/94013",
    "sg:postcode":"54470",
    "sg:province":"Rheinland-Pfalz",
    "wof:name":"Beate Gehrle",
    "wof:placetype":"venue"
},
  "geometry": {"coordinates":[7.076369,49.915707],"type":"Point"}
}