{
  "type": "Feature",
  "properties": {
    "iso:country":"DE",
    "sg:address":"Marktstr. 1",
    "sg:city":"H\u00fcckeswagen",
    "sg:phone":"+49 2192/4489",
    "sg:postcode":"42499",
    "sg:province":"Nordrhein-Westfalen",
    "wof:name":"Burghoff",
    "wof:placetype":"venue"
},
  "geometry": {"coordinates":[7.3391718864,51.1490516663],"type":"Point"}
}