{
  "type": "Feature",
  "properties": {
    "iso:country":"DE",
    "sg:address":"M\u00e4rzenweg 54",
    "sg:city":"N\u00fcrnberg",
    "sg:phone":"+49 911/522532",
    "sg:postcode":"90411",
    "sg:province":"Bayern",
    "wof:name":"Motherm Handelsges. F\u00fcr W\u00e4rmetechnik Mbh",
    "wof:placetype":"venue"
},
  "geometry": {"coordinates":[11.1051111221,49.506980896],"type":"Point"}
}