{
  "type": "Feature",
  "properties": {
    "iso:country":"DE",
    "sg:address":"D\u00fcsseldorfer Str. 7",
    "sg:city":"Ha\u00dffurt",
    "sg:phone":"+49 9521/5407",
    "sg:postcode":"97437",
    "sg:province":"Bayern",
    "wof:name":"Bernhard Und Lillian Langer",
    "wof:placetype":"venue"
},
  "geometry": {"coordinates":[10.51698,50.037174],"type":"Point"}
}