{
  "type": "Feature",
  "properties": {
    "iso:country":"DE",
    "sg:address":"Kapellgasse 11",
    "sg:city":"Trochtelfingen",
    "sg:phone":"+49 7124/876",
    "sg:postcode":"72818",
    "sg:province":"Baden-W\u00fcrttemberg",
    "wof:name":"Rudi Grunwald",
    "wof:placetype":"venue"
},
  "geometry": {"coordinates":[9.240611,48.307152],"type":"Point"}
}