{
  "type": "Feature",
  "properties": {
    "iso:country":"DE",
    "sg:address":"An den Drei\u00dfigruten 25",
    "sg:city":"B\u00fcttelborn",
    "sg:phone":"+49 6152/82468",
    "sg:postcode":"64572",
    "sg:province":"Hessen",
    "wof:name":"Rahner Software Beratungs Gmbh",
    "wof:placetype":"venue"
},
  "geometry": {"coordinates":[8.5210132599,49.9210205078],"type":"Point"}
}