{
  "type": "Feature",
  "properties": {
    "iso:country":"DE",
    "sg:address":"Schauinslandstr. 8",
    "sg:city":"Freiburg",
    "sg:phone":"+49 761/29369",
    "sg:postcode":"79100",
    "sg:province":"Baden-W\u00fcrttemberg",
    "wof:name":"Otto Maria F. Pasquay Architekt",
    "wof:placetype":"venue"
},
  "geometry": {"coordinates":[7.863819,47.955917],"type":"Point"}
}