{
  "type": "Feature",
  "properties": {
    "iso:country":"DE",
    "sg:address":"M\u00fchlenweg 11",
    "sg:city":"Egenhausen",
    "sg:phone":"+49 7453/8578",
    "sg:postcode":"72227",
    "sg:province":"Baden-W\u00fcrttemberg",
    "wof:name":"Fritz Rothfu\u00df",
    "wof:placetype":"venue"
},
  "geometry": {"coordinates":[8.619442,48.570782],"type":"Point"}
}