{
  "type": "Feature",
  "properties": {
    "iso:country":"DE",
    "sg:address":"Bundesstr. 5 14",
    "sg:city":"Weddingstedt",
    "sg:phone":"+49 4948/15159",
    "sg:postcode":"25795",
    "sg:province":"Schleswig-Holstein",
    "wof:name":"Johann Schl\u00dcter Gmbh",
    "wof:placetype":"venue"
},
  "geometry": {"coordinates":[9.086549,54.237717],"type":"Point"}
}