{
  "type": "Feature",
  "properties": {
    "iso:country":"DE",
    "sg:address":"Gudrunstr. 31",
    "sg:city":"Hamburg",
    "sg:phone":"+49 40/812654",
    "sg:postcode":"22559",
    "sg:province":"Hamburg",
    "wof:name":"Horst Behn",
    "wof:placetype":"venue"
},
  "geometry": {"coordinates":[9.758798,53.584637],"type":"Point"}
}