{
  "type": "Feature",
  "properties": {
    "iso:country":"DE",
    "sg:address":"Humboldtstr. 25",
    "sg:city":"Simmerath",
    "sg:phone":"+49 2473/1662",
    "sg:postcode":"52152",
    "sg:province":"Nordrhein-Westfalen",
    "wof:name":"Fuma C. Boue",
    "wof:placetype":"venue"
},
  "geometry": {"coordinates":[6.306949,50.608238],"type":"Point"}
}