{
  "type": "Feature",
  "properties": {
    "iso:country":"DE",
    "sg:address":"Kellerstr. 36",
    "sg:city":"Pfaffenhofen",
    "sg:postcode":"85276",
    "sg:province":"Bayern",
    "wof:name":"Urban Verwaltungs Gmbh",
    "wof:placetype":"venue"
},
  "geometry": {"coordinates":[11.503821373,48.5293388367],"type":"Point"}
}