{
  "type": "Feature",
  "properties": {
    "iso:country":"DE",
    "sg:address":"Hans-Graf-Sponeck-Str. 7",
    "sg:city":"Germersheim",
    "sg:phone":"+49 7274/4641",
    "sg:postcode":"76726",
    "sg:province":"Rheinland-Pfalz",
    "wof:name":"Gerald Klein",
    "wof:placetype":"venue"
},
  "geometry": {"coordinates":[8.365242,49.213154],"type":"Point"}
}