{
  "type": "Feature",
  "properties": {
    "iso:country":"DE",
    "sg:address":"Lerchenfeld 11",
    "sg:city":"Hamburg",
    "sg:phone":"+49 40/2201191",
    "sg:postcode":"22081",
    "sg:province":"Hamburg",
    "wof:name":"Ibt Bunkering & Trading Bunkergesellschaft Mbh",
    "wof:placetype":"venue"
},
  "geometry": {"coordinates":[10.029340744,53.5682296753],"type":"Point"}
}