{
  "type": "Feature",
  "properties": {
    "iso:country":"DE",
    "sg:address":"Schulstr. 18",
    "sg:city":"Nister",
    "sg:phone":"+49 2662/6685",
    "sg:postcode":"57645",
    "sg:province":"Rheinland-Pfalz",
    "wof:name":"Gisela Habermann",
    "wof:placetype":"venue"
},
  "geometry": {"coordinates":[7.8388738632,50.6753921509],"type":"Point"}
}