{
  "type": "Feature",
  "properties": {
    "iso:country":"DE",
    "sg:address":"Gartenstr. 24",
    "sg:city":"Carlsberg",
    "sg:phone":"+49 6356/201",
    "sg:postcode":"67316",
    "sg:province":"Rheinland-Pfalz",
    "wof:name":"Ev. Pfarramt Carlsberg",
    "wof:placetype":"venue"
},
  "geometry": {"coordinates":[8.0371322632,49.5018157959],"type":"Point"}
}