{
  "type": "Feature",
  "properties": {
    "iso:country":"DE",
    "sg:city":"K\u00f6nigsbrunn",
    "sg:postcode":"86343",
    "sg:province":"Bayern",
    "wof:name":"Aifp - Spanischschule In S\u00fcdspanien - Spanisch Lernen In Spa",
    "wof:placetype":"venue"
},
  "geometry": {"coordinates":[10.890975,48.268719],"type":"Point"}
}