{
  "type": "Feature",
  "properties": {
    "iso:country":"DE",
    "sg:address":"Lampestr. 4h",
    "sg:city":"Hamburg",
    "sg:phone":"+49 40/5709909",
    "sg:postcode":"22523",
    "sg:province":"Hamburg",
    "wof:name":"Paula Plagemann Krankengymnastin",
    "wof:placetype":"venue"
},
  "geometry": {"coordinates":[9.904842,53.599178],"type":"Point"}
}