{
  "type": "Feature",
  "properties": {
    "iso:country":"DE",
    "sg:address":"Am Vorderen Berg 9",
    "sg:city":"Ha\u00dfmersheim",
    "sg:phone":"+49 6266/371",
    "sg:postcode":"74855",
    "sg:province":"Baden-W\u00fcrttemberg",
    "wof:name":"Erhard Supp Weinanbau",
    "wof:placetype":"venue"
},
  "geometry": {"coordinates":[9.1309747696,49.2835006714],"type":"Point"}
}