{
  "type": "Feature",
  "properties": {
    "iso:country":"DE",
    "sg:address":"Altenburgerstr. 9",
    "sg:city":"Leipzig",
    "sg:phone":"+49 341/35003570",
    "sg:postcode":"04275",
    "sg:province":"Sachsen",
    "wof:name":"Cine Impuls Leipzig Film Und Fernsehproduktion Gmbh",
    "wof:placetype":"venue"
},
  "geometry": {"coordinates":[12.38309,51.319046],"type":"Point"}
}