{
  "type": "Feature",
  "properties": {
    "iso:country":"DE",
    "sg:address":"Georgstr. 6",
    "sg:city":"Osnabr\u00fcck",
    "sg:phone":"+49 541/357880",
    "sg:postcode":"49074",
    "sg:province":"Niedersachsen",
    "wof:name":"Hugo W\u00fcsthoff Gmbh & Co. Kg",
    "wof:placetype":"venue"
},
  "geometry": {"coordinates":[8.0479316711,52.274597168],"type":"Point"}
}