{
  "type": "Feature",
  "properties": {
    "iso:country":"DE",
    "sg:address":"Strunzstrasse 18",
    "sg:city":"Lengenfeld",
    "sg:phone":"+49 37606/33099",
    "sg:postcode":"08485",
    "sg:province":"Sachsen",
    "wof:name":"Design By Joundo",
    "wof:placetype":"venue"
},
  "geometry": {"coordinates":[12.3660411835,50.5639953613],"type":"Point"}
}