{
  "type": "Feature",
  "properties": {
    "iso:country":"DE",
    "sg:address":"Rohrbacher Str. 189",
    "sg:city":"Heidelberg",
    "sg:phone":"+49 6221/374969",
    "sg:postcode":"69126",
    "sg:province":"Baden-W\u00fcrttemberg",
    "wof:name":"Dr. Med. Klaus Schr\u00f6der Arzt F\u00fcr Allgemeinmedizin",
    "wof:placetype":"venue"
},
  "geometry": {"coordinates":[8.6902208328,49.3884925842],"type":"Point"}
}