{
  "type": "Feature",
  "properties": {
    "iso:country":"DE",
    "sg:address":"Schlo\u00dfstr. 17",
    "sg:city":"M\u00fchlacker",
    "sg:phone":"+49 7041/6849",
    "sg:postcode":"75417",
    "sg:province":"Baden-W\u00fcrttemberg",
    "wof:name":"Franz Spies",
    "wof:placetype":"venue"
},
  "geometry": {"coordinates":[8.892135,48.940945],"type":"Point"}
}