{
  "type": "Feature",
  "properties": {
    "iso:country":"DE",
    "sg:address":"Pestalozzistr. 4",
    "sg:city":"Coswig",
    "sg:phone":"+49 3523/67460",
    "sg:postcode":"01640",
    "sg:province":"Sachsen",
    "wof:name":"Christine Sch\u00f6ps",
    "wof:placetype":"venue"
},
  "geometry": {"coordinates":[13.5837907791,51.1254768372],"type":"Point"}
}