{
  "type": "Feature",
  "properties": {
    "iso:country":"DE",
    "sg:address":"Helmut-Kumpf-Str. 5",
    "sg:city":"Lennestadt",
    "sg:phone":"+49 2723/959575",
    "sg:postcode":"57368",
    "sg:province":"Nordrhein-Westfalen",
    "wof:name":"Simon-apotheke Ursula Hansknecht",
    "wof:placetype":"venue"
},
  "geometry": {"coordinates":[8.073343,51.105541],"type":"Point"}
}