{
  "type": "Feature",
  "properties": {
    "iso:country":"DE",
    "sg:address":"An der Prie\u00dfnitzaue 11-13",
    "sg:city":"Dresden",
    "sg:postcode":"01328",
    "sg:province":"Sachsen",
    "wof:name":"Gfs Ges. F\u00fcr Statistik Im Gesundheitswesen Mbh",
    "wof:placetype":"venue"
},
  "geometry": {"coordinates":[13.887345,51.06778],"type":"Point"}
}