{
  "type": "Feature",
  "properties": {
    "iso:country":"DE",
    "sg:address":"Harzstr. 9",
    "sg:city":"Langelsheim",
    "sg:phone":"+49 5326/2660",
    "sg:postcode":"38685",
    "sg:province":"Niedersachsen",
    "wof:name":"Heinrich Immenroth",
    "wof:placetype":"venue"
},
  "geometry": {"coordinates":[10.33117,51.937592],"type":"Point"}
}