{
  "type": "Feature",
  "properties": {
    "iso:country":"DE",
    "sg:address":"Weingasse 9",
    "sg:city":"Wintrich",
    "sg:phone":"+49 6534/495",
    "sg:postcode":"54487",
    "sg:province":"Rheinland-Pfalz",
    "wof:name":"Josef Gorges-reef",
    "wof:placetype":"venue"
},
  "geometry": {"coordinates":[6.9533638954,49.8835868835],"type":"Point"}
}