{
  "type": "Feature",
  "properties": {
    "iso:country":"DE",
    "sg:address":"Kirchhofstr.",
    "sg:city":"Demmin",
    "sg:phone":"+49 3998/432534",
    "sg:postcode":"17109",
    "sg:province":"Mecklenburg-Vorpommern",
    "wof:name":"Wolfgang Dziupa",
    "wof:placetype":"venue"
},
  "geometry": {"coordinates":[13.0398769379,53.9057273865],"type":"Point"}
}