{
  "type": "Feature",
  "properties": {
    "iso:country":"DE",
    "sg:address":"Ostendorfallee 5",
    "sg:city":"Lippstadt",
    "sg:phone":"+49 2941/3419",
    "sg:postcode":"59555",
    "sg:province":"Nordrhein-Westfalen",
    "wof:name":"Diether Pelz",
    "wof:placetype":"venue"
},
  "geometry": {"coordinates":[8.342769,51.677727],"type":"Point"}
}