{
  "type": "Feature",
  "properties": {
    "iso:country":"DE",
    "sg:address":"Jagdweg 17 a",
    "sg:city":"Swisttal",
    "sg:phone":"+49 2254/1517",
    "sg:postcode":"53913",
    "sg:province":"Nordrhein-Westfalen",
    "wof:name":"J. Rosin",
    "wof:placetype":"venue"
},
  "geometry": {"coordinates":[6.9106059074,50.713432312],"type":"Point"}
}