{
  "type": "Feature",
  "properties": {
    "iso:country":"DE",
    "sg:address":"In den Kreuzfeldern 5",
    "sg:city":"Longuich",
    "sg:phone":"+49 6502/92200",
    "sg:postcode":"54340",
    "sg:province":"Rheinland-Pfalz",
    "wof:name":"Fleischerei St. Marx Gmbh",
    "wof:placetype":"venue"
},
  "geometry": {"coordinates":[6.7640089989,49.808216095],"type":"Point"}
}