{
  "type": "Feature",
  "properties": {
    "iso:country":"DE",
    "sg:address":"Albrechtstr. 80",
    "sg:city":"Berlin",
    "sg:phone":"+49 30/7951721",
    "sg:postcode":"12167",
    "sg:province":"Berlin",
    "wof:name":"Bert Suplie",
    "wof:placetype":"venue"
},
  "geometry": {"coordinates":[13.338698,52.449188],"type":"Point"}
}