{
  "type": "Feature",
  "properties": {
    "iso:country":"DE",
    "sg:address":"Altenessener Str. 400a",
    "sg:city":"Essen",
    "sg:phone":"+49 201/351555",
    "sg:postcode":"45329",
    "sg:province":"Nordrhein-Westfalen",
    "wof:name":"Karl-heinz W. Brandt",
    "wof:placetype":"venue"
},
  "geometry": {"coordinates":[7.0082678795,51.4980010986],"type":"Point"}
}