{
  "type": "Feature",
  "properties": {
    "iso:country":"DE",
    "sg:address":"Friedrich-Ebert-Str. 38",
    "sg:city":"Duisburg",
    "sg:phone":"+49 2065/30660",
    "sg:postcode":"47226",
    "sg:province":"Nordrhein-Westfalen",
    "wof:name":"Heinz Dannenberg Ingenieur",
    "wof:placetype":"venue"
},
  "geometry": {"coordinates":[6.7119240761,51.4111747742],"type":"Point"}
}