{
  "type": "Feature",
  "properties": {
    "iso:country":"DE",
    "sg:address":"Hauptstr. 43",
    "sg:city":"Bietigheim-Bissingen",
    "sg:phone":"+49 7142/980514",
    "sg:postcode":"74321",
    "sg:province":"Baden-W\u00fcrttemberg",
    "wof:name":"Plus Warenhandels Gmbh & Co. Ohg",
    "wof:placetype":"venue"
},
  "geometry": {"coordinates":[9.1272726059,48.9594039917],"type":"Point"}
}