{
  "type": "Feature",
  "properties": {
    "iso:country":"DE",
    "sg:address":"Eschenweg 3",
    "sg:city":"Rosenheim",
    "sg:phone":"+49 8031/68262",
    "sg:postcode":"83022",
    "sg:province":"Bayern",
    "wof:name":"Max Beinhofer",
    "wof:placetype":"venue"
},
  "geometry": {"coordinates":[12.1464910507,47.8448638916],"type":"Point"}
}