{
  "type": "Feature",
  "properties": {
    "iso:country":"DE",
    "sg:address":"Alt-Tegel 28",
    "sg:city":"Berlin",
    "sg:phone":"+49 30/4345744",
    "sg:postcode":"13507",
    "sg:province":"Berlin",
    "wof:name":"Olaf Kaminski",
    "wof:placetype":"venue"
},
  "geometry": {"coordinates":[13.278056,52.588535],"type":"Point"}
}