{
  "type": "Feature",
  "properties": {
    "iso:country":"DE",
    "sg:address":"Pekingstr. 83",
    "sg:city":"Dortmund",
    "sg:phone":"+49 231/422031",
    "sg:postcode":"44269",
    "sg:province":"Nordrhein-Westfalen",
    "wof:name":"Klaus Gola",
    "wof:placetype":"venue"
},
  "geometry": {"coordinates":[7.52073,51.491943],"type":"Point"}
}