{
  "type": "Feature",
  "properties": {
    "iso:country":"DE",
    "sg:address":"Nettelstedter Str. 8",
    "sg:city":"L\u00fcbbecke",
    "sg:phone":"+49 5741/6285",
    "sg:postcode":"32312",
    "sg:province":"Nordrhein-Westfalen",
    "wof:name":"W. Grote",
    "wof:placetype":"venue"
},
  "geometry": {"coordinates":[8.7195196152,52.2959594727],"type":"Point"}
}