{
  "type": "Feature",
  "properties": {
    "iso:country":"DE",
    "sg:address":"Zeppelinstr. 2",
    "sg:city":"Bohmte",
    "sg:phone":"+49 5471/2370",
    "sg:postcode":"49163",
    "sg:province":"Niedersachsen",
    "wof:name":"Marlies Minderhoud Bw-kantine",
    "wof:placetype":"venue"
},
  "geometry": {"coordinates":[8.3220281601,52.3679466248],"type":"Point"}
}