{
  "type": "Feature",
  "properties": {
    "iso:country":"DE",
    "sg:address":"Marktstr. 195",
    "sg:city":"Pfullingen",
    "sg:phone":"+49 7121/29184",
    "sg:postcode":"72793",
    "sg:province":"Baden-W\u00fcrttemberg",
    "wof:name":"Eep-wm-kalt- Und Warmstrahltechnik Gmbh",
    "wof:placetype":"venue"
},
  "geometry": {"coordinates":[9.225153923,48.4837036133],"type":"Point"}
}