{
  "type": "Feature",
  "properties": {
    "iso:country":"DE",
    "sg:address":"Am Kalkwerk 3",
    "sg:city":"Banteln",
    "sg:phone":"+49 5182/6298",
    "sg:postcode":"31029",
    "sg:province":"Niedersachsen",
    "wof:name":"Wetzel Gmbh",
    "wof:placetype":"venue"
},
  "geometry": {"coordinates":[9.7466688156,52.0688819885],"type":"Point"}
}