{
  "type": "Feature",
  "properties": {
    "iso:country":"DE",
    "sg:address":"Vordere Schafstr. 18a",
    "sg:city":"Stuttgart",
    "sg:phone":"+49 711/454510",
    "sg:postcode":"70599",
    "sg:province":"Baden-W\u00fcrttemberg",
    "wof:name":"Werner Schad",
    "wof:placetype":"venue"
},
  "geometry": {"coordinates":[9.209556,48.702564],"type":"Point"}
}