{
  "type": "Feature",
  "properties": {
    "iso:country":"DE",
    "sg:address":"Seebohmstr. 39",
    "sg:city":"Uelzen",
    "sg:phone":"+49 581/90600",
    "sg:postcode":"29525",
    "sg:province":"Niedersachsen",
    "wof:name":"S\u00f6ffker Elektronik Uelzen Gmbh",
    "wof:placetype":"venue"
},
  "geometry": {"coordinates":[10.533934,52.992439],"type":"Point"}
}