{
  "type": "Feature",
  "properties": {
    "iso:country":"DE",
    "sg:address":"Rotenhanstr. 30",
    "sg:city":"M\u00fcnchen",
    "sg:phone":"+49 89/7552283",
    "sg:postcode":"81476",
    "sg:province":"Bayern",
    "wof:name":"G. C. Schulze",
    "wof:placetype":"venue"
},
  "geometry": {"coordinates":[11.4901895523,48.0754394531],"type":"Point"}
}