{
  "type": "Feature",
  "properties": {
    "iso:country":"DE",
    "sg:address":"Karl-Klein-Str. 28",
    "sg:city":"Petersberg",
    "sg:postcode":"66989",
    "sg:province":"Rheinland-Pfalz",
    "wof:name":"Karins Jeans-ecke",
    "wof:placetype":"venue"
},
  "geometry": {"coordinates":[7.5705327988,49.2394828796],"type":"Point"}
}