{
  "type": "Feature",
  "properties": {
    "iso:country":"DE",
    "sg:address":"Schlachthofstr. 4",
    "sg:city":"Annaberg-Buchholz",
    "sg:phone":"+49 3733/65378",
    "sg:postcode":"09456",
    "sg:province":"Sachsen",
    "wof:name":"Werner Reiske",
    "wof:placetype":"venue"
},
  "geometry": {"coordinates":[12.996052742,50.5557670593],"type":"Point"}
}