{
  "type": "Feature",
  "properties": {
    "iso:country":"DE",
    "sg:address":"Haingasse 88",
    "sg:city":"Colditz",
    "sg:phone":"+49 34381/3301",
    "sg:postcode":"04680",
    "sg:province":"Sachsen",
    "wof:name":"S. Sturz",
    "wof:placetype":"venue"
},
  "geometry": {"coordinates":[12.801056,51.137665],"type":"Point"}
}