{
  "type": "Feature",
  "properties": {
    "iso:country":"DE",
    "sg:address":"Wiesenstr. 1",
    "sg:city":"Bornheim",
    "sg:phone":"+49 6348/344",
    "sg:postcode":"76879",
    "sg:province":"Rheinland-Pfalz",
    "wof:name":"G Pauli",
    "wof:placetype":"venue"
},
  "geometry": {"coordinates":[8.1706132889,49.2220191956],"type":"Point"}
}