{
  "type": "Feature",
  "properties": {
    "iso:country":"DE",
    "sg:address":"Am Wehrhahn 41",
    "sg:city":"D\u00fcsseldorf",
    "sg:phone":"+49 211/172740",
    "sg:postcode":"40211",
    "sg:province":"Nordrhein-Westfalen",
    "wof:name":"Mitsui-soko Europe B. V. Zweigniederlassung D\u00fcsseldorf",
    "wof:placetype":"venue"
},
  "geometry": {"coordinates":[6.791225,51.22823],"type":"Point"}
}