{
  "type": "Feature",
  "properties": {
    "iso:country":"DE",
    "sg:address":"Rabegasse 2",
    "sg:city":"Gr\u00fcnberg",
    "sg:phone":"+49 6401/8153",
    "sg:postcode":"35305",
    "sg:province":"Hessen",
    "wof:name":"Stefan Nitsch Ihr Platz",
    "wof:placetype":"venue"
},
  "geometry": {"coordinates":[8.960247,50.590992],"type":"Point"}
}