{
  "type": "Feature",
  "properties": {
    "iso:country":"DE",
    "sg:address":"Schiffahrter Damm 486",
    "sg:city":"M\u00fcnster",
    "sg:phone":"+49 251/3211294",
    "sg:postcode":"48157",
    "sg:province":"Nordrhein-Westfalen",
    "wof:name":"Dieter Gerken",
    "wof:placetype":"venue"
},
  "geometry": {"coordinates":[7.677304,52.008686],"type":"Point"}
}