{
  "type": "Feature",
  "properties": {
    "iso:country":"DE",
    "sg:address":"Mosbacher Str. 68 Neckarelz",
    "sg:city":"Mosbach",
    "sg:phone":"+49 4962/616360",
    "sg:postcode":"74821",
    "sg:province":"Baden-W\u00fcrttemberg",
    "wof:name":"Autohaus Heinrich Gramling Gmbh & Co Kg",
    "wof:placetype":"venue"
},
  "geometry": {"coordinates":[9.146197319,49.3550186157],"type":"Point"}
}