{
  "type": "Feature",
  "properties": {
    "iso:country":"DE",
    "sg:address":"Herbersdorf",
    "sg:city":"Au",
    "sg:phone":"+49 8752/7304",
    "sg:postcode":"84072",
    "sg:province":"Bayern",
    "wof:name":"Helmut Schwaiger",
    "wof:placetype":"venue"
},
  "geometry": {"coordinates":[11.68483,48.535889],"type":"Point"}
}