{
  "type": "Feature",
  "properties": {
    "iso:country":"DE",
    "sg:address":"Schmalweg 50",
    "sg:city":"Mainz-Kastel",
    "sg:phone":"+49 6134/18140",
    "sg:postcode":"55252",
    "sg:province":"Hessen",
    "wof:name":"Cst Logic Softwareent- Wicklungs Gmbh",
    "wof:placetype":"venue"
},
  "geometry": {"coordinates":[8.291513443,50.0175018311],"type":"Point"}
}