{
  "type": "Feature",
  "properties": {
    "iso:country":"DE",
    "sg:address":"Gro\u00dfer Teil 8",
    "sg:city":"Enger",
    "sg:phone":"+49 4952/2497590",
    "sg:postcode":"32130",
    "sg:province":"Nordrhein-Westfalen",
    "wof:name":"Betron Industriesteuerung Gmbh",
    "wof:placetype":"venue"
},
  "geometry": {"coordinates":[8.535238,52.139481],"type":"Point"}
}