{
  "type": "Feature",
  "properties": {
    "iso:country":"DE",
    "sg:address":"Stuttgarter Str. 29",
    "sg:city":"Korntal-M\u00fcnchingen",
    "sg:phone":"+49 7150/2946",
    "sg:postcode":"70825",
    "sg:province":"Baden-W\u00fcrttemberg",
    "wof:name":"Kosmetik-insel",
    "wof:placetype":"venue"
},
  "geometry": {"coordinates":[9.091867,48.854492],"type":"Point"}
}