{
  "type": "Feature",
  "properties": {
    "iso:country":"DE",
    "sg:address":"Zweibr\u00fcckenstr. 8",
    "sg:city":"M\u00fcnchen",
    "sg:phone":"+49 89/296217",
    "sg:postcode":"80331",
    "sg:province":"Bayern",
    "wof:name":"M\u00fcnchner Filmpassage",
    "wof:placetype":"venue"
},
  "geometry": {"coordinates":[11.5830154419,48.1331481934],"type":"Point"}
}