{
  "type": "Feature",
  "properties": {
    "iso:country":"DE",
    "sg:address":"Bismarckstr. 10",
    "sg:city":"Weinheim",
    "sg:postcode":"69469",
    "sg:province":"Baden-W\u00fcrttemberg",
    "wof:name":"Ksi Karima Stephan Industrievertretungen E. K.",
    "wof:placetype":"venue"
},
  "geometry": {"coordinates":[8.6702108383,49.5522117615],"type":"Point"}
}