{
  "type": "Feature",
  "properties": {
    "iso:country":"DE",
    "sg:address":"Westkotter Str. 105",
    "sg:city":"Wuppertal",
    "sg:phone":"+49 202/503029",
    "sg:postcode":"42277",
    "sg:province":"Nordrhein-Westfalen",
    "wof:name":"Star Automaten Und Entertainment Gmbh",
    "wof:placetype":"venue"
},
  "geometry": {"coordinates":[7.2062129974,51.2811431885],"type":"Point"}
}