{
  "type": "Feature",
  "properties": {
    "iso:country":"DE",
    "sg:address":"Vierdener Str. 1",
    "sg:city":"Wohnste",
    "sg:phone":"+49 4169/91110",
    "sg:postcode":"27419",
    "sg:province":"Niedersachsen",
    "wof:name":"J. Vagts Gmbh",
    "wof:placetype":"venue"
},
  "geometry": {"coordinates":[9.5226697922,53.3549346924],"type":"Point"}
}