{
  "type": "Feature",
  "properties": {
    "iso:country":"DE",
    "sg:address":"Hertzstr.",
    "sg:city":"W\u00fcrzburg",
    "sg:phone":"+49 931/250620",
    "sg:postcode":"97076",
    "sg:province":"Bayern",
    "wof:name":"Kraftanlagen Ag",
    "wof:placetype":"venue"
},
  "geometry": {"coordinates":[9.976836,49.800213],"type":"Point"}
}