{
  "type": "Feature",
  "properties": {
    "iso:country":"DE",
    "sg:address":"Nachtigallenweg 52",
    "sg:city":"M\u00f6nchengladbach",
    "sg:phone":"+49 2161/603086",
    "sg:postcode":"41065",
    "sg:province":"Nordrhein-Westfalen",
    "wof:name":"Peter Bodewein",
    "wof:placetype":"venue"
},
  "geometry": {"coordinates":[6.487819,51.199577],"type":"Point"}
}