{
  "type": "Feature",
  "properties": {
    "iso:country":"DE",
    "sg:address":"Marienstr. 43",
    "sg:city":"Braunschweig",
    "sg:phone":"+49 531/76226",
    "sg:postcode":"38102",
    "sg:province":"Niedersachsen",
    "wof:name":"Dieter Wellner Kunststoffwaren",
    "wof:placetype":"venue"
},
  "geometry": {"coordinates":[10.5461673737,52.2642440796],"type":"Point"}
}