{
  "type": "Feature",
  "properties": {
    "iso:country":"DE",
    "sg:address":"Detmolder Str. 550",
    "sg:city":"Bielefeld",
    "sg:phone":"+49 521/924350",
    "sg:postcode":"33699",
    "sg:province":"Nordrhein-Westfalen",
    "wof:name":"Deppe Gmbh & Co. Kg",
    "wof:placetype":"venue"
},
  "geometry": {"coordinates":[8.6038827896,51.9936523438],"type":"Point"}
}