{
  "type": "Feature",
  "properties": {
    "iso:country":"DE",
    "sg:address":"Sophienstr. 27",
    "sg:city":"F\u00fcrth",
    "sg:phone":"+49 911/7906699",
    "sg:postcode":"90765",
    "sg:province":"Bayern",
    "wof:name":"H. M\u00fcnderlein",
    "wof:placetype":"venue"
},
  "geometry": {"coordinates":[11.0160417557,49.4763221741],"type":"Point"}
}