{
  "type": "Feature",
  "properties": {
    "iso:country":"DE",
    "sg:address":"Kneippstr. 9",
    "sg:city":"Wiesbaden",
    "sg:postcode":"65203",
    "sg:province":"Hessen",
    "wof:name":"Digit Art & Design Ohg",
    "wof:placetype":"venue"
},
  "geometry": {"coordinates":[8.232954,50.045712],"type":"Point"}
}