{
  "type": "Feature",
  "properties": {
    "iso:country":"DE",
    "sg:address":"Auf Der Sunhaar 30",
    "sg:city":"Gronau",
    "sg:phone":"+49 4925/652066",
    "sg:postcode":"48599",
    "sg:province":"Nordrhein-Westfalen",
    "wof:name":"Althues Gmbh",
    "wof:placetype":"venue"
},
  "geometry": {"coordinates":[7.044978,52.179825],"type":"Point"}
}