{
  "type": "Feature",
  "properties": {
    "iso:country":"DE",
    "sg:address":"In der Au 33",
    "sg:city":"Solms",
    "sg:phone":"+49 6441/5584",
    "sg:postcode":"35606",
    "sg:province":"Hessen",
    "wof:name":"Heinrich Steul Gmbh & Co. Kg",
    "wof:placetype":"venue"
},
  "geometry": {"coordinates":[8.4326896667,50.5505447388],"type":"Point"}
}