{
  "type": "Feature",
  "properties": {
    "iso:country":"DE",
    "sg:address":"Bentheimer Str. 59",
    "sg:city":"Nordhorn",
    "sg:phone":"+49 5921/71060",
    "sg:postcode":"48529",
    "sg:province":"Niedersachsen",
    "wof:name":"Schl\u00fcter & Niers Immobilien Gmbh",
    "wof:placetype":"venue"
},
  "geometry": {"coordinates":[7.072326,52.430069],"type":"Point"}
}