{
  "type": "Feature",
  "properties": {
    "iso:country":"DE",
    "sg:address":"Sterkrader Str. 45",
    "sg:city":"Bottrop",
    "sg:phone":"+49 2041/24263",
    "sg:postcode":"46236",
    "sg:province":"Nordrhein-Westfalen",
    "wof:name":"Helmut Rindle",
    "wof:placetype":"venue"
},
  "geometry": {"coordinates":[6.915895,51.521069],"type":"Point"}
}