{
  "type": "Feature",
  "properties": {
    "iso:country":"DE",
    "sg:address":"Zum Kap 16",
    "sg:city":"Dautphetal",
    "sg:phone":"+49 6468/254",
    "sg:postcode":"35232",
    "sg:province":"Hessen",
    "wof:name":"Friedel Burmann",
    "wof:placetype":"venue"
},
  "geometry": {"coordinates":[8.5052375793,50.8449859619],"type":"Point"}
}