{
  "type": "Feature",
  "properties": {
    "iso:country":"DE",
    "sg:address":"Uferstr. 21",
    "sg:city":"Bad Salzuflen",
    "sg:phone":"+49 5222/84837",
    "sg:postcode":"32108",
    "sg:province":"Nordrhein-Westfalen",
    "wof:name":"Farben-k\u00f6ster Fritz K\u00f6ster",
    "wof:placetype":"venue"
},
  "geometry": {"coordinates":[8.754322052,52.066280365],"type":"Point"}
}