{
  "type": "Feature",
  "properties": {
    "iso:country":"DE",
    "sg:address":"Waldweg 7",
    "sg:city":"Schwalmtal",
    "sg:phone":"+49 2163/30088",
    "sg:postcode":"41366",
    "sg:province":"Nordrhein-Westfalen",
    "wof:name":"H.-w. Feikes",
    "wof:placetype":"venue"
},
  "geometry": {"coordinates":[6.312743,51.198734],"type":"Point"}
}