{
  "type": "Feature",
  "properties": {
    "iso:country":"DE",
    "sg:address":"H\u00f6hlenweg 7",
    "sg:city":"Goslar",
    "sg:phone":"+49 5321/61104",
    "sg:postcode":"38642",
    "sg:province":"Niedersachsen",
    "wof:name":"J\u00fcrgen Brandt",
    "wof:placetype":"venue"
},
  "geometry": {"coordinates":[10.48017,51.899803],"type":"Point"}
}