{
  "type": "Feature",
  "properties": {
    "iso:country":"DE",
    "sg:address":"Marie-Curie-Str. 3",
    "sg:city":"Rheinbach",
    "sg:postcode":"53359",
    "sg:province":"Nordrhein-Westfalen",
    "wof:name":"Inmatec Innovative Materials U. Technologies Gmbh",
    "wof:placetype":"venue"
},
  "geometry": {"coordinates":[6.9523859024,50.6258163452],"type":"Point"}
}