{
  "type": "Feature",
  "properties": {
    "iso:country":"DE",
    "sg:address":"Brandenburger Allee 6",
    "sg:city":"Brandenburg",
    "sg:phone":"+49 3381/802253",
    "sg:postcode":"14774",
    "sg:province":"Brandenburg",
    "wof:name":"Foto-mayer",
    "wof:placetype":"venue"
},
  "geometry": {"coordinates":[12.4067821503,52.3977241516],"type":"Point"}
}