{
  "type": "Feature",
  "properties": {
    "iso:country":"DE",
    "sg:address":"Feuerbachstr. 8",
    "sg:city":"Mannheim",
    "sg:phone":"+49 621/4185070",
    "sg:postcode":"68163",
    "sg:province":"Baden-W\u00fcrttemberg",
    "wof:name":"S-tec Datenverarbeitung Gmbh",
    "wof:placetype":"venue"
},
  "geometry": {"coordinates":[8.5077362061,49.4803733826],"type":"Point"}
}