{
  "type": "Feature",
  "properties": {
    "iso:country":"DE",
    "sg:address":"Klosterstr. 15",
    "sg:city":"Straelen",
    "sg:phone":"+49 2834/93730",
    "sg:postcode":"47638",
    "sg:province":"Nordrhein-Westfalen",
    "wof:name":"Pollmann Flugreisen Gmbh",
    "wof:placetype":"venue"
},
  "geometry": {"coordinates":[6.2652111053,51.4443473816],"type":"Point"}
}