{
  "type": "Feature",
  "properties": {
    "iso:country":"DE",
    "sg:address":"Klein D\u00fcngener Str. 21",
    "sg:city":"Bad Salzdetfurth",
    "sg:phone":"+49 5064/283",
    "sg:postcode":"31162",
    "sg:province":"Niedersachsen",
    "wof:name":"Josef Meyer",
    "wof:placetype":"venue"
},
  "geometry": {"coordinates":[10.02811,52.094608],"type":"Point"}
}