{
  "type": "Feature",
  "properties": {
    "iso:country":"DE",
    "sg:address":"Kleiststr. 3",
    "sg:city":"Spraitbach",
    "sg:phone":"+49 7176/6322",
    "sg:postcode":"73565",
    "sg:province":"Baden-W\u00fcrttemberg",
    "wof:name":"H.-j. Martin Ingenieur",
    "wof:placetype":"venue"
},
  "geometry": {"coordinates":[9.7598400116,48.8844718933],"type":"Point"}
}