{
  "type": "Feature",
  "properties": {
    "iso:country":"DE",
    "sg:address":"Berliner Ring 109",
    "sg:city":"Wetzlar",
    "sg:phone":"+49 6441/5860",
    "sg:postcode":"35576",
    "sg:province":"Hessen",
    "wof:name":"Heinrich Sch\u00e4fer",
    "wof:placetype":"venue"
},
  "geometry": {"coordinates":[8.4681491852,50.5670089722],"type":"Point"}
}