{
  "type": "Feature",
  "properties": {
    "iso:country":"DE",
    "sg:address":"Leo-Baeck-Str. 14",
    "sg:city":"Berlin",
    "sg:phone":"+49 30/8151397",
    "sg:postcode":"14165",
    "sg:province":"Berlin",
    "wof:name":"W. Schmidt Tapeten-einzelhandel",
    "wof:placetype":"venue"
},
  "geometry": {"coordinates":[13.2610816956,52.4218215942],"type":"Point"}
}