{
  "type": "Feature",
  "properties": {
    "iso:country":"DE",
    "sg:address":"Robert-Koch-Str. 10",
    "sg:city":"Viernheim",
    "sg:phone":"+49 6204/75008",
    "sg:postcode":"68519",
    "sg:province":"Hessen",
    "wof:name":"Mas Maschinen-anlagen- Service Gmbh",
    "wof:placetype":"venue"
},
  "geometry": {"coordinates":[8.580549,49.536476],"type":"Point"}
}