{
  "type": "Feature",
  "properties": {
    "iso:country":"DE",
    "sg:address":"Parkhofstr. 27",
    "sg:city":"H\u00fcckelhoven",
    "sg:phone":"+49 2433/84044",
    "sg:postcode":"41836",
    "sg:province":"Nordrhein-Westfalen",
    "wof:name":"Thiemonds-knie Und Knie Rechtsanw\u00e4lte",
    "wof:placetype":"venue"
},
  "geometry": {"coordinates":[6.223760128,51.0514793396],"type":"Point"}
}