{
  "type": "Feature",
  "properties": {
    "iso:country":"DE",
    "sg:address":"Untere W\u00fclle 33",
    "sg:city":"Schwerte",
    "sg:phone":"+49 2304/16966",
    "sg:postcode":"58239",
    "sg:province":"Nordrhein-Westfalen",
    "wof:name":"Tus Wandhofen 1911 E. V. Heinz Bodenstein",
    "wof:placetype":"venue"
},
  "geometry": {"coordinates":[7.5588989258,51.4265937805],"type":"Point"}
}