{
  "type": "Feature",
  "properties": {
    "iso:country":"DE",
    "sg:address":"Bahnser Weg 18",
    "sg:city":"Suderburg",
    "sg:phone":"+49 5826/1277",
    "sg:postcode":"29556",
    "sg:province":"Niedersachsen",
    "wof:name":"Klaus Oelscher",
    "wof:placetype":"venue"
},
  "geometry": {"coordinates":[10.4332971573,52.931137085],"type":"Point"}
}