{
  "type": "Feature",
  "properties": {
    "iso:country":"DE",
    "sg:address":"Weilstr. 118",
    "sg:city":"Weilm\u00fcnster",
    "sg:phone":"+49 6472/419",
    "sg:postcode":"35789",
    "sg:province":"Hessen",
    "wof:name":"Christa Hammer",
    "wof:placetype":"venue"
},
  "geometry": {"coordinates":[8.374074,50.434761],"type":"Point"}
}