{
  "type": "Feature",
  "properties": {
    "iso:country":"DE",
    "sg:address":"Lange Str. 25",
    "sg:city":"Walsrode",
    "sg:phone":"+49 5161/8002",
    "sg:postcode":"29664",
    "sg:province":"Niedersachsen",
    "wof:name":"Hebra Gmbh",
    "wof:placetype":"venue"
},
  "geometry": {"coordinates":[9.5923070908,52.860244751],"type":"Point"}
}