{
  "type": "Feature",
  "properties": {
    "iso:country":"DE",
    "sg:address":"Schanzenweg 4",
    "sg:city":"Kirchhundem",
    "sg:phone":"+49 2723/72355",
    "sg:postcode":"57399",
    "sg:province":"Nordrhein-Westfalen",
    "wof:name":"Pension Hedwig Troester",
    "wof:placetype":"venue"
},
  "geometry": {"coordinates":[8.1779413223,51.08776474],"type":"Point"}
}