{
  "type": "Feature",
  "properties": {
    "iso:country":"DE",
    "sg:address":"Im Hahn 4",
    "sg:city":"Nauort",
    "sg:phone":"+49 2601/94000",
    "sg:postcode":"56237",
    "sg:province":"Rheinland-Pfalz",
    "wof:name":"Peter Josef Thewalt Gmbh & Co. Kg",
    "wof:placetype":"venue"
},
  "geometry": {"coordinates":[7.6321511269,50.4645805359],"type":"Point"}
}