{
  "type": "Feature",
  "properties": {
    "iso:country":"DE",
    "sg:address":"Paracelsusstr. 5",
    "sg:city":"Wetter",
    "sg:phone":"+49 2335/963237",
    "sg:postcode":"58300",
    "sg:province":"Nordrhein-Westfalen",
    "wof:name":"Mic-michaelis Consulting",
    "wof:placetype":"venue"
},
  "geometry": {"coordinates":[7.3730020523,51.365234375],"type":"Point"}
}