{
  "type": "Feature",
  "properties": {
    "iso:country":"DE",
    "sg:address":"Lessingstr. 4",
    "sg:city":"Frankfurt",
    "sg:phone":"+49 335/324630",
    "sg:postcode":"15230",
    "sg:province":"Brandenburg",
    "wof:name":"Klaus Daute Ingenieur",
    "wof:placetype":"venue"
},
  "geometry": {"coordinates":[14.5343675613,52.3436355591],"type":"Point"}
}