{
  "type": "Feature",
  "properties": {
    "iso:country":"DE",
    "sg:address":"Luchsweg 4b",
    "sg:city":"Augsburg",
    "sg:phone":"+49 821/707443",
    "sg:postcode":"86169",
    "sg:province":"Bayern",
    "wof:name":"A. Kirchberger",
    "wof:placetype":"venue"
},
  "geometry": {"coordinates":[10.897818,48.409542],"type":"Point"}
}