{
  "type": "Feature",
  "properties": {
    "iso:country":"DE",
    "sg:address":"Griesgasse 5",
    "sg:city":"Siegburg",
    "sg:phone":"+49 2241",
    "sg:postcode":"53721",
    "sg:province":"Nordrhein-Westfalen",
    "wof:name":"Anwaltskanzlei J. Helser",
    "wof:placetype":"venue"
},
  "geometry": {"coordinates":[7.206678,50.795795],"type":"Point"}
}