{
  "type": "Feature",
  "properties": {
    "iso:country":"DE",
    "sg:address":"Heilwigstr. 67 a",
    "sg:city":"M\u00fcnchen",
    "sg:postcode":"81827",
    "sg:province":"Bayern",
    "wof:name":"Ticket.de Ag",
    "wof:placetype":"venue"
},
  "geometry": {"coordinates":[11.684528,48.112831],"type":"Point"}
}