{
  "type": "Feature",
  "properties": {
    "iso:country":"DE",
    "sg:address":"Hinter dem Kloster 8",
    "sg:city":"Lemgo",
    "sg:phone":"+49 5261/5887",
    "sg:postcode":"32657",
    "sg:province":"Nordrhein-Westfalen",
    "wof:name":"Ev. Pfarramt S\u00fcd St. Johann",
    "wof:placetype":"venue"
},
  "geometry": {"coordinates":[8.8942117691,52.0280380249],"type":"Point"}
}