{
  "type": "Feature",
  "properties": {
    "iso:country":"DE",
    "sg:address":"Oberpfaffenhofen-Flugplatz",
    "sg:city":"We\u00dfling",
    "sg:postcode":"82234",
    "sg:province":"Bayern",
    "wof:name":"Ilona Luftfahrtechnik Vertriebs- Gmbh",
    "wof:placetype":"venue"
},
  "geometry": {"coordinates":[11.250382,48.075932],"type":"Point"}
}