{
  "type": "Feature",
  "properties": {
    "iso:country":"DE",
    "sg:address":"Schlo\u00dfstr. 4",
    "sg:city":"St\u00fchlingen",
    "sg:phone":"+49 7744/422",
    "sg:postcode":"79780",
    "sg:province":"Baden-W\u00fcrttemberg",
    "wof:name":"Angela Mut",
    "wof:placetype":"venue"
},
  "geometry": {"coordinates":[8.4395341873,47.7416114807],"type":"Point"}
}