{
  "type": "Feature",
  "properties": {
    "iso:country":"DE",
    "sg:address":"Waldstr. 75a",
    "sg:city":"Neu-Isenburg",
    "sg:phone":"+49 6102/6342",
    "sg:postcode":"63263",
    "sg:province":"Hessen",
    "wof:name":"R. Klee",
    "wof:placetype":"venue"
},
  "geometry": {"coordinates":[8.691638,50.053925],"type":"Point"}
}