{
  "type": "Feature",
  "properties": {
    "iso:country":"DE",
    "sg:address":"Hanauer Landstr. 19",
    "sg:city":"Hasselroth",
    "sg:phone":"+49 6055/6655",
    "sg:postcode":"63594",
    "sg:province":"Hessen",
    "wof:name":"Laurentius-apotheke",
    "wof:placetype":"venue"
},
  "geometry": {"coordinates":[9.097192,50.164162],"type":"Point"}
}