{
  "type": "Feature",
  "properties": {
    "iso:country":"DE",
    "sg:address":"Schlo\u00dfstr. 1",
    "sg:city":"Neuwied",
    "sg:postcode":"56564",
    "sg:province":"Rheinland-Pfalz",
    "wof:name":"Wiedische Rentkammer Verm\u00f6gens- Und",
    "wof:placetype":"venue"
},
  "geometry": {"coordinates":[7.4575,50.429359],"type":"Point"}
}