{
  "type": "Feature",
  "properties": {
    "iso:country":"DE",
    "sg:address":"Hauptstr. 22",
    "sg:city":"Elsterwerda",
    "sg:phone":"+49 3533/3517",
    "sg:postcode":"04910",
    "sg:province":"Brandenburg",
    "wof:name":"Karl-heinz Lerch",
    "wof:placetype":"venue"
},
  "geometry": {"coordinates":[13.52287,51.458477],"type":"Point"}
}