{
  "type": "Feature",
  "properties": {
    "iso:country":"DE",
    "sg:address":"Ruckteschellweg 4",
    "sg:city":"Hamburg",
    "sg:phone":"+49 40/2007160",
    "sg:postcode":"22089",
    "sg:province":"Hamburg",
    "wof:name":"Eduard K\u00f6llisch",
    "wof:placetype":"venue"
},
  "geometry": {"coordinates":[10.047963,53.567547],"type":"Point"}
}