{
  "type": "Feature",
  "properties": {
    "iso:country":"DE",
    "sg:address":"Oberwei\u00dfbacher Str.",
    "sg:city":"Berlin",
    "sg:phone":"+49 30/93798166",
    "sg:postcode":"12687",
    "sg:province":"Berlin",
    "wof:name":"Rossmann Drogeriemarkt",
    "wof:placetype":"venue"
},
  "geometry": {"coordinates":[13.570733,52.556957],"type":"Point"}
}