{
  "type": "Feature",
  "properties": {
    "iso:country":"DE",
    "sg:address":"Sch\u00f6ne Aussicht 55",
    "sg:city":"Neuhaus",
    "sg:phone":"+49 3679/7760",
    "sg:postcode":"98724",
    "sg:province":"Th\u00fcringen",
    "wof:name":"Angelika-stift Sch\u00f6ne Aussicht",
    "wof:placetype":"venue"
},
  "geometry": {"coordinates":[11.128521,50.509964],"type":"Point"}
}