{
  "type": "Feature",
  "properties": {
    "iso:country":"DE",
    "sg:address":"Am Ring 26",
    "sg:city":"Sinsheim",
    "sg:phone":"+49 7261/63529",
    "sg:postcode":"74889",
    "sg:province":"Baden-W\u00fcrttemberg",
    "wof:name":"Willi Rothmeier",
    "wof:placetype":"venue"
},
  "geometry": {"coordinates":[8.8483037949,49.2689971924],"type":"Point"}
}