{
  "type": "Feature",
  "properties": {
    "iso:country":"DE",
    "sg:address":"Zum S\u00fclzufer 1",
    "sg:city":"R\u00f6srath",
    "sg:phone":"+49 2205/1344",
    "sg:postcode":"51503",
    "sg:province":"Nordrhein-Westfalen",
    "wof:name":"Ingenieurkontor Laue Beratende Ingenieure Gmbh",
    "wof:placetype":"venue"
},
  "geometry": {"coordinates":[7.1931881905,50.9118881226],"type":"Point"}
}