{
  "type": "Feature",
  "properties": {
    "iso:country":"DE",
    "sg:address":"Bergstr. 7",
    "sg:city":"Otter",
    "sg:phone":"+49 4182/7188",
    "sg:postcode":"21259",
    "sg:province":"Niedersachsen",
    "wof:name":"Vicomed Gesellschaft Zum Vertrieb Medizinischer",
    "wof:placetype":"venue"
},
  "geometry": {"coordinates":[9.739711,53.239025],"type":"Point"}
}