{
  "type": "Feature",
  "properties": {
    "iso:country":"DE",
    "sg:address":"Mauritiusstr. 126",
    "sg:city":"Frechen",
    "sg:phone":"+49 2234/54262",
    "sg:postcode":"50226",
    "sg:province":"Nordrhein-Westfalen",
    "wof:name":"Peter Schwerfen",
    "wof:placetype":"venue"
},
  "geometry": {"coordinates":[6.817274,50.896755],"type":"Point"}
}