{
  "type": "Feature",
  "properties": {
    "iso:country":"DE",
    "sg:address":"Weidenweg 2",
    "sg:city":"Ketzin",
    "sg:phone":"+49 33233/83070",
    "sg:postcode":"14669",
    "sg:province":"Brandenburg",
    "wof:name":"Kaak & Sohn Gmbh",
    "wof:placetype":"venue"
},
  "geometry": {"coordinates":[12.8164386749,52.4833564758],"type":"Point"}
}