{
  "type": "Feature",
  "properties": {
    "iso:country":"DE",
    "sg:address":"Kattegatweg 1",
    "sg:city":"Emmerich",
    "sg:phone":"+49 2828/92033",
    "sg:postcode":"46446",
    "sg:province":"Nordrhein-Westfalen",
    "wof:name":"Gebr\u00fcder Derksen Gmbh",
    "wof:placetype":"venue"
},
  "geometry": {"coordinates":[6.1733980179,51.8801612854],"type":"Point"}
}