{
  "type": "Feature",
  "properties": {
    "iso:country":"DE",
    "sg:address":"Riedgasse 5",
    "sg:city":"Hungen",
    "sg:phone":"+49 6402/2701",
    "sg:postcode":"35410",
    "sg:province":"Hessen",
    "wof:name":"J\u00fcrgen Schmidt",
    "wof:placetype":"venue"
},
  "geometry": {"coordinates":[8.905542,50.447163],"type":"Point"}
}