{
  "type": "Feature",
  "properties": {
    "iso:country":"DE",
    "sg:address":"Waldbreitbacher Str. 90",
    "sg:city":"Bad H\u00f6nningen",
    "sg:phone":"+49 2635/5039",
    "sg:postcode":"53557",
    "sg:province":"Rheinland-Pfalz",
    "wof:name":"Restaurant M\u00f6nchhof",
    "wof:placetype":"venue"
},
  "geometry": {"coordinates":[7.3176860809,50.5222625732],"type":"Point"}
}