{
  "type": "Feature",
  "properties": {
    "iso:country":"DE",
    "sg:address":"Allg\u00e4uer Str. 44",
    "sg:city":"Bad W\u00f6rishofen",
    "sg:phone":"+49 8247/5298",
    "sg:postcode":"86825",
    "sg:province":"Bayern",
    "wof:name":"Gottlieb Riedler",
    "wof:placetype":"venue"
},
  "geometry": {"coordinates":[10.619319,47.968674],"type":"Point"}
}