{
  "type": "Feature",
  "properties": {
    "iso:country":"DE",
    "sg:address":"Dammstr. 5",
    "sg:city":"Bad Sch\u00f6nborn",
    "sg:phone":"+49 7253/954585",
    "sg:postcode":"76669",
    "sg:province":"Baden-W\u00fcrttemberg",
    "wof:name":"Hubeny Gmbh",
    "wof:placetype":"venue"
},
  "geometry": {"coordinates":[8.6407756805,49.2012901306],"type":"Point"}
}