{
  "type": "Feature",
  "properties": {
    "iso:country":"DE",
    "sg:address":"L\u00fctmarser Str. 44",
    "sg:city":"H\u00f6xter",
    "sg:phone":"+49 5271/8350",
    "sg:postcode":"37671",
    "sg:province":"Nordrhein-Westfalen",
    "wof:name":"Rudolf Peine",
    "wof:placetype":"venue"
},
  "geometry": {"coordinates":[9.367902,51.77375],"type":"Point"}
}