{
  "type": "Feature",
  "properties": {
    "iso:country":"DE",
    "sg:address":"F\u00e4rberstr. 24",
    "sg:city":"Albstadt",
    "sg:phone":"+49 7432/98180",
    "sg:postcode":"72461",
    "sg:province":"Baden-W\u00fcrttemberg",
    "wof:name":"M & A Gbr",
    "wof:placetype":"venue"
},
  "geometry": {"coordinates":[9.002578,48.257511],"type":"Point"}
}