{
  "type": "Feature",
  "properties": {
    "iso:country":"DE",
    "sg:address":"Kaiforter Str. 6",
    "sg:city":"Garrel",
    "sg:phone":"+49 4474/947414",
    "sg:postcode":"49681",
    "sg:province":"Niedersachsen",
    "wof:name":"Petra Lange Praxis F\u00fcr Ergotherapie",
    "wof:placetype":"venue"
},
  "geometry": {"coordinates":[8.023376,52.958881],"type":"Point"}
}