{
  "type": "Feature",
  "properties": {
    "iso:country":"DE",
    "sg:address":"August-Pf\u00e4nder-Str. 19",
    "sg:city":"N\u00fcrtingen",
    "sg:phone":"+49 7022/49852",
    "sg:postcode":"72622",
    "sg:province":"Baden-W\u00fcrttemberg",
    "wof:name":"Ralf Altd\u00f6rfer Steuerberater",
    "wof:placetype":"venue"
},
  "geometry": {"coordinates":[9.3549251556,48.6133346558],"type":"Point"}
}