{
  "type": "Feature",
  "properties": {
    "iso:country":"DE",
    "sg:address":"Anton-Hilz-Str. 2",
    "sg:city":"Riedlh\u00fctte",
    "sg:phone":"+49 8553/1526",
    "sg:postcode":"94566",
    "sg:province":"Bayern",
    "wof:name":"Willi Riedl",
    "wof:placetype":"venue"
},
  "geometry": {"coordinates":[13.3853464127,48.9086227417],"type":"Point"}
}