{
  "type": "Feature",
  "properties": {
    "iso:country":"DE",
    "sg:address":"Hamburger Str. 6",
    "sg:city":"Dessau",
    "sg:phone":"+49 340/610039",
    "sg:postcode":"06846",
    "sg:province":"Sachsen-Anhalt",
    "wof:name":"Fred Alisch",
    "wof:placetype":"venue"
},
  "geometry": {"coordinates":[12.2242031097,51.84973526],"type":"Point"}
}