{
  "type": "Feature",
  "properties": {
    "iso:country":"DE",
    "sg:address":"Reisachangerstr. 8",
    "sg:city":"Schwarzach",
    "sg:phone":"+49 9962/1600",
    "sg:postcode":"94374",
    "sg:province":"Bayern",
    "wof:name":"Freibad",
    "wof:placetype":"venue"
},
  "geometry": {"coordinates":[12.8129482269,48.918636322],"type":"Point"}
}