{
  "type": "Feature",
  "properties": {
    "iso:country":"DE",
    "sg:address":"St.-Rupert-Str. 5",
    "sg:city":"Brennberg",
    "sg:phone":"+49 9484/801",
    "sg:postcode":"93179",
    "sg:province":"Bayern",
    "wof:name":"Josef L\u00f6schner",
    "wof:placetype":"venue"
},
  "geometry": {"coordinates":[12.3976840973,49.0711021423],"type":"Point"}
}