{
  "type": "Feature",
  "properties": {
    "iso:country":"DE",
    "sg:address":"Enggasse 13",
    "sg:city":"Burladingen",
    "sg:phone":"+49 7475/1332",
    "sg:postcode":"72393",
    "sg:province":"Baden-W\u00fcrttemberg",
    "wof:name":"Gabriel Hipp",
    "wof:placetype":"venue"
},
  "geometry": {"coordinates":[9.1038799286,48.3240814209],"type":"Point"}
}