{
  "type": "Feature",
  "properties": {
    "iso:country":"DE",
    "sg:address":"S\u00fclzburgstr. 11",
    "sg:city":"K\u00f6ln",
    "sg:phone":"+49 221/443727",
    "sg:postcode":"50937",
    "sg:province":"Nordrhein-Westfalen",
    "wof:name":"K. Ariatabar",
    "wof:placetype":"venue"
},
  "geometry": {"coordinates":[6.9267778397,50.9163856506],"type":"Point"}
}