{
  "type": "Feature",
  "properties": {
    "iso:country":"DE",
    "sg:address":"Reginostr 10",
    "sg:city":"Altrip",
    "sg:phone":"+49 6236/2894",
    "sg:postcode":"67122",
    "sg:province":"Rheinland-Pfalz",
    "wof:name":"Karl-martin Gensinger",
    "wof:placetype":"venue"
},
  "geometry": {"coordinates":[8.501019,49.434132],"type":"Point"}
}