{
  "type": "Feature",
  "properties": {
    "iso:country":"DE",
    "sg:address":"Atenser Allee 50",
    "sg:city":"Nordenham",
    "sg:phone":"+49 4731/88662",
    "sg:postcode":"26954",
    "sg:province":"Niedersachsen",
    "wof:name":"Werner Steingr\u00e4ber",
    "wof:placetype":"venue"
},
  "geometry": {"coordinates":[8.473759,53.494736],"type":"Point"}
}