{
  "type": "Feature",
  "properties": {
    "iso:country":"DE",
    "sg:address":"Gumbertstr. 169",
    "sg:city":"D\u00fcsseldorf",
    "sg:phone":"+49 211/226356",
    "sg:postcode":"40229",
    "sg:province":"Nordrhein-Westfalen",
    "wof:name":"H. Sprenger",
    "wof:placetype":"venue"
},
  "geometry": {"coordinates":[6.8418450356,51.2004890442],"type":"Point"}
}