{
  "type": "Feature",
  "properties": {
    "iso:country":"DE",
    "sg:address":"Krefelder Str. 1",
    "sg:city":"Geldern",
    "sg:phone":"+49 2831/97170",
    "sg:postcode":"47608",
    "sg:province":"Nordrhein-Westfalen",
    "wof:name":"Reifen-behnke Verwaltungs - Gmbh",
    "wof:placetype":"venue"
},
  "geometry": {"coordinates":[6.331429,51.511959],"type":"Point"}
}