{
  "type": "Feature",
  "properties": {
    "iso:country":"DE",
    "sg:address":"Dr.-R\u00f6rig-Damm 64",
    "sg:city":"Paderborn",
    "sg:phone":"+49 5251/4563",
    "sg:postcode":"33102",
    "sg:province":"Nordrhein-Westfalen",
    "wof:name":"G. Geppert",
    "wof:placetype":"venue"
},
  "geometry": {"coordinates":[8.757918,51.737843],"type":"Point"}
}