{
  "type": "Feature",
  "properties": {
    "iso:country":"DE",
    "sg:address":"Zehntweg 205",
    "sg:city":"M\u00fclheim",
    "sg:phone":"+49 208/757511",
    "sg:postcode":"45475",
    "sg:province":"Nordrhein-Westfalen",
    "wof:name":"Mimo Mietmobile Gmbh",
    "wof:placetype":"venue"
},
  "geometry": {"coordinates":[6.8939471245,51.4523963928],"type":"Point"}
}