{
  "type": "Feature",
  "properties": {
    "iso:country":"DE",
    "sg:address":"Amselweg 11a",
    "sg:city":"Spiesen-Elversberg",
    "sg:phone":"+49 6821/973017",
    "sg:postcode":"66583",
    "sg:province":"Saarland",
    "wof:name":"Walter Habermann Anlageberater",
    "wof:placetype":"venue"
},
  "geometry": {"coordinates":[7.1304988861,49.3189086914],"type":"Point"}
}