{
  "type": "Feature",
  "properties": {
    "iso:country":"DE",
    "sg:address":"Talstr. 49",
    "sg:city":"Mannheim",
    "sg:phone":"+49 621/791446",
    "sg:postcode":"68259",
    "sg:province":"Baden-W\u00fcrttemberg",
    "wof:name":"Annette Zitzer",
    "wof:placetype":"venue"
},
  "geometry": {"coordinates":[8.524835,49.497086],"type":"Point"}
}