{
  "type": "Feature",
  "properties": {
    "iso:country":"DE",
    "sg:address":"Luxemburger Stra\u00dfe 31",
    "sg:city":"berlin",
    "sg:phone":"+49 30",
    "sg:postcode":"13353",
    "sg:province":"Berlin",
    "wof:name":"Pbc Queue Royale1994 E.v. Billard In Berlin",
    "wof:placetype":"venue"
},
  "geometry": {"coordinates":[13.35818,52.545498],"type":"Point"}
}