{
  "type": "Feature",
  "properties": {
    "iso:country":"DE",
    "sg:address":"M\u00fcnchener Str. 14",
    "sg:city":"Dietzenbach",
    "sg:phone":"+49 6074/27812",
    "sg:postcode":"63128",
    "sg:province":"Hessen",
    "wof:name":"Itc P. Rudolph Consulting Gmbh",
    "wof:placetype":"venue"
},
  "geometry": {"coordinates":[8.769346,49.995827],"type":"Point"}
}