{
  "type": "Feature",
  "properties": {
    "iso:country":"DE",
    "sg:address":"Gropiusplatz 1",
    "sg:city":"Meppen",
    "sg:phone":"+49 5931/20201",
    "sg:postcode":"49716",
    "sg:province":"Niedersachsen",
    "wof:name":"Vss Video Studio Service Gmbh",
    "wof:placetype":"venue"
},
  "geometry": {"coordinates":[7.308996,52.683609],"type":"Point"}
}