{
  "type": "Feature",
  "properties": {
    "iso:country":"DE",
    "sg:address":"Marktstr. 1",
    "sg:city":"Eschwege",
    "sg:phone":"+49 5651/70362",
    "sg:postcode":"37269",
    "sg:province":"Hessen",
    "wof:name":"Wiener",
    "wof:placetype":"venue"
},
  "geometry": {"coordinates":[10.0552711487,51.186706543],"type":"Point"}
}