{
  "type": "Feature",
  "properties": {
    "iso:country":"DE",
    "sg:address":"Borbeckerfeld",
    "sg:city":"Wiefelstede",
    "sg:phone":"+49 4402/4389",
    "sg:postcode":"26215",
    "sg:province":"Niedersachsen",
    "wof:name":"G. Und J. Ro\u00dfkamp",
    "wof:placetype":"venue"
},
  "geometry": {"coordinates":[8.14765,53.217312],"type":"Point"}
}