{
  "type": "Feature",
  "properties": {
    "iso:country":"DE",
    "sg:address":"Hauptstr. 15 a",
    "sg:city":"Heilshoop",
    "sg:phone":"+49 4506/412",
    "sg:postcode":"23619",
    "sg:province":"Schleswig-Holstein",
    "wof:name":"Erich Schoer",
    "wof:placetype":"venue"
},
  "geometry": {"coordinates":[10.534779,53.886856],"type":"Point"}
}