{
  "type": "Feature",
  "properties": {
    "iso:country":"DE",
    "sg:address":"Place de Caen 11",
    "sg:city":"W\u00fcrzburg",
    "sg:phone":"+49 931/69073",
    "sg:postcode":"97084",
    "sg:province":"Bayern",
    "wof:name":"Friedrich Zipfel",
    "wof:placetype":"venue"
},
  "geometry": {"coordinates":[9.9581632614,49.7465782166],"type":"Point"}
}