{
  "type": "Feature",
  "properties": {
    "iso:country":"DE",
    "sg:address":"Julius-Leber-Str. 12",
    "sg:city":"Hamburg",
    "sg:phone":"+49 40/6961996",
    "sg:postcode":"22765",
    "sg:province":"Hamburg",
    "wof:name":"International Ag Gmbh",
    "wof:placetype":"venue"
},
  "geometry": {"coordinates":[9.941277,53.555618],"type":"Point"}
}