{
  "type": "Feature",
  "properties": {
    "iso:country":"DE",
    "sg:address":"Usinger Str. 66",
    "sg:city":"Ober-M\u00f6rlen",
    "sg:phone":"+49 6002/7054",
    "sg:postcode":"61239",
    "sg:province":"Hessen",
    "wof:name":"Heinrich K\u00f6nig Kohlen-handlung",
    "wof:placetype":"venue"
},
  "geometry": {"coordinates":[8.688724,50.370865],"type":"Point"}
}