{
  "type": "Feature",
  "properties": {
    "iso:country":"DE",
    "sg:address":"Kuhlhoffstr. 71",
    "sg:city":"Essen",
    "sg:phone":"+49 201/367666",
    "sg:postcode":"45329",
    "sg:province":"Nordrhein-Westfalen",
    "wof:name":"Gemeinn\u00fctzige Jugendfarm Essen Gmbh",
    "wof:placetype":"venue"
},
  "geometry": {"coordinates":[7.0275588036,51.5042915344],"type":"Point"}
}