{
  "type": "Feature",
  "properties": {
    "iso:country":"DE",
    "sg:address":"Uhlenbergweg 1",
    "sg:city":"Bad M\u00fcnstereifel",
    "sg:phone":"+49 2253/2088",
    "sg:postcode":"53902",
    "sg:province":"Nordrhein-Westfalen",
    "wof:name":"Kneipp-kurhaus Uhlenberg",
    "wof:placetype":"venue"
},
  "geometry": {"coordinates":[6.7617430687,50.5631523132],"type":"Point"}
}