{
  "type": "Feature",
  "properties": {
    "iso:country":"DE",
    "sg:address":"Festeburgstr. 26",
    "sg:city":"Steinheid",
    "sg:phone":"+49 36704/80452",
    "sg:postcode":"98749",
    "sg:province":"Th\u00fcringen",
    "wof:name":"Goldgr\u00e4ber-stube",
    "wof:placetype":"venue"
},
  "geometry": {"coordinates":[11.0841636658,50.4675521851],"type":"Point"}
}