{
  "type": "Feature",
  "properties": {
    "iso:country":"DE",
    "sg:address":"Feilbergstr. 35",
    "sg:city":"Kempten",
    "sg:phone":"+49 831/22895",
    "sg:postcode":"87439",
    "sg:province":"Bayern",
    "wof:name":"Josef Hartmann",
    "wof:placetype":"venue"
},
  "geometry": {"coordinates":[10.302687645,47.7227325439],"type":"Point"}
}