{
  "type": "Feature",
  "properties": {
    "iso:country":"DE",
    "sg:address":"Grietgen-Haaks-Str. 28",
    "sg:city":"Willich",
    "sg:postcode":"47877",
    "sg:province":"Nordrhein-Westfalen",
    "wof:name":"In Media Aulich & Krahn Gmbh",
    "wof:placetype":"venue"
},
  "geometry": {"coordinates":[6.505661,51.247822],"type":"Point"}
}