{
  "type": "Feature",
  "properties": {
    "iso:country":"DE",
    "sg:address":"Heddernheimer Landstr. 10",
    "sg:city":"Frankfurt",
    "sg:phone":"+49 69/572092",
    "sg:postcode":"60439",
    "sg:province":"Hessen",
    "wof:name":"Hans Simons Immobilienmakler",
    "wof:placetype":"venue"
},
  "geometry": {"coordinates":[8.6497163773,50.1595458984],"type":"Point"}
}