{
  "type": "Feature",
  "properties": {
    "iso:country":"DE",
    "sg:address":"Els\u00e4sser Str. 10",
    "sg:city":"Wiesbaden",
    "sg:phone":"+49 611/9490226",
    "sg:postcode":"65197",
    "sg:province":"Hessen",
    "wof:name":"Gemeinn\u00fctzige Wohnungs- Gesellschaft Mbh",
    "wof:placetype":"venue"
},
  "geometry": {"coordinates":[8.2214832306,50.0792694092],"type":"Point"}
}