{
  "type": "Feature",
  "properties": {
    "iso:country":"DE",
    "sg:address":"Gr\u00fcng\u00fcrtelstr. 10",
    "sg:city":"K\u00f6ln",
    "sg:phone":"+49 221/9352127",
    "sg:postcode":"50996",
    "sg:province":"Nordrhein-Westfalen",
    "wof:name":"Leich Industrieausr\u00fcstungen",
    "wof:placetype":"venue"
},
  "geometry": {"coordinates":[7.01046,50.891403],"type":"Point"}
}