{
  "type": "Feature",
  "properties": {
    "iso:country":"DE",
    "sg:address":"K\u00e4kenflur 16e",
    "sg:city":"Hamburg",
    "sg:phone":"+49 40/5277631",
    "sg:postcode":"22419",
    "sg:province":"Hamburg",
    "wof:name":"K\u00e4ken-croque",
    "wof:placetype":"venue"
},
  "geometry": {"coordinates":[9.9998836517,53.6715583801],"type":"Point"}
}