{
  "type": "Feature",
  "properties": {
    "iso:country":"DE",
    "sg:address":"M\u00fchlenweg",
    "sg:city":"Frankfurt",
    "sg:postcode":"15232",
    "sg:province":"Brandenburg",
    "wof:name":"Toom-baumarkt",
    "wof:placetype":"venue"
},
  "geometry": {"coordinates":[14.5338363647,52.3235549927],"type":"Point"}
}