{
  "type": "Feature",
  "properties": {
    "iso:country":"DE",
    "sg:address":"Pfarrer-Baumann-Str. 40",
    "sg:city":"Oberaurach",
    "sg:phone":"+49 9529/244",
    "sg:postcode":"97514",
    "sg:province":"Bayern",
    "wof:name":"Edmund Biermann",
    "wof:placetype":"venue"
},
  "geometry": {"coordinates":[10.593514,49.950291],"type":"Point"}
}