{
  "type": "Feature",
  "properties": {
    "iso:country":"DE",
    "sg:address":"Rudolf-Diesel-Str. 9",
    "sg:city":"Nieb\u00fcll",
    "sg:phone":"+49 4661/20948",
    "sg:postcode":"25899",
    "sg:province":"Schleswig-Holstein",
    "wof:name":"Werner Petersen",
    "wof:placetype":"venue"
},
  "geometry": {"coordinates":[8.834043,54.796967],"type":"Point"}
}