{
  "type": "Feature",
  "properties": {
    "iso:country":"DE",
    "sg:address":"Kreuzbergstr. 144",
    "sg:city":"Saarlouis",
    "sg:phone":"+49 6831/84768",
    "sg:postcode":"66740",
    "sg:province":"Saarland",
    "wof:name":"Wolfgang Keller",
    "wof:placetype":"venue"
},
  "geometry": {"coordinates":[6.7859668732,49.3322982788],"type":"Point"}
}