{
  "type": "Feature",
  "properties": {
    "iso:country":"DE",
    "sg:address":"Desperweg 16",
    "sg:city":"Ransbach-Baumbach",
    "sg:phone":"+49 2623/4458",
    "sg:postcode":"56235",
    "sg:province":"Rheinland-Pfalz",
    "wof:name":"Helmut Sch\u00e4fer Bilderrahmen Holzverarbeitung",
    "wof:placetype":"venue"
},
  "geometry": {"coordinates":[7.729224205,50.4622917175],"type":"Point"}
}