{
  "type": "Feature",
  "properties": {
    "iso:country":"DE",
    "sg:address":"Hauptstr. 162",
    "sg:city":"Weil am Rhein",
    "sg:phone":"+49 7621/72312",
    "sg:postcode":"79576",
    "sg:province":"Baden-W\u00fcrttemberg",
    "wof:name":"P. Schwarz Heilpraktiker",
    "wof:placetype":"venue"
},
  "geometry": {"coordinates":[7.6260671616,47.5939331055],"type":"Point"}
}