{
  "type": "Feature",
  "properties": {
    "iso:country":"DE",
    "sg:address":"Altwahnsdorf 28",
    "sg:city":"Radebeul",
    "sg:phone":"+49 351/8303343",
    "sg:postcode":"01445",
    "sg:province":"Sachsen",
    "wof:name":"Landpension John",
    "wof:placetype":"venue"
},
  "geometry": {"coordinates":[13.6726837158,51.1185302734],"type":"Point"}
}