{
  "type": "Feature",
  "properties": {
    "iso:country":"DE",
    "sg:address":"Schottener Str. 2-4",
    "sg:city":"Laubach",
    "sg:phone":"+49 6405/267",
    "sg:postcode":"35321",
    "sg:province":"Hessen",
    "wof:name":"Stiftung Laubacher Stift",
    "wof:placetype":"venue"
},
  "geometry": {"coordinates":[8.9944658279,50.5423355103],"type":"Point"}
}