{
  "type": "Feature",
  "properties": {
    "iso:country":"DE",
    "sg:address":"Pappelweg 2",
    "sg:city":"Spitzkunnersdorf",
    "sg:phone":"+49 35842/25389",
    "sg:postcode":"02794",
    "sg:province":"Sachsen",
    "wof:name":"Werner Priebsch",
    "wof:placetype":"venue"
},
  "geometry": {"coordinates":[14.6896362305,50.9395675659],"type":"Point"}
}