{
  "type": "Feature",
  "properties": {
    "iso:country":"DE",
    "sg:address":"Britzer Damm 66",
    "sg:city":"Berlin",
    "sg:phone":"+49 30/6063337",
    "sg:postcode":"12347",
    "sg:province":"Berlin",
    "wof:name":"Britzer Damm 66 Spielhallen Gmbh",
    "wof:placetype":"venue"
},
  "geometry": {"coordinates":[13.4366464615,52.4566993713],"type":"Point"}
}