{
  "type": "Feature",
  "properties": {
    "iso:country":"DE",
    "sg:address":"B\u00fcrgermeister-Smidt-Str. 80",
    "sg:city":"Bremerhaven",
    "sg:phone":"+49 471/43106",
    "sg:postcode":"27568",
    "sg:province":"Bremen",
    "wof:name":"Otto May",
    "wof:placetype":"venue"
},
  "geometry": {"coordinates":[8.5779972076,53.5444450378],"type":"Point"}
}