{
  "type": "Feature",
  "properties": {
    "iso:country":"DE",
    "sg:address":"Nizzaallee 20",
    "sg:city":"Aachen",
    "sg:phone":"+49 241/918670",
    "sg:postcode":"52072",
    "sg:province":"Nordrhein-Westfalen",
    "wof:name":"Internationaler Freundeskreis Der Evang. Studentengemeinde",
    "wof:placetype":"venue"
},
  "geometry": {"coordinates":[6.0778779984,50.7852325439],"type":"Point"}
}