{
  "type": "Feature",
  "properties": {
    "iso:country":"DE",
    "sg:address":"Saalgasse 30",
    "sg:city":"Frankfurt",
    "sg:postcode":"60311",
    "sg:province":"Hessen",
    "wof:name":"Garban Marketing Gmbh",
    "wof:placetype":"venue"
},
  "geometry": {"coordinates":[8.682668,50.109924],"type":"Point"}
}