{
  "type": "Feature",
  "properties": {
    "iso:country":"DE",
    "sg:address":"Steinstr. 23",
    "sg:city":"Karlsruhe",
    "sg:phone":"+49 721/377647",
    "sg:postcode":"76133",
    "sg:province":"Baden-W\u00fcrttemberg",
    "wof:name":"Palaver",
    "wof:placetype":"venue"
},
  "geometry": {"coordinates":[8.40733,49.006958],"type":"Point"}
}