{
  "type": "Feature",
  "properties": {
    "iso:country":"DE",
    "sg:address":"Wilhelmstr. 50a",
    "sg:city":"Velbert",
    "sg:postcode":"42553",
    "sg:province":"Nordrhein-Westfalen",
    "wof:name":"A. Cibooglu",
    "wof:placetype":"venue"
},
  "geometry": {"coordinates":[7.0829219818,51.3109550476],"type":"Point"}
}