{
  "type": "Feature",
  "properties": {
    "iso:country":"DE",
    "sg:address":"Vahrenwalder Str. 209 a",
    "sg:city":"Hannover",
    "sg:phone":"+49 511/371663",
    "sg:postcode":"30165",
    "sg:province":"Niedersachsen",
    "wof:name":"Aktiva Beratungs- Und Beteiligungsges. Mbh",
    "wof:placetype":"venue"
},
  "geometry": {"coordinates":[9.734307,52.406849],"type":"Point"}
}