{
  "type": "Feature",
  "properties": {
    "iso:country":"DE",
    "sg:address":"Bendenweg 73",
    "sg:city":"Swisttal",
    "sg:phone":"+49 2255/8768",
    "sg:postcode":"53913",
    "sg:province":"Nordrhein-Westfalen",
    "wof:name":"Daniel Bauunternehmung Gmbh",
    "wof:placetype":"venue"
},
  "geometry": {"coordinates":[6.873749,50.65057],"type":"Point"}
}