{
  "type": "Feature",
  "properties": {
    "iso:country":"DE",
    "sg:address":"Postfach 1363",
    "sg:city":"Rottweil",
    "sg:postcode":"78613",
    "sg:province":"Baden-W\u00fcrttemberg",
    "wof:name":"Raymund Holzer Versandbuchhandlung Gmbh",
    "wof:placetype":"venue"
},
  "geometry": {"coordinates":[8.6280603409,48.1667289734],"type":"Point"}
}