{
  "type": "Feature",
  "properties": {
    "iso:country":"DE",
    "sg:address":"Richard-Wagner-Str. 65",
    "sg:city":"Halberstadt",
    "sg:postcode":"38820",
    "sg:province":"Sachsen-Anhalt",
    "wof:name":"Richard Mahlke",
    "wof:placetype":"venue"
},
  "geometry": {"coordinates":[11.0602588654,51.893787384],"type":"Point"}
}