{
  "type": "Feature",
  "properties": {
    "iso:country":"DE",
    "sg:address":"Woodsiepenweg 13",
    "sg:city":"Essen",
    "sg:phone":"+49 201/552694",
    "sg:postcode":"45309",
    "sg:province":"Nordrhein-Westfalen",
    "wof:name":"Alfons Schramm",
    "wof:placetype":"venue"
},
  "geometry": {"coordinates":[7.0785980225,51.4734840393],"type":"Point"}
}