{
  "type": "Feature",
  "properties": {
    "iso:country":"DE",
    "sg:address":"Welfenstr. 2",
    "sg:city":"Steingaden",
    "sg:phone":"+49 8862/234",
    "sg:postcode":"86989",
    "sg:province":"Bayern",
    "wof:name":"Kath. \u00d6ffentliche B\u00fccherei",
    "wof:placetype":"venue"
},
  "geometry": {"coordinates":[10.86181,47.701271],"type":"Point"}
}