{
  "type": "Feature",
  "properties": {
    "iso:country":"DE",
    "sg:address":"Triftweg 20",
    "sg:city":"Petersberg",
    "sg:phone":"+49 661/65420",
    "sg:postcode":"36100",
    "sg:province":"Hessen",
    "wof:name":"Stefan Lorenz Ingenieur",
    "wof:placetype":"venue"
},
  "geometry": {"coordinates":[9.7495613098,50.5985946655],"type":"Point"}
}