{
  "type": "Feature",
  "properties": {
    "iso:country":"DE",
    "sg:address":"Kreuzweg 2",
    "sg:city":"Nienburg",
    "sg:postcode":"31582",
    "sg:province":"Niedersachsen",
    "wof:name":"Horing-geb\u00e4ude Gmbh & Co. Kg",
    "wof:placetype":"venue"
},
  "geometry": {"coordinates":[9.245477,52.665447],"type":"Point"}
}