{
  "type": "Feature",
  "properties": {
    "iso:country":"DE",
    "sg:address":"Kaiser-Ludwig-Platz 18",
    "sg:city":"Ettal",
    "sg:phone":"+49 8822/3596",
    "sg:postcode":"82488",
    "sg:province":"Bayern",
    "wof:name":"Hotel Zur Post",
    "wof:placetype":"venue"
},
  "geometry": {"coordinates":[11.0949373245,47.5678825378],"type":"Point"}
}