{
  "type": "Feature",
  "properties": {
    "iso:country":"DE",
    "sg:address":"Pforzheimer Str. 15",
    "sg:city":"Leonberg",
    "sg:phone":"+49 7152/25503",
    "sg:postcode":"71229",
    "sg:province":"Baden-W\u00fcrttemberg",
    "wof:name":"G. Ahner",
    "wof:placetype":"venue"
},
  "geometry": {"coordinates":[9.0158462524,48.8167877197],"type":"Point"}
}