{
  "type": "Feature",
  "properties": {
    "iso:country":"DE",
    "sg:address":"Postfach 80:: 74355 B\u00f6nnigheim:: Germany.^^Hauptstr 33::",
    "sg:city":"B\u00f6nnigheim",
    "sg:phone":"+49 7143/2750",
    "sg:postcode":"74357",
    "sg:province":"Baden-W\u00fcrttemberg",
    "wof:name":"Volksbank Besigheim-b\u00f6nnigheim Eg",
    "wof:placetype":"venue"
},
  "geometry": {"coordinates":[9.09835,49.040852],"type":"Point"}
}