{
  "type": "Feature",
  "properties": {
    "iso:country":"DE",
    "sg:address":"Ludwigstr. 31",
    "sg:city":"Frankfurt",
    "sg:phone":"+49 69/9757270",
    "sg:postcode":"60327",
    "sg:province":"Hessen",
    "wof:name":"Xplicit Works Mediaproduktion Gmbh",
    "wof:placetype":"venue"
},
  "geometry": {"coordinates":[8.657413,50.108875],"type":"Point"}
}