{
  "type": "Feature",
  "properties": {
    "iso:country":"DE",
    "sg:address":"Am Bahnsteig 2",
    "sg:city":"Holtgast",
    "sg:phone":"+49 4971/1442",
    "sg:postcode":"26427",
    "sg:province":"Niedersachsen",
    "wof:name":"Tido Gerdes",
    "wof:placetype":"venue"
},
  "geometry": {"coordinates":[7.527569,53.632111],"type":"Point"}
}