{
  "type": "Feature",
  "properties": {
    "iso:country":"DE",
    "sg:address":"Landauer Str. 20",
    "sg:city":"Hauenstein",
    "sg:phone":"+49 6392/993160",
    "sg:postcode":"76846",
    "sg:province":"Rheinland-Pfalz",
    "wof:name":"Tkc Tennis-kegel-center",
    "wof:placetype":"venue"
},
  "geometry": {"coordinates":[7.8566799164,49.1935997009],"type":"Point"}
}