{
  "type": "Feature",
  "properties": {
    "iso:country":"DE",
    "sg:address":"R\u00f6merweg 2",
    "sg:city":"Melle",
    "sg:phone":"+49 4954/2295180",
    "sg:postcode":"49324",
    "sg:province":"Niedersachsen",
    "wof:name":"Heinrich Glane Gmbh",
    "wof:placetype":"venue"
},
  "geometry": {"coordinates":[8.337978,52.178356],"type":"Point"}
}