{
  "type": "Feature",
  "properties": {
    "iso:country":"DE",
    "sg:address":"Schwieberdinger Str. 117",
    "sg:city":"Stuttgart",
    "sg:phone":"+49 711/807378",
    "sg:postcode":"70435",
    "sg:province":"Baden-W\u00fcrttemberg",
    "wof:name":"Down Town Fitness-center",
    "wof:placetype":"venue"
},
  "geometry": {"coordinates":[9.1685886383,48.8323173523],"type":"Point"}
}