{
  "type": "Feature",
  "properties": {
    "iso:country":"DE",
    "sg:address":"Neuweg 9",
    "sg:city":"Dietzenbach",
    "sg:phone":"+49 6074/309716",
    "sg:postcode":"63128",
    "sg:province":"Hessen",
    "wof:name":"Lehr & Ahl Gmbh",
    "wof:placetype":"venue"
},
  "geometry": {"coordinates":[8.783435,50.004799],"type":"Point"}
}