{
  "type": "Feature",
  "properties": {
    "iso:country":"DE",
    "sg:address":"Zeppelinstr. 50",
    "sg:city":"L\u00f6rrach",
    "sg:phone":"+49 7621/45271",
    "sg:postcode":"79540",
    "sg:province":"Baden-W\u00fcrttemberg",
    "wof:name":"G\u00fcnter Mendel",
    "wof:placetype":"venue"
},
  "geometry": {"coordinates":[7.659344,47.60104],"type":"Point"}
}