{
  "type": "Feature",
  "properties": {
    "iso:country":"DE",
    "sg:address":"Poststr. 9",
    "sg:city":"Bad Neuenahr-Ahrweiler",
    "sg:phone":"+49 2641/21597",
    "sg:postcode":"53474",
    "sg:province":"Rheinland-Pfalz",
    "wof:name":"Rolf Kraus Masseur",
    "wof:placetype":"venue"
},
  "geometry": {"coordinates":[7.137755,50.545547],"type":"Point"}
}