{
  "type": "Feature",
  "properties": {
    "iso:country":"DE",
    "sg:address":"Hauptstr. 2",
    "sg:city":"Todtenweis",
    "sg:phone":"+49 8237/807",
    "sg:postcode":"86447",
    "sg:province":"Bayern",
    "wof:name":"Thomas Ri\u00df",
    "wof:placetype":"venue"
},
  "geometry": {"coordinates":[10.9255695343,48.5161895752],"type":"Point"}
}