{
  "type": "Feature",
  "properties": {
    "iso:country":"DE",
    "sg:address":"Wiener Str. 26",
    "sg:city":"Magdeburg",
    "sg:phone":"+49 391/614656",
    "sg:postcode":"39112",
    "sg:province":"Sachsen-Anhalt",
    "wof:name":"K. Bihlmayer",
    "wof:placetype":"venue"
},
  "geometry": {"coordinates":[11.616139,52.110268],"type":"Point"}
}