{
  "type": "Feature",
  "properties": {
    "iso:country":"DE",
    "sg:address":"N\u00fcrnberger Str. 1",
    "sg:city":"Neustadt",
    "sg:phone":"+49 9161/2502",
    "sg:postcode":"91413",
    "sg:province":"Bayern",
    "wof:name":"D\u00f6ller",
    "wof:placetype":"venue"
},
  "geometry": {"coordinates":[10.6094303131,49.5800895691],"type":"Point"}
}