{
  "type": "Feature",
  "properties": {
    "iso:country":"DE",
    "sg:address":"Taubentalstr. 16",
    "sg:city":"Zorge",
    "sg:phone":"+49 5586/272",
    "sg:postcode":"37449",
    "sg:province":"Niedersachsen",
    "wof:name":"Hotel Deutsches Haus",
    "wof:placetype":"venue"
},
  "geometry": {"coordinates":[10.6347227097,51.6328773499],"type":"Point"}
}