{
  "type": "Feature",
  "properties": {
    "iso:country":"DE",
    "sg:address":"Am Markt 17",
    "sg:city":"Sohland",
    "sg:postcode":"02689",
    "sg:province":"Sachsen",
    "wof:name":"Evangelisches Pfarramt Sohland",
    "wof:placetype":"venue"
},
  "geometry": {"coordinates":[14.4274129868,51.0457649231],"type":"Point"}
}