{
  "type": "Feature",
  "properties": {
    "iso:country":"DE",
    "sg:address":"Usinger Str. 43",
    "sg:city":"Weilrod",
    "sg:postcode":"61276",
    "sg:province":"Hessen",
    "wof:name":"Mtk Gmbh",
    "wof:placetype":"venue"
},
  "geometry": {"coordinates":[8.4069099426,50.3538818359],"type":"Point"}
}