{
  "type": "Feature",
  "properties": {
    "iso:country":"DE",
    "sg:address":"Schwabenbergstr. 1",
    "sg:city":"Emmering",
    "sg:phone":"+49 8141/92041",
    "sg:postcode":"82275",
    "sg:province":"Bayern",
    "wof:name":"H. Friedrich Steuerberater",
    "wof:placetype":"venue"
},
  "geometry": {"coordinates":[11.28540802,48.179058075],"type":"Point"}
}