{
  "type": "Feature",
  "properties": {
    "iso:country":"DE",
    "sg:address":"Auf der Grefenfurth 1-3",
    "sg:city":"R\u00f6srath",
    "sg:phone":"+49 2205/80040",
    "sg:postcode":"51503",
    "sg:province":"Nordrhein-Westfalen",
    "wof:name":"Gws Ges. F\u00fcr W\u00e4rme- Und Schalld\u00e4nmmende",
    "wof:placetype":"venue"
},
  "geometry": {"coordinates":[7.149475,50.902035],"type":"Point"}
}