{
  "type": "Feature",
  "properties": {
    "iso:country":"DE",
    "sg:address":"Molkereistr. 8",
    "sg:city":"Wesel",
    "sg:phone":"+49 2803/321",
    "sg:postcode":"46487",
    "sg:province":"Nordrhein-Westfalen",
    "wof:name":"Wenzel Bauer",
    "wof:placetype":"venue"
},
  "geometry": {"coordinates":[6.542683,51.642521],"type":"Point"}
}