{
  "type": "Feature",
  "properties": {
    "iso:country":"DE",
    "sg:address":"Bodmanstr. 21",
    "sg:city":"Kempten",
    "sg:phone":"+49 831/511500",
    "sg:postcode":"87439",
    "sg:province":"Bayern",
    "wof:name":"Masskleidung Peter Rossberger - Ihr Masschneider",
    "wof:placetype":"venue"
},
  "geometry": {"coordinates":[10.3075723648,47.724861145],"type":"Point"}
}