{
  "type": "Feature",
  "properties": {
    "iso:country":"DE",
    "sg:address":"Lerchenweg 7",
    "sg:city":"Domb\u00fchl",
    "sg:postcode":"91601",
    "sg:province":"Bayern",
    "wof:name":"G. Uhl Innenausbau Kg",
    "wof:placetype":"venue"
},
  "geometry": {"coordinates":[10.2860040665,49.2567253113],"type":"Point"}
}