{
  "type": "Feature",
  "properties": {
    "iso:country":"DE",
    "sg:address":"Hauptstr. 167",
    "sg:city":"Kerpen",
    "sg:phone":"+49 2273/2143",
    "sg:postcode":"50169",
    "sg:province":"Nordrhein-Westfalen",
    "wof:name":"Lidl Stiftung & Co. Kg",
    "wof:placetype":"venue"
},
  "geometry": {"coordinates":[6.7106690407,50.913860321],"type":"Point"}
}