{
  "type": "Feature",
  "properties": {
    "iso:country":"DE",
    "sg:address":"Postgasse 9",
    "sg:city":"Waging",
    "sg:phone":"+49 8681/45950",
    "sg:postcode":"83329",
    "sg:province":"Bayern",
    "wof:name":"Georg Huber",
    "wof:placetype":"venue"
},
  "geometry": {"coordinates":[12.733852,47.93438],"type":"Point"}
}