{
  "type": "Feature",
  "properties": {
    "iso:country":"DE",
    "sg:address":"Steinstr. 23",
    "sg:city":"Siegen",
    "sg:phone":"+49 271/484069",
    "sg:postcode":"57072",
    "sg:province":"Nordrhein-Westfalen",
    "wof:name":"Delius Baubetreuung Gmbh",
    "wof:placetype":"venue"
},
  "geometry": {"coordinates":[8.0336446762,50.8813323975],"type":"Point"}
}