{
  "type": "Feature",
  "properties": {
    "iso:country":"DE",
    "sg:address":"F\u00f6hringer Allee 6",
    "sg:city":"Unterf\u00f6hring",
    "sg:phone":"+49 89/9505651",
    "sg:postcode":"85774",
    "sg:province":"Bayern",
    "wof:name":"Apotheke Zur Post",
    "wof:placetype":"venue"
},
  "geometry": {"coordinates":[11.643752,48.190666],"type":"Point"}
}