{
  "type": "Feature",
  "properties": {
    "iso:country":"DE",
    "sg:address":"Bahnhofstr. 10",
    "sg:city":"Heilbad Heiligenstadt",
    "sg:phone":"+49 3606/4060",
    "sg:postcode":"37308",
    "sg:province":"Th\u00fcringen",
    "wof:name":"W. D\u00f6lle",
    "wof:placetype":"venue"
},
  "geometry": {"coordinates":[10.131979,51.380409],"type":"Point"}
}