{
  "type": "Feature",
  "properties": {
    "iso:country":"DE",
    "sg:address":"Hauptstr. 15",
    "sg:city":"Herdorf",
    "sg:phone":"+49 2744/5206",
    "sg:postcode":"57562",
    "sg:province":"Rheinland-Pfalz",
    "wof:name":"Eiscafe Venezia",
    "wof:placetype":"venue"
},
  "geometry": {"coordinates":[7.94899,50.778233],"type":"Point"}
}