{
  "type": "Feature",
  "properties": {
    "iso:country":"DE",
    "sg:address":"Lehen\u00e4cker 4",
    "sg:city":"Partenstein",
    "sg:phone":"+49 9355/1461",
    "sg:postcode":"97846",
    "sg:province":"Bayern",
    "wof:name":"Auto-fillinger Gmbh",
    "wof:placetype":"venue"
},
  "geometry": {"coordinates":[9.526988,50.035576],"type":"Point"}
}