{
  "type": "Feature",
  "properties": {
    "iso:country":"DE",
    "sg:address":"Bahnhofstr. 36",
    "sg:city":"Neuhaus",
    "sg:phone":"+49 3679/722490",
    "sg:postcode":"98724",
    "sg:province":"Th\u00fcringen",
    "wof:name":"H.-peter M\u00fcller",
    "wof:placetype":"venue"
},
  "geometry": {"coordinates":[14.4146966934,51.6795272827],"type":"Point"}
}