{
  "type": "Feature",
  "properties": {
    "iso:country":"DE",
    "sg:address":"Goethestr. 11",
    "sg:city":"Berlin",
    "sg:phone":"+49 30/3131194",
    "sg:postcode":"10623",
    "sg:province":"Berlin",
    "wof:name":"Kosmetik-salon Kim",
    "wof:placetype":"venue"
},
  "geometry": {"coordinates":[13.320449,52.509041],"type":"Point"}
}