{
  "type": "Feature",
  "properties": {
    "iso:country":"DE",
    "sg:address":"Dobernitz 4",
    "sg:city":"Bockelwitz",
    "sg:phone":"+49 34321/13505",
    "sg:postcode":"04703",
    "sg:province":"Sachsen",
    "wof:name":"Gottfried K\u00e4seberg",
    "wof:placetype":"venue"
},
  "geometry": {"coordinates":[12.952682,51.204845],"type":"Point"}
}