{
  "type": "Feature",
  "properties": {
    "iso:country":"DE",
    "sg:address":"Podbielskistr. 374",
    "sg:city":"Hannover",
    "sg:phone":"+49 511/649272",
    "sg:postcode":"30659",
    "sg:province":"Niedersachsen",
    "wof:name":"Alten- Und Pflegeheim Landhaus Gmbh",
    "wof:placetype":"venue"
},
  "geometry": {"coordinates":[9.804961,52.407867],"type":"Point"}
}