{
  "type": "Feature",
  "properties": {
    "iso:country":"DE",
    "sg:address":"Dorfstr. 8",
    "sg:city":"Blomberg",
    "sg:phone":"+49 5235/7273",
    "sg:postcode":"32825",
    "sg:province":"Nordrhein-Westfalen",
    "wof:name":"August Peter",
    "wof:placetype":"venue"
},
  "geometry": {"coordinates":[9.045673,51.950333],"type":"Point"}
}