{
  "type": "Feature",
  "properties": {
    "iso:country":"DE",
    "sg:address":"Erdmannsd\u00f6rferstr. 10",
    "sg:city":"M\u00fcnchen",
    "sg:phone":"+49 89/8111245",
    "sg:postcode":"81247",
    "sg:province":"Bayern",
    "wof:name":"Alois Schedl",
    "wof:placetype":"venue"
},
  "geometry": {"coordinates":[11.475096,48.16663],"type":"Point"}
}