{
  "type": "Feature",
  "properties": {
    "iso:country":"DE",
    "sg:address":"Rudolf-Bultmann-Str. 4",
    "sg:city":"Marburg",
    "sg:postcode":"35039",
    "sg:province":"Hessen",
    "wof:name":"Ab Security Gmbh",
    "wof:placetype":"venue"
},
  "geometry": {"coordinates":[8.780442,50.816254],"type":"Point"}
}