{
  "type": "Feature",
  "properties": {
    "iso:country":"DE",
    "sg:address":"Magdalenenstr. 42/43",
    "sg:city":"Hamburg",
    "sg:postcode":"20148",
    "sg:province":"Hamburg",
    "wof:name":"Einhundertundeins Ventures Beteiligungs- Ag",
    "wof:placetype":"venue"
},
  "geometry": {"coordinates":[9.9976949692,53.5710639954],"type":"Point"}
}