{
  "type": "Feature",
  "properties": {
    "iso:country":"DE",
    "sg:address":"Mainzer Gasse 5",
    "sg:city":"Schwalmstadt",
    "sg:phone":"+49 6691/1659",
    "sg:postcode":"34613",
    "sg:province":"Hessen",
    "wof:name":"Karl Keim Pozellanhaus Keim",
    "wof:placetype":"venue"
},
  "geometry": {"coordinates":[9.1892995834,50.9121055603],"type":"Point"}
}