{
  "type": "Feature",
  "properties": {
    "iso:country":"DE",
    "sg:address":"Neuzeilsheim 7",
    "sg:city":"Ladenburg",
    "sg:phone":"+49 6203/3688",
    "sg:postcode":"68526",
    "sg:province":"Baden-W\u00fcrttemberg",
    "wof:name":"J\u00e4ger",
    "wof:placetype":"venue"
},
  "geometry": {"coordinates":[8.622076,49.486691],"type":"Point"}
}