{
  "type": "Feature",
  "properties": {
    "iso:country":"DE",
    "sg:address":"Oleanderweg 20",
    "sg:city":"Wolfenb\u00fcttel",
    "sg:phone":"+49 5331/62540",
    "sg:postcode":"38300",
    "sg:province":"Niedersachsen",
    "wof:name":"Thomas Vahldiek",
    "wof:placetype":"venue"
},
  "geometry": {"coordinates":[10.569578,52.155159],"type":"Point"}
}