{
  "type": "Feature",
  "properties": {
    "iso:country":"DE",
    "sg:address":"Holzgartenstr. 62a",
    "sg:city":"Regensburg",
    "sg:phone":"+49 941/41931",
    "sg:postcode":"93059",
    "sg:province":"Bayern",
    "wof:name":"Johann B\u00f6hm",
    "wof:placetype":"venue"
},
  "geometry": {"coordinates":[12.109891,49.026245],"type":"Point"}
}