{
  "type": "Feature",
  "properties": {
    "iso:country":"DE",
    "sg:address":"Zum Rauenh\u00fcbel 15",
    "sg:city":"V\u00f6lklingen",
    "sg:phone":"+49 6898/24638",
    "sg:postcode":"66333",
    "sg:province":"Saarland",
    "wof:name":"Poth",
    "wof:placetype":"venue"
},
  "geometry": {"coordinates":[6.819437027,49.247303009],"type":"Point"}
}