{
  "type": "Feature",
  "properties": {
    "iso:country":"DE",
    "sg:address":"Spittelbergstr. 16",
    "sg:city":"St. Georgen",
    "sg:phone":"+49 7724/3211",
    "sg:postcode":"78112",
    "sg:province":"Baden-W\u00fcrttemberg",
    "wof:name":"Helga Kuchelmeister Heilpraktikerin",
    "wof:placetype":"venue"
},
  "geometry": {"coordinates":[8.3272371292,48.1231536865],"type":"Point"}
}