{
  "type": "Feature",
  "properties": {
    "iso:country":"DE",
    "sg:address":"G\u00f6nninger Str. 2",
    "sg:city":"Pfullingen",
    "sg:phone":"+49 7121/77832",
    "sg:postcode":"72793",
    "sg:province":"Baden-W\u00fcrttemberg",
    "wof:name":"Ludwig Tr\u00f6ster",
    "wof:placetype":"venue"
},
  "geometry": {"coordinates":[9.225381,48.463219],"type":"Point"}
}