{
  "type": "Feature",
  "properties": {
    "iso:country":"DE",
    "sg:address":"Bahnhofstr. 8",
    "sg:city":"Bad Laer",
    "sg:phone":"+49 5424/9283",
    "sg:postcode":"49196",
    "sg:province":"Niedersachsen",
    "wof:name":"A. Niehaus Transport-unternehmen",
    "wof:placetype":"venue"
},
  "geometry": {"coordinates":[8.0904130936,52.1024475098],"type":"Point"}
}