{
  "type": "Feature",
  "properties": {
    "iso:country":"DE",
    "sg:address":"Streitberg 33",
    "sg:city":"Garbsen",
    "sg:phone":"+49 5137/77244",
    "sg:postcode":"30823",
    "sg:province":"Niedersachsen",
    "wof:name":"Die Funzel",
    "wof:placetype":"venue"
},
  "geometry": {"coordinates":[9.6004285812,52.4167060852],"type":"Point"}
}