{
  "type": "Feature",
  "properties": {
    "iso:country":"DE",
    "sg:address":"D\u00f6rrenbachstr. 22 a",
    "sg:city":"Suhl",
    "sg:phone":"+49 3681/419986",
    "sg:postcode":"98528",
    "sg:province":"Th\u00fcringen",
    "wof:name":"Nord-apotheke Inh. Dr. Dieter Heller",
    "wof:placetype":"venue"
},
  "geometry": {"coordinates":[10.70502,50.627304],"type":"Point"}
}