{
  "type": "Feature",
  "properties": {
    "iso:country":"DE",
    "sg:address":"Kirchstr. 1",
    "sg:city":"Leer",
    "sg:phone":"+49 491/61915",
    "sg:postcode":"26789",
    "sg:province":"Niedersachsen",
    "wof:name":"O. Scholz-hildebrand Steuerberater",
    "wof:placetype":"venue"
},
  "geometry": {"coordinates":[7.4501252174,53.227596283],"type":"Point"}
}