{
  "type": "Feature",
  "properties": {
    "iso:country":"DE",
    "sg:address":"Heuchelheimer Hohlweg 3",
    "sg:city":"Bad Homburg",
    "sg:phone":"+49 6172/32564",
    "sg:postcode":"61350",
    "sg:province":"Hessen",
    "wof:name":"Rolf See",
    "wof:placetype":"venue"
},
  "geometry": {"coordinates":[8.590617,50.233074],"type":"Point"}
}