{
  "type": "Feature",
  "properties": {
    "iso:country":"DE",
    "sg:address":"Hynspergstr. 14",
    "sg:city":"Frankfurt",
    "sg:phone":"+49 69/592606",
    "sg:postcode":"60322",
    "sg:province":"Hessen",
    "wof:name":"Cosmos Export- Und Import Gmbh Hotelbetriebe Gmbh",
    "wof:placetype":"venue"
},
  "geometry": {"coordinates":[8.680351,50.128895],"type":"Point"}
}