{
  "type": "Feature",
  "properties": {
    "iso:country":"DE",
    "sg:address":"Marktplatz 5",
    "sg:city":"Gem\u00fcnden",
    "sg:phone":"+49 9351/3373",
    "sg:postcode":"97737",
    "sg:province":"Bayern",
    "wof:name":"A. Madlon",
    "wof:placetype":"venue"
},
  "geometry": {"coordinates":[9.6897468567,50.0565719604],"type":"Point"}
}