{
  "type": "Feature",
  "properties": {
    "iso:country":"DE",
    "sg:address":"Hauffstr. 2",
    "sg:city":"Nagold",
    "sg:phone":"+49 7452/3729",
    "sg:postcode":"72202",
    "sg:province":"Baden-W\u00fcrttemberg",
    "wof:name":"E. Ratzel Hebamme",
    "wof:placetype":"venue"
},
  "geometry": {"coordinates":[8.71573,48.541721],"type":"Point"}
}