{
  "type": "Feature",
  "properties": {
    "iso:country":"DE",
    "sg:address":"Friedrichstr. 6",
    "sg:city":"Bruchsal",
    "sg:phone":"+49 7251/8060",
    "sg:postcode":"76646",
    "sg:province":"Baden-W\u00fcrttemberg",
    "wof:name":"Redaktion Bruchsaler Rundschau",
    "wof:placetype":"venue"
},
  "geometry": {"coordinates":[8.5981960297,49.1266288757],"type":"Point"}
}