{
  "type": "Feature",
  "properties": {
    "iso:country":"DE",
    "sg:address":"Alte M\u00fchlstr. 11",
    "sg:city":"Osterhofen",
    "sg:phone":"+49 8547/364",
    "sg:postcode":"94486",
    "sg:province":"Bayern",
    "wof:name":"X. Wasmeier M\u00fchle Willing",
    "wof:placetype":"venue"
},
  "geometry": {"coordinates":[12.9544267654,48.6276550293],"type":"Point"}
}