{
  "type": "Feature",
  "properties": {
    "iso:country":"DE",
    "sg:address":"Dr.-Liebenthal-Str. 9",
    "sg:city":"Wismar",
    "sg:postcode":"23970",
    "sg:province":"Mecklenburg-Vorpommern",
    "wof:name":"Dr. Med. Helga Sadowski",
    "wof:placetype":"venue"
},
  "geometry": {"coordinates":[11.468665,53.887501],"type":"Point"}
}