{
  "type": "Feature",
  "properties": {
    "iso:country":"DE",
    "sg:address":"Achldorf 46",
    "sg:city":"Vilsbiburg",
    "sg:phone":"+49 8741/9660",
    "sg:postcode":"84137",
    "sg:province":"Bayern",
    "wof:name":"Hotel Kongressissimo Gmbh",
    "wof:placetype":"venue"
},
  "geometry": {"coordinates":[12.3552646637,48.4276733398],"type":"Point"}
}