{
  "type": "Feature",
  "properties": {
    "iso:country":"DE",
    "sg:address":"Dall'Armistr. 14",
    "sg:city":"Seeshaupt",
    "sg:postcode":"82402",
    "sg:province":"Bayern",
    "wof:name":"Kurt Egger Beteiligungs Gmbh",
    "wof:placetype":"venue"
},
  "geometry": {"coordinates":[11.302792,47.823071],"type":"Point"}
}