{
  "type": "Feature",
  "properties": {
    "iso:country":"DE",
    "sg:address":"Obere Marktstr. 52",
    "sg:city":"Neumarkt",
    "sg:phone":"+49 9181/2100",
    "sg:postcode":"92318",
    "sg:province":"Bayern",
    "wof:name":"Sparkasse Neumarkt-parsberg",
    "wof:placetype":"venue"
},
  "geometry": {"coordinates":[11.460681,49.27737],"type":"Point"}
}