{
  "type": "Feature",
  "properties": {
    "iso:country":"DE",
    "sg:address":"Leiningerstr. 18",
    "sg:city":"Bad D\u00fcrkheim",
    "sg:phone":"+49 6322/5355",
    "sg:postcode":"67098",
    "sg:province":"Rheinland-Pfalz",
    "wof:name":"G\u00fcnter Allbach",
    "wof:placetype":"venue"
},
  "geometry": {"coordinates":[8.1668,49.459332],"type":"Point"}
}