{
  "type": "Feature",
  "properties": {
    "iso:country":"DE",
    "sg:address":"Geithainer Str. 19",
    "sg:city":"K\u00f6nigsfeld",
    "sg:phone":"+49 3737/42158",
    "sg:postcode":"09306",
    "sg:province":"Sachsen",
    "wof:name":"Stelzer Inh. R. U. K. Stelzer",
    "wof:placetype":"venue"
},
  "geometry": {"coordinates":[12.826762,51.027431],"type":"Point"}
}