{
  "type": "Feature",
  "properties": {
    "iso:country":"DE",
    "sg:address":"Humboldtstr. 13",
    "sg:city":"Gladbeck",
    "sg:phone":"+49 2043/279313",
    "sg:postcode":"45964",
    "sg:province":"Nordrhein-Westfalen",
    "wof:name":"Diakonie",
    "wof:placetype":"venue"
},
  "geometry": {"coordinates":[6.990287,51.574657],"type":"Point"}
}