{
  "type": "Feature",
  "properties": {
    "iso:country":"DE",
    "sg:address":"H\u00f6hlchenstr. 11",
    "sg:city":"Worms",
    "sg:phone":"+49 6241/35313",
    "sg:postcode":"67551",
    "sg:province":"Rheinland-Pfalz",
    "wof:name":"Penny Gmbh",
    "wof:placetype":"venue"
},
  "geometry": {"coordinates":[8.3313131332,49.6129760742],"type":"Point"}
}