{
  "type": "Feature",
  "properties": {
    "iso:country":"DE",
    "sg:address":"Stockhausgasse 6",
    "sg:city":"D\u00fcsseldorf",
    "sg:phone":"+49 211/400452",
    "sg:postcode":"40489",
    "sg:province":"Nordrhein-Westfalen",
    "wof:name":"Regine Dichgans Architektin",
    "wof:placetype":"venue"
},
  "geometry": {"coordinates":[6.734727,51.29966],"type":"Point"}
}