{
  "type": "Feature",
  "properties": {
    "iso:country":"DE",
    "sg:address":"Birkenweg 4",
    "sg:city":"Bad Kreuznach",
    "sg:phone":"+49 671/68242",
    "sg:postcode":"55543",
    "sg:province":"Rheinland-Pfalz",
    "wof:name":"Paul Dhom",
    "wof:placetype":"venue"
},
  "geometry": {"coordinates":[7.8755779266,49.834148407],"type":"Point"}
}