{
  "type": "Feature",
  "properties": {
    "iso:country":"DE",
    "sg:address":"Maysweg 15",
    "sg:city":"T\u00f6nisvorst",
    "sg:phone":"+49 2151/791806",
    "sg:postcode":"47918",
    "sg:province":"Nordrhein-Westfalen",
    "wof:name":"Schott Dental Material Gmbh",
    "wof:placetype":"venue"
},
  "geometry": {"coordinates":[6.5108189583,51.3184928894],"type":"Point"}
}