{
  "type": "Feature",
  "properties": {
    "iso:country":"DE",
    "sg:address":"An der Egert 8",
    "sg:city":"Neuhof",
    "sg:phone":"+49 661/44219",
    "sg:postcode":"36119",
    "sg:province":"Hessen",
    "wof:name":"J\u00fcrgen Block",
    "wof:placetype":"venue"
},
  "geometry": {"coordinates":[9.565777,50.506542],"type":"Point"}
}