{
  "type": "Feature",
  "properties": {
    "iso:country":"DE",
    "sg:address":"Morgensternstr. 5",
    "sg:city":"Hameln",
    "sg:phone":"+49 5151/16824",
    "sg:postcode":"31787",
    "sg:province":"Niedersachsen",
    "wof:name":"Lotte Schn\u00e4pel",
    "wof:placetype":"venue"
},
  "geometry": {"coordinates":[9.37591,52.10479],"type":"Point"}
}