{
  "type": "Feature",
  "properties": {
    "iso:country":"DE",
    "sg:address":"Konrad-Haag-Str. 37",
    "sg:city":"Elmstein",
    "sg:phone":"+49 6328/707",
    "sg:postcode":"67471",
    "sg:province":"Rheinland-Pfalz",
    "wof:name":"Gebr. Steinm\u00fcller Gmbh",
    "wof:placetype":"venue"
},
  "geometry": {"coordinates":[7.949048,49.346138],"type":"Point"}
}