{
  "type": "Feature",
  "properties": {
    "iso:country":"DE",
    "sg:address":"Kirchstr. 20",
    "sg:city":"H\u00fcrtgenwald",
    "sg:postcode":"52393",
    "sg:province":"Nordrhein-Westfalen",
    "wof:name":"B\u00fccherei D. Kath. Kirchen- Gemeinde H\u00fcrtgen",
    "wof:placetype":"venue"
},
  "geometry": {"coordinates":[6.380084,50.709499],"type":"Point"}
}