{
  "type": "Feature",
  "properties": {
    "iso:country":"DE",
    "sg:address":"Albert-Schweitzer-Str. 39",
    "sg:city":"Memmingen",
    "sg:phone":"+49 8331/496971",
    "sg:postcode":"87700",
    "sg:province":"Bayern",
    "wof:name":"Bistro Wintergarten",
    "wof:placetype":"venue"
},
  "geometry": {"coordinates":[10.1972446442,47.9919281006],"type":"Point"}
}