{
  "type": "Feature",
  "properties": {
    "iso:country":"DE",
    "sg:address":"Lanker Str. 15 A",
    "sg:city":"Biesenthal",
    "sg:phone":"+49 3337",
    "sg:postcode":"16359",
    "sg:province":"Brandenburg",
    "wof:name":"Daiko-kfz-recycling",
    "wof:placetype":"venue"
},
  "geometry": {"coordinates":[13.6070146561,52.7654876709],"type":"Point"}
}