{
  "type": "Feature",
  "properties": {
    "iso:country":"DE",
    "sg:address":"Bahnhofstr. 29",
    "sg:city":"St. Michaelisdonn",
    "sg:phone":"+49 4853/80060",
    "sg:postcode":"25693",
    "sg:province":"Schleswig-Holstein",
    "wof:name":"Ferdinand Wittrock",
    "wof:placetype":"venue"
},
  "geometry": {"coordinates":[9.1164855957,53.9899368286],"type":"Point"}
}