{
  "type": "Feature",
  "properties": {
    "iso:country":"DE",
    "sg:address":"Ort 33",
    "sg:city":"Freyung",
    "sg:phone":"+49 8551/4274",
    "sg:postcode":"94078",
    "sg:province":"Bayern",
    "wof:name":"Gemeinn\u00fctzige Wohnungsbau Gmbh",
    "wof:placetype":"venue"
},
  "geometry": {"coordinates":[13.5288801193,48.8054199219],"type":"Point"}
}