{
  "type": "Feature",
  "properties": {
    "iso:country":"DE",
    "sg:address":"Bramfelder Chaussee 32",
    "sg:city":"Hamburg",
    "sg:phone":"+49 40/612316",
    "sg:postcode":"22177",
    "sg:province":"Hamburg",
    "wof:name":"W. Horstmann",
    "wof:placetype":"venue"
},
  "geometry": {"coordinates":[10.0614070892,53.595161438],"type":"Point"}
}