{
  "type": "Feature",
  "properties": {
    "iso:country":"DE",
    "sg:address":"Kochenbacher Str. 2",
    "sg:city":"Bad Honnef",
    "sg:phone":"+49 2224/81010",
    "sg:postcode":"53604",
    "sg:province":"Nordrhein-Westfalen",
    "wof:name":"Dieter Boll Rechtsanwalt",
    "wof:placetype":"venue"
},
  "geometry": {"coordinates":[7.3179001808,50.6764793396],"type":"Point"}
}