{
  "type": "Feature",
  "properties": {
    "iso:country":"DE",
    "sg:address":"Im Kurzen Tal 1",
    "sg:city":"St. Ingbert",
    "sg:phone":"+49 6894/80778",
    "sg:postcode":"66386",
    "sg:province":"Saarland",
    "wof:name":"Diak. Kinderheim",
    "wof:placetype":"venue"
},
  "geometry": {"coordinates":[7.1293811798,49.2549514771],"type":"Point"}
}