{
  "type": "Feature",
  "properties": {
    "iso:country":"DE",
    "sg:address":"Pirminstr. 152",
    "sg:city":"Reichenau",
    "sg:phone":"+49 7534/264",
    "sg:postcode":"78479",
    "sg:province":"Baden-W\u00fcrttemberg",
    "wof:name":"Kaufhaus Locher Ohg Inh. Hartmut Spitzh\u00fcttl E. K.",
    "wof:placetype":"venue"
},
  "geometry": {"coordinates":[9.062872,47.697094],"type":"Point"}
}