{
  "type": "Feature",
  "properties": {
    "iso:country":"DE",
    "sg:address":"Berliner Allee 25",
    "sg:city":"D\u00fcsseldorf",
    "sg:phone":"+49 211/135022",
    "sg:postcode":"40212",
    "sg:province":"Nordrhein-Westfalen",
    "wof:name":"It & I Industry Trade Und Investment Consulting Gmbh",
    "wof:placetype":"venue"
},
  "geometry": {"coordinates":[6.782418,51.223392],"type":"Point"}
}