{
  "type": "Feature",
  "properties": {
    "iso:country":"DE",
    "sg:address":"Salzufer 1-5",
    "sg:city":"Berlin",
    "sg:postcode":"10587",
    "sg:province":"Berlin",
    "wof:name":"Salt N Pepper Gmbh",
    "wof:placetype":"venue"
},
  "geometry": {"coordinates":[13.330441,52.514412],"type":"Point"}
}