{
  "type": "Feature",
  "properties": {
    "iso:country":"DE",
    "sg:address":"B\u00f6blinger Str. 47",
    "sg:city":"Leinfelden-Echterdingen",
    "sg:phone":"+49 711/7546047",
    "sg:postcode":"70771",
    "sg:province":"Baden-W\u00fcrttemberg",
    "wof:name":"Leonhard J\u00e4ger",
    "wof:placetype":"venue"
},
  "geometry": {"coordinates":[9.11523,48.69072],"type":"Point"}
}