{
  "type": "Feature",
  "properties": {
    "iso:country":"DE",
    "sg:address":"Sulzbacher Str. 95",
    "sg:city":"Frankfurt",
    "sg:phone":"+49 69/303093",
    "sg:postcode":"60326",
    "sg:province":"Hessen",
    "wof:name":"Friedhofsg\u00e4rtnerei Emert Gmbh",
    "wof:placetype":"venue"
},
  "geometry": {"coordinates":[8.641855,50.105484],"type":"Point"}
}