{
  "type": "Feature",
  "properties": {
    "iso:country":"DE",
    "sg:address":"Oberfeld 4",
    "sg:city":"Sangerhausen",
    "sg:phone":"+49 3464/571500",
    "sg:postcode":"06526",
    "sg:province":"Sachsen-Anhalt",
    "wof:name":"Zikmund Maler Gmbh & Co. Kg",
    "wof:placetype":"venue"
},
  "geometry": {"coordinates":[11.321159,51.474548],"type":"Point"}
}