{
  "type": "Feature",
  "properties": {
    "iso:country":"DE",
    "sg:address":"L\u00e4rchenstr. 2",
    "sg:city":"Sch\u00f6nberg",
    "sg:phone":"+49 8637/7493",
    "sg:postcode":"84573",
    "sg:province":"Bayern",
    "wof:name":"M. Peteratzinger",
    "wof:placetype":"venue"
},
  "geometry": {"coordinates":[12.434679985,48.3455581665],"type":"Point"}
}