{
  "type": "Feature",
  "properties": {
    "iso:country":"DE",
    "sg:address":"Grenzweg 5",
    "sg:city":"Krombach",
    "sg:phone":"+49 6024/630573",
    "sg:postcode":"63829",
    "sg:province":"Bayern",
    "wof:name":"Mht Gmbh",
    "wof:placetype":"venue"
},
  "geometry": {"coordinates":[9.2215461731,50.0720405579],"type":"Point"}
}