{
  "type": "Feature",
  "properties": {
    "iso:country":"DE",
    "sg:address":"Konrad-Adenauer-Str. 4",
    "sg:city":"Dachau",
    "sg:phone":"+49 8131/75229",
    "sg:postcode":"85221",
    "sg:province":"Bayern",
    "wof:name":"Redaktion Amperland Stadt Verlag",
    "wof:placetype":"venue"
},
  "geometry": {"coordinates":[11.4352283478,48.2595062256],"type":"Point"}
}