{
  "type": "Feature",
  "properties": {
    "iso:country":"DE",
    "sg:address":"Poststr. 26",
    "sg:city":"Oberthal",
    "sg:phone":"+49 6854/6008",
    "sg:postcode":"66649",
    "sg:province":"Saarland",
    "wof:name":"Marien-apotheke",
    "wof:placetype":"venue"
},
  "geometry": {"coordinates":[7.089974,49.511665],"type":"Point"}
}