{
  "type": "Feature",
  "properties": {
    "iso:country":"DE",
    "sg:address":"Wechold 31",
    "sg:city":"Hilgermissen",
    "sg:phone":"+49 4255/386",
    "sg:postcode":"27318",
    "sg:province":"Niedersachsen",
    "wof:name":"Johann Wurthmann",
    "wof:placetype":"venue"
},
  "geometry": {"coordinates":[9.112996,52.855553],"type":"Point"}
}