{
  "type": "Feature",
  "properties": {
    "iso:country":"DE",
    "sg:address":"Samuel-Frank-Str. 42",
    "sg:city":"Siegen",
    "sg:phone":"+49 271/46218",
    "sg:postcode":"57076",
    "sg:province":"Nordrhein-Westfalen",
    "wof:name":"M. Klingner Masseur",
    "wof:placetype":"venue"
},
  "geometry": {"coordinates":[8.035808,50.889519],"type":"Point"}
}