{
  "type": "Feature",
  "properties": {
    "iso:country":"DE",
    "sg:address":"Orleansstr. 90",
    "sg:city":"Bremen",
    "sg:phone":"+49 421/445031",
    "sg:postcode":"28211",
    "sg:province":"Bremen",
    "wof:name":"Wicke Blumen Inh. Irma Von Bloh",
    "wof:placetype":"venue"
},
  "geometry": {"coordinates":[8.850445,53.081848],"type":"Point"}
}