{
  "type": "Feature",
  "properties": {
    "iso:country":"DE",
    "sg:address":"Burchard-Retschy-Ring 3",
    "sg:city":"Lehrte",
    "sg:phone":"+49 5132/52503",
    "sg:postcode":"31275",
    "sg:province":"Niedersachsen",
    "wof:name":"G\u00fcnther H\u00e4nsch",
    "wof:placetype":"venue"
},
  "geometry": {"coordinates":[9.964671,52.386703],"type":"Point"}
}