{
  "type": "Feature",
  "properties": {
    "iso:country":"DE",
    "sg:address":"Baiershofener Str 7",
    "sg:city":"Westhausen",
    "sg:phone":"+49 7363/5005",
    "sg:postcode":"73463",
    "sg:province":"Baden-W\u00fcrttemberg",
    "wof:name":"Gts Getr\u00e4nke Technik S\u00fcd Gmbh",
    "wof:placetype":"venue"
},
  "geometry": {"coordinates":[10.161757,48.886375],"type":"Point"}
}