{
  "type": "Feature",
  "properties": {
    "iso:country":"DE",
    "sg:address":"Feldmannstr. 150",
    "sg:city":"Saarbr\u00fccken",
    "sg:phone":"+49 681/56353",
    "sg:postcode":"66119",
    "sg:province":"Saarland",
    "wof:name":"Almut Hinrichs & Prof. C. F. Hinrichs",
    "wof:placetype":"venue"
},
  "geometry": {"coordinates":[6.985425,49.221317],"type":"Point"}
}