{
  "type": "Feature",
  "properties": {
    "iso:country":"DE",
    "sg:address":"Landsberger Str. 56",
    "sg:city":"Waldheim",
    "sg:phone":"+49 34327/91544",
    "sg:postcode":"04736",
    "sg:province":"Sachsen",
    "wof:name":"W\u00e4scheservice Wilfried Sch\u00e4fer",
    "wof:placetype":"venue"
},
  "geometry": {"coordinates":[12.9875679016,51.0782241821],"type":"Point"}
}