{
  "type": "Feature",
  "properties": {
    "iso:country":"DE",
    "sg:address":"Waldweg 5",
    "sg:city":"Kurort Seiffen",
    "sg:phone":"+49 37362/8269",
    "sg:postcode":"09548",
    "sg:province":"Sachsen",
    "wof:name":"S. Pflugbeil",
    "wof:placetype":"venue"
},
  "geometry": {"coordinates":[13.4598741531,50.6391487122],"type":"Point"}
}