{
  "type": "Feature",
  "properties": {
    "iso:country":"DE",
    "sg:address":"Unter der Helle 7",
    "sg:city":"Halle",
    "sg:phone":"+49 5533/2723",
    "sg:postcode":"37620",
    "sg:province":"Niedersachsen",
    "wof:name":"Ernst Brennecke",
    "wof:placetype":"venue"
},
  "geometry": {"coordinates":[9.565456,51.988056],"type":"Point"}
}