{
  "type": "Feature",
  "properties": {
    "iso:country":"DE",
    "sg:address":"Bilohof",
    "sg:city":"Attenhausen",
    "sg:phone":"+49 2604/8595",
    "sg:postcode":"56370",
    "sg:province":"Rheinland-Pfalz",
    "wof:name":"Christof Bilo",
    "wof:placetype":"venue"
},
  "geometry": {"coordinates":[7.879205,50.299076],"type":"Point"}
}