{
  "type": "Feature",
  "properties": {
    "iso:country":"DE",
    "sg:address":"Redlingsweg 20",
    "sg:city":"Langenhorn",
    "sg:phone":"+49 4672/1552",
    "sg:postcode":"25842",
    "sg:province":"Schleswig-Holstein",
    "wof:name":"Steen Jacobsen",
    "wof:placetype":"venue"
},
  "geometry": {"coordinates":[8.9415493011,54.6732521057],"type":"Point"}
}