{
  "type": "Feature",
  "properties": {
    "iso:country":"DE",
    "sg:address":"Tannenweg 10",
    "sg:city":"Neuenhaus",
    "sg:phone":"+49 5941/354",
    "sg:postcode":"49828",
    "sg:province":"Niedersachsen",
    "wof:name":"Jan-egbert Str\u00f6tker",
    "wof:placetype":"venue"
},
  "geometry": {"coordinates":[7.008849,52.479328],"type":"Point"}
}