{
  "type": "Feature",
  "properties": {
    "iso:country":"DE",
    "sg:address":"Obergasse 17",
    "sg:city":"Schwarzenberg",
    "sg:phone":"+49 3774/15710",
    "sg:postcode":"08340",
    "sg:province":"Sachsen",
    "wof:name":"Eks-elektroanlagenbau Und Kfz-service Gmbh",
    "wof:placetype":"venue"
},
  "geometry": {"coordinates":[12.785058,50.532928],"type":"Point"}
}