{
  "type": "Feature",
  "properties": {
    "iso:country":"DE",
    "sg:address":"Zeithstr. 110",
    "sg:city":"Siegburg",
    "sg:phone":"+49 2241/53430",
    "sg:postcode":"53721",
    "sg:province":"Nordrhein-Westfalen",
    "wof:name":"Octopus",
    "wof:placetype":"venue"
},
  "geometry": {"coordinates":[7.2193598747,50.8029899597],"type":"Point"}
}