{
  "type": "Feature",
  "properties": {
    "iso:country":"DE",
    "sg:address":"Ulmenweg 15",
    "sg:city":"Wassertr\u00fcdingen",
    "sg:phone":"+49 9832/67846",
    "sg:postcode":"91717",
    "sg:province":"Bayern",
    "wof:name":"Ewas Eberlein-wechsel-akku-systeme",
    "wof:placetype":"venue"
},
  "geometry": {"coordinates":[10.586091,49.042641],"type":"Point"}
}