{
  "type": "Feature",
  "properties": {
    "iso:country":"DE",
    "sg:address":"Waldstr. 81",
    "sg:city":"Sch\u00f6neiche",
    "sg:phone":"+49 30/64903966",
    "sg:postcode":"15566",
    "sg:province":"Brandenburg",
    "wof:name":"Erhard Werner",
    "wof:placetype":"venue"
},
  "geometry": {"coordinates":[13.6918830872,52.4651451111],"type":"Point"}
}