{
  "type": "Feature",
  "properties": {
    "iso:country":"DE",
    "sg:address":"Mendelssohnstr. 92",
    "sg:city":"Frankfurt",
    "sg:phone":"+49 69/747992",
    "sg:postcode":"60325",
    "sg:province":"Hessen",
    "wof:name":"Hotel G. Backer",
    "wof:placetype":"venue"
},
  "geometry": {"coordinates":[8.6597070694,50.1186256409],"type":"Point"}
}