{
  "type": "Feature",
  "properties": {
    "iso:country":"DE",
    "sg:address":"Clemensstr. 22",
    "sg:city":"Bochum",
    "sg:phone":"+49 2327/57459",
    "sg:postcode":"44789",
    "sg:province":"Nordrhein-Westfalen",
    "wof:name":"Systembau Kleinertz Gmbh",
    "wof:placetype":"venue"
},
  "geometry": {"coordinates":[7.218148,51.473656],"type":"Point"}
}