{
  "type": "Feature",
  "properties": {
    "iso:country":"DE",
    "sg:address":"Boverstr. 15c",
    "sg:city":"M\u00fclheim",
    "sg:phone":"+49 208/756676",
    "sg:postcode":"45473",
    "sg:province":"Nordrhein-Westfalen",
    "wof:name":"J. Klees",
    "wof:placetype":"venue"
},
  "geometry": {"coordinates":[6.8902378082,51.4434967041],"type":"Point"}
}