{
  "type": "Feature",
  "properties": {
    "iso:country":"DE",
    "sg:address":"Mannheimer Str. 26",
    "sg:city":"Schwetzingen",
    "sg:phone":"+49 6202/923438",
    "sg:postcode":"68723",
    "sg:province":"Baden-W\u00fcrttemberg",
    "wof:name":"Werner Bellstedt",
    "wof:placetype":"venue"
},
  "geometry": {"coordinates":[8.574078,49.386116],"type":"Point"}
}