{
  "type": "Feature",
  "properties": {
    "iso:country":"DE",
    "sg:address":"Peutestr 18",
    "sg:city":"Hamburg",
    "sg:phone":"+49 40/78943661",
    "sg:postcode":"20539",
    "sg:province":"Hamburg",
    "wof:name":"Sts Silo & Tank Spedition Gmbh",
    "wof:placetype":"venue"
},
  "geometry": {"coordinates":[10.0326719284,53.5251121521],"type":"Point"}
}