{
  "type": "Feature",
  "properties": {
    "iso:country":"DE",
    "sg:address":"Elsenheimerstr. 56",
    "sg:city":"M\u00fcnchen",
    "sg:phone":"+49 89/5705142",
    "sg:postcode":"80687",
    "sg:province":"Bayern",
    "wof:name":"Santos Immobilien Gmbh",
    "wof:placetype":"venue"
},
  "geometry": {"coordinates":[11.5234880447,48.1362342834],"type":"Point"}
}