{
  "type": "Feature",
  "properties": {
    "iso:country":"DE",
    "sg:address":"Rathausplatz 2-1",
    "sg:city":"Esslingen",
    "sg:phone":"+49 711/353900",
    "sg:postcode":"73728",
    "sg:province":"Baden-W\u00fcrttemberg",
    "wof:name":"Restaurant Carmela",
    "wof:placetype":"venue"
},
  "geometry": {"coordinates":[9.307390213,48.7429504395],"type":"Point"}
}