{
  "type": "Feature",
  "properties": {
    "iso:country":"DE",
    "sg:address":"Am Markt 30",
    "sg:city":"Wismar",
    "sg:phone":"+49 3841/200028",
    "sg:postcode":"23966",
    "sg:province":"Mecklenburg-Vorpommern",
    "wof:name":"Arko Gmbh",
    "wof:placetype":"venue"
},
  "geometry": {"coordinates":[11.4669456482,53.8916816711],"type":"Point"}
}