{
  "type": "Feature",
  "properties": {
    "iso:country":"DE",
    "sg:address":"Promenade 19-23::",
    "sg:city":"Ansbach",
    "sg:href":"http://api.simplegeo.com/1.0/features/SG_0BeUhFcb2AZhl9XHjskbWK_49.301338_10.574656@1306268793.json",
    "sg:phone":"+49 981/1810",
    "sg:postcode":"91522",
    "sg:province":"Bayern",
    "wof:name":"Gewerbebank Ansbach Eg",
    "wof:placetype":"venue"
},
  "geometry": {"coordinates":[10.574656,49.301338],"type":"Point"}
}