{"geometry":{"type":"Point","coordinates":[10.574656,49.301338]},"type":"Feature","id":102560253,"bbox":[10.574656,49.301338,10.574656,49.301338],"properties":{"sg:province":"Bayern","geom:longitude":10.574656,"wof:breaches":[],"sg:href":"http://api.simplegeo.com/1.0/features/SG_0BeUhFcb2AZhl9XHjskbWK_49.301338_10.574656@1306268793.json","sg:owner":"simplegeo","sg:postcode":"91522","geom:latitude":49.301338,"sg:classifiers":[],"sg:address":"Promenade 19-23::","sg:phone":"+49 981/1810","wof:hierarchy":[{"locality_id":101782029,"venue_id":102560253,"country_id":85633111,"region_id":85682571,"county_id":102063409}],"geom:area":0.000000,"sg:city":"Ansbach","wof:lastmodified":1438093220,"iso:country":"DE","wof:geomhash":"e593488922103bbe68935ccd721bc81f","wof:name":"Gewerbebank Ansbach Eg","wof:belongsto":[101782029,85633111,85682571,102063409],"src:geom":"simplegeo","wof:placetype":"venue","wof:supersedes":[],"wof:id":102560253,"wof:superseded_by":[],"wof:concordances":{"sg:id":"SG_0BeUhFcb2AZhl9XHjskbWK_49.301338_10.574656@1306268793"},"wof:parent_id":101782029}}