{
  "type": "Feature",
  "properties": {
    "iso:country":"DE",
    "sg:address":"Theodor-Heuss-Platz 4",
    "sg:city":"Berlin",
    "sg:phone":"+49 30/3022146",
    "sg:postcode":"14052",
    "sg:province":"Berlin",
    "wof:name":"Gerhard Henoch Ingenieur",
    "wof:placetype":"venue"
},
  "geometry": {"coordinates":[13.2730474472,52.5099105835],"type":"Point"}
}