{
  "type": "Feature",
  "properties": {
    "iso:country":"DE",
    "sg:address":"Hauptstr. 17",
    "sg:city":"Linsengericht",
    "sg:postcode":"63589",
    "sg:province":"Hessen",
    "wof:name":"Sds Sicherheitsdienste Gmbh",
    "wof:placetype":"venue"
},
  "geometry": {"coordinates":[9.199822,50.188847],"type":"Point"}
}