{
  "type": "Feature",
  "properties": {
    "iso:country":"DE",
    "sg:address":"Multimediapark 71",
    "sg:city":"Zweibr\u00fccken",
    "sg:postcode":"66482",
    "sg:province":"Rheinland-Pfalz",
    "wof:name":"Mad Cat Interactive Software Gmbh",
    "wof:placetype":"venue"
},
  "geometry": {"coordinates":[7.3675551414,49.2426452637],"type":"Point"}
}