{
  "type": "Feature",
  "properties": {
    "iso:country":"DE",
    "sg:address":"Hauptstr. 108",
    "sg:city":"Kurort Seiffen",
    "sg:phone":"+49 37362/8538",
    "sg:postcode":"09548",
    "sg:province":"Sachsen",
    "wof:name":"Kai Pallent",
    "wof:placetype":"venue"
},
  "geometry": {"coordinates":[13.455194,50.647865],"type":"Point"}
}