{
  "type": "Feature",
  "properties": {
    "iso:country":"DE",
    "sg:address":"Dankwartstrasse 61 a",
    "sg:city":"Wismar",
    "sg:phone":"+49 3841/215317",
    "sg:postcode":"23966",
    "sg:province":"Mecklenburg-Vorpommern",
    "wof:name":"Portraitmalerei Von Manfred W. J\u00fcrgens",
    "wof:placetype":"venue"
},
  "geometry": {"coordinates":[11.4624938965,53.8887252808],"type":"Point"}
}