{
  "type": "Feature",
  "properties": {
    "iso:country":"DE",
    "sg:address":"Am Beckenberg 1",
    "sg:city":"Herzogenrath",
    "sg:phone":"+49 2406/929313",
    "sg:postcode":"52134",
    "sg:province":"Nordrhein-Westfalen",
    "wof:name":"Dr. H. Kluttig Ingenieur",
    "wof:placetype":"venue"
},
  "geometry": {"coordinates":[6.0886912346,50.8646697998],"type":"Point"}
}