{
  "type": "Feature",
  "properties": {
    "iso:country":"DE",
    "sg:address":"Welte 114 a",
    "sg:city":"D\u00fclmen",
    "sg:postcode":"48249",
    "sg:province":"Nordrhein-Westfalen",
    "wof:name":"Autrup Gmbh",
    "wof:placetype":"venue"
},
  "geometry": {"coordinates":[7.2204670906,51.8755950928],"type":"Point"}
}