{
  "type": "Feature",
  "properties": {
    "iso:country":"DE",
    "sg:address":"August-Bebel-Str. 58",
    "sg:city":"Reichenberg",
    "sg:postcode":"01468",
    "sg:province":"Sachsen",
    "wof:name":"Fliesenhandel Reichenberg Inh. Waltraud Anders",
    "wof:placetype":"venue"
},
  "geometry": {"coordinates":[13.680374,51.128353],"type":"Point"}
}