{
  "type": "Feature",
  "properties": {
    "iso:country":"DE",
    "sg:address":"Goerdelerstr. 50",
    "sg:city":"Rostock",
    "sg:postcode":"18069",
    "sg:province":"Mecklenburg-Vorpommern",
    "wof:name":"China Garden Gmbh",
    "wof:placetype":"venue"
},
  "geometry": {"coordinates":[12.0735397339,54.0960388184],"type":"Point"}
}