{
  "type": "Feature",
  "properties": {
    "iso:country":"DE",
    "sg:address":"Kurf\u00fcrsten-Anlage 53",
    "sg:city":"Heidelberg",
    "sg:phone":"+49 6221/21259",
    "sg:postcode":"69115",
    "sg:province":"Baden-W\u00fcrttemberg",
    "wof:name":"Zse-zippel Software- Entwicklung E. K.",
    "wof:placetype":"venue"
},
  "geometry": {"coordinates":[8.6819925308,49.4047622681],"type":"Point"}
}