{
  "type": "Feature",
  "properties": {
    "iso:country":"DE",
    "sg:address":"Gleueler Str. 68",
    "sg:city":"Frechen",
    "sg:phone":"+49 2234/54086",
    "sg:postcode":"50226",
    "sg:province":"Nordrhein-Westfalen",
    "wof:name":"Michael Spohn",
    "wof:placetype":"venue"
},
  "geometry": {"coordinates":[6.824969,50.894928],"type":"Point"}
}