{
  "type": "Feature",
  "properties": {
    "iso:country":"DE",
    "sg:address":"Reu\u00dfendorfer Str. 41",
    "sg:city":"Wildflecken",
    "sg:phone":"+49 9745/3191",
    "sg:postcode":"97772",
    "sg:province":"Bayern",
    "wof:name":"Manfred Rohmann",
    "wof:placetype":"venue"
},
  "geometry": {"coordinates":[9.908522,50.380692],"type":"Point"}
}