{
  "type": "Feature",
  "properties": {
    "iso:country":"DE",
    "sg:address":"Am Goldmorgen 2",
    "sg:city":"Neuss",
    "sg:phone":"+49 2137/6313",
    "sg:postcode":"41469",
    "sg:province":"Nordrhein-Westfalen",
    "wof:name":"Rolf Engelmann Steuerberater",
    "wof:placetype":"venue"
},
  "geometry": {"coordinates":[6.700232029,51.1450500488],"type":"Point"}
}