{
  "type": "Feature",
  "properties": {
    "iso:country":"DE",
    "sg:address":"Deversdonk 1",
    "sg:city":"Grefrath",
    "sg:phone":"+49 2158/4268",
    "sg:postcode":"47929",
    "sg:province":"Nordrhein-Westfalen",
    "wof:name":"U. K\u00fcsters-verlinden U. A. Verlinden",
    "wof:placetype":"venue"
},
  "geometry": {"coordinates":[6.342121,51.337021],"type":"Point"}
}