{
  "type": "Feature",
  "properties": {
    "iso:country":"DE",
    "sg:address":"Matthias-Gr\u00fcnewald-Str. 14",
    "sg:city":"Albstadt",
    "sg:phone":"+49 7432/22101",
    "sg:postcode":"72461",
    "sg:province":"Baden-W\u00fcrttemberg",
    "wof:name":"Willi Boss Architekt",
    "wof:placetype":"venue"
},
  "geometry": {"coordinates":[8.996988,48.289162],"type":"Point"}
}