{
  "type": "Feature",
  "properties": {
    "iso:country":"DE",
    "sg:address":"Bergstr. 77",
    "sg:city":"Timmendorfer Strand",
    "sg:phone":"+49 4503/889030",
    "sg:postcode":"23669",
    "sg:province":"Schleswig-Holstein",
    "wof:name":"Apotheke Am Kurpark",
    "wof:placetype":"venue"
},
  "geometry": {"coordinates":[10.779152,53.998425],"type":"Point"}
}