{
  "type": "Feature",
  "properties": {
    "iso:country":"DE",
    "sg:address":"Heinrich-Werner-Str. 17",
    "sg:city":"Kirchohmfeld",
    "sg:phone":"+49 36074/2552",
    "sg:postcode":"37339",
    "sg:province":"Th\u00fcringen",
    "wof:name":"W. Bonda",
    "wof:placetype":"venue"
},
  "geometry": {"coordinates":[10.3598766327,51.4428825378],"type":"Point"}
}