{
  "type": "Feature",
  "properties": {
    "iso:country":"DE",
    "sg:address":"Hauptstr. 34",
    "sg:city":"Niefern-\u00d6schelbronn",
    "sg:phone":"+49 7233/1332",
    "sg:postcode":"75223",
    "sg:province":"Baden-W\u00fcrttemberg",
    "wof:name":"Dieter Gerhardt",
    "wof:placetype":"venue"
},
  "geometry": {"coordinates":[8.7899856567,48.9065933228],"type":"Point"}
}