{
  "type": "Feature",
  "properties": {
    "iso:country":"DE",
    "sg:address":"Moselstr. 20",
    "sg:city":"Alken",
    "sg:phone":"+49 2605/8910",
    "sg:postcode":"56332",
    "sg:province":"Rheinland-Pfalz",
    "wof:name":"Aktiv Markt",
    "wof:placetype":"venue"
},
  "geometry": {"coordinates":[7.4470729828,50.2480697632],"type":"Point"}
}