{
  "type": "Feature",
  "properties": {
    "iso:country":"DE",
    "sg:address":"Osterstr. 28",
    "sg:city":"Katlenburg-Lindau",
    "sg:phone":"+49 5556/369",
    "sg:postcode":"37191",
    "sg:province":"Niedersachsen",
    "wof:name":"A. D\u00f6lle",
    "wof:placetype":"venue"
},
  "geometry": {"coordinates":[10.1200199127,51.656917572],"type":"Point"}
}