{
  "type": "Feature",
  "properties": {
    "iso:country":"DE",
    "sg:address":"Dinslakener Str. 120",
    "sg:city":"H\u00fcnxe",
    "sg:phone":"+49 2064/30430",
    "sg:postcode":"46569",
    "sg:province":"Nordrhein-Westfalen",
    "wof:name":"K.-h. R\u00fchl",
    "wof:placetype":"venue"
},
  "geometry": {"coordinates":[6.7568240166,51.6014976501],"type":"Point"}
}