{
  "type": "Feature",
  "properties": {
    "iso:country":"DE",
    "sg:address":"Mastauhof 1",
    "sg:city":"Homburg",
    "sg:phone":"+49 6841/4783",
    "sg:postcode":"66424",
    "sg:province":"Saarland",
    "wof:name":"Karl Maas",
    "wof:placetype":"venue"
},
  "geometry": {"coordinates":[7.317808,49.288918],"type":"Point"}
}