{
  "type": "Feature",
  "properties": {
    "iso:country":"DE",
    "sg:address":"An der Badeanstalt 1",
    "sg:city":"Bad Laer",
    "sg:phone":"+49 5424/9372",
    "sg:postcode":"49196",
    "sg:province":"Niedersachsen",
    "wof:name":"Freibad",
    "wof:placetype":"venue"
},
  "geometry": {"coordinates":[8.0808267593,52.10206604],"type":"Point"}
}