{
  "type": "Feature",
  "properties": {
    "iso:country":"DE",
    "sg:address":"Horbacher Str. 59",
    "sg:city":"Aachen",
    "sg:phone":"+49 241/175535",
    "sg:postcode":"52072",
    "sg:province":"Nordrhein-Westfalen",
    "wof:name":"Mad Media Advertising Developments Gmbh",
    "wof:placetype":"venue"
},
  "geometry": {"coordinates":[6.0583291054,50.8152656555],"type":"Point"}
}