{
  "type": "Feature",
  "properties": {
    "iso:country":"DE",
    "sg:address":"Hauptstr. 25",
    "sg:city":"Dahlen",
    "sg:phone":"+49 34361/51677",
    "sg:postcode":"04774",
    "sg:province":"Sachsen",
    "wof:name":"M. Leopold",
    "wof:placetype":"venue"
},
  "geometry": {"coordinates":[12.938076973,51.4044532776],"type":"Point"}
}