{
  "type": "Feature",
  "properties": {
    "iso:country":"DE",
    "sg:address":"Lustnauer Str 78",
    "sg:city":"Kusterdingen",
    "sg:phone":"+49 7071/1560",
    "sg:postcode":"72127",
    "sg:province":"Baden-W\u00fcrttemberg",
    "wof:name":"Die Wortwerkstatt Gmbh",
    "wof:placetype":"venue"
},
  "geometry": {"coordinates":[9.109975,48.519356],"type":"Point"}
}