{
  "type": "Feature",
  "properties": {
    "iso:country":"DE",
    "sg:address":"Dorfstr. 3a",
    "sg:city":"Kritzow",
    "sg:phone":"+49 3841/283844",
    "sg:postcode":"23970",
    "sg:province":"Mecklenburg-Vorpommern",
    "wof:name":"Windenergiepark Kritzow Gmbh",
    "wof:placetype":"venue"
},
  "geometry": {"coordinates":[-78.186058,36.74445],"type":"Point"}
}