{
  "type": "Feature",
  "properties": {
    "iso:country":"DE",
    "sg:address":"Friedrich-List-Str. 38",
    "sg:city":"Leinfelden-Echterdingen",
    "sg:postcode":"70771",
    "sg:province":"Baden-W\u00fcrttemberg",
    "wof:name":"Duplex Systemhaus Gmbh",
    "wof:placetype":"venue"
},
  "geometry": {"coordinates":[9.160351,48.695969],"type":"Point"}
}