{
  "type": "Feature",
  "properties": {
    "iso:country":"DE",
    "sg:address":"Brandstwiete 4",
    "sg:city":"Hamburg",
    "sg:phone":"+49 40/30380869",
    "sg:postcode":"20457",
    "sg:province":"Hamburg",
    "wof:name":"Hildegard Cramer Rechtsanw\u00e4ltin",
    "wof:placetype":"venue"
},
  "geometry": {"coordinates":[9.9966287613,53.5478210449],"type":"Point"}
}