{
  "type": "Feature",
  "properties": {
    "iso:country":"DE",
    "sg:address":"Hauptstr. 48",
    "sg:city":"Deggendorf",
    "sg:phone":"+49 991/5192",
    "sg:postcode":"94469",
    "sg:province":"Bayern",
    "wof:name":"A. Gevelhoff",
    "wof:placetype":"venue"
},
  "geometry": {"coordinates":[12.947062,48.822395],"type":"Point"}
}