{
  "type": "Feature",
  "properties": {
    "iso:country":"DE",
    "sg:address":"Goethestr. 6",
    "sg:city":"Illerkirchberg",
    "sg:phone":"+49 7346/2104",
    "sg:postcode":"89171",
    "sg:province":"Baden-W\u00fcrttemberg",
    "wof:name":"Otto Matheis",
    "wof:placetype":"venue"
},
  "geometry": {"coordinates":[10.0184583664,48.3240585327],"type":"Point"}
}