{
  "type": "Feature",
  "properties": {
    "iso:country":"DE",
    "sg:address":"Heinrich-Heine-Str. 1",
    "sg:city":"Ochtendung",
    "sg:phone":"+49 2625/957375",
    "sg:postcode":"56299",
    "sg:province":"Rheinland-Pfalz",
    "wof:name":"S\u00f6hn Technical Assistance Gmbh",
    "wof:placetype":"venue"
},
  "geometry": {"coordinates":[7.391011,50.352028],"type":"Point"}
}