{
  "type": "Feature",
  "properties": {
    "iso:country":"DE",
    "sg:address":"Maybachstr 2",
    "sg:city":"Frickenhausen",
    "sg:phone":"+49 7022/9480",
    "sg:postcode":"72636",
    "sg:province":"Baden-W\u00fcrttemberg",
    "wof:name":"Greiner Bio - One Gmbh",
    "wof:placetype":"venue"
},
  "geometry": {"coordinates":[9.357022,48.599564],"type":"Point"}
}