{
  "type": "Feature",
  "properties": {
    "iso:country":"DE",
    "sg:address":"Sternkamp 1",
    "sg:city":"M\u00fcnster",
    "sg:phone":"+49 2501/441875",
    "sg:postcode":"48165",
    "sg:province":"Nordrhein-Westfalen",
    "wof:name":"Chan Gmbh",
    "wof:placetype":"venue"
},
  "geometry": {"coordinates":[7.622351,51.896507],"type":"Point"}
}