{
  "type": "Feature",
  "properties": {
    "iso:country":"DE",
    "sg:address":"Am Querschlag 6",
    "sg:city":"Friedrichsthal",
    "sg:phone":"+49 6897/8190020",
    "sg:postcode":"66299",
    "sg:province":"Saarland",
    "wof:name":"Hs Bautr\u00e4ger Gmbh",
    "wof:placetype":"venue"
},
  "geometry": {"coordinates":[7.096192,49.327351],"type":"Point"}
}