{
  "type": "Feature",
  "properties": {
    "iso:country":"DE",
    "sg:address":"Pallaswiesenstr. 152",
    "sg:city":"Darmstadt",
    "sg:phone":"+49 6151/25152",
    "sg:postcode":"64293",
    "sg:province":"Hessen",
    "wof:name":"Pizzeria Victoria",
    "wof:placetype":"venue"
},
  "geometry": {"coordinates":[8.6354675293,49.8835716248],"type":"Point"}
}