{
  "type": "Feature",
  "properties": {
    "iso:country":"DE",
    "sg:address":"Holsterhauser Str. 57",
    "sg:city":"Essen",
    "sg:postcode":"45147",
    "sg:province":"Nordrhein-Westfalen",
    "wof:name":"Daheim Und Drin",
    "wof:placetype":"venue"
},
  "geometry": {"coordinates":[6.996965,51.441204],"type":"Point"}
}