{
  "type": "Feature",
  "properties": {
    "iso:country":"DE",
    "sg:address":"Riegelstr. 5",
    "sg:city":"Emsdetten",
    "sg:phone":"+49 2572/5107",
    "sg:postcode":"48282",
    "sg:province":"Nordrhein-Westfalen",
    "wof:name":"K & K Markt Klaas & Klock",
    "wof:placetype":"venue"
},
  "geometry": {"coordinates":[7.514318943,52.1725158691],"type":"Point"}
}