{
  "type": "Feature",
  "properties": {
    "iso:country":"DE",
    "sg:address":"Claude-Dornier-Str. 15",
    "sg:city":"Ostfildern",
    "sg:postcode":"73760",
    "sg:province":"Baden-W\u00fcrttemberg",
    "wof:name":"Distro Gmbh",
    "wof:placetype":"venue"
},
  "geometry": {"coordinates":[9.2511882782,48.7294197083],"type":"Point"}
}