{
  "type": "Feature",
  "properties": {
    "iso:country":"DE",
    "sg:address":"Ringstr. 14",
    "sg:city":"Alpen",
    "sg:phone":"+49 2802/2708",
    "sg:postcode":"46519",
    "sg:province":"Nordrhein-Westfalen",
    "wof:name":"E. Stolck",
    "wof:placetype":"venue"
},
  "geometry": {"coordinates":[6.53324,51.61586],"type":"Point"}
}