{
  "type": "Feature",
  "properties": {
    "iso:country":"DE",
    "sg:address":"Ganzhornstr. 28",
    "sg:city":"Ochsenfurt",
    "sg:phone":"+49 9331/2826",
    "sg:postcode":"97199",
    "sg:province":"Bayern",
    "wof:name":"Georg Schild Grabdenkm\u00e4ler",
    "wof:placetype":"venue"
},
  "geometry": {"coordinates":[10.0870847702,49.6645431519],"type":"Point"}
}