{
  "type": "Feature",
  "properties": {
    "iso:country":"DE",
    "sg:address":"Stadtplatz 21",
    "sg:city":"Eggenfelden",
    "sg:phone":"+49 8721/3123",
    "sg:postcode":"84307",
    "sg:province":"Bayern",
    "wof:name":"Alois Heiss Kg",
    "wof:placetype":"venue"
},
  "geometry": {"coordinates":[12.7629289627,48.4030036926],"type":"Point"}
}