{
  "type": "Feature",
  "properties": {
    "iso:country":"DE",
    "sg:address":"Lindenstr. 65",
    "sg:city":"L\u00fcbz",
    "sg:phone":"+49 38731/23382",
    "sg:postcode":"19386",
    "sg:province":"Mecklenburg-Vorpommern",
    "wof:name":"Thomas Grube",
    "wof:placetype":"venue"
},
  "geometry": {"coordinates":[12.0187225342,53.4652824402],"type":"Point"}
}