{
  "type": "Feature",
  "properties": {
    "iso:country":"DE",
    "sg:city":"Bad Camberg",
    "sg:postcode":"65520",
    "sg:province":"Hessen",
    "wof:name":"Tmp Team Innovationsberatung & Produktentwicklung",
    "wof:placetype":"venue"
},
  "geometry": {"coordinates":[8.26848,50.296871],"type":"Point"}
}