{
  "type": "Feature",
  "properties": {
    "iso:country":"DE",
    "sg:address":"Karolingerstr. 14",
    "sg:city":"D\u00fcsseldorf",
    "sg:phone":"+49 211/331984",
    "sg:postcode":"40223",
    "sg:province":"Nordrhein-Westfalen",
    "wof:name":"Wilhelm Spinrad",
    "wof:placetype":"venue"
},
  "geometry": {"coordinates":[6.7684512138,51.2070617676],"type":"Point"}
}