{
  "type": "Feature",
  "properties": {
    "iso:country":"DE",
    "sg:address":"Langheimer Str. 14",
    "sg:city":"Altenkunstadt",
    "sg:postcode":"96264",
    "sg:province":"Bayern",
    "wof:name":"Leikeim Verwaltungs- Gmbh",
    "wof:placetype":"venue"
},
  "geometry": {"coordinates":[11.2468700409,50.1246833801],"type":"Point"}
}