{
  "type": "Feature",
  "properties": {
    "iso:country":"DE",
    "sg:address":"Holzstr. 171",
    "sg:city":"Castrop-Rauxel",
    "sg:phone":"+49 2305/3050",
    "sg:postcode":"44575",
    "sg:province":"Nordrhein-Westfalen",
    "wof:name":"Geros Gesellschaft F\u00fcr Seniorenbetreuung Mbh",
    "wof:placetype":"venue"
},
  "geometry": {"coordinates":[7.302312,51.560314],"type":"Point"}
}