{
  "type": "Feature",
  "properties": {
    "iso:country":"DE",
    "sg:address":"Gumbertstr. 145",
    "sg:city":"D\u00fcsseldorf",
    "sg:phone":"+49 211/225499",
    "sg:postcode":"40229",
    "sg:province":"Nordrhein-Westfalen",
    "wof:name":"Rudis Reste Rampe",
    "wof:placetype":"venue"
},
  "geometry": {"coordinates":[6.839889,51.201092],"type":"Point"}
}