{
  "type": "Feature",
  "properties": {
    "iso:country":"DE",
    "sg:address":"Hauptstr. 25",
    "sg:city":"Hohenwarth",
    "sg:phone":"+49 9946/905005",
    "sg:postcode":"93480",
    "sg:province":"Bayern",
    "wof:name":"Edmund Dachs",
    "wof:placetype":"venue"
},
  "geometry": {"coordinates":[12.9371452332,49.2040596008],"type":"Point"}
}