{
  "type": "Feature",
  "properties": {
    "iso:country":"DE",
    "sg:address":"Taunustor 2",
    "sg:city":"Frankfurt",
    "sg:phone":"+49 4969/272820",
    "sg:postcode":"60311",
    "sg:province":"Hessen",
    "wof:name":"Mizuho Corporate Bank Germany Ag",
    "wof:placetype":"venue"
},
  "geometry": {"coordinates":[8.672673,50.111172],"type":"Point"}
}