{
  "type": "Feature",
  "properties": {
    "iso:country":"DE",
    "sg:address":"Kohlhauweg 16",
    "sg:city":"Murrhardt",
    "sg:phone":"+49 7192/3431",
    "sg:postcode":"71540",
    "sg:province":"Baden-W\u00fcrttemberg",
    "wof:name":"H. Thier",
    "wof:placetype":"venue"
},
  "geometry": {"coordinates":[9.5958271027,48.9949417114],"type":"Point"}
}