{
  "type": "Feature",
  "properties": {
    "iso:country":"DE",
    "sg:address":"Birlinghovener Str. 3",
    "sg:city":"K\u00f6nigswinter",
    "sg:phone":"+49 2244/3336",
    "sg:postcode":"53639",
    "sg:province":"Nordrhein-Westfalen",
    "wof:name":"W. Fu\u00dfh\u00f6ller",
    "wof:placetype":"venue"
},
  "geometry": {"coordinates":[7.218386,50.731026],"type":"Point"}
}