{
  "type": "Feature",
  "properties": {
    "iso:country":"DE",
    "sg:address":"Kirchstr. 6",
    "sg:city":"G\u00f6rwihl",
    "sg:phone":"+49 7754/237",
    "sg:postcode":"79733",
    "sg:province":"Baden-W\u00fcrttemberg",
    "wof:name":"Kath. \u00d6ffentliche Bibliothek St. Bartholom\u00e4us",
    "wof:placetype":"venue"
},
  "geometry": {"coordinates":[8.081372,47.640789],"type":"Point"}
}