{
  "type": "Feature",
  "properties": {
    "iso:country":"DE",
    "sg:address":"Alter Henkhauser Weg 4d",
    "sg:city":"Hagen",
    "sg:phone":"+49 2334/51973",
    "sg:postcode":"58119",
    "sg:province":"Nordrhein-Westfalen",
    "wof:name":"Wilhelm Sch\u00e4fers",
    "wof:placetype":"venue"
},
  "geometry": {"coordinates":[7.5624408722,51.3713111877],"type":"Point"}
}