{
  "type": "Feature",
  "properties": {
    "iso:country":"DE",
    "sg:address":"Ellerneck 58",
    "sg:city":"Hamburg",
    "sg:phone":"+49 40/6733983",
    "sg:postcode":"22149",
    "sg:province":"Hamburg",
    "wof:name":"Restaurant Bacchus",
    "wof:placetype":"venue"
},
  "geometry": {"coordinates":[10.1452293396,53.5913581848],"type":"Point"}
}