{
  "type": "Feature",
  "properties": {
    "iso:country":"DE",
    "sg:address":"Kastanienallee 2",
    "sg:city":"T\u00f6nisvorst",
    "sg:phone":"+49 2151/994470",
    "sg:postcode":"47918",
    "sg:province":"Nordrhein-Westfalen",
    "wof:name":"Horst Radeloff Ingenieur",
    "wof:placetype":"venue"
},
  "geometry": {"coordinates":[6.4907121658,51.3132133484],"type":"Point"}
}