{
  "type": "Feature",
  "properties": {
    "iso:country":"DE",
    "sg:address":"Distelrather Str. 2",
    "sg:city":"D\u00fcren",
    "sg:phone":"+49 2421/93770",
    "sg:postcode":"52351",
    "sg:province":"Nordrhein-Westfalen",
    "wof:name":"Hausger\u00e4te Und Servicecenter Frings & Gehlen & Co. Ohg",
    "wof:placetype":"venue"
},
  "geometry": {"coordinates":[6.5061497688,50.8152809143],"type":"Point"}
}