{
  "type": "Feature",
  "properties": {
    "iso:country":"DE",
    "sg:address":"Fassinstr. 6",
    "sg:city":"Aachen",
    "sg:phone":"+49 241/505007",
    "sg:postcode":"52072",
    "sg:province":"Nordrhein-Westfalen",
    "wof:name":"Rolf Zimmermann Heizungsbau Gmbh",
    "wof:placetype":"venue"
},
  "geometry": {"coordinates":[6.0602312088,50.8146247864],"type":"Point"}
}