{
  "type": "Feature",
  "properties": {
    "iso:country":"DE",
    "sg:address":"Sachswitzer Str",
    "sg:city":"Elsterberg",
    "sg:phone":"+49 36621/20350",
    "sg:postcode":"07985",
    "sg:province":"Th\u00fcringen",
    "wof:name":"Gws Werkzeuge Und Sonderfertigung Gmbh",
    "wof:placetype":"venue"
},
  "geometry": {"coordinates":[12.171242,50.615341],"type":"Point"}
}