{
  "type": "Feature",
  "properties": {
    "iso:country":"DE",
    "sg:address":"54612",
    "sg:city":"Lasel",
    "sg:phone":"+49 6553/2215",
    "sg:postcode":"54612",
    "sg:province":"Rheinland-Pfalz",
    "wof:name":"Zur Post",
    "wof:placetype":"venue"
},
  "geometry": {"coordinates":[6.4680070877,50.1129837036],"type":"Point"}
}