{
  "type": "Feature",
  "properties": {
    "iso:country":"DE",
    "sg:address":"Markt 12",
    "sg:city":"Usedom",
    "sg:phone":"+49 38372/70266",
    "sg:postcode":"17406",
    "sg:province":"Mecklenburg-Vorpommern",
    "wof:name":"Hotel Norddeutscher Hof",
    "wof:placetype":"venue"
},
  "geometry": {"coordinates":[13.9196796417,53.8721809387],"type":"Point"}
}