{
  "type": "Feature",
  "properties": {
    "iso:country":"DE",
    "sg:address":"Gewerbering 4",
    "sg:city":"Karlsruhe",
    "sg:phone":"+49 721/97790",
    "sg:postcode":"76149",
    "sg:province":"Baden-W\u00fcrttemberg",
    "wof:name":"Buchen Umweltservice Gmbh",
    "wof:placetype":"venue"
},
  "geometry": {"coordinates":[8.381867,49.058048],"type":"Point"}
}