{
  "type": "Feature",
  "properties": {
    "iso:country":"DE",
    "sg:address":"Markt 34",
    "sg:city":"Geldern",
    "sg:phone":"+49 2831/5827",
    "sg:postcode":"47608",
    "sg:province":"Nordrhein-Westfalen",
    "wof:name":"Stadtcafe Biesenbach",
    "wof:placetype":"venue"
},
  "geometry": {"coordinates":[6.3220119476,51.5168876648],"type":"Point"}
}