{
  "type": "Feature",
  "properties": {
    "iso:country":"DE",
    "sg:address":"Hegemerstr. 11",
    "sg:city":"Ascheberg",
    "sg:phone":"+49 2593/246",
    "sg:postcode":"59387",
    "sg:province":"Nordrhein-Westfalen",
    "wof:name":"Leo Geismann",
    "wof:placetype":"venue"
},
  "geometry": {"coordinates":[7.61059,51.770626],"type":"Point"}
}