{
  "type": "Feature",
  "properties": {
    "iso:country":"DE",
    "sg:address":"Ecksweg 2a",
    "sg:city":"Dassendorf",
    "sg:phone":"+49 40/6482272",
    "sg:postcode":"21521",
    "sg:province":"Schleswig-Holstein",
    "wof:name":"Plath & Kloppmann Transport Ohg",
    "wof:placetype":"venue"
},
  "geometry": {"coordinates":[10.3528280258,53.4999885559],"type":"Point"}
}