{
  "type": "Feature",
  "properties": {
    "iso:country":"DE",
    "sg:address":"Am Wetterschacht 17a",
    "sg:city":"L\u00fcnen",
    "sg:phone":"+49 2306/965495",
    "sg:postcode":"44534",
    "sg:province":"Nordrhein-Westfalen",
    "wof:name":"Menges Lufttechnik Gmbh",
    "wof:placetype":"venue"
},
  "geometry": {"coordinates":[7.503277,51.63324],"type":"Point"}
}