{
  "type": "Feature",
  "properties": {
    "iso:country":"DE",
    "sg:address":"R\u00f6nnelstr. 24",
    "sg:city":"Brake",
    "sg:phone":"+49 4401/5515",
    "sg:postcode":"26919",
    "sg:province":"Niedersachsen",
    "wof:name":"Ev. Pfarramt Ii Brake",
    "wof:placetype":"venue"
},
  "geometry": {"coordinates":[8.4743452072,53.3271751404],"type":"Point"}
}