{
  "type": "Feature",
  "properties": {
    "iso:country":"DE",
    "sg:city":"M\u00fcnchen",
    "sg:postcode":"81927",
    "sg:province":"Bayern",
    "wof:name":"Prosol It",
    "wof:placetype":"venue"
},
  "geometry": {"coordinates":[11.643815,48.167061],"type":"Point"}
}