{
  "type": "Feature",
  "properties": {
    "iso:country":"DE",
    "sg:address":"Karlstr. 33",
    "sg:city":"Eisenach",
    "sg:phone":"+49 3691/216753",
    "sg:postcode":"99817",
    "sg:province":"Th\u00fcringen",
    "wof:name":"Hans-peter Dehnhardt",
    "wof:placetype":"venue"
},
  "geometry": {"coordinates":[10.32256,50.975147],"type":"Point"}
}