{
  "type": "Feature",
  "properties": {
    "iso:country":"DE",
    "sg:address":"Seibersdorfer Str. 4",
    "sg:city":"Kirchdorf",
    "sg:phone":"+49 8571/915550",
    "sg:postcode":"84375",
    "sg:province":"Bayern",
    "wof:name":"St. Josef Altenheim",
    "wof:placetype":"venue"
},
  "geometry": {"coordinates":[12.974566,48.239933],"type":"Point"}
}