{
  "type": "Feature",
  "properties": {
    "iso:country":"DE",
    "sg:address":"Ludwigshafener Strasse 23",
    "sg:city":"D\u00fcsseldorf",
    "sg:phone":"+49 211/2612531",
    "sg:postcode":"40229",
    "sg:province":"Nordrhein-Westfalen",
    "wof:name":"Webdesigne-germany.de.vu",
    "wof:placetype":"venue"
},
  "geometry": {"coordinates":[6.830833,51.204098],"type":"Point"}
}