{
  "type": "Feature",
  "properties": {
    "iso:country":"DE",
    "sg:address":"Industriestr 5",
    "sg:city":"Rugendorf",
    "sg:phone":"+49 9223/9750",
    "sg:postcode":"95365",
    "sg:province":"Bayern",
    "wof:name":"Spedition Schmidt-hofmann Gmbh & Co Kg",
    "wof:placetype":"venue"
},
  "geometry": {"coordinates":[11.46301,50.203228],"type":"Point"}
}