{
  "type": "Feature",
  "properties": {
    "iso:country":"DE",
    "sg:address":"Friedrichsplatz 2",
    "sg:city":"Brochsal",
    "sg:phone":"+49 4972/51770",
    "sg:postcode":"76646",
    "sg:province":"Baden-W\u00fcrttemberg",
    "wof:name":"Sparkasse Kraichgau",
    "wof:placetype":"venue"
},
  "geometry": {"coordinates":[8.59561,49.124695],"type":"Point"}
}