{
  "type": "Feature",
  "properties": {
    "iso:country":"DE",
    "sg:address":"Kirnerstr. 6",
    "sg:city":"Sien",
    "sg:phone":"+49 4967/8897970",
    "sg:postcode":"55758",
    "sg:province":"Rheinland-Pfalz",
    "wof:name":"Otto Jung Bauunternehmung Gmbh & Cokg",
    "wof:placetype":"venue"
},
  "geometry": {"coordinates":[7.506453,49.696106],"type":"Point"}
}