{
  "type": "Feature",
  "properties": {
    "iso:country":"DE",
    "sg:address":"Hauptstr. 87",
    "sg:city":"Niederkr\u00fcchten",
    "sg:phone":"+49 2163/8518",
    "sg:postcode":"41372",
    "sg:province":"Nordrhein-Westfalen",
    "wof:name":"Andreas Grollik",
    "wof:placetype":"venue"
},
  "geometry": {"coordinates":[6.158909,51.209488],"type":"Point"}
}