{
  "type": "Feature",
  "properties": {
    "iso:country":"DE",
    "sg:address":"Emsstr. 34",
    "sg:city":"Emsdetten",
    "sg:phone":"+49 2572/960520",
    "sg:postcode":"48282",
    "sg:province":"Nordrhein-Westfalen",
    "wof:name":"Lauscher-beermann Treuhand Gmbh",
    "wof:placetype":"venue"
},
  "geometry": {"coordinates":[7.5286698341,52.1754417419],"type":"Point"}
}