{
  "type": "Feature",
  "properties": {
    "iso:country":"DE",
    "sg:address":"Passauer Str. 7",
    "sg:city":"Regensburg",
    "sg:phone":"+49 941/604060",
    "sg:postcode":"93055",
    "sg:province":"Bayern",
    "wof:name":"Muk K\u00fchlhaus Gmbh",
    "wof:placetype":"venue"
},
  "geometry": {"coordinates":[12.16936,49.009903],"type":"Point"}
}