{
  "type": "Feature",
  "properties": {
    "iso:country":"DE",
    "sg:address":"Gartenstr. 14",
    "sg:city":"Otterbach",
    "sg:postcode":"67731",
    "sg:province":"Rheinland-Pfalz",
    "wof:name":"Evangelisches Pfarramt Otterbach",
    "wof:placetype":"venue"
},
  "geometry": {"coordinates":[7.7331252098,49.4871635437],"type":"Point"}
}