{
  "type": "Feature",
  "properties": {
    "iso:country":"DE",
    "sg:address":"Oststr. 9",
    "sg:city":"Sinzig",
    "sg:phone":"+49 2642/5457",
    "sg:postcode":"53489",
    "sg:province":"Rheinland-Pfalz",
    "wof:name":"Rudolf Schuld",
    "wof:placetype":"venue"
},
  "geometry": {"coordinates":[7.232814,50.536289],"type":"Point"}
}