{
  "type": "Feature",
  "properties": {
    "iso:country":"DE",
    "sg:address":"Lindenstr. 6",
    "sg:city":"Waiblingen",
    "sg:phone":"+49 7151/28514",
    "sg:postcode":"71336",
    "sg:province":"Baden-W\u00fcrttemberg",
    "wof:name":"Automarkt Eisemann Gmbh",
    "wof:placetype":"venue"
},
  "geometry": {"coordinates":[9.3167762756,48.86693573],"type":"Point"}
}