{
  "type": "Feature",
  "properties": {
    "iso:country":"DE",
    "sg:address":"Goetheplatz 17",
    "sg:city":"B\u00f6hlitz-Ehrenberg",
    "sg:phone":"+49 341/4413012",
    "sg:postcode":"04430",
    "wof:name":"A. Freund",
    "wof:placetype":"venue"
},
  "geometry": {"coordinates":[12.288141,51.355637],"type":"Point"}
}