{
  "type": "Feature",
  "properties": {
    "iso:country":"DE",
    "sg:city":"Ertingen",
    "sg:postcode":"88521",
    "sg:province":"Baden-W\u00fcrttemberg",
    "wof:name":"Gerold Jaeggle",
    "wof:placetype":"venue"
},
  "geometry": {"coordinates":[9.463018,48.098927],"type":"Point"}
}