{
  "type": "Feature",
  "properties": {
    "iso:country":"DE",
    "sg:address":"Feldstr. 5",
    "sg:city":"Kevelaer",
    "sg:phone":"+49 2832/3806",
    "sg:postcode":"47625",
    "sg:province":"Nordrhein-Westfalen",
    "wof:name":"Hans K\u00fcppers",
    "wof:placetype":"venue"
},
  "geometry": {"coordinates":[6.2882699966,51.5699615479],"type":"Point"}
}