{
  "type": "Feature",
  "properties": {
    "iso:country":"DE",
    "sg:address":"Hermann-Geisen-Str. 9",
    "sg:city":"H\u00f6hr-Grenzhausen",
    "sg:phone":"+49 2624/2447",
    "sg:postcode":"56203",
    "sg:province":"Rheinland-Pfalz",
    "wof:name":"H. Menningen",
    "wof:placetype":"venue"
},
  "geometry": {"coordinates":[7.6565480232,50.4392127991],"type":"Point"}
}