{
  "type": "Feature",
  "properties": {
    "iso:country":"DE",
    "sg:address":"Breite-Str. 9",
    "sg:city":"Wernigerode",
    "sg:phone":"+49 3943/32781",
    "sg:postcode":"38855",
    "sg:province":"Sachsen-Anhalt",
    "wof:name":"Volksbank Wernigerode Eg",
    "wof:placetype":"venue"
},
  "geometry": {"coordinates":[10.785428,51.833897],"type":"Point"}
}