{
  "type": "Feature",
  "properties": {
    "iso:country":"DE",
    "sg:address":"Kirrlestr. 1",
    "sg:city":"Reutlingen",
    "sg:phone":"+49 7121/622645",
    "sg:postcode":"72768",
    "sg:province":"Baden-W\u00fcrttemberg",
    "wof:name":"Alte Schmiede",
    "wof:placetype":"venue"
},
  "geometry": {"coordinates":[9.2011547089,48.533367157],"type":"Point"}
}