{
  "type": "Feature",
  "properties": {
    "iso:country":"DE",
    "sg:address":"Untere Rodstr. 10",
    "sg:city":"Pforzheim",
    "sg:phone":"+49 7231/21814",
    "sg:postcode":"75173",
    "sg:province":"Baden-W\u00fcrttemberg",
    "wof:name":"Pelz-schickle Inh. I. Ehringer",
    "wof:placetype":"venue"
},
  "geometry": {"coordinates":[8.695804,48.884052],"type":"Point"}
}