{
  "type": "Feature",
  "properties": {
    "iso:country":"DE",
    "sg:address":"Burgstr. 1",
    "sg:city":"Radevormwald",
    "sg:phone":"+49 2195/933308",
    "sg:postcode":"42477",
    "sg:province":"Nordrhein-Westfalen",
    "wof:name":"Bistro Lambada",
    "wof:placetype":"venue"
},
  "geometry": {"coordinates":[7.3558320999,51.2033081055],"type":"Point"}
}