{
  "type": "Feature",
  "properties": {
    "iso:country":"DE",
    "sg:address":"88518",
    "sg:city":"Herbertingen",
    "sg:phone":"+49 7586/367",
    "sg:postcode":"88518",
    "sg:province":"Baden-W\u00fcrttemberg",
    "wof:name":"Deutsche Bahn Ag",
    "wof:placetype":"venue"
},
  "geometry": {"coordinates":[9.4425296783,48.0593299866],"type":"Point"}
}