{
  "type": "Feature",
  "properties": {
    "iso:country":"DE",
    "sg:address":"Mittelstr. 38",
    "sg:city":"Kalletal",
    "sg:phone":"+49 5264/7723",
    "sg:postcode":"32689",
    "sg:province":"Nordrhein-Westfalen",
    "wof:name":"T. Stock",
    "wof:placetype":"venue"
},
  "geometry": {"coordinates":[9.0134906769,52.0831756592],"type":"Point"}
}