{
  "type": "Feature",
  "properties": {
    "iso:country":"DE",
    "sg:address":"Im Tuchscheren",
    "sg:city":"Oberwesel",
    "sg:phone":"+49 6744/7300",
    "sg:postcode":"55430",
    "sg:province":"Rheinland-Pfalz",
    "wof:name":"Stockmanns Gmbh",
    "wof:placetype":"venue"
},
  "geometry": {"coordinates":[7.740655,50.098949],"type":"Point"}
}