{
  "type": "Feature",
  "properties": {
    "iso:country":"DE",
    "sg:address":"Idastr. 11",
    "sg:city":"Ennigerloh",
    "sg:phone":"+49 2524/950200",
    "sg:postcode":"59320",
    "sg:province":"Nordrhein-Westfalen",
    "wof:name":"K.-h. Gottwald",
    "wof:placetype":"venue"
},
  "geometry": {"coordinates":[8.0376710892,51.8353004456],"type":"Point"}
}