{
  "type": "Feature",
  "properties": {
    "iso:country":"DE",
    "sg:address":"Nicolaus-Zech-Str. 30",
    "sg:city":"Coburg",
    "sg:phone":"+49 9561/39855",
    "sg:postcode":"96450",
    "sg:province":"Bayern",
    "wof:name":"E. & H. Schmidt",
    "wof:placetype":"venue"
},
  "geometry": {"coordinates":[10.927666,50.255604],"type":"Point"}
}