{
  "type": "Feature",
  "properties": {
    "iso:country":"DE",
    "sg:address":"Pfarrgasse 3",
    "sg:city":"Sprendlingen",
    "sg:phone":"+49 6701/1410",
    "sg:postcode":"55576",
    "sg:province":"Rheinland-Pfalz",
    "wof:name":"Walter Hoffmann",
    "wof:placetype":"venue"
},
  "geometry": {"coordinates":[7.9858169556,49.8606796265],"type":"Point"}
}