{
  "type": "Feature",
  "properties": {
    "iso:country":"DE",
    "sg:address":"Hauptstr. 148",
    "sg:city":"Hattert",
    "sg:phone":"+49 2662/3151",
    "sg:postcode":"57644",
    "sg:province":"Rheinland-Pfalz",
    "wof:name":"Helmut N\u00f6llgen",
    "wof:placetype":"venue"
},
  "geometry": {"coordinates":[7.761469841,50.6614685059],"type":"Point"}
}