{
  "type": "Feature",
  "properties": {
    "iso:country":"DE",
    "sg:address":"Neershofer Str 123-125",
    "sg:city":"Coburg",
    "sg:phone":"+49 9563/2028",
    "sg:postcode":"96450",
    "sg:province":"Bayern",
    "wof:name":"Denk Keramische Werkst\u00e4tten Kg",
    "wof:placetype":"venue"
},
  "geometry": {"coordinates":[11.04238,50.268475],"type":"Point"}
}