{
  "type": "Feature",
  "properties": {
    "iso:country":"DE",
    "sg:address":"Bahnhofstr. 7",
    "sg:city":"Bruckm\u00fchl",
    "sg:phone":"+49 8062/1279",
    "sg:postcode":"83052",
    "sg:province":"Bayern",
    "wof:name":"Deutsche Bahn Ag",
    "wof:placetype":"venue"
},
  "geometry": {"coordinates":[11.9146232605,47.8812065125],"type":"Point"}
}