{
  "type": "Feature",
  "properties": {
    "iso:country":"DE",
    "sg:address":"Weberstr. 12",
    "sg:city":"Overath",
    "sg:phone":"+49 2206/5765",
    "sg:postcode":"51491",
    "sg:province":"Nordrhein-Westfalen",
    "wof:name":"Autohaus Wei\u00df Gmbh",
    "wof:placetype":"venue"
},
  "geometry": {"coordinates":[7.2777318954,50.9285430908],"type":"Point"}
}