{
  "type": "Feature",
  "properties": {
    "iso:country":"DE",
    "sg:address":"Hallerstr. 40",
    "sg:city":"Hamburg",
    "sg:phone":"+49 40/412931",
    "sg:postcode":"20146",
    "sg:province":"Hamburg",
    "wof:name":"Kg Happy Music Verlag Gmbh & Co.",
    "wof:placetype":"venue"
},
  "geometry": {"coordinates":[9.982517,53.572411],"type":"Point"}
}