{
  "type": "Feature",
  "properties": {
    "iso:country":"DE",
    "sg:address":"Rascheweg 24",
    "sg:city":"Wuppertal",
    "sg:phone":"+49 202/602393",
    "sg:postcode":"42389",
    "sg:province":"Nordrhein-Westfalen",
    "wof:name":"W. Und H. Ebbinghaus",
    "wof:placetype":"venue"
},
  "geometry": {"coordinates":[7.2571668625,51.2721672058],"type":"Point"}
}