{
  "type": "Feature",
  "properties": {
    "iso:country":"DE",
    "sg:address":"Liebensteiner Weg 32",
    "sg:city":"Selb",
    "sg:phone":"+49 9287/3003",
    "sg:postcode":"95100",
    "sg:province":"Bayern",
    "wof:name":"Oliver Schirmer",
    "wof:placetype":"venue"
},
  "geometry": {"coordinates":[12.1532802582,50.1696586609],"type":"Point"}
}