{
  "type": "Feature",
  "properties": {
    "iso:country":"DE",
    "sg:address":"Industriestr 6a",
    "sg:city":"Idar-Oberstein",
    "sg:phone":"+49 6784/7117",
    "sg:postcode":"55743",
    "sg:province":"Rheinland-Pfalz",
    "wof:name":"Aug. Kurt Loch",
    "wof:placetype":"venue"
},
  "geometry": {"coordinates":[7.375652,49.721657],"type":"Point"}
}