{
  "type": "Feature",
  "properties": {
    "iso:country":"DE",
    "sg:address":"Stocken 12",
    "sg:city":"Rottweil",
    "sg:phone":"+49 741/21718",
    "sg:postcode":"78628",
    "sg:province":"Baden-W\u00fcrttemberg",
    "wof:name":"Werner Blust Ingenieur",
    "wof:placetype":"venue"
},
  "geometry": {"coordinates":[8.6232185364,48.140171051],"type":"Point"}
}