{
  "type": "Feature",
  "properties": {
    "iso:country":"DE",
    "sg:address":"L\u00f6rracher Str. 8",
    "sg:city":"Rheinfelden",
    "sg:phone":"+49 7623/4890",
    "sg:postcode":"79618",
    "sg:province":"Baden-W\u00fcrttemberg",
    "wof:name":"Adler",
    "wof:placetype":"venue"
},
  "geometry": {"coordinates":[7.746931076,47.5717544556],"type":"Point"}
}