{
  "type": "Feature",
  "properties": {
    "iso:country":"DE",
    "sg:address":"Stiftsplatz 5",
    "sg:city":"Kaiserslautern",
    "sg:phone":"+49 631/800990",
    "sg:postcode":"67655",
    "sg:province":"Rheinland-Pfalz",
    "wof:name":"Bhw Immobilien Gmbh",
    "wof:placetype":"venue"
},
  "geometry": {"coordinates":[7.7719979286,49.4441795349],"type":"Point"}
}