{
  "type": "Feature",
  "properties": {
    "iso:country":"DE",
    "sg:address":"Hauptstr. 1 B",
    "sg:city":"Stutensee",
    "sg:phone":"+49 7244/74100",
    "sg:postcode":"76297",
    "sg:province":"Baden-W\u00fcrttemberg",
    "wof:name":"Ifm Industrieanlagen Holding Gmbh",
    "wof:placetype":"venue"
},
  "geometry": {"coordinates":[8.4744119644,49.0704803467],"type":"Point"}
}