{
  "type": "Feature",
  "properties": {
    "iso:country":"DE",
    "sg:address":"Reutlinger Str. 16",
    "sg:city":"T\u00fcbingen",
    "sg:phone":"+49 7071/32558",
    "sg:postcode":"72072",
    "sg:province":"Baden-W\u00fcrttemberg",
    "wof:name":"Fritz Kemmler",
    "wof:placetype":"venue"
},
  "geometry": {"coordinates":[9.062073,48.515358],"type":"Point"}
}