{
  "type": "Feature",
  "properties": {
    "iso:country":"DE",
    "sg:address":"Treuener Str. 4",
    "sg:city":"Rodewisch",
    "sg:phone":"+49 3744/33627",
    "sg:postcode":"08228",
    "sg:province":"Sachsen",
    "wof:name":"Harry Hein",
    "wof:placetype":"venue"
},
  "geometry": {"coordinates":[12.392124,50.541553],"type":"Point"}
}