{
  "type": "Feature",
  "properties": {
    "iso:country":"DE",
    "sg:address":"Talweg 9",
    "sg:city":"Freising",
    "sg:postcode":"85354",
    "sg:province":"Bayern",
    "wof:name":"Deka-lms Laser Und Medizin Systeme Vertriebs- Gmbh",
    "wof:placetype":"venue"
},
  "geometry": {"coordinates":[11.723877,48.438271],"type":"Point"}
}