{
  "type": "Feature",
  "properties": {
    "iso:country":"DE",
    "sg:address":"Allee 4",
    "sg:city":"Meisdorf",
    "sg:postcode":"06463",
    "sg:province":"Sachsen-Anhalt",
    "wof:name":"Hotel Thalm\u00fchle Van Der Valk Gmbh",
    "wof:placetype":"venue"
},
  "geometry": {"coordinates":[11.2866096497,51.7040481567],"type":"Point"}
}