{
  "type": "Feature",
  "properties": {
    "iso:country":"DE",
    "sg:address":"Sch\u00f6neggweg 21",
    "sg:city":"Babenhausen",
    "sg:phone":"+49 8333/7388",
    "sg:postcode":"87727",
    "sg:province":"Bayern",
    "wof:name":"Speed Tec Zerspanungstechnik Und Maschinenbau Gmbh",
    "wof:placetype":"venue"
},
  "geometry": {"coordinates":[10.239763,48.147369],"type":"Point"}
}