{
  "type": "Feature",
  "properties": {
    "iso:country":"DE",
    "sg:address":"Am Wasserberg 12",
    "sg:city":"Ruppichteroth",
    "sg:phone":"+49 2295/2449",
    "sg:postcode":"53809",
    "sg:province":"Nordrhein-Westfalen",
    "wof:name":"Contours Usa-konzert- Und Gruppenreisen Gmbh",
    "wof:placetype":"venue"
},
  "geometry": {"coordinates":[7.4788250923,50.847442627],"type":"Point"}
}