{
  "type": "Feature",
  "properties": {
    "iso:country":"DE",
    "sg:address":"Biskirchener Str. 36",
    "sg:city":"Greifenstein",
    "sg:postcode":"35753",
    "sg:province":"Hessen",
    "wof:name":"Kartmann Textilreinigung Gmbh",
    "wof:placetype":"venue"
},
  "geometry": {"coordinates":[8.2922754288,50.5699501038],"type":"Point"}
}