{
  "type": "Feature",
  "properties": {
    "iso:country":"DE",
    "sg:address":"Oehleckerring 2",
    "sg:city":"Hamburg",
    "sg:phone":"+49 40/5314077",
    "sg:postcode":"22419",
    "sg:province":"Hamburg",
    "wof:name":"Dtx Au\u00dfenhandels Gmbh",
    "wof:placetype":"venue"
},
  "geometry": {"coordinates":[10.0035476685,53.6601715088],"type":"Point"}
}