{
  "type": "Feature",
  "properties": {
    "iso:country":"DE",
    "sg:address":"Burgalber Str.",
    "sg:city":"Donsieders",
    "sg:phone":"+49 6333/4100",
    "sg:postcode":"66978",
    "sg:province":"Rheinland-Pfalz",
    "wof:name":"Sv Donsieders Fu\u00dfballverein",
    "wof:placetype":"venue"
},
  "geometry": {"coordinates":[7.6425971985,49.2654571533],"type":"Point"}
}