{
  "type": "Feature",
  "properties": {
    "iso:country":"DE",
    "sg:address":"Unterer Hofanger 8",
    "sg:city":"Kaufbeuren",
    "sg:phone":"+49 8341/2681",
    "sg:postcode":"87600",
    "sg:province":"Bayern",
    "wof:name":"Hermann Leibrecht E.k. Inh. Manfred Feix",
    "wof:placetype":"venue"
},
  "geometry": {"coordinates":[10.613948822,47.8936843872],"type":"Point"}
}