{
  "type": "Feature",
  "properties": {
    "iso:country":"DE",
    "sg:address":"Winthirstr. 20",
    "sg:city":"M\u00fcnchen",
    "sg:phone":"+49 89/1295269",
    "sg:postcode":"80639",
    "sg:province":"Bayern",
    "wof:name":"Alten- Und Pflegeheim Heim F\u00fcr Blinde Frauen",
    "wof:placetype":"venue"
},
  "geometry": {"coordinates":[11.528434,48.155407],"type":"Point"}
}