{
  "type": "Feature",
  "properties": {
    "iso:country":"DE",
    "sg:address":"Marie-Curie-Stra\u00dfe 7",
    "sg:city":"Neum\u00fcnster",
    "sg:phone":"+49 4321",
    "sg:postcode":"24537",
    "sg:province":"Schleswig-Holstein",
    "wof:name":"Bvm-immobilien",
    "wof:placetype":"venue"
},
  "geometry": {"coordinates":[9.9653568268,54.1044654846],"type":"Point"}
}