{
  "type": "Feature",
  "properties": {
    "iso:country":"DE",
    "sg:address":"Talstr. 33",
    "sg:city":"Glauchau",
    "sg:phone":"+49 3763/50880",
    "sg:postcode":"08371",
    "sg:province":"Sachsen",
    "wof:name":"Dr. M. Bormann Immobilienmakler",
    "wof:placetype":"venue"
},
  "geometry": {"coordinates":[12.5518360138,50.8223304749],"type":"Point"}
}