{
  "type": "Feature",
  "properties": {
    "iso:country":"DE",
    "sg:address":"Marktplatz 14",
    "sg:city":"Baunatal",
    "sg:phone":"+49 561/492499",
    "sg:postcode":"34225",
    "sg:province":"Hessen",
    "wof:name":"Stadthallen-restaurant",
    "wof:placetype":"venue"
},
  "geometry": {"coordinates":[9.4130840302,51.2550582886],"type":"Point"}
}