{
  "type": "Feature",
  "properties": {
    "iso:country":"DE",
    "sg:address":"Zand 2a",
    "sg:city":"Straelen",
    "sg:phone":"+49 2834/2110",
    "sg:postcode":"47638",
    "sg:province":"Nordrhein-Westfalen",
    "wof:name":"Wolfgang Maraczek",
    "wof:placetype":"venue"
},
  "geometry": {"coordinates":[6.268681,51.435257],"type":"Point"}
}