{
  "type": "Feature",
  "properties": {
    "iso:country":"DE",
    "sg:address":"Mittweidaer Str. 56",
    "sg:city":"Taura",
    "sg:phone":"+49 3724/15723",
    "sg:postcode":"09249",
    "sg:province":"Sachsen",
    "wof:name":"Bellevue",
    "wof:placetype":"venue"
},
  "geometry": {"coordinates":[12.8419904709,50.9205856323],"type":"Point"}
}