{
  "type": "Feature",
  "properties": {
    "iso:country":"DE",
    "sg:address":"Ortsstr. 110",
    "sg:city":"Liebengr\u00fcn",
    "sg:phone":"+49 36640/22362",
    "sg:postcode":"07368",
    "sg:province":"Th\u00fcringen",
    "wof:name":"Charles Triebner Gmbh",
    "wof:placetype":"venue"
},
  "geometry": {"coordinates":[11.6028175354,50.5349655151],"type":"Point"}
}