{
  "type": "Feature",
  "properties": {
    "iso:country":"DE",
    "sg:address":"Bahnhofstr. 15 a",
    "sg:city":"Roth",
    "sg:phone":"+49 9171/7663",
    "sg:postcode":"91154",
    "sg:province":"Bayern",
    "wof:name":"Helmut Stotz",
    "wof:placetype":"venue"
},
  "geometry": {"coordinates":[11.088642,49.247169],"type":"Point"}
}