{
  "type": "Feature",
  "properties": {
    "iso:country":"DE",
    "sg:address":"Heinrich-Delp-Str. 21",
    "sg:city":"Darmstadt",
    "sg:phone":"+49 6151/94185",
    "sg:postcode":"64297",
    "sg:province":"Hessen",
    "wof:name":"Hofmann & Alting Bau-fachhandel Gmbh & Co. Kg",
    "wof:placetype":"venue"
},
  "geometry": {"coordinates":[8.64842,49.819679],"type":"Point"}
}