{
  "type": "Feature",
  "properties": {
    "iso:country":"DE",
    "sg:address":"Gaustr. 40",
    "sg:city":"Bad D\u00fcrkheim",
    "sg:phone":"+49 6322/1708",
    "sg:postcode":"67098",
    "sg:province":"Rheinland-Pfalz",
    "wof:name":"Ferd. J. Bauer Weinanbau",
    "wof:placetype":"venue"
},
  "geometry": {"coordinates":[8.1683521271,49.4573631287],"type":"Point"}
}