{
  "type": "Feature",
  "properties": {
    "iso:country":"DE",
    "sg:address":"Leipziger Str. 10",
    "sg:city":"Hanau",
    "sg:phone":"+49 6181/99720",
    "sg:postcode":"63450",
    "sg:province":"Hessen",
    "wof:name":"Central National Gmbh",
    "wof:placetype":"venue"
},
  "geometry": {"coordinates":[8.9247150421,50.1298446655],"type":"Point"}
}