{
  "type": "Feature",
  "properties": {
    "iso:country":"DE",
    "sg:address":"Gruibinger Str. 43",
    "sg:city":"Boll",
    "sg:phone":"+49 7164/3046",
    "sg:postcode":"73087",
    "sg:province":"Baden-W\u00fcrttemberg",
    "wof:name":"H\u00e4derle Industrie- Vertretungen Gmbh",
    "wof:placetype":"venue"
},
  "geometry": {"coordinates":[9.6118450165,48.6323127747],"type":"Point"}
}