{
  "type": "Feature",
  "properties": {
    "iso:country":"DE",
    "sg:address":"Schulstr. 50 a",
    "sg:city":"Hermsdorf",
    "sg:phone":"+49 36601/40314",
    "sg:postcode":"07629",
    "sg:province":"Th\u00fcringen",
    "wof:name":"Karl Eckhardt",
    "wof:placetype":"venue"
},
  "geometry": {"coordinates":[11.854178,50.893581],"type":"Point"}
}