{
  "type": "Feature",
  "properties": {
    "iso:country":"DE",
    "sg:address":"Am Ziegelbrunn 18",
    "sg:city":"Ha\u00dffurt",
    "sg:phone":"+49 9521/8315",
    "sg:postcode":"97437",
    "sg:province":"Bayern",
    "wof:name":"E. Trommler",
    "wof:placetype":"venue"
},
  "geometry": {"coordinates":[10.515476,50.030239],"type":"Point"}
}