{
  "type": "Feature",
  "properties": {
    "iso:country":"DE",
    "sg:address":"Sensburger Allee 9 c",
    "sg:city":"Berlin",
    "sg:phone":"+49 30/3047158",
    "sg:postcode":"14055",
    "sg:province":"Berlin",
    "wof:name":"Klaus Kasparke",
    "wof:placetype":"venue"
},
  "geometry": {"coordinates":[13.2487440109,52.5113754272],"type":"Point"}
}