{
  "type": "Feature",
  "properties": {
    "iso:country":"DE",
    "sg:address":"Saarbr\u00fcckener Str. 250",
    "sg:city":"Braunschweig",
    "sg:phone":"+49 531/54031",
    "sg:postcode":"38116",
    "sg:province":"Niedersachsen",
    "wof:name":"G\u00fcnter Rausch Inhaber Wolfgang Rausch",
    "wof:placetype":"venue"
},
  "geometry": {"coordinates":[10.4872531891,52.2791290283],"type":"Point"}
}