{
  "type": "Feature",
  "properties": {
    "iso:country":"DE",
    "sg:address":"Grafenauer Str. 2",
    "sg:city":"Hengersberg",
    "sg:phone":"+49 9901/7430",
    "sg:postcode":"94491",
    "sg:province":"Bayern",
    "wof:name":"Gscheidmeier K\u00fcchen-bad- Massivholzstudio E. K.",
    "wof:placetype":"venue"
},
  "geometry": {"coordinates":[13.053428,48.78138],"type":"Point"}
}