{
  "type": "Feature",
  "properties": {
    "iso:country":"DE",
    "sg:address":"M\u00fclheimer Str.",
    "sg:city":"Ratingen",
    "sg:phone":"+49 2102/23930",
    "sg:postcode":"40878",
    "sg:province":"Nordrhein-Westfalen",
    "wof:name":"M\u00e4rchenzoo Blauer-see",
    "wof:placetype":"venue"
},
  "geometry": {"coordinates":[6.854658,51.301891],"type":"Point"}
}