{
  "type": "Feature",
  "properties": {
    "iso:country":"DE",
    "sg:address":"Diepenauer Str. 11",
    "sg:city":"Espelkamp",
    "sg:phone":"+49 5775/505",
    "sg:postcode":"32339",
    "sg:province":"Nordrhein-Westfalen",
    "wof:name":"Campingpark Osterwald",
    "wof:placetype":"venue"
},
  "geometry": {"coordinates":[8.701961,52.390163],"type":"Point"}
}