{
  "type": "Feature",
  "properties": {
    "iso:country":"DE",
    "sg:address":"Ettesterstr. 12",
    "sg:city":"Darmstadt",
    "sg:phone":"+49 6151/371207",
    "sg:postcode":"64291",
    "sg:province":"Hessen",
    "wof:name":"G. Stork",
    "wof:placetype":"venue"
},
  "geometry": {"coordinates":[8.656244278,49.9108734131],"type":"Point"}
}