{
  "type": "Feature",
  "properties": {
    "iso:country":"DE",
    "sg:address":"Lachenstr. 16",
    "sg:city":"Wehr",
    "sg:postcode":"79664",
    "sg:province":"Baden-W\u00fcrttemberg",
    "wof:name":"Geodata Gesellschaft Zur Anwendung Geographischer",
    "wof:placetype":"venue"
},
  "geometry": {"coordinates":[7.89921,47.632095],"type":"Point"}
}