{
  "type": "Feature",
  "properties": {
    "iso:country":"DE",
    "sg:address":"Kerkrader Str. 9",
    "sg:city":"Gie\u00dfen",
    "sg:phone":"+49 641/944660",
    "sg:postcode":"35394",
    "sg:province":"Hessen",
    "wof:name":"Deutscher Verband Unabh\u00e4ngiger Pr\u00fcf-",
    "wof:placetype":"venue"
},
  "geometry": {"coordinates":[8.7284946442,50.5740585327],"type":"Point"}
}