{
  "type": "Feature",
  "properties": {
    "iso:country":"DE",
    "sg:address":"Brandhof 1",
    "sg:city":"Schallstadt",
    "sg:phone":"+49 7664/6490",
    "sg:postcode":"79227",
    "sg:province":"Baden-W\u00fcrttemberg",
    "wof:name":"Wilhelm K\u00f6hler Architekt",
    "wof:placetype":"venue"
},
  "geometry": {"coordinates":[7.760059,47.959785],"type":"Point"}
}