{
  "type": "Feature",
  "properties": {
    "iso:country":"DE",
    "sg:address":"Graftstr. 2",
    "sg:city":"Uslar",
    "sg:phone":"+49 5571/913445",
    "sg:postcode":"37170",
    "sg:province":"Niedersachsen",
    "wof:name":"Richard Kraft",
    "wof:placetype":"venue"
},
  "geometry": {"coordinates":[9.6345396042,51.6590881348],"type":"Point"}
}