{
  "type": "Feature",
  "properties": {
    "iso:country":"DE",
    "sg:address":"Rosellener Weg 1",
    "sg:city":"D\u00fcsseldorf",
    "sg:phone":"+49 211/593377",
    "sg:postcode":"40547",
    "sg:province":"Nordrhein-Westfalen",
    "wof:name":"Karl-walter Roese Architket",
    "wof:placetype":"venue"
},
  "geometry": {"coordinates":[6.727243,51.24213],"type":"Point"}
}