{
  "type": "Feature",
  "properties": {
    "iso:country":"DE",
    "sg:address":"Birkenweg 5",
    "sg:city":"Raubling",
    "sg:phone":"+49 8035/87330",
    "sg:postcode":"83064",
    "sg:province":"Bayern",
    "wof:name":"Medjournal De Interaktive Publishing Gmbh",
    "wof:placetype":"venue"
},
  "geometry": {"coordinates":[12.075959,47.791763],"type":"Point"}
}