{
  "type": "Feature",
  "properties": {
    "iso:country":"DE",
    "sg:address":"An der Ziegelei 2",
    "sg:city":"Radeberg",
    "sg:phone":"+49 3528/445851",
    "sg:postcode":"01454",
    "sg:province":"Sachsen",
    "wof:name":"Florelia Einzelhandels Gmbh",
    "wof:placetype":"venue"
},
  "geometry": {"coordinates":[13.914548,51.130039],"type":"Point"}
}