{
  "type": "Feature",
  "properties": {
    "iso:country":"DE",
    "sg:address":"Am Schwanenplatz 9",
    "sg:city":"Stuttgart",
    "sg:phone":"+49 711/261060",
    "sg:postcode":"70190",
    "sg:province":"Baden-W\u00fcrttemberg",
    "wof:name":"Stuttgarter Mineral-bad Berg Ag",
    "wof:placetype":"venue"
},
  "geometry": {"coordinates":[9.205713,48.796288],"type":"Point"}
}