{
  "type": "Feature",
  "properties": {
    "iso:country":"DE",
    "sg:address":"Im Gewerbepark 49",
    "sg:city":"Regensburg",
    "sg:phone":"+49 941/463110",
    "sg:postcode":"93059",
    "sg:province":"Bayern",
    "wof:name":"Elko Computer Gmbh",
    "wof:placetype":"venue"
},
  "geometry": {"coordinates":[12.131607,49.031265],"type":"Point"}
}