{
  "type": "Feature",
  "properties": {
    "iso:country":"DE",
    "sg:address":"Rotkehlchenweg 9",
    "sg:city":"Viersen",
    "sg:phone":"+49 2162/70121",
    "sg:postcode":"41749",
    "sg:province":"Nordrhein-Westfalen",
    "wof:name":"Heinz Standfu\u00df",
    "wof:placetype":"venue"
},
  "geometry": {"coordinates":[6.36534,51.281136],"type":"Point"}
}