{
  "type": "Feature",
  "properties": {
    "iso:country":"DE",
    "sg:address":"Frischmuthstr. 23",
    "sg:city":"Grevenbroich",
    "sg:phone":"+49 2181/64441",
    "sg:postcode":"41515",
    "sg:province":"Nordrhein-Westfalen",
    "wof:name":"Casa Valeska Wohnaccessoires Und Ver-",
    "wof:placetype":"venue"
},
  "geometry": {"coordinates":[6.5872898102,51.094959259],"type":"Point"}
}