{
  "type": "Feature",
  "properties": {
    "iso:country":"DE",
    "sg:address":"Rotbachstr. 5",
    "sg:city":"Schemmerhofen",
    "sg:phone":"+49 7356/674",
    "sg:postcode":"88433",
    "sg:province":"Baden-W\u00fcrttemberg",
    "wof:name":"Maier Transporte Gmbh",
    "wof:placetype":"venue"
},
  "geometry": {"coordinates":[9.7762155533,48.1991729736],"type":"Point"}
}