{
  "type": "Feature",
  "properties": {
    "iso:country":"DE",
    "sg:address":"Innungsweg 9",
    "sg:city":"Voerde",
    "sg:phone":"+49 2855/92500",
    "sg:postcode":"46562",
    "sg:province":"Nordrhein-Westfalen",
    "wof:name":"Bleul Gmbh",
    "wof:placetype":"venue"
},
  "geometry": {"coordinates":[6.671607,51.618168],"type":"Point"}
}