{
  "type": "Feature",
  "properties": {
    "iso:country":"DE",
    "sg:address":"Rudolf-Diesel-Str. 50",
    "sg:city":"Halberstadt",
    "sg:phone":"+49 3941/320",
    "sg:postcode":"38820",
    "sg:province":"Sachsen-Anhalt",
    "wof:name":"Mbg Maschinenbauer Belegschaftsgesellschaft Ag",
    "wof:placetype":"venue"
},
  "geometry": {"coordinates":[11.063333,51.882427],"type":"Point"}
}