{
  "type": "Feature",
  "properties": {
    "iso:country":"DE",
    "sg:address":"Kr\u00fcckeberg 2",
    "sg:city":"Hessisch Oldendorf",
    "sg:phone":"+49 5152/8751",
    "sg:postcode":"31840",
    "sg:province":"Niedersachsen",
    "wof:name":"Akropolis",
    "wof:placetype":"venue"
},
  "geometry": {"coordinates":[9.2706384659,52.1679573059],"type":"Point"}
}