{
  "type": "Feature",
  "properties": {
    "iso:country":"DE",
    "sg:address":"Alte Schulstr. 5a",
    "sg:city":"Ha\u00dfloch",
    "sg:phone":"+49 6324/4209",
    "sg:postcode":"67454",
    "sg:province":"Rheinland-Pfalz",
    "wof:name":"Manfred Watta Architekt",
    "wof:placetype":"venue"
},
  "geometry": {"coordinates":[8.257796,49.36396],"type":"Point"}
}