{
  "type": "Feature",
  "properties": {
    "iso:country":"DE",
    "sg:address":"Horner Landstr. 205",
    "sg:city":"Hamburg",
    "sg:phone":"+49 40/6519075",
    "sg:postcode":"22111",
    "sg:province":"Hamburg",
    "wof:name":"Edith Trunk",
    "wof:placetype":"venue"
},
  "geometry": {"coordinates":[10.0813531876,53.5493354797],"type":"Point"}
}