{
  "type": "Feature",
  "properties": {
    "iso:country":"DE",
    "sg:address":"Essenberger Str. 218",
    "sg:city":"Duisburg",
    "sg:phone":"+49 203/310633",
    "sg:postcode":"47059",
    "sg:province":"Nordrhein-Westfalen",
    "wof:name":"M. Beba Obst Und Gem\u00fcse",
    "wof:placetype":"venue"
},
  "geometry": {"coordinates":[6.7294487953,51.4325561523],"type":"Point"}
}