{
  "type": "Feature",
  "properties": {
    "iso:country":"DE",
    "sg:address":"Am Anger 1",
    "sg:city":"Bad W\u00f6rishofen",
    "sg:phone":"+49 8247/5816",
    "sg:postcode":"86825",
    "sg:province":"Bayern",
    "wof:name":"Steinberger Und Holzner Ingenieur",
    "wof:placetype":"venue"
},
  "geometry": {"coordinates":[10.5981683731,48.0095481873],"type":"Point"}
}