{
  "type": "Feature",
  "properties": {
    "iso:country":"DE",
    "sg:address":"Robert-Koch-Str. 21",
    "sg:city":"Wolgast",
    "sg:phone":"+49 3836/203484",
    "sg:postcode":"17438",
    "sg:province":"Mecklenburg-Vorpommern",
    "wof:name":"K. K\u00f6pnick",
    "wof:placetype":"venue"
},
  "geometry": {"coordinates":[13.7549324036,54.0540733337],"type":"Point"}
}