{
  "type": "Feature",
  "properties": {
    "iso:country":"DE",
    "sg:address":"Therecker Weg 18",
    "sg:city":"Finnentrop",
    "sg:phone":"+49 2395/91820",
    "sg:postcode":"57413",
    "sg:province":"Nordrhein-Westfalen",
    "wof:name":"Holz Und Raum Gmbh & Co. Kg",
    "wof:placetype":"venue"
},
  "geometry": {"coordinates":[7.95279,51.224346],"type":"Point"}
}