{
  "type": "Feature",
  "properties": {
    "iso:country":"DE",
    "sg:address":"Camburger Str. 74",
    "sg:city":"Jena",
    "sg:postcode":"07743",
    "sg:province":"Th\u00fcringen",
    "wof:name":"Norddeutsche Saat- Und Pflanzgut Ag",
    "wof:placetype":"venue"
},
  "geometry": {"coordinates":[11.609261,50.94891],"type":"Point"}
}