{
  "type": "Feature",
  "properties": {
    "iso:country":"DE",
    "sg:address":"Bahnhofstr. 13",
    "sg:city":"Hatten",
    "sg:phone":"+49 4481/7471",
    "sg:postcode":"26209",
    "sg:province":"Niedersachsen",
    "wof:name":"Phototec Peter L\u00f6ffler Gmbh",
    "wof:placetype":"venue"
},
  "geometry": {"coordinates":[8.2573518753,53.0528793335],"type":"Point"}
}