{
  "type": "Feature",
  "properties": {
    "iso:country":"DE",
    "sg:address":"Poppenrother Str. 17",
    "sg:city":"Bad Kissingen",
    "sg:phone":"+49 9736/9172",
    "sg:postcode":"97688",
    "sg:province":"Bayern",
    "wof:name":"Pfrang Fliesen",
    "wof:placetype":"venue"
},
  "geometry": {"coordinates":[9.9954690933,50.229839325],"type":"Point"}
}