{
  "type": "Feature",
  "properties": {
    "iso:country":"DE",
    "sg:address":"Wellendingerstr 27",
    "sg:city":"Frittlingen",
    "sg:phone":"+49 7426",
    "sg:postcode":"78669",
    "sg:province":"Baden-W\u00fcrttemberg",
    "wof:name":"Pfeiffer-metalltechnologie-metallverarbeitung",
    "wof:placetype":"venue"
},
  "geometry": {"coordinates":[8.701123,48.146961],"type":"Point"}
}