{
  "type": "Feature",
  "properties": {
    "iso:country":"DE",
    "sg:address":"Darmst\u00e4dter Landstr. 10",
    "sg:city":"Frankfurt",
    "sg:postcode":"60594",
    "sg:province":"Hessen",
    "wof:name":"Aldi Gmbh & Co. Kg",
    "wof:placetype":"venue"
},
  "geometry": {"coordinates":[8.6902914047,50.1034317017],"type":"Point"}
}