{
  "type": "Feature",
  "properties": {
    "iso:country":"DE",
    "sg:address":"Comeniusstr. 66",
    "sg:city":"Dresden",
    "sg:phone":"+49 351/4727263",
    "sg:postcode":"01309",
    "sg:province":"Sachsen",
    "wof:name":"Gisela Mund",
    "wof:placetype":"venue"
},
  "geometry": {"coordinates":[13.777723,51.038368],"type":"Point"}
}