{
  "type": "Feature",
  "properties": {
    "iso:country":"DE",
    "sg:address":"Schmiedestr. 4",
    "sg:city":"Neunkirchen-Seelscheid",
    "sg:phone":"+49 2247/3490",
    "sg:postcode":"53819",
    "sg:province":"Nordrhein-Westfalen",
    "wof:name":"Staubach Fliesen Gmbh",
    "wof:placetype":"venue"
},
  "geometry": {"coordinates":[7.3330740929,50.8406257629],"type":"Point"}
}