{
  "type": "Feature",
  "properties": {
    "iso:country":"DE",
    "sg:address":"Ringelohstr. 25",
    "sg:city":"Dortmund",
    "sg:phone":"+49 231/485718",
    "sg:postcode":"44269",
    "sg:province":"Nordrhein-Westfalen",
    "wof:name":"Indutrec Gmbh",
    "wof:placetype":"venue"
},
  "geometry": {"coordinates":[7.542168,51.478821],"type":"Point"}
}