{
  "type": "Feature",
  "properties": {
    "iso:country":"DE",
    "sg:address":"Kirchstr. 1",
    "sg:city":"Sebnitz",
    "sg:phone":"+49 35971/57811",
    "sg:postcode":"01855",
    "sg:province":"Sachsen",
    "wof:name":"R. Martin",
    "wof:placetype":"venue"
},
  "geometry": {"coordinates":[14.2723369598,50.9718818665],"type":"Point"}
}