{
  "type": "Feature",
  "properties": {
    "iso:country":"DE",
    "sg:address":"Tulpenweg 6",
    "sg:city":"Rottenburg",
    "sg:phone":"+49 8781/1447",
    "sg:postcode":"84056",
    "sg:province":"Bayern",
    "wof:name":"Hartmut Zacher",
    "wof:placetype":"venue"
},
  "geometry": {"coordinates":[12.0009384155,48.6907043457],"type":"Point"}
}