{
  "type": "Feature",
  "properties": {
    "iso:country":"DE",
    "sg:address":"Bahnhofstr.67",
    "sg:city":"Nordheim",
    "sg:phone":"+49 7133/960480",
    "sg:postcode":"74226",
    "sg:province":"Baden-W\u00fcrttemberg",
    "wof:name":"Adfc",
    "wof:placetype":"venue"
},
  "geometry": {"coordinates":[9.1426391602,49.1085968018],"type":"Point"}
}