{
  "type": "Feature",
  "properties": {
    "iso:country":"DE",
    "sg:address":"Marktstr. 2",
    "sg:city":"Heuchelheim",
    "sg:phone":"+49 641/61919",
    "sg:postcode":"35452",
    "sg:province":"Hessen",
    "wof:name":"Keytec Elektronische Identifikationssysteme Gmbh",
    "wof:placetype":"venue"
},
  "geometry": {"coordinates":[8.6304330826,50.5827217102],"type":"Point"}
}