{
  "type": "Feature",
  "properties": {
    "iso:country":"DE",
    "sg:address":"Eutiner Str. 120",
    "sg:city":"Techau",
    "sg:postcode":"23689",
    "sg:province":"Schleswig-Holstein",
    "wof:name":"Schick Schnack Warenhandel Joachim Meyer",
    "wof:placetype":"venue"
},
  "geometry": {"coordinates":[10.7181110382,53.9633216858],"type":"Point"}
}