{
  "type": "Feature",
  "properties": {
    "iso:country":"DE",
    "sg:address":"Rudolf-Diesel-Ring 3",
    "sg:city":"Holzkirchen",
    "sg:phone":"+49 8024/49895",
    "sg:postcode":"83607",
    "sg:province":"Bayern",
    "wof:name":"City-billard",
    "wof:placetype":"venue"
},
  "geometry": {"coordinates":[11.7083539963,47.8828926086],"type":"Point"}
}