{
  "type": "Feature",
  "properties": {
    "iso:country":"DE",
    "sg:address":"Hauptstr. 65",
    "sg:city":"Neu-Ulm",
    "sg:phone":"+49 731",
    "sg:postcode":"89233",
    "sg:province":"Bayern",
    "wof:name":"Fahrrad Schmid Neu-ulm/pfuhl",
    "wof:placetype":"venue"
},
  "geometry": {"coordinates":[10.0381040573,48.4096565247],"type":"Point"}
}