{
  "type": "Feature",
  "properties": {
    "iso:country":"DE",
    "sg:address":"Bahnhofstr. 11b",
    "sg:city":"Leichlingen",
    "sg:postcode":"42799",
    "sg:province":"Nordrhein-Westfalen",
    "wof:name":"Gastronomische Betriebe Albatros Gmbh",
    "wof:placetype":"venue"
},
  "geometry": {"coordinates":[7.0101418495,51.1046066284],"type":"Point"}
}