{
  "type": "Feature",
  "properties": {
    "iso:country":"DE",
    "sg:address":"Saubertstr. 2",
    "sg:city":"N\u00fcrnberg",
    "sg:phone":"+49 911/262640",
    "sg:postcode":"90429",
    "sg:province":"Bayern",
    "wof:name":"Karlheinz Badstieber",
    "wof:placetype":"venue"
},
  "geometry": {"coordinates":[11.0565700531,49.4521980286],"type":"Point"}
}