{
  "type": "Feature",
  "properties": {
    "iso:country":"DE",
    "sg:address":"Marktstr. 25 a",
    "sg:city":"Gedern",
    "sg:phone":"+49 6045/7323",
    "sg:postcode":"63688",
    "sg:province":"Hessen",
    "wof:name":"H\u00f6hl & Suckau Bedachungs- Und Abdichtungs Gmbh",
    "wof:placetype":"venue"
},
  "geometry": {"coordinates":[9.202144,50.427639],"type":"Point"}
}