{
  "type": "Feature",
  "properties": {
    "iso:country":"DE",
    "sg:address":"Z\u00f6llners Garten 5",
    "sg:city":"Wedemark",
    "sg:postcode":"30900",
    "sg:province":"Niedersachsen",
    "wof:name":"Bima Bissendorfer Maschinenbau Gmbh",
    "wof:placetype":"venue"
},
  "geometry": {"coordinates":[9.734215,52.514732],"type":"Point"}
}