{
  "type": "Feature",
  "properties": {
    "iso:country":"DE",
    "sg:address":"Edith-Stein-Str. 18",
    "sg:city":"M\u00fchlheim",
    "sg:phone":"+49 6108/990313",
    "sg:postcode":"63165",
    "sg:province":"Hessen",
    "wof:name":"Domizil Immobilien Gmbh",
    "wof:placetype":"venue"
},
  "geometry": {"coordinates":[8.859407,50.099815],"type":"Point"}
}