{
  "type": "Feature",
  "properties": {
    "iso:country":"DE",
    "sg:address":"Freisestr. 27",
    "sg:city":"Braunschweig",
    "sg:postcode":"38118",
    "sg:province":"Niedersachsen",
    "wof:name":"Rhein-arax Deutsch-armenischer Freundschaftsverein E. V.",
    "wof:placetype":"venue"
},
  "geometry": {"coordinates":[10.5099611282,52.2681503296],"type":"Point"}
}