{
  "type": "Feature",
  "properties": {
    "iso:country":"DE",
    "sg:address":"Dorfstr. 19",
    "sg:city":"Gablenz",
    "sg:phone":"+49 3576/200881",
    "sg:postcode":"02953",
    "sg:province":"Sachsen",
    "wof:name":"Am Park",
    "wof:placetype":"venue"
},
  "geometry": {"coordinates":[14.6637353897,51.5343818665],"type":"Point"}
}