{
  "type": "Feature",
  "properties": {
    "iso:country":"DE",
    "sg:address":"Albert-Einstein-Str. 1",
    "sg:city":"B\u00f6nnigheim",
    "sg:phone":"+49 7143/23200",
    "sg:postcode":"74357",
    "sg:province":"Baden-W\u00fcrttemberg",
    "wof:name":"F. Hoffacker Ingenieur",
    "wof:placetype":"venue"
},
  "geometry": {"coordinates":[9.1040468216,49.0364532471],"type":"Point"}
}