{
  "type": "Feature",
  "properties": {
    "iso:country":"DE",
    "sg:address":"Kiebitzweg 2",
    "sg:city":"Neum\u00fcnster",
    "sg:phone":"+49 4321/72616",
    "sg:postcode":"24539",
    "sg:province":"Schleswig-Holstein",
    "wof:name":"Martina Waltersdorf",
    "wof:placetype":"venue"
},
  "geometry": {"coordinates":[10.0097141266,54.0500526428],"type":"Point"}
}