{
  "type": "Feature",
  "properties": {
    "iso:country":"DE",
    "sg:address":"Ablacher Str 14",
    "sg:city":"Sigmaringen",
    "sg:phone":"+49 7571/52099",
    "sg:postcode":"72488",
    "sg:province":"Baden-W\u00fcrttemberg",
    "wof:name":"E.k.f. Gnirss Gmbh & Co Kg",
    "wof:placetype":"venue"
},
  "geometry": {"coordinates":[9.194475,48.073639],"type":"Point"}
}