{
  "type": "Feature",
  "properties": {
    "iso:country":"DE",
    "sg:address":"Nordstr. 2",
    "sg:city":"Marktoberdorf",
    "sg:phone":"+49 8342/96070",
    "sg:postcode":"87616",
    "sg:province":"Bayern",
    "wof:name":"Unglert M\u00f6belschreinerei Innenausbau U. Treppenbau Gmbh",
    "wof:placetype":"venue"
},
  "geometry": {"coordinates":[10.623772,47.794949],"type":"Point"}
}