{
  "type": "Feature",
  "properties": {
    "iso:country":"DE",
    "sg:address":"Staffeler Weg 3",
    "sg:city":"Diez",
    "sg:phone":"+49 6483/6260",
    "sg:postcode":"65582",
    "sg:province":"Rheinland-Pfalz",
    "wof:name":"J\u00fcrgen Kronm\u00fcller",
    "wof:placetype":"venue"
},
  "geometry": {"coordinates":[8.0278406143,50.3732032776],"type":"Point"}
}