{
  "type": "Feature",
  "properties": {
    "iso:country":"DE",
    "sg:address":"Im Wingertsgrund 9",
    "sg:city":"Steinbach",
    "sg:postcode":"61449",
    "sg:province":"Hessen",
    "wof:name":"Joffi Gmbh",
    "wof:placetype":"venue"
},
  "geometry": {"coordinates":[8.5852451324,50.1644477844],"type":"Point"}
}