{
  "type": "Feature",
  "properties": {
    "iso:country":"DE",
    "sg:address":"Miesleuthen 6",
    "sg:city":"Bodenmais",
    "sg:phone":"+49 9924/451",
    "sg:postcode":"94249",
    "sg:province":"Bayern",
    "wof:name":"Haller",
    "wof:placetype":"venue"
},
  "geometry": {"coordinates":[13.1008682251,49.0633277893],"type":"Point"}
}