{
  "type": "Feature",
  "properties": {
    "iso:country":"DE",
    "sg:address":"Otto-Lilienthal-Str. 24",
    "sg:city":"B\u00f6blingen",
    "sg:postcode":"71034",
    "sg:province":"Baden-W\u00fcrttemberg",
    "wof:name":"Topkauf Gmbh & Co.",
    "wof:placetype":"venue"
},
  "geometry": {"coordinates":[8.9830360413,48.684261322],"type":"Point"}
}