{
  "type": "Feature",
  "properties": {
    "iso:country":"DE",
    "sg:address":"Stockfeldstr 5",
    "sg:city":"Herbolzheim",
    "sg:phone":"+49 7643/93360",
    "sg:postcode":"79336",
    "sg:province":"Baden-W\u00fcrttemberg",
    "wof:name":"Afp Hydraulik Gmbh",
    "wof:placetype":"venue"
},
  "geometry": {"coordinates":[7.7646369934,48.2258338928],"type":"Point"}
}