{
  "type": "Feature",
  "properties": {
    "iso:country":"DE",
    "sg:address":"L\u00fcbecker Str. 232",
    "sg:city":"B\u00fcnde",
    "sg:phone":"+49 4952/234774",
    "sg:postcode":"32257",
    "sg:province":"Nordrhein-Westfalen",
    "wof:name":"Wipos Gmbh",
    "wof:placetype":"venue"
},
  "geometry": {"coordinates":[8.614217,52.210762],"type":"Point"}
}