{
  "type": "Feature",
  "properties": {
    "iso:country":"DE",
    "sg:address":"Hackethalstr. 4",
    "sg:city":"Hannover",
    "sg:phone":"+49 511/639993",
    "sg:postcode":"30179",
    "sg:province":"Niedersachsen",
    "wof:name":"Ingra",
    "wof:placetype":"venue"
},
  "geometry": {"coordinates":[9.722595,52.41943],"type":"Point"}
}