{
  "type": "Feature",
  "properties": {
    "iso:country":"DE",
    "sg:address":"Schmiedegasse 3",
    "sg:city":"Leipzig",
    "sg:postcode":"04158",
    "sg:province":"Sachsen",
    "wof:name":"Peter Schmoll & Stefan Kuckuck Gbr",
    "wof:placetype":"venue"
},
  "geometry": {"coordinates":[12.368564,51.395451],"type":"Point"}
}