{
  "type": "Feature",
  "properties": {
    "iso:country":"DE",
    "sg:address":"Netphener Weg 3",
    "sg:city":"Netphen",
    "sg:phone":"+49 2738/8764",
    "sg:postcode":"57250",
    "sg:province":"Nordrhein-Westfalen",
    "wof:name":"Horst Rudolff",
    "wof:placetype":"venue"
},
  "geometry": {"coordinates":[8.1304321289,50.9138412476],"type":"Point"}
}