{
  "type": "Feature",
  "properties": {
    "iso:country":"DE",
    "sg:address":"Werler Str. 37",
    "sg:city":"Arnsberg",
    "sg:phone":"+49 2932/21220",
    "sg:postcode":"59755",
    "sg:province":"Nordrhein-Westfalen",
    "wof:name":"M. Wenner",
    "wof:placetype":"venue"
},
  "geometry": {"coordinates":[7.9647,51.462109],"type":"Point"}
}