{
  "type": "Feature",
  "properties": {
    "iso:country":"DE",
    "sg:address":"Bismarckstr. 231",
    "sg:city":"Wilhelmshaven",
    "sg:phone":"+49 4421/21327",
    "sg:postcode":"26382",
    "sg:province":"Niedersachsen",
    "wof:name":"Gerd Hollje Masseur",
    "wof:placetype":"venue"
},
  "geometry": {"coordinates":[8.097068,53.528809],"type":"Point"}
}