{
  "type": "Feature",
  "properties": {
    "iso:country":"DE",
    "sg:address":"Friedensstr. 13",
    "sg:city":"Altlu\u00dfheim",
    "sg:phone":"+49 6205/31917",
    "sg:postcode":"68804",
    "sg:province":"Baden-W\u00fcrttemberg",
    "wof:name":"Klaus Marker Steuerberater",
    "wof:placetype":"venue"
},
  "geometry": {"coordinates":[8.4998435974,49.2941665649],"type":"Point"}
}