{
  "type": "Feature",
  "properties": {
    "iso:country":"DE",
    "sg:address":"Bugstr. 21",
    "sg:city":"Herbolzheim",
    "sg:phone":"+49 7643/6776",
    "sg:postcode":"79336",
    "sg:province":"Baden-W\u00fcrttemberg",
    "wof:name":"Gustav Maurer Vergn\u00fcgungsst\u00e4tte",
    "wof:placetype":"venue"
},
  "geometry": {"coordinates":[7.766031,48.220692],"type":"Point"}
}