{
  "type": "Feature",
  "properties": {
    "iso:country":"DE",
    "sg:address":"Innere Herlasgr\u00fcner Str. 3",
    "sg:city":"Treuen",
    "sg:phone":"+49 37468/7013",
    "sg:postcode":"08233",
    "sg:province":"Sachsen",
    "wof:name":"Dentaltechnik Treuen Gmbh",
    "wof:placetype":"venue"
},
  "geometry": {"coordinates":[12.301583,50.542599],"type":"Point"}
}