{
  "type": "Feature",
  "properties": {
    "iso:country":"DE",
    "sg:address":"Nordersteinstr. 30",
    "sg:city":"Cuxhaven",
    "sg:phone":"+49 4721/35277",
    "sg:postcode":"27472",
    "sg:province":"Niedersachsen",
    "wof:name":"K. Thiemann",
    "wof:placetype":"venue"
},
  "geometry": {"coordinates":[8.6992778778,53.8617134094],"type":"Point"}
}