{
  "type": "Feature",
  "properties": {
    "iso:country":"DE",
    "sg:address":"Grandweg 17 a",
    "sg:city":"Soest",
    "sg:phone":"+49 2921/2505",
    "sg:postcode":"59494",
    "sg:province":"Nordrhein-Westfalen",
    "wof:name":"Gerhard Dust Buch- Und Offsetdruck",
    "wof:placetype":"venue"
},
  "geometry": {"coordinates":[8.109726,51.570347],"type":"Point"}
}