{
  "type": "Feature",
  "properties": {
    "iso:country":"DE",
    "sg:address":"Kyllstr. 33",
    "sg:city":"Trier",
    "sg:phone":"+49 651/9960100",
    "sg:postcode":"54293",
    "sg:province":"Rheinland-Pfalz",
    "wof:name":"Wolfgang Kickert",
    "wof:placetype":"venue"
},
  "geometry": {"coordinates":[6.6853561401,49.8096046448],"type":"Point"}
}