{
  "type": "Feature",
  "properties": {
    "iso:country":"DE",
    "sg:address":"Schurwaldstr. 44",
    "sg:city":"G\u00f6ppingen",
    "sg:phone":"+49 7161/27211",
    "sg:postcode":"73035",
    "sg:province":"Baden-W\u00fcrttemberg",
    "wof:name":"Ernst Bosch",
    "wof:placetype":"venue"
},
  "geometry": {"coordinates":[9.647165,48.719402],"type":"Point"}
}