{
  "type": "Feature",
  "properties": {
    "iso:country":"DE",
    "sg:address":"Weisinger Str. 46",
    "sg:city":"Lauingen",
    "sg:phone":"+49 9071/4781",
    "sg:postcode":"89415",
    "sg:province":"Bayern",
    "wof:name":"J\u00f6rg Linckh Gmbh",
    "wof:placetype":"venue"
},
  "geometry": {"coordinates":[10.480751,48.541985],"type":"Point"}
}