{
  "type": "Feature",
  "properties": {
    "iso:country":"DE",
    "sg:address":"Bachgasse 11",
    "sg:city":"M\u00f6ssingen",
    "sg:phone":"+49 7473/8452",
    "sg:postcode":"72116",
    "sg:province":"Baden-W\u00fcrttemberg",
    "wof:name":"O. Nill",
    "wof:placetype":"venue"
},
  "geometry": {"coordinates":[9.057111,48.407597],"type":"Point"}
}