{
  "type": "Feature",
  "properties": {
    "iso:country":"DE",
    "sg:address":"Gogrevenstr. 10",
    "sg:city":"Paderborn",
    "sg:phone":"+49 5252/6303",
    "sg:postcode":"33100",
    "sg:province":"Nordrhein-Westfalen",
    "wof:name":"Ernst Wewer",
    "wof:placetype":"venue"
},
  "geometry": {"coordinates":[8.849441,51.744003],"type":"Point"}
}