{
  "type": "Feature",
  "properties": {
    "iso:country":"DE",
    "sg:address":"Marktplatz 9",
    "sg:city":"Grabenst\u00e4tt",
    "sg:phone":"+49 861/60121",
    "sg:postcode":"83355",
    "sg:province":"Bayern",
    "wof:name":"Max Huber",
    "wof:placetype":"venue"
},
  "geometry": {"coordinates":[12.5425815582,47.8429260254],"type":"Point"}
}