{
  "type": "Feature",
  "properties": {
    "iso:country":"DE",
    "sg:address":"Eurener Str. 181",
    "sg:city":"Trier",
    "sg:phone":"+49 651/80807",
    "sg:postcode":"54294",
    "sg:province":"Rheinland-Pfalz",
    "wof:name":"F.-j. Golumbeck",
    "wof:placetype":"venue"
},
  "geometry": {"coordinates":[6.609642,49.740715],"type":"Point"}
}