{
  "type": "Feature",
  "properties": {
    "iso:country":"DE",
    "sg:address":"Balhorn",
    "sg:city":"Bad Emstal",
    "sg:phone":"+49 5625/7411",
    "sg:postcode":"34308",
    "sg:province":"Hessen",
    "wof:name":"Freibad Balhorn",
    "wof:placetype":"venue"
},
  "geometry": {"coordinates":[9.2521209717,51.231174469],"type":"Point"}
}