{
  "type": "Feature",
  "properties": {
    "iso:country":"DE",
    "sg:address":"Fliederweg 2",
    "sg:city":"Burglauer",
    "sg:phone":"+49 9733/9578",
    "sg:postcode":"97724",
    "sg:province":"Bayern",
    "wof:name":"Gustav Fu\u00df E. K.",
    "wof:placetype":"venue"
},
  "geometry": {"coordinates":[10.1762199402,50.2795982361],"type":"Point"}
}