{
  "type": "Feature",
  "properties": {
    "iso:country":"DE",
    "sg:address":"Maier\u00e4ckerstr. 10",
    "sg:city":"Rottenburg",
    "sg:phone":"+49 7472/25507",
    "sg:postcode":"72108",
    "sg:province":"Baden-W\u00fcrttemberg",
    "wof:name":"Gernot Michael Palm Rechtsanwalt",
    "wof:placetype":"venue"
},
  "geometry": {"coordinates":[8.950419426,48.4781799316],"type":"Point"}
}