{
  "type": "Feature",
  "properties": {
    "iso:country":"DE",
    "sg:address":"Halskestr. 7",
    "sg:city":"Berlin",
    "sg:phone":"+49 30/7966488",
    "sg:postcode":"12167",
    "sg:province":"Berlin",
    "wof:name":"D & S Elektroinstallation Gmbh",
    "wof:placetype":"venue"
},
  "geometry": {"coordinates":[13.344618,52.448288],"type":"Point"}
}