{
  "type": "Feature",
  "properties": {
    "iso:country":"DE",
    "sg:address":"Golddistelweg 21",
    "sg:city":"Hamburg",
    "sg:phone":"+49 40/5360534",
    "sg:postcode":"22391",
    "sg:province":"Hamburg",
    "wof:name":"Knut Reichelt Architekt",
    "wof:placetype":"venue"
},
  "geometry": {"coordinates":[10.064947,53.647041],"type":"Point"}
}