{
  "type": "Feature",
  "properties": {
    "iso:country":"DE",
    "sg:address":"Behrensstr 27",
    "sg:city":"Erftstadt",
    "sg:phone":"+49 2235/42445",
    "sg:postcode":"50374",
    "sg:province":"Nordrhein-Westfalen",
    "wof:name":"Becker Elektro-stapler-service Gbr",
    "wof:placetype":"venue"
},
  "geometry": {"coordinates":[6.81031,50.816936],"type":"Point"}
}