{
  "type": "Feature",
  "properties": {
    "iso:country":"DE",
    "sg:address":"Roelckestr. 67",
    "sg:city":"Berlin",
    "sg:phone":"+49 30/9252860",
    "sg:postcode":"13086",
    "sg:province":"Berlin",
    "wof:name":"Dr. Med. Horst Meyer Arzt F\u00fcr P\u00e4diatrie",
    "wof:placetype":"venue"
},
  "geometry": {"coordinates":[13.4565591812,52.5603027344],"type":"Point"}
}