{
  "type": "Feature",
  "properties": {
    "iso:country":"DE",
    "sg:address":"Fritz-Josephs-Str. 7",
    "sg:city":"Warstein",
    "sg:phone":"+49 2925/743",
    "sg:postcode":"59581",
    "sg:province":"Nordrhein-Westfalen",
    "wof:name":"Josef Quente",
    "wof:placetype":"venue"
},
  "geometry": {"coordinates":[8.353955,51.442299],"type":"Point"}
}