{
  "type": "Feature",
  "properties": {
    "iso:country":"DE",
    "sg:address":"Hemsbacher Str. 19",
    "sg:city":"Osterburken",
    "sg:phone":"+49 6291/8485",
    "sg:postcode":"74706",
    "sg:province":"Baden-W\u00fcrttemberg",
    "wof:name":"Anton Matheis",
    "wof:placetype":"venue"
},
  "geometry": {"coordinates":[9.4153928757,49.4307441711],"type":"Point"}
}