{
  "type": "Feature",
  "properties": {
    "iso:country":"DE",
    "sg:address":"Loh\u00f6fenerweg 37",
    "sg:city":"M\u00fcnster",
    "sg:phone":"+49 251/785950",
    "sg:postcode":"48153",
    "sg:province":"Nordrhein-Westfalen",
    "wof:name":"E & M Spielautomaten- Aufstellungs-gmbh",
    "wof:placetype":"venue"
},
  "geometry": {"coordinates":[7.6083340645,51.9242744446],"type":"Point"}
}