{
  "type": "Feature",
  "properties": {
    "iso:country":"DE",
    "sg:address":"Am M\u00fchlgraben 70",
    "sg:city":"Bayreuth",
    "sg:phone":"+49 921/746000",
    "sg:postcode":"95445",
    "sg:province":"Bayern",
    "wof:name":"Semmelconcerts Gmbh",
    "wof:placetype":"venue"
},
  "geometry": {"coordinates":[11.5509700775,49.9406204224],"type":"Point"}
}