{
  "type": "Feature",
  "properties": {
    "iso:country":"DE",
    "sg:address":"Coesfelder Str. 7",
    "sg:city":"Velen",
    "sg:phone":"+49 2863/1888",
    "sg:postcode":"46342",
    "sg:province":"Nordrhein-Westfalen",
    "wof:name":"Gastst\u00e4tte Paul Fragemann",
    "wof:placetype":"venue"
},
  "geometry": {"coordinates":[6.9867191315,51.8950958252],"type":"Point"}
}