{
  "type": "Feature",
  "properties": {
    "iso:country":"DE",
    "sg:address":"Beuroner Str. 7",
    "sg:city":"M\u00fchlheim",
    "sg:phone":"+49 7463/316",
    "sg:postcode":"78570",
    "sg:province":"Baden-W\u00fcrttemberg",
    "wof:name":"Josef Betzler",
    "wof:placetype":"venue"
},
  "geometry": {"coordinates":[8.8893299103,48.022857666],"type":"Point"}
}