{
  "type": "Feature",
  "properties": {
    "iso:country":"DE",
    "sg:address":"Maximilianplatz 37",
    "sg:city":"Mindelheim",
    "sg:phone":"+49 8261/4066",
    "sg:postcode":"87719",
    "sg:province":"Bayern",
    "wof:name":"Volksbank Mindelheim Eg",
    "wof:placetype":"venue"
},
  "geometry": {"coordinates":[10.488359,48.046192],"type":"Point"}
}