{
  "type": "Feature",
  "properties": {
    "iso:country":"DE",
    "sg:address":"Seelower Str. 9",
    "sg:city":"Berlin",
    "sg:phone":"+49 30/44650203",
    "sg:postcode":"10439",
    "sg:province":"Berlin",
    "wof:name":"H\u00e4usliche Krankenpflege Johanna",
    "wof:placetype":"venue"
},
  "geometry": {"coordinates":[13.410879,52.552139],"type":"Point"}
}