{
  "type": "Feature",
  "properties": {
    "iso:country":"DE",
    "sg:address":"Schwalbenweg 12",
    "sg:city":"Leopoldsh\u00f6he",
    "sg:phone":"+49 5208/951150",
    "sg:postcode":"33818",
    "sg:province":"Nordrhein-Westfalen",
    "wof:name":"Vereinigte Postversicherung",
    "wof:placetype":"venue"
},
  "geometry": {"coordinates":[8.6640100479,52.0306510925],"type":"Point"}
}