{
  "type": "Feature",
  "properties": {
    "iso:country":"DE",
    "sg:address":"Jahnstr. 25",
    "sg:city":"Schwandorf",
    "sg:phone":"+49 9431/41890",
    "sg:postcode":"92421",
    "sg:province":"Bayern",
    "wof:name":"B. E. S. E. Gmbh",
    "wof:placetype":"venue"
},
  "geometry": {"coordinates":[12.116913,49.328358],"type":"Point"}
}