{
  "type": "Feature",
  "properties": {
    "iso:country":"DE",
    "sg:address":"An Lentzen K\u00e4mpen 40",
    "sg:city":"Soest",
    "sg:phone":"+49 2921/60041",
    "sg:postcode":"59494",
    "sg:province":"Nordrhein-Westfalen",
    "wof:name":"Hermessen Reisedienst Inh. S. Hermessen-franke",
    "wof:placetype":"venue"
},
  "geometry": {"coordinates":[8.0867643356,51.5754814148],"type":"Point"}
}