{
  "type": "Feature",
  "properties": {
    "iso:country":"DE",
    "sg:address":"Walld\u00fcrner Str. 24",
    "sg:city":"Buchen",
    "sg:phone":"+49 6281/1839",
    "sg:postcode":"74722",
    "sg:province":"Baden-W\u00fcrttemberg",
    "wof:name":"Richard Steiner Innenarchitekt",
    "wof:placetype":"venue"
},
  "geometry": {"coordinates":[9.326771,49.524487],"type":"Point"}
}