{
  "type": "Feature",
  "properties": {
    "iso:country":"DE",
    "sg:address":"Burger Str. 100",
    "sg:city":"Remscheid",
    "sg:phone":"+49 2191/343436",
    "sg:postcode":"42859",
    "sg:province":"Nordrhein-Westfalen",
    "wof:name":"Burger 100",
    "wof:placetype":"venue"
},
  "geometry": {"coordinates":[7.2010998726,51.1670761108],"type":"Point"}
}