{
  "type": "Feature",
  "properties": {
    "iso:country":"DE",
    "sg:address":"Bieberer Str. 47",
    "sg:city":"Obertshausen",
    "sg:phone":"+49 6104/95465",
    "sg:postcode":"63179",
    "sg:province":"Hessen",
    "wof:name":"Gastro Immobilien Gaho Gmbh",
    "wof:placetype":"venue"
},
  "geometry": {"coordinates":[8.8310184479,50.069152832],"type":"Point"}
}