{
  "type": "Feature",
  "properties": {
    "iso:country":"DE",
    "sg:address":"Unterdorfstr. 46",
    "sg:city":"Niederkassel",
    "sg:phone":"+49 228/453127",
    "sg:postcode":"53859",
    "sg:province":"Nordrhein-Westfalen",
    "wof:name":"Herbert Pohl",
    "wof:placetype":"venue"
},
  "geometry": {"coordinates":[7.0661940575,50.775302887],"type":"Point"}
}