{
  "type": "Feature",
  "properties": {
    "iso:country":"DE",
    "sg:address":"Zollhausstr. 18",
    "sg:city":"Heppenheim",
    "sg:phone":"+49 6252/2479",
    "sg:postcode":"64646",
    "sg:province":"Hessen",
    "wof:name":"Franz Frank",
    "wof:placetype":"venue"
},
  "geometry": {"coordinates":[8.641673,49.637981],"type":"Point"}
}