{
  "type": "Feature",
  "properties": {
    "iso:country":"DE",
    "sg:address":"Moorweg 5",
    "sg:city":"Lanz",
    "sg:phone":"+49 38780/7432",
    "sg:postcode":"19309",
    "sg:province":"Brandenburg",
    "wof:name":"Bodo B\u00f6gel",
    "wof:placetype":"venue"
},
  "geometry": {"coordinates":[11.604079,53.072937],"type":"Point"}
}