{
  "type": "Feature",
  "properties": {
    "iso:country":"DE",
    "sg:address":"izdochegal 5",
    "sg:city":"Plasmanien",
    "sg:phone":"+49 190332332",
    "sg:postcode":"69874",
    "wof:name":"Photonv7",
    "wof:placetype":"venue"
},
  "geometry": {"coordinates":[-97.64260101319999,17.2678394318],"type":"Point"}
}