{
  "type": "Feature",
  "properties": {
    "iso:country":"DE",
    "sg:address":"Albert-Kuntz-Str. 23",
    "sg:city":"Wurzen",
    "sg:phone":"+49 3425/9820",
    "sg:postcode":"04808",
    "sg:province":"Sachsen",
    "wof:name":"Vereinigte Feierabend- Und Pflegeheime Des Kreises Wurzen",
    "wof:placetype":"venue"
},
  "geometry": {"coordinates":[12.736222,51.373264],"type":"Point"}
}