{
  "type": "Feature",
  "properties": {
    "iso:country":"DE",
    "sg:address":"Peperm\u00f6lenbek 57",
    "sg:city":"Hamburg",
    "sg:phone":"+49 40/310291",
    "sg:postcode":"22767",
    "sg:province":"Hamburg",
    "wof:name":"Tefi-radio",
    "wof:placetype":"venue"
},
  "geometry": {"coordinates":[9.9547891617,53.5487976074],"type":"Point"}
}