{
  "type": "Feature",
  "properties": {
    "iso:country":"DE",
    "sg:address":"Stresemannstr. 90",
    "sg:city":"Berlin",
    "sg:postcode":"10963",
    "sg:province":"Berlin",
    "wof:name":"Bernd L\u00fctzenkirchen Gmbh",
    "wof:placetype":"venue"
},
  "geometry": {"coordinates":[13.382159,52.504959],"type":"Point"}
}