{
  "type": "Feature",
  "properties": {
    "iso:country":"DE",
    "sg:address":"Weg\u00e4cker 9 a",
    "sg:city":"Bubenreuth",
    "sg:postcode":"91088",
    "sg:province":"Bayern",
    "wof:name":"Sales Prognos Zimmermann Unternehmensberatung E. K.",
    "wof:placetype":"venue"
},
  "geometry": {"coordinates":[11.0220251083,49.6288604736],"type":"Point"}
}