{
  "type": "Feature",
  "properties": {
    "iso:country":"DE",
    "sg:address":"Maarweg 19",
    "sg:city":"K\u00f6ln",
    "sg:phone":"+49 221/4911465",
    "sg:postcode":"50933",
    "sg:province":"Nordrhein-Westfalen",
    "wof:name":"Berthold Reinfeldt Architekt",
    "wof:placetype":"venue"
},
  "geometry": {"coordinates":[6.899204,50.939281],"type":"Point"}
}