{
  "type": "Feature",
  "properties": {
    "iso:country":"DE",
    "sg:address":"Borg 1",
    "sg:city":"L\u00fcdinghausen",
    "sg:postcode":"59348",
    "sg:province":"Nordrhein-Westfalen",
    "wof:name":"Pizza Flizza Angelo Ferraro",
    "wof:placetype":"venue"
},
  "geometry": {"coordinates":[7.4429550171,51.7715339661],"type":"Point"}
}