{
  "type": "Feature",
  "properties": {
    "iso:country":"DE",
    "sg:address":"Schulstr. 14",
    "sg:city":"Bad Soden",
    "sg:phone":"+49 6196/21838",
    "sg:postcode":"65812",
    "sg:province":"Hessen",
    "wof:name":"Johann Ochs",
    "wof:placetype":"venue"
},
  "geometry": {"coordinates":[8.490733,50.156845],"type":"Point"}
}