{
  "type": "Feature",
  "properties": {
    "iso:country":"DE",
    "sg:address":"Luisenstr. 40",
    "sg:city":"Mannheim",
    "sg:phone":"+49 621/858894",
    "sg:postcode":"68199",
    "sg:province":"Baden-W\u00fcrttemberg",
    "wof:name":"C. Klostermann",
    "wof:placetype":"venue"
},
  "geometry": {"coordinates":[8.488259,49.455265],"type":"Point"}
}