{
  "type": "Feature",
  "properties": {
    "iso:country":"DE",
    "sg:address":"Osterwiese 6",
    "sg:city":"Ludwigsburg",
    "sg:phone":"+49 7141/31817",
    "sg:postcode":"71634",
    "sg:province":"Baden-W\u00fcrttemberg",
    "wof:name":"Max Trampitsch",
    "wof:placetype":"venue"
},
  "geometry": {"coordinates":[9.173494339,48.906288147],"type":"Point"}
}