{
  "type": "Feature",
  "properties": {
    "iso:country":"DE",
    "sg:address":"Bahnhofstr. 43",
    "sg:city":"Bleicherode",
    "sg:phone":"+49 36338/60994",
    "sg:postcode":"99752",
    "sg:province":"Th\u00fcringen",
    "wof:name":"R. Hirschfeld",
    "wof:placetype":"venue"
},
  "geometry": {"coordinates":[10.578031,51.442589],"type":"Point"}
}