{
  "type": "Feature",
  "properties": {
    "iso:country":"DE",
    "sg:address":"Bahnhofsvorplatz 1",
    "sg:city":"Cochem",
    "sg:phone":"+49 2671/4500",
    "sg:postcode":"56812",
    "sg:province":"Rheinland-Pfalz",
    "wof:name":"Berenz Gmbh",
    "wof:placetype":"venue"
},
  "geometry": {"coordinates":[7.1674227715,50.1529884338],"type":"Point"}
}