{
  "type": "Feature",
  "properties": {
    "iso:country":"DE",
    "sg:address":"H\u00e4tschenkamp 29 a",
    "sg:city":"Pinneberg",
    "sg:phone":"+49 4101/62217",
    "sg:postcode":"25421",
    "sg:province":"Schleswig-Holstein",
    "wof:name":"Martin M\u00fcller",
    "wof:placetype":"venue"
},
  "geometry": {"coordinates":[9.802686,53.650112],"type":"Point"}
}