{
  "type": "Feature",
  "properties": {
    "iso:country":"DE",
    "sg:address":"Christophstr. 22",
    "sg:city":"Limbach-Oberfrohna",
    "sg:phone":"+49 3722/98397",
    "sg:postcode":"09212",
    "sg:province":"Sachsen",
    "wof:name":"J. Peters Ingenieur",
    "wof:placetype":"venue"
},
  "geometry": {"coordinates":[12.7620162964,50.8610534668],"type":"Point"}
}