{
  "type": "Feature",
  "properties": {
    "iso:country":"DE",
    "sg:address":"Einigkeitstr. 16",
    "sg:city":"Essen",
    "sg:phone":"+49 201/410327",
    "sg:postcode":"45133",
    "sg:province":"Nordrhein-Westfalen",
    "wof:name":"Bredeneyer Hof",
    "wof:placetype":"venue"
},
  "geometry": {"coordinates":[6.9974851608,51.4222335815],"type":"Point"}
}