{
  "type": "Feature",
  "properties": {
    "iso:country":"DE",
    "sg:address":"Werderstr. 36",
    "sg:city":"Hornberg",
    "sg:phone":"+49 7833/700",
    "sg:postcode":"78132",
    "sg:province":"Baden-W\u00fcrttemberg",
    "wof:name":"Duravit Ag",
    "wof:placetype":"venue"
},
  "geometry": {"coordinates":[8.2319126129,48.208366394],"type":"Point"}
}