{
  "type": "Feature",
  "properties": {
    "iso:country":"DE",
    "sg:address":"Hofenfelsstr. 175",
    "sg:city":"Zweibr\u00fccken",
    "sg:phone":"+49 6332/44857",
    "sg:postcode":"66482",
    "sg:province":"Rheinland-Pfalz",
    "wof:name":"Restaurant Djangos Schnitzel Eck",
    "wof:placetype":"venue"
},
  "geometry": {"coordinates":[7.3799347878,49.2571640015],"type":"Point"}
}