{
  "type": "Feature",
  "properties": {
    "iso:country":"DE",
    "sg:address":"Postfach 129:: 99003 Erfurt:: Germany.^^Europaplatz 5::",
    "sg:city":"Efurt",
    "sg:postcode":"99091",
    "sg:province":"Th\u00fcringen",
    "wof:name":"Tishman Speyer Berlin Gmbh & Co",
    "wof:placetype":"venue"
},
  "geometry": {"coordinates":[13.376987,52.516075],"type":"Point"}
}