{
  "type": "Feature",
  "properties": {
    "iso:country":"DE",
    "sg:address":"Hauptstr. 77",
    "sg:city":"Badbergen",
    "sg:phone":"+49 5433/9292",
    "sg:postcode":"49635",
    "sg:province":"Niedersachsen",
    "wof:name":"Erika Vollmer",
    "wof:placetype":"venue"
},
  "geometry": {"coordinates":[7.981117,52.632389],"type":"Point"}
}