{
  "type": "Feature",
  "properties": {
    "iso:country":"DE",
    "sg:address":"Hauptstr. 22",
    "sg:city":"Ehingen",
    "sg:phone":"+49 9835/292",
    "sg:postcode":"91725",
    "sg:province":"Bayern",
    "wof:name":"Sparkasse Wassertr\u00fcdingen",
    "wof:placetype":"venue"
},
  "geometry": {"coordinates":[10.543381,49.086849],"type":"Point"}
}