{
  "type": "Feature",
  "properties": {
    "iso:country":"DE",
    "sg:address":"Borsigstr. 3",
    "sg:city":"Wiesbaden",
    "sg:postcode":"65205",
    "sg:province":"Hessen",
    "wof:name":"Ith Iranische Teppich Handels Gmbh",
    "wof:placetype":"venue"
},
  "geometry": {"coordinates":[8.3370981216,50.0570030212],"type":"Point"}
}