{
  "type": "Feature",
  "properties": {
    "iso:country":"DE",
    "sg:address":"Neue Str. 33",
    "sg:city":"Sinsheim",
    "sg:phone":"+49 7261/2105",
    "sg:postcode":"74889",
    "sg:province":"Baden-W\u00fcrttemberg",
    "wof:name":"Hans K\u00f6hler",
    "wof:placetype":"venue"
},
  "geometry": {"coordinates":[8.890042,49.243301],"type":"Point"}
}