{
  "type": "Feature",
  "properties": {
    "iso:country":"DE",
    "sg:address":"02977",
    "sg:city":"Hoyerswerda",
    "sg:postcode":"02977",
    "sg:province":"Sachsen",
    "wof:name":"Volks-und Raiffeisenbank Hoyerswerda Eg",
    "wof:placetype":"venue"
},
  "geometry": {"coordinates":[14.244285,51.439018],"type":"Point"}
}