{
  "type": "Feature",
  "properties": {
    "iso:country":"DE",
    "sg:address":"Im Br\u00fchl 2",
    "sg:city":"Weinbach",
    "sg:phone":"+49 6474/1308",
    "sg:postcode":"35796",
    "sg:province":"Hessen",
    "wof:name":"Karl-heinz Jung",
    "wof:placetype":"venue"
},
  "geometry": {"coordinates":[8.301812,50.414768],"type":"Point"}
}