{
  "type": "Feature",
  "properties": {
    "iso:country":"DE",
    "sg:address":"Beim Meilenstein 8",
    "sg:city":"L\u00fcbeck",
    "sg:phone":"+49 451/690100",
    "sg:postcode":"23568",
    "sg:province":"Schleswig-Holstein",
    "wof:name":"Thomas Timmermann",
    "wof:placetype":"venue"
},
  "geometry": {"coordinates":[10.79198,53.888779],"type":"Point"}
}