{
  "type": "Feature",
  "properties": {
    "iso:country":"DE",
    "sg:address":"Virchowstr. 26",
    "sg:city":"Heidenheim",
    "sg:postcode":"89518",
    "sg:province":"Baden-W\u00fcrttemberg",
    "wof:name":"Hellenstein Sport- Marketing Gmbh",
    "wof:placetype":"venue"
},
  "geometry": {"coordinates":[10.1485414505,48.6871681213],"type":"Point"}
}