{
  "type": "Feature",
  "properties": {
    "iso:country":"DE",
    "sg:address":"Chausseestr. 30",
    "sg:city":"W\u00fcnsdorf",
    "sg:phone":"+49 3377/393911",
    "sg:postcode":"15838",
    "sg:province":"Brandenburg",
    "wof:name":"Belger & Partner Ingenieur Gmbh",
    "wof:placetype":"venue"
},
  "geometry": {"coordinates":[13.468723,52.162418],"type":"Point"}
}