{
  "type": "Feature",
  "properties": {
    "iso:country":"DE",
    "sg:address":"Geleitsstr 82-90",
    "sg:city":"Offenbach",
    "sg:phone":"+49 69/813234",
    "sg:postcode":"63067",
    "sg:province":"Hessen",
    "wof:name":"Seeger Solution Gmbh",
    "wof:placetype":"venue"
},
  "geometry": {"coordinates":[8.754745,50.101387],"type":"Point"}
}