{
  "type": "Feature",
  "properties": {
    "iso:country":"DE",
    "sg:address":"Nohlstr. 26",
    "sg:city":"Glienicke",
    "sg:phone":"+49 33056/80226",
    "sg:postcode":"16548",
    "sg:province":"Brandenburg",
    "wof:name":"Wilhelm Loechel",
    "wof:placetype":"venue"
},
  "geometry": {"coordinates":[13.310181,52.635551],"type":"Point"}
}