{
  "type": "Feature",
  "properties": {
    "iso:country":"DE",
    "sg:address":"Morgensternstr. 9",
    "sg:city":"M\u00fcnchen",
    "sg:phone":"+49 89/749170",
    "sg:postcode":"81479",
    "sg:province":"Bayern",
    "wof:name":"Alkor Draka Handel Gmbh",
    "wof:placetype":"venue"
},
  "geometry": {"coordinates":[11.5090417862,48.0726776123],"type":"Point"}
}