{
  "type": "Feature",
  "properties": {
    "iso:country":"DE",
    "sg:address":"Tempelhofer Damm 131",
    "sg:city":"Berlin",
    "sg:phone":"+49 30/75702070",
    "sg:postcode":"12099",
    "sg:province":"Berlin",
    "wof:name":"Copy-light",
    "wof:placetype":"venue"
},
  "geometry": {"coordinates":[13.3858823776,52.4678497314],"type":"Point"}
}