{
  "type": "Feature",
  "properties": {
    "iso:country":"DE",
    "sg:address":"Barschweg 19",
    "sg:city":"Dornum",
    "sg:phone":"+49 4933/575",
    "sg:postcode":"26553",
    "sg:province":"Niedersachsen",
    "wof:name":"Wilhelm Schmidt",
    "wof:placetype":"venue"
},
  "geometry": {"coordinates":[7.439028,53.644417],"type":"Point"}
}