{
  "type": "Feature",
  "properties": {
    "iso:country":"DE",
    "sg:address":"Dr.-Virchow-Str. 18",
    "sg:city":"Gera",
    "sg:phone":"+49 365/8001391",
    "sg:postcode":"07548",
    "sg:province":"Th\u00fcringen",
    "wof:name":"Schoenitz Und Melzer Architekten",
    "wof:placetype":"venue"
},
  "geometry": {"coordinates":[12.037504,50.868713],"type":"Point"}
}