{
  "type": "Feature",
  "properties": {
    "iso:country":"DE",
    "sg:address":"Kirchstr. 36",
    "sg:city":"Bad Segeberg",
    "sg:phone":"+49 4551/2586",
    "sg:postcode":"23795",
    "sg:province":"Schleswig-Holstein",
    "wof:name":"Walter Path Ohg",
    "wof:placetype":"venue"
},
  "geometry": {"coordinates":[10.3086595535,53.9363441467],"type":"Point"}
}