{
  "type": "Feature",
  "properties": {
    "iso:country":"DE",
    "sg:address":"Turmstr. 24",
    "sg:city":"Berlin",
    "sg:phone":"+49 30/39839170",
    "sg:postcode":"10559",
    "sg:province":"Berlin",
    "wof:name":"Gastst\u00e4tte Zum Haxenwirt",
    "wof:placetype":"venue"
},
  "geometry": {"coordinates":[13.3449449539,52.5264472961],"type":"Point"}
}