{
  "type": "Feature",
  "properties": {
    "iso:country":"DE",
    "sg:address":"Bruchstr. 24",
    "sg:city":"Hilchenbach",
    "sg:phone":"+49 2733/3110",
    "sg:postcode":"57271",
    "sg:province":"Nordrhein-Westfalen",
    "wof:name":"Ginsburg-apotheke",
    "wof:placetype":"venue"
},
  "geometry": {"coordinates":[8.106242,50.994366],"type":"Point"}
}