{
  "type": "Feature",
  "properties": {
    "iso:country":"DE",
    "sg:address":"Fauerbacher Str. 87",
    "sg:city":"Friedberg",
    "sg:postcode":"61169",
    "sg:province":"Hessen",
    "wof:name":"Die Br\u00fccke Grundst\u00fccks- Verwaltungsgesellschaft Mbh",
    "wof:placetype":"venue"
},
  "geometry": {"coordinates":[8.7676372528,50.3307342529],"type":"Point"}
}