{
  "type": "Feature",
  "properties": {
    "iso:country":"DE",
    "sg:address":"Emmastr. 17",
    "sg:city":"D\u00fcsseldorf",
    "sg:phone":"+49 211/784013",
    "sg:postcode":"40227",
    "sg:province":"Nordrhein-Westfalen",
    "wof:name":"M\u00f6rsch Transporte Gmbh",
    "wof:placetype":"venue"
},
  "geometry": {"coordinates":[6.8001408577,51.2095336914],"type":"Point"}
}