{
  "type": "Feature",
  "properties": {
    "iso:country":"DE",
    "sg:address":"Hirschsprung 11",
    "sg:city":"Erkner",
    "sg:phone":"+49 3362/20195",
    "sg:postcode":"15537",
    "sg:province":"Brandenburg",
    "wof:name":"Regina Fischer",
    "wof:placetype":"venue"
},
  "geometry": {"coordinates":[13.760029,52.414913],"type":"Point"}
}