{
  "type": "Feature",
  "properties": {
    "iso:country":"DE",
    "sg:address":"Brendstr. 123",
    "sg:city":"Bischofsheim",
    "sg:phone":"+49 9772/453",
    "sg:postcode":"97653",
    "sg:province":"Bayern",
    "wof:name":"Pension Oswin Walter",
    "wof:placetype":"venue"
},
  "geometry": {"coordinates":[10.0401611328,50.3984603882],"type":"Point"}
}