{
  "type": "Feature",
  "properties": {
    "iso:country":"DE",
    "sg:address":"Mittelstr. 20",
    "sg:city":"Heilbad Heiligenstadt",
    "sg:phone":"+49 36083/41313",
    "sg:postcode":"37308",
    "sg:province":"Th\u00fcringen",
    "wof:name":"Karl Schneemann",
    "wof:placetype":"venue"
},
  "geometry": {"coordinates":[10.1387815475,51.3196868896],"type":"Point"}
}