{
  "type": "Feature",
  "properties": {
    "iso:country":"DE",
    "sg:address":"Gr\u00fcner Weg 30",
    "sg:city":"Hamm",
    "sg:phone":"+49 2381/50426",
    "sg:postcode":"59063",
    "sg:province":"Nordrhein-Westfalen",
    "wof:name":"Helga Malien",
    "wof:placetype":"venue"
},
  "geometry": {"coordinates":[7.8190460205,51.6596183777],"type":"Point"}
}