{
  "type": "Feature",
  "properties": {
    "iso:country":"DE",
    "sg:address":"Im Eberstal 1",
    "sg:city":"Retzstadt",
    "sg:phone":"+49 9364/5760",
    "sg:postcode":"97282",
    "sg:province":"Bayern",
    "wof:name":"Weingut Rudolf May - Retzstadt",
    "wof:placetype":"venue"
},
  "geometry": {"coordinates":[9.8677749634,49.9125137329],"type":"Point"}
}