{
  "type": "Feature",
  "properties": {
    "iso:country":"DE",
    "sg:address":"Eschlkamer Str. 20",
    "sg:city":"Furth im Wald",
    "sg:phone":"+49 9973/9244",
    "sg:postcode":"93437",
    "sg:province":"Bayern",
    "wof:name":"Super 2000",
    "wof:placetype":"venue"
},
  "geometry": {"coordinates":[12.8501176834,49.3050384521],"type":"Point"}
}