{
  "type": "Feature",
  "properties": {
    "iso:country":"DE",
    "sg:address":"Vogesenweg 10",
    "sg:city":"Dresden",
    "sg:phone":"+49 351/318780",
    "sg:postcode":"01309",
    "sg:province":"Sachsen",
    "wof:name":"Verein Zur F\u00f6rderung Des Tc Blau-wei\u00df Dresden-",
    "wof:placetype":"venue"
},
  "geometry": {"coordinates":[13.7970190048,51.0547409058],"type":"Point"}
}