{
  "type": "Feature",
  "properties": {
    "iso:country":"DE",
    "sg:address":"Gro\u00df-Quern",
    "sg:city":"Quern",
    "sg:phone":"+49 4632/333",
    "sg:postcode":"24972",
    "sg:province":"Schleswig-Holstein",
    "wof:name":"Franz Szidat",
    "wof:placetype":"venue"
},
  "geometry": {"coordinates":[9.71607,54.746449],"type":"Point"}
}