{
  "type": "Feature",
  "properties": {
    "iso:country":"DE",
    "sg:address":"Otto-Lilienthal-Str.",
    "sg:city":"Oschatz",
    "sg:phone":"+49 3435/939995",
    "sg:postcode":"04758",
    "sg:province":"Sachsen",
    "wof:name":"Pasa-systembauelemente Gmbh",
    "wof:placetype":"venue"
},
  "geometry": {"coordinates":[13.07096,51.297421],"type":"Point"}
}