{
  "type": "Feature",
  "properties": {
    "iso:country":"DE",
    "sg:address":"Schlackenstr. 9",
    "sg:city":"Seesen",
    "sg:phone":"+49 4953/84497",
    "sg:postcode":"38723",
    "sg:province":"Niedersachsen",
    "wof:name":"Norddeutsche Landesbank",
    "wof:placetype":"venue"
},
  "geometry": {"coordinates":[10.125547,51.941383],"type":"Point"}
}