{
  "type": "Feature",
  "properties": {
    "iso:country":"DE",
    "sg:address":"Weberstr. 10",
    "sg:city":"Illingen",
    "sg:phone":"+49 6825/42904",
    "sg:postcode":"66557",
    "sg:province":"Saarland",
    "wof:name":"Rudolf Lauer",
    "wof:placetype":"venue"
},
  "geometry": {"coordinates":[7.0800719261,49.4008903503],"type":"Point"}
}