{
  "type": "Feature",
  "properties": {
    "iso:country":"DE",
    "sg:address":"Marmagener Str. 22",
    "sg:city":"Kall",
    "sg:phone":"+49 2486/369",
    "sg:postcode":"53925",
    "sg:province":"Nordrhein-Westfalen",
    "wof:name":"Horst Krahe",
    "wof:placetype":"venue"
},
  "geometry": {"coordinates":[6.560486,50.484409],"type":"Point"}
}