{
  "type": "Feature",
  "properties": {
    "iso:country":"DE",
    "sg:address":"Espachstr. 1",
    "sg:city":"Erolzheim",
    "sg:phone":"+49 7354/91270",
    "sg:postcode":"88453",
    "sg:province":"Baden-W\u00fcrttemberg",
    "wof:name":"Peter Musch",
    "wof:placetype":"venue"
},
  "geometry": {"coordinates":[10.075475,48.095798],"type":"Point"}
}