{
  "type": "Feature",
  "properties": {
    "iso:country":"DE",
    "sg:address":"Wellerswalder Weg 10-12",
    "sg:city":"Oschatz",
    "sg:phone":"+49 3435/661100",
    "sg:postcode":"04758",
    "sg:province":"Sachsen",
    "wof:name":"Lube & Krings Gmbh",
    "wof:placetype":"venue"
},
  "geometry": {"coordinates":[13.1043796539,51.3155517578],"type":"Point"}
}