{
  "type": "Feature",
  "properties": {
    "iso:country":"DE",
    "sg:address":"Bredelaerstr. 51",
    "sg:city":"D\u00fcsseldorf",
    "sg:phone":"+49 211/4530830",
    "sg:postcode":"40474",
    "sg:province":"Nordrhein-Westfalen",
    "wof:name":"Clever Reisen Gmbh",
    "wof:placetype":"venue"
},
  "geometry": {"coordinates":[6.7461981773,51.2741241455],"type":"Point"}
}