{
  "type": "Feature",
  "properties": {
    "iso:country":"DE",
    "sg:address":"St\u00f6berlstr. 8",
    "sg:city":"M\u00fcnchen",
    "sg:phone":"+49 89/587848",
    "sg:postcode":"80687",
    "sg:province":"Bayern",
    "wof:name":"Walter Schwarzer",
    "wof:placetype":"venue"
},
  "geometry": {"coordinates":[11.4949550629,48.1428947449],"type":"Point"}
}