{
  "type": "Feature",
  "properties": {
    "iso:country":"DE",
    "sg:address":"Bahnhofstr. 8",
    "sg:city":"Rotthalm\u00fcnster",
    "sg:phone":"+49 8532/973811",
    "sg:postcode":"94094",
    "sg:province":"Bayern",
    "wof:name":"Baywa Ag",
    "wof:placetype":"venue"
},
  "geometry": {"coordinates":[13.2057571411,48.3572044373],"type":"Point"}
}