{
  "type": "Feature",
  "properties": {
    "iso:country":"DE",
    "sg:address":"Leipziger Str. 52",
    "sg:city":"Markranst\u00e4dt",
    "sg:phone":"+49 34205/397",
    "sg:postcode":"04420",
    "sg:province":"Sachsen",
    "wof:name":"W. Schubert Ziegelei Eythra",
    "wof:placetype":"venue"
},
  "geometry": {"coordinates":[12.226354599,51.3064346313],"type":"Point"}
}