{
  "type": "Feature",
  "properties": {
    "iso:country":"DE",
    "sg:address":"Telleringstr. 40",
    "sg:city":"D\u00fcsseldorf",
    "sg:phone":"+49 211/7186681",
    "sg:postcode":"40597",
    "sg:province":"Nordrhein-Westfalen",
    "wof:name":"Grillparadies",
    "wof:placetype":"venue"
},
  "geometry": {"coordinates":[6.88207,51.163704],"type":"Point"}
}