{
  "type": "Feature",
  "properties": {
    "iso:country":"DE",
    "sg:address":"Berliner Str. 128",
    "sg:city":"Potsdam",
    "sg:phone":"+49 331/2800866",
    "sg:postcode":"14467",
    "sg:province":"Brandenburg",
    "wof:name":"Kfz-sachverst\u00e4ndigenb\u00fcro Kittlitz Gmbh",
    "wof:placetype":"venue"
},
  "geometry": {"coordinates":[13.0736913681,52.4063568115],"type":"Point"}
}