{
  "type": "Feature",
  "properties": {
    "iso:country":"DE",
    "sg:address":"Fuhrmannsweg 2",
    "sg:city":"Trusetal",
    "sg:phone":"+49 36840/80119",
    "sg:postcode":"98596",
    "sg:province":"Th\u00fcringen",
    "wof:name":"Niels Roth",
    "wof:placetype":"venue"
},
  "geometry": {"coordinates":[10.404848,50.785927],"type":"Point"}
}