{
  "type": "Feature",
  "properties": {
    "iso:country":"DE",
    "sg:address":"Turmstr. 18a",
    "sg:city":"Wiesbaden",
    "sg:phone":"+49 6122/8860",
    "sg:postcode":"65205",
    "sg:province":"Hessen",
    "wof:name":"Michael Fr\u00f6hlich Architekt",
    "wof:placetype":"venue"
},
  "geometry": {"coordinates":[8.341906,50.06374],"type":"Point"}
}