{
  "type": "Feature",
  "properties": {
    "iso:country":"DE",
    "sg:address":"Weinstr. 23",
    "sg:city":"Pegnitz",
    "sg:phone":"+49 9241/2202",
    "sg:postcode":"91257",
    "sg:province":"Bayern",
    "wof:name":"Restaurant Krieg",
    "wof:placetype":"venue"
},
  "geometry": {"coordinates":[11.533452034,49.7267379761],"type":"Point"}
}