{
  "type": "Feature",
  "properties": {
    "iso:country":"DE",
    "sg:address":"Friedrichsgracht 56",
    "sg:city":"Berlin",
    "sg:phone":"+49 30/2011221",
    "sg:postcode":"10178",
    "sg:province":"Berlin",
    "wof:name":"Peter Koal",
    "wof:placetype":"venue"
},
  "geometry": {"coordinates":[13.402132988,52.5135612488],"type":"Point"}
}