{
  "type": "Feature",
  "properties": {
    "iso:country":"DE",
    "sg:address":"K\u00fchried 6",
    "sg:city":"Randersacker",
    "sg:phone":"+49 9303/677",
    "sg:postcode":"97236",
    "sg:province":"Bayern",
    "wof:name":"Dr. Karl H\u00f6hne Tierarzt",
    "wof:placetype":"venue"
},
  "geometry": {"coordinates":[10.033700943,49.7358055115],"type":"Point"}
}