{
  "type": "Feature",
  "properties": {
    "iso:country":"DE",
    "sg:address":"Am Friedhof 15a",
    "sg:city":"Visbek",
    "sg:phone":"+49 4445/8364",
    "sg:postcode":"49429",
    "sg:province":"Niedersachsen",
    "wof:name":"Transportgesellschaft Reiner Hermes Mbh",
    "wof:placetype":"venue"
},
  "geometry": {"coordinates":[8.3761672974,52.843952179],"type":"Point"}
}