{
  "type": "Feature",
  "properties": {
    "iso:country":"DE",
    "sg:address":"B\u00fcrgermeister-Fischer-Str. 11",
    "sg:city":"Augsburg",
    "sg:phone":"+49 821/156569",
    "sg:postcode":"86150",
    "sg:province":"Bayern",
    "wof:name":"Vitalia Reformhaus Gmbh",
    "wof:placetype":"venue"
},
  "geometry": {"coordinates":[10.8952531815,48.3663825989],"type":"Point"}
}