{
  "type": "Feature",
  "properties": {
    "iso:country":"DE",
    "sg:address":"Am Schieferacker 27",
    "sg:city":"Wetzlar",
    "sg:phone":"+49 6441/31438",
    "sg:postcode":"35586",
    "sg:province":"Hessen",
    "wof:name":"Egon Schwartz",
    "wof:placetype":"venue"
},
  "geometry": {"coordinates":[8.4872722626,50.5851860046],"type":"Point"}
}