{
  "type": "Feature",
  "properties": {
    "iso:country":"DE",
    "sg:address":"Mozartstr. 13",
    "sg:city":"Kelkheim",
    "sg:phone":"+49 6195/2185",
    "sg:postcode":"65779",
    "sg:province":"Hessen",
    "wof:name":"G. Lehmann",
    "wof:placetype":"venue"
},
  "geometry": {"coordinates":[8.460425,50.122517],"type":"Point"}
}