{
  "type": "Feature",
  "properties": {
    "iso:country":"DE",
    "sg:address":"Hauptstr. 26",
    "sg:city":"Hirschstein",
    "sg:postcode":"01594",
    "sg:province":"Sachsen",
    "wof:name":"Evangelisches Pfarramt Heyda",
    "wof:placetype":"venue"
},
  "geometry": {"coordinates":[13.3094911575,51.2620391846],"type":"Point"}
}