{
  "type": "Feature",
  "properties": {
    "iso:country":"DE",
    "sg:address":"Saarlandstr. 3",
    "sg:city":"Bochum",
    "sg:phone":"+49 2327/88177",
    "sg:postcode":"44866",
    "sg:province":"Nordrhein-Westfalen",
    "wof:name":"Les Sirenes",
    "wof:placetype":"venue"
},
  "geometry": {"coordinates":[7.134661,51.48064],"type":"Point"}
}