{
  "type": "Feature",
  "properties": {
    "iso:country":"DE",
    "sg:address":"Woogstr. 89",
    "sg:city":"Landau",
    "sg:phone":"+49 6341/51243",
    "sg:postcode":"76829",
    "sg:province":"Rheinland-Pfalz",
    "wof:name":"Werner Scheid",
    "wof:placetype":"venue"
},
  "geometry": {"coordinates":[8.1394739151,49.1970596313],"type":"Point"}
}