{
  "type": "Feature",
  "properties": {
    "iso:country":"DE",
    "sg:address":"Hermanstr. 25",
    "sg:city":"Augsburg",
    "sg:phone":"+49 821/50310",
    "sg:postcode":"86150",
    "sg:province":"Bayern",
    "wof:name":"Hotel Ibis",
    "wof:placetype":"venue"
},
  "geometry": {"coordinates":[10.8923196793,48.3624534607],"type":"Point"}
}