{
  "type": "Feature",
  "properties": {
    "iso:country":"DE",
    "sg:address":"Luisenstr. 11",
    "sg:city":"M\u00fcnchen",
    "sg:phone":"+49 89/557645",
    "sg:postcode":"80333",
    "sg:province":"Bayern",
    "wof:name":"Berufsbildungszentrum F\u00fcr Bau Und Gestaltung",
    "wof:placetype":"venue"
},
  "geometry": {"coordinates":[11.561968,48.143269],"type":"Point"}
}