{
  "type": "Feature",
  "properties": {
    "iso:country":"DE",
    "sg:address":"Im Bruche 9",
    "sg:city":"Landwehr",
    "sg:phone":"+49 5183/1780",
    "sg:postcode":"31087",
    "sg:province":"Niedersachsen",
    "wof:name":"Ernst Ahrens",
    "wof:placetype":"venue"
},
  "geometry": {"coordinates":[9.9766769409,51.924659729],"type":"Point"}
}