{
  "type": "Feature",
  "properties": {
    "iso:country":"DE",
    "sg:address":"Wilhelmstr. 62",
    "sg:city":"Filderstadt",
    "sg:phone":"+49 7158/8238",
    "sg:postcode":"70794",
    "sg:province":"Baden-W\u00fcrttemberg",
    "wof:name":"Karl Schweizer Gmbh",
    "wof:placetype":"venue"
},
  "geometry": {"coordinates":[9.2421588898,48.6728477478],"type":"Point"}
}