{
  "type": "Feature",
  "properties": {
    "iso:country":"DE",
    "sg:address":"Eschenstr. 2",
    "sg:city":"Taufkirchen",
    "sg:phone":"+49 89/6663640",
    "sg:postcode":"82024",
    "sg:province":"Bayern",
    "wof:name":"Physiomed Gesellschaft F\u00fcr Krankengymnastik Und",
    "wof:placetype":"venue"
},
  "geometry": {"coordinates":[11.608223,48.051491],"type":"Point"}
}