{
  "type": "Feature",
  "properties": {
    "iso:country":"DE",
    "sg:address":"St.-Lorenz-Str. 19",
    "sg:city":"Berching",
    "sg:phone":"+49 8462/1072",
    "sg:postcode":"92334",
    "sg:province":"Bayern",
    "wof:name":"Georg Gmelch Inh. Resi Billner",
    "wof:placetype":"venue"
},
  "geometry": {"coordinates":[11.4445419312,49.1047744751],"type":"Point"}
}