{
  "type": "Feature",
  "properties": {
    "iso:country":"DE",
    "sg:address":"Ludwigstr. 36",
    "sg:city":"L\u00fcbbecke",
    "sg:phone":"+49 5741/7381",
    "sg:postcode":"32312",
    "sg:province":"Nordrhein-Westfalen",
    "wof:name":"H. Arensmeier Versicherungs-vertreter",
    "wof:placetype":"venue"
},
  "geometry": {"coordinates":[8.6057291031,52.3154525757],"type":"Point"}
}