{
  "type": "Feature",
  "properties": {
    "iso:country":"DE",
    "sg:address":"Kneippstr. 17",
    "sg:city":"Hessisch Oldendorf",
    "sg:phone":"+49 5152/8748",
    "sg:postcode":"31840",
    "sg:province":"Niedersachsen",
    "wof:name":"Fleischerei Schulte",
    "wof:placetype":"venue"
},
  "geometry": {"coordinates":[9.2972602844,52.1837425232],"type":"Point"}
}