{
  "type": "Feature",
  "properties": {
    "iso:country":"DE",
    "sg:address":"Sebastianusstr. 14",
    "sg:city":"Korschenbroich",
    "sg:phone":"+49 2161/64688",
    "sg:postcode":"41352",
    "sg:province":"Nordrhein-Westfalen",
    "wof:name":"B\u00e4rbel Klinkenberg Heilpraktikerin",
    "wof:placetype":"venue"
},
  "geometry": {"coordinates":[6.5130410194,51.1905860901],"type":"Point"}
}