{
  "type": "Feature",
  "properties": {
    "iso:country":"DE",
    "sg:address":"Dinglinger Hauptstr. 25",
    "sg:city":"Lahr",
    "sg:phone":"+49 7821/26131",
    "sg:postcode":"77933",
    "sg:province":"Baden-W\u00fcrttemberg",
    "wof:name":"Rudolf Stulz",
    "wof:placetype":"venue"
},
  "geometry": {"coordinates":[7.855041,48.340714],"type":"Point"}
}