{
  "type": "Feature",
  "properties": {
    "iso:country":"DE",
    "sg:address":"Pollweinstr. 17",
    "sg:city":"Bad Kissingen",
    "sg:phone":"+49 971/62737",
    "sg:postcode":"97688",
    "sg:province":"Bayern",
    "wof:name":"W. Ruppert",
    "wof:placetype":"venue"
},
  "geometry": {"coordinates":[10.0929708481,50.2059593201],"type":"Point"}
}