{
  "type": "Feature",
  "properties": {
    "iso:country":"DE",
    "sg:address":"M\u00fchlenstr. 91",
    "sg:city":"Herzogenrath",
    "sg:phone":"+49 2407/2701",
    "sg:postcode":"52134",
    "sg:province":"Nordrhein-Westfalen",
    "wof:name":"Heinrich Frohn Gmbh",
    "wof:placetype":"venue"
},
  "geometry": {"coordinates":[6.079453,50.839031],"type":"Point"}
}