{
  "type": "Feature",
  "properties": {
    "iso:country":"DE",
    "sg:address":"Ohlendiekskamp 25",
    "sg:city":"Hamburg",
    "sg:phone":"+49 40/60849660",
    "sg:postcode":"22399",
    "sg:province":"Hamburg",
    "wof:name":"G. Weber Immobilien Gmbh",
    "wof:placetype":"venue"
},
  "geometry": {"coordinates":[10.0745487213,53.6679115295],"type":"Point"}
}