{
  "type": "Feature",
  "properties": {
    "iso:country":"DE",
    "sg:address":"Brauhausstr. 5",
    "sg:city":"Gro\u00dfbardorf",
    "sg:phone":"+49 9766/329",
    "sg:postcode":"97633",
    "sg:province":"Bayern",
    "wof:name":"Brauhaussch\u00e4nke",
    "wof:placetype":"venue"
},
  "geometry": {"coordinates":[10.3689842224,50.2713661194],"type":"Point"}
}