{
  "type": "Feature",
  "properties": {
    "iso:country":"DE",
    "sg:address":"Auf der Dahl 18",
    "sg:city":"Burbach",
    "sg:phone":"+49 2736/1295",
    "sg:postcode":"57299",
    "sg:province":"Nordrhein-Westfalen",
    "wof:name":"Verlag Leichtes Lernen",
    "wof:placetype":"venue"
},
  "geometry": {"coordinates":[8.1257638931,50.7617111206],"type":"Point"}
}