{
  "type": "Feature",
  "properties": {
    "iso:country":"DE",
    "sg:address":"Bodenseestr. 24",
    "sg:city":"Memmingen",
    "sg:phone":"+49 8331/81371",
    "sg:postcode":"87700",
    "sg:province":"Bayern",
    "wof:name":"Norbert Deutschmann",
    "wof:placetype":"venue"
},
  "geometry": {"coordinates":[10.175866,47.981224],"type":"Point"}
}