{
  "type": "Feature",
  "properties": {
    "iso:country":"DE",
    "sg:address":"Inninger Str. 105",
    "sg:city":"Augsburg",
    "sg:phone":"+49 821/87422",
    "sg:postcode":"86179",
    "sg:province":"Bayern",
    "wof:name":"B\u00f6hm Fahrradland Gmbh",
    "wof:placetype":"venue"
},
  "geometry": {"coordinates":[10.889517,48.309875],"type":"Point"}
}