{
  "type": "Feature",
  "properties": {
    "iso:country":"DE",
    "sg:address":"Nordstr. 21",
    "sg:city":"Horn-Bad Meinberg",
    "sg:phone":"+49 5234/820800",
    "sg:postcode":"32805",
    "sg:province":"Nordrhein-Westfalen",
    "wof:name":"Erika Hanke",
    "wof:placetype":"venue"
},
  "geometry": {"coordinates":[8.931543,51.890701],"type":"Point"}
}