{
  "type": "Feature",
  "properties": {
    "iso:country":"DE",
    "sg:address":"Am St\u00fchm-S\u00fcd 85",
    "sg:city":"Hamburg",
    "sg:phone":"+49 40/6402705",
    "sg:postcode":"22175",
    "sg:province":"Hamburg",
    "wof:name":"Ev. Pfarramt Simeonkirche",
    "wof:placetype":"venue"
},
  "geometry": {"coordinates":[10.0990028381,53.6255149841],"type":"Point"}
}