{
  "type": "Feature",
  "properties": {
    "iso:country":"DE",
    "sg:address":"Am Scheidebach 2",
    "sg:city":"Gr\u00f6mitz",
    "sg:phone":"+49 4562/5409",
    "sg:postcode":"23743",
    "sg:province":"Schleswig-Holstein",
    "wof:name":"Georg Wilms",
    "wof:placetype":"venue"
},
  "geometry": {"coordinates":[10.970652,54.15321],"type":"Point"}
}