{
  "type": "Feature",
  "properties": {
    "iso:country":"DE",
    "sg:address":"Jakobstr. 81",
    "sg:city":"Aachen",
    "sg:phone":"+49 241/34163",
    "sg:postcode":"52064",
    "sg:province":"Nordrhein-Westfalen",
    "wof:name":"Josefine Jacobs",
    "wof:placetype":"venue"
},
  "geometry": {"coordinates":[6.0772762299,50.7724456787],"type":"Point"}
}