{
  "type": "Feature",
  "properties": {
    "iso:country":"DE",
    "sg:address":"Bodanstr. 8",
    "sg:city":"Konstanz",
    "sg:phone":"+49 7531/22602",
    "sg:postcode":"78462",
    "sg:province":"Baden-W\u00fcrttemberg",
    "wof:name":"Bistro-bar Ii Can",
    "wof:placetype":"venue"
},
  "geometry": {"coordinates":[9.175725,47.658031],"type":"Point"}
}