{
  "type": "Feature",
  "properties": {
    "iso:country":"DE",
    "sg:address":"Sportfeldstr. 27",
    "sg:city":"Siegsdorf",
    "sg:phone":"+49 8662/9769",
    "sg:postcode":"83313",
    "sg:province":"Bayern",
    "wof:name":"Schwimmbad",
    "wof:placetype":"venue"
},
  "geometry": {"coordinates":[12.6444797516,47.8257484436],"type":"Point"}
}