{
  "type": "Feature",
  "properties": {
    "iso:country":"DE",
    "sg:address":"Dr.-Traugott-Bender-Str. 2",
    "sg:city":"Adelsheim",
    "sg:phone":"+49 6291/280",
    "sg:postcode":"74740",
    "sg:province":"Baden-W\u00fcrttemberg",
    "wof:name":"Justizvollzugsanstalt Adelsheim",
    "wof:placetype":"venue"
},
  "geometry": {"coordinates":[9.3910121918,49.4028968811],"type":"Point"}
}