{
  "type": "Feature",
  "properties": {
    "iso:country":"DE",
    "sg:address":"Leopoldstr. 3",
    "sg:city":"Daun",
    "sg:phone":"+49 6592/4066",
    "sg:postcode":"54550",
    "sg:province":"Rheinland-Pfalz",
    "wof:name":"H. Minninger",
    "wof:placetype":"venue"
},
  "geometry": {"coordinates":[6.830163,50.197525],"type":"Point"}
}