{
  "type": "Feature",
  "properties": {
    "iso:country":"DE",
    "sg:address":"H\u00f6lderlinstr. 49",
    "sg:city":"Geislingen",
    "sg:phone":"+49 7331/62961",
    "sg:postcode":"73312",
    "sg:province":"Baden-W\u00fcrttemberg",
    "wof:name":"Eva Mory Heilpraktikerin",
    "wof:placetype":"venue"
},
  "geometry": {"coordinates":[9.8306646347,48.6223106384],"type":"Point"}
}