{
  "type": "Feature",
  "properties": {
    "iso:country":"DE",
    "sg:address":"Brandenburgische Str. 39",
    "sg:city":"Berlin",
    "sg:phone":"+49 30/8914046",
    "sg:postcode":"10707",
    "sg:province":"Berlin",
    "wof:name":"Sawin Reisen Gmbh",
    "wof:placetype":"venue"
},
  "geometry": {"coordinates":[13.3073835373,52.497718811],"type":"Point"}
}