{
  "type": "Feature",
  "properties": {
    "iso:country":"DE",
    "sg:address":"Untergeisenfelden 11",
    "sg:city":"Fridolfing",
    "sg:phone":"+49 8684/571",
    "sg:postcode":"83413",
    "sg:province":"Bayern",
    "wof:name":"Sch\u00f6nsmaul - Zeif Gmbh",
    "wof:placetype":"venue"
},
  "geometry": {"coordinates":[12.8548583984,47.981086731],"type":"Point"}
}