{
  "type": "Feature",
  "properties": {
    "iso:country":"DE",
    "sg:address":"Julius-Kreis-Str. 42",
    "sg:city":"M\u00fcnchen",
    "sg:postcode":"81245",
    "sg:province":"Bayern",
    "wof:name":"Hfv Heimatfilm- Und Video- Vertriebs-gmbh",
    "wof:placetype":"venue"
},
  "geometry": {"coordinates":[11.4480075836,48.1612281799],"type":"Point"}
}