{
  "type": "Feature",
  "properties": {
    "iso:country":"DE",
    "sg:address":"Heinrich-L\u00fcbke-Str. 19",
    "sg:city":"Bestwig",
    "sg:phone":"+49 2905/294",
    "sg:postcode":"59909",
    "sg:province":"Nordrhein-Westfalen",
    "wof:name":"Josef Kutsch",
    "wof:placetype":"venue"
},
  "geometry": {"coordinates":[8.4026441574,51.3104324341],"type":"Point"}
}