{
  "type": "Feature",
  "properties": {
    "iso:country":"DE",
    "sg:address":"Wasserstrasse 46",
    "sg:city":"Wiedenbr\u00fcck",
    "sg:postcode":"33378",
    "sg:province":"Nordrhein-Westfalen",
    "wof:name":"Cybernautic - Internet L\u00f6sungen",
    "wof:placetype":"venue"
},
  "geometry": {"coordinates":[8.313709259,51.8350448608],"type":"Point"}
}