{
  "type": "Feature",
  "properties": {
    "iso:country":"DE",
    "sg:address":"Poststr. 3",
    "sg:city":"Kamenz",
    "sg:phone":"+49 35783/01047",
    "sg:postcode":"01917",
    "sg:province":"Sachsen",
    "wof:name":"W. Bubnick",
    "wof:placetype":"venue"
},
  "geometry": {"coordinates":[14.093647,51.2719],"type":"Point"}
}