{
  "type": "Feature",
  "properties": {
    "iso:country":"DE",
    "sg:city":"Bad Nauheim",
    "sg:phone":"+49 6032/921579",
    "sg:postcode":"61231",
    "sg:province":"Hessen",
    "wof:name":"Sprachdienstleistung",
    "wof:placetype":"venue"
},
  "geometry": {"coordinates":[8.73452,50.362446],"type":"Point"}
}