{
  "type": "Feature",
  "properties": {
    "iso:country":"DE",
    "sg:address":"F\u00fcssener Str. 15",
    "sg:city":"Oy-Mittelberg",
    "sg:phone":"+49 8366/386",
    "sg:postcode":"87466",
    "sg:province":"Bayern",
    "wof:name":"Cafe Elster",
    "wof:placetype":"venue"
},
  "geometry": {"coordinates":[10.420152,47.666477],"type":"Point"}
}