{
  "type": "Feature",
  "properties": {
    "iso:country":"DE",
    "sg:address":"Kirchgasse 13",
    "sg:city":"Markt Erlbach",
    "sg:phone":"+49 9106/92980",
    "sg:postcode":"91459",
    "sg:province":"Bayern",
    "wof:name":"Kmv Daten- Und Kommunikationstechnik Gmbh",
    "wof:placetype":"venue"
},
  "geometry": {"coordinates":[10.6542310715,49.494102478],"type":"Point"}
}