{
  "type": "Feature",
  "properties": {
    "iso:country":"DE",
    "sg:address":"Gammertinger Str. 12",
    "sg:city":"Trochtelfingen",
    "sg:phone":"+49 7124/2389",
    "sg:postcode":"72818",
    "sg:province":"Baden-W\u00fcrttemberg",
    "wof:name":"Jos. Heinzelmann",
    "wof:placetype":"venue"
},
  "geometry": {"coordinates":[9.276431,48.308659],"type":"Point"}
}