{
  "type": "Feature",
  "properties": {
    "iso:country":"DE",
    "sg:address":"Im Wispertal 20",
    "sg:city":"Lorch",
    "sg:phone":"+49 6726/533",
    "sg:postcode":"65391",
    "sg:province":"Rheinland-Pfalz",
    "wof:name":"Pohl Bedachungen Gmbh",
    "wof:placetype":"venue"
},
  "geometry": {"coordinates":[7.9165530205,50.0998802185],"type":"Point"}
}