{
  "type": "Feature",
  "properties": {
    "iso:country":"DE",
    "sg:address":"Oberer Stadtplatz 12",
    "sg:city":"Landau",
    "sg:phone":"+49 9951/7628",
    "sg:postcode":"94405",
    "sg:province":"Bayern",
    "wof:name":"Maria Helene Meyer Rechtsanw\u00e4ltin",
    "wof:placetype":"venue"
},
  "geometry": {"coordinates":[12.6905698776,48.6693344116],"type":"Point"}
}