{
  "type": "Feature",
  "properties": {
    "iso:country":"DE",
    "sg:address":"Peter-Link-Str. 12 a",
    "sg:city":"Forchheim",
    "sg:phone":"+49 9191/729949",
    "sg:postcode":"91301",
    "sg:province":"Bayern",
    "wof:name":"Silvia Freimuth Und Thomas Kersbach",
    "wof:placetype":"venue"
},
  "geometry": {"coordinates":[11.0681152344,49.6845855713],"type":"Point"}
}