{
  "type": "Feature",
  "properties": {
    "iso:country":"DE",
    "sg:address":"Am Ohrt 12",
    "sg:city":"Ense",
    "sg:phone":"+49 2938/2788",
    "sg:postcode":"59469",
    "sg:province":"Nordrhein-Westfalen",
    "wof:name":"Wetzel Kg",
    "wof:placetype":"venue"
},
  "geometry": {"coordinates":[7.9768481255,51.4889717102],"type":"Point"}
}