{
  "type": "Feature",
  "properties": {
    "iso:country":"DE",
    "sg:address":"Buchenweg 2",
    "sg:city":"Brakel",
    "sg:phone":"+49 5272/8847",
    "sg:postcode":"33034",
    "sg:province":"Nordrhein-Westfalen",
    "wof:name":"Erika Hellwig",
    "wof:placetype":"venue"
},
  "geometry": {"coordinates":[9.1856832504,51.7254714966],"type":"Point"}
}