{
  "type": "Feature",
  "properties": {
    "iso:country":"DE",
    "sg:address":"Uhlandstr. 7-8",
    "sg:city":"Berlin",
    "sg:phone":"+49 30/3186600",
    "sg:postcode":"10623",
    "sg:province":"Berlin",
    "wof:name":"Public Consult Gesellschaft F\u00fcr Die Beratung Der",
    "wof:placetype":"venue"
},
  "geometry": {"coordinates":[13.3256845474,52.5067825317],"type":"Point"}
}