{
  "type": "Feature",
  "properties": {
    "iso:country":"DE",
    "sg:address":"Altchemnitzer Str. 62",
    "sg:city":"Chemnitz",
    "sg:phone":"+49 371/530150",
    "sg:postcode":"09120",
    "sg:province":"Sachsen",
    "wof:name":"Sandvik Gmbh",
    "wof:placetype":"venue"
},
  "geometry": {"coordinates":[12.918577,50.817604],"type":"Point"}
}