{
  "type": "Feature",
  "properties": {
    "iso:country":"DE",
    "sg:address":"Weserstr. 119",
    "sg:city":"Bremerhaven",
    "sg:phone":"+49 471",
    "sg:postcode":"27572",
    "sg:province":"Bremen",
    "wof:name":"Automarkt Wulsdorf",
    "wof:placetype":"venue"
},
  "geometry": {"coordinates":[8.5963010788,53.5097465515],"type":"Point"}
}