{
  "type": "Feature",
  "properties": {
    "iso:country":"DE",
    "sg:address":"Bartholom\u00e4usstr. 37",
    "sg:city":"Wuppertal",
    "sg:phone":"+49 202/559963",
    "sg:postcode":"42275",
    "sg:province":"Nordrhein-Westfalen",
    "wof:name":"J. Becker Gmbh",
    "wof:placetype":"venue"
},
  "geometry": {"coordinates":[7.2090339661,51.2780189514],"type":"Point"}
}