{
  "type": "Feature",
  "properties": {
    "iso:country":"DE",
    "sg:address":"Sachsenring 83",
    "sg:city":"K\u00f6ln",
    "sg:phone":"+49 221/20120",
    "sg:postcode":"50677",
    "sg:province":"Nordrhein-Westfalen",
    "wof:name":"Ge Capital Mietfinanz Gmbh & Co. Kg",
    "wof:placetype":"venue"
},
  "geometry": {"coordinates":[6.948506,50.925304],"type":"Point"}
}