{
  "type": "Feature",
  "properties": {
    "iso:country":"DE",
    "sg:address":"Schulstr. 17",
    "sg:city":"Lage",
    "sg:phone":"+49 5232/2482",
    "sg:postcode":"32791",
    "sg:province":"Nordrhein-Westfalen",
    "wof:name":"Ekkehard Reuter",
    "wof:placetype":"venue"
},
  "geometry": {"coordinates":[8.796663,51.991562],"type":"Point"}
}