{
  "type": "Feature",
  "properties": {
    "iso:country":"DE",
    "sg:address":"Klosterstr. 1",
    "sg:city":"Lauffen",
    "sg:phone":"+49 7133/16817",
    "sg:postcode":"74348",
    "sg:province":"Baden-W\u00fcrttemberg",
    "wof:name":"Klostergartenlaube",
    "wof:placetype":"venue"
},
  "geometry": {"coordinates":[9.149939537,49.0795707703],"type":"Point"}
}