{
  "type": "Feature",
  "properties": {
    "iso:country":"DE",
    "sg:address":"Rather Kreuzweg 62",
    "sg:city":"D\u00fcsseldorf",
    "sg:phone":"+49 211/656323",
    "sg:postcode":"40472",
    "sg:province":"Nordrhein-Westfalen",
    "wof:name":"Friedel K\u00fcster",
    "wof:placetype":"venue"
},
  "geometry": {"coordinates":[6.8050169945,51.2642211914],"type":"Point"}
}