{
  "type": "Feature",
  "properties": {
    "iso:country":"DE",
    "sg:address":"Ludwig-van-Beethoven-Str. 6",
    "sg:city":"Taucha",
    "sg:postcode":"04425",
    "sg:province":"Sachsen",
    "wof:name":"Angelika Klepel",
    "wof:placetype":"venue"
},
  "geometry": {"coordinates":[12.4947252274,51.377243042],"type":"Point"}
}