{
  "type": "Feature",
  "properties": {
    "iso:country":"DE",
    "sg:address":"Am Buckberg 5",
    "sg:city":"Leinburg",
    "sg:phone":"+49 9120/9661",
    "sg:postcode":"91227",
    "sg:province":"Bayern",
    "wof:name":"Johann Vogl",
    "wof:placetype":"venue"
},
  "geometry": {"coordinates":[11.295248,49.460625],"type":"Point"}
}