{
  "type": "Feature",
  "properties": {
    "iso:country":"DE",
    "sg:address":"Melchior-Otto-Platz 13",
    "sg:city":"Kronach",
    "sg:phone":"+49 9261/52100",
    "sg:postcode":"96317",
    "sg:province":"Bayern",
    "wof:name":"Alte Torwache",
    "wof:placetype":"venue"
},
  "geometry": {"coordinates":[11.3234558105,50.2408714294],"type":"Point"}
}