{
  "type": "Feature",
  "properties": {
    "iso:country":"DE",
    "sg:address":"Fabrikstr. 21",
    "sg:city":"Algermissen",
    "sg:phone":"+49 5126/2836",
    "sg:postcode":"31191",
    "sg:province":"Niedersachsen",
    "wof:name":"Baubetrieb Flacht & Wei\u00df Gmbh",
    "wof:placetype":"venue"
},
  "geometry": {"coordinates":[9.967566,52.280361],"type":"Point"}
}