{
  "type": "Feature",
  "properties": {
    "iso:country":"DE",
    "sg:address":"Barmer Str. 60",
    "sg:city":"Remscheid",
    "sg:phone":"+49 2191/53053",
    "sg:postcode":"42899",
    "sg:province":"Nordrhein-Westfalen",
    "wof:name":"G\u00dcha G\u00fcnter Halbach Gmbh & Co. Kg",
    "wof:placetype":"venue"
},
  "geometry": {"coordinates":[7.241157,51.218952],"type":"Point"}
}