{
  "type": "Feature",
  "properties": {
    "iso:country":"DE",
    "sg:address":"Querstr. 6",
    "sg:city":"Gotha",
    "sg:phone":"+49 3621/402387",
    "sg:postcode":"99867",
    "sg:province":"Th\u00fcringen",
    "wof:name":"Wolfgang Kestner",
    "wof:placetype":"venue"
},
  "geometry": {"coordinates":[10.703504,50.949669],"type":"Point"}
}