{
  "type": "Feature",
  "properties": {
    "iso:country":"DE",
    "sg:address":"Rudolf-Sch\u00f6nstedt-Str. 50",
    "sg:city":"Duisburg",
    "sg:postcode":"47053",
    "sg:province":"Nordrhein-Westfalen",
    "wof:name":"Bn Dachbau Gmbh",
    "wof:placetype":"venue"
},
  "geometry": {"coordinates":[6.7612380981,51.4122085571],"type":"Point"}
}