{
  "type": "Feature",
  "properties": {
    "iso:country":"DE",
    "sg:address":"Pechhofer Str. 16",
    "sg:city":"Pressath",
    "sg:phone":"+49 9644/368",
    "sg:postcode":"92690",
    "sg:province":"Bayern",
    "wof:name":"J. R\u00f6misch & S\u00f6hne Ohg",
    "wof:placetype":"venue"
},
  "geometry": {"coordinates":[11.9748382568,49.7253837585],"type":"Point"}
}