{
  "type": "Feature",
  "properties": {
    "iso:country":"DE",
    "sg:address":"Schulstra\u00dfe 9",
    "sg:city":"Landsham",
    "sg:phone":"+49 89/9010810",
    "sg:postcode":"85652",
    "sg:province":"Bayern",
    "wof:name":"Brandschadensanierung Baumeister",
    "wof:placetype":"venue"
},
  "geometry": {"coordinates":[11.773004,48.187683],"type":"Point"}
}