{
  "type": "Feature",
  "properties": {
    "iso:country":"DE",
    "sg:address":"Colmarer Str. 30",
    "sg:city":"Memmingen",
    "sg:phone":"+49 8331/3764",
    "sg:postcode":"87700",
    "sg:province":"Bayern",
    "wof:name":"Chr. Graber",
    "wof:placetype":"venue"
},
  "geometry": {"coordinates":[10.1819162369,47.9936637878],"type":"Point"}
}