{
  "type": "Feature",
  "properties": {
    "iso:country":"DE",
    "sg:address":"Alter Dorfweg 30-50",
    "sg:city":"Bremen",
    "sg:postcode":"28259",
    "sg:province":"Bremen",
    "wof:name":"Deutsche Telekom T-punkt",
    "wof:placetype":"venue"
},
  "geometry": {"coordinates":[8.740354538,53.048374176],"type":"Point"}
}