{
  "type": "Feature",
  "properties": {
    "iso:country":"DE",
    "sg:address":"Biemser Str. 28",
    "sg:city":"Bad Salzuflen",
    "sg:postcode":"32107",
    "sg:province":"Nordrhein-Westfalen",
    "wof:name":"Transportbeton- Gmbh Garant",
    "wof:placetype":"venue"
},
  "geometry": {"coordinates":[8.714715004,52.0791282654],"type":"Point"}
}