{
  "type": "Feature",
  "properties": {
    "iso:country":"DE",
    "sg:address":"Ludwigstr. 13",
    "sg:city":"Landstuhl",
    "sg:phone":"+49 6371/912549",
    "sg:postcode":"66849",
    "sg:province":"Rheinland-Pfalz",
    "wof:name":"Restaurant La Fontana",
    "wof:placetype":"venue"
},
  "geometry": {"coordinates":[7.5687379837,49.411113739],"type":"Point"}
}