{
  "type": "Feature",
  "properties": {
    "iso:country":"DE",
    "sg:address":"Werkstr. 4",
    "sg:city":"Schwerin",
    "sg:phone":"+49 385/645730",
    "sg:postcode":"19061",
    "sg:province":"Mecklenburg-Vorpommern",
    "wof:name":"Brock-baustoffe",
    "wof:placetype":"venue"
},
  "geometry": {"coordinates":[11.3880491257,53.5716018677],"type":"Point"}
}