{
  "type": "Feature",
  "properties": {
    "iso:country":"DE",
    "sg:address":"Buchenauer Str 29",
    "sg:city":"Biedenkopf",
    "sg:phone":"+49 6461/2684",
    "sg:postcode":"35216",
    "sg:province":"Hessen",
    "wof:name":"Redes",
    "wof:placetype":"venue"
},
  "geometry": {"coordinates":[8.5623903275,50.8748397827],"type":"Point"}
}