{
  "type": "Feature",
  "properties": {
    "iso:country":"DE",
    "sg:address":"Hildachstr. 16",
    "sg:city":"M\u00fcnchen",
    "sg:phone":"+49 89/8292940",
    "sg:postcode":"81245",
    "sg:province":"Bayern",
    "wof:name":"Schaffelhuber Gmbh & Co. Landmaschinen-ersatzteile Kg",
    "wof:placetype":"venue"
},
  "geometry": {"coordinates":[11.474125,48.147964],"type":"Point"}
}