{
  "type": "Feature",
  "properties": {
    "iso:country":"DE",
    "sg:address":"Warnstedtstr. 10",
    "sg:city":"Hamburg",
    "sg:phone":"+49 40/5406061",
    "sg:postcode":"22525",
    "sg:province":"Hamburg",
    "wof:name":"Adolf Hogrefe",
    "wof:placetype":"venue"
},
  "geometry": {"coordinates":[9.932149,53.583572],"type":"Point"}
}