{
  "type": "Feature",
  "properties": {
    "iso:country":"DE",
    "sg:address":"Gewerbestr. 12",
    "sg:city":"Lehrte",
    "sg:phone":"+49 5175/7051",
    "sg:postcode":"31275",
    "sg:province":"Niedersachsen",
    "wof:name":"Adco Attwods & Dixi Umweltschutz Gmbh",
    "wof:placetype":"venue"
},
  "geometry": {"coordinates":[10.1274833679,52.3607025146],"type":"Point"}
}