{
  "type": "Feature",
  "properties": {
    "iso:country":"DE",
    "sg:address":"Alte Turmstr. 6",
    "sg:city":"Aldenhoven",
    "sg:phone":"+49 2464/7173",
    "sg:postcode":"52457",
    "sg:province":"Nordrhein-Westfalen",
    "wof:name":"Hubert Beyss",
    "wof:placetype":"venue"
},
  "geometry": {"coordinates":[6.283129,50.895367],"type":"Point"}
}