{
  "type": "Feature",
  "properties": {
    "iso:country":"DE",
    "sg:address":"Rudolf-Diesel-Str. 23",
    "sg:city":"Riemerling",
    "sg:phone":"+49 89/6098040",
    "sg:postcode":"85521",
    "sg:province":"Bayern",
    "wof:name":"Reifen Widholzer Gmbh",
    "wof:placetype":"venue"
},
  "geometry": {"coordinates":[11.6735181808,48.055305481],"type":"Point"}
}