{
  "type": "Feature",
  "properties": {
    "iso:country":"DE",
    "sg:address":"Blumenstr. 8",
    "sg:city":"Landshut",
    "sg:phone":"+49 871/12954",
    "sg:postcode":"84032",
    "sg:province":"Bayern",
    "wof:name":"G\u00fcnter Kirchmeier",
    "wof:placetype":"venue"
},
  "geometry": {"coordinates":[12.1244974136,48.5497093201],"type":"Point"}
}