{
  "type": "Feature",
  "properties": {
    "iso:country":"DE",
    "sg:address":"Am Buchrain 5",
    "sg:city":"Gengenbach",
    "sg:phone":"+49 7803/5805",
    "sg:postcode":"77723",
    "sg:province":"Baden-W\u00fcrttemberg",
    "wof:name":"Wolfgang Bamberger",
    "wof:placetype":"venue"
},
  "geometry": {"coordinates":[8.016389,48.427132],"type":"Point"}
}