{
  "type": "Feature",
  "properties": {
    "iso:country":"DE",
    "sg:address":"Dinst\u00fchlerstr. 58",
    "sg:city":"H\u00fcckelhoven",
    "sg:phone":"+49 2433/1368",
    "sg:postcode":"41836",
    "sg:province":"Nordrhein-Westfalen",
    "wof:name":"J\u00e4gerhof",
    "wof:placetype":"venue"
},
  "geometry": {"coordinates":[6.2271699905,51.0510559082],"type":"Point"}
}