{
  "type": "Feature",
  "properties": {
    "iso:country":"DE",
    "sg:address":"Hansastr. 84",
    "sg:city":"Bochum",
    "sg:postcode":"44866",
    "sg:province":"Nordrhein-Westfalen",
    "wof:name":"Top Handel Net Gmbh",
    "wof:placetype":"venue"
},
  "geometry": {"coordinates":[7.154201,51.484303],"type":"Point"}
}