{
  "type": "Feature",
  "properties": {
    "iso:country":"DE",
    "sg:address":"Beim Industriehafen 49",
    "sg:city":"Bremen",
    "sg:phone":"+49 421/612024",
    "sg:postcode":"28237",
    "sg:province":"Bremen",
    "wof:name":"Hans Baltus Gmbh",
    "wof:placetype":"venue"
},
  "geometry": {"coordinates":[8.7168741226,53.1340255737],"type":"Point"}
}