{
  "type": "Feature",
  "properties": {
    "iso:country":"DE",
    "sg:address":"Quirnbacher Str. 9",
    "sg:city":"Vielbach",
    "sg:phone":"+49 2626/8613",
    "sg:postcode":"56244",
    "sg:province":"Rheinland-Pfalz",
    "wof:name":"Hans-joachim Jansson",
    "wof:placetype":"venue"
},
  "geometry": {"coordinates":[7.776088,50.509251],"type":"Point"}
}