{
  "type": "Feature",
  "properties": {
    "iso:country":"DE",
    "sg:address":"Im Guten Land 11",
    "sg:city":"Knopp-Labach",
    "sg:phone":"+49 6375/5485",
    "sg:postcode":"66917",
    "sg:province":"Rheinland-Pfalz",
    "wof:name":"Fremdenheim Labach",
    "wof:placetype":"venue"
},
  "geometry": {"coordinates":[7.5049438477,49.346862793],"type":"Point"}
}