{
  "type": "Feature",
  "properties": {
    "iso:country":"DE",
    "sg:address":"Mittelstr. 68",
    "sg:city":"Altenstadt",
    "sg:phone":"+49 6047/1844",
    "sg:postcode":"63674",
    "sg:province":"Hessen",
    "wof:name":"Otto M\u00e4drich",
    "wof:placetype":"venue"
},
  "geometry": {"coordinates":[8.924983,50.271183],"type":"Point"}
}