{
  "type": "Feature",
  "properties": {
    "iso:country":"DE",
    "sg:address":"Stra\u00dfburger Weg 5",
    "sg:city":"Halle",
    "sg:phone":"+49 345/558840",
    "sg:postcode":"06120",
    "sg:province":"Sachsen-Anhalt",
    "wof:name":"Gs Immobilien Gmbh",
    "wof:placetype":"venue"
},
  "geometry": {"coordinates":[11.9386863708,51.4988746643],"type":"Point"}
}