{
  "type": "Feature",
  "properties": {
    "iso:country":"DE",
    "sg:address":"Rheinstr. 614",
    "sg:city":"Kalkar",
    "sg:postcode":"47546",
    "sg:province":"Nordrhein-Westfalen",
    "wof:name":"Euro-wachdienst Beteiligungsges. Mbh",
    "wof:placetype":"venue"
},
  "geometry": {"coordinates":[6.3642549515,51.74792099],"type":"Point"}
}