{
  "type": "Feature",
  "properties": {
    "iso:country":"DE",
    "sg:address":"Schillerstr. 30",
    "sg:city":"Besigheim",
    "sg:phone":"+49 69/9218850",
    "sg:postcode":"74354",
    "sg:province":"Baden-W\u00fcrttemberg",
    "wof:name":"Kling Jelko Wertpapierhandelsbank Ag",
    "wof:placetype":"venue"
},
  "geometry": {"coordinates":[8.675442,50.113674],"type":"Point"}
}