{
  "type": "Feature",
  "properties": {
    "iso:country":"DE",
    "sg:address":"Hauptstr. 23",
    "sg:city":"Haldenwang",
    "sg:phone":"+49 8374/25030",
    "sg:postcode":"87490",
    "sg:province":"Bayern",
    "wof:name":"Cafe Hirsch",
    "wof:placetype":"venue"
},
  "geometry": {"coordinates":[10.346262,47.801685],"type":"Point"}
}