{
  "type": "Feature",
  "properties": {
    "iso:country":"DE",
    "sg:address":"F\u00fcrstenbergerstr. 229",
    "sg:city":"Frankfurt",
    "sg:postcode":"60323",
    "sg:province":"Hessen",
    "wof:name":"Josef-buchmann-stiftung",
    "wof:placetype":"venue"
},
  "geometry": {"coordinates":[8.6669788361,50.1237297058],"type":"Point"}
}