{
  "type": "Feature",
  "properties": {
    "iso:country":"DE",
    "sg:address":"Adelenstr. 33",
    "sg:city":"Dortmund",
    "sg:phone":"+49 231/441495",
    "sg:postcode":"44269",
    "sg:province":"Nordrhein-Westfalen",
    "wof:name":"J\u00f6rg Wefing Architekt",
    "wof:placetype":"venue"
},
  "geometry": {"coordinates":[7.530215,51.490906],"type":"Point"}
}