{
  "type": "Feature",
  "properties": {
    "iso:country":"DE",
    "sg:address":"Richtersh\u00f6he 13",
    "sg:city":"Lutter",
    "sg:phone":"+49 5383/8634",
    "sg:postcode":"38729",
    "sg:province":"Niedersachsen",
    "wof:name":"Gottschalk - Erdbau Gmbh",
    "wof:placetype":"venue"
},
  "geometry": {"coordinates":[10.2721643448,51.9922332764],"type":"Point"}
}