{
  "type": "Feature",
  "properties": {
    "iso:country":"DE",
    "sg:address":"Im Grafeld 35",
    "sg:city":"Bergisch Gladbach",
    "sg:phone":"+49 2202/21249",
    "sg:postcode":"51469",
    "sg:province":"Nordrhein-Westfalen",
    "wof:name":"Hans Denseler",
    "wof:placetype":"venue"
},
  "geometry": {"coordinates":[7.0905098915,50.9903106689],"type":"Point"}
}