{
  "type": "Feature",
  "properties": {
    "iso:country":"DE",
    "sg:address":"Liebenzeller Str. 51",
    "sg:city":"Calw",
    "sg:phone":"+49 7051/59605",
    "sg:postcode":"75365",
    "sg:province":"Baden-W\u00fcrttemberg",
    "wof:name":"Tengelmann-markt",
    "wof:placetype":"venue"
},
  "geometry": {"coordinates":[8.732011795,48.7408599854],"type":"Point"}
}