{
  "type": "Feature",
  "properties": {
    "iso:country":"DE",
    "sg:address":"Altendorf 1",
    "sg:city":"Nordhausen",
    "sg:phone":"+49 3631/900877",
    "sg:postcode":"99734",
    "sg:province":"Th\u00fcringen",
    "wof:name":"Katrin Eberhardt",
    "wof:placetype":"venue"
},
  "geometry": {"coordinates":[10.790597,51.50602],"type":"Point"}
}