{
  "type": "Feature",
  "properties": {
    "iso:country":"DE",
    "sg:address":"Marktplatz 6",
    "sg:city":"Magstadt",
    "sg:phone":"+49 7159/41563",
    "sg:postcode":"71106",
    "sg:province":"Baden-W\u00fcrttemberg",
    "wof:name":"Heimatmuseum Magstadt",
    "wof:placetype":"venue"
},
  "geometry": {"coordinates":[8.963495,48.742081],"type":"Point"}
}