{
  "type": "Feature",
  "properties": {
    "iso:country":"DE",
    "sg:address":"Zum Sportplatz",
    "sg:city":"Hahnheim",
    "sg:phone":"+49 6133/59410",
    "sg:postcode":"55278",
    "sg:province":"Rheinland-Pfalz",
    "wof:name":"Tus Dexheim 1848 E. V.",
    "wof:placetype":"venue"
},
  "geometry": {"coordinates":[8.2455301285,49.8611755371],"type":"Point"}
}