{
  "type": "Feature",
  "properties": {
    "iso:country":"DE",
    "sg:address":"Schnakenburg 13",
    "sg:city":"Dassel",
    "sg:postcode":"37586",
    "sg:province":"Niedersachsen",
    "wof:name":"M. Thiele Restaurator",
    "wof:placetype":"venue"
},
  "geometry": {"coordinates":[9.7206087112,51.7741546631],"type":"Point"}
}