{
  "type": "Feature",
  "properties": {
    "iso:country":"DE",
    "sg:address":"Hohe Str. 57",
    "sg:city":"Dortmund",
    "sg:phone":"+49 231/121906",
    "sg:postcode":"44139",
    "sg:province":"Nordrhein-Westfalen",
    "wof:name":"Strathmann Inh. M. H\u00f6per",
    "wof:placetype":"venue"
},
  "geometry": {"coordinates":[7.459043026,51.5048408508],"type":"Point"}
}