{
  "type": "Feature",
  "properties": {
    "iso:country":"DE",
    "sg:address":"Friedrich-Borgwardt-Str. 27",
    "sg:city":"K\u00fchlungsborn",
    "sg:phone":"+49 38293/14823",
    "sg:postcode":"18225",
    "sg:province":"Mecklenburg-Vorpommern",
    "wof:name":"J\u00fcrgen Plaschke Hausservice Gmbh",
    "wof:placetype":"venue"
},
  "geometry": {"coordinates":[11.7298660278,54.1496887207],"type":"Point"}
}