{
  "type": "Feature",
  "properties": {
    "iso:country":"DE",
    "sg:address":"Brandfeldweg 18",
    "sg:city":"R\u00f6hrmoos",
    "sg:phone":"+49 8139/352",
    "sg:postcode":"85244",
    "sg:province":"Bayern",
    "wof:name":"Egbert Czerny Finanzberater",
    "wof:placetype":"venue"
},
  "geometry": {"coordinates":[11.4164400101,48.3220405579],"type":"Point"}
}