{
  "type": "Feature",
  "properties": {
    "iso:country":"DE",
    "sg:address":"B\u00f6heimstr. 45",
    "sg:city":"Stuttgart",
    "sg:phone":"+49 711/60173430",
    "sg:postcode":"70199",
    "sg:province":"Baden-W\u00fcrttemberg",
    "wof:name":"Sch\u00f6bitz Und Sch\u00f6bitz Rechtsanwalte",
    "wof:placetype":"venue"
},
  "geometry": {"coordinates":[9.1613283157,48.761013031],"type":"Point"}
}