{
  "type": "Feature",
  "properties": {
    "iso:country":"DE",
    "sg:address":"Henschelstr. 1",
    "sg:city":"Ritterhude",
    "sg:phone":"+49 421/6162501",
    "sg:postcode":"27721",
    "sg:province":"Niedersachsen",
    "wof:name":"Hansa Tec Hebe- Und Zurrtechnik Gmbh",
    "wof:placetype":"venue"
},
  "geometry": {"coordinates":[8.7609710693,53.1936645508],"type":"Point"}
}