{
  "type": "Feature",
  "properties": {
    "iso:country":"DE",
    "sg:address":"Hauptstr. 108",
    "sg:city":"Weibersbrunn",
    "sg:phone":"+49 6094/360",
    "sg:postcode":"63879",
    "sg:province":"Bayern",
    "wof:name":"Irma Amrhein Inh. Silvia Haun",
    "wof:placetype":"venue"
},
  "geometry": {"coordinates":[9.365299,49.930882],"type":"Point"}
}