{
  "type": "Feature",
  "properties": {
    "iso:country":"DE",
    "sg:address":"Kirchplatz 1",
    "sg:city":"Durbach",
    "sg:phone":"+49 781/41121",
    "sg:postcode":"77770",
    "sg:province":"Baden-W\u00fcrttemberg",
    "wof:name":"Paul M\u00fcller",
    "wof:placetype":"venue"
},
  "geometry": {"coordinates":[8.016819,48.494698],"type":"Point"}
}