{
  "type": "Feature",
  "properties": {
    "iso:country":"DE",
    "sg:address":"Beerenstr. 43",
    "sg:city":"Berlin",
    "sg:postcode":"14163",
    "sg:province":"Berlin",
    "wof:name":"Gr\u00e4flich Von Wilamowitz- Moellendorff Vermittlungs- Und",
    "wof:placetype":"venue"
},
  "geometry": {"coordinates":[13.236155,52.437214],"type":"Point"}
}