{
  "type": "Feature",
  "properties": {
    "iso:country":"DE",
    "sg:address":"Friedrichstr. 108",
    "sg:city":"Berlin",
    "sg:phone":"+49 4930/231220",
    "sg:postcode":"10117",
    "sg:province":"Berlin",
    "wof:name":"Ddp",
    "wof:placetype":"venue"
},
  "geometry": {"coordinates":[13.38779,52.524597],"type":"Point"}
}