{
  "type": "Feature",
  "properties": {
    "iso:country":"DE",
    "sg:address":"Moosl\u00e4ngstr. 6",
    "sg:city":"Puchheim",
    "sg:phone":"+49 89/803417",
    "sg:postcode":"82178",
    "sg:province":"Bayern",
    "wof:name":"Fritz Dulas",
    "wof:placetype":"venue"
},
  "geometry": {"coordinates":[11.349325,48.161865],"type":"Point"}
}