{
  "type": "Feature",
  "properties": {
    "iso:country":"DE",
    "sg:address":"Brunnenstr. 10",
    "sg:city":"Sinzing",
    "sg:phone":"+49 9404/2070",
    "sg:postcode":"93161",
    "sg:province":"Bayern",
    "wof:name":"Georg Emmerl",
    "wof:placetype":"venue"
},
  "geometry": {"coordinates":[11.960729,48.977192],"type":"Point"}
}