{
  "type": "Feature",
  "properties": {
    "iso:country":"DE",
    "sg:address":"Hauptstr. 3",
    "sg:city":"Wadgassen",
    "sg:phone":"+49 6834/6693",
    "sg:postcode":"66787",
    "sg:province":"Saarland",
    "wof:name":"Ottilie Tasch",
    "wof:placetype":"venue"
},
  "geometry": {"coordinates":[6.777756,49.242046],"type":"Point"}
}