{
  "type": "Feature",
  "properties": {
    "iso:country":"DE",
    "sg:address":"Prinzregentenstr. 2",
    "sg:city":"Bad Kissingen",
    "sg:phone":"+49 971/2355",
    "sg:postcode":"97688",
    "sg:province":"Bayern",
    "wof:name":"Hubers Gute Stube",
    "wof:placetype":"venue"
},
  "geometry": {"coordinates":[10.07771,50.198864],"type":"Point"}
}