{
  "type": "Feature",
  "properties": {
    "iso:country":"DE",
    "sg:address":"L\u00fche 57 a",
    "sg:city":"Jork",
    "sg:phone":"+49 4142/2275",
    "sg:postcode":"21635",
    "sg:province":"Niedersachsen",
    "wof:name":"Uwe K\u00f6pcke",
    "wof:placetype":"venue"
},
  "geometry": {"coordinates":[9.6394443512,53.5669288635],"type":"Point"}
}