{
  "type": "Feature",
  "properties": {
    "iso:country":"DE",
    "sg:address":"Ellmaierstr. 2",
    "sg:city":"Rosenheim",
    "sg:phone":"+49 8031/31641",
    "sg:postcode":"83022",
    "sg:province":"Bayern",
    "wof:name":"Video Holiday Freizeitbetriebe Gmbh",
    "wof:placetype":"venue"
},
  "geometry": {"coordinates":[12.1285037994,47.8585128784],"type":"Point"}
}