{
  "type": "Feature",
  "properties": {
    "iso:country":"DE",
    "sg:address":"Bahnhofstr. 22",
    "sg:city":"Neu-Isenburg",
    "sg:phone":"+49 6102/89992",
    "sg:postcode":"63263",
    "sg:province":"Hessen",
    "wof:name":"Altan",
    "wof:placetype":"venue"
},
  "geometry": {"coordinates":[8.6928157806,50.0533180237],"type":"Point"}
}