{
  "type": "Feature",
  "properties": {
    "iso:country":"DE",
    "sg:address":"Parlerstr. 9",
    "sg:city":"Schw\u00e4bisch Gm\u00fcnd",
    "sg:phone":"+49 7171/63026",
    "sg:postcode":"73525",
    "sg:province":"Baden-W\u00fcrttemberg",
    "wof:name":"Gentner",
    "wof:placetype":"venue"
},
  "geometry": {"coordinates":[9.793615,48.797604],"type":"Point"}
}