{
  "type": "Feature",
  "properties": {
    "iso:country":"DE",
    "sg:address":"Stadel 15",
    "sg:city":"Regenstauf",
    "sg:phone":"+49 9402/4561",
    "sg:postcode":"93128",
    "sg:province":"Bayern",
    "wof:name":"Christian Wiedenmann",
    "wof:placetype":"venue"
},
  "geometry": {"coordinates":[12.157910347,49.1466598511],"type":"Point"}
}