{
  "type": "Feature",
  "properties": {
    "iso:country":"DE",
    "sg:address":"G\u00f6belstr. 8",
    "sg:city":"Barsinghausen",
    "sg:phone":"+49 4951/0552410",
    "sg:postcode":"30890",
    "sg:province":"Niedersachsen",
    "wof:name":"Franz Brand M\u00d6bel- U. Innenausbau Gmbh",
    "wof:placetype":"venue"
},
  "geometry": {"coordinates":[9.485442,52.301651],"type":"Point"}
}