{
  "type": "Feature",
  "properties": {
    "iso:country":"DE",
    "sg:address":"Bismarckstr. 25",
    "sg:city":"K\u00f6ln",
    "sg:phone":"+49 221/516691",
    "sg:postcode":"50672",
    "sg:province":"Nordrhein-Westfalen",
    "wof:name":"E. Schneider",
    "wof:placetype":"venue"
},
  "geometry": {"coordinates":[6.9362039566,50.9415397644],"type":"Point"}
}