{
  "type": "Feature",
  "properties": {
    "iso:country":"DE",
    "sg:address":"Derentaler Str. 10",
    "sg:city":"Holzminden",
    "sg:phone":"+49 5536/1200",
    "sg:postcode":"37603",
    "sg:province":"Niedersachsen",
    "wof:name":"Angelika Reuter",
    "wof:placetype":"venue"
},
  "geometry": {"coordinates":[9.514184,51.748581],"type":"Point"}
}