{
  "type": "Feature",
  "properties": {
    "iso:country":"DE",
    "sg:address":"Ootmarsumer Weg 197",
    "sg:city":"Nordhorn",
    "sg:phone":"+49 5921/994920",
    "sg:postcode":"48527",
    "sg:province":"Niedersachsen",
    "wof:name":"G. Nierste",
    "wof:placetype":"venue"
},
  "geometry": {"coordinates":[7.0286140442,52.4252586365],"type":"Point"}
}