{
  "type": "Feature",
  "properties": {
    "iso:country":"DE",
    "sg:address":"Wellendinger Str. 48",
    "sg:city":"Sch\u00f6mberg",
    "sg:phone":"+49 7427/2441",
    "sg:postcode":"72355",
    "sg:province":"Baden-W\u00fcrttemberg",
    "wof:name":"Selle Ledermode Gmbh",
    "wof:placetype":"venue"
},
  "geometry": {"coordinates":[8.756047,48.201603],"type":"Point"}
}