{
  "type": "Feature",
  "properties": {
    "iso:country":"DE",
    "sg:address":"Grabengasse 7",
    "sg:city":"Heidelberg",
    "sg:phone":"+49 6221/25757",
    "sg:postcode":"69117",
    "sg:province":"Baden-W\u00fcrttemberg",
    "wof:name":"G. Romer Wohnbedarf Gmbh",
    "wof:placetype":"venue"
},
  "geometry": {"coordinates":[8.70671,49.409599],"type":"Point"}
}