{
  "type": "Feature",
  "properties": {
    "iso:country":"DE",
    "sg:address":"Lindenstr. 67 a",
    "sg:city":"L\u00fcbeck",
    "sg:phone":"+49 451/82794",
    "sg:postcode":"23558",
    "sg:province":"Schleswig-Holstein",
    "wof:name":"A. Hoch",
    "wof:placetype":"venue"
},
  "geometry": {"coordinates":[10.6654338837,53.8616142273],"type":"Point"}
}