{
  "type": "Feature",
  "properties": {
    "iso:country":"DE",
    "sg:address":"Ingolst\u00e4dter Str. 21-25",
    "sg:city":"Schrobenhausen",
    "sg:postcode":"86529",
    "sg:province":"Bayern",
    "wof:name":"Max W\u00f6hrl Gmbh",
    "wof:placetype":"venue"
},
  "geometry": {"coordinates":[11.2786941528,48.567615509],"type":"Point"}
}