{
  "type": "Feature",
  "properties": {
    "iso:country":"DE",
    "sg:address":"Schulbergstr. 15",
    "sg:city":"Apolda",
    "sg:phone":"+49 3644/559100",
    "sg:postcode":"99510",
    "sg:province":"Th\u00fcringen",
    "wof:name":"Matthias Folgert Steuerberater",
    "wof:placetype":"venue"
},
  "geometry": {"coordinates":[11.5081377029,51.0257797241],"type":"Point"}
}