{
  "type": "Feature",
  "properties": {
    "iso:country":"DE",
    "sg:address":"Sch\u00fctzenstr. 24",
    "sg:city":"Gummersbach",
    "sg:phone":"+49 2261/29219",
    "sg:postcode":"51643",
    "sg:province":"Nordrhein-Westfalen",
    "wof:name":"Kottsieper",
    "wof:placetype":"venue"
},
  "geometry": {"coordinates":[7.5676140785,51.0276298523],"type":"Point"}
}