{
  "type": "Feature",
  "properties": {
    "iso:country":"DE",
    "sg:address":"Fleischmannstr. 10",
    "sg:city":"Esslingen",
    "sg:phone":"+49 711/352385",
    "sg:postcode":"73728",
    "sg:province":"Baden-W\u00fcrttemberg",
    "wof:name":"Staufeneck",
    "wof:placetype":"venue"
},
  "geometry": {"coordinates":[9.2996473312,48.7402458191],"type":"Point"}
}