{
  "type": "Feature",
  "properties": {
    "iso:country":"DE",
    "sg:address":"Alte Poststr. 3",
    "sg:city":"Stuttgart",
    "sg:phone":"+49 711/2265947",
    "sg:postcode":"70173",
    "sg:province":"Baden-W\u00fcrttemberg",
    "wof:name":"Optik Friedemann & Tr\u00f6ster Inh. Bernhard Rieger",
    "wof:placetype":"venue"
},
  "geometry": {"coordinates":[9.1743679047,48.7744026184],"type":"Point"}
}