{
  "type": "Feature",
  "properties": {
    "iso:country":"DE",
    "sg:address":"Rigipsstr. 27",
    "sg:city":"Herrenberg",
    "sg:phone":"+49 7032/97700",
    "sg:postcode":"71083",
    "sg:province":"Baden-W\u00fcrttemberg",
    "wof:name":"E. Sauer",
    "wof:placetype":"venue"
},
  "geometry": {"coordinates":[8.8841285706,48.5774269104],"type":"Point"}
}