{
  "type": "Feature",
  "properties": {
    "iso:country":"DE",
    "sg:address":"Am Alten Eisenwerk 6",
    "sg:city":"L\u00fcneburg",
    "sg:phone":"+49 4131/233000",
    "sg:postcode":"21339",
    "sg:province":"Niedersachsen",
    "wof:name":"Heidenreich Elektrotechnik Und Elektromaschinenbau Gmbh",
    "wof:placetype":"venue"
},
  "geometry": {"coordinates":[10.411695,53.258076],"type":"Point"}
}