{
  "type": "Feature",
  "properties": {
    "iso:country":"DE",
    "sg:address":"Diedenhofener Str. 3a",
    "sg:city":"Trier",
    "sg:phone":"+49 651/99849500",
    "sg:postcode":"54294",
    "sg:province":"Rheinland-Pfalz",
    "wof:name":"Helmut Junkes Gmbh",
    "wof:placetype":"venue"
},
  "geometry": {"coordinates":[6.610024,49.731033],"type":"Point"}
}