{
  "type": "Feature",
  "properties": {
    "iso:country":"DE",
    "sg:address":"Nikolaistr. 57",
    "sg:city":"Leipzig",
    "sg:phone":"+49 341/9803892",
    "sg:postcode":"04109",
    "sg:province":"Sachsen",
    "wof:name":"Karin Angermann",
    "wof:placetype":"venue"
},
  "geometry": {"coordinates":[12.3783092499,51.3432235718],"type":"Point"}
}