{
  "type": "Feature",
  "properties": {
    "iso:country":"DE",
    "sg:address":"Achtstr. 12",
    "sg:city":"Birkenfeld",
    "sg:phone":"+49 6782/3770",
    "sg:postcode":"55765",
    "sg:province":"Rheinland-Pfalz",
    "wof:name":"Offterdinger-zender Gmbh",
    "wof:placetype":"venue"
},
  "geometry": {"coordinates":[7.1680631638,49.6494445801],"type":"Point"}
}