{
  "type": "Feature",
  "properties": {
    "iso:country":"DE",
    "sg:address":"Br\u00fcckenstr. 12",
    "sg:city":"L\u00f6rrach",
    "sg:phone":"+49 7621/949130",
    "sg:postcode":"79541",
    "sg:province":"Baden-W\u00fcrttemberg",
    "wof:name":"Ulrich Tr\u00f6ndlin",
    "wof:placetype":"venue"
},
  "geometry": {"coordinates":[7.694749,47.64143],"type":"Point"}
}