{
  "type": "Feature",
  "properties": {
    "iso:country":"DE",
    "sg:address":"Ilshofener Str.",
    "sg:city":"Ilshofen",
    "sg:phone":"+49 7904/7734",
    "sg:postcode":"74532",
    "sg:province":"Baden-W\u00fcrttemberg",
    "wof:name":"Restaurant Pizza Alla Casa",
    "wof:placetype":"venue"
},
  "geometry": {"coordinates":[9.9304256439,49.153553009],"type":"Point"}
}