{
  "type": "Feature",
  "properties": {
    "iso:country":"DE",
    "sg:address":"Sirnauer Str. 50",
    "sg:city":"Deizisau",
    "sg:phone":"+49 7153/83850",
    "sg:postcode":"73779",
    "sg:province":"Baden-W\u00fcrttemberg",
    "wof:name":"Hs J\u00fcrgen Schmidt Gmbh",
    "wof:placetype":"venue"
},
  "geometry": {"coordinates":[9.3767795563,48.7140731812],"type":"Point"}
}