{
  "type": "Feature",
  "properties": {
    "iso:country":"DE",
    "sg:address":"Gebr\u00fcder-Netzsch-Str. 19",
    "sg:city":"Selb",
    "sg:phone":"+49 9287/750",
    "sg:postcode":"95100",
    "sg:province":"Bayern",
    "wof:name":"Erich Netzsch Gmbh & Co. Holding Kg",
    "wof:placetype":"venue"
},
  "geometry": {"coordinates":[12.1411018372,50.1752738953],"type":"Point"}
}