{
  "type": "Feature",
  "properties": {
    "iso:country":"DE",
    "sg:address":"Jupiterstr. 44a",
    "sg:city":"Leipzig",
    "sg:phone":"+49 341/4229873",
    "sg:postcode":"04205",
    "sg:province":"Sachsen",
    "wof:name":"Reisewelt Europ\u00e4isches Reiseb\u00fcro Gmbh",
    "wof:placetype":"venue"
},
  "geometry": {"coordinates":[12.2715463638,51.3215446472],"type":"Point"}
}