{
  "type": "Feature",
  "properties": {
    "iso:country":"DE",
    "sg:address":"August - Bebel - Platz 2",
    "sg:city":"Deetz",
    "sg:phone":"+49 33207",
    "sg:postcode":"14550",
    "sg:province":"Brandenburg",
    "wof:name":"Hausverwaltung Heike Kretschmer",
    "wof:placetype":"venue"
},
  "geometry": {"coordinates":[12.771073,52.44556],"type":"Point"}
}