{
  "type": "Feature",
  "properties": {
    "iso:country":"DE",
    "sg:address":"Bergstr. 1",
    "sg:city":"Pfronstetten",
    "sg:phone":"+49 7373/622",
    "sg:postcode":"72539",
    "sg:province":"Baden-W\u00fcrttemberg",
    "wof:name":"G. Kerber",
    "wof:placetype":"venue"
},
  "geometry": {"coordinates":[9.400489,48.235226],"type":"Point"}
}