{
  "type": "Feature",
  "properties": {
    "iso:country":"DE",
    "sg:address":"Mittelh\u00e4user Str. 28",
    "sg:city":"Erfurt",
    "sg:postcode":"99089",
    "sg:province":"Th\u00fcringen",
    "wof:name":"Kraftfahrzeug Handels- Und Servicegesellschaft Mok",
    "wof:placetype":"venue"
},
  "geometry": {"coordinates":[11.0154848099,51.0107650757],"type":"Point"}
}