{
  "type": "Feature",
  "properties": {
    "iso:country":"DE",
    "sg:address":"Semmelweisstr. 13",
    "sg:city":"Camburg",
    "sg:phone":"+49 36421/22335",
    "sg:postcode":"07774",
    "sg:province":"Th\u00fcringen",
    "wof:name":"Dr. Alders Tiernahrung Gmbh",
    "wof:placetype":"venue"
},
  "geometry": {"coordinates":[11.70391,51.058224],"type":"Point"}
}