{
  "type": "Feature",
  "properties": {
    "iso:country":"DE",
    "sg:address":"Gebbertstr. 38",
    "sg:city":"Erlangen",
    "sg:phone":"+49 9131/22766",
    "sg:postcode":"91052",
    "sg:province":"Bayern",
    "wof:name":"Deutsche Shell Ag",
    "wof:placetype":"venue"
},
  "geometry": {"coordinates":[11.017493248,49.593875885],"type":"Point"}
}