{
  "type": "Feature",
  "properties": {
    "iso:country":"DE",
    "sg:address":"Bieberstr. 16",
    "sg:city":"Arnsberg",
    "sg:phone":"+49 2932/33869",
    "sg:postcode":"59757",
    "sg:province":"Nordrhein-Westfalen",
    "wof:name":"Heinz Loh\u00f6lter",
    "wof:placetype":"venue"
},
  "geometry": {"coordinates":[7.9382472038,51.4180183411],"type":"Point"}
}