{
  "type": "Feature",
  "properties": {
    "iso:country":"DE",
    "sg:address":"Hasenweg 16",
    "sg:city":"Elchingen",
    "sg:phone":"+49 731/264200",
    "sg:postcode":"89275",
    "sg:province":"Bayern",
    "wof:name":"G\u00fcnther Mitsche",
    "wof:placetype":"venue"
},
  "geometry": {"coordinates":[10.052444,48.443264],"type":"Point"}
}