{
  "type": "Feature",
  "properties": {
    "iso:country":"DE",
    "sg:address":"Rudolf-Diesel-Str. 29",
    "sg:city":"M\u00fcnster",
    "sg:phone":"+49 251/272714",
    "sg:postcode":"48157",
    "sg:province":"Nordrhein-Westfalen",
    "wof:name":"Wothke-weber",
    "wof:placetype":"venue"
},
  "geometry": {"coordinates":[7.66832,51.990238],"type":"Point"}
}