{
  "type": "Feature",
  "properties": {
    "iso:country":"DE",
    "sg:address":"Alte Bahnhofstr. 24",
    "sg:city":"St. Ingbert",
    "sg:phone":"+49 6894/3370",
    "sg:postcode":"66386",
    "sg:province":"Saarland",
    "wof:name":"B. Jost",
    "wof:placetype":"venue"
},
  "geometry": {"coordinates":[7.1140232086,49.2763366699],"type":"Point"}
}