{
  "type": "Feature",
  "properties": {
    "iso:country":"DE",
    "sg:address":"Robert-Bosch-Str 5",
    "sg:city":"Mayen",
    "sg:phone":"+49 2651/98870",
    "sg:postcode":"56727",
    "sg:province":"Rheinland-Pfalz",
    "wof:name":"Wilh. Schmitt Gmbh",
    "wof:placetype":"venue"
},
  "geometry": {"coordinates":[7.216376,50.323193],"type":"Point"}
}