{
  "type": "Feature",
  "properties": {
    "iso:country":"DE",
    "sg:address":"Sauerlandstr. 9",
    "sg:city":"Warstein",
    "sg:phone":"+49 2925/8080",
    "sg:postcode":"59581",
    "sg:province":"Nordrhein-Westfalen",
    "wof:name":"Objekta St\u00f6rmann Gmbh & Co. Kg",
    "wof:placetype":"venue"
},
  "geometry": {"coordinates":[8.2284078598,51.4733123779],"type":"Point"}
}