{
  "type": "Feature",
  "properties": {
    "iso:country":"DE",
    "sg:address":"Osterstr. 16-18",
    "sg:city":"Detern",
    "sg:phone":"+49 4957/1055",
    "sg:postcode":"26847",
    "sg:province":"Niedersachsen",
    "wof:name":"Focko L\u00fcpsen & Sohn Gmbh",
    "wof:placetype":"venue"
},
  "geometry": {"coordinates":[7.678632,53.210537],"type":"Point"}
}