{
  "type": "Feature",
  "properties": {
    "iso:country":"DE",
    "sg:address":"Milanweg 8a",
    "sg:city":"Gro\u00dfbeeren",
    "sg:phone":"+49 33701/55712",
    "sg:postcode":"14979",
    "sg:province":"Brandenburg",
    "wof:name":"Kath Gmbh",
    "wof:placetype":"venue"
},
  "geometry": {"coordinates":[13.3113021851,52.3699073792],"type":"Point"}
}