{
  "type": "Feature",
  "properties": {
    "iso:country":"DE",
    "sg:address":"Lange Reihe 71",
    "sg:city":"Hamburg",
    "sg:postcode":"20099",
    "sg:province":"Hamburg",
    "wof:name":"Bo Unterhaltungs- Produktion E. K.",
    "wof:placetype":"venue"
},
  "geometry": {"coordinates":[10.011852,53.558086],"type":"Point"}
}