{
  "type": "Feature",
  "properties": {
    "iso:country":"DE",
    "sg:address":"Heumarkt 14",
    "sg:city":"K\u00f6ln",
    "sg:postcode":"50667",
    "sg:province":"Nordrhein-Westfalen",
    "wof:name":"Euro-innopart Produktentwicklungs- Und",
    "wof:placetype":"venue"
},
  "geometry": {"coordinates":[6.961618,50.934742],"type":"Point"}
}