{
  "type": "Feature",
  "properties": {
    "iso:country":"DE",
    "sg:address":"Bonner Str. 7",
    "sg:city":"Bad Soden-Salm\u00fcnster",
    "sg:phone":"+49 6056/2333",
    "sg:postcode":"63628",
    "sg:province":"Hessen",
    "wof:name":"B. Nitsche & W. Wunderlich",
    "wof:placetype":"venue"
},
  "geometry": {"coordinates":[9.367318,50.266117],"type":"Point"}
}