{
  "type": "Feature",
  "properties": {
    "iso:country":"DE",
    "sg:address":"Kalkumer Str. 152",
    "sg:city":"D\u00fcsseldorf",
    "sg:phone":"+49 211/4708012",
    "sg:postcode":"40468",
    "sg:province":"Nordrhein-Westfalen",
    "wof:name":"Middlesex Metall",
    "wof:placetype":"venue"
},
  "geometry": {"coordinates":[6.774076,51.272781],"type":"Point"}
}