{
  "type": "Feature",
  "properties": {
    "iso:country":"DE",
    "sg:address":"Gerbergasse 10",
    "sg:city":"M\u00fcnchberg",
    "sg:phone":"+49 9251/85605",
    "sg:postcode":"95213",
    "sg:province":"Bayern",
    "wof:name":"R. Fraas",
    "wof:placetype":"venue"
},
  "geometry": {"coordinates":[11.787718,50.191082],"type":"Point"}
}