{
  "type": "Feature",
  "properties": {
    "iso:country":"DE",
    "sg:address":"Westerweder Str. 20",
    "sg:city":"Lilienthal",
    "sg:phone":"+49 4792/7415",
    "sg:postcode":"28865",
    "sg:province":"Niedersachsen",
    "wof:name":"Gustav Geffken",
    "wof:placetype":"venue"
},
  "geometry": {"coordinates":[8.927984,53.201786],"type":"Point"}
}