{
  "type": "Feature",
  "properties": {
    "iso:country":"DE",
    "sg:address":"Appenzeller Str. 113",
    "sg:city":"M\u00fcnchen",
    "sg:phone":"+49 89/7556424",
    "sg:postcode":"81475",
    "sg:province":"Bayern",
    "wof:name":"Gigl Und Breithaupt Werbeartikel",
    "wof:placetype":"venue"
},
  "geometry": {"coordinates":[11.4747619629,48.0920600891],"type":"Point"}
}