{
  "type": "Feature",
  "properties": {
    "iso:country":"DE",
    "sg:address":"Braustr. 38",
    "sg:city":"Wei\u00dfenbrunn",
    "sg:phone":"+49 9261/3948",
    "sg:postcode":"96369",
    "sg:province":"Bayern",
    "wof:name":"H. Und H. Roth",
    "wof:placetype":"venue"
},
  "geometry": {"coordinates":[11.349383,50.197952],"type":"Point"}
}