{
  "type": "Feature",
  "properties": {
    "iso:country":"DE",
    "sg:address":"Winckelmannstr. 3",
    "sg:city":"Wuppertal",
    "sg:phone":"+49 202/594401",
    "sg:postcode":"42287",
    "sg:province":"Nordrhein-Westfalen",
    "wof:name":"Salzburger Verein Horst Leiber",
    "wof:placetype":"venue"
},
  "geometry": {"coordinates":[7.1957831383,51.2454032898],"type":"Point"}
}