{
  "type": "Feature",
  "properties": {
    "iso:country":"DE",
    "sg:address":"Wibbeltstr. 39",
    "sg:city":"Kranenburg",
    "sg:phone":"+49 2826/5290",
    "sg:postcode":"47559",
    "sg:province":"Nordrhein-Westfalen",
    "wof:name":"Kath. Pfarramt St. Martinus",
    "wof:placetype":"venue"
},
  "geometry": {"coordinates":[6.0495400429,51.8111610413],"type":"Point"}
}