{
  "type": "Feature",
  "properties": {
    "iso:country":"DE",
    "sg:address":"Eisenbahnstr.",
    "sg:city":"Senftenberg",
    "sg:phone":"+49 3573/2156",
    "sg:postcode":"01968",
    "sg:province":"Brandenburg",
    "wof:name":"Kippenstolz",
    "wof:placetype":"venue"
},
  "geometry": {"coordinates":[13.9966154099,51.5256195068],"type":"Point"}
}