{
  "type": "Feature",
  "properties": {
    "iso:country":"DE",
    "sg:address":"Friedrich-Ebert-Ring 1",
    "sg:city":"Idar-Oberstein",
    "sg:phone":"+49 6781/22019",
    "sg:postcode":"55743",
    "sg:province":"Rheinland-Pfalz",
    "wof:name":"Psycho-sozialer Dienst D. Caritasverbandes",
    "wof:placetype":"venue"
},
  "geometry": {"coordinates":[7.333473,49.702019],"type":"Point"}
}