{
  "type": "Feature",
  "properties": {
    "iso:country":"DE",
    "sg:address":"Kattenb\u00fchl 31",
    "sg:city":"Hann. M\u00fcnden",
    "sg:phone":"+49 5541/32636",
    "sg:postcode":"34346",
    "sg:province":"Niedersachsen",
    "wof:name":"Erwin Schormann Architekt",
    "wof:placetype":"venue"
},
  "geometry": {"coordinates":[9.657807,51.40863],"type":"Point"}
}