{
  "type": "Feature",
  "properties": {
    "iso:country":"DE",
    "sg:address":"Leinenweberstr 42",
    "sg:city":"Stuttgart",
    "sg:phone":"+49 711/669630",
    "sg:postcode":"70567",
    "sg:province":"Baden-W\u00fcrttemberg",
    "wof:name":"Rolf Schmid Ohg",
    "wof:placetype":"venue"
},
  "geometry": {"coordinates":[9.145572,48.729389],"type":"Point"}
}