{
  "type": "Feature",
  "properties": {
    "iso:country":"DE",
    "sg:address":"Bahnstr. 76",
    "sg:city":"K\u00f6ln",
    "sg:phone":"+49 2234/75586",
    "sg:postcode":"50858",
    "sg:province":"Nordrhein-Westfalen",
    "wof:name":"Peter Schieffer",
    "wof:placetype":"venue"
},
  "geometry": {"coordinates":[6.8407030106,50.939743042],"type":"Point"}
}