{
  "type": "Feature",
  "properties": {
    "iso:country":"DE",
    "sg:address":"Stuttgarter Str. 78",
    "sg:city":"Bad Urach",
    "sg:phone":"+49 7125/40383",
    "sg:postcode":"72574",
    "sg:province":"Baden-W\u00fcrttemberg",
    "wof:name":"Renate Gremmelspacher Hebamme",
    "wof:placetype":"venue"
},
  "geometry": {"coordinates":[9.391058,48.494717],"type":"Point"}
}