{
  "type": "Feature",
  "properties": {
    "iso:country":"DE",
    "sg:address":"Hans-Sachs-Weg 1",
    "sg:city":"Darmstadt",
    "sg:phone":"+49 6151/351626",
    "sg:postcode":"64291",
    "sg:province":"Hessen",
    "wof:name":"Hdt Industrieplanung Gmbh",
    "wof:placetype":"venue"
},
  "geometry": {"coordinates":[8.6626472473,49.9063224792],"type":"Point"}
}