{
  "type": "Feature",
  "properties": {
    "iso:country":"DE",
    "sg:address":"Friedrich-Engels-Str. 39",
    "sg:city":"Eisenh\u00fcttenstadt",
    "sg:phone":"+49 3364/44705",
    "sg:postcode":"15890",
    "sg:province":"Brandenburg",
    "wof:name":"Orthop\u00e4die Schwoch",
    "wof:placetype":"venue"
},
  "geometry": {"coordinates":[14.6253614426,52.1426200867],"type":"Point"}
}