{
  "type": "Feature",
  "properties": {
    "iso:country":"DE",
    "sg:address":"Rheinstr. 25",
    "sg:city":"Au",
    "sg:phone":"+49 7245/81385",
    "sg:postcode":"76474",
    "sg:province":"Baden-W\u00fcrttemberg",
    "wof:name":"Thomas Busch",
    "wof:placetype":"venue"
},
  "geometry": {"coordinates":[8.234616,48.952408],"type":"Point"}
}