{
  "type": "Feature",
  "properties": {
    "iso:country":"DE",
    "sg:address":"Erlenstr. 1",
    "sg:city":"Wunsiedel",
    "sg:phone":"+49 9232/5491",
    "sg:postcode":"95632",
    "sg:province":"Bayern",
    "wof:name":"Eva Maier",
    "wof:placetype":"venue"
},
  "geometry": {"coordinates":[12.0326728821,50.0472145081],"type":"Point"}
}