{
  "type": "Feature",
  "properties": {
    "iso:country":"DE",
    "sg:address":"Neukirchen zu St. Christoph 19",
    "sg:city":"Georgenberg",
    "sg:phone":"+49 9658/564",
    "sg:postcode":"92697",
    "sg:province":"Bayern",
    "wof:name":"Karl H. Und Liane Fleischmann",
    "wof:placetype":"venue"
},
  "geometry": {"coordinates":[12.429464,49.708054],"type":"Point"}
}