{
  "type": "Feature",
  "properties": {
    "iso:country":"DE",
    "sg:address":"Michael-Kazmierczak-Str. 4",
    "sg:city":"Leipzig",
    "sg:postcode":"04157",
    "sg:province":"Sachsen",
    "wof:name":"Dr. Med. Regina Hofmann",
    "wof:placetype":"venue"
},
  "geometry": {"coordinates":[12.373155,51.365005],"type":"Point"}
}