{
  "type": "Feature",
  "properties": {
    "iso:country":"DE",
    "sg:address":"Badweg 13",
    "sg:city":"Bad Schwalbach",
    "sg:phone":"+49 6124/70620",
    "sg:postcode":"65307",
    "sg:province":"Hessen",
    "wof:name":"Park-cafe",
    "wof:placetype":"venue"
},
  "geometry": {"coordinates":[8.0630102158,50.1340789795],"type":"Point"}
}