{
  "type": "Feature",
  "properties": {
    "iso:country":"DE",
    "sg:address":"Boschstr. 13",
    "sg:city":"Rheinstetten",
    "sg:phone":"+49 7242/952240",
    "sg:postcode":"76287",
    "sg:province":"Baden-W\u00fcrttemberg",
    "wof:name":"G.-p. Rheinboth",
    "wof:placetype":"venue"
},
  "geometry": {"coordinates":[8.281073,48.960758],"type":"Point"}
}