{
  "type": "Feature",
  "properties": {
    "iso:country":"DE",
    "sg:address":"Jakobsberg 17",
    "sg:city":"K\u00f6nigsfeld",
    "sg:phone":"+49 9207/316",
    "sg:postcode":"96167",
    "sg:province":"Bayern",
    "wof:name":"Hartwig Gmbh",
    "wof:placetype":"venue"
},
  "geometry": {"coordinates":[11.162682,49.943928],"type":"Point"}
}