{
  "type": "Feature",
  "properties": {
    "iso:country":"DE",
    "sg:address":"Gewerbeallee 12",
    "sg:city":"Brandis",
    "sg:phone":"+49 34292/7120",
    "sg:postcode":"04821",
    "sg:province":"Sachsen",
    "wof:name":"Ziza & Druck-chemie Gmbh",
    "wof:placetype":"venue"
},
  "geometry": {"coordinates":[12.5828094482,51.3301467896],"type":"Point"}
}