{
  "type": "Feature",
  "properties": {
    "iso:country":"DE",
    "sg:address":"Marktoberdorfer Str. 30",
    "sg:city":"Wald",
    "sg:phone":"+49 8302/393",
    "sg:postcode":"87616",
    "sg:province":"Bayern",
    "wof:name":"Alois Epp",
    "wof:placetype":"venue"
},
  "geometry": {"coordinates":[10.5584421158,47.7254981995],"type":"Point"}
}