{
  "type": "Feature",
  "properties": {
    "iso:country":"DE",
    "sg:address":"Emsdorfer Str. 13",
    "sg:city":"Frankfurt",
    "sg:phone":"+49 69/529675",
    "sg:postcode":"60433",
    "sg:province":"Hessen",
    "wof:name":"Wolfgang Seibel",
    "wof:placetype":"venue"
},
  "geometry": {"coordinates":[8.6683139801,50.1564254761],"type":"Point"}
}