{
  "type": "Feature",
  "properties": {
    "iso:country":"DE",
    "sg:address":"Fockensteinstr. 6",
    "sg:city":"M\u00fcnchen",
    "sg:phone":"+49 89/6970731",
    "sg:postcode":"81539",
    "sg:province":"Bayern",
    "wof:name":"Haydar Yagcioglu",
    "wof:placetype":"venue"
},
  "geometry": {"coordinates":[11.589251,48.111053],"type":"Point"}
}