{
  "type": "Feature",
  "properties": {
    "iso:country":"DE",
    "sg:address":"Nobelstr. 3",
    "sg:city":"Bocholt",
    "sg:phone":"+49 2871/8324",
    "sg:postcode":"46399",
    "sg:province":"Nordrhein-Westfalen",
    "wof:name":"B\u00f6ing Und Est",
    "wof:placetype":"venue"
},
  "geometry": {"coordinates":[6.6146512032,51.8391418457],"type":"Point"}
}