{
  "type": "Feature",
  "properties": {
    "iso:country":"DE",
    "sg:address":"Holzener Str. 35-37",
    "sg:city":"Menden",
    "sg:phone":"+49 4923/736840",
    "sg:postcode":"58708",
    "sg:province":"Nordrhein-Westfalen",
    "wof:name":"Bartec Sicherheits-schaltanlagen Gmbh",
    "wof:placetype":"venue"
},
  "geometry": {"coordinates":[7.75792,51.445026],"type":"Point"}
}