{
  "type": "Feature",
  "properties": {
    "iso:country":"DE",
    "sg:address":"Echternhagen 1",
    "sg:city":"Meinerzhagen",
    "sg:phone":"+49 2358/904030",
    "sg:postcode":"58540",
    "sg:province":"Nordrhein-Westfalen",
    "wof:name":"Die Jause",
    "wof:placetype":"venue"
},
  "geometry": {"coordinates":[7.785171032,51.1303024292],"type":"Point"}
}