{
  "type": "Feature",
  "properties": {
    "iso:country":"DE",
    "sg:address":"Rudelsdorfer Str. 16",
    "sg:city":"Kammerstein",
    "sg:phone":"+49 9178/829",
    "sg:postcode":"91126",
    "sg:province":"Bayern",
    "wof:name":"Erwin Heyder",
    "wof:placetype":"venue"
},
  "geometry": {"coordinates":[10.927738,49.276077],"type":"Point"}
}