{
  "type": "Feature",
  "properties": {
    "iso:country":"DE",
    "sg:address":"Am Rosenbusch 34",
    "sg:city":"Springe",
    "sg:phone":"+49 5045/6381",
    "sg:postcode":"31832",
    "sg:province":"Niedersachsen",
    "wof:name":"Gerhard Maciejewski",
    "wof:placetype":"venue"
},
  "geometry": {"coordinates":[9.6712875366,52.2402267456],"type":"Point"}
}