{
  "type": "Feature",
  "properties": {
    "iso:country":"DE",
    "sg:address":"Reuenberg 61",
    "sg:city":"Essen",
    "sg:phone":"+49 201/697471",
    "sg:postcode":"45357",
    "sg:province":"Nordrhein-Westfalen",
    "wof:name":"Steakhaus Haus Nothoff",
    "wof:placetype":"venue"
},
  "geometry": {"coordinates":[6.9283809662,51.4794654846],"type":"Point"}
}