{
  "type": "Feature",
  "properties": {
    "iso:country":"DE",
    "sg:address":"Erbsengasse 14",
    "sg:city":"Ebsdorfergrund",
    "sg:phone":"+49 6424/1502",
    "sg:postcode":"35085",
    "sg:province":"Hessen",
    "wof:name":"Heinrich Steitz",
    "wof:placetype":"venue"
},
  "geometry": {"coordinates":[8.855711,50.7271],"type":"Point"}
}