{
  "type": "Feature",
  "properties": {
    "iso:country":"DE",
    "sg:address":"Forststr 7",
    "sg:city":"Stuttgart",
    "sg:phone":"+49 711/614160",
    "sg:postcode":"70174",
    "sg:province":"Baden-W\u00fcrttemberg",
    "wof:name":"Abaxx Technology Ag",
    "wof:placetype":"venue"
},
  "geometry": {"coordinates":[9.166876,48.780186],"type":"Point"}
}