{
  "type": "Feature",
  "properties": {
    "iso:country":"DE",
    "sg:address":"Burchardstr. 8",
    "sg:city":"Hamburg",
    "sg:phone":"+49 40/3201050",
    "sg:postcode":"20095",
    "sg:province":"Hamburg",
    "wof:name":"Karlsten Kg",
    "wof:placetype":"venue"
},
  "geometry": {"coordinates":[10.004003,53.548645],"type":"Point"}
}