{
  "type": "Feature",
  "properties": {
    "iso:country":"DE",
    "sg:address":"Siemensstr. 16-18",
    "sg:city":"Syke",
    "sg:phone":"+49 4942/4295610",
    "sg:postcode":"28857",
    "sg:province":"Niedersachsen",
    "wof:name":"Cramer Construction",
    "wof:placetype":"venue"
},
  "geometry": {"coordinates":[8.801131,52.918121],"type":"Point"}
}