{
  "type": "Feature",
  "properties": {
    "iso:country":"DE",
    "sg:address":"Platz der Republik 11",
    "sg:city":"Grevenbroich",
    "sg:phone":"+49 2181/9512",
    "sg:postcode":"41515",
    "sg:province":"Nordrhein-Westfalen",
    "wof:name":"Beratungsstelle Der Arbeiterwohlfahrt F.",
    "wof:placetype":"venue"
},
  "geometry": {"coordinates":[6.584509,51.087818],"type":"Point"}
}