{
  "type": "Feature",
  "properties": {
    "iso:country":"DE",
    "sg:address":"Stephansplatz 3",
    "sg:city":"M\u00fcnchen",
    "sg:phone":"+49 89/265464",
    "sg:postcode":"80337",
    "sg:province":"Bayern",
    "wof:name":"Klerusblatt",
    "wof:placetype":"venue"
},
  "geometry": {"coordinates":[11.5665435791,48.1312065125],"type":"Point"}
}