{
  "type": "Feature",
  "properties": {
    "iso:country":"DE",
    "sg:address":"Schlo\u00dfstrasse 73",
    "sg:city":"Stuttgart",
    "sg:phone":"+49 711/666310",
    "sg:postcode":"70176",
    "sg:province":"Baden-W\u00fcrttemberg",
    "wof:name":"Lohrmann Und Kollegen",
    "wof:placetype":"venue"
},
  "geometry": {"coordinates":[9.162838,48.776302],"type":"Point"}
}