{
  "type": "Feature",
  "properties": {
    "iso:country":"DE",
    "sg:address":"Ostkamp 24",
    "sg:city":"Wardenburg",
    "sg:phone":"+49 4407/921930",
    "sg:postcode":"26203",
    "sg:province":"Niedersachsen",
    "wof:name":"Guss-asphalt Wilfried Ceh Gmbh",
    "wof:placetype":"venue"
},
  "geometry": {"coordinates":[8.214589119,53.0450248718],"type":"Point"}
}