{
  "type": "Feature",
  "properties": {
    "iso:country":"DE",
    "sg:address":"Yorckstr. 28",
    "sg:city":"Ludwigshafen",
    "sg:phone":"+49 621/581067",
    "sg:postcode":"67061",
    "sg:province":"Rheinland-Pfalz",
    "wof:name":"Edwin Ehrhart",
    "wof:placetype":"venue"
},
  "geometry": {"coordinates":[8.4519968033,49.4781570435],"type":"Point"}
}