{
  "type": "Feature",
  "properties": {
    "iso:country":"DE",
    "sg:address":"Jakob-Lang-Str. 2",
    "sg:city":"Weiler-Simmerberg",
    "sg:postcode":"88171",
    "sg:province":"Bayern",
    "wof:name":"Binder Verwaltungsges. Mbh",
    "wof:placetype":"venue"
},
  "geometry": {"coordinates":[9.9136886597,47.5819282532],"type":"Point"}
}