{
  "type": "Feature",
  "properties": {
    "iso:country":"DE",
    "sg:address":"Wehrblecker Str. 18",
    "sg:city":"Varrel",
    "sg:phone":"+49 4274/295",
    "sg:postcode":"27259",
    "sg:province":"Niedersachsen",
    "wof:name":"Winfried Wiegmann",
    "wof:placetype":"venue"
},
  "geometry": {"coordinates":[8.702095,52.626007],"type":"Point"}
}