{
  "type": "Feature",
  "properties": {
    "iso:country":"DE",
    "sg:address":"Mainzer Landstr. 10",
    "sg:city":"Irmtraut",
    "sg:phone":"+49 6436/4714",
    "sg:postcode":"56479",
    "sg:province":"Rheinland-Pfalz",
    "wof:name":"Ernst Schneider Landwirtschaftlicher",
    "wof:placetype":"venue"
},
  "geometry": {"coordinates":[8.060918,50.554428],"type":"Point"}
}