{
  "type": "Feature",
  "properties": {
    "iso:country":"DE",
    "sg:address":"Hauptstr. 78/1",
    "sg:city":"Ehingen",
    "sg:phone":"+49 7391/52120",
    "sg:postcode":"89584",
    "sg:province":"Baden-W\u00fcrttemberg",
    "wof:name":"Elke G\u00f6tz",
    "wof:placetype":"venue"
},
  "geometry": {"coordinates":[9.7261238098,48.2833900452],"type":"Point"}
}