{
  "type": "Feature",
  "properties": {
    "iso:country":"DE",
    "sg:address":"Kronprinzstr 18",
    "sg:city":"Stuttgart",
    "sg:phone":"+49 711/2292944",
    "sg:postcode":"70173",
    "sg:province":"Baden-W\u00fcrttemberg",
    "wof:name":"Rabobank Deutschland Ag",
    "wof:placetype":"venue"
},
  "geometry": {"coordinates":[9.174931,48.776142],"type":"Point"}
}