{
  "type": "Feature",
  "properties": {
    "iso:country":"DE",
    "sg:address":"R\u00e4mel",
    "sg:city":"Zingst",
    "sg:postcode":"18374",
    "sg:province":"Mecklenburg-Vorpommern",
    "wof:name":"Kurbetrieb Kraus Gmbh",
    "wof:placetype":"venue"
},
  "geometry": {"coordinates":[12.692558,54.440277],"type":"Point"}
}