{
  "type": "Feature",
  "properties": {
    "iso:country":"DE",
    "sg:address":"Tilsiter Weg 2",
    "sg:city":"Schwetzingen",
    "sg:phone":"+49 6202/929688",
    "sg:postcode":"68723",
    "sg:province":"Baden-W\u00fcrttemberg",
    "wof:name":"Ralf Weiland",
    "wof:placetype":"venue"
},
  "geometry": {"coordinates":[8.5653610229,49.3930931091],"type":"Point"}
}