{
  "type": "Feature",
  "properties": {
    "iso:country":"DE",
    "sg:address":"Linkstr 9a",
    "sg:city":"M\u00f6hnesee",
    "sg:phone":"+49 2924/7264",
    "sg:postcode":"59519",
    "sg:province":"Nordrhein-Westfalen",
    "wof:name":"Maschinen + Technik Vogt Gmbh",
    "wof:placetype":"venue"
},
  "geometry": {"coordinates":[8.09001,51.488361],"type":"Point"}
}