{
  "type": "Feature",
  "properties": {
    "iso:country":"DE",
    "sg:address":"Krautlachenweg 3a",
    "sg:city":"Hirschhorn",
    "sg:phone":"+49 6272/2137",
    "sg:postcode":"69434",
    "sg:province":"Baden-W\u00fcrttemberg",
    "wof:name":"Energieberatungsb\u00fcro Hess Gmbh",
    "wof:placetype":"venue"
},
  "geometry": {"coordinates":[8.9011898041,49.4449882507],"type":"Point"}
}