{
  "type": "Feature",
  "properties": {
    "iso:country":"DE",
    "sg:address":"Lindenstr. 34",
    "sg:city":"Seebad Ahlbeck",
    "sg:phone":"+49 38378/28236",
    "sg:postcode":"17419",
    "sg:province":"Mecklenburg-Vorpommern",
    "wof:name":"Norbert A\u00dfmann",
    "wof:placetype":"venue"
},
  "geometry": {"coordinates":[14.0651,53.886711],"type":"Point"}
}