{
  "type": "Feature",
  "properties": {
    "iso:country":"DE",
    "sg:address":"Husumer Baum 39",
    "sg:city":"Schleswig",
    "sg:phone":"+49 4621/36199",
    "sg:postcode":"24837",
    "sg:province":"Schleswig-Holstein",
    "wof:name":"Kegler Stuben",
    "wof:placetype":"venue"
},
  "geometry": {"coordinates":[9.5381860733,54.4972610474],"type":"Point"}
}