{
  "type": "Feature",
  "properties": {
    "iso:country":"DE",
    "sg:address":"Vor dem Celler Tor 7",
    "sg:city":"Burgdorf",
    "sg:phone":"+49 5136/899821",
    "sg:postcode":"31303",
    "sg:province":"Niedersachsen",
    "wof:name":"Jutta Behle Rechtsanw\u00e4ltin",
    "wof:placetype":"venue"
},
  "geometry": {"coordinates":[10.0129137039,52.4524078369],"type":"Point"}
}