{
  "type": "Feature",
  "properties": {
    "iso:country":"DE",
    "sg:address":"Korverweg 1 b",
    "sg:city":"Hamburg",
    "sg:phone":"+49 40/7135503",
    "sg:postcode":"22117",
    "sg:province":"Hamburg",
    "wof:name":"C. B\u00fcchsensch\u00fctz & B. Schmidl",
    "wof:placetype":"venue"
},
  "geometry": {"coordinates":[10.116489,53.534248],"type":"Point"}
}