{
  "type": "Feature",
  "properties": {
    "iso:country":"DE",
    "sg:address":"Hauptstr. 24",
    "sg:city":"Dillenburg",
    "sg:phone":"+49 2771/21968",
    "sg:postcode":"35687",
    "sg:province":"Hessen",
    "wof:name":"Stephanie G\u00f6bel",
    "wof:placetype":"venue"
},
  "geometry": {"coordinates":[8.30397,50.718781],"type":"Point"}
}