{
  "type": "Feature",
  "properties": {
    "iso:country":"DE",
    "sg:address":"Brahmsstr. 12",
    "sg:city":"Ritterhude",
    "sg:phone":"+49 4292/9221",
    "sg:postcode":"27721",
    "sg:province":"Niedersachsen",
    "wof:name":"Franz Sommer",
    "wof:placetype":"venue"
},
  "geometry": {"coordinates":[8.7470779419,53.1808204651],"type":"Point"}
}