{
  "type": "Feature",
  "properties": {
    "iso:country":"DE",
    "sg:address":"Daimlerstr. 9",
    "sg:city":"G\u00fcnzburg",
    "sg:phone":"+49 8221/90040",
    "sg:postcode":"89312",
    "sg:province":"Bayern",
    "wof:name":"Kalka Dienstleitsungs-gmbh",
    "wof:placetype":"venue"
},
  "geometry": {"coordinates":[10.2756147385,48.4758720398],"type":"Point"}
}