{
  "type": "Feature",
  "properties": {
    "iso:country":"DE",
    "sg:address":"Weberstr. 43",
    "sg:city":"Memmingen",
    "sg:phone":"+49 8331/901035",
    "sg:postcode":"87700",
    "sg:province":"Bayern",
    "wof:name":"Bestattungsdienst Memmingen Steib & Schauppel Gmbh",
    "wof:placetype":"venue"
},
  "geometry": {"coordinates":[10.180915,47.980862],"type":"Point"}
}