{
  "type": "Feature",
  "properties": {
    "iso:country":"DE",
    "sg:address":"Welterpfad 12 a",
    "sg:city":"Berlin",
    "sg:phone":"+49 30/7212312",
    "sg:postcode":"12277",
    "sg:province":"Berlin",
    "wof:name":"Karin Und Klaus R\u00f6se",
    "wof:placetype":"venue"
},
  "geometry": {"coordinates":[13.3665761948,52.4241828918],"type":"Point"}
}