{
  "type": "Feature",
  "properties": {
    "iso:country":"DE",
    "sg:address":"Unterer Metzgerbach 13",
    "sg:city":"Esslingen",
    "sg:phone":"+49 711/353412",
    "sg:postcode":"73728",
    "sg:province":"Baden-W\u00fcrttemberg",
    "wof:name":"Apotheke Unterer Metzgerbach",
    "wof:placetype":"venue"
},
  "geometry": {"coordinates":[9.304793,48.740402],"type":"Point"}
}