{
  "type": "Feature",
  "properties": {
    "iso:country":"DE",
    "sg:address":"Rosenheimer Str. 24",
    "sg:city":"Raubling",
    "sg:phone":"+49 8035/8611",
    "sg:postcode":"83064",
    "sg:province":"Bayern",
    "wof:name":"Elektro Elton Inh. Anton Rahm Jun.",
    "wof:placetype":"venue"
},
  "geometry": {"coordinates":[12.1192779541,47.7937698364],"type":"Point"}
}