{
  "type": "Feature",
  "properties": {
    "iso:country":"DE",
    "sg:address":"Industriestr. 1",
    "sg:city":"Stockstadt",
    "sg:phone":"+49 6027/3071",
    "sg:postcode":"63811",
    "sg:province":"Bayern",
    "wof:name":"Fvg Freie Vermittlungs- Gesellschaft Carl Bauer",
    "wof:placetype":"venue"
},
  "geometry": {"coordinates":[9.0800037384,49.9680900574],"type":"Point"}
}