{
  "type": "Feature",
  "properties": {
    "iso:country":"DE",
    "sg:address":"Dr.-Bock-Br\u00fccke 2",
    "sg:city":"Duingen",
    "sg:phone":"+49 5185/238",
    "sg:postcode":"31089",
    "sg:province":"Niedersachsen",
    "wof:name":"R. Hoppe Architekt",
    "wof:placetype":"venue"
},
  "geometry": {"coordinates":[9.698,52.005447],"type":"Point"}
}