{
  "type": "Feature",
  "properties": {
    "iso:country":"DE",
    "sg:address":"Schulstr. 9",
    "sg:city":"Wehingen",
    "sg:phone":"+49 7426/4125",
    "sg:postcode":"78564",
    "sg:province":"Baden-W\u00fcrttemberg",
    "wof:name":"H & M Massivbau Verwaltungs Gmbh",
    "wof:placetype":"venue"
},
  "geometry": {"coordinates":[8.789671,48.14777],"type":"Point"}
}