{
  "type": "Feature",
  "properties": {
    "iso:country":"DE",
    "sg:address":"M\u00fchlh\u00e4userstr.",
    "sg:city":"Oberdorla",
    "sg:phone":"+49 36017/50307",
    "sg:postcode":"99986",
    "sg:province":"Th\u00fcringen",
    "wof:name":"Oberdorlaer-carnevals-verein",
    "wof:placetype":"venue"
},
  "geometry": {"coordinates":[10.4298,51.16819],"type":"Point"}
}