{
  "type": "Feature",
  "properties": {
    "iso:country":"DE",
    "sg:address":"Linderter Str. 3",
    "sg:city":"Wennigsen",
    "sg:phone":"+49 5109/56000",
    "sg:postcode":"30974",
    "sg:province":"Niedersachsen",
    "wof:name":"Haustechnik Hantigk Gmbh",
    "wof:placetype":"venue"
},
  "geometry": {"coordinates":[9.6310167313,52.2636871338],"type":"Point"}
}