{
  "type": "Feature",
  "properties": {
    "iso:country":"DE",
    "sg:address":"Theresienstr.17",
    "sg:city":"Hof/Saale",
    "sg:phone":"+49 9281/84776",
    "sg:postcode":"95028",
    "sg:province":"Bayern",
    "wof:name":"Gemeinschaftspraxis Dr.med.pia Schmitt-mickley Und Dr.med.ma",
    "wof:placetype":"venue"
},
  "geometry": {"coordinates":[11.918688,50.321609],"type":"Point"}
}