{
  "type": "Feature",
  "properties": {
    "iso:country":"DE",
    "sg:address":"Solalindenstr. 44",
    "sg:city":"M\u00fcnchen",
    "sg:phone":"+49 89/4309177",
    "sg:postcode":"81825",
    "sg:province":"Bayern",
    "wof:name":"Paul Meyer",
    "wof:placetype":"venue"
},
  "geometry": {"coordinates":[11.677512,48.115776],"type":"Point"}
}