{
  "type": "Feature",
  "properties": {
    "iso:country":"DE",
    "sg:address":"Rennbahnring 73",
    "sg:city":"Halle",
    "sg:phone":"+49 345/8045234",
    "sg:postcode":"06124",
    "sg:province":"Sachsen-Anhalt",
    "wof:name":"U. Rother & E. Adam",
    "wof:placetype":"venue"
},
  "geometry": {"coordinates":[11.936578,51.475945],"type":"Point"}
}