{
  "type": "Feature",
  "properties": {
    "iso:country":"DE",
    "sg:address":"Heuweg 12",
    "sg:city":"Jungingen",
    "sg:phone":"+49 7477/91126",
    "sg:postcode":"72417",
    "sg:province":"Baden-W\u00fcrttemberg",
    "wof:name":"H. Bo\u00dfmann Ingenieur",
    "wof:placetype":"venue"
},
  "geometry": {"coordinates":[9.0440292358,48.3309631348],"type":"Point"}
}