{
  "type": "Feature",
  "properties": {
    "iso:country":"DE",
    "sg:address":"Mitteltal 27",
    "sg:city":"Stegen",
    "sg:phone":"+49 7661/2221",
    "sg:postcode":"79252",
    "sg:province":"Baden-W\u00fcrttemberg",
    "wof:name":"W. Deimling Kg",
    "wof:placetype":"venue"
},
  "geometry": {"coordinates":[7.9753670692,48.0003395081],"type":"Point"}
}