{
  "type": "Feature",
  "properties": {
    "iso:country":"DE",
    "sg:address":"Im Heidchesgarten 5",
    "sg:city":"Alsdorf",
    "sg:phone":"+49 2741/24090",
    "sg:postcode":"57518",
    "sg:province":"Rheinland-Pfalz",
    "wof:name":"Hermann Schuth Ingenieur",
    "wof:placetype":"venue"
},
  "geometry": {"coordinates":[7.8869199753,50.7758903503],"type":"Point"}
}