{
  "type": "Feature",
  "properties": {
    "iso:country":"DE",
    "sg:address":"Kamper Str 24",
    "sg:city":"Aachen",
    "sg:phone":"+49 241/1730290",
    "sg:postcode":"52064",
    "sg:province":"Nordrhein-Westfalen",
    "wof:name":"W.w.s! Werbeagentur Schuberth Gmbh",
    "wof:placetype":"venue"
},
  "geometry": {"coordinates":[6.082324,50.763546],"type":"Point"}
}