{
  "type": "Feature",
  "properties": {
    "iso:country":"DE",
    "sg:address":"Pyrmonter Str. 3",
    "sg:city":"Bad Arolsen",
    "sg:phone":"+49 5691/2168",
    "sg:postcode":"34454",
    "sg:province":"Hessen",
    "wof:name":"A. Wenk",
    "wof:placetype":"venue"
},
  "geometry": {"coordinates":[9.017719,51.381313],"type":"Point"}
}