{
  "type": "Feature",
  "properties": {
    "iso:country":"DE",
    "sg:address":"Ingolst\u00e4dter Str. 245",
    "sg:city":"M\u00fcnchen",
    "sg:phone":"+49 89/3160880",
    "sg:postcode":"80939",
    "sg:province":"Bayern",
    "wof:name":"Akm Autokran Vermietung Gmbh",
    "wof:placetype":"venue"
},
  "geometry": {"coordinates":[11.5873403549,48.2215080261],"type":"Point"}
}