{
  "type": "Feature",
  "properties": {
    "iso:country":"DE",
    "sg:address":"Hauptstr. 2",
    "sg:city":"Me\u00dfkirch",
    "sg:phone":"+49 7575/3735",
    "sg:postcode":"88605",
    "sg:province":"Baden-W\u00fcrttemberg",
    "wof:name":"Eduard Palm Gmbh",
    "wof:placetype":"venue"
},
  "geometry": {"coordinates":[9.1141233444,47.993396759],"type":"Point"}
}