{
  "type": "Feature",
  "properties": {
    "iso:country":"DE",
    "sg:address":"Hinter der Burg 203",
    "sg:city":"Berka v d Hainich",
    "sg:postcode":"99826",
    "sg:province":"Th\u00fcringen",
    "wof:name":"Ebz Dachtechnik Gmbh Zwndl. Der Firma Ebz",
    "wof:placetype":"venue"
},
  "geometry": {"coordinates":[10.38173,51.042858],"type":"Point"}
}