{
  "type": "Feature",
  "properties": {
    "iso:country":"DE",
    "sg:address":"An der Promenade 16",
    "sg:city":"Artern",
    "sg:phone":"+49 3466/319829",
    "sg:postcode":"06556",
    "sg:province":"Th\u00fcringen",
    "wof:name":"Privater Pflegedienst Humanitas",
    "wof:placetype":"venue"
},
  "geometry": {"coordinates":[11.305845,51.391827],"type":"Point"}
}