{
  "type": "Feature",
  "properties": {
    "iso:country":"DE",
    "sg:address":"Stephanstr.16",
    "sg:city":"Neuss",
    "sg:postcode":"41464",
    "sg:province":"Nordrhein-Westfalen",
    "wof:name":"Coverband Neuss",
    "wof:placetype":"venue"
},
  "geometry": {"coordinates":[6.67894,51.199429],"type":"Point"}
}