{
  "type": "Feature",
  "properties": {
    "iso:country":"DE",
    "sg:address":"Bahnhofstr. 1",
    "sg:city":"Rehfelde",
    "sg:phone":"+49 33435/261",
    "sg:postcode":"15345",
    "sg:province":"Brandenburg",
    "wof:name":"F. Haube",
    "wof:placetype":"venue"
},
  "geometry": {"coordinates":[13.92141,52.526009],"type":"Point"}
}