{
  "type": "Feature",
  "properties": {
    "iso:country":"DE",
    "sg:address":"Postfach 1220:: 93130 Burglengenfeld:: Germany::  Tel: +49 9471 70420::  Fax: +49 9471 7042140.^^Marktplatz 8::",
    "sg:city":"Burglengenfeld",
    "sg:postcode":"93133",
    "sg:province":"Bayern",
    "wof:name":"Volksbank-raiffeisenbank Burglengenfeld Eg",
    "wof:placetype":"venue"
},
  "geometry": {"coordinates":[12.039755,49.208977],"type":"Point"}
}