{
  "type": "Feature",
  "properties": {
    "iso:country":"DE",
    "sg:address":"Norderholm 22",
    "sg:city":"Gelting",
    "sg:phone":"+49 4643/2202",
    "sg:postcode":"24395",
    "sg:province":"Schleswig-Holstein",
    "wof:name":"Georg Borowski",
    "wof:placetype":"venue"
},
  "geometry": {"coordinates":[9.8990116119,54.7486915588],"type":"Point"}
}