{
  "type": "Feature",
  "properties": {
    "iso:country":"DE",
    "sg:address":"Hauptstr. 92",
    "sg:city":"B\u00f6hmenkirch",
    "sg:phone":"+49 7332/6548",
    "sg:postcode":"89558",
    "sg:province":"Baden-W\u00fcrttemberg",
    "wof:name":"Julius B\u00f6lstler",
    "wof:placetype":"venue"
},
  "geometry": {"coordinates":[9.9316558838,48.6847686768],"type":"Point"}
}