{
  "type": "Feature",
  "properties": {
    "iso:country":"DE",
    "sg:address":"Bei Der Gr\u00fcnen Br\u00fccke 55",
    "sg:city":"Hamburg",
    "sg:phone":"+49 40/781366",
    "sg:postcode":"20539",
    "sg:province":"Hamburg",
    "wof:name":"Robert E.m. Tilge",
    "wof:placetype":"venue"
},
  "geometry": {"coordinates":[10.042282,53.542816],"type":"Point"}
}