{
  "type": "Feature",
  "properties": {
    "iso:country":"DE",
    "sg:address":"Grouvener Str. 58",
    "sg:city":"Elsdorf",
    "sg:phone":"+49 2274/1471",
    "sg:postcode":"50189",
    "sg:province":"Nordrhein-Westfalen",
    "wof:name":"W. Wolf",
    "wof:placetype":"venue"
},
  "geometry": {"coordinates":[6.590272,50.927635],"type":"Point"}
}