{
  "type": "Feature",
  "properties": {
    "iso:country":"DE",
    "sg:address":"Klein B\u00fcnstorfer Str. 5",
    "sg:city":"Bad Bevensen",
    "sg:phone":"+49 5821/7523",
    "sg:postcode":"29549",
    "sg:province":"Niedersachsen",
    "wof:name":"Hans-heinrich Winkelmann",
    "wof:placetype":"venue"
},
  "geometry": {"coordinates":[10.57907,53.077866],"type":"Point"}
}