{
  "type": "Feature",
  "properties": {
    "iso:country":"DE",
    "sg:address":"L\u00e4rchenstr. 7",
    "sg:city":"Hebertsfelden",
    "sg:phone":"+49 8721/2167",
    "sg:postcode":"84332",
    "sg:province":"Bayern",
    "wof:name":"Hermann Wieslhuber",
    "wof:placetype":"venue"
},
  "geometry": {"coordinates":[12.8240251541,48.4088897705],"type":"Point"}
}