{
  "type": "Feature",
  "properties": {
    "iso:country":"DE",
    "sg:address":"K\u00f6nigstr. 4",
    "sg:city":"Duisburg",
    "sg:phone":"+49 203/26387",
    "sg:postcode":"47051",
    "sg:province":"Nordrhein-Westfalen",
    "wof:name":"Jeans-palast Schmidt & G\u00f6rgens Gmbh & Co.",
    "wof:placetype":"venue"
},
  "geometry": {"coordinates":[6.764898777,51.4334793091],"type":"Point"}
}