{
  "type": "Feature",
  "properties": {
    "iso:country":"DE",
    "sg:address":"Bismarckstr. 9",
    "sg:city":"Marktredwitz",
    "sg:postcode":"95615",
    "sg:province":"Bayern",
    "wof:name":"Hmc Heinz Marketing Consult E. K.",
    "wof:placetype":"venue"
},
  "geometry": {"coordinates":[12.081353,49.998676],"type":"Point"}
}