{
  "type": "Feature",
  "properties": {
    "iso:country":"DE",
    "sg:address":"Wonnitz 2",
    "sg:city":"Camburg",
    "sg:phone":"+49 36421/22217",
    "sg:postcode":"07774",
    "sg:province":"Th\u00fcringen",
    "wof:name":"Horst Bechmann",
    "wof:placetype":"venue"
},
  "geometry": {"coordinates":[11.723833,51.051151],"type":"Point"}
}