{
  "type": "Feature",
  "properties": {
    "iso:country":"DE",
    "sg:address":"Kirchplatz 2",
    "sg:city":"Wickede",
    "sg:phone":"+49 2377/3010",
    "sg:postcode":"58739",
    "sg:province":"Nordrhein-Westfalen",
    "wof:name":"Katholisches Pfarramt St. Vinzenz",
    "wof:placetype":"venue"
},
  "geometry": {"coordinates":[7.8556241989,51.5025787354],"type":"Point"}
}