{
  "type": "Feature",
  "properties": {
    "iso:country":"DE",
    "sg:address":"Sch\u00f6nlanker Str. 55",
    "sg:city":"Husum",
    "sg:phone":"+49 4841/4180",
    "sg:postcode":"25813",
    "sg:province":"Schleswig-Holstein",
    "wof:name":"Hans Heydtmann Architekt",
    "wof:placetype":"venue"
},
  "geometry": {"coordinates":[9.042999,54.492207],"type":"Point"}
}