{
  "type": "Feature",
  "properties": {
    "iso:country":"DE",
    "sg:address":"Oberscheidstr.22",
    "sg:city":"Bochum",
    "sg:phone":"+49 234/9536683",
    "sg:postcode":"44807",
    "sg:province":"Nordrhein-Westfalen",
    "wof:name":"Kurierdienst Gabriele Wetzel",
    "wof:placetype":"venue"
},
  "geometry": {"coordinates":[7.217765,51.516659],"type":"Point"}
}