{
  "type": "Feature",
  "properties": {
    "iso:country":"DE",
    "sg:address":"Im S\u00fcdholz 6",
    "sg:city":"R\u00f6dinghausen",
    "sg:phone":"+49 5223/699716",
    "sg:postcode":"32289",
    "sg:province":"Nordrhein-Westfalen",
    "wof:name":"Binger Gmbh",
    "wof:placetype":"venue"
},
  "geometry": {"coordinates":[8.5372638702,52.2351226807],"type":"Point"}
}