{
  "type": "Feature",
  "properties": {
    "iso:country":"DE",
    "sg:address":"Im Hofacker 22",
    "sg:city":"Staufen",
    "sg:phone":"+49 7633/6122",
    "sg:postcode":"79219",
    "sg:province":"Baden-W\u00fcrttemberg",
    "wof:name":"Horst Meyer",
    "wof:placetype":"venue"
},
  "geometry": {"coordinates":[7.7251358032,47.8825073242],"type":"Point"}
}