{
  "type": "Feature",
  "properties": {
    "iso:country":"DE",
    "sg:address":"Nideggener Str. 13",
    "sg:city":"Euskirchen",
    "sg:phone":"+49 2251/54176",
    "sg:postcode":"53881",
    "sg:province":"Nordrhein-Westfalen",
    "wof:name":"Christian Loosen",
    "wof:placetype":"venue"
},
  "geometry": {"coordinates":[6.737927,50.682858],"type":"Point"}
}