{
  "type": "Feature",
  "properties": {
    "iso:country":"DE",
    "sg:address":"Donaustr. 102- 104",
    "sg:city":"Bremen",
    "sg:phone":"+49 421/505170",
    "sg:postcode":"28199",
    "sg:province":"Bremen",
    "wof:name":"Corinna Arras",
    "wof:placetype":"venue"
},
  "geometry": {"coordinates":[8.78860569,53.0670661926],"type":"Point"}
}