{
  "type": "Feature",
  "properties": {
    "iso:country":"DE",
    "sg:address":"Wiesenbrunnen 12",
    "sg:city":"Gleichen",
    "sg:phone":"+49 5592/1648",
    "sg:postcode":"37130",
    "sg:province":"Niedersachsen",
    "wof:name":"Heinz Gr\u00fcne",
    "wof:placetype":"venue"
},
  "geometry": {"coordinates":[10.0437698364,51.4451446533],"type":"Point"}
}