{
  "type": "Feature",
  "properties": {
    "iso:country":"DE",
    "sg:address":"Weipertstr. 26",
    "sg:city":"Heilbronn",
    "sg:phone":"+49 7131/1850",
    "sg:postcode":"74076",
    "sg:province":"Baden-W\u00fcrttemberg",
    "wof:name":"Media Markt Verbund Heilbronn Gmbh",
    "wof:placetype":"venue"
},
  "geometry": {"coordinates":[9.2139043808,49.1490516663],"type":"Point"}
}