{
  "type": "Feature",
  "properties": {
    "iso:country":"DE",
    "sg:address":"Im Nonnengarten 51",
    "sg:city":"Bad D\u00fcrkheim",
    "sg:phone":"+49 6322/92465",
    "sg:postcode":"67098",
    "sg:province":"Rheinland-Pfalz",
    "wof:name":"Bsk Finanzdienstleistung Und Vermittlungs Gmbh",
    "wof:placetype":"venue"
},
  "geometry": {"coordinates":[8.1834640503,49.4673690796],"type":"Point"}
}