{
  "type": "Feature",
  "properties": {
    "iso:country":"DE",
    "sg:address":"Siebachstr. 26",
    "sg:city":"K\u00f6ln",
    "sg:phone":"+49 221/7392636",
    "sg:postcode":"50733",
    "sg:province":"Nordrhein-Westfalen",
    "wof:name":"Helga Heister",
    "wof:placetype":"venue"
},
  "geometry": {"coordinates":[6.9501318932,50.9600296021],"type":"Point"}
}