{
  "type": "Feature",
  "properties": {
    "iso:country":"DE",
    "sg:address":"Elbeallee 155",
    "sg:city":"Bielefeld",
    "sg:phone":"+49 5205/105457",
    "sg:postcode":"33689",
    "sg:province":"Nordrhein-Westfalen",
    "wof:name":"L. Langer",
    "wof:placetype":"venue"
},
  "geometry": {"coordinates":[8.5946407318,51.9510993958],"type":"Point"}
}