{
  "type": "Feature",
  "properties": {
    "iso:country":"DE",
    "sg:address":"Dernbacherstr 53-55",
    "sg:city":"Ebernhahn",
    "sg:phone":"+49 2623/96460",
    "sg:postcode":"56424",
    "sg:province":"Rheinland-Pfalz",
    "wof:name":"Sks Schr\u00f6der Kie\u00dfling Spedition Gmbh",
    "wof:placetype":"venue"
},
  "geometry": {"coordinates":[7.7736301422,50.4692878723],"type":"Point"}
}