{
  "type": "Feature",
  "properties": {
    "iso:country":"DE",
    "sg:address":"Nordeschstr. 14 b",
    "sg:city":"D\u00f6rpen",
    "sg:postcode":"26892",
    "sg:province":"Niedersachsen",
    "wof:name":"Ahrens Bau Gmbh",
    "wof:placetype":"venue"
},
  "geometry": {"coordinates":[7.3262982368,52.9685401917],"type":"Point"}
}