{
  "type": "Feature",
  "properties": {
    "iso:country":"DE",
    "sg:address":"Friedrichstr. 22",
    "sg:city":"Wernigerode",
    "sg:postcode":"38855",
    "sg:province":"Sachsen-Anhalt",
    "wof:name":"Arbeitsf\u00f6rderung- Und Sanierungsges. Osterwieck Mbh",
    "wof:placetype":"venue"
},
  "geometry": {"coordinates":[10.77155,51.828636],"type":"Point"}
}