{
  "type": "Feature",
  "properties": {
    "iso:country":"DE",
    "sg:address":"Laubanger 14",
    "sg:city":"Bamberg",
    "sg:phone":"+49 951/966250",
    "sg:postcode":"96052",
    "sg:province":"Bayern",
    "wof:name":"Obi Heimwerkermarkt Gmbh & Co. Kg",
    "wof:placetype":"venue"
},
  "geometry": {"coordinates":[10.874759,49.910522],"type":"Point"}
}