{
  "type": "Feature",
  "properties": {
    "iso:country":"DE",
    "sg:address":"Zur Malsch 6",
    "sg:city":"Siegen",
    "sg:phone":"+49 271/311161",
    "sg:postcode":"57080",
    "sg:province":"Nordrhein-Westfalen",
    "wof:name":"Johannes Schuldt Ingenieur",
    "wof:placetype":"venue"
},
  "geometry": {"coordinates":[8.001663208,50.848739624],"type":"Point"}
}