{
  "type": "Feature",
  "properties": {
    "iso:country":"DE",
    "sg:address":"Robert-Bosch-Str. 6",
    "sg:city":"Boxberg",
    "sg:postcode":"97944",
    "sg:province":"Baden-W\u00fcrttemberg",
    "wof:name":"Lvo Industrieservice Gmbh",
    "wof:placetype":"venue"
},
  "geometry": {"coordinates":[9.633579,49.441647],"type":"Point"}
}