{
  "type": "Feature",
  "properties": {
    "iso:country":"DE",
    "sg:address":"Uferstr. 10",
    "sg:city":"Heidelberg",
    "sg:postcode":"69120",
    "sg:province":"Baden-W\u00fcrttemberg",
    "wof:name":"Osadnik & Kamienski Heidelberger Bauges. Mbh",
    "wof:placetype":"venue"
},
  "geometry": {"coordinates":[8.6909160614,49.4135475159],"type":"Point"}
}