{
  "type": "Feature",
  "properties": {
    "iso:country":"DE",
    "sg:address":"Dahlienweg 10",
    "sg:city":"G\u00f6rlitz",
    "sg:phone":"+49 3581/78857",
    "sg:postcode":"02827",
    "sg:province":"Sachsen",
    "wof:name":"E. Donath",
    "wof:placetype":"venue"
},
  "geometry": {"coordinates":[14.938492,51.136559],"type":"Point"}
}