{
  "type": "Feature",
  "properties": {
    "iso:country":"DE",
    "sg:address":"Haselstr. 33",
    "sg:city":"Kaiserslautern",
    "sg:phone":"+49 631",
    "sg:postcode":"67659",
    "sg:province":"Rheinland-Pfalz",
    "wof:name":"Internetservice Und Dienstleistungsgesellschaft",
    "wof:placetype":"venue"
},
  "geometry": {"coordinates":[7.760719,49.464748],"type":"Point"}
}