{
  "type": "Feature",
  "properties": {
    "iso:country":"DE",
    "sg:address":"Steinkirchrg. 56/3",
    "sg:city":"Villingen-Schwenningen",
    "sg:phone":"+49 4977/204006",
    "sg:postcode":"78056",
    "sg:province":"Baden-W\u00fcrttemberg",
    "wof:name":"Singoli Chemie Gmbh",
    "wof:placetype":"venue"
},
  "geometry": {"coordinates":[8.558779,48.066849],"type":"Point"}
}