{
  "type": "Feature",
  "properties": {
    "iso:country":"DE",
    "sg:address":"In der Brache 8",
    "sg:city":"Wermelskirchen",
    "sg:phone":"+49 2196/80119",
    "sg:postcode":"42929",
    "sg:province":"Nordrhein-Westfalen",
    "wof:name":"Rolf D\u00fcltgen Steuerberater",
    "wof:placetype":"venue"
},
  "geometry": {"coordinates":[7.2637381554,51.1068954468],"type":"Point"}
}