{
  "type": "Feature",
  "properties": {
    "iso:country":"DE",
    "sg:address":"Vahrenwalder Str. 285",
    "sg:city":"Hannover",
    "sg:phone":"+49 511/3732830",
    "sg:postcode":"30179",
    "sg:province":"Niedersachsen",
    "wof:name":"Clean Car Autoservice",
    "wof:placetype":"venue"
},
  "geometry": {"coordinates":[9.733186,52.417522],"type":"Point"}
}