{
  "type": "Feature",
  "properties": {
    "iso:country":"DE",
    "sg:address":"Klosterstern 6",
    "sg:city":"Hamburg",
    "sg:phone":"+49 40/474357",
    "sg:postcode":"20149",
    "sg:province":"Hamburg",
    "wof:name":"Leica Meister Foto-drogerie",
    "wof:placetype":"venue"
},
  "geometry": {"coordinates":[9.988143,53.58215],"type":"Point"}
}