{
  "type": "Feature",
  "properties": {
    "iso:country":"DE",
    "sg:address":"Hauptstr. 55",
    "sg:city":"Heubach",
    "sg:phone":"+49 7173/6798",
    "sg:postcode":"73540",
    "sg:province":"Baden-W\u00fcrttemberg",
    "wof:name":"Artesana Gebr. Heinzelmann Gmbh",
    "wof:placetype":"venue"
},
  "geometry": {"coordinates":[9.9354391098,48.7881774902],"type":"Point"}
}