{
  "type": "Feature",
  "properties": {
    "iso:country":"DE",
    "sg:address":"Auf der B\u00f6ck 12",
    "sg:city":"D\u00fcsseldorf",
    "sg:phone":"+49 211/308947",
    "sg:postcode":"40221",
    "sg:province":"Nordrhein-Westfalen",
    "wof:name":"Hans Wiese",
    "wof:placetype":"venue"
},
  "geometry": {"coordinates":[6.735002,51.202496],"type":"Point"}
}