{
  "type": "Feature",
  "properties": {
    "iso:country":"DE",
    "sg:city":"Giggenhausen",
    "sg:phone":"+49 8165/8405",
    "sg:postcode":"85376",
    "sg:province":"Bayern",
    "wof:name":"Jos-bau Bauunternehmung Gmbh",
    "wof:placetype":"venue"
},
  "geometry": {"coordinates":[11.648442,48.363461],"type":"Point"}
}