{
  "type": "Feature",
  "properties": {
    "iso:country":"DE",
    "sg:address":"Berliner Str. 56",
    "sg:city":"Dortmund",
    "sg:phone":"+49 231/5600054",
    "sg:postcode":"44143",
    "sg:province":"Nordrhein-Westfalen",
    "wof:name":"Peter Rosenbaum Und Sabine T\u00f6lke",
    "wof:placetype":"venue"
},
  "geometry": {"coordinates":[7.5018129349,51.519241333],"type":"Point"}
}