{
  "type": "Feature",
  "properties": {
    "iso:country":"DE",
    "sg:address":"Daimlerstr. 7",
    "sg:city":"Marl",
    "sg:phone":"+49 2365/81237",
    "sg:postcode":"45770",
    "sg:province":"Nordrhein-Westfalen",
    "wof:name":"Fricke Kg",
    "wof:placetype":"venue"
},
  "geometry": {"coordinates":[7.165762,51.669788],"type":"Point"}
}