{
  "type": "Feature",
  "properties": {
    "iso:country":"DE",
    "sg:address":"Marktplatz 22",
    "sg:city":"Berchtesgaden",
    "sg:phone":"+49 8652/2390",
    "sg:postcode":"83471",
    "sg:province":"Bayern",
    "wof:name":"Bier-adam",
    "wof:placetype":"venue"
},
  "geometry": {"coordinates":[13.0005350113,47.6324806213],"type":"Point"}
}