{
  "type": "Feature",
  "properties": {
    "iso:country":"DE",
    "sg:address":"Birlenbacher Str 19",
    "sg:city":"Siegen",
    "sg:phone":"+49 271/313820",
    "sg:postcode":"57078",
    "sg:province":"Nordrhein-Westfalen",
    "wof:name":"Micro Mechatronic Technologies Ag",
    "wof:placetype":"venue"
},
  "geometry": {"coordinates":[8.006528,50.908329],"type":"Point"}
}