{
  "type": "Feature",
  "properties": {
    "iso:country":"DE",
    "sg:address":"Derner Str. 50",
    "sg:city":"Kamen",
    "sg:phone":"+49 2307/73169",
    "sg:postcode":"59174",
    "sg:province":"Nordrhein-Westfalen",
    "wof:name":"Kok",
    "wof:placetype":"venue"
},
  "geometry": {"coordinates":[7.6772141457,51.5944137573],"type":"Point"}
}