{
  "type": "Feature",
  "properties": {
    "iso:country":"DE",
    "sg:address":"Marktstr. 43",
    "sg:city":"Nagold",
    "sg:phone":"+49 7452/5055",
    "sg:postcode":"72202",
    "sg:province":"Baden-W\u00fcrttemberg",
    "wof:name":"Irion",
    "wof:placetype":"venue"
},
  "geometry": {"coordinates":[8.723064,48.552177],"type":"Point"}
}