{
  "type": "Feature",
  "properties": {
    "iso:country":"DE",
    "sg:address":"Otto-Findeisen-Str. 5",
    "sg:city":"Eibenstock",
    "sg:phone":"+49 37752/2071",
    "sg:postcode":"08309",
    "sg:province":"Sachsen",
    "wof:name":"Frank Neidhardt",
    "wof:placetype":"venue"
},
  "geometry": {"coordinates":[12.601275,50.494007],"type":"Point"}
}