{
  "type": "Feature",
  "properties": {
    "iso:country":"DE",
    "sg:address":"Lange Str. 39",
    "sg:city":"G\u00f6ppingen",
    "sg:phone":"+49 7161/75088",
    "sg:postcode":"73033",
    "sg:province":"Baden-W\u00fcrttemberg",
    "wof:name":"Senfkorn",
    "wof:placetype":"venue"
},
  "geometry": {"coordinates":[9.6506299973,48.7036628723],"type":"Point"}
}