{
  "type": "Feature",
  "properties": {
    "iso:country":"DE",
    "sg:address":"Johann-Strau\u00df-Str. 3",
    "sg:city":"Burgau",
    "sg:phone":"+49 8222/90129",
    "sg:postcode":"89331",
    "sg:province":"Bayern",
    "wof:name":"Wolfgang Renner Gmbh",
    "wof:placetype":"venue"
},
  "geometry": {"coordinates":[10.404079,48.420761],"type":"Point"}
}