{
  "type": "Feature",
  "properties": {
    "iso:country":"DE",
    "sg:address":"Bottroper Str. 2",
    "sg:city":"Braunschweig",
    "sg:phone":"+49 531/371753",
    "sg:postcode":"38108",
    "sg:province":"Niedersachsen",
    "wof:name":"K. P. Hoffmann",
    "wof:placetype":"venue"
},
  "geometry": {"coordinates":[10.5555582047,52.2887306213],"type":"Point"}
}