{
  "type": "Feature",
  "properties": {
    "iso:country":"DE",
    "sg:address":"Immenweg 17",
    "sg:city":"D\u00fcsseldorf",
    "sg:postcode":"40489",
    "sg:province":"Nordrhein-Westfalen",
    "wof:name":"Dvb - D\u00fcsseldorfer Verm\u00f6gensberatung Ohg",
    "wof:placetype":"venue"
},
  "geometry": {"coordinates":[6.7754950523,51.3217353821],"type":"Point"}
}