{
  "type": "Feature",
  "properties": {
    "iso:country":"DE",
    "sg:address":"Fichtenweg 18",
    "sg:city":"Germaringen",
    "sg:phone":"+49 8341/600600",
    "sg:postcode":"87656",
    "sg:province":"Bayern",
    "wof:name":"A. Woithe",
    "wof:placetype":"venue"
},
  "geometry": {"coordinates":[10.6731710434,47.9229621887],"type":"Point"}
}