{
  "type": "Feature",
  "properties": {
    "iso:country":"DE",
    "sg:address":"Aloisstr. 9",
    "sg:city":"Essen",
    "sg:phone":"+49 201/401169",
    "sg:postcode":"45239",
    "sg:province":"Nordrhein-Westfalen",
    "wof:name":"Dr. Henning Hattwig Dipl.-chem.",
    "wof:placetype":"venue"
},
  "geometry": {"coordinates":[7.0278429985,51.3874664307],"type":"Point"}
}