{
  "type": "Feature",
  "properties": {
    "iso:country":"DE",
    "sg:address":"Sonnenstr. 16",
    "sg:city":"Waldkraiburg",
    "sg:phone":"+49 8638/889134",
    "sg:postcode":"84478",
    "sg:province":"Bayern",
    "wof:name":"Gustav-adolf Assmann Rechtsanwalt",
    "wof:placetype":"venue"
},
  "geometry": {"coordinates":[12.3993663788,48.1982116699],"type":"Point"}
}