{
  "type": "Feature",
  "properties": {
    "iso:country":"DE",
    "sg:address":"Erbsenacker 3",
    "sg:city":"Wiesbaden",
    "sg:phone":"+49 6127/4151",
    "sg:postcode":"65207",
    "sg:province":"Hessen",
    "wof:name":"R. Thiel",
    "wof:placetype":"venue"
},
  "geometry": {"coordinates":[8.2965173721,50.1274490356],"type":"Point"}
}