{
  "type": "Feature",
  "properties": {
    "iso:country":"DE",
    "sg:address":"Am M\u00fchlgraben 10",
    "sg:city":"Zw\u00f6nitz",
    "sg:phone":"+49 37754/2904",
    "sg:postcode":"08297",
    "sg:province":"Sachsen",
    "wof:name":"Hotel Stadt Zw\u00f6nitz",
    "wof:placetype":"venue"
},
  "geometry": {"coordinates":[12.8112277985,50.6315574646],"type":"Point"}
}