{
  "type": "Feature",
  "properties": {
    "iso:country":"DE",
    "sg:address":"Gartenstr. 1",
    "sg:city":"Laubach",
    "sg:phone":"+49 6405/7379",
    "sg:postcode":"35321",
    "sg:province":"Hessen",
    "wof:name":"Reiner Sch\u00e4fer Heissmangel",
    "wof:placetype":"venue"
},
  "geometry": {"coordinates":[9.0224523544,50.5152359009],"type":"Point"}
}