{
  "type": "Feature",
  "properties": {
    "iso:country":"DE",
    "sg:address":"Hermann-Pistor-Str. 1",
    "sg:city":"Jena",
    "sg:phone":"+49 3641/617777",
    "sg:postcode":"07745",
    "sg:province":"Th\u00fcringen",
    "wof:name":"Carola Kaiser Gmbh Physiotherapie",
    "wof:placetype":"venue"
},
  "geometry": {"coordinates":[11.5719480515,50.9005088806],"type":"Point"}
}