{
  "type": "Feature",
  "properties": {
    "iso:country":"DE",
    "sg:address":"Annaburger Str. 29",
    "sg:city":"Gro\u00df Naundorf",
    "sg:phone":"+49 35385/20814",
    "sg:postcode":"06925",
    "sg:province":"Sachsen-Anhalt",
    "wof:name":"H. M\u00f6bius",
    "wof:placetype":"venue"
},
  "geometry": {"coordinates":[13.0054664612,51.6959495544],"type":"Point"}
}