{
  "type": "Feature",
  "properties": {
    "iso:country":"DE",
    "sg:address":"Norderstr. 38",
    "sg:city":"Flensburg",
    "sg:phone":"+49 461/957710",
    "sg:postcode":"24939",
    "sg:province":"Schleswig-Holstein",
    "wof:name":"Ergo Dialogmarketing",
    "wof:placetype":"venue"
},
  "geometry": {"coordinates":[9.4315786362,54.7915534973],"type":"Point"}
}