{
  "type": "Feature",
  "properties": {
    "iso:country":"DE",
    "sg:address":"Normannenstr. 52",
    "sg:city":"Oberhausen",
    "sg:phone":"+49 208/866294",
    "sg:postcode":"46047",
    "sg:province":"Nordrhein-Westfalen",
    "wof:name":"Peter Skrypczak",
    "wof:placetype":"venue"
},
  "geometry": {"coordinates":[6.867896,51.470139],"type":"Point"}
}