{
  "type": "Feature",
  "properties": {
    "iso:country":"DE",
    "sg:address":"Bruchhausenstr. 56",
    "sg:city":"D\u00fcsseldorf",
    "sg:postcode":"40591",
    "sg:province":"Nordrhein-Westfalen",
    "wof:name":"Rising Systems Networks Gmbh",
    "wof:placetype":"venue"
},
  "geometry": {"coordinates":[6.8257551193,51.1934013367],"type":"Point"}
}