{
  "type": "Feature",
  "properties": {
    "iso:country":"DE",
    "sg:address":"Erich-M\u00fchsam-Str. 6",
    "sg:city":"Rathenow",
    "sg:phone":"+49 3385/3570",
    "sg:postcode":"14712",
    "sg:province":"Brandenburg",
    "wof:name":"Artur Rausch",
    "wof:placetype":"venue"
},
  "geometry": {"coordinates":[12.349867,52.62286],"type":"Point"}
}