{
  "type": "Feature",
  "properties": {
    "iso:country":"DE",
    "sg:address":"Bauernweg 7",
    "sg:city":"Kelheim",
    "sg:phone":"+49 9441/21432",
    "sg:postcode":"93309",
    "sg:province":"Bayern",
    "wof:name":"B. Kemna Ingenieur",
    "wof:placetype":"venue"
},
  "geometry": {"coordinates":[11.893447,48.90081],"type":"Point"}
}