{
  "type": "Feature",
  "properties": {
    "iso:country":"DE",
    "sg:address":"Wanneweg 1",
    "sg:city":"Liebenau",
    "sg:phone":"+49 5676/1253",
    "sg:postcode":"34396",
    "sg:province":"Hessen",
    "wof:name":"Erich Kleinschmidt",
    "wof:placetype":"venue"
},
  "geometry": {"coordinates":[9.3008,51.48698],"type":"Point"}
}