{
  "type": "Feature",
  "properties": {
    "iso:country":"DE",
    "sg:address":"Stuttgarter Str. 38-42",
    "sg:city":"G\u00f6ppingen",
    "sg:phone":"+49 7161/23790",
    "sg:postcode":"73033",
    "sg:province":"Baden-W\u00fcrttemberg",
    "wof:name":"Gustav Blickle Gmbh Metallwarenfabrik",
    "wof:placetype":"venue"
},
  "geometry": {"coordinates":[9.6416501999,48.7060585022],"type":"Point"}
}