{
  "type": "Feature",
  "properties": {
    "iso:country":"DE",
    "sg:address":"Neue Liebe 1",
    "sg:city":"Essen",
    "sg:phone":"+49 201/8516860",
    "sg:postcode":"45276",
    "sg:province":"Nordrhein-Westfalen",
    "wof:name":"Bhw Bausparkasse Ag",
    "wof:placetype":"venue"
},
  "geometry": {"coordinates":[7.074526,51.452267],"type":"Point"}
}