{
  "type": "Feature",
  "properties": {
    "iso:country":"DE",
    "sg:address":"Im Buttendicksfeld 5",
    "sg:city":"Wesel",
    "sg:phone":"+49 281/82536",
    "sg:postcode":"46485",
    "sg:province":"Nordrhein-Westfalen",
    "wof:name":"K. Ayse",
    "wof:placetype":"venue"
},
  "geometry": {"coordinates":[6.668913,51.661514],"type":"Point"}
}