{
  "type": "Feature",
  "properties": {
    "iso:country":"DE",
    "sg:address":"Breslauer Str. 25",
    "sg:city":"Kaiserslautern",
    "sg:phone":"+49 631/70393",
    "sg:postcode":"67659",
    "sg:province":"Rheinland-Pfalz",
    "wof:name":"Arnold Scheubeck",
    "wof:placetype":"venue"
},
  "geometry": {"coordinates":[7.7435698509,49.4518585205],"type":"Point"}
}