{
  "type": "Feature",
  "properties": {
    "iso:country":"DE",
    "sg:address":"Reinsburgstr. 10::",
    "sg:city":"Stuttgart",
    "sg:phone":"+49 4971/166030",
    "sg:postcode":"70178",
    "sg:province":"Baden-W\u00fcrttemberg",
    "wof:name":"Hallesche-nationalekrankenversicherung A.g.",
    "wof:placetype":"venue"
},
  "geometry": {"coordinates":[9.169127,48.771351],"type":"Point"}
}