{
  "type": "Feature",
  "properties": {
    "iso:country":"DE",
    "sg:address":"Friedrichstr. 54",
    "sg:city":"Ettenheim",
    "sg:phone":"+49 7822/1493",
    "sg:postcode":"77955",
    "sg:province":"Baden-W\u00fcrttemberg",
    "wof:name":"Schulz Gmbh",
    "wof:placetype":"venue"
},
  "geometry": {"coordinates":[7.8132948875,48.2559280396],"type":"Point"}
}