{
  "type": "Feature",
  "properties": {
    "iso:country":"DE",
    "sg:address":"Beethovenstr. 12",
    "sg:city":"Illerkirchberg",
    "sg:phone":"+49 7346/3589",
    "sg:postcode":"89171",
    "sg:province":"Baden-W\u00fcrttemberg",
    "wof:name":"Erich Gerum Elektroinstallation",
    "wof:placetype":"venue"
},
  "geometry": {"coordinates":[10.018996,48.320267],"type":"Point"}
}