{
  "type": "Feature",
  "properties": {
    "iso:country":"DE",
    "sg:address":"Dorfstr. 41",
    "sg:city":"R\u00f6thlein",
    "sg:phone":"+49 9723/1320",
    "sg:postcode":"97520",
    "sg:province":"Bayern",
    "wof:name":"Robert Faulhaber",
    "wof:placetype":"venue"
},
  "geometry": {"coordinates":[10.204551,49.965969],"type":"Point"}
}