{
  "type": "Feature",
  "properties": {
    "iso:country":"DE",
    "sg:address":"Lange Gasse 18",
    "sg:city":"Elstra",
    "sg:phone":"+49 35793/5202",
    "sg:postcode":"01920",
    "sg:province":"Sachsen",
    "wof:name":"Rolf Schurig",
    "wof:placetype":"venue"
},
  "geometry": {"coordinates":[14.131521225,51.2223815918],"type":"Point"}
}