{
  "type": "Feature",
  "properties": {
    "iso:country":"DE",
    "sg:address":"Hoergenauer Str. 16 Engelrod",
    "sg:city":"Lautertal",
    "sg:phone":"+49 4966/4596140",
    "sg:postcode":"36369",
    "sg:province":"Hessen",
    "wof:name":"Caspar Bau Gmbh",
    "wof:placetype":"venue"
},
  "geometry": {"coordinates":[9.26444,50.580219],"type":"Point"}
}