{
  "type": "Feature",
  "properties": {
    "iso:country":"DE",
    "sg:address":"Melanchthonstr. 114",
    "sg:city":"Bretten",
    "sg:phone":"+49 7252/9140",
    "sg:postcode":"75015",
    "sg:province":"Baden-W\u00fcrttemberg",
    "wof:name":"Johann Stork Gmbh",
    "wof:placetype":"venue"
},
  "geometry": {"coordinates":[8.6963043213,49.0390548706],"type":"Point"}
}