{
  "type": "Feature",
  "properties": {
    "iso:country":"DE",
    "sg:address":"Bonner Wall 122",
    "sg:city":"K\u00f6ln",
    "sg:phone":"+49 221/382739",
    "sg:postcode":"50677",
    "sg:province":"Nordrhein-Westfalen",
    "wof:name":"Elmot Bollig & Beyenburg Ohg",
    "wof:placetype":"venue"
},
  "geometry": {"coordinates":[6.950541,50.918758],"type":"Point"}
}