{
  "type": "Feature",
  "properties": {
    "iso:country":"DE",
    "sg:address":"Vordere Str. 46",
    "sg:city":"Bissingen",
    "sg:phone":"+49 7023/5441",
    "sg:postcode":"73266",
    "sg:province":"Baden-W\u00fcrttemberg",
    "wof:name":"Magda Schaufler Haus- Und K\u00fcchenger\u00e4te",
    "wof:placetype":"venue"
},
  "geometry": {"coordinates":[9.4915437698,48.5996017456],"type":"Point"}
}