{
  "type": "Feature",
  "properties": {
    "iso:country":"DE",
    "sg:address":"W\u00e4hlingsweg 30",
    "sg:city":"Hamburg",
    "sg:phone":"+49 40/5508914",
    "sg:postcode":"22459",
    "sg:province":"Hamburg",
    "wof:name":"Fritz Puszies Ingenieur",
    "wof:placetype":"venue"
},
  "geometry": {"coordinates":[9.9191818237,53.6292533875],"type":"Point"}
}