{
  "type": "Feature",
  "properties": {
    "iso:country":"DE",
    "sg:address":"Max-Eyth-Str. 12",
    "sg:city":"H\u00fcttlingen",
    "sg:phone":"+49 7361/78360",
    "sg:postcode":"73460",
    "sg:province":"Baden-W\u00fcrttemberg",
    "wof:name":"P. D\u00f6rr",
    "wof:placetype":"venue"
},
  "geometry": {"coordinates":[10.113314,48.894432],"type":"Point"}
}