{
  "type": "Feature",
  "properties": {
    "iso:country":"DE",
    "sg:address":"Am Waldrand 11",
    "sg:city":"Karlskron",
    "sg:phone":"+49 8453/1212",
    "sg:postcode":"85123",
    "sg:province":"Bayern",
    "wof:name":"Kurt Kraus",
    "wof:placetype":"venue"
},
  "geometry": {"coordinates":[11.400103569,48.6528511047],"type":"Point"}
}