{
  "type": "Feature",
  "properties": {
    "iso:country":"DE",
    "sg:address":"Ulestr. 2",
    "sg:city":"Halle",
    "sg:phone":"+49 345/3881851",
    "sg:postcode":"06114",
    "sg:province":"Sachsen-Anhalt",
    "wof:name":"Peter Sch\u00f6ne",
    "wof:placetype":"venue"
},
  "geometry": {"coordinates":[11.9588661194,51.4928016663],"type":"Point"}
}