{
  "type": "Feature",
  "properties": {
    "iso:country":"DE",
    "sg:address":"Hertzstr. 18",
    "sg:city":"Berlin",
    "sg:phone":"+49 30/9169990",
    "sg:postcode":"13158",
    "sg:province":"Berlin",
    "wof:name":"Steuerberatungs Gmbh",
    "wof:placetype":"venue"
},
  "geometry": {"coordinates":[13.3653593063,52.585105896],"type":"Point"}
}