{
  "type": "Feature",
  "properties": {
    "iso:country":"DE",
    "sg:address":"Walther-Rathenau-Str. 168a",
    "sg:city":"Nordenham",
    "sg:phone":"+49 4731/21982",
    "sg:postcode":"26954",
    "sg:province":"Niedersachsen",
    "wof:name":"Wohnungsbaugesellschaft Wesermarsch Gmbh",
    "wof:placetype":"venue"
},
  "geometry": {"coordinates":[8.4830684662,53.4943237305],"type":"Point"}
}