{
  "type": "Feature",
  "properties": {
    "iso:country":"DE",
    "sg:address":"\u00d6lstr. 2",
    "sg:city":"K\u00f6ln",
    "sg:phone":"+49 221/541226",
    "sg:postcode":"50825",
    "sg:province":"Nordrhein-Westfalen",
    "wof:name":"Kunst- Und Einrichtungshaus Georg Fahrbach Gmbh & Co. Kg",
    "wof:placetype":"venue"
},
  "geometry": {"coordinates":[6.9098100662,50.9432411194],"type":"Point"}
}