{
  "type": "Feature",
  "properties": {
    "iso:country":"DE",
    "sg:address":"Gartenstr. 14",
    "sg:city":"Ahlen",
    "sg:phone":"+49 2528/521",
    "sg:postcode":"59227",
    "sg:province":"Nordrhein-Westfalen",
    "wof:name":"J. Schlimbach",
    "wof:placetype":"venue"
},
  "geometry": {"coordinates":[7.939740181,51.8066444397],"type":"Point"}
}