{
  "type": "Feature",
  "properties": {
    "iso:country":"DE",
    "sg:address":"Breitensteinweg 14",
    "sg:city":"Ober-Ramstadt",
    "sg:postcode":"64372",
    "sg:province":"Hessen",
    "wof:name":"Cms Caparol Marketing Services Gmbh",
    "wof:placetype":"venue"
},
  "geometry": {"coordinates":[8.7457265854,49.824344635],"type":"Point"}
}