{
  "type": "Feature",
  "properties": {
    "iso:country":"DE",
    "sg:address":"Haus 39",
    "sg:city":"Techentin",
    "sg:phone":"+49 38736/7528",
    "sg:postcode":"19399",
    "sg:province":"Mecklenburg-Vorpommern",
    "wof:name":"R. Lewerenz",
    "wof:placetype":"venue"
},
  "geometry": {"coordinates":[12.08928,53.591721],"type":"Point"}
}