{
  "type": "Feature",
  "properties": {
    "iso:country":"DE",
    "sg:address":"W\u00f6hrder Hauptstr. 1",
    "sg:city":"N\u00fcrnberg",
    "sg:phone":"+49 911/532848",
    "sg:postcode":"90489",
    "sg:province":"Bayern",
    "wof:name":"Kosmetikstudio Ott",
    "wof:placetype":"venue"
},
  "geometry": {"coordinates":[11.093484,49.454781],"type":"Point"}
}