{
  "type": "Feature",
  "properties": {
    "iso:country":"DE",
    "sg:address":"Industriestra\u00dfe 1",
    "sg:city":"Nottuln",
    "sg:phone":"+49 2509/99140",
    "sg:postcode":"48301",
    "sg:province":"Nordrhein-Westfalen",
    "wof:name":"Kleancontor Gmbh",
    "wof:placetype":"venue"
},
  "geometry": {"coordinates":[7.4306550026,51.8919906616],"type":"Point"}
}