{
  "type": "Feature",
  "properties": {
    "iso:country":"DE",
    "sg:address":"Am Hofgarten 6",
    "sg:city":"B\u00fcckeburg",
    "sg:phone":"+49 5722/3677",
    "sg:postcode":"31675",
    "sg:province":"Niedersachsen",
    "wof:name":"Heinrich Nordmeier",
    "wof:placetype":"venue"
},
  "geometry": {"coordinates":[9.0395059586,52.2640266418],"type":"Point"}
}