{
  "type": "Feature",
  "properties": {
    "iso:country":"DE",
    "sg:address":"Peterssteinweg 13",
    "sg:city":"Leipzig",
    "sg:phone":"+49 341/9612964",
    "sg:postcode":"04107",
    "sg:province":"Sachsen",
    "wof:name":"Wolfgang Fischer",
    "wof:placetype":"venue"
},
  "geometry": {"coordinates":[12.3738937378,51.3333091736],"type":"Point"}
}