{
  "type": "Feature",
  "properties": {
    "iso:country":"DE",
    "sg:address":"Schulstr. 11",
    "sg:city":"Wilkau-Ha\u00dflau",
    "sg:postcode":"08112",
    "sg:province":"Sachsen",
    "wof:name":"Evangelische-meth. Kreuzkirche",
    "wof:placetype":"venue"
},
  "geometry": {"coordinates":[12.5153617859,50.672542572],"type":"Point"}
}