{
  "type": "Feature",
  "properties": {
    "iso:country":"DE",
    "sg:address":"Benzstr. 6",
    "sg:city":"Bocholt",
    "sg:phone":"+49 2871/181081",
    "sg:postcode":"46395",
    "sg:province":"Nordrhein-Westfalen",
    "wof:name":"Kawatherm Metallverarbeitung Gmbh",
    "wof:placetype":"venue"
},
  "geometry": {"coordinates":[6.608876,51.820602],"type":"Point"}
}