{
  "type": "Feature",
  "properties": {
    "iso:country":"DE",
    "sg:address":"Osserstr. 10",
    "sg:city":"Deuerling",
    "sg:phone":"+49 9498/1777",
    "sg:postcode":"93180",
    "sg:province":"Bayern",
    "wof:name":"Gustav Heller Bauschlosserei",
    "wof:placetype":"venue"
},
  "geometry": {"coordinates":[11.917792,49.042282],"type":"Point"}
}