{
  "type": "Feature",
  "properties": {
    "iso:country":"DE",
    "sg:address":"Kohlhasenbr\u00fccker Str. 9",
    "sg:city":"Berlin",
    "sg:phone":"+49 30/8052575",
    "sg:postcode":"14109",
    "sg:province":"Berlin",
    "wof:name":"Manfred Wernicke",
    "wof:placetype":"venue"
},
  "geometry": {"coordinates":[13.143245697,52.4113388062],"type":"Point"}
}