{
  "type": "Feature",
  "properties": {
    "iso:country":"DE",
    "sg:address":"R\u00fcdesheimer Str. 18",
    "sg:city":"Wiesbaden",
    "sg:postcode":"65197",
    "sg:province":"Hessen",
    "wof:name":"Schilling Hmd Gmbh",
    "wof:placetype":"venue"
},
  "geometry": {"coordinates":[8.2279205322,50.0753173828],"type":"Point"}
}