{
  "type": "Feature",
  "properties": {
    "iso:country":"DE",
    "sg:address":"Ohligser Weg 22",
    "sg:city":"Hilden",
    "sg:phone":"+49 2103/64922",
    "sg:postcode":"40723",
    "sg:province":"Nordrhein-Westfalen",
    "wof:name":"Albert Mellinghoff Architekt",
    "wof:placetype":"venue"
},
  "geometry": {"coordinates":[6.948695,51.158031],"type":"Point"}
}