{
  "type": "Feature",
  "properties": {
    "iso:country":"DE",
    "sg:address":"Karlsruher Str. 26",
    "sg:city":"Hockenheim",
    "sg:phone":"+49 6205/16210",
    "sg:postcode":"68766",
    "sg:province":"Baden-W\u00fcrttemberg",
    "wof:name":"Et Cetera",
    "wof:placetype":"venue"
},
  "geometry": {"coordinates":[8.542157,49.317802],"type":"Point"}
}