{
  "type": "Feature",
  "properties": {
    "iso:country":"DE",
    "sg:address":"Hausacher Str. 23",
    "sg:city":"Haslach",
    "sg:postcode":"77716",
    "sg:province":"Baden-W\u00fcrttemberg",
    "wof:name":"Dragon Verkaufsges. Mbh",
    "wof:placetype":"venue"
},
  "geometry": {"coordinates":[8.1109752655,48.287071228],"type":"Point"}
}