{
  "type": "Feature",
  "properties": {
    "iso:country":"DE",
    "sg:address":"Ringstr. 7",
    "sg:city":"Messel",
    "sg:phone":"+49 6159/1356",
    "sg:postcode":"64409",
    "sg:province":"Hessen",
    "wof:name":"Steffen Geiger",
    "wof:placetype":"venue"
},
  "geometry": {"coordinates":[8.7395372391,49.933216095],"type":"Point"}
}