{
  "type": "Feature",
  "properties": {
    "iso:country":"DE",
    "sg:address":"Neuheider Weg 6a",
    "sg:city":"St\u00fctzengr\u00fcn",
    "sg:phone":"+49 37462/3520",
    "sg:postcode":"08328",
    "sg:province":"Sachsen",
    "wof:name":"Modehaus Tr\u00f6ger Gmbh",
    "wof:placetype":"venue"
},
  "geometry": {"coordinates":[12.5203771591,50.5238609314],"type":"Point"}
}