{
  "type": "Feature",
  "properties": {
    "iso:country":"DE",
    "sg:address":"Stellenbachstr. 36-38",
    "sg:city":"L\u00fcnen",
    "sg:phone":"+49 231/875643",
    "sg:postcode":"44536",
    "sg:province":"Nordrhein-Westfalen",
    "wof:name":"W\u00fcnderich-brennstoffhandel- Transporte Gmbh",
    "wof:placetype":"venue"
},
  "geometry": {"coordinates":[7.45727,51.605461],"type":"Point"}
}