{
  "type": "Feature",
  "properties": {
    "iso:country":"DE",
    "sg:address":"R\u00fctenbrocker Str. 17",
    "sg:city":"Haren",
    "sg:phone":"+49 5932/5060",
    "sg:postcode":"49733",
    "sg:province":"Niedersachsen",
    "wof:name":"Albers Verm\u00f6gensverwaltungs- Und Beteiligungsges. Mbh",
    "wof:placetype":"venue"
},
  "geometry": {"coordinates":[7.22989,52.792816],"type":"Point"}
}