{
  "type": "Feature",
  "properties": {
    "iso:country":"DE",
    "sg:address":"Dahlienweg 19",
    "sg:city":"Ostfildern",
    "sg:phone":"+49 711/4411028",
    "sg:postcode":"73760",
    "sg:province":"Baden-W\u00fcrttemberg",
    "wof:name":"Contrast Gesellschaft F\u00fcr Entwurf Und Druck Mbh",
    "wof:placetype":"venue"
},
  "geometry": {"coordinates":[9.2581014633,48.7318153381],"type":"Point"}
}