{
  "type": "Feature",
  "properties": {
    "iso:country":"DE",
    "sg:address":"Ostring 16",
    "sg:city":"Landau",
    "sg:phone":"+49 6341/86901",
    "sg:postcode":"76829",
    "sg:province":"Rheinland-Pfalz",
    "wof:name":"Boulevard",
    "wof:placetype":"venue"
},
  "geometry": {"coordinates":[8.1193752289,49.1979484558],"type":"Point"}
}