{
  "type": "Feature",
  "properties": {
    "iso:country":"DE",
    "sg:address":"Feldbergstrasse 8",
    "sg:city":"Weilm\u00fcnster",
    "sg:phone":"+49 6472",
    "sg:postcode":"35789",
    "sg:province":"Hessen",
    "wof:name":"Otto Jung Gmbh",
    "wof:placetype":"venue"
},
  "geometry": {"coordinates":[8.384839,50.424824],"type":"Point"}
}