{
  "type": "Feature",
  "properties": {
    "iso:country":"DE",
    "sg:address":"Killistr. 6",
    "sg:city":"Egmating",
    "sg:phone":"+49 8093/5336",
    "sg:postcode":"85658",
    "sg:province":"Bayern",
    "wof:name":"Haflhof Ott",
    "wof:placetype":"venue"
},
  "geometry": {"coordinates":[11.8342838287,47.9706840515],"type":"Point"}
}