{
  "type": "Feature",
  "properties": {
    "iso:country":"DE",
    "sg:address":"Maxim-Gorki-Str. 33",
    "sg:city":"Seebad Heringsdorf",
    "sg:phone":"+49 38378/22954",
    "sg:postcode":"17424",
    "sg:province":"Mecklenburg-Vorpommern",
    "wof:name":"Manfred Wanke",
    "wof:placetype":"venue"
},
  "geometry": {"coordinates":[14.1511068344,53.966758728],"type":"Point"}
}