{
  "type": "Feature",
  "properties": {
    "iso:country":"DE",
    "sg:address":"Provinzialstr. 109",
    "sg:city":"Ensdorf",
    "sg:phone":"+49 6831/54092",
    "sg:postcode":"66806",
    "sg:province":"Saarland",
    "wof:name":"Seniorenheim Alten- Und Pflegeheim",
    "wof:placetype":"venue"
},
  "geometry": {"coordinates":[6.778361,49.307594],"type":"Point"}
}