{
  "type": "Feature",
  "properties": {
    "iso:country":"DE",
    "sg:address":"R\u00fcdersdorfer Str. 35",
    "sg:city":"Woltersdorf",
    "sg:phone":"+49 3362/75762",
    "sg:postcode":"15569",
    "sg:province":"Brandenburg",
    "wof:name":"Verena Adolph Ingenieurin",
    "wof:placetype":"venue"
},
  "geometry": {"coordinates":[13.7609052658,52.4610328674],"type":"Point"}
}