{
  "type": "Feature",
  "properties": {
    "iso:country":"DE",
    "sg:address":"Hildesheimer Str. 123",
    "sg:city":"Laatzen",
    "sg:phone":"+49 511/862429",
    "sg:postcode":"30880",
    "sg:province":"Niedersachsen",
    "wof:name":"Manfred R\u00f6sler Gmbh",
    "wof:placetype":"venue"
},
  "geometry": {"coordinates":[9.796955,52.311008],"type":"Point"}
}