{
  "type": "Feature",
  "properties": {
    "iso:country":"DE",
    "sg:address":"St.-Wendeler-Str. 29",
    "sg:city":"Namborn",
    "sg:phone":"+49 6851/70907",
    "sg:postcode":"66640",
    "sg:province":"Saarland",
    "wof:name":"H.-j. Jung",
    "wof:placetype":"venue"
},
  "geometry": {"coordinates":[7.162479,49.489086],"type":"Point"}
}