{
  "type": "Feature",
  "properties": {
    "iso:country":"DE",
    "sg:address":"Alexanderstr. 89",
    "sg:city":"Oldenburg",
    "sg:phone":"+49 441/85910",
    "sg:postcode":"26121",
    "sg:province":"Niedersachsen",
    "wof:name":"Esso Deutschland Gmbh",
    "wof:placetype":"venue"
},
  "geometry": {"coordinates":[8.2101669312,53.1540527344],"type":"Point"}
}