{
  "type": "Feature",
  "properties": {
    "iso:country":"DE",
    "sg:address":"Backesweg 2",
    "sg:city":"Brachbach",
    "sg:phone":"+49 2745/8328",
    "sg:postcode":"57555",
    "sg:province":"Rheinland-Pfalz",
    "wof:name":"Ludwig Euteneuer Ingenieur",
    "wof:placetype":"venue"
},
  "geometry": {"coordinates":[7.9343371391,50.814617157],"type":"Point"}
}