{
  "type": "Feature",
  "properties": {
    "iso:country":"DE",
    "sg:address":"Himmelreichstr. 34",
    "sg:city":"Ebensfeld",
    "sg:phone":"+49 9573/5502",
    "sg:postcode":"96250",
    "sg:province":"Bayern",
    "wof:name":"Carussell",
    "wof:placetype":"venue"
},
  "geometry": {"coordinates":[10.9590482712,50.0715675354],"type":"Point"}
}