{
  "type": "Feature",
  "properties": {
    "iso:country":"DE",
    "sg:address":"Christine-Englerth-Str. 6",
    "sg:city":"Recklinghausen",
    "sg:postcode":"45665",
    "sg:province":"Nordrhein-Westfalen",
    "wof:name":"Ms-maschinen-service Gmbh & Co. Handels-kg",
    "wof:placetype":"venue"
},
  "geometry": {"coordinates":[7.246286,51.605827],"type":"Point"}
}