{
  "type": "Feature",
  "properties": {
    "iso:country":"DE",
    "sg:address":"Bahnhofstr. 54",
    "sg:city":"Witten",
    "sg:phone":"+49 2302/276873",
    "sg:postcode":"58452",
    "sg:province":"Nordrhein-Westfalen",
    "wof:name":"Gu Gastst\u00e4ttenbetriebs- Gmbh",
    "wof:placetype":"venue"
},
  "geometry": {"coordinates":[7.3308429718,51.4378852844],"type":"Point"}
}