{
  "type": "Feature",
  "properties": {
    "iso:country":"DE",
    "sg:address":"F\u00fcrbringer Str. 25",
    "sg:city":"Berlin",
    "sg:phone":"+49 4930/691202",
    "sg:postcode":"10961",
    "sg:province":"Berlin",
    "wof:name":"Timescraper Music",
    "wof:placetype":"venue"
},
  "geometry": {"coordinates":[13.3963851929,52.4932060242],"type":"Point"}
}