{
  "type": "Feature",
  "properties": {
    "iso:country":"DE",
    "sg:address":"Teutendorfer Weg 10a",
    "sg:city":"L\u00fcbeck",
    "sg:phone":"+49 4502/3207",
    "sg:postcode":"23570",
    "sg:province":"Schleswig-Holstein",
    "wof:name":"Farben Schr\u00f6der Gmbh",
    "wof:placetype":"venue"
},
  "geometry": {"coordinates":[10.8547258377,53.9577713013],"type":"Point"}
}