{
  "type": "Feature",
  "properties": {
    "iso:country":"DE",
    "sg:address":"Akazienallee 15",
    "sg:city":"Zepernick",
    "sg:phone":"+49 30/9444320",
    "sg:postcode":"16341",
    "sg:province":"Brandenburg",
    "wof:name":"Lutz Kramer",
    "wof:placetype":"venue"
},
  "geometry": {"coordinates":[13.5189743042,52.653087616],"type":"Point"}
}