{
  "type": "Feature",
  "properties": {
    "iso:country":"DE",
    "sg:address":"Husumer Str. 11",
    "sg:city":"Bredstedt",
    "sg:phone":"+49 4671/2331",
    "sg:postcode":"25821",
    "sg:province":"Schleswig-Holstein",
    "wof:name":"Hans-heinrich Lorenzen",
    "wof:placetype":"venue"
},
  "geometry": {"coordinates":[8.973669,54.615669],"type":"Point"}
}