{
  "type": "Feature",
  "properties": {
    "iso:country":"DE",
    "sg:address":"Bahnhofstrasse 12-21",
    "sg:city":"Ettlingen",
    "sg:postcode":"76275",
    "sg:province":"Baden-W\u00fcrttemberg",
    "wof:name":"Elba Werk Maschinengesellschaft Mbh Ettlingen",
    "wof:placetype":"venue"
},
  "geometry": {"coordinates":[8.3882598877,48.9460716248],"type":"Point"}
}