{
  "type": "Feature",
  "properties": {
    "iso:country":"DE",
    "sg:address":"Bixterhauser Hellweg 49",
    "sg:city":"Iserlohn",
    "sg:phone":"+49 2371/41513",
    "sg:postcode":"58640",
    "sg:province":"Nordrhein-Westfalen",
    "wof:name":"K. Mackenbach",
    "wof:placetype":"venue"
},
  "geometry": {"coordinates":[7.7183,51.409767],"type":"Point"}
}