{
  "type": "Feature",
  "properties": {
    "iso:country":"DE",
    "sg:address":"Kirchstr. 5",
    "sg:city":"Sinn",
    "sg:phone":"+49 2772/52077",
    "sg:postcode":"35764",
    "sg:province":"Hessen",
    "wof:name":"Karl Metz Gmbh",
    "wof:placetype":"venue"
},
  "geometry": {"coordinates":[8.32975,50.653141],"type":"Point"}
}