{
  "type": "Feature",
  "properties": {
    "iso:country":"DE",
    "sg:address":"Frankenstr. 10",
    "sg:city":"Hamburg",
    "sg:phone":"+49 40/237770",
    "sg:postcode":"20097",
    "sg:province":"Hamburg",
    "wof:name":"Oskar Schunck Kg",
    "wof:placetype":"venue"
},
  "geometry": {"coordinates":[10.0229816437,53.5479354858],"type":"Point"}
}