{
  "type": "Feature",
  "properties": {
    "iso:country":"DE",
    "sg:address":"Dorfstr. 2",
    "sg:city":"Dresden",
    "sg:phone":"+49 351/2019514",
    "sg:postcode":"01257",
    "sg:province":"Sachsen",
    "wof:name":"Gertraude Br\u00fcckner",
    "wof:placetype":"venue"
},
  "geometry": {"coordinates":[13.822257,50.997913],"type":"Point"}
}