{
  "type": "Feature",
  "properties": {
    "iso:country":"DE",
    "sg:address":"Prenzlauer Str. 51",
    "sg:city":"Gramzow",
    "sg:phone":"+49 39861/821",
    "sg:postcode":"17291",
    "sg:province":"Brandenburg",
    "wof:name":"Gr\u00fcner Baum",
    "wof:placetype":"venue"
},
  "geometry": {"coordinates":[14.0038948059,53.2106399536],"type":"Point"}
}