{
  "type": "Feature",
  "properties": {
    "iso:country":"DE",
    "sg:address":"Ludwigstr. 14",
    "sg:city":"Winnenden",
    "sg:phone":"+49 7195/178046",
    "sg:postcode":"71364",
    "sg:province":"Baden-W\u00fcrttemberg",
    "wof:name":"Bernhardt Leppin \u00dcbersetzer",
    "wof:placetype":"venue"
},
  "geometry": {"coordinates":[9.408004,48.873386],"type":"Point"}
}