{
  "type": "Feature",
  "properties": {
    "iso:country":"DE",
    "sg:address":"Am Neuen Garten 10",
    "sg:city":"Potsdam",
    "sg:postcode":"14469",
    "sg:province":"Brandenburg",
    "wof:name":"Regenbogenwelt Marketing Gmbh",
    "wof:placetype":"venue"
},
  "geometry": {"coordinates":[13.0630559921,52.4115257263],"type":"Point"}
}