{
  "type": "Feature",
  "properties": {
    "iso:country":"DE",
    "sg:city":"Oerel",
    "sg:phone":"+49 4765/715",
    "sg:postcode":"27432",
    "sg:province":"Niedersachsen",
    "wof:name":"Anke Sylvester",
    "wof:placetype":"venue"
},
  "geometry": {"coordinates":[9.055175,53.48138],"type":"Point"}
}