{
  "type": "Feature",
  "properties": {
    "iso:country":"DE",
    "sg:address":"M\u00fchlhofweg 2",
    "sg:city":"Wolfhagen",
    "sg:phone":"+49 5606/53797",
    "sg:postcode":"34466",
    "sg:province":"Hessen",
    "wof:name":"Heinz Lindenborn",
    "wof:placetype":"venue"
},
  "geometry": {"coordinates":[9.170094,51.328537],"type":"Point"}
}