{
  "type": "Feature",
  "properties": {
    "iso:country":"DE",
    "sg:address":"W\u00fcrzburger Str. 74",
    "sg:city":"Dresden",
    "sg:phone":"+49 351/4714922",
    "sg:postcode":"01187",
    "sg:province":"Sachsen",
    "wof:name":"Autohaus Herbe Gmbh",
    "wof:placetype":"venue"
},
  "geometry": {"coordinates":[13.718917,51.027569],"type":"Point"}
}