{
  "type": "Feature",
  "properties": {
    "iso:country":"DE",
    "sg:address":"Laubersteigweg 19",
    "sg:city":"Gro\u00dfbottwar",
    "sg:phone":"+49 7148/1276",
    "sg:postcode":"71723",
    "sg:province":"Baden-W\u00fcrttemberg",
    "wof:name":"Landwirtschaftlicher Orts- Verein Winzerhausen",
    "wof:placetype":"venue"
},
  "geometry": {"coordinates":[9.2578468323,49.0243797302],"type":"Point"}
}