{
  "type": "Feature",
  "properties": {
    "iso:country":"DE",
    "sg:address":"Merianstr. 23",
    "sg:city":"Bruchsal",
    "sg:phone":"+49 7251/5129",
    "sg:postcode":"76646",
    "sg:province":"Baden-W\u00fcrttemberg",
    "wof:name":"Horst K\u00f6ger",
    "wof:placetype":"venue"
},
  "geometry": {"coordinates":[8.6456613541,49.1012306213],"type":"Point"}
}