{
  "type": "Feature",
  "properties": {
    "iso:country":"DE",
    "sg:address":"Rothenburger Str. 13",
    "sg:city":"Gro\u00dfhabersdorf",
    "sg:phone":"+49 9105/798",
    "sg:postcode":"90613",
    "sg:province":"Bayern",
    "wof:name":"G\u00fcnther Reitzammer",
    "wof:placetype":"venue"
},
  "geometry": {"coordinates":[10.7876291275,49.4054985046],"type":"Point"}
}