{
  "type": "Feature",
  "properties": {
    "iso:country":"DE",
    "sg:address":"Gaststr. 13",
    "sg:city":"Oldenburg",
    "sg:phone":"+49 441/27788",
    "sg:postcode":"26122",
    "sg:province":"Niedersachsen",
    "wof:name":"Flic Flac",
    "wof:placetype":"venue"
},
  "geometry": {"coordinates":[8.211939,53.13942],"type":"Point"}
}