{
  "type": "Feature",
  "properties": {
    "iso:country":"DE",
    "sg:address":"Kalkweg 72",
    "sg:city":"Duisburg",
    "sg:phone":"+49 203/726285",
    "sg:postcode":"47055",
    "sg:province":"Nordrhein-Westfalen",
    "wof:name":"Josef Arend Ingenieur",
    "wof:placetype":"venue"
},
  "geometry": {"coordinates":[6.777162075,51.4057540894],"type":"Point"}
}