{
  "type": "Feature",
  "properties": {
    "iso:country":"DE",
    "sg:address":"Marbachweg 57",
    "sg:city":"Frankfurt",
    "sg:phone":"+49 69/234309",
    "sg:postcode":"60435",
    "sg:province":"Hessen",
    "wof:name":"H. Freyholdt Parf\u00fcmerie",
    "wof:placetype":"venue"
},
  "geometry": {"coordinates":[8.698673,50.144882],"type":"Point"}
}