{
  "type": "Feature",
  "properties": {
    "iso:country":"DE",
    "sg:address":"Theresienh\u00f6he 141",
    "sg:city":"H\u00fcrth",
    "sg:phone":"+49 2233/974720",
    "sg:postcode":"50354",
    "sg:province":"Nordrhein-Westfalen",
    "wof:name":"Kaufmann Fachgesch\u00e4ft F\u00fcr Haushaltstechnik Gmbh",
    "wof:placetype":"venue"
},
  "geometry": {"coordinates":[6.8759050369,50.8783454895],"type":"Point"}
}