{
  "type": "Feature",
  "properties": {
    "iso:country":"DE",
    "sg:address":"Nikolaus-Unruh-Str. 15",
    "sg:city":"Arzberg",
    "sg:phone":"+49 9233/774040",
    "sg:postcode":"95659",
    "sg:province":"Bayern",
    "wof:name":"Arzberger",
    "wof:placetype":"venue"
},
  "geometry": {"coordinates":[12.1782197952,50.0580291748],"type":"Point"}
}