{
  "type": "Feature",
  "properties": {
    "iso:country":"DE",
    "sg:address":"Wolfweg 23",
    "sg:city":"Schwanau",
    "sg:phone":"+49 7824/992",
    "sg:postcode":"77963",
    "sg:province":"Baden-W\u00fcrttemberg",
    "wof:name":"Gerold Zimmer",
    "wof:placetype":"venue"
},
  "geometry": {"coordinates":[7.7637729645,48.3464584351],"type":"Point"}
}