{
  "type": "Feature",
  "properties": {
    "iso:country":"DE",
    "sg:address":"Thomas-Mann-Str. 17",
    "sg:city":"Herzebrock-Clarholz",
    "sg:postcode":"33442",
    "sg:province":"Nordrhein-Westfalen",
    "wof:name":"West Holding Gmbh",
    "wof:placetype":"venue"
},
  "geometry": {"coordinates":[8.235555,51.881615],"type":"Point"}
}