{
  "type": "Feature",
  "properties": {
    "iso:country":"DE",
    "sg:address":"Grombacher Str. 11",
    "sg:city":"Bad Rappenau",
    "sg:phone":"+49 7268/911357",
    "sg:postcode":"74906",
    "sg:province":"Baden-W\u00fcrttemberg",
    "wof:name":"R. Granzer",
    "wof:placetype":"venue"
},
  "geometry": {"coordinates":[9.039475441,49.2550964355],"type":"Point"}
}