{
  "type": "Feature",
  "properties": {
    "iso:country":"DE",
    "sg:address":"Irmgardstr. 18",
    "sg:city":"Gelsenkirchen",
    "sg:phone":"+49 209/1487851",
    "sg:postcode":"45888",
    "sg:province":"Nordrhein-Westfalen",
    "wof:name":"K & F Trockenbau Gmbh",
    "wof:placetype":"venue"
},
  "geometry": {"coordinates":[7.116773,51.515755],"type":"Point"}
}