{
  "type": "Feature",
  "properties": {
    "iso:country":"DE",
    "sg:address":"Bronnbachergasse 29/31",
    "sg:city":"W\u00fcrzburg",
    "sg:phone":"+49 931/3043943",
    "sg:postcode":"97070",
    "sg:province":"Bayern",
    "wof:name":"Bernhard Horsinka Rechtsanwalt",
    "wof:placetype":"venue"
},
  "geometry": {"coordinates":[9.9295244217,49.7958908081],"type":"Point"}
}