{
  "type": "Feature",
  "properties": {
    "iso:country":"DE",
    "sg:address":"Obere Hauptstr. 260 a",
    "sg:city":"Lustadt",
    "sg:phone":"+49 6347/338",
    "sg:postcode":"67363",
    "sg:province":"Rheinland-Pfalz",
    "wof:name":"Georg Vollmer",
    "wof:placetype":"venue"
},
  "geometry": {"coordinates":[8.2717399597,49.2447471619],"type":"Point"}
}