{
  "type": "Feature",
  "properties": {
    "iso:country":"DE",
    "sg:address":"Friedensstra\u00dfe 6",
    "sg:city":"Bad Salzungen",
    "sg:phone":"+49 3695",
    "sg:postcode":"36433",
    "sg:province":"Th\u00fcringen",
    "wof:name":"Computer-web-shop",
    "wof:placetype":"venue"
},
  "geometry": {"coordinates":[10.208945,50.790794],"type":"Point"}
}