{
  "type": "Feature",
  "properties": {
    "iso:country":"DE",
    "sg:address":"Seydelstr. 19",
    "sg:city":"Berlin",
    "sg:phone":"+49 30/2792530",
    "sg:postcode":"10117",
    "sg:province":"Berlin",
    "wof:name":"Dr. Rummert Immobilienmakler",
    "wof:placetype":"venue"
},
  "geometry": {"coordinates":[13.4052295685,52.5084686279],"type":"Point"}
}