{
  "type": "Feature",
  "properties": {
    "iso:country":"DE",
    "sg:address":"Dinglingerstr. 45",
    "sg:city":"Biberach",
    "sg:phone":"+49 7351/12046",
    "sg:postcode":"88400",
    "sg:province":"Baden-W\u00fcrttemberg",
    "wof:name":"Wilhelm Belz Spedition Gmbh & Co. Kg",
    "wof:placetype":"venue"
},
  "geometry": {"coordinates":[9.7766494751,48.0955047607],"type":"Point"}
}