{
  "type": "Feature",
  "properties": {
    "iso:country":"DE",
    "sg:address":"Schwabenallee 33",
    "sg:city":"Berlin",
    "sg:phone":"+49 30/5143598",
    "sg:postcode":"12683",
    "sg:province":"Berlin",
    "wof:name":"Btb L\u00fcgger Gmbh",
    "wof:placetype":"venue"
},
  "geometry": {"coordinates":[13.5658311844,52.4954833984],"type":"Point"}
}