{
  "type": "Feature",
  "properties": {
    "iso:country":"DE",
    "sg:address":"Am Schlifter 4",
    "sg:city":"Ro\u00dfleben",
    "sg:postcode":"06571",
    "sg:province":"Th\u00fcringen",
    "wof:name":"Bro Bau Gmbh",
    "wof:placetype":"venue"
},
  "geometry": {"coordinates":[11.4496297836,51.3054695129],"type":"Point"}
}