{
  "type": "Feature",
  "properties": {
    "iso:country":"DE",
    "sg:address":"Friedrich-Engels-Str. 5",
    "sg:city":"Kurort Oybin",
    "sg:phone":"+49 35844/70690",
    "sg:postcode":"02797",
    "sg:province":"Sachsen",
    "wof:name":"Klaus K\u00f6hler",
    "wof:placetype":"venue"
},
  "geometry": {"coordinates":[14.74655,50.84573],"type":"Point"}
}