{
  "type": "Feature",
  "properties": {
    "iso:country":"DE",
    "sg:address":"Schlo\u00dfstr. 24",
    "sg:city":"Schwarzenbach a Wald",
    "sg:phone":"+49 9289/1332",
    "sg:postcode":"95131",
    "sg:province":"Bayern",
    "wof:name":"Elisabeth Lippert",
    "wof:placetype":"venue"
},
  "geometry": {"coordinates":[11.6192493439,50.2823600769],"type":"Point"}
}