{
  "type": "Feature",
  "properties": {
    "iso:country":"DE",
    "sg:address":"Albert-Kuntz-Str. 8",
    "sg:city":"Wurzen",
    "sg:postcode":"04808",
    "sg:province":"Sachsen",
    "wof:name":"Aldi Gmbh & Co. Kg",
    "wof:placetype":"venue"
},
  "geometry": {"coordinates":[12.7352104187,51.3707084656],"type":"Point"}
}