{
  "type": "Feature",
  "properties": {
    "iso:country":"DE",
    "sg:address":"Laubacherstr. 38",
    "sg:city":"Berlin",
    "sg:phone":"+49 30/89748873",
    "sg:postcode":"14197",
    "sg:province":"Berlin",
    "wof:name":"First Class Umz\u00dcge",
    "wof:placetype":"venue"
},
  "geometry": {"coordinates":[13.3199796677,52.4740753174],"type":"Point"}
}