{
  "type": "Feature",
  "properties": {
    "iso:country":"DE",
    "sg:address":"Leobsch\u00fctzer Str 11e",
    "sg:city":"Bremerhaven",
    "sg:phone":"+49 471/801542",
    "sg:postcode":"27578",
    "sg:province":"Bremen",
    "wof:name":"Horst Eichholz F\u00f6rder- Und Lagertechnik F\u00fcr Langg\u00fcter & Bleche",
    "wof:placetype":"venue"
},
  "geometry": {"coordinates":[8.609133,53.573479],"type":"Point"}
}