{
  "type": "Feature",
  "properties": {
    "iso:country":"DE",
    "sg:address":"Burscheider Str. 536 a",
    "sg:city":"Leverkusen",
    "sg:phone":"+49 2171/31448",
    "sg:postcode":"51381",
    "sg:province":"Nordrhein-Westfalen",
    "wof:name":"Klaus Olbricht",
    "wof:placetype":"venue"
},
  "geometry": {"coordinates":[7.07165,51.091171],"type":"Point"}
}