{
  "type": "Feature",
  "properties": {
    "iso:country":"DE",
    "sg:address":"Sonnhalde 1",
    "sg:city":"Oberreute",
    "sg:phone":"+49 8387/464",
    "sg:postcode":"88179",
    "sg:province":"Bayern",
    "wof:name":"Siegbert Ochsenreiter Heilpraktiker",
    "wof:placetype":"venue"
},
  "geometry": {"coordinates":[9.9429836273,47.5617713928],"type":"Point"}
}