{
  "type": "Feature",
  "properties": {
    "iso:country":"DE",
    "sg:address":"Ochsenholz 27",
    "sg:city":"Mistelgau",
    "sg:phone":"+49 9279/1397",
    "sg:postcode":"95490",
    "sg:province":"Bayern",
    "wof:name":"Hacker Gmbh",
    "wof:placetype":"venue"
},
  "geometry": {"coordinates":[11.416063,49.905846],"type":"Point"}
}