{
  "type": "Feature",
  "properties": {
    "iso:country":"DE",
    "sg:address":"Goltenkamp 18",
    "sg:city":"Witten",
    "sg:phone":"+49 2302/54833",
    "sg:postcode":"58452",
    "sg:province":"Nordrhein-Westfalen",
    "wof:name":"Monika Borgert Heilpraktikerin",
    "wof:placetype":"venue"
},
  "geometry": {"coordinates":[7.3404312134,51.4216918945],"type":"Point"}
}