{
  "type": "Feature",
  "properties": {
    "iso:country":"DE",
    "sg:address":"Bauch\u00e4ckerstr. 1",
    "sg:city":"Wurmberg",
    "sg:phone":"+49 7044/48158",
    "sg:postcode":"75449",
    "sg:province":"Baden-W\u00fcrttemberg",
    "wof:name":"A. Elwinger",
    "wof:placetype":"venue"
},
  "geometry": {"coordinates":[8.81848526,48.8713874817],"type":"Point"}
}