{
  "type": "Feature",
  "properties": {
    "iso:country":"DE",
    "sg:address":"Schleusinger Str. 2",
    "sg:city":"Ilmenau",
    "sg:phone":"+49 3677/893371",
    "sg:postcode":"98693",
    "sg:province":"Th\u00fcringen",
    "wof:name":"Imbi\u00dfbetrieb B. K\u00fcmmerling",
    "wof:placetype":"venue"
},
  "geometry": {"coordinates":[10.90944767,50.6819496155],"type":"Point"}
}