{
  "type": "Feature",
  "properties": {
    "iso:country":"DE",
    "sg:address":"Goethering 4",
    "sg:city":"Bad Liebenstein",
    "sg:phone":"+49 36961/72784",
    "sg:postcode":"36448",
    "sg:province":"Th\u00fcringen",
    "wof:name":"Dr. Med. Helga Nitsch",
    "wof:placetype":"venue"
},
  "geometry": {"coordinates":[10.34835,50.812626],"type":"Point"}
}