{
  "type": "Feature",
  "properties": {
    "iso:country":"DE",
    "sg:address":"B\u00f6ckenhoffstr. 53",
    "sg:city":"Bottrop",
    "sg:phone":"+49 2041/20925",
    "sg:postcode":"46236",
    "sg:province":"Nordrhein-Westfalen",
    "wof:name":"Werner Albers",
    "wof:placetype":"venue"
},
  "geometry": {"coordinates":[6.9198980331,51.5227241516],"type":"Point"}
}