{
  "type": "Feature",
  "properties": {
    "iso:country":"DE",
    "sg:address":"Friedhofstr. 3",
    "sg:city":"Leutenbach",
    "sg:phone":"+49 7195/2084",
    "sg:postcode":"71397",
    "sg:province":"Baden-W\u00fcrttemberg",
    "wof:name":"Raiffeisenmarkt Weiler",
    "wof:placetype":"venue"
},
  "geometry": {"coordinates":[9.37423,48.902],"type":"Point"}
}