{
  "type": "Feature",
  "properties": {
    "iso:country":"DE",
    "sg:address":"Osterstr. 78",
    "sg:city":"Bremen",
    "sg:phone":"+49 421/533450",
    "sg:postcode":"28199",
    "sg:province":"Bremen",
    "wof:name":"Neust\u00e4dter Bierstuben",
    "wof:placetype":"venue"
},
  "geometry": {"coordinates":[8.8011541367,53.0692977905],"type":"Point"}
}