{
  "type": "Feature",
  "properties": {
    "iso:country":"DE",
    "sg:address":"Keplerstr. 4",
    "sg:city":"G\u00f6ttingen",
    "sg:phone":"+49 551/548080",
    "sg:postcode":"37085",
    "sg:province":"Niedersachsen",
    "wof:name":"Ursula Wolter Steuerberaterin",
    "wof:placetype":"venue"
},
  "geometry": {"coordinates":[9.9413414001,51.5291824341],"type":"Point"}
}