{
  "type": "Feature",
  "properties": {
    "iso:country":"DE",
    "sg:address":"Rotdornweg 29a",
    "sg:city":"Sankt Augustin",
    "sg:phone":"+49 2241/345564",
    "sg:postcode":"53757",
    "sg:province":"Nordrhein-Westfalen",
    "wof:name":"Blechwelt Gmbh",
    "wof:placetype":"venue"
},
  "geometry": {"coordinates":[7.203849,50.774998],"type":"Point"}
}