{
  "type": "Feature",
  "properties": {
    "iso:country":"DE",
    "sg:address":"Klosterallee 4",
    "sg:city":"St Oswald",
    "sg:postcode":"94568",
    "sg:province":"Bayern",
    "wof:name":"Tourist-service St. Oswald-riedlh\u00fctte Gmbh",
    "wof:placetype":"venue"
},
  "geometry": {"coordinates":[13.42768,48.891453],"type":"Point"}
}