{
  "type": "Feature",
  "properties": {
    "iso:country":"DE",
    "sg:address":"Schlutuper Str. 3-5",
    "sg:city":"L\u00fcbeck",
    "sg:phone":"+49 451/63337",
    "sg:postcode":"23566",
    "sg:province":"Schleswig-Holstein",
    "wof:name":"Reiseb\u00fcro Am Kaufhof Karin Olbers",
    "wof:placetype":"venue"
},
  "geometry": {"coordinates":[10.7197380066,53.8645019531],"type":"Point"}
}