{
  "type": "Feature",
  "properties": {
    "iso:country":"DE",
    "sg:address":"Gomaringer Str. 7",
    "sg:city":"Stuttgart",
    "sg:phone":"+49 711/767700",
    "sg:postcode":"70597",
    "sg:province":"Baden-W\u00fcrttemberg",
    "wof:name":"P. Jestland",
    "wof:placetype":"venue"
},
  "geometry": {"coordinates":[9.168387413,48.7436790466],"type":"Point"}
}