{
  "type": "Feature",
  "properties": {
    "iso:country":"DE",
    "sg:address":"M\u00fcnderstr. 8",
    "sg:city":"Hameln",
    "sg:phone":"+49 5151/59420",
    "sg:postcode":"31789",
    "sg:province":"Niedersachsen",
    "wof:name":"M. Bodem",
    "wof:placetype":"venue"
},
  "geometry": {"coordinates":[9.4346828461,52.1274223328],"type":"Point"}
}