{
  "type": "Feature",
  "properties": {
    "iso:country":"DE",
    "sg:address":"Bandhausstr. 6",
    "sg:city":"Brackenheim",
    "sg:phone":"+49 7135/8467",
    "sg:postcode":"74336",
    "sg:province":"Baden-W\u00fcrttemberg",
    "wof:name":"Ralf Binder",
    "wof:placetype":"venue"
},
  "geometry": {"coordinates":[9.0668649673,49.0770721436],"type":"Point"}
}