{
  "type": "Feature",
  "properties": {
    "iso:country":"DE",
    "sg:address":"Waldschlo\u00dfstr. 55",
    "sg:city":"Frammersbach",
    "sg:phone":"+49 9355/649",
    "sg:postcode":"97833",
    "sg:province":"Bayern",
    "wof:name":"Fem Fernmelde-elektro- Montage Gmbh",
    "wof:placetype":"venue"
},
  "geometry": {"coordinates":[9.4629068375,50.0734214783],"type":"Point"}
}