{
  "type": "Feature",
  "properties": {
    "iso:country":"DE",
    "sg:address":"Breite Str. 19-20",
    "sg:city":"Luckenwalde",
    "sg:phone":"+49 3371/614138",
    "sg:postcode":"14943",
    "sg:province":"Brandenburg",
    "wof:name":"Park-apotheke",
    "wof:placetype":"venue"
},
  "geometry": {"coordinates":[13.17024,52.086666],"type":"Point"}
}