{
  "type": "Feature",
  "properties": {
    "iso:country":"DE",
    "sg:address":"Krausenstr. 7",
    "sg:city":"Wriezen",
    "sg:postcode":"16269",
    "sg:province":"Brandenburg",
    "wof:name":"Wbg Wohnungsbaugesellschaft Der Gemeinden Des Amtes",
    "wof:placetype":"venue"
},
  "geometry": {"coordinates":[14.1337814331,52.7192153931],"type":"Point"}
}