{
  "type": "Feature",
  "properties": {
    "iso:country":"DE",
    "sg:address":"In D\u00fcrrfeldslach 3",
    "sg:city":"Rehlingen-Siersburg",
    "sg:phone":"+49 6835/92020",
    "sg:postcode":"66780",
    "sg:province":"Saarland",
    "wof:name":"Zita Becker Edv-service Und Handel Gmbh",
    "wof:placetype":"venue"
},
  "geometry": {"coordinates":[6.6861991882,49.3718338013],"type":"Point"}
}