{
  "type": "Feature",
  "properties": {
    "iso:country":"DE",
    "sg:city":"Gro\u00dfwig",
    "sg:postcode":"04860",
    "sg:province":"Sachsen",
    "wof:name":"Gemeindeschwesterstation",
    "wof:placetype":"venue"
},
  "geometry": {"coordinates":[12.888413,51.561951],"type":"Point"}
}