{
  "type": "Feature",
  "properties": {
    "iso:country":"DE",
    "sg:address":"Industrieweg 13",
    "sg:city":"Sendenhorst",
    "sg:phone":"+49 2526/3090",
    "sg:postcode":"48324",
    "sg:province":"Nordrhein-Westfalen",
    "wof:name":"Werner Bisplinghoff Immobilienberwaltungs Gmbh",
    "wof:placetype":"venue"
},
  "geometry": {"coordinates":[7.8427929878,51.8391571045],"type":"Point"}
}