{
  "type": "Feature",
  "properties": {
    "iso:country":"DE",
    "sg:address":"Kornwestheimer Str. 18",
    "sg:city":"Remseck",
    "sg:phone":"+49 7146/90399",
    "sg:postcode":"71686",
    "sg:province":"Baden-W\u00fcrttemberg",
    "wof:name":"Maria W\u00f6hrnschimmel",
    "wof:placetype":"venue"
},
  "geometry": {"coordinates":[9.252229,48.864902],"type":"Point"}
}