{
  "type": "Feature",
  "properties": {
    "iso:country":"DE",
    "sg:address":"Unter den Eichen 7",
    "sg:city":"Wiesbaden",
    "sg:phone":"+49 611",
    "sg:postcode":"65195",
    "sg:province":"Hessen",
    "wof:name":"Vft Film & Tv Production",
    "wof:placetype":"venue"
},
  "geometry": {"coordinates":[8.217419,50.094936],"type":"Point"}
}