{
  "type": "Feature",
  "properties": {
    "iso:country":"DE",
    "sg:address":"Westfleth 33",
    "sg:city":"Buxtehude",
    "sg:phone":"+49 4161/2519",
    "sg:postcode":"21614",
    "sg:province":"Niedersachsen",
    "wof:name":"Klaus Bitter",
    "wof:placetype":"venue"
},
  "geometry": {"coordinates":[9.6987524033,53.477268219],"type":"Point"}
}