{
  "type": "Feature",
  "properties": {
    "iso:country":"DE",
    "sg:address":"Theresienh\u00f6he 6",
    "sg:city":"M\u00fcnchen",
    "sg:phone":"+49 89/5024165",
    "sg:postcode":"80339",
    "sg:province":"Bayern",
    "wof:name":"Galerie Pritschow",
    "wof:placetype":"venue"
},
  "geometry": {"coordinates":[11.548242,48.13636],"type":"Point"}
}