{
  "type": "Feature",
  "properties": {
    "iso:country":"DE",
    "sg:address":"Papenstr. 10",
    "sg:city":"Emsb\u00fcren",
    "sg:phone":"+49 5903/7243",
    "sg:postcode":"48488",
    "sg:province":"Niedersachsen",
    "wof:name":"G\u00fcnter Kiewit Architekt",
    "wof:placetype":"venue"
},
  "geometry": {"coordinates":[7.29091,52.391548],"type":"Point"}
}