{
  "type": "Feature",
  "properties": {
    "iso:country":"DE",
    "sg:address":"Kleinmarschierstr. 1",
    "sg:city":"Aachen",
    "sg:phone":"+49 241/27752",
    "sg:postcode":"52062",
    "sg:province":"Nordrhein-Westfalen",
    "wof:name":"Margret Vanforsch",
    "wof:placetype":"venue"
},
  "geometry": {"coordinates":[6.083758,50.774124],"type":"Point"}
}