{
  "type": "Feature",
  "properties": {
    "iso:country":"DE",
    "sg:address":"Scheppe Gewissegasse 28",
    "sg:city":"Marburg",
    "sg:phone":"+49 6421/92770",
    "sg:postcode":"35039",
    "sg:province":"Hessen",
    "wof:name":"Inter Active Systems Gesellschaft F\u00fcr Interaktive",
    "wof:placetype":"venue"
},
  "geometry": {"coordinates":[8.7828264236,50.8031005859],"type":"Point"}
}