{
  "type": "Feature",
  "properties": {
    "iso:country":"DE",
    "sg:address":"Feldstr. 77",
    "sg:city":"D\u00fcsseldorf",
    "sg:phone":"+49 211/4921431",
    "sg:postcode":"40479",
    "sg:province":"Nordrhein-Westfalen",
    "wof:name":"Stahlelek Gmbh Stahl Im- Und Export",
    "wof:placetype":"venue"
},
  "geometry": {"coordinates":[6.783361,51.231075],"type":"Point"}
}