{
  "type": "Feature",
  "properties": {
    "iso:country":"DE",
    "sg:address":"Hatzper Str. 125",
    "sg:city":"Essen",
    "sg:phone":"+49 201/871020",
    "sg:postcode":"45149",
    "sg:province":"Nordrhein-Westfalen",
    "wof:name":"Wbt Industrie-elektro- Mechanische Produkte Gmbh",
    "wof:placetype":"venue"
},
  "geometry": {"coordinates":[6.966588,51.417637],"type":"Point"}
}