{
  "type": "Feature",
  "properties": {
    "iso:country":"DE",
    "sg:address":"Kehlsteinstr. 2",
    "sg:city":"Burgkirchen",
    "sg:phone":"+49 8679/6222",
    "sg:postcode":"84508",
    "sg:province":"Bayern",
    "wof:name":"Rudolf Zeiler Praxis F\u00fcr Physiotherapie",
    "wof:placetype":"venue"
},
  "geometry": {"coordinates":[12.730774,48.158657],"type":"Point"}
}