{
  "type": "Feature",
  "properties": {
    "iso:country":"DE",
    "sg:address":"Hugenottenallee 173",
    "sg:city":"Neu-Isenburg",
    "sg:phone":"+49 6102/180",
    "sg:postcode":"63263",
    "sg:province":"Hessen",
    "wof:name":"Du Pont De Nemours Deutschland Gmbh",
    "wof:placetype":"venue"
},
  "geometry": {"coordinates":[8.691154,50.044006],"type":"Point"}
}