{
  "type": "Feature",
  "properties": {
    "iso:country":"DE",
    "sg:address":"Rheinallee 7",
    "sg:city":"Mainz",
    "sg:phone":"+49 6131/960240",
    "sg:postcode":"55118",
    "sg:province":"Rheinland-Pfalz",
    "wof:name":"Elfering",
    "wof:placetype":"venue"
},
  "geometry": {"coordinates":[8.267951,50.009247],"type":"Point"}
}