{
  "type": "Feature",
  "properties": {
    "iso:country":"DE",
    "sg:address":"Sandweg 21",
    "sg:city":"Basdorf",
    "sg:phone":"+49 33397/22197",
    "sg:postcode":"16352",
    "sg:province":"Brandenburg",
    "wof:name":"Metallbau Peter Liebehenschel",
    "wof:placetype":"venue"
},
  "geometry": {"coordinates":[13.43783,52.715099],"type":"Point"}
}