{
  "type": "Feature",
  "properties": {
    "iso:country":"DE",
    "sg:address":"M\u00fchlenstr. 13",
    "sg:city":"Losheim",
    "sg:phone":"+49 6872/2204",
    "sg:postcode":"66679",
    "sg:province":"Saarland",
    "wof:name":"Conrad",
    "wof:placetype":"venue"
},
  "geometry": {"coordinates":[6.745823,49.511841],"type":"Point"}
}