{
  "type": "Feature",
  "properties": {
    "iso:country":"DE",
    "sg:address":"Josef-H\u00f6rl-Str. 14",
    "sg:city":"Fahrenzhausen",
    "sg:phone":"+49 8133/92996",
    "sg:postcode":"85777",
    "sg:province":"Bayern",
    "wof:name":"Gertraud Adam-braun Steuerberaterin",
    "wof:placetype":"venue"
},
  "geometry": {"coordinates":[11.5709552765,48.3408508301],"type":"Point"}
}