{
  "type": "Feature",
  "properties": {
    "iso:country":"DE",
    "sg:address":"Am Br\u00f6mderhof 13",
    "sg:city":"Wesel",
    "sg:postcode":"46485",
    "sg:province":"Nordrhein-Westfalen",
    "wof:name":"Ilse Bross Vertriebsges. F\u00fcr Med.pflegebedarf Gmbh",
    "wof:placetype":"venue"
},
  "geometry": {"coordinates":[6.6423921585,51.6736717224],"type":"Point"}
}