{
  "type": "Feature",
  "properties": {
    "iso:country":"DE",
    "sg:address":"Freiwaldauer Str. 2",
    "sg:city":"Schwalmstadt",
    "sg:phone":"+49 6691/4157",
    "sg:postcode":"34613",
    "sg:province":"Hessen",
    "wof:name":"Sch\u00f6nw\u00e4lder Immobilienmakler",
    "wof:placetype":"venue"
},
  "geometry": {"coordinates":[9.1860618591,50.9128417969],"type":"Point"}
}