{
  "type": "Feature",
  "properties": {
    "iso:country":"DE",
    "sg:address":"Chemnitzer Str. 14",
    "sg:city":"Albstadt",
    "sg:phone":"+49 7431/72970",
    "sg:postcode":"72458",
    "sg:province":"Baden-W\u00fcrttemberg",
    "wof:name":"Willy Zeller",
    "wof:placetype":"venue"
},
  "geometry": {"coordinates":[8.994414,48.208473],"type":"Point"}
}