{
  "type": "Feature",
  "properties": {
    "iso:country":"DE",
    "sg:address":"Altenhainer Dorfstr. 4",
    "sg:city":"Chemnitz",
    "sg:postcode":"09128",
    "sg:province":"Sachsen",
    "wof:name":"Ivs-immobilien Verwaltungs Und Sanierungs Gmbh",
    "wof:placetype":"venue"
},
  "geometry": {"coordinates":[13.020125,50.791744],"type":"Point"}
}