{
  "type": "Feature",
  "properties": {
    "iso:country":"DE",
    "sg:address":"Meringer Str. 47",
    "sg:city":"Friedberg",
    "sg:phone":"+49 821/663898",
    "sg:postcode":"86316",
    "sg:province":"Bayern",
    "wof:name":"Heinrich Rammelm\u00fcller",
    "wof:placetype":"venue"
},
  "geometry": {"coordinates":[10.9537630081,48.3484458923],"type":"Point"}
}