{
  "type": "Feature",
  "properties": {
    "iso:country":"DE",
    "sg:address":"B\u00f6hlitz 4a",
    "sg:city":"Mutzschen",
    "sg:phone":"+49 34385/52322",
    "sg:postcode":"04688",
    "sg:province":"Sachsen",
    "wof:name":"H.-p. Langhammer",
    "wof:placetype":"venue"
},
  "geometry": {"coordinates":[12.882257,51.259426],"type":"Point"}
}