{
  "type": "Feature",
  "properties": {
    "iso:country":"DE",
    "sg:address":"Henriettenstr. 45",
    "sg:city":"Chemnitz",
    "sg:phone":"+49 371/301423",
    "sg:postcode":"09112",
    "sg:province":"Sachsen",
    "wof:name":"Reiseb\u00fcro Gaudig Gmbh",
    "wof:placetype":"venue"
},
  "geometry": {"coordinates":[12.8993616104,50.8352279663],"type":"Point"}
}