{
  "type": "Feature",
  "properties": {
    "iso:country":"DE",
    "sg:address":"Sonderdorf 16",
    "sg:city":"Bolsterlang",
    "sg:phone":"+49 8326/402",
    "sg:postcode":"87538",
    "sg:province":"Bayern",
    "wof:name":"Hermann Luitz",
    "wof:placetype":"venue"
},
  "geometry": {"coordinates":[10.233184,47.454128],"type":"Point"}
}