{
  "type": "Feature",
  "properties": {
    "iso:country":"DE",
    "sg:address":"Graf-Recke-Str. 46",
    "sg:city":"D\u00fcsseldorf",
    "sg:phone":"+49 211/664319",
    "sg:postcode":"40239",
    "sg:province":"Nordrhein-Westfalen",
    "wof:name":"Hans Stevens Steuerberater",
    "wof:placetype":"venue"
},
  "geometry": {"coordinates":[6.8072810173,51.2404403687],"type":"Point"}
}