{
  "type": "Feature",
  "properties": {
    "iso:country":"DE",
    "sg:address":"Friedrich-Hofmann-Str. 8",
    "sg:city":"Ilmenau",
    "sg:phone":"+49 3677/202589",
    "sg:postcode":"98693",
    "sg:province":"Th\u00fcringen",
    "wof:name":"Wolfgang Hallauer",
    "wof:placetype":"venue"
},
  "geometry": {"coordinates":[10.915883,50.684937],"type":"Point"}
}