{
  "type": "Feature",
  "properties": {
    "iso:country":"DE",
    "sg:address":"An den Feldern 61",
    "sg:city":"Wuppertal",
    "sg:phone":"+49 202/462260",
    "sg:postcode":"42369",
    "sg:province":"Nordrhein-Westfalen",
    "wof:name":"Siegfried Hager",
    "wof:placetype":"venue"
},
  "geometry": {"coordinates":[7.2297968864,51.2262954712],"type":"Point"}
}