{
  "type": "Feature",
  "properties": {
    "iso:country":"DE",
    "sg:address":"Schwabenring 55",
    "sg:city":"Minden",
    "sg:phone":"+49 571/53228",
    "sg:postcode":"32427",
    "sg:province":"Nordrhein-Westfalen",
    "wof:name":"Ev. Pfarramt St. Thomas Kirche",
    "wof:placetype":"venue"
},
  "geometry": {"coordinates":[8.8878498077,52.2781791687],"type":"Point"}
}