{
  "type": "Feature",
  "properties": {
    "iso:country":"DE",
    "sg:address":"St.-Anno-H\u00f6he 4",
    "sg:city":"Overath",
    "sg:phone":"+49 2206/3400",
    "sg:postcode":"51491",
    "sg:province":"Nordrhein-Westfalen",
    "wof:name":"Dr. Alexander Kiss Tierarzt",
    "wof:placetype":"venue"
},
  "geometry": {"coordinates":[7.2780218124,50.9325637817],"type":"Point"}
}