{
  "type": "Feature",
  "properties": {
    "iso:country":"DE",
    "sg:address":"Graf-Bernadotte-Str. 39",
    "sg:city":"Bielefeld",
    "sg:phone":"+49 521/3368338",
    "sg:postcode":"33719",
    "sg:province":"Nordrhein-Westfalen",
    "wof:name":"Ms-bau Gmbh & Co. Kg",
    "wof:placetype":"venue"
},
  "geometry": {"coordinates":[8.5914258957,52.021987915],"type":"Point"}
}