{
  "type": "Feature",
  "properties": {
    "iso:country":"DE",
    "sg:address":"Am Weyersberg 13",
    "sg:city":"Mehren",
    "sg:postcode":"54552",
    "sg:province":"Rheinland-Pfalz",
    "wof:name":"Alex.computers Mehren",
    "wof:placetype":"venue"
},
  "geometry": {"coordinates":[6.887686,50.17944],"type":"Point"}
}