{
  "type": "Feature",
  "properties": {
    "iso:country":"DE",
    "sg:address":"H\u00fcttenweg 26",
    "sg:city":"Heiligenhaus",
    "sg:phone":"+49 2054/2080",
    "sg:postcode":"42579",
    "sg:province":"Nordrhein-Westfalen",
    "wof:name":"Willi Sowieja Gmbh",
    "wof:placetype":"venue"
},
  "geometry": {"coordinates":[6.9540410042,51.3452262878],"type":"Point"}
}