{
  "type": "Feature",
  "properties": {
    "iso:country":"DE",
    "sg:address":"Hauptstr. 28",
    "sg:city":"Zweibr\u00fccken",
    "sg:phone":"+49 6332/16564",
    "sg:postcode":"66482",
    "sg:province":"Rheinland-Pfalz",
    "wof:name":"Fr\u00fcchte-ecke Dehlem Gmbh",
    "wof:placetype":"venue"
},
  "geometry": {"coordinates":[7.3634982109,49.2480354309],"type":"Point"}
}