{
  "type": "Feature",
  "properties": {
    "iso:country":"DE",
    "sg:address":"Georgenschwaigstr. 38",
    "sg:city":"M\u00fcnchen",
    "sg:postcode":"80807",
    "sg:province":"Bayern",
    "wof:name":"Ugichem Gesellschaft F\u00fcr Organische Chemie Mbh",
    "wof:placetype":"venue"
},
  "geometry": {"coordinates":[11.572502,48.180691],"type":"Point"}
}