{
  "type": "Feature",
  "properties": {
    "iso:country":"DE",
    "sg:address":"St\u00f6rwiesen 11",
    "sg:city":"Neum\u00fcnster",
    "sg:phone":"+49 4321/84671",
    "sg:postcode":"24539",
    "sg:province":"Schleswig-Holstein",
    "wof:name":"Hermann Schnoor",
    "wof:placetype":"venue"
},
  "geometry": {"coordinates":[9.9809989929,54.0558700562],"type":"Point"}
}