{
  "type": "Feature",
  "properties": {
    "iso:country":"DE",
    "sg:address":"Warthestr. 49",
    "sg:city":"Berlin",
    "sg:phone":"+49 30/6266849",
    "sg:postcode":"12051",
    "sg:province":"Berlin",
    "wof:name":"Bengsch & Pahl Gmbh",
    "wof:placetype":"venue"
},
  "geometry": {"coordinates":[13.4233665466,52.4692344666],"type":"Point"}
}