{
  "type": "Feature",
  "properties": {
    "iso:country":"DE",
    "sg:address":"Zabitzer Str. 22",
    "sg:city":"Kleinpaschleben",
    "sg:phone":"+49 34979/21842",
    "sg:postcode":"06369",
    "sg:province":"Sachsen-Anhalt",
    "wof:name":"I. Hildebrand",
    "wof:placetype":"venue"
},
  "geometry": {"coordinates":[11.89032,51.784058],"type":"Point"}
}