{
  "type": "Feature",
  "properties": {
    "iso:country":"DE",
    "sg:address":"Castroper Str. 241",
    "sg:city":"Datteln",
    "sg:phone":"+49 2363/9740",
    "sg:postcode":"45711",
    "sg:province":"Nordrhein-Westfalen",
    "wof:name":"Bundesverband Der Berufs- Kraftfahrerschulen E. V.",
    "wof:placetype":"venue"
},
  "geometry": {"coordinates":[7.332426,51.635563],"type":"Point"}
}