{
  "type": "Feature",
  "properties": {
    "iso:country":"DE",
    "sg:address":"Rathausstr. 50",
    "sg:city":"Heidelberg",
    "sg:phone":"+49 6221/393289",
    "sg:postcode":"69126",
    "sg:province":"Baden-W\u00fcrttemberg",
    "wof:name":"Hans Christ",
    "wof:placetype":"venue"
},
  "geometry": {"coordinates":[8.6908416748,49.3791732788],"type":"Point"}
}