{
  "type": "Feature",
  "properties": {
    "iso:country":"DE",
    "sg:address":"Wollankstr. 28",
    "sg:city":"Berlin",
    "sg:phone":"+49 30/4939140",
    "sg:postcode":"13359",
    "sg:province":"Berlin",
    "wof:name":"Imbi\u00df Ly Vinh Cuong",
    "wof:placetype":"venue"
},
  "geometry": {"coordinates":[13.3916959763,52.5638389587],"type":"Point"}
}