{
  "type": "Feature",
  "properties": {
    "iso:country":"DE",
    "sg:address":"Galgweiser Str. 1 a",
    "sg:city":"Aldersbach",
    "sg:phone":"+49 8547/91006",
    "sg:postcode":"94501",
    "sg:province":"Bayern",
    "wof:name":"Max Huber",
    "wof:placetype":"venue"
},
  "geometry": {"coordinates":[13.030571,48.608093],"type":"Point"}
}