{
  "type": "Feature",
  "properties": {
    "iso:country":"DE",
    "sg:address":"Jagdsch\u00e4nkenstr. 31",
    "sg:city":"Chemnitz",
    "sg:postcode":"09117",
    "sg:province":"Sachsen",
    "wof:name":"Etv Fahrzeugvermietung Gmbh",
    "wof:placetype":"venue"
},
  "geometry": {"coordinates":[12.842698,50.80872],"type":"Point"}
}