{
  "type": "Feature",
  "properties": {
    "iso:country":"DE",
    "sg:address":"Leversum 85",
    "sg:city":"D\u00fclmen",
    "sg:phone":"+49 2594/5331",
    "sg:postcode":"48249",
    "sg:province":"Nordrhein-Westfalen",
    "wof:name":"Haus Borkenberge",
    "wof:placetype":"venue"
},
  "geometry": {"coordinates":[7.2757029533,51.7813949585],"type":"Point"}
}