{
  "type": "Feature",
  "properties": {
    "iso:country":"DE",
    "sg:address":"W\u00f6rthstr. 4",
    "sg:city":"Uhingen",
    "sg:phone":"+49 7161/39067",
    "sg:postcode":"73066",
    "sg:province":"Baden-W\u00fcrttemberg",
    "wof:name":"Willi S\u00e4ufferer",
    "wof:placetype":"venue"
},
  "geometry": {"coordinates":[9.5904788971,48.7040786743],"type":"Point"}
}