{
  "type": "Feature",
  "properties": {
    "iso:country":"DE",
    "sg:address":"Lessingstr. 8",
    "sg:city":"Heidenau",
    "sg:phone":"+49 3529/590010",
    "sg:postcode":"01809",
    "sg:province":"Sachsen",
    "wof:name":"Bestattungshaus W. Billing Gmbh",
    "wof:placetype":"venue"
},
  "geometry": {"coordinates":[13.86861,50.968983],"type":"Point"}
}