{
  "type": "Feature",
  "properties": {
    "iso:country":"DE",
    "sg:address":"Beckhauser Strasse 20",
    "sg:city":"Erkrath",
    "sg:phone":"+49 2104/448050",
    "sg:postcode":"40699",
    "sg:province":"Nordrhein-Westfalen",
    "wof:name":"World Of Dessous And Erotics",
    "wof:placetype":"venue"
},
  "geometry": {"coordinates":[6.954859,51.206318],"type":"Point"}
}