{
  "type": "Feature",
  "properties": {
    "iso:country":"DE",
    "sg:address":"Alois-Steinecker-Str. 22",
    "sg:city":"Freising",
    "sg:phone":"+49 8161/6080",
    "sg:postcode":"85354",
    "sg:province":"Bayern",
    "wof:name":"Kuhnen & Wacker Patentanwaltsgesellschaft Mbh",
    "wof:placetype":"venue"
},
  "geometry": {"coordinates":[11.7409572601,48.4034004211],"type":"Point"}
}