{
  "type": "Feature",
  "properties": {
    "iso:country":"DE",
    "sg:address":"Barbyer Str. 7 a",
    "sg:city":"Sch\u00f6nebeck",
    "sg:postcode":"39218",
    "sg:province":"Sachsen-Anhalt",
    "wof:name":"Aldi Gmbh & Co. Kg",
    "wof:placetype":"venue"
},
  "geometry": {"coordinates":[11.747797966,52.0182991028],"type":"Point"}
}