{
  "type": "Feature",
  "properties": {
    "iso:country":"DE",
    "sg:address":"Gewerbepark",
    "sg:city":"Oberviechtach",
    "sg:phone":"+49 9671/1656",
    "sg:postcode":"92526",
    "sg:province":"Bayern",
    "wof:name":"W. Bauer",
    "wof:placetype":"venue"
},
  "geometry": {"coordinates":[12.407042,49.460526],"type":"Point"}
}