{
  "type": "Feature",
  "properties": {
    "iso:country":"DE",
    "sg:address":"Altweg 5",
    "sg:city":"Eichstetten",
    "sg:phone":"+49 4976/631323",
    "sg:postcode":"79356",
    "sg:province":"Baden-W\u00fcrttemberg",
    "wof:name":"Sparkasse N\u00f6rdlicher Breisgau",
    "wof:placetype":"venue"
},
  "geometry": {"coordinates":[7.744287,48.093487],"type":"Point"}
}