{
  "type": "Feature",
  "properties": {
    "iso:country":"DE",
    "sg:address":"Am See",
    "sg:city":"Neukloster",
    "sg:phone":"+49 38429/305",
    "sg:postcode":"23992",
    "sg:province":"Mecklenburg-Vorpommern",
    "wof:name":"Horst Kempka S\u00e4gewerk-holzhandel",
    "wof:placetype":"venue"
},
  "geometry": {"coordinates":[11.7049751282,53.8595085144],"type":"Point"}
}