{
  "type": "Feature",
  "properties": {
    "iso:country":"DE",
    "sg:address":"Hauptstr. 7",
    "sg:city":"Rieneck",
    "sg:phone":"+49 9354/759",
    "sg:postcode":"97794",
    "sg:province":"Bayern",
    "wof:name":"H. Krutsch",
    "wof:placetype":"venue"
},
  "geometry": {"coordinates":[9.648393631,50.0932617188],"type":"Point"}
}