{
  "type": "Feature",
  "properties": {
    "iso:country":"DE",
    "sg:address":"Potsdamer Str. 10",
    "sg:city":"Aerzen",
    "sg:phone":"+49 5154/2447",
    "sg:postcode":"31855",
    "sg:province":"Niedersachsen",
    "wof:name":"Z\u00f6rner Gmbh Malerbetrieb L\u00f6nnecker-specka",
    "wof:placetype":"venue"
},
  "geometry": {"coordinates":[9.272599,52.066898],"type":"Point"}
}