{
  "type": "Feature",
  "properties": {
    "iso:country":"DE",
    "sg:address":"Dam 1a",
    "sg:city":"Straelen",
    "sg:phone":"+49 2834/984406",
    "sg:postcode":"47638",
    "sg:province":"Nordrhein-Westfalen",
    "wof:name":"E.-p. Brinkmann",
    "wof:placetype":"venue"
},
  "geometry": {"coordinates":[6.24132,51.41185],"type":"Point"}
}