{
  "type": "Feature",
  "properties": {
    "iso:country":"DE",
    "sg:address":"Berliner Str.41",
    "sg:city":"Berlin-Tegel",
    "sg:phone":"+49 30/4322042",
    "sg:postcode":"13507",
    "sg:province":"Berlin",
    "wof:name":"Zahnarztpraxis Michael Regen",
    "wof:placetype":"venue"
},
  "geometry": {"coordinates":[13.28903,52.554798],"type":"Point"}
}