{
  "type": "Feature",
  "properties": {
    "iso:country":"DE",
    "sg:address":"Viernauer Weg 24",
    "sg:city":"Springstille",
    "sg:phone":"+49 36847/38080",
    "sg:postcode":"98587",
    "sg:province":"Th\u00fcringen",
    "wof:name":"Schneider Metallwaren Gmbh",
    "wof:placetype":"venue"
},
  "geometry": {"coordinates":[10.526572,50.682896],"type":"Point"}
}