{
  "type": "Feature",
  "properties": {
    "iso:country":"DE",
    "sg:address":"Zaunk\u00f6nigweg 41",
    "sg:city":"D\u00fcsseldorf",
    "sg:phone":"+49 211/636791",
    "sg:postcode":"40470",
    "sg:province":"Nordrhein-Westfalen",
    "wof:name":"Karl-heinz Sieber",
    "wof:placetype":"venue"
},
  "geometry": {"coordinates":[6.796813,51.262115],"type":"Point"}
}