{
  "type": "Feature",
  "properties": {
    "iso:country":"DE",
    "sg:address":"Gottorfer Damm",
    "sg:city":"Schleswig",
    "sg:postcode":"24837",
    "sg:province":"Schleswig-Holstein",
    "wof:name":"Tanken Und Auto Service Gmbh",
    "wof:placetype":"venue"
},
  "geometry": {"coordinates":[9.5428800583,54.5096664429],"type":"Point"}
}