{
  "type": "Feature",
  "properties": {
    "iso:country":"DE",
    "sg:address":"Haldesdorfer Str. 72",
    "sg:city":"Hamburg",
    "sg:phone":"+49 40/6420490",
    "sg:postcode":"22179",
    "sg:province":"Hamburg",
    "wof:name":"Afos-ger\u00e4te-herstellungs- Und Vertriebs Gmbh",
    "wof:placetype":"venue"
},
  "geometry": {"coordinates":[10.0758171082,53.5986328125],"type":"Point"}
}