{
  "type": "Feature",
  "properties": {
    "iso:country":"DE",
    "sg:address":"Neustadt 9",
    "sg:city":"G\u00f6ttingen",
    "sg:phone":"+49 551/5313450",
    "sg:postcode":"37073",
    "sg:province":"Niedersachsen",
    "wof:name":"Computer-service-center E. K.",
    "wof:placetype":"venue"
},
  "geometry": {"coordinates":[9.9299983978,51.5339241028],"type":"Point"}
}