{
  "type": "Feature",
  "properties": {
    "iso:country":"DE",
    "sg:address":"Walther-Rathenau-Str. 39",
    "sg:city":"Zwickau",
    "sg:phone":"+49 375/212998",
    "sg:postcode":"08058",
    "sg:province":"Sachsen",
    "wof:name":"Heinz Kempe",
    "wof:placetype":"venue"
},
  "geometry": {"coordinates":[12.485537,50.731358],"type":"Point"}
}