{
  "type": "Feature",
  "properties": {
    "iso:country":"DE",
    "sg:city":"Fuchstal",
    "sg:postcode":"86925",
    "sg:province":"Bayern",
    "wof:name":"Genossenschaftliche Elektrizit\u00e4tswerke Eg",
    "wof:placetype":"venue"
},
  "geometry": {"coordinates":[10.832652,47.94849],"type":"Point"}
}