{
  "type": "Feature",
  "properties": {
    "iso:country":"DE",
    "sg:address":"K\u00f6nigstr 24-28",
    "sg:city":"Marne",
    "sg:phone":"+49 4851/9000",
    "sg:postcode":"25709",
    "sg:province":"Schleswig-Holstein",
    "wof:name":"Lutzkat & Sohn",
    "wof:placetype":"venue"
},
  "geometry": {"coordinates":[9.008877,53.953815],"type":"Point"}
}