{
  "type": "Feature",
  "properties": {
    "iso:country":"DE",
    "sg:address":"Hattenhofer Str. 1",
    "sg:city":"Holzmaden",
    "sg:phone":"+49 7023/909271",
    "sg:postcode":"73271",
    "sg:province":"Baden-W\u00fcrttemberg",
    "wof:name":"Manfred Stark",
    "wof:placetype":"venue"
},
  "geometry": {"coordinates":[9.5314064026,48.6376724243],"type":"Point"}
}