{
  "type": "Feature",
  "properties": {
    "iso:country":"DE",
    "sg:address":"Auweg 6",
    "sg:city":"Dillenburg",
    "sg:phone":"+49 2771/34500",
    "sg:postcode":"35683",
    "sg:province":"Hessen",
    "wof:name":"Friederike Miller Masseurin",
    "wof:placetype":"venue"
},
  "geometry": {"coordinates":[8.283247,50.742188],"type":"Point"}
}