{
  "type": "Feature",
  "properties": {
    "iso:country":"DE",
    "sg:address":"Bauernreihe 6",
    "sg:city":"Worpswede",
    "sg:phone":"+49 4792/93110",
    "sg:postcode":"27726",
    "sg:province":"Niedersachsen",
    "wof:name":"Max Ag",
    "wof:placetype":"venue"
},
  "geometry": {"coordinates":[8.9199180603,53.222492218],"type":"Point"}
}