{
  "type": "Feature",
  "properties": {
    "iso:country":"DE",
    "sg:address":"Hornh\u00e4user Str. 6",
    "sg:city":"Oschersleben",
    "sg:postcode":"39387",
    "sg:province":"Sachsen-Anhalt",
    "wof:name":"Dienstleistungscenter Presse B\u00f6rdekreis Gmbh",
    "wof:placetype":"venue"
},
  "geometry": {"coordinates":[11.2256746292,52.0267448425],"type":"Point"}
}