{
  "type": "Feature",
  "properties": {
    "iso:country":"DE",
    "sg:address":"Dammstr. 20",
    "sg:city":"Burgwedel",
    "sg:phone":"+49 5139/2430",
    "sg:postcode":"30938",
    "sg:province":"Niedersachsen",
    "wof:name":"Prof.dr. H. Behrens Tierarzt",
    "wof:placetype":"venue"
},
  "geometry": {"coordinates":[9.8492803574,52.4936256409],"type":"Point"}
}