{
  "type": "Feature",
  "properties": {
    "iso:country":"DE",
    "sg:address":"Jahnstr. 1a",
    "sg:city":"Garz",
    "sg:postcode":"18574",
    "sg:province":"Mecklenburg-Vorpommern",
    "wof:name":"Katholisches Pfarramt Garz",
    "wof:placetype":"venue"
},
  "geometry": {"coordinates":[13.2749252319,54.2978363037],"type":"Point"}
}