{
  "type": "Feature",
  "properties": {
    "iso:country":"DE",
    "sg:address":"Kirchstr. 8",
    "sg:city":"Jesenwang",
    "sg:phone":"+49 8146/92030",
    "sg:postcode":"82287",
    "sg:province":"Bayern",
    "wof:name":"Hotel Garni St. Blasius",
    "wof:placetype":"venue"
},
  "geometry": {"coordinates":[11.1318883896,48.1693916321],"type":"Point"}
}