{
  "type": "Feature",
  "properties": {
    "iso:country":"DE",
    "sg:address":"Tegernseer Str. 15",
    "sg:city":"Holzkirchen",
    "sg:phone":"+49 8024/7331",
    "sg:postcode":"83607",
    "sg:province":"Bayern",
    "wof:name":"Redaktion Elcomp Verlag Hofacker",
    "wof:placetype":"venue"
},
  "geometry": {"coordinates":[11.7044401169,47.8758087158],"type":"Point"}
}