{
  "type": "Feature",
  "properties": {
    "iso:country":"DE",
    "sg:address":"Bergedorfer Str. 46",
    "sg:city":"Geesthacht",
    "sg:phone":"+49 4152/3372",
    "sg:postcode":"21502",
    "sg:province":"Schleswig-Holstein",
    "wof:name":"Olaf Fries Kg",
    "wof:placetype":"venue"
},
  "geometry": {"coordinates":[10.3706884384,53.4347877502],"type":"Point"}
}