{
  "type": "Feature",
  "properties": {
    "iso:country":"DE",
    "sg:address":"Puschkinpromenade 22",
    "sg:city":"Zerbst",
    "sg:phone":"+49 3923/73760",
    "sg:postcode":"39261",
    "sg:province":"Sachsen-Anhalt",
    "wof:name":"Gebhardt Und Gebhardt Ingenieur",
    "wof:placetype":"venue"
},
  "geometry": {"coordinates":[12.0900249481,51.963218689],"type":"Point"}
}