{
  "type": "Feature",
  "properties": {
    "iso:country":"DE",
    "sg:address":"Walther-Rathenau-Str. 7",
    "sg:city":"K\u00f6nnern",
    "sg:phone":"+49 34691/20214",
    "sg:postcode":"06420",
    "sg:province":"Sachsen-Anhalt",
    "wof:name":"Margot Edner",
    "wof:placetype":"venue"
},
  "geometry": {"coordinates":[11.771622,51.672379],"type":"Point"}
}