{
  "type": "Feature",
  "properties": {
    "iso:country":"DE",
    "sg:address":"Schmalkalder Str. 13",
    "sg:city":"Christes",
    "sg:phone":"+49 36844/46194",
    "sg:postcode":"98547",
    "sg:province":"Th\u00fcringen",
    "wof:name":"D\u00f6ll",
    "wof:placetype":"venue"
},
  "geometry": {"coordinates":[10.4785614014,50.6614761353],"type":"Point"}
}