{
  "type": "Feature",
  "properties": {
    "iso:country":"DE",
    "sg:address":"Marktstr. 3",
    "sg:city":"Ebersbach",
    "sg:phone":"+49 3586/764676",
    "sg:postcode":"02730",
    "sg:province":"Sachsen",
    "wof:name":"G\u00fcnter Horn",
    "wof:placetype":"venue"
},
  "geometry": {"coordinates":[14.578404,51.006462],"type":"Point"}
}