{
  "type": "Feature",
  "properties": {
    "iso:country":"DE",
    "sg:address":"Friedrich-K\u00f6nig-Str. 11",
    "sg:city":"Suhl",
    "sg:phone":"+49 3681/305466",
    "sg:postcode":"98527",
    "sg:province":"Th\u00fcringen",
    "wof:name":"Hans Wedemeyer",
    "wof:placetype":"venue"
},
  "geometry": {"coordinates":[10.7046260834,50.6111526489],"type":"Point"}
}