{
  "type": "Feature",
  "properties": {
    "iso:country":"DE",
    "sg:address":"Rubensstr. 11",
    "sg:city":"Heddesheim",
    "sg:phone":"+49 6203/44161",
    "sg:postcode":"68542",
    "sg:province":"Baden-W\u00fcrttemberg",
    "wof:name":"Axel Heckmann",
    "wof:placetype":"venue"
},
  "geometry": {"coordinates":[8.5965003967,49.503868103],"type":"Point"}
}