{
  "type": "Feature",
  "properties": {
    "iso:country":"DE",
    "sg:address":"Bahnhofstr. 26",
    "sg:city":"Rosdorf",
    "sg:phone":"+49 551/782758",
    "sg:postcode":"37124",
    "sg:province":"Niedersachsen",
    "wof:name":"Bachmann Und Dettlaff Architekten",
    "wof:placetype":"venue"
},
  "geometry": {"coordinates":[9.907407,51.500607],"type":"Point"}
}