{
  "type": "Feature",
  "properties": {
    "iso:country":"DE",
    "sg:address":"Ludwig-Uhland-Str. 2",
    "sg:city":"Ravensburg",
    "sg:postcode":"88214",
    "sg:province":"Baden-W\u00fcrttemberg",
    "wof:name":"Kulturhaus Heidenau Grundst\u00fccksges. Mbh & Co. Kg",
    "wof:placetype":"venue"
},
  "geometry": {"coordinates":[9.6090936661,47.7734336853],"type":"Point"}
}