{
  "type": "Feature",
  "properties": {
    "iso:country":"DE",
    "sg:address":"Niedere Hauptstr. 45",
    "sg:city":"Niedercunnersdorf",
    "sg:phone":"+49 35875/60229",
    "sg:postcode":"02708",
    "sg:province":"Sachsen",
    "wof:name":"U. Bitterlich",
    "wof:placetype":"venue"
},
  "geometry": {"coordinates":[14.658955574,51.0537109375],"type":"Point"}
}