{
  "type": "Feature",
  "properties": {
    "iso:country":"DE",
    "sg:address":"Reichenhaller Str. 54a",
    "sg:city":"Freilassing",
    "sg:phone":"+49 8654/9573",
    "sg:postcode":"83395",
    "sg:province":"Bayern",
    "wof:name":"Nikolaus Schm\u00f6lz",
    "wof:placetype":"venue"
},
  "geometry": {"coordinates":[12.976268,47.831364],"type":"Point"}
}