{
  "type": "Feature",
  "properties": {
    "iso:country":"DE",
    "sg:address":"Im Steinisl\u00e4ndle 4",
    "sg:city":"Engen",
    "sg:phone":"+49 7733/8284",
    "sg:postcode":"78234",
    "sg:province":"Baden-W\u00fcrttemberg",
    "wof:name":"L. Keller Gmbh",
    "wof:placetype":"venue"
},
  "geometry": {"coordinates":[8.764589,47.825962],"type":"Point"}
}