{
  "type": "Feature",
  "properties": {
    "iso:country":"DE",
    "sg:address":"Franseckystr. 2",
    "sg:city":"Eltville",
    "sg:phone":"+49 6123/62643",
    "sg:postcode":"65346",
    "sg:province":"Hessen",
    "wof:name":"Zur Traube",
    "wof:placetype":"venue"
},
  "geometry": {"coordinates":[8.0931406021,50.0212440491],"type":"Point"}
}