{
  "type": "Feature",
  "properties": {
    "iso:country":"DE",
    "sg:address":"Mainzer Str. 8",
    "sg:city":"Gro\u00df-Gerau",
    "sg:postcode":"64521",
    "sg:province":"Hessen",
    "wof:name":"Kaufhaus Heinrich S\u00fc\u00df Ohg",
    "wof:placetype":"venue"
},
  "geometry": {"coordinates":[8.480966,49.921185],"type":"Point"}
}