{
  "type": "Feature",
  "properties": {
    "iso:country":"DE",
    "sg:address":"Otto-Behaghel-Str. 10",
    "sg:city":"Gie\u00dfen",
    "sg:phone":"+49 641/70225",
    "sg:postcode":"35394",
    "sg:province":"Hessen",
    "wof:name":"Zentrum F. Philosophie Und Grundlagen Der Wissenschaft",
    "wof:placetype":"venue"
},
  "geometry": {"coordinates":[8.6932172775,50.5754776001],"type":"Point"}
}