{
  "type": "Feature",
  "properties": {
    "iso:country":"DE",
    "sg:address":"Bergstr. 11",
    "sg:city":"Hamburg",
    "sg:phone":"+49 40/320943",
    "sg:postcode":"20095",
    "sg:province":"Hamburg",
    "wof:name":"Hdi Lebensversicherung Ag",
    "wof:placetype":"venue"
},
  "geometry": {"coordinates":[9.995143,53.550926],"type":"Point"}
}