{
  "type": "Feature",
  "properties": {
    "iso:country":"DE",
    "sg:address":"Kettelerstr. 1",
    "sg:city":"Recke",
    "sg:phone":"+49 5453/80480",
    "sg:postcode":"49509",
    "sg:province":"Nordrhein-Westfalen",
    "wof:name":"Dorfgrill",
    "wof:placetype":"venue"
},
  "geometry": {"coordinates":[7.6478490829,52.3453941345],"type":"Point"}
}