{
  "type": "Feature",
  "properties": {
    "iso:country":"DE",
    "sg:address":"Kathekerstr. 22",
    "sg:city":"Schee\u00dfel",
    "sg:phone":"+49 4263/3997",
    "sg:postcode":"27383",
    "sg:province":"Niedersachsen",
    "wof:name":"Johann Dittmer",
    "wof:placetype":"venue"
},
  "geometry": {"coordinates":[9.561349,53.147686],"type":"Point"}
}