{
  "type": "Feature",
  "properties": {
    "iso:country":"DE",
    "sg:city":"Hochdorf-Assenheim",
    "sg:postcode":"67126",
    "sg:province":"Rheinland-Pfalz",
    "wof:name":"Tegra Gmbh",
    "wof:placetype":"venue"
},
  "geometry": {"coordinates":[8.279088,49.418179],"type":"Point"}
}