{
  "type": "Feature",
  "properties": {
    "iso:country":"DE",
    "sg:address":"Bahnhofstr. 10",
    "sg:city":"Unna",
    "sg:postcode":"59423",
    "sg:province":"Nordrhein-Westfalen",
    "wof:name":"Fleischerm. K. Sprenger E. K.",
    "wof:placetype":"venue"
},
  "geometry": {"coordinates":[7.6904191971,51.5355224609],"type":"Point"}
}