{
  "type": "Feature",
  "properties": {
    "iso:country":"DE",
    "sg:address":"Hegemalweg 27",
    "sg:city":"Erfurt",
    "sg:phone":"+49 361/735373",
    "sg:postcode":"99087",
    "sg:province":"Th\u00fcringen",
    "wof:name":"Britta Rosenbauer Anlageberater",
    "wof:placetype":"venue"
},
  "geometry": {"coordinates":[11.0284986496,51.0166130066],"type":"Point"}
}