{
  "type": "Feature",
  "properties": {
    "iso:country":"DE",
    "sg:address":"Pfannkuchstr. 4",
    "sg:city":"Karlsruhe",
    "sg:phone":"+49 4972/195290",
    "sg:postcode":"76185",
    "sg:province":"Baden-W\u00fcrttemberg",
    "wof:name":"Kommunale Informationsverarbeitung Baden-franken (zv)",
    "wof:placetype":"venue"
},
  "geometry": {"coordinates":[8.344556,49.007851],"type":"Point"}
}