{
  "type": "Feature",
  "properties": {
    "iso:country":"DE",
    "sg:address":"Am Rodebach 34",
    "sg:city":"Geilenkirchen",
    "sg:phone":"+49 2451/8686",
    "sg:postcode":"52511",
    "sg:province":"Nordrhein-Westfalen",
    "wof:name":"Johann Eigelshoven",
    "wof:placetype":"venue"
},
  "geometry": {"coordinates":[6.077375,50.969688],"type":"Point"}
}