{
  "type": "Feature",
  "properties": {
    "iso:country":"DE",
    "sg:address":"Auf der L\u00f6h 13",
    "sg:city":"Lohmar",
    "sg:phone":"+49 2246/913512",
    "sg:postcode":"53797",
    "sg:province":"Nordrhein-Westfalen",
    "wof:name":"A Und B",
    "wof:placetype":"venue"
},
  "geometry": {"coordinates":[7.276357,50.832611],"type":"Point"}
}