{
  "type": "Feature",
  "properties": {
    "iso:country":"DE",
    "sg:address":"Georgstr. 53",
    "sg:city":"Lingen",
    "sg:phone":"+49 591/91630",
    "sg:postcode":"49809",
    "sg:province":"Niedersachsen",
    "wof:name":"Vgh-service",
    "wof:placetype":"venue"
},
  "geometry": {"coordinates":[7.3355731964,52.5218353271],"type":"Point"}
}