{
  "type": "Feature",
  "properties": {
    "iso:country":"DE",
    "sg:address":"Melkerweg 10",
    "sg:city":"Cuxhaven",
    "sg:phone":"+49 4723/4212",
    "sg:postcode":"27478",
    "sg:province":"Niedersachsen",
    "wof:name":"Ewald Bursky",
    "wof:placetype":"venue"
},
  "geometry": {"coordinates":[8.667455,53.825729],"type":"Point"}
}