{
  "type": "Feature",
  "properties": {
    "iso:country":"DE",
    "sg:address":"H\u00fclsstr. 5",
    "sg:city":"Marl",
    "sg:phone":"+49 2365/45441",
    "sg:postcode":"45772",
    "sg:province":"Nordrhein-Westfalen",
    "wof:name":"Arkaden-apotheke Inh. I. Herbig",
    "wof:placetype":"venue"
},
  "geometry": {"coordinates":[7.130151,51.664658],"type":"Point"}
}