{
  "type": "Feature",
  "properties": {
    "iso:country":"DE",
    "sg:address":"Schillerstr. 10",
    "sg:city":"Stollberg",
    "sg:phone":"+49 37296/15131",
    "sg:postcode":"09366",
    "sg:province":"Sachsen",
    "wof:name":"K. Ulbricht",
    "wof:placetype":"venue"
},
  "geometry": {"coordinates":[12.778158,50.711178],"type":"Point"}
}