{
  "type": "Feature",
  "properties": {
    "iso:country":"DE",
    "sg:address":"D\u00e4tzinger Str. 1",
    "sg:city":"Aidlingen",
    "sg:phone":"+49 7034/63566",
    "sg:postcode":"71134",
    "sg:province":"Baden-W\u00fcrttemberg",
    "wof:name":"Martin Maly",
    "wof:placetype":"venue"
},
  "geometry": {"coordinates":[8.888052,48.700226],"type":"Point"}
}