{
  "type": "Feature",
  "properties": {
    "iso:country":"DE",
    "sg:address":"Steinheimer Str. 9",
    "sg:city":"Heidenheim",
    "sg:phone":"+49 7321/949502",
    "sg:postcode":"89518",
    "sg:province":"Baden-W\u00fcrttemberg",
    "wof:name":"K. Scheel & Irene Vollmer",
    "wof:placetype":"venue"
},
  "geometry": {"coordinates":[10.1243200302,48.6792755127],"type":"Point"}
}