{
  "type": "Feature",
  "properties": {
    "iso:country":"DE",
    "sg:address":"Zur Wolfskuhle 10 b",
    "sg:city":"Balve",
    "sg:postcode":"58802",
    "sg:province":"Nordrhein-Westfalen",
    "wof:name":"Gisbar Gmbh",
    "wof:placetype":"venue"
},
  "geometry": {"coordinates":[7.8632478714,51.335067749],"type":"Point"}
}