{
  "type": "Feature",
  "properties": {
    "iso:country":"DE",
    "sg:address":"Burgenlandstr.",
    "sg:city":"Stuttgart",
    "sg:postcode":"70469",
    "sg:province":"Baden-W\u00fcrttemberg",
    "wof:name":"Erste Aktionsgemeinschaft Aktiver B\u00fcrger Stg.-feuerbach",
    "wof:placetype":"venue"
},
  "geometry": {"coordinates":[9.1548995972,48.809715271],"type":"Point"}
}