{
  "type": "Feature",
  "properties": {
    "iso:country":"DE",
    "sg:address":"K\u00f6nigstr. 54",
    "sg:city":"Minden",
    "sg:phone":"+49 571/24575",
    "sg:postcode":"32427",
    "sg:province":"Nordrhein-Westfalen",
    "wof:name":"Lichthaus Am K\u00f6nigswall",
    "wof:placetype":"venue"
},
  "geometry": {"coordinates":[8.909052,52.287148],"type":"Point"}
}