{
  "type": "Feature",
  "properties": {
    "iso:country":"DE",
    "sg:address":"Vorstadt 60",
    "sg:city":"Bingen",
    "sg:phone":"+49 6721/10663",
    "sg:postcode":"55411",
    "sg:province":"Rheinland-Pfalz",
    "wof:name":"Brunnenst\u00fcbchen",
    "wof:placetype":"venue"
},
  "geometry": {"coordinates":[7.8996767998,49.9691734314],"type":"Point"}
}