{
  "type": "Feature",
  "properties": {
    "iso:country":"DE",
    "sg:address":"Betzenriedstr. 94",
    "sg:city":"Reutlingen",
    "sg:phone":"+49 7121/492852",
    "sg:postcode":"72766",
    "sg:province":"Baden-W\u00fcrttemberg",
    "wof:name":"Franz Bausch",
    "wof:placetype":"venue"
},
  "geometry": {"coordinates":[9.229912,48.488319],"type":"Point"}
}