{
  "type": "Feature",
  "properties": {
    "iso:country":"DE",
    "sg:address":"Hauptstr. 2",
    "sg:city":"Teistungen",
    "sg:phone":"+49 36071/97044",
    "sg:postcode":"37339",
    "sg:province":"Th\u00fcringen",
    "wof:name":"Pizzaria Giovanni",
    "wof:placetype":"venue"
},
  "geometry": {"coordinates":[10.2653236389,51.4718971252],"type":"Point"}
}