{
  "type": "Feature",
  "properties": {
    "iso:country":"DE",
    "sg:address":"Buchenkamp 2",
    "sg:city":"Braunschweig",
    "sg:phone":"+49 531/693518",
    "sg:postcode":"38126",
    "sg:province":"Niedersachsen",
    "wof:name":"Teodoro Raddatz Architekt",
    "wof:placetype":"venue"
},
  "geometry": {"coordinates":[10.57315,52.227966],"type":"Point"}
}