{
  "type": "Feature",
  "properties": {
    "iso:country":"DE",
    "sg:address":"Im Leuchensang 73",
    "sg:city":"Bitburg",
    "sg:phone":"+49 6561/2870",
    "sg:postcode":"54634",
    "sg:province":"Rheinland-Pfalz",
    "wof:name":"K.-k. Britten",
    "wof:placetype":"venue"
},
  "geometry": {"coordinates":[6.5401859283,49.9805145264],"type":"Point"}
}