{
  "type": "Feature",
  "properties": {
    "iso:country":"DE",
    "sg:address":"Weizenstr. 2",
    "sg:city":"Vaihingen",
    "sg:postcode":"71665",
    "sg:province":"Baden-W\u00fcrttemberg",
    "wof:name":"Contentus Gmbh",
    "wof:placetype":"venue"
},
  "geometry": {"coordinates":[8.9713916779,48.950969696],"type":"Point"}
}