{
  "type": "Feature",
  "properties": {
    "iso:country":"DE",
    "sg:address":"Villeparisis Platz",
    "sg:city":"Wathlingen",
    "sg:phone":"+49 5144/3911",
    "sg:postcode":"29339",
    "sg:province":"Niedersachsen",
    "wof:name":"B\u00fcrgerhaus",
    "wof:placetype":"venue"
},
  "geometry": {"coordinates":[10.144952774,52.5360870361],"type":"Point"}
}