{
  "type": "Feature",
  "properties": {
    "iso:country":"DE",
    "sg:address":"Birkenweg 2",
    "sg:city":"Sebnitz",
    "sg:postcode":"01855",
    "sg:province":"Sachsen",
    "wof:name":"Sbs Hoch-und Tiefbau Gmbh",
    "wof:placetype":"venue"
},
  "geometry": {"coordinates":[14.2843589783,50.9616127014],"type":"Point"}
}