{
  "type": "Feature",
  "properties": {
    "iso:country":"DE",
    "sg:address":"Frankfurter Str. 267",
    "sg:city":"K\u00f6ln",
    "sg:postcode":"51147",
    "sg:province":"Nordrhein-Westfalen",
    "wof:name":"Pdt Paffendorf Datentechnik E. K.",
    "wof:placetype":"venue"
},
  "geometry": {"coordinates":[7.0838499069,50.863368988],"type":"Point"}
}