{
  "type": "Feature",
  "properties": {
    "iso:country":"DE",
    "sg:address":"Bauerhausener Weg 1",
    "sg:city":"Uelsen",
    "sg:phone":"+49 5942/387",
    "sg:postcode":"49843",
    "sg:province":"Niedersachsen",
    "wof:name":"Albert-jan Lucas",
    "wof:placetype":"venue"
},
  "geometry": {"coordinates":[6.89439,52.507271],"type":"Point"}
}