{
  "type": "Feature",
  "properties": {
    "iso:country":"DE",
    "sg:address":"Hoherodskopfstr. 28",
    "sg:city":"Schotten",
    "sg:phone":"+49 6044/2551",
    "sg:postcode":"63679",
    "sg:province":"Hessen",
    "wof:name":"Manfred Ludwig",
    "wof:placetype":"venue"
},
  "geometry": {"coordinates":[9.2072181702,50.5087738037],"type":"Point"}
}