{
  "type": "Feature",
  "properties": {
    "iso:country":"DE",
    "sg:address":"Harzblick 18",
    "sg:city":"B\u00f6r\u00dfum",
    "sg:phone":"+49 5334/6626",
    "sg:postcode":"38312",
    "sg:province":"Niedersachsen",
    "wof:name":"Babette Baier Heilpraktikerin",
    "wof:placetype":"venue"
},
  "geometry": {"coordinates":[10.5803442001,52.0698699951],"type":"Point"}
}