{
  "type": "Feature",
  "properties": {
    "iso:country":"DE",
    "sg:address":"Donaustr. 7a",
    "sg:city":"Forst / Baden",
    "sg:phone":"+49 7251/71283",
    "sg:postcode":"76694",
    "sg:province":"Baden-W\u00fcrttemberg",
    "wof:name":"Virgin Holding Inc.",
    "wof:placetype":"venue"
},
  "geometry": {"coordinates":[8.5804176331,49.156879425],"type":"Point"}
}