{
  "type": "Feature",
  "properties": {
    "iso:country":"DE",
    "sg:address":"Schlachthofstr. 21",
    "sg:city":"Witten",
    "sg:phone":"+49 2302/912255",
    "sg:postcode":"58455",
    "sg:province":"Nordrhein-Westfalen",
    "wof:name":"Mobiles Pflegeteam Lamik Und Taunitz",
    "wof:placetype":"venue"
},
  "geometry": {"coordinates":[7.340979,51.443821],"type":"Point"}
}