{
  "type": "Feature",
  "properties": {
    "iso:country":"DE",
    "sg:address":"Stenzelring 21",
    "sg:city":"Hamburg",
    "sg:postcode":"21107",
    "sg:province":"Hamburg",
    "wof:name":"International Veneer Company Europe Mbh",
    "wof:placetype":"venue"
},
  "geometry": {"coordinates":[10.0069694519,53.5179862976],"type":"Point"}
}