{
  "type": "Feature",
  "properties": {
    "iso:country":"DE",
    "sg:address":"Am Busbahnhof 6",
    "sg:city":"Westerr\u00f6nfeld",
    "sg:phone":"+49 4331/84760",
    "sg:postcode":"24784",
    "sg:province":"Schleswig-Holstein",
    "wof:name":"Strabag Ag",
    "wof:placetype":"venue"
},
  "geometry": {"coordinates":[9.65476,54.277252],"type":"Point"}
}