{
  "type": "Feature",
  "properties": {
    "iso:country":"DE",
    "sg:address":"Anton-Loevenich-Str. 11",
    "sg:city":"Heinsberg",
    "sg:phone":"+49 2452/61301",
    "sg:postcode":"52525",
    "sg:province":"Nordrhein-Westfalen",
    "wof:name":"Martin Zelissen",
    "wof:placetype":"venue"
},
  "geometry": {"coordinates":[6.128561,51.072865],"type":"Point"}
}