{
  "type": "Feature",
  "properties": {
    "iso:country":"DE",
    "sg:address":"Martin-Luther-Str. 17",
    "sg:city":"Landau",
    "sg:phone":"+49 6341/87102",
    "sg:postcode":"76829",
    "sg:province":"Rheinland-Pfalz",
    "wof:name":"Tapisserie Im Heiligenthaler Hof",
    "wof:placetype":"venue"
},
  "geometry": {"coordinates":[8.1147422791,49.1962089539],"type":"Point"}
}