{
  "type": "Feature",
  "properties": {
    "iso:country":"DE",
    "sg:address":"Staffhorster Str. 1",
    "sg:city":"Wietzen",
    "sg:phone":"+49 5022/1729",
    "sg:postcode":"31613",
    "sg:province":"Niedersachsen",
    "wof:name":"Heinrich Schlemermeyer",
    "wof:placetype":"venue"
},
  "geometry": {"coordinates":[9.066243,52.684624],"type":"Point"}
}