{
  "type": "Feature",
  "properties": {
    "iso:country":"DE",
    "sg:address":"Sch\u00f6ninger Str. 74",
    "sg:city":"Delbr\u00fcck",
    "sg:phone":"+49 5250/53483",
    "sg:postcode":"33129",
    "sg:province":"Nordrhein-Westfalen",
    "wof:name":"B. Hessel",
    "wof:placetype":"venue"
},
  "geometry": {"coordinates":[8.497298,51.788136],"type":"Point"}
}