{
  "type": "Feature",
  "properties": {
    "iso:country":"DE",
    "sg:address":"Fr\u00f6hlefelderweg 100",
    "sg:city":"Reutlingen",
    "sg:phone":"+49 7127/70250",
    "sg:postcode":"72766",
    "sg:province":"Baden-W\u00fcrttemberg",
    "wof:name":"Hermann M\u00fcllersch\u00f6n",
    "wof:placetype":"venue"
},
  "geometry": {"coordinates":[9.2384395599,48.5638771057],"type":"Point"}
}