{
  "type": "Feature",
  "properties": {
    "iso:country":"DE",
    "sg:address":"Laawiesenweg 9",
    "sg:city":"Schw\u00e4bisch Gm\u00fcnd",
    "sg:phone":"+49 7171/40852",
    "sg:postcode":"73529",
    "sg:province":"Baden-W\u00fcrttemberg",
    "wof:name":"U. Wetzel Steuerberater",
    "wof:placetype":"venue"
},
  "geometry": {"coordinates":[9.7987422943,48.782875061],"type":"Point"}
}