{
  "type": "Feature",
  "properties": {
    "iso:country":"DE",
    "sg:address":"Ruhrstr. 12",
    "sg:city":"Neum\u00fcnster",
    "sg:phone":"+49 4321/99990",
    "sg:postcode":"24539",
    "sg:province":"Schleswig-Holstein",
    "wof:name":"Marion Paredes Gmbh",
    "wof:placetype":"venue"
},
  "geometry": {"coordinates":[9.9803562164,54.0508308411],"type":"Point"}
}