{
  "type": "Feature",
  "properties": {
    "iso:country":"DE",
    "sg:address":"Salzstr. 96",
    "sg:city":"Gera",
    "sg:phone":"+49 365/7106047",
    "sg:postcode":"07551",
    "sg:province":"Th\u00fcringen",
    "wof:name":"Sch\u00e4dlingsbek\u00e4mpfung Gera Gmbh",
    "wof:placetype":"venue"
},
  "geometry": {"coordinates":[12.0823707581,50.8322296143],"type":"Point"}
}