{
  "type": "Feature",
  "properties": {
    "iso:country":"DE",
    "sg:address":"In der Felster 62",
    "sg:city":"Andernach",
    "sg:phone":"+49 2632/42256",
    "sg:postcode":"56626",
    "sg:province":"Rheinland-Pfalz",
    "wof:name":"Herbert Brach Handelsvertr. Inh. Konstantin Brach",
    "wof:placetype":"venue"
},
  "geometry": {"coordinates":[7.383641,50.440121],"type":"Point"}
}