{
  "type": "Feature",
  "properties": {
    "iso:country":"DE",
    "sg:address":"Blumenau 11",
    "sg:city":"Duderstadt",
    "sg:phone":"+49 5527/3125",
    "sg:postcode":"37115",
    "sg:province":"Niedersachsen",
    "wof:name":"Wilhelm Rudolph Tischlerei",
    "wof:placetype":"venue"
},
  "geometry": {"coordinates":[10.224832,51.523792],"type":"Point"}
}