{
  "type": "Feature",
  "properties": {
    "iso:country":"DE",
    "sg:address":"Breslauer Str. 4",
    "sg:city":"Konstanz",
    "sg:phone":"+49 7531/77161",
    "sg:postcode":"78467",
    "sg:province":"Baden-W\u00fcrttemberg",
    "wof:name":"Ried-apotheke",
    "wof:placetype":"venue"
},
  "geometry": {"coordinates":[9.148805,47.685612],"type":"Point"}
}