{
  "type": "Feature",
  "properties": {
    "iso:country":"DE",
    "sg:address":"Celler Str. 11",
    "sg:city":"Wedemark",
    "sg:phone":"+49 5130/58929",
    "sg:postcode":"30900",
    "sg:province":"Niedersachsen",
    "wof:name":"Deutsche Verm\u00f6gensberatung Ag",
    "wof:placetype":"venue"
},
  "geometry": {"coordinates":[9.7565803528,52.547088623],"type":"Point"}
}