{
  "type": "Feature",
  "properties": {
    "iso:country":"DE",
    "sg:address":"Mozartstr. 21",
    "sg:city":"Crailsheim",
    "sg:phone":"+49 7951/24610",
    "sg:postcode":"74564",
    "sg:province":"Baden-W\u00fcrttemberg",
    "wof:name":"M. Belschner Heissmangel",
    "wof:placetype":"venue"
},
  "geometry": {"coordinates":[10.0466880798,49.1479682922],"type":"Point"}
}