{
  "type": "Feature",
  "properties": {
    "iso:country":"DE",
    "sg:address":"Spaichinger Str. 3",
    "sg:city":"Aldingen",
    "sg:phone":"+49 7424/601357",
    "sg:postcode":"78554",
    "sg:province":"Baden-W\u00fcrttemberg",
    "wof:name":"Ingbert Merz",
    "wof:placetype":"venue"
},
  "geometry": {"coordinates":[8.7120027542,48.0967941284],"type":"Point"}
}