{
  "type": "Feature",
  "properties": {
    "iso:country":"DE",
    "sg:address":"Krokusstr. 21",
    "sg:city":"B\u00f6blingen",
    "sg:postcode":"71034",
    "sg:province":"Baden-W\u00fcrttemberg",
    "wof:name":"Pokes Gmbh",
    "wof:placetype":"venue"
},
  "geometry": {"coordinates":[8.9548501968,48.6864814758],"type":"Point"}
}