{
  "type": "Feature",
  "properties": {
    "iso:country":"DE",
    "sg:address":"Langenbrook 3",
    "sg:city":"Kollmar",
    "sg:postcode":"25377",
    "sg:province":"Schleswig-Holstein",
    "wof:name":"Wbs Zweite Vermietungs Gmbh & Co. Kg",
    "wof:placetype":"venue"
},
  "geometry": {"coordinates":[9.501545,53.744843],"type":"Point"}
}