{
  "type": "Feature",
  "properties": {
    "iso:country":"DE",
    "sg:address":"Frauenstr. 17",
    "sg:city":"Goch",
    "sg:phone":"+49 2823/6774",
    "sg:postcode":"47574",
    "sg:province":"Nordrhein-Westfalen",
    "wof:name":"Rinkenh\u00f6fchen",
    "wof:placetype":"venue"
},
  "geometry": {"coordinates":[6.155228138,51.6749382019],"type":"Point"}
}