{
  "type": "Feature",
  "properties": {
    "iso:country":"DE",
    "sg:address":"Neue Maastrichter Str. 2",
    "sg:city":"K\u00f6ln",
    "sg:phone":"+49 221/529618",
    "sg:postcode":"50672",
    "sg:province":"Nordrhein-Westfalen",
    "wof:name":"Atik",
    "wof:placetype":"venue"
},
  "geometry": {"coordinates":[6.9346108437,50.9388847351],"type":"Point"}
}