{
  "type": "Feature",
  "properties": {
    "iso:country":"DE",
    "sg:address":"Stubenrauchstr. 33 c",
    "sg:city":"Berlin",
    "sg:phone":"+49 30/8114524",
    "sg:postcode":"14167",
    "sg:province":"Berlin",
    "wof:name":"Otto Harnisch Architekt",
    "wof:placetype":"venue"
},
  "geometry": {"coordinates":[13.267059,52.426735],"type":"Point"}
}