{
  "type": "Feature",
  "properties": {
    "iso:country":"DE",
    "sg:city":"Bodenkirchen",
    "sg:phone":"+49 8741/8776",
    "sg:postcode":"84155",
    "sg:province":"Bayern",
    "wof:name":"Raimund Fredlmeier",
    "wof:placetype":"venue"
},
  "geometry": {"coordinates":[12.386795,48.383858],"type":"Point"}
}