{
  "type": "Feature",
  "properties": {
    "iso:country":"DE",
    "sg:address":"Staufeneckstr. 12-3",
    "sg:city":"G\u00f6ppingen",
    "sg:phone":"+49 7161/811663",
    "sg:postcode":"73037",
    "sg:province":"Baden-W\u00fcrttemberg",
    "wof:name":"Gerhard Neunecker Mech. Werkstatt",
    "wof:placetype":"venue"
},
  "geometry": {"coordinates":[9.697051,48.670918],"type":"Point"}
}