{
  "type": "Feature",
  "properties": {
    "iso:country":"DE",
    "sg:address":"Molldiete 1",
    "sg:city":"Ravensburg",
    "sg:phone":"+49 751/31213",
    "sg:postcode":"88212",
    "sg:province":"Baden-W\u00fcrttemberg",
    "wof:name":"Ff Wohn- Und Gewerbebau Gmbh",
    "wof:placetype":"venue"
},
  "geometry": {"coordinates":[9.6162395477,47.7651672363],"type":"Point"}
}