{
  "type": "Feature",
  "properties": {
    "iso:country":"DE",
    "sg:address":"Buckower Damm 90",
    "sg:city":"Berlin",
    "sg:phone":"+49 30/6048653",
    "sg:postcode":"12349",
    "sg:province":"Berlin",
    "wof:name":"Ramazan Kurtoglu",
    "wof:placetype":"venue"
},
  "geometry": {"coordinates":[13.4347009659,52.4357833862],"type":"Point"}
}