{
  "type": "Feature",
  "properties": {
    "iso:country":"DE",
    "sg:address":"Neubrandenburger Str. 9 c",
    "sg:city":"Friedland",
    "sg:phone":"+49 39601/20342",
    "sg:postcode":"17098",
    "sg:province":"Mecklenburg-Vorpommern",
    "wof:name":"Kik In",
    "wof:placetype":"venue"
},
  "geometry": {"coordinates":[13.5433244705,53.6615791321],"type":"Point"}
}