{
  "type": "Feature",
  "properties": {
    "iso:country":"DE",
    "sg:address":"Margeritenstr. 7",
    "sg:city":"Wiesmoor",
    "sg:phone":"+49 4944/2632",
    "sg:postcode":"26639",
    "sg:province":"Niedersachsen",
    "wof:name":"Heinrich Becker Angiokard Medizint. Gmbh",
    "wof:placetype":"venue"
},
  "geometry": {"coordinates":[7.743781,53.412647],"type":"Point"}
}