{
  "type": "Feature",
  "properties": {
    "iso:country":"DE",
    "sg:address":"Industriestr. 5",
    "sg:city":"Pleinfeld",
    "sg:phone":"+49 9144/331",
    "sg:postcode":"91785",
    "sg:province":"Bayern",
    "wof:name":"Roman Hentsch",
    "wof:placetype":"venue"
},
  "geometry": {"coordinates":[10.974525,49.101234],"type":"Point"}
}