{
  "type": "Feature",
  "properties": {
    "iso:country":"DE",
    "sg:address":"Auf den Gleichen 3",
    "sg:city":"Trendelburg",
    "sg:phone":"+49 5675/352",
    "sg:postcode":"34388",
    "sg:province":"Hessen",
    "wof:name":"Herbert Dettmar",
    "wof:placetype":"venue"
},
  "geometry": {"coordinates":[9.513983,51.56546],"type":"Point"}
}