{
  "type": "Feature",
  "properties": {
    "iso:country":"DE",
    "sg:address":"Vor dem Tor",
    "sg:city":"Leun",
    "sg:postcode":"35638",
    "sg:province":"Hessen",
    "wof:name":"Bau- Und Betriebs Gmbh",
    "wof:placetype":"venue"
},
  "geometry": {"coordinates":[8.309805,50.530125],"type":"Point"}
}