{
  "type": "Feature",
  "properties": {
    "iso:country":"DE",
    "sg:address":"Querstr. 2",
    "sg:city":"Neu Bartelshagen",
    "sg:phone":"+49 38321/60663",
    "sg:postcode":"18442",
    "sg:province":"Mecklenburg-Vorpommern",
    "wof:name":"Hsa Holz- Und Bautenschutz Gmbh",
    "wof:placetype":"venue"
},
  "geometry": {"coordinates":[12.892254,54.344696],"type":"Point"}
}