{
  "type": "Feature",
  "properties": {
    "iso:country":"DE",
    "sg:address":"Zeppelinstr. 4A",
    "sg:city":"Isernhagen",
    "sg:phone":"+49 511/615240",
    "sg:postcode":"30916",
    "sg:province":"Niedersachsen",
    "wof:name":"Beck Technisches B\u00fcro Hannover Gmbh",
    "wof:placetype":"venue"
},
  "geometry": {"coordinates":[9.8333501816,52.4318771362],"type":"Point"}
}