{
  "type": "Feature",
  "properties": {
    "iso:country":"DE",
    "sg:address":"Immenbecker Weg 18a",
    "sg:city":"Hamburg",
    "sg:postcode":"21149",
    "sg:province":"Hamburg",
    "wof:name":"Nexus Conzept Gmbh",
    "wof:placetype":"venue"
},
  "geometry": {"coordinates":[9.8273506165,53.4679641724],"type":"Point"}
}