{
  "type": "Feature",
  "properties": {
    "iso:country":"DE",
    "sg:address":"Hermann-L\u00f6ns-Str. 1",
    "sg:city":"Edemissen",
    "sg:phone":"+49 5176/7335",
    "sg:postcode":"31234",
    "sg:province":"Niedersachsen",
    "wof:name":"Elke Schmidt",
    "wof:placetype":"venue"
},
  "geometry": {"coordinates":[10.258888,52.382809],"type":"Point"}
}