{
  "type": "Feature",
  "properties": {
    "iso:country":"DE",
    "sg:address":"Raiffeisenstr. 30",
    "sg:city":"Filderstadt",
    "sg:phone":"+49 711/907710",
    "sg:postcode":"70794",
    "sg:province":"Baden-W\u00fcrttemberg",
    "wof:name":"Tera Port Gmbh",
    "wof:placetype":"venue"
},
  "geometry": {"coordinates":[9.2282447815,48.6579284668],"type":"Point"}
}