{
  "type": "Feature",
  "properties": {
    "iso:country":"DE",
    "sg:address":"Mulden\u00e4ckerstr. 11",
    "sg:city":"Stuttgart",
    "sg:phone":"+49 711/531756",
    "sg:postcode":"70378",
    "sg:province":"Baden-W\u00fcrttemberg",
    "wof:name":"Manfred Morlock Ingenieur",
    "wof:placetype":"venue"
},
  "geometry": {"coordinates":[9.2370672226,48.834400177],"type":"Point"}
}