{
  "type": "Feature",
  "properties": {
    "iso:country":"DE",
    "sg:address":"MBA - IMC",
    "sg:city":"Ludwigshafen",
    "sg:phone":"+49 621/5203251",
    "sg:postcode":"67059",
    "sg:province":"Rheinland-Pfalz",
    "wof:name":"Mba-imc",
    "wof:placetype":"venue"
},
  "geometry": {"coordinates":[8.44734,49.480995],"type":"Point"}
}