{
  "type": "Feature",
  "properties": {
    "iso:country":"DE",
    "sg:address":"Lunzenauer Str. 17",
    "sg:city":"Penig",
    "sg:phone":"+49 37381/80234",
    "sg:postcode":"09322",
    "sg:province":"Sachsen",
    "wof:name":"Grill- Und Pizzabar",
    "wof:placetype":"venue"
},
  "geometry": {"coordinates":[12.7033100128,50.9349517822],"type":"Point"}
}