{
  "type": "Feature",
  "properties": {
    "iso:country":"DE",
    "sg:address":"K\u00f6nigstr. 18",
    "sg:city":"Ahlen",
    "sg:phone":"+49 2382/3080",
    "sg:postcode":"59227",
    "sg:province":"Nordrhein-Westfalen",
    "wof:name":"Gerhard R\u00fcschenschmidt",
    "wof:placetype":"venue"
},
  "geometry": {"coordinates":[7.893184185,51.7638778687],"type":"Point"}
}