{
  "type": "Feature",
  "properties": {
    "iso:country":"DE",
    "sg:address":"Nickelstr. 26",
    "sg:city":"Eschweiler",
    "sg:phone":"+49 2403/25673",
    "sg:postcode":"52249",
    "sg:province":"Nordrhein-Westfalen",
    "wof:name":"Nickel",
    "wof:placetype":"venue"
},
  "geometry": {"coordinates":[6.2391037941,50.8229827881],"type":"Point"}
}