{
  "type": "Feature",
  "properties": {
    "iso:country":"DE",
    "sg:address":"H\u00fcttenberger Str. 4",
    "sg:city":"Linden",
    "sg:phone":"+49 6403/72474",
    "sg:postcode":"35440",
    "sg:province":"Hessen",
    "wof:name":"Pirr Gesch\u00e4ftsf\u00fchrung Und Verwaltungs Gmbh",
    "wof:placetype":"venue"
},
  "geometry": {"coordinates":[8.6470556259,50.5294647217],"type":"Point"}
}