{
  "type": "Feature",
  "properties": {
    "iso:country":"DE",
    "sg:address":"Grenzstr. 21",
    "sg:city":"Halle",
    "sg:phone":"+49 345/57130",
    "sg:postcode":"06112",
    "sg:province":"Sachsen-Anhalt",
    "wof:name":"Stz Ohg Sparkassen-technik-zentrum Der",
    "wof:placetype":"venue"
},
  "geometry": {"coordinates":[12.00388,51.480236],"type":"Point"}
}