{
  "type": "Feature",
  "properties": {
    "iso:country":"DE",
    "sg:address":"Am Luftschacht 11-17",
    "sg:city":"Essen",
    "sg:phone":"+49 201/852030",
    "sg:postcode":"45307",
    "sg:province":"Nordrhein-Westfalen",
    "wof:name":"Mollen Wohnen & Sparen Essen Gmbh & Co. Kg",
    "wof:placetype":"venue"
},
  "geometry": {"coordinates":[7.06752491,51.4606323242],"type":"Point"}
}