{
  "type": "Feature",
  "properties": {
    "iso:country":"DE",
    "sg:address":"Alexander-Koenig-Str. 6",
    "sg:city":"Bonn",
    "sg:phone":"+49 228/212308",
    "sg:postcode":"53115",
    "sg:province":"Nordrhein-Westfalen",
    "wof:name":"Dr. Hermann Riedel Dipl.-landwirt",
    "wof:placetype":"venue"
},
  "geometry": {"coordinates":[7.0912518501,50.7151145935],"type":"Point"}
}