{
  "type": "Feature",
  "properties": {
    "iso:country":"DE",
    "sg:address":"Rimbergstr. 4",
    "sg:city":"Dautphetal",
    "sg:phone":"+49 6420/7339",
    "sg:postcode":"35232",
    "sg:province":"Hessen",
    "wof:name":"E. Spies",
    "wof:placetype":"venue"
},
  "geometry": {"coordinates":[8.6127510071,50.8314247131],"type":"Point"}
}