{
  "type": "Feature",
  "properties": {
    "iso:country":"DE",
    "sg:address":"Sch\u00f6ntalweg 80",
    "sg:city":"Alfter",
    "sg:phone":"+49 228/641686",
    "sg:postcode":"53347",
    "sg:province":"Nordrhein-Westfalen",
    "wof:name":"J. Nettekoven Gmbh Kunst- Und Bauschlosserei",
    "wof:placetype":"venue"
},
  "geometry": {"coordinates":[7.0237798691,50.7122688293],"type":"Point"}
}