{
  "type": "Feature",
  "properties": {
    "iso:country":"DE",
    "sg:address":"Goethestr. 20",
    "sg:city":"Ilmenau",
    "sg:phone":"+49 3677/67790",
    "sg:postcode":"98693",
    "sg:province":"Th\u00fcringen",
    "wof:name":"Phaidros Gmbh",
    "wof:placetype":"venue"
},
  "geometry": {"coordinates":[10.904885,50.680408],"type":"Point"}
}