{
  "type": "Feature",
  "properties": {
    "iso:country":"DE",
    "sg:address":"Vogtsreichenbacher Str. 4",
    "sg:city":"Ammerndorf",
    "sg:phone":"+49 9127/6677",
    "sg:postcode":"90614",
    "sg:province":"Bayern",
    "wof:name":"Akg Agrar Kompost Gmbh",
    "wof:placetype":"venue"
},
  "geometry": {"coordinates":[10.8498134613,49.421043396],"type":"Point"}
}