{
  "type": "Feature",
  "properties": {
    "iso:country":"DE",
    "sg:address":"Tulpenweg 3",
    "sg:city":"N\u00fcbbel",
    "sg:phone":"+49 4331/61636",
    "sg:postcode":"24809",
    "sg:province":"Schleswig-Holstein",
    "wof:name":"H. Und M. Koll",
    "wof:placetype":"venue"
},
  "geometry": {"coordinates":[9.6168889999,54.2751312256],"type":"Point"}
}