{
  "type": "Feature",
  "properties": {
    "iso:country":"DE",
    "sg:address":"Kindergartenweg 13",
    "sg:city":"Allmendingen",
    "sg:phone":"+49 7391/2250",
    "sg:postcode":"89604",
    "sg:province":"Baden-W\u00fcrttemberg",
    "wof:name":"Franz Rothenbacher Baumaschinenhandel Gmbh",
    "wof:placetype":"venue"
},
  "geometry": {"coordinates":[9.72856,48.325649],"type":"Point"}
}