{
  "type": "Feature",
  "properties": {
    "iso:country":"DE",
    "sg:address":"Hauptstr. 78",
    "sg:city":"Mainz",
    "sg:phone":"+49 6131/962420",
    "sg:postcode":"55120",
    "sg:province":"Rheinland-Pfalz",
    "wof:name":"Hl Markt",
    "wof:placetype":"venue"
},
  "geometry": {"coordinates":[8.229929924,50.0208206177],"type":"Point"}
}