{
  "type": "Feature",
  "properties": {
    "iso:country":"DE",
    "sg:address":"Birkerstr. 4",
    "sg:city":"M\u00fcnchen",
    "sg:phone":"+49 89/185102",
    "sg:postcode":"80636",
    "sg:province":"Bayern",
    "wof:name":"Gartenbau Fischer Gmbh",
    "wof:placetype":"venue"
},
  "geometry": {"coordinates":[11.541333,48.149277],"type":"Point"}
}