{
  "type": "Feature",
  "properties": {
    "iso:country":"DE",
    "sg:address":"He\u00dflerstr. 40",
    "sg:city":"Hamm",
    "sg:postcode":"59065",
    "sg:province":"Nordrhein-Westfalen",
    "wof:name":"Hanna Klessmann Holding Gmbh",
    "wof:placetype":"venue"
},
  "geometry": {"coordinates":[7.826388,51.679878],"type":"Point"}
}