{
  "type": "Feature",
  "properties": {
    "iso:country":"DE",
    "sg:address":"August-Bebel-Platz",
    "sg:city":"Bautzen",
    "sg:phone":"+49 3591/44416",
    "sg:postcode":"02625",
    "sg:province":"Sachsen",
    "wof:name":"Macs Imbi\u00df",
    "wof:placetype":"venue"
},
  "geometry": {"coordinates":[14.4329099655,51.1761741638],"type":"Point"}
}