{
  "type": "Feature",
  "properties": {
    "iso:country":"DE",
    "sg:address":"Raiffeisenstr. 1",
    "sg:city":"Blindheim",
    "sg:phone":"+49 9074/921555",
    "sg:postcode":"89434",
    "sg:province":"Bayern",
    "wof:name":"Ml Sicherheitstechnik Gmbh",
    "wof:placetype":"venue"
},
  "geometry": {"coordinates":[10.6096286774,48.6486167908],"type":"Point"}
}