{
  "type": "Feature",
  "properties": {
    "iso:country":"DE",
    "sg:address":"Bismarckall. 2",
    "sg:city":"Kiel",
    "sg:phone":"+49 4943/138940",
    "sg:postcode":"24105",
    "sg:province":"Schleswig-Holstein",
    "wof:name":"Maritim Hotel Bellevue",
    "wof:placetype":"venue"
},
  "geometry": {"coordinates":[10.150586,54.345406],"type":"Point"}
}