{
  "type": "Feature",
  "properties": {
    "iso:country":"DE",
    "sg:address":"\u00c4u\u00dferer Schlo\u00dfhof 1",
    "sg:city":"Sachsenheim",
    "sg:phone":"+49 7147/7274",
    "sg:postcode":"74343",
    "sg:province":"Baden-W\u00fcrttemberg",
    "wof:name":"P. Haussmann",
    "wof:placetype":"venue"
},
  "geometry": {"coordinates":[9.0655374527,48.9597473145],"type":"Point"}
}