{
  "type": "Feature",
  "properties": {
    "iso:country":"DE",
    "sg:address":"Castroper Str. 14",
    "sg:city":"Datteln",
    "sg:phone":"+49 2363/33585",
    "sg:postcode":"45711",
    "sg:province":"Nordrhein-Westfalen",
    "wof:name":"Pizzeria L Aurora",
    "wof:placetype":"venue"
},
  "geometry": {"coordinates":[7.3383808136,51.6510887146],"type":"Point"}
}