{
  "type": "Feature",
  "properties": {
    "iso:country":"DE",
    "sg:address":"Adalbertstr. 37",
    "sg:city":"Frankfurt",
    "sg:phone":"+49 69/702752",
    "sg:postcode":"60486",
    "sg:province":"Hessen",
    "wof:name":"Restaurant Ban Thai",
    "wof:placetype":"venue"
},
  "geometry": {"coordinates":[8.6449184418,50.1191520691],"type":"Point"}
}