{
  "type": "Feature",
  "properties": {
    "iso:country":"DE",
    "sg:address":"Falkensteiner Str. 31",
    "sg:city":"Gerstetten",
    "sg:phone":"+49 7324/919216",
    "sg:postcode":"89547",
    "sg:province":"Baden-W\u00fcrttemberg",
    "wof:name":"Kolb & Gr\u00f6ber Gmbh",
    "wof:placetype":"venue"
},
  "geometry": {"coordinates":[10.132977,48.600533],"type":"Point"}
}