{
  "type": "Feature",
  "properties": {
    "iso:country":"DE",
    "sg:address":"Markelsbach 73",
    "sg:city":"Much",
    "sg:phone":"+49 2245/2349",
    "sg:postcode":"53804",
    "sg:province":"Nordrhein-Westfalen",
    "wof:name":"R. Scholder",
    "wof:placetype":"venue"
},
  "geometry": {"coordinates":[7.3593120575,50.8879127502],"type":"Point"}
}