{
  "type": "Feature",
  "properties": {
    "iso:country":"DE",
    "sg:address":"Eichingerweg 8",
    "sg:city":"Ramerberg",
    "sg:phone":"+49 8039/408898",
    "sg:postcode":"83561",
    "sg:province":"Bayern",
    "wof:name":"Sokatec - Tools F\u00fcr Server Based Computing - Tips",
    "wof:placetype":"venue"
},
  "geometry": {"coordinates":[12.155361,48.017715],"type":"Point"}
}