{
  "type": "Feature",
  "properties": {
    "iso:country":"DE",
    "sg:address":"Gersthofer Str 9",
    "sg:city":"Gersthofen",
    "sg:phone":"+49 821/464201",
    "sg:postcode":"86368",
    "sg:province":"Bayern",
    "wof:name":"Holzbau Wittmann Gbr",
    "wof:placetype":"venue"
},
  "geometry": {"coordinates":[10.8348741531,48.4211349487],"type":"Point"}
}