{
  "type": "Feature",
  "properties": {
    "iso:country":"DE",
    "sg:address":"Ackerstr. 133",
    "sg:city":"Kleve",
    "sg:phone":"+49 2821/28947",
    "sg:postcode":"47533",
    "sg:province":"Nordrhein-Westfalen",
    "wof:name":"J. Winters",
    "wof:placetype":"venue"
},
  "geometry": {"coordinates":[6.118098,51.778023],"type":"Point"}
}