{
  "type": "Feature",
  "properties": {
    "iso:country":"DE",
    "sg:address":"Breslauer Str. 53",
    "sg:city":"Freilassing",
    "sg:phone":"+49 8654/3680",
    "sg:postcode":"83395",
    "sg:province":"Bayern",
    "wof:name":"Virgil Niedermayr Ohg",
    "wof:placetype":"venue"
},
  "geometry": {"coordinates":[12.9588308334,47.8552703857],"type":"Point"}
}