{
  "type": "Feature",
  "properties": {
    "iso:country":"DE",
    "sg:address":"Luitpoldstr. 28-30",
    "sg:city":"Zweibr\u00fccken",
    "sg:phone":"+49 4963/3215482",
    "sg:postcode":"66482",
    "sg:province":"Rheinland-Pfalz",
    "wof:name":"Merkur-druck Werle Gmbh",
    "wof:placetype":"venue"
},
  "geometry": {"coordinates":[7.359389782,49.2470054626],"type":"Point"}
}