{
  "type": "Feature",
  "properties": {
    "iso:country":"DE",
    "sg:address":"Kranstrasse 15",
    "sg:city":"Hamm",
    "sg:phone":"+49 2388",
    "sg:postcode":"59071",
    "sg:province":"Nordrhein-Westfalen",
    "wof:name":"Interlogo Internetdienstleistungen Gmbh & Co Kg",
    "wof:placetype":"venue"
},
  "geometry": {"coordinates":[7.9410128593,51.6879501343],"type":"Point"}
}