{
  "type": "Feature",
  "properties": {
    "iso:country":"DE",
    "sg:address":"Kardinal-Galen-Str. 72",
    "sg:city":"Duisburg",
    "sg:phone":"+49 203/343369",
    "sg:postcode":"47051",
    "sg:province":"Nordrhein-Westfalen",
    "wof:name":"Grill-pfanne",
    "wof:placetype":"venue"
},
  "geometry": {"coordinates":[6.774720192,51.4373321533],"type":"Point"}
}