{
  "type": "Feature",
  "properties": {
    "iso:country":"DE",
    "sg:address":"Untere Ebnat 4",
    "sg:city":"Sonthofen",
    "sg:phone":"+49 8321/84461",
    "sg:postcode":"87527",
    "sg:province":"Bayern",
    "wof:name":"Alois Riegler",
    "wof:placetype":"venue"
},
  "geometry": {"coordinates":[10.2831144333,47.4869499207],"type":"Point"}
}