{
  "type": "Feature",
  "properties": {
    "iso:country":"DE",
    "sg:address":"Rattlarer Str. 4",
    "sg:city":"Willingen",
    "sg:phone":"+49 5632/5388",
    "sg:postcode":"34508",
    "sg:province":"Hessen",
    "wof:name":"Pension Pohlmann",
    "wof:placetype":"venue"
},
  "geometry": {"coordinates":[8.6622209549,51.2848968506],"type":"Point"}
}