{
  "type": "Feature",
  "properties": {
    "iso:country":"DE",
    "sg:address":"Schie\u00dfmauerstr. 34",
    "sg:city":"Laudenbach",
    "sg:phone":"+49 6201/44931",
    "sg:postcode":"69514",
    "sg:province":"Baden-W\u00fcrttemberg",
    "wof:name":"Bobrowsky",
    "wof:placetype":"venue"
},
  "geometry": {"coordinates":[8.64823,49.609589],"type":"Point"}
}