{
  "type": "Feature",
  "properties": {
    "iso:country":"DE",
    "sg:address":"Kaiserstr. 8",
    "sg:city":"M\u00fcnchsm\u00fcnster",
    "sg:phone":"+49 8402/231",
    "sg:postcode":"85126",
    "sg:province":"Bayern",
    "wof:name":"Fritz Eisenrieder",
    "wof:placetype":"venue"
},
  "geometry": {"coordinates":[11.6900310516,48.7613525391],"type":"Point"}
}