{
  "type": "Feature",
  "properties": {
    "iso:country":"DE",
    "sg:address":"An Gut Nazareth 8",
    "sg:city":"D\u00fcren",
    "sg:phone":"+49 2421/86928",
    "sg:postcode":"52353",
    "sg:province":"Nordrhein-Westfalen",
    "wof:name":"Kloster-apotheke",
    "wof:placetype":"venue"
},
  "geometry": {"coordinates":[6.45046,50.813519],"type":"Point"}
}