{
  "type": "Feature",
  "properties": {
    "iso:country":"DE",
    "sg:address":"Rathausstr. 87",
    "sg:city":"Viernheim",
    "sg:phone":"+49 6204/72634",
    "sg:postcode":"68519",
    "sg:province":"Hessen",
    "wof:name":"Walter Niebler",
    "wof:placetype":"venue"
},
  "geometry": {"coordinates":[8.57489,49.534409],"type":"Point"}
}