{
  "type": "Feature",
  "properties": {
    "iso:country":"DE",
    "sg:address":"Waldstr. 2",
    "sg:city":"Loddin",
    "sg:phone":"+49 38375/20177",
    "sg:postcode":"17459",
    "sg:province":"Mecklenburg-Vorpommern",
    "wof:name":"Haus Nixe",
    "wof:placetype":"venue"
},
  "geometry": {"coordinates":[14.0219173431,54.0402603149],"type":"Point"}
}