{
  "type": "Feature",
  "properties": {
    "iso:country":"DE",
    "sg:address":"Weinmarkt 4",
    "sg:city":"Memmingen",
    "sg:phone":"+49 8331/3113",
    "sg:postcode":"87700",
    "sg:province":"Bayern",
    "wof:name":"Apotheke Am Weinmarkt",
    "wof:placetype":"venue"
},
  "geometry": {"coordinates":[10.181638,47.984993],"type":"Point"}
}