{
  "type": "Feature",
  "properties": {
    "iso:country":"DE",
    "sg:address":"Wilhelm-Liebknecht-Str 1",
    "sg:city":"Hohenstein-Ernstthal",
    "sg:phone":"+49 3723/41940",
    "sg:postcode":"09337",
    "sg:province":"Sachsen",
    "wof:name":"A + L Geb\u00e4udetechnik Ammon Und Lichtenstein Gmbh",
    "wof:placetype":"venue"
},
  "geometry": {"coordinates":[12.710447,50.795811],"type":"Point"}
}