{
  "type": "Feature",
  "properties": {
    "iso:country":"DE",
    "sg:address":"Waldstr. 1",
    "sg:city":"Markkleeberg",
    "sg:phone":"+49 341/3542614",
    "sg:postcode":"04416",
    "sg:province":"Sachsen",
    "wof:name":"Wega Handels- Und Bauleistunges. Mbh",
    "wof:placetype":"venue"
},
  "geometry": {"coordinates":[12.3760995865,51.2768745422],"type":"Point"}
}