{
  "type": "Feature",
  "properties": {
    "iso:country":"DE",
    "sg:address":"Maingasse 6",
    "sg:city":"Kulmbach",
    "sg:phone":"+49 9221/75936",
    "sg:postcode":"95326",
    "sg:province":"Bayern",
    "wof:name":"Naser Transport Gmbh",
    "wof:placetype":"venue"
},
  "geometry": {"coordinates":[11.4149160385,50.0923728943],"type":"Point"}
}