{
  "type": "Feature",
  "properties": {
    "iso:country":"DE",
    "sg:address":"Lausitzer Str. 10",
    "sg:city":"Berlin",
    "sg:phone":"+49 30/61288167",
    "sg:postcode":"10999",
    "sg:province":"Berlin",
    "wof:name":"Biblio Copy Fotokopierger\u00e4te Aufstellungs Und Betriebs Gmbh",
    "wof:placetype":"venue"
},
  "geometry": {"coordinates":[13.428678,52.497486],"type":"Point"}
}