{
  "type": "Feature",
  "properties": {
    "iso:country":"DE",
    "sg:address":"Klobikauer Str. 5",
    "sg:city":"Merseburg",
    "sg:phone":"+49 3461/210925",
    "sg:postcode":"06217",
    "sg:province":"Sachsen-Anhalt",
    "wof:name":"Dieter Neumann",
    "wof:placetype":"venue"
},
  "geometry": {"coordinates":[11.987797,51.353474],"type":"Point"}
}