{
  "type": "Feature",
  "properties": {
    "iso:country":"DE",
    "sg:address":"Geyersdorfer Str. 12",
    "sg:city":"Annaberg-Buchholz",
    "sg:phone":"+49 3733/23070",
    "sg:postcode":"09456",
    "sg:province":"Sachsen",
    "wof:name":"Susanne Kamprad Rechtsanw\u00e4ltin",
    "wof:placetype":"venue"
},
  "geometry": {"coordinates":[13.0105228424,50.5832672119],"type":"Point"}
}