{
  "type": "Feature",
  "properties": {
    "iso:country":"DE",
    "sg:address":"annenstra\u00dfe 144j",
    "sg:city":"witten",
    "sg:phone":"+49 2302/189997",
    "sg:postcode":"58453",
    "sg:province":"Nordrhein-Westfalen",
    "wof:name":"Olaf City",
    "wof:placetype":"venue"
},
  "geometry": {"coordinates":[7.372099,51.44619],"type":"Point"}
}