{
  "type": "Feature",
  "properties": {
    "iso:country":"DE",
    "sg:address":"Auf der Lay 2",
    "sg:city":"Idar-Oberstein",
    "sg:phone":"+49 6781/93430",
    "sg:postcode":"55743",
    "sg:province":"Rheinland-Pfalz",
    "wof:name":"Paul Wild Edelsteine - Lapidaries",
    "wof:placetype":"venue"
},
  "geometry": {"coordinates":[7.292724,49.71637],"type":"Point"}
}