{
  "type": "Feature",
  "properties": {
    "iso:country":"DE",
    "sg:address":"Ginsterweg 7",
    "sg:city":"Blomberg",
    "sg:phone":"+49 5235/8619",
    "sg:postcode":"32825",
    "sg:province":"Nordrhein-Westfalen",
    "wof:name":"Waldow Metallbau-gmbh & Co. Kommanditgesellschaft",
    "wof:placetype":"venue"
},
  "geometry": {"coordinates":[9.032821,51.916183],"type":"Point"}
}