{
  "type": "Feature",
  "properties": {
    "iso:country":"DE",
    "sg:address":"Uhlandstr. 6",
    "sg:city":"Rauenberg",
    "sg:phone":"+49 7253/924686",
    "sg:postcode":"69231",
    "sg:province":"Baden-W\u00fcrttemberg",
    "wof:name":"Bellemann Bautr\u00e4ger- Und Betreuungs Gmbh",
    "wof:placetype":"venue"
},
  "geometry": {"coordinates":[8.684194,49.257748],"type":"Point"}
}