{
  "type": "Feature",
  "properties": {
    "iso:country":"DE",
    "sg:address":"Lachtaubenweg 17A",
    "sg:city":"Berlin",
    "sg:phone":"+49 30/4361040",
    "sg:postcode":"13505",
    "sg:province":"Berlin",
    "wof:name":"Peter Malinowski Ingenieur",
    "wof:placetype":"venue"
},
  "geometry": {"coordinates":[13.2265586853,52.5909614563],"type":"Point"}
}