{
  "type": "Feature",
  "properties": {
    "iso:country":"DE",
    "sg:address":"Gewerbeparkring 11",
    "sg:city":"M\u00fcllrose",
    "sg:postcode":"15299",
    "sg:province":"Brandenburg",
    "wof:name":"Brandenburger Sondermaschinen- Und Anlagenbau De Haan",
    "wof:placetype":"venue"
},
  "geometry": {"coordinates":[14.4321699142,52.2567749023],"type":"Point"}
}