{
  "type": "Feature",
  "properties": {
    "iso:country":"DE",
    "sg:address":"Bahnhofstr. 17",
    "sg:city":"Heidelberg",
    "sg:phone":"+49 6221/602682",
    "sg:postcode":"69115",
    "sg:province":"Baden-W\u00fcrttemberg",
    "wof:name":"R. Garipoglu",
    "wof:placetype":"venue"
},
  "geometry": {"coordinates":[8.690574646,49.4058761597],"type":"Point"}
}