{
  "type": "Feature",
  "properties": {
    "iso:country":"DE",
    "sg:address":"Ernst-Th\u00e4lmann-Str. 22",
    "sg:city":"Putlitz",
    "sg:phone":"+49 33981/80652",
    "sg:postcode":"16949",
    "sg:province":"Brandenburg",
    "wof:name":"Volker Ludewig",
    "wof:placetype":"venue"
},
  "geometry": {"coordinates":[12.0414867401,53.2501678467],"type":"Point"}
}