{
  "type": "Feature",
  "properties": {
    "iso:country":"DE",
    "sg:address":"Hermann - L\u00f6ns - Str. 29",
    "sg:city":"Garbsen OT Berenbostel",
    "sg:phone":"+49 5131",
    "sg:postcode":"30827",
    "sg:province":"Niedersachsen",
    "wof:name":"L\u00f6ns Hotel Garbsen",
    "wof:placetype":"venue"
},
  "geometry": {"coordinates":[9.6245946884,52.4499397278],"type":"Point"}
}