{
  "type": "Feature",
  "properties": {
    "iso:country":"DE",
    "sg:address":"Potsdamer Str. 81",
    "sg:city":"Michendorf",
    "sg:phone":"+49 33205/44480",
    "sg:postcode":"14552",
    "sg:province":"Brandenburg",
    "wof:name":"Knipper Bauelementehandel Gmbh",
    "wof:placetype":"venue"
},
  "geometry": {"coordinates":[13.062095,52.2981],"type":"Point"}
}