{
  "type": "Feature",
  "properties": {
    "iso:country":"DE",
    "sg:address":"Astallerstr. 7",
    "sg:city":"M\u00fcnchen",
    "sg:phone":"+49 89/5024082",
    "sg:postcode":"80339",
    "sg:province":"Bayern",
    "wof:name":"Driefer Gmbh",
    "wof:placetype":"venue"
},
  "geometry": {"coordinates":[11.5314702988,48.1394615173],"type":"Point"}
}