{
  "type": "Feature",
  "properties": {
    "iso:country":"DE",
    "sg:address":"Oldenburger Str. 19",
    "sg:city":"Delmenhorst",
    "sg:phone":"+49 4221/17854",
    "sg:postcode":"27753",
    "sg:province":"Niedersachsen",
    "wof:name":"E. Leuschner",
    "wof:placetype":"venue"
},
  "geometry": {"coordinates":[8.6219434738,53.0494728088],"type":"Point"}
}