{
  "type": "Feature",
  "properties": {
    "iso:country":"DE",
    "sg:address":"92693",
    "sg:city":"Eslarn",
    "sg:phone":"+49 9653/1779",
    "sg:postcode":"92693",
    "sg:province":"Bayern",
    "wof:name":"Goldenes Kreuz",
    "wof:placetype":"venue"
},
  "geometry": {"coordinates":[12.5219202042,49.5816993713],"type":"Point"}
}