{
  "type": "Feature",
  "properties": {
    "iso:country":"DE",
    "sg:address":"Pfarrer-Wekenborg-Str. 2",
    "sg:city":"Geeste",
    "sg:postcode":"49744",
    "sg:province":"Niedersachsen",
    "wof:name":"Kath. Pfarramt St. Nikolaus",
    "wof:placetype":"venue"
},
  "geometry": {"coordinates":[7.2364082336,52.6253700256],"type":"Point"}
}