{
  "type": "Feature",
  "properties": {
    "iso:country":"DE",
    "sg:address":"Gro\u00dfriedgasse 24",
    "sg:city":"Neuried",
    "sg:phone":"+49 7807/790",
    "sg:postcode":"77743",
    "sg:province":"Baden-W\u00fcrttemberg",
    "wof:name":"E. Marzluf",
    "wof:placetype":"venue"
},
  "geometry": {"coordinates":[7.800409,48.463047],"type":"Point"}
}