{
  "type": "Feature",
  "properties": {
    "iso:country":"DE",
    "sg:address":"Postfach 1180",
    "sg:city":"Wiesmoor",
    "sg:phone":"+49 4944/841",
    "sg:postcode":"26633",
    "sg:province":"Niedersachsen",
    "wof:name":"Bohlen & Doyen Seeschiffahrt-unternehmen",
    "wof:placetype":"venue"
},
  "geometry": {"coordinates":[7.733989,53.41354],"type":"Point"}
}