{
  "type": "Feature",
  "properties": {
    "iso:country":"DE",
    "sg:address":"Hauptstr. 19b",
    "sg:city":"Bodman-Ludwigshafen",
    "sg:phone":"+49 7773/920047",
    "sg:postcode":"78351",
    "sg:province":"Baden-W\u00fcrttemberg",
    "wof:name":"Agentur Geissler Gmbh & Co. Kg",
    "wof:placetype":"venue"
},
  "geometry": {"coordinates":[9.058306694,47.8185043335],"type":"Point"}
}