{
  "type": "Feature",
  "properties": {
    "iso:country":"DE",
    "sg:address":"Heyenbaumstr. 96",
    "sg:city":"Krefeld",
    "sg:phone":"+49 2151/560711",
    "sg:postcode":"47802",
    "sg:province":"Nordrhein-Westfalen",
    "wof:name":"Karl Metzer",
    "wof:placetype":"venue"
},
  "geometry": {"coordinates":[6.5791702271,51.3613433838],"type":"Point"}
}