{
  "type": "Feature",
  "properties": {
    "iso:country":"DE",
    "sg:address":"Friedensstr 54",
    "sg:city":"Plauen",
    "sg:phone":"+49 3741/528033",
    "sg:postcode":"08523",
    "sg:province":"Sachsen",
    "wof:name":"E.k.h. Plauen Gmbh",
    "wof:placetype":"venue"
},
  "geometry": {"coordinates":[12.1242923737,50.4968757629],"type":"Point"}
}