{
  "type": "Feature",
  "properties": {
    "iso:country":"DE",
    "sg:address":"Am Gehsteig 52",
    "sg:city":"Neu-Isenburg",
    "sg:postcode":"60299",
    "sg:province":"Hessen",
    "wof:name":"Philipp Holzmann Ag",
    "wof:placetype":"venue"
},
  "geometry": {"coordinates":[8.6951398849,50.0565185547],"type":"Point"}
}