{
  "type": "Feature",
  "properties": {
    "iso:country":"DE",
    "sg:address":"Heinrichstr. 13",
    "sg:city":"Helsa",
    "sg:postcode":"34298",
    "sg:province":"Hessen",
    "wof:name":"Webconstructions-zone E. K.",
    "wof:placetype":"venue"
},
  "geometry": {"coordinates":[9.6458940506,51.2183456421],"type":"Point"}
}