{
  "type": "Feature",
  "properties": {
    "iso:country":"DE",
    "sg:address":"Aichelberger Str. 40",
    "sg:city":"Holzmaden",
    "sg:phone":"+49 7023/3573",
    "sg:postcode":"73271",
    "sg:province":"Baden-W\u00fcrttemberg",
    "wof:name":"D. Liebrich",
    "wof:placetype":"venue"
},
  "geometry": {"coordinates":[9.523696,48.634163],"type":"Point"}
}