{
  "type": "Feature",
  "properties": {
    "iso:country":"DE",
    "sg:address":"Schwimmbadstr. 2",
    "sg:city":"Bad Lippspringe",
    "sg:phone":"+49 5252/9640",
    "sg:postcode":"33175",
    "sg:province":"Nordrhein-Westfalen",
    "wof:name":"Westfalen Therme",
    "wof:placetype":"venue"
},
  "geometry": {"coordinates":[8.8241224289,51.7915420532],"type":"Point"}
}