{
  "type": "Feature",
  "properties": {
    "iso:country":"DE",
    "sg:address":"Dorfstr. 14",
    "sg:city":"Prebberede",
    "sg:phone":"+49 39976/50262",
    "sg:postcode":"17168",
    "sg:province":"Mecklenburg-Vorpommern",
    "wof:name":"Henri Liefke",
    "wof:placetype":"venue"
},
  "geometry": {"coordinates":[12.4889774323,53.9100914001],"type":"Point"}
}