{
  "type": "Feature",
  "properties": {
    "iso:country":"DE",
    "sg:address":"Hauptstr. 48",
    "sg:city":"Falkenstein",
    "sg:phone":"+49 3745/70521",
    "sg:postcode":"08223",
    "sg:province":"Sachsen",
    "wof:name":"Guse Und Ha\u00df Rechtsanw\u00e4lte",
    "wof:placetype":"venue"
},
  "geometry": {"coordinates":[12.3676996231,50.4735298157],"type":"Point"}
}