{
  "type": "Feature",
  "properties": {
    "iso:country":"DE",
    "sg:address":"Am Hochgericht 1 a",
    "sg:city":"Staffelstein",
    "sg:phone":"+49 9573/950376",
    "sg:postcode":"96231",
    "sg:province":"Bayern",
    "wof:name":"Steiner Massivhaus Gmbh",
    "wof:placetype":"venue"
},
  "geometry": {"coordinates":[10.995435,50.096848],"type":"Point"}
}