{
  "type": "Feature",
  "properties": {
    "iso:country":"DE",
    "sg:address":"Brunnenstr. 10",
    "sg:city":"Ihringen",
    "sg:phone":"+49 7668/7520",
    "sg:postcode":"79241",
    "sg:province":"Baden-W\u00fcrttemberg",
    "wof:name":"Fritz Stein",
    "wof:placetype":"venue"
},
  "geometry": {"coordinates":[7.646373,48.04631],"type":"Point"}
}