{
  "type": "Feature",
  "properties": {
    "iso:country":"DE",
    "sg:address":"Blumenstr. 11",
    "sg:city":"Sonthofen",
    "sg:phone":"+49 8321/84151",
    "sg:postcode":"87527",
    "sg:province":"Bayern",
    "wof:name":"M. D\u00fcsterfeld-baier",
    "wof:placetype":"venue"
},
  "geometry": {"coordinates":[10.276653,47.514179],"type":"Point"}
}