{
  "type": "Feature",
  "properties": {
    "iso:country":"DE",
    "sg:address":"Pilsheim 34",
    "sg:city":"Burglengenfeld",
    "sg:phone":"+49 9474/272",
    "sg:postcode":"93133",
    "sg:province":"Bayern",
    "wof:name":"T. Hellmuth",
    "wof:placetype":"venue"
},
  "geometry": {"coordinates":[11.966093,49.271271],"type":"Point"}
}