{
  "type": "Feature",
  "properties": {
    "iso:country":"DE",
    "sg:address":"Ernteweg 12",
    "sg:city":"Amberg",
    "sg:phone":"+49 9621/15724",
    "sg:postcode":"92224",
    "sg:province":"Bayern",
    "wof:name":"Josef Dietz",
    "wof:placetype":"venue"
},
  "geometry": {"coordinates":[11.8339385986,49.4510726929],"type":"Point"}
}