{
  "type": "Feature",
  "properties": {
    "iso:country":"DE",
    "sg:address":"Hansastr. 4",
    "sg:city":"Steinfurt",
    "sg:phone":"+49 2552/2258",
    "sg:postcode":"48565",
    "sg:province":"Nordrhein-Westfalen",
    "wof:name":"Ewald Riering",
    "wof:placetype":"venue"
},
  "geometry": {"coordinates":[7.391297,52.123466],"type":"Point"}
}