{
  "type": "Feature",
  "properties": {
    "iso:country":"DE",
    "sg:address":"Siegburger Str. 39",
    "sg:city":"Sankt Augustin",
    "sg:phone":"+49 2241/31106365",
    "sg:postcode":"53757",
    "sg:province":"Nordrhein-Westfalen",
    "wof:name":"Intersurgical Beatmungsprodukte Gmbh",
    "wof:placetype":"venue"
},
  "geometry": {"coordinates":[7.178225,50.787743],"type":"Point"}
}