{
  "type": "Feature",
  "properties": {
    "iso:country":"DE",
    "sg:address":"Werftstr. 12",
    "sg:city":"Karlsruhe",
    "sg:postcode":"76189",
    "sg:province":"Baden-W\u00fcrttemberg",
    "wof:name":"Nahrungsmittelwerke Gmbh",
    "wof:placetype":"venue"
},
  "geometry": {"coordinates":[8.3366661072,49.0163116455],"type":"Point"}
}