{
  "type": "Feature",
  "properties": {
    "iso:country":"DE",
    "sg:address":"Spandauer Str. 1",
    "sg:city":"Siegen",
    "sg:phone":"+49 271/21529",
    "sg:postcode":"57072",
    "sg:province":"Nordrhein-Westfalen",
    "wof:name":"Gastst\u00e4tte Tsolias",
    "wof:placetype":"venue"
},
  "geometry": {"coordinates":[8.0166816711,50.8715629578],"type":"Point"}
}