{
  "type": "Feature",
  "properties": {
    "iso:country":"DE",
    "sg:address":"St. Ulrich 32b",
    "sg:city":"Bollschweil",
    "sg:phone":"+49 7602/510",
    "sg:postcode":"79283",
    "sg:province":"Baden-W\u00fcrttemberg",
    "wof:name":"K. Karle",
    "wof:placetype":"venue"
},
  "geometry": {"coordinates":[7.839802,47.919144],"type":"Point"}
}