{
  "type": "Feature",
  "properties": {
    "iso:country":"DE",
    "sg:address":"Joseph-K\u00f6nig-Str. 9",
    "sg:city":"Singen",
    "sg:phone":"+49 7731/47660",
    "sg:postcode":"78224",
    "sg:province":"Baden-W\u00fcrttemberg",
    "wof:name":"Tbs Thurner Bau Gmbh",
    "wof:placetype":"venue"
},
  "geometry": {"coordinates":[8.843659,47.792316],"type":"Point"}
}