{
  "type": "Feature",
  "properties": {
    "iso:country":"DE",
    "sg:address":"Hohenzollernstr 55",
    "sg:city":"Karlsruhe",
    "sg:phone":"+49 721/812161",
    "sg:postcode":"76135",
    "sg:province":"Baden-W\u00fcrttemberg",
    "wof:name":"Kassenschreck",
    "wof:placetype":"venue"
},
  "geometry": {"coordinates":[8.38737,48.993759],"type":"Point"}
}