{
  "type": "Feature",
  "properties": {
    "iso:country":"DE",
    "sg:address":"Frundsbergstr. 1",
    "sg:city":"Mindelheim",
    "sg:phone":"+49 8261/21678",
    "sg:postcode":"87719",
    "sg:province":"Bayern",
    "wof:name":"C. Rupp",
    "wof:placetype":"venue"
},
  "geometry": {"coordinates":[10.4909172058,48.0458602905],"type":"Point"}
}