{
  "type": "Feature",
  "properties": {
    "iso:country":"DE",
    "sg:address":"Sennlicher Weg 4-6",
    "sg:city":"Lotte",
    "sg:postcode":"49504",
    "sg:province":"Nordrhein-Westfalen",
    "wof:name":"Fritz Kr\u00fcger Beteiligungs-gmbh",
    "wof:placetype":"venue"
},
  "geometry": {"coordinates":[7.919013,52.310829],"type":"Point"}
}