{
  "type": "Feature",
  "properties": {
    "iso:country":"DE",
    "sg:address":"Oulustr. 7",
    "sg:city":"Leverkusen",
    "sg:phone":"+49 214/505360",
    "sg:postcode":"51375",
    "sg:province":"Nordrhein-Westfalen",
    "wof:name":"Klaus Schmitz Ingenieur",
    "wof:placetype":"venue"
},
  "geometry": {"coordinates":[7.0480360985,51.0343017578],"type":"Point"}
}