{
  "type": "Feature",
  "properties": {
    "iso:country":"DE",
    "sg:address":"Curt-Tausch-Str. 8",
    "sg:city":"K\u00f6nigsbr\u00fcck",
    "sg:phone":"+49 35795/42635",
    "sg:postcode":"01936",
    "sg:province":"Sachsen",
    "wof:name":"I. Seidel",
    "wof:placetype":"venue"
},
  "geometry": {"coordinates":[13.9045581818,51.2644805908],"type":"Point"}
}