{
  "type": "Feature",
  "properties": {
    "iso:country":"DE",
    "sg:address":"Poststr. 126",
    "sg:city":"Mainz",
    "sg:phone":"+49 6131/40401",
    "sg:postcode":"55126",
    "sg:province":"Rheinland-Pfalz",
    "wof:name":"Philipp F. Pfaff",
    "wof:placetype":"venue"
},
  "geometry": {"coordinates":[8.1769,49.987549],"type":"Point"}
}