{
  "type": "Feature",
  "properties": {
    "iso:country":"DE",
    "sg:address":"Strandstr. 8",
    "sg:city":"Brodersby",
    "sg:postcode":"24398",
    "sg:province":"Schleswig-Holstein",
    "wof:name":"Seegarten",
    "wof:placetype":"venue"
},
  "geometry": {"coordinates":[10.0260868073,54.6336898804],"type":"Point"}
}