{
  "type": "Feature",
  "properties": {
    "iso:country":"DE",
    "sg:address":"Auf Der Roese 16-18",
    "sg:city":"Hilchenbach",
    "sg:phone":"+49 4974/63458",
    "sg:postcode":"57271",
    "sg:province":"Nordrhein-Westfalen",
    "wof:name":"M.u.j. Spiegel",
    "wof:placetype":"venue"
},
  "geometry": {"coordinates":[8.9333715439,48.0224876404],"type":"Point"}
}