{
  "type": "Feature",
  "properties": {
    "iso:country":"DE",
    "sg:address":"T\u00f6nsfeldtstr. 9",
    "sg:city":"Hamburg",
    "sg:phone":"+49 40/390500",
    "sg:postcode":"22763",
    "sg:province":"Hamburg",
    "wof:name":"Re-cla-me-worldwide B\u00fcro F\u00fcr Werbung Und",
    "wof:placetype":"venue"
},
  "geometry": {"coordinates":[9.9195995331,53.5515174866],"type":"Point"}
}