{
  "type": "Feature",
  "properties": {
    "iso:country":"DE",
    "sg:address":"Berliner Ring 25",
    "sg:city":"Bensheim",
    "sg:postcode":"64625",
    "sg:province":"Hessen",
    "wof:name":"Schmiedeberger Reform- Warenversand Gmbh",
    "wof:placetype":"venue"
},
  "geometry": {"coordinates":[8.6068763733,49.6709289551],"type":"Point"}
}