{
  "type": "Feature",
  "properties": {
    "iso:country":"DE",
    "sg:address":"Stauferstr. 8",
    "sg:city":"Renningen",
    "sg:phone":"+49 7159/7833",
    "sg:postcode":"71272",
    "sg:province":"Baden-W\u00fcrttemberg",
    "wof:name":"H. H. Liebs Steuerberater",
    "wof:placetype":"venue"
},
  "geometry": {"coordinates":[8.9432735443,48.7724647522],"type":"Point"}
}