{
  "type": "Feature",
  "properties": {
    "iso:country":"DE",
    "sg:address":"Maienweg 107",
    "sg:city":"Hamburg",
    "sg:phone":"+49 40/597178",
    "sg:postcode":"22297",
    "sg:province":"Hamburg",
    "wof:name":"S\u00f6rensen-gr\u00fcngestaltung",
    "wof:placetype":"venue"
},
  "geometry": {"coordinates":[10.011762,53.615959],"type":"Point"}
}