{
  "type": "Feature",
  "properties": {
    "iso:country":"DE",
    "sg:address":"Im Sonnental 9",
    "sg:city":"Karlsruhe",
    "sg:phone":"+49 721/468316",
    "sg:postcode":"76229",
    "sg:province":"Baden-W\u00fcrttemberg",
    "wof:name":"Harsch Grundbesitzver- Waltungsgesellschaft Mbh",
    "wof:placetype":"venue"
},
  "geometry": {"coordinates":[8.5008716583,49.0005073547],"type":"Point"}
}