{
  "type": "Feature",
  "properties": {
    "iso:country":"DE",
    "sg:address":"G\u00fcttersbacher Str. 10",
    "sg:city":"Grasellenbach",
    "sg:phone":"+49 6207/5259",
    "sg:postcode":"64689",
    "sg:province":"Hessen",
    "wof:name":"Pension A. Helm",
    "wof:placetype":"venue"
},
  "geometry": {"coordinates":[8.8616609573,49.6302719116],"type":"Point"}
}