{
  "type": "Feature",
  "properties": {
    "iso:country":"DE",
    "sg:address":"Alois-Senefelder-Str. 9",
    "sg:city":"Mannheim",
    "sg:phone":"+49 621/333572",
    "sg:postcode":"68167",
    "sg:province":"Baden-W\u00fcrttemberg",
    "wof:name":"Sanicalor Sanit\u00e4re Installa- Tions- Und Heizungs Gmbh",
    "wof:placetype":"venue"
},
  "geometry": {"coordinates":[8.5001554489,49.4973640442],"type":"Point"}
}