{
  "type": "Feature",
  "properties": {
    "iso:country":"DE",
    "sg:city":"Ingolstadt",
    "sg:postcode":"85053",
    "sg:province":"Bayern",
    "wof:name":"Global Engineering",
    "wof:placetype":"venue"
},
  "geometry": {"coordinates":[11.459161,48.735893],"type":"Point"}
}