{
  "type": "Feature",
  "properties": {
    "iso:country":"DE",
    "sg:address":"Rudliebstr. 27",
    "sg:city":"M\u00fcnchen",
    "sg:phone":"+49 89/988929",
    "sg:postcode":"81925",
    "sg:province":"Bayern",
    "wof:name":"U. Sauer Immobilienmakler",
    "wof:placetype":"venue"
},
  "geometry": {"coordinates":[11.616736412,48.1580963135],"type":"Point"}
}