{
  "type": "Feature",
  "properties": {
    "iso:country":"DE",
    "sg:address":"Essenheimer Str. 125 B",
    "sg:city":"Mainz",
    "sg:phone":"+49 6131/140790",
    "sg:postcode":"55128",
    "sg:province":"Rheinland-Pfalz",
    "wof:name":"Egu Medien Vertriebs Gmbh",
    "wof:placetype":"venue"
},
  "geometry": {"coordinates":[8.2367601395,49.9771118164],"type":"Point"}
}