{
  "type": "Feature",
  "properties": {
    "iso:country":"DE",
    "sg:address":"Rheinstr. 16",
    "sg:city":"Ruppertshofen",
    "sg:phone":"+49 6772/8411",
    "sg:postcode":"56357",
    "sg:province":"Rheinland-Pfalz",
    "wof:name":"Herbert M\u00fcller",
    "wof:placetype":"venue"
},
  "geometry": {"coordinates":[7.805407,50.198967],"type":"Point"}
}