{
  "type": "Feature",
  "properties": {
    "iso:country":"DE",
    "sg:address":"Rabensberg 19",
    "sg:city":"Wedemark",
    "sg:phone":"+49 5130/7480",
    "sg:postcode":"30900",
    "sg:province":"Niedersachsen",
    "wof:name":"Cosmetic College Hannover Prof. Dr. M. Rimpler Gmbh",
    "wof:placetype":"venue"
},
  "geometry": {"coordinates":[9.7498083115,52.5253334045],"type":"Point"}
}