{
  "type": "Feature",
  "properties": {
    "iso:country":"DE",
    "sg:address":"Blochmattenstr. 8",
    "sg:city":"Teningen",
    "sg:phone":"+49 7641/1277",
    "sg:postcode":"79331",
    "sg:province":"Baden-W\u00fcrttemberg",
    "wof:name":"Haas Rolladen Gmbh",
    "wof:placetype":"venue"
},
  "geometry": {"coordinates":[7.810763,48.135201],"type":"Point"}
}