{
  "type": "Feature",
  "properties": {
    "iso:country":"DE",
    "sg:address":"Stadtlohner Str. 45",
    "sg:city":"Ahaus",
    "sg:phone":"+49 2561/98507",
    "sg:postcode":"48683",
    "sg:province":"Nordrhein-Westfalen",
    "wof:name":"Ostendorf Und Br\u00f6skamp Rechtsanw\u00e4ltinnen",
    "wof:placetype":"venue"
},
  "geometry": {"coordinates":[6.9763031006,52.0665588379],"type":"Point"}
}