{
  "type": "Feature",
  "properties": {
    "iso:country":"DE",
    "sg:address":"Wietbrede 31",
    "sg:city":"L\u00f6hne",
    "sg:phone":"+49 5732/71787",
    "sg:postcode":"32584",
    "sg:province":"Nordrhein-Westfalen",
    "wof:name":"Schulverein Mennigh\u00fcffen-ost Karl-heinz Bernsmeier",
    "wof:placetype":"venue"
},
  "geometry": {"coordinates":[8.7327709198,52.2177352905],"type":"Point"}
}