{
  "type": "Feature",
  "properties": {
    "iso:country":"DE",
    "sg:address":"Melanchthonstr. 72",
    "sg:city":"Bretten",
    "sg:phone":"+49 7252/7171",
    "sg:postcode":"75015",
    "sg:province":"Baden-W\u00fcrttemberg",
    "wof:name":"Willi Zimmermann",
    "wof:placetype":"venue"
},
  "geometry": {"coordinates":[8.701652,49.037952],"type":"Point"}
}