{
  "type": "Feature",
  "properties": {
    "iso:country":"DE",
    "sg:address":"Am Park 4",
    "sg:city":"Oranienburg",
    "sg:phone":"+49 3301/703252",
    "sg:postcode":"16515",
    "sg:province":"Brandenburg",
    "wof:name":"Tks Transport Und Handels Gmbh",
    "wof:placetype":"venue"
},
  "geometry": {"coordinates":[13.2347183228,52.773563385],"type":"Point"}
}