{
  "type": "Feature",
  "properties": {
    "iso:country":"DE",
    "sg:address":"Clarissenstr. 12",
    "sg:city":"Korschenbroich",
    "sg:postcode":"41352",
    "sg:province":"Nordrhein-Westfalen",
    "wof:name":"Project-consulting Heine E. K.",
    "wof:placetype":"venue"
},
  "geometry": {"coordinates":[6.5972299576,51.1617965698],"type":"Point"}
}