{
  "type": "Feature",
  "properties": {
    "iso:country":"DE",
    "sg:address":"Annenstrasse 19",
    "sg:city":"L\u00fcdinghausen",
    "sg:phone":"+49 2591/949349",
    "sg:postcode":"59348",
    "sg:province":"Nordrhein-Westfalen",
    "wof:name":"Irgel-zimmermann",
    "wof:placetype":"venue"
},
  "geometry": {"coordinates":[7.447197,51.754616],"type":"Point"}
}