{
  "type": "Feature",
  "properties": {
    "iso:country":"DE",
    "sg:address":"Vilshofener Str. 27",
    "sg:city":"Ortenburg",
    "sg:phone":"+49 8542/401",
    "sg:postcode":"94496",
    "sg:province":"Bayern",
    "wof:name":"Franz \u00d6ller",
    "wof:placetype":"venue"
},
  "geometry": {"coordinates":[13.2216396332,48.5496406555],"type":"Point"}
}