{
  "type": "Feature",
  "properties": {
    "iso:country":"DE",
    "sg:address":"Leipziger Str. 42",
    "sg:city":"Frankfurt",
    "sg:phone":"+49 69/777273",
    "sg:postcode":"60487",
    "sg:province":"Hessen",
    "wof:name":"Ingeborg Koller",
    "wof:placetype":"venue"
},
  "geometry": {"coordinates":[8.6471920013,50.1221199036],"type":"Point"}
}