{
  "type": "Feature",
  "properties": {
    "iso:country":"DE",
    "sg:address":"Berliner Str. 47",
    "sg:city":"Seligenstadt",
    "sg:postcode":"63500",
    "sg:province":"Hessen",
    "wof:name":"Express Uysal Transporte Inh. Ali Uysal",
    "wof:placetype":"venue"
},
  "geometry": {"coordinates":[8.9702415466,50.0544509888],"type":"Point"}
}