{
  "type": "Feature",
  "properties": {
    "iso:country":"DE",
    "sg:address":"Schlo\u00dfstr. 66",
    "sg:city":"Bergisch Gladbach",
    "sg:phone":"+49 2204/584566",
    "sg:postcode":"51429",
    "sg:province":"Nordrhein-Westfalen",
    "wof:name":"Lenges & Schwartner Gbr",
    "wof:placetype":"venue"
},
  "geometry": {"coordinates":[7.1607508659,50.9651985168],"type":"Point"}
}