{
  "type": "Feature",
  "properties": {
    "iso:country":"DE",
    "sg:address":"Stuttgarter Str. 52",
    "sg:city":"Geislingen",
    "sg:phone":"+49 7331/63551",
    "sg:postcode":"73312",
    "sg:province":"Baden-W\u00fcrttemberg",
    "wof:name":"Alfred Maurer",
    "wof:placetype":"venue"
},
  "geometry": {"coordinates":[9.829671,48.6245],"type":"Point"}
}