{
  "type": "Feature",
  "properties": {
    "iso:country":"DE",
    "sg:address":"Moselstr. 24",
    "sg:city":"Mannheim",
    "sg:phone":"+49 621/332148",
    "sg:postcode":"68167",
    "sg:province":"Baden-W\u00fcrttemberg",
    "wof:name":"Alfred Ebert Haus- Und K\u00fcchenger\u00e4te",
    "wof:placetype":"venue"
},
  "geometry": {"coordinates":[8.4845476151,49.4993438721],"type":"Point"}
}