{
  "type": "Feature",
  "properties": {
    "iso:country":"DE",
    "sg:address":"K\u00f6lnstr. 208",
    "sg:city":"Br\u00fchl",
    "sg:phone":"+49 2232/945000",
    "sg:postcode":"50321",
    "sg:province":"Nordrhein-Westfalen",
    "wof:name":"Engelbert Fu\u00dfel Gesell- Schaft Mit Beschr\u00e4nkter",
    "wof:placetype":"venue"
},
  "geometry": {"coordinates":[6.9121389389,50.8410873413],"type":"Point"}
}