{
  "type": "Feature",
  "properties": {
    "iso:country":"DE",
    "sg:address":"Schulstr 22a",
    "sg:city":"N\u00fcsttal",
    "sg:phone":"+49 6684/550",
    "sg:postcode":"36167",
    "sg:province":"Hessen",
    "wof:name":"Rh\u00f6n-holz",
    "wof:placetype":"venue"
},
  "geometry": {"coordinates":[9.848638,50.630295],"type":"Point"}
}