{
  "type": "Feature",
  "properties": {
    "iso:country":"DE",
    "sg:address":"Lindenstr. 20",
    "sg:city":"Lauterbach",
    "sg:phone":"+49 6641/2772",
    "sg:postcode":"36341",
    "sg:province":"Hessen",
    "wof:name":"Cemal Sadet",
    "wof:placetype":"venue"
},
  "geometry": {"coordinates":[9.399345,50.636532],"type":"Point"}
}