{
  "type": "Feature",
  "properties": {
    "iso:country":"DE",
    "sg:address":"Markt 5",
    "sg:city":"Teuchern",
    "sg:phone":"+49 34443/20426",
    "sg:postcode":"06682",
    "sg:province":"Sachsen-Anhalt",
    "wof:name":"Bernd Glauner Ingenieur",
    "wof:placetype":"venue"
},
  "geometry": {"coordinates":[12.0214624405,51.1192207336],"type":"Point"}
}