{
  "type": "Feature",
  "properties": {
    "iso:country":"DE",
    "sg:address":"Manteuffelstr. 64",
    "sg:city":"Berlin",
    "sg:phone":"+49 30/7516073",
    "sg:postcode":"12103",
    "sg:province":"Berlin",
    "wof:name":"Burkhard Palik",
    "wof:placetype":"venue"
},
  "geometry": {"coordinates":[13.377774,52.464375],"type":"Point"}
}