{
  "type": "Feature",
  "properties": {
    "iso:country":"DE",
    "sg:address":"Heidelberger Str. 5",
    "sg:city":"Sandhausen",
    "sg:phone":"+49 6224/2407",
    "sg:postcode":"69207",
    "sg:province":"Baden-W\u00fcrttemberg",
    "wof:name":"Blumen Bernhard Ohg",
    "wof:placetype":"venue"
},
  "geometry": {"coordinates":[8.658466,49.344486],"type":"Point"}
}