{
  "type": "Feature",
  "properties": {
    "iso:country":"DE",
    "sg:address":"Wasserstr. 23",
    "sg:city":"Donaueschingen",
    "sg:phone":"+49 771/7878",
    "sg:postcode":"78166",
    "sg:province":"Baden-W\u00fcrttemberg",
    "wof:name":"Thomas Und Juliane Hartauer",
    "wof:placetype":"venue"
},
  "geometry": {"coordinates":[8.493786,47.951454],"type":"Point"}
}