{
  "type": "Feature",
  "properties": {
    "iso:country":"DE",
    "sg:address":"\u00c4pfingen",
    "sg:city":"Maselheim",
    "sg:phone":"+49 7356/1701",
    "sg:postcode":"88437",
    "sg:province":"Baden-W\u00fcrttemberg",
    "wof:name":"Mehrzweckhalle",
    "wof:placetype":"venue"
},
  "geometry": {"coordinates":[9.862882,48.156219],"type":"Point"}
}