{
  "type": "Feature",
  "properties": {
    "iso:country":"DE",
    "sg:address":"K\u00f6nigsteiner Str. 192",
    "sg:city":"Bad Soden",
    "sg:phone":"+49 6196/28950",
    "sg:postcode":"65812",
    "sg:province":"Hessen",
    "wof:name":"Werkzeugbau Und Metall- Waren A. Reul Gesellschaft",
    "wof:placetype":"venue"
},
  "geometry": {"coordinates":[8.4890365601,50.1574668884],"type":"Point"}
}