{
  "type": "Feature",
  "properties": {
    "iso:country":"DE",
    "sg:address":"Wolbecker Str. 42",
    "sg:city":"Sendenhorst",
    "sg:phone":"+49 2535/305",
    "sg:postcode":"48324",
    "sg:province":"Nordrhein-Westfalen",
    "wof:name":"Franz Hankamp",
    "wof:placetype":"venue"
},
  "geometry": {"coordinates":[7.736359,51.872269],"type":"Point"}
}