{
  "type": "Feature",
  "properties": {
    "iso:country":"DE",
    "sg:address":"Weedegasse 13",
    "sg:city":"Ober-Fl\u00f6rsheim",
    "sg:phone":"+49 6735/314",
    "sg:postcode":"55234",
    "sg:province":"Rheinland-Pfalz",
    "wof:name":"Manfred Und Erhard Stauff",
    "wof:placetype":"venue"
},
  "geometry": {"coordinates":[8.1571493149,49.6845779419],"type":"Point"}
}