{
  "type": "Feature",
  "properties": {
    "iso:country":"DE",
    "sg:address":"S\u00fcderende 5",
    "sg:city":"Oederquart",
    "sg:phone":"+49 4779/8233",
    "sg:postcode":"21734",
    "sg:province":"Niedersachsen",
    "wof:name":"Ev. Pfarramt Oederquart",
    "wof:placetype":"venue"
},
  "geometry": {"coordinates":[9.238079071,53.8037528992],"type":"Point"}
}