{
  "type": "Feature",
  "properties": {
    "iso:country":"DE",
    "sg:address":"Karl-Kunger-Str. 69",
    "sg:city":"Berlin",
    "sg:phone":"+49 30/5336167",
    "sg:postcode":"12435",
    "sg:province":"Berlin",
    "wof:name":"Treptower Klause",
    "wof:placetype":"venue"
},
  "geometry": {"coordinates":[13.4452676773,52.4926567078],"type":"Point"}
}