{
  "type": "Feature",
  "properties": {
    "iso:country":"DE",
    "sg:address":"Altenburger Str. 44",
    "sg:city":"Waldenburg",
    "sg:phone":"+49 37608/22717",
    "sg:postcode":"08396",
    "sg:province":"Sachsen",
    "wof:name":"H. G\u00e4nsehals",
    "wof:placetype":"venue"
},
  "geometry": {"coordinates":[12.5985,50.875889],"type":"Point"}
}