{
  "type": "Feature",
  "properties": {
    "iso:country":"DE",
    "sg:address":"Lauchst\u00e4dter Str. 21",
    "sg:city":"Delitz",
    "sg:phone":"+49 345/6130276",
    "sg:postcode":"06246",
    "sg:province":"Sachsen-Anhalt",
    "wof:name":"Gasthof Zum Berg",
    "wof:placetype":"venue"
},
  "geometry": {"coordinates":[11.8459596634,51.38904953],"type":"Point"}
}