{
  "type": "Feature",
  "properties": {
    "iso:country":"DE",
    "sg:address":"In der Gasse 15",
    "sg:city":"Frankenau",
    "sg:phone":"+49 6455/8066",
    "sg:postcode":"35110",
    "sg:province":"Hessen",
    "wof:name":"H. Menkel",
    "wof:placetype":"venue"
},
  "geometry": {"coordinates":[8.887187,51.081032],"type":"Point"}
}