{
  "type": "Feature",
  "properties": {
    "iso:country":"DE",
    "sg:address":"Mielenforster Str. 6",
    "sg:city":"K\u00f6ln",
    "sg:phone":"+49 221/6803422",
    "sg:postcode":"51069",
    "sg:province":"Nordrhein-Westfalen",
    "wof:name":"Manfred Van Issem",
    "wof:placetype":"venue"
},
  "geometry": {"coordinates":[7.072308,50.962482],"type":"Point"}
}