{
  "type": "Feature",
  "properties": {
    "iso:country":"DE",
    "sg:address":"Christophstr. 7",
    "sg:city":"K\u00f6ln",
    "sg:phone":"+49 221/9131040",
    "sg:postcode":"50670",
    "sg:province":"Nordrhein-Westfalen",
    "wof:name":"Gzg Gesundheitszentrum An Der Kirche St. Gereon Gmbh",
    "wof:placetype":"venue"
},
  "geometry": {"coordinates":[6.9456019402,50.9436225891],"type":"Point"}
}