{
  "type": "Feature",
  "properties": {
    "iso:country":"DE",
    "sg:address":"Friedrich-Krupp-Str. 14",
    "sg:city":"Langenfeld",
    "sg:phone":"+49 2173/988588",
    "sg:postcode":"40764",
    "sg:province":"Nordrhein-Westfalen",
    "wof:name":"Suttons International Gmbh",
    "wof:placetype":"venue"
},
  "geometry": {"coordinates":[6.9616980553,51.1387481689],"type":"Point"}
}