{
  "type": "Feature",
  "properties": {
    "iso:country":"DE",
    "sg:address":"Schlo\u00dfstr. 12",
    "sg:city":"Falkenstein",
    "sg:phone":"+49 3745/5971",
    "sg:postcode":"08223",
    "sg:province":"Sachsen",
    "wof:name":"Ihr Platz Drogeriemarkt",
    "wof:placetype":"venue"
},
  "geometry": {"coordinates":[12.36818,50.47559],"type":"Point"}
}