{
  "type": "Feature",
  "properties": {
    "iso:country":"DE",
    "sg:address":"Prenzlauer Chaussee 5",
    "sg:city":"Woldegk",
    "sg:phone":"+49 3963/210590",
    "sg:postcode":"17348",
    "sg:province":"Mecklenburg-Vorpommern",
    "wof:name":"Thomas Gall",
    "wof:placetype":"venue"
},
  "geometry": {"coordinates":[13.5991697311,53.4628486633],"type":"Point"}
}