{
  "type": "Feature",
  "properties": {
    "iso:country":"DE",
    "sg:address":"Wei\u00dfenfelser Str. 16",
    "sg:city":"Thei\u00dfen",
    "sg:phone":"+49 3441/680319",
    "sg:postcode":"06727",
    "sg:province":"Sachsen-Anhalt",
    "wof:name":"Borde Gmbh",
    "wof:placetype":"venue"
},
  "geometry": {"coordinates":[12.104658,51.091812],"type":"Point"}
}