{
  "type": "Feature",
  "properties": {
    "iso:country":"DE",
    "sg:address":"Carl-Maria-von-Weber-Str. 14",
    "sg:city":"Worms",
    "sg:phone":"+49 6241/78039",
    "sg:postcode":"67549",
    "sg:province":"Rheinland-Pfalz",
    "wof:name":"Dr. Horst H. Knuth Rechtsanwalt",
    "wof:placetype":"venue"
},
  "geometry": {"coordinates":[8.3305330276,49.6336174011],"type":"Point"}
}