{
  "type": "Feature",
  "properties": {
    "iso:country":"DE",
    "sg:address":"Am K\u00f6chhof 39",
    "sg:city":"K\u00f6ln",
    "sg:phone":"+49 221/722614",
    "sg:postcode":"50765",
    "sg:province":"Nordrhein-Westfalen",
    "wof:name":"Evers Bauunternehmung Gmbh Bauunternehmen",
    "wof:placetype":"venue"
},
  "geometry": {"coordinates":[6.854303,51.002773],"type":"Point"}
}