{
  "type": "Feature",
  "properties": {
    "iso:country":"DE",
    "sg:address":"Marienstr. 12",
    "sg:city":"Stuttgart",
    "sg:phone":"+49 711/618819",
    "sg:postcode":"70178",
    "sg:province":"Baden-W\u00fcrttemberg",
    "wof:name":"H. Zimmermann",
    "wof:placetype":"venue"
},
  "geometry": {"coordinates":[9.173352,48.773602],"type":"Point"}
}