{
  "type": "Feature",
  "properties": {
    "iso:country":"DE",
    "sg:address":"Am Markt",
    "sg:city":"Nortorf",
    "sg:phone":"+49 4392/4393",
    "sg:postcode":"24589",
    "sg:province":"Schleswig-Holstein",
    "wof:name":"Moritz-grill",
    "wof:placetype":"venue"
},
  "geometry": {"coordinates":[9.8558397293,54.1691589355],"type":"Point"}
}