{
  "type": "Feature",
  "properties": {
    "iso:country":"DE",
    "sg:address":"Im Oberen Felde 11",
    "sg:city":"Bad M\u00fcnder",
    "sg:phone":"+49 5042/2523",
    "sg:postcode":"31848",
    "sg:province":"Niedersachsen",
    "wof:name":"Walter Volker",
    "wof:placetype":"venue"
},
  "geometry": {"coordinates":[9.46055,52.217773],"type":"Point"}
}