{
  "type": "Feature",
  "properties": {
    "iso:country":"DE",
    "sg:address":"Auf der H\u00f6he 3",
    "sg:city":"Oberstdorf",
    "sg:phone":"+49 8322/3838",
    "sg:postcode":"87561",
    "sg:province":"Bayern",
    "wof:name":"Ferdinand Brutscher Gmbh & Co. Kg",
    "wof:placetype":"venue"
},
  "geometry": {"coordinates":[10.2781095505,47.3965034485],"type":"Point"}
}