{
  "type": "Feature",
  "properties": {
    "iso:country":"DE",
    "sg:address":"Spaldingstr. 210",
    "sg:city":"Hamburg",
    "sg:phone":"+49 40/23809301",
    "sg:postcode":"20097",
    "sg:province":"Hamburg",
    "wof:name":"Stamms Courier Gmbh",
    "wof:placetype":"venue"
},
  "geometry": {"coordinates":[10.0249595642,53.5514945984],"type":"Point"}
}