{
  "type": "Feature",
  "properties": {
    "iso:country":"DE",
    "sg:address":"Arnold-Janssen-Str.",
    "sg:city":"Sankt Augustin",
    "sg:phone":"+49 2241/29013",
    "sg:postcode":"53757",
    "sg:province":"Nordrhein-Westfalen",
    "wof:name":"Frei- Und Hallenbad",
    "wof:placetype":"venue"
},
  "geometry": {"coordinates":[7.1789898872,50.7750434875],"type":"Point"}
}