{
  "type": "Feature",
  "properties": {
    "iso:country":"DE",
    "sg:address":"Barsb\u00fctteler Weg 30",
    "sg:city":"Oststeinbek",
    "sg:phone":"+49 40/7136174",
    "sg:postcode":"22113",
    "sg:province":"Schleswig-Holstein",
    "wof:name":"Casa Ricardo",
    "wof:placetype":"venue"
},
  "geometry": {"coordinates":[10.1650629044,53.5473976135],"type":"Point"}
}