{
  "type": "Feature",
  "properties": {
    "iso:country":"DE",
    "sg:address":"Am H\u00f6hinger Felsen 24",
    "sg:city":"Epfendorf",
    "sg:phone":"+49 7404/551",
    "sg:postcode":"78736",
    "sg:province":"Baden-W\u00fcrttemberg",
    "wof:name":"Franz Mayer",
    "wof:placetype":"venue"
},
  "geometry": {"coordinates":[8.6000385284,48.2546005249],"type":"Point"}
}