{
  "type": "Feature",
  "properties": {
    "iso:country":"DE",
    "sg:address":"Leopoldstr.4",
    "sg:city":"Chemnitz",
    "sg:phone":"+49 371",
    "sg:postcode":"09113",
    "sg:province":"Sachsen",
    "wof:name":"Frank Sch\u00f6nfeld Kurierdienst",
    "wof:placetype":"venue"
},
  "geometry": {"coordinates":[12.899732,50.842678],"type":"Point"}
}