{
  "type": "Feature",
  "properties": {
    "iso:country":"DE",
    "sg:address":"Angerstr. 1",
    "sg:city":"Rattelsdorf",
    "sg:phone":"+49 9547/8612",
    "sg:postcode":"96179",
    "sg:province":"Bayern",
    "wof:name":"Martin Kaiser Kg",
    "wof:placetype":"venue"
},
  "geometry": {"coordinates":[10.8921375275,50.016708374],"type":"Point"}
}