{
  "type": "Feature",
  "properties": {
    "iso:country":"DE",
    "sg:address":"J\u00fcdtstr. 13",
    "sg:city":"Ansbach",
    "sg:phone":"+49 981/86391",
    "sg:postcode":"91522",
    "sg:province":"Bayern",
    "wof:name":"E. M. Gebhardt Steuerberaterin",
    "wof:placetype":"venue"
},
  "geometry": {"coordinates":[10.5737476349,49.3084983826],"type":"Point"}
}