{
  "type": "Feature",
  "properties": {
    "iso:country":"DE",
    "sg:address":"Neuer Wall 75",
    "sg:city":"Hamburg",
    "sg:phone":"+49 40/372323",
    "sg:postcode":"20354",
    "sg:province":"Hamburg",
    "wof:name":"Dr. Adam Kottwitz Notar",
    "wof:placetype":"venue"
},
  "geometry": {"coordinates":[9.9868602753,53.5499191284],"type":"Point"}
}