{
  "type": "Feature",
  "properties": {
    "iso:country":"DE",
    "sg:address":"Untermarkt 45",
    "sg:city":"Murnau",
    "sg:phone":"+49 8841/40015",
    "sg:postcode":"82418",
    "sg:province":"Bayern",
    "wof:name":"Markt-apotheke",
    "wof:placetype":"venue"
},
  "geometry": {"coordinates":[11.201638,47.675308],"type":"Point"}
}