{
  "type": "Feature",
  "properties": {
    "iso:country":"DE",
    "sg:address":"Kauflandener Str. 9",
    "sg:city":"Triftern",
    "sg:phone":"+49 8562/704",
    "sg:postcode":"84371",
    "sg:province":"Bayern",
    "wof:name":"Gastwirtschaft Fritz Zi\u00dfler",
    "wof:placetype":"venue"
},
  "geometry": {"coordinates":[13.0283641815,48.4108428955],"type":"Point"}
}