{
  "type": "Feature",
  "properties": {
    "iso:country":"DE",
    "sg:address":"Waldfrieden 58",
    "sg:city":"Mannheim",
    "sg:phone":"+49 621/747852",
    "sg:postcode":"68305",
    "sg:province":"Baden-W\u00fcrttemberg",
    "wof:name":"Kunst Und Verlag Peter Holme",
    "wof:placetype":"venue"
},
  "geometry": {"coordinates":[8.4948120117,49.5311431885],"type":"Point"}
}