{
  "type": "Feature",
  "properties": {
    "iso:country":"DE",
    "sg:address":"Auf der Lauge 10",
    "sg:city":"Neuenkirchen",
    "sg:phone":"+49 5973/94470",
    "sg:postcode":"48485",
    "sg:province":"Nordrhein-Westfalen",
    "wof:name":"S 4 Fashion Partner Gmbh",
    "wof:placetype":"venue"
},
  "geometry": {"coordinates":[7.365856,52.243317],"type":"Point"}
}