{
  "type": "Feature",
  "properties": {
    "iso:country":"DE",
    "sg:address":"Haigerlocher Str. 5",
    "sg:city":"Rangendingen",
    "sg:phone":"+49 7471/82334",
    "sg:postcode":"72414",
    "sg:province":"Baden-W\u00fcrttemberg",
    "wof:name":"R\u00f6\u00dfle",
    "wof:placetype":"venue"
},
  "geometry": {"coordinates":[8.8869714737,48.3806800842],"type":"Point"}
}