{
  "type": "Feature",
  "properties": {
    "iso:country":"DE",
    "sg:address":"Clemensstr. 22",
    "sg:city":"Kerpen",
    "sg:phone":"+49 2273/2521",
    "sg:postcode":"50169",
    "sg:province":"Nordrhein-Westfalen",
    "wof:name":"Pilot Projekt- Und Qualit\u00e4tsmanagement Gmbh",
    "wof:placetype":"venue"
},
  "geometry": {"coordinates":[6.7152290344,50.9104003906],"type":"Point"}
}