{
  "type": "Feature",
  "properties": {
    "iso:country":"DE",
    "sg:address":"Bergstr. 4",
    "sg:city":"Hardthausen",
    "sg:phone":"+49 7139/1366",
    "sg:postcode":"74239",
    "sg:province":"Baden-W\u00fcrttemberg",
    "wof:name":"Ev. Pfarramt Gochsen",
    "wof:placetype":"venue"
},
  "geometry": {"coordinates":[9.3657932281,49.2423629761],"type":"Point"}
}