{
  "type": "Feature",
  "properties": {
    "iso:country":"DE",
    "sg:address":"Hussengutstr. 82",
    "sg:city":"Bayreuth",
    "sg:phone":"+49 921/27145",
    "sg:postcode":"95445",
    "sg:province":"Bayern",
    "wof:name":"Karlheinz Frank",
    "wof:placetype":"venue"
},
  "geometry": {"coordinates":[11.589341,49.964996],"type":"Point"}
}