{
  "type": "Feature",
  "properties": {
    "iso:country":"DE",
    "sg:address":"Zehlendorfer Weg 20",
    "sg:city":"Weitendorf",
    "sg:phone":"+49 38454/20316",
    "sg:postcode":"18299",
    "sg:province":"Mecklenburg-Vorpommern",
    "wof:name":"D. J\u00fcdes",
    "wof:placetype":"venue"
},
  "geometry": {"coordinates":[12.3469247818,53.9287796021],"type":"Point"}
}