{
  "type": "Feature",
  "properties": {
    "iso:country":"DE",
    "sg:address":"Rahlstedter Str. 150h",
    "sg:city":"Hamburg",
    "sg:phone":"+49 40/6776265",
    "sg:postcode":"22143",
    "sg:province":"Hamburg",
    "wof:name":"Spielschiff",
    "wof:placetype":"venue"
},
  "geometry": {"coordinates":[10.1598968506,53.6040115356],"type":"Point"}
}