{
  "type": "Feature",
  "properties": {
    "iso:country":"DE",
    "sg:address":"Schweriner Str. 3",
    "sg:city":"Varel",
    "sg:phone":"+49 4451/5996",
    "sg:postcode":"26316",
    "sg:province":"Niedersachsen",
    "wof:name":"E. Henke & D. Brunken Bauunternehmen Gmbh",
    "wof:placetype":"venue"
},
  "geometry": {"coordinates":[8.137228,53.40554],"type":"Point"}
}