{
  "type": "Feature",
  "properties": {
    "iso:country":"DE",
    "sg:address":"M\u00f6rkenstr. 3",
    "sg:city":"Hamburg",
    "sg:phone":"+49 40/3806376",
    "sg:postcode":"22767",
    "sg:province":"Hamburg",
    "wof:name":"Tan Trading Gmbh",
    "wof:placetype":"venue"
},
  "geometry": {"coordinates":[9.947881,53.54895],"type":"Point"}
}