{
  "type": "Feature",
  "properties": {
    "iso:country":"DE",
    "sg:address":"L\u00e4mmerweide 4",
    "sg:city":"F\u00fcrstenfeldbruck",
    "sg:phone":"+49 8141/16421",
    "sg:postcode":"82256",
    "sg:province":"Bayern",
    "wof:name":"Gottfried Grimm Rechtsanwalt",
    "wof:placetype":"venue"
},
  "geometry": {"coordinates":[11.2333803177,48.167552948],"type":"Point"}
}