{
  "type": "Feature",
  "properties": {
    "iso:country":"DE",
    "sg:address":"Karlstr. 7",
    "sg:city":"Ravensburg",
    "sg:phone":"+49 751/32084",
    "sg:postcode":"88212",
    "sg:province":"Baden-W\u00fcrttemberg",
    "wof:name":"Herbert Und Volker Merz Steuerberater",
    "wof:placetype":"venue"
},
  "geometry": {"coordinates":[9.6088161469,47.7823982239],"type":"Point"}
}