{
  "type": "Feature",
  "properties": {
    "iso:country":"DE",
    "sg:address":"Bahnhofstr. 19",
    "sg:city":"Dahlenburg",
    "sg:phone":"+49 5851/404",
    "sg:postcode":"21368",
    "sg:province":"Niedersachsen",
    "wof:name":"Wilh. Schuart Steinmetzbetrieb",
    "wof:placetype":"venue"
},
  "geometry": {"coordinates":[10.7358446121,53.1863555908],"type":"Point"}
}