{
  "type": "Feature",
  "properties": {
    "iso:country":"DE",
    "sg:address":"Braunsh\u00e4user Str. 8",
    "sg:city":"Frankenberg",
    "sg:phone":"+49 2984/655",
    "sg:postcode":"35066",
    "sg:province":"Hessen",
    "wof:name":"Haus M\u00fcller",
    "wof:placetype":"venue"
},
  "geometry": {"coordinates":[8.7086200714,51.1057319641],"type":"Point"}
}