{
  "type": "Feature",
  "properties": {
    "iso:country":"DE",
    "sg:address":"Hainbuchenstr. 10",
    "sg:city":"Ingolstadt",
    "sg:phone":"+49 841/370317",
    "sg:postcode":"85055",
    "sg:province":"Bayern",
    "wof:name":"Werner Neumayer",
    "wof:placetype":"venue"
},
  "geometry": {"coordinates":[11.4855833054,48.7716217041],"type":"Point"}
}