{
  "type": "Feature",
  "properties": {
    "iso:country":"DE",
    "sg:address":"Rudolf-Breitscheid-Str. 20",
    "sg:city":"Zeitz",
    "sg:phone":"+49 3441/710306",
    "sg:postcode":"06712",
    "sg:province":"Sachsen-Anhalt",
    "wof:name":"M\u00fcller & Wolff Gmbh",
    "wof:placetype":"venue"
},
  "geometry": {"coordinates":[12.147242,51.049198],"type":"Point"}
}