{
  "type": "Feature",
  "properties": {
    "iso:country":"DE",
    "sg:address":"Stromkaje",
    "sg:city":"Bremerhaven",
    "sg:phone":"+49 471/413169",
    "sg:postcode":"27568",
    "sg:province":"Bremen",
    "wof:name":"K. Eger Gmbh",
    "wof:placetype":"venue"
},
  "geometry": {"coordinates":[8.5820817947,53.5442886353],"type":"Point"}
}