{
  "type": "Feature",
  "properties": {
    "iso:country":"DE",
    "sg:address":"Schlesische Str. 5",
    "sg:city":"Hohenhameln",
    "sg:phone":"+49 5128/5427",
    "sg:postcode":"31249",
    "sg:province":"Niedersachsen",
    "wof:name":"P. Dierschke",
    "wof:placetype":"venue"
},
  "geometry": {"coordinates":[10.075267,52.258144],"type":"Point"}
}