{
  "type": "Feature",
  "properties": {
    "iso:country":"DE",
    "sg:address":"B\u00e4ckerstr 14",
    "sg:city":"Marne",
    "sg:phone":"+49 4851/9569830",
    "sg:postcode":"25709",
    "sg:province":"Schleswig-Holstein",
    "wof:name":"Optima Printsystems Ag",
    "wof:placetype":"venue"
},
  "geometry": {"coordinates":[9.0097551346,53.951385498],"type":"Point"}
}