{
  "type": "Feature",
  "properties": {
    "iso:country":"DE",
    "sg:address":"S\u00f6deler Str. 25",
    "sg:city":"W\u00f6lfersheim",
    "sg:phone":"+49 6036/5098",
    "sg:postcode":"61200",
    "sg:province":"Hessen",
    "wof:name":"Reinhold Weber",
    "wof:placetype":"venue"
},
  "geometry": {"coordinates":[8.8071813583,50.3957366943],"type":"Point"}
}