{
  "type": "Feature",
  "properties": {
    "iso:country":"DE",
    "sg:address":"Kubaldallee 2",
    "sg:city":"Neustadt",
    "sg:phone":"+49 5032/8960",
    "sg:postcode":"31535",
    "sg:province":"Niedersachsen",
    "wof:name":"Kubald-service Gmbh",
    "wof:placetype":"venue"
},
  "geometry": {"coordinates":[9.4634180069,52.4675979614],"type":"Point"}
}