{
  "type": "Feature",
  "properties": {
    "iso:country":"DE",
    "sg:address":"Kirchstr. 11",
    "sg:city":"Herborn",
    "sg:phone":"+49 2772/52829",
    "sg:postcode":"35745",
    "sg:province":"Hessen",
    "wof:name":"Manfred Hohlfeld",
    "wof:placetype":"venue"
},
  "geometry": {"coordinates":[8.300909,50.68214],"type":"Point"}
}