{
  "type": "Feature",
  "properties": {
    "iso:country":"DE",
    "sg:address":"Saarstr. 23",
    "sg:city":"Ensdorf",
    "sg:phone":"+49 6831/951140",
    "sg:postcode":"66806",
    "sg:province":"Saarland",
    "wof:name":"Werner Loris Gmbh",
    "wof:placetype":"venue"
},
  "geometry": {"coordinates":[6.775897,49.305969],"type":"Point"}
}