{
  "type": "Feature",
  "properties": {
    "iso:country":"DE",
    "sg:address":"Maxim-Gorki-Str. 57 a",
    "sg:city":"Kyritz",
    "sg:phone":"+49 33971/71217",
    "sg:postcode":"16866",
    "sg:province":"Brandenburg",
    "wof:name":"Manfred Streege",
    "wof:placetype":"venue"
},
  "geometry": {"coordinates":[12.3976325989,52.9446716309],"type":"Point"}
}