{
  "type": "Feature",
  "properties": {
    "iso:country":"DE",
    "sg:address":"Rechbergstr. 67",
    "sg:city":"Notzingen",
    "sg:phone":"+49 7021/45719",
    "sg:postcode":"73274",
    "sg:province":"Baden-W\u00fcrttemberg",
    "wof:name":"K. Schur Kohlenhandlung",
    "wof:placetype":"venue"
},
  "geometry": {"coordinates":[9.472713,48.675316],"type":"Point"}
}