{
  "type": "Feature",
  "properties": {
    "iso:country":"DE",
    "sg:address":"Leopoldstr. 48",
    "sg:city":"M\u00fcnchen",
    "sg:phone":"+49 89/33007980",
    "sg:postcode":"80802",
    "sg:province":"Bayern",
    "wof:name":"Oertle Hausverwaltung E. K. Inh. Monika Amann",
    "wof:placetype":"venue"
},
  "geometry": {"coordinates":[11.5848493576,48.1576843262],"type":"Point"}
}