{
  "type": "Feature",
  "properties": {
    "iso:country":"DE",
    "sg:address":"Riedweg 1",
    "sg:city":"Ursberg",
    "sg:phone":"+49 8281/1390",
    "sg:postcode":"86513",
    "sg:province":"Bayern",
    "wof:name":"Johann B\u00f6ck",
    "wof:placetype":"venue"
},
  "geometry": {"coordinates":[10.4348335266,48.2762794495],"type":"Point"}
}