{
  "type": "Feature",
  "properties": {
    "iso:country":"DE",
    "sg:address":"Mendelweg 11",
    "sg:city":"Marktredwitz",
    "sg:phone":"+49 9231/81126",
    "sg:postcode":"95615",
    "sg:province":"Bayern",
    "wof:name":"Reinhard Striegl Steuerberater",
    "wof:placetype":"venue"
},
  "geometry": {"coordinates":[12.0644302368,50.0076293945],"type":"Point"}
}