{
  "type": "Feature",
  "properties": {
    "iso:country":"DE",
    "sg:address":"Schlo\u00dfhof 2",
    "sg:city":"Weidhausen",
    "sg:phone":"+49 9562/981111",
    "sg:postcode":"96279",
    "sg:province":"Bayern",
    "wof:name":"H. M\u00e4dl",
    "wof:placetype":"venue"
},
  "geometry": {"coordinates":[11.139657,50.202396],"type":"Point"}
}