{
  "type": "Feature",
  "properties": {
    "iso:country":"DE",
    "sg:address":"St.-Agatha-Platz 8",
    "sg:city":"Everswinkel",
    "sg:phone":"+49 2582/7001",
    "sg:postcode":"48351",
    "sg:province":"Nordrhein-Westfalen",
    "wof:name":"Hotel-restaurant Landhaus Bisping",
    "wof:placetype":"venue"
},
  "geometry": {"coordinates":[7.8094968796,51.9130439758],"type":"Point"}
}