{
  "type": "Feature",
  "properties": {
    "iso:country":"DE",
    "sg:address":"Homberger Str. 73",
    "sg:city":"Moers",
    "sg:phone":"+49 2841/16757",
    "sg:postcode":"47441",
    "sg:province":"Nordrhein-Westfalen",
    "wof:name":"Ha Bo Video-filmverleih Gmbh",
    "wof:placetype":"venue"
},
  "geometry": {"coordinates":[6.6370930672,51.4502563477],"type":"Point"}
}