{
  "type": "Feature",
  "properties": {
    "iso:country":"DE",
    "sg:address":"Tilsiter Str. 6 d",
    "sg:city":"Lindhorst",
    "sg:phone":"+49 5725/5462",
    "sg:postcode":"31698",
    "sg:province":"Niedersachsen",
    "wof:name":"Giso Jungk",
    "wof:placetype":"venue"
},
  "geometry": {"coordinates":[9.2777366638,52.3610420227],"type":"Point"}
}