{
  "type": "Feature",
  "properties": {
    "iso:country":"DE",
    "sg:address":"Wilhelm-Theodor-R\u00f6mheld-Str. 8",
    "sg:city":"Mainz",
    "sg:postcode":"55130",
    "sg:province":"Rheinland-Pfalz",
    "wof:name":"Weinhaus-verwaltungsges. Mbh",
    "wof:placetype":"venue"
},
  "geometry": {"coordinates":[8.291015625,49.9792747498],"type":"Point"}
}