{
  "type": "Feature",
  "properties": {
    "iso:country":"DE",
    "sg:address":"Stra\u00df 33",
    "sg:city":"Ainring",
    "sg:phone":"+49 8654/2400",
    "sg:postcode":"83404",
    "sg:province":"Bayern",
    "wof:name":"H. Hasen\u00f6hrl",
    "wof:placetype":"venue"
},
  "geometry": {"coordinates":[12.8938846588,47.8379402161],"type":"Point"}
}