{
  "type": "Feature",
  "properties": {
    "iso:country":"DE",
    "sg:address":"Nottebohmstr 18",
    "sg:city":"L\u00fcdenscheid",
    "sg:phone":"+49 2351/80143",
    "sg:postcode":"58511",
    "sg:province":"Nordrhein-Westfalen",
    "wof:name":"Rentrop Gravuren U.formenbau Gmbh",
    "wof:placetype":"venue"
},
  "geometry": {"coordinates":[7.6598720551,51.2123069763],"type":"Point"}
}