{
  "type": "Feature",
  "properties": {
    "iso:country":"DE",
    "sg:address":"Herzog-Max-Str. 14",
    "sg:city":"Bamberg",
    "sg:phone":"+49 951/986260",
    "sg:postcode":"96047",
    "sg:province":"Bayern",
    "wof:name":"Firlus Und Kollegen Rechtsanw\u00e4lte",
    "wof:placetype":"venue"
},
  "geometry": {"coordinates":[10.8957138062,49.8904342651],"type":"Point"}
}