{
  "type": "Feature",
  "properties": {
    "iso:country":"DE",
    "sg:address":"An der Warmen Pader 5",
    "sg:city":"Paderborn",
    "sg:phone":"+49 5251/22411",
    "sg:postcode":"33098",
    "sg:province":"Nordrhein-Westfalen",
    "wof:name":"Bestattungen Albrecht",
    "wof:placetype":"venue"
},
  "geometry": {"coordinates":[8.749867,51.718723],"type":"Point"}
}