{
  "type": "Feature",
  "properties": {
    "iso:country":"DE",
    "sg:address":"Dammweg 22",
    "sg:city":"Sch\u00f6nebeck",
    "sg:postcode":"39218",
    "sg:province":"Sachsen-Anhalt",
    "wof:name":"St\u00e4dtischer Bauhof Sch\u00f6nebeck Elbe",
    "wof:placetype":"venue"
},
  "geometry": {"coordinates":[11.7502593994,52.0144462585],"type":"Point"}
}