{
  "type": "Feature",
  "properties": {
    "iso:country":"DE",
    "sg:address":"Viktoriastr. 4",
    "sg:city":"Betzdorf",
    "sg:phone":"+49 2741/22769",
    "sg:postcode":"57518",
    "sg:province":"Rheinland-Pfalz",
    "wof:name":"Paul Acher",
    "wof:placetype":"venue"
},
  "geometry": {"coordinates":[7.8730039597,50.7879562378],"type":"Point"}
}