{
  "type": "Feature",
  "properties": {
    "iso:country":"DE",
    "sg:address":"Liebigstr. 19",
    "sg:city":"Aurich",
    "sg:phone":"+49 4941/97400",
    "sg:postcode":"26607",
    "sg:province":"Niedersachsen",
    "wof:name":"Heinrich Kehrbach Gmbh Ausbildung",
    "wof:placetype":"venue"
},
  "geometry": {"coordinates":[7.49056,53.50703],"type":"Point"}
}