{
  "type": "Feature",
  "properties": {
    "iso:country":"DE",
    "sg:address":"Niederhofer Weg 2",
    "sg:city":"B\u00f6nen",
    "sg:phone":"+49 2383/8257",
    "sg:postcode":"59199",
    "sg:province":"Nordrhein-Westfalen",
    "wof:name":"Helmut B\u00f6ckelmann",
    "wof:placetype":"venue"
},
  "geometry": {"coordinates":[7.801739,51.612823],"type":"Point"}
}