{
  "type": "Feature",
  "properties": {
    "iso:country":"DE",
    "sg:address":"Obere Str. 1",
    "sg:city":"Saalfeld",
    "sg:phone":"+49 3671/529975",
    "sg:postcode":"07318",
    "sg:province":"Th\u00fcringen",
    "wof:name":"Gewerbe-treuhand Oberfranken Gmbh",
    "wof:placetype":"venue"
},
  "geometry": {"coordinates":[11.3611698151,50.6453857422],"type":"Point"}
}