{
  "type": "Feature",
  "properties": {
    "iso:country":"DE",
    "sg:address":"Hansaplatz 13",
    "sg:city":"Hamburg",
    "sg:phone":"+49 40/249150",
    "sg:postcode":"20099",
    "sg:province":"Hamburg",
    "wof:name":"Asiye-belge",
    "wof:placetype":"venue"
},
  "geometry": {"coordinates":[10.0127153397,53.5548973083],"type":"Point"}
}