{
  "type": "Feature",
  "properties": {
    "iso:country":"DE",
    "sg:address":"Von-Sandt-Str. 9",
    "sg:city":"Bonn",
    "sg:phone":"+49 228/466298",
    "sg:postcode":"53225",
    "sg:province":"Nordrhein-Westfalen",
    "wof:name":"Oppermann-schwedler",
    "wof:placetype":"venue"
},
  "geometry": {"coordinates":[7.116854,50.739784],"type":"Point"}
}