{
  "type": "Feature",
  "properties": {
    "iso:country":"DE",
    "sg:address":"Jahnstr. 1",
    "sg:city":"Steinheim",
    "sg:phone":"+49 7329/1300",
    "sg:postcode":"89555",
    "sg:province":"Baden-W\u00fcrttemberg",
    "wof:name":"Vereinsgastst\u00e4tte Turnverein Steinheim 1904 E.v.",
    "wof:placetype":"venue"
},
  "geometry": {"coordinates":[9.08614254,51.8740158081],"type":"Point"}
}