{
  "type": "Feature",
  "properties": {
    "iso:country":"DE",
    "sg:address":"Eckentaler Str. 16",
    "sg:city":"Eckental",
    "sg:phone":"+49 9126/8072",
    "sg:postcode":"90542",
    "sg:province":"Bayern",
    "wof:name":"Michel Seiler Architekt",
    "wof:placetype":"venue"
},
  "geometry": {"coordinates":[11.206709,49.575813],"type":"Point"}
}