{
  "type": "Feature",
  "properties": {
    "iso:country":"DE",
    "sg:address":"Zollernplatz 3",
    "sg:city":"Esslingen",
    "sg:phone":"+49 711/385819",
    "sg:postcode":"73734",
    "sg:province":"Baden-W\u00fcrttemberg",
    "wof:name":"Bierbrezel",
    "wof:placetype":"venue"
},
  "geometry": {"coordinates":[9.304473877,48.7283554077],"type":"Point"}
}