{
  "type": "Feature",
  "properties": {
    "iso:country":"DE",
    "sg:address":"Hauptstr. 18",
    "sg:city":"Pappenheim",
    "sg:phone":"+49 9143/715",
    "sg:postcode":"91788",
    "sg:province":"Bayern",
    "wof:name":"Raiffeisenbank Wei\u00dfenburg Eg",
    "wof:placetype":"venue"
},
  "geometry": {"coordinates":[11.037583,48.928123],"type":"Point"}
}