{
  "type": "Feature",
  "properties": {
    "iso:country":"DE",
    "sg:address":"Pfaffenhofener Str. 10",
    "sg:city":"Hohenwart",
    "sg:phone":"+49 8443/276",
    "sg:postcode":"86558",
    "sg:province":"Bayern",
    "wof:name":"Jakob Dischner",
    "wof:placetype":"venue"
},
  "geometry": {"coordinates":[11.382024765,48.5923309326],"type":"Point"}
}