{
  "type": "Feature",
  "properties": {
    "iso:country":"DE",
    "sg:address":"Theresienstr. 21",
    "sg:city":"Feldkirchen",
    "sg:phone":"+49 89/90480617",
    "sg:postcode":"85622",
    "sg:province":"Bayern",
    "wof:name":"Autzeider Optik Vertriebs Gmbh Johann Augustin",
    "wof:placetype":"venue"
},
  "geometry": {"coordinates":[11.7258367538,48.1470718384],"type":"Point"}
}