{
  "type": "Feature",
  "properties": {
    "iso:country":"DE",
    "sg:address":"Neuburger Str. 96 c",
    "sg:city":"Passau",
    "sg:phone":"+49 851/58108",
    "sg:postcode":"94032",
    "sg:province":"Bayern",
    "wof:name":"Hallenbad-restaurant",
    "wof:placetype":"venue"
},
  "geometry": {"coordinates":[13.4372177124,48.5663948059],"type":"Point"}
}