{
  "type": "Feature",
  "properties": {
    "iso:country":"DE",
    "sg:address":"Gumpersdorfer Weg 6 b",
    "sg:city":"Kulmbach",
    "sg:phone":"+49 9221/88060",
    "sg:postcode":"95326",
    "sg:province":"Bayern",
    "wof:name":"Berata Gmbh",
    "wof:placetype":"venue"
},
  "geometry": {"coordinates":[11.4824924469,50.1144142151],"type":"Point"}
}