{
  "type": "Feature",
  "properties": {
    "iso:country":"DE",
    "sg:address":"Hohenzollernstr. 59-61",
    "sg:city":"Siegburg",
    "sg:phone":"+49 2241/62993",
    "sg:postcode":"53721",
    "sg:province":"Nordrhein-Westfalen",
    "wof:name":"Peter Weber Gmbh Fenster",
    "wof:placetype":"venue"
},
  "geometry": {"coordinates":[7.197679,50.794525],"type":"Point"}
}