{
  "type": "Feature",
  "properties": {
    "iso:country":"DE",
    "sg:address":"Am Diek 35a",
    "sg:city":"Wuppertal",
    "sg:phone":"+49 202/521713",
    "sg:postcode":"42277",
    "sg:province":"Nordrhein-Westfalen",
    "wof:name":"Dirk Steinhaus",
    "wof:placetype":"venue"
},
  "geometry": {"coordinates":[7.2228159904,51.2856292725],"type":"Point"}
}