{
  "type": "Feature",
  "properties": {
    "iso:country":"DE",
    "sg:address":"Otto-Suhr-Allee 115",
    "sg:city":"Berlin",
    "sg:phone":"+49 30/3414870",
    "sg:postcode":"10585",
    "sg:province":"Berlin",
    "wof:name":"Ski-shop Charlottenburg",
    "wof:placetype":"venue"
},
  "geometry": {"coordinates":[13.305528,52.517494],"type":"Point"}
}