{
  "type": "Feature",
  "properties": {
    "iso:country":"DE",
    "sg:address":"Stauffenbergstr. 34",
    "sg:city":"Worms",
    "sg:phone":"+49 6241/22485",
    "sg:postcode":"67547",
    "sg:province":"Rheinland-Pfalz",
    "wof:name":"Rohrlache",
    "wof:placetype":"venue"
},
  "geometry": {"coordinates":[8.3575525284,49.6116752625],"type":"Point"}
}