{
  "type": "Feature",
  "properties": {
    "iso:country":"DE",
    "sg:address":"Brandenburger Str. 3",
    "sg:city":"Konstanz",
    "sg:phone":"+49 7531/75428",
    "sg:postcode":"78467",
    "sg:province":"Baden-W\u00fcrttemberg",
    "wof:name":"Viktor Weindl",
    "wof:placetype":"venue"
},
  "geometry": {"coordinates":[9.1468133926,47.6846427917],"type":"Point"}
}