{
  "type": "Feature",
  "properties": {
    "iso:country":"DE",
    "sg:address":"Steinstr. 5a",
    "sg:city":"Rennerod",
    "sg:phone":"+49 2664/999363",
    "sg:postcode":"56477",
    "sg:province":"Rheinland-Pfalz",
    "wof:name":"Elcotechnik Gmbh",
    "wof:placetype":"venue"
},
  "geometry": {"coordinates":[8.0690717697,50.6096496582],"type":"Point"}
}