{
  "type": "Feature",
  "properties": {
    "iso:country":"DE",
    "sg:address":"Kirchstr. 5",
    "sg:city":"Kl\u00f6tze",
    "sg:phone":"+49 3909/2854",
    "sg:postcode":"38486",
    "sg:province":"Sachsen-Anhalt",
    "wof:name":"Siegbert Unger",
    "wof:placetype":"venue"
},
  "geometry": {"coordinates":[11.1602487564,52.6243553162],"type":"Point"}
}