{
  "type": "Feature",
  "properties": {
    "iso:country":"DE",
    "sg:address":"Mahlower Str. 142",
    "sg:city":"Teltow",
    "sg:phone":"+49 3328/41236",
    "sg:postcode":"14513",
    "sg:province":"Brandenburg",
    "wof:name":"Hocotz K\u00e4rcher",
    "wof:placetype":"venue"
},
  "geometry": {"coordinates":[13.280344,52.395905],"type":"Point"}
}