{
  "type": "Feature",
  "properties": {
    "iso:country":"DE",
    "sg:address":"Bebelstr. 217 b",
    "sg:city":"Oberhausen",
    "sg:phone":"+49 208/840250",
    "sg:postcode":"46049",
    "sg:province":"Nordrhein-Westfalen",
    "wof:name":"Rolf Schmidt",
    "wof:placetype":"venue"
},
  "geometry": {"coordinates":[6.832992,51.460079],"type":"Point"}
}