{
  "type": "Feature",
  "properties": {
    "iso:country":"DE",
    "sg:address":"Buschweg 1",
    "sg:city":"Mobschatz",
    "sg:phone":"+49 351/4520127",
    "sg:postcode":"01462",
    "wof:name":"Tischlerei Rolf Grie\u00dfbach - Mobschatz Bei Dresden",
    "wof:placetype":"venue"
},
  "geometry": {"coordinates":[13.641561,51.076298],"type":"Point"}
}