{
  "type": "Feature",
  "properties": {
    "iso:country":"DE",
    "sg:address":"Holzstr. 52",
    "sg:city":"Witten",
    "sg:phone":"+49 2302/60214",
    "sg:postcode":"58453",
    "sg:province":"Nordrhein-Westfalen",
    "wof:name":"Heinrich Fuhrmann",
    "wof:placetype":"venue"
},
  "geometry": {"coordinates":[7.370566,51.433838],"type":"Point"}
}