{
  "type": "Feature",
  "properties": {
    "iso:country":"DE",
    "sg:address":"Im Garbrock 39",
    "sg:city":"Ahaus",
    "sg:phone":"+49 4925/6198240",
    "sg:postcode":"48683",
    "sg:province":"Nordrhein-Westfalen",
    "wof:name":"Ottensteiner Kunststoff Gmbh & Co Kg",
    "wof:placetype":"venue"
},
  "geometry": {"coordinates":[6.9250030518,52.0755119324],"type":"Point"}
}