{
  "type": "Feature",
  "properties": {
    "iso:country":"DE",
    "sg:address":"Carl-von-Ossietzky-Str. 5",
    "sg:city":"Leverkusen",
    "sg:phone":"+49 214/92634",
    "sg:postcode":"51377",
    "sg:province":"Nordrhein-Westfalen",
    "wof:name":"Rolf Ludwig",
    "wof:placetype":"venue"
},
  "geometry": {"coordinates":[7.0629200935,51.0491981506],"type":"Point"}
}