{
  "type": "Feature",
  "properties": {
    "iso:country":"DE",
    "sg:address":"Dorfkulmer Weg 3b",
    "sg:city":"Saalfeld",
    "sg:phone":"+49 3671/513371",
    "sg:postcode":"07318",
    "sg:province":"Th\u00fcringen",
    "wof:name":"Feist & Truckenbrodt",
    "wof:placetype":"venue"
},
  "geometry": {"coordinates":[11.357894,50.671192],"type":"Point"}
}