{
  "type": "Feature",
  "properties": {
    "iso:country":"DE",
    "sg:address":"Ayb\u00fchlweg 32",
    "sg:city":"Kempten",
    "sg:phone":"+49 831/8221",
    "sg:postcode":"87435",
    "sg:province":"Bayern",
    "wof:name":"Bayerische Vereinsbank Ag",
    "wof:placetype":"venue"
},
  "geometry": {"coordinates":[10.294539,47.715408],"type":"Point"}
}