{
  "type": "Feature",
  "properties": {
    "iso:country":"DE",
    "sg:address":"In de Tarpen 114",
    "sg:city":"Norderstedt",
    "sg:phone":"+49 40/5235867",
    "sg:postcode":"22848",
    "sg:province":"Schleswig-Holstein",
    "wof:name":"Erhard Lange",
    "wof:placetype":"venue"
},
  "geometry": {"coordinates":[9.988485,53.665791],"type":"Point"}
}