{
  "type": "Feature",
  "properties": {
    "iso:country":"DE",
    "sg:address":"S\u00fcderstr. 33",
    "sg:city":"Gettorf",
    "sg:phone":"+49 4346/7073",
    "sg:postcode":"24214",
    "sg:province":"Schleswig-Holstein",
    "wof:name":"Tierpark Gettorf",
    "wof:placetype":"venue"
},
  "geometry": {"coordinates":[9.9741430283,54.4034690857],"type":"Point"}
}