{
  "type": "Feature",
  "properties": {
    "iso:country":"DE",
    "sg:address":"Rheinstr. 18b",
    "sg:city":"Stadtallendorf",
    "sg:phone":"+49 4934/243740",
    "sg:postcode":"35260",
    "sg:province":"Hessen",
    "wof:name":"Bad D\u00dcben Profilwalzmaschinen Gmbh",
    "wof:placetype":"venue"
},
  "geometry": {"coordinates":[12.57597,51.587433],"type":"Point"}
}