{
  "type": "Feature",
  "properties": {
    "iso:country":"DE",
    "sg:address":"Viktor-von-Scheffel-Str. 7",
    "sg:city":"Hof",
    "sg:phone":"+49 9281/94400",
    "sg:postcode":"95032",
    "sg:province":"Bayern",
    "wof:name":"Hospitalstiftung",
    "wof:placetype":"venue"
},
  "geometry": {"coordinates":[11.897113,50.296207],"type":"Point"}
}