{
  "type": "Feature",
  "properties": {
    "iso:country":"DE",
    "sg:address":"M\u00fchlenweg 88 b",
    "sg:city":"Seevetal",
    "sg:phone":"+49 4105/4199",
    "sg:postcode":"21217",
    "sg:province":"Niedersachsen",
    "wof:name":"Pk Reinigungsdienst Paul Koryciak",
    "wof:placetype":"venue"
},
  "geometry": {"coordinates":[9.981142,53.414234],"type":"Point"}
}