{
  "type": "Feature",
  "properties": {
    "iso:country":"DE",
    "sg:address":"Einsteinstr. 28",
    "sg:city":"Aschaffenburg",
    "sg:phone":"+49 6021/48444",
    "sg:postcode":"63741",
    "sg:province":"Bayern",
    "wof:name":"Dr. Michael Weise Tierarzt",
    "wof:placetype":"venue"
},
  "geometry": {"coordinates":[9.1122274399,49.9875297546],"type":"Point"}
}