{
  "type": "Feature",
  "properties": {
    "iso:country":"DE",
    "sg:address":"Leeraue 59",
    "sg:city":"Dresden",
    "sg:phone":"+49 351/8845410",
    "sg:postcode":"01109",
    "sg:province":"Sachsen",
    "wof:name":"Alter Weinberg Hotel, Pension, Ferienwohnung",
    "wof:placetype":"venue"
},
  "geometry": {"coordinates":[13.7221603394,51.1091690063],"type":"Point"}
}