{
  "type": "Feature",
  "properties": {
    "iso:country":"DE",
    "sg:address":"Auf dem Bock 19",
    "sg:city":"Wachtendonk",
    "sg:phone":"+49 2836/230",
    "sg:postcode":"47669",
    "sg:province":"Nordrhein-Westfalen",
    "wof:name":"W. Heussen",
    "wof:placetype":"venue"
},
  "geometry": {"coordinates":[6.34899,51.41095],"type":"Point"}
}