{
  "type": "Feature",
  "properties": {
    "iso:country":"DE",
    "sg:address":"Egestorfer Str. 26",
    "sg:city":"Barsinghausen",
    "sg:phone":"+49 5105/52510",
    "sg:postcode":"30890",
    "sg:province":"Niedersachsen",
    "wof:name":"Jordan Gmbh",
    "wof:placetype":"venue"
},
  "geometry": {"coordinates":[9.47692,52.296921],"type":"Point"}
}