{
  "type": "Feature",
  "properties": {
    "iso:country":"DE",
    "sg:address":"Bahnstr. 20",
    "sg:city":"Rommerskirchen",
    "sg:phone":"+49 2183/317",
    "sg:postcode":"41569",
    "sg:province":"Nordrhein-Westfalen",
    "wof:name":"Georg Fischer",
    "wof:placetype":"venue"
},
  "geometry": {"coordinates":[6.699733,51.03804],"type":"Point"}
}