{
  "type": "Feature",
  "properties": {
    "iso:country":"DE",
    "sg:address":"Krautgasse 3",
    "sg:city":"P\u00f6\u00dfneck",
    "sg:phone":"+49 3647/413005",
    "sg:postcode":"07381",
    "sg:province":"Th\u00fcringen",
    "wof:name":"Gardinen & Bettenetage Gmbh",
    "wof:placetype":"venue"
},
  "geometry": {"coordinates":[11.5936336517,50.6944694519],"type":"Point"}
}