{
  "type": "Feature",
  "properties": {
    "iso:country":"DE",
    "sg:address":"Paradiesring 1 a",
    "sg:city":"Gro\u00dfharthau",
    "sg:phone":"+49 35954/53368",
    "sg:postcode":"01909",
    "sg:province":"Sachsen",
    "wof:name":"Restaurant Zum Paradies Inh. Fam. Voigt",
    "wof:placetype":"venue"
},
  "geometry": {"coordinates":[14.0981912613,51.1030235291],"type":"Point"}
}