{
  "type": "Feature",
  "properties": {
    "iso:country":"DE",
    "sg:address":"Hauptstr. 62",
    "sg:city":"Knetzgau",
    "sg:phone":"+49 9529/752",
    "sg:postcode":"97478",
    "sg:province":"Bayern",
    "wof:name":"Gerhard H\u00fcgerich",
    "wof:placetype":"venue"
},
  "geometry": {"coordinates":[10.5438108444,49.9988594055],"type":"Point"}
}