{
  "type": "Feature",
  "properties": {
    "iso:country":"DE",
    "sg:address":"Seligenst\u00e4dter Str. 37",
    "sg:city":"Obertshausen",
    "sg:phone":"+49 6104/71626",
    "sg:postcode":"63179",
    "sg:province":"Hessen",
    "wof:name":"Rau",
    "wof:placetype":"venue"
},
  "geometry": {"coordinates":[8.8638801575,50.0794677734],"type":"Point"}
}