{
  "type": "Feature",
  "properties": {
    "iso:country":"DE",
    "sg:address":"B\u00fcndelstockweg 20",
    "sg:city":"Aulendorf",
    "sg:phone":"+49 4975/259400",
    "sg:postcode":"88326",
    "sg:province":"Baden-W\u00fcrttemberg",
    "wof:name":"Schramm Ohg",
    "wof:placetype":"venue"
},
  "geometry": {"coordinates":[9.6367683411,47.9592285156],"type":"Point"}
}