{
  "type": "Feature",
  "properties": {
    "iso:country":"DE",
    "sg:address":"Friedrich-Breuer-Str. 86",
    "sg:city":"Bonn",
    "sg:phone":"+49 228/462938",
    "sg:postcode":"53225",
    "sg:province":"Nordrhein-Westfalen",
    "wof:name":"Dr. Winfried Behr",
    "wof:placetype":"venue"
},
  "geometry": {"coordinates":[7.1222457886,50.7397460938],"type":"Point"}
}