{
  "type": "Feature",
  "properties": {
    "iso:country":"DE",
    "sg:address":"J\u00e4gerstr. 7",
    "sg:city":"Witten",
    "sg:phone":"+49 2302/12038",
    "sg:postcode":"58453",
    "sg:province":"Nordrhein-Westfalen",
    "wof:name":"Lothar Hautkapp",
    "wof:placetype":"venue"
},
  "geometry": {"coordinates":[7.3783278465,51.4339332581],"type":"Point"}
}