{
  "type": "Feature",
  "properties": {
    "iso:country":"DE",
    "sg:address":"Friedrich-Ebert-Str. 55a",
    "sg:city":"Neustadt",
    "sg:phone":"+49 6321/32606",
    "sg:postcode":"67433",
    "sg:province":"Rheinland-Pfalz",
    "wof:name":"Peter Koch",
    "wof:placetype":"venue"
},
  "geometry": {"coordinates":[8.1504745483,49.3510894775],"type":"Point"}
}