{
  "type": "Feature",
  "properties": {
    "iso:country":"DE",
    "sg:address":"Jahnstr. 36",
    "sg:city":"Sprockh\u00f6vel",
    "sg:phone":"+49 2339/6130",
    "sg:postcode":"45549",
    "sg:province":"Nordrhein-Westfalen",
    "wof:name":"Resol Mikroelektronik Gmbh",
    "wof:placetype":"venue"
},
  "geometry": {"coordinates":[7.293129921,51.3562812805],"type":"Point"}
}