{
  "type": "Feature",
  "properties": {
    "iso:country":"DE",
    "sg:address":"Annaberger Str 182",
    "sg:city":"Chemnitz",
    "sg:phone":"+49 371/510217",
    "sg:postcode":"09120",
    "sg:province":"Sachsen",
    "wof:name":"Frank Pickl",
    "wof:placetype":"venue"
},
  "geometry": {"coordinates":[12.9107980728,50.8015060425],"type":"Point"}
}