{
  "type": "Feature",
  "properties": {
    "iso:country":"DE",
    "sg:address":"Harxheimer Weg 2",
    "sg:city":"Mainz",
    "sg:phone":"+49 6136/4188",
    "sg:postcode":"55129",
    "sg:province":"Rheinland-Pfalz",
    "wof:name":"Landhandel Andreas Ackermann Gmbh",
    "wof:placetype":"venue"
},
  "geometry": {"coordinates":[8.246035,49.910664],"type":"Point"}
}