{
  "type": "Feature",
  "properties": {
    "iso:country":"DE",
    "sg:address":"Dresdener Str. 18",
    "sg:city":"Cottbus",
    "sg:phone":"+49 355/473465",
    "sg:postcode":"03050",
    "sg:province":"Brandenburg",
    "wof:name":"Siebert & Co. Glas- Und Geb\u00e4udereinigung Ohg",
    "wof:placetype":"venue"
},
  "geometry": {"coordinates":[14.334098,51.740849],"type":"Point"}
}