{
  "type": "Feature",
  "properties": {
    "iso:country":"DE",
    "sg:address":"Viktoriastr. 8",
    "sg:city":"Minden",
    "sg:phone":"+49 571/36314",
    "sg:postcode":"32423",
    "sg:province":"Nordrhein-Westfalen",
    "wof:name":"Helga Zendel",
    "wof:placetype":"venue"
},
  "geometry": {"coordinates":[8.934362,52.288597],"type":"Point"}
}