{
  "type": "Feature",
  "properties": {
    "iso:country":"DE",
    "sg:address":"S\u00fcderstr 10::",
    "sg:city":"Holtland",
    "sg:postcode":"26835",
    "sg:province":"Niedersachsen",
    "wof:name":"Spar-und Darlehnskasse Isselhorst Eg",
    "wof:placetype":"venue"
},
  "geometry": {"coordinates":[8.38098,51.909306],"type":"Point"}
}