{
  "type": "Feature",
  "properties": {
    "iso:country":"DE",
    "sg:address":"Adolfstr. 3",
    "sg:city":"Mudersbach",
    "sg:phone":"+49 271/354060",
    "sg:postcode":"57555",
    "sg:province":"Rheinland-Pfalz",
    "wof:name":"Kontra-lebensmittelmarkt Niederschelderh\u00fctte",
    "wof:placetype":"venue"
},
  "geometry": {"coordinates":[7.9662938118,50.8440322876],"type":"Point"}
}