{
  "type": "Feature",
  "properties": {
    "iso:country":"DE",
    "sg:address":"Girchinger Str. 16",
    "sg:city":"K\u00fcnzing",
    "sg:phone":"+49 8549/8194",
    "sg:postcode":"94550",
    "sg:province":"Bayern",
    "wof:name":"Fanny Brandner",
    "wof:placetype":"venue"
},
  "geometry": {"coordinates":[13.077331543,48.6651992798],"type":"Point"}
}