{
  "type": "Feature",
  "properties": {
    "iso:country":"DE",
    "sg:address":"Margaretenweg 4",
    "sg:city":"Kirchheim",
    "sg:phone":"+49 7143/91836",
    "sg:postcode":"74366",
    "sg:province":"Baden-W\u00fcrttemberg",
    "wof:name":"Michael Pook",
    "wof:placetype":"venue"
},
  "geometry": {"coordinates":[9.138976,49.03846],"type":"Point"}
}