{
  "type": "Feature",
  "properties": {
    "iso:country":"DE",
    "sg:address":"S\u00fcderstr. 3",
    "sg:city":"Weener",
    "sg:phone":"+49 4951/3488",
    "sg:postcode":"26826",
    "sg:province":"Niedersachsen",
    "wof:name":"Pizzast\u00fcbchen Inh. Kemal J\u00fcs\u00fcn",
    "wof:placetype":"venue"
},
  "geometry": {"coordinates":[7.3549928665,53.1648025513],"type":"Point"}
}