{
  "type": "Feature",
  "properties": {
    "iso:country":"DE",
    "sg:address":"Am Dahlumer Holze 10",
    "sg:city":"Braunschweig",
    "sg:phone":"+49 531/65066",
    "sg:postcode":"38126",
    "sg:province":"Niedersachsen",
    "wof:name":"F\u00f6rdergesellschaft Des Kiwanis Club Braunschweig E. V.",
    "wof:placetype":"venue"
},
  "geometry": {"coordinates":[10.575676918,52.2246360779],"type":"Point"}
}