{
  "type": "Feature",
  "properties": {
    "iso:country":"DE",
    "sg:address":"Hadmerslebener Str. 22",
    "sg:city":"Westeregeln",
    "sg:phone":"+49 39268/35138",
    "sg:postcode":"39448",
    "sg:province":"Sachsen-Anhalt",
    "wof:name":"Eckard Christel",
    "wof:placetype":"venue"
},
  "geometry": {"coordinates":[11.37649,51.96521],"type":"Point"}
}