{
  "type": "Feature",
  "properties": {
    "iso:country":"DE",
    "sg:address":"Cisinskistr. 5",
    "sg:city":"Crostwitz",
    "sg:phone":"+49 35796/96448",
    "sg:postcode":"01920",
    "sg:province":"Sachsen",
    "wof:name":"Benno Kurf\u00fcrst Heilpraktiker",
    "wof:placetype":"venue"
},
  "geometry": {"coordinates":[14.2361822128,51.2383537292],"type":"Point"}
}