{
  "type": "Feature",
  "properties": {
    "iso:country":"DE",
    "sg:address":"Sedanstr. 19",
    "sg:city":"Hamburg",
    "sg:postcode":"20146",
    "sg:province":"Hamburg",
    "wof:name":"Institut F\u00fcr Berufs- Und Wirtschaftsp\u00e4dagogik",
    "wof:placetype":"venue"
},
  "geometry": {"coordinates":[9.9775791168,53.5693664551],"type":"Point"}
}