{
  "type": "Feature",
  "properties": {
    "iso:country":"DE",
    "sg:address":"Barntruper Str. 12",
    "sg:city":"Paderborn",
    "sg:phone":"+49 5251/480970",
    "sg:postcode":"33102",
    "sg:province":"Nordrhein-Westfalen",
    "wof:name":"Hsp-vertriebsges. Mbh",
    "wof:placetype":"venue"
},
  "geometry": {"coordinates":[8.7694587708,51.7440414429],"type":"Point"}
}