{
  "type": "Feature",
  "properties": {
    "iso:country":"DE",
    "sg:address":"Postfach 710329",
    "sg:city":"Hamburg",
    "sg:postcode":"22163",
    "sg:province":"Hamburg",
    "wof:name":"Deutsches Schwules Callboy Und Escort Verzeichnis",
    "wof:placetype":"venue"
},
  "geometry": {"coordinates":[9.9733,53.549831],"type":"Point"}
}