{
  "type": "Feature",
  "properties": {
    "iso:country":"DE",
    "sg:address":"Langer Damm 39",
    "sg:city":"Finsterwalde",
    "sg:postcode":"03238",
    "sg:province":"Brandenburg",
    "wof:name":"Bundesverband Mittelst\u00e4ndische Wirtschaft Bvmw",
    "wof:placetype":"venue"
},
  "geometry": {"coordinates":[13.714108,51.62867],"type":"Point"}
}