{
  "type": "Feature",
  "properties": {
    "iso:country":"DE",
    "sg:address":"Hertha-Petersen-Str. 20",
    "sg:city":"Kaltenkirchen",
    "sg:postcode":"24568",
    "sg:province":"Schleswig-Holstein",
    "wof:name":"Mike Grimm Bedachungs- Gmbh",
    "wof:placetype":"venue"
},
  "geometry": {"coordinates":[9.9365,53.820328],"type":"Point"}
}