{
  "type": "Feature",
  "properties": {
    "iso:country":"DE",
    "sg:address":"Von-C\u00f6lln-Str. 12",
    "sg:city":"Lage",
    "sg:phone":"+49 5232/3058",
    "sg:postcode":"32791",
    "sg:province":"Nordrhein-Westfalen",
    "wof:name":"M. Fuchs",
    "wof:placetype":"venue"
},
  "geometry": {"coordinates":[8.7984323502,51.9895820618],"type":"Point"}
}