{
  "type": "Feature",
  "properties": {
    "iso:country":"DE",
    "sg:address":"Eduard-Gerhard-Str. 5",
    "sg:city":"Bad Br\u00fcckenau",
    "sg:phone":"+49 9741/2385",
    "sg:postcode":"97769",
    "sg:province":"Bayern",
    "wof:name":"G\u00e4stehaus Breitenbach Karl Herdt",
    "wof:placetype":"venue"
},
  "geometry": {"coordinates":[9.820151329,50.3201713562],"type":"Point"}
}