{
  "type": "Feature",
  "properties": {
    "iso:country":"DE",
    "sg:address":"Friedensstr. 22",
    "sg:city":"Wittenberge",
    "sg:phone":"+49 3877/74551",
    "sg:postcode":"19322",
    "sg:province":"Brandenburg",
    "wof:name":"Adolf Tober",
    "wof:placetype":"venue"
},
  "geometry": {"coordinates":[11.7460308075,52.9980583191],"type":"Point"}
}