{
  "type": "Feature",
  "properties": {
    "iso:country":"DE",
    "sg:address":"Gro\u00dfe Bergstr. 172",
    "sg:city":"Hamburg",
    "sg:phone":"+49 40/3893207",
    "sg:postcode":"22767",
    "sg:province":"Hamburg",
    "wof:name":"N. Ntafebis",
    "wof:placetype":"venue"
},
  "geometry": {"coordinates":[9.9416837692,53.5517311096],"type":"Point"}
}