{
  "type": "Feature",
  "properties": {
    "iso:country":"DE",
    "sg:address":"Am Elsheimer Tor 5",
    "sg:city":"Schwabenheim",
    "sg:postcode":"55270",
    "sg:province":"Rheinland-Pfalz",
    "wof:name":"Mailmen Telekommunikation Und Dienstleistungs Gmbh",
    "wof:placetype":"venue"
},
  "geometry": {"coordinates":[8.0976982117,49.9296836853],"type":"Point"}
}