{
  "type": "Feature",
  "properties": {
    "iso:country":"DE",
    "sg:address":"Cosimastr. 121",
    "sg:city":"M\u00fcnchen",
    "sg:phone":"+49 89/9578586",
    "sg:postcode":"81925",
    "sg:province":"Bayern",
    "wof:name":"Wow World Of Wine Gmbh",
    "wof:placetype":"venue"
},
  "geometry": {"coordinates":[11.6290102005,48.1639251709],"type":"Point"}
}