{
  "type": "Feature",
  "properties": {
    "iso:country":"DE",
    "sg:address":"Kirchstr. 51",
    "sg:city":"Gelsenkirchen",
    "sg:phone":"+49 209/1580622",
    "sg:postcode":"45879",
    "sg:province":"Nordrhein-Westfalen",
    "wof:name":"Caritas-gemeindestation",
    "wof:placetype":"venue"
},
  "geometry": {"coordinates":[7.10136,51.509941],"type":"Point"}
}