{
  "type": "Feature",
  "properties": {
    "iso:country":"DE",
    "sg:address":"Herrenachtstr. 33",
    "sg:city":"Eppelborn",
    "sg:phone":"+49 6881/6550",
    "sg:postcode":"66571",
    "sg:province":"Saarland",
    "wof:name":"Hans-dieter Klose",
    "wof:placetype":"venue"
},
  "geometry": {"coordinates":[6.94822,49.409603],"type":"Point"}
}