{
  "type": "Feature",
  "properties": {
    "iso:country":"DE",
    "sg:address":"Luitpoldstr. 22",
    "sg:city":"Helmbrechts",
    "sg:phone":"+49 9252/3052",
    "sg:postcode":"95233",
    "sg:province":"Bayern",
    "wof:name":"Orient Kebaphaus",
    "wof:placetype":"venue"
},
  "geometry": {"coordinates":[11.7174396515,50.2394943237],"type":"Point"}
}