{
  "type": "Feature",
  "properties": {
    "iso:country":"DE",
    "sg:address":"Wiesenstr 16",
    "sg:city":"Sch\u00f6nwalde",
    "sg:phone":"+49 33056/82491",
    "sg:postcode":"16352",
    "sg:province":"Mecklenburg-Vorpommern",
    "wof:name":"Ingenieurb\u00fcro Bodinus",
    "wof:placetype":"venue"
},
  "geometry": {"coordinates":[13.4359951019,52.6771392822],"type":"Point"}
}