{
  "type": "Feature",
  "properties": {
    "iso:country":"DE",
    "sg:address":"Seilerstr. 1b",
    "sg:city":"Zwickau",
    "sg:phone":"+49 4937/5818650",
    "sg:postcode":"08056",
    "sg:province":"Sachsen",
    "wof:name":"Westf\u00c4lischedrahtindustrie Gmbh",
    "wof:placetype":"venue"
},
  "geometry": {"coordinates":[12.480705,50.720997],"type":"Point"}
}