{
  "type": "Feature",
  "properties": {
    "iso:country":"DE",
    "sg:address":"Fritz-Raab-Str. 13-15",
    "sg:city":"Gunzenhausen",
    "sg:postcode":"91710",
    "sg:province":"Bayern",
    "wof:name":"Vema-tec Gmbh & Co. Kg",
    "wof:placetype":"venue"
},
  "geometry": {"coordinates":[10.7619895935,49.1134414673],"type":"Point"}
}