{
  "type": "Feature",
  "properties": {
    "iso:country":"DE",
    "sg:address":"Hauptstr. 10",
    "sg:city":"Freisen",
    "sg:phone":"+49 6855/1675",
    "sg:postcode":"66629",
    "sg:province":"Saarland",
    "wof:name":"Neu Handels Gmbh & Co. Kg",
    "wof:placetype":"venue"
},
  "geometry": {"coordinates":[7.2612309456,49.525138855],"type":"Point"}
}