{
  "type": "Feature",
  "properties": {
    "iso:country":"DE",
    "sg:address":"Plittersdorfer Str. 7",
    "sg:city":"Rastatt",
    "sg:phone":"+49 7222/200075",
    "sg:postcode":"76437",
    "sg:province":"Baden-W\u00fcrttemberg",
    "wof:name":"Neckura Versicherungen Klaus K\u00fchn",
    "wof:placetype":"venue"
},
  "geometry": {"coordinates":[8.1984500885,48.8689994812],"type":"Point"}
}