{
  "type": "Feature",
  "properties": {
    "iso:country":"DE",
    "sg:address":"Henschelplatz 1",
    "sg:city":"Kassel",
    "sg:phone":"+49 561/8016885",
    "sg:postcode":"34127",
    "sg:province":"Hessen",
    "wof:name":"Henschel Recycling Technik Gmbh & Co Kg",
    "wof:placetype":"venue"
},
  "geometry": {"coordinates":[9.484712,51.333725],"type":"Point"}
}