{
  "type": "Feature",
  "properties": {
    "iso:country":"DE",
    "sg:address":"Lange Str. 17",
    "sg:city":"Malchow",
    "sg:phone":"+49 39932/19406",
    "sg:postcode":"17213",
    "sg:province":"Mecklenburg-Vorpommern",
    "wof:name":"Modepartner Schmidt R + H Schmidt Gmbh",
    "wof:placetype":"venue"
},
  "geometry": {"coordinates":[12.4289960861,53.4748649597],"type":"Point"}
}