{
  "type": "Feature",
  "properties": {
    "iso:country":"DE",
    "sg:address":"Laubanger 11",
    "sg:city":"Bamberg",
    "sg:phone":"+49 951/965540",
    "sg:postcode":"96052",
    "sg:province":"Bayern",
    "wof:name":"Quelle Verkaufshaus",
    "wof:placetype":"venue"
},
  "geometry": {"coordinates":[10.8768005371,49.9092788696],"type":"Point"}
}