{
  "type": "Feature",
  "properties": {
    "iso:country":"DE",
    "sg:address":"Primstalstr. 22",
    "sg:city":"Tholey",
    "sg:postcode":"66636",
    "sg:province":"Saarland",
    "wof:name":"Bard Metzgereiprodukte Gmbh",
    "wof:placetype":"venue"
},
  "geometry": {"coordinates":[7.0069770813,49.5076675415],"type":"Point"}
}