{
  "type": "Feature",
  "properties": {
    "iso:country":"DE",
    "sg:address":"Weidener Str. 3",
    "sg:city":"Speichersdorf",
    "sg:phone":"+49 9275/301",
    "sg:postcode":"95469",
    "sg:province":"Bayern",
    "wof:name":"F. Und A. Zetlmeisl",
    "wof:placetype":"venue"
},
  "geometry": {"coordinates":[11.769502,49.876259],"type":"Point"}
}