{
  "type": "Feature",
  "properties": {
    "iso:country":"DE",
    "sg:address":"Hollenbergstr. 17",
    "sg:city":"Duisburg",
    "sg:phone":"+49 203/442616",
    "sg:postcode":"47137",
    "sg:province":"Nordrhein-Westfalen",
    "wof:name":"Gerhard Berns Bildhauer",
    "wof:placetype":"venue"
},
  "geometry": {"coordinates":[6.775284,51.466675],"type":"Point"}
}