{
  "type": "Feature",
  "properties": {
    "iso:country":"DE",
    "sg:address":"Bibelstr. 14",
    "sg:city":"Saarlouis",
    "sg:phone":"+49 6831/121712",
    "sg:postcode":"66740",
    "sg:province":"Saarland",
    "wof:name":"Hobbymaler Gmbh",
    "wof:placetype":"venue"
},
  "geometry": {"coordinates":[6.7530941963,49.314666748],"type":"Point"}
}