{
  "type": "Feature",
  "properties": {
    "iso:country":"DE",
    "sg:address":"Sittardsberger Allee 21",
    "sg:city":"Duisburg",
    "sg:phone":"+49 203/701293",
    "sg:postcode":"47249",
    "sg:province":"Nordrhein-Westfalen",
    "wof:name":"Kurt Kuhnen",
    "wof:placetype":"venue"
},
  "geometry": {"coordinates":[6.781355,51.387203],"type":"Point"}
}