{
  "type": "Feature",
  "properties": {
    "iso:country":"DE",
    "sg:address":"Neukirchener Str. 7",
    "sg:city":"Moers",
    "sg:phone":"+49 2841/62009",
    "sg:postcode":"47447",
    "sg:province":"Nordrhein-Westfalen",
    "wof:name":"Alt Kapellen",
    "wof:placetype":"venue"
},
  "geometry": {"coordinates":[6.593102932,51.4181213379],"type":"Point"}
}