{
  "type": "Feature",
  "properties": {
    "iso:country":"DE",
    "sg:address":"Herrengraben 30",
    "sg:city":"Hamburg",
    "sg:phone":"+49 40/367737",
    "sg:postcode":"20459",
    "sg:province":"Hamburg",
    "wof:name":"Wolfgang Moritz",
    "wof:placetype":"venue"
},
  "geometry": {"coordinates":[9.9818553925,53.5462760925],"type":"Point"}
}