{
  "type": "Feature",
  "properties": {
    "iso:country":"DE",
    "sg:address":"Friedrichsplatz 17",
    "sg:city":"Mannheim",
    "sg:phone":"+49 4962/1419350",
    "sg:postcode":"68165",
    "sg:province":"Baden-W\u00fcrttemberg",
    "wof:name":"S\u00dcdwest Ag",
    "wof:placetype":"venue"
},
  "geometry": {"coordinates":[8.478372,49.483582],"type":"Point"}
}