{
  "type": "Feature",
  "properties": {
    "iso:country":"DE",
    "sg:address":"Scharn 19",
    "sg:city":"Minden",
    "sg:phone":"+49 571/22060",
    "sg:postcode":"32423",
    "sg:province":"Nordrhein-Westfalen",
    "wof:name":"Dr. Kr\u00f6ncke Verwaltungs Gmbh",
    "wof:placetype":"venue"
},
  "geometry": {"coordinates":[8.9164276123,52.2898406982],"type":"Point"}
}