{
  "type": "Feature",
  "properties": {
    "iso:country":"DE",
    "sg:address":"Greuel 17",
    "sg:city":"Remscheid",
    "sg:phone":"+49 2191/52860",
    "sg:postcode":"42897",
    "sg:province":"Nordrhein-Westfalen",
    "wof:name":"Wolter Gmbh",
    "wof:placetype":"venue"
},
  "geometry": {"coordinates":[7.245791,51.180092],"type":"Point"}
}