{
  "type": "Feature",
  "properties": {
    "iso:country":"DE",
    "sg:address":"Am Kuhkamp 16",
    "sg:city":"L\u00fcbbecke",
    "sg:phone":"+49 5741/7506",
    "sg:postcode":"32312",
    "sg:province":"Nordrhein-Westfalen",
    "wof:name":"K.-h. H\u00f6ke",
    "wof:placetype":"venue"
},
  "geometry": {"coordinates":[8.573072,52.302273],"type":"Point"}
}