{
  "type": "Feature",
  "properties": {
    "iso:country":"DE",
    "sg:address":"Landstr. 14",
    "sg:city":"Sinzheim",
    "sg:phone":"+49 7221/9850",
    "sg:postcode":"76547",
    "sg:province":"Baden-W\u00fcrttemberg",
    "wof:name":"Hermann Rauch Kg",
    "wof:placetype":"venue"
},
  "geometry": {"coordinates":[8.1686973572,48.7593650818],"type":"Point"}
}