{
  "type": "Feature",
  "properties": {
    "iso:country":"DE",
    "sg:address":"Alstertor 23",
    "sg:city":"Hamburg",
    "sg:postcode":"20095",
    "sg:province":"Hamburg",
    "wof:name":"Treuhand Contor Verm\u00f6gensverwaltungs Gmbh",
    "wof:placetype":"venue"
},
  "geometry": {"coordinates":[9.9966478348,53.5527000427],"type":"Point"}
}