{
  "type": "Feature",
  "properties": {
    "iso:country":"DE",
    "sg:address":"An der Kirche 1",
    "sg:city":"Bad Bramstedt",
    "sg:phone":"+49 4192/2219",
    "sg:postcode":"24576",
    "sg:province":"Schleswig-Holstein",
    "wof:name":"Horst Ellerbrock Architekt",
    "wof:placetype":"venue"
},
  "geometry": {"coordinates":[9.882545,53.920864],"type":"Point"}
}