{
  "type": "Feature",
  "properties": {
    "iso:country":"DE",
    "sg:address":"Kumpfm\u00fchler Str. 40",
    "sg:city":"Regensburg",
    "sg:phone":"+49 941/92807",
    "sg:postcode":"93051",
    "sg:province":"Bayern",
    "wof:name":"Optik Matt Gmbh & Co. Kg",
    "wof:placetype":"venue"
},
  "geometry": {"coordinates":[12.0872325897,49.0086326599],"type":"Point"}
}