{
  "type": "Feature",
  "properties": {
    "iso:country":"DE",
    "sg:address":"Von-dem-Bussche-M\u00fcnch-Str. 4",
    "sg:city":"Espelkamp",
    "sg:phone":"+49 5772/6711",
    "sg:postcode":"32339",
    "sg:province":"Nordrhein-Westfalen",
    "wof:name":"Klostermann Chemie Gmbh & Co. Kg",
    "wof:placetype":"venue"
},
  "geometry": {"coordinates":[8.625835,52.39172],"type":"Point"}
}