{
  "type": "Feature",
  "properties": {
    "iso:country":"DE",
    "sg:address":"Neum\u00fchler Weg 73",
    "sg:city":"Saarbr\u00fccken",
    "sg:phone":"+49 681/57508",
    "sg:postcode":"66130",
    "sg:province":"Saarland",
    "wof:name":"Johannes Stein",
    "wof:placetype":"venue"
},
  "geometry": {"coordinates":[7.022005,49.204781],"type":"Point"}
}