{
  "type": "Feature",
  "properties": {
    "iso:country":"DE",
    "sg:address":"Hardenbergstr. 41",
    "sg:city":"M\u00f6nchengladbach",
    "sg:phone":"+49 2166/40025",
    "sg:postcode":"41236",
    "sg:province":"Nordrhein-Westfalen",
    "wof:name":"J\u00fcrgen K\u00f6hler",
    "wof:placetype":"venue"
},
  "geometry": {"coordinates":[6.4527387619,51.1595954895],"type":"Point"}
}