{
  "type": "Feature",
  "properties": {
    "iso:country":"DE",
    "sg:address":"Pfarrer-Wiggen-Str. 38",
    "sg:city":"Menden",
    "sg:phone":"+49 2373/63227",
    "sg:postcode":"58708",
    "sg:province":"Nordrhein-Westfalen",
    "wof:name":"Hermann Haber",
    "wof:placetype":"venue"
},
  "geometry": {"coordinates":[7.7625308037,51.4536933899],"type":"Point"}
}