{
  "type": "Feature",
  "properties": {
    "iso:country":"DE",
    "sg:address":"Friedhofstr. 4",
    "sg:city":"Altom\u00fcnster",
    "sg:phone":"+49 8254/8505",
    "sg:postcode":"85250",
    "sg:province":"Bayern",
    "wof:name":"Gerhard Grosshauser",
    "wof:placetype":"venue"
},
  "geometry": {"coordinates":[11.2571306229,48.3862075806],"type":"Point"}
}