{
  "type": "Feature",
  "properties": {
    "iso:country":"DE",
    "sg:address":"Nordring 39",
    "sg:city":"Waltrop",
    "sg:postcode":"45731",
    "sg:province":"Nordrhein-Westfalen",
    "wof:name":"Thiele & Rotte Partnerschaft",
    "wof:placetype":"venue"
},
  "geometry": {"coordinates":[7.3904590607,51.6250572205],"type":"Point"}
}