{
  "type": "Feature",
  "properties": {
    "iso:country":"DE",
    "sg:address":"Robert-Bosch-Str. 7",
    "sg:city":"Darmstadt",
    "sg:phone":"+49 6151/8724040",
    "sg:postcode":"64293",
    "sg:province":"Hessen",
    "wof:name":"Genius Gmbh",
    "wof:placetype":"venue"
},
  "geometry": {"coordinates":[8.6249713898,49.871006012],"type":"Point"}
}