{
  "type": "Feature",
  "properties": {
    "iso:country":"DE",
    "sg:address":"Ziegelstr. 10",
    "sg:city":"Essen",
    "sg:phone":"+49 201/226296",
    "sg:postcode":"45139",
    "sg:province":"Nordrhein-Westfalen",
    "wof:name":"Dt. St\u00e4dtereklame Gmbh",
    "wof:placetype":"venue"
},
  "geometry": {"coordinates":[7.0262699127,51.4580345154],"type":"Point"}
}