{
  "type": "Feature",
  "properties": {
    "iso:country":"DE",
    "sg:address":"Beyerstra\u00dfe 8",
    "sg:city":"Potsdam",
    "sg:phone":"+49 331",
    "sg:postcode":"14469",
    "sg:province":"Brandenburg",
    "wof:name":"Artisti Agentur",
    "wof:placetype":"venue"
},
  "geometry": {"coordinates":[13.0610980988,52.4119567871],"type":"Point"}
}