{
  "type": "Feature",
  "properties": {
    "iso:country":"DE",
    "sg:address":"Moorenstr. 19",
    "sg:city":"Wachtendonk",
    "sg:phone":"+49 2836/7289",
    "sg:postcode":"47669",
    "sg:province":"Nordrhein-Westfalen",
    "wof:name":"E. Dworatzek",
    "wof:placetype":"venue"
},
  "geometry": {"coordinates":[6.3427062035,51.4058837891],"type":"Point"}
}