{
  "type": "Feature",
  "properties": {
    "iso:country":"DE",
    "sg:address":"Osterhofen 21",
    "sg:city":"Bayrischzell",
    "sg:phone":"+49 8023/651",
    "sg:postcode":"83735",
    "sg:province":"Bayern",
    "wof:name":"Hannes Acher",
    "wof:placetype":"venue"
},
  "geometry": {"coordinates":[11.986845,47.68549],"type":"Point"}
}