{
  "type": "Feature",
  "properties": {
    "iso:country":"DE",
    "sg:address":"Oeynhausener Str. 4",
    "sg:city":"L\u00f6hne",
    "sg:phone":"+49 5732/81141",
    "sg:postcode":"32584",
    "sg:province":"Nordrhein-Westfalen",
    "wof:name":"Kreft-bau Kg",
    "wof:placetype":"venue"
},
  "geometry": {"coordinates":[8.7208194733,52.1981735229],"type":"Point"}
}