{
  "type": "Feature",
  "properties": {
    "iso:country":"DE",
    "sg:address":"Neuenbrooker Str. 20",
    "sg:city":"Krempe",
    "sg:phone":"+49 4824/669",
    "sg:postcode":"25361",
    "sg:province":"Schleswig-Holstein",
    "wof:name":"F. Raffeldt Heissmangel",
    "wof:placetype":"venue"
},
  "geometry": {"coordinates":[9.4876213074,53.8381652832],"type":"Point"}
}