{
  "type": "Feature",
  "properties": {
    "iso:country":"DE",
    "sg:address":"Hofkammerstr. 10",
    "sg:city":"Tettnang",
    "sg:phone":"+49 4975/4255237",
    "sg:postcode":"88069",
    "sg:province":"Baden-W\u00fcrttemberg",
    "wof:name":"Turbo-music Nonnenhorn",
    "wof:placetype":"venue"
},
  "geometry": {"coordinates":[9.5872945786,47.6587371826],"type":"Point"}
}