{
  "type": "Feature",
  "properties": {
    "iso:country":"DE",
    "sg:address":"Wielandstr. 1",
    "sg:city":"Bad Oeynhausen",
    "sg:phone":"+49 5731/96370",
    "sg:postcode":"32545",
    "sg:province":"Nordrhein-Westfalen",
    "wof:name":"J.h. Natursteinimport Gmbh",
    "wof:placetype":"venue"
},
  "geometry": {"coordinates":[8.7956609726,52.1965827942],"type":"Point"}
}