{
  "type": "Feature",
  "properties": {
    "iso:country":"DE",
    "sg:address":"Adolf-Damaschke-Str. 19",
    "sg:city":"Schwalbach",
    "sg:phone":"+49 6196/1605",
    "sg:postcode":"65824",
    "sg:province":"Hessen",
    "wof:name":"Hans-volker W\u00fcnscher",
    "wof:placetype":"venue"
},
  "geometry": {"coordinates":[8.5279159546,50.1562423706],"type":"Point"}
}