{
  "type": "Feature",
  "properties": {
    "iso:country":"DE",
    "sg:address":"Oberheinrieter Str. 61",
    "sg:city":"Untergruppenbach",
    "sg:phone":"+49 7130/6431",
    "sg:postcode":"74199",
    "sg:province":"Baden-W\u00fcrttemberg",
    "wof:name":"Joachim Hutzel",
    "wof:placetype":"venue"
},
  "geometry": {"coordinates":[9.3243150711,49.0921096802],"type":"Point"}
}