{
  "type": "Feature",
  "properties": {
    "iso:country":"DE",
    "sg:address":"Am Schwanensee 11",
    "sg:city":"Lich",
    "sg:phone":"+49 6404/950902",
    "sg:postcode":"35423",
    "sg:province":"Hessen",
    "wof:name":"Heinrich Pastau Landesprodukte Und",
    "wof:placetype":"venue"
},
  "geometry": {"coordinates":[8.823157,50.520172],"type":"Point"}
}