{
  "type": "Feature",
  "properties": {
    "iso:country":"DE",
    "sg:address":"In den Wiesen 14",
    "sg:city":"Triefenstein",
    "sg:phone":"+49 9395/1031",
    "sg:postcode":"97855",
    "sg:province":"Bayern",
    "wof:name":"F. Huth",
    "wof:placetype":"venue"
},
  "geometry": {"coordinates":[9.617808,49.798649],"type":"Point"}
}