{
  "type": "Feature",
  "properties": {
    "iso:country":"DE",
    "sg:address":"Pariner Str. 80",
    "sg:city":"Bad Schwartau",
    "sg:phone":"+49 451/21700",
    "sg:postcode":"23611",
    "sg:province":"Schleswig-Holstein",
    "wof:name":"Usico Handels- Gmbh",
    "wof:placetype":"venue"
},
  "geometry": {"coordinates":[10.6927137375,53.9331207275],"type":"Point"}
}