{
  "type": "Feature",
  "properties": {
    "iso:country":"DE",
    "sg:address":"Behamstr. 18",
    "sg:city":"M\u00fcnchen",
    "sg:phone":"+49 89/565569",
    "sg:postcode":"80687",
    "sg:province":"Bayern",
    "wof:name":"Hans M\u00fcnch",
    "wof:placetype":"venue"
},
  "geometry": {"coordinates":[11.5088891983,48.1407852173],"type":"Point"}
}