{
  "type": "Feature",
  "properties": {
    "iso:country":"DE",
    "sg:address":"Hans-B\u00f6ckler-Str. 21",
    "sg:city":"Schongau",
    "sg:phone":"+49 8861/241909",
    "sg:postcode":"86956",
    "sg:province":"Bayern",
    "wof:name":"Ing. Grad. Heinrich Bartsch Architekt",
    "wof:placetype":"venue"
},
  "geometry": {"coordinates":[10.88204,47.811848],"type":"Point"}
}