{
  "type": "Feature",
  "properties": {
    "iso:country":"DE",
    "sg:address":"Bahnhofstr. 42",
    "sg:city":"Mallersdorf-Pfaffenberg",
    "sg:phone":"+49 8772/6032",
    "sg:postcode":"84066",
    "sg:province":"Bayern",
    "wof:name":"Girgner",
    "wof:placetype":"venue"
},
  "geometry": {"coordinates":[12.2555742264,48.7692909241],"type":"Point"}
}