{
  "type": "Feature",
  "properties": {
    "iso:country":"DE",
    "sg:address":"K\u00f6lnstr. 25",
    "sg:city":"Bonn",
    "sg:phone":"+49 228/652286",
    "sg:postcode":"53111",
    "sg:province":"Nordrhein-Westfalen",
    "wof:name":"Dream Sports",
    "wof:placetype":"venue"
},
  "geometry": {"coordinates":[7.100662,50.738678],"type":"Point"}
}