{
  "type": "Feature",
  "properties": {
    "iso:country":"DE",
    "sg:address":"Weyerstr. 87",
    "sg:city":"Solingen",
    "sg:phone":"+49 212/331499",
    "sg:postcode":"42697",
    "sg:province":"Nordrhein-Westfalen",
    "wof:name":"Mandelbl\u00fcte Gbr",
    "wof:placetype":"venue"
},
  "geometry": {"coordinates":[7.014143,51.169994],"type":"Point"}
}