{
  "type": "Feature",
  "properties": {
    "iso:country":"DE",
    "sg:address":"Planiger Str. 34 a",
    "sg:city":"Bad Kreuznach",
    "sg:phone":"+49 671/65425",
    "sg:postcode":"55543",
    "sg:province":"Rheinland-Pfalz",
    "wof:name":"Semaco Cosmetic Gmbh",
    "wof:placetype":"venue"
},
  "geometry": {"coordinates":[7.866487,49.8456],"type":"Point"}
}