{
  "type": "Feature",
  "properties": {
    "iso:country":"DE",
    "sg:address":"Hauptstr. 50",
    "sg:city":"Kirchwald",
    "sg:phone":"+49 2651/1520",
    "sg:postcode":"56729",
    "sg:province":"Rheinland-Pfalz",
    "wof:name":"Volksbank Mayen-mendig Eg",
    "wof:placetype":"venue"
},
  "geometry": {"coordinates":[7.15333,50.371471],"type":"Point"}
}