{
  "type": "Feature",
  "properties": {
    "iso:country":"DE",
    "sg:address":"Robert-Bosch-Str. 9",
    "sg:city":"Leutenbach",
    "sg:postcode":"71397",
    "sg:province":"Baden-W\u00fcrttemberg",
    "wof:name":"Schmider Papierh\u00fclsen Gmbh",
    "wof:placetype":"venue"
},
  "geometry": {"coordinates":[9.4130249023,48.9039878845],"type":"Point"}
}