{
  "type": "Feature",
  "properties": {
    "iso:country":"DE",
    "sg:address":"Weener Weg 36",
    "sg:city":"Aurich",
    "sg:phone":"+49 4941/3178",
    "sg:postcode":"26605",
    "sg:province":"Niedersachsen",
    "wof:name":"Gerhard Carstens",
    "wof:placetype":"venue"
},
  "geometry": {"coordinates":[7.5268740654,53.4335365295],"type":"Point"}
}