{
  "type": "Feature",
  "properties": {
    "iso:country":"DE",
    "sg:address":"Karl-Marx-Allee 112",
    "sg:city":"Berlin",
    "sg:phone":"+49 30/2946865",
    "sg:postcode":"10243",
    "sg:province":"Berlin",
    "wof:name":"Hartmut Spaethe",
    "wof:placetype":"venue"
},
  "geometry": {"coordinates":[13.445976,52.516396],"type":"Point"}
}