{
  "type": "Feature",
  "properties": {
    "iso:country":"DE",
    "sg:address":"Friedrich-Ebert-Str. 31-37",
    "sg:city":"Dinslaken",
    "sg:phone":"+49 4920/644150",
    "sg:postcode":"46535",
    "sg:province":"Nordrhein-Westfalen",
    "wof:name":"Sparkasse Dinslaken - Voerde - H\u00dcnxe",
    "wof:placetype":"venue"
},
  "geometry": {"coordinates":[6.736083,51.565071],"type":"Point"}
}