{
  "type": "Feature",
  "properties": {
    "iso:country":"DE",
    "sg:address":"Auf der Blo\u00df 16",
    "sg:city":"Reutlingen",
    "sg:postcode":"72762",
    "sg:province":"Baden-W\u00fcrttemberg",
    "wof:name":"P. Kimmerle-usuner Architektin",
    "wof:placetype":"venue"
},
  "geometry": {"coordinates":[9.193566,48.489136],"type":"Point"}
}