{
  "type": "Feature",
  "properties": {
    "iso:country":"DE",
    "sg:address":"Westerstr. 32",
    "sg:city":"Bremen",
    "sg:postcode":"28199",
    "sg:province":"Bremen",
    "wof:name":"Huchtinger Grundst\u00fccks- Gesellschaft Mbh",
    "wof:placetype":"venue"
},
  "geometry": {"coordinates":[8.7975502014,53.0732955933],"type":"Point"}
}