{
  "type": "Feature",
  "properties": {
    "iso:country":"DE",
    "sg:address":"Friedrich-List-Str. 4",
    "sg:city":"Ebersbach",
    "sg:phone":"+49 7163/2552",
    "sg:postcode":"73061",
    "sg:province":"Baden-W\u00fcrttemberg",
    "wof:name":"G\u00fcnther Koch Ingenieur",
    "wof:placetype":"venue"
},
  "geometry": {"coordinates":[9.5344934464,48.715587616],"type":"Point"}
}