{
  "type": "Feature",
  "properties": {
    "iso:country":"DE",
    "sg:address":"Viktoriastr. 16",
    "sg:city":"Duisburg",
    "sg:phone":"+49 2065/48617",
    "sg:postcode":"47229",
    "sg:province":"Nordrhein-Westfalen",
    "wof:name":"Klaus Sp\u00f6rkmann Heilpraktiker",
    "wof:placetype":"venue"
},
  "geometry": {"coordinates":[6.7089929581,51.3920898438],"type":"Point"}
}