{
  "type": "Feature",
  "properties": {
    "iso:country":"DE",
    "sg:address":"Rodinger Str. 12",
    "sg:city":"Cham",
    "sg:postcode":"93413",
    "sg:province":"Bayern",
    "wof:name":"Alpha Grundbesitz-gmbh",
    "wof:placetype":"venue"
},
  "geometry": {"coordinates":[12.6587057114,49.2027778625],"type":"Point"}
}