{
  "type": "Feature",
  "properties": {
    "iso:country":"DE",
    "sg:address":"Carnaper Str. 8",
    "sg:city":"Wuppertal",
    "sg:phone":"+49 202/507403",
    "sg:postcode":"42283",
    "sg:province":"Nordrhein-Westfalen",
    "wof:name":"Spormann Altenheim",
    "wof:placetype":"venue"
},
  "geometry": {"coordinates":[7.191752,51.272778],"type":"Point"}
}