{
  "type": "Feature",
  "properties": {
    "iso:country":"DE",
    "sg:address":"Graeffstr. 5",
    "sg:city":"K\u00f6ln",
    "sg:phone":"+49 221/574020",
    "sg:postcode":"50823",
    "sg:province":"Nordrhein-Westfalen",
    "wof:name":"Aew Control Projektmanagement Gmbh",
    "wof:placetype":"venue"
},
  "geometry": {"coordinates":[6.933021,50.949951],"type":"Point"}
}