{
  "type": "Feature",
  "properties": {
    "iso:country":"DE",
    "sg:address":"Quedlinburger Tor 8",
    "sg:city":"Wegeleben",
    "sg:phone":"+49 39423/254",
    "sg:postcode":"38828",
    "sg:province":"Sachsen-Anhalt",
    "wof:name":"Zur Tanne Inh. Marianne Wolf",
    "wof:placetype":"venue"
},
  "geometry": {"coordinates":[11.1726579666,51.8822402954],"type":"Point"}
}