{
  "type": "Feature",
  "properties": {
    "iso:country":"DE",
    "sg:address":"Lothringerstr. 83",
    "sg:city":"Aachen",
    "sg:phone":"+49 241/505353",
    "sg:postcode":"52070",
    "sg:province":"Nordrhein-Westfalen",
    "wof:name":"Psycholog. Beratungsstelle F. Studenten",
    "wof:placetype":"venue"
},
  "geometry": {"coordinates":[6.098498,50.770172],"type":"Point"}
}