{
  "type": "Feature",
  "properties": {
    "iso:country":"DE",
    "sg:address":"Hamburger Str. 21",
    "sg:city":"Gr\u00f6mitz",
    "sg:phone":"+49 4562/8657",
    "sg:postcode":"23743",
    "sg:province":"Schleswig-Holstein",
    "wof:name":"G\u00e4stehaus Lehmann",
    "wof:placetype":"venue"
},
  "geometry": {"coordinates":[10.9725961685,54.1525421143],"type":"Point"}
}