{
  "type": "Feature",
  "properties": {
    "iso:country":"DE",
    "sg:address":"Munkmarscher Chaussee 42",
    "sg:city":"Sylt-Ost",
    "sg:phone":"+49 4651/31621",
    "sg:postcode":"25980",
    "sg:province":"Schleswig-Holstein",
    "wof:name":"Hans-j\u00fcrgen Jessen",
    "wof:placetype":"venue"
},
  "geometry": {"coordinates":[8.365971,54.898926],"type":"Point"}
}