{
  "type": "Feature",
  "properties": {
    "iso:country":"DE",
    "sg:address":"Bergstr. 3",
    "sg:city":"Bopfingen",
    "sg:phone":"+49 7362/21757",
    "sg:postcode":"73441",
    "sg:province":"Baden-W\u00fcrttemberg",
    "wof:name":"S. Graf",
    "wof:placetype":"venue"
},
  "geometry": {"coordinates":[10.3564128876,48.852432251],"type":"Point"}
}