{
  "type": "Feature",
  "properties": {
    "iso:country":"DE",
    "sg:address":"L\u00f6hner Str. 69",
    "sg:city":"L\u00f6hne",
    "sg:phone":"+49 5731/81839",
    "sg:postcode":"32584",
    "sg:province":"Nordrhein-Westfalen",
    "wof:name":"Gohfeld-grill",
    "wof:placetype":"venue"
},
  "geometry": {"coordinates":[8.7724094391,52.2022857666],"type":"Point"}
}