{
  "type": "Feature",
  "properties": {
    "iso:country":"DE",
    "sg:address":"Alte Br\u00fcckenstr. 4",
    "sg:city":"Witzenhausen",
    "sg:phone":"+49 5542/5887",
    "sg:postcode":"37218",
    "sg:province":"Hessen",
    "wof:name":"G\u00fcnter Ludwig",
    "wof:placetype":"venue"
},
  "geometry": {"coordinates":[9.802824,51.377445],"type":"Point"}
}