{
  "type": "Feature",
  "properties": {
    "iso:country":"DE",
    "sg:address":"Magstadter Str. 4",
    "sg:city":"Renningen",
    "sg:phone":"+49 7159/7784",
    "sg:postcode":"71272",
    "sg:province":"Baden-W\u00fcrttemberg",
    "wof:name":"Magstadter Tor",
    "wof:placetype":"venue"
},
  "geometry": {"coordinates":[8.9372,48.763519],"type":"Point"}
}