{
  "type": "Feature",
  "properties": {
    "iso:country":"DE",
    "sg:address":"Glash\u00fctter Weg 31",
    "sg:city":"Stuttgart",
    "sg:phone":"+49 711/7286172",
    "sg:postcode":"70567",
    "sg:province":"Baden-W\u00fcrttemberg",
    "wof:name":"Bernd Schieber",
    "wof:placetype":"venue"
},
  "geometry": {"coordinates":[9.156312,48.725704],"type":"Point"}
}