{
  "type": "Feature",
  "properties": {
    "iso:country":"DE",
    "sg:address":"Benrather Schlo\u00dfallee 129",
    "sg:city":"D\u00fcsseldorf",
    "sg:phone":"+49 211/7110935",
    "sg:postcode":"40212",
    "sg:province":"Nordrhein-Westfalen",
    "wof:name":"Deutsche Bank Ag",
    "wof:placetype":"venue"
},
  "geometry": {"coordinates":[6.873387,51.16238],"type":"Point"}
}