{
  "type": "Feature",
  "properties": {
    "iso:country":"DE",
    "sg:address":"Bodanstr. 29",
    "sg:city":"Konstanz",
    "sg:phone":"+49 7531/21320",
    "sg:postcode":"78462",
    "sg:province":"Baden-W\u00fcrttemberg",
    "wof:name":"Ph. Piroth Inh. E. B\u00f6hler",
    "wof:placetype":"venue"
},
  "geometry": {"coordinates":[9.17207,47.658207],"type":"Point"}
}