{
  "type": "Feature",
  "properties": {
    "iso:country":"DE",
    "sg:address":"Markt 2",
    "sg:city":"Heide",
    "sg:phone":"+49 481/61560",
    "sg:postcode":"25746",
    "sg:province":"Schleswig-Holstein",
    "wof:name":"L & B Mode",
    "wof:placetype":"venue"
},
  "geometry": {"coordinates":[9.094791,54.195656],"type":"Point"}
}