{
  "type": "Feature",
  "properties": {
    "iso:country":"DE",
    "sg:address":"Am Honigberg 28",
    "sg:city":"Luckenwalde",
    "sg:phone":"+49 3371/610405",
    "sg:postcode":"14943",
    "sg:province":"Brandenburg",
    "wof:name":"Bauservice Reiner Ma\u00df",
    "wof:placetype":"venue"
},
  "geometry": {"coordinates":[13.1935634613,52.0889816284],"type":"Point"}
}