{
  "type": "Feature",
  "properties": {
    "iso:country":"DE",
    "sg:address":"Murgtalstr. 167",
    "sg:city":"Baiersbronn",
    "sg:phone":"+49 7442/2277",
    "sg:postcode":"72270",
    "sg:province":"Baden-W\u00fcrttemberg",
    "wof:name":"Hotel Sonne-post Sigwart Fleischle",
    "wof:placetype":"venue"
},
  "geometry": {"coordinates":[8.3849620819,48.4759025574],"type":"Point"}
}