{
  "type": "Feature",
  "properties": {
    "iso:country":"DE",
    "sg:address":"Weingartenstr. 11",
    "sg:city":"Wiesbaden",
    "sg:phone":"+49 611/9507238",
    "sg:postcode":"65207",
    "sg:province":"Hessen",
    "wof:name":"Peters Immobilienmakler",
    "wof:placetype":"venue"
},
  "geometry": {"coordinates":[8.3281059265,50.0794944763],"type":"Point"}
}