{
  "type": "Feature",
  "properties": {
    "iso:country":"DE",
    "sg:address":"Reinhold-Frank-Str. 48 b",
    "sg:city":"Karlsruhe",
    "sg:phone":"+49 721/18190",
    "sg:postcode":"76133",
    "sg:province":"Baden-W\u00fcrttemberg",
    "wof:name":"Harrer Ingenieure Gesellschaft Beratender Ingenieure Vbi Mbh",
    "wof:placetype":"venue"
},
  "geometry": {"coordinates":[8.3876686096,49.0108604431],"type":"Point"}
}