{
  "type": "Feature",
  "properties": {
    "iso:country":"DE",
    "sg:address":"Leonhardtstr. 21",
    "sg:city":"Celle",
    "sg:phone":"+49 5141/86540",
    "sg:postcode":"29227",
    "sg:province":"Niedersachsen",
    "wof:name":"S. Richter",
    "wof:placetype":"venue"
},
  "geometry": {"coordinates":[10.0949993134,52.6038703918],"type":"Point"}
}