{
  "type": "Feature",
  "properties": {
    "iso:country":"DE",
    "sg:address":"Hohensyburgstr. 2",
    "sg:city":"K\u00f6ln",
    "sg:phone":"+49 221/692968",
    "sg:postcode":"51109",
    "sg:province":"Nordrhein-Westfalen",
    "wof:name":"Clownerie",
    "wof:placetype":"venue"
},
  "geometry": {"coordinates":[7.0403971672,50.9511184692],"type":"Point"}
}