{
  "type": "Feature",
  "properties": {
    "iso:country":"DE",
    "sg:address":"Essiger Str. 26",
    "sg:city":"Stolberg",
    "sg:phone":"+49 2402/30231",
    "sg:postcode":"52223",
    "sg:province":"Nordrhein-Westfalen",
    "wof:name":"K.-h. Winter",
    "wof:placetype":"venue"
},
  "geometry": {"coordinates":[6.218,50.746269],"type":"Point"}
}