{
  "type": "Feature",
  "properties": {
    "iso:country":"DE",
    "sg:address":"Dorfstr. 27",
    "sg:city":"Prohn",
    "sg:phone":"+49 38323/849",
    "sg:postcode":"18445",
    "sg:province":"Mecklenburg-Vorpommern",
    "wof:name":"Fliesenhof Pautz Gmbh",
    "wof:placetype":"venue"
},
  "geometry": {"coordinates":[12.9881944656,54.3708724976],"type":"Point"}
}