{
  "type": "Feature",
  "properties": {
    "iso:country":"DE",
    "sg:address":"Zeughausstr. 10",
    "sg:city":"Meschede",
    "sg:phone":"+49 291/1714",
    "sg:postcode":"59872",
    "sg:province":"Nordrhein-Westfalen",
    "wof:name":"Blumenhaus Wamser E. Kfr. Inh. B\u00e4rbel Dierk-schulz",
    "wof:placetype":"venue"
},
  "geometry": {"coordinates":[8.28526,51.346069],"type":"Point"}
}