{
  "type": "Feature",
  "properties": {
    "iso:country":"DE",
    "sg:address":"Werastr. 45",
    "sg:city":"Reutlingen",
    "sg:phone":"+49 7121/92770",
    "sg:postcode":"72764",
    "sg:province":"Baden-W\u00fcrttemberg",
    "wof:name":"K\u00fchner Industrie- Vertretungen Gmbh",
    "wof:placetype":"venue"
},
  "geometry": {"coordinates":[9.2120065689,48.4801063538],"type":"Point"}
}