{
  "type": "Feature",
  "properties": {
    "iso:country":"DE",
    "sg:address":"Hauptstr. 255",
    "sg:city":"Bergisch Gladbach",
    "sg:phone":"+49 2202/37139",
    "sg:postcode":"51465",
    "sg:province":"Nordrhein-Westfalen",
    "wof:name":"Edith Und D. Fiorentino",
    "wof:placetype":"venue"
},
  "geometry": {"coordinates":[7.1352090836,50.9917678833],"type":"Point"}
}