{
  "type": "Feature",
  "properties": {
    "iso:country":"DE",
    "sg:address":"Burchard-Retschy-Ring 1",
    "sg:city":"Lehrte",
    "sg:phone":"+49 5132/585691",
    "sg:postcode":"31275",
    "sg:province":"Niedersachsen",
    "wof:name":"Purkus Bauelemente Handelsgesellschaft Mbh",
    "wof:placetype":"venue"
},
  "geometry": {"coordinates":[9.964831,52.385933],"type":"Point"}
}