{
  "type": "Feature",
  "properties": {
    "iso:country":"DE",
    "sg:address":"Drosselweg 23",
    "sg:city":"Rain",
    "sg:postcode":"86641",
    "sg:province":"Bayern",
    "wof:name":"Emil Hahn Ingenieur",
    "wof:placetype":"venue"
},
  "geometry": {"coordinates":[10.9136285782,48.6861457825],"type":"Point"}
}