{
  "type": "Feature",
  "properties": {
    "iso:country":"DE",
    "sg:address":"Ulmenstr. 11",
    "sg:city":"Rohrdorf",
    "sg:phone":"+49 8031/73853",
    "sg:postcode":"83101",
    "sg:province":"Bayern",
    "wof:name":"Walter Schwangler",
    "wof:placetype":"venue"
},
  "geometry": {"coordinates":[12.150576,47.824425],"type":"Point"}
}