{
  "type": "Feature",
  "properties": {
    "iso:country":"DE",
    "sg:address":"Fuhrparkstr. 16-20",
    "sg:city":"Hagen",
    "sg:postcode":"58089",
    "sg:province":"Nordrhein-Westfalen",
    "wof:name":"Hui Gmbh",
    "wof:placetype":"venue"
},
  "geometry": {"coordinates":[7.4570322037,51.3777503967],"type":"Point"}
}