{
  "type": "Feature",
  "properties": {
    "iso:country":"DE",
    "sg:address":"Bleckenweg 11",
    "sg:city":"Celle",
    "sg:phone":"+49 5141/85535",
    "sg:postcode":"29227",
    "sg:province":"Niedersachsen",
    "wof:name":"E. Tanner",
    "wof:placetype":"venue"
},
  "geometry": {"coordinates":[10.118635,52.600403],"type":"Point"}
}