{
  "type": "Feature",
  "properties": {
    "iso:country":"DE",
    "sg:address":"Schriesheimer Str. 32",
    "sg:city":"Ladenburg",
    "sg:phone":"+49 6203/2291",
    "sg:postcode":"68526",
    "sg:province":"Baden-W\u00fcrttemberg",
    "wof:name":"Willi Lowinger",
    "wof:placetype":"venue"
},
  "geometry": {"coordinates":[8.6182556152,49.471950531],"type":"Point"}
}