{
  "type": "Feature",
  "properties": {
    "iso:country":"DE",
    "sg:address":"Lochhauser Str. 57",
    "sg:city":"Puchheim",
    "sg:phone":"+49 89/803610",
    "sg:postcode":"82178",
    "sg:province":"Bayern",
    "wof:name":"La Colomba",
    "wof:placetype":"venue"
},
  "geometry": {"coordinates":[11.3622579575,48.1757392883],"type":"Point"}
}