{
  "type": "Feature",
  "properties": {
    "iso:country":"DE",
    "sg:address":"Th\u00fcringer-Wald-Str. 72",
    "sg:city":"Stuttgart",
    "sg:phone":"+49 711/8892405",
    "sg:postcode":"70469",
    "sg:province":"Baden-W\u00fcrttemberg",
    "wof:name":"Karl Sch\u00e4fer Architekt",
    "wof:placetype":"venue"
},
  "geometry": {"coordinates":[9.138538,48.813801],"type":"Point"}
}