{
  "type": "Feature",
  "properties": {
    "iso:country":"DE",
    "sg:address":"Hasenb\u00fchlweg 46",
    "sg:city":"Ulm",
    "sg:phone":"+49 731/62325",
    "sg:postcode":"89081",
    "sg:province":"Baden-W\u00fcrttemberg",
    "wof:name":"Walter Sp\u00e4th \u00d6fen Und Herde",
    "wof:placetype":"venue"
},
  "geometry": {"coordinates":[9.9911289215,48.4486961365],"type":"Point"}
}