{
  "type": "Feature",
  "properties": {
    "iso:country":"DE",
    "sg:address":"Turmstr. 5",
    "sg:city":"Monheim",
    "sg:phone":"+49 2173/95200",
    "sg:postcode":"40789",
    "sg:province":"Nordrhein-Westfalen",
    "wof:name":"Monheimer Versorgungs- Und Verkehrs-gmbh",
    "wof:placetype":"venue"
},
  "geometry": {"coordinates":[6.88299,51.091244],"type":"Point"}
}