{
  "type": "Feature",
  "properties": {
    "iso:country":"DE",
    "sg:address":"Schwedenstr. 2a",
    "sg:city":"Kronach",
    "sg:phone":"+49 9261/5690",
    "sg:postcode":"96317",
    "sg:province":"Bayern",
    "wof:name":"Bayerische Vereinsbank Ag",
    "wof:placetype":"venue"
},
  "geometry": {"coordinates":[11.323172,50.23978],"type":"Point"}
}