{
  "type": "Feature",
  "properties": {
    "iso:country":"DE",
    "sg:address":"Schillerstr. 10",
    "sg:city":"Lahr",
    "sg:phone":"+49 7821/22379",
    "sg:postcode":"77933",
    "sg:province":"Baden-W\u00fcrttemberg",
    "wof:name":"K. K\u00e4lble Augenoptiker",
    "wof:placetype":"venue"
},
  "geometry": {"coordinates":[7.8700919151,48.3403205872],"type":"Point"}
}