{
  "type": "Feature",
  "properties": {
    "iso:country":"DE",
    "sg:address":"Hildener Str. 25",
    "sg:city":"D\u00fcsseldorf",
    "sg:phone":"+49 211/713497",
    "sg:postcode":"40597",
    "sg:province":"Nordrhein-Westfalen",
    "wof:name":"Peter Lampenscherf",
    "wof:placetype":"venue"
},
  "geometry": {"coordinates":[6.8916797638,51.1610603333],"type":"Point"}
}