{
  "type": "Feature",
  "properties": {
    "iso:country":"DE",
    "sg:address":"Berghamer Str. 19",
    "sg:city":"Obing",
    "sg:phone":"+49 8624/89690",
    "sg:postcode":"83119",
    "sg:province":"Bayern",
    "wof:name":"Cover Tex Gmbh",
    "wof:placetype":"venue"
},
  "geometry": {"coordinates":[12.414044,47.99831],"type":"Point"}
}