{
  "type": "Feature",
  "properties": {
    "iso:country":"DE",
    "sg:address":"Am Rathaus 8",
    "sg:city":"Hauzenberg",
    "sg:phone":"+49 8586/1236",
    "sg:postcode":"94051",
    "sg:province":"Bayern",
    "wof:name":"Hermann Anetzberger",
    "wof:placetype":"venue"
},
  "geometry": {"coordinates":[13.6233453751,48.6523513794],"type":"Point"}
}