{
  "type": "Feature",
  "properties": {
    "iso:country":"DE",
    "sg:address":"Robert-Koch-Str. 7",
    "sg:city":"Oerlinghausen",
    "sg:phone":"+49 5202/4063",
    "sg:postcode":"33813",
    "sg:province":"Nordrhein-Westfalen",
    "wof:name":"I. Pietsch",
    "wof:placetype":"venue"
},
  "geometry": {"coordinates":[8.659683,51.954472],"type":"Point"}
}