{
  "type": "Feature",
  "properties": {
    "iso:country":"DE",
    "sg:address":"B\u00f6blinger Str. 20",
    "sg:city":"Stuttgart",
    "sg:phone":"+49 711/6409155",
    "sg:postcode":"70178",
    "sg:province":"Baden-W\u00fcrttemberg",
    "wof:name":"Schatz-truhe Textil-handels Gmbh",
    "wof:placetype":"venue"
},
  "geometry": {"coordinates":[9.165384,48.764034],"type":"Point"}
}