{
  "type": "Feature",
  "properties": {
    "iso:country":"DE",
    "sg:address":"Bahnstr. 16",
    "sg:city":"Kerpen",
    "sg:postcode":"50170",
    "sg:province":"Nordrhein-Westfalen",
    "wof:name":"Beerdigungsinstitut Vinzenz Kick",
    "wof:placetype":"venue"
},
  "geometry": {"coordinates":[6.579575,50.860706],"type":"Point"}
}