{
  "type": "Feature",
  "properties": {
    "iso:country":"DE",
    "sg:address":"Otto-Braun-Str. 31",
    "sg:city":"Berlin",
    "sg:phone":"+49 30/2413366",
    "sg:postcode":"10178",
    "sg:province":"Berlin",
    "wof:name":"Klaus Taubert",
    "wof:placetype":"venue"
},
  "geometry": {"coordinates":[13.4191026688,52.5249671936],"type":"Point"}
}