{
  "type": "Feature",
  "properties": {
    "iso:country":"DE",
    "sg:address":"Varreler Kirchweg 33",
    "sg:city":"Wagenfeld",
    "sg:phone":"+49 5774/448",
    "sg:postcode":"49419",
    "sg:province":"Niedersachsen",
    "wof:name":"Gerhard Skoda",
    "wof:placetype":"venue"
},
  "geometry": {"coordinates":[8.704597,52.544022],"type":"Point"}
}