{
  "type": "Feature",
  "properties": {
    "iso:country":"DE",
    "sg:address":"Frauenschuhweg 22b",
    "sg:city":"Geretsried",
    "sg:phone":"+49 8171/96036",
    "sg:postcode":"82538",
    "sg:province":"Bayern",
    "wof:name":"Estee Lauder Cosmetics Gmbh",
    "wof:placetype":"venue"
},
  "geometry": {"coordinates":[11.468702,47.887684],"type":"Point"}
}