{
  "type": "Feature",
  "properties": {
    "iso:country":"DE",
    "sg:address":"Am Hohen Gstad 12",
    "sg:city":"G\u00fcnzburg",
    "sg:phone":"+49 8221/4089",
    "sg:postcode":"89312",
    "sg:province":"Bayern",
    "wof:name":"Dipl.ing. Andreas Sedlmeier Architekt",
    "wof:placetype":"venue"
},
  "geometry": {"coordinates":[10.279487,48.447559],"type":"Point"}
}