{
  "type": "Feature",
  "properties": {
    "iso:country":"DE",
    "sg:address":"Hagdornstr. 10",
    "sg:city":"Xanten",
    "sg:phone":"+49 2801/740",
    "sg:postcode":"46509",
    "sg:province":"Nordrhein-Westfalen",
    "wof:name":"Wessel Verm\u00f6gensverwaltungs Gmbh",
    "wof:placetype":"venue"
},
  "geometry": {"coordinates":[6.4389438629,51.65782547],"type":"Point"}
}