{
  "type": "Feature",
  "properties": {
    "iso:country":"DE",
    "sg:address":"Jakobstr. 75",
    "sg:city":"Aachen",
    "sg:phone":"+49 241/406013",
    "sg:postcode":"52064",
    "sg:province":"Nordrhein-Westfalen",
    "wof:name":"Jakob-imbiss",
    "wof:placetype":"venue"
},
  "geometry": {"coordinates":[6.0773310661,50.772605896],"type":"Point"}
}