{
  "type": "Feature",
  "properties": {
    "iso:country":"DE",
    "sg:address":"Phantasiestr. 8",
    "sg:city":"M\u00fcnchen",
    "sg:phone":"+49 89/45301891",
    "sg:postcode":"81827",
    "sg:province":"Bayern",
    "wof:name":"Helga Walchner",
    "wof:placetype":"venue"
},
  "geometry": {"coordinates":[11.702482,48.113693],"type":"Point"}
}