{
  "type": "Feature",
  "properties": {
    "iso:country":"DE",
    "sg:address":"Batschkastr. 10",
    "sg:city":"Ludwigshafen",
    "sg:phone":"+49 621/554362",
    "sg:postcode":"67065",
    "sg:province":"Rheinland-Pfalz",
    "wof:name":"Otto Hoffmann",
    "wof:placetype":"venue"
},
  "geometry": {"coordinates":[8.400510788,49.4765319824],"type":"Point"}
}