{
  "type": "Feature",
  "properties": {
    "iso:country":"DE",
    "sg:address":"\u00c4gidienmarkt 14",
    "sg:city":"Braunschweig",
    "sg:phone":"+49 531/43703",
    "sg:postcode":"38100",
    "sg:province":"Niedersachsen",
    "wof:name":"Ahrenbeck Immobilien",
    "wof:placetype":"venue"
},
  "geometry": {"coordinates":[10.5252828598,52.2601470947],"type":"Point"}
}