{
  "type": "Feature",
  "properties": {
    "iso:country":"DE",
    "sg:address":"Kirchgasse",
    "sg:city":"Kr\u00f6lpa",
    "sg:postcode":"07387",
    "sg:province":"Th\u00fcringen",
    "wof:name":"B. Bartsch Architekt",
    "wof:placetype":"venue"
},
  "geometry": {"coordinates":[11.535006,50.679245],"type":"Point"}
}