{
  "type": "Feature",
  "properties": {
    "iso:country":"DE",
    "sg:address":"Niedernstr. 6",
    "sg:city":"L\u00fcbbecke",
    "sg:phone":"+49 5741/8786",
    "sg:postcode":"32312",
    "sg:province":"Nordrhein-Westfalen",
    "wof:name":"Peter Babilon",
    "wof:placetype":"venue"
},
  "geometry": {"coordinates":[8.6177759171,52.3043670654],"type":"Point"}
}