{
  "type": "Feature",
  "properties": {
    "iso:country":"DE",
    "sg:address":"Endenicher Str. 303",
    "sg:city":"Bonn",
    "sg:phone":"+49 228/5269910",
    "sg:postcode":"53121",
    "sg:province":"Nordrhein-Westfalen",
    "wof:name":"Komline-gmbh",
    "wof:placetype":"venue"
},
  "geometry": {"coordinates":[7.0734238625,50.7274894714],"type":"Point"}
}