{
  "type": "Feature",
  "properties": {
    "iso:country":"DE",
    "sg:address":"August-Bebel-Str. 4",
    "sg:city":"Jocketa",
    "sg:phone":"+49 37439/6814",
    "sg:postcode":"08543",
    "sg:province":"Sachsen",
    "wof:name":"Gerd Robaschik",
    "wof:placetype":"venue"
},
  "geometry": {"coordinates":[12.172524,50.554276],"type":"Point"}
}