{
  "type": "Feature",
  "properties": {
    "iso:country":"DE",
    "sg:address":"Steigestr. 66",
    "sg:city":"Eberbach",
    "sg:phone":"+49 6271/3419",
    "sg:postcode":"69412",
    "sg:province":"Baden-W\u00fcrttemberg",
    "wof:name":"Joachim K\u00f6nig",
    "wof:placetype":"venue"
},
  "geometry": {"coordinates":[8.988325,49.47665],"type":"Point"}
}