{
  "type": "Feature",
  "properties": {
    "iso:country":"DE",
    "sg:address":"Schanzenbachstr. 4",
    "sg:city":"M\u00fcnchen",
    "sg:phone":"+49 89/778295",
    "sg:postcode":"81371",
    "sg:province":"Bayern",
    "wof:name":"Nikolaus Klein",
    "wof:placetype":"venue"
},
  "geometry": {"coordinates":[11.5474376678,48.1143875122],"type":"Point"}
}