{
  "type": "Feature",
  "properties": {
    "iso:country":"DE",
    "sg:address":"Schillerstr. 22",
    "sg:city":"Bietigheim-Bissingen",
    "sg:phone":"+49 7142/31077",
    "sg:postcode":"74321",
    "sg:province":"Baden-W\u00fcrttemberg",
    "wof:name":"Peter Laub",
    "wof:placetype":"venue"
},
  "geometry": {"coordinates":[9.100386,48.943253],"type":"Point"}
}