{
  "type": "Feature",
  "properties": {
    "iso:country":"DE",
    "sg:address":"M\u00fchlenstr. 3",
    "sg:city":"M\u00f6ckern",
    "sg:postcode":"39291",
    "sg:province":"Sachsen-Anhalt",
    "wof:name":"Ortloff Stahlbau Gmbh",
    "wof:placetype":"venue"
},
  "geometry": {"coordinates":[11.940797,52.142811],"type":"Point"}
}