{
  "type": "Feature",
  "properties": {
    "iso:country":"DE",
    "sg:address":"Alte Frachtstr. 16",
    "sg:city":"Neuekrug",
    "sg:phone":"+49 3902/60440",
    "sg:postcode":"29413",
    "sg:province":"Sachsen-Anhalt",
    "wof:name":"Flechtner",
    "wof:placetype":"venue"
},
  "geometry": {"coordinates":[10.8025655746,52.7705802917],"type":"Point"}
}