{
  "type": "Feature",
  "properties": {
    "iso:country":"DE",
    "sg:address":"Am Langen St\u00fcck 6",
    "sg:city":"Sailauf",
    "sg:phone":"+49 6093/93178",
    "sg:postcode":"63877",
    "sg:province":"Bayern",
    "wof:name":"T. K\u00f6rbel Anlageberater",
    "wof:placetype":"venue"
},
  "geometry": {"coordinates":[9.2557029724,50.0221252441],"type":"Point"}
}