{
  "type": "Feature",
  "properties": {
    "iso:country":"DE",
    "sg:address":"Elbuferstr. 56",
    "sg:city":"Bleckede",
    "sg:phone":"+49 5857/241",
    "sg:postcode":"21354",
    "sg:province":"Niedersachsen",
    "wof:name":"Otto Pabst",
    "wof:placetype":"venue"
},
  "geometry": {"coordinates":[10.713296,53.349617],"type":"Point"}
}