{
  "type": "Feature",
  "properties": {
    "iso:country":"DE",
    "sg:address":"Am Rheinbach 6",
    "sg:city":"Delligsen",
    "sg:phone":"+49 5187/2304",
    "sg:postcode":"31073",
    "sg:province":"Niedersachsen",
    "wof:name":"E. Wittkuhn",
    "wof:placetype":"venue"
},
  "geometry": {"coordinates":[9.8543796539,51.9111938477],"type":"Point"}
}