{
  "type": "Feature",
  "properties": {
    "iso:country":"DE",
    "sg:address":"Brehnaer Str 3",
    "sg:city":"Bitterfeld",
    "sg:phone":"+49 3493/60430",
    "sg:postcode":"06749",
    "sg:province":"Sachsen-Anhalt",
    "wof:name":"Meba Bitterfeld Gmbh",
    "wof:placetype":"venue"
},
  "geometry": {"coordinates":[12.313915,51.615925],"type":"Point"}
}