{
  "type": "Feature",
  "properties": {
    "iso:country":"DE",
    "sg:address":"Herzogin-Elisabeth-Str. 81",
    "sg:city":"Braunschweig",
    "sg:phone":"+49 531/345314",
    "sg:postcode":"38104",
    "sg:province":"Niedersachsen",
    "wof:name":"Sportheim Franzsches Feld",
    "wof:placetype":"venue"
},
  "geometry": {"coordinates":[10.5540895462,52.2612609863],"type":"Point"}
}