{
  "type": "Feature",
  "properties": {
    "iso:country":"DE",
    "sg:address":"B\u00fcrgermeister-Smidt-Str. 140",
    "sg:city":"Bremerhaven",
    "sg:phone":"+49 471/413068",
    "sg:postcode":"27568",
    "sg:province":"Bremen",
    "wof:name":"Petra Stelljes Rechtsanw\u00e4ltin",
    "wof:placetype":"venue"
},
  "geometry": {"coordinates":[8.5734586716,53.549156189],"type":"Point"}
}