{
  "type": "Feature",
  "properties": {
    "iso:country":"DE",
    "sg:address":"Beim Gro\u00dfen Markstein 7",
    "sg:city":"Neckarwestheim",
    "sg:phone":"+49 7133/21878",
    "sg:postcode":"74382",
    "sg:province":"Baden-W\u00fcrttemberg",
    "wof:name":"Jhk Hack Fliesen Und Bord\u00fcren Gmbh",
    "wof:placetype":"venue"
},
  "geometry": {"coordinates":[9.1859750748,49.0491371155],"type":"Point"}
}