{
  "type": "Feature",
  "properties": {
    "iso:country":"DE",
    "sg:address":"Am Schaftrieb 18",
    "sg:city":"Linsengericht",
    "sg:phone":"+49 6051/969818",
    "sg:postcode":"63589",
    "sg:province":"Hessen",
    "wof:name":"K. Fritsch",
    "wof:placetype":"venue"
},
  "geometry": {"coordinates":[9.19613,50.18235],"type":"Point"}
}