{
  "type": "Feature",
  "properties": {
    "iso:country":"DE",
    "sg:address":"Kastanienstr. 9",
    "sg:city":"Dallgow",
    "sg:phone":"+49 3322/215389",
    "sg:postcode":"14624",
    "sg:province":"Brandenburg",
    "wof:name":"M\u00fcller-andree",
    "wof:placetype":"venue"
},
  "geometry": {"coordinates":[13.05508,52.508881],"type":"Point"}
}