{
  "type": "Feature",
  "properties": {
    "iso:country":"DE",
    "sg:address":"Pomona 6",
    "sg:city":"Neuss",
    "sg:phone":"+49 2131/43877",
    "sg:postcode":"41464",
    "sg:province":"Nordrhein-Westfalen",
    "wof:name":"Rhein. Handels Gmbh & Co. Kg",
    "wof:placetype":"venue"
},
  "geometry": {"coordinates":[6.6912407875,51.180973053],"type":"Point"}
}