{
  "type": "Feature",
  "properties": {
    "iso:country":"DE",
    "sg:address":"Frankfurter Str. 309",
    "sg:city":"Kassel",
    "sg:phone":"+49 561/41949",
    "sg:postcode":"34134",
    "sg:province":"Hessen",
    "wof:name":"Pelikan-apotheke",
    "wof:placetype":"venue"
},
  "geometry": {"coordinates":[9.466743,51.282406],"type":"Point"}
}