{
  "type": "Feature",
  "properties": {
    "iso:country":"DE",
    "sg:address":"Rechbergstra\u00dfe 3",
    "sg:city":"Denkendorf",
    "sg:phone":"+49 711",
    "sg:postcode":"73770",
    "sg:province":"Baden-W\u00fcrttemberg",
    "wof:name":"Festo Didactic",
    "wof:placetype":"venue"
},
  "geometry": {"coordinates":[9.311439,48.702316],"type":"Point"}
}