{
  "type": "Feature",
  "properties": {
    "iso:country":"DE",
    "sg:address":"S\u00fcdring 8",
    "sg:city":"Markkleeberg",
    "sg:phone":"+49 34297/729160",
    "sg:postcode":"04416",
    "sg:province":"Sachsen",
    "wof:name":"Wlw Wagner Leisner Wolter Gmbh",
    "wof:placetype":"venue"
},
  "geometry": {"coordinates":[12.42323,51.280006],"type":"Point"}
}