{
  "type": "Feature",
  "properties": {
    "iso:country":"DE",
    "sg:address":"Hauptstr. 46",
    "sg:city":"Untereisesheim",
    "sg:phone":"+49 7132/43472",
    "sg:postcode":"74257",
    "sg:province":"Baden-W\u00fcrttemberg",
    "wof:name":"Schwarz & Partner Ohg",
    "wof:placetype":"venue"
},
  "geometry": {"coordinates":[9.2019376755,49.2109413147],"type":"Point"}
}