{
  "type": "Feature",
  "properties": {
    "iso:country":"DE",
    "sg:address":"Schubartstr. 6",
    "sg:city":"Geislingen",
    "sg:phone":"+49 7331/45245",
    "sg:postcode":"73312",
    "sg:province":"Baden-W\u00fcrttemberg",
    "wof:name":"Reiseb\u00fcro Knauss Reisen Dieter Frank Gmbh & Co.",
    "wof:placetype":"venue"
},
  "geometry": {"coordinates":[9.8438177109,48.6143913269],"type":"Point"}
}