{
  "type": "Feature",
  "properties": {
    "iso:country":"DE",
    "sg:city":"Oberstdorf",
    "sg:postcode":"87561",
    "sg:province":"Bayern",
    "wof:name":"Allgaeuer Branchenbuch",
    "wof:placetype":"venue"
},
  "geometry": {"coordinates":[10.277377,47.411488],"type":"Point"}
}