{
  "type": "Feature",
  "properties": {
    "iso:country":"DE",
    "sg:address":"Bedburger Str. 9",
    "sg:city":"Bergheim",
    "sg:phone":"+49 2272/2200",
    "sg:postcode":"50126",
    "sg:province":"Nordrhein-Westfalen",
    "wof:name":"Hans-josef Becker",
    "wof:placetype":"venue"
},
  "geometry": {"coordinates":[6.592651844,50.9728889465],"type":"Point"}
}