{
  "type": "Feature",
  "properties": {
    "iso:country":"DE",
    "sg:address":"Am Handwerkerzentrum 1",
    "sg:city":"Monschau",
    "sg:postcode":"52156",
    "sg:province":"Nordrhein-Westfalen",
    "wof:name":"Taz-telearbeitszentrum Kreis Aachen Gmbh",
    "wof:placetype":"venue"
},
  "geometry": {"coordinates":[6.261429,50.578552],"type":"Point"}
}