{
  "type": "Feature",
  "properties": {
    "iso:country":"DE",
    "sg:address":"Heyestr. 17",
    "sg:city":"D\u00fcsseldorf",
    "sg:phone":"+49 211/296454",
    "sg:postcode":"40625",
    "sg:province":"Nordrhein-Westfalen",
    "wof:name":"Norbert Werner Gmbh",
    "wof:placetype":"venue"
},
  "geometry": {"coordinates":[6.861267,51.233517],"type":"Point"}
}