{
  "type": "Feature",
  "properties": {
    "iso:country":"DE",
    "sg:address":"Hoheneggerstr. 1",
    "sg:city":"Bruchsal",
    "sg:phone":"+49 7251/2331",
    "sg:postcode":"76646",
    "sg:province":"Baden-W\u00fcrttemberg",
    "wof:name":"F. Bohleber",
    "wof:placetype":"venue"
},
  "geometry": {"coordinates":[8.5964822769,49.1257247925],"type":"Point"}
}