{
  "type": "Feature",
  "properties": {
    "iso:country":"DE",
    "sg:address":"Ebertstr. 25",
    "sg:city":"T\u00fcbingen",
    "sg:phone":"+49 7071/34160",
    "sg:postcode":"72072",
    "sg:province":"Baden-W\u00fcrttemberg",
    "wof:name":"Ambul. Koronargruppe T\u00fcbingen Uwe A. Beck",
    "wof:placetype":"venue"
},
  "geometry": {"coordinates":[9.0608911514,48.512096405],"type":"Point"}
}