{
  "type": "Feature",
  "properties": {
    "iso:country":"DE",
    "sg:address":"Hauptstr. 33",
    "sg:city":"Wagenfeld",
    "sg:phone":"+49 4954/44212",
    "sg:postcode":"49419",
    "sg:province":"Niedersachsen",
    "wof:name":"Volksbank Eg",
    "wof:placetype":"venue"
},
  "geometry": {"coordinates":[8.588217,52.549603],"type":"Point"}
}