{
  "type": "Feature",
  "properties": {
    "iso:country":"DE",
    "sg:address":"Kommenderiestr. 128",
    "sg:city":"Osnabr\u00fcck",
    "sg:phone":"+49 541/21550",
    "sg:postcode":"49080",
    "sg:province":"Niedersachsen",
    "wof:name":"Esb Elektronic-shop Gmbh",
    "wof:placetype":"venue"
},
  "geometry": {"coordinates":[8.05073,52.26585],"type":"Point"}
}