{
  "type": "Feature",
  "properties": {
    "iso:country":"DE",
    "sg:address":"Baumgartenstr. 5",
    "sg:city":"Oldenburg",
    "sg:phone":"+49 441/13130",
    "sg:postcode":"26122",
    "sg:province":"Niedersachsen",
    "wof:name":"Jul. Freyer",
    "wof:placetype":"venue"
},
  "geometry": {"coordinates":[8.213812,53.13995],"type":"Point"}
}