{
  "type": "Feature",
  "properties": {
    "iso:country":"DE",
    "sg:address":"Am Markt 4",
    "sg:city":"Sulzbach",
    "sg:phone":"+49 6897/3106",
    "sg:postcode":"66280",
    "sg:province":"Saarland",
    "wof:name":"Markt-apotheke Dorothee M\u00fccke E. K.",
    "wof:placetype":"venue"
},
  "geometry": {"coordinates":[7.071549,49.310757],"type":"Point"}
}