{
  "type": "Feature",
  "properties": {
    "iso:country":"DE",
    "sg:address":"Frankfurter Str. 80/82",
    "sg:city":"Fulda",
    "sg:phone":"+49 661",
    "sg:postcode":"36043",
    "sg:province":"Hessen",
    "wof:name":"Wagner Fahrzeugteilefabrik",
    "wof:placetype":"venue"
},
  "geometry": {"coordinates":[9.6761198044,50.5344238281],"type":"Point"}
}