{
  "type": "Feature",
  "properties": {
    "iso:country":"DE",
    "sg:address":"Zeisgendorfer Weg 12",
    "sg:city":"Berlin",
    "sg:phone":"+49 30/4314061",
    "sg:postcode":"13503",
    "sg:province":"Berlin",
    "wof:name":"Hartwig Braune",
    "wof:placetype":"venue"
},
  "geometry": {"coordinates":[13.231433,52.616409],"type":"Point"}
}