{
  "type": "Feature",
  "properties": {
    "iso:country":"DE",
    "sg:address":"Dresdener Str. 4",
    "sg:city":"M\u00fcnster",
    "sg:phone":"+49 6071/32251",
    "sg:postcode":"64839",
    "sg:province":"Hessen",
    "wof:name":"Heinz Ebert Dipl.-ing.",
    "wof:placetype":"venue"
},
  "geometry": {"coordinates":[8.8646993637,49.917175293],"type":"Point"}
}