{
  "type": "Feature",
  "properties": {
    "iso:country":"DE",
    "sg:city":"Bovenden",
    "sg:phone":"+49 5594/8238",
    "sg:postcode":"37120",
    "sg:province":"Niedersachsen",
    "wof:name":"P. Oetken Innenarchitekt",
    "wof:placetype":"venue"
},
  "geometry": {"coordinates":[9.92533,51.587269],"type":"Point"}
}