{
  "type": "Feature",
  "properties": {
    "iso:country":"DE",
    "sg:address":"Ohrdrufer Str. 9",
    "sg:city":"Frankenhain",
    "sg:phone":"+49 36205/7430",
    "sg:postcode":"99330",
    "sg:province":"Th\u00fcringen",
    "wof:name":"Gasthaus Gisselgrund",
    "wof:placetype":"venue"
},
  "geometry": {"coordinates":[10.792301178,50.7577629089],"type":"Point"}
}