{
  "type": "Feature",
  "properties": {
    "iso:country":"DE",
    "sg:address":"Bastenhaus",
    "sg:city":"Dannenfels",
    "sg:phone":"+49 6357/5021",
    "sg:postcode":"67814",
    "sg:province":"Rheinland-Pfalz",
    "wof:name":"Stollhof Hotel-restaurant Gmbh",
    "wof:placetype":"venue"
},
  "geometry": {"coordinates":[7.9179310799,49.6407470703],"type":"Point"}
}