{
  "type": "Feature",
  "properties": {
    "iso:country":"DE",
    "sg:address":"Industriestr. 75",
    "sg:city":"Ratingen",
    "sg:phone":"+49 2102/842435",
    "sg:postcode":"40878",
    "sg:province":"Nordrhein-Westfalen",
    "wof:name":"A. Heuchert",
    "wof:placetype":"venue"
},
  "geometry": {"coordinates":[6.855905056,51.288734436],"type":"Point"}
}