{
  "type": "Feature",
  "properties": {
    "iso:country":"DE",
    "sg:address":"Kreuthof 2",
    "sg:city":"Heidenheim",
    "sg:phone":"+49 9833/1375",
    "sg:postcode":"91719",
    "sg:province":"Bayern",
    "wof:name":"Karl B\u00fcttner",
    "wof:placetype":"venue"
},
  "geometry": {"coordinates":[10.726041,48.997906],"type":"Point"}
}