{
  "type": "Feature",
  "properties": {
    "iso:country":"DE",
    "sg:address":"Obere Paulusstr. 80",
    "sg:city":"Stuttgart",
    "sg:phone":"+49 711/562221",
    "sg:postcode":"70197",
    "sg:province":"Baden-W\u00fcrttemberg",
    "wof:name":"Heinrich Wissenbach",
    "wof:placetype":"venue"
},
  "geometry": {"coordinates":[9.1454143524,48.7725296021],"type":"Point"}
}