{
  "type": "Feature",
  "properties": {
    "iso:country":"DE",
    "sg:address":"Mindener Str. 85",
    "sg:city":"Uchte",
    "sg:phone":"+49 5763/403",
    "sg:postcode":"31600",
    "sg:province":"Niedersachsen",
    "wof:name":"Lahrmann Reisen Gmbh",
    "wof:placetype":"venue"
},
  "geometry": {"coordinates":[8.8915100098,52.4907989502],"type":"Point"}
}