{
  "type": "Feature",
  "properties": {
    "iso:country":"DE",
    "sg:address":"Elsterwerdaer Str. 7",
    "sg:city":"Ortrand",
    "sg:postcode":"01990",
    "sg:province":"Brandenburg",
    "wof:name":"Ev. Kirche",
    "wof:placetype":"venue"
},
  "geometry": {"coordinates":[13.7560873032,51.3758659363],"type":"Point"}
}