{
  "type": "Feature",
  "properties": {
    "iso:country":"DE",
    "sg:address":"Raiffeisenstr. 15",
    "sg:city":"Harsum",
    "sg:phone":"+49 5127/9780",
    "sg:postcode":"31177",
    "sg:province":"Niedersachsen",
    "wof:name":"Thomas Ernst Gmbh",
    "wof:placetype":"venue"
},
  "geometry": {"coordinates":[9.971221,52.218292],"type":"Point"}
}