{
  "type": "Feature",
  "properties": {
    "iso:country":"DE",
    "sg:address":"Passauer Str. 17",
    "sg:city":"Pfarrkirchen",
    "sg:phone":"+49 8561/1479",
    "sg:postcode":"84347",
    "sg:province":"Bayern",
    "wof:name":"Wirnhier",
    "wof:placetype":"venue"
},
  "geometry": {"coordinates":[12.942284,48.432636],"type":"Point"}
}