{
  "type": "Feature",
  "properties": {
    "iso:country":"DE",
    "sg:address":"Windstr. 1",
    "sg:city":"Steinfurt",
    "sg:postcode":"48565",
    "sg:province":"Nordrhein-Westfalen",
    "wof:name":"Deutsche Telekom T-punkt",
    "wof:placetype":"venue"
},
  "geometry": {"coordinates":[7.3333940506,52.151966095],"type":"Point"}
}