{
  "type": "Feature",
  "properties": {
    "iso:country":"DE",
    "sg:address":"Oststr. 92",
    "sg:city":"Norderstedt",
    "sg:phone":"+49 170 5512618",
    "sg:postcode":"22844",
    "sg:province":"Schleswig-Holstein",
    "wof:name":"Architektur Und Konzept Gmbh Sonja Marklin",
    "wof:placetype":"venue"
},
  "geometry": {"coordinates":[10.02184,53.740879],"type":"Point"}
}