{
  "type": "Feature",
  "properties": {
    "iso:country":"DE",
    "sg:address":"Marienberger Str. 36",
    "sg:city":"Elkenroth",
    "sg:phone":"+49 2747/2490",
    "sg:postcode":"57578",
    "sg:province":"Rheinland-Pfalz",
    "wof:name":"Hermann Weller",
    "wof:placetype":"venue"
},
  "geometry": {"coordinates":[7.8862829208,50.7242355347],"type":"Point"}
}