{
  "type": "Feature",
  "properties": {
    "iso:country":"DE",
    "sg:address":"Hauptstr. 24",
    "sg:city":"Lautenbach",
    "sg:phone":"+49 7802/4767",
    "sg:postcode":"77794",
    "sg:province":"Baden-W\u00fcrttemberg",
    "wof:name":"Adolf Schnurr",
    "wof:placetype":"venue"
},
  "geometry": {"coordinates":[8.112663,48.521442],"type":"Point"}
}