{
  "type": "Feature",
  "properties": {
    "iso:country":"DE",
    "sg:address":"In den Lindeschen",
    "sg:city":"Langenau",
    "sg:postcode":"89129",
    "sg:province":"Baden-W\u00fcrttemberg",
    "wof:name":"Ihr Platz Drogeriemarkt",
    "wof:placetype":"venue"
},
  "geometry": {"coordinates":[10.130751,48.500816],"type":"Point"}
}