{
  "type": "Feature",
  "properties": {
    "iso:country":"DE",
    "sg:address":"Hauptstr. 24",
    "sg:city":"Utzstetten",
    "sg:phone":"+49 7175/8735",
    "sg:postcode":"73577",
    "sg:province":"Baden-W\u00fcrttemberg",
    "wof:name":"Karl Bareis",
    "wof:placetype":"venue"
},
  "geometry": {"coordinates":[9.851605,48.866104],"type":"Point"}
}