{
  "type": "Feature",
  "properties": {
    "iso:country":"DE",
    "sg:address":"Breslauer Str. 1",
    "sg:city":"Hockenheim",
    "sg:phone":"+49 6205/15799",
    "sg:postcode":"68766",
    "sg:province":"Baden-W\u00fcrttemberg",
    "wof:name":"Maud Stadtler",
    "wof:placetype":"venue"
},
  "geometry": {"coordinates":[8.5579004288,49.3200683594],"type":"Point"}
}