{
  "type": "Feature",
  "properties": {
    "iso:country":"DE",
    "sg:address":"Grillparzerstr. 25",
    "sg:city":"M\u00fcnchen",
    "sg:postcode":"81675",
    "sg:province":"Bayern",
    "wof:name":"Pk B\u00fcro Service Gmbh",
    "wof:placetype":"venue"
},
  "geometry": {"coordinates":[11.609599,48.135086],"type":"Point"}
}