{
  "type": "Feature",
  "properties": {
    "iso:country":"DE",
    "sg:address":"Sommergasse 51",
    "sg:city":"Weinheim",
    "sg:phone":"+49 6201/592233",
    "sg:postcode":"69469",
    "sg:province":"Baden-W\u00fcrttemberg",
    "wof:name":"El Kosht",
    "wof:placetype":"venue"
},
  "geometry": {"coordinates":[8.6642084122,49.527053833],"type":"Point"}
}