{
  "type": "Feature",
  "properties": {
    "iso:country":"DE",
    "sg:address":"Ibbenb\u00fcrener Str. 6",
    "sg:city":"Hopsten",
    "sg:postcode":"48496",
    "sg:province":"Nordrhein-Westfalen",
    "wof:name":"B\u00e4umer Folientechnik Gmbh",
    "wof:placetype":"venue"
},
  "geometry": {"coordinates":[7.596728,52.38026],"type":"Point"}
}