{
  "type": "Feature",
  "properties": {
    "iso:country":"DE",
    "sg:address":"Traubenstr. 3",
    "sg:city":"Lorch",
    "sg:phone":"+49 7172/5840",
    "sg:postcode":"73547",
    "sg:province":"Baden-W\u00fcrttemberg",
    "wof:name":"Christel G\u00f6rgens Finanzberaterin",
    "wof:placetype":"venue"
},
  "geometry": {"coordinates":[9.6360387802,48.7846069336],"type":"Point"}
}