{
  "type": "Feature",
  "properties": {
    "iso:country":"DE",
    "sg:address":"Halberst\u00e4dter Str. 79a",
    "sg:city":"Magdeburg",
    "sg:phone":"+49 391/6224236",
    "sg:postcode":"39112",
    "sg:province":"Sachsen-Anhalt",
    "wof:name":"Claus Vo\u00df",
    "wof:placetype":"venue"
},
  "geometry": {"coordinates":[11.6065263748,52.1122016907],"type":"Point"}
}