{
  "type": "Feature",
  "properties": {
    "iso:country":"DE",
    "sg:address":"Sauerstr. 5",
    "sg:city":"R\u00fcthen",
    "sg:phone":"+49 2952/757",
    "sg:postcode":"59602",
    "sg:province":"Nordrhein-Westfalen",
    "wof:name":"Klaus Creutzer Steuerberater",
    "wof:placetype":"venue"
},
  "geometry": {"coordinates":[8.4378328323,51.4949455261],"type":"Point"}
}