{
  "type": "Feature",
  "properties": {
    "iso:country":"DE",
    "sg:address":"Reichenbachstr. 29",
    "sg:city":"M\u00fcnchen",
    "sg:phone":"+49 89/2013248",
    "sg:postcode":"80469",
    "sg:province":"Bayern",
    "wof:name":"T. Kiefl",
    "wof:placetype":"venue"
},
  "geometry": {"coordinates":[11.576077,48.130505],"type":"Point"}
}