{
  "type": "Feature",
  "properties": {
    "iso:country":"DE",
    "sg:address":"Hauptstr. 25",
    "sg:city":"Bisterschied",
    "sg:phone":"+49 4963/64220",
    "sg:postcode":"67806",
    "sg:province":"Rheinland-Pfalz",
    "wof:name":"Raiffeisenbank Rockenhausen Egmbh",
    "wof:placetype":"venue"
},
  "geometry": {"coordinates":[7.749227,49.645428],"type":"Point"}
}