{
  "type": "Feature",
  "properties": {
    "iso:country":"DE",
    "sg:address":"Busenbacher Str. 1",
    "sg:city":"Waldbronn",
    "sg:phone":"+49 7243/532810",
    "sg:postcode":"76337",
    "sg:province":"Baden-W\u00fcrttemberg",
    "wof:name":"Hotel Garni",
    "wof:placetype":"venue"
},
  "geometry": {"coordinates":[8.4748392105,48.9240341187],"type":"Point"}
}