{
  "type": "Feature",
  "properties": {
    "iso:country":"DE",
    "sg:address":"Ameisenstr. 12",
    "sg:city":"Berglen",
    "sg:phone":"+49 7181/978410",
    "sg:postcode":"73663",
    "sg:province":"Baden-W\u00fcrttemberg",
    "wof:name":"B\u00dchner & Schaible Elektronik Gmbh",
    "wof:placetype":"venue"
},
  "geometry": {"coordinates":[9.459664,48.828686],"type":"Point"}
}