{
  "type": "Feature",
  "properties": {
    "iso:country":"DE",
    "sg:address":"Am Schlo\u00dfpark 1",
    "sg:city":"Wiesbaden",
    "sg:phone":"+49 611/1861110",
    "sg:postcode":"65203",
    "sg:province":"Hessen",
    "wof:name":"La Casa Toscana",
    "wof:placetype":"venue"
},
  "geometry": {"coordinates":[8.2353906631,50.0369720459],"type":"Point"}
}