{
  "type": "Feature",
  "properties": {
    "iso:country":"DE",
    "sg:address":"Meiersberger Str. 47",
    "sg:city":"Ratingen",
    "sg:phone":"+49 2102/5811",
    "sg:postcode":"40882",
    "sg:province":"Nordrhein-Westfalen",
    "wof:name":"Gier Verwaltungs-gmbh",
    "wof:placetype":"venue"
},
  "geometry": {"coordinates":[6.946952,51.295853],"type":"Point"}
}