{
  "type": "Feature",
  "properties": {
    "iso:country":"DE",
    "sg:address":"Goethestr. 12",
    "sg:city":"Mieste",
    "sg:postcode":"39649",
    "sg:province":"Sachsen-Anhalt",
    "wof:name":"Wohnungsgenossenschaft Mieste Eg",
    "wof:placetype":"venue"
},
  "geometry": {"coordinates":[11.2106714249,52.4792556763],"type":"Point"}
}