{
  "type": "Feature",
  "properties": {
    "iso:country":"DE",
    "sg:address":"Hauptstr. 72",
    "sg:city":"Otterberg",
    "sg:phone":"+49 6301/9447",
    "sg:postcode":"67697",
    "sg:province":"Rheinland-Pfalz",
    "wof:name":"Hans Kirchner",
    "wof:placetype":"venue"
},
  "geometry": {"coordinates":[7.7724108696,49.5029792786],"type":"Point"}
}