{
  "type": "Feature",
  "properties": {
    "iso:country":"DE",
    "sg:address":"Karlsgartenstr. 14",
    "sg:city":"Berlin",
    "sg:phone":"+49 30/695030",
    "sg:postcode":"12049",
    "sg:province":"Berlin",
    "wof:name":"Stimmlabor",
    "wof:placetype":"venue"
},
  "geometry": {"coordinates":[13.421872,52.481865],"type":"Point"}
}