{
  "type": "Feature",
  "properties": {
    "iso:country":"DE",
    "sg:address":"Mittelstr. 46",
    "sg:city":"Laudenbach",
    "sg:phone":"+49 6201/44388",
    "sg:postcode":"69514",
    "sg:province":"Baden-W\u00fcrttemberg",
    "wof:name":"R. Br\u00fcmmer Masseur",
    "wof:placetype":"venue"
},
  "geometry": {"coordinates":[8.6528539658,49.6116027832],"type":"Point"}
}