{
  "type": "Feature",
  "properties": {
    "iso:country":"DE",
    "sg:address":"Lindenstr. 15",
    "sg:city":"Waldstetten",
    "sg:phone":"+49 7162/24693",
    "sg:postcode":"73550",
    "sg:province":"Baden-W\u00fcrttemberg",
    "wof:name":"Sunway-hosen Gmbh",
    "wof:placetype":"venue"
},
  "geometry": {"coordinates":[9.8077859879,48.7257537842],"type":"Point"}
}