{
  "type": "Feature",
  "properties": {
    "iso:country":"DE",
    "sg:address":"Bismarckring 48",
    "sg:city":"Biberach",
    "sg:phone":"+49 7351/75757",
    "sg:postcode":"88400",
    "sg:province":"Baden-W\u00fcrttemberg",
    "wof:name":"H\u00e4rle & Co. Gmbh Elektroinstallation",
    "wof:placetype":"venue"
},
  "geometry": {"coordinates":[9.789834,48.100994],"type":"Point"}
}