{
  "type": "Feature",
  "properties": {
    "iso:country":"DE",
    "sg:address":"Rodenbecker Str. 74",
    "sg:city":"Minden",
    "sg:phone":"+49 4957/129675",
    "sg:postcode":"32427",
    "sg:province":"Nordrhein-Westfalen",
    "wof:name":"City Sofort Druck",
    "wof:placetype":"venue"
},
  "geometry": {"coordinates":[8.8978385925,52.2861213684],"type":"Point"}
}