{
  "type": "Feature",
  "properties": {
    "iso:country":"DE",
    "sg:address":"Hofkurat-Diehl-Str. 5",
    "sg:city":"Oberschlei\u00dfheim",
    "sg:phone":"+49 89/3150101",
    "sg:postcode":"85764",
    "sg:province":"Bayern",
    "wof:name":"Katholisches Pfarramt Patrona Bavaria",
    "wof:placetype":"venue"
},
  "geometry": {"coordinates":[11.5594587326,48.2520446777],"type":"Point"}
}