{
  "type": "Feature",
  "properties": {
    "iso:country":"DE",
    "sg:address":"Postfach 1544",
    "sg:city":"Leonberg",
    "sg:phone":"+49 7152/948486",
    "sg:postcode":"71205",
    "sg:province":"Baden-W\u00fcrttemberg",
    "wof:name":"Kingsize-pro",
    "wof:placetype":"venue"
},
  "geometry": {"coordinates":[9.0164604187,48.8022499084],"type":"Point"}
}