{
  "type": "Feature",
  "properties": {
    "iso:country":"DE",
    "sg:address":"Zur Waldzeche 58",
    "sg:city":"Siegen",
    "sg:phone":"+49 271/6609333",
    "sg:postcode":"57080",
    "sg:province":"Nordrhein-Westfalen",
    "wof:name":"Helmut Schlabach",
    "wof:placetype":"venue"
},
  "geometry": {"coordinates":[7.9889850616,50.8334960938],"type":"Point"}
}