{
  "type": "Feature",
  "properties": {
    "iso:country":"DE",
    "sg:address":"Rahmedestr. 406",
    "sg:city":"Altena",
    "sg:phone":"+49 2352/5430",
    "sg:postcode":"58762",
    "sg:province":"Nordrhein-Westfalen",
    "wof:name":"C. Hohage Verwaltungs Gmbh",
    "wof:placetype":"venue"
},
  "geometry": {"coordinates":[7.648437,51.256012],"type":"Point"}
}