{
  "type": "Feature",
  "properties": {
    "iso:country":"DE",
    "sg:address":"Kirchstr. 21",
    "sg:city":"Wickede",
    "sg:phone":"+49 2377/2128",
    "sg:postcode":"58739",
    "sg:province":"Nordrhein-Westfalen",
    "wof:name":"Josef Hartmann",
    "wof:placetype":"venue"
},
  "geometry": {"coordinates":[7.866766,51.494164],"type":"Point"}
}