{
  "type": "Feature",
  "properties": {
    "iso:country":"DE",
    "sg:address":"Wei\u00dfenfelser Str. 7",
    "sg:city":"Gransch\u00fctz",
    "sg:phone":"+49 34441/93256",
    "sg:postcode":"06679",
    "sg:province":"Sachsen-Anhalt",
    "wof:name":"Andreas Koch",
    "wof:placetype":"venue"
},
  "geometry": {"coordinates":[12.0521621704,51.1832008362],"type":"Point"}
}