{
  "type": "Feature",
  "properties": {
    "iso:country":"DE",
    "sg:address":"Hagener Str. 16",
    "sg:city":"Dortmund",
    "sg:phone":"+49 231/714029",
    "sg:postcode":"44225",
    "sg:province":"Nordrhein-Westfalen",
    "wof:name":"Ic Industry Computer Int.",
    "wof:placetype":"venue"
},
  "geometry": {"coordinates":[7.459004879,51.4780807495],"type":"Point"}
}