{
  "type": "Feature",
  "properties": {
    "iso:country":"DE",
    "sg:address":"Lindenstr. 107/Nordring",
    "sg:city":"Gelsenkirchen",
    "sg:postcode":"45894",
    "sg:province":"Nordrhein-Westfalen",
    "wof:name":"Ossmann Gmbh",
    "wof:placetype":"venue"
},
  "geometry": {"coordinates":[7.053895,51.577209],"type":"Point"}
}