{
  "type": "Feature",
  "properties": {
    "iso:country":"DE",
    "sg:address":"D\u00fcrnaststr. 10",
    "sg:city":"Geltendorf",
    "sg:phone":"+49 8193/999261",
    "sg:postcode":"82269",
    "sg:province":"Bayern",
    "wof:name":"Bernd Kornd\u00f6rfer",
    "wof:placetype":"venue"
},
  "geometry": {"coordinates":[11.001153,48.12249],"type":"Point"}
}