{
  "type": "Feature",
  "properties": {
    "iso:country":"DE",
    "sg:address":"Schwanhildenstr. 2",
    "sg:city":"Wang",
    "sg:phone":"+49 8764/644",
    "sg:postcode":"85368",
    "sg:province":"Bayern",
    "wof:name":"Simon Halbinger Bauunternehmung Gmbh",
    "wof:placetype":"venue"
},
  "geometry": {"coordinates":[11.870028,48.507229],"type":"Point"}
}