{
  "type": "Feature",
  "properties": {
    "iso:country":"DE",
    "sg:address":"S\u00fcdstr. 7",
    "sg:city":"Klettgau",
    "sg:phone":"+49 7742/5408",
    "sg:postcode":"79771",
    "sg:province":"Baden-W\u00fcrttemberg",
    "wof:name":"Strauch Gmbh",
    "wof:placetype":"venue"
},
  "geometry": {"coordinates":[8.3953332901,47.6179199219],"type":"Point"}
}