{
  "type": "Feature",
  "properties": {
    "iso:country":"DE",
    "sg:address":"Rathausstr. 50",
    "sg:city":"W\u00f6rth",
    "sg:phone":"+49 9372/6684",
    "sg:postcode":"63939",
    "sg:province":"Bayern",
    "wof:name":"Erich Stappel",
    "wof:placetype":"venue"
},
  "geometry": {"coordinates":[9.1578,49.79789],"type":"Point"}
}