{
  "type": "Feature",
  "properties": {
    "iso:country":"DE",
    "sg:address":"Steinweg 8",
    "sg:city":"Kirn",
    "sg:phone":"+49 6752/5775",
    "sg:postcode":"55606",
    "sg:province":"Rheinland-Pfalz",
    "wof:name":"Peter Herrmann Heilpraktiker",
    "wof:placetype":"venue"
},
  "geometry": {"coordinates":[7.4592080116,49.7868309021],"type":"Point"}
}