{
  "type": "Feature",
  "properties": {
    "iso:country":"DE",
    "sg:address":"Zimmerplatz 6",
    "sg:city":"Legau",
    "sg:phone":"+49 8330/268",
    "sg:postcode":"87764",
    "sg:province":"Bayern",
    "wof:name":"Hoerberg Cases",
    "wof:placetype":"venue"
},
  "geometry": {"coordinates":[10.129845,47.854782],"type":"Point"}
}