{
  "type": "Feature",
  "properties": {
    "iso:country":"DE",
    "sg:address":"Breitlacherstr. 16",
    "sg:city":"Frankfurt",
    "sg:phone":"+49 69/783875",
    "sg:postcode":"60489",
    "sg:province":"Hessen",
    "wof:name":"Gerhard Kempf",
    "wof:placetype":"venue"
},
  "geometry": {"coordinates":[8.607732,50.120525],"type":"Point"}
}