{
  "type": "Feature",
  "properties": {
    "iso:country":"DE",
    "sg:address":"Rascheider Str. 4",
    "sg:city":"Meisburg",
    "sg:phone":"+49 6599/321",
    "sg:postcode":"54570",
    "sg:province":"Rheinland-Pfalz",
    "wof:name":"M. N\u00e4gel",
    "wof:placetype":"venue"
},
  "geometry": {"coordinates":[6.6899709702,50.108341217],"type":"Point"}
}