{
  "type": "Feature",
  "properties": {
    "iso:country":"DE",
    "sg:address":"Kapellenstr. 44",
    "sg:city":"Aachen",
    "sg:phone":"+49 241/64169",
    "sg:postcode":"52066",
    "sg:province":"Nordrhein-Westfalen",
    "wof:name":"Ludwig Hungs Masseur",
    "wof:placetype":"venue"
},
  "geometry": {"coordinates":[6.093494,50.760334],"type":"Point"}
}