{
  "type": "Feature",
  "properties": {
    "iso:country":"DE",
    "sg:address":"Bachtelweg 5",
    "sg:city":"Betzigau",
    "sg:phone":"+49 831/76840",
    "sg:postcode":"87488",
    "sg:province":"Bayern",
    "wof:name":"Josef Hopp",
    "wof:placetype":"venue"
},
  "geometry": {"coordinates":[10.3821706772,47.7334365845],"type":"Point"}
}