{
  "type": "Feature",
  "properties": {
    "iso:country":"DE",
    "sg:address":"Gro\u00dfe Str. 8",
    "sg:city":"Bretzenheim",
    "sg:phone":"+49 671/29568",
    "sg:postcode":"55559",
    "sg:province":"Rheinland-Pfalz",
    "wof:name":"Weingut Gerhardt Bischof",
    "wof:placetype":"venue"
},
  "geometry": {"coordinates":[7.9014258385,49.8782501221],"type":"Point"}
}