{
  "type": "Feature",
  "properties": {
    "iso:country":"DE",
    "sg:address":"Timmerhellstr. 28",
    "sg:city":"M\u00fclheim",
    "sg:phone":"+49 4920/899400",
    "sg:postcode":"45478",
    "sg:province":"Nordrhein-Westfalen",
    "wof:name":"Dhc Solvent Chemie Gmbh",
    "wof:placetype":"venue"
},
  "geometry": {"coordinates":[6.852351,51.435047],"type":"Point"}
}