{
  "type": "Feature",
  "properties": {
    "iso:country":"DE",
    "sg:address":"Wallstr. 24",
    "sg:city":"Oldenburg",
    "sg:phone":"+49 441/15711",
    "sg:postcode":"26122",
    "sg:province":"Niedersachsen",
    "wof:name":"New York-new York Gesellschaft F\u00fcr",
    "wof:placetype":"venue"
},
  "geometry": {"coordinates":[8.2130117416,53.1426467896],"type":"Point"}
}