{
  "type": "Feature",
  "properties": {
    "iso:country":"DE",
    "sg:address":"Regensburger Str. 59",
    "sg:city":"Schwandorf",
    "sg:phone":"+49 9431/50364",
    "sg:postcode":"92421",
    "sg:province":"Bayern",
    "wof:name":"Harald Frank",
    "wof:placetype":"venue"
},
  "geometry": {"coordinates":[12.1018247604,49.3164901733],"type":"Point"}
}