{
  "type": "Feature",
  "properties": {
    "iso:country":"DE",
    "sg:address":"\u00dcberruckweg 12",
    "sg:city":"Villingen-Schwenningen",
    "sg:phone":"+49 7721/3104",
    "sg:postcode":"78052",
    "sg:province":"Baden-W\u00fcrttemberg",
    "wof:name":"Alfred Engesser Industrievertretungen Gmbh",
    "wof:placetype":"venue"
},
  "geometry": {"coordinates":[8.4534111023,48.032623291],"type":"Point"}
}