{
  "type": "Feature",
  "properties": {
    "iso:country":"DE",
    "sg:address":"Gerlinger Str. 27",
    "sg:city":"Ditzingen",
    "sg:phone":"+49 7156/9320",
    "sg:postcode":"71254",
    "sg:province":"Baden-W\u00fcrttemberg",
    "wof:name":"Hotel Blankenburg",
    "wof:placetype":"venue"
},
  "geometry": {"coordinates":[9.0686206818,48.8245582581],"type":"Point"}
}