{
  "type": "Feature",
  "properties": {
    "iso:country":"DE",
    "sg:address":"K\u00f6nigstr. 21",
    "sg:city":"Halstenbek",
    "sg:phone":"+49 4101/401057",
    "sg:postcode":"25469",
    "sg:province":"Schleswig-Holstein",
    "wof:name":"Hpb Haustechnische Planungs- Und Beratungs-",
    "wof:placetype":"venue"
},
  "geometry": {"coordinates":[9.845035553,53.6345214844],"type":"Point"}
}