{
  "type": "Feature",
  "properties": {
    "iso:country":"DE",
    "sg:address":"Fritz-Peters-Str. 40",
    "sg:city":"Moers",
    "sg:phone":"+49 2841/96790",
    "sg:postcode":"47447",
    "sg:province":"Nordrhein-Westfalen",
    "wof:name":"Kapellener Service-center Inh. Hinrich Podendorf",
    "wof:placetype":"venue"
},
  "geometry": {"coordinates":[6.5961151123,51.4180488586],"type":"Point"}
}