{
  "type": "Feature",
  "properties": {
    "iso:country":"DE",
    "sg:address":"Oberkasseler Str. 10",
    "sg:city":"Bonn",
    "sg:phone":"+49 228/970960",
    "sg:postcode":"53227",
    "sg:province":"Nordrhein-Westfalen",
    "wof:name":"Kommende Ramersdorf Restaurant",
    "wof:placetype":"venue"
},
  "geometry": {"coordinates":[7.1599640846,50.7243614197],"type":"Point"}
}