{
  "type": "Feature",
  "properties": {
    "iso:country":"DE",
    "sg:address":"Buschkamp 20",
    "sg:city":"Hamburg",
    "sg:phone":"+49 40/590122",
    "sg:postcode":"22339",
    "sg:province":"Hamburg",
    "wof:name":"G\u00fcnther Schertz",
    "wof:placetype":"venue"
},
  "geometry": {"coordinates":[10.0299358368,53.6352577209],"type":"Point"}
}