{
  "type": "Feature",
  "properties": {
    "iso:country":"DE",
    "sg:address":"M\u00fchlenfeldstr. 85",
    "sg:city":"Bremen",
    "sg:phone":"+49 421/2575036",
    "sg:postcode":"28355",
    "sg:province":"Bremen",
    "wof:name":"Alfred Baulig Innenarchitekt",
    "wof:placetype":"venue"
},
  "geometry": {"coordinates":[8.94053,53.082939],"type":"Point"}
}