{
  "type": "Feature",
  "properties": {
    "iso:country":"DE",
    "sg:address":"Ahornweg 3a",
    "sg:city":"Lauenau",
    "sg:phone":"+49 5043/98039",
    "sg:postcode":"31867",
    "sg:province":"Niedersachsen",
    "wof:name":"Miller-roth-vermietung Gbr",
    "wof:placetype":"venue"
},
  "geometry": {"coordinates":[9.3607568741,52.2751617432],"type":"Point"}
}