{
  "type": "Feature",
  "properties": {
    "iso:country":"DE",
    "sg:address":"Breitunger Weg 22",
    "sg:city":"Berlin",
    "sg:phone":"+49 30",
    "sg:postcode":"12349",
    "sg:province":"Berlin",
    "wof:name":"Horst Mochow",
    "wof:placetype":"venue"
},
  "geometry": {"coordinates":[13.424633,52.42276],"type":"Point"}
}