{
  "type": "Feature",
  "properties": {
    "iso:country":"DE",
    "sg:address":"Hardeckstr 4",
    "sg:city":"Karlsruhe",
    "sg:phone":"+49 721/957820",
    "sg:postcode":"76185",
    "sg:province":"Baden-W\u00fcrttemberg",
    "wof:name":"Dara-stahl Eisenhandelsges. Mbh & Co Kg",
    "wof:placetype":"venue"
},
  "geometry": {"coordinates":[8.3622989655,48.9994430542],"type":"Point"}
}