{
  "type": "Feature",
  "properties": {
    "iso:country":"DE",
    "sg:address":"Hausmannstr. 4",
    "sg:city":"Brandenburg",
    "sg:phone":"+49 3381/225545",
    "sg:postcode":"14776",
    "sg:province":"Brandenburg",
    "wof:name":"Burgstaller Immobilien Gmbh",
    "wof:placetype":"venue"
},
  "geometry": {"coordinates":[12.561554,52.401348],"type":"Point"}
}