{
  "type": "Feature",
  "properties": {
    "iso:country":"DE",
    "sg:address":"John-Brinckman-Str. 9",
    "sg:city":"Rostock",
    "sg:postcode":"18055",
    "sg:province":"Mecklenburg-Vorpommern",
    "wof:name":"Vr-coninstruct Immobiliengesellschaft Mbh",
    "wof:placetype":"venue"
},
  "geometry": {"coordinates":[12.1410865784,54.0793075562],"type":"Point"}
}