{
  "type": "Feature",
  "properties": {
    "iso:country":"DE",
    "sg:address":"Osnabr\u00fccker Str. 16",
    "sg:city":"Rheine",
    "sg:phone":"+49 5971/71340",
    "sg:postcode":"48429",
    "sg:province":"Nordrhein-Westfalen",
    "wof:name":"Hermann & Heilen",
    "wof:placetype":"venue"
},
  "geometry": {"coordinates":[7.447213,52.281265],"type":"Point"}
}