{
  "type": "Feature",
  "properties": {
    "iso:country":"DE",
    "sg:address":"Hans-Driesch-Str. 45",
    "sg:city":"Leipzig",
    "sg:postcode":"04179",
    "sg:province":"Sachsen",
    "wof:name":"Dr. Med. Regina Brunner",
    "wof:placetype":"venue"
},
  "geometry": {"coordinates":[12.312672,51.346424],"type":"Point"}
}