{
  "type": "Feature",
  "properties": {
    "iso:country":"DE",
    "sg:address":"Alte Heerstr. 36",
    "sg:city":"Weeze",
    "sg:phone":"+49 2837/2424",
    "sg:postcode":"47652",
    "sg:province":"Nordrhein-Westfalen",
    "wof:name":"Alpha-tex Textilhandels Gmbh",
    "wof:placetype":"venue"
},
  "geometry": {"coordinates":[6.2028021812,51.622379303],"type":"Point"}
}