{
  "type": "Feature",
  "properties": {
    "iso:country":"DE",
    "sg:address":"Schleswiger Str. 6",
    "sg:city":"Eckernf\u00f6rde",
    "sg:phone":"+49 4351/82782",
    "sg:postcode":"24340",
    "sg:province":"Schleswig-Holstein",
    "wof:name":"Ingo Harwerth",
    "wof:placetype":"venue"
},
  "geometry": {"coordinates":[9.8323278427,54.4771766663],"type":"Point"}
}