{
  "type": "Feature",
  "properties": {
    "iso:country":"DE",
    "sg:address":"Niesiger Str. 44",
    "sg:city":"Fulda",
    "sg:phone":"+49 661/51119",
    "sg:postcode":"36039",
    "sg:province":"Hessen",
    "wof:name":"Hans St\u00fcbinger",
    "wof:placetype":"venue"
},
  "geometry": {"coordinates":[9.6650056839,50.5677032471],"type":"Point"}
}