{
  "type": "Feature",
  "properties": {
    "iso:country":"DE",
    "sg:address":"Gustav-Heinemann-Str. 3",
    "sg:city":"Leverkusen",
    "sg:phone":"+49 214/4047447",
    "sg:postcode":"51373",
    "sg:province":"Nordrhein-Westfalen",
    "wof:name":"C. Otten",
    "wof:placetype":"venue"
},
  "geometry": {"coordinates":[7.0094680786,51.0316123962],"type":"Point"}
}