{
  "type": "Feature",
  "properties": {
    "iso:country":"DE",
    "sg:address":"Poststr. 49",
    "sg:city":"B\u00f6blingen",
    "sg:phone":"+49 7031/236751",
    "sg:postcode":"71032",
    "sg:province":"Baden-W\u00fcrttemberg",
    "wof:name":"Sonne",
    "wof:placetype":"venue"
},
  "geometry": {"coordinates":[9.0143651962,48.6851119995],"type":"Point"}
}