{
  "type": "Feature",
  "properties": {
    "iso:country":"DE",
    "sg:address":"K\u00f6nigsberger Str. 10",
    "sg:city":"Hofgeismar",
    "sg:phone":"+49 5671/3800",
    "sg:postcode":"34369",
    "sg:province":"Hessen",
    "wof:name":"B. U. D. Wulff",
    "wof:placetype":"venue"
},
  "geometry": {"coordinates":[9.3915691376,51.4874267578],"type":"Point"}
}