{
  "type": "Feature",
  "properties": {
    "iso:country":"DE",
    "sg:address":"Vilshofener Str. 14",
    "sg:city":"Eging",
    "sg:phone":"+49 8544/509",
    "sg:postcode":"94535",
    "sg:province":"Bayern",
    "wof:name":"Konrad Springer",
    "wof:placetype":"venue"
},
  "geometry": {"coordinates":[13.264856,48.711819],"type":"Point"}
}