{
  "type": "Feature",
  "properties": {
    "iso:country":"DE",
    "sg:address":"Bahnhofstr. 21",
    "sg:city":"Heuchelheim",
    "sg:phone":"+49 641/61188",
    "sg:postcode":"35452",
    "sg:province":"Hessen",
    "wof:name":"Hans Neidel",
    "wof:placetype":"venue"
},
  "geometry": {"coordinates":[8.61373,50.584801],"type":"Point"}
}