{
  "type": "Feature",
  "properties": {
    "iso:country":"DE",
    "sg:address":"Schultenfeld 30",
    "sg:city":"Oelde",
    "sg:phone":"+49 5245/5416",
    "sg:postcode":"59302",
    "sg:province":"Nordrhein-Westfalen",
    "wof:name":"Wilhelm Hegemann",
    "wof:placetype":"venue"
},
  "geometry": {"coordinates":[8.164462,51.880474],"type":"Point"}
}