{
  "type": "Feature",
  "properties": {
    "iso:country":"DE",
    "sg:address":"Im Brande 13",
    "sg:city":"Seelze",
    "sg:phone":"+49 511/486646",
    "sg:postcode":"30926",
    "sg:province":"Niedersachsen",
    "wof:name":"M\u00fcller-korinth Transport & Logistic Kg",
    "wof:placetype":"venue"
},
  "geometry": {"coordinates":[9.6469202042,52.3725318909],"type":"Point"}
}