{
  "type": "Feature",
  "properties": {
    "iso:country":"DE",
    "sg:address":"Wahlenstr. 23",
    "sg:city":"Regensburg",
    "sg:phone":"+49 941/566518",
    "sg:postcode":"93047",
    "sg:province":"Bayern",
    "wof:name":"M\u00fchldorfer",
    "wof:placetype":"venue"
},
  "geometry": {"coordinates":[12.0956459045,49.0187110901],"type":"Point"}
}