{
  "type": "Feature",
  "properties": {
    "iso:country":"DE",
    "sg:address":"Pirolstr. 10 a",
    "sg:city":"M\u00fcnchen",
    "sg:phone":"+49 89/89712446",
    "sg:postcode":"81249",
    "sg:province":"Bayern",
    "wof:name":"Gentz Und Gentz Rechtsanw\u00e4lte",
    "wof:placetype":"venue"
},
  "geometry": {"coordinates":[11.3943033218,48.176197052],"type":"Point"}
}