{
  "type": "Feature",
  "properties": {
    "iso:country":"DE",
    "sg:address":"Raiffeisenstr 15",
    "sg:city":"Ki\u00dflegg",
    "sg:phone":"+49 7563/91160",
    "sg:postcode":"88353",
    "sg:province":"Baden-W\u00fcrttemberg",
    "wof:name":"Pekana\u00ae-naturheilmittel Gmbh",
    "wof:placetype":"venue"
},
  "geometry": {"coordinates":[9.893798,47.77113],"type":"Point"}
}