{
  "type": "Feature",
  "properties": {
    "iso:country":"DE",
    "sg:address":"Mirower Str. 13",
    "sg:city":"Flecken Zechlin",
    "sg:phone":"+49 33923/70450",
    "sg:postcode":"16837",
    "sg:province":"Brandenburg",
    "wof:name":"Detlef Hagenow",
    "wof:placetype":"venue"
},
  "geometry": {"coordinates":[12.768738,53.161766],"type":"Point"}
}