{
  "type": "Feature",
  "properties": {
    "iso:country":"DE",
    "sg:address":"Kaiserstr. 79",
    "sg:city":"Bruchsal",
    "sg:phone":"+49 7251/2072",
    "sg:postcode":"76646",
    "sg:province":"Baden-W\u00fcrttemberg",
    "wof:name":"Doering Grundbesitz Gmbh & Co. Kg",
    "wof:placetype":"venue"
},
  "geometry": {"coordinates":[8.5985536575,49.1241378784],"type":"Point"}
}