{
  "type": "Feature",
  "properties": {
    "iso:country":"DE",
    "sg:address":"Holstenstr. 106",
    "sg:city":"Kiel",
    "sg:phone":"+49 431/9719770",
    "sg:postcode":"24103",
    "sg:province":"Schleswig-Holstein",
    "wof:name":"E-plus Shop",
    "wof:placetype":"venue"
},
  "geometry": {"coordinates":[10.1329088211,54.3190765381],"type":"Point"}
}