{
  "type": "Feature",
  "properties": {
    "iso:country":"DE",
    "sg:address":"Adriansweg 11",
    "sg:city":"Viersen",
    "sg:phone":"+49 2162/355116",
    "sg:postcode":"41748",
    "sg:province":"Nordrhein-Westfalen",
    "wof:name":"Karl-heinz Pelzer",
    "wof:placetype":"venue"
},
  "geometry": {"coordinates":[6.3831071854,51.237739563],"type":"Point"}
}