{
  "type": "Feature",
  "properties": {
    "iso:country":"DE",
    "sg:address":"Hauptstr. 1",
    "sg:city":"Holm",
    "sg:phone":"+49 4103/85341",
    "sg:postcode":"25488",
    "sg:province":"Schleswig-Holstein",
    "wof:name":"Hans Werner Groth",
    "wof:placetype":"venue"
},
  "geometry": {"coordinates":[9.674612,53.61805],"type":"Point"}
}