{
  "type": "Feature",
  "properties": {
    "iso:country":"DE",
    "sg:address":"Zum Wildpark 3",
    "sg:city":"Edertal",
    "sg:phone":"+49 5623/2019",
    "sg:postcode":"34549",
    "sg:province":"Hessen",
    "wof:name":"G\u00e4stehaus E. Kr\u00fcger",
    "wof:placetype":"venue"
},
  "geometry": {"coordinates":[9.0542573929,51.1802711487],"type":"Point"}
}