{
  "type": "Feature",
  "properties": {
    "iso:country":"DE",
    "sg:address":"Kaiserdamm 31",
    "sg:city":"Berlin",
    "sg:postcode":"14057",
    "sg:province":"Berlin",
    "wof:name":"Verband Der Betriebsbeauf- Tragten F\u00fcr Umweltschutz E. V.",
    "wof:placetype":"venue"
},
  "geometry": {"coordinates":[13.278939,52.510029],"type":"Point"}
}