{
  "type": "Feature",
  "properties": {
    "iso:country":"DE",
    "sg:address":"Dernekamp 28",
    "sg:city":"D\u00fclmen",
    "sg:phone":"+49 2594/5738",
    "sg:postcode":"48249",
    "sg:province":"Nordrhein-Westfalen",
    "wof:name":"Aloys Mengelkamp",
    "wof:placetype":"venue"
},
  "geometry": {"coordinates":[7.3392109871,51.7947235107],"type":"Point"}
}