{
  "type": "Feature",
  "properties": {
    "iso:country":"DE",
    "sg:address":"Gr\u00fcnberger Str. 81",
    "sg:city":"Reiskirchen",
    "sg:phone":"+49 6408/62584",
    "sg:postcode":"35447",
    "sg:province":"Hessen",
    "wof:name":"Philipp Pfeffer",
    "wof:placetype":"venue"
},
  "geometry": {"coordinates":[8.83511,50.595608],"type":"Point"}
}