{
  "type": "Feature",
  "properties": {
    "iso:country":"DE",
    "sg:address":"Bundesstr. 94",
    "sg:city":"Gundelfingen",
    "sg:phone":"+49 761/592990",
    "sg:postcode":"79194",
    "sg:province":"Baden-W\u00fcrttemberg",
    "wof:name":"Christian Smaczny Steuerberater",
    "wof:placetype":"venue"
},
  "geometry": {"coordinates":[7.8702788353,48.0446548462],"type":"Point"}
}