{
  "type": "Feature",
  "properties": {
    "iso:country":"DE",
    "sg:address":"Gustavstr. 7",
    "sg:city":"K\u00f6ln",
    "sg:postcode":"50937",
    "sg:province":"Nordrhein-Westfalen",
    "wof:name":"A. S. H. Gmbh",
    "wof:placetype":"venue"
},
  "geometry": {"coordinates":[6.925590992,50.9196014404],"type":"Point"}
}