{
  "type": "Feature",
  "properties": {
    "iso:country":"DE",
    "sg:address":"Am Anger 56",
    "sg:city":"Leipzig",
    "sg:phone":"+49 34298/68504",
    "sg:postcode":"04356",
    "sg:province":"Sachsen",
    "wof:name":"Pension R\u00f6hrborn",
    "wof:placetype":"venue"
},
  "geometry": {"coordinates":[12.4518613815,51.4213752747],"type":"Point"}
}