{
  "type": "Feature",
  "properties": {
    "iso:country":"DE",
    "sg:address":"Theatinerstr. 45",
    "sg:city":"M\u00fcnchen",
    "sg:phone":"+49 89/2901340",
    "sg:postcode":"80333",
    "sg:province":"Bayern",
    "wof:name":"Gerstner Und Kollmar Notare",
    "wof:placetype":"venue"
},
  "geometry": {"coordinates":[11.5760688782,48.1396408081],"type":"Point"}
}