{
  "type": "Feature",
  "properties": {
    "iso:country":"DE",
    "sg:address":"Untergath 200",
    "sg:city":"Krefeld",
    "sg:phone":"+49 2151/542972",
    "sg:postcode":"47805",
    "sg:province":"Nordrhein-Westfalen",
    "wof:name":"Thuringia",
    "wof:placetype":"venue"
},
  "geometry": {"coordinates":[6.5899739265,51.3236846924],"type":"Point"}
}