{
  "type": "Feature",
  "properties": {
    "iso:country":"DE",
    "sg:address":"Postfach 1141",
    "sg:city":"Geilenkirchen",
    "sg:phone":"+49 2451/4037",
    "sg:postcode":"52501",
    "sg:province":"Nordrhein-Westfalen",
    "wof:name":"Gewerkschaft Carolus-magnus Steinkohlenbergwerk",
    "wof:placetype":"venue"
},
  "geometry": {"coordinates":[6.12210989,50.9654884338],"type":"Point"}
}