{
  "type": "Feature",
  "properties": {
    "iso:country":"DE",
    "sg:address":"Alte J\u00fclicher Str. 103",
    "sg:city":"D\u00fcren",
    "sg:phone":"+49 2421/41936",
    "sg:postcode":"52353",
    "sg:province":"Nordrhein-Westfalen",
    "wof:name":"Gaffel Stube",
    "wof:placetype":"venue"
},
  "geometry": {"coordinates":[6.4764490128,50.8157463074],"type":"Point"}
}