{
  "type": "Feature",
  "properties": {
    "iso:country":"DE",
    "sg:address":"Geschwister-Burch-Str. 33",
    "sg:city":"Euskirchen",
    "sg:phone":"+49 2255/950270",
    "sg:postcode":"53881",
    "sg:province":"Nordrhein-Westfalen",
    "wof:name":"W. Jonas",
    "wof:placetype":"venue"
},
  "geometry": {"coordinates":[6.83356,50.603474],"type":"Point"}
}