{
  "type": "Feature",
  "properties": {
    "iso:country":"DE",
    "sg:address":"Balinger Str 135",
    "sg:city":"Balingen",
    "sg:phone":"+49 7433/99010",
    "sg:postcode":"72336",
    "sg:province":"Baden-W\u00fcrttemberg",
    "wof:name":"H\u00e4ndel + Diller Gmbh",
    "wof:placetype":"venue"
},
  "geometry": {"coordinates":[8.8617572784,48.2518196106],"type":"Point"}
}