{
  "type": "Feature",
  "properties": {
    "iso:country":"DE",
    "sg:address":"Torstensonring 12",
    "sg:city":"Leipzig",
    "sg:phone":"+49 341/467320",
    "sg:postcode":"04158",
    "sg:province":"Sachsen",
    "wof:name":"Ing. Holzbau Und Zimmerei Kandler Gmbh",
    "wof:placetype":"venue"
},
  "geometry": {"coordinates":[12.3597211838,51.4032897949],"type":"Point"}
}