{
  "type": "Feature",
  "properties": {
    "iso:country":"DE",
    "sg:address":"Walther-Rathenau-Str. 1",
    "sg:city":"Bad Elster",
    "sg:phone":"+49 37437/3481",
    "sg:postcode":"08645",
    "sg:province":"Sachsen",
    "wof:name":"Cafe Fortuna",
    "wof:placetype":"venue"
},
  "geometry": {"coordinates":[12.234991,50.278992],"type":"Point"}
}