{
  "type": "Feature",
  "properties": {
    "iso:country":"DE",
    "sg:address":"Lange Str. 23",
    "sg:city":"Bad Zwischenahn",
    "sg:phone":"+49 4403/93690",
    "sg:postcode":"26160",
    "sg:province":"Niedersachsen",
    "wof:name":"Schwalbennest",
    "wof:placetype":"venue"
},
  "geometry": {"coordinates":[8.0048027039,53.1811141968],"type":"Point"}
}