{
  "type": "Feature",
  "properties": {
    "iso:country":"DE",
    "sg:address":"Dammstr. 14",
    "sg:city":"Hildesheim",
    "sg:phone":"+49 5121/36624",
    "sg:postcode":"31134",
    "sg:province":"Niedersachsen",
    "wof:name":"Dkv Deutsche Krankenversicherung",
    "wof:placetype":"venue"
},
  "geometry": {"coordinates":[9.943353653,52.1499900818],"type":"Point"}
}