{
  "type": "Feature",
  "properties": {
    "iso:country":"DE",
    "sg:address":"M\u00fchlenstr. 6",
    "sg:city":"Aschheim",
    "sg:phone":"+49 89/9038836",
    "sg:postcode":"85609",
    "sg:province":"Bayern",
    "wof:name":"Dieter Eigner",
    "wof:placetype":"venue"
},
  "geometry": {"coordinates":[11.704669,48.188545],"type":"Point"}
}