{
  "type": "Feature",
  "properties": {
    "iso:country":"DE",
    "sg:address":"R\u00f6ntgenstr. 10",
    "sg:city":"Duisburg",
    "sg:phone":"+49 203/446232",
    "sg:postcode":"47167",
    "sg:province":"Nordrhein-Westfalen",
    "wof:name":"Bernd Muhlack Transporte Gmbh",
    "wof:placetype":"venue"
},
  "geometry": {"coordinates":[6.8146109581,51.4919548035],"type":"Point"}
}