{
  "type": "Feature",
  "properties": {
    "iso:country":"DE",
    "sg:address":"Hermann-L\u00f6ns-Str. 14",
    "sg:city":"Budenheim",
    "sg:phone":"+49 6139/92240",
    "sg:postcode":"55257",
    "sg:province":"Rheinland-Pfalz",
    "wof:name":"Johann Hinkel Verlag Gmbh",
    "wof:placetype":"venue"
},
  "geometry": {"coordinates":[8.1640796661,50.0177497864],"type":"Point"}
}