{
  "type": "Feature",
  "properties": {
    "iso:country":"DE",
    "sg:address":"Judeng\u00e4\u00dfchen",
    "sg:city":"M\u00fclheim-K\u00e4rlich",
    "sg:phone":"+49 2630/3313",
    "sg:postcode":"56218",
    "sg:province":"Rheinland-Pfalz",
    "wof:name":"Tenniszentrum M\u00fclheim-k\u00e4rlich",
    "wof:placetype":"venue"
},
  "geometry": {"coordinates":[7.498374939,50.3976898193],"type":"Point"}
}