{
  "type": "Feature",
  "properties": {
    "iso:country":"DE",
    "sg:address":"M\u00fcllerstr. 39",
    "sg:city":"M\u00fcnchen",
    "sg:phone":"+49 89/263188",
    "sg:postcode":"80469",
    "sg:province":"Bayern",
    "wof:name":"Emil Huber",
    "wof:placetype":"venue"
},
  "geometry": {"coordinates":[11.5687494278,48.1311187744],"type":"Point"}
}