{
  "type": "Feature",
  "properties": {
    "iso:country":"DE",
    "sg:address":"Zum Gallerturm 5",
    "sg:city":"\u00dcberlingen",
    "sg:phone":"+49 7551/5969",
    "sg:postcode":"88662",
    "sg:province":"Baden-W\u00fcrttemberg",
    "wof:name":"C.-h. Munding Steuerberater",
    "wof:placetype":"venue"
},
  "geometry": {"coordinates":[9.1583786011,47.7692832947],"type":"Point"}
}