{
  "type": "Feature",
  "properties": {
    "iso:country":"DE",
    "sg:address":"Attendorner Str. 148",
    "sg:city":"Finnentrop",
    "sg:phone":"+49 4977/221037",
    "sg:postcode":"57413",
    "sg:province":"Nordrhein-Westfalen",
    "wof:name":"Joseph Wehrle Gmbh & Co. Kg",
    "wof:placetype":"venue"
},
  "geometry": {"coordinates":[8.230225,48.130173],"type":"Point"}
}