{
  "type": "Feature",
  "properties": {
    "iso:country":"DE",
    "sg:address":"K\u00f6lnische Str. 62",
    "sg:city":"Kassel",
    "sg:phone":"+49 561/18985",
    "sg:postcode":"34117",
    "sg:province":"Hessen",
    "wof:name":"Esso Tankstelle",
    "wof:placetype":"venue"
},
  "geometry": {"coordinates":[9.484087944,51.3171234131],"type":"Point"}
}