{
  "type": "Feature",
  "properties": {
    "iso:country":"DE",
    "sg:address":"Kipdorf 1",
    "sg:city":"Wuppertal",
    "sg:phone":"+49 202/2443273",
    "sg:postcode":"42103",
    "sg:province":"Nordrhein-Westfalen",
    "wof:name":"Autec H\u00f6rger\u00e4te Gmbh",
    "wof:placetype":"venue"
},
  "geometry": {"coordinates":[7.148233,51.256832],"type":"Point"}
}