{
  "type": "Feature",
  "properties": {
    "iso:country":"DE",
    "sg:address":"Silcherstr. 8",
    "sg:city":"Friesenheim",
    "sg:phone":"+49 7821/68090",
    "sg:postcode":"77948",
    "sg:province":"Baden-W\u00fcrttemberg",
    "wof:name":"Bruno Eble",
    "wof:placetype":"venue"
},
  "geometry": {"coordinates":[7.900603,48.377983],"type":"Point"}
}