{
  "type": "Feature",
  "properties": {
    "iso:country":"DE",
    "sg:address":"Stemwarder Str. 19",
    "sg:city":"Reinbek",
    "sg:phone":"+49 40/71095120",
    "sg:postcode":"21465",
    "sg:province":"Schleswig-Holstein",
    "wof:name":"Poch & Kondrats Ohg",
    "wof:placetype":"venue"
},
  "geometry": {"coordinates":[10.2519645691,53.5559692383],"type":"Point"}
}