{
  "type": "Feature",
  "properties": {
    "iso:country":"DE",
    "sg:address":"Obervierauer Weg 2",
    "sg:city":"Miltach",
    "sg:phone":"+49 9944/2552",
    "sg:postcode":"93468",
    "sg:province":"Bayern",
    "wof:name":"Martin Peintinger",
    "wof:placetype":"venue"
},
  "geometry": {"coordinates":[12.76502,49.12896],"type":"Point"}
}