{
  "type": "Feature",
  "properties": {
    "iso:country":"DE",
    "sg:address":"Waldstr. 9",
    "sg:city":"Kulmain",
    "sg:phone":"+49 9234/354",
    "sg:postcode":"95508",
    "sg:province":"Bayern",
    "wof:name":"R. Kopp",
    "wof:placetype":"venue"
},
  "geometry": {"coordinates":[11.9259996414,49.926864624],"type":"Point"}
}