{
  "type": "Feature",
  "properties": {
    "iso:country":"DE",
    "sg:address":"Baarer Str. 12",
    "sg:city":"Holzheim",
    "sg:phone":"+49 8276/58950",
    "sg:postcode":"86684",
    "sg:province":"Bayern",
    "wof:name":"Hammerl Ohg",
    "wof:placetype":"venue"
},
  "geometry": {"coordinates":[10.9497489929,48.6099815369],"type":"Point"}
}