{
  "type": "Feature",
  "properties": {
    "iso:country":"DE",
    "sg:address":"Gustav-Freytag-Str. 38",
    "sg:city":"Erfurt",
    "sg:postcode":"99096",
    "sg:province":"Th\u00fcringen",
    "wof:name":"Winkler Eigenheim Bau Gmbh",
    "wof:placetype":"venue"
},
  "geometry": {"coordinates":[11.020166,50.962509],"type":"Point"}
}