{
  "type": "Feature",
  "properties": {
    "iso:country":"DE",
    "sg:address":"Rosengang 4",
    "sg:city":"Eckernf\u00f6rde",
    "sg:phone":"+49 4351/71720",
    "sg:postcode":"24340",
    "sg:province":"Schleswig-Holstein",
    "wof:name":"Stefan Rimpf Architekt",
    "wof:placetype":"venue"
},
  "geometry": {"coordinates":[9.83812,54.47208],"type":"Point"}
}