{
  "type": "Feature",
  "properties": {
    "iso:country":"DE",
    "sg:address":"R\u00f6vekampstr. 5",
    "sg:city":"Wildeshausen",
    "sg:phone":"+49 4431/4246",
    "sg:postcode":"27793",
    "sg:province":"Niedersachsen",
    "wof:name":"Eduard Jankowski Heilpraktiker",
    "wof:placetype":"venue"
},
  "geometry": {"coordinates":[8.446844101,52.8903388977],"type":"Point"}
}