{
  "type": "Feature",
  "properties": {
    "iso:country":"DE",
    "sg:address":"Schmiedestr. 34",
    "sg:city":"Gelting",
    "sg:phone":"+49 4643/2778",
    "sg:postcode":"24395",
    "sg:province":"Schleswig-Holstein",
    "wof:name":"Herbert Gaartz",
    "wof:placetype":"venue"
},
  "geometry": {"coordinates":[9.8908405304,54.7486381531],"type":"Point"}
}