{
  "type": "Feature",
  "properties": {
    "iso:country":"DE",
    "sg:address":"Kaiserstr. 30",
    "sg:city":"Frankfurt",
    "sg:phone":"+49 4969/26910",
    "sg:postcode":"60311",
    "sg:province":"Hessen",
    "wof:name":"Schweizerische, Kreditanstalt (deutschl.)",
    "wof:placetype":"venue"
},
  "geometry": {"coordinates":[8.673194,50.109951],"type":"Point"}
}