{
  "type": "Feature",
  "properties": {
    "iso:country":"DE",
    "sg:address":"Oberer Markt 12",
    "sg:city":"Volkach",
    "sg:phone":"+49 9381/8081",
    "sg:postcode":"97332",
    "sg:province":"Bayern",
    "wof:name":"Dr. Christina Wolf Notarin",
    "wof:placetype":"venue"
},
  "geometry": {"coordinates":[10.2269296646,49.8641395569],"type":"Point"}
}