{
  "type": "Feature",
  "properties": {
    "iso:country":"DE",
    "sg:address":"Mittelstra\u00dfe 3",
    "sg:city":"Bordesholm",
    "sg:phone":"+49 4322/1061",
    "sg:postcode":"22454",
    "sg:province":"Schleswig-Holstein",
    "wof:name":"Fliesenverlegung",
    "wof:placetype":"venue"
},
  "geometry": {"coordinates":[-76.848083,37.84396],"type":"Point"}
}