{
  "type": "Feature",
  "properties": {
    "iso:country":"DE",
    "sg:address":"Glaswandstr. 8",
    "sg:city":"Benediktbeuern",
    "sg:phone":"+49 8857/9318",
    "sg:postcode":"83671",
    "sg:province":"Bayern",
    "wof:name":"Hausbau Hermann Gmbh",
    "wof:placetype":"venue"
},
  "geometry": {"coordinates":[11.410582,47.703785],"type":"Point"}
}