{
  "type": "Feature",
  "properties": {
    "iso:country":"DE",
    "sg:address":"Kalkweg 26",
    "sg:city":"Duisburg",
    "sg:phone":"+49 203/725790",
    "sg:postcode":"47055",
    "sg:province":"Nordrhein-Westfalen",
    "wof:name":"Dettmanns Restaurant",
    "wof:placetype":"venue"
},
  "geometry": {"coordinates":[6.7739720345,51.4104804993],"type":"Point"}
}