{
  "type": "Feature",
  "properties": {
    "iso:country":"DE",
    "sg:address":"Goethestr. 11",
    "sg:city":"Nu\u00dfloch",
    "sg:phone":"+49 6224/12953",
    "sg:postcode":"69226",
    "sg:province":"Baden-W\u00fcrttemberg",
    "wof:name":"Vvg Gmbh",
    "wof:placetype":"venue"
},
  "geometry": {"coordinates":[8.6947116852,49.3203964233],"type":"Point"}
}