{
  "type": "Feature",
  "properties": {
    "iso:country":"DE",
    "sg:address":"Dreyer Stra\u00dfe 82",
    "sg:city":"Weyhe-Dreye",
    "sg:phone":"+49 4203/783101",
    "sg:postcode":"28844",
    "sg:province":"Niedersachsen",
    "wof:name":"Landwehr Metall- Und Anlagenbau",
    "wof:placetype":"venue"
},
  "geometry": {"coordinates":[8.8805,53.015099],"type":"Point"}
}