{
  "type": "Feature",
  "properties": {
    "iso:country":"DE",
    "sg:address":"Paul-Ehrlich-Str. 10",
    "sg:city":"Dietzenbach",
    "sg:phone":"+49 6074/2043",
    "sg:postcode":"63128",
    "sg:province":"Hessen",
    "wof:name":"Knipp Gmbh",
    "wof:placetype":"venue"
},
  "geometry": {"coordinates":[8.7914056778,50.0075721741],"type":"Point"}
}