{
  "type": "Feature",
  "properties": {
    "iso:country":"DE",
    "sg:address":"Hauptstr. 93",
    "sg:city":"Malsch",
    "sg:phone":"+49 4972/5321235",
    "sg:postcode":"76316",
    "sg:province":"Baden-W\u00fcrttemberg",
    "wof:name":"Volksbank Wiesloch Eg",
    "wof:placetype":"venue"
},
  "geometry": {"coordinates":[8.33922,48.878132],"type":"Point"}
}