{
  "type": "Feature",
  "properties": {
    "iso:country":"DE",
    "sg:address":"Seelbacher Str. 1",
    "sg:city":"Mittenaar",
    "sg:phone":"+49 2772/62856",
    "sg:postcode":"35756",
    "sg:province":"Hessen",
    "wof:name":"Willi Kraus",
    "wof:placetype":"venue"
},
  "geometry": {"coordinates":[8.366117,50.687599],"type":"Point"}
}