{
  "type": "Feature",
  "properties": {
    "iso:country":"DE",
    "sg:address":"M\u00fcnsterstr. 20",
    "sg:city":"\u00dcberlingen",
    "sg:phone":"+49 7551/63363",
    "sg:postcode":"88662",
    "sg:province":"Baden-W\u00fcrttemberg",
    "wof:name":"H. Und H. Keller",
    "wof:placetype":"venue"
},
  "geometry": {"coordinates":[9.1610660553,47.7665748596],"type":"Point"}
}