{
  "type": "Feature",
  "properties": {
    "iso:country":"DE",
    "sg:address":"Im Wiesental 5",
    "sg:city":"Baunatal",
    "sg:phone":"+49 561/949250",
    "sg:postcode":"34225",
    "sg:province":"Hessen",
    "wof:name":"Willi Sonnenschein Ingenieur",
    "wof:placetype":"venue"
},
  "geometry": {"coordinates":[9.4170389175,51.2539596558],"type":"Point"}
}