{
  "type": "Feature",
  "properties": {
    "iso:country":"DE",
    "sg:address":"Weinbergstr. 4",
    "sg:city":"Bad Salzuflen",
    "sg:phone":"+49 5222/85133",
    "sg:postcode":"32108",
    "sg:province":"Nordrhein-Westfalen",
    "wof:name":"Herbert Wend",
    "wof:placetype":"venue"
},
  "geometry": {"coordinates":[8.747779,52.069416],"type":"Point"}
}