{
  "type": "Feature",
  "properties": {
    "iso:country":"DE",
    "sg:address":"Mathias-Thesen-Str. 4c",
    "sg:city":"Oranienburg",
    "sg:postcode":"16515",
    "sg:province":"Brandenburg",
    "wof:name":"Dr. Uta Laufer",
    "wof:placetype":"venue"
},
  "geometry": {"coordinates":[13.258249,52.761299],"type":"Point"}
}