{
  "type": "Feature",
  "properties": {
    "iso:country":"DE",
    "sg:address":"Neue Bachstr. 2",
    "sg:city":"Herdecke",
    "sg:phone":"+49 2330/2300",
    "sg:postcode":"58313",
    "sg:province":"Nordrhein-Westfalen",
    "wof:name":"Reim",
    "wof:placetype":"venue"
},
  "geometry": {"coordinates":[7.43196,51.397774],"type":"Point"}
}