{
  "type": "Feature",
  "properties": {
    "iso:country":"DE",
    "sg:address":"Siemensstr. 4",
    "sg:city":"Altenstadt",
    "sg:phone":"+49 6047/96360",
    "sg:postcode":"63674",
    "sg:province":"Hessen",
    "wof:name":"Tele Plus Gmbh",
    "wof:placetype":"venue"
},
  "geometry": {"coordinates":[8.9673452377,50.2720718384],"type":"Point"}
}