{
  "type": "Feature",
  "properties": {
    "iso:country":"DE",
    "sg:address":"Max-Planck-Str. 10",
    "sg:city":"Bad Neuenahr-Ahrweiler",
    "sg:phone":"+49 2641/900088",
    "sg:postcode":"53474",
    "sg:province":"Rheinland-Pfalz",
    "wof:name":"Fre\u00dfnapf Tierbedarfs Gmbh",
    "wof:placetype":"venue"
},
  "geometry": {"coordinates":[7.1082677841,50.5441360474],"type":"Point"}
}