{
  "type": "Feature",
  "properties": {
    "iso:country":"DE",
    "sg:address":"Artur-Ladebeck-Str. 181",
    "sg:city":"Bielefeld",
    "sg:phone":"+49 521/942280",
    "sg:postcode":"33647",
    "sg:province":"Nordrhein-Westfalen",
    "wof:name":"Medi Part Praxis-computer Vertriebsges. Mbh",
    "wof:placetype":"venue"
},
  "geometry": {"coordinates":[8.5058288574,52.0013656616],"type":"Point"}
}