{
  "type": "Feature",
  "properties": {
    "iso:country":"DE",
    "sg:address":"D\u00fcppelstr. 9",
    "sg:city":"Minden",
    "sg:phone":"+49 571/31200",
    "sg:postcode":"32423",
    "sg:province":"Nordrhein-Westfalen",
    "wof:name":"Wolfgang M. Jochheim Architekt",
    "wof:placetype":"venue"
},
  "geometry": {"coordinates":[8.945333,52.288288],"type":"Point"}
}