{
  "type": "Feature",
  "properties": {
    "iso:country":"DE",
    "sg:address":"Obertal 13",
    "sg:city":"Titisee-Neustadt",
    "sg:phone":"+49 7669/921051",
    "sg:postcode":"79822",
    "sg:province":"Baden-W\u00fcrttemberg",
    "wof:name":"Ganters Holzh\u00e4user Gmbh",
    "wof:placetype":"venue"
},
  "geometry": {"coordinates":[8.17271,47.984829],"type":"Point"}
}