{
  "type": "Feature",
  "properties": {
    "iso:country":"DE",
    "sg:address":"Untere Dorfstr. 43",
    "sg:city":"Buchhofen",
    "sg:phone":"+49 9938/468",
    "sg:postcode":"94533",
    "sg:province":"Bayern",
    "wof:name":"Ludwig Apfelbeck",
    "wof:placetype":"venue"
},
  "geometry": {"coordinates":[12.95075,48.72052],"type":"Point"}
}