{
  "type": "Feature",
  "properties": {
    "iso:country":"DE",
    "sg:address":"Liepgartener Str. 18",
    "sg:city":"Ueckerm\u00fcnde",
    "sg:phone":"+49 39771/2870",
    "sg:postcode":"17373",
    "sg:province":"Mecklenburg-Vorpommern",
    "wof:name":"Tusek-bau Gmbh",
    "wof:placetype":"venue"
},
  "geometry": {"coordinates":[14.034403801,53.7298927307],"type":"Point"}
}