{
  "type": "Feature",
  "properties": {
    "iso:country":"DE",
    "sg:address":"Ulrichgasse 16 A",
    "sg:city":"K\u00f6ln",
    "sg:phone":"+49 221/321895",
    "sg:postcode":"50678",
    "sg:province":"Nordrhein-Westfalen",
    "wof:name":"Hedwig Bittner",
    "wof:placetype":"venue"
},
  "geometry": {"coordinates":[6.9552741051,50.9267959595],"type":"Point"}
}