{
  "type": "Feature",
  "properties": {
    "iso:country":"DE",
    "sg:address":"An der \u00d6lm\u00fchle 1-2",
    "sg:city":"Hardegsen",
    "sg:phone":"+49 5505/2345",
    "sg:postcode":"37181",
    "sg:province":"Niedersachsen",
    "wof:name":"Gerwig Bau Gmbh",
    "wof:placetype":"venue"
},
  "geometry": {"coordinates":[9.841151,51.647587],"type":"Point"}
}