{
  "type": "Feature",
  "properties": {
    "iso:country":"DE",
    "sg:address":"An der Wittgeshohl 32",
    "sg:city":"Westhofen",
    "sg:phone":"+49 6244/57359",
    "sg:postcode":"67593",
    "sg:province":"Rheinland-Pfalz",
    "wof:name":"Hans-j\u00fcrgen Hemer Anlageberater",
    "wof:placetype":"venue"
},
  "geometry": {"coordinates":[8.2513399124,49.7062301636],"type":"Point"}
}