{
  "type": "Feature",
  "properties": {
    "iso:country":"DE",
    "sg:address":"G\u00f6tzensteinstr. 33c",
    "sg:city":"M\u00f6rlenbach",
    "sg:phone":"+49 6209/5603",
    "sg:postcode":"69509",
    "sg:province":"Hessen",
    "wof:name":"Hartmut Rautenberg",
    "wof:placetype":"venue"
},
  "geometry": {"coordinates":[8.768864,49.572163],"type":"Point"}
}