{
  "type": "Feature",
  "properties": {
    "iso:country":"DE",
    "sg:address":"Nu\u00dflocher Str. 12",
    "sg:city":"Leimen",
    "sg:phone":"+49 6224/72966",
    "sg:postcode":"69181",
    "sg:province":"Baden-W\u00fcrttemberg",
    "wof:name":"Werner Scholz",
    "wof:placetype":"venue"
},
  "geometry": {"coordinates":[8.692284584,49.3473472595],"type":"Point"}
}