{
  "type": "Feature",
  "properties": {
    "iso:country":"DE",
    "sg:address":"Maistr. 29",
    "sg:city":"M\u00fcnchen",
    "sg:phone":"+49 89/5438188",
    "sg:postcode":"80337",
    "sg:province":"Bayern",
    "wof:name":"Tvrdovski",
    "wof:placetype":"venue"
},
  "geometry": {"coordinates":[11.5624036789,48.1293907166],"type":"Point"}
}