{
  "type": "Feature",
  "properties": {
    "iso:country":"DE",
    "sg:address":"Maienweg 23",
    "sg:city":"Ulm",
    "sg:phone":"+49 731/381729",
    "sg:postcode":"89081",
    "sg:province":"Baden-W\u00fcrttemberg",
    "wof:name":"Bilger Kg Enzian-milchprodukte",
    "wof:placetype":"venue"
},
  "geometry": {"coordinates":[9.9479856491,48.3947486877],"type":"Point"}
}