{
  "type": "Feature",
  "properties": {
    "iso:country":"DE",
    "sg:address":"Lehmbruckstr. 9",
    "sg:city":"Duisburg",
    "sg:phone":"+49 203/427309",
    "sg:postcode":"47138",
    "sg:province":"Nordrhein-Westfalen",
    "wof:name":"Udo Segelke",
    "wof:placetype":"venue"
},
  "geometry": {"coordinates":[6.8172559738,51.4697761536],"type":"Point"}
}