{
  "type": "Feature",
  "properties": {
    "iso:country":"DE",
    "sg:address":"Meininger Str. 222",
    "sg:city":"Suhl",
    "sg:phone":"+49 3681/303789",
    "sg:postcode":"98529",
    "sg:province":"Th\u00fcringen",
    "wof:name":"Avis",
    "wof:placetype":"venue"
},
  "geometry": {"coordinates":[10.637045,50.604767],"type":"Point"}
}