{
  "type": "Feature",
  "properties": {
    "iso:country":"DE",
    "sg:address":"Unterm Stein 14",
    "sg:city":"Heubach",
    "sg:phone":"+49 7173/6553",
    "sg:postcode":"73540",
    "sg:province":"Baden-W\u00fcrttemberg",
    "wof:name":"Hans W. Haag Architekt",
    "wof:placetype":"venue"
},
  "geometry": {"coordinates":[9.968388,48.801987],"type":"Point"}
}