{
  "type": "Feature",
  "properties": {
    "iso:country":"DE",
    "sg:address":"Alfredstr. 31",
    "sg:city":"Essen",
    "sg:phone":"+49 201/7200660",
    "sg:postcode":"45130",
    "sg:province":"Nordrhein-Westfalen",
    "wof:name":"Meier Behrendt Und Knoblauch Rechtsanw\u00e4lte Und Notare",
    "wof:placetype":"venue"
},
  "geometry": {"coordinates":[7.003674984,51.4388237],"type":"Point"}
}