{
  "type": "Feature",
  "properties": {
    "iso:country":"DE",
    "sg:address":"Sonderm\u00fcllerweg 8",
    "sg:city":"Freising",
    "sg:phone":"+49 8161/7555",
    "sg:postcode":"85354",
    "sg:province":"Bayern",
    "wof:name":"Ant. Seidl Gmbh",
    "wof:placetype":"venue"
},
  "geometry": {"coordinates":[11.748512,48.399323],"type":"Point"}
}