{
  "type": "Feature",
  "properties": {
    "iso:country":"DE",
    "sg:address":"Neue Str. 9-11",
    "sg:city":"Jever",
    "sg:phone":"+49 4461/3244",
    "sg:postcode":"26441",
    "sg:province":"Niedersachsen",
    "wof:name":"Seemann Gmbh",
    "wof:placetype":"venue"
},
  "geometry": {"coordinates":[7.90324,53.574478],"type":"Point"}
}