{
  "type": "Feature",
  "properties": {
    "iso:country":"DE",
    "sg:address":"Putzbrunner Str. 193",
    "sg:city":"M\u00fcnchen",
    "sg:phone":"+49 89/603429",
    "sg:postcode":"81739",
    "sg:province":"Bayern",
    "wof:name":"Heinrich M\u00e4chler",
    "wof:placetype":"venue"
},
  "geometry": {"coordinates":[11.6628046036,48.0904579163],"type":"Point"}
}