{
  "type": "Feature",
  "properties": {
    "iso:country":"DE",
    "sg:address":"Neugrabener Markt 9",
    "sg:city":"Hamburg",
    "sg:phone":"+49 40/7015900",
    "sg:postcode":"21149",
    "sg:province":"Hamburg",
    "wof:name":"S\u00fcderelbe Hallenbad",
    "wof:placetype":"venue"
},
  "geometry": {"coordinates":[9.8513612747,53.4695549011],"type":"Point"}
}