{
  "type": "Feature",
  "properties": {
    "iso:country":"DE",
    "sg:address":"Vor dem Ha\u00dfel 6c",
    "sg:city":"Brackel",
    "sg:phone":"+49 4185/585810",
    "sg:postcode":"21438",
    "sg:province":"Niedersachsen",
    "wof:name":"Hpm Gmbh",
    "wof:placetype":"venue"
},
  "geometry": {"coordinates":[10.06044,53.304642],"type":"Point"}
}