{
  "type": "Feature",
  "properties": {
    "iso:country":"DE",
    "sg:address":"Jeversche Str. 100a",
    "sg:city":"Wangerland",
    "sg:phone":"+49 4463/942106",
    "sg:postcode":"26434",
    "sg:province":"Niedersachsen",
    "wof:name":"Hans-j\u00fcrgen Maevus",
    "wof:placetype":"venue"
},
  "geometry": {"coordinates":[7.8683681488,53.5970802307],"type":"Point"}
}