{
  "type": "Feature",
  "properties": {
    "iso:country":"DE",
    "sg:address":"Wilbaser Str. 41",
    "sg:city":"Blomberg",
    "sg:postcode":"32825",
    "sg:province":"Nordrhein-Westfalen",
    "wof:name":"Nat\u00fcrlich Sch\u00f6n Verwaltungsgesellschaft Mbh",
    "wof:placetype":"venue"
},
  "geometry": {"coordinates":[9.0609302521,51.9330596924],"type":"Point"}
}