{
  "type": "Feature",
  "properties": {
    "iso:country":"DE",
    "sg:address":"Hauptstr. 71",
    "sg:city":"Miehlen",
    "sg:phone":"+49 6772/93150",
    "sg:postcode":"56357",
    "sg:province":"Rheinland-Pfalz",
    "wof:name":"Heuser Maschinen- Und Formenbau Gmbh",
    "wof:placetype":"venue"
},
  "geometry": {"coordinates":[7.832934,50.22435],"type":"Point"}
}