{
  "type": "Feature",
  "properties": {
    "iso:country":"DE",
    "sg:address":"Kasseler Str. 4",
    "sg:city":"Fritzlar",
    "sg:phone":"+49 5622/3200",
    "sg:postcode":"34560",
    "sg:province":"Hessen",
    "wof:name":"Deniz Ates",
    "wof:placetype":"venue"
},
  "geometry": {"coordinates":[9.274887,51.13224],"type":"Point"}
}