{
  "type": "Feature",
  "properties": {
    "iso:country":"DE",
    "sg:address":"Friedrich-Franz-Str. 19",
    "sg:city":"Brandenburg",
    "sg:phone":"+49 3381/522464",
    "sg:postcode":"14770",
    "sg:province":"Brandenburg",
    "wof:name":"Kurth-b\u00fcrotechnik",
    "wof:placetype":"venue"
},
  "geometry": {"coordinates":[12.5085706711,52.3951416016],"type":"Point"}
}