{
  "type": "Feature",
  "properties": {
    "iso:country":"DE",
    "sg:address":"Asamstr 8",
    "sg:city":"M\u00fcnchen",
    "sg:phone":"+49 89/652356",
    "sg:postcode":"81541",
    "sg:province":"Bayern",
    "wof:name":"Buchdruckerei Christian V\u00f6hringer",
    "wof:placetype":"venue"
},
  "geometry": {"coordinates":[11.577969,48.124973],"type":"Point"}
}