{
  "type": "Feature",
  "properties": {
    "iso:country":"DE",
    "sg:address":"Olgastr. 16",
    "sg:city":"Bad Urach",
    "sg:phone":"+49 7125/8485",
    "sg:postcode":"72574",
    "sg:province":"Baden-W\u00fcrttemberg",
    "wof:name":"Martina Jung Gmbh",
    "wof:placetype":"venue"
},
  "geometry": {"coordinates":[9.4033279419,48.4947357178],"type":"Point"}
}