{
  "type": "Feature",
  "properties": {
    "iso:country":"DE",
    "sg:address":"Adamsweg 1",
    "sg:city":"Wegberg",
    "sg:phone":"+49 2434/6862",
    "sg:postcode":"41844",
    "sg:province":"Nordrhein-Westfalen",
    "wof:name":"Basten & Pl\u00fccken",
    "wof:placetype":"venue"
},
  "geometry": {"coordinates":[6.2537288666,51.135219574],"type":"Point"}
}