{
  "type": "Feature",
  "properties": {
    "iso:country":"DE",
    "sg:address":"An der D\u00fcnung 25",
    "sg:city":"Wismar",
    "sg:phone":"+49 3841/642271",
    "sg:postcode":"23968",
    "sg:province":"Mecklenburg-Vorpommern",
    "wof:name":"Jochen Hammerich",
    "wof:placetype":"venue"
},
  "geometry": {"coordinates":[11.3968000412,53.9093704224],"type":"Point"}
}