{
  "type": "Feature",
  "properties": {
    "iso:country":"DE",
    "sg:address":"Vor der Egge 8",
    "sg:city":"L\u00f6hne",
    "sg:phone":"+49 5732/2000",
    "sg:postcode":"32584",
    "sg:province":"Nordrhein-Westfalen",
    "wof:name":"Arno Hagemeier",
    "wof:placetype":"venue"
},
  "geometry": {"coordinates":[8.699454,52.203934],"type":"Point"}
}