{
  "type": "Feature",
  "properties": {
    "iso:country":"DE",
    "sg:address":"Lindenfeldweg 3",
    "sg:city":"Ottersweier",
    "sg:phone":"+49 7223/910933",
    "sg:postcode":"77833",
    "sg:province":"Baden-W\u00fcrttemberg",
    "wof:name":"Marin Gmbh",
    "wof:placetype":"venue"
},
  "geometry": {"coordinates":[8.1209640503,48.6722793579],"type":"Point"}
}