{
  "type": "Feature",
  "properties": {
    "iso:country":"DE",
    "sg:address":"Ehlersstr. 17",
    "sg:city":"Friedrichshafen",
    "sg:phone":"+49 7541/71006",
    "sg:postcode":"88046",
    "sg:province":"Baden-W\u00fcrttemberg",
    "wof:name":"Bodensee-apotheke",
    "wof:placetype":"venue"
},
  "geometry": {"coordinates":[9.484123,47.658916],"type":"Point"}
}