{
  "type": "Feature",
  "properties": {
    "iso:country":"DE",
    "sg:address":"Neckarstr. 25",
    "sg:city":"Oberndorf",
    "sg:postcode":"78727",
    "sg:province":"Baden-W\u00fcrttemberg",
    "wof:name":"Werner Hauer Gmbh",
    "wof:placetype":"venue"
},
  "geometry": {"coordinates":[8.576378,48.299686],"type":"Point"}
}