{
  "type": "Feature",
  "properties": {
    "iso:country":"DE",
    "sg:address":"Fl\u00f6\u00dferstr. 1",
    "sg:city":"Wallgau",
    "sg:phone":"+49 8825/376",
    "sg:postcode":"82499",
    "sg:province":"Bayern",
    "wof:name":"Fremdenheim J. Wackerle",
    "wof:placetype":"venue"
},
  "geometry": {"coordinates":[11.2847757339,47.523639679],"type":"Point"}
}