{
  "type": "Feature",
  "properties": {
    "iso:country":"DE",
    "sg:address":"Worpswede",
    "sg:city":"Worpswede",
    "sg:phone":"+49 4792/7001",
    "sg:postcode":"27726",
    "sg:province":"Niedersachsen",
    "wof:name":"Kreissparkasse Osterholz",
    "wof:placetype":"venue"
},
  "geometry": {"coordinates":[8.97585,53.261318],"type":"Point"}
}