{
  "type": "Feature",
  "properties": {
    "iso:country":"DE",
    "sg:address":"Wertherstr. 32",
    "sg:city":"Spenge",
    "sg:phone":"+49 5225/9577",
    "sg:postcode":"32139",
    "sg:province":"Nordrhein-Westfalen",
    "wof:name":"W. Schiering",
    "wof:placetype":"venue"
},
  "geometry": {"coordinates":[8.4772424698,52.1148414612],"type":"Point"}
}