{
  "type": "Feature",
  "properties": {
    "iso:country":"DE",
    "sg:address":"Klausenerplatz 4",
    "sg:city":"Berlin",
    "sg:phone":"+49 30/3212005",
    "sg:postcode":"14059",
    "sg:province":"Berlin",
    "wof:name":"Restaurant Karagiosis",
    "wof:placetype":"venue"
},
  "geometry": {"coordinates":[13.292766571,52.5184555054],"type":"Point"}
}