{
  "type": "Feature",
  "properties": {
    "iso:country":"DE",
    "sg:address":"Viktor-Scheffel-Str. 13",
    "sg:city":"Erfurt",
    "sg:phone":"+49 361/420030",
    "sg:postcode":"99096",
    "sg:province":"Th\u00fcringen",
    "wof:name":"Bestattugen Thorwesten",
    "wof:placetype":"venue"
},
  "geometry": {"coordinates":[11.030057,50.961777],"type":"Point"}
}