{
  "type": "Feature",
  "properties": {
    "iso:country":"DE",
    "sg:address":"Ruhbachstr.",
    "sg:city":"Spiesen-Elversberg",
    "sg:phone":"+49 6821/71555",
    "sg:postcode":"66583",
    "sg:province":"Saarland",
    "wof:name":"Heinrich M\u00fcller",
    "wof:placetype":"venue"
},
  "geometry": {"coordinates":[7.122464,49.311481],"type":"Point"}
}