{
  "type": "Feature",
  "properties": {
    "iso:country":"DE",
    "sg:address":"Berlinstr. 97",
    "sg:city":"Bingen",
    "sg:phone":"+49 6721/48180",
    "sg:postcode":"55411",
    "sg:province":"Rheinland-Pfalz",
    "wof:name":"Bistro Roxi",
    "wof:placetype":"venue"
},
  "geometry": {"coordinates":[7.9211387634,49.9530563354],"type":"Point"}
}