{
  "type": "Feature",
  "properties": {
    "iso:country":"DE",
    "sg:address":"Gr\u00f6nenweg 29",
    "sg:city":"Hamburg",
    "sg:phone":"+49 40/802858",
    "sg:postcode":"22549",
    "sg:province":"Hamburg",
    "wof:name":"Ruth Barth",
    "wof:placetype":"venue"
},
  "geometry": {"coordinates":[9.848083,53.578228],"type":"Point"}
}