{
  "type": "Feature",
  "properties": {
    "iso:country":"DE",
    "sg:address":"Otto-von-Guericke-Ring 3",
    "sg:city":"Wiesbaden",
    "sg:postcode":"65205",
    "sg:province":"Hessen",
    "wof:name":"Top - Media Vertrieb",
    "wof:placetype":"venue"
},
  "geometry": {"coordinates":[8.3376226425,50.0577087402],"type":"Point"}
}