{
  "type": "Feature",
  "properties": {
    "iso:country":"DE",
    "sg:address":"In der Hardt 42",
    "sg:city":"Kempenich",
    "sg:postcode":"56746",
    "sg:province":"Rheinland-Pfalz",
    "wof:name":"Alltime Jagdartikelversand Gmbh",
    "wof:placetype":"venue"
},
  "geometry": {"coordinates":[7.109978199,50.4208679199],"type":"Point"}
}