{
  "type": "Feature",
  "properties": {
    "iso:country":"DE",
    "sg:address":"Neue Rabenstr. 5",
    "sg:city":"Hamburg",
    "sg:postcode":"20354",
    "sg:province":"Hamburg",
    "wof:name":"Allegro Beteiligungs- Gesellschaft Mbh",
    "wof:placetype":"venue"
},
  "geometry": {"coordinates":[9.9939613342,53.5619773865],"type":"Point"}
}