{
  "type": "Feature",
  "properties": {
    "iso:country":"DE",
    "sg:address":"Zum Kn\u00f6schen 2",
    "sg:city":"Flieden",
    "sg:phone":"+49 6669/1788",
    "sg:postcode":"36103",
    "sg:province":"Hessen",
    "wof:name":"Lvm S\u00e4mann Gmbh",
    "wof:placetype":"venue"
},
  "geometry": {"coordinates":[9.5108642578,50.4489746094],"type":"Point"}
}