{
  "type": "Feature",
  "properties": {
    "iso:country":"DE",
    "sg:address":"Hauptmarkt 17",
    "sg:city":"Trier",
    "sg:phone":"+49 651/75644",
    "sg:postcode":"54290",
    "sg:province":"Rheinland-Pfalz",
    "wof:name":"Parf\u00fcmerie Douglas S\u00fcd Gmbh & Co. Kg",
    "wof:placetype":"venue"
},
  "geometry": {"coordinates":[6.641326,49.756969],"type":"Point"}
}