{
  "type": "Feature",
  "properties": {
    "iso:country":"DE",
    "sg:address":"Im Knick 1 B",
    "sg:city":"Ganderkesee",
    "sg:phone":"+49 4222/950177",
    "sg:postcode":"27777",
    "sg:province":"Niedersachsen",
    "wof:name":"Henry Meissner Praxis F\u00fcr Ergotherapie",
    "wof:placetype":"venue"
},
  "geometry": {"coordinates":[8.544542,53.033512],"type":"Point"}
}