{
  "type": "Feature",
  "properties": {
    "iso:country":"DE",
    "sg:address":"D\u00f6rrenbachstr. 22",
    "sg:city":"Suhl",
    "sg:phone":"+49 3681/422469",
    "sg:postcode":"98528",
    "sg:province":"Th\u00fcringen",
    "wof:name":"Restaurant Inh. Mehmet Cesur Oruc",
    "wof:placetype":"venue"
},
  "geometry": {"coordinates":[10.7050199509,50.6273040771],"type":"Point"}
}