{
  "type": "Feature",
  "properties": {
    "iso:country":"DE",
    "sg:address":"Kyreinstr. 8",
    "sg:city":"M\u00fcnchen",
    "sg:postcode":"81371",
    "sg:province":"Bayern",
    "wof:name":"Thywissen Consulting Gmbh",
    "wof:placetype":"venue"
},
  "geometry": {"coordinates":[11.5487222672,48.1202964783],"type":"Point"}
}