{
  "type": "Feature",
  "properties": {
    "iso:country":"DE",
    "sg:address":"Aff\u00f6llerstr. 47-49",
    "sg:city":"Marburg",
    "sg:phone":"+49 6421/96340",
    "sg:postcode":"35039",
    "sg:province":"Hessen",
    "wof:name":"Beteiligungs-gesellschaft Daube Gmbh",
    "wof:placetype":"venue"
},
  "geometry": {"coordinates":[8.769297,50.826393],"type":"Point"}
}