{
  "type": "Feature",
  "properties": {
    "iso:country":"DE",
    "sg:address":"Hauptstr. 3",
    "sg:city":"Ro\u00dfdorf",
    "sg:phone":"+49 36968/60249",
    "sg:postcode":"98590",
    "sg:province":"Th\u00fcringen",
    "wof:name":"Erich Specht",
    "wof:placetype":"venue"
},
  "geometry": {"coordinates":[10.21581,50.702469],"type":"Point"}
}