{
  "type": "Feature",
  "properties": {
    "iso:country":"DE",
    "sg:address":"Lieselottestr. 13",
    "sg:city":"Dielheim",
    "sg:phone":"+49 6222/72021",
    "sg:postcode":"69234",
    "sg:province":"Baden-W\u00fcrttemberg",
    "wof:name":"Zusarth Immobilienmakler",
    "wof:placetype":"venue"
},
  "geometry": {"coordinates":[8.7325468063,49.2884101868],"type":"Point"}
}