{
  "type": "Feature",
  "properties": {
    "iso:country":"DE",
    "sg:address":"Herborner Str. 23",
    "sg:city":"Siegbach",
    "sg:phone":"+49 4927/7891300",
    "sg:postcode":"35768",
    "sg:province":"Hessen",
    "wof:name":"Team Tec Gmbh",
    "wof:placetype":"venue"
},
  "geometry": {"coordinates":[8.417278,50.735153],"type":"Point"}
}