{
  "type": "Feature",
  "properties": {
    "iso:country":"DE",
    "sg:address":"Marktplatz 2",
    "sg:city":"Ratingen",
    "sg:phone":"+49 2102/23619",
    "sg:postcode":"40878",
    "sg:province":"Nordrhein-Westfalen",
    "wof:name":"Hugo Strotmann Rechtsanwalt",
    "wof:placetype":"venue"
},
  "geometry": {"coordinates":[6.8493828773,51.2970428467],"type":"Point"}
}