{
  "type": "Feature",
  "properties": {
    "iso:country":"DE",
    "sg:address":"Kreuzgasse 38",
    "sg:city":"Steinweiler",
    "sg:phone":"+49 6349/8613",
    "sg:postcode":"76872",
    "sg:province":"Rheinland-Pfalz",
    "wof:name":"Karl Bevier",
    "wof:placetype":"venue"
},
  "geometry": {"coordinates":[8.136715,49.119938],"type":"Point"}
}