{
  "type": "Feature",
  "properties": {
    "iso:country":"DE",
    "sg:address":"\u00dcfter Weg 30",
    "sg:city":"Schermbeck",
    "sg:phone":"+49 2858/6050",
    "sg:postcode":"46514",
    "sg:province":"Nordrhein-Westfalen",
    "wof:name":"Albert Schulte",
    "wof:placetype":"venue"
},
  "geometry": {"coordinates":[6.777669,51.684055],"type":"Point"}
}