{
  "type": "Feature",
  "properties": {
    "iso:country":"DE",
    "sg:address":"Berliner Chaussee 37",
    "sg:city":"L\u00fcbben",
    "sg:phone":"+49 3546/4812",
    "sg:postcode":"15907",
    "sg:province":"Brandenburg",
    "wof:name":"Wolfgang Stahl",
    "wof:placetype":"venue"
},
  "geometry": {"coordinates":[13.8641166687,51.9472541809],"type":"Point"}
}