{
  "type": "Feature",
  "properties": {
    "iso:country":"DE",
    "sg:address":"Wiesenstr. 63",
    "sg:city":"Buseck",
    "sg:phone":"+49 6408/7643",
    "sg:postcode":"35418",
    "sg:province":"Hessen",
    "wof:name":"M. Kusterer Immobilienmakler",
    "wof:placetype":"venue"
},
  "geometry": {"coordinates":[8.7843561172,50.6044769287],"type":"Point"}
}