{
  "type": "Feature",
  "properties": {
    "iso:country":"DE",
    "sg:address":"Georg-Sch\u00e4fer-Str. 2",
    "sg:city":"Ebern",
    "sg:phone":"+49 9531/941123",
    "sg:postcode":"96106",
    "sg:province":"Bayern",
    "wof:name":"Freddy Siabanis Praxis F\u00fcr Ergotherapie",
    "wof:placetype":"venue"
},
  "geometry": {"coordinates":[10.79631,50.09985],"type":"Point"}
}