{
  "type": "Feature",
  "properties": {
    "iso:country":"DE",
    "sg:address":"G\u00f6rresstr. 1",
    "sg:city":"L\u00fcnen",
    "sg:postcode":"44532",
    "sg:province":"Nordrhein-Westfalen",
    "wof:name":"K + S Ger\u00fcstbau Gmbh",
    "wof:placetype":"venue"
},
  "geometry": {"coordinates":[7.50283,51.58147],"type":"Point"}
}