{
  "type": "Feature",
  "properties": {
    "iso:country":"DE",
    "sg:address":"Mittlere M\u00fchle 18",
    "sg:city":"Recklinghausen",
    "sg:phone":"+49 2361/44003",
    "sg:postcode":"45665",
    "sg:province":"Nordrhein-Westfalen",
    "wof:name":"Golze Ladenbau Gmbh",
    "wof:placetype":"venue"
},
  "geometry": {"coordinates":[7.214173,51.602917],"type":"Point"}
}