{
  "type": "Feature",
  "properties": {
    "iso:country":"DE",
    "sg:address":"Ehrenpreisstieg 23",
    "sg:city":"Hamburg",
    "sg:phone":"+49 3695/608700",
    "sg:postcode":"22589",
    "sg:province":"Hamburg",
    "wof:name":"Klaus T\u00f6pfer Gmbh",
    "wof:placetype":"venue"
},
  "geometry": {"coordinates":[10.255611,50.816223],"type":"Point"}
}