{
  "type": "Feature",
  "properties": {
    "iso:country":"DE",
    "sg:address":"Hasselbrookstr. 52",
    "sg:city":"Hamburg",
    "sg:phone":"+49 40/2504925",
    "sg:postcode":"22089",
    "sg:province":"Hamburg",
    "wof:name":"Gerhard Mueller",
    "wof:placetype":"venue"
},
  "geometry": {"coordinates":[10.0421161652,53.563293457],"type":"Point"}
}