{
  "type": "Feature",
  "properties": {
    "iso:country":"DE",
    "sg:address":"Hauptstr. 18",
    "sg:city":"Blankenstein",
    "sg:phone":"+49 36642/22941",
    "sg:postcode":"07366",
    "sg:province":"Th\u00fcringen",
    "wof:name":"Sandra Steinm\u00fcller",
    "wof:placetype":"venue"
},
  "geometry": {"coordinates":[11.700581,50.402439],"type":"Point"}
}