{
  "type": "Feature",
  "properties": {
    "iso:country":"DE",
    "sg:address":"Industriestr. 50",
    "sg:city":"Pforzheim",
    "sg:phone":"+49 4971/5395160",
    "sg:postcode":"75181",
    "sg:province":"Baden-W\u00fcrttemberg",
    "wof:name":"Locke Cnc Pr\u00c4zision Gmbh",
    "wof:placetype":"venue"
},
  "geometry": {"coordinates":[9.475652,48.710896],"type":"Point"}
}