{
  "type": "Feature",
  "properties": {
    "iso:country":"DE",
    "sg:address":"Olgastr. 94",
    "sg:city":"Ulm",
    "sg:phone":"+49 4969/298050",
    "sg:postcode":"89073",
    "sg:province":"Baden-W\u00fcrttemberg",
    "wof:name":"Ziraat Bank International Ag",
    "wof:placetype":"venue"
},
  "geometry": {"coordinates":[8.6733,50.115585],"type":"Point"}
}