{
  "type": "Feature",
  "properties": {
    "iso:country":"DE",
    "sg:address":"Rheydter Str. 29",
    "sg:city":"Neuss",
    "sg:phone":"+49 2131/858020",
    "sg:postcode":"41464",
    "sg:province":"Nordrhein-Westfalen",
    "wof:name":"Tischlerbetrieb Vetters Gmbh",
    "wof:placetype":"venue"
},
  "geometry": {"coordinates":[6.677864,51.199085],"type":"Point"}
}