{
  "type": "Feature",
  "properties": {
    "iso:country":"DE",
    "sg:address":"Brandensteinweg 6",
    "sg:city":"Berlin",
    "sg:phone":"+49 30/3614055",
    "sg:postcode":"13595",
    "sg:province":"Berlin",
    "wof:name":"Jacques Wein Depot Wein- Einzelhandel",
    "wof:placetype":"venue"
},
  "geometry": {"coordinates":[13.2102947235,52.5120735168],"type":"Point"}
}