{
  "type": "Feature",
  "properties": {
    "iso:country":"DE",
    "sg:address":"Eichendorffstr. 32",
    "sg:city":"Ingelfingen",
    "sg:phone":"+49 7940/92450",
    "sg:postcode":"74653",
    "sg:province":"Baden-W\u00fcrttemberg",
    "wof:name":"Autohaus Walter Mulfinger Gmbh",
    "wof:placetype":"venue"
},
  "geometry": {"coordinates":[9.663655,49.295876],"type":"Point"}
}