{
  "type": "Feature",
  "properties": {
    "iso:country":"DE",
    "sg:address":"Zur Birk 1",
    "sg:city":"Waltrop",
    "sg:phone":"+49 2309/74883",
    "sg:postcode":"45731",
    "sg:province":"Nordrhein-Westfalen",
    "wof:name":"Hufnagel Gmbh & Co. Kg",
    "wof:placetype":"venue"
},
  "geometry": {"coordinates":[7.3954467773,51.6103782654],"type":"Point"}
}