{
  "type": "Feature",
  "properties": {
    "iso:country":"DE",
    "sg:address":"Beerentalweg 40",
    "sg:city":"Hamburg",
    "sg:phone":"+49 40/7926433",
    "sg:postcode":"21077",
    "sg:province":"Hamburg",
    "wof:name":"H. Und G. Bolz",
    "wof:placetype":"venue"
},
  "geometry": {"coordinates":[9.952792,53.449043],"type":"Point"}
}