{
  "type": "Feature",
  "properties": {
    "iso:country":"DE",
    "sg:address":"Sch\u00e4ferweg 1",
    "sg:city":"Markgr\u00f6ningen",
    "sg:phone":"+49 7145/5337",
    "sg:postcode":"71706",
    "sg:province":"Baden-W\u00fcrttemberg",
    "wof:name":"Hermann Krebs",
    "wof:placetype":"venue"
},
  "geometry": {"coordinates":[9.07929,48.902485],"type":"Point"}
}