{
  "type": "Feature",
  "properties": {
    "iso:country":"DE",
    "sg:address":"Dillsteiner Str. 2",
    "sg:city":"Pforzheim",
    "sg:phone":"+49 7231/22475",
    "sg:postcode":"75173",
    "sg:province":"Baden-W\u00fcrttemberg",
    "wof:name":"Gisela Seitz",
    "wof:placetype":"venue"
},
  "geometry": {"coordinates":[8.697855,48.889297],"type":"Point"}
}