{
  "type": "Feature",
  "properties": {
    "iso:country":"DE",
    "sg:address":"St.-Nikolaus-Str. 2a",
    "sg:city":"Rheinberg",
    "sg:phone":"+49 2844/99220",
    "sg:postcode":"47495",
    "sg:province":"Nordrhein-Westfalen",
    "wof:name":"Chateau D Orsoy",
    "wof:placetype":"venue"
},
  "geometry": {"coordinates":[6.6888837814,51.5240936279],"type":"Point"}
}