{
  "type": "Feature",
  "properties": {
    "iso:country":"DE",
    "sg:address":"Schwabstr. 21",
    "sg:city":"Schwaigern",
    "sg:phone":"+49 7138/7960",
    "sg:postcode":"74193",
    "sg:province":"Baden-W\u00fcrttemberg",
    "wof:name":"A. Demant",
    "wof:placetype":"venue"
},
  "geometry": {"coordinates":[9.0607910156,49.1447906494],"type":"Point"}
}