{
  "type": "Feature",
  "properties": {
    "iso:country":"DE",
    "sg:address":"Anlagen 21",
    "sg:city":"Fichtenberg",
    "sg:phone":"+49 7971/5361",
    "sg:postcode":"74427",
    "sg:province":"Baden-W\u00fcrttemberg",
    "wof:name":"Robert Schaible Gmbh",
    "wof:placetype":"venue"
},
  "geometry": {"coordinates":[9.7162132263,48.9858436584],"type":"Point"}
}