{
  "type": "Feature",
  "properties": {
    "iso:country":"DE",
    "sg:address":"Neue Str. 5",
    "sg:city":"Gro\u00dfrudestedt",
    "sg:phone":"+49 36204/51720",
    "sg:postcode":"99195",
    "sg:province":"Th\u00fcringen",
    "wof:name":"E. Wenke",
    "wof:placetype":"venue"
},
  "geometry": {"coordinates":[11.098628,51.092113],"type":"Point"}
}