{
  "type": "Feature",
  "properties": {
    "iso:country":"DE",
    "sg:address":"Bahnhofstr. 7",
    "sg:city":"Wiesloch",
    "sg:phone":"+49 6222/2305",
    "sg:postcode":"69168",
    "sg:province":"Baden-W\u00fcrttemberg",
    "wof:name":"Landes-foto-studio-video Reimer Landes",
    "wof:placetype":"venue"
},
  "geometry": {"coordinates":[8.6965904236,49.2916069031],"type":"Point"}
}