{
  "type": "Feature",
  "properties": {
    "iso:country":"DE",
    "sg:address":"L\u00fcbecker Weg 13",
    "sg:city":"Hanau",
    "sg:phone":"+49 6181/780839",
    "sg:postcode":"63454",
    "sg:province":"Hessen",
    "wof:name":"Reitz Und Schreiber Finanzberater",
    "wof:placetype":"venue"
},
  "geometry": {"coordinates":[8.8940629959,50.1806716919],"type":"Point"}
}