{
  "type": "Feature",
  "properties": {
    "iso:country":"DE",
    "sg:address":"Alte Bergstr. 2",
    "sg:city":"Simbach",
    "sg:phone":"+49 9954/7627",
    "sg:postcode":"94436",
    "sg:province":"Bayern",
    "wof:name":"Pimms Pub",
    "wof:placetype":"venue"
},
  "geometry": {"coordinates":[12.7391767502,48.5657196045],"type":"Point"}
}