{
  "type": "Feature",
  "properties": {
    "iso:country":"DE",
    "sg:address":"Kampstr. 4",
    "sg:city":"Detern",
    "sg:phone":"+49 4957/1200",
    "sg:postcode":"26847",
    "sg:province":"Niedersachsen",
    "wof:name":"Helmut Kramer Masseur",
    "wof:placetype":"venue"
},
  "geometry": {"coordinates":[7.669514,53.208828],"type":"Point"}
}