{
  "type": "Feature",
  "properties": {
    "iso:country":"DE",
    "sg:address":"Kleckener Kirchweg 19",
    "sg:city":"Seevetal",
    "sg:phone":"+49 4105/2551",
    "sg:postcode":"21218",
    "sg:province":"Niedersachsen",
    "wof:name":"Lv Lager- Und Verwaltungsgesellschaft Mbh",
    "wof:placetype":"venue"
},
  "geometry": {"coordinates":[9.9607572556,53.3737068176],"type":"Point"}
}