{
  "type": "Feature",
  "properties": {
    "iso:country":"DE",
    "sg:address":"L\u00fcdersdorfer Weg 12",
    "sg:city":"L\u00fcbeck",
    "sg:phone":"+49 451/692143",
    "sg:postcode":"23568",
    "sg:province":"Schleswig-Holstein",
    "wof:name":"J\u00fcrgen Berthold Ingenieur",
    "wof:placetype":"venue"
},
  "geometry": {"coordinates":[10.7986497879,53.8772544861],"type":"Point"}
}