{
  "type": "Feature",
  "properties": {
    "iso:country":"DE",
    "sg:address":"Gottfried-von-Cramm-Str. 8",
    "sg:city":"Neufahrn",
    "sg:phone":"+49 8165/3736",
    "sg:postcode":"85375",
    "sg:province":"Bayern",
    "wof:name":"Armin Ellwanger",
    "wof:placetype":"venue"
},
  "geometry": {"coordinates":[11.653999,48.316685],"type":"Point"}
}