{
  "type": "Feature",
  "properties": {
    "iso:country":"DE",
    "sg:address":"Lohwaldstr. 22",
    "sg:city":"Neus\u00e4\u00df",
    "sg:phone":"+49 821/483014",
    "sg:postcode":"86356",
    "sg:province":"Bayern",
    "wof:name":"Ingenieurb\u00fcro M\u00fcller Und Ullmann Planung Bauleitung Und",
    "wof:placetype":"venue"
},
  "geometry": {"coordinates":[10.820315361,48.389251709],"type":"Point"}
}