{
  "type": "Feature",
  "properties": {
    "iso:country":"DE",
    "sg:address":"Driburger Str. 44",
    "sg:city":"Paderborn",
    "sg:phone":"+49 5251/680828",
    "sg:postcode":"33100",
    "sg:province":"Nordrhein-Westfalen",
    "wof:name":"Weltall",
    "wof:placetype":"venue"
},
  "geometry": {"coordinates":[8.7771100998,51.7180786133],"type":"Point"}
}