{
  "type": "Feature",
  "properties": {
    "iso:country":"DE",
    "sg:address":"Zeughausstr. 16",
    "sg:city":"Wuppertal",
    "sg:phone":"+49 202/2543396",
    "sg:postcode":"42287",
    "sg:province":"Nordrhein-Westfalen",
    "wof:name":"Im Zeughaus",
    "wof:placetype":"venue"
},
  "geometry": {"coordinates":[7.1940140724,51.2639884949],"type":"Point"}
}