{
  "type": "Feature",
  "properties": {
    "iso:country":"DE",
    "sg:address":"Hainbergstr. 19",
    "sg:city":"Nidda",
    "sg:phone":"+49 6043/8511",
    "sg:postcode":"63667",
    "sg:province":"Hessen",
    "wof:name":"Karl H. Fried",
    "wof:placetype":"venue"
},
  "geometry": {"coordinates":[9.0311145782,50.4464035034],"type":"Point"}
}