{
  "type": "Feature",
  "properties": {
    "iso:country":"DE",
    "sg:address":"In den Weiden 5",
    "sg:city":"Burbach",
    "sg:phone":"+49 2736/3206",
    "sg:postcode":"57299",
    "sg:province":"Nordrhein-Westfalen",
    "wof:name":"S\u00e4gewerk Heidt Gmbh",
    "wof:placetype":"venue"
},
  "geometry": {"coordinates":[8.1080970764,50.7206993103],"type":"Point"}
}