{
  "type": "Feature",
  "properties": {
    "iso:country":"DE",
    "sg:address":"Schaufelhaus",
    "sg:city":"Sulzbach-Laufen",
    "sg:phone":"+49 7976/360",
    "sg:postcode":"74429",
    "sg:province":"Baden-W\u00fcrttemberg",
    "wof:name":"Harry Arnold",
    "wof:placetype":"venue"
},
  "geometry": {"coordinates":[9.886352,48.971691],"type":"Point"}
}