{
  "type": "Feature",
  "properties": {
    "iso:country":"DE",
    "sg:address":"Plattlinger Str. 30",
    "sg:city":"Osterhofen",
    "sg:phone":"+49 9932/95080",
    "sg:postcode":"94486",
    "sg:province":"Bayern",
    "wof:name":"Bfd B\u00dcro F\u00dcr Dienstleistungen Gmbh",
    "wof:placetype":"venue"
},
  "geometry": {"coordinates":[13.01627,48.703896],"type":"Point"}
}