{
  "type": "Feature",
  "properties": {
    "iso:country":"DE",
    "sg:address":"Heinrich-Br\u00fcning-Str. 4",
    "sg:city":"K\u00f6ln",
    "sg:phone":"+49 221/369036",
    "sg:postcode":"50969",
    "sg:province":"Nordrhein-Westfalen",
    "wof:name":"Sport Hornig & Gro\u00dfmann Gmbh",
    "wof:placetype":"venue"
},
  "geometry": {"coordinates":[6.946198,50.914688],"type":"Point"}
}