{
  "type": "Feature",
  "properties": {
    "iso:country":"DE",
    "sg:address":"Kennedyallee 62-70::",
    "sg:city":"Bonn",
    "sg:phone":"+49 69/75831300",
    "sg:postcode":"53175",
    "sg:province":"Nordrhein-Westfalen",
    "wof:name":"Credis (deutschland) Gmbh",
    "wof:placetype":"venue"
},
  "geometry": {"coordinates":[8.69185,50.11684],"type":"Point"}
}