{
  "type": "Feature",
  "properties": {
    "iso:country":"DE",
    "sg:address":"Odenwaldstr. 5",
    "sg:city":"Berlin",
    "sg:phone":"+49 30/8522956",
    "sg:postcode":"12161",
    "sg:province":"Berlin",
    "wof:name":"Heidemarie Olschewski",
    "wof:placetype":"venue"
},
  "geometry": {"coordinates":[13.325436,52.468342],"type":"Point"}
}