{
  "type": "Feature",
  "properties": {
    "iso:country":"DE",
    "sg:address":"Stettiner Str. 41",
    "sg:city":"Baunatal",
    "sg:phone":"+49 5601/87526",
    "sg:postcode":"34225",
    "sg:province":"Hessen",
    "wof:name":"Transport Gmbh",
    "wof:placetype":"venue"
},
  "geometry": {"coordinates":[9.383184433,51.2548370361],"type":"Point"}
}