{
  "type": "Feature",
  "properties": {
    "iso:country":"DE",
    "sg:address":"Freier Grunder Str. 104",
    "sg:city":"Wilnsdorf",
    "sg:phone":"+49 2739/87090",
    "sg:postcode":"57234",
    "sg:province":"Nordrhein-Westfalen",
    "wof:name":"Franz Wohnbau Gmbh",
    "wof:placetype":"venue"
},
  "geometry": {"coordinates":[8.062832,50.806023],"type":"Point"}
}