{
  "type": "Feature",
  "properties": {
    "iso:country":"DE",
    "sg:address":"Schleusinger Str. 14",
    "sg:city":"Br\u00fcnn",
    "sg:phone":"+49 36878/60376",
    "sg:postcode":"98673",
    "sg:province":"Th\u00fcringen",
    "wof:name":"Reichshof",
    "wof:placetype":"venue"
},
  "geometry": {"coordinates":[10.9053535461,50.4261779785],"type":"Point"}
}