{
  "type": "Feature",
  "properties": {
    "iso:country":"DE",
    "sg:address":"Raiffeisenring 6",
    "sg:city":"Bocholt",
    "sg:phone":"+49 2871/24780",
    "sg:postcode":"46395",
    "sg:province":"Nordrhein-Westfalen",
    "wof:name":"Pk Werbemittel Gmbh",
    "wof:placetype":"venue"
},
  "geometry": {"coordinates":[6.5648498535,51.8151054382],"type":"Point"}
}