{
  "type": "Feature",
  "properties": {
    "iso:country":"DE",
    "sg:address":"Ahornstr. 5 b",
    "sg:city":"Pilsting",
    "sg:phone":"+49 9953/2516",
    "sg:postcode":"94431",
    "sg:province":"Bayern",
    "wof:name":"Franz Rauhmeier",
    "wof:placetype":"venue"
},
  "geometry": {"coordinates":[12.657381,48.695297],"type":"Point"}
}