{
  "type": "Feature",
  "properties": {
    "iso:country":"DE",
    "sg:address":"Enzring 52",
    "sg:city":"Bad Wildbad",
    "sg:postcode":"75323",
    "sg:province":"Baden-W\u00fcrttemberg",
    "wof:name":"Helble Immobilien",
    "wof:placetype":"venue"
},
  "geometry": {"coordinates":[8.5784187317,48.7835578918],"type":"Point"}
}