{
  "type": "Feature",
  "properties": {
    "iso:country":"DE",
    "sg:address":"Rheiner Strasse 33A",
    "sg:city":"Lingen",
    "sg:phone":"+49 591",
    "sg:postcode":"49808",
    "sg:province":"Niedersachsen",
    "wof:name":"Re/max Immobilien Lingen",
    "wof:placetype":"venue"
},
  "geometry": {"coordinates":[7.2893052101,52.5628166199],"type":"Point"}
}