{
  "type": "Feature",
  "properties": {
    "iso:country":"DE",
    "sg:address":"Schleiermacherstr. 23",
    "sg:city":"Hannover",
    "sg:phone":"+49 511/5389700",
    "sg:postcode":"30625",
    "sg:province":"Niedersachsen",
    "wof:name":"Versteyl Meldert Und Birnbaum Rechtsanw\u00e4lte",
    "wof:placetype":"venue"
},
  "geometry": {"coordinates":[9.789981842,52.3712158203],"type":"Point"}
}