{
  "type": "Feature",
  "properties": {
    "iso:country":"DE",
    "sg:address":"P\u00fctzdelle 5",
    "sg:city":"Leverkusen",
    "sg:phone":"+49 214/202305",
    "sg:postcode":"51371",
    "sg:province":"Nordrhein-Westfalen",
    "wof:name":"Optik Weisheit Gmbh",
    "wof:placetype":"venue"
},
  "geometry": {"coordinates":[6.9482450485,51.0512084961],"type":"Point"}
}