{
  "type": "Feature",
  "properties": {
    "iso:country":"DE",
    "sg:address":"Ernststr. 22",
    "sg:city":"Berlin",
    "sg:phone":"+49 30/4322078",
    "sg:postcode":"13509",
    "sg:province":"Berlin",
    "wof:name":"W\u00e4rme Wartungsdienst Nord Gmbh",
    "wof:placetype":"venue"
},
  "geometry": {"coordinates":[13.2961177826,52.5827903748],"type":"Point"}
}