{
  "type": "Feature",
  "properties": {
    "iso:country":"DE",
    "sg:address":"Industriestr. 3",
    "sg:city":"D\u00f6rpen",
    "sg:postcode":"26892",
    "sg:province":"Niedersachsen",
    "wof:name":"Futtermittelwerk D\u00f6rpen Gmbh",
    "wof:placetype":"venue"
},
  "geometry": {"coordinates":[7.36142,52.969662],"type":"Point"}
}