{
  "type": "Feature",
  "properties": {
    "iso:country":"DE",
    "sg:address":"Gro\u00dfmoorkehre 3",
    "sg:city":"Hamburg",
    "sg:postcode":"21079",
    "sg:province":"Hamburg",
    "wof:name":"Marco Polo Vertriebs Gmbh",
    "wof:placetype":"venue"
},
  "geometry": {"coordinates":[10.009519577,53.4585266113],"type":"Point"}
}