{
  "type": "Feature",
  "properties": {
    "iso:country":"DE",
    "sg:address":"Scheibenstr. 5",
    "sg:city":"Oberstdorf",
    "sg:phone":"+49 8322/4748",
    "sg:postcode":"87561",
    "sg:province":"Bayern",
    "wof:name":"Fremdenheim Hans K\u00f6cheler",
    "wof:placetype":"venue"
},
  "geometry": {"coordinates":[10.2829332352,47.3909301758],"type":"Point"}
}