{
  "type": "Feature",
  "properties": {
    "iso:country":"DE",
    "sg:address":"Brunhildestr. 77 a",
    "sg:city":"Schmitten",
    "sg:phone":"+49 6082/2895",
    "sg:postcode":"61389",
    "sg:province":"Hessen",
    "wof:name":"Peter Grafwallner Rechtsanwalt",
    "wof:placetype":"venue"
},
  "geometry": {"coordinates":[8.4334497452,50.237449646],"type":"Point"}
}