{
  "type": "Feature",
  "properties": {
    "iso:country":"DE",
    "sg:city":"Traitsching",
    "sg:phone":"+49 9974/537",
    "sg:postcode":"93455",
    "sg:province":"Bayern",
    "wof:name":"Raiffeisenbank Cham Eg",
    "wof:placetype":"venue"
},
  "geometry": {"coordinates":[12.64525,49.152348],"type":"Point"}
}