{
  "type": "Feature",
  "properties": {
    "iso:country":"DE",
    "sg:address":"Dorfstr. 174",
    "sg:city":"Tangstedt",
    "sg:phone":"+49 4109/6072",
    "sg:postcode":"22889",
    "sg:province":"Schleswig-Holstein",
    "wof:name":"Moderne Farbgestaltung Malermeister Gerhard Ader Gmbh",
    "wof:placetype":"venue"
},
  "geometry": {"coordinates":[10.068636,53.719669],"type":"Point"}
}