{
  "type": "Feature",
  "properties": {
    "iso:country":"DE",
    "sg:address":"Am Gra\u00dfdorfer W\u00e4ldchen 91",
    "sg:city":"Taucha",
    "sg:postcode":"04425",
    "sg:province":"Sachsen",
    "wof:name":"Heytech Wohnbau Gmbh",
    "wof:placetype":"venue"
},
  "geometry": {"coordinates":[12.482202,51.38678],"type":"Point"}
}