{
  "type": "Feature",
  "properties": {
    "iso:country":"DE",
    "sg:address":"Br\u00fcckelstr. 72",
    "sg:city":"Duisburg",
    "sg:phone":"+49 203/422358",
    "sg:postcode":"47137",
    "sg:province":"Nordrhein-Westfalen",
    "wof:name":"G.h. Schmidt",
    "wof:placetype":"venue"
},
  "geometry": {"coordinates":[6.7851600647,51.4729270935],"type":"Point"}
}