{
  "type": "Feature",
  "properties": {
    "iso:country":"DE",
    "sg:address":"Posener Str. 25",
    "sg:city":"L\u00fcbeck",
    "sg:phone":"+49 4945/1408640",
    "sg:postcode":"23554",
    "sg:province":"Schleswig-Holstein",
    "wof:name":"L\u00dcders & Stange Ldg",
    "wof:placetype":"venue"
},
  "geometry": {"coordinates":[10.6919307709,53.8919715881],"type":"Point"}
}