{
  "type": "Feature",
  "properties": {
    "iso:country":"DE",
    "sg:address":"K\u00f6hlerhof 12",
    "sg:city":"Spardorf",
    "sg:phone":"+49 9131/53590",
    "sg:postcode":"91080",
    "sg:province":"Bayern",
    "wof:name":"Ingenieurb\u00fcro S. Lang Und Dr. Gerhard Schulze",
    "wof:placetype":"venue"
},
  "geometry": {"coordinates":[11.0543756485,49.6108169556],"type":"Point"}
}