{
  "type": "Feature",
  "properties": {
    "iso:country":"DE",
    "sg:address":"Im Brauck 4",
    "sg:city":"Lennestadt",
    "sg:phone":"+49 2723/8308",
    "sg:postcode":"57368",
    "sg:province":"Nordrhein-Westfalen",
    "wof:name":"Peter Heinemann",
    "wof:placetype":"venue"
},
  "geometry": {"coordinates":[8.0960006714,51.1136474609],"type":"Point"}
}