{
  "type": "Feature",
  "properties": {
    "iso:country":"DE",
    "sg:address":"Niederhoferstr. 94",
    "sg:city":"Rimpar",
    "sg:phone":"+49 9365/89984",
    "sg:postcode":"97222",
    "sg:province":"Bayern",
    "wof:name":"Alfred Flammersberger Gmbh",
    "wof:placetype":"venue"
},
  "geometry": {"coordinates":[9.9560489655,49.8488616943],"type":"Point"}
}