{
  "type": "Feature",
  "properties": {
    "iso:country":"DE",
    "sg:address":"Gosbacher Str. 12",
    "sg:city":"Drackenstein",
    "sg:phone":"+49 4973/355311",
    "sg:postcode":"73345",
    "sg:province":"Baden-W\u00fcrttemberg",
    "wof:name":"G\u00dcnter Goller",
    "wof:placetype":"venue"
},
  "geometry": {"coordinates":[9.66937,48.55867],"type":"Point"}
}