{
  "type": "Feature",
  "properties": {
    "iso:country":"DE",
    "sg:address":"Schulthei\u00dfgasse 4",
    "sg:city":"Bonn",
    "sg:phone":"+49 228/9563756",
    "sg:postcode":"53177",
    "sg:province":"Nordrhein-Westfalen",
    "wof:name":"F. M. T. K.-fotografie- Marketing-touristik-",
    "wof:placetype":"venue"
},
  "geometry": {"coordinates":[7.1539740562,50.6849021912],"type":"Point"}
}