{
  "type": "Feature",
  "properties": {
    "iso:country":"DE",
    "sg:address":"Oberstr. 46",
    "sg:city":"Freyburg",
    "sg:phone":"+49 34464/27742",
    "sg:postcode":"06632",
    "sg:province":"Sachsen-Anhalt",
    "wof:name":"Eiskaffee-konditorei",
    "wof:placetype":"venue"
},
  "geometry": {"coordinates":[11.769699,51.213848],"type":"Point"}
}