{
  "type": "Feature",
  "properties": {
    "iso:country":"DE",
    "sg:address":"Kirchstr. 22",
    "sg:city":"Werneck",
    "sg:phone":"+49 9722/8399",
    "sg:postcode":"97440",
    "sg:province":"Bayern",
    "wof:name":"Pizzeria Antonio Zum Schwan",
    "wof:placetype":"venue"
},
  "geometry": {"coordinates":[10.0770940781,49.9447898865],"type":"Point"}
}