{
  "type": "Feature",
  "properties": {
    "iso:country":"DE",
    "sg:address":"Am Ruhmbach 11",
    "sg:city":"Essen",
    "sg:phone":"+49 201/713033",
    "sg:postcode":"45149",
    "sg:province":"Nordrhein-Westfalen",
    "wof:name":"Klaus Pelizaeus",
    "wof:placetype":"venue"
},
  "geometry": {"coordinates":[6.9513630867,51.4105911255],"type":"Point"}
}