{
  "type": "Feature",
  "properties": {
    "iso:country":"DE",
    "sg:address":"Sch\u00f6ngeisinger Str. 14",
    "sg:city":"F\u00fcrstenfeldbruck",
    "sg:phone":"+49 8141/26081",
    "sg:postcode":"82256",
    "sg:province":"Bayern",
    "wof:name":"H\u00f6gg Reiseb\u00fcro",
    "wof:placetype":"venue"
},
  "geometry": {"coordinates":[11.2534780502,48.1773948669],"type":"Point"}
}