{
  "type": "Feature",
  "properties": {
    "iso:country":"DE",
    "sg:address":"Hauptstr. 83",
    "sg:city":"Tannheim",
    "sg:phone":"+49 8395/613",
    "sg:postcode":"88459",
    "sg:province":"Baden-W\u00fcrttemberg",
    "wof:name":"Die Adresse F\u00fcr Italienische Gastlichkeit",
    "wof:placetype":"venue"
},
  "geometry": {"coordinates":[10.075625,48.00045],"type":"Point"}
}