{
  "type": "Feature",
  "properties": {
    "iso:country":"DE",
    "sg:address":"Schulstr. 23",
    "sg:city":"B\u00e4k",
    "sg:phone":"+49 4541/858612",
    "sg:postcode":"23909",
    "sg:province":"Schleswig-Holstein",
    "wof:name":"Amg Akustikdecken Und Montagebau Gmbh",
    "wof:placetype":"venue"
},
  "geometry": {"coordinates":[10.781563,53.713337],"type":"Point"}
}