{
  "type": "Feature",
  "properties": {
    "iso:country":"DE",
    "sg:address":"Bergstr. 8",
    "sg:city":"Giebelstadt",
    "sg:phone":"+49 9336/460",
    "sg:postcode":"97232",
    "sg:province":"Bayern",
    "wof:name":"Katholisches Pfarramt St. Walburga",
    "wof:placetype":"venue"
},
  "geometry": {"coordinates":[9.9012928009,49.6277923584],"type":"Point"}
}