{
  "type": "Feature",
  "properties": {
    "iso:country":"DE",
    "sg:address":"Schwalbacher Str. 29",
    "sg:city":"Nast\u00e4tten",
    "sg:phone":"+49 6772/8486",
    "sg:postcode":"56355",
    "sg:province":"Rheinland-Pfalz",
    "wof:name":"H. G. Schlick Steuerbevollm\u00e4chtigter",
    "wof:placetype":"venue"
},
  "geometry": {"coordinates":[7.8641548157,50.1962013245],"type":"Point"}
}