{
  "type": "Feature",
  "properties": {
    "iso:country":"DE",
    "sg:address":"Kornstr. 25",
    "sg:city":"Neubulach",
    "sg:phone":"+49 7055/7550",
    "sg:postcode":"75387",
    "sg:province":"Baden-W\u00fcrttemberg",
    "wof:name":"Tannenhof",
    "wof:placetype":"venue"
},
  "geometry": {"coordinates":[8.6271600723,48.6434783936],"type":"Point"}
}