{
  "type": "Feature",
  "properties": {
    "iso:country":"DE",
    "sg:address":"Evertsstr. 45",
    "sg:city":"Krefeld",
    "sg:phone":"+49 2151/23319",
    "sg:postcode":"47798",
    "sg:province":"Nordrhein-Westfalen",
    "wof:name":"Das Aquarium",
    "wof:placetype":"venue"
},
  "geometry": {"coordinates":[6.559903,51.330891],"type":"Point"}
}