{
  "type": "Feature",
  "properties": {
    "iso:country":"DE",
    "sg:address":"Heiderh\u00f6fen 65",
    "sg:city":"Oberhausen",
    "sg:phone":"+49 208/853912",
    "sg:postcode":"46049",
    "sg:province":"Nordrhein-Westfalen",
    "wof:name":"Brieden",
    "wof:placetype":"venue"
},
  "geometry": {"coordinates":[6.8273668289,51.4586105347],"type":"Point"}
}