{
  "type": "Feature",
  "properties": {
    "iso:country":"DE",
    "sg:address":"Hauptstr. 61",
    "sg:city":"\u00d6llingen",
    "sg:phone":"+49 7345/6928",
    "sg:postcode":"89129",
    "sg:province":"Baden-W\u00fcrttemberg",
    "wof:name":"Ernst H\u00e4ge",
    "wof:placetype":"venue"
},
  "geometry": {"coordinates":[10.145362,48.529739],"type":"Point"}
}