{
  "type": "Feature",
  "properties": {
    "iso:country":"DE",
    "sg:address":"Bockumer Weg 223",
    "sg:city":"Hamm",
    "sg:phone":"+49 2381/65039",
    "sg:postcode":"59065",
    "sg:province":"Nordrhein-Westfalen",
    "wof:name":"Von Der Beck & Sohn Gmbh",
    "wof:placetype":"venue"
},
  "geometry": {"coordinates":[7.7843818665,51.6883354187],"type":"Point"}
}