{
  "type": "Feature",
  "properties": {
    "iso:country":"DE",
    "sg:address":"Hertsfeld 2",
    "sg:city":"Bad Bentheim",
    "sg:phone":"+49 5924/1667",
    "sg:postcode":"48455",
    "sg:province":"Niedersachsen",
    "wof:name":"Helmut Jonas",
    "wof:placetype":"venue"
},
  "geometry": {"coordinates":[7.100258,52.332939],"type":"Point"}
}