{
  "type": "Feature",
  "properties": {
    "iso:country":"DE",
    "sg:address":"Griemshorster Str. 10",
    "sg:city":"Harsefeld",
    "sg:phone":"+49 4164/5194",
    "sg:postcode":"21698",
    "sg:province":"Niedersachsen",
    "wof:name":"Ralph Wohlert",
    "wof:placetype":"venue"
},
  "geometry": {"coordinates":[9.503384,53.451763],"type":"Point"}
}