{
  "type": "Feature",
  "properties": {
    "iso:country":"DE",
    "sg:address":"Webergasse 2",
    "sg:city":"Riedenheim",
    "sg:phone":"+49 9338/376",
    "sg:postcode":"97283",
    "sg:province":"Bayern",
    "wof:name":"Albin Henkelmann",
    "wof:placetype":"venue"
},
  "geometry": {"coordinates":[9.976386,49.556408],"type":"Point"}
}