{
  "type": "Feature",
  "properties": {
    "iso:country":"DE",
    "sg:address":"Am L\u00e4ger 10",
    "sg:city":"Kehl",
    "sg:phone":"+49 7851/73581",
    "sg:postcode":"77694",
    "sg:province":"Baden-W\u00fcrttemberg",
    "wof:name":"Barth Holzagentur Gmbh",
    "wof:placetype":"venue"
},
  "geometry": {"coordinates":[7.8137788773,48.5748596191],"type":"Point"}
}