{
  "type": "Feature",
  "properties": {
    "iso:country":"DE",
    "sg:address":"Stubenrauchstr. 65c",
    "sg:city":"Berlin",
    "sg:phone":"+49 30/6312214",
    "sg:postcode":"12487",
    "sg:province":"Berlin",
    "wof:name":"R. Und H. Kothe",
    "wof:placetype":"venue"
},
  "geometry": {"coordinates":[13.504887,52.436928],"type":"Point"}
}