{
  "type": "Feature",
  "properties": {
    "iso:country":"DE",
    "sg:address":"August-Fuhrmann-Str. 1",
    "sg:city":"Bielefeld",
    "sg:phone":"+49 521/203740",
    "sg:postcode":"33719",
    "sg:province":"Nordrhein-Westfalen",
    "wof:name":"Dorothea Ebmeyer Praxis F\u00fcr Krankengymnastik",
    "wof:placetype":"venue"
},
  "geometry": {"coordinates":[8.60621,52.011852],"type":"Point"}
}