{
  "type": "Feature",
  "properties": {
    "iso:country":"DE",
    "sg:address":"Eickloherstr. 1",
    "sg:city":"Hodenhagen",
    "sg:phone":"+49 4951/64555",
    "sg:postcode":"29693",
    "sg:province":"Niedersachsen",
    "wof:name":"Walo Handelsgesellschaft Nollau Gmbh & Co Kg",
    "wof:placetype":"venue"
},
  "geometry": {"coordinates":[9.5940799713,52.7523231506],"type":"Point"}
}