{
  "type": "Feature",
  "properties": {
    "iso:country":"DE",
    "sg:address":"Ringstr.",
    "sg:city":"Halle",
    "sg:phone":"+49 5201/5503",
    "sg:postcode":"33790",
    "sg:province":"Nordrhein-Westfalen",
    "wof:name":"Schulz Transporte",
    "wof:placetype":"venue"
},
  "geometry": {"coordinates":[8.3313913345,52.039478302],"type":"Point"}
}