{
  "type": "Feature",
  "properties": {
    "iso:country":"DE",
    "sg:address":"Soltauer Str. 106",
    "sg:city":"Munster",
    "sg:phone":"+49 5192/5214",
    "sg:postcode":"29633",
    "sg:province":"Niedersachsen",
    "wof:name":"Volker Arning",
    "wof:placetype":"venue"
},
  "geometry": {"coordinates":[10.060661,53.000114],"type":"Point"}
}