{
  "type": "Feature",
  "properties": {
    "iso:country":"DE",
    "sg:address":"Flughafenstr. 5",
    "sg:city":"B\u00fcren",
    "sg:phone":"+49 2955/7301",
    "sg:postcode":"33142",
    "sg:province":"Nordrhein-Westfalen",
    "wof:name":"P\u00e4tzold & Co. Beteiligungs- Und Verwaltungs-gmbh",
    "wof:placetype":"venue"
},
  "geometry": {"coordinates":[8.616093,51.608738],"type":"Point"}
}