{
  "type": "Feature",
  "properties": {
    "iso:country":"DE",
    "sg:address":"Julian-Marchlewski-Str. 54",
    "sg:city":"Leipzig",
    "sg:phone":"+49 341/2312094",
    "sg:postcode":"04347",
    "sg:province":"Sachsen",
    "wof:name":"J\u00fcrgen Heyder Ingenieur",
    "wof:placetype":"venue"
},
  "geometry": {"coordinates":[12.4269685745,51.3566169739],"type":"Point"}
}