{
  "type": "Feature",
  "properties": {
    "iso:country":"DE",
    "sg:address":"Ziegel\u00e4cker",
    "sg:city":"Berg",
    "sg:phone":"+49 7273/2457",
    "sg:postcode":"76768",
    "sg:province":"Rheinland-Pfalz",
    "wof:name":"Keg-kies- Und Edelsplittges. Mbh",
    "wof:placetype":"venue"
},
  "geometry": {"coordinates":[8.2012681961,48.9780960083],"type":"Point"}
}