{
  "type": "Feature",
  "properties": {
    "iso:country":"DE",
    "sg:address":"Kornweg 3",
    "sg:city":"K\u00f6nigsbr\u00fcck",
    "sg:phone":"+49 35795/30284",
    "sg:postcode":"01936",
    "sg:province":"Sachsen",
    "wof:name":"Erhard Gey Gmbh",
    "wof:placetype":"venue"
},
  "geometry": {"coordinates":[13.8879489899,51.2577629089],"type":"Point"}
}