{
  "type": "Feature",
  "properties": {
    "iso:country":"DE",
    "sg:address":"Bahnhofstr. 32",
    "sg:city":"Hemmoor",
    "sg:phone":"+49 4771/2590",
    "sg:postcode":"21745",
    "sg:province":"Niedersachsen",
    "wof:name":"G\u00fcnther Kr\u00f6ncke",
    "wof:placetype":"venue"
},
  "geometry": {"coordinates":[9.167936,53.684746],"type":"Point"}
}