{
  "type": "Feature",
  "properties": {
    "iso:country":"DE",
    "sg:address":"H\u00f6gsdorfer Ziegelei",
    "sg:city":"H\u00f6gsdorf",
    "sg:phone":"+49 4381/7546",
    "sg:postcode":"24327",
    "sg:province":"Schleswig-Holstein",
    "wof:name":"Wolfgang Doose Ziegelei",
    "wof:placetype":"venue"
},
  "geometry": {"coordinates":[10.6007452011,54.2425994873],"type":"Point"}
}