{
  "type": "Feature",
  "properties": {
    "iso:country":"DE",
    "sg:address":"W\u00fcstenh\u00f6ferstr. 219",
    "sg:city":"Essen",
    "sg:phone":"+49 201/670828",
    "sg:postcode":"45355",
    "sg:province":"Nordrhein-Westfalen",
    "wof:name":"Form In Form Krolik Bettenparadies",
    "wof:placetype":"venue"
},
  "geometry": {"coordinates":[6.9505500793,51.4728965759],"type":"Point"}
}