{
  "type": "Feature",
  "properties": {
    "iso:country":"DE",
    "sg:address":"Bismarckstr. 6",
    "sg:city":"Dormagen",
    "sg:phone":"+49 2133/72828",
    "sg:postcode":"41542",
    "sg:province":"Nordrhein-Westfalen",
    "wof:name":"Anpado Gmbh",
    "wof:placetype":"venue"
},
  "geometry": {"coordinates":[6.7727122307,51.1151847839],"type":"Point"}
}