{
  "type": "Feature",
  "properties": {
    "iso:country":"DE",
    "sg:address":"Turnstr. 37",
    "sg:city":"Neuenb\u00fcrg",
    "sg:phone":"+49 7082/79130",
    "sg:postcode":"75305",
    "sg:province":"Baden-W\u00fcrttemberg",
    "wof:name":"Herbstreith & Fox Kg",
    "wof:placetype":"venue"
},
  "geometry": {"coordinates":[8.5935382843,48.8452415466],"type":"Point"}
}