{
  "type": "Feature",
  "properties": {
    "iso:country":"DE",
    "sg:address":"Laustr. 36",
    "sg:city":"Stuttgart",
    "sg:postcode":"70597",
    "sg:province":"Baden-W\u00fcrttemberg",
    "wof:name":"Der Quellhof E. V.",
    "wof:placetype":"venue"
},
  "geometry": {"coordinates":[9.1544733047,48.7446098328],"type":"Point"}
}