{
  "type": "Feature",
  "properties": {
    "iso:country":"DE",
    "sg:address":"Kranichfelder Str. 68",
    "sg:city":"Erfurt",
    "sg:phone":"+49 361/3807267",
    "sg:postcode":"99097",
    "sg:province":"Th\u00fcringen",
    "wof:name":"Pension Fiege",
    "wof:placetype":"venue"
},
  "geometry": {"coordinates":[11.0638971329,50.9561462402],"type":"Point"}
}