{
  "type": "Feature",
  "properties": {
    "iso:country":"DE",
    "sg:address":"Briver Allee 1",
    "sg:city":"Lauf",
    "sg:phone":"+49 9123/988330",
    "sg:postcode":"91207",
    "sg:province":"Bayern",
    "wof:name":"Schettler Consulting Kg",
    "wof:placetype":"venue"
},
  "geometry": {"coordinates":[11.2839632034,49.5135116577],"type":"Point"}
}