{
  "type": "Feature",
  "properties": {
    "iso:country":"DE",
    "sg:address":"Hauptstr. 29",
    "sg:city":"Zwiefalten",
    "sg:phone":"+49 7373/2805",
    "sg:postcode":"88529",
    "sg:province":"Baden-W\u00fcrttemberg",
    "wof:name":"Boris Aierstock",
    "wof:placetype":"venue"
},
  "geometry": {"coordinates":[9.4640979767,48.2306022644],"type":"Point"}
}