{
  "type": "Feature",
  "properties": {
    "iso:country":"DE",
    "sg:address":"Mei\u00dfner Landstr. 1",
    "sg:city":"Dresden",
    "sg:phone":"+49 351/4220501",
    "sg:postcode":"01157",
    "sg:province":"Sachsen",
    "wof:name":"Dr. Sonja Biermann",
    "wof:placetype":"venue"
},
  "geometry": {"coordinates":[13.6809196472,51.0617980957],"type":"Point"}
}