{
  "type": "Feature",
  "properties": {
    "iso:country":"DE",
    "sg:address":"Ki\u00dflingweg 35",
    "sg:city":"M\u00fchlacker",
    "sg:phone":"+49 7041/8050",
    "sg:postcode":"75417",
    "sg:province":"Baden-W\u00fcrttemberg",
    "wof:name":"Karl Elser Gmbh",
    "wof:placetype":"venue"
},
  "geometry": {"coordinates":[8.858874321,48.9533500671],"type":"Point"}
}