{
  "type": "Feature",
  "properties": {
    "iso:country":"DE",
    "sg:address":"Erfurter Str. 1",
    "sg:city":"Stuttgart",
    "sg:phone":"+49 711/544611",
    "sg:postcode":"70376",
    "sg:province":"Baden-W\u00fcrttemberg",
    "wof:name":"W. Gronwald Und K. Gronwald-lohrer",
    "wof:placetype":"venue"
},
  "geometry": {"coordinates":[9.2084703445,48.8099403381],"type":"Point"}
}