{
  "type": "Feature",
  "properties": {
    "iso:country":"DE",
    "sg:address":"Zur Wasserm\u00fchle 2",
    "sg:city":"Xanten",
    "sg:phone":"+49 2801/1302",
    "sg:postcode":"46509",
    "sg:province":"Nordrhein-Westfalen",
    "wof:name":"J\u00fcrgen Brammen",
    "wof:placetype":"venue"
},
  "geometry": {"coordinates":[6.47524,51.634892],"type":"Point"}
}