{
  "type": "Feature",
  "properties": {
    "iso:country":"DE",
    "sg:address":"Stra\u00dfe der Bodenreform 16",
    "sg:city":"Kleinpaschleben",
    "sg:phone":"+49 34979/21420",
    "sg:postcode":"06369",
    "sg:province":"Sachsen-Anhalt",
    "wof:name":"A. Rosemeier",
    "wof:placetype":"venue"
},
  "geometry": {"coordinates":[11.8836746216,51.7877922058],"type":"Point"}
}