{
  "type": "Feature",
  "properties": {
    "iso:country":"DE",
    "sg:address":"Allee 8",
    "sg:city":"Lichtenfels",
    "sg:phone":"+49 5636/315",
    "sg:postcode":"35104",
    "sg:province":"Hessen",
    "wof:name":"Karl Greisler",
    "wof:placetype":"venue"
},
  "geometry": {"coordinates":[8.812291,51.199886],"type":"Point"}
}