{
  "type": "Feature",
  "properties": {
    "iso:country":"DE",
    "sg:address":"Kampstr. 28",
    "sg:city":"Gelsenkirchen",
    "sg:phone":"+49 209/586240",
    "sg:postcode":"45899",
    "sg:province":"Nordrhein-Westfalen",
    "wof:name":"Horst Laschet Gmbh",
    "wof:placetype":"venue"
},
  "geometry": {"coordinates":[7.038848877,51.5507354736],"type":"Point"}
}