{
  "type": "Feature",
  "properties": {
    "iso:country":"DE",
    "sg:address":"K\u00f6nigsberger Weg 1",
    "sg:city":"Offenburg",
    "sg:phone":"+49 781/66312",
    "sg:postcode":"77656",
    "sg:province":"Baden-W\u00fcrttemberg",
    "wof:name":"Keiper Versicherungs- Und Finanzierungs-",
    "wof:placetype":"venue"
},
  "geometry": {"coordinates":[7.9227371216,48.4606933594],"type":"Point"}
}