{
  "type": "Feature",
  "properties": {
    "iso:country":"DE",
    "sg:address":"Staubstr. 6 / 3",
    "sg:city":"Kuchen",
    "sg:phone":"+49 7331/82949",
    "sg:postcode":"73329",
    "sg:province":"Baden-W\u00fcrttemberg",
    "wof:name":"Eberhard Gnilka",
    "wof:placetype":"venue"
},
  "geometry": {"coordinates":[9.8012886047,48.6408233643],"type":"Point"}
}