{
  "type": "Feature",
  "properties": {
    "iso:country":"DE",
    "sg:address":"Kemptener Str. 1",
    "sg:city":"Sulzberg",
    "sg:phone":"+49 8376/553",
    "sg:postcode":"87477",
    "sg:province":"Bayern",
    "wof:name":"Stadt- Und Kreissparkasse Kempten",
    "wof:placetype":"venue"
},
  "geometry": {"coordinates":[10.34868,47.66087],"type":"Point"}
}