{
  "type": "Feature",
  "properties": {
    "iso:country":"DE",
    "sg:address":"Sudetenstr. 12",
    "sg:city":"Waiblingen",
    "sg:phone":"+49 7151/51188",
    "sg:postcode":"71332",
    "sg:province":"Baden-W\u00fcrttemberg",
    "wof:name":"Sommerhalde",
    "wof:placetype":"venue"
},
  "geometry": {"coordinates":[9.3084783554,48.8181381226],"type":"Point"}
}