{
  "type": "Feature",
  "properties": {
    "iso:country":"DE",
    "sg:address":"Kortumstr. 54",
    "sg:city":"Bochum",
    "sg:phone":"+49 234/67123",
    "sg:postcode":"44787",
    "sg:province":"Nordrhein-Westfalen",
    "wof:name":"H.-j. Struck",
    "wof:placetype":"venue"
},
  "geometry": {"coordinates":[7.217245,51.479385],"type":"Point"}
}