{
  "type": "Feature",
  "properties": {
    "iso:country":"DE",
    "sg:address":"Lange Str. 28",
    "sg:city":"Beverungen",
    "sg:phone":"+49 5273/1359",
    "sg:postcode":"37688",
    "sg:province":"Nordrhein-Westfalen",
    "wof:name":"August Sch\u00fcbeler",
    "wof:placetype":"venue"
},
  "geometry": {"coordinates":[9.373625,51.664364],"type":"Point"}
}