{
  "type": "Feature",
  "properties": {
    "iso:country":"DE",
    "sg:address":"Bahnhofstr. 7",
    "sg:city":"L\u00fcbs",
    "sg:phone":"+49 39242/379",
    "sg:postcode":"39264",
    "sg:province":"Sachsen-Anhalt",
    "wof:name":"Walter Schunke",
    "wof:placetype":"venue"
},
  "geometry": {"coordinates":[11.93729,52.0201],"type":"Point"}
}