{
  "type": "Feature",
  "properties": {
    "iso:country":"DE",
    "sg:address":"Salierring 6",
    "sg:city":"K\u00f6ln",
    "sg:phone":"+49 221/311099",
    "sg:postcode":"50677",
    "sg:province":"Nordrhein-Westfalen",
    "wof:name":"Dieter Reichenbach Rechtsanwalt",
    "wof:placetype":"venue"
},
  "geometry": {"coordinates":[6.9463911057,50.9266471863],"type":"Point"}
}