{
  "type": "Feature",
  "properties": {
    "iso:country":"DE",
    "sg:address":"Dorfstr. 170C",
    "sg:city":"Mildenau",
    "sg:phone":"+49 3733/52716",
    "sg:postcode":"09456",
    "sg:province":"Sachsen",
    "wof:name":"U. Groschopp",
    "wof:placetype":"venue"
},
  "geometry": {"coordinates":[13.046305,50.588924],"type":"Point"}
}