{
  "type": "Feature",
  "properties": {
    "iso:country":"DE",
    "sg:address":"Heimst\u00e4ttenweg 8",
    "sg:city":"Braunschweig",
    "sg:phone":"+49 531/696435",
    "sg:postcode":"38126",
    "sg:province":"Niedersachsen",
    "wof:name":"Georg Fli\u00df",
    "wof:placetype":"venue"
},
  "geometry": {"coordinates":[10.563641,52.237335],"type":"Point"}
}