{
  "type": "Feature",
  "properties": {
    "iso:country":"DE",
    "sg:address":"Meisengasse 7 a",
    "sg:city":"Frankfurt",
    "sg:phone":"+49 69/281603",
    "sg:postcode":"60313",
    "sg:province":"Hessen",
    "wof:name":"Mayk Azzato",
    "wof:placetype":"venue"
},
  "geometry": {"coordinates":[8.6760835648,50.1152954102],"type":"Point"}
}