{
  "type": "Feature",
  "properties": {
    "iso:country":"DE",
    "sg:address":"Spindelgang 21",
    "sg:city":"Essen",
    "sg:phone":"+49 201/404823",
    "sg:postcode":"45239",
    "sg:province":"Nordrhein-Westfalen",
    "wof:name":"Waldemar M\u00fcller-berthold Architekt",
    "wof:placetype":"venue"
},
  "geometry": {"coordinates":[7.011933,51.39695],"type":"Point"}
}