{
  "type": "Feature",
  "properties": {
    "iso:country":"DE",
    "sg:address":"Wilhelmstr. 26a",
    "sg:city":"Kleve",
    "sg:phone":"+49 2821/995304",
    "sg:postcode":"47533",
    "sg:province":"Nordrhein-Westfalen",
    "wof:name":"Ticheloven",
    "wof:placetype":"venue"
},
  "geometry": {"coordinates":[6.1662759781,51.8002128601],"type":"Point"}
}