{
  "type": "Feature",
  "properties": {
    "iso:country":"DE",
    "sg:address":"Alte Leipziger Str. 14",
    "sg:city":"Gelnhausen",
    "sg:phone":"+49 6051/53231",
    "sg:postcode":"63571",
    "sg:province":"Hessen",
    "wof:name":"Budde Und Kraehe",
    "wof:placetype":"venue"
},
  "geometry": {"coordinates":[9.2305192947,50.2062263489],"type":"Point"}
}