{
  "type": "Feature",
  "properties": {
    "iso:country":"DE",
    "sg:address":"Am Vogelherd 16",
    "sg:city":"Germering",
    "sg:phone":"+49 89/8941510",
    "sg:postcode":"82110",
    "sg:province":"Bayern",
    "wof:name":"Jobst Frhr. Von Schirnding Architekt",
    "wof:placetype":"venue"
},
  "geometry": {"coordinates":[11.366581,48.118027],"type":"Point"}
}