{
  "type": "Feature",
  "properties": {
    "iso:country":"DE",
    "sg:address":"Staustr. 11",
    "sg:city":"Oldenburg",
    "sg:phone":"+49 441/219040",
    "sg:postcode":"26122",
    "sg:province":"Niedersachsen",
    "wof:name":"Becker Binkowski Und Kollegen",
    "wof:placetype":"venue"
},
  "geometry": {"coordinates":[8.2152872086,53.1404685974],"type":"Point"}
}