{
  "type": "Feature",
  "properties": {
    "iso:country":"DE",
    "sg:address":"Tannhauser Str. 21",
    "sg:city":"Aulendorf",
    "sg:phone":"+49 7525/1787",
    "sg:postcode":"88326",
    "sg:province":"Baden-W\u00fcrttemberg",
    "wof:name":"Erwin Laub",
    "wof:placetype":"venue"
},
  "geometry": {"coordinates":[9.663306,47.952072],"type":"Point"}
}