{
  "type": "Feature",
  "properties": {
    "iso:country":"DE",
    "sg:address":"K\u00f6nigsallee 92 a",
    "sg:city":"D\u00fcsseldorf",
    "sg:phone":"+49 211/83870",
    "sg:postcode":"40212",
    "sg:province":"Nordrhein-Westfalen",
    "wof:name":"Wessing Und Partner Rechtsanw\u00e4lte",
    "wof:placetype":"venue"
},
  "geometry": {"coordinates":[6.7794327736,51.2200012207],"type":"Point"}
}