{
  "type": "Feature",
  "properties": {
    "iso:country":"DE",
    "sg:address":"Schlo\u00dfstr. 12a",
    "sg:city":"Pegnitz",
    "sg:phone":"+49 9241/80195",
    "sg:postcode":"91257",
    "sg:province":"Bayern",
    "wof:name":"C. Kolpak-krieger",
    "wof:placetype":"venue"
},
  "geometry": {"coordinates":[11.5428390503,49.7549362183],"type":"Point"}
}