{
  "type": "Feature",
  "properties": {
    "iso:country":"DE",
    "sg:address":"Wiesmahdstr. 4a",
    "sg:city":"Gauting",
    "sg:phone":"+49 89/8505848",
    "sg:postcode":"82131",
    "sg:province":"Bayern",
    "wof:name":"Dr. Klaus-p. Arnold Rechtsanwalt",
    "wof:placetype":"venue"
},
  "geometry": {"coordinates":[11.3710012436,48.0755882263],"type":"Point"}
}