{
  "type": "Feature",
  "properties": {
    "iso:country":"DE",
    "sg:address":"J\u00fclicher Str. 14",
    "sg:city":"D\u00fcsseldorf",
    "sg:phone":"+49 211/446132",
    "sg:postcode":"40477",
    "sg:province":"Nordrhein-Westfalen",
    "wof:name":"Barbara S\u00f6hn-veigl",
    "wof:placetype":"venue"
},
  "geometry": {"coordinates":[6.7836179733,51.2427139282],"type":"Point"}
}