{
  "type": "Feature",
  "properties": {
    "iso:country":"DE",
    "sg:address":"Ziegelstr. 3",
    "sg:city":"Bergheim",
    "sg:postcode":"50129",
    "sg:province":"Nordrhein-Westfalen",
    "wof:name":"Klara Effertz",
    "wof:placetype":"venue"
},
  "geometry": {"coordinates":[6.754539,50.966545],"type":"Point"}
}