{
  "type": "Feature",
  "properties": {
    "iso:country":"DE",
    "sg:address":"Kirchfeldstr. 24",
    "sg:city":"Essen",
    "sg:phone":"+49 2054/3885",
    "sg:postcode":"45219",
    "sg:province":"Nordrhein-Westfalen",
    "wof:name":"G\u00fcnter Gerwinski",
    "wof:placetype":"venue"
},
  "geometry": {"coordinates":[6.9391732216,51.3652763367],"type":"Point"}
}