{
  "type": "Feature",
  "properties": {
    "iso:country":"DE",
    "sg:address":"J\u00fccherstr. 1",
    "sg:city":"Esens",
    "sg:phone":"+49 4971/7878",
    "sg:postcode":"26427",
    "sg:province":"Niedersachsen",
    "wof:name":"Doris Schneider",
    "wof:placetype":"venue"
},
  "geometry": {"coordinates":[7.613656044,53.6473388672],"type":"Point"}
}