{
  "type": "Feature",
  "properties": {
    "iso:country":"DE",
    "sg:address":"J\u00e4gerstr. 13",
    "sg:city":"Wiehl",
    "sg:phone":"+49 2262/92627",
    "sg:postcode":"51674",
    "sg:province":"Nordrhein-Westfalen",
    "wof:name":"Heinz Biermann Ingenieur",
    "wof:placetype":"venue"
},
  "geometry": {"coordinates":[7.5533108711,50.9378967285],"type":"Point"}
}