{
  "type": "Feature",
  "properties": {
    "iso:country":"DE",
    "sg:address":"Barbarossastr. 70",
    "sg:city":"Chemnitz",
    "sg:phone":"+49 371/306128",
    "sg:postcode":"09112",
    "sg:province":"Sachsen",
    "wof:name":"Hesa-immobilien Gmbh",
    "wof:placetype":"venue"
},
  "geometry": {"coordinates":[12.901513,50.833775],"type":"Point"}
}