{
  "type": "Feature",
  "properties": {
    "iso:country":"DE",
    "sg:address":"Hattroper Weg 32",
    "sg:city":"Soest",
    "sg:phone":"+49 2921/13379",
    "sg:postcode":"59494",
    "sg:province":"Nordrhein-Westfalen",
    "wof:name":"W. Borghoff",
    "wof:placetype":"venue"
},
  "geometry": {"coordinates":[8.093683,51.57431],"type":"Point"}
}