{
  "type": "Feature",
  "properties": {
    "iso:country":"DE",
    "sg:address":"Schmalenhofer Str. 59",
    "sg:city":"Velbert",
    "sg:phone":"+49 2051/253255",
    "sg:postcode":"42551",
    "sg:province":"Nordrhein-Westfalen",
    "wof:name":"Weber Metallbearbeitungs Gmbh",
    "wof:placetype":"venue"
},
  "geometry": {"coordinates":[7.0630111694,51.3288154602],"type":"Point"}
}