{
  "type": "Feature",
  "properties": {
    "iso:country":"DE",
    "sg:address":"In der Spreng 3",
    "sg:city":"Asendorf",
    "sg:phone":"+49 4253/573",
    "sg:postcode":"27330",
    "sg:province":"Niedersachsen",
    "wof:name":"Fritz Stegmann",
    "wof:placetype":"venue"
},
  "geometry": {"coordinates":[8.996995,52.751007],"type":"Point"}
}