{
  "type": "Feature",
  "properties": {
    "iso:country":"DE",
    "sg:address":"Steinweg 20",
    "sg:city":"Lohfelden",
    "sg:phone":"+49 5608/1286",
    "sg:postcode":"34253",
    "sg:province":"Hessen",
    "wof:name":"Wilhelm Kaiser",
    "wof:placetype":"venue"
},
  "geometry": {"coordinates":[9.564542,51.25663],"type":"Point"}
}