{
  "type": "Feature",
  "properties": {
    "iso:country":"DE",
    "sg:address":"Oberschledorner Str. 2",
    "sg:city":"Medebach",
    "sg:phone":"+49 5632/5036",
    "sg:postcode":"59964",
    "sg:province":"Nordrhein-Westfalen",
    "wof:name":"Asmuth Leuchten Gmbh & Co. Kg",
    "wof:placetype":"venue"
},
  "geometry": {"coordinates":[8.7042198181,51.2513999939],"type":"Point"}
}