{
  "type": "Feature",
  "properties": {
    "iso:country":"DE",
    "sg:address":"Maierhofstr. 21",
    "sg:city":"M\u00fcnchen",
    "sg:phone":"+49 89/833887",
    "sg:postcode":"81241",
    "sg:province":"Bayern",
    "wof:name":"Heinz Rath",
    "wof:placetype":"venue"
},
  "geometry": {"coordinates":[11.4650831223,48.1397132874],"type":"Point"}
}