{
  "type": "Feature",
  "properties": {
    "iso:country":"DE",
    "sg:address":"Donrather Str. 21",
    "sg:city":"Lohmar",
    "sg:phone":"+49 2246/912031",
    "sg:postcode":"53797",
    "sg:province":"Nordrhein-Westfalen",
    "wof:name":"H. Stellberg",
    "wof:placetype":"venue"
},
  "geometry": {"coordinates":[7.226635,50.854683],"type":"Point"}
}