{
  "type": "Feature",
  "properties": {
    "iso:country":"DE",
    "sg:address":"Nahering 8",
    "sg:city":"Ingelheim",
    "sg:phone":"+49 6132/85692",
    "sg:postcode":"55218",
    "sg:province":"Rheinland-Pfalz",
    "wof:name":"Polster-richter",
    "wof:placetype":"venue"
},
  "geometry": {"coordinates":[8.0289831161,49.9820594788],"type":"Point"}
}