{
  "type": "Feature",
  "properties": {
    "iso:country":"DE",
    "sg:address":"Blissestr. 48",
    "sg:city":"Berlin",
    "sg:postcode":"10713",
    "sg:province":"Berlin",
    "wof:name":"Steuerberater G\u00fcttner G\u00e4bel Und Ruef",
    "wof:placetype":"venue"
},
  "geometry": {"coordinates":[13.3201313019,52.4807434082],"type":"Point"}
}