{
  "type": "Feature",
  "properties": {
    "iso:country":"DE",
    "sg:address":"Hesselbacher Str. 6",
    "sg:city":"Bad Laasphe",
    "sg:phone":"+49 2752/478676",
    "sg:postcode":"57334",
    "sg:province":"Nordrhein-Westfalen",
    "wof:name":"Klaus Schwarzer`s Flugschule Flyart",
    "wof:placetype":"venue"
},
  "geometry": {"coordinates":[8.3597364426,50.8855438232],"type":"Point"}
}