{
  "type": "Feature",
  "properties": {
    "iso:country":"DE",
    "sg:address":"Beethovenstr. 5",
    "sg:city":"Trossingen",
    "sg:phone":"+49 7425/6738",
    "sg:postcode":"78647",
    "sg:province":"Baden-W\u00fcrttemberg",
    "wof:name":"T.-m. Herrmann",
    "wof:placetype":"venue"
},
  "geometry": {"coordinates":[8.641041,48.079498],"type":"Point"}
}