{
  "type": "Feature",
  "properties": {
    "iso:country":"DE",
    "sg:address":"Strohmarkt 12",
    "sg:city":"Neustadt",
    "sg:phone":"+49 6321/355454",
    "sg:postcode":"67433",
    "sg:province":"Rheinland-Pfalz",
    "wof:name":"Dilan",
    "wof:placetype":"venue"
},
  "geometry": {"coordinates":[8.1366615295,49.3554496765],"type":"Point"}
}