{
  "type": "Feature",
  "properties": {
    "iso:country":"DE",
    "sg:address":"Industriestra\u00dfe 12",
    "sg:city":"Miltenberg",
    "sg:postcode":"63920",
    "sg:province":"Bayern",
    "wof:name":"Bauunternehmen Tr\u00fctzler",
    "wof:placetype":"venue"
},
  "geometry": {"coordinates":[9.2229576111,49.728767395],"type":"Point"}
}