{
  "type": "Feature",
  "properties": {
    "iso:country":"DE",
    "sg:address":"Hauptstr. 28",
    "sg:city":"Menslage",
    "sg:phone":"+49 5437/719",
    "sg:postcode":"49637",
    "sg:province":"Niedersachsen",
    "wof:name":"F. G. Asmus",
    "wof:placetype":"venue"
},
  "geometry": {"coordinates":[7.816766,52.677418],"type":"Point"}
}