{
  "type": "Feature",
  "properties": {
    "iso:country":"DE",
    "sg:address":"Frankenstr. 8",
    "sg:city":"Rosbach",
    "sg:phone":"+49 6003/7004",
    "sg:postcode":"61191",
    "sg:province":"Hessen",
    "wof:name":"A. Simon",
    "wof:placetype":"venue"
},
  "geometry": {"coordinates":[8.707973,50.299652],"type":"Point"}
}