{
  "type": "Feature",
  "properties": {
    "iso:country":"DE",
    "sg:address":"Kolpingstr. 55",
    "sg:city":"Bedburg",
    "sg:phone":"+49 2272/82664",
    "sg:postcode":"50181",
    "sg:province":"Nordrhein-Westfalen",
    "wof:name":"M\u00fcller",
    "wof:placetype":"venue"
},
  "geometry": {"coordinates":[6.5756468773,50.9844284058],"type":"Point"}
}