{
  "type": "Feature",
  "properties": {
    "iso:country":"DE",
    "sg:address":"Landshuter Str. 30",
    "sg:city":"Freising",
    "sg:postcode":"85356",
    "sg:province":"Bayern",
    "wof:name":"Vfh Gmbh",
    "wof:placetype":"venue"
},
  "geometry": {"coordinates":[11.754104,48.404621],"type":"Point"}
}