{
  "type": "Feature",
  "properties": {
    "iso:country":"DE",
    "sg:address":"H\u00f6landstr. 13 b",
    "sg:city":"Lemgo",
    "sg:phone":"+49 5261/13822",
    "sg:postcode":"32657",
    "sg:province":"Nordrhein-Westfalen",
    "wof:name":"Wilhelm Wehrbein",
    "wof:placetype":"venue"
},
  "geometry": {"coordinates":[8.9119024277,52.0282897949],"type":"Point"}
}