{
  "type": "Feature",
  "properties": {
    "iso:country":"DE",
    "sg:address":"Frankfurter Str. 794",
    "sg:city":"K\u00f6ln",
    "sg:phone":"+49 221/891971",
    "sg:postcode":"51107",
    "sg:province":"Nordrhein-Westfalen",
    "wof:name":"E. Stephan",
    "wof:placetype":"venue"
},
  "geometry": {"coordinates":[7.048032,50.921032],"type":"Point"}
}