{
  "type": "Feature",
  "properties": {
    "iso:country":"DE",
    "sg:address":"Kirchenstr. 7",
    "sg:city":"W\u00fcrselen",
    "sg:phone":"+49 2405/808000",
    "sg:postcode":"52146",
    "sg:province":"Nordrhein-Westfalen",
    "wof:name":"H. Derichs Steinmetzbetrieb",
    "wof:placetype":"venue"
},
  "geometry": {"coordinates":[6.114812851,50.8412246704],"type":"Point"}
}