{
  "type": "Feature",
  "properties": {
    "iso:country":"DE",
    "sg:address":"Brockhorstweg 58-60",
    "sg:city":"Heiligenhaus",
    "sg:phone":"+49 2054/5075",
    "sg:postcode":"42579",
    "sg:province":"Nordrhein-Westfalen",
    "wof:name":"Reg Roger & Eckhard Gr\u00fcn",
    "wof:placetype":"venue"
},
  "geometry": {"coordinates":[6.922892,51.337578],"type":"Point"}
}