{
  "type": "Feature",
  "properties": {
    "iso:country":"DE",
    "sg:address":"Rathausplatz 5",
    "sg:city":"Lahr",
    "sg:phone":"+49 7821/22696",
    "sg:postcode":"77933",
    "sg:province":"Baden-W\u00fcrttemberg",
    "wof:name":"Photo Stober Paul Stober Gmbh",
    "wof:placetype":"venue"
},
  "geometry": {"coordinates":[7.8710827827,48.337890625],"type":"Point"}
}