{
  "type": "Feature",
  "properties": {
    "iso:country":"DE",
    "sg:address":"Lietzenburger Str. 77",
    "sg:city":"Berlin",
    "sg:phone":"+49 30/8813754",
    "sg:postcode":"10719",
    "sg:province":"Berlin",
    "wof:name":"Action Bar",
    "wof:placetype":"venue"
},
  "geometry": {"coordinates":[13.324525,52.499847],"type":"Point"}
}