{
  "type": "Feature",
  "properties": {
    "iso:country":"DE",
    "sg:address":"Schulweg 36",
    "sg:city":"Werdohl",
    "sg:phone":"+49 2392/970938",
    "sg:postcode":"58791",
    "sg:province":"Nordrhein-Westfalen",
    "wof:name":"Automaten Geier Gmbh",
    "wof:placetype":"venue"
},
  "geometry": {"coordinates":[7.7644882202,51.2556266785],"type":"Point"}
}