{
  "type": "Feature",
  "properties": {
    "iso:country":"DE",
    "sg:address":"Wittenaustr. 18",
    "sg:city":"Ummendorf",
    "sg:phone":"+49 7351/4749100",
    "sg:postcode":"88444",
    "sg:province":"Baden-W\u00fcrttemberg",
    "wof:name":"H\u00c4rle Innenausbau Gmbh",
    "wof:placetype":"venue"
},
  "geometry": {"coordinates":[9.8334522247,48.0616836548],"type":"Point"}
}