{
  "type": "Feature",
  "properties": {
    "iso:country":"DE",
    "sg:address":"Westring 14",
    "sg:city":"Gr\u00fcnstadt",
    "sg:postcode":"67269",
    "sg:province":"Rheinland-Pfalz",
    "wof:name":"Ipg Ingenieurb\u00fcro F\u00fcr Prozess- Optimierung Dr. Gierend Gmbh",
    "wof:placetype":"venue"
},
  "geometry": {"coordinates":[8.1610603333,49.5603408813],"type":"Point"}
}