{
  "type": "Feature",
  "properties": {
    "iso:country":"DE",
    "sg:address":"Gutenbergstr. 21",
    "sg:city":"Mannheim",
    "sg:phone":"+49 621/39050",
    "sg:postcode":"68167",
    "sg:province":"Baden-W\u00fcrttemberg",
    "wof:name":"Bauhaus Gmbh & Co. Kg Rhein-main-neckar",
    "wof:placetype":"venue"
},
  "geometry": {"coordinates":[8.49888134,49.496711731],"type":"Point"}
}