{
  "type": "Feature",
  "properties": {
    "iso:country":"DE",
    "sg:address":"Neue Str 3",
    "sg:city":"Steinen",
    "sg:phone":"+49 7627/510",
    "sg:postcode":"79585",
    "sg:province":"Baden-W\u00fcrttemberg",
    "wof:name":"Max Boll Gmbh",
    "wof:placetype":"venue"
},
  "geometry": {"coordinates":[7.739115,47.644474],"type":"Point"}
}