{
  "type": "Feature",
  "properties": {
    "iso:country":"DE",
    "sg:address":"Rhein-Mosel-Str. 9",
    "sg:city":"Emmelshausen",
    "sg:postcode":"56281",
    "sg:province":"Rheinland-Pfalz",
    "wof:name":"Internetangebot Der Agrarverwaltung Rheinland-pfalz",
    "wof:placetype":"venue"
},
  "geometry": {"coordinates":[7.5633077621,50.1559371948],"type":"Point"}
}