{
  "type": "Feature",
  "properties": {
    "iso:country":"DE",
    "sg:address":"Sch\u00fctzenstr. 19",
    "sg:city":"Cadenberge",
    "sg:phone":"+49 4777/1880",
    "sg:postcode":"21781",
    "sg:province":"Niedersachsen",
    "wof:name":"Fila Management- Und Beteiligungs Gmbh",
    "wof:placetype":"venue"
},
  "geometry": {"coordinates":[9.062844,53.77169],"type":"Point"}
}