{
  "type": "Feature",
  "properties": {
    "iso:country":"DE",
    "sg:address":"Ifflandstr. 67 b",
    "sg:city":"Hamburg",
    "sg:postcode":"22087",
    "sg:province":"Hamburg",
    "wof:name":"Quandt Bauregie Gmbh",
    "wof:placetype":"venue"
},
  "geometry": {"coordinates":[10.022845,53.562885],"type":"Point"}
}