{
  "type": "Feature",
  "properties": {
    "iso:country":"DE",
    "sg:address":"Gau\u00dfstr. 37-39",
    "sg:city":"Kirchheim",
    "sg:phone":"+49 7021/50050",
    "sg:postcode":"73230",
    "sg:province":"Baden-W\u00fcrttemberg",
    "wof:name":"Amk A. M\u00fcller Gmbh & Co. Kg",
    "wof:placetype":"venue"
},
  "geometry": {"coordinates":[9.469932,48.636604],"type":"Point"}
}