{
  "type": "Feature",
  "properties": {
    "iso:country":"DE",
    "sg:address":"Kellerstr. 5",
    "sg:city":"Stadtoldendorf",
    "sg:phone":"+49 5532/5757",
    "sg:postcode":"37627",
    "sg:province":"Niedersachsen",
    "wof:name":"Thomas Holzmann",
    "wof:placetype":"venue"
},
  "geometry": {"coordinates":[9.6244306564,51.8840866089],"type":"Point"}
}