{
  "type": "Feature",
  "properties": {
    "iso:country":"DE",
    "sg:address":"Hauptstr. 25",
    "sg:city":"Hornberg",
    "sg:phone":"+49 7833/1259",
    "sg:postcode":"78132",
    "sg:province":"Baden-W\u00fcrttemberg",
    "wof:name":"Stadt Hornberg",
    "wof:placetype":"venue"
},
  "geometry": {"coordinates":[8.2264261246,48.2167396545],"type":"Point"}
}