{
  "type": "Feature",
  "properties": {
    "iso:country":"DE",
    "sg:address":"Waldstr. 38",
    "sg:city":"F\u00fcrth",
    "sg:postcode":"90763",
    "sg:province":"Bayern",
    "wof:name":"Boesner Feulner & S\u00f6hne Gmbh",
    "wof:placetype":"venue"
},
  "geometry": {"coordinates":[11.0022659302,49.4631385803],"type":"Point"}
}