{
  "type": "Feature",
  "properties": {
    "iso:country":"DE",
    "sg:address":"Hauptstr. 28",
    "sg:city":"Gro\u00df Beuchow",
    "sg:postcode":"03222",
    "sg:province":"Brandenburg",
    "wof:name":"Michael Schulze",
    "wof:placetype":"venue"
},
  "geometry": {"coordinates":[13.9000940323,51.8480682373],"type":"Point"}
}