{
  "type": "Feature",
  "properties": {
    "iso:country":"DE",
    "sg:address":"Freiberger Str. 47",
    "sg:city":"Nossen",
    "sg:phone":"+49 35242/68322",
    "sg:postcode":"01683",
    "sg:province":"Sachsen",
    "wof:name":"Friedhelm Dilck",
    "wof:placetype":"venue"
},
  "geometry": {"coordinates":[13.292637,51.053982],"type":"Point"}
}