{
  "type": "Feature",
  "properties": {
    "iso:country":"DE",
    "sg:address":"Ittenhauser Str. 35",
    "sg:city":"Friedrichshafen",
    "sg:phone":"+49 7541/56163",
    "sg:postcode":"88048",
    "sg:province":"Baden-W\u00fcrttemberg",
    "wof:name":"Rotachhalle",
    "wof:placetype":"venue"
},
  "geometry": {"coordinates":[9.484210968,47.6881484985],"type":"Point"}
}