{
  "type": "Feature",
  "properties": {
    "iso:country":"DE",
    "sg:address":"Steubenstr. 74-76",
    "sg:city":"Heidelberg",
    "sg:phone":"+49 6221/436695",
    "sg:postcode":"69121",
    "sg:province":"Baden-W\u00fcrttemberg",
    "wof:name":"Handschusheimer Wollstube Inh. Edith Schmitt",
    "wof:placetype":"venue"
},
  "geometry": {"coordinates":[8.686895,49.427101],"type":"Point"}
}