{
  "type": "Feature",
  "properties": {
    "iso:country":"DE",
    "sg:address":"Boeler Str. 122",
    "sg:city":"Hagen",
    "sg:phone":"+49 2331/84931",
    "sg:postcode":"58097",
    "sg:province":"Nordrhein-Westfalen",
    "wof:name":"S. Nennmann",
    "wof:placetype":"venue"
},
  "geometry": {"coordinates":[7.477232,51.379715],"type":"Point"}
}