{
  "type": "Feature",
  "properties": {
    "iso:country":"DE",
    "sg:address":"Eisenbahnstr.50",
    "sg:city":"Dreieich",
    "sg:phone":"+49 6103/697093",
    "sg:postcode":"63303",
    "sg:province":"Hessen",
    "wof:name":"Design2day",
    "wof:placetype":"venue"
},
  "geometry": {"coordinates":[8.689011,50.016277],"type":"Point"}
}