{
  "type": "Feature",
  "properties": {
    "iso:country":"DE",
    "sg:address":"Wilhelm-Busch-Str. 10",
    "sg:city":"Pegnitz",
    "sg:phone":"+49 9241/3950",
    "sg:postcode":"91257",
    "sg:province":"Bayern",
    "wof:name":"Oliver Fuchs",
    "wof:placetype":"venue"
},
  "geometry": {"coordinates":[11.5359916687,49.7439231873],"type":"Point"}
}