{
  "type": "Feature",
  "properties": {
    "iso:country":"DE",
    "sg:address":"Prinzenallee 89-90",
    "sg:city":"Berlin",
    "sg:postcode":"13357",
    "sg:province":"Berlin",
    "wof:name":"Vergi-consult Gmbh",
    "wof:placetype":"venue"
},
  "geometry": {"coordinates":[13.3815870285,52.5526771545],"type":"Point"}
}