{
  "type": "Feature",
  "properties": {
    "iso:country":"DE",
    "sg:address":"Maxhuetter Str. 16",
    "sg:city":"Teublitz",
    "sg:phone":"+49 9471/3100200",
    "sg:postcode":"93158",
    "sg:province":"Bayern",
    "wof:name":"Socratec Gmbh",
    "wof:placetype":"venue"
},
  "geometry": {"coordinates":[12.0853462219,49.2175941467],"type":"Point"}
}