{
  "type": "Feature",
  "properties": {
    "iso:country":"DE",
    "sg:address":"Hobbacher Weg 4",
    "sg:city":"Elsenfeld",
    "sg:phone":"+49 9374/418",
    "sg:postcode":"63820",
    "sg:province":"Bayern",
    "wof:name":"Robert Weis",
    "wof:placetype":"venue"
},
  "geometry": {"coordinates":[9.2380180359,49.848197937],"type":"Point"}
}