{
  "type": "Feature",
  "properties": {
    "iso:country":"DE",
    "sg:address":"Wyhler Str. 26",
    "sg:city":"Forchheim",
    "sg:phone":"+49 7642/7336",
    "sg:postcode":"79362",
    "sg:province":"Baden-W\u00fcrttemberg",
    "wof:name":"Eugen Eckert",
    "wof:placetype":"venue"
},
  "geometry": {"coordinates":[7.698252,48.16209],"type":"Point"}
}