{
  "type": "Feature",
  "properties": {
    "iso:country":"DE",
    "sg:address":"Alte Landstr. 39-41",
    "sg:city":"Hasloh",
    "sg:phone":"+49 4106/2039",
    "sg:postcode":"25474",
    "sg:province":"Schleswig-Holstein",
    "wof:name":"Tankschutz Fago - Fachbetrieb F\u00fcr Dieseltank",
    "wof:placetype":"venue"
},
  "geometry": {"coordinates":[9.905622,53.695877],"type":"Point"}
}