{
  "type": "Feature",
  "properties": {
    "iso:country":"DE",
    "sg:address":"Hansering 20",
    "sg:city":"Halle",
    "sg:phone":"+49 345/298450",
    "sg:postcode":"06108",
    "sg:province":"Sachsen-Anhalt",
    "wof:name":"Werner Und Wuchterl Architekten",
    "wof:placetype":"venue"
},
  "geometry": {"coordinates":[11.974347,51.483814],"type":"Point"}
}