{
  "type": "Feature",
  "properties": {
    "iso:country":"DE",
    "sg:address":"Im Hagen 6",
    "sg:city":"Radevormwald",
    "sg:phone":"+49 2195/1841",
    "sg:postcode":"42477",
    "sg:province":"Nordrhein-Westfalen",
    "wof:name":"Friedhelm Goller",
    "wof:placetype":"venue"
},
  "geometry": {"coordinates":[7.3391308784,51.2115287781],"type":"Point"}
}