{
  "type": "Feature",
  "properties": {
    "iso:country":"DE",
    "sg:address":"Marktstr. 154",
    "sg:city":"Wilhelmshaven",
    "sg:phone":"+49 4421/203579",
    "sg:postcode":"26382",
    "sg:province":"Niedersachsen",
    "wof:name":"U. Schmidt Finanzberater",
    "wof:placetype":"venue"
},
  "geometry": {"coordinates":[8.1006355286,53.5196380615],"type":"Point"}
}