{
  "type": "Feature",
  "properties": {
    "iso:country":"DE",
    "sg:address":"In der Steinwiese 16",
    "sg:city":"Siegen",
    "sg:phone":"+49 271/6920",
    "sg:postcode":"57074",
    "sg:province":"Nordrhein-Westfalen",
    "wof:name":"Electrolux Dienstleistungs-gmbh",
    "wof:placetype":"venue"
},
  "geometry": {"coordinates":[8.0728750229,50.8682441711],"type":"Point"}
}