{
  "type": "Feature",
  "properties": {
    "iso:country":"DE",
    "sg:address":"Kleine Gasse 6",
    "sg:city":"Hamburg",
    "sg:phone":"+49 40/7657486",
    "sg:postcode":"21073",
    "sg:province":"Hamburg",
    "wof:name":"La Bastille",
    "wof:placetype":"venue"
},
  "geometry": {"coordinates":[9.981180191,53.4634895325],"type":"Point"}
}