{
  "type": "Feature",
  "properties": {
    "iso:country":"DE",
    "sg:address":"Goethestr. 6",
    "sg:city":"Rielasingen-Worblingen",
    "sg:phone":"+49 7731/28090",
    "sg:postcode":"78239",
    "sg:province":"Baden-W\u00fcrttemberg",
    "wof:name":"Ingrid Graf Masseurin",
    "wof:placetype":"venue"
},
  "geometry": {"coordinates":[8.855554,47.729069],"type":"Point"}
}