{
  "type": "Feature",
  "properties": {
    "iso:country":"DE",
    "sg:address":"Kurf\u00fcrstenwall 2",
    "sg:city":"Recklinghausen",
    "sg:phone":"+49 2361/24424",
    "sg:postcode":"45657",
    "sg:province":"Nordrhein-Westfalen",
    "wof:name":"Engel-apotheke Mecke Schweda",
    "wof:placetype":"venue"
},
  "geometry": {"coordinates":[7.200435,51.616009],"type":"Point"}
}