{
  "type": "Feature",
  "properties": {
    "iso:country":"DE",
    "sg:address":"Amselstr. 35",
    "sg:city":"Rohrdorf",
    "sg:phone":"+49 8031/737782",
    "sg:postcode":"83101",
    "sg:province":"Bayern",
    "wof:name":"Lothar Fr\u00f6mel",
    "wof:placetype":"venue"
},
  "geometry": {"coordinates":[12.1607971191,47.8202705383],"type":"Point"}
}