{
  "type": "Feature",
  "properties": {
    "iso:country":"DE",
    "sg:address":"Bahnhofstr.",
    "sg:city":"Gr\u00fcnberg",
    "sg:phone":"+49 6401/6379",
    "sg:postcode":"35305",
    "sg:province":"Hessen",
    "wof:name":"Deutsche Bahn Ag",
    "wof:placetype":"venue"
},
  "geometry": {"coordinates":[8.9600849152,50.5958442688],"type":"Point"}
}