{
  "type": "Feature",
  "properties": {
    "iso:country":"DE",
    "sg:address":"Meyra-Ring 6",
    "sg:city":"Kalletal",
    "sg:phone":"+49 5733/4481",
    "sg:postcode":"32689",
    "sg:province":"Nordrhein-Westfalen",
    "wof:name":"Kalldorfer-brunnen",
    "wof:placetype":"venue"
},
  "geometry": {"coordinates":[8.9220485687,52.1594390869],"type":"Point"}
}