{
  "type": "Feature",
  "properties": {
    "iso:country":"DE",
    "sg:address":"Geistwall 32",
    "sg:city":"L\u00fcbbecke",
    "sg:phone":"+49 5741/1081",
    "sg:postcode":"32312",
    "sg:province":"Nordrhein-Westfalen",
    "wof:name":"Kirchenkreis L\u00fcbbecke",
    "wof:placetype":"venue"
},
  "geometry": {"coordinates":[8.6198759079,52.3014831543],"type":"Point"}
}