{
  "type": "Feature",
  "properties": {
    "iso:country":"DE",
    "sg:address":"Obere Vorstadt 40",
    "sg:city":"Auerbach",
    "sg:phone":"+49 9643/91420",
    "sg:postcode":"91275",
    "sg:province":"Bayern",
    "wof:name":"Werner M\u00fcller",
    "wof:placetype":"venue"
},
  "geometry": {"coordinates":[11.633667,49.689774],"type":"Point"}
}