{
  "type": "Feature",
  "properties": {
    "iso:country":"DE",
    "sg:address":"L\u00fcneburger Str. 6",
    "sg:city":"Soltau",
    "sg:phone":"+49 5191/13550",
    "sg:postcode":"29614",
    "sg:province":"Niedersachsen",
    "wof:name":"Papillon",
    "wof:placetype":"venue"
},
  "geometry": {"coordinates":[9.8460512161,52.9867897034],"type":"Point"}
}