{
  "type": "Feature",
  "properties": {
    "iso:country":"DE",
    "sg:address":"Leonrodstr. 77",
    "sg:city":"M\u00fcnchen",
    "sg:phone":"+49 89/1293954",
    "sg:postcode":"80636",
    "sg:province":"Bayern",
    "wof:name":"Anna-blume",
    "wof:placetype":"venue"
},
  "geometry": {"coordinates":[11.54474,48.158272],"type":"Point"}
}