{
  "type": "Feature",
  "properties": {
    "iso:country":"DE",
    "sg:address":"Frankfurterstr. 187",
    "sg:city":"Kassel",
    "sg:phone":"+49 561/200970",
    "sg:postcode":"34121",
    "sg:province":"Hessen",
    "wof:name":"Roehrenrutschen",
    "wof:placetype":"venue"
},
  "geometry": {"coordinates":[9.477006,51.293736],"type":"Point"}
}