{
  "type": "Feature",
  "properties": {
    "iso:country":"DE",
    "sg:address":"Marxheimer Str. 4",
    "sg:city":"Frankfurt",
    "sg:phone":"+49 69/732868",
    "sg:postcode":"60326",
    "sg:province":"Hessen",
    "wof:name":"Wohnbaugenossenschaft In Frankfurt Am Main Eg",
    "wof:placetype":"venue"
},
  "geometry": {"coordinates":[8.6199016571,50.1008415222],"type":"Point"}
}