{
  "type": "Feature",
  "properties": {
    "iso:country":"DE",
    "sg:address":"Ahornweg 5a",
    "sg:city":"Zell",
    "sg:phone":"+49 6542/4992",
    "sg:postcode":"56856",
    "sg:province":"Rheinland-Pfalz",
    "wof:name":"H. Borr",
    "wof:placetype":"venue"
},
  "geometry": {"coordinates":[7.167848,50.028904],"type":"Point"}
}