{
  "type": "Feature",
  "properties": {
    "iso:country":"DE",
    "sg:address":"Bahrenbergring 16",
    "sg:city":"Essen",
    "sg:phone":"+49 201/460044",
    "sg:postcode":"45259",
    "sg:province":"Nordrhein-Westfalen",
    "wof:name":"Dr. Heinz Reintges Rechtsanwalt",
    "wof:placetype":"venue"
},
  "geometry": {"coordinates":[7.0684437752,51.4072189331],"type":"Point"}
}