{
  "type": "Feature",
  "properties": {
    "iso:country":"DE",
    "sg:address":"Oppenweher Str. 25",
    "sg:city":"Wagenfeld",
    "sg:phone":"+49 5444/326",
    "sg:postcode":"49419",
    "sg:province":"Niedersachsen",
    "wof:name":"Otto P\u00f6rtner",
    "wof:placetype":"venue"
},
  "geometry": {"coordinates":[8.58043,52.547928],"type":"Point"}
}