{
  "type": "Feature",
  "properties": {
    "iso:country":"DE",
    "sg:address":"Neundorferstra\u00dfe 1",
    "sg:city":"Weischlitz",
    "sg:phone":"+49 3741/131229",
    "sg:postcode":"08538",
    "sg:province":"Sachsen",
    "wof:name":"Roland Zaumseil & Co Gmbh",
    "wof:placetype":"venue"
},
  "geometry": {"coordinates":[12.058506012,50.4901885986],"type":"Point"}
}