{
  "type": "Feature",
  "properties": {
    "iso:country":"DE",
    "sg:address":"Twicklerstr. 17",
    "sg:city":"Vreden",
    "sg:phone":"+49 2564/32092",
    "sg:postcode":"48691",
    "sg:province":"Nordrhein-Westfalen",
    "wof:name":"Josef Umme Architekt",
    "wof:placetype":"venue"
},
  "geometry": {"coordinates":[6.825799,52.036705],"type":"Point"}
}