{
  "type": "Feature",
  "properties": {
    "iso:country":"DE",
    "sg:address":"Burgstr. 1",
    "sg:city":"Melsungen",
    "sg:phone":"+49 5661/2229",
    "sg:postcode":"34212",
    "sg:province":"Hessen",
    "wof:name":"Centralkaufhaus",
    "wof:placetype":"venue"
},
  "geometry": {"coordinates":[9.54258,51.131168],"type":"Point"}
}