{
  "type": "Feature",
  "properties": {
    "iso:country":"DE",
    "sg:address":"Auf den Kuhlen 16",
    "sg:city":"Damme",
    "sg:phone":"+49 5491/2583",
    "sg:postcode":"49401",
    "sg:province":"Niedersachsen",
    "wof:name":"Josef R\u00f6mer",
    "wof:placetype":"venue"
},
  "geometry": {"coordinates":[8.22839,52.506458],"type":"Point"}
}