{
  "type": "Feature",
  "properties": {
    "iso:country":"DE",
    "sg:address":"Kirchenstr. 9",
    "sg:city":"Norderstedt",
    "sg:phone":"+49 40/5231721",
    "sg:postcode":"22848",
    "sg:province":"Schleswig-Holstein",
    "wof:name":"Horst Kleyer",
    "wof:placetype":"venue"
},
  "geometry": {"coordinates":[9.969509,53.678921],"type":"Point"}
}