{
  "type": "Feature",
  "properties": {
    "iso:country":"DE",
    "sg:address":"Beim Kleinen Tagwerk 50",
    "sg:city":"Bremen",
    "sg:postcode":"28355",
    "sg:province":"Bremen",
    "wof:name":"Mos Messebau Merchandising Objektgestaltung Service",
    "wof:placetype":"venue"
},
  "geometry": {"coordinates":[8.90292,53.094696],"type":"Point"}
}