{
  "type": "Feature",
  "properties": {
    "iso:country":"DE",
    "sg:address":"Kantstr. 37",
    "sg:city":"Ostheim",
    "sg:phone":"+49 9777/9255",
    "sg:postcode":"97645",
    "sg:province":"Bayern",
    "wof:name":"Christine Hartmann Steuerberaterin",
    "wof:placetype":"venue"
},
  "geometry": {"coordinates":[10.2202129364,50.462059021],"type":"Point"}
}