{
  "type": "Feature",
  "properties": {
    "iso:country":"DE",
    "sg:address":"Wilhelm-J\u00e4ger-Str. 4",
    "sg:city":"Darmstadt",
    "sg:phone":"+49 6151/45742",
    "sg:postcode":"64287",
    "sg:province":"Hessen",
    "wof:name":"Industria Bautr\u00e4ger Gmbh & Co. Wasserweg Kg",
    "wof:placetype":"venue"
},
  "geometry": {"coordinates":[8.67281,49.869175],"type":"Point"}
}