{
  "type": "Feature",
  "properties": {
    "iso:country":"DE",
    "sg:city":"Altdorf",
    "sg:phone":"+49 9187/804813",
    "sg:postcode":"90518",
    "sg:province":"Bayern",
    "wof:name":"Epog Reiseveranstalter",
    "wof:placetype":"venue"
},
  "geometry": {"coordinates":[11.38631,49.393188],"type":"Point"}
}