{
  "type": "Feature",
  "properties": {
    "iso:country":"DE",
    "sg:address":"Wertenbachstr. 34",
    "sg:city":"Balingen",
    "sg:phone":"+49 7433/15869",
    "sg:postcode":"72336",
    "sg:province":"Baden-W\u00fcrttemberg",
    "wof:name":"Walter Spiess Strickmoden Gmbh",
    "wof:placetype":"venue"
},
  "geometry": {"coordinates":[8.8825941086,48.296585083],"type":"Point"}
}