{
  "type": "Feature",
  "properties": {
    "iso:country":"DE",
    "sg:address":"Wilhelm-Maybach-Str 12",
    "sg:city":"Rottenburg",
    "sg:phone":"+49 7472/925300",
    "sg:postcode":"72108",
    "sg:province":"Baden-W\u00fcrttemberg",
    "wof:name":"Operational Umwelttechnik Gmbh",
    "wof:placetype":"venue"
},
  "geometry": {"coordinates":[8.953137,48.478821],"type":"Point"}
}