{
  "type": "Feature",
  "properties": {
    "iso:country":"DE",
    "sg:address":"Berliner Ring 54",
    "sg:city":"Harsewinkel",
    "sg:phone":"+49 5247/2980",
    "sg:postcode":"33428",
    "sg:province":"Nordrhein-Westfalen",
    "wof:name":"Gr\u00fctzner Druck Gmbh",
    "wof:placetype":"venue"
},
  "geometry": {"coordinates":[8.242819,51.968197],"type":"Point"}
}