{
  "type": "Feature",
  "properties": {
    "iso:country":"DE",
    "sg:address":"Techentiner Str. 5",
    "sg:city":"Ludwigslust",
    "sg:postcode":"19288",
    "sg:province":"Mecklenburg-Vorpommern",
    "wof:name":"Dh Unterhaltungs Gmbh",
    "wof:placetype":"venue"
},
  "geometry": {"coordinates":[11.4972047806,53.3204841614],"type":"Point"}
}