{
  "type": "Feature",
  "properties": {
    "iso:country":"DE",
    "sg:address":"Steinstr. 1",
    "sg:city":"J\u00fcchen",
    "sg:postcode":"41363",
    "sg:province":"Nordrhein-Westfalen",
    "wof:name":"Hatec Hafentechnik Consulting Gmbh",
    "wof:placetype":"venue"
},
  "geometry": {"coordinates":[6.5012478828,51.102180481],"type":"Point"}
}