{
  "type": "Feature",
  "properties": {
    "iso:country":"DE",
    "sg:address":"Eichendorffstr. 44-46",
    "sg:city":"Euskirchen",
    "sg:postcode":"53879",
    "sg:province":"Nordrhein-Westfalen",
    "wof:name":"Hdg Handwerker Dienstleistung Gmbh",
    "wof:placetype":"venue"
},
  "geometry": {"coordinates":[6.7835469246,50.6557540894],"type":"Point"}
}