{
  "type": "Feature",
  "properties": {
    "iso:country":"DE",
    "sg:address":"Markt 7 A",
    "sg:city":"Sch\u00f6nebeck",
    "sg:phone":"+49 3928/403608",
    "sg:postcode":"39218",
    "sg:province":"Sachsen-Anhalt",
    "wof:name":"Dietrich Punken",
    "wof:placetype":"venue"
},
  "geometry": {"coordinates":[11.738593,52.021351],"type":"Point"}
}