{
  "type": "Feature",
  "properties": {
    "iso:country":"DE",
    "sg:address":"Matthias-Erzberger-Str. 3",
    "sg:city":"Lambrecht",
    "sg:phone":"+49 6325/8162",
    "sg:postcode":"67466",
    "sg:province":"Rheinland-Pfalz",
    "wof:name":"Reinhold Bullinger",
    "wof:placetype":"venue"
},
  "geometry": {"coordinates":[8.06772995,49.3725891113],"type":"Point"}
}