{
  "type": "Feature",
  "properties": {
    "iso:country":"DE",
    "sg:address":"Schlo\u00dfstr. 3",
    "sg:city":"Dresden",
    "sg:postcode":"01067",
    "sg:province":"Sachsen",
    "wof:name":"Kaufcenter",
    "wof:placetype":"venue"
},
  "geometry": {"coordinates":[13.737143,51.050934],"type":"Point"}
}