{
  "type": "Feature",
  "properties": {
    "iso:country":"DE",
    "sg:address":"Waisenstr. 1",
    "sg:city":"Berlin",
    "sg:phone":"+49 30/24390890",
    "sg:postcode":"10179",
    "sg:province":"Berlin",
    "wof:name":"Achte Spreeinsel Liegenschaftsgesellschaft",
    "wof:placetype":"venue"
},
  "geometry": {"coordinates":[13.4145345688,52.5159797668],"type":"Point"}
}