{
  "type": "Feature",
  "properties": {
    "iso:country":"DE",
    "sg:address":"Stockholmer Allee 24",
    "sg:city":"Dortmund",
    "sg:postcode":"44269",
    "sg:province":"Nordrhein-Westfalen",
    "wof:name":"Gambit Web Und Phone Gmbh & Co. Kg",
    "wof:placetype":"venue"
},
  "geometry": {"coordinates":[7.528143,51.50433],"type":"Point"}
}