{
  "type": "Feature",
  "properties": {
    "iso:country":"DE",
    "sg:address":"Sonnenstr. 19",
    "sg:city":"M\u00fcnchen",
    "sg:phone":"+49 89/55254127",
    "sg:postcode":"80331",
    "sg:province":"Bayern",
    "wof:name":"Forum F. Naturheilkunde, Psychotherapie U. Esoterik",
    "wof:placetype":"venue"
},
  "geometry": {"coordinates":[11.565343,48.136467],"type":"Point"}
}