{
  "type": "Feature",
  "properties": {
    "iso:country":"DE",
    "sg:address":"Bergstr. 7",
    "sg:city":"Augustusburg",
    "sg:phone":"+49 37291/2970",
    "sg:postcode":"09573",
    "sg:province":"Sachsen",
    "wof:name":"Georgi Werbe- Und Design Studio Gmbh",
    "wof:placetype":"venue"
},
  "geometry": {"coordinates":[13.0672178268,50.8183097839],"type":"Point"}
}