{
  "type": "Feature",
  "properties": {
    "iso:country":"DE",
    "sg:address":"Kuh\u00e4ckerstr. 12",
    "sg:city":"Erligheim",
    "sg:postcode":"74391",
    "sg:province":"Baden-W\u00fcrttemberg",
    "wof:name":"W & R Naturreisen",
    "wof:placetype":"venue"
},
  "geometry": {"coordinates":[9.0982217789,49.0162239075],"type":"Point"}
}