{
  "type": "Feature",
  "properties": {
    "iso:country":"DE",
    "sg:address":"Markt 7",
    "sg:city":"Vetschau",
    "sg:phone":"+49 35433/70388",
    "sg:postcode":"03226",
    "sg:province":"Brandenburg",
    "wof:name":"Spreewald Touristik E. K.",
    "wof:placetype":"venue"
},
  "geometry": {"coordinates":[14.0741987228,51.7841567993],"type":"Point"}
}