{
  "type": "Feature",
  "properties": {
    "iso:country":"DE",
    "sg:address":"Mousonstr. 15",
    "sg:city":"Frankfurt",
    "sg:phone":"+49 69/491601",
    "sg:postcode":"60316",
    "sg:province":"Hessen",
    "wof:name":"M. E. Kuntz-wiedemann Dipl. \u00dcbersetzerin",
    "wof:placetype":"venue"
},
  "geometry": {"coordinates":[8.697359,50.118355],"type":"Point"}
}