{
  "type": "Feature",
  "properties": {
    "iso:country":"DE",
    "sg:address":"Immengarten 14",
    "sg:city":"Hannover",
    "sg:phone":"+49 511/6965960",
    "sg:postcode":"30177",
    "sg:province":"Niedersachsen",
    "wof:name":"Herbert Plonske Architekt",
    "wof:placetype":"venue"
},
  "geometry": {"coordinates":[9.765905,52.397129],"type":"Point"}
}