{
  "type": "Feature",
  "properties": {
    "iso:country":"DE",
    "sg:address":"Lange Str. 24",
    "sg:city":"Wremen",
    "sg:phone":"+49 4705/780",
    "sg:postcode":"27638",
    "sg:province":"Niedersachsen",
    "wof:name":"Kr\u00f6ger",
    "wof:placetype":"venue"
},
  "geometry": {"coordinates":[8.5090360641,53.6504058838],"type":"Point"}
}