{
  "type": "Feature",
  "properties": {
    "iso:country":"DE",
    "sg:address":"Rauhhalde 26",
    "sg:city":"Sch\u00f6ntal",
    "sg:phone":"+49 7943/2988",
    "sg:postcode":"74214",
    "sg:province":"Baden-W\u00fcrttemberg",
    "wof:name":"Manfred Karl",
    "wof:placetype":"venue"
},
  "geometry": {"coordinates":[9.536308,49.342075],"type":"Point"}
}