{
  "type": "Feature",
  "properties": {
    "iso:country":"DE",
    "sg:address":"Rehmsweg 6",
    "sg:city":"Schalkholz",
    "sg:phone":"+49 4838/7581",
    "sg:postcode":"25782",
    "sg:province":"Schleswig-Holstein",
    "wof:name":"City-plan- Und Bau Gmbh",
    "wof:placetype":"venue"
},
  "geometry": {"coordinates":[9.2562847137,54.2438392639],"type":"Point"}
}