{
  "type": "Feature",
  "properties": {
    "iso:country":"DE",
    "sg:address":"S\u00e4ngerbuchenweg 3",
    "sg:city":"Darmstadt",
    "sg:phone":"+49 6150/7129",
    "sg:postcode":"64291",
    "sg:province":"Hessen",
    "wof:name":"Gemeinn. Wohnungsbau- Genosschenschaft Wixhausen Eg",
    "wof:placetype":"venue"
},
  "geometry": {"coordinates":[8.6565475464,49.9321708679],"type":"Point"}
}