{
  "type": "Feature",
  "properties": {
    "iso:country":"DE",
    "sg:address":"Wallensteinstr. 11c",
    "sg:city":"Stuttgart",
    "sg:phone":"+49 711/842861",
    "sg:postcode":"70437",
    "sg:province":"Baden-W\u00fcrttemberg",
    "wof:name":"Walter H\u00e4ussermann",
    "wof:placetype":"venue"
},
  "geometry": {"coordinates":[9.208295,48.841747],"type":"Point"}
}