{
  "type": "Feature",
  "properties": {
    "iso:country":"DE",
    "sg:address":"Bergh\u00e4user Str. 211",
    "sg:city":"Recklinghausen",
    "sg:phone":"+49 2361/35551",
    "sg:postcode":"45659",
    "sg:province":"Nordrhein-Westfalen",
    "wof:name":"Johannes Wild",
    "wof:placetype":"venue"
},
  "geometry": {"coordinates":[7.2276721001,51.59141922],"type":"Point"}
}