{
  "type": "Feature",
  "properties": {
    "iso:country":"DE",
    "sg:address":"Bahnhofstr. 54",
    "sg:city":"Eschenbach",
    "sg:phone":"+49 7161/44971",
    "sg:postcode":"73107",
    "sg:province":"Baden-W\u00fcrttemberg",
    "wof:name":"Apotheke Eschenbach E. K.",
    "wof:placetype":"venue"
},
  "geometry": {"coordinates":[9.671784,48.65966],"type":"Point"}
}