{
  "type": "Feature",
  "properties": {
    "iso:country":"DE",
    "sg:address":"Am Hang 2",
    "sg:city":"Friedberg",
    "sg:postcode":"61169",
    "sg:province":"Hessen",
    "wof:name":"Werner Bachmann Tennislehrer",
    "wof:placetype":"venue"
},
  "geometry": {"coordinates":[8.7928762436,50.3223228455],"type":"Point"}
}