{
  "type": "Feature",
  "properties": {
    "iso:country":"DE",
    "sg:address":"Altenmeller Str. 7",
    "sg:city":"Melle",
    "sg:phone":"+49 5429/921017",
    "sg:postcode":"49326",
    "sg:province":"Niedersachsen",
    "wof:name":"R. Teders",
    "wof:placetype":"venue"
},
  "geometry": {"coordinates":[8.2681627274,52.1600074768],"type":"Point"}
}