{
  "type": "Feature",
  "properties": {
    "iso:country":"DE",
    "sg:address":"M\u00f6hlstr. 31",
    "sg:city":"M\u00fcnchen",
    "sg:phone":"+49 89/984675",
    "sg:postcode":"81675",
    "sg:province":"Bayern",
    "wof:name":"Petrom Int. Trade Gmbh",
    "wof:placetype":"venue"
},
  "geometry": {"coordinates":[11.6015233994,48.1460266113],"type":"Point"}
}