{
  "type": "Feature",
  "properties": {
    "iso:country":"DE",
    "sg:address":"Moselstr. 13",
    "sg:city":"Eggenstein-Leopoldshafen",
    "sg:phone":"+49 7247/21263",
    "sg:postcode":"76344",
    "sg:province":"Baden-W\u00fcrttemberg",
    "wof:name":"Edwin Heger Ingenieur",
    "wof:placetype":"venue"
},
  "geometry": {"coordinates":[8.4004001617,49.0944786072],"type":"Point"}
}