{
  "type": "Feature",
  "properties": {
    "iso:country":"DE",
    "sg:address":"Rheinstr. 1",
    "sg:city":"Mettmann",
    "sg:phone":"+49 2104/70847",
    "sg:postcode":"40822",
    "sg:province":"Nordrhein-Westfalen",
    "wof:name":"P. Plasa Und Wallmeier",
    "wof:placetype":"venue"
},
  "geometry": {"coordinates":[6.9690861702,51.2484664917],"type":"Point"}
}