{
  "type": "Feature",
  "properties": {
    "iso:country":"DE",
    "sg:address":"Bahnhofstr. 15",
    "sg:city":"Damme",
    "sg:phone":"+49 5491/4403",
    "sg:postcode":"49401",
    "sg:province":"Niedersachsen",
    "wof:name":"Musikhaus Raska",
    "wof:placetype":"venue"
},
  "geometry": {"coordinates":[8.1917009354,52.5200309753],"type":"Point"}
}