{
  "type": "Feature",
  "properties": {
    "iso:country":"DE",
    "sg:address":"Am Goldstein 4",
    "sg:city":"Bad Nauheim",
    "sg:phone":"+49 6032/71151",
    "sg:postcode":"61231",
    "sg:province":"Hessen",
    "wof:name":"Institut F\u00fcr Umweltanalytik Bad Nauheim Kg",
    "wof:placetype":"venue"
},
  "geometry": {"coordinates":[8.7510461807,50.365447998],"type":"Point"}
}