{
  "type": "Feature",
  "properties": {
    "iso:country":"DE",
    "sg:address":"Friedrichstr 187",
    "sg:city":"Berlin",
    "sg:phone":"+49 30/3110900",
    "sg:postcode":"10117",
    "sg:province":"Berlin",
    "wof:name":"Mpi Management Partner International Gmbh",
    "wof:placetype":"venue"
},
  "geometry": {"coordinates":[13.389466,52.511707],"type":"Point"}
}