{
  "type": "Feature",
  "properties": {
    "iso:country":"DE",
    "sg:address":"Karlstra\u00dfe 35",
    "sg:city":"M\u00fcnchen",
    "sg:phone":"+49 89",
    "sg:postcode":"80333",
    "sg:province":"Bayern",
    "wof:name":"Druckerei M\u00fchlthaler",
    "wof:placetype":"venue"
},
  "geometry": {"coordinates":[11.562247,48.14418],"type":"Point"}
}