{
  "type": "Feature",
  "properties": {
    "iso:country":"DE",
    "sg:address":"In den Zwergen 50",
    "sg:city":"Dillingen",
    "sg:phone":"+49 6831/72567",
    "sg:postcode":"66763",
    "sg:province":"Saarland",
    "wof:name":"Gerd Drexel",
    "wof:placetype":"venue"
},
  "geometry": {"coordinates":[6.714148,49.351936],"type":"Point"}
}