{
  "type": "Feature",
  "properties": {
    "iso:country":"DE",
    "sg:address":"Schlachthausstr. 1",
    "sg:city":"L\u00fcdenscheid",
    "sg:phone":"+49 2351/80090",
    "sg:postcode":"58511",
    "sg:province":"Nordrhein-Westfalen",
    "wof:name":"Tayfuns Grill",
    "wof:placetype":"venue"
},
  "geometry": {"coordinates":[7.645468235,51.2115402222],"type":"Point"}
}