{
  "type": "Feature",
  "properties": {
    "iso:country":"DE",
    "sg:address":"K\u00f6nig-Ludwig-Weg 23",
    "sg:city":"Berg",
    "sg:phone":"+49 8151/50365",
    "sg:postcode":"82335",
    "sg:province":"Bayern",
    "wof:name":"Fashion Marketing Rolf Griesinger Gmbh",
    "wof:placetype":"venue"
},
  "geometry": {"coordinates":[11.351604,47.964901],"type":"Point"}
}