{
  "type": "Feature",
  "properties": {
    "iso:country":"DE",
    "sg:address":"M\u00f6rscher Str 17-25",
    "sg:city":"Ettlingen",
    "sg:phone":"+49 7243/50590",
    "sg:postcode":"76275",
    "sg:province":"Baden-W\u00fcrttemberg",
    "wof:name":"Tp-cad Gmbh",
    "wof:placetype":"venue"
},
  "geometry": {"coordinates":[8.376776,48.948441],"type":"Point"}
}