{
  "type": "Feature",
  "properties": {
    "iso:country":"DE",
    "sg:address":"Kirchplatz 3",
    "sg:city":"Berg",
    "sg:phone":"+49 9189/288",
    "sg:postcode":"92348",
    "sg:province":"Bayern",
    "wof:name":"M. Fuchs",
    "wof:placetype":"venue"
},
  "geometry": {"coordinates":[11.4372701645,49.3842773438],"type":"Point"}
}