{
  "type": "Feature",
  "properties": {
    "iso:country":"DE",
    "sg:address":"Am Friedhof 6",
    "sg:city":"Gersheim",
    "sg:phone":"+49 6843/8732",
    "sg:postcode":"66453",
    "sg:province":"Saarland",
    "wof:name":"Michael Schmitt",
    "wof:placetype":"venue"
},
  "geometry": {"coordinates":[7.2037620544,49.1729507446],"type":"Point"}
}