{
  "type": "Feature",
  "properties": {
    "iso:country":"DE",
    "sg:address":"Nordstr. 12",
    "sg:city":"Wunstorf",
    "sg:phone":"+49 5031/4554",
    "sg:postcode":"31515",
    "sg:province":"Niedersachsen",
    "wof:name":"Wilhelm K\u00e4hler",
    "wof:placetype":"venue"
},
  "geometry": {"coordinates":[9.427445,52.426567],"type":"Point"}
}