{
  "type": "Feature",
  "properties": {
    "iso:country":"DE",
    "sg:address":"Ludwig-Rinn-Str. 15",
    "sg:city":"Lohra",
    "sg:postcode":"35102",
    "sg:province":"Hessen",
    "wof:name":"Kvs K\u00e4lte- Vakuum- Steuerungstechnik Gmbh",
    "wof:placetype":"venue"
},
  "geometry": {"coordinates":[8.626858,50.738762],"type":"Point"}
}