{
  "type": "Feature",
  "properties": {
    "iso:country":"DE",
    "sg:address":"Am Ro\u00dfberg 29",
    "sg:city":"Braunfels",
    "sg:phone":"+49 6442/22360",
    "sg:postcode":"35619",
    "sg:province":"Hessen",
    "wof:name":"W. Auriga Architekt",
    "wof:placetype":"venue"
},
  "geometry": {"coordinates":[8.4206,50.50108],"type":"Point"}
}