{
  "type": "Feature",
  "properties": {
    "iso:country":"DE",
    "sg:address":"Europastr. 14",
    "sg:city":"Hemer",
    "sg:phone":"+49 2372/62551",
    "sg:postcode":"58675",
    "sg:province":"Nordrhein-Westfalen",
    "wof:name":"H.-p. Amelung",
    "wof:placetype":"venue"
},
  "geometry": {"coordinates":[7.797669,51.38065],"type":"Point"}
}