{
  "type": "Feature",
  "properties": {
    "iso:country":"DE",
    "sg:address":"Hans-vom-Stein-Str. 15",
    "sg:city":"Oberg\u00fcnzburg",
    "sg:phone":"+49 8372/2179",
    "sg:postcode":"87634",
    "sg:province":"Bayern",
    "wof:name":"Willi Steinhauser",
    "wof:placetype":"venue"
},
  "geometry": {"coordinates":[10.4248313904,47.8541526794],"type":"Point"}
}