{
  "type": "Feature",
  "properties": {
    "iso:country":"DE",
    "sg:address":"Theodor-K\u00f6rner-Str. 35 a",
    "sg:city":"Taucha",
    "sg:phone":"+49 34298/34590",
    "sg:postcode":"04425",
    "sg:province":"Sachsen",
    "wof:name":"Wohnungsverwaltung",
    "wof:placetype":"venue"
},
  "geometry": {"coordinates":[12.4838066101,51.3725891113],"type":"Point"}
}