{
  "type": "Feature",
  "properties": {
    "iso:country":"DE",
    "sg:address":"Schmiedestr. 9a",
    "sg:city":"Lengenbostel",
    "sg:postcode":"27419",
    "sg:province":"Niedersachsen",
    "wof:name":"Sbs Containerservice Gmbh",
    "wof:placetype":"venue"
},
  "geometry": {"coordinates":[9.505536,53.300316],"type":"Point"}
}