{
  "type": "Feature",
  "properties": {
    "iso:country":"DE",
    "sg:address":"N\u00f6rdliche Hauptstr. 13",
    "sg:city":"Rottach-Egern",
    "sg:phone":"+49 8022/26719",
    "sg:postcode":"83700",
    "sg:province":"Bayern",
    "wof:name":"B\u00e4rmann",
    "wof:placetype":"venue"
},
  "geometry": {"coordinates":[11.7703361511,47.6917915344],"type":"Point"}
}