{
  "type": "Feature",
  "properties": {
    "iso:country":"DE",
    "sg:address":"S\u00fcrther Hauptstr. 73",
    "sg:city":"K\u00f6ln",
    "sg:phone":"+49 2236/68222",
    "sg:postcode":"50999",
    "sg:province":"Nordrhein-Westfalen",
    "wof:name":"Rheinbogen-apotheke Plangemann E. K.",
    "wof:placetype":"venue"
},
  "geometry": {"coordinates":[7.008305,50.862629],"type":"Point"}
}