{
  "type": "Feature",
  "properties": {
    "iso:country":"DE",
    "sg:address":"Alte K\u00f6nigsseer Strasse 51",
    "sg:city":"Sch\u00f6nau am K\u00f6nigssee",
    "sg:postcode":"83471",
    "sg:province":"Bayern",
    "wof:name":"Kindergarten Sch\u00f6nau Am K\u00f6nigssee",
    "wof:placetype":"venue"
},
  "geometry": {"coordinates":[12.995543,47.603863],"type":"Point"}
}