{
  "type": "Feature",
  "properties": {
    "iso:country":"DE",
    "sg:address":"Rollnerstr. 14",
    "sg:city":"N\u00fcrnberg",
    "sg:postcode":"90408",
    "sg:province":"Bayern",
    "wof:name":"Sca Packaging Deutschland Logistics Gmbh",
    "wof:placetype":"venue"
},
  "geometry": {"coordinates":[11.082452774,49.4601097107],"type":"Point"}
}