{
  "type": "Feature",
  "properties": {
    "iso:country":"DE",
    "sg:address":"Auf der Heide 58",
    "sg:city":"Weiskirchen",
    "sg:phone":"+49 6876/7357",
    "sg:postcode":"66709",
    "sg:province":"Saarland",
    "wof:name":"I. Kautenburger",
    "wof:placetype":"venue"
},
  "geometry": {"coordinates":[6.8236718178,49.5545005798],"type":"Point"}
}