{
  "type": "Feature",
  "properties": {
    "iso:country":"DE",
    "sg:address":"Hohenrenner Weg 5",
    "sg:city":"Blomberg",
    "sg:phone":"+49 5235/7177",
    "sg:postcode":"32825",
    "sg:province":"Nordrhein-Westfalen",
    "wof:name":"Adria-restaurant",
    "wof:placetype":"venue"
},
  "geometry": {"coordinates":[9.0967321396,51.9446792603],"type":"Point"}
}