{
  "type": "Feature",
  "properties": {
    "iso:country":"DE",
    "sg:address":"Schulstr. 9",
    "sg:city":"Titz",
    "sg:postcode":"52445",
    "sg:province":"Nordrhein-Westfalen",
    "wof:name":"D & F Massivhaus Gmbh",
    "wof:placetype":"venue"
},
  "geometry": {"coordinates":[6.4280819893,51.0030403137],"type":"Point"}
}