{
  "type": "Feature",
  "properties": {
    "iso:country":"DE",
    "sg:address":"Homburger Landstr. 120",
    "sg:city":"Frankfurt",
    "sg:phone":"+49 69/541736",
    "sg:postcode":"60435",
    "sg:province":"Hessen",
    "wof:name":"Delphin-apotheke Inh. Christoph Howitz",
    "wof:placetype":"venue"
},
  "geometry": {"coordinates":[8.691479,50.150658],"type":"Point"}
}