{
  "type": "Feature",
  "properties": {
    "iso:country":"DE",
    "sg:address":"Weinberg 24",
    "sg:city":"Hildesheim",
    "sg:phone":"+49 5121/869400",
    "sg:postcode":"31134",
    "sg:province":"Niedersachsen",
    "wof:name":"Klaus Montag Garten-u. Landschaftsarchitekt",
    "wof:placetype":"venue"
},
  "geometry": {"coordinates":[9.954726,52.139896],"type":"Point"}
}