{
  "type": "Feature",
  "properties": {
    "iso:country":"DE",
    "sg:address":"Gabelsbergerstr 9",
    "sg:city":"Ilmenau",
    "sg:phone":"+49 3677/666777",
    "sg:postcode":"98693",
    "sg:province":"Th\u00fcringen",
    "wof:name":"S & T Systemtechnik Gmbh",
    "wof:placetype":"venue"
},
  "geometry": {"coordinates":[10.915475,50.681301],"type":"Point"}
}