{
  "type": "Feature",
  "properties": {
    "iso:country":"DE",
    "sg:address":"Ziegelh\u00fcttenstr. 50",
    "sg:city":"Riedlingen",
    "sg:phone":"+49 7371/10373",
    "sg:postcode":"88499",
    "sg:province":"Baden-W\u00fcrttemberg",
    "wof:name":"Pizzaservice Alfonsos",
    "wof:placetype":"venue"
},
  "geometry": {"coordinates":[9.475381,48.158981],"type":"Point"}
}