{
  "type": "Feature",
  "properties": {
    "iso:country":"DE",
    "sg:address":"Niehler Stra\u00dfe 3e",
    "sg:city":"K\u00f6ln",
    "sg:phone":"+49 221/9727060",
    "sg:postcode":"50670",
    "sg:province":"Nordrhein-Westfalen",
    "wof:name":"Udo L\u00fccke Unternehmensberatung",
    "wof:placetype":"venue"
},
  "geometry": {"coordinates":[6.957467,50.956829],"type":"Point"}
}