{
  "type": "Feature",
  "properties": {
    "iso:country":"DE",
    "sg:address":"Blutenburgstr. 64",
    "sg:city":"M\u00fcnchen",
    "sg:phone":"+49 89/1292263",
    "sg:postcode":"80636",
    "sg:province":"Bayern",
    "wof:name":"Barbara Kleiber-wurm",
    "wof:placetype":"venue"
},
  "geometry": {"coordinates":[11.543751,48.149311],"type":"Point"}
}