{
  "type": "Feature",
  "properties": {
    "iso:country":"DE",
    "sg:address":"Enhofer Str. 47 Ot Wilflingen",
    "sg:city":"Langenenslingen",
    "sg:phone":"+49 4973/7696200",
    "sg:postcode":"88515",
    "sg:province":"Baden-W\u00fcrttemberg",
    "wof:name":"Rumpel Pr\u00c4zionstechnik",
    "wof:placetype":"venue"
},
  "geometry": {"coordinates":[9.37874,48.148491],"type":"Point"}
}