{
  "type": "Feature",
  "properties": {
    "iso:country":"DE",
    "sg:address":"Kapellenweg 4",
    "sg:city":"Bickenriede",
    "sg:postcode":"99976",
    "sg:province":"Th\u00fcringen",
    "wof:name":"Enertronic Gmbh",
    "wof:placetype":"venue"
},
  "geometry": {"coordinates":[10.329281,51.258678],"type":"Point"}
}