{
  "type": "Feature",
  "properties": {
    "iso:country":"DE",
    "sg:address":"Hauptstr. 37",
    "sg:city":"Bruchk\u00f6bel",
    "sg:phone":"+49 6181/76242",
    "sg:postcode":"63486",
    "sg:province":"Hessen",
    "wof:name":"M. M\u00fcller",
    "wof:placetype":"venue"
},
  "geometry": {"coordinates":[8.9174976349,50.1781387329],"type":"Point"}
}