{
  "type": "Feature",
  "properties": {
    "iso:country":"DE",
    "sg:address":"L\u00fcttgenr\u00f6der Str 6",
    "sg:city":"Osterwieck",
    "sg:phone":"+49 39421/88930",
    "sg:postcode":"38835",
    "sg:province":"Sachsen-Anhalt",
    "wof:name":"Druckluft-krenge Gmbh",
    "wof:placetype":"venue"
},
  "geometry": {"coordinates":[10.700015,51.966991],"type":"Point"}
}