{
  "type": "Feature",
  "properties": {
    "iso:country":"DE",
    "sg:address":"Gewerbestr. 7",
    "sg:city":"Varel",
    "sg:postcode":"26316",
    "sg:province":"Niedersachsen",
    "wof:name":"Scholz Beteiligungs Gmbh",
    "wof:placetype":"venue"
},
  "geometry": {"coordinates":[8.116113,53.398163],"type":"Point"}
}