{
  "type": "Feature",
  "properties": {
    "iso:country":"DE",
    "sg:address":"Daimlerstr. 71",
    "sg:city":"Hamburg",
    "sg:postcode":"22761",
    "sg:province":"Hamburg",
    "wof:name":"Von Meyer Gmbh & Co. Kg",
    "wof:placetype":"venue"
},
  "geometry": {"coordinates":[9.919762,53.561611],"type":"Point"}
}