{
  "type": "Feature",
  "properties": {
    "iso:country":"DE",
    "sg:address":"Luxemburger Str. 86",
    "sg:city":"K\u00f6ln",
    "sg:phone":"+49 221/445620",
    "sg:postcode":"50674",
    "sg:province":"Nordrhein-Westfalen",
    "wof:name":"Achim Zimmermann",
    "wof:placetype":"venue"
},
  "geometry": {"coordinates":[6.9373521805,50.9254264832],"type":"Point"}
}