{
  "type": "Feature",
  "properties": {
    "iso:country":"DE",
    "sg:address":"Marktplatz 6",
    "sg:city":"Winnweiler",
    "sg:phone":"+49 6302/2017",
    "sg:postcode":"67722",
    "sg:province":"Rheinland-Pfalz",
    "wof:name":"Hauswirtschaft Bischoff",
    "wof:placetype":"venue"
},
  "geometry": {"coordinates":[7.8527059555,49.5679626465],"type":"Point"}
}