{
  "type": "Feature",
  "properties": {
    "iso:country":"DE",
    "sg:address":"Vogelsbergstr. 14a",
    "sg:city":"Steinau",
    "sg:phone":"+49 6663/7766",
    "sg:postcode":"36396",
    "sg:province":"Hessen",
    "wof:name":"Pizzeria Adria",
    "wof:placetype":"venue"
},
  "geometry": {"coordinates":[9.4625597,50.3184738159],"type":"Point"}
}