{
  "type": "Feature",
  "properties": {
    "iso:country":"DE",
    "sg:address":"Rheing\u00f6nheimer Str. 62",
    "sg:city":"Ludwigshafen",
    "sg:phone":"+49 621/574668",
    "sg:postcode":"67065",
    "sg:province":"Rheinland-Pfalz",
    "wof:name":"Wolfgang Hoffmann",
    "wof:placetype":"venue"
},
  "geometry": {"coordinates":[8.4277200699,49.4591026306],"type":"Point"}
}