{
  "type": "Feature",
  "properties": {
    "iso:country":"DE",
    "sg:address":"Lauerweg 12",
    "sg:city":"Heilbronn",
    "sg:phone":"+49 7131/177226",
    "sg:postcode":"74076",
    "sg:province":"Baden-W\u00fcrttemberg",
    "wof:name":"Hechenberger Gmbh",
    "wof:placetype":"venue"
},
  "geometry": {"coordinates":[9.2114925385,49.1452217102],"type":"Point"}
}