{
  "type": "Feature",
  "properties": {
    "iso:country":"DE",
    "sg:address":"Augustenstr. 46",
    "sg:city":"M\u00fcnchen",
    "sg:phone":"+49 89/1786360",
    "sg:postcode":"80333",
    "sg:province":"Bayern",
    "wof:name":"Diehl Glaeser Und Partner Patentanw\u00e4lte",
    "wof:placetype":"venue"
},
  "geometry": {"coordinates":[11.5622758865,48.147819519],"type":"Point"}
}