{
  "type": "Feature",
  "properties": {
    "iso:country":"DE",
    "sg:address":"Maxstr. 8",
    "sg:city":"Berlin",
    "sg:phone":"+49 30/3952294",
    "sg:postcode":"13347",
    "sg:province":"Berlin",
    "wof:name":"Fbm Fladenbrot- D\u00f6ner- Produktion Und",
    "wof:placetype":"venue"
},
  "geometry": {"coordinates":[13.365227,52.549313],"type":"Point"}
}