{
  "type": "Feature",
  "properties": {
    "iso:country":"DE",
    "sg:address":"Martinstr. 7",
    "sg:city":"Hannover",
    "sg:phone":"+49 511/6463439",
    "sg:postcode":"30659",
    "sg:province":"Niedersachsen",
    "wof:name":"Ristorante La Tavernetta",
    "wof:placetype":"venue"
},
  "geometry": {"coordinates":[9.8032503128,52.4114952087],"type":"Point"}
}