{
  "type": "Feature",
  "properties": {
    "iso:country":"DE",
    "sg:address":"Rosenstr. 6",
    "sg:city":"Langenhagen",
    "sg:phone":"+49 511/7242040",
    "sg:postcode":"30853",
    "sg:province":"Niedersachsen",
    "wof:name":"J\u00fcrgen Busch Heilpraktiker",
    "wof:placetype":"venue"
},
  "geometry": {"coordinates":[9.7340154648,52.4434890747],"type":"Point"}
}