{
  "type": "Feature",
  "properties": {
    "iso:country":"DE",
    "sg:address":"Herosestr. 3",
    "sg:city":"Konstanz",
    "sg:phone":"+49 7531/71132",
    "sg:postcode":"78467",
    "sg:province":"Baden-W\u00fcrttemberg",
    "wof:name":"M. Lutz",
    "wof:placetype":"venue"
},
  "geometry": {"coordinates":[9.1571073532,47.6840782166],"type":"Point"}
}