{
  "type": "Feature",
  "properties": {
    "iso:country":"DE",
    "sg:address":"Alaunstr. 41",
    "sg:city":"Dresden",
    "sg:phone":"+49 351/8036767",
    "sg:postcode":"01099",
    "sg:province":"Sachsen",
    "wof:name":"Schau Fuss Andrea Meyer",
    "wof:placetype":"venue"
},
  "geometry": {"coordinates":[13.7510175705,51.0665626526],"type":"Point"}
}