{
  "type": "Feature",
  "properties": {
    "iso:country":"DE",
    "sg:address":"Bayreuther Str. 111",
    "sg:city":"Bad Berneck",
    "sg:phone":"+49 9273/338",
    "sg:postcode":"95460",
    "sg:province":"Bayern",
    "wof:name":"G\u00e4stehaus H. Und Wilma Krasser",
    "wof:placetype":"venue"
},
  "geometry": {"coordinates":[11.6613521576,50.0405693054],"type":"Point"}
}