{
  "type": "Feature",
  "properties": {
    "iso:country":"DE",
    "sg:address":"Annaberger Str. 53",
    "sg:city":"Markersbach",
    "sg:phone":"+49 3774/86129",
    "sg:postcode":"08352",
    "sg:province":"Sachsen",
    "wof:name":"Goldener Hahn Inh. Wolfgang Zahn",
    "wof:placetype":"venue"
},
  "geometry": {"coordinates":[12.8641386032,50.5347557068],"type":"Point"}
}