{
  "type": "Feature",
  "properties": {
    "iso:country":"DE",
    "sg:address":"Schulze-Delitsch-Str. 63",
    "sg:city":"K\u00f6ln",
    "sg:phone":"+49 221",
    "sg:postcode":"50968",
    "sg:province":"Nordrhein-Westfalen",
    "wof:name":"Eduard Mermagen Kraftfahrzeuggutachter",
    "wof:placetype":"venue"
},
  "geometry": {"coordinates":[6.951239,50.898891],"type":"Point"}
}