{
  "type": "Feature",
  "properties": {
    "iso:country":"DE",
    "sg:address":"Max-M\u00fcller-Str. 31",
    "sg:city":"Hannover",
    "sg:postcode":"30179",
    "sg:province":"Niedersachsen",
    "wof:name":"U. I. Lapp Verm\u00f6gens- Verwaltungs Gmbh & Co. Kg",
    "wof:placetype":"venue"
},
  "geometry": {"coordinates":[9.7505846024,52.4106063843],"type":"Point"}
}