{
  "type": "Feature",
  "properties": {
    "iso:country":"DE",
    "sg:address":"Marktplatz 18",
    "sg:city":"Marktleuthen",
    "sg:phone":"+49 9285/1249",
    "sg:postcode":"95168",
    "sg:province":"Bayern",
    "wof:name":"Schmidt Bank",
    "wof:placetype":"venue"
},
  "geometry": {"coordinates":[11.994385,50.127838],"type":"Point"}
}