{
  "type": "Feature",
  "properties": {
    "iso:country":"DE",
    "sg:address":"Damm 5",
    "sg:city":"Osterwieck",
    "sg:postcode":"38835",
    "sg:province":"Sachsen-Anhalt",
    "wof:name":"Evangelisches Pfarramt Oberpfarre",
    "wof:placetype":"venue"
},
  "geometry": {"coordinates":[10.7118597031,51.9700508118],"type":"Point"}
}