{
  "type": "Feature",
  "properties": {
    "iso:country":"DE",
    "sg:address":"Bad Kreuznacher Str. 38",
    "sg:city":"Mannheim",
    "sg:phone":"+49 621/727060",
    "sg:postcode":"68309",
    "sg:province":"Baden-W\u00fcrttemberg",
    "wof:name":"Engmann K\u00e4ltetechnik Gmbh",
    "wof:placetype":"venue"
},
  "geometry": {"coordinates":[8.525079,49.507046],"type":"Point"}
}