{
  "type": "Feature",
  "properties": {
    "iso:country":"DE",
    "sg:address":"Am Buchholzplatz 10",
    "sg:city":"Braunlage",
    "sg:phone":"+49 5520",
    "sg:postcode":"38700",
    "sg:province":"Niedersachsen",
    "wof:name":"Autohaus R. Peinemann",
    "wof:placetype":"venue"
},
  "geometry": {"coordinates":[10.61627388,51.7199668884],"type":"Point"}
}