{
  "type": "Feature",
  "properties": {
    "iso:country":"DE",
    "sg:address":"Wittenbergstr. 4",
    "sg:city":"Jena",
    "sg:phone":"+49 3641/42700",
    "sg:postcode":"07743",
    "sg:province":"Th\u00fcringen",
    "wof:name":"Siemers Gmbh",
    "wof:placetype":"venue"
},
  "geometry": {"coordinates":[11.573928833,50.9298820496],"type":"Point"}
}