{
  "type": "Feature",
  "properties": {
    "iso:country":"DE",
    "sg:address":"Backnanger Str. 28",
    "sg:city":"Allmersbach",
    "sg:phone":"+49 7191/310474",
    "sg:postcode":"71573",
    "sg:province":"Baden-W\u00fcrttemberg",
    "wof:name":"B. Handel",
    "wof:placetype":"venue"
},
  "geometry": {"coordinates":[9.467599,48.906963],"type":"Point"}
}