{
  "type": "Feature",
  "properties": {
    "iso:country":"DE",
    "sg:address":"Talstr. 9",
    "sg:city":"Wetzlar",
    "sg:phone":"+49 6441/34242",
    "sg:postcode":"35584",
    "sg:province":"Hessen",
    "wof:name":"R. Meissner Kfz-verwertungsunt.",
    "wof:placetype":"venue"
},
  "geometry": {"coordinates":[8.5197906494,50.5806617737],"type":"Point"}
}