{
  "type": "Feature",
  "properties": {
    "iso:country":"DE",
    "sg:address":"Am Stadtwald 5",
    "sg:city":"Delitzsch",
    "sg:postcode":"04509",
    "sg:province":"Sachsen",
    "wof:name":"Dr. Med. Helmut Stietzel",
    "wof:placetype":"venue"
},
  "geometry": {"coordinates":[12.358869,51.530857],"type":"Point"}
}