{
  "type": "Feature",
  "properties": {
    "iso:country":"DE",
    "sg:address":"M\u00e4lzerstr. 3",
    "sg:city":"Gro\u00dfaitingen",
    "sg:phone":"+49 8203/1659",
    "sg:postcode":"86845",
    "sg:province":"Bayern",
    "wof:name":"F. Wittmann",
    "wof:placetype":"venue"
},
  "geometry": {"coordinates":[10.801504,48.223606],"type":"Point"}
}