{
  "type": "Feature",
  "properties": {
    "iso:country":"DE",
    "sg:address":"Reutbergstr. 34",
    "sg:city":"Gunzenhausen",
    "sg:phone":"+49 9831/67810",
    "sg:postcode":"91710",
    "sg:province":"Bayern",
    "wof:name":"Zweckverband Reckenberg Gruppe",
    "wof:placetype":"venue"
},
  "geometry": {"coordinates":[10.7639455795,49.1101989746],"type":"Point"}
}