{
  "type": "Feature",
  "properties": {
    "iso:country":"DE",
    "sg:address":"Nidacorso 9",
    "sg:city":"Frankfurt",
    "sg:phone":"+49 69/571189",
    "sg:postcode":"60439",
    "sg:province":"Hessen",
    "wof:name":"Zoohaus G. Haindl",
    "wof:placetype":"venue"
},
  "geometry": {"coordinates":[8.633472,50.157192],"type":"Point"}
}