{
  "type": "Feature",
  "properties": {
    "iso:country":"DE",
    "sg:address":"Sandhagen 15",
    "sg:city":"Bielefeld",
    "sg:phone":"+49 521/142281",
    "sg:postcode":"33617",
    "sg:province":"Nordrhein-Westfalen",
    "wof:name":"B. Lippert",
    "wof:placetype":"venue"
},
  "geometry": {"coordinates":[8.5163326263,52.0083084106],"type":"Point"}
}