{
  "type": "Feature",
  "properties": {
    "iso:country":"DE",
    "sg:address":"Markt 5",
    "sg:city":"Blankenburg",
    "sg:phone":"+49 3944/2614",
    "sg:postcode":"38889",
    "sg:province":"Sachsen-Anhalt",
    "wof:name":"China Restaurant Peking",
    "wof:placetype":"venue"
},
  "geometry": {"coordinates":[10.9548616409,51.7885627747],"type":"Point"}
}