{
  "type": "Feature",
  "properties": {
    "iso:country":"DE",
    "sg:address":"Mannheimer Str. 13",
    "sg:city":"M\u00fcnchen",
    "sg:phone":"+49 89/4363644",
    "sg:postcode":"80803",
    "sg:province":"Bayern",
    "wof:name":"B. B. Blank Immobilienmakler",
    "wof:placetype":"venue"
},
  "geometry": {"coordinates":[11.5845537186,48.1662979126],"type":"Point"}
}