{
  "type": "Feature",
  "properties": {
    "iso:country":"DE",
    "sg:address":"Im Riepen 15",
    "sg:city":"Medebach",
    "sg:phone":"+49 5632/5296",
    "sg:postcode":"59964",
    "sg:province":"Nordrhein-Westfalen",
    "wof:name":"Karl Asmuth",
    "wof:placetype":"venue"
},
  "geometry": {"coordinates":[8.6930904388,51.2635498047],"type":"Point"}
}