{
  "type": "Feature",
  "properties": {
    "iso:country":"DE",
    "sg:address":"Kufsteiner Str. 44",
    "sg:city":"Raubling",
    "sg:phone":"+49 8035/2522",
    "sg:postcode":"83064",
    "sg:province":"Bayern",
    "wof:name":"Georg Eberl Elektroinstallation",
    "wof:placetype":"venue"
},
  "geometry": {"coordinates":[12.107863,47.778515],"type":"Point"}
}