{
  "type": "Feature",
  "properties": {
    "iso:country":"DE",
    "sg:address":"Bielefelder Str. 42",
    "sg:city":"Steinhagen",
    "sg:phone":"+49 5204/920725",
    "sg:postcode":"33803",
    "sg:province":"Nordrhein-Westfalen",
    "wof:name":"Gebr Schmidt Maschinenbau Gmbh",
    "wof:placetype":"venue"
},
  "geometry": {"coordinates":[8.426767,52.008141],"type":"Point"}
}