{
  "type": "Feature",
  "properties": {
    "iso:country":"DE",
    "sg:address":"Lange Str. 26",
    "sg:city":"G\u00f6ppingen",
    "sg:phone":"+49 7161/73563",
    "sg:postcode":"73033",
    "sg:province":"Baden-W\u00fcrttemberg",
    "wof:name":"Konditorei-caf\u00e9 Berner Inh. Mathias Bidlingmaier E.k.",
    "wof:placetype":"venue"
},
  "geometry": {"coordinates":[9.6522130966,48.702999115],"type":"Point"}
}