{
  "type": "Feature",
  "properties": {
    "iso:country":"DE",
    "sg:address":"Hauptstr. 6",
    "sg:city":"Bedburg",
    "sg:phone":"+49 2272/2397",
    "sg:postcode":"50181",
    "sg:province":"Nordrhein-Westfalen",
    "wof:name":"Hirsch-antiquit\u00e4ten Gmbh",
    "wof:placetype":"venue"
},
  "geometry": {"coordinates":[6.557851,51.009678],"type":"Point"}
}