{
  "type": "Feature",
  "properties": {
    "iso:country":"DE",
    "sg:address":"Hatzper Str. 223",
    "sg:city":"Essen",
    "sg:postcode":"45149",
    "sg:province":"Nordrhein-Westfalen",
    "wof:name":"Schwering Immobilien Gmbh",
    "wof:placetype":"venue"
},
  "geometry": {"coordinates":[6.9550719261,51.4210548401],"type":"Point"}
}