{
  "type": "Feature",
  "properties": {
    "iso:country":"DE",
    "sg:address":"Bergstr. 27",
    "sg:city":"Pforzheim",
    "sg:phone":"+49 7231/922320",
    "sg:postcode":"75173",
    "sg:province":"Baden-W\u00fcrttemberg",
    "wof:name":"Adserv Gmbh",
    "wof:placetype":"venue"
},
  "geometry": {"coordinates":[8.6918001175,48.8875770569],"type":"Point"}
}