{
  "type": "Feature",
  "properties": {
    "iso:country":"DE",
    "sg:address":"Kloppstr. 20",
    "sg:city":"Schmelz",
    "sg:phone":"+49 6887/2969",
    "sg:postcode":"66839",
    "sg:province":"Saarland",
    "wof:name":"Alois Koch Gmbh",
    "wof:placetype":"venue"
},
  "geometry": {"coordinates":[6.896628,49.474949],"type":"Point"}
}