{
  "type": "Feature",
  "properties": {
    "iso:country":"DE",
    "sg:address":"Coburger Str. 38",
    "sg:city":"Eisfeld",
    "sg:phone":"+49 3686/322088",
    "sg:postcode":"98673",
    "sg:province":"Th\u00fcringen",
    "wof:name":"Thomas Schmidt",
    "wof:placetype":"venue"
},
  "geometry": {"coordinates":[10.9100427628,50.4191589355],"type":"Point"}
}