{
  "type": "Feature",
  "properties": {
    "iso:country":"DE",
    "sg:address":"Neust\u00e4dter Str. 18",
    "sg:city":"Titisee-Neustadt",
    "sg:phone":"+49 7651/8374",
    "sg:postcode":"79822",
    "sg:province":"Baden-W\u00fcrttemberg",
    "wof:name":"G\u00f6tz & Moriz Besitz Gmbh & Co.",
    "wof:placetype":"venue"
},
  "geometry": {"coordinates":[8.1571826935,47.9055252075],"type":"Point"}
}