{
  "type": "Feature",
  "properties": {
    "iso:country":"DE",
    "sg:address":"Spielbach 19",
    "sg:city":"Schrozberg",
    "sg:phone":"+49 7939/461",
    "sg:postcode":"74575",
    "sg:province":"Baden-W\u00fcrttemberg",
    "wof:name":"Fritz Unbehauen Brauerei Spielbach",
    "wof:placetype":"venue"
},
  "geometry": {"coordinates":[10.067948,49.385399],"type":"Point"}
}