{
  "type": "Feature",
  "properties": {
    "iso:country":"DE",
    "sg:address":"Grasweg 1",
    "sg:city":"Heidelberg",
    "sg:phone":"+49 6221/785493",
    "sg:postcode":"69124",
    "sg:province":"Baden-W\u00fcrttemberg",
    "wof:name":"Rolf Jost",
    "wof:placetype":"venue"
},
  "geometry": {"coordinates":[8.63202,49.378304],"type":"Point"}
}