{
  "type": "Feature",
  "properties": {
    "iso:country":"DE",
    "sg:address":"Gro\u00df-Lunow 28",
    "sg:city":"Boddin",
    "sg:phone":"+49 39971/12197",
    "sg:postcode":"17179",
    "sg:province":"Mecklenburg-Vorpommern",
    "wof:name":"Agrargen. Eg Boddin",
    "wof:placetype":"venue"
},
  "geometry": {"coordinates":[12.646363,53.923286],"type":"Point"}
}