{
  "type": "Feature",
  "properties": {
    "iso:country":"DE",
    "sg:address":"Plan 12",
    "sg:city":"Wenigenlupnitz",
    "sg:postcode":"99819",
    "sg:province":"Th\u00fcringen",
    "wof:name":"M\u00f6bel Cranz & Sch\u00e4fer Ohg",
    "wof:placetype":"venue"
},
  "geometry": {"coordinates":[10.2028627396,50.9129257202],"type":"Point"}
}