{
  "type": "Feature",
  "properties": {
    "iso:country":"DE",
    "sg:address":"Gewerbegebiet Nord 6",
    "sg:city":"Prenzlau",
    "sg:phone":"+49 3984/87010",
    "sg:postcode":"17291",
    "sg:province":"Brandenburg",
    "wof:name":"Wolff & Partner Gmbh",
    "wof:placetype":"venue"
},
  "geometry": {"coordinates":[13.8797225952,53.3497428894],"type":"Point"}
}