{
  "type": "Feature",
  "properties": {
    "iso:country":"DE",
    "sg:address":"Lehmweg 7",
    "sg:city":"Holm",
    "sg:phone":"+49 4941/034221",
    "sg:postcode":"25488",
    "sg:province":"Schleswig-Holstein",
    "wof:name":"R\u00d6pke & R\u00d6pke Gmbh",
    "wof:placetype":"venue"
},
  "geometry": {"coordinates":[9.6747455597,53.6230392456],"type":"Point"}
}