{
  "type": "Feature",
  "properties": {
    "iso:country":"DE",
    "sg:address":"Grabenstr. 6",
    "sg:city":"Heinsberg",
    "sg:phone":"+49 2452/64680",
    "sg:postcode":"52525",
    "sg:province":"Nordrhein-Westfalen",
    "wof:name":"Willi Kleinen",
    "wof:placetype":"venue"
},
  "geometry": {"coordinates":[6.1486449242,51.0415344238],"type":"Point"}
}