{
  "type": "Feature",
  "properties": {
    "iso:country":"DE",
    "sg:address":"Kirchhofstr. 27",
    "sg:city":"Sch\u00f6nwalde",
    "sg:phone":"+49 35474/685",
    "sg:postcode":"15910",
    "sg:province":"Brandenburg",
    "wof:name":"Horst Liebig",
    "wof:placetype":"venue"
},
  "geometry": {"coordinates":[13.764624,51.97821],"type":"Point"}
}