{
  "type": "Feature",
  "properties": {
    "iso:country":"DE",
    "sg:address":"Pfarrer-Kneipp-Str. 19",
    "sg:city":"Mandelbachtal",
    "sg:phone":"+49 6893/2102",
    "sg:postcode":"66399",
    "sg:province":"Saarland",
    "wof:name":"T. Thinnes",
    "wof:placetype":"venue"
},
  "geometry": {"coordinates":[7.146635,49.199276],"type":"Point"}
}