{
  "type": "Feature",
  "properties": {
    "iso:country":"DE",
    "sg:address":"F\u00fcssener Str. 11",
    "sg:city":"Schwangau",
    "sg:phone":"+49 8362/98230",
    "sg:postcode":"87645",
    "sg:province":"Bayern",
    "wof:name":"Lextel Office Shop Erika Mayerhofer",
    "wof:placetype":"venue"
},
  "geometry": {"coordinates":[10.731698,47.573738],"type":"Point"}
}