{
  "type": "Feature",
  "properties": {
    "iso:country":"DE",
    "sg:address":"Sandstr. 3",
    "sg:city":"Wachtberg",
    "sg:postcode":"53343",
    "sg:province":"Nordrhein-Westfalen",
    "wof:name":"Von W\u00fclfing Gmbh",
    "wof:placetype":"venue"
},
  "geometry": {"coordinates":[7.135614,50.625813],"type":"Point"}
}