{
  "type": "Feature",
  "properties": {
    "iso:country":"DE",
    "sg:address":"Taubeng\u00e4\u00dfchen 3",
    "sg:city":"Regensburg",
    "sg:postcode":"93047",
    "sg:province":"Bayern",
    "wof:name":"Vital Fitne\u00df- Und Gesundheits- Zentrum Am Comeniusberg Gmbh",
    "wof:placetype":"venue"
},
  "geometry": {"coordinates":[12.0973377228,49.0205383301],"type":"Point"}
}