{
  "type": "Feature",
  "properties": {
    "iso:country":"DE",
    "sg:address":"M\u00fchlenstr. 14",
    "sg:city":"L\u00f6bau",
    "sg:phone":"+49 3585/402220",
    "sg:postcode":"02708",
    "sg:province":"Sachsen",
    "wof:name":"Christian Sch\u00f6nlein",
    "wof:placetype":"venue"
},
  "geometry": {"coordinates":[14.669376,51.092102],"type":"Point"}
}