{
  "type": "Feature",
  "properties": {
    "iso:country":"DE",
    "sg:address":"Vockerter Str. 26",
    "sg:city":"Solingen",
    "sg:phone":"+49 212/811446",
    "sg:postcode":"42657",
    "sg:province":"Nordrhein-Westfalen",
    "wof:name":"Elsterklause",
    "wof:placetype":"venue"
},
  "geometry": {"coordinates":[7.0792951584,51.1494026184],"type":"Point"}
}