{
  "type": "Feature",
  "properties": {
    "iso:country":"DE",
    "sg:address":"Rappenfeldstr. 4",
    "sg:city":"Monheim",
    "sg:phone":"+49 9091/50000",
    "sg:postcode":"86653",
    "sg:province":"Bayern",
    "wof:name":"Mkr Metzger Gmbh & Co. Kg",
    "wof:placetype":"venue"
},
  "geometry": {"coordinates":[10.8367938995,48.8438072205],"type":"Point"}
}