{
  "type": "Feature",
  "properties": {
    "iso:country":"DE",
    "sg:address":"Neuenkirchener Str. 39",
    "sg:city":"Neubrandenburg",
    "sg:phone":"+49 395/4226328",
    "sg:postcode":"17034",
    "sg:province":"Mecklenburg-Vorpommern",
    "wof:name":"Traba Gmbh",
    "wof:placetype":"venue"
},
  "geometry": {"coordinates":[13.275654,53.565506],"type":"Point"}
}