{
  "type": "Feature",
  "properties": {
    "iso:country":"DE",
    "sg:address":"Leipziger Str 242",
    "sg:city":"Kassel",
    "sg:phone":"+49 561/500430",
    "sg:postcode":"34123",
    "sg:province":"Hessen",
    "wof:name":"Cfb",
    "wof:placetype":"venue"
},
  "geometry": {"coordinates":[9.539977,51.297035],"type":"Point"}
}