{
  "type": "Feature",
  "properties": {
    "iso:country":"DE",
    "sg:address":"Theodor-von-Zahn 25",
    "sg:city":"Erlangen",
    "sg:phone":"+49 9131/49386",
    "sg:postcode":"91052",
    "sg:province":"Bayern",
    "wof:name":"Wolfrum Kommunikationslogik - D-erlangen",
    "wof:placetype":"venue"
},
  "geometry": {"coordinates":[11.0188694,49.5914497375],"type":"Point"}
}