{
  "type": "Feature",
  "properties": {
    "iso:country":"DE",
    "sg:address":"Bohlweg 11",
    "sg:city":"Salzgitter",
    "sg:phone":"+49 5341/811113",
    "sg:postcode":"38259",
    "sg:province":"Niedersachsen",
    "wof:name":"Ms-reisen-toto-lotto",
    "wof:placetype":"venue"
},
  "geometry": {"coordinates":[10.3740139008,52.0495147705],"type":"Point"}
}