{
  "type": "Feature",
  "properties": {
    "iso:country":"DE",
    "sg:address":"Stettbachstr. 10",
    "sg:city":"Jengen",
    "sg:phone":"+49 8241/910875",
    "sg:postcode":"86860",
    "sg:province":"Bayern",
    "wof:name":"Gabriele M\u00fcller Masseurin",
    "wof:placetype":"venue"
},
  "geometry": {"coordinates":[10.70462,47.994991],"type":"Point"}
}