{
  "type": "Feature",
  "properties": {
    "iso:country":"DE",
    "sg:address":"Magdeburger Allee 200",
    "sg:city":"Erfurt",
    "sg:postcode":"99086",
    "sg:province":"Th\u00fcringen",
    "wof:name":"Ammann D\u00f6rflein & Partner Ing.-b\u00fcro Gmbh",
    "wof:placetype":"venue"
},
  "geometry": {"coordinates":[11.0308847427,51.0034408569],"type":"Point"}
}