{
  "type": "Feature",
  "properties": {
    "iso:country":"DE",
    "sg:address":"Hub 2",
    "sg:city":"Wessobrunn",
    "sg:phone":"+49 8809/163106",
    "sg:postcode":"82405",
    "sg:province":"Bayern",
    "wof:name":"Ct Cooperate Trading Handels Gmbh",
    "wof:placetype":"venue"
},
  "geometry": {"coordinates":[11.0312929153,47.8429450989],"type":"Point"}
}