{
  "type": "Feature",
  "properties": {
    "iso:country":"DE",
    "sg:address":"M\u00fcnchnerstr. 113",
    "sg:city":"Unterf\u00f6hring",
    "sg:postcode":"85774",
    "sg:province":"Bayern",
    "wof:name":"Blsg-business And Logistic Systems-ges. F. Unternehmens-",
    "wof:placetype":"venue"
},
  "geometry": {"coordinates":[11.6462993622,48.1968574524],"type":"Point"}
}