{
  "type": "Feature",
  "properties": {
    "iso:country":"DE",
    "sg:address":"Westliche Zwingergasse 44",
    "sg:city":"Deggendorf",
    "sg:phone":"+49 991/342543",
    "sg:postcode":"94469",
    "sg:province":"Bayern",
    "wof:name":"Weingastst\u00e4tte Bacchuskeller",
    "wof:placetype":"venue"
},
  "geometry": {"coordinates":[12.9605045319,48.8322792053],"type":"Point"}
}