{
  "type": "Feature",
  "properties": {
    "iso:country":"DE",
    "sg:address":"Maarstr. 16",
    "sg:city":"Schalkenmehren",
    "sg:phone":"+49 6592/2258",
    "sg:postcode":"54552",
    "sg:province":"Rheinland-Pfalz",
    "wof:name":"B\u00e4ckerei-cafe Bernhard Lenerz",
    "wof:placetype":"venue"
},
  "geometry": {"coordinates":[6.857909,50.166283],"type":"Point"}
}