{
  "type": "Feature",
  "properties": {
    "iso:country":"DE",
    "sg:address":"Grafenstr. 9",
    "sg:city":"Gro\u00dferlach",
    "sg:phone":"+49 7903/833",
    "sg:postcode":"71577",
    "sg:province":"Baden-W\u00fcrttemberg",
    "wof:name":"H. Griese",
    "wof:placetype":"venue"
},
  "geometry": {"coordinates":[9.5131969452,49.0508384705],"type":"Point"}
}