{
  "type": "Feature",
  "properties": {
    "iso:country":"DE",
    "sg:address":"Bundesstr. 36",
    "sg:city":"Hechingen",
    "sg:phone":"+49 7477/1624",
    "sg:postcode":"72379",
    "sg:province":"Baden-W\u00fcrttemberg",
    "wof:name":"D. Staffa",
    "wof:placetype":"venue"
},
  "geometry": {"coordinates":[9.025349,48.344269],"type":"Point"}
}