{
  "type": "Feature",
  "properties": {
    "iso:country":"DE",
    "sg:address":"Roter Sand 9",
    "sg:city":"Wertheim",
    "sg:phone":"+49 9342/5042",
    "sg:postcode":"97877",
    "sg:province":"Baden-W\u00fcrttemberg",
    "wof:name":"Dobslaff Holzbau Gmbh",
    "wof:placetype":"venue"
},
  "geometry": {"coordinates":[9.474319,49.778858],"type":"Point"}
}