{
  "type": "Feature",
  "properties": {
    "iso:country":"DE",
    "sg:address":"Hauptstr. 4",
    "sg:city":"Stockach",
    "sg:phone":"+49 7771/93020",
    "sg:postcode":"78333",
    "sg:province":"Baden-W\u00fcrttemberg",
    "wof:name":"Redaktion Stockacher Zeitung",
    "wof:placetype":"venue"
},
  "geometry": {"coordinates":[9.0121030807,47.851890564],"type":"Point"}
}