{
  "type": "Feature",
  "properties": {
    "iso:country":"DE",
    "sg:address":"Fr\u00fchlingstr. 15",
    "sg:city":"Ergolding",
    "sg:phone":"+49 871/78185",
    "sg:postcode":"84030",
    "sg:province":"Bayern",
    "wof:name":"Lackermeier Gmbh",
    "wof:placetype":"venue"
},
  "geometry": {"coordinates":[12.1754455566,48.5800895691],"type":"Point"}
}