{
  "type": "Feature",
  "properties": {
    "iso:country":"DE",
    "sg:address":"Ankerstr. 9",
    "sg:city":"K\u00f6nigsbach-Stein",
    "sg:phone":"+49 7232/6584",
    "sg:postcode":"75203",
    "sg:province":"Baden-W\u00fcrttemberg",
    "wof:name":"Anker",
    "wof:placetype":"venue"
},
  "geometry": {"coordinates":[8.6116437912,48.9650688171],"type":"Point"}
}