{
  "type": "Feature",
  "properties": {
    "iso:country":"DE",
    "sg:address":"Damaschkeweg 29",
    "sg:city":"Crimmitschau",
    "sg:phone":"+49 3762/3859",
    "sg:postcode":"08451",
    "sg:province":"Sachsen",
    "wof:name":"Erhard Saalfrank",
    "wof:placetype":"venue"
},
  "geometry": {"coordinates":[12.378859,50.825264],"type":"Point"}
}