{
  "type": "Feature",
  "properties": {
    "iso:country":"DE",
    "sg:address":"Webergasse 3",
    "sg:city":"Torgau",
    "sg:phone":"+49 3421/711666",
    "sg:postcode":"04860",
    "sg:province":"Sachsen",
    "wof:name":"K. Wehner",
    "wof:placetype":"venue"
},
  "geometry": {"coordinates":[12.9999370575,51.56016922],"type":"Point"}
}