{
  "type": "Feature",
  "properties": {
    "iso:country":"DE",
    "sg:address":"Wilhelm-Raabe-Str. 4",
    "sg:city":"H\u00f6xter",
    "sg:phone":"+49 5271/380111",
    "sg:postcode":"37671",
    "sg:province":"Nordrhein-Westfalen",
    "wof:name":"Jens Lorenz",
    "wof:placetype":"venue"
},
  "geometry": {"coordinates":[9.4345083237,51.793598175],"type":"Point"}
}