{
  "type": "Feature",
  "properties": {
    "iso:country":"DE",
    "sg:address":"Feldstr. 45",
    "sg:city":"Ahlen",
    "sg:phone":"+49 2382/61214",
    "sg:postcode":"59229",
    "sg:province":"Nordrhein-Westfalen",
    "wof:name":"Anton",
    "wof:placetype":"venue"
},
  "geometry": {"coordinates":[7.9115891457,51.762714386],"type":"Point"}
}