{
  "type": "Feature",
  "properties": {
    "iso:country":"DE",
    "sg:address":"Schwertestr. 16",
    "sg:city":"H\u00f6xter",
    "sg:phone":"+49 5277/514",
    "sg:postcode":"37671",
    "sg:province":"Nordrhein-Westfalen",
    "wof:name":"J. Henneke",
    "wof:placetype":"venue"
},
  "geometry": {"coordinates":[9.317831,51.830879],"type":"Point"}
}