{
  "type": "Feature",
  "properties": {
    "iso:country":"DE",
    "sg:address":"Rheinstr. 20",
    "sg:city":"Duisburg",
    "sg:phone":"+49 203/370629",
    "sg:postcode":"47198",
    "sg:province":"Nordrhein-Westfalen",
    "wof:name":"Prause & R\u00f6der Gmbh",
    "wof:placetype":"venue"
},
  "geometry": {"coordinates":[6.7168650627,51.4535598755],"type":"Point"}
}