{
  "type": "Feature",
  "properties": {
    "iso:country":"DE",
    "sg:address":"Dorfmitte 7a",
    "sg:city":"Gerswalde",
    "sg:phone":"+49 39887/265",
    "sg:postcode":"17268",
    "sg:province":"Brandenburg",
    "wof:name":"A. Gittel",
    "wof:placetype":"venue"
},
  "geometry": {"coordinates":[13.7501688004,53.1701812744],"type":"Point"}
}