{
  "type": "Feature",
  "properties": {
    "iso:country":"DE",
    "sg:address":"Klein Feldhus 8",
    "sg:city":"Rastede",
    "sg:postcode":"26180",
    "sg:province":"Niedersachsen",
    "wof:name":"L\u00fcdeking Papierweiter- Verarbeitung Gmbh",
    "wof:placetype":"venue"
},
  "geometry": {"coordinates":[8.222243309,53.2152023315],"type":"Point"}
}