{
  "type": "Feature",
  "properties": {
    "iso:country":"DE",
    "sg:address":"Hohentorstr. 67-69",
    "sg:city":"Bremen",
    "sg:postcode":"28199",
    "sg:province":"Bremen",
    "wof:name":"Rp Fotosatz Gmbh & Co. Nachf.",
    "wof:placetype":"venue"
},
  "geometry": {"coordinates":[8.7913503647,53.0748710632],"type":"Point"}
}