{
  "type": "Feature",
  "properties": {
    "iso:country":"DE",
    "sg:address":"Uhlandstr. 99",
    "sg:city":"M\u00f6nchengladbach",
    "sg:phone":"+49 2166/80492",
    "sg:postcode":"41238",
    "sg:province":"Nordrhein-Westfalen",
    "wof:name":"Hans J\u00e4ger Kg Heiz\u00f6l-hdl.",
    "wof:placetype":"venue"
},
  "geometry": {"coordinates":[6.48148489,51.1534118652],"type":"Point"}
}