{
  "type": "Feature",
  "properties": {
    "iso:country":"DE",
    "sg:address":"Gutenbergstr. 70",
    "sg:city":"K\u00f6ln",
    "sg:phone":"+49 221/9514770",
    "sg:postcode":"50823",
    "sg:province":"Nordrhein-Westfalen",
    "wof:name":"Hans Linden Bestattungsinstitut",
    "wof:placetype":"venue"
},
  "geometry": {"coordinates":[6.92669,50.949757],"type":"Point"}
}