{
  "type": "Feature",
  "properties": {
    "iso:country":"DE",
    "sg:address":"Siesmayerstr. 5",
    "sg:city":"Frankfurt",
    "sg:phone":"+49 69/751595",
    "sg:postcode":"60323",
    "sg:province":"Hessen",
    "wof:name":"Dora Feyer Dolmetscherin Und",
    "wof:placetype":"venue"
},
  "geometry": {"coordinates":[8.659527,50.119503],"type":"Point"}
}