{
  "type": "Feature",
  "properties": {
    "iso:country":"DE",
    "sg:address":"K\u00f6nigsforststr. 81",
    "sg:city":"K\u00f6ln",
    "sg:phone":"+49 221/842759",
    "sg:postcode":"51109",
    "sg:province":"Nordrhein-Westfalen",
    "wof:name":"Wilhelm Marx",
    "wof:placetype":"venue"
},
  "geometry": {"coordinates":[7.088544,50.946747],"type":"Point"}
}