{
  "type": "Feature",
  "properties": {
    "iso:country":"DE",
    "sg:address":"Karl-Diehl-Str.",
    "sg:city":"Nonnweiler",
    "sg:phone":"+49 6873/700",
    "sg:postcode":"66620",
    "sg:province":"Saarland",
    "wof:name":"Karl Diehl Gmbh & Co.",
    "wof:placetype":"venue"
},
  "geometry": {"coordinates":[6.978041172,49.5903282166],"type":"Point"}
}