{
  "type": "Feature",
  "properties": {
    "iso:country":"DE",
    "sg:address":"Vahrenkampstr. 12-16",
    "sg:city":"Kirchlengern",
    "sg:phone":"+49 5223/770",
    "sg:postcode":"32278",
    "sg:province":"Nordrhein-Westfalen",
    "wof:name":"Hettich Maschinentechnik Gmbh & Co. Kg",
    "wof:placetype":"venue"
},
  "geometry": {"coordinates":[8.623304,52.203476],"type":"Point"}
}