{
  "type": "Feature",
  "properties": {
    "iso:country":"DE",
    "sg:address":"Alte Heerstr. 30",
    "sg:city":"Asendorf",
    "sg:phone":"+49 4253/525",
    "sg:postcode":"27330",
    "sg:province":"Niedersachsen",
    "wof:name":"Gastst\u00e4tte Sigrid Burckert",
    "wof:placetype":"venue"
},
  "geometry": {"coordinates":[9.0049734116,52.7723007202],"type":"Point"}
}