{
  "type": "Feature",
  "properties": {
    "iso:country":"DE",
    "sg:address":"Elsa-Br\u00e4ndstr\u00f6m-Str. 203",
    "sg:city":"Halle",
    "sg:phone":"+49 345/4444373",
    "sg:postcode":"06110",
    "sg:province":"Sachsen-Anhalt",
    "wof:name":"Nicolaus Vogt",
    "wof:placetype":"venue"
},
  "geometry": {"coordinates":[11.9710054398,51.4605407715],"type":"Point"}
}