{
  "type": "Feature",
  "properties": {
    "iso:country":"DE",
    "sg:address":"Reifl\u00e4nder Str. 8",
    "sg:city":"Lengefeld",
    "sg:phone":"+49 37367/2490",
    "sg:postcode":"09514",
    "sg:province":"Sachsen",
    "wof:name":"J\u00fcrgen Brachmann Architekt",
    "wof:placetype":"venue"
},
  "geometry": {"coordinates":[13.194877,50.719212],"type":"Point"}
}