{
  "type": "Feature",
  "properties": {
    "iso:country":"DE",
    "sg:address":"Altstadt 216",
    "sg:city":"Landshut",
    "sg:phone":"+49 871/28351",
    "sg:postcode":"84028",
    "sg:province":"Bayern",
    "wof:name":"W. Eller Immobilienmakler",
    "wof:placetype":"venue"
},
  "geometry": {"coordinates":[12.150431633,48.5336952209],"type":"Point"}
}