{
  "type": "Feature",
  "properties": {
    "iso:country":"DE",
    "sg:address":"Br\u00fchlstr. 9",
    "sg:city":"Hannover",
    "sg:postcode":"30169",
    "sg:province":"Niedersachsen",
    "wof:name":"Gbg Bestattungen Zwndl. Der Ahorn-grieneisen",
    "wof:placetype":"venue"
},
  "geometry": {"coordinates":[9.725905,52.37558],"type":"Point"}
}