{
  "type": "Feature",
  "properties": {
    "iso:country":"DE",
    "sg:address":"Finkenstr 1",
    "sg:city":"Garmisch-Partenkirchen",
    "sg:phone":"+49 8821/943070",
    "sg:postcode":"82467",
    "sg:province":"Bayern",
    "wof:name":"Alphaform-claho Gmbh",
    "wof:placetype":"venue"
},
  "geometry": {"coordinates":[11.1001968384,47.5047187805],"type":"Point"}
}