{
  "type": "Feature",
  "properties": {
    "iso:country":"DE",
    "sg:address":"Mainzer Str. 168",
    "sg:city":"Saarbr\u00fccken",
    "sg:phone":"+49 4968/1815067",
    "sg:postcode":"66121",
    "sg:province":"Saarland",
    "wof:name":"Ald Auto Leasing D, Gmbh (saarbr\u00fccken)",
    "wof:placetype":"venue"
},
  "geometry": {"coordinates":[7.025592,49.226055],"type":"Point"}
}