{
  "type": "Feature",
  "properties": {
    "iso:country":"DE",
    "sg:address":"F\u00e4rberstr. 3",
    "sg:city":"Burgdorf",
    "sg:phone":"+49 4951/3688910",
    "sg:postcode":"31303",
    "sg:province":"Niedersachsen",
    "wof:name":"Clou & Classic Gmbh",
    "wof:placetype":"venue"
},
  "geometry": {"coordinates":[10.039467,52.446747],"type":"Point"}
}