{
  "type": "Feature",
  "properties": {
    "iso:country":"DE",
    "sg:address":"Walterscheid 9",
    "sg:city":"Much",
    "sg:phone":"+49 2245/3937",
    "sg:postcode":"53804",
    "sg:province":"Nordrhein-Westfalen",
    "wof:name":"Van Giersbergen & Meurer Gmbh",
    "wof:placetype":"venue"
},
  "geometry": {"coordinates":[7.415395,50.882969],"type":"Point"}
}