{
  "type": "Feature",
  "properties": {
    "iso:country":"DE",
    "sg:address":"Friedrich-Ebert-Allee 61",
    "sg:city":"Schenefeld",
    "sg:phone":"+49 40/8302728",
    "sg:postcode":"22869",
    "sg:province":"Schleswig-Holstein",
    "wof:name":"Manfred K\u00fchn Gmbh",
    "wof:placetype":"venue"
},
  "geometry": {"coordinates":[9.849223,53.608112],"type":"Point"}
}