{
  "type": "Feature",
  "properties": {
    "iso:country":"DE",
    "sg:address":"Ameisenstr. 68",
    "sg:city":"Leipzig",
    "sg:postcode":"04249",
    "sg:province":"Sachsen",
    "wof:name":"Hartmut Polzin",
    "wof:placetype":"venue"
},
  "geometry": {"coordinates":[12.3216485977,51.2967338562],"type":"Point"}
}