{
  "type": "Feature",
  "properties": {
    "iso:country":"DE",
    "sg:address":"B\u00fcrgermeister-Smidt-",
    "sg:city":"Bremerhaven",
    "sg:phone":"+49 471/4822120",
    "sg:postcode":"27568",
    "sg:province":"Bremen",
    "wof:name":"Geestem\u00fcnder Bank Ag",
    "wof:placetype":"venue"
},
  "geometry": {"coordinates":[8.582082,53.544289],"type":"Point"}
}