{
  "type": "Feature",
  "properties": {
    "iso:country":"DE",
    "sg:address":"An den Drei Hasen 34-36",
    "sg:city":"Oberursel",
    "sg:phone":"+49 6171/63300",
    "sg:postcode":"61440",
    "sg:province":"Hessen",
    "wof:name":"Oar Kommunikations- Und Outsourcing-beratungs Gmbh",
    "wof:placetype":"venue"
},
  "geometry": {"coordinates":[8.5973958969,50.2059211731],"type":"Point"}
}