{
  "type": "Feature",
  "properties": {
    "iso:country":"DE",
    "sg:address":"Gr\u00fcner Markt 8",
    "sg:city":"Bamberg",
    "sg:phone":"+49 951/202201",
    "sg:postcode":"96047",
    "sg:province":"Bayern",
    "wof:name":"Albert",
    "wof:placetype":"venue"
},
  "geometry": {"coordinates":[10.888912,49.893238],"type":"Point"}
}