{
  "type": "Feature",
  "properties": {
    "iso:country":"DE",
    "sg:address":"Marienburger Str. 29",
    "sg:city":"Nordhorn",
    "sg:phone":"+49 4959/2197310",
    "sg:postcode":"48529",
    "sg:province":"Niedersachsen",
    "wof:name":"Rosink Gmbh",
    "wof:placetype":"venue"
},
  "geometry": {"coordinates":[7.0768251419,52.4132575989],"type":"Point"}
}