{
  "type": "Feature",
  "properties": {
    "iso:country":"DE",
    "sg:address":"Didierstr 42",
    "sg:city":"Staufenberg",
    "sg:phone":"+49 6406/911510",
    "sg:postcode":"35460",
    "sg:province":"Hessen",
    "wof:name":"Friedrich Zufall Gmbh & Co Kg",
    "wof:placetype":"venue"
},
  "geometry": {"coordinates":[8.74885,50.658791],"type":"Point"}
}