{
  "type": "Feature",
  "properties": {
    "iso:country":"DE",
    "sg:address":"Kammermartinsdobel 10",
    "sg:city":"Lauterbach",
    "sg:phone":"+49 7422/22242",
    "sg:postcode":"78730",
    "sg:province":"Baden-W\u00fcrttemberg",
    "wof:name":"L. Und C. Efinger",
    "wof:placetype":"venue"
},
  "geometry": {"coordinates":[8.3541908264,48.2281265259],"type":"Point"}
}