{
  "type": "Feature",
  "properties": {
    "iso:country":"DE",
    "sg:address":"Laurinweg 15",
    "sg:city":"Ottobrunn",
    "sg:phone":"+49 89/6096835",
    "sg:postcode":"85521",
    "sg:province":"Bayern",
    "wof:name":"Voigt",
    "wof:placetype":"venue"
},
  "geometry": {"coordinates":[11.6638097763,48.0641555786],"type":"Point"}
}