{
  "type": "Feature",
  "properties": {
    "iso:country":"DE",
    "sg:address":"Rehh\u00e4usergasse 6",
    "sg:city":"Wiesentheid",
    "sg:phone":"+49 9383/427",
    "sg:postcode":"97353",
    "sg:province":"Bayern",
    "wof:name":"Anton Maurer",
    "wof:placetype":"venue"
},
  "geometry": {"coordinates":[10.345198,49.793152],"type":"Point"}
}