{
  "type": "Feature",
  "properties": {
    "iso:country":"DE",
    "sg:address":"Bachstr. 17",
    "sg:city":"H\u00f6velhof",
    "sg:phone":"+49 5257/930801",
    "sg:postcode":"33161",
    "sg:province":"Nordrhein-Westfalen",
    "wof:name":"Philipp Roos",
    "wof:placetype":"venue"
},
  "geometry": {"coordinates":[8.6498832703,51.8251838684],"type":"Point"}
}