{
  "type": "Feature",
  "properties": {
    "iso:country":"DE",
    "sg:address":"Buschgasse 25",
    "sg:city":"Br\u00fchl",
    "sg:phone":"+49 2232/932020",
    "sg:postcode":"50321",
    "sg:province":"Nordrhein-Westfalen",
    "wof:name":"J\u00fcrgen J\u00fclich Steuerberater",
    "wof:placetype":"venue"
},
  "geometry": {"coordinates":[6.8876199722,50.8152770996],"type":"Point"}
}