{
  "type": "Feature",
  "properties": {
    "iso:country":"DE",
    "sg:address":"Sch\u00e4fflerring 3",
    "sg:city":"Eggenfelden",
    "sg:phone":"+49 8721/3653",
    "sg:postcode":"84307",
    "sg:province":"Bayern",
    "wof:name":"T. Und Gabriele Thaller",
    "wof:placetype":"venue"
},
  "geometry": {"coordinates":[12.736131,48.403187],"type":"Point"}
}