{
  "type": "Feature",
  "properties": {
    "iso:country":"DE",
    "sg:address":"Osnabr\u00fccker Landstr 270",
    "sg:city":"G\u00fctersloh",
    "sg:phone":"+49 5241/688987",
    "sg:postcode":"33335",
    "sg:province":"Nordrhein-Westfalen",
    "wof:name":"Gt Berufsbekleidung Inh. Bernd Zodrow",
    "wof:placetype":"venue"
},
  "geometry": {"coordinates":[8.4226398468,51.9363708496],"type":"Point"}
}