{
  "type": "Feature",
  "properties": {
    "iso:country":"DE",
    "sg:address":"Wei\u00dfenburgstr 61-63",
    "sg:city":"D\u00fcsseldorf",
    "sg:phone":"+49 211/484790",
    "sg:postcode":"40476",
    "sg:province":"Nordrhein-Westfalen",
    "wof:name":"Aci Gmbh",
    "wof:placetype":"venue"
},
  "geometry": {"coordinates":[6.78794,51.247482],"type":"Point"}
}