{
  "type": "Feature",
  "properties": {
    "iso:country":"DE",
    "sg:address":"Wittenbergstr. 5-7",
    "sg:city":"Solingen",
    "sg:phone":"+49 212/267010",
    "sg:postcode":"42697",
    "sg:province":"Nordrhein-Westfalen",
    "wof:name":"Deutsche Post Ag",
    "wof:placetype":"venue"
},
  "geometry": {"coordinates":[7.0017170906,51.1620826721],"type":"Point"}
}