{
  "type": "Feature",
  "properties": {
    "iso:country":"DE",
    "sg:address":"Holl 5",
    "sg:city":"Elbenschwand",
    "sg:phone":"+49 7629/919125",
    "sg:postcode":"79692",
    "sg:province":"Baden-W\u00fcrttemberg",
    "wof:name":"Restaurant Hirschen",
    "wof:placetype":"venue"
},
  "geometry": {"coordinates":[7.8128018379,47.7371292114],"type":"Point"}
}