{
  "type": "Feature",
  "properties": {
    "iso:country":"DE",
    "sg:address":"Daimlerstr. 32",
    "sg:city":"Walldorf",
    "sg:postcode":"69190",
    "sg:province":"Baden-W\u00fcrttemberg",
    "wof:name":"Heku Komponenten Gmbh",
    "wof:placetype":"venue"
},
  "geometry": {"coordinates":[8.642912,49.291126],"type":"Point"}
}