{
  "type": "Feature",
  "properties": {
    "iso:country":"DE",
    "sg:address":"M\u00fchlenbergstr. 33b",
    "sg:city":"Menden",
    "sg:phone":"+49 2373/62303",
    "sg:postcode":"58708",
    "sg:province":"Nordrhein-Westfalen",
    "wof:name":"Max Frank Gmbh & Co. Kg",
    "wof:placetype":"venue"
},
  "geometry": {"coordinates":[7.767084,51.456242],"type":"Point"}
}