{
  "type": "Feature",
  "properties": {
    "iso:country":"DE",
    "sg:address":"Industriestr. 3",
    "sg:city":"Bad Zwischenahn",
    "sg:phone":"+49 4403/670",
    "sg:postcode":"26160",
    "sg:province":"Niedersachsen",
    "wof:name":"H\u00fcppe Gmbh & Co.",
    "wof:placetype":"venue"
},
  "geometry": {"coordinates":[8.059241,53.174419],"type":"Point"}
}