{
  "type": "Feature",
  "properties": {
    "iso:country":"DE",
    "sg:address":"Gr\u00fcnberger Str. 48",
    "sg:city":"Berlin",
    "sg:phone":"+49 30/293950",
    "sg:postcode":"10245",
    "sg:province":"Berlin",
    "wof:name":"Dooyoo Ag",
    "wof:placetype":"venue"
},
  "geometry": {"coordinates":[13.45505,52.511906],"type":"Point"}
}