{
  "type": "Feature",
  "properties": {
    "iso:country":"DE",
    "sg:address":"Birkenweg 2",
    "sg:city":"Zwickau",
    "sg:phone":"+49 5207/916925",
    "sg:postcode":"08058",
    "sg:province":"Sachsen",
    "wof:name":"Spradow Gmbh & Co. Kg",
    "wof:placetype":"venue"
},
  "geometry": {"coordinates":[8.6289539337,51.8965263367],"type":"Point"}
}