{
  "type": "Feature",
  "properties": {
    "iso:country":"DE",
    "sg:address":"Robert-Bloch-Str. 5",
    "sg:city":"R\u00f6dermark",
    "sg:phone":"+49 6074/629533",
    "sg:postcode":"63322",
    "sg:province":"Hessen",
    "wof:name":"Das Sonnenstudio In Urberach",
    "wof:placetype":"venue"
},
  "geometry": {"coordinates":[8.82807,49.977612],"type":"Point"}
}