{
  "type": "Feature",
  "properties": {
    "iso:country":"DE",
    "sg:address":"K\u00f6nigsberger Str. 24",
    "sg:city":"Garrel",
    "sg:phone":"+49 4474/7980",
    "sg:postcode":"49681",
    "sg:province":"Niedersachsen",
    "wof:name":"J. Tellmann Makler",
    "wof:placetype":"venue"
},
  "geometry": {"coordinates":[8.0405712128,52.9453620911],"type":"Point"}
}