{
  "type": "Feature",
  "properties": {
    "iso:country":"DE",
    "sg:address":"Schauenburgerstr 112",
    "sg:city":"Kiel",
    "sg:phone":"+49 431/570060",
    "sg:postcode":"24118",
    "sg:province":"Schleswig-Holstein",
    "wof:name":"Solar Gmbh",
    "wof:placetype":"venue"
},
  "geometry": {"coordinates":[10.118717,54.334888],"type":"Point"}
}