{
  "type": "Feature",
  "properties": {
    "iso:country":"DE",
    "sg:address":"Hans-Schw\u00f6rer-Str. 8",
    "sg:city":"Hohenstein",
    "sg:phone":"+49 7387/160",
    "sg:postcode":"72531",
    "sg:province":"Baden-W\u00fcrttemberg",
    "wof:name":"Schw\u00f6rer Haus Kg",
    "wof:placetype":"venue"
},
  "geometry": {"coordinates":[9.374518,48.348232],"type":"Point"}
}