{
  "type": "Feature",
  "properties": {
    "iso:country":"DE",
    "sg:address":"Hermann-Gmeiner-Weg 32",
    "sg:city":"M\u00fcnchen",
    "sg:phone":"+49 89/932005",
    "sg:postcode":"81929",
    "sg:province":"Bayern",
    "wof:name":"Siglinde Rankl",
    "wof:placetype":"venue"
},
  "geometry": {"coordinates":[11.641876,48.145657],"type":"Point"}
}