{
  "type": "Feature",
  "properties": {
    "iso:country":"DE",
    "sg:address":"Terrassenstieg 4",
    "sg:city":"Hildesheim",
    "sg:phone":"+49 5064/963660",
    "sg:postcode":"31141",
    "sg:province":"Niedersachsen",
    "wof:name":"Teambau Eigenheime Gmbh",
    "wof:placetype":"venue"
},
  "geometry": {"coordinates":[9.9884223938,52.1145973206],"type":"Point"}
}