{
  "type": "Feature",
  "properties": {
    "iso:country":"DE",
    "sg:address":"Weidener Str. 16",
    "sg:city":"Regensburg",
    "sg:phone":"+49 941/69500",
    "sg:postcode":"93057",
    "sg:province":"Bayern",
    "wof:name":"Sillner Industries Gmbh & Co. Kg",
    "wof:placetype":"venue"
},
  "geometry": {"coordinates":[12.128029,49.062572],"type":"Point"}
}