{
  "type": "Feature",
  "properties": {
    "iso:country":"DE",
    "sg:address":"Flachsweg 3",
    "sg:city":"Stemwede",
    "sg:phone":"+49 5773/616",
    "sg:postcode":"32351",
    "sg:province":"Nordrhein-Westfalen",
    "wof:name":"Fr. Kemper",
    "wof:placetype":"venue"
},
  "geometry": {"coordinates":[8.497755,52.455021],"type":"Point"}
}