{
  "type": "Feature",
  "properties": {
    "iso:country":"DE",
    "sg:address":"Friedenstr. 11",
    "sg:city":"Zaberfeld",
    "sg:phone":"+49 7046/2815",
    "sg:postcode":"74374",
    "sg:province":"Baden-W\u00fcrttemberg",
    "wof:name":"Wgv Ochenburg",
    "wof:placetype":"venue"
},
  "geometry": {"coordinates":[8.9006938934,49.071975708],"type":"Point"}
}