{
  "type": "Feature",
  "properties": {
    "iso:country":"DE",
    "sg:address":"Weinbergweg 22",
    "sg:city":"Rangsdorf",
    "sg:phone":"+49 30/7411309",
    "sg:postcode":"15834",
    "sg:province":"Brandenburg",
    "wof:name":"Arnold Fahrig",
    "wof:placetype":"venue"
},
  "geometry": {"coordinates":[13.420857,52.297764],"type":"Point"}
}