{
  "type": "Feature",
  "properties": {
    "iso:country":"DE",
    "sg:address":"Pasinger Str. 12",
    "sg:city":"Gr\u00e4felfing",
    "sg:phone":"+49 89/853077",
    "sg:postcode":"82166",
    "sg:province":"Bayern",
    "wof:name":"Restaurant Olympia",
    "wof:placetype":"venue"
},
  "geometry": {"coordinates":[11.4382047653,48.117061615],"type":"Point"}
}