{
  "type": "Feature",
  "properties": {
    "iso:country":"DE",
    "sg:address":"Landauer Str. 15",
    "sg:city":"Neustadt",
    "sg:phone":"+49 6321/33922",
    "sg:postcode":"67434",
    "sg:province":"Rheinland-Pfalz",
    "wof:name":"Erhard",
    "wof:placetype":"venue"
},
  "geometry": {"coordinates":[8.138907,49.35112],"type":"Point"}
}