{
  "type": "Feature",
  "properties": {
    "iso:country":"DE",
    "sg:address":"Strumannstr 18",
    "sg:city":"Gelsenkirchen",
    "sg:phone":"+49 6032/96100",
    "sg:postcode":"45891",
    "sg:province":"Nordrhein-Westfalen",
    "wof:name":"Aki-anton Koppai Ingenieure Gmbh",
    "wof:placetype":"venue"
},
  "geometry": {"coordinates":[8.715976,50.381077],"type":"Point"}
}