{
  "type": "Feature",
  "properties": {
    "iso:country":"DE",
    "sg:address":"Siepenheide 4",
    "sg:city":"Recklinghausen",
    "sg:postcode":"45661",
    "sg:province":"Nordrhein-Westfalen",
    "wof:name":"Feuer-multimedia-partneragentur",
    "wof:placetype":"venue"
},
  "geometry": {"coordinates":[7.1907668114,51.5695343018],"type":"Point"}
}