{
  "type": "Feature",
  "properties": {
    "iso:country":"DE",
    "sg:address":"Lusthof 19 a",
    "sg:city":"Kappeln",
    "sg:phone":"+49 4642/4084",
    "sg:postcode":"24376",
    "sg:province":"Schleswig-Holstein",
    "wof:name":"Holger Jensen Steuerberater",
    "wof:placetype":"venue"
},
  "geometry": {"coordinates":[9.9360618591,54.6643829346],"type":"Point"}
}