{
  "type": "Feature",
  "properties": {
    "iso:country":"DE",
    "sg:address":"Salemer Str. 9",
    "sg:city":"Bermatingen",
    "sg:phone":"+49 7544/2022",
    "sg:postcode":"88697",
    "sg:province":"Baden-W\u00fcrttemberg",
    "wof:name":"Klaus Wehr",
    "wof:placetype":"venue"
},
  "geometry": {"coordinates":[9.348685,47.730846],"type":"Point"}
}