{
  "type": "Feature",
  "properties": {
    "iso:country":"DE",
    "sg:address":"Gartenstr. 8",
    "sg:city":"Burgdorf",
    "sg:phone":"+49 5136/3899",
    "sg:postcode":"31303",
    "sg:province":"Niedersachsen",
    "wof:name":"Pizzeria Portofino Inh. Carlo Pacilli",
    "wof:placetype":"venue"
},
  "geometry": {"coordinates":[10.0064058304,52.449508667],"type":"Point"}
}