{
  "type": "Feature",
  "properties": {
    "iso:country":"DE",
    "sg:address":"Essener Str. 71",
    "sg:city":"Gelsenkirchen",
    "sg:phone":"+49 209/512590",
    "sg:postcode":"45899",
    "sg:province":"Nordrhein-Westfalen",
    "wof:name":"Spielparadies Automatenaufstellungs- Und",
    "wof:placetype":"venue"
},
  "geometry": {"coordinates":[7.0186271667,51.5359992981],"type":"Point"}
}