{
  "type": "Feature",
  "properties": {
    "iso:country":"DE",
    "sg:address":"Hohenzollernstr. 16",
    "sg:city":"Pforzheim",
    "sg:phone":"+49 7231/302990",
    "sg:postcode":"75177",
    "sg:province":"Baden-W\u00fcrttemberg",
    "wof:name":"K & P Training Und Consulting Gmbh",
    "wof:placetype":"venue"
},
  "geometry": {"coordinates":[8.7088441849,48.8970031738],"type":"Point"}
}