{
  "type": "Feature",
  "properties": {
    "iso:country":"DE",
    "sg:address":"Kornkamp 38",
    "sg:city":"Ahrensburg",
    "sg:phone":"+49 4102/42855",
    "sg:postcode":"22926",
    "sg:province":"Schleswig-Holstein",
    "wof:name":"Schoch & Siege Papierverarbeitungs- Gmbh",
    "wof:placetype":"venue"
},
  "geometry": {"coordinates":[10.2564220428,53.6875915527],"type":"Point"}
}