{
  "type": "Feature",
  "properties": {
    "iso:country":"DE",
    "sg:address":"Schwarzburger Str. 14",
    "sg:city":"Berlin",
    "sg:postcode":"12687",
    "sg:province":"Berlin",
    "wof:name":"Kassanova Vertrieb Von Pc Und Gastronomiekassen",
    "wof:placetype":"venue"
},
  "geometry": {"coordinates":[13.571173,52.55822],"type":"Point"}
}