{
  "type": "Feature",
  "properties": {
    "iso:country":"DE",
    "sg:address":"Trierer Str. 65",
    "sg:city":"Weimar",
    "sg:phone":"+49 3643/202068",
    "sg:postcode":"99423",
    "sg:province":"Th\u00fcringen",
    "wof:name":"Kickeritz Und Zeitze Rechtsanw\u00e4lte",
    "wof:placetype":"venue"
},
  "geometry": {"coordinates":[11.3164720535,50.9795227051],"type":"Point"}
}