{
  "type": "Feature",
  "properties": {
    "iso:country":"DE",
    "sg:address":"Dorfstr. 17",
    "sg:city":"Westfehmarn",
    "sg:phone":"+49 4372/1549",
    "sg:postcode":"23769",
    "sg:province":"Schleswig-Holstein",
    "wof:name":"Fehmarn - Hof Kg",
    "wof:placetype":"venue"
},
  "geometry": {"coordinates":[11.09954,54.439781],"type":"Point"}
}