{
  "type": "Feature",
  "properties": {
    "iso:country":"DE",
    "sg:address":"Herzogspitalstr. 8",
    "sg:city":"M\u00fcnchen",
    "sg:postcode":"80331",
    "sg:province":"Bayern",
    "wof:name":"Ipf-interprojekt Finanzberatung Gmbh",
    "wof:placetype":"venue"
},
  "geometry": {"coordinates":[11.5683403015,48.137802124],"type":"Point"}
}