{
  "type": "Feature",
  "properties": {
    "iso:country":"DE",
    "sg:address":"Rackertshofener Str. 8",
    "sg:city":"Gaimersheim",
    "sg:phone":"+49 8458/2977",
    "sg:postcode":"85080",
    "sg:province":"Bayern",
    "wof:name":"Urbanietz Waagenservice",
    "wof:placetype":"venue"
},
  "geometry": {"coordinates":[11.370376,48.811554],"type":"Point"}
}