{
  "type": "Feature",
  "properties": {
    "iso:country":"DE",
    "sg:address":"M\u00fchlh\u00e4user Str. 311",
    "sg:city":"Stuttgart",
    "sg:phone":"+49 711/531601",
    "sg:postcode":"70378",
    "sg:province":"Baden-W\u00fcrttemberg",
    "wof:name":"Vereinsgastst\u00e4tte W\u00fcrttem- Berger Angler-verein E. V.",
    "wof:placetype":"venue"
},
  "geometry": {"coordinates":[9.2193031311,48.8348197937],"type":"Point"}
}