{
  "type": "Feature",
  "properties": {
    "iso:country":"DE",
    "sg:address":"Neue Meinigstr. 15",
    "sg:city":"Bad Harzburg",
    "sg:phone":"+49 5322/86484",
    "sg:postcode":"38667",
    "sg:province":"Niedersachsen",
    "wof:name":"Ulrich Neumann",
    "wof:placetype":"venue"
},
  "geometry": {"coordinates":[10.522731,51.905514],"type":"Point"}
}