{
  "type": "Feature",
  "properties": {
    "iso:country":"DE",
    "sg:address":"Elligersweg 73",
    "sg:city":"Hamburg",
    "sg:phone":"+49 40/6300700",
    "sg:postcode":"22307",
    "sg:province":"Hamburg",
    "wof:name":"Konrad Bunk",
    "wof:placetype":"venue"
},
  "geometry": {"coordinates":[10.051667,53.601185],"type":"Point"}
}