{
  "type": "Feature",
  "properties": {
    "iso:country":"DE",
    "sg:address":"Kirchardtsbrunnen 4",
    "sg:city":"Bad Rappenau",
    "sg:phone":"+49 7268/1551",
    "sg:postcode":"74906",
    "sg:province":"Baden-W\u00fcrttemberg",
    "wof:name":"Procomp",
    "wof:placetype":"venue"
},
  "geometry": {"coordinates":[9.0408411026,49.2595901489],"type":"Point"}
}