{
  "type": "Feature",
  "properties": {
    "iso:country":"DE",
    "sg:address":"Schwelmer Str. 235b",
    "sg:city":"Wuppertal",
    "sg:phone":"+49 202/2602050",
    "sg:postcode":"42389",
    "sg:province":"Nordrhein-Westfalen",
    "wof:name":"Karl Eckert-b\u00fchnenlicht Inh. Frank Albert Vonhoff",
    "wof:placetype":"venue"
},
  "geometry": {"coordinates":[7.2703142166,51.2786445618],"type":"Point"}
}