{
  "type": "Feature",
  "properties": {
    "iso:country":"DE",
    "sg:address":"Gorch-Fock-Str. 24",
    "sg:city":"Ratingen",
    "sg:phone":"+49 2102/445400",
    "sg:postcode":"40880",
    "sg:province":"Nordrhein-Westfalen",
    "wof:name":"Annemarie Bein",
    "wof:placetype":"venue"
},
  "geometry": {"coordinates":[6.8289542198,51.3094367981],"type":"Point"}
}