{
  "type": "Feature",
  "properties": {
    "iso:country":"DE",
    "sg:address":"Lyoner Stra\u00dfe 22",
    "sg:city":"Frankfurt",
    "sg:phone":"+49 69/66770",
    "sg:postcode":"60528",
    "sg:province":"Hessen",
    "wof:name":"Lahmeyer International Gmbh",
    "wof:placetype":"venue"
},
  "geometry": {"coordinates":[8.623784,50.081841],"type":"Point"}
}