{
  "type": "Feature",
  "properties": {
    "iso:country":"DE",
    "sg:address":"Munscheidstr. 14",
    "sg:city":"Gelsenkirchen",
    "sg:postcode":"45886",
    "sg:province":"Nordrhein-Westfalen",
    "wof:name":"Verband Lokaler Rundfunk In Nrw",
    "wof:placetype":"venue"
},
  "geometry": {"coordinates":[7.1084017754,51.498588562],"type":"Point"}
}