{
  "type": "Feature",
  "properties": {
    "iso:country":"DE",
    "sg:address":"Berthelsdorfer Str. 11",
    "sg:city":"Freiberg",
    "sg:phone":"+49 3731/247655",
    "sg:postcode":"09599",
    "sg:province":"Sachsen",
    "wof:name":"Klaus Jahn Und Uta Lippmann",
    "wof:placetype":"venue"
},
  "geometry": {"coordinates":[13.3480005264,50.9132385254],"type":"Point"}
}