{
  "type": "Feature",
  "properties": {
    "iso:country":"DE",
    "sg:address":"Stubenbergstr.",
    "sg:city":"Weil der Stadt",
    "sg:phone":"+49 7033/693966",
    "sg:postcode":"71263",
    "sg:province":"Baden-W\u00fcrttemberg",
    "wof:name":"Sportgastst\u00e4tte Vereinsheim",
    "wof:placetype":"venue"
},
  "geometry": {"coordinates":[8.8957853317,48.7282371521],"type":"Point"}
}