{
  "type": "Feature",
  "properties": {
    "iso:country":"DE",
    "sg:address":"Weststr. 98a",
    "sg:city":"Chemnitz",
    "sg:phone":"+49 371/307408",
    "sg:postcode":"09116",
    "sg:province":"Sachsen",
    "wof:name":"Wendel",
    "wof:placetype":"venue"
},
  "geometry": {"coordinates":[12.89177,50.830639],"type":"Point"}
}