{
  "type": "Feature",
  "properties": {
    "iso:country":"DE",
    "sg:address":"Invalidenstr. 102",
    "sg:city":"Berlin",
    "sg:phone":"+49 30/2814027",
    "sg:postcode":"10115",
    "sg:province":"Berlin",
    "wof:name":"Dr. Med. Peter Leitner",
    "wof:placetype":"venue"
},
  "geometry": {"coordinates":[13.380487,52.529716],"type":"Point"}
}