{
  "type": "Feature",
  "properties": {
    "iso:country":"DE",
    "sg:address":"Reichsdorfstr. 53",
    "sg:city":"G\u00f6ppingen",
    "sg:phone":"+49 7165/8060",
    "sg:postcode":"73037",
    "sg:province":"Baden-W\u00fcrttemberg",
    "wof:name":"Waldhorn",
    "wof:placetype":"venue"
},
  "geometry": {"coordinates":[9.7215871811,48.742023468],"type":"Point"}
}