{
  "type": "Feature",
  "properties": {
    "iso:country":"DE",
    "sg:address":"Peerekopp 8",
    "sg:city":"Wees",
    "sg:phone":"+49 4631/623535",
    "sg:postcode":"24999",
    "sg:province":"Schleswig-Holstein",
    "wof:name":"Adler-computer Multimedia-gesellschaft Mbh",
    "wof:placetype":"venue"
},
  "geometry": {"coordinates":[9.5208320618,54.8046722412],"type":"Point"}
}