{
  "type": "Feature",
  "properties": {
    "iso:country":"DE",
    "sg:address":"Johannesstr. 19",
    "sg:city":"Aldenhoven",
    "sg:phone":"+49 2464/6510",
    "sg:postcode":"52457",
    "sg:province":"Nordrhein-Westfalen",
    "wof:name":"Zur Linde",
    "wof:placetype":"venue"
},
  "geometry": {"coordinates":[6.2667679787,50.8813476562],"type":"Point"}
}