{
  "type": "Feature",
  "properties": {
    "iso:country":"DE",
    "sg:address":"Braunmattstr. 24",
    "sg:city":"Baden-Baden",
    "sg:phone":"+49 7221/66434",
    "sg:postcode":"76532",
    "sg:province":"Baden-W\u00fcrttemberg",
    "wof:name":"Achim Dennig Abschleppdienst",
    "wof:placetype":"venue"
},
  "geometry": {"coordinates":[8.2135324478,48.8169555664],"type":"Point"}
}