{
  "type": "Feature",
  "properties": {
    "iso:country":"DE",
    "sg:address":"Kiefernweg 1",
    "sg:city":"Detmold",
    "sg:phone":"+49 5231/63000",
    "sg:postcode":"32758",
    "sg:province":"Nordrhein-Westfalen",
    "wof:name":"Lippisches Blindenwerk Gmbh Alter Postweg",
    "wof:placetype":"venue"
},
  "geometry": {"coordinates":[8.82126,51.938541],"type":"Point"}
}