{
  "type": "Feature",
  "properties": {
    "iso:country":"DE",
    "sg:address":"Schenkendorfer Flur 12",
    "sg:city":"K\u00f6nigs Wusterhausen",
    "sg:phone":"+49 3375/872890",
    "sg:postcode":"15711",
    "sg:province":"Brandenburg",
    "wof:name":"Helga Fuchs",
    "wof:placetype":"venue"
},
  "geometry": {"coordinates":[13.6097002029,52.2857818604],"type":"Point"}
}