{
  "type": "Feature",
  "properties": {
    "iso:country":"DE",
    "sg:address":"Kusserstr.",
    "sg:city":"Hauzenberg",
    "sg:phone":"+49 8586/4450",
    "sg:postcode":"94051",
    "sg:province":"Bayern",
    "wof:name":"Georg Mandl",
    "wof:placetype":"venue"
},
  "geometry": {"coordinates":[13.62386,48.655632],"type":"Point"}
}