{
  "type": "Feature",
  "properties": {
    "iso:country":"DE",
    "sg:address":"Nordstr. 22",
    "sg:city":"Bocholt",
    "sg:phone":"+49 2871/13876",
    "sg:postcode":"46399",
    "sg:province":"Nordrhein-Westfalen",
    "wof:name":"Drogerie-parf\u00fcmerie Bruns Hermann Dieckhues",
    "wof:placetype":"venue"
},
  "geometry": {"coordinates":[6.615427,51.839901],"type":"Point"}
}