{
  "type": "Feature",
  "properties": {
    "iso:country":"DE",
    "sg:address":"Hauptstr. 21",
    "sg:city":"Freiburg",
    "sg:phone":"+49 4779/396",
    "sg:postcode":"21729",
    "sg:province":"Niedersachsen",
    "wof:name":"Schuhhaus Kr\u00fcger Inh. Uwe Kr\u00fcger",
    "wof:placetype":"venue"
},
  "geometry": {"coordinates":[9.2896766663,53.8254432678],"type":"Point"}
}