{
  "type": "Feature",
  "properties": {
    "iso:country":"DE",
    "sg:address":"Hollerberg 4",
    "sg:city":"Kupferberg",
    "sg:phone":"+49 9227/4724",
    "sg:postcode":"95362",
    "sg:province":"Bayern",
    "wof:name":"Michel Projekt Gmbh",
    "wof:placetype":"venue"
},
  "geometry": {"coordinates":[11.5763454437,50.137928009],"type":"Point"}
}