{
  "type": "Feature",
  "properties": {
    "iso:country":"DE",
    "sg:address":"Karl-Liebknecht-Str. 8",
    "sg:city":"Nerchau",
    "sg:phone":"+49 34382/41000",
    "sg:postcode":"04685",
    "sg:province":"Sachsen",
    "wof:name":"Peter Schubert",
    "wof:placetype":"venue"
},
  "geometry": {"coordinates":[12.7931489944,51.2739906311],"type":"Point"}
}