{
  "type": "Feature",
  "properties": {
    "iso:country":"DE",
    "sg:address":"Redder am See 25",
    "sg:city":"Schlesen",
    "sg:phone":"+49 4303/217",
    "sg:postcode":"24256",
    "sg:province":"Schleswig-Holstein",
    "wof:name":"Erich Brenneiser",
    "wof:placetype":"venue"
},
  "geometry": {"coordinates":[10.325875,54.322346],"type":"Point"}
}