{
  "type": "Feature",
  "properties": {
    "iso:country":"DE",
    "sg:address":"Bessemerstr. 8",
    "sg:city":"Chemnitz",
    "sg:postcode":"09116",
    "sg:province":"Sachsen",
    "wof:name":"Ps Consult Gmbh",
    "wof:placetype":"venue"
},
  "geometry": {"coordinates":[12.862475,50.818695],"type":"Point"}
}