{
  "type": "Feature",
  "properties": {
    "iso:country":"DE",
    "sg:address":"Glockenhofstr. 28",
    "sg:city":"N\u00fcrnberg",
    "sg:phone":"+49 911/497551",
    "sg:postcode":"90478",
    "sg:province":"Bayern",
    "wof:name":"W. Mayer & Kraft",
    "wof:placetype":"venue"
},
  "geometry": {"coordinates":[11.0906229019,49.4441986084],"type":"Point"}
}