{
  "type": "Feature",
  "properties": {
    "iso:country":"DE",
    "sg:address":"Br\u00fcckenweg 9",
    "sg:city":"M\u00fcnchsteinach",
    "sg:phone":"+49 9166/245",
    "sg:postcode":"91481",
    "sg:province":"Bayern",
    "wof:name":"Georg Auer Lebensmittel",
    "wof:placetype":"venue"
},
  "geometry": {"coordinates":[10.5932130814,49.6394195557],"type":"Point"}
}