{
  "type": "Feature",
  "properties": {
    "iso:country":"DE",
    "sg:address":"Saarlandstr. 156",
    "sg:city":"Bingen",
    "sg:phone":"+49 6721/41320",
    "sg:postcode":"55411",
    "sg:province":"Rheinland-Pfalz",
    "wof:name":"Eckert & Mayer Ohg",
    "wof:placetype":"venue"
},
  "geometry": {"coordinates":[7.9101171494,49.9504928589],"type":"Point"}
}