{
  "type": "Feature",
  "properties": {
    "iso:country":"DE",
    "sg:address":"Gasstr. 19",
    "sg:city":"Guben",
    "sg:phone":"+49 3561/3918",
    "sg:postcode":"03172",
    "sg:province":"Brandenburg",
    "wof:name":"Hirsch Und Emmer Rechtsanw\u00e4lte",
    "wof:placetype":"venue"
},
  "geometry": {"coordinates":[14.7165079117,51.9510917664],"type":"Point"}
}