{
  "type": "Feature",
  "properties": {
    "iso:country":"DE",
    "sg:address":"Kurt-Schumacher-Str. 26",
    "sg:city":"Troisdorf",
    "sg:phone":"+49 2241/71814",
    "sg:postcode":"53840",
    "sg:province":"Nordrhein-Westfalen",
    "wof:name":"B\u00fcrgerhof",
    "wof:placetype":"venue"
},
  "geometry": {"coordinates":[7.1495862007,50.8003311157],"type":"Point"}
}