{
  "type": "Feature",
  "properties": {
    "iso:country":"DE",
    "sg:address":"Alte Uhldinger Str. 5 A",
    "sg:city":"Uhldingen-M\u00fchlhofen",
    "sg:postcode":"88690",
    "sg:province":"Baden-W\u00fcrttemberg",
    "wof:name":"Drp Project-plan Gmbh",
    "wof:placetype":"venue"
},
  "geometry": {"coordinates":[9.2373504639,47.7297134399],"type":"Point"}
}