{
  "type": "Feature",
  "properties": {
    "iso:country":"DE",
    "sg:address":"Wittenbergener Weg 47a",
    "sg:city":"Hamburg",
    "sg:postcode":"22559",
    "sg:province":"Hamburg",
    "wof:name":"Metcor Metall Gmbh",
    "wof:placetype":"venue"
},
  "geometry": {"coordinates":[9.757627,53.575245],"type":"Point"}
}