{
  "type": "Feature",
  "properties": {
    "iso:country":"DE",
    "sg:address":"Bismarckstr. 19",
    "sg:city":"Hof",
    "sg:phone":"+49 9281/16983",
    "sg:postcode":"95028",
    "sg:province":"Bayern",
    "wof:name":"Efes",
    "wof:placetype":"venue"
},
  "geometry": {"coordinates":[11.9154376984,50.3152809143],"type":"Point"}
}