{
  "type": "Feature",
  "properties": {
    "iso:country":"DE",
    "sg:address":"Wethgasse 8",
    "sg:city":"Dinkelsb\u00fchl",
    "sg:phone":"+49 9851/6992",
    "sg:postcode":"91550",
    "sg:province":"Bayern",
    "wof:name":"M. Hammer",
    "wof:placetype":"venue"
},
  "geometry": {"coordinates":[10.3208818436,49.0674209595],"type":"Point"}
}