{
  "type": "Feature",
  "properties": {
    "iso:country":"DE",
    "sg:address":"Wittenberger Str. 21",
    "sg:city":"Bitterfeld",
    "sg:phone":"+49 3493/22343",
    "sg:postcode":"06749",
    "sg:province":"Sachsen-Anhalt",
    "wof:name":"T & W D\u00e4mm- Und Baustoffhandels-gmbh",
    "wof:placetype":"venue"
},
  "geometry": {"coordinates":[12.32869,51.629887],"type":"Point"}
}