{
  "type": "Feature",
  "properties": {
    "iso:country":"DE",
    "sg:address":"Gl\u00fcckaufstra\u00dfe 174",
    "sg:city":"Georgsmarienh\u00fctte",
    "sg:phone":"+49 174 6839423",
    "sg:postcode":"49124",
    "sg:province":"Niedersachsen",
    "wof:name":"David`s Rollerseite",
    "wof:placetype":"venue"
},
  "geometry": {"coordinates":[8.11979,52.20113],"type":"Point"}
}