{
  "type": "Feature",
  "properties": {
    "iso:country":"DE",
    "sg:address":"Sch\u00e4fergarten 6",
    "sg:city":"Elbe",
    "sg:phone":"+49 5345/209",
    "sg:postcode":"38274",
    "sg:province":"Niedersachsen",
    "wof:name":"H. Ehrbar",
    "wof:placetype":"venue"
},
  "geometry": {"coordinates":[10.270936,52.088921],"type":"Point"}
}