{
  "type": "Feature",
  "properties": {
    "iso:country":"DE",
    "sg:address":"Uferweg 42",
    "sg:city":"Gelnhausen",
    "sg:phone":"+49 6051/48030",
    "sg:postcode":"63571",
    "sg:province":"Hessen",
    "wof:name":"Hein & Partner Treuhandgesellschaft Mbh",
    "wof:placetype":"venue"
},
  "geometry": {"coordinates":[9.1783103943,50.1991882324],"type":"Point"}
}