{
  "type": "Feature",
  "properties": {
    "iso:country":"DE",
    "sg:address":"Allee 4",
    "sg:city":"D\u00f6llst\u00e4dt",
    "sg:phone":"+49 36206/21981",
    "sg:postcode":"99100",
    "sg:province":"Th\u00fcringen",
    "wof:name":"Grube & Ehrlich Holzverarbeitungsgesellschaft Mbh",
    "wof:placetype":"venue"
},
  "geometry": {"coordinates":[10.8107471466,51.0829429626],"type":"Point"}
}