{
  "type": "Feature",
  "properties": {
    "iso:country":"DE",
    "sg:address":"Reichenbacher Str. 39",
    "sg:city":"Lautertal",
    "sg:phone":"+49 6254/555",
    "sg:postcode":"64686",
    "sg:province":"Hessen",
    "wof:name":"Felsenmeer",
    "wof:placetype":"venue"
},
  "geometry": {"coordinates":[8.707318306,49.7342338562],"type":"Point"}
}