{
  "type": "Feature",
  "properties": {
    "iso:country":"DE",
    "sg:address":"Wallenroder Str. 7",
    "sg:city":"Berlin",
    "sg:phone":"+49 30/41990",
    "sg:postcode":"13435",
    "sg:province":"Berlin",
    "wof:name":"Edeka Berlin-brandenburg Eg",
    "wof:placetype":"venue"
},
  "geometry": {"coordinates":[13.340265274,52.6035270691],"type":"Point"}
}