{
  "type": "Feature",
  "properties": {
    "iso:country":"DE",
    "sg:address":"Ekenknick 3",
    "sg:city":"Hamburg",
    "sg:phone":"+49 40/5709222",
    "sg:postcode":"22523",
    "sg:province":"Hamburg",
    "wof:name":"Brillen Krille E. K.",
    "wof:placetype":"venue"
},
  "geometry": {"coordinates":[9.902893,53.608097],"type":"Point"}
}