{
  "type": "Feature",
  "properties": {
    "iso:country":"DE",
    "sg:address":"Pulverh\u00e4userweg 83",
    "sg:city":"Darmstadt",
    "sg:phone":"+49 6151/317744",
    "sg:postcode":"64295",
    "sg:province":"Hessen",
    "wof:name":"Elektronik 61 Gesellschaft F\u00fcr Hard- Und",
    "wof:placetype":"venue"
},
  "geometry": {"coordinates":[8.6287870407,49.8471717834],"type":"Point"}
}