{
  "type": "Feature",
  "properties": {
    "iso:country":"DE",
    "sg:address":"Wickeder Hellweg 93-97",
    "sg:city":"Dortmund",
    "sg:postcode":"44319",
    "sg:province":"Nordrhein-Westfalen",
    "wof:name":"Seniorenhaus Lucia Gmbh & Co. Kg",
    "wof:placetype":"venue"
},
  "geometry": {"coordinates":[7.610656,51.532219],"type":"Point"}
}