{
  "type": "Feature",
  "properties": {
    "iso:country":"DE",
    "sg:address":"Goethestr. 38",
    "sg:city":"Abensberg",
    "sg:phone":"+49 9443/6853",
    "sg:postcode":"93326",
    "sg:province":"Bayern",
    "wof:name":"Heinz",
    "wof:placetype":"venue"
},
  "geometry": {"coordinates":[11.85868,48.821918],"type":"Point"}
}