{
  "type": "Feature",
  "properties": {
    "iso:country":"DE",
    "sg:address":"Pirckheimerstr. 90",
    "sg:city":"N\u00fcrnberg",
    "sg:phone":"+49 911/557835",
    "sg:postcode":"90409",
    "sg:province":"Bayern",
    "wof:name":"Claudia Saffer",
    "wof:placetype":"venue"
},
  "geometry": {"coordinates":[11.0863180161,49.4609298706],"type":"Point"}
}