{
  "type": "Feature",
  "properties": {
    "iso:country":"DE",
    "sg:address":"goethestra\u00dfe 5",
    "sg:city":"Mauer",
    "sg:phone":"+49 6226/991333",
    "sg:postcode":"69256",
    "sg:province":"Baden-W\u00fcrttemberg",
    "wof:name":"S. Nikolaus",
    "wof:placetype":"venue"
},
  "geometry": {"coordinates":[8.7968626022,49.3434867859],"type":"Point"}
}