{
  "type": "Feature",
  "properties": {
    "iso:country":"DE",
    "sg:address":"Mooser Str. 3",
    "sg:city":"Radolfzell",
    "sg:phone":"+49 7732/95070",
    "sg:postcode":"78315",
    "sg:province":"Baden-W\u00fcrttemberg",
    "wof:name":"U. Gebhard-rundel Rechtsanwalt",
    "wof:placetype":"venue"
},
  "geometry": {"coordinates":[8.9636249542,47.7403106689],"type":"Point"}
}