{
  "type": "Feature",
  "properties": {
    "iso:country":"DE",
    "sg:address":"Richardstr. 15",
    "sg:city":"D\u00fcsseldorf",
    "sg:phone":"+49 211/226625",
    "sg:postcode":"40231",
    "sg:province":"Nordrhein-Westfalen",
    "wof:name":"Michael Weber",
    "wof:placetype":"venue"
},
  "geometry": {"coordinates":[6.8390932083,51.2043380737],"type":"Point"}
}