{
  "type": "Feature",
  "properties": {
    "iso:country":"DE",
    "sg:address":"Heinrichstr. 35",
    "sg:city":"D\u00fcsseldorf",
    "sg:phone":"+49 211/632241",
    "sg:postcode":"40239",
    "sg:province":"Nordrhein-Westfalen",
    "wof:name":"R. Bias",
    "wof:placetype":"venue"
},
  "geometry": {"coordinates":[6.812278,51.244713],"type":"Point"}
}