{
  "type": "Feature",
  "properties": {
    "iso:country":"DE",
    "sg:address":"Neumeisterstr. 16",
    "sg:city":"Berlin",
    "sg:phone":"+49 30/3366475",
    "sg:postcode":"13585",
    "sg:province":"Berlin",
    "wof:name":"Dart-bedarf-beydoun",
    "wof:placetype":"venue"
},
  "geometry": {"coordinates":[13.202084,52.547974],"type":"Point"}
}