{
  "type": "Feature",
  "properties": {
    "iso:country":"DE",
    "sg:address":"Vor der Steyer 1",
    "sg:city":"Riestedt",
    "sg:phone":"+49 3464/572346",
    "sg:postcode":"06528",
    "sg:province":"Sachsen-Anhalt",
    "wof:name":"Maik Altenburg Kunst- Und Naturstein Gmbh",
    "wof:placetype":"venue"
},
  "geometry": {"coordinates":[11.3635177612,51.5010299683],"type":"Point"}
}