{
  "type": "Feature",
  "properties": {
    "iso:country":"DE",
    "sg:address":"G\u00fcnzburger Str. 3",
    "sg:city":"Gundelfingen",
    "sg:phone":"+49 9073/7294",
    "sg:postcode":"89423",
    "sg:province":"Bayern",
    "wof:name":"Geschwister Konrad",
    "wof:placetype":"venue"
},
  "geometry": {"coordinates":[10.3661394119,48.5509681702],"type":"Point"}
}