{
  "type": "Feature",
  "properties": {
    "iso:country":"DE",
    "sg:address":"Kasterstr. 2",
    "sg:city":"Bergheim",
    "sg:phone":"+49 2238/42522",
    "sg:postcode":"50129",
    "sg:province":"Nordrhein-Westfalen",
    "wof:name":"Hans Bayer Fleischerei",
    "wof:placetype":"venue"
},
  "geometry": {"coordinates":[6.7071099281,50.9931945801],"type":"Point"}
}