{
  "type": "Feature",
  "properties": {
    "iso:country":"DE",
    "sg:address":"Aichacher Str. 13",
    "sg:city":"Schrobenhausen",
    "sg:phone":"+49 8252/910020",
    "sg:postcode":"86529",
    "sg:province":"Bayern",
    "wof:name":"Bauzentrum Pfaffenhofen Gmbh & Co. Kg",
    "wof:placetype":"venue"
},
  "geometry": {"coordinates":[11.2649707794,48.5573348999],"type":"Point"}
}