{
  "type": "Feature",
  "properties": {
    "iso:country":"DE",
    "sg:address":"Use Akschen 4",
    "sg:city":"Bremen",
    "sg:postcode":"28237",
    "sg:province":"Bremen",
    "wof:name":"Space Park Gmbh & Co. Kg",
    "wof:placetype":"venue"
},
  "geometry": {"coordinates":[8.750391,53.1124],"type":"Point"}
}