{
  "type": "Feature",
  "properties": {
    "iso:country":"DE",
    "sg:address":"R\u00f6ttgener Str. 141",
    "sg:city":"Bonn",
    "sg:phone":"+49 228/281795",
    "sg:postcode":"53127",
    "sg:province":"Nordrhein-Westfalen",
    "wof:name":"Bedachungen Reuter- Grommes Gmbh",
    "wof:placetype":"venue"
},
  "geometry": {"coordinates":[7.080409,50.696972],"type":"Point"}
}