{
  "type": "Feature",
  "properties": {
    "iso:country":"DE",
    "sg:address":"Gro\u00dfe Geldstr. 17",
    "sg:city":"Recklinghausen",
    "sg:phone":"+49 2361/23696",
    "sg:postcode":"45657",
    "sg:province":"Nordrhein-Westfalen",
    "wof:name":"Franz-josef Kellerhoff Beteiligungs-gmbh",
    "wof:placetype":"venue"
},
  "geometry": {"coordinates":[7.196023,51.613976],"type":"Point"}
}