{
  "type": "Feature",
  "properties": {
    "iso:country":"DE",
    "sg:address":"Sachsenh\u00e4userstr. 30 a",
    "sg:city":"Bad Orb",
    "sg:phone":"+49 6052/5204",
    "sg:postcode":"63619",
    "sg:province":"Hessen",
    "wof:name":"Hans Ruppert",
    "wof:placetype":"venue"
},
  "geometry": {"coordinates":[9.33813,50.228092],"type":"Point"}
}