{
  "type": "Feature",
  "properties": {
    "iso:country":"DE",
    "sg:address":"Lychener Str. 1",
    "sg:city":"Wokuhl",
    "sg:phone":"+49 39825/20511",
    "sg:postcode":"17237",
    "sg:province":"Mecklenburg-Vorpommern",
    "wof:name":"Kck Haustechnik Gmbh",
    "wof:placetype":"venue"
},
  "geometry": {"coordinates":[13.2027664185,53.2851905823],"type":"Point"}
}