{
  "type": "Feature",
  "properties": {
    "iso:country":"DE",
    "sg:address":"Nieskyer Str. 100",
    "sg:city":"G\u00f6rlitz",
    "sg:phone":"+49 3581/317448",
    "sg:postcode":"02828",
    "sg:province":"Sachsen",
    "wof:name":"B\u00fcro-architekt-basedahl",
    "wof:placetype":"venue"
},
  "geometry": {"coordinates":[14.969724,51.16832],"type":"Point"}
}