{
  "type": "Feature",
  "properties": {
    "iso:country":"DE",
    "sg:address":"Stiftstr. 16a",
    "sg:city":"Uelzen",
    "sg:phone":"+49 581/70946",
    "sg:postcode":"29525",
    "sg:province":"Niedersachsen",
    "wof:name":"Walter Lehmhus",
    "wof:placetype":"venue"
},
  "geometry": {"coordinates":[10.5593919754,52.9743499756],"type":"Point"}
}