{
  "type": "Feature",
  "properties": {
    "iso:country":"DE",
    "sg:address":"Oberstr. 19",
    "sg:city":"R\u00fcdesheim am Rhein",
    "sg:phone":"+49 6722/2521",
    "sg:postcode":"65385",
    "sg:province":"Hessen",
    "wof:name":"Von Ritter Zu Groenesteyn Weinanbau",
    "wof:placetype":"venue"
},
  "geometry": {"coordinates":[7.9298200607,49.9872055054],"type":"Point"}
}