{
  "type": "Feature",
  "properties": {
    "iso:country":"DE",
    "sg:address":"Lessingplatz 1",
    "sg:city":"Braunschweig",
    "sg:phone":"+49 531/4807934",
    "sg:postcode":"38100",
    "sg:province":"Niedersachsen",
    "wof:name":"Pflege In Der Eigenen Wohnung",
    "wof:placetype":"venue"
},
  "geometry": {"coordinates":[10.524177,52.259411],"type":"Point"}
}