{
  "type": "Feature",
  "properties": {
    "iso:country":"DE",
    "sg:address":"Eisengasse 124",
    "sg:city":"Neuburg",
    "sg:phone":"+49 8431/67410",
    "sg:postcode":"86633",
    "sg:province":"Bayern",
    "wof:name":"Erwin G. Kettl Und Dr. Dieter Munzinger",
    "wof:placetype":"venue"
},
  "geometry": {"coordinates":[11.1826334,48.7365875244],"type":"Point"}
}