{
  "type": "Feature",
  "properties": {
    "iso:country":"DE",
    "sg:address":"Schillerstr. 2",
    "sg:city":"Emmendingen",
    "sg:phone":"+49 7641/8989",
    "sg:postcode":"79312",
    "sg:province":"Baden-W\u00fcrttemberg",
    "wof:name":"Darja Hess Krankengymnastin",
    "wof:placetype":"venue"
},
  "geometry": {"coordinates":[7.860956,48.10923],"type":"Point"}
}