{
  "type": "Feature",
  "properties": {
    "iso:country":"DE",
    "sg:address":"Bucherweg 1",
    "sg:city":"Baienfurt",
    "sg:phone":"+49 751/43673",
    "sg:postcode":"88255",
    "sg:province":"Baden-W\u00fcrttemberg",
    "wof:name":"Thomas Zerr",
    "wof:placetype":"venue"
},
  "geometry": {"coordinates":[9.6284313202,47.8320503235],"type":"Point"}
}