{
  "type": "Feature",
  "properties": {
    "iso:country":"DE",
    "sg:address":"Hainsbach 1",
    "sg:city":"Geiselh\u00f6ring",
    "sg:postcode":"94333",
    "sg:province":"Bayern",
    "wof:name":"Elha Consulting Gmbh",
    "wof:placetype":"venue"
},
  "geometry": {"coordinates":[12.4238004684,48.8087615967],"type":"Point"}
}