{
  "type": "Feature",
  "properties": {
    "iso:country":"DE",
    "sg:address":"Inselstr. 21",
    "sg:city":"Esslingen",
    "sg:phone":"+49 711/314800",
    "sg:postcode":"73730",
    "sg:province":"Baden-W\u00fcrttemberg",
    "wof:name":"Fischerheim",
    "wof:placetype":"venue"
},
  "geometry": {"coordinates":[9.3237524033,48.7272262573],"type":"Point"}
}