{
  "type": "Feature",
  "properties": {
    "iso:country":"DE",
    "sg:address":"Schlehenweg 8",
    "sg:city":"Buchholz",
    "sg:phone":"+49 4187/6832",
    "sg:postcode":"21244",
    "sg:province":"Niedersachsen",
    "wof:name":"Thl Sportst\u00e4ttenbetriebs Gmbh",
    "wof:placetype":"venue"
},
  "geometry": {"coordinates":[9.8731021881,53.2931594849],"type":"Point"}
}