{
  "type": "Feature",
  "properties": {
    "iso:country":"DE",
    "sg:address":"Industriestr. 5",
    "sg:city":"Maxdorf",
    "sg:phone":"+49 6237/92800",
    "sg:postcode":"67133",
    "sg:province":"Rheinland-Pfalz",
    "wof:name":"W. T. Armatur Gmbh",
    "wof:placetype":"venue"
},
  "geometry": {"coordinates":[8.292885,49.486446],"type":"Point"}
}