{
  "type": "Feature",
  "properties": {
    "iso:country":"DE",
    "sg:address":"Homrigh\u00e4user Weg 2",
    "sg:city":"Bad Berleburg",
    "sg:postcode":"57319",
    "sg:province":"Nordrhein-Westfalen",
    "wof:name":"Comeca Immobilien Management Gmbh",
    "wof:placetype":"venue"
},
  "geometry": {"coordinates":[8.3928775787,51.0593757629],"type":"Point"}
}