{
  "type": "Feature",
  "properties": {
    "iso:country":"DE",
    "sg:address":"Hanselsberg 4",
    "sg:city":"Volkenschwand",
    "sg:phone":"+49 8754/1242",
    "sg:postcode":"84106",
    "sg:province":"Bayern",
    "wof:name":"Harald Wenzl",
    "wof:placetype":"venue"
},
  "geometry": {"coordinates":[11.867353,48.601898],"type":"Point"}
}