{
  "type": "Feature",
  "properties": {
    "iso:country":"DE",
    "sg:address":"Heidenh\u00e4uschenstr. 4",
    "sg:city":"Elbtal",
    "sg:phone":"+49 6436/4247",
    "sg:postcode":"65627",
    "sg:province":"Hessen",
    "wof:name":"Dr. Peter Simon Rechtsanwalt",
    "wof:placetype":"venue"
},
  "geometry": {"coordinates":[8.0730228424,50.4877166748],"type":"Point"}
}