{
  "type": "Feature",
  "properties": {
    "iso:country":"DE",
    "sg:address":"G\u00fctersloher Str. 43",
    "sg:city":"Verl",
    "sg:phone":"+49 5246/925060",
    "sg:postcode":"33415",
    "sg:province":"Nordrhein-Westfalen",
    "wof:name":"Harald Hoppe",
    "wof:placetype":"venue"
},
  "geometry": {"coordinates":[8.5019350052,51.8803672791],"type":"Point"}
}