{
  "type": "Feature",
  "properties": {
    "iso:country":"DE",
    "sg:address":"Am Stadtgarten 1",
    "sg:city":"Gelsenkirchen",
    "sg:phone":"+49 209/146010",
    "sg:postcode":"45879",
    "sg:province":"Nordrhein-Westfalen",
    "wof:name":"R. Kahls",
    "wof:placetype":"venue"
},
  "geometry": {"coordinates":[7.085434,51.508945],"type":"Point"}
}