{
  "type": "Feature",
  "properties": {
    "iso:country":"DE",
    "sg:address":"Schulstr. 5",
    "sg:city":"Dettingen",
    "sg:phone":"+49 7123/972600",
    "sg:postcode":"72581",
    "sg:province":"Baden-W\u00fcrttemberg",
    "wof:name":"Leibfarth Gmbh",
    "wof:placetype":"venue"
},
  "geometry": {"coordinates":[9.115489,47.735195],"type":"Point"}
}