{
  "type": "Feature",
  "properties": {
    "iso:country":"DE",
    "sg:address":"Vogelsanger Str. 462",
    "sg:city":"K\u00f6ln",
    "sg:phone":"+49 221/583627",
    "sg:postcode":"50829",
    "sg:province":"Nordrhein-Westfalen",
    "wof:name":"Karl-heinz Mertens B\u00e4ckerei Gmbh",
    "wof:placetype":"venue"
},
  "geometry": {"coordinates":[6.879239,50.956352],"type":"Point"}
}