{
  "type": "Feature",
  "properties": {
    "iso:country":"DE",
    "sg:address":"Holstenstr. 15",
    "sg:city":"Schenefeld",
    "sg:phone":"+49 4892/402",
    "sg:postcode":"25560",
    "sg:province":"Schleswig-Holstein",
    "wof:name":"R. Struve",
    "wof:placetype":"venue"
},
  "geometry": {"coordinates":[9.481434,54.048603],"type":"Point"}
}