{
  "type": "Feature",
  "properties": {
    "iso:country":"DE",
    "sg:address":"Ubierstr. 80",
    "sg:city":"Bonn",
    "sg:phone":"+49 228/353218",
    "sg:postcode":"53173",
    "sg:province":"Nordrhein-Westfalen",
    "wof:name":"H. Riek",
    "wof:placetype":"venue"
},
  "geometry": {"coordinates":[7.1653518677,50.6910858154],"type":"Point"}
}