{
  "type": "Feature",
  "properties": {
    "iso:country":"DE",
    "sg:address":"Oberweyerer Str. 17",
    "sg:city":"Hadamar",
    "sg:phone":"+49 6433/3897",
    "sg:postcode":"65589",
    "sg:province":"Hessen",
    "wof:name":"Rainer Wingender",
    "wof:placetype":"venue"
},
  "geometry": {"coordinates":[8.1027336121,50.4697036743],"type":"Point"}
}