{
  "type": "Feature",
  "properties": {
    "iso:country":"DE",
    "sg:address":"Freiherr-von-Drais-Str. 51",
    "sg:city":"Waldbrunn",
    "sg:phone":"+49 6274/1594",
    "sg:postcode":"69429",
    "sg:province":"Baden-W\u00fcrttemberg",
    "wof:name":"Dieter Vogel",
    "wof:placetype":"venue"
},
  "geometry": {"coordinates":[9.0556850433,49.4603652954],"type":"Point"}
}