{
  "type": "Feature",
  "properties": {
    "iso:country":"DE",
    "sg:address":"Fichtestr. 7",
    "sg:city":"Durmersheim",
    "sg:phone":"+49 7245/3805",
    "sg:postcode":"76448",
    "sg:province":"Baden-W\u00fcrttemberg",
    "wof:name":"Edwin Stolz",
    "wof:placetype":"venue"
},
  "geometry": {"coordinates":[8.2805862427,48.9407958984],"type":"Point"}
}