{
  "type": "Feature",
  "properties": {
    "iso:country":"DE",
    "sg:address":"Im B\u00f6h 5",
    "sg:city":"Uelzen",
    "sg:phone":"+49 581/70012",
    "sg:postcode":"29525",
    "sg:province":"Niedersachsen",
    "wof:name":"W. Baucke",
    "wof:placetype":"venue"
},
  "geometry": {"coordinates":[10.558548,52.987392],"type":"Point"}
}