{
  "type": "Feature",
  "properties": {
    "iso:country":"DE",
    "sg:address":"Testorf 2a",
    "sg:city":"Weste",
    "sg:postcode":"29599",
    "sg:province":"Niedersachsen",
    "wof:name":"Gefl\u00fcgelzucht Bad Bevensen",
    "wof:placetype":"venue"
},
  "geometry": {"coordinates":[10.7169971466,53.0468635559],"type":"Point"}
}