{
  "type": "Feature",
  "properties": {
    "iso:country":"DE",
    "sg:address":"Bleicherstrasse 20",
    "sg:city":"Konstanz",
    "sg:phone":"+49 7531/458156",
    "sg:postcode":"78467",
    "sg:province":"Baden-W\u00fcrttemberg",
    "wof:name":"Qualigo Gmbh",
    "wof:placetype":"venue"
},
  "geometry": {"coordinates":[9.1562738419,47.6699295044],"type":"Point"}
}