{
  "type": "Feature",
  "properties": {
    "iso:country":"DE",
    "sg:address":"Klein-Calden",
    "sg:city":"Calden",
    "sg:phone":"+49 5674/7010",
    "sg:postcode":"34379",
    "sg:province":"Hessen",
    "wof:name":"Zf Luftfahrttechnik Gmbh",
    "wof:placetype":"venue"
},
  "geometry": {"coordinates":[9.3729572296,51.4005966187],"type":"Point"}
}