{
  "type": "Feature",
  "properties": {
    "iso:country":"DE",
    "sg:address":"Bahnhofstr. 13 a",
    "sg:city":"Brilon",
    "sg:postcode":"59929",
    "sg:province":"Nordrhein-Westfalen",
    "wof:name":"Carpe Diem Simone Geck-leppek E. Kfr.",
    "wof:placetype":"venue"
},
  "geometry": {"coordinates":[8.5699615479,51.3955154419],"type":"Point"}
}