{
  "type": "Feature",
  "properties": {
    "iso:country":"DE",
    "sg:address":"K\u00f6nigstr. 3 b",
    "sg:city":"Wietzendorf",
    "sg:phone":"+49 5196/1603",
    "sg:postcode":"29649",
    "sg:province":"Niedersachsen",
    "wof:name":"Elke Brockmann",
    "wof:placetype":"venue"
},
  "geometry": {"coordinates":[9.9741239548,52.91847229],"type":"Point"}
}