{
  "type": "Feature",
  "properties": {
    "iso:country":"DE",
    "sg:address":"Obere Kirchstr. 16",
    "sg:city":"Eltville",
    "sg:phone":"+49 6123/72245",
    "sg:postcode":"65344",
    "sg:province":"Hessen",
    "wof:name":"Jakob Scharhag Kohlen-handlung",
    "wof:placetype":"venue"
},
  "geometry": {"coordinates":[8.12033,50.052422],"type":"Point"}
}