{
  "type": "Feature",
  "properties": {
    "iso:country":"DE",
    "sg:address":"Hinter den G\u00e4rten 1",
    "sg:city":"Ettlingen",
    "sg:phone":"+49 7243/52060",
    "sg:postcode":"76275",
    "sg:province":"Baden-W\u00fcrttemberg",
    "wof:name":"Frank St\u00e4hle Handelsagentur Gmbh",
    "wof:placetype":"venue"
},
  "geometry": {"coordinates":[8.4352092743,48.911819458],"type":"Point"}
}