{
  "type": "Feature",
  "properties": {
    "iso:country":"DE",
    "sg:address":"K\u00f6tzenm\u00fchle",
    "sg:city":"Schl\u00fcchtern",
    "sg:phone":"+49 6661/2605",
    "sg:postcode":"36381",
    "sg:province":"Hessen",
    "wof:name":"Hans Kohlhepp Elektroinstallation",
    "wof:placetype":"venue"
},
  "geometry": {"coordinates":[9.532842,50.31995],"type":"Point"}
}