{
  "type": "Feature",
  "properties": {
    "iso:country":"DE",
    "sg:address":"Hauffstr. 1",
    "sg:city":"Riedlingen",
    "sg:phone":"+49 7371/2560",
    "sg:postcode":"88499",
    "sg:province":"Baden-W\u00fcrttemberg",
    "wof:name":"Kurt Kadus Architekt",
    "wof:placetype":"venue"
},
  "geometry": {"coordinates":[9.467847,48.156719],"type":"Point"}
}