{
  "type": "Feature",
  "properties": {
    "iso:country":"DE",
    "sg:address":"Plochinger Str. 12",
    "sg:city":"K\u00f6ngen",
    "sg:phone":"+49 7024/82621",
    "sg:postcode":"73257",
    "sg:province":"Baden-W\u00fcrttemberg",
    "wof:name":"Old Pub",
    "wof:placetype":"venue"
},
  "geometry": {"coordinates":[9.3673467636,48.6800956726],"type":"Point"}
}