{
  "type": "Feature",
  "properties": {
    "iso:country":"DE",
    "sg:address":"Im Haderwald 5",
    "sg:city":"Kaiserslautern",
    "sg:phone":"+49 631/59076",
    "sg:postcode":"67661",
    "sg:province":"Rheinland-Pfalz",
    "wof:name":"H. Schmelzer",
    "wof:placetype":"venue"
},
  "geometry": {"coordinates":[7.6781449318,49.4314498901],"type":"Point"}
}