{
  "type": "Feature",
  "properties": {
    "iso:country":"DE",
    "sg:address":"Bahnhofstr. 5",
    "sg:city":"Herrsching",
    "sg:phone":"+49 8152/6703",
    "sg:postcode":"82211",
    "sg:province":"Bayern",
    "wof:name":"Harald Trepte Ingenieur",
    "wof:placetype":"venue"
},
  "geometry": {"coordinates":[11.176181,47.998638],"type":"Point"}
}