{
  "type": "Feature",
  "properties": {
    "iso:country":"DE",
    "sg:address":"Edelrather Weg 187",
    "sg:city":"Leverkusen",
    "sg:phone":"+49 214/52407",
    "sg:postcode":"51375",
    "sg:province":"Nordrhein-Westfalen",
    "wof:name":"Heinrich Hertel",
    "wof:placetype":"venue"
},
  "geometry": {"coordinates":[7.0811638832,51.0324821472],"type":"Point"}
}