{
  "type": "Feature",
  "properties": {
    "iso:country":"DE",
    "sg:address":"Ludwigstr. 15",
    "sg:city":"Bad Nauheim",
    "sg:phone":"+49 6032/93010",
    "sg:postcode":"61231",
    "sg:province":"Hessen",
    "wof:name":"Erich Kreuzer Steuerberater",
    "wof:placetype":"venue"
},
  "geometry": {"coordinates":[8.745347023,50.3661956787],"type":"Point"}
}