{
  "type": "Feature",
  "properties": {
    "iso:country":"DE",
    "sg:address":"Altonaer Str. 70-72",
    "sg:city":"Berlin",
    "sg:postcode":"13581",
    "sg:province":"Berlin",
    "wof:name":"Thiem Systems E. K.",
    "wof:placetype":"venue"
},
  "geometry": {"coordinates":[13.1869344711,52.5326499939],"type":"Point"}
}