{
  "type": "Feature",
  "properties": {
    "iso:country":"DE",
    "sg:address":"Tannenweg 10",
    "sg:city":"Schiffweiler",
    "sg:phone":"+49 6821/963322",
    "sg:postcode":"66578",
    "sg:province":"Saarland",
    "wof:name":"Rudi Thiel Gmbh",
    "wof:placetype":"venue"
},
  "geometry": {"coordinates":[7.130311,49.370701],"type":"Point"}
}