{
  "type": "Feature",
  "properties": {
    "iso:country":"DE",
    "sg:address":"Friedrichstr. 31",
    "sg:city":"Lahr",
    "sg:phone":"+49 7821/22859",
    "sg:postcode":"77933",
    "sg:province":"Baden-W\u00fcrttemberg",
    "wof:name":"Ehrensberger",
    "wof:placetype":"venue"
},
  "geometry": {"coordinates":[7.8766150475,48.3416976929],"type":"Point"}
}