{
  "type": "Feature",
  "properties": {
    "iso:country":"DE",
    "sg:address":"Ohrdrufer Str. 13",
    "sg:city":"Frankenhain",
    "sg:phone":"+49 36205/95461",
    "sg:postcode":"99330",
    "sg:province":"Th\u00fcringen",
    "wof:name":"W. Ostermann",
    "wof:placetype":"venue"
},
  "geometry": {"coordinates":[10.7912721634,50.7573356628],"type":"Point"}
}