{
  "type": "Feature",
  "properties": {
    "iso:country":"DE",
    "sg:address":"Brahmsstr. 12",
    "sg:city":"Weimar",
    "sg:postcode":"99423",
    "sg:province":"Th\u00fcringen",
    "wof:name":"Tauerinvent Georg Tauer & Partner Gmbh",
    "wof:placetype":"venue"
},
  "geometry": {"coordinates":[11.3161993027,50.9821395874],"type":"Point"}
}