{
  "type": "Feature",
  "properties": {
    "iso:country":"DE",
    "sg:address":"Dachsbau 1",
    "sg:city":"Haltern",
    "sg:phone":"+49 2364/69290",
    "sg:postcode":"45721",
    "sg:province":"Nordrhein-Westfalen",
    "wof:name":"Eugen Dickerhoff",
    "wof:placetype":"venue"
},
  "geometry": {"coordinates":[7.2213029861,51.762840271],"type":"Point"}
}