{
  "type": "Feature",
  "properties": {
    "iso:country":"DE",
    "sg:address":"H\u00fclsbergstr. 59 b",
    "sg:city":"Bochum",
    "sg:phone":"+49 234/795423",
    "sg:postcode":"44797",
    "sg:province":"Nordrhein-Westfalen",
    "wof:name":"Michael Zimmermann Rechtsanwalt",
    "wof:placetype":"venue"
},
  "geometry": {"coordinates":[7.2196669579,51.4327316284],"type":"Point"}
}