{
  "type": "Feature",
  "properties": {
    "iso:country":"DE",
    "sg:address":"K\u00fcsterkamp 27",
    "sg:city":"Melle",
    "sg:phone":"+49 5226/379",
    "sg:postcode":"49328",
    "sg:province":"Niedersachsen",
    "wof:name":"Verein Zur Erhaltung Der Westhoyeler Windm\u00fchlen",
    "wof:placetype":"venue"
},
  "geometry": {"coordinates":[8.4232797623,52.1833686829],"type":"Point"}
}