{
  "type": "Feature",
  "properties": {
    "iso:country":"DE",
    "sg:address":"Am St\u00fccksken 19",
    "sg:city":"Duisburg",
    "sg:phone":"+49 2125",
    "sg:postcode":"42778",
    "sg:province":"Nordrhein-Westfalen",
    "wof:name":"Nelfort",
    "wof:placetype":"venue"
},
  "geometry": {"coordinates":[6.76395,51.431419],"type":"Point"}
}