{
  "type": "Feature",
  "properties": {
    "iso:country":"DE",
    "sg:address":"Am Freibad 3",
    "sg:city":"Dinklage",
    "sg:phone":"+49 4443/1318",
    "sg:postcode":"49413",
    "sg:province":"Niedersachsen",
    "wof:name":"Franz-josef Bl\u00f6mer",
    "wof:placetype":"venue"
},
  "geometry": {"coordinates":[8.1367883682,52.6634483337],"type":"Point"}
}