{
  "type": "Feature",
  "properties": {
    "iso:country":"DE",
    "sg:address":"Bergstr.",
    "sg:city":"Friedrichroda",
    "sg:phone":"+49 3623/4565",
    "sg:postcode":"99894",
    "sg:province":"Th\u00fcringen",
    "wof:name":"Berghotel Friedrichroda Gmbh",
    "wof:placetype":"venue"
},
  "geometry": {"coordinates":[10.6396341324,50.8562393188],"type":"Point"}
}