{
  "type": "Feature",
  "properties": {
    "iso:country":"DE",
    "sg:address":"Naumburger Str.",
    "sg:city":"Zeitz",
    "sg:phone":"+49 3441/211327",
    "sg:postcode":"06712",
    "sg:province":"Sachsen-Anhalt",
    "wof:name":"H. Sch\u00e4fer",
    "wof:placetype":"venue"
},
  "geometry": {"coordinates":[12.1297798157,51.0602607727],"type":"Point"}
}