{
  "type": "Feature",
  "properties": {
    "iso:country":"DE",
    "sg:address":"Bahnhofstr. 39",
    "sg:city":"Naumburg",
    "sg:phone":"+49 5625/378",
    "sg:postcode":"34311",
    "sg:province":"Hessen",
    "wof:name":"H. Lippe Steinmetzbetrieb",
    "wof:placetype":"venue"
},
  "geometry": {"coordinates":[9.1709508896,51.2518539429],"type":"Point"}
}