{
  "type": "Feature",
  "properties": {
    "iso:country":"DE",
    "sg:address":"Herrmannstr.29",
    "sg:city":"Berlin",
    "sg:phone":"+49 4930/8139874",
    "sg:postcode":"14163",
    "sg:province":"Berlin",
    "wof:name":"Brave Old World Inc.",
    "wof:placetype":"venue"
},
  "geometry": {"coordinates":[13.2343473434,52.4471282959],"type":"Point"}
}