{
  "type": "Feature",
  "properties": {
    "iso:country":"DE",
    "sg:address":"Bornholmer Str. 6",
    "sg:city":"Berlin",
    "sg:postcode":"10439",
    "sg:province":"Berlin",
    "wof:name":"Uni-tec Maschinen Gmbh",
    "wof:placetype":"venue"
},
  "geometry": {"coordinates":[13.4124555588,52.5541572571],"type":"Point"}
}