{
  "type": "Feature",
  "properties": {
    "iso:country":"DE",
    "sg:address":"Ostheimer Weg 8",
    "sg:city":"Gotha",
    "sg:postcode":"99867",
    "sg:province":"Th\u00fcringen",
    "wof:name":"Victoria Versicherungen",
    "wof:placetype":"venue"
},
  "geometry": {"coordinates":[10.6924152374,50.9610481262],"type":"Point"}
}