{
  "type": "Feature",
  "properties": {
    "iso:country":"DE",
    "sg:address":"Stra\u00dfe des Friedens 63",
    "sg:city":"Limbach-Oberfrohna",
    "sg:phone":"+49 3722/92339",
    "sg:postcode":"09212",
    "sg:province":"Sachsen",
    "wof:name":"Heinz Geigenm\u00fcller",
    "wof:placetype":"venue"
},
  "geometry": {"coordinates":[12.750113,50.861439],"type":"Point"}
}