{
  "type": "Feature",
  "properties": {
    "iso:country":"DE",
    "sg:address":"Frankengraben 11-13",
    "sg:city":"Bonn",
    "sg:postcode":"53175",
    "sg:province":"Nordrhein-Westfalen",
    "wof:name":"Elektro Hubert Stuch Gmbh",
    "wof:placetype":"venue"
},
  "geometry": {"coordinates":[7.1264891624,50.6982460022],"type":"Point"}
}