{
  "type": "Feature",
  "properties": {
    "iso:country":"DE",
    "sg:address":"Einsteinallee 2",
    "sg:city":"Lahr",
    "sg:phone":"+49 7821/906890",
    "sg:postcode":"77933",
    "sg:province":"Baden-W\u00fcrttemberg",
    "wof:name":"G\u00fcnther Brennstoffe Gmbh",
    "wof:placetype":"venue"
},
  "geometry": {"coordinates":[7.807296,48.353741],"type":"Point"}
}