{
  "type": "Feature",
  "properties": {
    "iso:country":"DE",
    "sg:address":"Gerhart-Hauptmann-Str. 21",
    "sg:city":"Ginsheim-Gustavsburg",
    "sg:phone":"+49 6144/2534",
    "sg:postcode":"65462",
    "sg:province":"Hessen",
    "wof:name":"Innova Handels- Und Werbe- Agentur Hanno Janz E. Kfm.",
    "wof:placetype":"venue"
},
  "geometry": {"coordinates":[8.3429317474,49.969493866],"type":"Point"}
}