{
  "type": "Feature",
  "properties": {
    "iso:country":"DE",
    "sg:address":"Am Walde 36",
    "sg:city":"Haverlah",
    "sg:phone":"+49 5341/331036",
    "sg:postcode":"38275",
    "sg:province":"Niedersachsen",
    "wof:name":"Heinz Westermann",
    "wof:placetype":"venue"
},
  "geometry": {"coordinates":[10.333395,52.073566],"type":"Point"}
}