{
  "type": "Feature",
  "properties": {
    "iso:country":"DE",
    "sg:address":"H\u00e4selweg 35",
    "sg:city":"Pleidelsheim",
    "sg:phone":"+49 7144/207995",
    "sg:postcode":"74385",
    "sg:province":"Baden-W\u00fcrttemberg",
    "wof:name":"Thomas Bender",
    "wof:placetype":"venue"
},
  "geometry": {"coordinates":[9.211926,48.967091],"type":"Point"}
}