{
  "type": "Feature",
  "properties": {
    "iso:country":"DE",
    "sg:address":"Steinweg 5",
    "sg:city":"Kreiensen",
    "sg:phone":"+49 5563/70010",
    "sg:postcode":"37547",
    "sg:province":"Niedersachsen",
    "wof:name":"Schelm Gastst\u00e4tten Gmbh",
    "wof:placetype":"venue"
},
  "geometry": {"coordinates":[9.9437561035,51.8589134216],"type":"Point"}
}