{
  "type": "Feature",
  "properties": {
    "iso:country":"DE",
    "sg:address":"An der Erftaue 9",
    "sg:city":"Bergheim",
    "sg:phone":"+49 2271/41049",
    "sg:postcode":"50126",
    "sg:province":"Nordrhein-Westfalen",
    "wof:name":"H. Aberle Rechtsanwalt",
    "wof:placetype":"venue"
},
  "geometry": {"coordinates":[6.6323490143,50.9598350525],"type":"Point"}
}