{
  "type": "Feature",
  "properties": {
    "iso:country":"DE",
    "sg:address":"Rudolf-Diesel-Str. 4",
    "sg:city":"Wiesloch",
    "sg:phone":"+49 6222/74371",
    "sg:postcode":"69168",
    "sg:province":"Baden-W\u00fcrttemberg",
    "wof:name":"Benno Stroh",
    "wof:placetype":"venue"
},
  "geometry": {"coordinates":[8.7455749512,49.2975654602],"type":"Point"}
}