{
  "type": "Feature",
  "properties": {
    "iso:country":"DE",
    "sg:address":"Ambo\u00dfstr.",
    "sg:city":"Wuppertal",
    "sg:phone":"+49 202/471087",
    "sg:postcode":"42349",
    "sg:province":"Nordrhein-Westfalen",
    "wof:name":"H.-d. Gronau",
    "wof:placetype":"venue"
},
  "geometry": {"coordinates":[7.1349802017,51.2063751221],"type":"Point"}
}