{
  "type": "Feature",
  "properties": {
    "iso:country":"DE",
    "sg:address":"Bavariaring 29",
    "sg:city":"M\u00fcnchen",
    "sg:postcode":"80336",
    "sg:province":"Bayern",
    "wof:name":"Reha Spezial Gutekunst Gmbh",
    "wof:placetype":"venue"
},
  "geometry": {"coordinates":[11.553659,48.130688],"type":"Point"}
}