{
  "type": "Feature",
  "properties": {
    "iso:country":"DE",
    "sg:address":"Ohmstr. 9",
    "sg:city":"Dachau",
    "sg:phone":"+49 8131/1898",
    "sg:postcode":"85221",
    "sg:province":"Bayern",
    "wof:name":"Horst-peter Gmbh",
    "wof:placetype":"venue"
},
  "geometry": {"coordinates":[11.4771718979,48.2673072815],"type":"Point"}
}