{
  "type": "Feature",
  "properties": {
    "iso:country":"DE",
    "sg:address":"Geseker Str. 8",
    "sg:city":"Geseke",
    "sg:phone":"+49 2942/9749305",
    "sg:postcode":"59590",
    "sg:province":"Nordrhein-Westfalen",
    "wof:name":"Eugen L\u00fcchtefeld Heilpraktiker",
    "wof:placetype":"venue"
},
  "geometry": {"coordinates":[8.4556522369,51.6756744385],"type":"Point"}
}