{
  "type": "Feature",
  "properties": {
    "iso:country":"DE",
    "sg:address":"Sandweg 13",
    "sg:city":"Bietigheim-Bissingen",
    "sg:phone":"+49 7142/773551",
    "sg:postcode":"74321",
    "sg:province":"Baden-W\u00fcrttemberg",
    "wof:name":"Sch\u00fcller Gmbh",
    "wof:placetype":"venue"
},
  "geometry": {"coordinates":[9.137579,48.961414],"type":"Point"}
}