{
  "type": "Feature",
  "properties": {
    "iso:country":"DE",
    "sg:address":"K\u00f6lnische Str. 116",
    "sg:city":"Kassel",
    "sg:phone":"+49 561/15352",
    "sg:postcode":"34119",
    "sg:province":"Hessen",
    "wof:name":"Wolfgang Ahrens",
    "wof:placetype":"venue"
},
  "geometry": {"coordinates":[9.476276,51.317673],"type":"Point"}
}