{
  "type": "Feature",
  "properties": {
    "iso:country":"DE",
    "sg:address":"Schepersweg 92",
    "sg:city":"Wesel",
    "sg:phone":"+49 281/206550",
    "sg:postcode":"46485",
    "sg:province":"Nordrhein-Westfalen",
    "wof:name":"Dzk Dienstleistungszentrum F\u00fcr Krankenkassen Gmbh",
    "wof:placetype":"venue"
},
  "geometry": {"coordinates":[6.640271,51.662025],"type":"Point"}
}