{
  "type": "Feature",
  "properties": {
    "iso:country":"DE",
    "sg:address":"Marienplatz 1",
    "sg:city":"Ebersberg",
    "sg:phone":"+49 8092/2470",
    "sg:postcode":"85560",
    "sg:province":"Bayern",
    "wof:name":"Stadtarchiv",
    "wof:placetype":"venue"
},
  "geometry": {"coordinates":[11.968835,48.078159],"type":"Point"}
}