{
  "type": "Feature",
  "properties": {
    "iso:country":"DE",
    "sg:address":"Rosenplatz 11",
    "sg:city":"M\u00fcnster",
    "sg:phone":"+49 251/57899",
    "sg:postcode":"48143",
    "sg:province":"Nordrhein-Westfalen",
    "wof:name":"Stadtb\u00e4ckerei M\u00fcnster Limberg Gmbh",
    "wof:placetype":"venue"
},
  "geometry": {"coordinates":[7.621554,51.965122],"type":"Point"}
}