{
  "type": "Feature",
  "properties": {
    "iso:country":"DE",
    "sg:address":"Adolfstr. 26",
    "sg:city":"Braunschweig",
    "sg:phone":"+49 531/273790",
    "sg:postcode":"38102",
    "sg:province":"Niedersachsen",
    "wof:name":"Steuerberatungsges. Ekt Treuhandgesellschaft Mbh",
    "wof:placetype":"venue"
},
  "geometry": {"coordinates":[10.5325803757,52.2583236694],"type":"Point"}
}