{
  "type": "Feature",
  "properties": {
    "iso:country":"DE",
    "sg:address":"Jachenauer Str. 35",
    "sg:city":"Lenggries",
    "sg:phone":"+49 8042/2259",
    "sg:postcode":"83661",
    "sg:province":"Bayern",
    "wof:name":"Alois Leichmann Elektroinstallation",
    "wof:placetype":"venue"
},
  "geometry": {"coordinates":[11.575906,47.663597],"type":"Point"}
}