{
  "type": "Feature",
  "properties": {
    "iso:country":"DE",
    "sg:address":"Hamburger Str. 143",
    "sg:city":"Heide",
    "sg:phone":"+49 481/86071",
    "sg:postcode":"25746",
    "sg:province":"Schleswig-Holstein",
    "wof:name":"Heinrich Stade Gmbh & Co. Bohrunternehmen Kg",
    "wof:placetype":"venue"
},
  "geometry": {"coordinates":[9.120585,54.197861],"type":"Point"}
}