{
  "type": "Feature",
  "properties": {
    "iso:country":"DE",
    "sg:address":"Ortrander Str. 20",
    "sg:city":"Lauchhammer",
    "sg:phone":"+49 3574/2248",
    "sg:postcode":"01979",
    "sg:province":"Brandenburg",
    "wof:name":"Uwe Schm\u00e4hl Ingenieur",
    "wof:placetype":"venue"
},
  "geometry": {"coordinates":[13.7646532059,51.4924125671],"type":"Point"}
}