{
  "type": "Feature",
  "properties": {
    "iso:country":"DE",
    "sg:address":"An der Ro\u00dfweid 9",
    "sg:city":"Karlsruhe",
    "sg:phone":"+49 721/61810",
    "sg:postcode":"76229",
    "sg:province":"Baden-W\u00fcrttemberg",
    "wof:name":"Binding Brauerei Ag",
    "wof:placetype":"venue"
},
  "geometry": {"coordinates":[8.471354,49.029964],"type":"Point"}
}