{
  "type": "Feature",
  "properties": {
    "iso:country":"DE",
    "sg:address":"Hermann-Herder-Str. 7",
    "sg:city":"Freiburg",
    "sg:postcode":"79104",
    "sg:province":"Baden-W\u00fcrttemberg",
    "wof:name":"Biochemisches Institut Bibliothek",
    "wof:placetype":"venue"
},
  "geometry": {"coordinates":[7.849775,48.002823],"type":"Point"}
}