{
  "type": "Feature",
  "properties": {
    "iso:country":"DE",
    "sg:address":"Badtorstr. 2",
    "sg:city":"Schrozberg",
    "sg:phone":"+49 7935/230",
    "sg:postcode":"74575",
    "sg:province":"Baden-W\u00fcrttemberg",
    "wof:name":"Robert Nussbaum",
    "wof:placetype":"venue"
},
  "geometry": {"coordinates":[9.980561,49.344799],"type":"Point"}
}