{
  "type": "Feature",
  "properties": {
    "iso:country":"DE",
    "sg:address":"Hegestr. 7",
    "sg:city":"Hamburg",
    "sg:phone":"+49 40/474648",
    "sg:postcode":"20251",
    "sg:province":"Hamburg",
    "wof:name":"Hege-zwerg",
    "wof:placetype":"venue"
},
  "geometry": {"coordinates":[9.9814739227,53.5832214355],"type":"Point"}
}