{
  "type": "Feature",
  "properties": {
    "iso:country":"DE",
    "sg:address":"Professor-Bier-Str. 7 a",
    "sg:city":"Korbach",
    "sg:postcode":"34497",
    "sg:province":"Hessen",
    "wof:name":"Mgm Bau Gmbh",
    "wof:placetype":"venue"
},
  "geometry": {"coordinates":[8.87143,51.275452],"type":"Point"}
}