{
  "type": "Feature",
  "properties": {
    "iso:country":"DE",
    "sg:address":"Wilhelmstr. 16",
    "sg:city":"Weikersheim",
    "sg:phone":"+49 7934/1569",
    "sg:postcode":"97990",
    "sg:province":"Baden-W\u00fcrttemberg",
    "wof:name":"Hermann Emmert",
    "wof:placetype":"venue"
},
  "geometry": {"coordinates":[9.900084,49.480572],"type":"Point"}
}