{
  "type": "Feature",
  "properties": {
    "iso:country":"DE",
    "sg:address":"Blankenburger Weg 8",
    "sg:city":"Frankfurt",
    "sg:phone":"+49 69/362488",
    "sg:postcode":"65931",
    "sg:province":"Hessen",
    "wof:name":"Roman Bartholome Bildhauer",
    "wof:placetype":"venue"
},
  "geometry": {"coordinates":[8.500697,50.092098],"type":"Point"}
}