{
  "type": "Feature",
  "properties": {
    "iso:country":"DE",
    "sg:address":"Waldstr. 2",
    "sg:city":"Gelsenkirchen",
    "sg:phone":"+49 209/72359",
    "sg:postcode":"45891",
    "sg:province":"Nordrhein-Westfalen",
    "wof:name":"Fotostudio Grundmann",
    "wof:placetype":"venue"
},
  "geometry": {"coordinates":[7.0935249329,51.5582542419],"type":"Point"}
}