{
  "type": "Feature",
  "properties": {
    "iso:country":"DE",
    "sg:address":"M\u00f6hlenau 17",
    "sg:city":"M\u00fchlenbarbek",
    "sg:phone":"+49 4822/3261",
    "sg:postcode":"25548",
    "sg:province":"Schleswig-Holstein",
    "wof:name":"Lutz Freund",
    "wof:placetype":"venue"
},
  "geometry": {"coordinates":[9.675239563,53.9617881775],"type":"Point"}
}