{
  "type": "Feature",
  "properties": {
    "iso:country":"DE",
    "sg:address":"Dorfstr. 10",
    "sg:city":"Atterwasch",
    "sg:phone":"+49 35692/242",
    "sg:postcode":"03172",
    "sg:province":"Brandenburg",
    "wof:name":"Gastst\u00e4tte Michael Berger",
    "wof:placetype":"venue"
},
  "geometry": {"coordinates":[14.6419296265,51.9538383484],"type":"Point"}
}