{
  "type": "Feature",
  "properties": {
    "iso:country":"DE",
    "sg:address":"Plessestr.",
    "sg:city":"Hasel\u00fcnne",
    "sg:postcode":"49740",
    "sg:province":"Niedersachsen",
    "wof:name":"Comet",
    "wof:placetype":"venue"
},
  "geometry": {"coordinates":[7.4902091026,52.673614502],"type":"Point"}
}