{
  "type": "Feature",
  "properties": {
    "iso:country":"DE",
    "sg:address":"Blumenstr. 119",
    "sg:city":"Emsdetten",
    "sg:phone":"+49 2572/93840",
    "sg:postcode":"48282",
    "sg:province":"Nordrhein-Westfalen",
    "wof:name":"Stottrop-textil Gmbh & Co. Kg",
    "wof:placetype":"venue"
},
  "geometry": {"coordinates":[7.5407919884,52.1604728699],"type":"Point"}
}