{
  "type": "Feature",
  "properties": {
    "iso:country":"DE",
    "sg:address":"Elzer Stra\u00dfe 74",
    "sg:city":"Hildesheim",
    "sg:phone":"+49 5121/97370",
    "sg:postcode":"33137",
    "sg:province":"Niedersachsen",
    "wof:name":"Hoffmann Erdbau & Abbruch",
    "wof:placetype":"venue"
},
  "geometry": {"coordinates":[9.92068,52.15612],"type":"Point"}
}