{
  "type": "Feature",
  "properties": {
    "iso:country":"DE",
    "sg:address":"Heinkelstr. 2",
    "sg:city":"Neu-Ulm",
    "sg:phone":"+49 731/78371",
    "sg:postcode":"89231",
    "sg:province":"Bayern",
    "wof:name":"Teamfoto Ulm Gmbh",
    "wof:placetype":"venue"
},
  "geometry": {"coordinates":[10.0192108154,48.3840866089],"type":"Point"}
}