{
  "type": "Feature",
  "properties": {
    "iso:country":"DE",
    "sg:address":"W\u00fcrzburger Str. 1",
    "sg:city":"Hammelburg",
    "sg:phone":"+49 9732/2282",
    "sg:postcode":"97762",
    "sg:province":"Bayern",
    "wof:name":"M. Hermann",
    "wof:placetype":"venue"
},
  "geometry": {"coordinates":[9.897301,50.116116],"type":"Point"}
}