{
  "type": "Feature",
  "properties": {
    "iso:country":"DE",
    "sg:address":"Untere Hauptstr. 23",
    "sg:city":"Freising",
    "sg:phone":"+49 8161/12106",
    "sg:postcode":"85354",
    "sg:province":"Bayern",
    "wof:name":"Hartl-schuster Und Parma Rechtsanw\u00e4lte",
    "wof:placetype":"venue"
},
  "geometry": {"coordinates":[11.7465429306,48.4016418457],"type":"Point"}
}