{
  "type": "Feature",
  "properties": {
    "iso:country":"DE",
    "sg:address":"Am Stadtbach 8",
    "sg:city":"G\u00fcnzburg",
    "sg:phone":"+49 8221/4021",
    "sg:postcode":"89312",
    "sg:province":"Bayern",
    "wof:name":"Dr. Ludwig R\u00f6ll Notar",
    "wof:placetype":"venue"
},
  "geometry": {"coordinates":[10.2826004028,48.4522247314],"type":"Point"}
}