{
  "type": "Feature",
  "properties": {
    "iso:country":"DE",
    "sg:address":"Lange Wiese 25",
    "sg:city":"Burgstall",
    "sg:phone":"+49 39364/367",
    "sg:postcode":"39517",
    "sg:province":"Sachsen-Anhalt",
    "wof:name":"Eiscafe M. Schulz",
    "wof:placetype":"venue"
},
  "geometry": {"coordinates":[11.69944,52.41045],"type":"Point"}
}