{
  "type": "Feature",
  "properties": {
    "iso:country":"DE",
    "sg:address":"Plaggestr. 41",
    "sg:city":"Schortens",
    "sg:phone":"+49 4461/82294",
    "sg:postcode":"26419",
    "sg:province":"Niedersachsen",
    "wof:name":"W. U. D. Speckmann",
    "wof:placetype":"venue"
},
  "geometry": {"coordinates":[7.9564499855,53.53099823],"type":"Point"}
}