{
  "type": "Feature",
  "properties": {
    "iso:country":"DE",
    "sg:address":"Schl\u00fcterstr. 39",
    "sg:city":"Berlin",
    "sg:phone":"+49 30/8844030",
    "sg:postcode":"10629",
    "sg:province":"Berlin",
    "wof:name":"Italienisches Institut F\u00fcr Au\u00dfenhandel",
    "wof:placetype":"venue"
},
  "geometry": {"coordinates":[13.3166828156,52.5020103455],"type":"Point"}
}