{
  "type": "Feature",
  "properties": {
    "iso:country":"DE",
    "sg:address":"Reichestrasse 11",
    "sg:city":"Salzwedel",
    "sg:phone":"+49 163 4393784",
    "sg:postcode":"29410",
    "sg:province":"Sachsen-Anhalt",
    "wof:name":"Uniq Media",
    "wof:placetype":"venue"
},
  "geometry": {"coordinates":[11.152904,52.85358],"type":"Point"}
}