{
  "type": "Feature",
  "properties": {
    "iso:country":"DE",
    "sg:address":"In Gerderhahn 88",
    "sg:city":"Erkelenz",
    "sg:phone":"+49 2431/5159",
    "sg:postcode":"41812",
    "sg:province":"Nordrhein-Westfalen",
    "wof:name":"Werner Hahn",
    "wof:placetype":"venue"
},
  "geometry": {"coordinates":[6.241272,51.097118],"type":"Point"}
}