{
  "type": "Feature",
  "properties": {
    "iso:country":"DE",
    "sg:address":"Gro\u00df Sterneberger Str. 18",
    "sg:city":"Hammah",
    "sg:phone":"+49 4144/1268",
    "sg:postcode":"21714",
    "sg:province":"Niedersachsen",
    "wof:name":"Karl-heinz Appel",
    "wof:placetype":"venue"
},
  "geometry": {"coordinates":[9.38944,53.633137],"type":"Point"}
}