{
  "type": "Feature",
  "properties": {
    "iso:country":"DE",
    "sg:address":"M\u00fchleweg 1",
    "sg:city":"Eisenbach",
    "sg:phone":"+49 4976/57322",
    "sg:postcode":"79871",
    "sg:province":"Baden-W\u00fcrttemberg",
    "wof:name":"Sparkasse Hochschwarzwald",
    "wof:placetype":"venue"
},
  "geometry": {"coordinates":[9.112692,49.834332],"type":"Point"}
}