{
  "type": "Feature",
  "properties": {
    "iso:country":"DE",
    "sg:address":"Im Gotthelf 6",
    "sg:city":"Hattersheim",
    "sg:phone":"+49 6145/33001",
    "sg:postcode":"65795",
    "sg:province":"Hessen",
    "wof:name":"Georg Gernhard Gmbh",
    "wof:placetype":"venue"
},
  "geometry": {"coordinates":[8.464948,50.033478],"type":"Point"}
}