{
  "type": "Feature",
  "properties": {
    "iso:country":"DE",
    "sg:address":"Max-Brauer-Allee 86",
    "sg:city":"Hamburg",
    "sg:phone":"+49 40/382556",
    "sg:postcode":"22765",
    "sg:province":"Hamburg",
    "wof:name":"Gastst\u00e4tte Woodpecker",
    "wof:placetype":"venue"
},
  "geometry": {"coordinates":[9.9424295425,53.5552597046],"type":"Point"}
}