{
  "type": "Feature",
  "properties": {
    "iso:country":"DE",
    "sg:address":"Untere Alpe 6",
    "sg:city":"Icking",
    "sg:phone":"+49 8171/10934",
    "sg:postcode":"82057",
    "sg:province":"Bayern",
    "wof:name":"Bavaria Finanz Agentur Gmbh",
    "wof:placetype":"venue"
},
  "geometry": {"coordinates":[11.3982639313,47.9392814636],"type":"Point"}
}