{
  "type": "Feature",
  "properties": {
    "iso:country":"DE",
    "sg:address":"Bahnhofstr. 20",
    "sg:city":"Schwerte",
    "sg:phone":"+49 2304/15272",
    "sg:postcode":"58239",
    "sg:province":"Nordrhein-Westfalen",
    "wof:name":"Karl-heinz Schubert",
    "wof:placetype":"venue"
},
  "geometry": {"coordinates":[7.562474,51.442101],"type":"Point"}
}