{
  "type": "Feature",
  "properties": {
    "iso:country":"DE",
    "sg:address":"Carl-Zeiss-Str. 51",
    "sg:city":"G\u00fctersloh",
    "sg:phone":"+49 5241/76266",
    "sg:postcode":"33334",
    "sg:province":"Nordrhein-Westfalen",
    "wof:name":"H. Richter",
    "wof:placetype":"venue"
},
  "geometry": {"coordinates":[8.4162006378,51.9293365479],"type":"Point"}
}