{
  "type": "Feature",
  "properties": {
    "iso:country":"DE",
    "sg:address":"R\u00f6mstedter Str. 25",
    "sg:city":"Bad Bevensen",
    "sg:phone":"+49 5821/967404",
    "sg:postcode":"29549",
    "sg:province":"Niedersachsen",
    "wof:name":"Med Quality Forschungsges. Mbh",
    "wof:placetype":"venue"
},
  "geometry": {"coordinates":[10.6022520065,53.0861968994],"type":"Point"}
}