{
  "type": "Feature",
  "properties": {
    "iso:country":"DE",
    "sg:address":"Erkerdinger Str. 16",
    "sg:city":"Hengersberg",
    "sg:phone":"+49 9901/7718",
    "sg:postcode":"94491",
    "sg:province":"Bayern",
    "wof:name":"German Habermann",
    "wof:placetype":"venue"
},
  "geometry": {"coordinates":[13.055241,48.779953],"type":"Point"}
}