{
  "type": "Feature",
  "properties": {
    "iso:country":"DE",
    "sg:address":"Reinthal 118",
    "sg:city":"Weyarn",
    "sg:phone":"+49 8020/646",
    "sg:postcode":"83629",
    "sg:province":"Bayern",
    "wof:name":"Tulpen Gmbh",
    "wof:placetype":"venue"
},
  "geometry": {"coordinates":[11.820848465,47.8528060913],"type":"Point"}
}