{
  "type": "Feature",
  "properties": {
    "iso:country":"DE",
    "sg:address":"Postfach 102",
    "sg:city":"Wei\u00dfenbrunn",
    "sg:phone":"+49 172 8442244",
    "sg:postcode":"96369",
    "sg:province":"Bayern",
    "wof:name":"Secuguard - Personenschutz",
    "wof:placetype":"venue"
},
  "geometry": {"coordinates":[11.346298,50.200218],"type":"Point"}
}