{
  "type": "Feature",
  "properties": {
    "iso:country":"DE",
    "sg:address":"Fischerpf\u00f6rtchen 7",
    "sg:city":"Worms",
    "sg:phone":"+49 6241/23657",
    "sg:postcode":"67547",
    "sg:province":"Rheinland-Pfalz",
    "wof:name":"Franz K\u00f6nig",
    "wof:placetype":"venue"
},
  "geometry": {"coordinates":[8.366625,49.629189],"type":"Point"}
}