{
  "type": "Feature",
  "properties": {
    "iso:country":"DE",
    "sg:address":"Hans-Marchwitza-Ring 1",
    "sg:city":"Potsdam",
    "sg:phone":"+49 331/711627",
    "sg:postcode":"14473",
    "sg:province":"Brandenburg",
    "wof:name":"Dr. Med. Peter Hoffmann Arzt F\u00fcr Allgemeinmedizin",
    "wof:placetype":"venue"
},
  "geometry": {"coordinates":[13.0775651932,52.3951835632],"type":"Point"}
}