{
  "type": "Feature",
  "properties": {
    "iso:country":"DE",
    "sg:address":"Daimlerstr 1",
    "sg:city":"Pfullingen",
    "sg:phone":"+49 7121/7506080",
    "sg:postcode":"72793",
    "sg:province":"Baden-W\u00fcrttemberg",
    "wof:name":"Hagenloch Metallbearbeitung Gmbh",
    "wof:placetype":"venue"
},
  "geometry": {"coordinates":[9.2284755707,48.4783210754],"type":"Point"}
}