{
  "type": "Feature",
  "properties": {
    "iso:country":"DE",
    "sg:address":"Heidenhof 7",
    "sg:city":"Soltau",
    "sg:postcode":"29614",
    "sg:province":"Niedersachsen",
    "wof:name":"Stapelfeldt Bauges. Mbh",
    "wof:placetype":"venue"
},
  "geometry": {"coordinates":[9.841318,52.986729],"type":"Point"}
}