{
  "type": "Feature",
  "properties": {
    "iso:country":"DE",
    "sg:address":"Baumschulenweg",
    "sg:city":"Genthin",
    "sg:postcode":"39307",
    "sg:province":"Sachsen-Anhalt",
    "wof:name":"Gerhard Werner",
    "wof:placetype":"venue"
},
  "geometry": {"coordinates":[12.160805,52.399151],"type":"Point"}
}