{
  "type": "Feature",
  "properties": {
    "iso:country":"DE",
    "sg:address":"Taubenstr. 55",
    "sg:city":"Emsdetten",
    "sg:phone":"+49 2572/5042",
    "sg:postcode":"48282",
    "sg:province":"Nordrhein-Westfalen",
    "wof:name":"Tonius Hilbert Mineral\u00f6lgro\u00dfhandlung",
    "wof:placetype":"venue"
},
  "geometry": {"coordinates":[7.5103797913,52.1637802124],"type":"Point"}
}