{
  "type": "Feature",
  "properties": {
    "iso:country":"DE",
    "sg:address":"Hauptstr. 77",
    "sg:city":"Tambach-Dietharz",
    "sg:postcode":"99897",
    "sg:province":"Th\u00fcringen",
    "wof:name":"Evangelische-luth. Kirche",
    "wof:placetype":"venue"
},
  "geometry": {"coordinates":[10.6088657379,50.7919769287],"type":"Point"}
}