{
  "type": "Feature",
  "properties": {
    "iso:country":"DE",
    "sg:address":"Am Neuen Deich 2",
    "sg:city":"Dorum",
    "sg:phone":"+49 4741/96970",
    "sg:postcode":"27632",
    "sg:province":"Niedersachsen",
    "wof:name":"Deichhotel Grube Inh. Olaf Wurm",
    "wof:placetype":"venue"
},
  "geometry": {"coordinates":[8.5194101334,53.7388687134],"type":"Point"}
}