{
  "type": "Feature",
  "properties": {
    "iso:country":"DE",
    "sg:address":"Am Waldrand 2",
    "sg:city":"Wernrode",
    "sg:phone":"+49 36334/50066",
    "sg:postcode":"99735",
    "sg:province":"Th\u00fcringen",
    "wof:name":"Dirk Beyermann",
    "wof:placetype":"venue"
},
  "geometry": {"coordinates":[10.736998558,51.4001083374],"type":"Point"}
}