{
  "type": "Feature",
  "properties": {
    "iso:country":"DE",
    "sg:address":"Nonnenstrasse 11c",
    "sg:city":"Leipzig",
    "sg:phone":"+49 341",
    "sg:postcode":"04229",
    "sg:province":"Sachsen",
    "wof:name":"Edv Problemloesung And Software Entwicklung",
    "wof:placetype":"venue"
},
  "geometry": {"coordinates":[12.344862,51.32951],"type":"Point"}
}