{
  "type": "Feature",
  "properties": {
    "iso:country":"DE",
    "sg:address":"Frohnhausen 7",
    "sg:city":"H\u00fcckeswagen",
    "sg:phone":"+49 2192/2384",
    "sg:postcode":"42499",
    "sg:province":"Nordrhein-Westfalen",
    "wof:name":"Walter Hager",
    "wof:placetype":"venue"
},
  "geometry": {"coordinates":[7.344907,51.160065],"type":"Point"}
}