{
  "type": "Feature",
  "properties": {
    "iso:country":"DE",
    "sg:address":"Wei\u00dfenburger Str. 25",
    "sg:city":"Eichst\u00e4tt",
    "sg:phone":"+49 8421/97150",
    "sg:postcode":"85072",
    "sg:province":"Bayern",
    "wof:name":"Finanz- Und Versorgungsservice Franz X. Obeth",
    "wof:placetype":"venue"
},
  "geometry": {"coordinates":[11.1843338013,48.8906288147],"type":"Point"}
}