{
  "type": "Feature",
  "properties": {
    "iso:country":"DE",
    "sg:address":"Marienthaler Str. 31",
    "sg:city":"Schermbeck",
    "sg:phone":"+49 2856/580",
    "sg:postcode":"46514",
    "sg:province":"Nordrhein-Westfalen",
    "wof:name":"Ernst Tebbe",
    "wof:placetype":"venue"
},
  "geometry": {"coordinates":[6.747769,51.720188],"type":"Point"}
}