{
  "type": "Feature",
  "properties": {
    "iso:country":"DE",
    "sg:address":"Krakeloh 31",
    "sg:city":"Arnsberg",
    "sg:phone":"+49 2932/33308",
    "sg:postcode":"59757",
    "sg:province":"Nordrhein-Westfalen",
    "wof:name":"Franz Voss",
    "wof:placetype":"venue"
},
  "geometry": {"coordinates":[7.9986348152,51.404083252],"type":"Point"}
}