{
  "type": "Feature",
  "properties": {
    "iso:country":"DE",
    "sg:address":"Hauptstr. 510",
    "sg:city":"Idar-Oberstein",
    "sg:phone":"+49 6781/20970",
    "sg:postcode":"55743",
    "sg:province":"Rheinland-Pfalz",
    "wof:name":"Joachim K\u00f6nig",
    "wof:placetype":"venue"
},
  "geometry": {"coordinates":[7.3338570595,49.7038726807],"type":"Point"}
}