{
  "type": "Feature",
  "properties": {
    "iso:country":"DE",
    "sg:address":"Bachstr. 2",
    "sg:city":"Bad Saulgau",
    "sg:phone":"+49 7581/7529",
    "sg:postcode":"88348",
    "sg:province":"Baden-W\u00fcrttemberg",
    "wof:name":"Paulus",
    "wof:placetype":"venue"
},
  "geometry": {"coordinates":[9.4990653992,48.0168914795],"type":"Point"}
}