{
  "type": "Feature",
  "properties": {
    "iso:country":"DE",
    "sg:address":"Distlerstr. 37",
    "sg:city":"Stuttgart",
    "sg:phone":"+49 711/424977",
    "sg:postcode":"70184",
    "sg:province":"Baden-W\u00fcrttemberg",
    "wof:name":"Heinrich Verhoeven Auskunftei",
    "wof:placetype":"venue"
},
  "geometry": {"coordinates":[9.219628,48.762241],"type":"Point"}
}