{
  "type": "Feature",
  "properties": {
    "iso:country":"DE",
    "sg:address":"Kaiserstr. 24",
    "sg:city":"Dortmund",
    "sg:phone":"+49 231/526130",
    "sg:postcode":"44135",
    "sg:province":"Nordrhein-Westfalen",
    "wof:name":"Zum Advokaten",
    "wof:placetype":"venue"
},
  "geometry": {"coordinates":[7.4750418663,51.5138587952],"type":"Point"}
}