{
  "type": "Feature",
  "properties": {
    "iso:country":"DE",
    "sg:address":"Appenweierstr. 6",
    "sg:city":"Offenburg",
    "sg:phone":"+49 781/9706533",
    "sg:postcode":"77652",
    "sg:province":"Baden-W\u00fcrttemberg",
    "wof:name":"Peter Scheuffele Rechtsanwalt",
    "wof:placetype":"venue"
},
  "geometry": {"coordinates":[7.9634227753,48.514465332],"type":"Point"}
}