{
  "type": "Feature",
  "properties": {
    "iso:country":"DE",
    "sg:address":"Gartenstr. 30",
    "sg:city":"W\u00fcstenrot",
    "sg:phone":"+49 7945/651",
    "sg:postcode":"71543",
    "sg:province":"Baden-W\u00fcrttemberg",
    "wof:name":"Ernst Pfeiffer Elektroinstallation",
    "wof:placetype":"venue"
},
  "geometry": {"coordinates":[9.488197,49.108421],"type":"Point"}
}