{
  "type": "Feature",
  "properties": {
    "iso:country":"DE",
    "sg:address":"Poststr. 5",
    "sg:city":"Celle",
    "sg:phone":"+49 5141/21354",
    "sg:postcode":"29221",
    "sg:province":"Niedersachsen",
    "wof:name":"Hermann Hensel",
    "wof:placetype":"venue"
},
  "geometry": {"coordinates":[10.0818586349,52.6231956482],"type":"Point"}
}