{
  "type": "Feature",
  "properties": {
    "iso:country":"DE",
    "sg:address":"Arnulfstra\u00dfe 6",
    "sg:city":"K\u00f6ln",
    "sg:postcode":"50937",
    "sg:province":"Nordrhein-Westfalen",
    "wof:name":"Erotik Versand",
    "wof:placetype":"venue"
},
  "geometry": {"coordinates":[6.930480957,50.9194564819],"type":"Point"}
}