{
  "type": "Feature",
  "properties": {
    "iso:country":"DE",
    "sg:address":"Elbestr. 1",
    "sg:city":"Friesoythe",
    "sg:phone":"+49 4491/3198",
    "sg:postcode":"26169",
    "sg:province":"Niedersachsen",
    "wof:name":"Edith Hemmen Kg",
    "wof:placetype":"venue"
},
  "geometry": {"coordinates":[7.848464,53.014942],"type":"Point"}
}