{
  "type": "Feature",
  "properties": {
    "iso:country":"DE",
    "sg:address":"Halfinger Str. 4",
    "sg:city":"S\u00f6chtenau",
    "sg:phone":"+49 8055/474",
    "sg:postcode":"83139",
    "sg:province":"Bayern",
    "wof:name":"Zur Post",
    "wof:placetype":"venue"
},
  "geometry": {"coordinates":[12.2316999435,47.9321403503],"type":"Point"}
}