{
  "type": "Feature",
  "properties": {
    "iso:country":"DE",
    "sg:address":"M\u00fcnsterstr. 61",
    "sg:city":"D\u00fclmen",
    "sg:phone":"+49 2594/99510",
    "sg:postcode":"48249",
    "sg:province":"Nordrhein-Westfalen",
    "wof:name":"Kolpinghaus",
    "wof:placetype":"venue"
},
  "geometry": {"coordinates":[7.2813467979,51.8327445984],"type":"Point"}
}