{
  "type": "Feature",
  "properties": {
    "iso:country":"DE",
    "sg:address":"Eutelis-Platz 2",
    "sg:city":"Ratingen",
    "sg:phone":"+49 2102/1060",
    "sg:postcode":"40878",
    "sg:province":"Nordrhein-Westfalen",
    "wof:name":"Infitel Deutschland Ohg",
    "wof:placetype":"venue"
},
  "geometry": {"coordinates":[6.840506,51.30389],"type":"Point"}
}