{
  "type": "Feature",
  "properties": {
    "iso:country":"DE",
    "sg:address":"F\u00e4rbergraben 4",
    "sg:city":"M\u00fcnchen",
    "sg:phone":"+49 89/2608051",
    "sg:postcode":"80331",
    "sg:province":"Bayern",
    "wof:name":"Pfaff Handels- Gmbh",
    "wof:placetype":"venue"
},
  "geometry": {"coordinates":[11.5710802078,48.1376571655],"type":"Point"}
}