{
  "type": "Feature",
  "properties": {
    "iso:country":"DE",
    "sg:address":"Gentestr. 53",
    "sg:city":"Verl",
    "sg:phone":"+49 5246/4617",
    "sg:postcode":"33415",
    "sg:province":"Nordrhein-Westfalen",
    "wof:name":"Hans R\u00f6chter",
    "wof:placetype":"venue"
},
  "geometry": {"coordinates":[8.541625,51.863827],"type":"Point"}
}