{
  "type": "Feature",
  "properties": {
    "iso:country":"DE",
    "sg:address":"Frankfurter Str. 40",
    "sg:city":"Limburg",
    "sg:phone":"+49 6431/947815",
    "sg:postcode":"65549",
    "sg:province":"Hessen",
    "wof:name":"Busch & Jordan Antiquit\u00e4ten",
    "wof:placetype":"venue"
},
  "geometry": {"coordinates":[8.068401,50.384712],"type":"Point"}
}