{
  "type": "Feature",
  "properties": {
    "iso:country":"DE",
    "sg:address":"Stra\u00df\u00e4cker 31",
    "sg:city":"Murnau",
    "sg:phone":"+49 8841/99710",
    "sg:postcode":"82418",
    "sg:province":"Bayern",
    "wof:name":"Baywa Ag",
    "wof:placetype":"venue"
},
  "geometry": {"coordinates":[11.2019863129,47.6906471252],"type":"Point"}
}