{
  "type": "Feature",
  "properties": {
    "iso:country":"DE",
    "sg:address":"Bergstr. 9",
    "sg:city":"Roxheim",
    "sg:phone":"+49 671/45592",
    "sg:postcode":"55595",
    "sg:province":"Rheinland-Pfalz",
    "wof:name":"Deutscher Verband F\u00fcr Berufsberatung E. V.",
    "wof:placetype":"venue"
},
  "geometry": {"coordinates":[7.8151779175,49.8661727905],"type":"Point"}
}