{
  "type": "Feature",
  "properties": {
    "iso:country":"DE",
    "sg:address":"Blaumeisenweg 8",
    "sg:city":"Kiel",
    "sg:phone":"+49 431/680894",
    "sg:postcode":"24113",
    "sg:province":"Schleswig-Holstein",
    "wof:name":"H. Kreins",
    "wof:placetype":"venue"
},
  "geometry": {"coordinates":[10.1219730377,54.3016471863],"type":"Point"}
}