{
  "type": "Feature",
  "properties": {
    "iso:country":"DE",
    "sg:address":"Am Leninplatz 23",
    "sg:city":"Finowfurt",
    "sg:phone":"+49 3335/618",
    "sg:postcode":"16244",
    "sg:province":"Brandenburg",
    "wof:name":"Am \u00dcdersee",
    "wof:placetype":"venue"
},
  "geometry": {"coordinates":[13.6899280548,52.8470306396],"type":"Point"}
}