{
  "type": "Feature",
  "properties": {
    "iso:country":"DE",
    "sg:address":"Weingartlstr. 4",
    "sg:city":"Hengersberg",
    "sg:phone":"+49 9901/7460",
    "sg:postcode":"94491",
    "sg:province":"Bayern",
    "wof:name":"Ferdinand Wallner",
    "wof:placetype":"venue"
},
  "geometry": {"coordinates":[13.05605,48.78661],"type":"Point"}
}