{
  "type": "Feature",
  "properties": {
    "iso:country":"DE",
    "sg:address":"Raiffeisenstr. 29",
    "sg:city":"Biebern",
    "sg:phone":"+49 6761/908092",
    "sg:postcode":"55471",
    "sg:province":"Rheinland-Pfalz",
    "wof:name":"Jafona-verwaltungs- Und Mediaservice Gmbh",
    "wof:placetype":"venue"
},
  "geometry": {"coordinates":[7.4399709702,49.9911689758],"type":"Point"}
}