{
  "type": "Feature",
  "properties": {
    "iso:country":"DE",
    "sg:address":"M\u00fchlenstr. 6a",
    "sg:city":"K\u00f6ln",
    "sg:phone":"+49 2203/84671",
    "sg:postcode":"51143",
    "sg:province":"Nordrhein-Westfalen",
    "wof:name":"Ev. Pfarramt Porz",
    "wof:placetype":"venue"
},
  "geometry": {"coordinates":[7.0561847687,50.8808555603],"type":"Point"}
}