{
  "type": "Feature",
  "properties": {
    "iso:country":"DE",
    "sg:address":"Auer Str. 14",
    "sg:city":"L\u00f6\u00dfnitz",
    "sg:phone":"+49 3771/553574",
    "sg:postcode":"08294",
    "sg:province":"Sachsen",
    "wof:name":"R. Michael Gmbh",
    "wof:placetype":"venue"
},
  "geometry": {"coordinates":[12.71822,50.604511],"type":"Point"}
}