{
  "type": "Feature",
  "properties": {
    "iso:country":"DE",
    "sg:address":"Zeppelinweg 2",
    "sg:city":"M\u00f6lln",
    "sg:phone":"+49 4542/6880",
    "sg:postcode":"23879",
    "sg:province":"Schleswig-Holstein",
    "wof:name":"Jupp H\u00fcttmann",
    "wof:placetype":"venue"
},
  "geometry": {"coordinates":[10.6745691299,53.6062965393],"type":"Point"}
}