{
  "type": "Feature",
  "properties": {
    "iso:country":"DE",
    "sg:address":"Bahnhofstr. 58",
    "sg:city":"Michelstadt",
    "sg:postcode":"64720",
    "sg:province":"Hessen",
    "wof:name":"Huzur Supermarkt Ges. Mbh",
    "wof:placetype":"venue"
},
  "geometry": {"coordinates":[9.0015974045,49.6830406189],"type":"Point"}
}