{
  "type": "Feature",
  "properties": {
    "iso:country":"DE",
    "sg:address":"Bahnhofstr. 53",
    "sg:city":"Herne",
    "sg:phone":"+49 2323/50368",
    "sg:postcode":"44623",
    "sg:province":"Nordrhein-Westfalen",
    "wof:name":"Hettlage & Fischer Gmbh",
    "wof:placetype":"venue"
},
  "geometry": {"coordinates":[7.221969,51.540913],"type":"Point"}
}