{
  "type": "Feature",
  "properties": {
    "iso:country":"DE",
    "sg:address":"Rathausplatz 5",
    "sg:city":"Hemmoor",
    "sg:phone":"+49 4771/6020",
    "sg:postcode":"21745",
    "sg:province":"Niedersachsen",
    "wof:name":"Abwasser-entsorgung Hemmoor Gmbh",
    "wof:placetype":"venue"
},
  "geometry": {"coordinates":[9.157073,53.687519],"type":"Point"}
}