{
  "type": "Feature",
  "properties": {
    "iso:country":"DE",
    "sg:address":"Sonnenbichlstr. 31",
    "sg:city":"Nonnenhorn",
    "sg:phone":"+49 8382/8291",
    "sg:postcode":"88149",
    "sg:province":"Bayern",
    "wof:name":"Erich Gierer",
    "wof:placetype":"venue"
},
  "geometry": {"coordinates":[9.6159486771,47.5749282837],"type":"Point"}
}