{
  "type": "Feature",
  "properties": {
    "iso:country":"DE",
    "sg:address":"Obereckstr. 49a",
    "sg:city":"L\u00f6rrach",
    "sg:phone":"+49 7621/45212",
    "sg:postcode":"79539",
    "sg:province":"Baden-W\u00fcrttemberg",
    "wof:name":"Aric Advanced Risk Und Insurance Consulting Gmbh",
    "wof:placetype":"venue"
},
  "geometry": {"coordinates":[7.6765818596,47.6164131165],"type":"Point"}
}