{
  "type": "Feature",
  "properties": {
    "iso:country":"DE",
    "sg:address":"Schillbergstr. 23",
    "sg:city":"Wilnsdorf",
    "sg:phone":"+49 2737/91028",
    "sg:postcode":"57234",
    "sg:province":"Nordrhein-Westfalen",
    "wof:name":"W. G\u00f6rg",
    "wof:placetype":"venue"
},
  "geometry": {"coordinates":[8.1774110794,50.8478088379],"type":"Point"}
}