{
  "type": "Feature",
  "properties": {
    "iso:country":"DE",
    "sg:address":"Schaapwaschweg 3",
    "sg:city":"Harsefeld",
    "sg:phone":"+49 4163/5553",
    "sg:postcode":"21698",
    "sg:province":"Niedersachsen",
    "wof:name":"G. Wiessner",
    "wof:placetype":"venue"
},
  "geometry": {"coordinates":[9.514158,53.483299],"type":"Point"}
}