{
  "type": "Feature",
  "properties": {
    "iso:country":"DE",
    "sg:address":"B\u00fcnder Str. 55",
    "sg:city":"Enger",
    "sg:phone":"+49 5224/5679",
    "sg:postcode":"32130",
    "sg:province":"Nordrhein-Westfalen",
    "wof:name":"Heika-baubedarf Gmbh",
    "wof:placetype":"venue"
},
  "geometry": {"coordinates":[8.5626516342,52.1465187073],"type":"Point"}
}