{
  "type": "Feature",
  "properties": {
    "iso:country":"DE",
    "sg:address":"Paternusstr. 2",
    "sg:city":"Worms",
    "sg:phone":"+49 6247/5620",
    "sg:postcode":"67551",
    "sg:province":"Rheinland-Pfalz",
    "wof:name":"Cafe Royal",
    "wof:placetype":"venue"
},
  "geometry": {"coordinates":[8.2783021927,49.6348304749],"type":"Point"}
}