{
  "type": "Feature",
  "properties": {
    "iso:country":"DE",
    "sg:address":"Oberstr. 114",
    "sg:city":"Neuss",
    "sg:phone":"+49 2131/9701",
    "sg:postcode":"41460",
    "sg:province":"Nordrhein-Westfalen",
    "wof:name":"Stadtsparkasse Neuss",
    "wof:placetype":"venue"
},
  "geometry": {"coordinates":[6.693704,51.19722],"type":"Point"}
}