{
  "type": "Feature",
  "properties": {
    "iso:country":"DE",
    "sg:address":"Dettenh\u00e4user Str. 16",
    "sg:city":"Weil im Sch\u00f6nbuch",
    "sg:phone":"+49 7157/62194",
    "sg:postcode":"71093",
    "sg:province":"Baden-W\u00fcrttemberg",
    "wof:name":"Walter Ulmer",
    "wof:placetype":"venue"
},
  "geometry": {"coordinates":[9.0670852661,48.6222915649],"type":"Point"}
}