{
  "type": "Feature",
  "properties": {
    "iso:country":"DE",
    "sg:address":"Bismarckallee 10",
    "sg:city":"Freiburg",
    "sg:phone":"+49 761/23888",
    "sg:postcode":"79098",
    "sg:province":"Baden-W\u00fcrttemberg",
    "wof:name":"Mibicon Ges. F\u00fcr Mikrobilog. Und Biologisch-chemische",
    "wof:placetype":"venue"
},
  "geometry": {"coordinates":[7.84303,47.997631],"type":"Point"}
}