{
  "type": "Feature",
  "properties": {
    "iso:country":"DE",
    "sg:address":"Sch\u00fctzstra\u00dfe",
    "sg:city":"Kurtscheid",
    "sg:phone":"+49 2634",
    "sg:postcode":"56581",
    "sg:province":"Rheinland-Pfalz",
    "wof:name":"Nm Stahlger\u00e4te Gmbh",
    "wof:placetype":"venue"
},
  "geometry": {"coordinates":[7.4658050537,50.5351715088],"type":"Point"}
}