{
  "type": "Feature",
  "properties": {
    "iso:country":"DE",
    "sg:address":"Hauptstr 31",
    "sg:city":"K\u00f6nigsfeld",
    "sg:phone":"+49 3737/40811",
    "sg:postcode":"09306",
    "sg:province":"Sachsen",
    "wof:name":"Bothen & Kugler Gmbh",
    "wof:placetype":"venue"
},
  "geometry": {"coordinates":[12.749168,51.067284],"type":"Point"}
}