{
  "type": "Feature",
  "properties": {
    "iso:country":"DE",
    "sg:address":"Rinnstr. 13",
    "sg:city":"Laubach",
    "sg:phone":"+49 6405/1341",
    "sg:postcode":"35321",
    "sg:province":"Hessen",
    "wof:name":"Erwin Riedel",
    "wof:placetype":"venue"
},
  "geometry": {"coordinates":[9.0467567444,50.558921814],"type":"Point"}
}