{
  "type": "Feature",
  "properties": {
    "iso:country":"DE",
    "sg:address":"Genossenschaftsstr. 4",
    "sg:city":"Ahnsbeck",
    "sg:phone":"+49 5145/2550",
    "sg:postcode":"29353",
    "sg:province":"Niedersachsen",
    "wof:name":"Brunke",
    "wof:placetype":"venue"
},
  "geometry": {"coordinates":[10.2865228653,52.6094512939],"type":"Point"}
}