{
  "type": "Feature",
  "properties": {
    "iso:country":"DE",
    "sg:address":"Bremer Str. 14",
    "sg:city":"Marklohe",
    "sg:phone":"+49 5021/4941",
    "sg:postcode":"31608",
    "sg:province":"Niedersachsen",
    "wof:name":"Helmuth Rode",
    "wof:placetype":"venue"
},
  "geometry": {"coordinates":[9.137628,52.667912],"type":"Point"}
}