{
  "type": "Feature",
  "properties": {
    "iso:country":"DE",
    "sg:address":"Hauptstr. 14",
    "sg:city":"Dielheim",
    "sg:phone":"+49 6222/74463",
    "sg:postcode":"69234",
    "sg:province":"Baden-W\u00fcrttemberg",
    "wof:name":"L. Rothermel",
    "wof:placetype":"venue"
},
  "geometry": {"coordinates":[8.737515,49.282379],"type":"Point"}
}