{
  "type": "Feature",
  "properties": {
    "iso:country":"DE",
    "sg:address":"Kaiserstr. 23",
    "sg:city":"Berlin",
    "sg:postcode":"12209",
    "sg:province":"Berlin",
    "wof:name":"Zet 2 Exclusive Baggage Und Luggage Handelsges. Mbh",
    "wof:placetype":"venue"
},
  "geometry": {"coordinates":[13.32462,52.417519],"type":"Point"}
}