{
  "type": "Feature",
  "properties": {
    "iso:country":"DE",
    "sg:address":"L\u00fcner Kirchweg 4",
    "sg:city":"L\u00fcneburg",
    "sg:phone":"+49 4131/51381",
    "sg:postcode":"21337",
    "sg:province":"Niedersachsen",
    "wof:name":"Ev. Pfarramt I",
    "wof:placetype":"venue"
},
  "geometry": {"coordinates":[10.423418045,53.2603034973],"type":"Point"}
}