{
  "type": "Feature",
  "properties": {
    "iso:country":"DE",
    "sg:address":"Moosstr 46",
    "sg:city":"Bamberg",
    "sg:phone":"+49 951/918270",
    "sg:postcode":"96050",
    "sg:province":"Bayern",
    "wof:name":"Maisel Br\u00e4u Bamberg Privatbrauerei Gmbh",
    "wof:placetype":"venue"
},
  "geometry": {"coordinates":[10.913186,49.893173],"type":"Point"}
}