{
  "type": "Feature",
  "properties": {
    "iso:country":"DE",
    "sg:address":"Emkendorfstr. 38 a",
    "sg:city":"Hamburg",
    "sg:postcode":"22605",
    "sg:province":"Hamburg",
    "wof:name":"Andaco Consulting Und Trading Gmbh",
    "wof:placetype":"venue"
},
  "geometry": {"coordinates":[9.8928594589,53.5548629761],"type":"Point"}
}