{
  "type": "Feature",
  "properties": {
    "iso:country":"DE",
    "sg:address":"Hofer Str. 3",
    "sg:city":"Selbitz",
    "sg:phone":"+49 5541/700302",
    "sg:postcode":"95152",
    "sg:province":"Bayern",
    "wof:name":"Decotric Gmbh",
    "wof:placetype":"venue"
},
  "geometry": {"coordinates":[9.668557,51.447693],"type":"Point"}
}