{
  "type": "Feature",
  "properties": {
    "iso:country":"DE",
    "sg:address":"Bozzarisstr. 9 a",
    "sg:city":"M\u00fcnchen",
    "sg:phone":"+49 89/643822",
    "sg:postcode":"81545",
    "sg:province":"Bayern",
    "wof:name":"G\u00fcnther Koch Architekt",
    "wof:placetype":"venue"
},
  "geometry": {"coordinates":[11.569339,48.091553],"type":"Point"}
}