{
  "type": "Feature",
  "properties": {
    "iso:country":"DE",
    "sg:address":"Johannes-R.-Becher-Str. 12 a",
    "sg:city":"K\u00f6nigs Wusterhausen",
    "sg:postcode":"15711",
    "sg:province":"Brandenburg",
    "wof:name":"Flemming Dental Gmbh & Co. Kg",
    "wof:placetype":"venue"
},
  "geometry": {"coordinates":[13.6202068329,52.2906074524],"type":"Point"}
}