{
  "type": "Feature",
  "properties": {
    "iso:country":"DE",
    "sg:address":"Brachtesendeweg 170",
    "sg:city":"H\u00f6rstel",
    "sg:phone":"+49 5454/7152",
    "sg:postcode":"48477",
    "sg:province":"Nordrhein-Westfalen",
    "wof:name":"Isidor Seifert Landw.lohnbetrieb",
    "wof:placetype":"venue"
},
  "geometry": {"coordinates":[7.634081,52.230026],"type":"Point"}
}