{
  "type": "Feature",
  "properties": {
    "iso:country":"DE",
    "sg:address":"Ernst-Robert-Curtius-Str. 10",
    "sg:city":"Bonn",
    "sg:phone":"+49 228/559950",
    "sg:postcode":"53117",
    "sg:province":"Nordrhein-Westfalen",
    "wof:name":"Schallenberg Getr\u00e4nke Verwaltungs Gmbh",
    "wof:placetype":"venue"
},
  "geometry": {"coordinates":[7.0600671768,50.7542304993],"type":"Point"}
}