{
  "type": "Feature",
  "properties": {
    "iso:country":"DE",
    "sg:address":"Oderweg 3",
    "sg:city":"Zierenberg",
    "sg:phone":"+49 5606/51920",
    "sg:postcode":"34289",
    "sg:province":"Hessen",
    "wof:name":"Harald M\u00f6de Kg",
    "wof:placetype":"venue"
},
  "geometry": {"coordinates":[9.3167142868,51.3734016418],"type":"Point"}
}