{
  "type": "Feature",
  "properties": {
    "iso:country":"DE",
    "sg:address":"Schillerstr. 14",
    "sg:city":"Steinen",
    "sg:phone":"+49 7627/7452",
    "sg:postcode":"79585",
    "sg:province":"Baden-W\u00fcrttemberg",
    "wof:name":"Berthold Sutterer Immobilien Und Wohnbau Gmbh",
    "wof:placetype":"venue"
},
  "geometry": {"coordinates":[7.755864,47.641277],"type":"Point"}
}