{
  "type": "Feature",
  "properties": {
    "iso:country":"DE",
    "sg:address":"Einbleckstr. 53",
    "sg:city":"Oberhausen",
    "sg:phone":"+49 208/861423",
    "sg:postcode":"46117",
    "sg:province":"Nordrhein-Westfalen",
    "wof:name":"H.-w. J\u00fcnkersfeld Wettannahme",
    "wof:placetype":"venue"
},
  "geometry": {"coordinates":[6.911361,51.492603],"type":"Point"}
}