{
  "type": "Feature",
  "properties": {
    "iso:country":"DE",
    "sg:address":"Corinthstr. 4",
    "sg:city":"Dresden",
    "sg:phone":"+49 351/4707712",
    "sg:postcode":"01219",
    "sg:province":"Sachsen",
    "wof:name":"Roland Kloppe",
    "wof:placetype":"venue"
},
  "geometry": {"coordinates":[13.763642,51.021111],"type":"Point"}
}