{
  "type": "Feature",
  "properties": {
    "iso:country":"DE",
    "sg:address":"Friedrich-Ebert-Str. 33",
    "sg:city":"Dillingen",
    "sg:phone":"+49 6831/976707",
    "sg:postcode":"66763",
    "sg:province":"Saarland",
    "wof:name":"Erwin Sonnhalter",
    "wof:placetype":"venue"
},
  "geometry": {"coordinates":[6.7274250984,49.3584251404],"type":"Point"}
}