{
  "type": "Feature",
  "properties": {
    "iso:country":"DE",
    "sg:address":"Hauptstr. 22",
    "sg:city":"Eu\u00dfenheim",
    "sg:phone":"+49 9353/7755",
    "sg:postcode":"97776",
    "sg:province":"Bayern",
    "wof:name":"Kaufhaus Caecilie Emmert",
    "wof:placetype":"venue"
},
  "geometry": {"coordinates":[9.810225,49.990776],"type":"Point"}
}