{
  "type": "Feature",
  "properties": {
    "iso:country":"DE",
    "sg:address":"Pfleggasse 12",
    "sg:city":"Deggendorf",
    "sg:phone":"+49 991/4916",
    "sg:postcode":"94469",
    "sg:province":"Bayern",
    "wof:name":"Kurt Falk",
    "wof:placetype":"venue"
},
  "geometry": {"coordinates":[12.9632463455,48.8334541321],"type":"Point"}
}