{
  "type": "Feature",
  "properties": {
    "iso:country":"DE",
    "sg:address":"Glash\u00fctter Str. 20",
    "sg:city":"Sankt Englmar",
    "sg:phone":"+49 9965/209",
    "sg:postcode":"94379",
    "sg:province":"Bayern",
    "wof:name":"Pension-cafe J. Und E. Haimerl",
    "wof:placetype":"venue"
},
  "geometry": {"coordinates":[12.8250083923,49.0001792908],"type":"Point"}
}