{
  "type": "Feature",
  "properties": {
    "iso:country":"DE",
    "sg:address":"Von-H\u00fcnefeld-Str. 67",
    "sg:city":"Langenfeld",
    "sg:postcode":"40764",
    "sg:province":"Nordrhein-Westfalen",
    "wof:name":"Pamir Ohg",
    "wof:placetype":"venue"
},
  "geometry": {"coordinates":[6.9422550201,51.1133651733],"type":"Point"}
}