{
  "type": "Feature",
  "properties": {
    "iso:country":"DE",
    "sg:address":"Ditzinger Str. 32",
    "sg:city":"Gerlingen",
    "sg:phone":"+49 7156/21845",
    "sg:postcode":"70839",
    "sg:province":"Baden-W\u00fcrttemberg",
    "wof:name":"Hofwiesen- Grundst\u00fccksgesellschaft Mbh",
    "wof:placetype":"venue"
},
  "geometry": {"coordinates":[9.0640220642,48.8031311035],"type":"Point"}
}