{
  "type": "Feature",
  "properties": {
    "iso:country":"DE",
    "sg:address":"Oberm\u00f6llricher Str. 2",
    "sg:city":"Fritzlar",
    "sg:phone":"+49 5622/1836",
    "sg:postcode":"34560",
    "sg:province":"Hessen",
    "wof:name":"Helmut Grass",
    "wof:placetype":"venue"
},
  "geometry": {"coordinates":[9.309751,51.155396],"type":"Point"}
}