{
  "type": "Feature",
  "properties": {
    "iso:country":"DE",
    "sg:address":"M\u00fchlenweg 3",
    "sg:city":"B\u00f6rnicke",
    "sg:phone":"+49 33230/50334",
    "sg:postcode":"14641",
    "sg:province":"Brandenburg",
    "wof:name":"Pronutz Verwaltungs Gmbh",
    "wof:placetype":"venue"
},
  "geometry": {"coordinates":[12.8791751862,52.6088981628],"type":"Point"}
}