{
  "type": "Feature",
  "properties": {
    "iso:country":"DE",
    "sg:address":"M\u00f6llner Landstr. 144",
    "sg:city":"Hamburg",
    "sg:phone":"+49 40/7136759",
    "sg:postcode":"22117",
    "sg:province":"Hamburg",
    "wof:name":"M. Pitzka",
    "wof:placetype":"venue"
},
  "geometry": {"coordinates":[10.1268625259,53.5386924744],"type":"Point"}
}