{
  "type": "Feature",
  "properties": {
    "iso:country":"DE",
    "sg:address":"Roonstr. 61",
    "sg:city":"Oberhausen",
    "sg:phone":"+49 208/841427",
    "sg:postcode":"46049",
    "sg:province":"Nordrhein-Westfalen",
    "wof:name":"Bei Uns Zu Hause",
    "wof:placetype":"venue"
},
  "geometry": {"coordinates":[6.8397860527,51.4680328369],"type":"Point"}
}