{
  "type": "Feature",
  "properties": {
    "iso:country":"DE",
    "sg:address":"Bakenstr. 6",
    "sg:city":"Nottuln",
    "sg:phone":"+49 2509/8121",
    "sg:postcode":"48301",
    "sg:province":"Nordrhein-Westfalen",
    "wof:name":"Drees & S\u00f6hne",
    "wof:placetype":"venue"
},
  "geometry": {"coordinates":[7.34705,51.928631],"type":"Point"}
}