{
  "type": "Feature",
  "properties": {
    "iso:country":"DE",
    "sg:address":"Hermann-B\u00f6cker-Str. 6",
    "sg:city":"Dachau",
    "sg:phone":"+49 8131/85766",
    "sg:postcode":"85221",
    "sg:province":"Bayern",
    "wof:name":"H. Kirchmeier",
    "wof:placetype":"venue"
},
  "geometry": {"coordinates":[11.437877655,48.2344894409],"type":"Point"}
}