{
  "type": "Feature",
  "properties": {
    "iso:country":"DE",
    "sg:address":"Hauptstr. 6",
    "sg:city":"Zella-Mehlis",
    "sg:phone":"+49 3682/482107",
    "sg:postcode":"98544",
    "sg:province":"Th\u00fcringen",
    "wof:name":"Magdalenen-apotheke Hans-joachim Kehr E. K.",
    "wof:placetype":"venue"
},
  "geometry": {"coordinates":[10.654877,50.661465],"type":"Point"}
}