{
  "type": "Feature",
  "properties": {
    "iso:country":"DE",
    "sg:address":"Promenadenstr. 26",
    "sg:city":"Apolda",
    "sg:phone":"+49 3644/619706",
    "sg:postcode":"99510",
    "sg:province":"Th\u00fcringen",
    "wof:name":"Parkidyll",
    "wof:placetype":"venue"
},
  "geometry": {"coordinates":[11.509155,51.020931],"type":"Point"}
}