{
  "type": "Feature",
  "properties": {
    "iso:country":"DE",
    "sg:address":"Markt 40",
    "sg:city":"Lutherstadt Eisleben",
    "sg:phone":"+49 3475/602640",
    "sg:postcode":"06295",
    "sg:province":"Sachsen-Anhalt",
    "wof:name":"Reiseb\u00fcro",
    "wof:placetype":"venue"
},
  "geometry": {"coordinates":[11.5480527878,51.5280570984],"type":"Point"}
}