{
  "type": "Feature",
  "properties": {
    "iso:country":"DE",
    "sg:address":"Sch\u00e4ferstr. 38",
    "sg:city":"Bad W\u00fcnnenberg",
    "sg:phone":"+49 2953/8180",
    "sg:postcode":"33181",
    "sg:province":"Nordrhein-Westfalen",
    "wof:name":"Gerhard Lange",
    "wof:placetype":"venue"
},
  "geometry": {"coordinates":[8.703823,51.521011],"type":"Point"}
}