{
  "type": "Feature",
  "properties": {
    "iso:country":"DE",
    "sg:address":"Stephan-Schleich-Str. 4",
    "sg:city":"Landshut",
    "sg:phone":"+49 871/42961",
    "sg:postcode":"84036",
    "sg:province":"Bayern",
    "wof:name":"Ziegler Holzbau Verwaltungs-gmbh",
    "wof:placetype":"venue"
},
  "geometry": {"coordinates":[12.142367,48.525459],"type":"Point"}
}