{
  "type": "Feature",
  "properties": {
    "iso:country":"DE",
    "sg:address":"Am Degenried 32",
    "sg:city":"Aalen",
    "sg:phone":"+49 7366/919175",
    "sg:postcode":"73434",
    "sg:province":"Baden-W\u00fcrttemberg",
    "wof:name":"J\u00fcrgen Tobias Immobilienmakler",
    "wof:placetype":"venue"
},
  "geometry": {"coordinates":[10.0160446167,48.8658027649],"type":"Point"}
}