{
  "type": "Feature",
  "properties": {
    "iso:country":"DE",
    "sg:address":"Austr. 5",
    "sg:city":"\u00d6hringen",
    "sg:phone":"+49 7941/61711",
    "sg:postcode":"74613",
    "sg:province":"Baden-W\u00fcrttemberg",
    "wof:name":"Frankenstube",
    "wof:placetype":"venue"
},
  "geometry": {"coordinates":[9.4890127182,49.2054023743],"type":"Point"}
}