{
  "type": "Feature",
  "properties": {
    "iso:country":"DE",
    "sg:address":"Falkenberger Str. 168 A",
    "sg:city":"Berlin",
    "sg:phone":"+49 30/9251498",
    "sg:postcode":"13088",
    "sg:province":"Berlin",
    "wof:name":"Dr. Dieter Schulze Ingenieur Und Architekt",
    "wof:placetype":"venue"
},
  "geometry": {"coordinates":[13.475631,52.555725],"type":"Point"}
}