{
  "type": "Feature",
  "properties": {
    "iso:country":"DE",
    "sg:address":"Talweg 2",
    "sg:city":"Wertheim",
    "sg:phone":"+49 9342/7845",
    "sg:postcode":"97877",
    "sg:province":"Baden-W\u00fcrttemberg",
    "wof:name":"J\u00fcrgen Gr\u00fcn",
    "wof:placetype":"venue"
},
  "geometry": {"coordinates":[9.5238418579,49.7436561584],"type":"Point"}
}