{
  "type": "Feature",
  "properties": {
    "iso:country":"DE",
    "sg:address":"Schloss Strasse 4a",
    "sg:city":"Koblenz",
    "sg:phone":"+49 261",
    "sg:postcode":"56068",
    "sg:province":"Rheinland-Pfalz",
    "wof:name":"Fotograf Jarmusch",
    "wof:placetype":"venue"
},
  "geometry": {"coordinates":[7.597606,50.35643],"type":"Point"}
}