{
  "type": "Feature",
  "properties": {
    "iso:country":"DE",
    "sg:address":"Fellnerstr. 8",
    "sg:city":"Frankfurt",
    "sg:phone":"+49 69/5970330",
    "sg:postcode":"60322",
    "sg:province":"Hessen",
    "wof:name":"Aerolineas Dominicanas",
    "wof:placetype":"venue"
},
  "geometry": {"coordinates":[8.67721,50.11832],"type":"Point"}
}