{
  "type": "Feature",
  "properties": {
    "iso:country":"DE",
    "sg:address":"Bahnhofstr. 12",
    "sg:city":"Euskirchen",
    "sg:phone":"+49 2251/55668",
    "sg:postcode":"53879",
    "sg:province":"Nordrhein-Westfalen",
    "wof:name":"New System Textil-handels Gmbh",
    "wof:placetype":"venue"
},
  "geometry": {"coordinates":[6.791205,50.658932],"type":"Point"}
}