{
  "type": "Feature",
  "properties": {
    "iso:country":"DE",
    "sg:address":"Alter Weg 20",
    "sg:city":"Freiburg",
    "sg:phone":"+49 7664/93070",
    "sg:postcode":"79112",
    "sg:province":"Baden-W\u00fcrttemberg",
    "wof:name":"Acw Agentur F\u00fcr Creative Werbung Gmbh",
    "wof:placetype":"venue"
},
  "geometry": {"coordinates":[7.6979870796,47.9657554626],"type":"Point"}
}