{
  "type": "Feature",
  "properties": {
    "iso:country":"DE",
    "sg:address":"R\u00f6ddinger Str. 13",
    "sg:city":"Garbsen",
    "sg:phone":"+49 5137/73404",
    "sg:postcode":"30823",
    "sg:province":"Niedersachsen",
    "wof:name":"Norbert Sprei",
    "wof:placetype":"venue"
},
  "geometry": {"coordinates":[9.5990276337,52.4143562317],"type":"Point"}
}