{
  "type": "Feature",
  "properties": {
    "iso:country":"DE",
    "sg:address":"Hauptstr. 22",
    "sg:city":"D\u00fcmmer",
    "sg:phone":"+49 3869/516",
    "sg:postcode":"19073",
    "sg:province":"Mecklenburg-Vorpommern",
    "wof:name":"Zur Schmiede",
    "wof:placetype":"venue"
},
  "geometry": {"coordinates":[11.2047119141,53.5639228821],"type":"Point"}
}