{
  "type": "Feature",
  "properties": {
    "iso:country":"DE",
    "sg:address":"B\u00f6dekerstr. 85",
    "sg:city":"Hannover",
    "sg:phone":"+49 511/629474",
    "sg:postcode":"30161",
    "sg:province":"Niedersachsen",
    "wof:name":"Modejournal",
    "wof:placetype":"venue"
},
  "geometry": {"coordinates":[9.750267,52.388535],"type":"Point"}
}