{
  "type": "Feature",
  "properties": {
    "iso:country":"DE",
    "sg:address":"Kaiserstr 18-22",
    "sg:city":"Wetter",
    "sg:phone":"+49 33631/8950",
    "sg:postcode":"58300",
    "sg:province":"Nordrhein-Westfalen",
    "wof:name":"Stama Stahl- Und Maschinenbau Bad Saarow Gmbh",
    "wof:placetype":"venue"
},
  "geometry": {"coordinates":[13.996875,52.26469],"type":"Point"}
}