{
  "type": "Feature",
  "properties": {
    "iso:country":"DE",
    "sg:address":"Industriestr. 2",
    "sg:city":"Heiden",
    "sg:phone":"+49 2867/90073",
    "sg:postcode":"46359",
    "sg:province":"Nordrhein-Westfalen",
    "wof:name":"K & K Klaas & Kock Inh. Hans Klaas",
    "wof:placetype":"venue"
},
  "geometry": {"coordinates":[6.9445810318,51.824848175],"type":"Point"}
}