{
  "type": "Feature",
  "properties": {
    "iso:country":"DE",
    "sg:address":"Bireneichen 11",
    "sg:city":"Wuppertal",
    "sg:phone":"+49 202/80031",
    "sg:postcode":"42285",
    "sg:province":"Nordrhein-Westfalen",
    "wof:name":"Die Grauen Landesverband Nrw",
    "wof:placetype":"venue"
},
  "geometry": {"coordinates":[7.1794791222,51.2589836121],"type":"Point"}
}