{
  "type": "Feature",
  "properties": {
    "iso:country":"DE",
    "sg:address":"Holdorfer Str. 1",
    "sg:city":"Dinklage",
    "sg:phone":"+49 4443/4757",
    "sg:postcode":"49413",
    "sg:province":"Niedersachsen",
    "wof:name":"Mann Und Mode Gmbh",
    "wof:placetype":"venue"
},
  "geometry": {"coordinates":[8.120633,52.655678],"type":"Point"}
}