{
  "type": "Feature",
  "properties": {
    "iso:country":"DE",
    "sg:address":"Heckinghauser Str. 56",
    "sg:city":"Wuppertal",
    "sg:phone":"+49 202/2621241",
    "sg:postcode":"42289",
    "sg:province":"Nordrhein-Westfalen",
    "wof:name":"St. Georg-apotheke",
    "wof:placetype":"venue"
},
  "geometry": {"coordinates":[7.209322,51.271027],"type":"Point"}
}