{
  "type": "Feature",
  "properties": {
    "iso:country":"DE",
    "sg:address":"Pr\u00e4lat-Werthmann-Str. 3",
    "sg:city":"Geisenheim",
    "sg:phone":"+49 6722/64824",
    "sg:postcode":"65366",
    "sg:province":"Hessen",
    "wof:name":"Rainer Paulien",
    "wof:placetype":"venue"
},
  "geometry": {"coordinates":[7.9650402069,49.9845504761],"type":"Point"}
}