{
  "type": "Feature",
  "properties": {
    "iso:country":"DE",
    "sg:address":"Hauptstr. 4",
    "sg:city":"Elze",
    "sg:phone":"+49 5068/5306",
    "sg:postcode":"31008",
    "sg:province":"Niedersachsen",
    "wof:name":"Istanbul Athena",
    "wof:placetype":"venue"
},
  "geometry": {"coordinates":[9.7356462479,52.1214294434],"type":"Point"}
}