{
  "type": "Feature",
  "properties": {
    "iso:country":"DE",
    "sg:address":"Hauptstr. 15",
    "sg:city":"Oberkirch",
    "sg:phone":"+49 7802/6706",
    "sg:postcode":"77704",
    "sg:province":"Baden-W\u00fcrttemberg",
    "wof:name":"Wolfgang Ducksch Holzbildhauer",
    "wof:placetype":"venue"
},
  "geometry": {"coordinates":[8.082383,48.529156],"type":"Point"}
}