{
  "type": "Feature",
  "properties": {
    "iso:country":"DE",
    "sg:address":"Claus-Ferck-Str. 35",
    "sg:city":"Hamburg",
    "sg:phone":"+49 40/6031275",
    "sg:postcode":"22359",
    "sg:province":"Hamburg",
    "wof:name":"Helmut Kr\u00fcger",
    "wof:placetype":"venue"
},
  "geometry": {"coordinates":[10.165140152,53.6517410278],"type":"Point"}
}