{
  "type": "Feature",
  "properties": {
    "iso:country":"DE",
    "sg:address":"Sandweg 20",
    "sg:city":"Eppertshausen",
    "sg:phone":"+49 6071/391730",
    "sg:postcode":"64859",
    "sg:province":"Hessen",
    "wof:name":"Tier-exklusiv",
    "wof:placetype":"venue"
},
  "geometry": {"coordinates":[8.842028,49.951344],"type":"Point"}
}