{
  "type": "Feature",
  "properties": {
    "iso:country":"DE",
    "sg:address":"Hauptstr. 17",
    "sg:city":"Radebeul",
    "sg:phone":"+49 351/8308185",
    "sg:postcode":"01445",
    "sg:province":"Sachsen",
    "wof:name":"Mei\u00dfner",
    "wof:placetype":"venue"
},
  "geometry": {"coordinates":[13.6800222397,51.100818634],"type":"Point"}
}