{
  "type": "Feature",
  "properties": {
    "iso:country":"DE",
    "sg:address":"T\u00fcrrschmidtstr. 35",
    "sg:city":"Berlin",
    "sg:phone":"+49 30/5593220",
    "sg:postcode":"10317",
    "sg:province":"Berlin",
    "wof:name":"Hans-joachim Kr\u00fcger X",
    "wof:placetype":"venue"
},
  "geometry": {"coordinates":[13.480497,52.503216],"type":"Point"}
}