{
  "type": "Feature",
  "properties": {
    "iso:country":"DE",
    "sg:address":"Robert-Koch-Ring 43",
    "sg:city":"Meppen",
    "sg:phone":"+49 5931/16706",
    "sg:postcode":"49716",
    "sg:province":"Niedersachsen",
    "wof:name":"Stefan Meyer",
    "wof:placetype":"venue"
},
  "geometry": {"coordinates":[7.296293,52.674519],"type":"Point"}
}