{
  "type": "Feature",
  "properties": {
    "iso:country":"DE",
    "sg:address":"Lindauer Str. 58",
    "sg:city":"Wangen",
    "sg:phone":"+49 7522/3788",
    "sg:postcode":"88239",
    "sg:province":"Baden-W\u00fcrttemberg",
    "wof:name":"Simeon Brauchle",
    "wof:placetype":"venue"
},
  "geometry": {"coordinates":[9.824946,47.682804],"type":"Point"}
}