{
  "type": "Feature",
  "properties": {
    "iso:country":"DE",
    "sg:address":"Hauptstr. 13",
    "sg:city":"Breunigweiler",
    "sg:phone":"+49 6357/204",
    "sg:postcode":"67725",
    "sg:province":"Rheinland-Pfalz",
    "wof:name":"Zuspann",
    "wof:placetype":"venue"
},
  "geometry": {"coordinates":[7.9635977745,49.5694503784],"type":"Point"}
}