{
  "type": "Feature",
  "properties": {
    "iso:country":"DE",
    "sg:address":"Gerberg\u00e4\u00dfle 5",
    "sg:city":"Markgr\u00f6ningen",
    "sg:phone":"+49 7145/7474",
    "sg:postcode":"71706",
    "sg:province":"Baden-W\u00fcrttemberg",
    "wof:name":"Harald Hofmiller Rechtsanwalt",
    "wof:placetype":"venue"
},
  "geometry": {"coordinates":[9.0807323456,48.9042854309],"type":"Point"}
}