{
  "type": "Feature",
  "properties": {
    "iso:country":"DE",
    "sg:address":"Graben 14",
    "sg:city":"Heppenheim",
    "sg:phone":"+49 6252/93130",
    "sg:postcode":"64646",
    "sg:province":"Hessen",
    "wof:name":"Lbs Immobilien Gmbh",
    "wof:placetype":"venue"
},
  "geometry": {"coordinates":[8.6429243088,49.641834259],"type":"Point"}
}