{
  "type": "Feature",
  "properties": {
    "iso:country":"DE",
    "sg:address":"Sirchenrieder Str. 13",
    "sg:city":"Ried",
    "sg:phone":"+49 8233/5113",
    "sg:postcode":"86510",
    "sg:province":"Bayern",
    "wof:name":"Kommunale Dienstleistungs Gmbh",
    "wof:placetype":"venue"
},
  "geometry": {"coordinates":[11.043967,48.28894],"type":"Point"}
}