{
  "type": "Feature",
  "properties": {
    "iso:country":"DE",
    "sg:address":"Rebhuhnstr. 2-4",
    "sg:city":"Mannheim",
    "sg:phone":"+49 621/77070",
    "sg:postcode":"68307",
    "sg:province":"Baden-W\u00fcrttemberg",
    "wof:name":"Wilhelm Sch\u00e4fer Gmbh",
    "wof:placetype":"venue"
},
  "geometry": {"coordinates":[8.455579,49.549454],"type":"Point"}
}