{
  "type": "Feature",
  "properties": {
    "iso:country":"DE",
    "sg:address":"Nordertorstriftweg 49",
    "sg:city":"Nienburg",
    "sg:phone":"+49 5021/13170",
    "sg:postcode":"31582",
    "sg:province":"Niedersachsen",
    "wof:name":"Deutsche Bahn Ag",
    "wof:placetype":"venue"
},
  "geometry": {"coordinates":[9.2201099396,52.6423606873],"type":"Point"}
}