{
  "type": "Feature",
  "properties": {
    "iso:country":"DE",
    "sg:address":"Wiesbadener Str. 1a",
    "sg:city":"Eggenstein-Leopoldshafen",
    "sg:phone":"+49 7247/22151",
    "sg:postcode":"76344",
    "sg:province":"Baden-W\u00fcrttemberg",
    "wof:name":"Edith Wagner Heilpraktikerin",
    "wof:placetype":"venue"
},
  "geometry": {"coordinates":[8.4046401978,49.0993385315],"type":"Point"}
}