{
  "type": "Feature",
  "properties": {
    "iso:country":"DE",
    "sg:address":"Mozartstr. 300",
    "sg:city":"Luckenwalde",
    "sg:phone":"+49 3371/630490",
    "sg:postcode":"14943",
    "sg:province":"Brandenburg",
    "wof:name":"Gastst\u00e4tte In Der Gartenanlage",
    "wof:placetype":"venue"
},
  "geometry": {"coordinates":[13.1537504196,52.0867271423],"type":"Point"}
}