{
  "type": "Feature",
  "properties": {
    "iso:country":"DE",
    "sg:address":"An der Autobahn 40",
    "sg:city":"Oyten",
    "sg:phone":"+49 4207/913050",
    "sg:postcode":"28876",
    "sg:province":"Niedersachsen",
    "wof:name":"Bernhard Papenmeier Gmbh",
    "wof:placetype":"venue"
},
  "geometry": {"coordinates":[9.045071,53.057674],"type":"Point"}
}