{
  "type": "Feature",
  "properties": {
    "iso:country":"DE",
    "sg:address":"Ludwigstr. 14",
    "sg:city":"Bad Kissingen",
    "sg:phone":"+49 971/3450",
    "sg:postcode":"97688",
    "sg:province":"Bayern",
    "wof:name":"Brillen Voigt Augenoptik",
    "wof:placetype":"venue"
},
  "geometry": {"coordinates":[10.0771837234,50.1989707947],"type":"Point"}
}