{
  "type": "Feature",
  "properties": {
    "iso:country":"DE",
    "sg:address":"Oskar-Sommer-Str. 15",
    "sg:city":"Frankfurt",
    "sg:phone":"+49 69/635390",
    "sg:postcode":"60596",
    "sg:province":"Hessen",
    "wof:name":"Stresemannsch\u00e4nke Inh. D. Lappas",
    "wof:placetype":"venue"
},
  "geometry": {"coordinates":[8.671254158,50.0956993103],"type":"Point"}
}