{
  "type": "Feature",
  "properties": {
    "iso:country":"DE",
    "sg:address":"Eichenknick 2",
    "sg:city":"Hamburg",
    "sg:phone":"+49 40/5209752",
    "sg:postcode":"22415",
    "sg:province":"Hamburg",
    "wof:name":"Malerbetrieb Gmbh",
    "wof:placetype":"venue"
},
  "geometry": {"coordinates":[10.009535,53.651882],"type":"Point"}
}