{
  "type": "Feature",
  "properties": {
    "iso:country":"DE",
    "sg:address":"Fortm\u00fchlstr.",
    "sg:city":"Bellheim",
    "sg:phone":"+49 7272/919774",
    "sg:postcode":"76756",
    "sg:province":"Rheinland-Pfalz",
    "wof:name":"Penny-markt Gmbh",
    "wof:placetype":"venue"
},
  "geometry": {"coordinates":[8.2915220261,49.1930046082],"type":"Point"}
}