{
  "type": "Feature",
  "properties": {
    "iso:country":"DE",
    "sg:address":"Hoher Turm 19",
    "sg:city":"Hildesheim",
    "sg:phone":"+49 5121/21789",
    "sg:postcode":"31137",
    "sg:province":"Niedersachsen",
    "wof:name":"Stefan A. H\u00e4nisch",
    "wof:placetype":"venue"
},
  "geometry": {"coordinates":[9.9168901443,52.1597290039],"type":"Point"}
}