{
  "type": "Feature",
  "properties": {
    "iso:country":"DE",
    "sg:address":"Gasstr. 7-16",
    "sg:city":"Lage",
    "sg:phone":"+49 5232/6050",
    "sg:postcode":"32791",
    "sg:province":"Nordrhein-Westfalen",
    "wof:name":"Reiche Gmbh & Co. Kg",
    "wof:placetype":"venue"
},
  "geometry": {"coordinates":[8.8060369492,51.9889297485],"type":"Point"}
}