{
  "type": "Feature",
  "properties": {
    "iso:country":"DE",
    "sg:address":"Gildestr. 6",
    "sg:city":"Sonsbeck",
    "sg:postcode":"47665",
    "sg:province":"Nordrhein-Westfalen",
    "wof:name":"B & M Handels Gmbh",
    "wof:placetype":"venue"
},
  "geometry": {"coordinates":[6.3805232048,51.6038665771],"type":"Point"}
}