{
  "type": "Feature",
  "properties": {
    "iso:country":"DE",
    "sg:address":"Krokusweg 35",
    "sg:city":"Zirndorf",
    "sg:phone":"+49 9127/579716",
    "sg:postcode":"90513",
    "sg:province":"Bayern",
    "wof:name":"Josef Hipp",
    "wof:placetype":"venue"
},
  "geometry": {"coordinates":[10.9049110413,49.4269866943],"type":"Point"}
}