{
  "type": "Feature",
  "properties": {
    "iso:country":"DE",
    "sg:address":"Wilhelm-Gerlach-Str. 14",
    "sg:city":"Weimar",
    "sg:phone":"+49 6421/78190",
    "sg:postcode":"35096",
    "sg:province":"Hessen",
    "wof:name":"Ried Gmbh",
    "wof:placetype":"venue"
},
  "geometry": {"coordinates":[8.736779213,50.7636032104],"type":"Point"}
}