{
  "type": "Feature",
  "properties": {
    "iso:country":"DE",
    "sg:address":"Nieder Worth 1-10",
    "sg:city":"Schalksm\u00fchle",
    "sg:phone":"+49 4923/55820",
    "sg:postcode":"58579",
    "sg:province":"Nordrhein-Westfalen",
    "wof:name":"Wilhelm Rutenbeck Gmbh & Co",
    "wof:placetype":"venue"
},
  "geometry": {"coordinates":[7.5454058647,51.2416534424],"type":"Point"}
}