{
  "type": "Feature",
  "properties": {
    "iso:country":"DE",
    "sg:address":"Sonnenstr. 20",
    "sg:city":"M\u00fcnchen",
    "sg:phone":"+49 89/595421",
    "sg:postcode":"80331",
    "sg:province":"Bayern",
    "wof:name":"Florian Hau\u00dfleiter Rechtsanwalt",
    "wof:placetype":"venue"
},
  "geometry": {"coordinates":[11.5645313263,48.1360588074],"type":"Point"}
}