{
  "type": "Feature",
  "properties": {
    "iso:country":"DE",
    "sg:address":"K\u00f6titzer Str. 63",
    "sg:city":"Radebeul",
    "sg:phone":"+49 351/8386762",
    "sg:postcode":"01445",
    "sg:province":"Sachsen",
    "wof:name":"Otto Grosse",
    "wof:placetype":"venue"
},
  "geometry": {"coordinates":[13.611823,51.108685],"type":"Point"}
}