{
  "type": "Feature",
  "properties": {
    "iso:country":"DE",
    "sg:address":"Neustadt 517",
    "sg:city":"Landshut",
    "sg:phone":"+49 871/925910",
    "sg:postcode":"84028",
    "sg:province":"Bayern",
    "wof:name":"Igl Putz & Partner Ingenieurb\u00fcro",
    "wof:placetype":"venue"
},
  "geometry": {"coordinates":[12.1542739868,48.5360984802],"type":"Point"}
}