{
  "type": "Feature",
  "properties": {
    "iso:country":"DE",
    "sg:address":"Marktstr. 32",
    "sg:city":"Leutkirch",
    "sg:phone":"+49 7561/4223",
    "sg:postcode":"88299",
    "sg:province":"Baden-W\u00fcrttemberg",
    "wof:name":"A. K\u00e4stle Ohg",
    "wof:placetype":"venue"
},
  "geometry": {"coordinates":[10.02402,47.827396],"type":"Point"}
}