{
  "type": "Feature",
  "properties": {
    "iso:country":"DE",
    "sg:address":"Bernhard-B\u00e4stlein-Str. 3",
    "sg:city":"Berlin",
    "sg:phone":"+49 30/9720895",
    "sg:postcode":"10367",
    "sg:province":"Berlin",
    "wof:name":"Gabriele Hoffmann",
    "wof:placetype":"venue"
},
  "geometry": {"coordinates":[13.481664,52.527016],"type":"Point"}
}