{
  "type": "Feature",
  "properties": {
    "iso:country":"DE",
    "sg:address":"Am Brunnen 17",
    "sg:city":"Kirchheim",
    "sg:phone":"+49 89/9033366",
    "sg:postcode":"85551",
    "sg:province":"Bayern",
    "wof:name":"Praxis Dr. Hammer Und Dr. Med. Hingerle",
    "wof:placetype":"venue"
},
  "geometry": {"coordinates":[11.7509622574,48.1744422913],"type":"Point"}
}