{
  "type": "Feature",
  "properties": {
    "iso:country":"DE",
    "sg:address":"Friedensplatz 19",
    "sg:city":"Oestrich-Winkel",
    "sg:phone":"+49 6723/5032",
    "sg:postcode":"65375",
    "sg:province":"Hessen",
    "wof:name":"August Eser",
    "wof:placetype":"venue"
},
  "geometry": {"coordinates":[8.028336525,50.0065002441],"type":"Point"}
}