{
  "type": "Feature",
  "properties": {
    "iso:country":"DE",
    "sg:address":"Landshuter Str. 15",
    "sg:city":"Regensburg",
    "sg:phone":"+49 941/57036",
    "sg:postcode":"93047",
    "sg:province":"Bayern",
    "wof:name":"G. Braun Rechtsanwalt",
    "wof:placetype":"venue"
},
  "geometry": {"coordinates":[12.1055212021,49.0150146484],"type":"Point"}
}