{
  "type": "Feature",
  "properties": {
    "iso:country":"DE",
    "sg:address":"Pfarrhaus",
    "sg:city":"D\u00f6rentrup",
    "sg:phone":"+49 5265/8675",
    "sg:postcode":"32694",
    "sg:province":"Nordrhein-Westfalen",
    "wof:name":"Klasse B\u00f6singfeld",
    "wof:placetype":"venue"
},
  "geometry": {"coordinates":[9.0024499893,52.0334014893],"type":"Point"}
}