{
  "type": "Feature",
  "properties": {
    "iso:country":"DE",
    "sg:address":"Birkenweg 15",
    "sg:city":"B\u00f6tzingen",
    "sg:phone":"+49 7663/4537",
    "sg:postcode":"79268",
    "sg:province":"Baden-W\u00fcrttemberg",
    "wof:name":"Willi Sexauer",
    "wof:placetype":"venue"
},
  "geometry": {"coordinates":[7.710506916,48.0659980774],"type":"Point"}
}