{
  "type": "Feature",
  "properties": {
    "iso:country":"DE",
    "sg:address":"Fabrikstr. 10",
    "sg:city":"Esslingen",
    "sg:phone":"+49 711/357196",
    "sg:postcode":"73728",
    "sg:province":"Baden-W\u00fcrttemberg",
    "wof:name":"Wolfgang Schmidt Gmbh",
    "wof:placetype":"venue"
},
  "geometry": {"coordinates":[9.3077220917,48.7375564575],"type":"Point"}
}