{
  "type": "Feature",
  "properties": {
    "iso:country":"DE",
    "sg:address":"Leipziger Str. 14",
    "sg:city":"Reuden",
    "sg:phone":"+49 34424/21592",
    "sg:postcode":"06725",
    "sg:province":"Sachsen-Anhalt",
    "wof:name":"G\u00fcnter Goldhahn",
    "wof:placetype":"venue"
},
  "geometry": {"coordinates":[12.194585,51.112083],"type":"Point"}
}