{
  "type": "Feature",
  "properties": {
    "iso:country":"DE",
    "sg:address":"Blumenstr. 4-6",
    "sg:city":"Andernach",
    "sg:phone":"+49 2632/710002",
    "sg:postcode":"56626",
    "sg:province":"Rheinland-Pfalz",
    "wof:name":"H Tex Textilwerbung Gmbh",
    "wof:placetype":"venue"
},
  "geometry": {"coordinates":[7.4075112343,50.3949966431],"type":"Point"}
}