{
  "type": "Feature",
  "properties": {
    "iso:country":"DE",
    "sg:address":"Rellieh\u00e4user Str.38-40",
    "sg:city":"Dassel",
    "sg:phone":"+49 4955/6496170",
    "sg:postcode":"37586",
    "sg:province":"Niedersachsen",
    "wof:name":"Schaeferwerk Goedeke Gmbh & Co. Kg",
    "wof:placetype":"venue"
},
  "geometry": {"coordinates":[9.6852035522,51.7960281372],"type":"Point"}
}