{
  "type": "Feature",
  "properties": {
    "iso:country":"DE",
    "sg:address":"Ahornallee 12",
    "sg:city":"Berlin",
    "sg:postcode":"12587",
    "sg:province":"Berlin",
    "wof:name":"S. Th. U. Projekt- Entwicklungsges. Mbh",
    "wof:placetype":"venue"
},
  "geometry": {"coordinates":[13.618325,52.453682],"type":"Point"}
}