{
  "type": "Feature",
  "properties": {
    "iso:country":"DE",
    "sg:address":"Kleegartenstr. 3",
    "sg:city":"Sandhausen",
    "sg:phone":"+49 6224/592155",
    "sg:postcode":"69207",
    "sg:province":"Baden-W\u00fcrttemberg",
    "wof:name":"Festhalle Sandhausen",
    "wof:placetype":"venue"
},
  "geometry": {"coordinates":[8.659104,49.342159],"type":"Point"}
}