{
  "type": "Feature",
  "properties": {
    "iso:country":"DE",
    "sg:address":"Kapuzinerstr. 6",
    "sg:city":"Laufen",
    "sg:phone":"+49 8682/9655",
    "sg:postcode":"83410",
    "sg:province":"Bayern",
    "wof:name":"Herbert Rohr",
    "wof:placetype":"venue"
},
  "geometry": {"coordinates":[12.935874939,47.9358177185],"type":"Point"}
}