{
  "type": "Feature",
  "properties": {
    "iso:country":"DE",
    "sg:address":"B\u00fcrgermeister-Heine-Str. 3",
    "sg:city":"Celle",
    "sg:phone":"+49 5141/95720",
    "sg:postcode":"29229",
    "sg:province":"Niedersachsen",
    "wof:name":"Erdmannsky Automobile Gesch\u00e4ftsf\u00fchrungs Gmbh",
    "wof:placetype":"venue"
},
  "geometry": {"coordinates":[10.0630550385,52.6527404785],"type":"Point"}
}