{
  "type": "Feature",
  "properties": {
    "iso:country":"DE",
    "sg:address":"Berthelsdorfer Str. 22",
    "sg:city":"Hainichen",
    "sg:phone":"+49 37207/2636",
    "sg:postcode":"09661",
    "sg:province":"Sachsen",
    "wof:name":"Matthias Otto",
    "wof:placetype":"venue"
},
  "geometry": {"coordinates":[13.1151723862,50.9562301636],"type":"Point"}
}