{
  "type": "Feature",
  "properties": {
    "iso:country":"DE",
    "sg:address":"Am Kohlhain 12",
    "sg:city":"Kirchheim",
    "sg:phone":"+49 6625/7041",
    "sg:postcode":"36275",
    "sg:province":"Hessen",
    "wof:name":"Hans Huras Gmbh",
    "wof:placetype":"venue"
},
  "geometry": {"coordinates":[9.5972232819,50.8637008667],"type":"Point"}
}