{
  "type": "Feature",
  "properties": {
    "iso:country":"DE",
    "sg:address":"Bartels Feld A 20",
    "sg:city":"G\u00fctersloh",
    "sg:phone":"+49 5241/30090",
    "sg:postcode":"33332",
    "sg:province":"Nordrhein-Westfalen",
    "wof:name":"Fa Stahlbearbeitung Gmbh",
    "wof:placetype":"venue"
},
  "geometry": {"coordinates":[8.3939914703,51.9159927368],"type":"Point"}
}