{
  "type": "Feature",
  "properties": {
    "iso:country":"DE",
    "sg:address":"Saarbr\u00fccker Str. 20/21",
    "sg:city":"Berlin",
    "sg:postcode":"10405",
    "sg:province":"Berlin",
    "wof:name":"Mediacon Gmbh",
    "wof:placetype":"venue"
},
  "geometry": {"coordinates":[13.412836,52.530804],"type":"Point"}
}