{
  "type": "Feature",
  "properties": {
    "iso:country":"DE",
    "sg:address":"Dorfstr. 11",
    "sg:city":"Sielenbach",
    "sg:phone":"+49 8258/240",
    "sg:postcode":"86577",
    "sg:province":"Bayern",
    "wof:name":"H & M Popfinger Gmbh & Co. Kg",
    "wof:placetype":"venue"
},
  "geometry": {"coordinates":[11.1618652344,48.3779716492],"type":"Point"}
}