{
  "type": "Feature",
  "properties": {
    "iso:country":"DE",
    "sg:address":"Amalienstr. 23",
    "sg:city":"Ettlingen",
    "sg:phone":"+49 7243/93553",
    "sg:postcode":"76275",
    "sg:province":"Baden-W\u00fcrttemberg",
    "wof:name":"Gewie Technologietransfer Gmbh",
    "wof:placetype":"venue"
},
  "geometry": {"coordinates":[8.369449,48.929123],"type":"Point"}
}