{
  "type": "Feature",
  "properties": {
    "iso:country":"DE",
    "sg:address":"Landsberger Str. 139",
    "sg:city":"M\u00fcnchen",
    "sg:phone":"+49 89/5003780",
    "sg:postcode":"80339",
    "sg:province":"Bayern",
    "wof:name":"Peter Kutschka Steuerberater",
    "wof:placetype":"venue"
},
  "geometry": {"coordinates":[11.5298500061,48.14012146],"type":"Point"}
}