{
  "type": "Feature",
  "properties": {
    "iso:country":"DE",
    "sg:city":"L\u00fcneburg",
    "sg:postcode":"21335",
    "sg:province":"Niedersachsen",
    "wof:name":"Landeskrankenhilfe V.v.a.g.",
    "wof:placetype":"venue"
},
  "geometry": {"coordinates":[10.41414,53.247585],"type":"Point"}
}