{
  "type": "Feature",
  "properties": {
    "iso:country":"DE",
    "sg:address":"M\u00fcller-Breslau-Str. 40",
    "sg:city":"Essen",
    "sg:phone":"+49 201/264844",
    "sg:postcode":"45130",
    "sg:province":"Nordrhein-Westfalen",
    "wof:name":"Dea Tankstelle",
    "wof:placetype":"venue"
},
  "geometry": {"coordinates":[7.018889904,51.4357795715],"type":"Point"}
}