{
  "type": "Feature",
  "properties": {
    "iso:country":"DE",
    "sg:address":"Riedm\u00fchle 1",
    "sg:city":"Erbach",
    "sg:phone":"+49 7305/17312",
    "sg:postcode":"89155",
    "sg:province":"Baden-W\u00fcrttemberg",
    "wof:name":"Wlz-raiffeisen Ag",
    "wof:placetype":"venue"
},
  "geometry": {"coordinates":[9.889206,48.315029],"type":"Point"}
}