{
  "type": "Feature",
  "properties": {
    "iso:country":"DE",
    "sg:address":"An der Hecke 13",
    "sg:city":"Zellingen",
    "sg:phone":"+49 9364/2540",
    "sg:postcode":"97225",
    "sg:province":"Bayern",
    "wof:name":"Ing. Arno Sohn Architekt",
    "wof:placetype":"venue"
},
  "geometry": {"coordinates":[9.823864,49.905773],"type":"Point"}
}