{
  "type": "Feature",
  "properties": {
    "iso:country":"DE",
    "sg:address":"Ringstr. 1",
    "sg:city":"St. Wendel",
    "sg:phone":"+49 6851/3750",
    "sg:postcode":"66606",
    "sg:province":"Saarland",
    "wof:name":"Erich Sannicolo",
    "wof:placetype":"venue"
},
  "geometry": {"coordinates":[7.1005568504,49.4702720642],"type":"Point"}
}