{
  "type": "Feature",
  "properties": {
    "iso:country":"DE",
    "sg:address":"Heusteg 9",
    "sg:city":"Erlangen",
    "sg:phone":"+49 9131/75520",
    "sg:postcode":"91056",
    "sg:province":"Bayern",
    "wof:name":"Kaiser Trockenbau Gmbh",
    "wof:placetype":"venue"
},
  "geometry": {"coordinates":[10.9612026215,49.6184158325],"type":"Point"}
}