{
  "type": "Feature",
  "properties": {
    "iso:country":"DE",
    "sg:address":"Meerstr. 4a",
    "sg:city":"Rees",
    "sg:phone":"+49 2851/6541",
    "sg:postcode":"46459",
    "sg:province":"Nordrhein-Westfalen",
    "wof:name":"Bernhard Legeland",
    "wof:placetype":"venue"
},
  "geometry": {"coordinates":[6.393643,51.808891],"type":"Point"}
}