{
  "type": "Feature",
  "properties": {
    "iso:country":"DE",
    "sg:address":"Wehdestr. 28",
    "sg:city":"Zetel",
    "sg:phone":"+49 4453/2306",
    "sg:postcode":"26340",
    "sg:province":"Niedersachsen",
    "wof:name":"Hans Dieter M\u00f6nck",
    "wof:placetype":"venue"
},
  "geometry": {"coordinates":[7.946542,53.419193],"type":"Point"}
}