{
  "type": "Feature",
  "properties": {
    "iso:country":"DE",
    "sg:address":"Rudolf-K\u00f6niger-Str. 3-5",
    "sg:city":"Delmenhorst",
    "sg:postcode":"27753",
    "sg:province":"Niedersachsen",
    "wof:name":"Volkart Gmbh",
    "wof:placetype":"venue"
},
  "geometry": {"coordinates":[8.6246118546,53.0482635498],"type":"Point"}
}