{
  "type": "Feature",
  "properties": {
    "iso:country":"DE",
    "sg:address":"Goethestr. 12",
    "sg:city":"H\u00f6chst\u00e4dt",
    "sg:phone":"+49 9074/2264",
    "sg:postcode":"89420",
    "sg:province":"Bayern",
    "wof:name":"Wolfgang R\u00f6der Alt- Und Abfallstoffe",
    "wof:placetype":"venue"
},
  "geometry": {"coordinates":[10.576963,48.620708],"type":"Point"}
}