{
  "type": "Feature",
  "properties": {
    "iso:country":"DE",
    "sg:address":"Aschheimer Str. 9",
    "sg:city":"Feldkirchen",
    "sg:phone":"+49 89/9035187",
    "sg:postcode":"85622",
    "sg:province":"Bayern",
    "wof:name":"Josef Oberhauser",
    "wof:placetype":"venue"
},
  "geometry": {"coordinates":[11.7286510468,48.1479301453],"type":"Point"}
}