{
  "type": "Feature",
  "properties": {
    "iso:country":"DE",
    "sg:city":"Asperg",
    "sg:phone":"+49 7141/660444",
    "sg:postcode":"71679",
    "sg:province":"Baden-W\u00fcrttemberg",
    "wof:name":"Magic Thomas Zauberk\u00fcnstler Zauberer",
    "wof:placetype":"venue"
},
  "geometry": {"coordinates":[9.135654,48.905659],"type":"Point"}
}