{
  "type": "Feature",
  "properties": {
    "iso:country":"DE",
    "sg:address":"K\u00f6nigsteiner Str. 71",
    "sg:city":"Bad Soden",
    "sg:phone":"+49 6196/29631",
    "sg:postcode":"65812",
    "sg:province":"Hessen",
    "wof:name":"Ursula Zetzsche",
    "wof:placetype":"venue"
},
  "geometry": {"coordinates":[8.501189,50.144295],"type":"Point"}
}