{
  "type": "Feature",
  "properties": {
    "iso:country":"DE",
    "sg:address":"Meinlohstr. 9",
    "sg:city":"Ulm",
    "sg:phone":"+49 731/9386899",
    "sg:postcode":"89081",
    "sg:province":"Baden-W\u00fcrttemberg",
    "wof:name":"Andreas M\u00d6genburgjutta B\u00dchrle",
    "wof:placetype":"venue"
},
  "geometry": {"coordinates":[9.951425,48.399158],"type":"Point"}
}