{
  "type": "Feature",
  "properties": {
    "iso:country":"DE",
    "sg:address":"Grenzstr. 1",
    "sg:city":"Coswig",
    "sg:postcode":"01640",
    "sg:province":"Sachsen",
    "wof:name":"Imf Ingenieurb\u00fcro F\u00fcr Maschinenbaukonstruktion Und",
    "wof:placetype":"venue"
},
  "geometry": {"coordinates":[13.5849504471,51.1196289062],"type":"Point"}
}