{
  "type": "Feature",
  "properties": {
    "iso:country":"DE",
    "sg:address":"Leonhardtstr. 64",
    "sg:city":"Greiz",
    "sg:phone":"+49 3661/433004",
    "sg:postcode":"07973",
    "sg:province":"Th\u00fcringen",
    "wof:name":"Klaus Meinhardt",
    "wof:placetype":"venue"
},
  "geometry": {"coordinates":[12.197769,50.670033],"type":"Point"}
}