{
  "type": "Feature",
  "properties": {
    "iso:country":"DE",
    "sg:address":"Bahnhofstr. 26",
    "sg:city":"Wienhausen",
    "sg:phone":"+49 5149/397",
    "sg:postcode":"29342",
    "sg:province":"Niedersachsen",
    "wof:name":"Saatzucht Flettmar-wittingen Eg",
    "wof:placetype":"venue"
},
  "geometry": {"coordinates":[10.186621,52.573971],"type":"Point"}
}