{
  "type": "Feature",
  "properties": {
    "iso:country":"DE",
    "sg:address":"Oderstr. 47",
    "sg:city":"Villingen-Schwenningen",
    "sg:phone":"+49 7721/72923",
    "sg:postcode":"78052",
    "sg:province":"Baden-W\u00fcrttemberg",
    "wof:name":"Willibald Greitzke",
    "wof:placetype":"venue"
},
  "geometry": {"coordinates":[8.4631795883,48.0825691223],"type":"Point"}
}