{
  "type": "Feature",
  "properties": {
    "iso:country":"DE",
    "sg:address":"M\u00fcnchner Ring 2",
    "sg:city":"Unterschlei\u00dfheim",
    "sg:phone":"+49 89/3102282",
    "sg:postcode":"85716",
    "sg:province":"Bayern",
    "wof:name":"E. R\u00f6dder",
    "wof:placetype":"venue"
},
  "geometry": {"coordinates":[11.56376,48.27401],"type":"Point"}
}