{
  "type": "Feature",
  "properties": {
    "iso:country":"DE",
    "sg:address":"Johannes-R\u00e4dlein-Weg 1",
    "sg:city":"Bad Sooden-Allendorf",
    "sg:phone":"+49 5652/3358",
    "sg:postcode":"37242",
    "sg:province":"Hessen",
    "wof:name":"Julius Goebel",
    "wof:placetype":"venue"
},
  "geometry": {"coordinates":[9.9829816818,51.2737121582],"type":"Point"}
}