{
  "type": "Feature",
  "properties": {
    "iso:country":"DE",
    "sg:address":"Westerwaldstr. 81",
    "sg:city":"Rengsdorf",
    "sg:phone":"+49 2634/2417",
    "sg:postcode":"56579",
    "sg:province":"Rheinland-Pfalz",
    "wof:name":"Kur-apotheke",
    "wof:placetype":"venue"
},
  "geometry": {"coordinates":[7.491788,50.504734],"type":"Point"}
}