{
  "type": "Feature",
  "properties": {
    "iso:country":"DE",
    "sg:address":"Leinestr. 7",
    "sg:city":"Leipzig",
    "sg:phone":"+49 341/312328",
    "sg:postcode":"04279",
    "sg:province":"Sachsen",
    "wof:name":"H\u00f6velmann",
    "wof:placetype":"venue"
},
  "geometry": {"coordinates":[12.393701,51.287529],"type":"Point"}
}