{
  "type": "Feature",
  "properties": {
    "iso:country":"DE",
    "sg:address":"Gernstall 2",
    "sg:city":"Mindelheim",
    "sg:postcode":"87719",
    "sg:province":"Bayern",
    "wof:name":"Weiss Grundst\u00fccksges. Mbh",
    "wof:placetype":"venue"
},
  "geometry": {"coordinates":[10.483880043,48.0272903442],"type":"Point"}
}