{
  "type": "Feature",
  "properties": {
    "iso:country":"DE",
    "sg:address":"Stra\u00dfe des 18. Oktober 10",
    "sg:city":"Leipzig",
    "sg:postcode":"04103",
    "sg:province":"Sachsen",
    "wof:name":"Rudolf Wildgrube",
    "wof:placetype":"venue"
},
  "geometry": {"coordinates":[12.387712,51.326283],"type":"Point"}
}