{
  "type": "Feature",
  "properties": {
    "iso:country":"DE",
    "sg:address":"Alexander-Puschkin-Str. 3",
    "sg:city":"Schm\u00f6lln",
    "sg:phone":"+49 34491/26137",
    "sg:postcode":"04626",
    "sg:province":"Th\u00fcringen",
    "wof:name":"Riewe",
    "wof:placetype":"venue"
},
  "geometry": {"coordinates":[12.350596,50.894402],"type":"Point"}
}