{
  "type": "Feature",
  "properties": {
    "iso:country":"DE",
    "sg:address":"Onsdorfer Str. 14",
    "sg:city":"Tawern",
    "sg:phone":"+49 6501/16798",
    "sg:postcode":"54456",
    "sg:province":"Rheinland-Pfalz",
    "wof:name":"Johann Wolff",
    "wof:placetype":"venue"
},
  "geometry": {"coordinates":[6.513507,49.670769],"type":"Point"}
}