{
  "type": "Feature",
  "properties": {
    "iso:country":"DE",
    "sg:address":"Kaninchenborn 15-19",
    "sg:city":"L\u00fcbeck",
    "sg:phone":"+49 451/583270",
    "sg:postcode":"23560",
    "sg:province":"Schleswig-Holstein",
    "wof:name":"Viking Global Kg",
    "wof:placetype":"venue"
},
  "geometry": {"coordinates":[10.6801357269,53.8478469849],"type":"Point"}
}