{
  "type": "Feature",
  "properties": {
    "iso:country":"DE",
    "sg:address":"Auf dem L\u00e4rchenberge 18",
    "sg:city":"Hannover",
    "sg:phone":"+49 511/343933",
    "sg:postcode":"30161",
    "sg:province":"Niedersachsen",
    "wof:name":"Gerd Lauterbach Architekt",
    "wof:placetype":"venue"
},
  "geometry": {"coordinates":[9.755152,52.382717],"type":"Point"}
}