{
  "type": "Feature",
  "properties": {
    "iso:country":"DE",
    "sg:address":"Zeppelinstr. 3",
    "sg:city":"Limburg",
    "sg:phone":"+49 6431/94200",
    "sg:postcode":"65549",
    "sg:province":"Hessen",
    "wof:name":"Zeppelin-apotheke",
    "wof:placetype":"venue"
},
  "geometry": {"coordinates":[8.065246,50.371922],"type":"Point"}
}