{
  "type": "Feature",
  "properties": {
    "iso:country":"DE",
    "sg:address":"Kurt-Schumacher-Allee 19-21",
    "sg:city":"Bremen",
    "sg:phone":"+49 421/4676652",
    "sg:postcode":"28329",
    "sg:province":"Bremen",
    "wof:name":"Wilhelm-leuschner-apotheke Inh. Hildegard Hassenkamp",
    "wof:placetype":"venue"
},
  "geometry": {"coordinates":[8.885345,53.078934],"type":"Point"}
}