{
  "type": "Feature",
  "properties": {
    "iso:country":"DE",
    "sg:address":"Triftstr. 80",
    "sg:city":"Monschau",
    "sg:phone":"+49 2472/1467",
    "sg:postcode":"52156",
    "sg:province":"Nordrhein-Westfalen",
    "wof:name":"Hubert Kirch Ingenieur",
    "wof:placetype":"venue"
},
  "geometry": {"coordinates":[6.2649188042,50.5317649841],"type":"Point"}
}