{
  "type": "Feature",
  "properties": {
    "iso:country":"DE",
    "sg:address":"Parkstr. 1",
    "sg:city":"Taunusstein",
    "sg:phone":"+49 6128/71450",
    "sg:postcode":"65232",
    "sg:province":"Hessen",
    "wof:name":"Albert Gros",
    "wof:placetype":"venue"
},
  "geometry": {"coordinates":[8.21345,50.170307],"type":"Point"}
}