{
  "type": "Feature",
  "properties": {
    "iso:country":"DE",
    "sg:address":"Marktstr. 47",
    "sg:city":"Rennertshofen",
    "sg:phone":"+49 8434/678",
    "sg:postcode":"86643",
    "sg:province":"Bayern",
    "wof:name":"Rainer Eller",
    "wof:placetype":"venue"
},
  "geometry": {"coordinates":[11.050653,48.755562],"type":"Point"}
}