{
  "type": "Feature",
  "properties": {
    "iso:country":"DE",
    "sg:address":"Franz-von-Taxis-Ring 54",
    "sg:city":"Regensburg",
    "sg:postcode":"93049",
    "sg:province":"Bayern",
    "wof:name":"Papeteria Nagelneu Inh. Hans-j\u00fcrgen Strohmeier E. K.",
    "wof:placetype":"venue"
},
  "geometry": {"coordinates":[12.0516853333,49.0141868591],"type":"Point"}
}