{
  "type": "Feature",
  "properties": {
    "iso:country":"DE",
    "sg:address":"Johannes-R.-Becher-Str. 42",
    "sg:city":"Magdeburg",
    "sg:phone":"+49 391/2544975",
    "sg:postcode":"39128",
    "sg:province":"Sachsen-Anhalt",
    "wof:name":"Pflege Daheim Gaworski",
    "wof:placetype":"venue"
},
  "geometry": {"coordinates":[11.624315,52.167671],"type":"Point"}
}