{
  "type": "Feature",
  "properties": {
    "iso:country":"DE",
    "sg:address":"Kegelhofstr. 50",
    "sg:city":"Hamburg",
    "sg:phone":"+49 40/487566",
    "sg:postcode":"20251",
    "sg:province":"Hamburg",
    "wof:name":"Hanseatische Konzertdirektion Klaus Wollny Gmbh",
    "wof:placetype":"venue"
},
  "geometry": {"coordinates":[9.9772052765,53.5952301025],"type":"Point"}
}