{
  "type": "Feature",
  "properties": {
    "iso:country":"DE",
    "sg:address":"Rombergerstr 26a",
    "sg:city":"Waldbr\u00f6l",
    "sg:phone":"+49 2291/6003",
    "sg:postcode":"51545",
    "sg:province":"Nordrhein-Westfalen",
    "wof:name":"Hespo Hebbinghaus Gmbh",
    "wof:placetype":"venue"
},
  "geometry": {"coordinates":[7.604546,50.883076],"type":"Point"}
}