{
  "type": "Feature",
  "properties": {
    "iso:country":"DE",
    "sg:address":"Caprivistr. 25",
    "sg:city":"Kiel",
    "sg:phone":"+49 431/803756",
    "sg:postcode":"24105",
    "sg:province":"Schleswig-Holstein",
    "wof:name":"Klaus Ohm Gmbh",
    "wof:placetype":"venue"
},
  "geometry": {"coordinates":[10.1468572617,54.3394889832],"type":"Point"}
}