{
  "type": "Feature",
  "properties": {
    "iso:country":"DE",
    "sg:address":"Dr.-Salvador-Allende-Str. 114",
    "sg:city":"Chemnitz",
    "sg:phone":"+49 371/229429",
    "sg:postcode":"09119",
    "sg:province":"Sachsen",
    "wof:name":"E. G\u00f6rmer",
    "wof:placetype":"venue"
},
  "geometry": {"coordinates":[12.888882,50.806156],"type":"Point"}
}