{
  "type": "Feature",
  "properties": {
    "iso:country":"DE",
    "sg:address":"Meringerzeller Str. 14",
    "sg:city":"Mering",
    "sg:phone":"+49 8233/30026",
    "sg:postcode":"86415",
    "sg:province":"Bayern",
    "wof:name":"M. Schallermeir",
    "wof:placetype":"venue"
},
  "geometry": {"coordinates":[10.98990345,48.2675361633],"type":"Point"}
}