{
  "type": "Feature",
  "properties": {
    "iso:country":"DE",
    "sg:address":"Langener Landstr. 134",
    "sg:city":"Bremerhaven",
    "sg:phone":"+49 471/801035",
    "sg:postcode":"27580",
    "sg:province":"Bremen",
    "wof:name":"Fun Fabrik",
    "wof:placetype":"venue"
},
  "geometry": {"coordinates":[8.5979404449,53.5789794922],"type":"Point"}
}