{
  "type": "Feature",
  "properties": {
    "iso:country":"DE",
    "sg:address":"Attenhofener Str.",
    "sg:city":"Greding",
    "sg:phone":"+49 8463/9950",
    "sg:postcode":"91171",
    "sg:province":"Bayern",
    "wof:name":"Josef Klinger",
    "wof:placetype":"venue"
},
  "geometry": {"coordinates":[11.35896492,49.0483894348],"type":"Point"}
}