{
  "type": "Feature",
  "properties": {
    "iso:country":"DE",
    "sg:address":"Wendenschlo\u00dfstr. 49",
    "sg:city":"Berlin",
    "sg:phone":"+49 30/65470312",
    "sg:postcode":"12559",
    "sg:province":"Berlin",
    "wof:name":"Laurentius Apotheke Christiane Lehmann E. Kfr.",
    "wof:placetype":"venue"
},
  "geometry": {"coordinates":[13.584025,52.443726],"type":"Point"}
}