{
  "type": "Feature",
  "properties": {
    "iso:country":"DE",
    "sg:address":"Nobelring 2",
    "sg:city":"Hannover",
    "sg:phone":"+49 511/571966",
    "sg:postcode":"30627",
    "sg:province":"Niedersachsen",
    "wof:name":"Bistro",
    "wof:placetype":"venue"
},
  "geometry": {"coordinates":[9.8082885742,52.3891410828],"type":"Point"}
}