{
  "type": "Feature",
  "properties": {
    "iso:country":"DE",
    "sg:address":"Winnender Str. 10",
    "sg:city":"Leutenbach",
    "sg:phone":"+49 7195/91240",
    "sg:postcode":"71397",
    "sg:province":"Baden-W\u00fcrttemberg",
    "wof:name":"G. Gempp Elektro Installation",
    "wof:placetype":"venue"
},
  "geometry": {"coordinates":[9.392358,48.887402],"type":"Point"}
}