{
  "type": "Feature",
  "properties": {
    "iso:country":"DE",
    "sg:address":"Waldshuter Str. 1",
    "sg:city":"Jestetten",
    "sg:phone":"+49 7745/8901",
    "sg:postcode":"79798",
    "sg:province":"Baden-W\u00fcrttemberg",
    "wof:name":"Henninger",
    "wof:placetype":"venue"
},
  "geometry": {"coordinates":[8.5677423477,47.6493110657],"type":"Point"}
}