{
  "type": "Feature",
  "properties": {
    "iso:country":"DE",
    "sg:address":"Thiensen 7",
    "sg:city":"Ellerhoop",
    "sg:phone":"+49 4120/305",
    "sg:postcode":"25373",
    "sg:province":"Schleswig-Holstein",
    "wof:name":"Hermann Pingel",
    "wof:placetype":"venue"
},
  "geometry": {"coordinates":[9.769732,53.717049],"type":"Point"}
}