{
  "type": "Feature",
  "properties": {
    "iso:country":"DE",
    "sg:address":"Am Langwiesfeld 6",
    "sg:city":"Obertraubling",
    "sg:phone":"+49 9401/52002",
    "sg:postcode":"93083",
    "sg:province":"Bayern",
    "wof:name":"Gerhard Schiegl",
    "wof:placetype":"venue"
},
  "geometry": {"coordinates":[12.171855,48.969955],"type":"Point"}
}