{
  "type": "Feature",
  "properties": {
    "iso:country":"DE",
    "sg:address":"In der Aue 2",
    "sg:city":"Flieden",
    "sg:phone":"+49 6655/2820",
    "sg:postcode":"36103",
    "sg:province":"Hessen",
    "wof:name":"Norbert Kramer",
    "wof:placetype":"venue"
},
  "geometry": {"coordinates":[9.5664358139,50.4207878113],"type":"Point"}
}