{
  "type": "Feature",
  "properties": {
    "iso:country":"DE",
    "sg:address":"Natruper Str. 18a",
    "sg:city":"Osnabr\u00fcck",
    "sg:postcode":"49076",
    "sg:province":"Niedersachsen",
    "wof:name":"Windpark Support Beteiligungs- Und",
    "wof:placetype":"venue"
},
  "geometry": {"coordinates":[8.036925,52.280735],"type":"Point"}
}