{
  "type": "Feature",
  "properties": {
    "iso:country":"DE",
    "sg:address":"Ziegelstr. 26",
    "sg:city":"Werther",
    "sg:phone":"+49 5203/97210",
    "sg:postcode":"33824",
    "sg:province":"Nordrhein-Westfalen",
    "wof:name":"Werther Klinkerwerk Verwaltungs Gmbh",
    "wof:placetype":"venue"
},
  "geometry": {"coordinates":[8.427057,52.079037],"type":"Point"}
}