{
  "type": "Feature",
  "properties": {
    "iso:country":"DE",
    "sg:address":"Lexf\u00e4hre",
    "sg:city":"Wrohm",
    "sg:phone":"+49 4802/313",
    "sg:postcode":"25799",
    "sg:province":"Schleswig-Holstein",
    "wof:name":"Gastst\u00e4tte Zum Alten F\u00e4hrhaus",
    "wof:placetype":"venue"
},
  "geometry": {"coordinates":[9.4296035767,54.2200126648],"type":"Point"}
}