{
  "type": "Feature",
  "properties": {
    "iso:country":"DE",
    "sg:address":"Taunusstr. 25",
    "sg:city":"Birstein",
    "sg:phone":"+49 6054/900290",
    "sg:postcode":"63633",
    "sg:province":"Hessen",
    "wof:name":"Peter Blum\u00f6hr Architekten",
    "wof:placetype":"venue"
},
  "geometry": {"coordinates":[9.312848,50.36248],"type":"Point"}
}