{
  "type": "Feature",
  "properties": {
    "iso:country":"DE",
    "sg:address":"L\u00fcneburger Landstr. 5",
    "sg:city":"Reppenstedt",
    "sg:phone":"+49 4131/64859",
    "sg:postcode":"21391",
    "sg:province":"Niedersachsen",
    "wof:name":"Werner Willert",
    "wof:placetype":"venue"
},
  "geometry": {"coordinates":[10.355946,53.248146],"type":"Point"}
}