{
  "type": "Feature",
  "properties": {
    "iso:country":"DE",
    "sg:address":"Suurleegdenweg 5",
    "sg:city":"Aurich",
    "sg:phone":"+49 4941/982098",
    "sg:postcode":"26607",
    "sg:province":"Niedersachsen",
    "wof:name":"Domus Wohnbau Gmbh",
    "wof:placetype":"venue"
},
  "geometry": {"coordinates":[7.424215,53.483418],"type":"Point"}
}