{
  "type": "Feature",
  "properties": {
    "iso:country":"DE",
    "sg:address":"Buchenstr. 3",
    "sg:city":"Diedorf",
    "sg:phone":"+49 8238/90145",
    "sg:postcode":"86420",
    "sg:province":"Bayern",
    "wof:name":"Josef Niedermair",
    "wof:placetype":"venue"
},
  "geometry": {"coordinates":[10.757204,48.353935],"type":"Point"}
}