{
  "type": "Feature",
  "properties": {
    "iso:country":"DE",
    "sg:address":"Zum Schoren 2",
    "sg:city":"Engen",
    "sg:phone":"+49 7733/2369",
    "sg:postcode":"78234",
    "sg:province":"Baden-W\u00fcrttemberg",
    "wof:name":"H. J. Petschko",
    "wof:placetype":"venue"
},
  "geometry": {"coordinates":[8.7766294479,47.850063324],"type":"Point"}
}