{
  "type": "Feature",
  "properties": {
    "iso:country":"DE",
    "sg:address":"Krumme Jauchert 16",
    "sg:city":"Langenargen",
    "sg:phone":"+49 7543/3766",
    "sg:postcode":"88085",
    "sg:province":"Baden-W\u00fcrttemberg",
    "wof:name":"S.w.s.d. Kraus & Partner Gmbh",
    "wof:placetype":"venue"
},
  "geometry": {"coordinates":[9.5519695282,47.6012229919],"type":"Point"}
}