{
  "type": "Feature",
  "properties": {
    "iso:country":"DE",
    "sg:address":"Parkstr. 11",
    "sg:city":"Finowfurt",
    "sg:postcode":"16244",
    "sg:province":"Brandenburg",
    "wof:name":"2. Universal Bautr\u00e4gerges. Mbh",
    "wof:placetype":"venue"
},
  "geometry": {"coordinates":[13.693152,52.851303],"type":"Point"}
}