{
  "type": "Feature",
  "properties": {
    "iso:country":"DE",
    "sg:address":"Gardesch\u00fctzenweg 17",
    "sg:city":"Berlin",
    "sg:phone":"+49 30",
    "sg:postcode":"12203",
    "sg:province":"Berlin",
    "wof:name":"Katholische Pfarrgemeinde St. Annen Berlin",
    "wof:placetype":"venue"
},
  "geometry": {"coordinates":[13.313183,52.448708],"type":"Point"}
}