{
  "type": "Feature",
  "properties": {
    "iso:country":"DE",
    "sg:address":"Berger Str. 168",
    "sg:city":"Frankfurt",
    "sg:phone":"+49 69/4940380",
    "sg:postcode":"60385",
    "sg:province":"Hessen",
    "wof:name":"Bernhard Naumann Und Heinz Eisenbletter",
    "wof:placetype":"venue"
},
  "geometry": {"coordinates":[8.7111501694,50.1304931641],"type":"Point"}
}