{
  "type": "Feature",
  "properties": {
    "iso:country":"DE",
    "sg:address":"Ruppertslohe 18",
    "sg:city":"Lauterhofen",
    "sg:phone":"+49 9186",
    "sg:postcode":"92283",
    "sg:province":"Bayern",
    "wof:name":"Golfclub Lauterhofen E.v.",
    "wof:placetype":"venue"
},
  "geometry": {"coordinates":[11.576918602,49.3811302185],"type":"Point"}
}