{
  "type": "Feature",
  "properties": {
    "iso:country":"DE",
    "sg:address":"Arnsburger Str. 5",
    "sg:city":"Karben",
    "sg:phone":"+49 172 3121219",
    "sg:postcode":"61184",
    "sg:province":"Hessen",
    "wof:name":"Dr. Alexander Hugo Stopp Rechtsanwalt",
    "wof:placetype":"venue"
},
  "geometry": {"coordinates":[8.7223577499,50.2413368225],"type":"Point"}
}