{
  "type": "Feature",
  "properties": {
    "iso:country":"DE",
    "sg:address":"Alexanderstr. 8",
    "sg:city":"Bayreuth",
    "sg:phone":"+49 921/13506",
    "sg:postcode":"95444",
    "sg:province":"Bayern",
    "wof:name":"Brigitte Dietel",
    "wof:placetype":"venue"
},
  "geometry": {"coordinates":[11.578452,49.94582],"type":"Point"}
}