{
  "type": "Feature",
  "properties": {
    "iso:country":"DE",
    "sg:address":"Wagnerstra\u00dfe 4",
    "sg:city":"Winnenden",
    "sg:phone":"+49 7195",
    "sg:postcode":"71364",
    "sg:province":"Baden-W\u00fcrttemberg",
    "wof:name":"R\u00f6mer Reisen",
    "wof:placetype":"venue"
},
  "geometry": {"coordinates":[9.39819,48.87619],"type":"Point"}
}