{
  "type": "Feature",
  "properties": {
    "iso:country":"DE",
    "sg:address":"Adenauerring 32",
    "sg:city":"Karlsruhe",
    "sg:phone":"+49 721/71240",
    "sg:postcode":"76131",
    "sg:province":"Baden-W\u00fcrttemberg",
    "wof:name":"Neues Sch\u00fctzenhaus",
    "wof:placetype":"venue"
},
  "geometry": {"coordinates":[8.3980360031,49.0238456726],"type":"Point"}
}