{
  "type": "Feature",
  "properties": {
    "iso:country":"DE",
    "sg:address":"Platz\u00f6derweg 2 a",
    "sg:city":"Dachau",
    "sg:phone":"+49 8131/55200",
    "sg:postcode":"85221",
    "sg:province":"Bayern",
    "wof:name":"E. U. Verwaltungs Gmbh",
    "wof:placetype":"venue"
},
  "geometry": {"coordinates":[11.416796,48.25481],"type":"Point"}
}