{
  "type": "Feature",
  "properties": {
    "iso:country":"DE",
    "sg:address":"Salinenstr. 17",
    "sg:city":"Kirchardt",
    "sg:phone":"+49 7266/201",
    "sg:postcode":"74912",
    "sg:province":"Baden-W\u00fcrttemberg",
    "wof:name":"Ev. Pfarramt Gem. Berwangen",
    "wof:placetype":"venue"
},
  "geometry": {"coordinates":[8.9813613892,49.1845550537],"type":"Point"}
}