{
  "type": "Feature",
  "properties": {
    "iso:country":"DE",
    "sg:address":"Dorstener Str. 644",
    "sg:city":"Haltern",
    "sg:phone":"+49 2360/1644",
    "sg:postcode":"45721",
    "sg:province":"Nordrhein-Westfalen",
    "wof:name":"Pfannkuchenhaus",
    "wof:placetype":"venue"
},
  "geometry": {"coordinates":[7.0947341919,51.7147445679],"type":"Point"}
}