{
  "type": "Feature",
  "properties": {
    "iso:country":"DE",
    "sg:address":"Hauptstr. 28",
    "sg:city":"Gehrden",
    "sg:phone":"+49 5108/5343",
    "sg:postcode":"30989",
    "sg:province":"Niedersachsen",
    "wof:name":"Gasthaus Behnsen",
    "wof:placetype":"venue"
},
  "geometry": {"coordinates":[9.5511207581,52.3183746338],"type":"Point"}
}