{
  "type": "Feature",
  "properties": {
    "iso:country":"DE",
    "sg:address":"Liebetraustr. 21",
    "sg:city":"Gotha",
    "sg:phone":"+49 3621/743140",
    "sg:postcode":"99867",
    "sg:province":"Th\u00fcringen",
    "wof:name":"Kerstin Zappe",
    "wof:placetype":"venue"
},
  "geometry": {"coordinates":[10.6931266785,50.9459495544],"type":"Point"}
}