{
  "type": "Feature",
  "properties": {
    "iso:country":"DE",
    "sg:address":"Kirschenallee 1",
    "sg:city":"Dettum",
    "sg:phone":"+49 5333/517",
    "sg:postcode":"38173",
    "sg:province":"Niedersachsen",
    "wof:name":"Gemeindeb\u00fccherei",
    "wof:placetype":"venue"
},
  "geometry": {"coordinates":[10.66463,52.173676],"type":"Point"}
}