{
  "type": "Feature",
  "properties": {
    "iso:country":"DE",
    "sg:address":"Sch\u00f6nblick 8",
    "sg:city":"Laichingen",
    "sg:phone":"+49 7333/5360",
    "sg:postcode":"89150",
    "sg:province":"Baden-W\u00fcrttemberg",
    "wof:name":"Leonhard Reiber",
    "wof:placetype":"venue"
},
  "geometry": {"coordinates":[9.6255712509,48.4795036316],"type":"Point"}
}