{
  "type": "Feature",
  "properties": {
    "iso:country":"DE",
    "sg:address":"Eich 2",
    "sg:city":"Radevormwald",
    "sg:phone":"+49 2195/4275",
    "sg:postcode":"42477",
    "sg:province":"Nordrhein-Westfalen",
    "wof:name":"Zum Eichst\u00fcbchen",
    "wof:placetype":"venue"
},
  "geometry": {"coordinates":[7.4074611664,51.2020530701],"type":"Point"}
}