{
  "type": "Feature",
  "properties": {
    "iso:country":"DE",
    "sg:address":"Lautzschke 2",
    "sg:city":"D\u00f6lzig",
    "sg:phone":"+49 34205/58227",
    "sg:postcode":"04430",
    "wof:name":"Falk Sperling",
    "wof:placetype":"venue"
},
  "geometry": {"coordinates":[12.2091093063,51.3536300659],"type":"Point"}
}