{
  "type": "Feature",
  "properties": {
    "iso:country":"DE",
    "sg:address":"Viertelstr. 7",
    "sg:city":"Bad Herrenalb",
    "sg:phone":"+49 7083/2998",
    "sg:postcode":"76332",
    "sg:province":"Baden-W\u00fcrttemberg",
    "wof:name":"Karl Und M. Wacker",
    "wof:placetype":"venue"
},
  "geometry": {"coordinates":[8.472049,48.815681],"type":"Point"}
}