{
  "type": "Feature",
  "properties": {
    "iso:country":"DE",
    "sg:address":"Hauptstr. 44",
    "sg:city":"Ro\u00dfdorf",
    "sg:phone":"+49 6071/74361",
    "sg:postcode":"64380",
    "sg:province":"Hessen",
    "wof:name":"Pizza-imbi\u00df Gran Sasso Giovanna",
    "wof:placetype":"venue"
},
  "geometry": {"coordinates":[8.7862386703,49.8708763123],"type":"Point"}
}