{
  "type": "Feature",
  "properties": {
    "iso:country":"DE",
    "sg:address":"Am Parir 12",
    "sg:city":"Langerwehe",
    "sg:phone":"+49 2423/5717",
    "sg:postcode":"52379",
    "sg:province":"Nordrhein-Westfalen",
    "wof:name":"Jordans & Hompesch Beschallungstechnik Ohg",
    "wof:placetype":"venue"
},
  "geometry": {"coordinates":[6.3794908524,50.8132743835],"type":"Point"}
}