{
  "type": "Feature",
  "properties": {
    "iso:country":"DE",
    "sg:address":"Kronprinzenstr. 5",
    "sg:city":"Essen",
    "sg:phone":"+49 201/10040",
    "sg:postcode":"45128",
    "sg:province":"Nordrhein-Westfalen",
    "wof:name":"Abb Digi Table Sicherheitstechnik Gmbh",
    "wof:placetype":"venue"
},
  "geometry": {"coordinates":[7.017669,51.445629],"type":"Point"}
}