{
  "type": "Feature",
  "properties": {
    "iso:country":"DE",
    "sg:address":"Fl\u00e4mingstr. 70",
    "sg:city":"Berlin",
    "sg:postcode":"12689",
    "sg:province":"Berlin",
    "wof:name":"Extra",
    "wof:placetype":"venue"
},
  "geometry": {"coordinates":[13.5670909882,52.5676651001],"type":"Point"}
}