{
  "type": "Feature",
  "properties": {
    "iso:country":"DE",
    "sg:address":"S\u00f6flinger Str. 248",
    "sg:city":"Ulm",
    "sg:phone":"+49 731/9387881",
    "sg:postcode":"89077",
    "sg:province":"Baden-W\u00fcrttemberg",
    "wof:name":"Rm-security Gmbh",
    "wof:placetype":"venue"
},
  "geometry": {"coordinates":[9.9618196487,48.3944396973],"type":"Point"}
}