{
  "type": "Feature",
  "properties": {
    "iso:country":"DE",
    "sg:address":"Bonifaz-Huber-Str. 10",
    "sg:city":"Burghausen",
    "sg:phone":"+49 8677/62329",
    "sg:postcode":"84489",
    "sg:province":"Bayern",
    "wof:name":"Rauchclub Der Gem\u00fctliche Max Duschi",
    "wof:placetype":"venue"
},
  "geometry": {"coordinates":[12.8140945435,48.1537399292],"type":"Point"}
}