{
  "type": "Feature",
  "properties": {
    "iso:country":"DE",
    "sg:address":"Marktstr. 4",
    "sg:city":"Alfeld",
    "sg:phone":"+49 5181/84140",
    "sg:postcode":"31061",
    "sg:province":"Niedersachsen",
    "wof:name":"L\u00f6wen-apotheke",
    "wof:placetype":"venue"
},
  "geometry": {"coordinates":[9.824018,51.98698],"type":"Point"}
}