{
  "type": "Feature",
  "properties": {
    "iso:country":"DE",
    "sg:address":"Carl-Cetto-Str. 13",
    "sg:city":"St. Wendel",
    "sg:phone":"+49 6851/81811",
    "sg:postcode":"66606",
    "sg:province":"Saarland",
    "wof:name":"Treibhaus",
    "wof:placetype":"venue"
},
  "geometry": {"coordinates":[7.1713180542,49.4667472839],"type":"Point"}
}