{
  "type": "Feature",
  "properties": {
    "iso:country":"DE",
    "sg:address":"Sobrigauer Weg 4",
    "sg:city":"Dresden",
    "sg:phone":"+49 4935/1270460",
    "sg:postcode":"01257",
    "sg:province":"Sachsen",
    "wof:name":"Aeronova Gmbh & Co",
    "wof:placetype":"venue"
},
  "geometry": {"coordinates":[13.792434,50.978897],"type":"Point"}
}