{
  "type": "Feature",
  "properties": {
    "iso:country":"DE",
    "sg:address":"Pfinzstr. 64",
    "sg:city":"Karlsruhe",
    "sg:phone":"+49 721/943860",
    "sg:postcode":"76227",
    "sg:province":"Baden-W\u00fcrttemberg",
    "wof:name":"Gastst\u00e4tte Ochsen",
    "wof:placetype":"venue"
},
  "geometry": {"coordinates":[8.4725751877,49.0014305115],"type":"Point"}
}