{
  "type": "Feature",
  "properties": {
    "iso:country":"DE",
    "sg:address":"Windm\u00fchlenweg 15",
    "sg:city":"Alach",
    "sg:phone":"+49 4936/2087630",
    "sg:postcode":"99100",
    "sg:province":"Th\u00fcringen",
    "wof:name":"Strassing Limes Bau Gmbh",
    "wof:placetype":"venue"
},
  "geometry": {"coordinates":[10.937666,50.988094],"type":"Point"}
}