{
  "type": "Feature",
  "properties": {
    "iso:country":"DE",
    "sg:address":"Wanheimer Str. 219",
    "sg:city":"Duisburg",
    "sg:phone":"+49 203/667285",
    "sg:postcode":"47053",
    "sg:province":"Nordrhein-Westfalen",
    "wof:name":"Polster-spektrum",
    "wof:placetype":"venue"
},
  "geometry": {"coordinates":[6.7525281906,51.4098968506],"type":"Point"}
}