{
  "type": "Feature",
  "properties": {
    "iso:country":"DE",
    "sg:address":"Im Versuchsfeld 2",
    "sg:city":"Fu\u00dfg\u00f6nheim",
    "sg:phone":"+49 6237/929060",
    "sg:postcode":"67136",
    "sg:province":"Rheinland-Pfalz",
    "wof:name":"T. Bauer",
    "wof:placetype":"venue"
},
  "geometry": {"coordinates":[8.289822,49.464882],"type":"Point"}
}