{
  "type": "Feature",
  "properties": {
    "iso:country":"DE",
    "sg:address":"Karower Str. 22",
    "sg:city":"Genthin",
    "sg:phone":"+49 3933/3019",
    "sg:postcode":"39307",
    "sg:province":"Sachsen-Anhalt",
    "wof:name":"K.-heinz Koszior",
    "wof:placetype":"venue"
},
  "geometry": {"coordinates":[12.168413,52.405445],"type":"Point"}
}