{
  "type": "Feature",
  "properties": {
    "iso:country":"DE",
    "sg:address":"Hartfeldstr. 42",
    "sg:city":"Neukirchen-Vluyn",
    "sg:phone":"+49 2845/2219",
    "sg:postcode":"47506",
    "sg:province":"Nordrhein-Westfalen",
    "wof:name":"M\u00f6bel Schmitz Gmbh",
    "wof:placetype":"venue"
},
  "geometry": {"coordinates":[6.5467300415,51.4368133545],"type":"Point"}
}