{
  "type": "Feature",
  "properties": {
    "iso:country":"DE",
    "sg:city":"Mainz",
    "sg:postcode":"55130",
    "sg:province":"Rheinland-Pfalz",
    "wof:name":"Prisma Analog Digital Imaging Gmbh",
    "wof:placetype":"venue"
},
  "geometry": {"coordinates":[8.313231,49.959606],"type":"Point"}
}