{
  "type": "Feature",
  "properties": {
    "iso:country":"DE",
    "sg:address":"Rosenstr. 17",
    "sg:city":"Hamburg",
    "sg:phone":"+49 40/323041",
    "sg:postcode":"20095",
    "sg:province":"Hamburg",
    "wof:name":"Tunis Air",
    "wof:placetype":"venue"
},
  "geometry": {"coordinates":[10.00085,53.552799],"type":"Point"}
}