{
  "type": "Feature",
  "properties": {
    "iso:country":"DE",
    "sg:address":"Klein Rietz 21a",
    "sg:city":"Gro\u00df Rietz",
    "sg:phone":"+49 3366/21164",
    "sg:postcode":"15848",
    "sg:province":"Brandenburg",
    "wof:name":"Willkommen Bei Ewald-korn-bau",
    "wof:placetype":"venue"
},
  "geometry": {"coordinates":[14.197433,52.211697],"type":"Point"}
}