{
  "type": "Feature",
  "properties": {
    "iso:country":"DE",
    "sg:address":"Ziegelofenweg 13",
    "sg:city":"Speyer",
    "sg:phone":"+49 6232/620644",
    "sg:postcode":"67346",
    "sg:province":"Rheinland-Pfalz",
    "wof:name":"Trim-line",
    "wof:placetype":"venue"
},
  "geometry": {"coordinates":[8.440477,49.322968],"type":"Point"}
}