{
  "type": "Feature",
  "properties": {
    "iso:country":"DE",
    "sg:address":"M\u00f6hlstr. 3",
    "sg:city":"M\u00fcnchen",
    "sg:phone":"+49 89/4180030",
    "sg:postcode":"81675",
    "sg:province":"Bayern",
    "wof:name":"Generalkonsulat Der Republik Italien",
    "wof:placetype":"venue"
},
  "geometry": {"coordinates":[11.5990371704,48.1415596008],"type":"Point"}
}