{
  "type": "Feature",
  "properties": {
    "iso:country":"DE",
    "sg:address":"Rosenstr. 15",
    "sg:city":"Ahrensfelde",
    "sg:postcode":"16356",
    "sg:province":"Brandenburg",
    "wof:name":"Vo\u00df & Meister Gmbh",
    "wof:placetype":"venue"
},
  "geometry": {"coordinates":[13.5846204758,52.5860404968],"type":"Point"}
}