{
  "type": "Feature",
  "properties": {
    "iso:country":"DE",
    "sg:address":"Max-Winkelmann-Str. 4",
    "sg:city":"M\u00fcnster",
    "sg:phone":"+49 2501/4600",
    "sg:postcode":"48165",
    "sg:province":"Nordrhein-Westfalen",
    "wof:name":"Michael Seidel Masseur",
    "wof:placetype":"venue"
},
  "geometry": {"coordinates":[7.6442,51.902348],"type":"Point"}
}