{
  "type": "Feature",
  "properties": {
    "iso:country":"DE",
    "sg:address":"Bruchsaler Str. 5",
    "sg:city":"Weinheim",
    "sg:phone":"+49 6201/18900",
    "sg:postcode":"69469",
    "sg:province":"Baden-W\u00fcrttemberg",
    "wof:name":"Abt Print Und Medien Gmbh",
    "wof:placetype":"venue"
},
  "geometry": {"coordinates":[8.634922,49.548702],"type":"Point"}
}