{
  "type": "Feature",
  "properties": {
    "iso:country":"DE",
    "sg:address":"Martin-Luther-Str. 103",
    "sg:city":"Stuttgart",
    "sg:phone":"+49 711/5499540",
    "sg:postcode":"70372",
    "sg:province":"Baden-W\u00fcrttemberg",
    "wof:name":"Weiss Teuchert Beck Br\u00e4unling Steuerberater Und Rechtsanwalt",
    "wof:placetype":"venue"
},
  "geometry": {"coordinates":[9.225894928,48.8010635376],"type":"Point"}
}