{
  "type": "Feature",
  "properties": {
    "iso:country":"DE",
    "sg:address":"Kirchstr. 1",
    "sg:city":"M\u00fchltal",
    "sg:phone":"+49 6151/146640",
    "sg:postcode":"64367",
    "sg:province":"Hessen",
    "wof:name":"Tryschuk Ingenieur",
    "wof:placetype":"venue"
},
  "geometry": {"coordinates":[8.7016296387,49.8245544434],"type":"Point"}
}