{
  "type": "Feature",
  "properties": {
    "iso:country":"DE",
    "sg:address":"Osterwaldstr. 10",
    "sg:city":"M\u00fcnchen",
    "sg:phone":"+49 89/3684980",
    "sg:postcode":"80805",
    "sg:province":"Bayern",
    "wof:name":"Trendhouse Eventmarketing Gmbh",
    "wof:placetype":"venue"
},
  "geometry": {"coordinates":[11.597666,48.163261],"type":"Point"}
}