{
  "type": "Feature",
  "properties": {
    "iso:country":"DE",
    "sg:address":"Guerickestr. 3",
    "sg:city":"S\u00f6mmerda",
    "sg:phone":"+49 3634/610050",
    "sg:postcode":"99610",
    "sg:province":"Th\u00fcringen",
    "wof:name":"Elektro Steffen K\u00f6nig Gmbh",
    "wof:placetype":"venue"
},
  "geometry": {"coordinates":[11.12846,51.161179],"type":"Point"}
}