{
  "type": "Feature",
  "properties": {
    "iso:country":"DE",
    "sg:address":"Frauenrichter Str.",
    "sg:city":"Weiden",
    "sg:phone":"+49 961/22365",
    "sg:postcode":"92637",
    "sg:province":"Bayern",
    "wof:name":"Edeltraud Glo\u00dfner",
    "wof:placetype":"venue"
},
  "geometry": {"coordinates":[12.155475,49.672752],"type":"Point"}
}