{
  "type": "Feature",
  "properties": {
    "iso:country":"DE",
    "sg:address":"Hamerweg 238",
    "sg:city":"M\u00f6nchengladbach",
    "sg:phone":"+49 2161/531942",
    "sg:postcode":"41068",
    "sg:province":"Nordrhein-Westfalen",
    "wof:name":"Hans-dieter Janzen",
    "wof:placetype":"venue"
},
  "geometry": {"coordinates":[6.3949,51.203514],"type":"Point"}
}