{
  "type": "Feature",
  "properties": {
    "iso:country":"DE",
    "sg:address":"Augustastr. 9",
    "sg:city":"Wesel",
    "sg:phone":"+49 281",
    "sg:postcode":"46483",
    "sg:province":"Nordrhein-Westfalen",
    "wof:name":"Immobilien Anbieter",
    "wof:placetype":"venue"
},
  "geometry": {"coordinates":[6.624198,51.656055],"type":"Point"}
}