{
  "type": "Feature",
  "properties": {
    "iso:country":"DE",
    "sg:address":"Lerchenberger Str. 37",
    "sg:city":"G\u00f6ppingen",
    "sg:phone":"+49 7161/21790",
    "sg:postcode":"73035",
    "sg:province":"Baden-W\u00fcrttemberg",
    "wof:name":"Pilsbar Domino",
    "wof:placetype":"venue"
},
  "geometry": {"coordinates":[9.6564559937,48.7243652344],"type":"Point"}
}