{
  "type": "Feature",
  "properties": {
    "iso:country":"DE",
    "sg:address":"Marienburgweg 6",
    "sg:city":"Cremlingen",
    "sg:phone":"+49 5306/4446",
    "sg:postcode":"38162",
    "sg:province":"Niedersachsen",
    "wof:name":"Dr. A. Giesau Rechtsanw\u00e4ltin",
    "wof:placetype":"venue"
},
  "geometry": {"coordinates":[10.6342344284,52.2750167847],"type":"Point"}
}