{
  "type": "Feature",
  "properties": {
    "iso:country":"DE",
    "sg:address":"Asterstr. 17",
    "sg:city":"Montabaur",
    "sg:phone":"+49 2602/4522",
    "sg:postcode":"56410",
    "sg:province":"Rheinland-Pfalz",
    "wof:name":"Esther M\u00fcller",
    "wof:placetype":"venue"
},
  "geometry": {"coordinates":[7.8113470078,50.4486579895],"type":"Point"}
}