{
  "type": "Feature",
  "properties": {
    "iso:country":"DE",
    "sg:address":"Barnkruger Str. 30",
    "sg:city":"Drochtersen",
    "sg:phone":"+49 4148/238",
    "sg:postcode":"21706",
    "sg:province":"Niedersachsen",
    "wof:name":"Klaus Adami",
    "wof:placetype":"venue"
},
  "geometry": {"coordinates":[9.470722,53.681557],"type":"Point"}
}