{
  "type": "Feature",
  "properties": {
    "iso:country":"DE",
    "sg:address":"Schmidtstr. 24",
    "sg:city":"Emmerich",
    "sg:phone":"+49 2828/2287",
    "sg:postcode":"46446",
    "sg:province":"Nordrhein-Westfalen",
    "wof:name":"T. Van Lier",
    "wof:placetype":"venue"
},
  "geometry": {"coordinates":[6.161125,51.872501],"type":"Point"}
}