{
  "type": "Feature",
  "properties": {
    "iso:country":"DE",
    "sg:address":"Geschwister-Scholl-Stadion",
    "sg:city":"Apolda",
    "sg:phone":"+49 3644/619935",
    "sg:postcode":"99510",
    "sg:province":"Th\u00fcringen",
    "wof:name":"Tennisanlage Apolda",
    "wof:placetype":"venue"
},
  "geometry": {"coordinates":[11.509604454,51.0231628418],"type":"Point"}
}