{
  "type": "Feature",
  "properties": {
    "iso:country":"DE",
    "sg:address":"Lindenstr. 31",
    "sg:city":"Torgelow",
    "sg:phone":"+49 3976/433162",
    "sg:postcode":"17358",
    "sg:province":"Mecklenburg-Vorpommern",
    "wof:name":"B. Ha\u00df",
    "wof:placetype":"venue"
},
  "geometry": {"coordinates":[13.9995079041,53.6298980713],"type":"Point"}
}