{
  "type": "Feature",
  "properties": {
    "iso:country":"DE",
    "sg:address":"Otten Damm 55",
    "sg:city":"Lengerich",
    "sg:phone":"+49 5484/1503",
    "sg:postcode":"49525",
    "sg:province":"Nordrhein-Westfalen",
    "wof:name":"Gustav Otte",
    "wof:placetype":"venue"
},
  "geometry": {"coordinates":[7.851585,52.145576],"type":"Point"}
}