{
  "type": "Feature",
  "properties": {
    "iso:country":"DE",
    "sg:address":"Schmiedberg 1",
    "sg:city":"Zschorlau",
    "sg:phone":"+49 3771/458246",
    "sg:postcode":"08321",
    "sg:province":"Sachsen",
    "wof:name":"A. Leonhardt",
    "wof:placetype":"venue"
},
  "geometry": {"coordinates":[12.655464,50.571262],"type":"Point"}
}