{
  "type": "Feature",
  "properties": {
    "iso:country":"DE",
    "sg:address":"Gustav-Sch\u00f6nleber-Str. 3",
    "sg:city":"Karlsruhe",
    "sg:phone":"+49 721/566776",
    "sg:postcode":"76187",
    "sg:province":"Baden-W\u00fcrttemberg",
    "wof:name":"R. Igel",
    "wof:placetype":"venue"
},
  "geometry": {"coordinates":[8.349614,49.031757],"type":"Point"}
}