{
  "type": "Feature",
  "properties": {
    "iso:country":"DE",
    "sg:address":"Oesfeldstr. 15",
    "sg:city":"L\u00f6\u00dfnitz",
    "sg:phone":"+49 3771/554040",
    "sg:postcode":"08294",
    "sg:province":"Sachsen",
    "wof:name":"Reiseb\u00fcro Marion Koch",
    "wof:placetype":"venue"
},
  "geometry": {"coordinates":[12.7293653488,50.620803833],"type":"Point"}
}