{
  "type": "Feature",
  "properties": {
    "iso:country":"DE",
    "sg:address":"Hermesberg 19",
    "sg:city":"M\u00f6nchengladbach",
    "sg:phone":"+49 2161/583881",
    "sg:postcode":"41179",
    "sg:province":"Nordrhein-Westfalen",
    "wof:name":"G\u00fcnter Coun",
    "wof:placetype":"venue"
},
  "geometry": {"coordinates":[6.335328,51.160538],"type":"Point"}
}