{
  "type": "Feature",
  "properties": {
    "iso:country":"DE",
    "sg:address":"Breiter Weg 123a",
    "sg:city":"Magdeburg",
    "sg:postcode":"39104",
    "sg:province":"Sachsen-Anhalt",
    "wof:name":"Copyshop",
    "wof:placetype":"venue"
},
  "geometry": {"coordinates":[11.6370925903,52.1349411011],"type":"Point"}
}