{
  "type": "Feature",
  "properties": {
    "iso:country":"DE",
    "sg:address":"Ernst-Th\u00e4lmann-Str. 110",
    "sg:city":"Viernau",
    "sg:phone":"+49 36847/32526",
    "sg:postcode":"98547",
    "sg:province":"Th\u00fcringen",
    "wof:name":"Fliesenmeisterbetrieb Mathias Tausch E. Kfm.",
    "wof:placetype":"venue"
},
  "geometry": {"coordinates":[10.5527477264,50.6678581238],"type":"Point"}
}