{
  "type": "Feature",
  "properties": {
    "iso:country":"DE",
    "sg:address":"Burgstemmer Str. 3",
    "sg:city":"Nordstemmen",
    "sg:phone":"+49 5069/549",
    "sg:postcode":"31171",
    "sg:province":"Niedersachsen",
    "wof:name":"Fritz M\u00fcnter",
    "wof:placetype":"venue"
},
  "geometry": {"coordinates":[9.781025,52.157631],"type":"Point"}
}