{
  "type": "Feature",
  "properties": {
    "iso:country":"DE",
    "sg:address":"Kennedyallee 33",
    "sg:city":"Frankfurt",
    "sg:phone":"+49 69/638070",
    "sg:postcode":"60596",
    "sg:province":"Hessen",
    "wof:name":"Integra Ingenieurbau Gmbh",
    "wof:placetype":"venue"
},
  "geometry": {"coordinates":[8.67418,50.100403],"type":"Point"}
}