{
  "type": "Feature",
  "properties": {
    "iso:country":"DE",
    "sg:address":"Schmiedestr 26",
    "sg:city":"Gro\u00dfefehn",
    "sg:phone":"+49 4943/91080",
    "sg:postcode":"26629",
    "sg:province":"Niedersachsen",
    "wof:name":"Apx Ag",
    "wof:placetype":"venue"
},
  "geometry": {"coordinates":[7.5679411888,53.402469635],"type":"Point"}
}