{
  "type": "Feature",
  "properties": {
    "iso:country":"DE",
    "sg:address":"Bergstr. 2",
    "sg:city":"Ehrenkirchen",
    "sg:phone":"+49 7633/101607",
    "sg:postcode":"79238",
    "sg:province":"Baden-W\u00fcrttemberg",
    "wof:name":"Bernhard Br\u00fcstle",
    "wof:placetype":"venue"
},
  "geometry": {"coordinates":[7.727521,47.938389],"type":"Point"}
}