{
  "type": "Feature",
  "properties": {
    "iso:country":"DE",
    "sg:address":"Elisabethstr. 4",
    "sg:city":"Hofgeismar",
    "sg:phone":"+49 5671/920432",
    "sg:postcode":"34369",
    "sg:province":"Hessen",
    "wof:name":"Restaurant Dornr\u00f6schen",
    "wof:placetype":"venue"
},
  "geometry": {"coordinates":[9.382774353,51.4933738708],"type":"Point"}
}