{
  "type": "Feature",
  "properties": {
    "iso:country":"DE",
    "sg:address":"Sautener Str. 18a",
    "sg:city":"Gersthofen",
    "sg:phone":"+49 8230/89050",
    "sg:postcode":"86368",
    "sg:province":"Bayern",
    "wof:name":"Contecta Immobilien Gmbh",
    "wof:placetype":"venue"
},
  "geometry": {"coordinates":[10.8071365356,48.4346199036],"type":"Point"}
}