{
  "type": "Feature",
  "properties": {
    "iso:country":"DE",
    "sg:address":"Pfalzgrafenstr. 2",
    "sg:city":"Neustadt",
    "sg:phone":"+49 6321/39270",
    "sg:postcode":"67434",
    "sg:province":"Rheinland-Pfalz",
    "wof:name":"Gerhard D\u00fcrr Architekt",
    "wof:placetype":"venue"
},
  "geometry": {"coordinates":[8.144044,49.347244],"type":"Point"}
}