{
  "type": "Feature",
  "properties": {
    "iso:country":"DE",
    "sg:address":"Brandfeldstr. 4",
    "sg:city":"M\u00f6nchsroth",
    "sg:phone":"+49 9853/3691",
    "sg:postcode":"91614",
    "sg:province":"Bayern",
    "wof:name":"Mtv Streng Gmbh",
    "wof:placetype":"venue"
},
  "geometry": {"coordinates":[10.367742,49.018669],"type":"Point"}
}