{
  "type": "Feature",
  "properties": {
    "iso:country":"DE",
    "sg:address":"Siemensstr. 6 a",
    "sg:city":"Sch\u00f6naich",
    "sg:phone":"+49 7031/652865",
    "sg:postcode":"71101",
    "sg:province":"Baden-W\u00fcrttemberg",
    "wof:name":"E. Ressl",
    "wof:placetype":"venue"
},
  "geometry": {"coordinates":[9.0637769699,48.6698303223],"type":"Point"}
}