{
  "type": "Feature",
  "properties": {
    "iso:country":"DE",
    "sg:address":"Drosselweg 15",
    "sg:city":"Chemnitz",
    "sg:phone":"+49 371/741888",
    "sg:postcode":"09130",
    "sg:province":"Sachsen",
    "wof:name":"Gerhard Uhlig",
    "wof:placetype":"venue"
},
  "geometry": {"coordinates":[12.964377,50.837605],"type":"Point"}
}