{
  "type": "Feature",
  "properties": {
    "iso:country":"DE",
    "sg:address":"Adlerstr 2c",
    "sg:city":"Rellingen",
    "sg:phone":"+49 4101/371347",
    "sg:postcode":"25462",
    "sg:province":"Schleswig-Holstein",
    "wof:name":"Kreissparkasse Pinneberg",
    "wof:placetype":"venue"
},
  "geometry": {"coordinates":[9.872911,53.631145],"type":"Point"}
}