{
  "type": "Feature",
  "properties": {
    "iso:country":"DE",
    "sg:address":"Schlachte 10-11",
    "sg:city":"Bremen",
    "sg:phone":"+49 7633/92640",
    "sg:postcode":"28195",
    "sg:province":"Bremen",
    "wof:name":"Engler Spedition Gmbh",
    "wof:placetype":"venue"
},
  "geometry": {"coordinates":[7.674846,47.953846],"type":"Point"}
}