{
  "type": "Feature",
  "properties": {
    "iso:country":"DE",
    "sg:address":"Albert-Krieg-Str. 12",
    "sg:city":"Nagold",
    "sg:phone":"+49 7452/65103",
    "sg:postcode":"72202",
    "sg:province":"Baden-W\u00fcrttemberg",
    "wof:name":"B\u00e4rbel Und Peter Gl\u00fcck",
    "wof:placetype":"venue"
},
  "geometry": {"coordinates":[8.7175607681,48.5340194702],"type":"Point"}
}