{
  "type": "Feature",
  "properties": {
    "iso:country":"DE",
    "sg:address":"Heiliggeistgasse 1",
    "sg:city":"Passau",
    "sg:phone":"+49 851/2578",
    "sg:postcode":"94032",
    "sg:province":"Bayern",
    "wof:name":"Mumme Ohg",
    "wof:placetype":"venue"
},
  "geometry": {"coordinates":[13.4588699341,48.5739250183],"type":"Point"}
}