{
  "type": "Feature",
  "properties": {
    "iso:country":"DE",
    "sg:address":"Trift 11",
    "sg:city":"Langwedel",
    "sg:phone":"+49 4232/8090",
    "sg:postcode":"27299",
    "sg:province":"Niedersachsen",
    "wof:name":"Diedrich Siemer",
    "wof:placetype":"venue"
},
  "geometry": {"coordinates":[9.23052,52.980869],"type":"Point"}
}