{
  "type": "Feature",
  "properties": {
    "iso:country":"DE",
    "sg:address":"Max-Eyth-Str. 36",
    "sg:city":"Wolfschlugen",
    "sg:phone":"+49 7022/953300",
    "sg:postcode":"72649",
    "sg:province":"Baden-W\u00fcrttemberg",
    "wof:name":"Litho-team Stoll Und Maurer Gmbh",
    "wof:placetype":"venue"
},
  "geometry": {"coordinates":[9.29676,48.649189],"type":"Point"}
}