{
  "type": "Feature",
  "properties": {
    "iso:country":"DE",
    "sg:address":"Morsestr. 12",
    "sg:city":"K\u00f6ln",
    "sg:phone":"+49 221/9703160",
    "sg:postcode":"50769",
    "sg:province":"Nordrhein-Westfalen",
    "wof:name":"Klaus H. Loeffel Gmbh",
    "wof:placetype":"venue"
},
  "geometry": {"coordinates":[6.9264678955,51.0369186401],"type":"Point"}
}