{
  "type": "Feature",
  "properties": {
    "iso:country":"DE",
    "sg:address":"Morgensternweg 10 a",
    "sg:city":"Hannover",
    "sg:phone":"+49 511/795265",
    "sg:postcode":"30419",
    "sg:province":"Niedersachsen",
    "wof:name":"Werner Lindau Ingenieur Und Architekt",
    "wof:placetype":"venue"
},
  "geometry": {"coordinates":[9.691473,52.390892],"type":"Point"}
}