{
  "type": "Feature",
  "properties": {
    "iso:country":"DE",
    "sg:address":"Glash\u00fctte 43",
    "sg:city":"Kreuth",
    "sg:phone":"+49 8029/1363",
    "sg:postcode":"83708",
    "sg:province":"Bayern",
    "wof:name":"R. Sennhofer",
    "wof:placetype":"venue"
},
  "geometry": {"coordinates":[11.6505451202,47.6121635437],"type":"Point"}
}