{
  "type": "Feature",
  "properties": {
    "iso:country":"DE",
    "sg:address":"Tychsenstr. 13",
    "sg:city":"Rostock",
    "sg:postcode":"18059",
    "sg:province":"Mecklenburg-Vorpommern",
    "wof:name":"Dr. Med. Renate Oschatz",
    "wof:placetype":"venue"
},
  "geometry": {"coordinates":[12.117225,54.067524],"type":"Point"}
}