{
  "type": "Feature",
  "properties": {
    "iso:country":"DE",
    "sg:address":"Mitterhof 5",
    "sg:city":"Eggenfelden",
    "sg:postcode":"84307",
    "sg:province":"Bayern",
    "wof:name":"Gvg Grundst\u00fccksverwertungs- Gmbh & Co. Kg",
    "wof:placetype":"venue"
},
  "geometry": {"coordinates":[12.7663640976,48.4050750732],"type":"Point"}
}