{
  "type": "Feature",
  "properties": {
    "iso:country":"DE",
    "sg:address":"Radensdorfer Hauptstr. 42",
    "sg:city":"L\u00fcbben",
    "sg:phone":"+49 3546/7647",
    "sg:postcode":"15907",
    "sg:province":"Brandenburg",
    "wof:name":"Kaisers Restaurant",
    "wof:placetype":"venue"
},
  "geometry": {"coordinates":[13.9894094467,51.9429893494],"type":"Point"}
}