{
  "type": "Feature",
  "properties": {
    "iso:country":"DE",
    "sg:address":"Weiler",
    "sg:city":"Weiler",
    "sg:phone":"+49 7261/2185",
    "sg:postcode":"74889",
    "sg:province":"Baden-W\u00fcrttemberg",
    "wof:name":"Raiffeisenbank Steinsberg Eg",
    "wof:placetype":"venue"
},
  "geometry": {"coordinates":[8.87587,49.208618],"type":"Point"}
}