{
  "type": "Feature",
  "properties": {
    "iso:country":"DE",
    "sg:address":"Querstr 3",
    "sg:city":"Friedrichroda",
    "sg:phone":"+49 3623/309652",
    "sg:postcode":"99894",
    "sg:province":"Th\u00fcringen",
    "wof:name":"Dieter Piegert",
    "wof:placetype":"venue"
},
  "geometry": {"coordinates":[10.621468544,50.8668708801],"type":"Point"}
}