{
  "type": "Feature",
  "properties": {
    "iso:country":"DE",
    "sg:address":"Brennereiweg 43b",
    "sg:city":"Wagenitz",
    "sg:phone":"+49 33237/89019",
    "sg:postcode":"14641",
    "sg:province":"Brandenburg",
    "wof:name":"Landfleischerei Wagenitz",
    "wof:placetype":"venue"
},
  "geometry": {"coordinates":[12.6418323517,52.675037384],"type":"Point"}
}