{
  "type": "Feature",
  "properties": {
    "iso:country":"DE",
    "sg:address":"Bleiswijker Str. 2",
    "sg:city":"Dreieich",
    "sg:phone":"+49 6103/651544",
    "sg:postcode":"63303",
    "sg:province":"Hessen",
    "wof:name":"Stadtb\u00fccherei",
    "wof:placetype":"venue"
},
  "geometry": {"coordinates":[8.732981,49.997799],"type":"Point"}
}