{
  "type": "Feature",
  "properties": {
    "iso:country":"DE",
    "sg:address":"Wolfsberg 1",
    "sg:city":"Eggenfelden",
    "sg:phone":"+49 8721/8833",
    "sg:postcode":"84307",
    "sg:province":"Bayern",
    "wof:name":"Alois Hager",
    "wof:placetype":"venue"
},
  "geometry": {"coordinates":[12.750667572,48.4206619263],"type":"Point"}
}