{
  "type": "Feature",
  "properties": {
    "iso:country":"DE",
    "sg:address":"Bauterweg 12",
    "sg:city":"Schwabm\u00fcnchen",
    "sg:phone":"+49 8232/74188",
    "sg:postcode":"86830",
    "sg:province":"Bayern",
    "wof:name":"Schiller & Borne",
    "wof:placetype":"venue"
},
  "geometry": {"coordinates":[10.753176,48.179764],"type":"Point"}
}