{
  "type": "Feature",
  "properties": {
    "iso:country":"DE",
    "sg:address":"Ansbacher Str. 4",
    "sg:city":"Aurach",
    "sg:phone":"+49 9804/216",
    "sg:postcode":"91589",
    "sg:province":"Bayern",
    "wof:name":"Franz Rattelmeier",
    "wof:placetype":"venue"
},
  "geometry": {"coordinates":[10.4151210785,49.2460250854],"type":"Point"}
}