{
  "type": "Feature",
  "properties": {
    "iso:country":"DE",
    "sg:address":"Sandkaulerweg 52",
    "sg:city":"Sinzig",
    "sg:phone":"+49 2636/7123",
    "sg:postcode":"53489",
    "sg:province":"Rheinland-Pfalz",
    "wof:name":"Sila Konservenvertriebs- Und Verwaltungs-gmbh",
    "wof:placetype":"venue"
},
  "geometry": {"coordinates":[7.2662401199,50.5411109924],"type":"Point"}
}