{
  "type": "Feature",
  "properties": {
    "iso:country":"DE",
    "sg:address":"Alte Landstr. 5",
    "sg:city":"Laugna",
    "sg:phone":"+49 8272/2414",
    "sg:postcode":"86502",
    "sg:province":"Bayern",
    "wof:name":"Hubert Sapper",
    "wof:placetype":"venue"
},
  "geometry": {"coordinates":[10.688864,48.504459],"type":"Point"}
}