{
  "type": "Feature",
  "properties": {
    "iso:country":"DE",
    "sg:address":"Am Kurbaum 9",
    "sg:city":"Steinfurt",
    "sg:phone":"+49 2551/2659",
    "sg:postcode":"48565",
    "sg:province":"Nordrhein-Westfalen",
    "wof:name":"Willi Denkler Architekt",
    "wof:placetype":"venue"
},
  "geometry": {"coordinates":[7.327092,52.154072],"type":"Point"}
}