{
  "type": "Feature",
  "properties": {
    "iso:country":"DE",
    "sg:address":"Herforder Str. 425",
    "sg:city":"Vlotho",
    "sg:phone":"+49 5733/7180",
    "sg:postcode":"32602",
    "sg:province":"Nordrhein-Westfalen",
    "wof:name":"Potthast",
    "wof:placetype":"venue"
},
  "geometry": {"coordinates":[8.772600174,52.1374206543],"type":"Point"}
}