{
  "type": "Feature",
  "properties": {
    "iso:country":"DE",
    "sg:address":"Kirchstra\u00dfe 64",
    "sg:city":"D\u00fclmen",
    "sg:phone":"+49 172 9117085",
    "sg:postcode":"48249",
    "sg:province":"Nordrhein-Westfalen",
    "wof:name":"Emissionsprospekt - Stephan Temming",
    "wof:placetype":"venue"
},
  "geometry": {"coordinates":[7.278960228,51.8292732239],"type":"Point"}
}