{
  "type": "Feature",
  "properties": {
    "iso:country":"DE",
    "sg:address":"Sachsenstr. 10",
    "sg:city":"Schwalbach",
    "sg:phone":"+49 6196/3222",
    "sg:postcode":"65824",
    "sg:province":"Hessen",
    "wof:name":"Dr. Reinhard Gadomski Steuerberater",
    "wof:placetype":"venue"
},
  "geometry": {"coordinates":[8.5180912018,50.1624488831],"type":"Point"}
}