{
  "type": "Feature",
  "properties": {
    "iso:country":"DE",
    "sg:address":"Sophienstr. 10",
    "sg:city":"Erlangen",
    "sg:phone":"+49 8247/96840",
    "sg:postcode":"91052",
    "sg:province":"Bayern",
    "wof:name":"Hotel L\u00d6wenbr\u00c4u Braugasthof",
    "wof:placetype":"venue"
},
  "geometry": {"coordinates":[10.589585,48.002998],"type":"Point"}
}