{
  "type": "Feature",
  "properties": {
    "iso:country":"DE",
    "sg:address":"Jahnstr. 19",
    "sg:city":"Heidelberg",
    "sg:phone":"+49 6221/412408",
    "sg:postcode":"69120",
    "sg:province":"Baden-W\u00fcrttemberg",
    "wof:name":"E. Joachim",
    "wof:placetype":"venue"
},
  "geometry": {"coordinates":[8.6765298843,49.4125404358],"type":"Point"}
}