{
  "type": "Feature",
  "properties": {
    "iso:country":"DE",
    "sg:address":"M\u00fchlenheider Str. 18",
    "sg:city":"Delbr\u00fcck",
    "sg:phone":"+49 2944/7005",
    "sg:postcode":"33129",
    "sg:province":"Nordrhein-Westfalen",
    "wof:name":"Anton Brunnert",
    "wof:placetype":"venue"
},
  "geometry": {"coordinates":[8.439491,51.721684],"type":"Point"}
}