{
  "type": "Feature",
  "properties": {
    "iso:country":"DE",
    "sg:address":"Boschstr. 8",
    "sg:city":"Ratingen",
    "sg:phone":"+49 2102/74060",
    "sg:postcode":"40880",
    "sg:province":"Nordrhein-Westfalen",
    "wof:name":"Hubert Von Ameln",
    "wof:placetype":"venue"
},
  "geometry": {"coordinates":[6.820136,51.298706],"type":"Point"}
}