{
  "type": "Feature",
  "properties": {
    "iso:country":"DE",
    "sg:address":"Leistruper-Wald-Str. 100",
    "sg:city":"Detmold",
    "sg:phone":"+49 5231/57339",
    "sg:postcode":"32760",
    "sg:province":"Nordrhein-Westfalen",
    "wof:name":"Berghof Stork Inh. Tatjana Hergaden-ge\u00dfner",
    "wof:placetype":"venue"
},
  "geometry": {"coordinates":[8.9573392868,51.9081802368],"type":"Point"}
}