{
  "type": "Feature",
  "properties": {
    "iso:country":"DE",
    "sg:address":"Am Markt 7",
    "sg:city":"Kaltenkirchen",
    "sg:phone":"+49 4191/85616",
    "sg:postcode":"24568",
    "sg:province":"Schleswig-Holstein",
    "wof:name":"Speicher Handels Gmbh",
    "wof:placetype":"venue"
},
  "geometry": {"coordinates":[9.9630661011,53.8376045227],"type":"Point"}
}