{
  "type": "Feature",
  "properties": {
    "iso:country":"DE",
    "sg:address":"Hauptstr. 384",
    "sg:city":"K\u00f6nigswinter",
    "sg:phone":"+49 2223/28823",
    "sg:postcode":"53639",
    "sg:province":"Nordrhein-Westfalen",
    "wof:name":"Kaktus",
    "wof:placetype":"venue"
},
  "geometry": {"coordinates":[7.1932630539,50.6749458313],"type":"Point"}
}