{
  "type": "Feature",
  "properties": {
    "iso:country":"DE",
    "sg:address":"Verdistr. 4",
    "sg:city":"Baldham",
    "sg:postcode":"85598",
    "sg:province":"Bayern",
    "wof:name":"Vip Verbundforschung F. Inform. U. Ges.-fortb. Gmbh",
    "wof:placetype":"venue"
},
  "geometry": {"coordinates":[11.7918872833,48.1069030762],"type":"Point"}
}