{
  "type": "Feature",
  "properties": {
    "iso:country":"DE",
    "sg:address":"Pfaffenreuther Str. 13",
    "sg:city":"Waldsassen",
    "sg:phone":"+49 9632/8585",
    "sg:postcode":"95652",
    "sg:province":"Bayern",
    "wof:name":"Horst-ludwig Schlokat Ingenieur",
    "wof:placetype":"venue"
},
  "geometry": {"coordinates":[12.3136177063,49.9962921143],"type":"Point"}
}