{
  "type": "Feature",
  "properties": {
    "iso:country":"DE",
    "sg:address":"Staatsstr. 6",
    "sg:city":"Stromberg",
    "sg:phone":"+49 6724/592",
    "sg:postcode":"55442",
    "sg:province":"Rheinland-Pfalz",
    "wof:name":"Rosen Apotheke Peter Bader E.k.",
    "wof:placetype":"venue"
},
  "geometry": {"coordinates":[7.771562,49.943577],"type":"Point"}
}