{
  "type": "Feature",
  "properties": {
    "iso:country":"DE",
    "sg:address":"Deckemattstr. 8",
    "sg:city":"Kandern",
    "sg:phone":"+49 7626/971524",
    "sg:postcode":"79400",
    "sg:province":"Baden-W\u00fcrttemberg",
    "wof:name":"Klaus Eichin Anlageberater",
    "wof:placetype":"venue"
},
  "geometry": {"coordinates":[7.6646800041,47.712184906],"type":"Point"}
}