{
  "type": "Feature",
  "properties": {
    "iso:country":"DE",
    "sg:address":"D\u00e4nenweg 5",
    "sg:city":"Hamm",
    "sg:phone":"+49 2381/419182",
    "sg:postcode":"59067",
    "sg:province":"Nordrhein-Westfalen",
    "wof:name":"Dr. U. Meyer",
    "wof:placetype":"venue"
},
  "geometry": {"coordinates":[7.78789711,51.6735839844],"type":"Point"}
}