{
  "type": "Feature",
  "properties": {
    "iso:country":"DE",
    "sg:address":"Hauptstr. 39",
    "sg:city":"Strehla",
    "sg:phone":"+49 35264/90364",
    "sg:postcode":"01616",
    "sg:province":"Sachsen",
    "wof:name":"Richard J\u00e4hnig",
    "wof:placetype":"venue"
},
  "geometry": {"coordinates":[13.230802,51.351871],"type":"Point"}
}