{
  "type": "Feature",
  "properties": {
    "iso:country":"DE",
    "sg:address":"Schillerstr. 7",
    "sg:city":"Freital",
    "sg:phone":"+49 351/6494084",
    "sg:postcode":"01705",
    "sg:province":"Sachsen",
    "wof:name":"W. Fleischer",
    "wof:placetype":"venue"
},
  "geometry": {"coordinates":[13.6518783569,50.9939918518],"type":"Point"}
}