{
  "type": "Feature",
  "properties": {
    "iso:country":"DE",
    "sg:address":"Oberstr. 54",
    "sg:city":"St. Goar",
    "sg:phone":"+49 6741/337",
    "sg:postcode":"56329",
    "sg:province":"Rheinland-Pfalz",
    "wof:name":"Ernst-otto Breidenbach",
    "wof:placetype":"venue"
},
  "geometry": {"coordinates":[7.716058,50.150063],"type":"Point"}
}