{
  "type": "Feature",
  "properties": {
    "iso:country":"DE",
    "sg:address":"Gewerbestr. 1",
    "sg:city":"Muldenstein",
    "sg:phone":"+49 3493/56537",
    "sg:postcode":"06804",
    "sg:province":"Sachsen-Anhalt",
    "wof:name":"Thomas Quandt",
    "wof:placetype":"venue"
},
  "geometry": {"coordinates":[12.351173,51.667469],"type":"Point"}
}