{
  "type": "Feature",
  "properties": {
    "iso:country":"DE",
    "sg:address":"Im Winkel 8",
    "sg:city":"Giesen",
    "sg:phone":"+49 5066/62095",
    "sg:postcode":"31180",
    "sg:province":"Niedersachsen",
    "wof:name":"Friedrich Ohms",
    "wof:placetype":"venue"
},
  "geometry": {"coordinates":[9.907497,52.209538],"type":"Point"}
}