{
  "type": "Feature",
  "properties": {
    "iso:country":"DE",
    "sg:address":"Mannheimer Str. 27",
    "sg:city":"Heidelberg",
    "sg:phone":"+49 6221/8410",
    "sg:postcode":"69115",
    "sg:province":"Baden-W\u00fcrttemberg",
    "wof:name":"Regionales Rechenzentrum Heidelberg",
    "wof:placetype":"venue"
},
  "geometry": {"coordinates":[8.6842803955,49.4077682495],"type":"Point"}
}