{
  "type": "Feature",
  "properties": {
    "iso:country":"DE",
    "sg:address":"Landecker Str. 2",
    "sg:city":"Freiamt",
    "sg:phone":"+49 7645/418",
    "sg:postcode":"79348",
    "sg:province":"Baden-W\u00fcrttemberg",
    "wof:name":"Ernst Wagner",
    "wof:placetype":"venue"
},
  "geometry": {"coordinates":[7.883106,48.175869],"type":"Point"}
}