{
  "type": "Feature",
  "properties": {
    "iso:country":"DE",
    "sg:address":"Rosastr. 15",
    "sg:city":"Freiburg",
    "sg:phone":"+49 761/381338",
    "sg:postcode":"79098",
    "sg:province":"Baden-W\u00fcrttemberg",
    "wof:name":"Gerhard Holz Steuerberater-rechtsanwalt",
    "wof:placetype":"venue"
},
  "geometry": {"coordinates":[7.8460001945,47.9981994629],"type":"Point"}
}