{
  "type": "Feature",
  "properties": {
    "iso:country":"DE",
    "sg:address":"B\u00fcdericher Str. 11-13",
    "sg:city":"Neuss",
    "sg:phone":"+49 2131/274872",
    "sg:postcode":"41460",
    "sg:province":"Nordrhein-Westfalen",
    "wof:name":"Rtn Immobilien Gmbh",
    "wof:placetype":"venue"
},
  "geometry": {"coordinates":[6.6906352043,51.2153091431],"type":"Point"}
}