{
  "type": "Feature",
  "properties": {
    "iso:country":"DE",
    "sg:address":"Kreuznacher Str. 27",
    "sg:city":"Bad Sobernheim",
    "sg:phone":"+49 6751/2684",
    "sg:postcode":"55566",
    "sg:province":"Rheinland-Pfalz",
    "wof:name":"G\u00fcnter Frick",
    "wof:placetype":"venue"
},
  "geometry": {"coordinates":[7.6749520302,49.8059120178],"type":"Point"}
}