{
  "type": "Feature",
  "properties": {
    "iso:country":"DE",
    "sg:address":"Enzberger Str. 1",
    "sg:city":"Niefern-\u00d6schelbronn",
    "sg:phone":"+49 7233/4206",
    "sg:postcode":"75223",
    "sg:province":"Baden-W\u00fcrttemberg",
    "wof:name":"G\u00e4stehaus Maierhof",
    "wof:placetype":"venue"
},
  "geometry": {"coordinates":[8.7747535706,48.9213371277],"type":"Point"}
}