{
  "type": "Feature",
  "properties": {
    "iso:country":"DE",
    "sg:address":"Untere Hauptstr. 1",
    "sg:city":"Tuttlingen",
    "sg:phone":"+49 7461/75413",
    "sg:postcode":"78532",
    "sg:province":"Baden-W\u00fcrttemberg",
    "wof:name":"Helmut Heppeler",
    "wof:placetype":"venue"
},
  "geometry": {"coordinates":[8.818948,47.984222],"type":"Point"}
}