{
  "type": "Feature",
  "properties": {
    "iso:country":"DE",
    "sg:address":"Wildenbruchstr. 41",
    "sg:city":"Duesseldorf",
    "sg:phone":"+49 211/556207",
    "sg:postcode":"40545",
    "sg:province":"Nordrhein-Westfalen",
    "wof:name":"Anwaltskanzlei Ciper & Coll.",
    "wof:placetype":"venue"
},
  "geometry": {"coordinates":[6.754314,51.228432],"type":"Point"}
}