{
  "type": "Feature",
  "properties": {
    "iso:country":"DE",
    "sg:address":"Rathenaustr. 1",
    "sg:city":"Braunschweig",
    "sg:phone":"+49 531/323488",
    "sg:postcode":"38126",
    "sg:province":"Niedersachsen",
    "wof:name":"Dpa Deutsche Presse Agentur Gmbh",
    "wof:placetype":"venue"
},
  "geometry": {"coordinates":[10.5531282425,52.2309837341],"type":"Point"}
}