{
  "type": "Feature",
  "properties": {
    "iso:country":"DE",
    "sg:address":"Lingestrote 4",
    "sg:city":"Schmallenberg",
    "sg:phone":"+49 2971/9609006",
    "sg:postcode":"57392",
    "sg:province":"Nordrhein-Westfalen",
    "wof:name":"Alois Gierse",
    "wof:placetype":"venue"
},
  "geometry": {"coordinates":[8.2858181,51.154045105],"type":"Point"}
}