{
  "type": "Feature",
  "properties": {
    "iso:country":"DE",
    "sg:address":"Weinbergstr 2",
    "sg:city":"Rimpar",
    "sg:phone":"+49 9365/4165",
    "sg:postcode":"97222",
    "sg:province":"Bayern",
    "wof:name":"Gf Kalender & Werbeartikel",
    "wof:placetype":"venue"
},
  "geometry": {"coordinates":[9.951442,49.858765],"type":"Point"}
}