{
  "type": "Feature",
  "properties": {
    "iso:country":"DE",
    "sg:address":"An der Angerwiese 6",
    "sg:city":"Steinberg",
    "sg:phone":"+49 37462/3700",
    "sg:postcode":"08237",
    "sg:province":"Sachsen",
    "wof:name":"Leistner",
    "wof:placetype":"venue"
},
  "geometry": {"coordinates":[12.504815,50.537544],"type":"Point"}
}