{
  "type": "Feature",
  "properties": {
    "iso:country":"DE",
    "sg:address":"Marienstr 5",
    "sg:city":"Bestwig",
    "sg:phone":"+49 2904/97070",
    "sg:postcode":"59909",
    "sg:province":"Nordrhein-Westfalen",
    "wof:name":"Josef Middel B\u00fcrom\u00f6belwerk Gmbh & Co Kg",
    "wof:placetype":"venue"
},
  "geometry": {"coordinates":[8.4025411606,51.3590240479],"type":"Point"}
}