{
  "type": "Feature",
  "properties": {
    "iso:country":"DE",
    "sg:address":"Westerlandstr. 8",
    "sg:city":"Wenningstedt",
    "sg:phone":"+49 4651/7423",
    "sg:postcode":"25996",
    "sg:province":"Schleswig-Holstein",
    "wof:name":"Blumenhaus Goemann Inh. Rolf Goemann",
    "wof:placetype":"venue"
},
  "geometry": {"coordinates":[8.322746,54.935719],"type":"Point"}
}