{
  "type": "Feature",
  "properties": {
    "iso:country":"DE",
    "sg:address":"Schwarzer Weg",
    "sg:city":"Berlin",
    "sg:phone":"+49 30/4337063",
    "sg:postcode":"13505",
    "sg:province":"Berlin",
    "wof:name":"Restaurant Toulouse",
    "wof:placetype":"venue"
},
  "geometry": {"coordinates":[13.2582025528,52.5916748047],"type":"Point"}
}