{
  "type": "Feature",
  "properties": {
    "iso:country":"DE",
    "sg:address":"Klaus-Mewes-Str. 15",
    "sg:city":"Moormerland",
    "sg:phone":"+49 4954/89278",
    "sg:postcode":"26802",
    "sg:province":"Niedersachsen",
    "wof:name":"Hfh Zeichenstudio Gmbh",
    "wof:placetype":"venue"
},
  "geometry": {"coordinates":[7.490673,53.314632],"type":"Point"}
}