{
  "type": "Feature",
  "properties": {
    "iso:country":"DE",
    "sg:city":"Wies",
    "sg:phone":"+49 4976/29351",
    "sg:postcode":"79697",
    "sg:province":"Baden-W\u00fcrttemberg",
    "wof:name":"Raiffeisenbank Eg",
    "wof:placetype":"venue"
},
  "geometry": {"coordinates":[7.76723,47.74789],"type":"Point"}
}