{
  "type": "Feature",
  "properties": {
    "iso:country":"DE",
    "sg:address":"Am Hellweg 7",
    "sg:city":"Bad Driburg",
    "sg:phone":"+49 5253/2511",
    "sg:postcode":"33014",
    "sg:province":"Nordrhein-Westfalen",
    "wof:name":"Elektro Versen Heinrich Versen",
    "wof:placetype":"venue"
},
  "geometry": {"coordinates":[9.0207872391,51.7352905273],"type":"Point"}
}