{
  "type": "Feature",
  "properties": {
    "iso:country":"DE",
    "sg:address":"Hermann-Hesse-Str. 26",
    "sg:city":"Mainz",
    "sg:phone":"+49 6131/78050",
    "sg:postcode":"55127",
    "sg:province":"Rheinland-Pfalz",
    "wof:name":"Prof. W. Elfers Kunstmaler",
    "wof:placetype":"venue"
},
  "geometry": {"coordinates":[8.191051,49.955029],"type":"Point"}
}