{
  "type": "Feature",
  "properties": {
    "iso:country":"DE",
    "sg:address":"Westernstr. 26",
    "sg:city":"Paderborn",
    "sg:phone":"+49 5251/22220",
    "sg:postcode":"33098",
    "sg:province":"Nordrhein-Westfalen",
    "wof:name":"Atlas Reisen Gmbh",
    "wof:placetype":"venue"
},
  "geometry": {"coordinates":[8.7490606308,51.7164421082],"type":"Point"}
}