{
  "type": "Feature",
  "properties": {
    "iso:country":"DE",
    "sg:address":"Baron-M\u00fcller-Weg 7",
    "sg:city":"M\u00fchlacker",
    "sg:phone":"+49 7041/4806",
    "sg:postcode":"75417",
    "sg:province":"Baden-W\u00fcrttemberg",
    "wof:name":"A & K Cnc-drehen- Gmbh",
    "wof:placetype":"venue"
},
  "geometry": {"coordinates":[8.83769,48.940861],"type":"Point"}
}