{
  "type": "Feature",
  "properties": {
    "iso:country":"DE",
    "sg:address":"Hauptstr. 31a",
    "sg:city":"K\u00f6nigsbrunn",
    "sg:phone":"+49 831/4041",
    "sg:postcode":"86343",
    "sg:province":"Bayern",
    "wof:name":"Bayerische Vereinsbank Ag",
    "wof:placetype":"venue"
},
  "geometry": {"coordinates":[10.890975,48.268719],"type":"Point"}
}