{
  "type": "Feature",
  "properties": {
    "iso:country":"DE",
    "sg:address":"Hornauer Str. 55",
    "sg:city":"Kelkheim",
    "sg:phone":"+49 6195/996400",
    "sg:postcode":"65779",
    "sg:province":"Hessen",
    "wof:name":"D. Lange",
    "wof:placetype":"venue"
},
  "geometry": {"coordinates":[8.450075,50.143055],"type":"Point"}
}