{
  "type": "Feature",
  "properties": {
    "iso:country":"DE",
    "sg:address":"Weibermarkt 7",
    "sg:city":"Reutlingen",
    "sg:phone":"+49 7121/93520",
    "sg:postcode":"72764",
    "sg:province":"Baden-W\u00fcrttemberg",
    "wof:name":"Harald Eysel Rechtsanwalt",
    "wof:placetype":"venue"
},
  "geometry": {"coordinates":[9.2147598267,48.4916687012],"type":"Point"}
}