{
  "type": "Feature",
  "properties": {
    "iso:country":"DE",
    "sg:address":"Stangeng\u00e4rtenstr. 22",
    "sg:city":"Bad Liebenwerda",
    "sg:phone":"+49 35341/10172",
    "sg:postcode":"04924",
    "sg:province":"Brandenburg",
    "wof:name":"Baugesch\u00e4ft Wagner & Co. Gmbh",
    "wof:placetype":"venue"
},
  "geometry": {"coordinates":[13.3968877792,51.5115318298],"type":"Point"}
}