{
  "type": "Feature",
  "properties": {
    "iso:country":"DE",
    "sg:address":"Benckiserplatz 1",
    "sg:city":"Ludwigshafen",
    "sg:phone":"+49 621/59660",
    "sg:postcode":"67059",
    "sg:province":"Rheinland-Pfalz",
    "wof:name":"Basf Ag L\u00e4nderbereich Vertrieb",
    "wof:placetype":"venue"
},
  "geometry": {"coordinates":[8.4363203049,49.4796905518],"type":"Point"}
}