{
  "type": "Feature",
  "properties": {
    "iso:country":"DE",
    "sg:address":"Uhlandstr. 6",
    "sg:city":"Bad Kreuznach",
    "sg:phone":"+49 671/62845",
    "sg:postcode":"55543",
    "sg:province":"Rheinland-Pfalz",
    "wof:name":"Heinz Jung Ingenieur",
    "wof:placetype":"venue"
},
  "geometry": {"coordinates":[7.8780832291,49.8304824829],"type":"Point"}
}