{
  "type": "Feature",
  "properties": {
    "iso:country":"DE",
    "sg:address":"Unterer Markt 7",
    "sg:city":"Triftern",
    "sg:phone":"+49 8562/1250",
    "sg:postcode":"84371",
    "sg:province":"Bayern",
    "wof:name":"Wei\u00dfbierbrauerei Bauer Franco Und Gudrun Testor",
    "wof:placetype":"venue"
},
  "geometry": {"coordinates":[13.006477,48.39518],"type":"Point"}
}