{
  "type": "Feature",
  "properties": {
    "iso:country":"DE",
    "sg:address":"Am Storrenacker 13",
    "sg:city":"Karlsruhe",
    "sg:phone":"+49 5545/961035",
    "sg:postcode":"76139",
    "sg:province":"Baden-W\u00fcrttemberg",
    "wof:name":"Fehrensen Gmbh",
    "wof:placetype":"venue"
},
  "geometry": {"coordinates":[9.7532949448,51.3939285278],"type":"Point"}
}