{
  "type": "Feature",
  "properties": {
    "iso:country":"DE",
    "sg:address":"M\u00fchlendamm 4",
    "sg:city":"Hamburg",
    "sg:phone":"+49 40/256406",
    "sg:postcode":"22087",
    "sg:province":"Hamburg",
    "wof:name":"Arno Baumann B\u00fcrotechnik Ohg",
    "wof:placetype":"venue"
},
  "geometry": {"coordinates":[10.025762558,53.560218811],"type":"Point"}
}