{
  "type": "Feature",
  "properties": {
    "iso:country":"DE",
    "sg:address":"Industriestr. 14",
    "sg:city":"Gie\u00dfen",
    "sg:phone":"+49 641/494580",
    "sg:postcode":"35394",
    "sg:province":"Hessen",
    "wof:name":"Dietrich-bergler Gmbh & Co. Kg",
    "wof:placetype":"venue"
},
  "geometry": {"coordinates":[8.737066,50.593636],"type":"Point"}
}