{
  "type": "Feature",
  "properties": {
    "iso:country":"DE",
    "sg:address":"Gesteinerstr. 56",
    "sg:city":"Konnersreuth",
    "sg:phone":"+49 9632/5408",
    "sg:postcode":"95692",
    "sg:province":"Bayern",
    "wof:name":"H. W.-bau Gmbh",
    "wof:placetype":"venue"
},
  "geometry": {"coordinates":[12.221495,50.0047],"type":"Point"}
}