{
  "type": "Feature",
  "properties": {
    "iso:country":"DE",
    "sg:address":"Schlosserstr. 39",
    "sg:city":"Stuttgart",
    "sg:phone":"+49 711/6406970",
    "sg:postcode":"70180",
    "sg:province":"Baden-W\u00fcrttemberg",
    "wof:name":"Arnold Prasse",
    "wof:placetype":"venue"
},
  "geometry": {"coordinates":[9.1733703613,48.767868042],"type":"Point"}
}