{
  "type": "Feature",
  "properties": {
    "iso:country":"DE",
    "sg:address":"Zerbster Str. 9",
    "sg:city":"Bornum",
    "sg:phone":"+49 39248/9400",
    "sg:postcode":"39264",
    "sg:province":"Sachsen-Anhalt",
    "wof:name":"Agrargenossenschaft Bornum Eg",
    "wof:placetype":"venue"
},
  "geometry": {"coordinates":[12.1985569,51.9846382141],"type":"Point"}
}