{
  "type": "Feature",
  "properties": {
    "iso:country":"DE",
    "sg:address":"Gutenbergstr. 4",
    "sg:city":"G\u00f6llheim",
    "sg:phone":"+49 6351/13000",
    "sg:postcode":"67307",
    "sg:province":"Rheinland-Pfalz",
    "wof:name":"Verbandsgemeidewerke G\u00f6llheim",
    "wof:placetype":"venue"
},
  "geometry": {"coordinates":[8.040798,49.593376],"type":"Point"}
}