{
  "type": "Feature",
  "properties": {
    "iso:country":"DE",
    "sg:address":"Ursulastr 85",
    "sg:city":"Essen",
    "sg:phone":"+49 201/435040",
    "sg:postcode":"45131",
    "sg:province":"Nordrhein-Westfalen",
    "wof:name":"Alfred Paas & Cie Gmbh",
    "wof:placetype":"venue"
},
  "geometry": {"coordinates":[7.0039200783,51.4240951538],"type":"Point"}
}