{
  "type": "Feature",
  "properties": {
    "iso:country":"DE",
    "sg:address":"Neuenhauser Str. 3",
    "sg:city":"Nordhorn",
    "sg:phone":"+49 5921/39017",
    "sg:postcode":"48529",
    "sg:province":"Niedersachsen",
    "wof:name":"Biercafe Mona Lisa",
    "wof:placetype":"venue"
},
  "geometry": {"coordinates":[7.0697741508,52.43800354],"type":"Point"}
}