{
  "type": "Feature",
  "properties": {
    "iso:country":"DE",
    "sg:address":"Uferallee 1a",
    "sg:city":"Bernkastel-Kues",
    "sg:phone":"+49 6531/6077",
    "sg:postcode":"54470",
    "sg:province":"Rheinland-Pfalz",
    "wof:name":"Eduard Keil Gmbh",
    "wof:placetype":"venue"
},
  "geometry": {"coordinates":[7.036485,49.944824],"type":"Point"}
}