{
  "type": "Feature",
  "properties": {
    "iso:country":"DE",
    "sg:address":"Nierenhofer Str. 8-10",
    "sg:city":"Essen",
    "sg:phone":"+49 201/45200",
    "sg:postcode":"45257",
    "sg:province":"Nordrhein-Westfalen",
    "wof:name":"Museumslandschaft Deilbachtal",
    "wof:placetype":"venue"
},
  "geometry": {"coordinates":[7.09024,51.381584],"type":"Point"}
}