{
  "type": "Feature",
  "properties": {
    "iso:country":"DE",
    "sg:address":"Uelzener Str. 1",
    "sg:city":"L\u00fcneburg",
    "sg:phone":"+49 4131/730040",
    "sg:postcode":"21335",
    "sg:province":"Niedersachsen",
    "wof:name":"Restaurant Come In",
    "wof:placetype":"venue"
},
  "geometry": {"coordinates":[10.4039497375,53.2414474487],"type":"Point"}
}