{
  "type": "Feature",
  "properties": {
    "iso:country":"DE",
    "sg:address":"Dieselstr. 5",
    "sg:city":"Dossenheim",
    "sg:phone":"+49 6221/866516",
    "sg:postcode":"69221",
    "sg:province":"Baden-W\u00fcrttemberg",
    "wof:name":"Kurt Dremel Mech. Werkstatt",
    "wof:placetype":"venue"
},
  "geometry": {"coordinates":[8.663796,49.441265],"type":"Point"}
}