{
  "type": "Feature",
  "properties": {
    "iso:country":"DE",
    "sg:address":"Luisenstr. 12",
    "sg:city":"Velten",
    "sg:phone":"+49 3304/502460",
    "sg:postcode":"16727",
    "sg:province":"Brandenburg",
    "wof:name":"Helmut Faber",
    "wof:placetype":"venue"
},
  "geometry": {"coordinates":[13.173996,52.692493],"type":"Point"}
}