{
  "type": "Feature",
  "properties": {
    "iso:country":"DE",
    "sg:address":"Ludwig-Nissen-Str. 39",
    "sg:city":"Husum",
    "sg:postcode":"25813",
    "sg:province":"Schleswig-Holstein",
    "wof:name":"Windpark Osterrade Gmbh",
    "wof:placetype":"venue"
},
  "geometry": {"coordinates":[9.055745,54.475677],"type":"Point"}
}