{
  "type": "Feature",
  "properties": {
    "iso:country":"DE",
    "sg:address":"Mittelstr. 3",
    "sg:city":"Kaufungen",
    "sg:phone":"+49 5605/5455",
    "sg:postcode":"34260",
    "sg:province":"Hessen",
    "wof:name":"Ludwig Werner",
    "wof:placetype":"venue"
},
  "geometry": {"coordinates":[9.604909,51.286015],"type":"Point"}
}