{
  "type": "Feature",
  "properties": {
    "iso:country":"DE",
    "sg:address":"Berliner Str. 111",
    "sg:city":"Offenbach",
    "sg:phone":"+49 69/829990",
    "sg:postcode":"63065",
    "sg:province":"Hessen",
    "wof:name":"Arabella Sheraton Am B\u00fcsing Palais",
    "wof:placetype":"venue"
},
  "geometry": {"coordinates":[8.7615203857,50.1063652039],"type":"Point"}
}