{
  "type": "Feature",
  "properties": {
    "iso:country":"DE",
    "sg:address":"Gottlieb-Fecht-Str. 20",
    "sg:city":"Kehl",
    "sg:postcode":"77694",
    "sg:province":"Baden-W\u00fcrttemberg",
    "wof:name":"Mfa Verwaltungs- Gmbh",
    "wof:placetype":"venue"
},
  "geometry": {"coordinates":[7.876543045,48.569229126],"type":"Point"}
}