{
  "type": "Feature",
  "properties": {
    "iso:country":"DE",
    "sg:address":"Rabenkirchenholz 20",
    "sg:city":"Rabenkirchen-Faul\u00fcck",
    "sg:postcode":"24407",
    "sg:province":"Schleswig-Holstein",
    "wof:name":"Uwe Br\u00fcckner Bauunternehmen Gmbh",
    "wof:placetype":"venue"
},
  "geometry": {"coordinates":[9.874833107,54.6592140198],"type":"Point"}
}