{
  "type": "Feature",
  "properties": {
    "iso:country":"DE",
    "sg:address":"Saarlandstr. 359",
    "sg:city":"Bingen",
    "sg:phone":"+49 6721/43900",
    "sg:postcode":"55411",
    "sg:province":"Rheinland-Pfalz",
    "wof:name":"G\u00fcnther Braden",
    "wof:placetype":"venue"
},
  "geometry": {"coordinates":[7.910232,49.93568],"type":"Point"}
}