{
  "type": "Feature",
  "properties": {
    "iso:country":"DE",
    "sg:address":"Pegelsberg 12a",
    "sg:city":"Kuhstorf",
    "sg:phone":"+49 3883/723028",
    "sg:postcode":"19230",
    "sg:province":"Mecklenburg-Vorpommern",
    "wof:name":"Peter Bollow",
    "wof:placetype":"venue"
},
  "geometry": {"coordinates":[11.245829,53.382545],"type":"Point"}
}