{
  "type": "Feature",
  "properties": {
    "iso:country":"DE",
    "sg:address":"Heyerhof",
    "sg:city":"Schornsheim",
    "sg:phone":"+49 6732/4333",
    "sg:postcode":"55288",
    "sg:province":"Rheinland-Pfalz",
    "wof:name":"H. Und J. Hofmeister",
    "wof:placetype":"venue"
},
  "geometry": {"coordinates":[8.1742582321,49.850769043],"type":"Point"}
}