{
  "type": "Feature",
  "properties": {
    "iso:country":"DE",
    "sg:address":"Am Kohlenberg 6",
    "sg:city":"Nordstemmen",
    "sg:phone":"+49 5069/8040385",
    "sg:postcode":"31171",
    "sg:province":"Niedersachsen",
    "wof:name":"It-dienstleitungen",
    "wof:placetype":"venue"
},
  "geometry": {"coordinates":[9.847167,52.150028],"type":"Point"}
}