{
  "type": "Feature",
  "properties": {
    "iso:country":"DE",
    "sg:address":"Karlsruher Str. 2",
    "sg:city":"Bruchsal",
    "sg:phone":"+49 7251/17675",
    "sg:postcode":"76646",
    "sg:province":"Baden-W\u00fcrttemberg",
    "wof:name":"Cafe K\u00e4nguruh",
    "wof:placetype":"venue"
},
  "geometry": {"coordinates":[8.589928,49.118893],"type":"Point"}
}