{
  "type": "Feature",
  "properties": {
    "iso:country":"DE",
    "sg:address":"Binger Str. 26",
    "sg:city":"Worms",
    "sg:phone":"+49 6241/75347",
    "sg:postcode":"67549",
    "sg:province":"Rheinland-Pfalz",
    "wof:name":"Fritz Schr\u00f6ter",
    "wof:placetype":"venue"
},
  "geometry": {"coordinates":[8.335306,49.638916],"type":"Point"}
}