{
  "type": "Feature",
  "properties": {
    "iso:country":"DE",
    "sg:address":"Hufeisenstr. 23",
    "sg:city":"Naumburg",
    "sg:phone":"+49 5625/5327",
    "sg:postcode":"34311",
    "sg:province":"Hessen",
    "wof:name":"Georg Griesel",
    "wof:placetype":"venue"
},
  "geometry": {"coordinates":[9.205131,51.215038],"type":"Point"}
}