{
  "type": "Feature",
  "properties": {
    "iso:country":"DE",
    "sg:address":"Schleifmattstr 16",
    "sg:city":"Haslach",
    "sg:phone":"+49 7081/92520",
    "sg:postcode":"77716",
    "sg:province":"Baden-W\u00fcrttemberg",
    "wof:name":"Eisele Druck Gmbh",
    "wof:placetype":"venue"
},
  "geometry": {"coordinates":[8.5532150269,48.7553062439],"type":"Point"}
}