{
  "type": "Feature",
  "properties": {
    "iso:country":"DE",
    "sg:address":"Schwarzwaldstr. 17",
    "sg:city":"Pforzheim",
    "sg:phone":"+49 7231/22358",
    "sg:postcode":"75173",
    "sg:province":"Baden-W\u00fcrttemberg",
    "wof:name":"Reinhold Krause",
    "wof:placetype":"venue"
},
  "geometry": {"coordinates":[8.692356,48.884937],"type":"Point"}
}