{
  "type": "Feature",
  "properties": {
    "iso:country":"DE",
    "sg:address":"Bahnhofstr. 19",
    "sg:city":"Uelzen",
    "sg:phone":"+49 581/2895",
    "sg:postcode":"29525",
    "sg:province":"Niedersachsen",
    "wof:name":"Erich Rudolph",
    "wof:placetype":"venue"
},
  "geometry": {"coordinates":[10.556019783,52.9662094116],"type":"Point"}
}