{
  "type": "Feature",
  "properties": {
    "iso:country":"DE",
    "sg:address":"Erfurter Tor 2",
    "sg:city":"T\u00f6ttelst\u00e4dt",
    "sg:phone":"+49 36208/7540",
    "sg:postcode":"99100",
    "sg:province":"Th\u00fcringen",
    "wof:name":"Pension Wei\u00dfbachtal",
    "wof:placetype":"venue"
},
  "geometry": {"coordinates":[10.8845567703,51.007648468],"type":"Point"}
}