{
  "type": "Feature",
  "properties": {
    "iso:country":"DE",
    "sg:address":"Weiherwiesen 13",
    "sg:city":"Burgthann",
    "sg:phone":"+49 9183/1328",
    "sg:postcode":"90559",
    "sg:province":"Bayern",
    "wof:name":"Hilpert-fischer Gmbh",
    "wof:placetype":"venue"
},
  "geometry": {"coordinates":[11.346138,49.347004],"type":"Point"}
}