{
  "type": "Feature",
  "properties": {
    "iso:country":"DE",
    "sg:address":"Graf-Dietrich-Str. 23 b",
    "sg:city":"Oldenburg",
    "sg:phone":"+49 441/36854",
    "sg:postcode":"26123",
    "sg:province":"Niedersachsen",
    "wof:name":"Wolfgang Uschmann Bauunternehmen",
    "wof:placetype":"venue"
},
  "geometry": {"coordinates":[8.233714,53.153229],"type":"Point"}
}