{
  "type": "Feature",
  "properties": {
    "iso:country":"DE",
    "sg:address":"Stiftsweg 4",
    "sg:city":"Bellenberg",
    "sg:phone":"+49 7306/8871",
    "sg:postcode":"89287",
    "sg:province":"Bayern",
    "wof:name":"Hansa Metallwerke Ag",
    "wof:placetype":"venue"
},
  "geometry": {"coordinates":[10.081996,48.254704],"type":"Point"}
}