{
  "type": "Feature",
  "properties": {
    "iso:country":"DE",
    "sg:address":"Nottkampstr. 1",
    "sg:city":"Gelsenkirchen",
    "sg:phone":"+49 209/594377",
    "sg:postcode":"45897",
    "sg:province":"Nordrhein-Westfalen",
    "wof:name":"Apotheke Schaffrath",
    "wof:placetype":"venue"
},
  "geometry": {"coordinates":[7.03001,51.560467],"type":"Point"}
}