{
  "type": "Feature",
  "properties": {
    "iso:country":"DE",
    "sg:address":"Am Fillerberg 1",
    "sg:city":"Hankensb\u00fcttel",
    "sg:phone":"+49 5832/1777",
    "sg:postcode":"29386",
    "sg:province":"Niedersachsen",
    "wof:name":"Schlegel Gmbh",
    "wof:placetype":"venue"
},
  "geometry": {"coordinates":[10.608733,52.726128],"type":"Point"}
}