{
  "type": "Feature",
  "properties": {
    "iso:country":"DE",
    "sg:address":"Schubertweg 3",
    "sg:city":"Bad Sassendorf",
    "sg:phone":"+49 2921/55164",
    "sg:postcode":"59505",
    "sg:province":"Nordrhein-Westfalen",
    "wof:name":"Ferdinand Sander Steuerberater",
    "wof:placetype":"venue"
},
  "geometry": {"coordinates":[8.1663322449,51.5970458984],"type":"Point"}
}