{
  "type": "Feature",
  "properties": {
    "iso:country":"DE",
    "sg:address":"Lindenstr. 4",
    "sg:city":"Neckarsulm",
    "sg:phone":"+49 7132/42806",
    "sg:postcode":"74172",
    "sg:province":"Baden-W\u00fcrttemberg",
    "wof:name":"Thomas Sennert",
    "wof:placetype":"venue"
},
  "geometry": {"coordinates":[9.2015237808,49.1960754395],"type":"Point"}
}