{
  "type": "Feature",
  "properties": {
    "iso:country":"DE",
    "sg:address":"Zietenstr. 71",
    "sg:city":"Chemnitz",
    "sg:phone":"+49 371/4011664",
    "sg:postcode":"09130",
    "sg:province":"Sachsen",
    "wof:name":"W. Thiele",
    "wof:placetype":"venue"
},
  "geometry": {"coordinates":[12.9410266876,50.8384895325],"type":"Point"}
}