{
  "type": "Feature",
  "properties": {
    "iso:country":"DE",
    "sg:address":"Lange Str. 10",
    "sg:city":"Tonna",
    "sg:phone":"+49 36042/364",
    "sg:postcode":"99958",
    "sg:province":"Th\u00fcringen",
    "wof:name":"C. Braun",
    "wof:placetype":"venue"
},
  "geometry": {"coordinates":[10.7307395935,51.090259552],"type":"Point"}
}