{
  "type": "Feature",
  "properties": {
    "iso:country":"DE",
    "sg:address":"Hauptstr. 22",
    "sg:city":"Hauenstein",
    "sg:phone":"+49 6392/1533",
    "sg:postcode":"76846",
    "sg:province":"Rheinland-Pfalz",
    "wof:name":"Albert Hasselwander",
    "wof:placetype":"venue"
},
  "geometry": {"coordinates":[7.8568019867,49.1911048889],"type":"Point"}
}