{
  "type": "Feature",
  "properties": {
    "iso:country":"DE",
    "sg:address":"Hans-Sachs-Str. 4",
    "sg:city":"F\u00fcrstenwalde",
    "sg:phone":"+49 3361/77030",
    "sg:postcode":"15517",
    "sg:province":"Brandenburg",
    "wof:name":"Hartwig & Co. Bauausf\u00fchrungen Gmbh",
    "wof:placetype":"venue"
},
  "geometry": {"coordinates":[14.0508813858,52.3512878418],"type":"Point"}
}