{
  "type": "Feature",
  "properties": {
    "iso:country":"DE",
    "sg:address":"Forster Str. 114 b",
    "sg:city":"Pei\u00dfenberg",
    "sg:phone":"+49 8803/5665",
    "sg:postcode":"82380",
    "sg:province":"Bayern",
    "wof:name":"Leonhard Schwaller",
    "wof:placetype":"venue"
},
  "geometry": {"coordinates":[11.0614519119,47.8074302673],"type":"Point"}
}