{
  "type": "Feature",
  "properties": {
    "iso:country":"DE",
    "sg:address":"Im Hasengrund 78",
    "sg:city":"R\u00fcsselsheim",
    "sg:phone":"+49 6142/31903",
    "sg:postcode":"65428",
    "sg:province":"Hessen",
    "wof:name":"Marino Gmbh",
    "wof:placetype":"venue"
},
  "geometry": {"coordinates":[8.423284,49.978741],"type":"Point"}
}