{
  "type": "Feature",
  "properties": {
    "iso:country":"DE",
    "sg:address":"Bismarckstr. 235",
    "sg:city":"Wilhelmshaven",
    "sg:phone":"+49 4421/25359",
    "sg:postcode":"26382",
    "sg:province":"Niedersachsen",
    "wof:name":"Rainer Schlieker Gmbh",
    "wof:placetype":"venue"
},
  "geometry": {"coordinates":[8.096276,53.528809],"type":"Point"}
}