{
  "type": "Feature",
  "properties": {
    "iso:country":"DE",
    "sg:address":"Eschenauer Str. 20",
    "sg:city":"Knetzgau",
    "sg:phone":"+49 9527/92270",
    "sg:postcode":"97478",
    "sg:province":"Bayern",
    "wof:name":"Walter Bautenschutz Gmbh",
    "wof:placetype":"venue"
},
  "geometry": {"coordinates":[10.5009222031,49.977104187],"type":"Point"}
}