{
  "type": "Feature",
  "properties": {
    "iso:country":"DE",
    "sg:address":"Weidenstr. 26",
    "sg:city":"Stuhr",
    "sg:phone":"+49 421/560717",
    "sg:postcode":"28816",
    "sg:province":"Niedersachsen",
    "wof:name":"Max G\u00fcnther",
    "wof:placetype":"venue"
},
  "geometry": {"coordinates":[8.750088,53.031433],"type":"Point"}
}