{
  "type": "Feature",
  "properties": {
    "iso:country":"DE",
    "sg:address":"Schiefbahner Str. 21",
    "sg:city":"Korschenbroich",
    "sg:phone":"+49 2161/672480",
    "sg:postcode":"41352",
    "sg:province":"Nordrhein-Westfalen",
    "wof:name":"Gerhard Lenzen",
    "wof:placetype":"venue"
},
  "geometry": {"coordinates":[6.552916,51.209297],"type":"Point"}
}