{
  "type": "Feature",
  "properties": {
    "iso:country":"DE",
    "sg:address":"Hauptstr. 11-13",
    "sg:city":"Solingen",
    "sg:phone":"+49 212/204025",
    "sg:postcode":"42651",
    "sg:province":"Nordrhein-Westfalen",
    "wof:name":"Qtc Solingen",
    "wof:placetype":"venue"
},
  "geometry": {"coordinates":[7.084900856,51.1697807312],"type":"Point"}
}