{
  "type": "Feature",
  "properties": {
    "iso:country":"DE",
    "sg:address":"Hauptstr. 7",
    "sg:city":"T\u00f6ging",
    "sg:phone":"+49 8631/99997",
    "sg:postcode":"84513",
    "sg:province":"Bayern",
    "wof:name":"Norbert Altmannshofer",
    "wof:placetype":"venue"
},
  "geometry": {"coordinates":[12.5871868134,48.2548522949],"type":"Point"}
}