{
  "type": "Feature",
  "properties": {
    "iso:country":"DE",
    "sg:address":"Stra\u00dfe des Friedens 7",
    "sg:city":"Ilmenau",
    "sg:phone":"+49 3677/203209",
    "sg:postcode":"98693",
    "sg:province":"Th\u00fcringen",
    "wof:name":"Restaurant Ali Baba",
    "wof:placetype":"venue"
},
  "geometry": {"coordinates":[10.9141283035,50.6848182678],"type":"Point"}
}