{
  "type": "Feature",
  "properties": {
    "iso:country":"DE",
    "sg:address":"Raven\u00e9str. 35",
    "sg:city":"Cochem",
    "sg:phone":"+49 4926/7198990",
    "sg:postcode":"56812",
    "sg:province":"Rheinland-Pfalz",
    "wof:name":"Koll & Cie.",
    "wof:placetype":"venue"
},
  "geometry": {"coordinates":[7.166291,50.150021],"type":"Point"}
}