{
  "type": "Feature",
  "properties": {
    "iso:country":"DE",
    "sg:address":"Raiffeisenstr. 7a",
    "sg:city":"Korbach",
    "sg:phone":"+49 5631/64520",
    "sg:postcode":"34497",
    "sg:province":"Hessen",
    "wof:name":"Autosattlerei Endricat",
    "wof:placetype":"venue"
},
  "geometry": {"coordinates":[8.856053,51.291534],"type":"Point"}
}