{
  "type": "Feature",
  "properties": {
    "iso:country":"DE",
    "sg:address":"Schafbaumstr. 28",
    "sg:city":"Fluorn-Winzeln",
    "sg:phone":"+49 7402/7703",
    "sg:postcode":"78737",
    "sg:province":"Baden-W\u00fcrttemberg",
    "wof:name":"G. Und D. Herrmann",
    "wof:placetype":"venue"
},
  "geometry": {"coordinates":[8.4918193817,48.2981414795],"type":"Point"}
}