{
  "type": "Feature",
  "properties": {
    "iso:country":"DE",
    "sg:address":"Gewerbegebiet Sandfeld 10",
    "sg:city":"Rippershausen",
    "sg:phone":"+49 4936/9389930",
    "sg:postcode":"98639",
    "sg:province":"Th\u00fcringen",
    "wof:name":"Lenkungstechnik Willi Elbegmbh & Co. Kg",
    "wof:placetype":"venue"
},
  "geometry": {"coordinates":[10.3620471954,50.6049308777],"type":"Point"}
}