{
  "type": "Feature",
  "properties": {
    "iso:country":"DE",
    "sg:address":"Hamburger Str. 26",
    "sg:city":"Br\u00fchl",
    "sg:postcode":"50321",
    "sg:province":"Nordrhein-Westfalen",
    "wof:name":"K\u00f6nig Gleitlagertechnik Gmbh",
    "wof:placetype":"venue"
},
  "geometry": {"coordinates":[6.91356,50.845619],"type":"Point"}
}