{
  "type": "Feature",
  "properties": {
    "iso:country":"DE",
    "sg:address":"Mutterbachweg 18",
    "sg:city":"Spiesen-Elversberg",
    "sg:phone":"+49 6821/70063",
    "sg:postcode":"66583",
    "sg:province":"Saarland",
    "wof:name":"Beck & Schlosser Gmbh",
    "wof:placetype":"venue"
},
  "geometry": {"coordinates":[7.137244,49.312733],"type":"Point"}
}