{
  "type": "Feature",
  "properties": {
    "iso:country":"DE",
    "sg:city":"R\u00f6hrmoos",
    "sg:phone":"+49 8139/7641",
    "sg:postcode":"85244",
    "sg:province":"Bayern",
    "wof:name":"Renates Mieder & Dessous",
    "wof:placetype":"venue"
},
  "geometry": {"coordinates":[11.44418,48.331223],"type":"Point"}
}