{
  "type": "Feature",
  "properties": {
    "iso:country":"DE",
    "sg:address":"Neue Str 61",
    "sg:city":"Seebach",
    "sg:phone":"+49 36929/8180",
    "sg:postcode":"99846",
    "sg:province":"Th\u00fcringen",
    "wof:name":"Dipl.-ing. Ullrich Fischer",
    "wof:placetype":"venue"
},
  "geometry": {"coordinates":[10.425733,50.911652],"type":"Point"}
}