{
  "type": "Feature",
  "properties": {
    "iso:country":"DE",
    "sg:address":"Schachtlau 4",
    "sg:city":"Neureichenau",
    "sg:phone":"+49 8583/290",
    "sg:postcode":"94089",
    "sg:province":"Bayern",
    "wof:name":"Parat Automotive Sch\u00f6nenbach Gmbh & Co. Kg",
    "wof:placetype":"venue"
},
  "geometry": {"coordinates":[13.753077,48.744858],"type":"Point"}
}