{
  "type": "Feature",
  "properties": {
    "iso:country":"DE",
    "sg:address":"Wilhelm-Busch-Weg 7",
    "sg:city":"Elmshorn",
    "sg:phone":"+49 4121/82555",
    "sg:postcode":"25335",
    "sg:province":"Schleswig-Holstein",
    "wof:name":"Alfred Gercken Masseur",
    "wof:placetype":"venue"
},
  "geometry": {"coordinates":[9.665335,53.758076],"type":"Point"}
}