{
  "type": "Feature",
  "properties": {
    "iso:country":"DE",
    "sg:address":"Im Hoffeld 66",
    "sg:city":"Detmold",
    "sg:phone":"+49 5231/48044",
    "sg:postcode":"32760",
    "sg:province":"Nordrhein-Westfalen",
    "wof:name":"Hans-g\u00fcnther Riemer",
    "wof:placetype":"venue"
},
  "geometry": {"coordinates":[8.8706464767,51.8923149109],"type":"Point"}
}