{
  "type": "Feature",
  "properties": {
    "iso:country":"DE",
    "sg:address":"Bredkamp 109",
    "sg:city":"Hamburg",
    "sg:phone":"+49 40/874393",
    "sg:postcode":"22589",
    "sg:province":"Hamburg",
    "wof:name":"B. Kr\u00fcger",
    "wof:placetype":"venue"
},
  "geometry": {"coordinates":[9.819051,53.575535],"type":"Point"}
}