{
  "type": "Feature",
  "properties": {
    "iso:country":"DE",
    "sg:address":"Pritzwalker Str. 20",
    "sg:city":"Havelberg",
    "sg:phone":"+49 39387/80622",
    "sg:postcode":"39539",
    "sg:province":"Sachsen-Anhalt",
    "wof:name":"Bistro Piccolo",
    "wof:placetype":"venue"
},
  "geometry": {"coordinates":[12.0775356293,52.8325500488],"type":"Point"}
}