{
  "type": "Feature",
  "properties": {
    "iso:country":"DE",
    "sg:address":"Kahrm\u00fchlweg 12",
    "sg:city":"Pressath",
    "sg:phone":"+49 9644/444",
    "sg:postcode":"92690",
    "sg:province":"Bayern",
    "wof:name":"Eduard Dippl",
    "wof:placetype":"venue"
},
  "geometry": {"coordinates":[11.936384201,49.7634315491],"type":"Point"}
}