{
  "type": "Feature",
  "properties": {
    "iso:country":"DE",
    "sg:address":"Talstr. 23",
    "sg:city":"Elzach",
    "sg:phone":"+49 7682/90890",
    "sg:postcode":"79215",
    "sg:province":"Baden-W\u00fcrttemberg",
    "wof:name":"Ringwald & Dufner Gmbh",
    "wof:placetype":"venue"
},
  "geometry": {"coordinates":[8.0994901657,48.195224762],"type":"Point"}
}