{
  "type": "Feature",
  "properties": {
    "iso:country":"DE",
    "sg:address":"Ruhlsdorfer Str. 23",
    "sg:city":"Teltow",
    "sg:phone":"+49 3328/45770",
    "sg:postcode":"14513",
    "sg:province":"Brandenburg",
    "wof:name":"Teltower Wohnungsbaugenossenschaft Eg",
    "wof:placetype":"venue"
},
  "geometry": {"coordinates":[13.267568,52.39801],"type":"Point"}
}