{
  "type": "Feature",
  "properties": {
    "iso:country":"DE",
    "sg:address":"Viktoriastr. 36",
    "sg:city":"Bad Kreuznach",
    "sg:phone":"+49 671/844000",
    "sg:postcode":"55543",
    "sg:province":"Rheinland-Pfalz",
    "wof:name":"Hubert Verheyen Ingenieur",
    "wof:placetype":"venue"
},
  "geometry": {"coordinates":[7.8645019531,49.8460884094],"type":"Point"}
}