{
  "type": "Feature",
  "properties": {
    "iso:country":"DE",
    "sg:address":"Dohnaer Str. 73",
    "sg:city":"Dresden",
    "sg:postcode":"01219",
    "sg:province":"Sachsen",
    "wof:name":"Dvo Anlageberatung Ohg",
    "wof:placetype":"venue"
},
  "geometry": {"coordinates":[13.7696561813,51.018409729],"type":"Point"}
}