{
  "type": "Feature",
  "properties": {
    "iso:country":"DE",
    "sg:address":"Fuggerstr. 25",
    "sg:city":"Ibbenb\u00fcren",
    "sg:phone":"+49 4954/5199305",
    "sg:postcode":"49479",
    "sg:province":"Nordrhein-Westfalen",
    "wof:name":"Duotec Sondermaschinenbau Rest & Runde Gmbh",
    "wof:placetype":"venue"
},
  "geometry": {"coordinates":[7.776612,52.262054],"type":"Point"}
}