{
  "type": "Feature",
  "properties": {
    "iso:country":"DE",
    "sg:address":"Mangenberger Str. 96",
    "sg:city":"Solingen",
    "sg:phone":"+49 212/207310",
    "sg:postcode":"42655",
    "sg:province":"Nordrhein-Westfalen",
    "wof:name":"Walter Kiehl Gmbh",
    "wof:placetype":"venue"
},
  "geometry": {"coordinates":[7.065925,51.171242],"type":"Point"}
}