{
  "type": "Feature",
  "properties": {
    "iso:country":"DE",
    "sg:address":"Hans-Thoma-Str. 18",
    "sg:city":"Brigachtal",
    "sg:phone":"+49 7721/21742",
    "sg:postcode":"78086",
    "sg:province":"Baden-W\u00fcrttemberg",
    "wof:name":"Gelis Brautmoden",
    "wof:placetype":"venue"
},
  "geometry": {"coordinates":[8.456387,48.013462],"type":"Point"}
}