{
  "type": "Feature",
  "properties": {
    "iso:country":"DE",
    "sg:address":"Lustgarten 2",
    "sg:city":"Salzgitter",
    "sg:phone":"+49 5341/72979",
    "sg:postcode":"38229",
    "sg:province":"Niedersachsen",
    "wof:name":"Uwe Wahler",
    "wof:placetype":"venue"
},
  "geometry": {"coordinates":[10.3599834442,52.1041946411],"type":"Point"}
}