{
  "type": "Feature",
  "properties": {
    "iso:country":"DE",
    "sg:address":"Waldseer Str. 143",
    "sg:city":"Biberach",
    "sg:phone":"+49 7351/9186",
    "sg:postcode":"88400",
    "sg:province":"Baden-W\u00fcrttemberg",
    "wof:name":"Lidl Gmbh & Co. Kg",
    "wof:placetype":"venue"
},
  "geometry": {"coordinates":[9.8033266068,48.082069397],"type":"Point"}
}