{
  "type": "Feature",
  "properties": {
    "iso:country":"DE",
    "sg:address":"Dorneystr. 19",
    "sg:city":"Dortmund",
    "sg:phone":"+49 231/321274",
    "sg:postcode":"44149",
    "sg:province":"Nordrhein-Westfalen",
    "wof:name":"Michael Piercyk",
    "wof:placetype":"venue"
},
  "geometry": {"coordinates":[7.3692708015,51.4875946045],"type":"Point"}
}