{
  "type": "Feature",
  "properties": {
    "iso:country":"DE",
    "sg:address":"Am Stock 4e",
    "sg:city":"Neuss",
    "sg:phone":"+49 2131/546354",
    "sg:postcode":"41462",
    "sg:province":"Nordrhein-Westfalen",
    "wof:name":"Hamburg-mannheimer Abraam Savvidis",
    "wof:placetype":"venue"
},
  "geometry": {"coordinates":[6.6399440765,51.2289543152],"type":"Point"}
}