{
  "type": "Feature",
  "properties": {
    "iso:country":"DE",
    "sg:address":"Hartmannsweilerstr. 71",
    "sg:city":"Frankfurt",
    "sg:phone":"+49 69/3803240",
    "sg:postcode":"65933",
    "sg:province":"Hessen",
    "wof:name":"Schneider Schneider-neumann Und Dirschke",
    "wof:placetype":"venue"
},
  "geometry": {"coordinates":[8.6049556732,50.0916519165],"type":"Point"}
}