{
  "type": "Feature",
  "properties": {
    "iso:country":"DE",
    "sg:address":"Im Burkhardtsfeld 15",
    "sg:city":"Dobel",
    "sg:phone":"+49 4968/9496330",
    "sg:postcode":"75335",
    "sg:province":"Baden-W\u00fcrttemberg",
    "wof:name":"Mdc Control Gmbh",
    "wof:placetype":"venue"
},
  "geometry": {"coordinates":[7.112035,49.272728],"type":"Point"}
}