{
  "type": "Feature",
  "properties": {
    "iso:country":"DE",
    "sg:address":"Maddau 9",
    "sg:city":"Waddeweitz",
    "sg:phone":"+49 5849/664",
    "sg:postcode":"29496",
    "sg:province":"Niedersachsen",
    "wof:name":"Vinzenz Freiherr V. Feilitzsch Architekt",
    "wof:placetype":"venue"
},
  "geometry": {"coordinates":[10.960172,53.012753],"type":"Point"}
}