{
  "type": "Feature",
  "properties": {
    "iso:country":"DE",
    "sg:address":"Germaniastr. 89",
    "sg:city":"Frankfurt",
    "sg:phone":"+49 69/4692362",
    "sg:postcode":"60389",
    "sg:province":"Hessen",
    "wof:name":"Medienwerkstattinitiative Mewi E. V.",
    "wof:placetype":"venue"
},
  "geometry": {"coordinates":[8.6993198395,50.1267318726],"type":"Point"}
}