{
  "type": "Feature",
  "properties": {
    "iso:country":"DE",
    "sg:address":"Ro\u00dfbacher Str. 14",
    "sg:city":"Ro\u00dfbach",
    "sg:phone":"+49 34633/22636",
    "sg:postcode":"06242",
    "sg:province":"Sachsen-Anhalt",
    "wof:name":"A. Kerger",
    "wof:placetype":"venue"
},
  "geometry": {"coordinates":[11.9042053223,51.2609443665],"type":"Point"}
}