{
  "type": "Feature",
  "properties": {
    "iso:country":"DE",
    "sg:address":"Talstr. 101",
    "sg:city":"D\u00fcsseldorf",
    "sg:phone":"+49 211/6005690",
    "sg:postcode":"40217",
    "sg:province":"Nordrhein-Westfalen",
    "wof:name":"Paul Knode",
    "wof:placetype":"venue"
},
  "geometry": {"coordinates":[6.7783880234,51.21118927],"type":"Point"}
}