{
  "type": "Feature",
  "properties": {
    "iso:country":"DE",
    "sg:address":"Lindenstr. 15",
    "sg:city":"M\u00fcnchberg",
    "sg:phone":"+49 9251/1381",
    "sg:postcode":"95213",
    "sg:province":"Bayern",
    "wof:name":"Hans Suttner",
    "wof:placetype":"venue"
},
  "geometry": {"coordinates":[11.790625,50.190376],"type":"Point"}
}