{
  "type": "Feature",
  "properties": {
    "iso:country":"DE",
    "sg:address":"Br\u00fcckenstr. 2",
    "sg:city":"Rodgau",
    "sg:phone":"+49 6106/5098",
    "sg:postcode":"63110",
    "sg:province":"Hessen",
    "wof:name":"Polytrans Vertriebs- Und Transport Gmbh",
    "wof:placetype":"venue"
},
  "geometry": {"coordinates":[8.8868627548,50.0209350586],"type":"Point"}
}