{
  "type": "Feature",
  "properties": {
    "iso:country":"DE",
    "sg:address":"Hochstr. 164",
    "sg:city":"Heinsberg",
    "sg:phone":"+49 2452/3930",
    "sg:postcode":"52525",
    "sg:province":"Nordrhein-Westfalen",
    "wof:name":"Grillmaster",
    "wof:placetype":"venue"
},
  "geometry": {"coordinates":[6.0976052284,51.0658569336],"type":"Point"}
}