{
  "type": "Feature",
  "properties": {
    "iso:country":"DE",
    "sg:address":"Eduard-Lucas-Str. 18",
    "sg:city":"Essen",
    "sg:phone":"+49 201/411384",
    "sg:postcode":"45131",
    "sg:province":"Nordrhein-Westfalen",
    "wof:name":"Messehotel Flair",
    "wof:placetype":"venue"
},
  "geometry": {"coordinates":[6.9986357689,51.4284324646],"type":"Point"}
}