{
  "type": "Feature",
  "properties": {
    "iso:country":"DE",
    "sg:address":"Kr\u00f6nerweg 37",
    "sg:city":"D\u00fcsseldorf",
    "sg:phone":"+49 211/4220387",
    "sg:postcode":"40468",
    "sg:province":"Nordrhein-Westfalen",
    "wof:name":"Schl\u00fcter Automaten",
    "wof:placetype":"venue"
},
  "geometry": {"coordinates":[6.7663087845,51.2661323547],"type":"Point"}
}