{
  "type": "Feature",
  "properties": {
    "iso:country":"DE",
    "sg:address":"Gailhofer Str. 16",
    "sg:city":"Wedemark",
    "sg:phone":"+49 5130/2958",
    "sg:postcode":"30900",
    "sg:province":"Niedersachsen",
    "wof:name":"G. Freund Elektromeister",
    "wof:placetype":"venue"
},
  "geometry": {"coordinates":[9.760078,52.563431],"type":"Point"}
}