{
  "type": "Feature",
  "properties": {
    "iso:country":"DE",
    "sg:address":"Konviktstr. 47",
    "sg:city":"Freiburg",
    "sg:phone":"+49 4976/1557820",
    "sg:postcode":"79098",
    "sg:province":"Baden-W\u00fcrttemberg",
    "wof:name":"Sabcasa",
    "wof:placetype":"venue"
},
  "geometry": {"coordinates":[7.8546161652,47.9933700562],"type":"Point"}
}