{
  "type": "Feature",
  "properties": {
    "iso:country":"DE",
    "sg:address":"Schottengasse 3",
    "sg:city":"N\u00fcrnberg",
    "sg:phone":"+49 911/226395",
    "sg:postcode":"90402",
    "sg:province":"Bayern",
    "wof:name":"Japan-restaurant Ishilhara",
    "wof:placetype":"venue"
},
  "geometry": {"coordinates":[11.070561409,49.4482460022],"type":"Point"}
}