{
  "type": "Feature",
  "properties": {
    "iso:country":"DE",
    "sg:address":"Mannheimer Str. 24-28",
    "sg:city":"Bad Kreuznach",
    "sg:phone":"+49 671/42445",
    "sg:postcode":"55545",
    "sg:province":"Rheinland-Pfalz",
    "wof:name":"Ad-opticum A. G\u00f6ckel Augenoptik Gmbh",
    "wof:placetype":"venue"
},
  "geometry": {"coordinates":[7.855418,49.846809],"type":"Point"}
}