{
  "type": "Feature",
  "properties": {
    "iso:country":"DE",
    "sg:address":"Hauptstr. 104",
    "sg:city":"Leverkusen",
    "sg:phone":"+49 214/46764",
    "sg:postcode":"51373",
    "sg:province":"Nordrhein-Westfalen",
    "wof:name":"Restaurant Arkade",
    "wof:placetype":"venue"
},
  "geometry": {"coordinates":[6.9787478447,51.0310554504],"type":"Point"}
}