{
  "type": "Feature",
  "properties": {
    "iso:country":"DE",
    "sg:address":"Hospitalstr. 9",
    "sg:city":"Hadamar",
    "sg:phone":"+49 6433/6313",
    "sg:postcode":"65589",
    "sg:province":"Hessen",
    "wof:name":"J\u00fcrgen Wagner",
    "wof:placetype":"venue"
},
  "geometry": {"coordinates":[8.0515165329,50.4470901489],"type":"Point"}
}