{
  "type": "Feature",
  "properties": {
    "iso:country":"DE",
    "sg:address":"Warschauer Str. 11a",
    "sg:city":"M\u00fcnchen",
    "sg:phone":"+49 89/1411549",
    "sg:postcode":"80992",
    "sg:province":"Bayern",
    "wof:name":"K.-p. Gantert Anlageberater",
    "wof:placetype":"venue"
},
  "geometry": {"coordinates":[11.504817009,48.174243927],"type":"Point"}
}