{
  "type": "Feature",
  "properties": {
    "iso:country":"DE",
    "sg:address":"Knobelsdorffstr. 47",
    "sg:city":"Berlin",
    "sg:phone":"+49 30/3227854",
    "sg:postcode":"14059",
    "sg:province":"Berlin",
    "wof:name":"Richard Storbeck",
    "wof:placetype":"venue"
},
  "geometry": {"coordinates":[13.289538,52.513],"type":"Point"}
}