{
  "type": "Feature",
  "properties": {
    "iso:country":"DE",
    "sg:address":"Niedere K\u00f6ditzgasse 16",
    "sg:city":"Saalfeld",
    "sg:phone":"+49 3671/510143",
    "sg:postcode":"07318",
    "sg:province":"Th\u00fcringen",
    "wof:name":"U. Herrmann",
    "wof:placetype":"venue"
},
  "geometry": {"coordinates":[11.3641252518,50.647064209],"type":"Point"}
}