{
  "type": "Feature",
  "properties": {
    "iso:country":"DE",
    "sg:address":"Alter Neust\u00e4dter Weg 34",
    "sg:city":"Waiblingen",
    "sg:phone":"+49 7151/54338",
    "sg:postcode":"71334",
    "sg:province":"Baden-W\u00fcrttemberg",
    "wof:name":"\u00d6tinger Salzvertriebs Gmbh",
    "wof:placetype":"venue"
},
  "geometry": {"coordinates":[9.3180446625,48.8352546692],"type":"Point"}
}