{
  "type": "Feature",
  "properties": {
    "iso:country":"DE",
    "sg:address":"Ramsdorf 1",
    "sg:city":"Wallerfing",
    "sg:phone":"+49 9936/287",
    "sg:postcode":"94574",
    "sg:province":"Bayern",
    "wof:name":"Kath. Pfarramt St. Johannes D. T.",
    "wof:placetype":"venue"
},
  "geometry": {"coordinates":[12.8965177536,48.683631897],"type":"Point"}
}