{
  "type": "Feature",
  "properties": {
    "iso:country":"DE",
    "sg:address":"Hans-Albers-Platz 8",
    "sg:city":"Hamburg",
    "sg:phone":"+49 40/311369",
    "sg:postcode":"20359",
    "sg:province":"Hamburg",
    "wof:name":"Bdk Gastst\u00e4tten Gmbh",
    "wof:placetype":"venue"
},
  "geometry": {"coordinates":[9.9609708786,53.5489196777],"type":"Point"}
}