{
  "type": "Feature",
  "properties": {
    "iso:country":"DE",
    "sg:address":"Neust\u00e4dter Passage 14",
    "sg:city":"Halle",
    "sg:phone":"+49 345/6902612",
    "sg:postcode":"06122",
    "sg:province":"Sachsen-Anhalt",
    "wof:name":"Dittrich Linzmann Saal & Partner",
    "wof:placetype":"venue"
},
  "geometry": {"coordinates":[11.9223031998,51.48072052],"type":"Point"}
}