{
  "type": "Feature",
  "properties": {
    "iso:country":"DE",
    "sg:address":"Hafenstr. 7",
    "sg:city":"Gelsenkirchen",
    "sg:phone":"+49 209/940880",
    "sg:postcode":"45881",
    "sg:province":"Nordrhein-Westfalen",
    "wof:name":"Schmitt Stahlbau Gmbh",
    "wof:placetype":"venue"
},
  "geometry": {"coordinates":[7.071337,51.527794],"type":"Point"}
}