{
  "type": "Feature",
  "properties": {
    "iso:country":"DE",
    "sg:address":"Annaberger Str. 258b",
    "sg:city":"Crottendorf",
    "sg:phone":"+49 4937/3448207",
    "sg:postcode":"09474",
    "sg:province":"Sachsen",
    "wof:name":"Crottendorfer Bauschlosserei Gmbh",
    "wof:placetype":"venue"
},
  "geometry": {"coordinates":[12.9361286163,50.5076713562],"type":"Point"}
}