{
  "type": "Feature",
  "properties": {
    "iso:country":"DE",
    "sg:address":"Mei\u00dfner Landstrasse 4",
    "sg:city":"Dresden",
    "sg:phone":"+49 351",
    "sg:postcode":"01157",
    "sg:province":"Sachsen",
    "wof:name":"Technik Des Theater Junge Generation Dresden",
    "wof:placetype":"venue"
},
  "geometry": {"coordinates":[13.679347,51.062988],"type":"Point"}
}