{
  "type": "Feature",
  "properties": {
    "iso:country":"DE",
    "sg:address":"Hansastr. 87 c",
    "sg:city":"Unna",
    "sg:phone":"+49 2303/238950",
    "sg:postcode":"59425",
    "sg:province":"Nordrhein-Westfalen",
    "wof:name":"Asa Bau- Und Industriebedarfshandel",
    "wof:placetype":"venue"
},
  "geometry": {"coordinates":[7.671943,51.541531],"type":"Point"}
}