{
  "type": "Feature",
  "properties": {
    "iso:country":"DE",
    "sg:address":"Adenauerstr. 69",
    "sg:city":"Altenbeken",
    "sg:phone":"+49 5255/6169",
    "sg:postcode":"33184",
    "sg:province":"Nordrhein-Westfalen",
    "wof:name":"H\u00f6wing",
    "wof:placetype":"venue"
},
  "geometry": {"coordinates":[8.9429979324,51.7637939453],"type":"Point"}
}