{
  "type": "Feature",
  "properties": {
    "iso:country":"DE",
    "sg:address":"Im Beekefeld 9",
    "sg:city":"Neustadt",
    "sg:phone":"+49 5034/4506",
    "sg:postcode":"31535",
    "sg:province":"Niedersachsen",
    "wof:name":"Ruwa Immobilienverwaltung Und -betreuung Gmbh",
    "wof:placetype":"venue"
},
  "geometry": {"coordinates":[9.430743,52.580959],"type":"Point"}
}