{
  "type": "Feature",
  "properties": {
    "iso:country":"DE",
    "sg:address":"J\u00e4gerweg 3",
    "sg:city":"Verden",
    "sg:phone":"+49 4231/73619",
    "sg:postcode":"27283",
    "sg:province":"Niedersachsen",
    "wof:name":"Harry Riske",
    "wof:placetype":"venue"
},
  "geometry": {"coordinates":[9.2273921967,52.9595947266],"type":"Point"}
}