{
  "type": "Feature",
  "properties": {
    "iso:country":"DE",
    "sg:address":"Unzlauer Str. 15",
    "sg:city":"Bielefeld",
    "sg:phone":"+49 4952/1964730",
    "sg:postcode":"33719",
    "sg:province":"Nordrhein-Westfalen",
    "wof:name":"Falter-fahrzeug-werke Gmbh & Co. Kg",
    "wof:placetype":"venue"
},
  "geometry": {"coordinates":[8.6187896729,52.0239715576],"type":"Point"}
}