{
  "type": "Feature",
  "properties": {
    "iso:country":"DE",
    "sg:address":"Ganghoferstr. 11",
    "sg:city":"Frankfurt",
    "sg:phone":"+49 69/562618",
    "sg:postcode":"60320",
    "sg:province":"Hessen",
    "wof:name":"Annette Herdt Massagepraxis",
    "wof:placetype":"venue"
},
  "geometry": {"coordinates":[8.666399,50.145367],"type":"Point"}
}