{
  "type": "Feature",
  "properties": {
    "iso:country":"DE",
    "sg:address":"Seydlitzstr. 36",
    "sg:city":"D\u00fcsseldorf",
    "sg:phone":"+49 211/484052",
    "sg:postcode":"40476",
    "sg:province":"Nordrhein-Westfalen",
    "wof:name":"Ingenieur-dienst Gmbh",
    "wof:placetype":"venue"
},
  "geometry": {"coordinates":[6.7801427841,51.2427444458],"type":"Point"}
}