{
  "type": "Feature",
  "properties": {
    "iso:country":"DE",
    "sg:address":"Alt Seulberg 40",
    "sg:city":"Friedrichsdorf",
    "sg:phone":"+49 6172/778621",
    "sg:postcode":"61381",
    "sg:province":"Hessen",
    "wof:name":"Reiner Und Thomas Schwickart",
    "wof:placetype":"venue"
},
  "geometry": {"coordinates":[8.6502990723,50.2458076477],"type":"Point"}
}