{
  "type": "Feature",
  "properties": {
    "iso:country":"DE",
    "sg:address":"H\u00f6cherbergstr. 153 b",
    "sg:city":"Bexbach",
    "sg:phone":"+49 6826/80922",
    "sg:postcode":"66450",
    "sg:province":"Saarland",
    "wof:name":"Gpl - G\u00f6lz Gitterboxen - Und Paletten - Handelsges. Mbh",
    "wof:placetype":"venue"
},
  "geometry": {"coordinates":[7.266058,49.372921],"type":"Point"}
}