{
  "type": "Feature",
  "properties": {
    "iso:country":"DE",
    "sg:address":"Taunusstr. 2",
    "sg:city":"K\u00f6ln",
    "sg:phone":"+49 221/831256",
    "sg:postcode":"51105",
    "sg:province":"Nordrhein-Westfalen",
    "wof:name":"Taunusbad",
    "wof:placetype":"venue"
},
  "geometry": {"coordinates":[6.997349,50.934937],"type":"Point"}
}