{
  "type": "Feature",
  "properties": {
    "iso:country":"DE",
    "sg:address":"Gro\u00dfer Hillen 10",
    "sg:city":"Hannover",
    "sg:phone":"+49 511/528787",
    "sg:postcode":"30559",
    "sg:province":"Niedersachsen",
    "wof:name":"Hermann Hunger Rechtsanw\u00e4lte",
    "wof:placetype":"venue"
},
  "geometry": {"coordinates":[9.8256587982,52.3609580994],"type":"Point"}
}