{
  "type": "Feature",
  "properties": {
    "iso:country":"DE",
    "sg:address":"Abteistr. 6",
    "sg:city":"Bendorf",
    "sg:phone":"+49 2622/2669",
    "sg:postcode":"56170",
    "sg:province":"Rheinland-Pfalz",
    "wof:name":"E.j. Meuer",
    "wof:placetype":"venue"
},
  "geometry": {"coordinates":[7.5773,50.43811],"type":"Point"}
}