{
  "type": "Feature",
  "properties": {
    "iso:country":"DE",
    "sg:address":"Ohmweg 11-15",
    "sg:city":"Mannheim",
    "sg:phone":"+49 621/81011",
    "sg:postcode":"68199",
    "sg:province":"Baden-W\u00fcrttemberg",
    "wof:name":"Thales Broadcast & Multimedia Gmbh",
    "wof:placetype":"venue"
},
  "geometry": {"coordinates":[8.491835,49.462528],"type":"Point"}
}