{
  "type": "Feature",
  "properties": {
    "iso:country":"DE",
    "sg:address":"Bergheimer Str. 17",
    "sg:city":"Z\u00fclpich",
    "sg:phone":"+49 2252/4492",
    "sg:postcode":"53909",
    "sg:province":"Nordrhein-Westfalen",
    "wof:name":"Helmut Glasmacher",
    "wof:placetype":"venue"
},
  "geometry": {"coordinates":[6.658079,50.702038],"type":"Point"}
}