{
  "type": "Feature",
  "properties": {
    "iso:country":"DE",
    "sg:address":"Schlo\u00dfstr. 23",
    "sg:city":"M\u00fchlhausen-Ehingen",
    "sg:phone":"+49 7733/2324",
    "sg:postcode":"78259",
    "sg:province":"Baden-W\u00fcrttemberg",
    "wof:name":"Barbara Seifert",
    "wof:placetype":"venue"
},
  "geometry": {"coordinates":[8.8114833832,47.8097305298],"type":"Point"}
}