{
  "type": "Feature",
  "properties": {
    "iso:country":"DE",
    "sg:address":"Gotthold-Roth-Str. 1",
    "sg:city":"Greiz",
    "sg:phone":"+49 3661/69931",
    "sg:postcode":"07973",
    "sg:province":"Th\u00fcringen",
    "wof:name":"P. M. Veranstaltungsagentur",
    "wof:placetype":"venue"
},
  "geometry": {"coordinates":[12.19608,50.651432],"type":"Point"}
}