{
  "type": "Feature",
  "properties": {
    "iso:country":"DE",
    "sg:address":"Am Studentenw\u00e4ldle 4",
    "sg:city":"Schw\u00e4bisch Gm\u00fcnd",
    "sg:postcode":"73525",
    "sg:province":"Baden-W\u00fcrttemberg",
    "wof:name":"Stauden Ring Gmbh",
    "wof:placetype":"venue"
},
  "geometry": {"coordinates":[9.779019,48.788715],"type":"Point"}
}