{
  "type": "Feature",
  "properties": {
    "iso:country":"DE",
    "sg:address":"Dieskaustr. 36",
    "sg:city":"Leipzig",
    "sg:phone":"+49 341/4246998",
    "sg:postcode":"04229",
    "sg:province":"Sachsen",
    "wof:name":"Glaserei Mock & Partner Gmbh",
    "wof:placetype":"venue"
},
  "geometry": {"coordinates":[12.326805,51.31699],"type":"Point"}
}