{
  "type": "Feature",
  "properties": {
    "iso:country":"DE",
    "sg:address":"Dronkestr. 34",
    "sg:city":"Schleiden",
    "sg:phone":"+49 2445/1310",
    "sg:postcode":"53937",
    "sg:province":"Nordrhein-Westfalen",
    "wof:name":"Heidemarie Walber Krankengymnastin",
    "wof:placetype":"venue"
},
  "geometry": {"coordinates":[6.465599,50.521751],"type":"Point"}
}