{
  "type": "Feature",
  "properties": {
    "iso:country":"DE",
    "sg:address":"Alt\u00f6ttinger Str. 3",
    "sg:city":"Landsberg",
    "sg:phone":"+49 8191/47046",
    "sg:postcode":"86899",
    "sg:province":"Bayern",
    "wof:name":"Vertrauens\u00e4rztlicher-dienst Der Lva Oberbayern",
    "wof:placetype":"venue"
},
  "geometry": {"coordinates":[10.8755207062,48.0559883118],"type":"Point"}
}