{
  "type": "Feature",
  "properties": {
    "iso:country":"DE",
    "sg:address":"Hildesheimer Str. 7",
    "sg:city":"Wilhelmshaven",
    "sg:phone":"+49 4421/93780",
    "sg:postcode":"26384",
    "sg:province":"Niedersachsen",
    "wof:name":"Sibobeton Gmbh & Co. Kg",
    "wof:placetype":"venue"
},
  "geometry": {"coordinates":[8.146355629,53.5258216858],"type":"Point"}
}