{
  "type": "Feature",
  "properties": {
    "iso:country":"DE",
    "sg:address":"Am Mittleren Moos 18",
    "sg:city":"Augsburg",
    "sg:phone":"+49 821/703019",
    "sg:postcode":"86167",
    "sg:province":"Bayern",
    "wof:name":"Kastenhofer Funktechnik Gmbh",
    "wof:placetype":"venue"
},
  "geometry": {"coordinates":[10.9363660812,48.3933334351],"type":"Point"}
}