{
  "type": "Feature",
  "properties": {
    "iso:country":"DE",
    "sg:address":"Platzgasse 10",
    "sg:city":"Laichingen",
    "sg:phone":"+49 7333/5343",
    "sg:postcode":"89150",
    "sg:province":"Baden-W\u00fcrttemberg",
    "wof:name":"Wilhelm Hirning",
    "wof:placetype":"venue"
},
  "geometry": {"coordinates":[9.6851758957,48.4898796082],"type":"Point"}
}