{
  "type": "Feature",
  "properties": {
    "iso:country":"DE",
    "sg:address":"Freiberger Str.",
    "sg:city":"Olbernhau",
    "sg:phone":"+49 37360/72183",
    "sg:postcode":"09526",
    "sg:province":"Sachsen",
    "wof:name":"Haltestelle Konsum",
    "wof:placetype":"venue"
},
  "geometry": {"coordinates":[13.3364772797,50.6622085571],"type":"Point"}
}