{
  "type": "Feature",
  "properties": {
    "iso:country":"DE",
    "sg:address":"Gneisenaustr. 11",
    "sg:city":"S\u00fc\u00dfen",
    "sg:phone":"+49 7162/42400",
    "sg:postcode":"73079",
    "sg:province":"Baden-W\u00fcrttemberg",
    "wof:name":"Siegbert Kleske",
    "wof:placetype":"venue"
},
  "geometry": {"coordinates":[9.7514667511,48.6737747192],"type":"Point"}
}