{
  "type": "Feature",
  "properties": {
    "iso:country":"DE",
    "sg:address":"Gewerbestr. 9",
    "sg:city":"Liebsch\u00fctzberg",
    "sg:phone":"+49 3435/620215",
    "sg:postcode":"04758",
    "sg:province":"Sachsen",
    "wof:name":"G. Schmidt",
    "wof:placetype":"venue"
},
  "geometry": {"coordinates":[13.114906311,51.3242759705],"type":"Point"}
}