{
  "type": "Feature",
  "properties": {
    "iso:country":"DE",
    "sg:address":"Bi de S\u00fcd 22",
    "sg:city":"Nieblum",
    "sg:phone":"+49 4681/2572",
    "sg:postcode":"25938",
    "sg:province":"Schleswig-Holstein",
    "wof:name":"Altes Landhaus",
    "wof:placetype":"venue"
},
  "geometry": {"coordinates":[8.49127388,54.6911621094],"type":"Point"}
}