{
  "type": "Feature",
  "properties": {
    "iso:country":"DE",
    "sg:address":"Limburgstr. 7",
    "sg:city":"Weisenheim am Sand",
    "sg:phone":"+49 6353/7417",
    "sg:postcode":"67256",
    "sg:province":"Rheinland-Pfalz",
    "wof:name":"Klaus Wiegand",
    "wof:placetype":"venue"
},
  "geometry": {"coordinates":[8.2408075333,49.5169448853],"type":"Point"}
}