{
  "type": "Feature",
  "properties": {
    "iso:country":"DE",
    "sg:address":"Memelstr. 13",
    "sg:city":"Rodalben",
    "sg:phone":"+49 6331",
    "sg:postcode":"66978",
    "sg:province":"Rheinland-Pfalz",
    "wof:name":"Rodalber Kurier-dienst",
    "wof:placetype":"venue"
},
  "geometry": {"coordinates":[7.653211,49.237675],"type":"Point"}
}