{
  "type": "Feature",
  "properties": {
    "iso:country":"DE",
    "sg:address":"Hauptstr. 32 a",
    "sg:city":"Bilkheim",
    "sg:phone":"+49 6435/6353",
    "sg:postcode":"56414",
    "sg:province":"Rheinland-Pfalz",
    "wof:name":"K.-p. Henrich",
    "wof:placetype":"venue"
},
  "geometry": {"coordinates":[7.9465432167,50.4976768494],"type":"Point"}
}