{
  "type": "Feature",
  "properties": {
    "iso:country":"DE",
    "sg:address":"Claus-von-der-Decken-Str. 22",
    "sg:city":"Achim",
    "sg:phone":"+49 4202/2185",
    "sg:postcode":"28832",
    "sg:province":"Niedersachsen",
    "wof:name":"Claus Von Der Decken",
    "wof:placetype":"venue"
},
  "geometry": {"coordinates":[9.053801,53.025036],"type":"Point"}
}