{
  "type": "Feature",
  "properties": {
    "iso:country":"DE",
    "sg:address":"B\u00fctlinger Str. 48",
    "sg:city":"Tespe",
    "sg:phone":"+49 4133/8442",
    "sg:postcode":"21395",
    "sg:province":"Niedersachsen",
    "wof:name":"Gastst\u00e4tte Dat Ole Amtshus",
    "wof:placetype":"venue"
},
  "geometry": {"coordinates":[10.4134225845,53.3633041382],"type":"Point"}
}