{
  "type": "Feature",
  "properties": {
    "iso:country":"DE",
    "sg:address":"Markt 6",
    "sg:city":"Dresden",
    "sg:phone":"+49 351/2679531",
    "sg:postcode":"01328",
    "sg:province":"Sachsen",
    "wof:name":"F. Gebel",
    "wof:placetype":"venue"
},
  "geometry": {"coordinates":[13.8951787949,51.0333595276],"type":"Point"}
}