{
  "type": "Feature",
  "properties": {
    "iso:country":"DE",
    "sg:address":"Roter Lohweg 32",
    "sg:city":"Butzbach",
    "sg:phone":"+49 6033/6191",
    "sg:postcode":"35510",
    "sg:province":"Hessen",
    "wof:name":"Fepilan Kunststoff Gmbh",
    "wof:placetype":"venue"
},
  "geometry": {"coordinates":[8.690236,50.435928],"type":"Point"}
}