{
  "type": "Feature",
  "properties": {
    "iso:country":"DE",
    "sg:address":"Ansgarstr. 8",
    "sg:city":"Paderborn",
    "sg:phone":"+49 5251/75859",
    "sg:postcode":"33098",
    "sg:province":"Nordrhein-Westfalen",
    "wof:name":"R. Bunse",
    "wof:placetype":"venue"
},
  "geometry": {"coordinates":[8.7472372055,51.7064361572],"type":"Point"}
}