{
  "type": "Feature",
  "properties": {
    "iso:country":"DE",
    "sg:address":"Kunibertskloster 1",
    "sg:city":"K\u00f6ln",
    "sg:phone":"+49 221/122740",
    "sg:postcode":"50668",
    "sg:province":"Nordrhein-Westfalen",
    "wof:name":"Jakob P\u00fctz",
    "wof:placetype":"venue"
},
  "geometry": {"coordinates":[6.9632720947,50.9470901489],"type":"Point"}
}