{
  "type": "Feature",
  "properties": {
    "iso:country":"DE",
    "sg:address":"Am Kohlenberg 8",
    "sg:city":"Nordstemmen",
    "sg:phone":"+49 5069/96111",
    "sg:postcode":"31171",
    "sg:province":"Niedersachsen",
    "wof:name":"Vereinte Versicherungen T. Wehmeyer",
    "wof:placetype":"venue"
},
  "geometry": {"coordinates":[9.8468255997,52.1500473022],"type":"Point"}
}