{
  "type": "Feature",
  "properties": {
    "iso:country":"DE",
    "sg:address":"Hohler Weg 2",
    "sg:city":"Attendorn",
    "sg:phone":"+49 2722/3064",
    "sg:postcode":"57439",
    "sg:province":"Nordrhein-Westfalen",
    "wof:name":"Praxis Dr. Med. Rustemeyer",
    "wof:placetype":"venue"
},
  "geometry": {"coordinates":[7.8994817734,51.1267433167],"type":"Point"}
}