{
  "type": "Feature",
  "properties": {
    "iso:country":"DE",
    "sg:address":"Sommerauer Str.",
    "sg:city":"Lohberg",
    "sg:phone":"+49 9943/1200",
    "sg:postcode":"93470",
    "sg:province":"Bayern",
    "wof:name":"Pension Mathilde Liebl",
    "wof:placetype":"venue"
},
  "geometry": {"coordinates":[13.1003160477,49.1636962891],"type":"Point"}
}