{
  "type": "Feature",
  "properties": {
    "iso:country":"DE",
    "sg:address":"Von-Ketteler-Str. 36",
    "sg:city":"Leverkusen",
    "sg:phone":"+49 214/65198",
    "sg:postcode":"51371",
    "sg:province":"Nordrhein-Westfalen",
    "wof:name":"Burkhard Dambeck",
    "wof:placetype":"venue"
},
  "geometry": {"coordinates":[6.984529,51.046825],"type":"Point"}
}