{
  "type": "Feature",
  "properties": {
    "iso:country":"DE",
    "sg:address":"Schulstr. 14",
    "sg:city":"Bischberg",
    "sg:postcode":"96120",
    "sg:province":"Bayern",
    "wof:name":"Kath. \u00f6ffentliche B\u00fccherei",
    "wof:placetype":"venue"
},
  "geometry": {"coordinates":[10.828648,49.910824],"type":"Point"}
}