{
  "type": "Feature",
  "properties": {
    "iso:country":"DE",
    "sg:address":"Bockenheimer Landstr. 73-77",
    "sg:city":"Frankfurt",
    "sg:phone":"+49 69/1590",
    "sg:postcode":"60325",
    "sg:province":"Hessen",
    "wof:name":"Gervinusstra\u00dfe Beteiligungs Gmbh",
    "wof:placetype":"venue"
},
  "geometry": {"coordinates":[8.6614122391,50.1184577942],"type":"Point"}
}