{
  "type": "Feature",
  "properties": {
    "iso:country":"DE",
    "sg:address":"Greuel 9",
    "sg:city":"Solingen",
    "sg:phone":"+49 212/2641423",
    "sg:postcode":"42699",
    "sg:province":"Nordrhein-Westfalen",
    "wof:name":"Bernhard Albat",
    "wof:placetype":"venue"
},
  "geometry": {"coordinates":[7.026986,51.154778],"type":"Point"}
}