{
  "type": "Feature",
  "properties": {
    "iso:country":"DE",
    "sg:address":"August-Bebel-Str. 3",
    "sg:city":"Sellin",
    "sg:postcode":"18586",
    "sg:province":"Mecklenburg-Vorpommern",
    "wof:name":"Gerhart-hauptmann-theater",
    "wof:placetype":"venue"
},
  "geometry": {"coordinates":[13.692674,54.377911],"type":"Point"}
}