{
  "type": "Feature",
  "properties": {
    "iso:country":"DE",
    "sg:address":"Wamslerstra\u00dfe 2",
    "sg:city":"Muenchen",
    "sg:phone":"+49 89/4271913",
    "sg:postcode":"81829",
    "sg:province":"Bayern",
    "wof:name":"Meierhofer Ag",
    "wof:placetype":"venue"
},
  "geometry": {"coordinates":[11.66072,48.135456],"type":"Point"}
}