{
  "type": "Feature",
  "properties": {
    "iso:country":"DE",
    "sg:address":"Georg-Metz-Str. 10 a",
    "sg:city":"Frankenthal",
    "sg:phone":"+49 6233/21353",
    "sg:postcode":"67227",
    "sg:province":"Rheinland-Pfalz",
    "wof:name":"Ernst Lutz",
    "wof:placetype":"venue"
},
  "geometry": {"coordinates":[8.34516716,49.5412368774],"type":"Point"}
}