{
  "type": "Feature",
  "properties": {
    "iso:country":"DE",
    "sg:address":"Ankergasse 5",
    "sg:city":"Frankfurt",
    "sg:phone":"+49 69/418328",
    "sg:postcode":"60386",
    "sg:province":"Hessen",
    "wof:name":"Vinothek Italia",
    "wof:placetype":"venue"
},
  "geometry": {"coordinates":[8.7715597153,50.1225662231],"type":"Point"}
}