{
  "type": "Feature",
  "properties": {
    "iso:country":"DE",
    "sg:address":"Johann-G.-Gutenberg-Str. 20",
    "sg:city":"Olching",
    "sg:phone":"+49 8145/5021",
    "sg:postcode":"82140",
    "sg:province":"Bayern",
    "wof:name":"Fischer & Fey Ingenieurgesellschaft Mbh",
    "wof:placetype":"venue"
},
  "geometry": {"coordinates":[11.3277196884,48.1987037659],"type":"Point"}
}