{
  "type": "Feature",
  "properties": {
    "iso:country":"DE",
    "sg:address":"Lessingstr. 2",
    "sg:city":"Ostseebad Rerik",
    "sg:phone":"+49 38296/78359",
    "sg:postcode":"18230",
    "sg:province":"Mecklenburg-Vorpommern",
    "wof:name":"Brita Ro\u00dfmann",
    "wof:placetype":"venue"
},
  "geometry": {"coordinates":[11.6265,54.111889],"type":"Point"}
}