{
  "type": "Feature",
  "properties": {
    "iso:country":"DE",
    "sg:address":"Wilhelmshaven",
    "sg:city":"Wilhelmshaven",
    "sg:phone":"+49 1805",
    "sg:postcode":"26388",
    "sg:province":"Niedersachsen",
    "wof:name":"Tarif-tipp.de - Sms In Alle Netze!",
    "wof:placetype":"venue"
},
  "geometry": {"coordinates":[8.07473,53.588139],"type":"Point"}
}