{
  "type": "Feature",
  "properties": {
    "iso:country":"DE",
    "sg:address":"Thuner Weg 68",
    "sg:city":"Paderborn",
    "sg:phone":"+49 5254/12444",
    "sg:postcode":"33104",
    "sg:province":"Nordrhein-Westfalen",
    "wof:name":"Claims Spielhallen Gmbh",
    "wof:placetype":"venue"
},
  "geometry": {"coordinates":[8.7361183167,51.7695541382],"type":"Point"}
}