{
  "type": "Feature",
  "properties": {
    "iso:country":"DE",
    "sg:address":"Hauptstr. 63",
    "sg:city":"Billigheim",
    "sg:phone":"+49 6265/252",
    "sg:postcode":"74842",
    "sg:province":"Baden-W\u00fcrttemberg",
    "wof:name":"Lamm",
    "wof:placetype":"venue"
},
  "geometry": {"coordinates":[9.2214889526,49.350151062],"type":"Point"}
}