{
  "type": "Feature",
  "properties": {
    "iso:country":"DE",
    "sg:address":"Karlstr. 52",
    "sg:city":"Wuppertal",
    "sg:phone":"+49 202/454348",
    "sg:postcode":"42105",
    "sg:province":"Nordrhein-Westfalen",
    "wof:name":"Klaus Werner",
    "wof:placetype":"venue"
},
  "geometry": {"coordinates":[7.1434469223,51.261013031],"type":"Point"}
}