{
  "type": "Feature",
  "properties": {
    "iso:country":"DE",
    "sg:address":"T\u00f6pferstr. 3",
    "sg:city":"Cadenberge",
    "sg:phone":"+49 4777/1001",
    "sg:postcode":"21781",
    "sg:province":"Niedersachsen",
    "wof:name":"Hartmann Baumaschinen Gmbh & Co. Kg",
    "wof:placetype":"venue"
},
  "geometry": {"coordinates":[9.055229,53.774284],"type":"Point"}
}