{
  "type": "Feature",
  "properties": {
    "iso:country":"DE",
    "sg:address":"Lindenstr. 12",
    "sg:city":"Windesheim",
    "sg:phone":"+49 6707/1042",
    "sg:postcode":"55452",
    "sg:province":"Rheinland-Pfalz",
    "wof:name":"Helmut Und Hans-j. Theobald",
    "wof:placetype":"venue"
},
  "geometry": {"coordinates":[7.8189721107,49.9030723572],"type":"Point"}
}