{
  "type": "Feature",
  "properties": {
    "iso:country":"DE",
    "sg:address":"Fichtenweg 41",
    "sg:city":"Unna",
    "sg:phone":"+49 2303/89781",
    "sg:postcode":"59423",
    "sg:province":"Nordrhein-Westfalen",
    "wof:name":"Ludwig Holm",
    "wof:placetype":"venue"
},
  "geometry": {"coordinates":[7.6687178612,51.5258903503],"type":"Point"}
}