{
  "type": "Feature",
  "properties": {
    "iso:country":"DE",
    "sg:address":"Hindenburgstr. 35",
    "sg:city":"Hannover",
    "sg:phone":"+49 511/85000",
    "sg:postcode":"30175",
    "sg:province":"Niedersachsen",
    "wof:name":"Allg. Deutsch. Automobil-club Adac Niedersachsen E.v.",
    "wof:placetype":"venue"
},
  "geometry": {"coordinates":[9.7620220184,52.3797721863],"type":"Point"}
}