{
  "type": "Feature",
  "properties": {
    "iso:country":"DE",
    "sg:address":"Dessauerstrasse 94",
    "sg:city":"Dessau",
    "sg:phone":"+49 340/2161302",
    "sg:postcode":"06844",
    "sg:province":"Sachsen-Anhalt",
    "wof:name":"Vertrieb Blue Vision",
    "wof:placetype":"venue"
},
  "geometry": {"coordinates":[12.25712,51.839779],"type":"Point"}
}