{
  "type": "Feature",
  "properties": {
    "iso:country":"DE",
    "sg:address":"Am Weiher 1",
    "sg:city":"Schauren",
    "sg:phone":"+49 6786/1787",
    "sg:postcode":"55758",
    "sg:province":"Rheinland-Pfalz",
    "wof:name":"Heinz Rodenkirch",
    "wof:placetype":"venue"
},
  "geometry": {"coordinates":[7.238173008,49.8059310913],"type":"Point"}
}