{
  "type": "Feature",
  "properties": {
    "iso:country":"DE",
    "sg:address":"Mainzer Str. 13",
    "sg:city":"M\u00fcnchen",
    "sg:phone":"+49 89/3609050",
    "sg:postcode":"80804",
    "sg:province":"Bayern",
    "wof:name":"Schuster Und Pechtold Architekten Gmbh",
    "wof:placetype":"venue"
},
  "geometry": {"coordinates":[11.5808229446,48.1686134338],"type":"Point"}
}