{
  "type": "Feature",
  "properties": {
    "iso:country":"DE",
    "sg:address":"Thanheimer Str. 39",
    "sg:city":"Albstadt",
    "sg:phone":"+49 7432/25061",
    "sg:postcode":"72461",
    "sg:province":"Baden-W\u00fcrttemberg",
    "wof:name":"Hotel Adler Restaurant",
    "wof:placetype":"venue"
},
  "geometry": {"coordinates":[8.9976263046,48.284828186],"type":"Point"}
}