{
  "type": "Feature",
  "properties": {
    "iso:country":"DE",
    "sg:address":"Windhalmweg 15",
    "sg:city":"Berlin",
    "sg:postcode":"13403",
    "sg:province":"Berlin",
    "wof:name":"Interconnect Kommunikations- Systeme E. K.",
    "wof:placetype":"venue"
},
  "geometry": {"coordinates":[13.3201971054,52.5813865662],"type":"Point"}
}