{
  "type": "Feature",
  "properties": {
    "iso:country":"DE",
    "sg:address":"Robert-Blum-Str. 12",
    "sg:city":"Rudolstadt",
    "sg:phone":"+49 3672/351066",
    "sg:postcode":"07407",
    "sg:province":"Th\u00fcringen",
    "wof:name":"Allmont Gmbh",
    "wof:placetype":"venue"
},
  "geometry": {"coordinates":[11.309296,50.686069],"type":"Point"}
}