{
  "type": "Feature",
  "properties": {
    "iso:country":"DE",
    "sg:address":"Wannweiler Str. 74",
    "sg:city":"Kirchentellinsfurt",
    "sg:phone":"+49 7121/68666",
    "sg:postcode":"72138",
    "sg:province":"Baden-W\u00fcrttemberg",
    "wof:name":"Kern Reisen E. K. Inh. Ingrid Rilling",
    "wof:placetype":"venue"
},
  "geometry": {"coordinates":[9.1437597275,48.5249176025],"type":"Point"}
}