{
  "type": "Feature",
  "properties": {
    "iso:country":"DE",
    "sg:address":"Schulstr. 11",
    "sg:city":"Waldachtal",
    "sg:phone":"+49 7443/7486",
    "sg:postcode":"72178",
    "sg:province":"Baden-W\u00fcrttemberg",
    "wof:name":"Haus Des Gastes",
    "wof:placetype":"venue"
},
  "geometry": {"coordinates":[8.5638628006,48.4909057617],"type":"Point"}
}