{
  "type": "Feature",
  "properties": {
    "iso:country":"DE",
    "sg:address":"Robert-Koch-Str. 35",
    "sg:city":"Gr\u00fcnwald",
    "sg:phone":"+49 89/6493655",
    "sg:postcode":"82031",
    "sg:province":"Bayern",
    "wof:name":"Von Pauer Gmbh",
    "wof:placetype":"venue"
},
  "geometry": {"coordinates":[11.5436372757,48.0563316345],"type":"Point"}
}