{
  "type": "Feature",
  "properties": {
    "iso:country":"DE",
    "sg:address":"Marktstr. 39",
    "sg:city":"Burgdorf",
    "sg:phone":"+49 5136/2639",
    "sg:postcode":"31303",
    "sg:province":"Niedersachsen",
    "wof:name":"Klaus Virkus Augenoptiker",
    "wof:placetype":"venue"
},
  "geometry": {"coordinates":[10.0104818344,52.4472465515],"type":"Point"}
}