{
  "type": "Feature",
  "properties": {
    "iso:country":"DE",
    "sg:address":"Hofstr. 4",
    "sg:city":"Zeitlofs",
    "sg:postcode":"97799",
    "sg:province":"Bayern",
    "wof:name":"Forstverwaltung Rupboden Verwaltungs- Gmbh",
    "wof:placetype":"venue"
},
  "geometry": {"coordinates":[9.7110939026,50.2729530334],"type":"Point"}
}