{
  "type": "Feature",
  "properties": {
    "iso:country":"DE",
    "sg:address":"L\u00e4ngerach 4",
    "sg:city":"Sipplingen",
    "sg:phone":"+49 7551/92060",
    "sg:postcode":"78354",
    "sg:province":"Baden-W\u00fcrttemberg",
    "wof:name":"Dwl Elektronische Systeme Gmbh",
    "wof:placetype":"venue"
},
  "geometry": {"coordinates":[9.102474,47.798069],"type":"Point"}
}