{
  "type": "Feature",
  "properties": {
    "iso:country":"DE",
    "sg:address":"Glatzer Str. 9",
    "sg:city":"Homburg",
    "sg:phone":"+49 6841/72669",
    "sg:postcode":"66424",
    "sg:province":"Saarland",
    "wof:name":"Hans-joachim Gr\u00f6tschel Innenarchitekt",
    "wof:placetype":"venue"
},
  "geometry": {"coordinates":[7.319351,49.332634],"type":"Point"}
}