{
  "type": "Feature",
  "properties": {
    "iso:country":"DE",
    "sg:address":"Bernburger Str. 27",
    "sg:city":"Halle",
    "sg:phone":"+49 345/3880750",
    "sg:postcode":"06108",
    "sg:province":"Sachsen-Anhalt",
    "wof:name":"Simone L\u00f6sch",
    "wof:placetype":"venue"
},
  "geometry": {"coordinates":[11.966191,51.492722],"type":"Point"}
}