{
  "type": "Feature",
  "properties": {
    "iso:country":"DE",
    "sg:address":"Kaiserdamm 99",
    "sg:city":"Berlin",
    "sg:phone":"+49 30/3213024",
    "sg:postcode":"14057",
    "sg:province":"Berlin",
    "wof:name":"Kkt - Kraus Klimatechnik Gmbh",
    "wof:placetype":"venue"
},
  "geometry": {"coordinates":[13.287055,52.510132],"type":"Point"}
}