{
  "type": "Feature",
  "properties": {
    "iso:country":"DE",
    "sg:address":"Robert-Wahl-Str. 11",
    "sg:city":"Balingen",
    "sg:phone":"+49 7433/2545",
    "sg:postcode":"72336",
    "sg:province":"Baden-W\u00fcrttemberg",
    "wof:name":"Heinrich Fritz",
    "wof:placetype":"venue"
},
  "geometry": {"coordinates":[8.8555717468,48.2758407593],"type":"Point"}
}