{
  "type": "Feature",
  "properties": {
    "iso:country":"DE",
    "sg:address":"Poststr. 9",
    "sg:city":"Wittstock",
    "sg:phone":"+49 3394/441517",
    "sg:postcode":"16909",
    "sg:province":"Brandenburg",
    "wof:name":"G. Schmiedel",
    "wof:placetype":"venue"
},
  "geometry": {"coordinates":[12.483579,53.16275],"type":"Point"}
}