{
  "type": "Feature",
  "properties": {
    "iso:country":"DE",
    "sg:address":"Richard-R\u00f6sicke-Str. 14",
    "sg:city":"Bernburg",
    "sg:phone":"+49 3471/333523",
    "sg:postcode":"06406",
    "sg:province":"Sachsen-Anhalt",
    "wof:name":"Jan Reinhold",
    "wof:placetype":"venue"
},
  "geometry": {"coordinates":[11.7626771927,51.7866859436],"type":"Point"}
}