{
  "type": "Feature",
  "properties": {
    "iso:country":"DE",
    "sg:address":"Brauereistr. 12",
    "sg:city":"Sch\u00f6nwald",
    "sg:phone":"+49 9287/50277",
    "sg:postcode":"95173",
    "sg:province":"Bayern",
    "wof:name":"G. Hofmann",
    "wof:placetype":"venue"
},
  "geometry": {"coordinates":[12.0825157166,50.2006111145],"type":"Point"}
}