{
  "type": "Feature",
  "properties": {
    "iso:country":"DE",
    "sg:address":"Sch\u00f6ne Aussicht 1",
    "sg:city":"Wetzlar",
    "sg:phone":"+49 6441/22949",
    "sg:postcode":"35578",
    "sg:province":"Hessen",
    "wof:name":"Scholz Grundst\u00fccks- Entwicklungs- Und",
    "wof:placetype":"venue"
},
  "geometry": {"coordinates":[8.516957,50.550648],"type":"Point"}
}