{
  "type": "Feature",
  "properties": {
    "iso:country":"DE",
    "sg:address":"R\u00f6merstr 21::",
    "sg:city":"Lichtenstein",
    "sg:phone":"+49 7129/92980",
    "sg:postcode":"72805",
    "sg:province":"Baden-W\u00fcrttemberg",
    "wof:name":"Raiffeisenbank Holzelfingen-ohnastetten Eg",
    "wof:placetype":"venue"
},
  "geometry": {"coordinates":[9.276706,48.425358],"type":"Point"}
}