{
  "type": "Feature",
  "properties": {
    "iso:country":"DE",
    "sg:address":"Bachstr. 62",
    "sg:city":"Aachen",
    "sg:phone":"+49 241/503053",
    "sg:postcode":"52066",
    "sg:province":"Nordrhein-Westfalen",
    "wof:name":"Frehn Papier U. B\u00fcrobedarf Inh. Karsten Pelzer E. K.",
    "wof:placetype":"venue"
},
  "geometry": {"coordinates":[6.099224,50.768772],"type":"Point"}
}