{
  "type": "Feature",
  "properties": {
    "iso:country":"DE",
    "sg:address":"Salzb\u00f6destr. 3",
    "sg:city":"Bad Endbach",
    "sg:phone":"+49 2776/1080",
    "sg:postcode":"35080",
    "sg:province":"Hessen",
    "wof:name":"Johann Schmalz",
    "wof:placetype":"venue"
},
  "geometry": {"coordinates":[8.465905,50.756966],"type":"Point"}
}