{
  "type": "Feature",
  "properties": {
    "iso:country":"DE",
    "sg:address":"Schleusenweg 1",
    "sg:city":"Friedrichskoog",
    "sg:phone":"+49 4854/824",
    "sg:postcode":"25718",
    "sg:province":"Schleswig-Holstein",
    "wof:name":"G. Und K. Harders",
    "wof:placetype":"venue"
},
  "geometry": {"coordinates":[8.8805427551,54.0055541992],"type":"Point"}
}