{
  "type": "Feature",
  "properties": {
    "iso:country":"DE",
    "sg:address":"Kaiserstr. 123",
    "sg:city":"Friedberg",
    "sg:phone":"+49 6031/62597",
    "sg:postcode":"61169",
    "sg:province":"Hessen",
    "wof:name":"Suncos Gmbh",
    "wof:placetype":"venue"
},
  "geometry": {"coordinates":[8.757265,50.3367],"type":"Point"}
}