{
  "type": "Feature",
  "properties": {
    "iso:country":"DE",
    "sg:address":"Hamminkelner Landstr. 207",
    "sg:city":"Wesel",
    "sg:postcode":"46487",
    "sg:province":"Nordrhein-Westfalen",
    "wof:name":"Blumenkampgrill",
    "wof:placetype":"venue"
},
  "geometry": {"coordinates":[6.6068201065,51.6943016052],"type":"Point"}
}