{
  "type": "Feature",
  "properties": {
    "iso:country":"DE",
    "sg:address":"Kleinfeldele 1",
    "sg:city":"Auggen",
    "sg:phone":"+49 7631/36800",
    "sg:postcode":"79424",
    "sg:province":"Baden-W\u00fcrttemberg",
    "wof:name":"Winzergenossenschaft Auggen Eg",
    "wof:placetype":"venue"
},
  "geometry": {"coordinates":[7.5957942009,47.7954978943],"type":"Point"}
}