{
  "type": "Feature",
  "properties": {
    "iso:country":"DE",
    "sg:address":"Riestedter Ring 15",
    "sg:city":"Riestedt",
    "sg:phone":"+49 5804/986820",
    "sg:postcode":"29525",
    "sg:province":"Niedersachsen",
    "wof:name":"Wolski Haftetiketten",
    "wof:placetype":"venue"
},
  "geometry": {"coordinates":[10.6493883133,52.9975891113],"type":"Point"}
}