{
  "type": "Feature",
  "properties": {
    "iso:country":"DE",
    "sg:address":"Marktstr. 5",
    "sg:city":"Salzhemmendorf",
    "sg:phone":"+49 5153/5240",
    "sg:postcode":"31020",
    "sg:province":"Niedersachsen",
    "wof:name":"Justus Falke",
    "wof:placetype":"venue"
},
  "geometry": {"coordinates":[9.5893249512,52.065322876],"type":"Point"}
}