{
  "type": "Feature",
  "properties": {
    "iso:country":"DE",
    "sg:address":"Lipper Weg 70",
    "sg:city":"Marl",
    "sg:phone":"+49 2365/34077",
    "sg:postcode":"45770",
    "sg:province":"Nordrhein-Westfalen",
    "wof:name":"K. H. Stolten",
    "wof:placetype":"venue"
},
  "geometry": {"coordinates":[7.1182909012,51.666759491],"type":"Point"}
}