{
  "type": "Feature",
  "properties": {
    "iso:country":"DE",
    "sg:address":"Rothweg 2",
    "sg:city":"Markt Indersdorf",
    "sg:phone":"+49 8136/7326",
    "sg:postcode":"85229",
    "sg:province":"Bayern",
    "wof:name":"Johann Zotz",
    "wof:placetype":"venue"
},
  "geometry": {"coordinates":[11.3827943802,48.3534126282],"type":"Point"}
}