{
  "type": "Feature",
  "properties": {
    "iso:country":"DE",
    "sg:address":"Deichstr. 36",
    "sg:city":"Hamburg",
    "sg:phone":"+49 40/37500330",
    "sg:postcode":"20459",
    "sg:province":"Hamburg",
    "wof:name":"Bws Beratungsdienst B\u00f6hlke Gmbh",
    "wof:placetype":"venue"
},
  "geometry": {"coordinates":[9.9869747162,53.546043396],"type":"Point"}
}