{
  "type": "Feature",
  "properties": {
    "iso:country":"DE",
    "sg:address":"Dachbergstr. 72 a",
    "sg:city":"Bad Soden",
    "sg:phone":"+49 6196/21866",
    "sg:postcode":"65812",
    "sg:province":"Hessen",
    "wof:name":"Roland Kreuzeder Rechtsanwalt",
    "wof:placetype":"venue"
},
  "geometry": {"coordinates":[8.4893064499,50.1416816711],"type":"Point"}
}