{
  "type": "Feature",
  "properties": {
    "iso:country":"DE",
    "sg:address":"Ysenburger Str. 77",
    "sg:city":"Karben",
    "sg:phone":"+49 6039/2190",
    "sg:postcode":"61184",
    "sg:province":"Hessen",
    "wof:name":"Richard Cost",
    "wof:placetype":"venue"
},
  "geometry": {"coordinates":[8.772262,50.237507],"type":"Point"}
}