{
  "type": "Feature",
  "properties": {
    "iso:country":"DE",
    "sg:address":"Neumarktstr. 46",
    "sg:city":"Wuppertal",
    "sg:phone":"+49 202/451744",
    "sg:postcode":"42103",
    "sg:province":"Nordrhein-Westfalen",
    "wof:name":"Gerd-peter Kl\u00fcser Rechtsanwalt",
    "wof:placetype":"venue"
},
  "geometry": {"coordinates":[7.1419491768,51.2573356628],"type":"Point"}
}