{
  "type": "Feature",
  "properties": {
    "iso:country":"DE",
    "sg:address":"Schmittstr. 39",
    "sg:city":"Bingen",
    "sg:phone":"+49 6721/14250",
    "sg:postcode":"55411",
    "sg:province":"Rheinland-Pfalz",
    "wof:name":"Roswitha Freitag",
    "wof:placetype":"venue"
},
  "geometry": {"coordinates":[7.894249,49.965961],"type":"Point"}
}