{
  "type": "Feature",
  "properties": {
    "iso:country":"DE",
    "sg:address":"Herrenstr. 18",
    "sg:city":"Karlsruhe",
    "sg:phone":"+49 721/21232",
    "sg:postcode":"76133",
    "sg:province":"Baden-W\u00fcrttemberg",
    "wof:name":"Harry Strobel Masseur",
    "wof:placetype":"venue"
},
  "geometry": {"coordinates":[8.39947,49.009937],"type":"Point"}
}