{
  "type": "Feature",
  "properties": {
    "iso:country":"DE",
    "sg:address":"Tr\u00e4glhof 2",
    "sg:city":"Hirschau",
    "sg:phone":"+49 9608/92000",
    "sg:postcode":"92242",
    "sg:province":"Bayern",
    "wof:name":"A. P. Bioenergietechnik Gmbh",
    "wof:placetype":"venue"
},
  "geometry": {"coordinates":[11.943544,49.592144],"type":"Point"}
}