{
  "type": "Feature",
  "properties": {
    "iso:country":"DE",
    "sg:address":"Bergstr. 4",
    "sg:city":"Tussenhausen",
    "sg:phone":"+49 8268/458",
    "sg:postcode":"86874",
    "sg:province":"Bayern",
    "wof:name":"Alois Sonntag",
    "wof:placetype":"venue"
},
  "geometry": {"coordinates":[10.5633106232,48.103351593],"type":"Point"}
}