{
  "type": "Feature",
  "properties": {
    "iso:country":"DE",
    "sg:address":"Im Dalle 2",
    "sg:city":"Kalletal",
    "sg:phone":"+49 5733/2527",
    "sg:postcode":"32689",
    "sg:province":"Nordrhein-Westfalen",
    "wof:name":"F. Stratemeier Gmbh",
    "wof:placetype":"venue"
},
  "geometry": {"coordinates":[8.9212503433,52.1543312073],"type":"Point"}
}