{
  "type": "Feature",
  "properties": {
    "iso:country":"DE",
    "sg:address":"Kopfsberg 3",
    "sg:city":"Iggensbach",
    "sg:phone":"+49 9903/729",
    "sg:postcode":"94547",
    "sg:province":"Bayern",
    "wof:name":"Alois Stoiber",
    "wof:placetype":"venue"
},
  "geometry": {"coordinates":[13.1690864563,48.7187652588],"type":"Point"}
}