{
  "type": "Feature",
  "properties": {
    "iso:country":"DE",
    "sg:address":"Hauptstr. 32",
    "sg:city":"Pfedelbach",
    "sg:phone":"+49 4979/4134013",
    "sg:postcode":"74629",
    "sg:province":"Baden-W\u00fcrttemberg",
    "wof:name":"Sparkasse Hohenlohekreis",
    "wof:placetype":"venue"
},
  "geometry": {"coordinates":[9.50376,49.176712],"type":"Point"}
}