{
  "type": "Feature",
  "properties": {
    "iso:country":"DE",
    "sg:address":"Frankenthaler Str. 44",
    "sg:city":"Beindersheim",
    "sg:phone":"+49 6233/71320",
    "sg:postcode":"67259",
    "sg:province":"Rheinland-Pfalz",
    "wof:name":"Salih Yesil",
    "wof:placetype":"venue"
},
  "geometry": {"coordinates":[8.3277626038,49.5572776794],"type":"Point"}
}