{
  "type": "Feature",
  "properties": {
    "iso:country":"DE",
    "sg:address":"Muggeng\u00e4rtlestr. 8",
    "sg:city":"Freudenstadt",
    "sg:phone":"+49 7441/4611",
    "sg:postcode":"72250",
    "sg:province":"Baden-W\u00fcrttemberg",
    "wof:name":"Helmut Heinzelmann Architekt",
    "wof:placetype":"venue"
},
  "geometry": {"coordinates":[8.466269,48.450855],"type":"Point"}
}