{
  "type": "Feature",
  "properties": {
    "iso:country":"DE",
    "sg:address":"Rosenstr. 99",
    "sg:city":"Dresden",
    "sg:postcode":"01159",
    "sg:province":"Sachsen",
    "wof:name":"Immobilien-service Management Gmbh",
    "wof:placetype":"venue"
},
  "geometry": {"coordinates":[13.713206,51.045296],"type":"Point"}
}