{
  "type": "Feature",
  "properties": {
    "iso:country":"DE",
    "sg:address":"Kleiststr. 1",
    "sg:city":"Lemgo",
    "sg:phone":"+49 5261/15811",
    "sg:postcode":"32657",
    "sg:province":"Nordrhein-Westfalen",
    "wof:name":"Klaus Jung Heilpraktiker",
    "wof:placetype":"venue"
},
  "geometry": {"coordinates":[8.9063749313,52.0320320129],"type":"Point"}
}