{
  "type": "Feature",
  "properties": {
    "iso:country":"DE",
    "sg:address":"Sachsenberger Str. 16",
    "sg:city":"Lichtenfels",
    "sg:phone":"+49 5636/1577",
    "sg:postcode":"35104",
    "sg:province":"Hessen",
    "wof:name":"Uwe Frain",
    "wof:placetype":"venue"
},
  "geometry": {"coordinates":[8.8044900894,51.1996421814],"type":"Point"}
}