{
  "type": "Feature",
  "properties": {
    "iso:country":"DE",
    "sg:address":"Stra\u00dfe des Friedens 10",
    "sg:city":"Vetschau",
    "sg:phone":"+49 35433/2127",
    "sg:postcode":"03226",
    "sg:province":"Brandenburg",
    "wof:name":"W. Britze",
    "wof:placetype":"venue"
},
  "geometry": {"coordinates":[14.0814838409,51.7854957581],"type":"Point"}
}