{
  "type": "Feature",
  "properties": {
    "iso:country":"DE",
    "sg:address":"Grille 54",
    "sg:city":"Minden",
    "sg:phone":"+49 571/33201",
    "sg:postcode":"32423",
    "sg:province":"Nordrhein-Westfalen",
    "wof:name":"Harald Pohlmann Ingenieur",
    "wof:placetype":"venue"
},
  "geometry": {"coordinates":[8.955239296,52.2817192078],"type":"Point"}
}