{
  "type": "Feature",
  "properties": {
    "iso:country":"DE",
    "sg:address":"Wildhofer Str. 5",
    "sg:city":"Heusenstamm",
    "sg:phone":"+49 6104/61569",
    "sg:postcode":"63150",
    "sg:province":"Hessen",
    "wof:name":"A. Und H. Beck",
    "wof:placetype":"venue"
},
  "geometry": {"coordinates":[8.7900419235,50.0594673157],"type":"Point"}
}