{
  "type": "Feature",
  "properties": {
    "iso:country":"DE",
    "sg:address":"Marschweg 36a",
    "sg:city":"Oldenburg",
    "sg:phone":"+49 441/26501",
    "sg:postcode":"26122",
    "sg:province":"Niedersachsen",
    "wof:name":"Harry Einfeld Gerd L\u00fchrs M. Neumann-nieschlag",
    "wof:placetype":"venue"
},
  "geometry": {"coordinates":[8.2043304443,53.1308441162],"type":"Point"}
}