{
  "type": "Feature",
  "properties": {
    "iso:country":"DE",
    "sg:address":"J\u00e4gerlauf 23",
    "sg:city":"Hamburg",
    "sg:postcode":"22529",
    "sg:province":"Hamburg",
    "wof:name":"Andreas Scheffler Rechtsanwalt",
    "wof:placetype":"venue"
},
  "geometry": {"coordinates":[9.9677915573,53.6009521484],"type":"Point"}
}