{
  "type": "Feature",
  "properties": {
    "iso:country":"DE",
    "sg:address":"Deganoweg 10",
    "sg:city":"Gmund",
    "sg:phone":"+49 8022/97511",
    "sg:postcode":"83703",
    "sg:province":"Bayern",
    "wof:name":"Mercon Gmbh",
    "wof:placetype":"venue"
},
  "geometry": {"coordinates":[11.732465744,47.7494125366],"type":"Point"}
}