{
  "type": "Feature",
  "properties": {
    "iso:country":"DE",
    "sg:address":"Im See 5",
    "sg:city":"Bad Soden-Salm\u00fcnster",
    "sg:postcode":"63628",
    "sg:province":"Hessen",
    "wof:name":"Wfg Wellpappen Freigericht Gmbh",
    "wof:placetype":"venue"
},
  "geometry": {"coordinates":[9.3617019653,50.2666740417],"type":"Point"}
}