{
  "type": "Feature",
  "properties": {
    "iso:country":"DE",
    "sg:address":"Nordstr. 29",
    "sg:city":"Dresden",
    "sg:postcode":"01099",
    "sg:province":"Sachsen",
    "wof:name":"Hans Pastyrik",
    "wof:placetype":"venue"
},
  "geometry": {"coordinates":[13.7629365921,51.0697631836],"type":"Point"}
}