{
  "type": "Feature",
  "properties": {
    "iso:country":"DE",
    "sg:address":"Achternfelde 19",
    "sg:city":"Norderstedt",
    "sg:phone":"+49 40/5237822",
    "sg:postcode":"22850",
    "sg:province":"Schleswig-Holstein",
    "wof:name":"Fischer",
    "wof:placetype":"venue"
},
  "geometry": {"coordinates":[9.9786310196,53.6833953857],"type":"Point"}
}