{
  "type": "Feature",
  "properties": {
    "iso:country":"DE",
    "sg:address":"Blankenhainer Str. 12",
    "sg:city":"Erfurt",
    "sg:phone":"+49 361/3455797",
    "sg:postcode":"99099",
    "sg:province":"Th\u00fcringen",
    "wof:name":"Erfurter Wohnungsbau- Genossenschaft Reichsbahn Eg",
    "wof:placetype":"venue"
},
  "geometry": {"coordinates":[11.058089,50.969582],"type":"Point"}
}