{
  "type": "Feature",
  "properties": {
    "iso:country":"DE",
    "sg:address":"Heinkelstr. 9",
    "sg:city":"Weinstadt",
    "sg:phone":"+49 7151/62744",
    "sg:postcode":"71384",
    "sg:province":"Baden-W\u00fcrttemberg",
    "wof:name":"Josef Kottmair",
    "wof:placetype":"venue"
},
  "geometry": {"coordinates":[9.388338,48.812389],"type":"Point"}
}