{
  "type": "Feature",
  "properties": {
    "iso:country":"DE",
    "sg:address":"Marienstr. 27",
    "sg:city":"Trier",
    "sg:phone":"+49 651/86230",
    "sg:postcode":"54294",
    "sg:province":"Rheinland-Pfalz",
    "wof:name":"Edmund Schilz",
    "wof:placetype":"venue"
},
  "geometry": {"coordinates":[6.5855951309,49.7253646851],"type":"Point"}
}