{
  "type": "Feature",
  "properties": {
    "iso:country":"DE",
    "sg:address":"Gutenbergstr. 2",
    "sg:city":"Halle",
    "sg:postcode":"33790",
    "sg:province":"Nordrhein-Westfalen",
    "wof:name":"Bratvogel Verlags Gmbh",
    "wof:placetype":"venue"
},
  "geometry": {"coordinates":[8.374771,52.046017],"type":"Point"}
}