{
  "type": "Feature",
  "properties": {
    "iso:country":"DE",
    "sg:address":"Mossendorfer Str. 33",
    "sg:city":"Burglengenfeld",
    "sg:phone":"+49 9471/5695",
    "sg:postcode":"93133",
    "sg:province":"Bayern",
    "wof:name":"Ludwig Faltermeier",
    "wof:placetype":"venue"
},
  "geometry": {"coordinates":[12.025197,49.207512],"type":"Point"}
}