{
  "type": "Feature",
  "properties": {
    "iso:country":"DE",
    "sg:address":"Bismarckstr. 7",
    "sg:city":"Norderney",
    "sg:phone":"+49 4932/2292",
    "sg:postcode":"26548",
    "sg:province":"Niedersachsen",
    "wof:name":"Pension E. Schipper",
    "wof:placetype":"venue"
},
  "geometry": {"coordinates":[7.1445178986,53.7088279724],"type":"Point"}
}