{
  "type": "Feature",
  "properties": {
    "iso:country":"DE",
    "sg:address":"Am Bl\u00f6cken 75c",
    "sg:city":"Kiel",
    "sg:postcode":"24111",
    "sg:province":"Schleswig-Holstein",
    "wof:name":"Freiwillige Feuerwehr Kiel-russee",
    "wof:placetype":"venue"
},
  "geometry": {"coordinates":[10.0715122223,54.3043632507],"type":"Point"}
}