{
  "type": "Feature",
  "properties": {
    "iso:country":"DE",
    "sg:address":"Spitzenweg 1",
    "sg:city":"Geiselh\u00f6ring",
    "sg:phone":"+49 9423/1319",
    "sg:postcode":"94333",
    "sg:province":"Bayern",
    "wof:name":"Hans U. Annelies P\u00f6schl",
    "wof:placetype":"venue"
},
  "geometry": {"coordinates":[12.3759403229,48.7946586609],"type":"Point"}
}