{
  "type": "Feature",
  "properties": {
    "iso:country":"DE",
    "sg:address":"Wurzner Str. 199",
    "sg:city":"Leipzig",
    "sg:phone":"+49 341/244980",
    "sg:postcode":"04318",
    "sg:province":"Sachsen",
    "wof:name":"Bestattungshaus B\u00f6ttge Gmbh",
    "wof:placetype":"venue"
},
  "geometry": {"coordinates":[12.432154,51.344139],"type":"Point"}
}