{
  "type": "Feature",
  "properties": {
    "iso:country":"DE",
    "sg:address":"Hochbr\u00fccktorstr. 26",
    "sg:city":"Rottweil",
    "sg:phone":"+49 741/42236",
    "sg:postcode":"78628",
    "sg:province":"Baden-W\u00fcrttemberg",
    "wof:name":"Franz Graf Von Bissingen Rechtsanwalt",
    "wof:placetype":"venue"
},
  "geometry": {"coordinates":[8.6277542114,48.166595459],"type":"Point"}
}