{
  "type": "Feature",
  "properties": {
    "iso:country":"DE",
    "sg:address":"Kolpingstr. 2",
    "sg:city":"Hamminkeln",
    "sg:phone":"+49 2852/968311",
    "sg:postcode":"46499",
    "sg:province":"Nordrhein-Westfalen",
    "wof:name":"Andreas Sack Rechtsanwalt",
    "wof:placetype":"venue"
},
  "geometry": {"coordinates":[6.61251688,51.7727432251],"type":"Point"}
}