{
  "type": "Feature",
  "properties": {
    "iso:country":"DE",
    "sg:address":"Eggergasse 14",
    "sg:city":"Frontenhausen",
    "sg:phone":"+49 8732/2717",
    "sg:postcode":"84160",
    "sg:province":"Bayern",
    "wof:name":"M. Brandhuber Gmbh",
    "wof:placetype":"venue"
},
  "geometry": {"coordinates":[12.528063,48.547539],"type":"Point"}
}