{
  "type": "Feature",
  "properties": {
    "iso:country":"DE",
    "sg:address":"Alte Gasse 9",
    "sg:city":"Mosel",
    "sg:phone":"+49 4937/6043133",
    "sg:postcode":"08129",
    "wof:name":"Sigrid Hofmann",
    "wof:placetype":"venue"
},
  "geometry": {"coordinates":[12.4831619263,50.7822875977],"type":"Point"}
}