{
  "type": "Feature",
  "properties": {
    "iso:country":"DE",
    "sg:address":"Eduard-M\u00f6rike-Str. 34",
    "sg:city":"Nordhorn",
    "sg:phone":"+49 5921/4898",
    "sg:postcode":"48527",
    "sg:province":"Niedersachsen",
    "wof:name":"Irmgard Hanenkamp",
    "wof:placetype":"venue"
},
  "geometry": {"coordinates":[7.0554070473,52.4266204834],"type":"Point"}
}