{
  "type": "Feature",
  "properties": {
    "iso:country":"DE",
    "sg:address":"S\u00fcderfischerstr. 20",
    "sg:city":"Flensburg",
    "sg:phone":"+49 461/22442",
    "sg:postcode":"24937",
    "sg:province":"Schleswig-Holstein",
    "wof:name":"Uwe Hansen",
    "wof:placetype":"venue"
},
  "geometry": {"coordinates":[9.440244,54.783543],"type":"Point"}
}