{
  "type": "Feature",
  "properties": {
    "iso:country":"DE",
    "sg:address":"Pienzenauerstr. 56",
    "sg:city":"M\u00fcnchen",
    "sg:phone":"+49 89/981581",
    "sg:postcode":"81925",
    "sg:province":"Bayern",
    "wof:name":"Foerstner Beiler & Co. Wertpapierhaus Ag",
    "wof:placetype":"venue"
},
  "geometry": {"coordinates":[11.6080722809,48.1563644409],"type":"Point"}
}