{
  "type": "Feature",
  "properties": {
    "iso:country":"DE",
    "sg:address":"Goldbachstr 9",
    "sg:city":"N\u00fcrnberg",
    "sg:phone":"+49 911/940830",
    "sg:postcode":"90480",
    "sg:province":"Bayern",
    "wof:name":"Hottinger Baldwin Messtechnik Gmbh",
    "wof:placetype":"venue"
},
  "geometry": {"coordinates":[11.1115074158,49.444934845],"type":"Point"}
}