{
  "type": "Feature",
  "properties": {
    "iso:country":"DE",
    "sg:address":"Marktler Str 50",
    "sg:city":"Burghausen",
    "sg:phone":"+49 8677/97470",
    "sg:postcode":"84489",
    "sg:province":"Bayern",
    "wof:name":"Coc Ag",
    "wof:placetype":"venue"
},
  "geometry": {"coordinates":[12.830616,48.173298],"type":"Point"}
}