{
  "type": "Feature",
  "properties": {
    "iso:country":"DE",
    "sg:address":"Bahnhofstr. 123",
    "sg:city":"Warmensteinach",
    "sg:phone":"+49 9277/1722",
    "sg:postcode":"95485",
    "sg:province":"Bayern",
    "wof:name":"Seidel Gmbh",
    "wof:placetype":"venue"
},
  "geometry": {"coordinates":[11.778364,49.996067],"type":"Point"}
}