{
  "type": "Feature",
  "properties": {
    "iso:country":"DE",
    "sg:address":"Hof Wilhelmsh\u00f6he",
    "sg:city":"Bad Soden",
    "sg:phone":"+49 6196/28553",
    "sg:postcode":"65812",
    "sg:province":"Hessen",
    "wof:name":"Landwirtschaftliche Lohn- Arbeit Pfeiffer Gmbh",
    "wof:placetype":"venue"
},
  "geometry": {"coordinates":[8.493305,50.134426],"type":"Point"}
}