{
  "type": "Feature",
  "properties": {
    "iso:country":"DE",
    "sg:address":"Hauptstr. 32",
    "sg:city":"Auggen",
    "sg:phone":"+49 7631/2640",
    "sg:postcode":"79424",
    "sg:province":"Baden-W\u00fcrttemberg",
    "wof:name":"Fritz Bolanz",
    "wof:placetype":"venue"
},
  "geometry": {"coordinates":[7.5962200165,47.7875328064],"type":"Point"}
}