{
  "type": "Feature",
  "properties": {
    "iso:country":"DE",
    "sg:address":"Am Rippinger Weg 2",
    "sg:city":"Paderborn",
    "sg:phone":"+49 5251/63351",
    "sg:postcode":"33098",
    "sg:province":"Nordrhein-Westfalen",
    "wof:name":"Landesstrassenbauamt",
    "wof:placetype":"venue"
},
  "geometry": {"coordinates":[8.7759332657,51.7091255188],"type":"Point"}
}