{
  "type": "Feature",
  "properties": {
    "iso:country":"DE",
    "sg:address":"Zollberg 39",
    "sg:city":"Aschersleben",
    "sg:phone":"+49 3473/806375",
    "sg:postcode":"06449",
    "sg:province":"Sachsen-Anhalt",
    "wof:name":"R. Baldauf",
    "wof:placetype":"venue"
},
  "geometry": {"coordinates":[11.4449977875,51.7577133179],"type":"Point"}
}