{
  "type": "Feature",
  "properties": {
    "iso:country":"DE",
    "sg:address":"Hallesche Stra\u00dfe 76",
    "sg:city":"Schkeuditz",
    "sg:phone":"+49 34204",
    "sg:postcode":"04435",
    "sg:province":"Sachsen",
    "wof:name":"Schwerdtner - Firmengruppe",
    "wof:placetype":"venue"
},
  "geometry": {"coordinates":[12.2131853104,51.3947906494],"type":"Point"}
}