{
  "type": "Feature",
  "properties": {
    "iso:country":"DE",
    "sg:address":"Warburger Str. 32",
    "sg:city":"Wolfhagen",
    "sg:phone":"+49 5606/2050",
    "sg:postcode":"34466",
    "sg:province":"Hessen",
    "wof:name":"Georg Gante",
    "wof:placetype":"venue"
},
  "geometry": {"coordinates":[9.1866464615,51.3911399841],"type":"Point"}
}