{
  "type": "Feature",
  "properties": {
    "iso:country":"DE",
    "sg:address":"Beienroder Str. 20",
    "sg:city":"Lehre",
    "sg:phone":"+49 5308/3942",
    "sg:postcode":"38165",
    "sg:province":"Niedersachsen",
    "wof:name":"W. Beyer",
    "wof:placetype":"venue"
},
  "geometry": {"coordinates":[10.711137,52.350506],"type":"Point"}
}