{
  "type": "Feature",
  "properties": {
    "iso:country":"DE",
    "sg:address":"Arnekenstr 9b",
    "sg:city":"Hildesheim",
    "sg:phone":"+49 5121/32318",
    "sg:postcode":"31134",
    "sg:province":"Niedersachsen",
    "wof:name":"Carl Schmidt U. Sohn Gmbh & Co Kg",
    "wof:placetype":"venue"
},
  "geometry": {"coordinates":[9.949495,52.153824],"type":"Point"}
}