{
  "type": "Feature",
  "properties": {
    "iso:country":"DE",
    "sg:address":"Siemensstr. 2",
    "sg:city":"Rodgau",
    "sg:phone":"+49 6106/21322",
    "sg:postcode":"63110",
    "sg:province":"Hessen",
    "wof:name":"Ludwig V. Klein Elektroinstallation",
    "wof:placetype":"venue"
},
  "geometry": {"coordinates":[8.887185,50.012863],"type":"Point"}
}