{
  "type": "Feature",
  "properties": {
    "iso:country":"DE",
    "sg:address":"K\u00f6nigin-Luise-Str. 19",
    "sg:city":"Berlin",
    "sg:postcode":"14195",
    "sg:province":"Berlin",
    "wof:name":"Institut F. Vorratsschutz",
    "wof:placetype":"venue"
},
  "geometry": {"coordinates":[13.2990922928,52.4579544067],"type":"Point"}
}