{
  "type": "Feature",
  "properties": {
    "iso:country":"DE",
    "sg:address":"Mecklenburger Str 27A",
    "sg:city":"Ha\u00dfloch",
    "sg:phone":"+49 6324/981076",
    "sg:postcode":"67454",
    "sg:province":"Rheinland-Pfalz",
    "wof:name":"M. Dannecker",
    "wof:placetype":"venue"
},
  "geometry": {"coordinates":[8.266285,49.370804],"type":"Point"}
}