{
  "type": "Feature",
  "properties": {
    "iso:country":"DE",
    "sg:address":"Kastanienweg 13",
    "sg:city":"Waltenhofen",
    "sg:phone":"+49 831/25850",
    "sg:postcode":"87448",
    "sg:province":"Bayern",
    "wof:name":"Milan Babicek Ingenieur",
    "wof:placetype":"venue"
},
  "geometry": {"coordinates":[10.3126602173,47.6858177185],"type":"Point"}
}