{
  "type": "Feature",
  "properties": {
    "iso:country":"DE",
    "sg:address":"Trierer Str. 15",
    "sg:city":"Merzig",
    "sg:phone":"+49 6861/89400",
    "sg:postcode":"66663",
    "sg:province":"Saarland",
    "wof:name":"Old Dad",
    "wof:placetype":"venue"
},
  "geometry": {"coordinates":[6.636254,49.44569],"type":"Point"}
}