{
  "type": "Feature",
  "properties": {
    "iso:country":"DE",
    "sg:address":"Lichterfelder Allee 35",
    "sg:city":"Teltow",
    "sg:phone":"+49 3328/41081",
    "sg:postcode":"14513",
    "sg:province":"Brandenburg",
    "wof:name":"H. Sch\u00e4fer",
    "wof:placetype":"venue"
},
  "geometry": {"coordinates":[13.2751350403,52.4028396606],"type":"Point"}
}