{
  "type": "Feature",
  "properties": {
    "iso:country":"DE",
    "sg:address":"Alter Weg 23",
    "sg:city":"Cuxhaven",
    "sg:phone":"+49 4722/91090",
    "sg:postcode":"27478",
    "sg:province":"Niedersachsen",
    "wof:name":"Umwelt Projekt Management Upm Gmbh",
    "wof:placetype":"venue"
},
  "geometry": {"coordinates":[8.7671365738,53.8254127502],"type":"Point"}
}