{
  "type": "Feature",
  "properties": {
    "iso:country":"DE",
    "sg:address":"Steinstr. 30",
    "sg:city":"Erfurt",
    "sg:phone":"+49 361/5610536",
    "sg:postcode":"99084",
    "sg:province":"Th\u00fcringen",
    "wof:name":"Artemis",
    "wof:placetype":"venue"
},
  "geometry": {"coordinates":[11.02617836,50.9824028015],"type":"Point"}
}