{
  "type": "Feature",
  "properties": {
    "iso:country":"DE",
    "sg:address":"Staakener Str. 18",
    "sg:city":"Berlin",
    "sg:phone":"+49 30/3327429",
    "sg:postcode":"13581",
    "sg:province":"Berlin",
    "wof:name":"Catalina Elektrobau Gmbh",
    "wof:placetype":"venue"
},
  "geometry": {"coordinates":[13.183395,52.535877],"type":"Point"}
}