{
  "type": "Feature",
  "properties": {
    "iso:country":"DE",
    "sg:address":"Sch\u00fccostr. 11",
    "sg:city":"Gro\u00df-Rohrheim",
    "sg:phone":"+49 6245/90170",
    "sg:postcode":"68649",
    "sg:province":"Hessen",
    "wof:name":"Sprung West Gmbh",
    "wof:placetype":"venue"
},
  "geometry": {"coordinates":[8.48365,49.715534],"type":"Point"}
}