{
  "type": "Feature",
  "properties": {
    "iso:country":"DE",
    "sg:address":"Hanger Weg 1",
    "sg:city":"Freren",
    "sg:phone":"+49 5902/940010",
    "sg:postcode":"49832",
    "sg:province":"Niedersachsen",
    "wof:name":"Edmund R\u00f6ttger",
    "wof:placetype":"venue"
},
  "geometry": {"coordinates":[7.566335,52.471348],"type":"Point"}
}