{
  "type": "Feature",
  "properties": {
    "iso:country":"DE",
    "sg:address":"Hochstr. 59",
    "sg:city":"Bobingen",
    "sg:phone":"+49 8234/2093",
    "sg:postcode":"86399",
    "sg:province":"Bayern",
    "wof:name":"Walter Strau\u00df",
    "wof:placetype":"venue"
},
  "geometry": {"coordinates":[10.8383674622,48.2752037048],"type":"Point"}
}