{
  "type": "Feature",
  "properties": {
    "iso:country":"DE",
    "sg:address":"Antonstr. 30",
    "sg:city":"Sigmaringen",
    "sg:phone":"+49 7571/12854",
    "sg:postcode":"72488",
    "sg:province":"Baden-W\u00fcrttemberg",
    "wof:name":"K. Frick",
    "wof:placetype":"venue"
},
  "geometry": {"coordinates":[9.2150201797,48.0864486694],"type":"Point"}
}