{
  "type": "Feature",
  "properties": {
    "iso:country":"DE",
    "sg:address":"Mariendorfer Damm 71",
    "sg:city":"Berlin",
    "sg:phone":"+49 30/7063175",
    "sg:postcode":"12109",
    "sg:province":"Berlin",
    "wof:name":"Rudi Rockstroh",
    "wof:placetype":"venue"
},
  "geometry": {"coordinates":[13.3859472275,52.4463157654],"type":"Point"}
}