{
  "type": "Feature",
  "properties": {
    "iso:country":"DE",
    "sg:address":"Gartenstr. 7",
    "sg:city":"Nieb\u00fcll",
    "sg:phone":"+49 4661/4270",
    "sg:postcode":"25899",
    "sg:province":"Schleswig-Holstein",
    "wof:name":"Walter Schnoor Architekt",
    "wof:placetype":"venue"
},
  "geometry": {"coordinates":[8.820462,54.791321],"type":"Point"}
}