{
  "type": "Feature",
  "properties": {
    "iso:country":"DE",
    "sg:address":"Buchheider Weg 42",
    "sg:city":"D\u00fcren",
    "sg:phone":"+49 2421/61108",
    "sg:postcode":"52355",
    "sg:province":"Nordrhein-Westfalen",
    "wof:name":"Hubert Wollseifen",
    "wof:placetype":"venue"
},
  "geometry": {"coordinates":[6.467046,50.779446],"type":"Point"}
}