{
  "type": "Feature",
  "properties": {
    "iso:country":"DE",
    "sg:address":"Hohefeldstr. 34",
    "sg:city":"Polle",
    "sg:phone":"+49 5535/300",
    "sg:postcode":"37647",
    "sg:province":"Niedersachsen",
    "wof:name":"Pension Renate Hesse",
    "wof:placetype":"venue"
},
  "geometry": {"coordinates":[9.3993740082,51.9016036987],"type":"Point"}
}