{
  "type": "Feature",
  "properties": {
    "iso:country":"DE",
    "sg:address":"Josephstr. 38",
    "sg:city":"Leipzig",
    "sg:phone":"+49 12343",
    "sg:postcode":"04177",
    "sg:province":"Sachsen",
    "wof:name":"Tango Andorinha",
    "wof:placetype":"venue"
},
  "geometry": {"coordinates":[12.334917,51.332973],"type":"Point"}
}