{
  "type": "Feature",
  "properties": {
    "iso:country":"DE",
    "sg:address":"Gropiusstr. 3",
    "sg:city":"Hildesheim",
    "sg:phone":"+49 5121/750960",
    "sg:postcode":"31137",
    "sg:province":"Niedersachsen",
    "wof:name":"Sch\u00e4dler Baugesellschaft Mbh",
    "wof:placetype":"venue"
},
  "geometry": {"coordinates":[9.938464,52.173351],"type":"Point"}
}