{
  "type": "Feature",
  "properties": {
    "iso:country":"DE",
    "sg:address":"Auweg 10",
    "sg:city":"Hohenahr",
    "sg:phone":"+49 6446/1411",
    "sg:postcode":"35644",
    "sg:province":"Hessen",
    "wof:name":"Arnold Herpel",
    "wof:placetype":"venue"
},
  "geometry": {"coordinates":[8.525378,50.676735],"type":"Point"}
}