{
  "type": "Feature",
  "properties": {
    "iso:country":"DE",
    "sg:address":"T\u00fcrkenlouisstr. 20",
    "sg:city":"Freiburg",
    "sg:phone":"+49 761/214356",
    "sg:postcode":"79102",
    "sg:province":"Baden-W\u00fcrttemberg",
    "wof:name":"Deutsche Bahn Ag",
    "wof:placetype":"venue"
},
  "geometry": {"coordinates":[7.8550162315,47.9828872681],"type":"Point"}
}