{
  "type": "Feature",
  "properties": {
    "iso:country":"DE",
    "sg:address":"Kolpingstr. 5",
    "sg:city":"Vechelde",
    "sg:postcode":"38159",
    "sg:province":"Niedersachsen",
    "wof:name":"Tritec Techn. Service F\u00fcr Camcorder",
    "wof:placetype":"venue"
},
  "geometry": {"coordinates":[10.367682457,52.2635574341],"type":"Point"}
}