{
  "type": "Feature",
  "properties": {
    "iso:country":"DE",
    "sg:address":"Hohentorstr. 1",
    "sg:city":"Alsfeld",
    "sg:phone":"+49 6639/239",
    "sg:postcode":"36304",
    "sg:province":"Hessen",
    "wof:name":"M. Martin",
    "wof:placetype":"venue"
},
  "geometry": {"coordinates":[9.4047002792,50.7614784241],"type":"Point"}
}