{
  "type": "Feature",
  "properties": {
    "iso:country":"DE",
    "sg:address":"Bei der Wette 7",
    "sg:city":"Stuttgart",
    "sg:phone":"+49 711/332513",
    "sg:postcode":"70327",
    "sg:province":"Baden-W\u00fcrttemberg",
    "wof:name":"R. Berner",
    "wof:placetype":"venue"
},
  "geometry": {"coordinates":[9.2711343765,48.783706665],"type":"Point"}
}