{
  "type": "Feature",
  "properties": {
    "iso:country":"DE",
    "sg:address":"Pirnaer Landstr. 133",
    "sg:city":"Dresden",
    "sg:phone":"+49 351/2034568",
    "sg:postcode":"01257",
    "sg:province":"Sachsen",
    "wof:name":"Schumanns K\u00fcchen Und Wohnideen",
    "wof:placetype":"venue"
},
  "geometry": {"coordinates":[13.8274087906,51.0116539001],"type":"Point"}
}