{
  "type": "Feature",
  "properties": {
    "iso:country":"DE",
    "sg:address":"H\u00fchndorfer Str. 21",
    "sg:city":"Sachsdorf",
    "sg:phone":"+49 35204/40047",
    "sg:postcode":"01665",
    "sg:province":"Sachsen",
    "wof:name":"Christian Becker",
    "wof:placetype":"venue"
},
  "geometry": {"coordinates":[13.540257,51.068142],"type":"Point"}
}