{
  "type": "Feature",
  "properties": {
    "iso:country":"DE",
    "sg:address":"Angerm\u00fcnder Str. 17a",
    "sg:city":"Joachimsthal",
    "sg:phone":"+49 33361/463",
    "sg:postcode":"16247",
    "sg:province":"Brandenburg",
    "wof:name":"Otto Boltz",
    "wof:placetype":"venue"
},
  "geometry": {"coordinates":[13.76506,52.968777],"type":"Point"}
}