{
  "type": "Feature",
  "properties": {
    "iso:country":"DE",
    "sg:address":"Am Hollerbroch 64",
    "sg:city":"R\u00f6srath",
    "sg:phone":"+49 2205/911031",
    "sg:postcode":"51503",
    "sg:province":"Nordrhein-Westfalen",
    "wof:name":"Peter Paus Kuczera Gmbh",
    "wof:placetype":"venue"
},
  "geometry": {"coordinates":[7.1731200218,50.8953208923],"type":"Point"}
}