{
  "type": "Feature",
  "properties": {
    "iso:country":"DE",
    "sg:address":"Raiffeisenstr 6",
    "sg:city":"Bockhorst",
    "sg:phone":"+49 4967/91810",
    "sg:postcode":"26897",
    "sg:province":"Niedersachsen",
    "wof:name":"Jab Industrieservice Gmbh & Co Kg",
    "wof:placetype":"venue"
},
  "geometry": {"coordinates":[7.577409,53.02702],"type":"Point"}
}