{
  "type": "Feature",
  "properties": {
    "iso:country":"DE",
    "sg:address":"Oberstadtstr 63",
    "sg:city":"Haigerloch",
    "sg:phone":"+49 7474/6115",
    "sg:postcode":"72401",
    "sg:province":"Baden-W\u00fcrttemberg",
    "wof:name":"Gotthilf Ammann",
    "wof:placetype":"venue"
},
  "geometry": {"coordinates":[8.7996196747,48.3673934937],"type":"Point"}
}