{
  "type": "Feature",
  "properties": {
    "iso:country":"DE",
    "sg:address":"Winsener Str. 13",
    "sg:city":"Bergen",
    "sg:phone":"+49 5051/2101",
    "sg:postcode":"29303",
    "sg:province":"Niedersachsen",
    "wof:name":"Karl-heinz Minuth Tischlerei Und Messe Gmbh",
    "wof:placetype":"venue"
},
  "geometry": {"coordinates":[9.935952,52.78894],"type":"Point"}
}