{
  "type": "Feature",
  "properties": {
    "iso:country":"DE",
    "sg:address":"Lange Str. 11",
    "sg:city":"Colbitz",
    "sg:postcode":"39326",
    "sg:province":"Sachsen-Anhalt",
    "wof:name":"Colbitzer Baugesellschaft Mbh",
    "wof:placetype":"venue"
},
  "geometry": {"coordinates":[11.605801,52.313679],"type":"Point"}
}