{
  "type": "Feature",
  "properties": {
    "iso:country":"DE",
    "sg:address":"Recklingh\u00e4user Str. 98",
    "sg:city":"Haltern",
    "sg:phone":"+49 2364/3579",
    "sg:postcode":"45721",
    "sg:province":"Nordrhein-Westfalen",
    "wof:name":"R. Schulz",
    "wof:placetype":"venue"
},
  "geometry": {"coordinates":[7.1875967979,51.7330627441],"type":"Point"}
}