{
  "type": "Feature",
  "properties": {
    "iso:country":"DE",
    "sg:address":"Steinweg 2",
    "sg:city":"Bockenem",
    "sg:phone":"+49 5067/3677",
    "sg:postcode":"31167",
    "sg:province":"Niedersachsen",
    "wof:name":"Klaus Matthes",
    "wof:placetype":"venue"
},
  "geometry": {"coordinates":[10.150929,52.017197],"type":"Point"}
}