{
  "type": "Feature",
  "properties": {
    "iso:country":"DE",
    "sg:address":"Am Marienpfad 55",
    "sg:city":"Mainz",
    "sg:phone":"+49 6131/361083",
    "sg:postcode":"55128",
    "sg:province":"Rheinland-Pfalz",
    "wof:name":"Thomas Metzenroth Steuerberater",
    "wof:placetype":"venue"
},
  "geometry": {"coordinates":[8.2522802353,49.98046875],"type":"Point"}
}