{
  "type": "Feature",
  "properties": {
    "iso:country":"DE",
    "sg:address":"Bramfelder Str. 83",
    "sg:city":"Hamburg",
    "sg:postcode":"22305",
    "sg:province":"Hamburg",
    "wof:name":"Video Extend",
    "wof:placetype":"venue"
},
  "geometry": {"coordinates":[10.0519475937,53.5877723694],"type":"Point"}
}