{
  "type": "Feature",
  "properties": {
    "iso:country":"DE",
    "sg:address":"Schatthauserstr. 9",
    "sg:city":"Dornum",
    "sg:postcode":"26553",
    "sg:province":"Niedersachsen",
    "wof:name":"Peg Projektentwicklungs- Gesellschaft Mahlbusen Mbh",
    "wof:placetype":"venue"
},
  "geometry": {"coordinates":[7.428612,53.645508],"type":"Point"}
}