{
  "type": "Feature",
  "properties": {
    "iso:country":"DE",
    "sg:address":"Uebigauer Str 30",
    "sg:city":"Wahrenbr\u00fcck",
    "sg:phone":"+49 35341/94846",
    "sg:postcode":"04924",
    "sg:province":"Brandenburg",
    "wof:name":"Albrecht & J\u00e4cker Nachf. Gmbh & Co",
    "wof:placetype":"venue"
},
  "geometry": {"coordinates":[13.361083,51.553528],"type":"Point"}
}