{
  "type": "Feature",
  "properties": {
    "iso:country":"DE",
    "sg:address":"Weichselstr. 7",
    "sg:city":"M\u00fcnster",
    "sg:phone":"+49 2506/2468",
    "sg:postcode":"48167",
    "sg:province":"Nordrhein-Westfalen",
    "wof:name":"Petra St\u00f6ppelmann Finanzberater",
    "wof:placetype":"venue"
},
  "geometry": {"coordinates":[7.7150969505,51.9104576111],"type":"Point"}
}