{
  "type": "Feature",
  "properties": {
    "iso:country":"DE",
    "sg:address":"Nordfeldstr. 16",
    "sg:city":"Versmold",
    "sg:phone":"+49 5423/5865",
    "sg:postcode":"33775",
    "sg:province":"Nordrhein-Westfalen",
    "wof:name":"Metallbau Ralf Gronau",
    "wof:placetype":"venue"
},
  "geometry": {"coordinates":[8.148781,52.046192],"type":"Point"}
}