{
  "type": "Feature",
  "properties": {
    "iso:country":"DE",
    "sg:address":"Glatzerstr.34",
    "sg:city":"Ahlen",
    "sg:postcode":"59227",
    "sg:province":"Nordrhein-Westfalen",
    "wof:name":"Willkommen Auf Den Seiten Von K. Schmidt",
    "wof:placetype":"venue"
},
  "geometry": {"coordinates":[7.93706,51.804779],"type":"Point"}
}