{
  "type": "Feature",
  "properties": {
    "iso:country":"DE",
    "sg:address":"Rudolf-Diesel-Str. 1a",
    "sg:city":"Anklam",
    "sg:phone":"+49 3971/240319",
    "sg:postcode":"17389",
    "sg:province":"Mecklenburg-Vorpommern",
    "wof:name":"Heitmann",
    "wof:placetype":"venue"
},
  "geometry": {"coordinates":[13.711724,53.840576],"type":"Point"}
}