{
  "type": "Feature",
  "properties": {
    "iso:country":"DE",
    "sg:address":"Gerold Damm 2",
    "sg:city":"Bosau",
    "sg:phone":"+49 4527/1839",
    "sg:postcode":"23715",
    "sg:province":"Schleswig-Holstein",
    "wof:name":"Ahrensb\u00f6ker Landb\u00e4cker",
    "wof:placetype":"venue"
},
  "geometry": {"coordinates":[10.429706,54.106533],"type":"Point"}
}