{
  "type": "Feature",
  "properties": {
    "iso:country":"DE",
    "sg:address":"Hauptstr. 90",
    "sg:city":"Mengen",
    "sg:phone":"+49 7572/60720",
    "sg:postcode":"88512",
    "sg:province":"Baden-W\u00fcrttemberg",
    "wof:name":"St\u00e4dtisches Heimatmuseum",
    "wof:placetype":"venue"
},
  "geometry": {"coordinates":[9.32878,48.048557],"type":"Point"}
}