{
  "type": "Feature",
  "properties": {
    "iso:country":"DE",
    "sg:address":"Johannisstr. 25",
    "sg:city":"L\u00f6bau",
    "sg:phone":"+49 3585/401793",
    "sg:postcode":"02708",
    "sg:province":"Sachsen",
    "wof:name":"Bettina Simon Anlageberaterin",
    "wof:placetype":"venue"
},
  "geometry": {"coordinates":[14.6677598953,51.094165802],"type":"Point"}
}