{
  "type": "Feature",
  "properties": {
    "iso:country":"DE",
    "sg:address":"Laurentiusstr. 14",
    "sg:city":"Borchen",
    "sg:phone":"+49 5251/39261",
    "sg:postcode":"33178",
    "sg:province":"Nordrhein-Westfalen",
    "wof:name":"Peter Kloke",
    "wof:placetype":"venue"
},
  "geometry": {"coordinates":[8.722102,51.668755],"type":"Point"}
}