{
  "type": "Feature",
  "properties": {
    "iso:country":"DE",
    "sg:address":"Sachsenh\u00e4user Landwehrweg 371",
    "sg:city":"Frankfurt",
    "sg:phone":"+49 69/635440",
    "sg:postcode":"60598",
    "sg:province":"Hessen",
    "wof:name":"Landwehrst\u00fcbchen",
    "wof:placetype":"venue"
},
  "geometry": {"coordinates":[8.675453186,50.0851364136],"type":"Point"}
}