{
  "type": "Feature",
  "properties": {
    "iso:country":"DE",
    "sg:address":"Deltzscherstr. 72",
    "sg:city":"Halle",
    "sg:phone":"+49 345/5600884",
    "sg:postcode":"06122",
    "sg:province":"Sachsen-Anhalt",
    "wof:name":"Heimbrauerei Alik Kunze",
    "wof:placetype":"venue"
},
  "geometry": {"coordinates":[11.9281797409,51.4850082397],"type":"Point"}
}