{
  "type": "Feature",
  "properties": {
    "iso:country":"DE",
    "sg:address":"Haydnstr. 3",
    "sg:city":"Lauingen",
    "sg:phone":"+49 9072/6111",
    "sg:postcode":"89415",
    "sg:province":"Bayern",
    "wof:name":"Siegtrud Hopp Masseur",
    "wof:placetype":"venue"
},
  "geometry": {"coordinates":[10.424288,48.567688],"type":"Point"}
}