{
  "type": "Feature",
  "properties": {
    "iso:country":"DE",
    "sg:address":"St\u00fcttinghauser Ringstr. 33",
    "sg:city":"L\u00fcdenscheid",
    "sg:phone":"+49 2351/973003",
    "sg:postcode":"58515",
    "sg:province":"Nordrhein-Westfalen",
    "wof:name":"Ingenieurb\u00fcro Susi Hunger",
    "wof:placetype":"venue"
},
  "geometry": {"coordinates":[7.5913939476,51.2089538574],"type":"Point"}
}