{
  "type": "Feature",
  "properties": {
    "iso:country":"DE",
    "sg:address":"Hasenbergsteige 35",
    "sg:city":"Stuttgart",
    "sg:phone":"+49 711/6402012",
    "sg:postcode":"70197",
    "sg:province":"Baden-W\u00fcrttemberg",
    "wof:name":"Ulrike Dieckh\u00f6fer Rechtsanw\u00e4ltin",
    "wof:placetype":"venue"
},
  "geometry": {"coordinates":[9.1587200165,48.7668952942],"type":"Point"}
}