{
  "type": "Feature",
  "properties": {
    "iso:country":"DE",
    "sg:address":"Schwiegle",
    "sg:city":"Wessobrunn",
    "sg:phone":"+49 8809/760",
    "sg:postcode":"82405",
    "sg:province":"Bayern",
    "wof:name":"Siegfried Strau\u00df",
    "wof:placetype":"venue"
},
  "geometry": {"coordinates":[11.01946,47.83371],"type":"Point"}
}