{
  "type": "Feature",
  "properties": {
    "iso:country":"DE",
    "sg:address":"Sonnenstr 48",
    "sg:city":"Greiz",
    "sg:phone":"+49 3661/455015",
    "sg:postcode":"07973",
    "sg:province":"Th\u00fcringen",
    "wof:name":"W. Kohlhammer Deutscher Gemeindeverlag Gmbh",
    "wof:placetype":"venue"
},
  "geometry": {"coordinates":[12.164021,50.66766],"type":"Point"}
}