{
  "type": "Feature",
  "properties": {
    "iso:country":"DE",
    "sg:address":"Waiblinger Str. 78",
    "sg:city":"Stuttgart",
    "sg:phone":"+49 711/569382",
    "sg:postcode":"70372",
    "sg:province":"Baden-W\u00fcrttemberg",
    "wof:name":"Hilbert",
    "wof:placetype":"venue"
},
  "geometry": {"coordinates":[9.227602005,48.8052139282],"type":"Point"}
}