{
  "type": "Feature",
  "properties": {
    "iso:country":"DE",
    "sg:address":"Jean-Paul-Allee 3",
    "sg:city":"Neustadt",
    "sg:phone":"+49 9568/5503",
    "sg:postcode":"96465",
    "sg:province":"Bayern",
    "wof:name":"G. Schr\u00f6der Haus- Und K\u00fcchenger\u00e4te",
    "wof:placetype":"venue"
},
  "geometry": {"coordinates":[11.1120853424,50.3327598572],"type":"Point"}
}