{
  "type": "Feature",
  "properties": {
    "iso:country":"DE",
    "sg:address":"Hauptstr. 99",
    "sg:city":"Sitzendorf",
    "sg:phone":"+49 36730/28137",
    "sg:postcode":"07429",
    "sg:province":"Th\u00fcringen",
    "wof:name":"Pension Haus Kokel",
    "wof:placetype":"venue"
},
  "geometry": {"coordinates":[11.1748714447,50.6330986023],"type":"Point"}
}