{
  "type": "Feature",
  "properties": {
    "iso:country":"DE",
    "sg:address":"Hahnenbacher Str. 41",
    "sg:city":"Annweiler",
    "sg:phone":"+49 6346/3303",
    "sg:postcode":"76855",
    "sg:province":"Rheinland-Pfalz",
    "wof:name":"Friedrich G\u00f6ttmann Inh. Gisela Mohra",
    "wof:placetype":"venue"
},
  "geometry": {"coordinates":[7.9712328911,49.2235565186],"type":"Point"}
}