{
  "type": "Feature",
  "properties": {
    "iso:country":"DE",
    "sg:address":"Am Kriegermal 26",
    "sg:city":"Wuppertal",
    "sg:phone":"+49 202/61001",
    "sg:postcode":"42399",
    "sg:province":"Nordrhein-Westfalen",
    "wof:name":"Ev. Pfarramt Beyenburg",
    "wof:placetype":"venue"
},
  "geometry": {"coordinates":[7.2924561501,51.2484664917],"type":"Point"}
}