{
  "type": "Feature",
  "properties": {
    "iso:country":"DE",
    "sg:address":"Schiffenberger Weg 72",
    "sg:city":"Gie\u00dfen",
    "sg:phone":"+49 641/979080",
    "sg:postcode":"35394",
    "sg:province":"Hessen",
    "wof:name":"St\u00f6rmer & Hahn",
    "wof:placetype":"venue"
},
  "geometry": {"coordinates":[8.6866283417,50.5733985901],"type":"Point"}
}