{
  "type": "Feature",
  "properties": {
    "iso:country":"DE",
    "sg:address":"Rathausstr. 1",
    "sg:city":"Eschenburg",
    "sg:phone":"+49 2774/1604",
    "sg:postcode":"35713",
    "sg:province":"Hessen",
    "wof:name":"Karl-heinz Weil",
    "wof:placetype":"venue"
},
  "geometry": {"coordinates":[8.339953,50.812881],"type":"Point"}
}