{
  "type": "Feature",
  "properties": {
    "iso:country":"DE",
    "sg:address":"Zeitzer Str. 31",
    "sg:city":"Altenburg",
    "sg:phone":"+49 3447/311831",
    "sg:postcode":"04600",
    "sg:province":"Th\u00fcringen",
    "wof:name":"Irmgard Saupe",
    "wof:placetype":"venue"
},
  "geometry": {"coordinates":[12.4268093109,50.9888267517],"type":"Point"}
}