{
  "type": "Feature",
  "properties": {
    "iso:country":"DE",
    "sg:address":"Ostbahnstr. 10",
    "sg:city":"Landau-Pfalz",
    "sg:phone":"+49 4979/315950",
    "sg:postcode":"76829",
    "sg:province":"Rheinland-Pfalz",
    "wof:name":"Sparkasse Tauberfranken",
    "wof:placetype":"venue"
},
  "geometry": {"coordinates":[9.774052,49.492943],"type":"Point"}
}