{
  "type": "Feature",
  "properties": {
    "iso:country":"DE",
    "sg:address":"Kilianstr. 118-122",
    "sg:city":"N\u00fcrnberg",
    "sg:phone":"+49 911/93530",
    "sg:postcode":"90425",
    "sg:province":"Bayern",
    "wof:name":"August Und Jean Hilpert Gmbh & Co.",
    "wof:placetype":"venue"
},
  "geometry": {"coordinates":[11.080222,49.473759],"type":"Point"}
}