{
  "type": "Feature",
  "properties": {
    "iso:country":"DE",
    "sg:address":"Hainburgstr. 25",
    "sg:city":"Rodgau",
    "sg:phone":"+49 6106/886966",
    "sg:postcode":"63110",
    "sg:province":"Hessen",
    "wof:name":"Oliver Heinze",
    "wof:placetype":"venue"
},
  "geometry": {"coordinates":[8.8773288727,49.9975547791],"type":"Point"}
}