{
  "type": "Feature",
  "properties": {
    "iso:country":"DE",
    "sg:address":"Flachter Str. 10",
    "sg:city":"Stuttgart",
    "sg:phone":"+49 711/221175",
    "sg:postcode":"70499",
    "sg:province":"Baden-W\u00fcrttemberg",
    "wof:name":"Donat Gmbh",
    "wof:placetype":"venue"
},
  "geometry": {"coordinates":[9.103938,48.82019],"type":"Point"}
}