{
  "type": "Feature",
  "properties": {
    "iso:country":"DE",
    "sg:address":"Steinenbergstr. 17",
    "sg:city":"Kirn",
    "sg:phone":"+49 6752/8048",
    "sg:postcode":"55606",
    "sg:province":"Rheinland-Pfalz",
    "wof:name":"Bodo Schmidt",
    "wof:placetype":"venue"
},
  "geometry": {"coordinates":[7.4621810913,49.7989311218],"type":"Point"}
}