{
  "type": "Feature",
  "properties": {
    "iso:country":"DE",
    "sg:address":"Birkenstr. 7",
    "sg:city":"Poxdorf",
    "sg:phone":"+49 9133/3103",
    "sg:postcode":"91099",
    "sg:province":"Bayern",
    "wof:name":"Schr\u00f6der-meisberger",
    "wof:placetype":"venue"
},
  "geometry": {"coordinates":[11.068945,49.66116],"type":"Point"}
}