{
  "type": "Feature",
  "properties": {
    "iso:country":"DE",
    "sg:address":"Dreieichstr. 17",
    "sg:city":"Obertshausen",
    "sg:phone":"+49 6104/71675",
    "sg:postcode":"63179",
    "sg:province":"Hessen",
    "wof:name":"Heinrich Heil",
    "wof:placetype":"venue"
},
  "geometry": {"coordinates":[8.8610334396,50.0794143677],"type":"Point"}
}