{
  "type": "Feature",
  "properties": {
    "iso:country":"DE",
    "sg:address":"Beethovenstr. 3",
    "sg:city":"Pfalzgrafenweiler",
    "sg:phone":"+49 7445/2779",
    "sg:postcode":"72285",
    "sg:province":"Baden-W\u00fcrttemberg",
    "wof:name":"Ev. Pfarramt Ii",
    "wof:placetype":"venue"
},
  "geometry": {"coordinates":[8.5689105988,48.5243492126],"type":"Point"}
}