{
  "type": "Feature",
  "properties": {
    "iso:country":"DE",
    "sg:address":"Oberweg 59",
    "sg:city":"Frankfurt",
    "sg:phone":"+49 69/441030",
    "sg:postcode":"60318",
    "sg:province":"Hessen",
    "wof:name":"Margot G\u00e4rtner",
    "wof:placetype":"venue"
},
  "geometry": {"coordinates":[8.681079,50.12225],"type":"Point"}
}