{
  "type": "Feature",
  "properties": {
    "iso:country":"DE",
    "sg:address":"Brunnenstr. 22",
    "sg:city":"Malente",
    "sg:phone":"+49 4523/988861",
    "sg:postcode":"23714",
    "sg:province":"Schleswig-Holstein",
    "wof:name":"Brunnen-hotel",
    "wof:placetype":"venue"
},
  "geometry": {"coordinates":[10.5504865646,54.1733665466],"type":"Point"}
}