{
  "type": "Feature",
  "properties": {
    "iso:country":"DE",
    "sg:address":"Kallenberg 2",
    "sg:city":"Wermelskirchen",
    "sg:phone":"+49 2196/93726",
    "sg:postcode":"42929",
    "sg:province":"Nordrhein-Westfalen",
    "wof:name":"Joachim Delan",
    "wof:placetype":"venue"
},
  "geometry": {"coordinates":[7.250871,51.143261],"type":"Point"}
}