{
  "type": "Feature",
  "properties": {
    "iso:country":"DE",
    "sg:address":"Christoph-Reich-Weg 2",
    "sg:city":"Hersbruck",
    "sg:phone":"+49 9151/3404",
    "sg:postcode":"91217",
    "sg:province":"Bayern",
    "wof:name":"W. Ziegler",
    "wof:placetype":"venue"
},
  "geometry": {"coordinates":[11.4273328781,49.506111145],"type":"Point"}
}