{
  "type": "Feature",
  "properties": {
    "iso:country":"DE",
    "sg:address":"Nerobergstr. 1",
    "sg:city":"Mainz",
    "sg:phone":"+49 6131/62060",
    "sg:postcode":"55120",
    "sg:province":"Rheinland-Pfalz",
    "wof:name":"Mit Gesellschaft F\u00fcr Geowissenschaftliche",
    "wof:placetype":"venue"
},
  "geometry": {"coordinates":[8.2219629288,50.0230369568],"type":"Point"}
}