{
  "type": "Feature",
  "properties": {
    "iso:country":"DE",
    "sg:address":"K\u00f6nigsturmstr. 21",
    "sg:city":"Schw\u00e4bisch Gm\u00fcnd",
    "sg:phone":"+49 7171/62195",
    "sg:postcode":"73525",
    "sg:province":"Baden-W\u00fcrttemberg",
    "wof:name":"Klaus Micklitz Werbeagentur Inh. Ellen Micklitz",
    "wof:placetype":"venue"
},
  "geometry": {"coordinates":[9.8009519577,48.7990646362],"type":"Point"}
}