{
  "type": "Feature",
  "properties": {
    "iso:country":"DE",
    "sg:address":"Auf dem Ritter 1-9",
    "sg:city":"Schauenburg",
    "sg:phone":"+49 5601/93200",
    "sg:postcode":"34270",
    "sg:province":"Hessen",
    "wof:name":"Ame Cp Gmbh",
    "wof:placetype":"venue"
},
  "geometry": {"coordinates":[9.3427648544,51.288646698],"type":"Point"}
}