{
  "type": "Feature",
  "properties": {
    "iso:country":"DE",
    "sg:address":"\u00c4u\u00dfere Sulzbacher Str. 88",
    "sg:city":"N\u00fcrnberg",
    "sg:phone":"+49 911/5988905",
    "sg:postcode":"90491",
    "sg:province":"Bayern",
    "wof:name":"Allgemeine H\u00e4usliche Senioren- U. Krankenbetreuung",
    "wof:placetype":"venue"
},
  "geometry": {"coordinates":[11.114539,49.462414],"type":"Point"}
}