{
  "type": "Feature",
  "properties": {
    "iso:country":"DE",
    "sg:address":"Richard-Wagner-Str. 13",
    "sg:city":"Leipzig",
    "sg:phone":"+49 341/2110999",
    "sg:postcode":"04109",
    "sg:province":"Sachsen",
    "wof:name":"Lipsia Tours International",
    "wof:placetype":"venue"
},
  "geometry": {"coordinates":[12.3762645721,51.3438110352],"type":"Point"}
}