{
  "type": "Feature",
  "properties": {
    "iso:country":"DE",
    "sg:address":"Arzlohe 2",
    "sg:city":"Pommelsbrunn",
    "sg:phone":"+49 9154/1218",
    "sg:postcode":"91224",
    "sg:province":"Bayern",
    "wof:name":"Zur Waldesruh",
    "wof:placetype":"venue"
},
  "geometry": {"coordinates":[11.5150575638,49.4878082275],"type":"Point"}
}