{
  "type": "Feature",
  "properties": {
    "iso:country":"DE",
    "sg:address":"Mittelstr. 24",
    "sg:city":"Gro\u00dfmaischeid",
    "sg:postcode":"56276",
    "sg:province":"Rheinland-Pfalz",
    "wof:name":"L & W Werbedruck Gmbh",
    "wof:placetype":"venue"
},
  "geometry": {"coordinates":[7.6360321045,50.5056037903],"type":"Point"}
}