{
  "type": "Feature",
  "properties": {
    "iso:country":"DE",
    "sg:address":"Hans-Sachs-Str 19",
    "sg:city":"Hilden",
    "sg:phone":"+49 2103/907880",
    "sg:postcode":"40721",
    "sg:province":"Nordrhein-Westfalen",
    "wof:name":"Europal - Packaging",
    "wof:placetype":"venue"
},
  "geometry": {"coordinates":[6.91753,51.1749],"type":"Point"}
}