{
  "type": "Feature",
  "properties": {
    "iso:country":"DE",
    "sg:address":"Pastor-V\u00f6mel-Str. 30",
    "sg:city":"Haan",
    "sg:phone":"+49 2104/969563",
    "sg:postcode":"42781",
    "sg:province":"Nordrhein-Westfalen",
    "wof:name":"Wiedenhof",
    "wof:placetype":"venue"
},
  "geometry": {"coordinates":[7.0090298653,51.2267532349],"type":"Point"}
}