{
  "type": "Feature",
  "properties": {
    "iso:country":"DE",
    "sg:address":"Ringstr. 7",
    "sg:city":"Duchroth",
    "sg:phone":"+49 6755/1452",
    "sg:postcode":"55585",
    "sg:province":"Rheinland-Pfalz",
    "wof:name":"Roland Und Monika Euler",
    "wof:placetype":"venue"
},
  "geometry": {"coordinates":[7.7407169342,49.7848968506],"type":"Point"}
}