{
  "type": "Feature",
  "properties": {
    "iso:country":"DE",
    "sg:address":"M\u00fcllerstr. 30",
    "sg:city":"Berlin",
    "sg:postcode":"13353",
    "sg:province":"Berlin",
    "wof:name":"D2-shop",
    "wof:placetype":"venue"
},
  "geometry": {"coordinates":[13.3574228287,52.547618866],"type":"Point"}
}