{
  "type": "Feature",
  "properties": {
    "iso:country":"DE",
    "sg:address":"Bergstr. 36",
    "sg:city":"Borchen",
    "sg:phone":"+49 5251/391521",
    "sg:postcode":"33178",
    "sg:province":"Nordrhein-Westfalen",
    "wof:name":"Franz W. Fretter",
    "wof:placetype":"venue"
},
  "geometry": {"coordinates":[8.695201,51.653103],"type":"Point"}
}