{
  "type": "Feature",
  "properties": {
    "iso:country":"DE",
    "sg:address":"Schwarzmaierstr. 37",
    "sg:city":"Grafenau",
    "sg:phone":"+49 8552/1389",
    "sg:postcode":"94481",
    "sg:province":"Bayern",
    "wof:name":"Eos-presse Sommerfeld Spezialdruckerei",
    "wof:placetype":"venue"
},
  "geometry": {"coordinates":[13.3919658661,48.8594512939],"type":"Point"}
}