{
  "type": "Feature",
  "properties": {
    "iso:country":"DE",
    "sg:address":"St.-Ingberter-Str. 15",
    "sg:city":"St. Ingbert",
    "sg:phone":"+49 6894/53333",
    "sg:postcode":"66386",
    "sg:province":"Saarland",
    "wof:name":"Brigitte Baldauf Masseurin",
    "wof:placetype":"venue"
},
  "geometry": {"coordinates":[7.139236,49.267113],"type":"Point"}
}