{
  "type": "Feature",
  "properties": {
    "iso:country":"DE",
    "sg:address":"Im Westfeld 5",
    "sg:city":"Olsberg",
    "sg:phone":"+49 2962/9840",
    "sg:postcode":"59939",
    "sg:province":"Nordrhein-Westfalen",
    "wof:name":"Carls-aue Fenster- Und Bauelemente Werk",
    "wof:placetype":"venue"
},
  "geometry": {"coordinates":[8.4969587326,51.3121452332],"type":"Point"}
}