{
  "type": "Feature",
  "properties": {
    "iso:country":"DE",
    "sg:address":"Schillerstr. 9a",
    "sg:city":"Vilshofen",
    "sg:postcode":"94474",
    "sg:province":"Bayern",
    "wof:name":"Pol-print Beteiligungs-gmbh",
    "wof:placetype":"venue"
},
  "geometry": {"coordinates":[13.1946763992,48.593547821],"type":"Point"}
}