{
  "type": "Feature",
  "properties": {
    "iso:country":"DE",
    "sg:address":"Wiesenweg 3",
    "sg:city":"Domnitz",
    "sg:phone":"+49 34603/20431",
    "sg:postcode":"06420",
    "sg:province":"Sachsen-Anhalt",
    "wof:name":"Prof. Dr. Med. K.-l. Schober",
    "wof:placetype":"venue"
},
  "geometry": {"coordinates":[11.84176,51.62999],"type":"Point"}
}