{
  "type": "Feature",
  "properties": {
    "iso:country":"DE",
    "sg:address":"Hahnenweg 5",
    "sg:city":"Schnaittach",
    "sg:postcode":"91220",
    "sg:province":"Bayern",
    "wof:name":"Armada Yaching Ag",
    "wof:placetype":"venue"
},
  "geometry": {"coordinates":[11.3447818756,49.5652885437],"type":"Point"}
}