{
  "type": "Feature",
  "properties": {
    "iso:country":"DE",
    "sg:address":"Barbarastr. 8",
    "sg:city":"W\u00fcrzburg",
    "sg:phone":"+49 931/7841903",
    "sg:postcode":"97074",
    "sg:province":"Bayern",
    "wof:name":"Wing Tsun Schulen Wt Selbstverteidigung",
    "wof:placetype":"venue"
},
  "geometry": {"coordinates":[9.9541769028,49.7961082458],"type":"Point"}
}