{
  "type": "Feature",
  "properties": {
    "iso:country":"DE",
    "sg:address":"M\u00fclheimer Str. 226",
    "sg:city":"Bergisch Gladbach",
    "sg:phone":"+49 2202/55229",
    "sg:postcode":"51469",
    "sg:province":"Nordrhein-Westfalen",
    "wof:name":"B\u00fcscher",
    "wof:placetype":"venue"
},
  "geometry": {"coordinates":[7.114498,50.98391],"type":"Point"}
}