{
  "type": "Feature",
  "properties": {
    "iso:country":"DE",
    "sg:address":"H\u00e4hnlehofstr. 104",
    "sg:city":"Weingarten",
    "sg:phone":"+49 751/44871",
    "sg:postcode":"88250",
    "sg:province":"Baden-W\u00fcrttemberg",
    "wof:name":"P. Isser",
    "wof:placetype":"venue"
},
  "geometry": {"coordinates":[9.6268520355,47.8106575012],"type":"Point"}
}