{
  "type": "Feature",
  "properties": {
    "iso:country":"DE",
    "sg:address":"Kafkastr. 31",
    "sg:city":"Bielefeld",
    "sg:phone":"+49 521/391363",
    "sg:postcode":"33729",
    "sg:province":"Nordrhein-Westfalen",
    "wof:name":"Hans-dieter Grimm",
    "wof:placetype":"venue"
},
  "geometry": {"coordinates":[8.640409,52.047043],"type":"Point"}
}