{
  "type": "Feature",
  "properties": {
    "iso:country":"DE",
    "sg:address":"Wiesentalstr 18",
    "sg:city":"Aalen",
    "sg:phone":"+49 7361/43048",
    "sg:postcode":"73434",
    "sg:province":"Baden-W\u00fcrttemberg",
    "wof:name":"Hans Baumann",
    "wof:placetype":"venue"
},
  "geometry": {"coordinates":[10.05279,48.85553],"type":"Point"}
}