{
  "type": "Feature",
  "properties": {
    "iso:country":"DE",
    "sg:address":"Burgstr. 19",
    "sg:city":"Solingen",
    "sg:phone":"+49 212/205795",
    "sg:postcode":"42655",
    "sg:province":"Nordrhein-Westfalen",
    "wof:name":"H. Bemboom",
    "wof:placetype":"venue"
},
  "geometry": {"coordinates":[7.0812301636,51.1779632568],"type":"Point"}
}