{
  "type": "Feature",
  "properties": {
    "iso:country":"DE",
    "sg:address":"Birkenstra\u00dfe 48/49",
    "sg:city":"Bremen",
    "sg:phone":"+49 4942/1169960",
    "sg:postcode":"28195",
    "sg:province":"Bremen",
    "wof:name":"Africa-consult-gmbh",
    "wof:placetype":"venue"
},
  "geometry": {"coordinates":[8.807875,53.081993],"type":"Point"}
}