{
  "type": "Feature",
  "properties": {
    "iso:country":"DE",
    "sg:address":"Lindenstr. 32",
    "sg:city":"Kropst\u00e4dt",
    "sg:postcode":"06895",
    "sg:province":"Sachsen-Anhalt",
    "wof:name":"Verm\u00f6gensverwaltungs-gmbh",
    "wof:placetype":"venue"
},
  "geometry": {"coordinates":[12.744893074,51.967124939],"type":"Point"}
}