{
  "type": "Feature",
  "properties": {
    "iso:country":"DE",
    "sg:address":"Lerchenfeldstr. 11",
    "sg:city":"M\u00fcnchen",
    "sg:postcode":"80538",
    "sg:province":"Bayern",
    "wof:name":"Thiel",
    "wof:placetype":"venue"
},
  "geometry": {"coordinates":[11.5931253433,48.1467514038],"type":"Point"}
}