{
  "type": "Feature",
  "properties": {
    "iso:country":"DE",
    "sg:address":"Hartensteiner Str. 10",
    "sg:city":"Schneeberg",
    "sg:phone":"+49 3772/28143",
    "sg:postcode":"08289",
    "sg:province":"Sachsen",
    "wof:name":"M\u00fcller & Kula",
    "wof:placetype":"venue"
},
  "geometry": {"coordinates":[12.640897,50.599232],"type":"Point"}
}