{
  "type": "Feature",
  "properties": {
    "iso:country":"DE",
    "sg:address":"Iglinger Str. 64",
    "sg:city":"Kaufering",
    "sg:phone":"+49 8191/7310",
    "sg:postcode":"86916",
    "sg:province":"Bayern",
    "wof:name":"Lech-beton Xaver Riebel Gmbh & Co. Kg",
    "wof:placetype":"venue"
},
  "geometry": {"coordinates":[10.8478498459,48.0816116333],"type":"Point"}
}