{
  "type": "Feature",
  "properties": {
    "iso:country":"DE",
    "sg:address":"Yorckstr. 21",
    "sg:city":"Mittenwalde",
    "sg:phone":"+49 33764/20309",
    "sg:postcode":"15749",
    "sg:province":"Brandenburg",
    "wof:name":"Erich Rattmann",
    "wof:placetype":"venue"
},
  "geometry": {"coordinates":[13.5363988876,52.2635307312],"type":"Point"}
}