{
  "type": "Feature",
  "properties": {
    "iso:country":"DE",
    "sg:address":"Westring 24",
    "sg:city":"Landau",
    "sg:phone":"+49 6341/80454",
    "sg:postcode":"76829",
    "sg:province":"Rheinland-Pfalz",
    "wof:name":"Schilder-reeg Inh. B. Reeg",
    "wof:placetype":"venue"
},
  "geometry": {"coordinates":[8.109256,49.194969],"type":"Point"}
}