{
  "type": "Feature",
  "properties": {
    "iso:country":"DE",
    "sg:address":"Wendelsweg 49",
    "sg:city":"Frankfurt",
    "sg:phone":"+49 69/626792",
    "sg:postcode":"60599",
    "sg:province":"Hessen",
    "wof:name":"Hans-joachim Lorenz Architekt",
    "wof:placetype":"venue"
},
  "geometry": {"coordinates":[8.695951,50.099232],"type":"Point"}
}