{
  "type": "Feature",
  "properties": {
    "iso:country":"DE",
    "sg:address":"Rohrbacher Str. 38",
    "sg:city":"Heidelberg",
    "sg:phone":"+49 6221/161097",
    "sg:postcode":"69115",
    "sg:province":"Baden-W\u00fcrttemberg",
    "wof:name":"Hsg Treuhand Heidelberg Gmbh",
    "wof:placetype":"venue"
},
  "geometry": {"coordinates":[8.6920146942,49.404094696],"type":"Point"}
}