{
  "type": "Feature",
  "properties": {
    "iso:country":"DE",
    "sg:address":"Am Wiesenhang 20",
    "sg:city":"Rostock",
    "sg:phone":"+49 381/6002565",
    "sg:postcode":"18147",
    "sg:province":"Mecklenburg-Vorpommern",
    "wof:name":"Hus An De See",
    "wof:placetype":"venue"
},
  "geometry": {"coordinates":[12.123034,54.101982],"type":"Point"}
}