{
  "type": "Feature",
  "properties": {
    "iso:country":"DE",
    "sg:address":"Kaiserstr. 55",
    "sg:city":"Bruchsal",
    "sg:phone":"+49 7251/84333",
    "sg:postcode":"76646",
    "sg:province":"Baden-W\u00fcrttemberg",
    "wof:name":"Pfaff N\u00e4hzentrum",
    "wof:placetype":"venue"
},
  "geometry": {"coordinates":[8.5972795486,49.1254692078],"type":"Point"}
}