{
  "type": "Feature",
  "properties": {
    "iso:country":"DE",
    "sg:address":"Hauptstr. 18",
    "sg:city":"Kandern",
    "sg:phone":"+49 7626/7029",
    "sg:postcode":"79400",
    "sg:province":"Baden-W\u00fcrttemberg",
    "wof:name":"Sweg-s\u00fcdwestdeutsche Verkehrs Ag",
    "wof:placetype":"venue"
},
  "geometry": {"coordinates":[7.6609559059,47.7142448425],"type":"Point"}
}