{
  "type": "Feature",
  "properties": {
    "iso:country":"DE",
    "sg:address":"G\u00f6xer Weg 21",
    "sg:city":"L\u00fcneburg",
    "sg:phone":"+49 4131/51122",
    "sg:postcode":"21337",
    "sg:province":"Niedersachsen",
    "wof:name":"Erich L\u00fcneburg",
    "wof:placetype":"venue"
},
  "geometry": {"coordinates":[10.431475,53.236038],"type":"Point"}
}