{
  "type": "Feature",
  "properties": {
    "iso:country":"DE",
    "sg:address":"Anton-Graff-Str. 17a",
    "sg:city":"Dresden",
    "sg:postcode":"01309",
    "sg:province":"Sachsen",
    "wof:name":"Ingrid Zeisberg",
    "wof:placetype":"venue"
},
  "geometry": {"coordinates":[13.7719459534,51.0447006226],"type":"Point"}
}