{
  "type": "Feature",
  "properties": {
    "iso:country":"DE",
    "sg:address":"Sandstr. 98",
    "sg:city":"Bergheim",
    "sg:phone":"+49 2271/95094",
    "sg:postcode":"50127",
    "sg:province":"Nordrhein-Westfalen",
    "wof:name":"Sitra Transport Gmbh",
    "wof:placetype":"venue"
},
  "geometry": {"coordinates":[6.6924982071,50.9336891174],"type":"Point"}
}