{
  "type": "Feature",
  "properties": {
    "iso:country":"DE",
    "sg:address":"Jakobstr. 132",
    "sg:city":"Aachen",
    "sg:phone":"+49 241/408362",
    "sg:postcode":"52064",
    "sg:province":"Nordrhein-Westfalen",
    "wof:name":"Gastst\u00e4tte Jakobssch\u00e4nke",
    "wof:placetype":"venue"
},
  "geometry": {"coordinates":[6.0768318176,50.7724456787],"type":"Point"}
}