{
  "type": "Feature",
  "properties": {
    "iso:country":"DE",
    "sg:address":"Im Felde 2",
    "sg:city":"Osnabr\u00fcck",
    "sg:phone":"+49 541/22299",
    "sg:postcode":"49076",
    "sg:province":"Niedersachsen",
    "wof:name":"S. H. U. L. Z. E. S Baguette Und Ice",
    "wof:placetype":"venue"
},
  "geometry": {"coordinates":[7.9479970932,52.2825546265],"type":"Point"}
}