{
  "type": "Feature",
  "properties": {
    "iso:country":"DE",
    "sg:address":"Bernburger Str. 26",
    "sg:city":"Sta\u00dffurt",
    "sg:phone":"+49 3925/303913",
    "sg:postcode":"39418",
    "sg:province":"Sachsen-Anhalt",
    "wof:name":"P & C Ausbau Gmbh",
    "wof:placetype":"venue"
},
  "geometry": {"coordinates":[11.594239,51.846317],"type":"Point"}
}