{
  "type": "Feature",
  "properties": {
    "iso:country":"DE",
    "sg:address":"Abts\u00e4ckerstr 11",
    "sg:city":"Ellhofen",
    "sg:phone":"+49 7134/916820",
    "sg:postcode":"74248",
    "sg:province":"Baden-W\u00fcrttemberg",
    "wof:name":"Bbk Kunststofftechnik Gmbh U. Co. Kg",
    "wof:placetype":"venue"
},
  "geometry": {"coordinates":[9.306861,49.152214],"type":"Point"}
}