{
  "type": "Feature",
  "properties": {
    "iso:country":"DE",
    "sg:address":"G\u00fcntterstr. 16",
    "sg:city":"Marbach",
    "sg:phone":"+49 7144/97580",
    "sg:postcode":"71672",
    "sg:province":"Baden-W\u00fcrttemberg",
    "wof:name":"Angele Gmbh & Co. Kg",
    "wof:placetype":"venue"
},
  "geometry": {"coordinates":[9.2622089386,48.9403038025],"type":"Point"}
}