{
  "type": "Feature",
  "properties": {
    "iso:country":"DE",
    "sg:address":"Durlacher Str. 63",
    "sg:city":"Bruchsal",
    "sg:phone":"+49 7251/18383",
    "sg:postcode":"76646",
    "sg:province":"Baden-W\u00fcrttemberg",
    "wof:name":"Maria-theresia Futterer",
    "wof:placetype":"venue"
},
  "geometry": {"coordinates":[8.59504,49.121143],"type":"Point"}
}