{
  "type": "Feature",
  "properties": {
    "iso:country":"DE",
    "sg:address":"Friedrich-Schiller-Str. 38",
    "sg:city":"Belzig",
    "sg:phone":"+49 33841/8191",
    "sg:postcode":"14806",
    "sg:province":"Brandenburg",
    "wof:name":"Rft Radio-television Brandenburg Gmbh",
    "wof:placetype":"venue"
},
  "geometry": {"coordinates":[12.6042089462,52.1389465332],"type":"Point"}
}