{
  "type": "Feature",
  "properties": {
    "iso:country":"DE",
    "sg:address":"Hauptstr. 36",
    "sg:city":"Wolkramshausen",
    "sg:phone":"+49 36334/53387",
    "sg:postcode":"99735",
    "sg:province":"Th\u00fcringen",
    "wof:name":"Helmut Thiemroth",
    "wof:placetype":"venue"
},
  "geometry": {"coordinates":[10.7393274307,51.4232635498],"type":"Point"}
}