{
  "type": "Feature",
  "properties": {
    "iso:country":"DE",
    "sg:address":"Obere Seestr. 11",
    "sg:city":"Langenargen",
    "sg:phone":"+49 7543/912792",
    "sg:postcode":"88085",
    "sg:province":"Baden-W\u00fcrttemberg",
    "wof:name":"Rehbeck Moden Renate Rehbeck",
    "wof:placetype":"venue"
},
  "geometry": {"coordinates":[9.540525,47.596241],"type":"Point"}
}