{
  "type": "Feature",
  "properties": {
    "iso:country":"DE",
    "sg:address":"Neumattenweg 11",
    "sg:city":"Feldberg",
    "sg:phone":"+49 7655/562",
    "sg:postcode":"79868",
    "sg:province":"Baden-W\u00fcrttemberg",
    "wof:name":"A. Kalker",
    "wof:placetype":"venue"
},
  "geometry": {"coordinates":[8.0364284515,47.8596343994],"type":"Point"}
}