{
  "type": "Feature",
  "properties": {
    "iso:country":"DE",
    "sg:address":"Schweinheimer Str. 35",
    "sg:city":"K\u00f6ln",
    "sg:phone":"+49 221/697119",
    "sg:postcode":"51067",
    "sg:province":"Nordrhein-Westfalen",
    "wof:name":"Ernst Bursch",
    "wof:placetype":"venue"
},
  "geometry": {"coordinates":[7.047752,50.967709],"type":"Point"}
}