{
  "type": "Feature",
  "properties": {
    "iso:country":"DE",
    "sg:address":"Husemannstr. 21",
    "sg:city":"Gelsenkirchen",
    "sg:phone":"+49 209/206441",
    "sg:postcode":"45879",
    "sg:province":"Nordrhein-Westfalen",
    "wof:name":"Teppich Steinb\u00fcchel Gmbh",
    "wof:placetype":"venue"
},
  "geometry": {"coordinates":[7.099023819,51.5063438416],"type":"Point"}
}