{
  "type": "Feature",
  "properties": {
    "iso:country":"DE",
    "sg:address":"Br\u00fcckelstr. 45-47",
    "sg:city":"Duisburg",
    "sg:phone":"+49 203/424615",
    "sg:postcode":"47137",
    "sg:province":"Nordrhein-Westfalen",
    "wof:name":"K\u00fcchenforum R\u00fcsen-b\u00f6rner Gmbh",
    "wof:placetype":"venue"
},
  "geometry": {"coordinates":[6.7825088501,51.4727859497],"type":"Point"}
}