{
  "type": "Feature",
  "properties": {
    "iso:country":"DE",
    "sg:address":"Reinsburgstr. 35",
    "sg:city":"Stuttgart",
    "sg:phone":"+49 711/618314",
    "sg:postcode":"70178",
    "sg:province":"Baden-W\u00fcrttemberg",
    "wof:name":"Roland V\u00f6hringer Ingenieur",
    "wof:placetype":"venue"
},
  "geometry": {"coordinates":[9.1651277542,48.7698020935],"type":"Point"}
}