{
  "type": "Feature",
  "properties": {
    "iso:country":"DE",
    "sg:address":"Mainzer Str. 15",
    "sg:city":"Wiesbaden",
    "sg:postcode":"65185",
    "sg:province":"Hessen",
    "wof:name":"Harbinger Gmbh",
    "wof:placetype":"venue"
},
  "geometry": {"coordinates":[8.247897,50.07663],"type":"Point"}
}