{
  "type": "Feature",
  "properties": {
    "iso:country":"DE",
    "sg:address":"P\u00fctzgasse 6",
    "sg:city":"Bad Neuenahr-Ahrweiler",
    "sg:phone":"+49 2641/37584",
    "sg:postcode":"53474",
    "sg:province":"Rheinland-Pfalz",
    "wof:name":"Walscheid",
    "wof:placetype":"venue"
},
  "geometry": {"coordinates":[7.078745,50.530415],"type":"Point"}
}