{
  "type": "Feature",
  "properties": {
    "iso:country":"DE",
    "sg:address":"Alt Erlenbach 200",
    "sg:city":"Frankfurt",
    "sg:phone":"+49 6101/54580",
    "sg:postcode":"60437",
    "sg:province":"Hessen",
    "wof:name":"Hans-l. Schuch",
    "wof:placetype":"venue"
},
  "geometry": {"coordinates":[8.707142,50.205921],"type":"Point"}
}