{
  "type": "Feature",
  "properties": {
    "iso:country":"DE",
    "sg:address":"Broicher Str. 165",
    "sg:city":"Alsdorf",
    "sg:phone":"+49 2404/957164",
    "sg:postcode":"52477",
    "sg:province":"Nordrhein-Westfalen",
    "wof:name":"August Heese",
    "wof:placetype":"venue"
},
  "geometry": {"coordinates":[6.1595602036,50.8679389954],"type":"Point"}
}