{
  "type": "Feature",
  "properties": {
    "iso:country":"DE",
    "sg:address":"Hamburger Str. 181",
    "sg:city":"Bremen",
    "sg:phone":"+49 421/324291",
    "sg:postcode":"28205",
    "sg:province":"Bremen",
    "wof:name":"G\u00fcnther Schleff Rechtsanwalt Und Notar",
    "wof:placetype":"venue"
},
  "geometry": {"coordinates":[8.844660759,53.068611145],"type":"Point"}
}