{
  "type": "Feature",
  "properties": {
    "iso:country":"DE",
    "sg:address":"Erhartinger Str. 18",
    "sg:city":"T\u00f6ging",
    "sg:phone":"+49 8631/39997",
    "sg:postcode":"84513",
    "sg:province":"Bayern",
    "wof:name":"Bestattungsinstitut Denk Trauerhilfe Gmbh & Co. Kg",
    "wof:placetype":"venue"
},
  "geometry": {"coordinates":[12.576226,48.276592],"type":"Point"}
}