{
  "type": "Feature",
  "properties": {
    "iso:country":"DE",
    "sg:address":"Willy- Mock- Str. 2",
    "sg:city":"Marburg",
    "sg:postcode":"35037",
    "sg:province":"Hessen",
    "wof:name":"Fitness Und Fun In Der Move Sportwelt",
    "wof:placetype":"venue"
},
  "geometry": {"coordinates":[8.756473,50.795059],"type":"Point"}
}