{
  "type": "Feature",
  "properties": {
    "iso:country":"DE",
    "sg:address":"Fahrlachstr. 22",
    "sg:city":"Mannheim",
    "sg:phone":"+49 621/444031",
    "sg:postcode":"68165",
    "sg:province":"Baden-W\u00fcrttemberg",
    "wof:name":"Fgs Fleischerei Und Gastronomie Service",
    "wof:placetype":"venue"
},
  "geometry": {"coordinates":[8.4936876297,49.4704246521],"type":"Point"}
}