{
  "type": "Feature",
  "properties": {
    "iso:country":"DE",
    "sg:address":"Neuetor 23",
    "sg:city":"Sch\u00f6ningen",
    "sg:postcode":"38364",
    "sg:province":"Niedersachsen",
    "wof:name":"Birgits Buchladen Inh. Birgit Gerczak",
    "wof:placetype":"venue"
},
  "geometry": {"coordinates":[10.9676294327,52.1396484375],"type":"Point"}
}