{
  "type": "Feature",
  "properties": {
    "iso:country":"DE",
    "sg:address":"Friedrichstr. 41",
    "sg:city":"Schw\u00e4bisch Hall",
    "sg:phone":"+49 791/89021",
    "sg:postcode":"74523",
    "sg:province":"Baden-W\u00fcrttemberg",
    "wof:name":"Rolf Sauter Rechtsanwalt",
    "wof:placetype":"venue"
},
  "geometry": {"coordinates":[9.7302999496,49.1047286987],"type":"Point"}
}