{
  "type": "Feature",
  "properties": {
    "iso:country":"DE",
    "sg:address":"Hauptstr. 12",
    "sg:city":"Oberhausen-Rheinhausen",
    "sg:phone":"+49 7254/1241",
    "sg:postcode":"68794",
    "sg:province":"Baden-W\u00fcrttemberg",
    "wof:name":"Hubert Ebner",
    "wof:placetype":"venue"
},
  "geometry": {"coordinates":[8.473181,49.281311],"type":"Point"}
}