{
  "type": "Feature",
  "properties": {
    "iso:country":"DE",
    "sg:address":"Postfach 100661::",
    "sg:city":"Balingen",
    "sg:phone":"+49 451/1470",
    "sg:postcode":"72336",
    "sg:province":"Baden-W\u00fcrttemberg",
    "wof:name":"Sparkasse Zu L\u00fcbeck",
    "wof:placetype":"venue"
},
  "geometry": {"coordinates":[10.687672,53.870056],"type":"Point"}
}