{
  "type": "Feature",
  "properties": {
    "iso:country":"DE",
    "sg:address":"Auf der Eck 24",
    "sg:city":"Villingen-Schwenningen",
    "sg:phone":"+49 7721/32277",
    "sg:postcode":"78052",
    "sg:province":"Baden-W\u00fcrttemberg",
    "wof:name":"L. Peduzzi",
    "wof:placetype":"venue"
},
  "geometry": {"coordinates":[8.4145069122,48.0387878418],"type":"Point"}
}