{
  "type": "Feature",
  "properties": {
    "iso:country":"DE",
    "sg:address":"Ludwigsluster Str. 3",
    "sg:city":"Parchim",
    "sg:phone":"+49 3871/42513",
    "sg:postcode":"19370",
    "sg:province":"Mecklenburg-Vorpommern",
    "wof:name":"U. Zastrow",
    "wof:placetype":"venue"
},
  "geometry": {"coordinates":[11.8351945877,53.4290275574],"type":"Point"}
}