{
  "type": "Feature",
  "properties": {
    "iso:country":"DE",
    "sg:address":"Tholeyer Str. 53",
    "sg:city":"St. Wendel",
    "sg:phone":"+49 6851/80050",
    "sg:postcode":"66606",
    "sg:province":"Saarland",
    "wof:name":"Rainer Kuhn Werkzeug- Und Maschinenbau Gmbh",
    "wof:placetype":"venue"
},
  "geometry": {"coordinates":[7.1458182335,49.4686317444],"type":"Point"}
}