{
  "type": "Feature",
  "properties": {
    "iso:country":"DE",
    "sg:address":"Breite Str. 44",
    "sg:city":"Bad Harzburg",
    "sg:phone":"+49 5322/987268",
    "sg:postcode":"38667",
    "sg:province":"Niedersachsen",
    "wof:name":"Kleber Bau Gmbh",
    "wof:placetype":"venue"
},
  "geometry": {"coordinates":[10.5423688889,51.8786735535],"type":"Point"}
}