{
  "type": "Feature",
  "properties": {
    "iso:country":"DE",
    "sg:address":"Hagweg 28",
    "sg:city":"Sch\u00f6ntal",
    "sg:phone":"+49 7943/8013",
    "sg:postcode":"74214",
    "sg:province":"Baden-W\u00fcrttemberg",
    "wof:name":"Grammling Gmbh",
    "wof:placetype":"venue"
},
  "geometry": {"coordinates":[9.488735,49.36388],"type":"Point"}
}