{
  "type": "Feature",
  "properties": {
    "iso:country":"DE",
    "sg:address":"Hauptstr. 17",
    "sg:city":"F\u00fcrth",
    "sg:phone":"+49 6253/3159",
    "sg:postcode":"64658",
    "sg:province":"Hessen",
    "wof:name":"Seyfert & Sohn",
    "wof:placetype":"venue"
},
  "geometry": {"coordinates":[8.7797546387,49.6503448486],"type":"Point"}
}