{
  "type": "Feature",
  "properties": {
    "iso:country":"DE",
    "sg:address":"59909",
    "sg:city":"Bestwig",
    "sg:phone":"+49 2904/571",
    "sg:postcode":"59909",
    "sg:province":"Nordrhein-Westfalen",
    "wof:name":"Deutsche Bahn Ag",
    "wof:placetype":"venue"
},
  "geometry": {"coordinates":[8.4010295868,51.3347892761],"type":"Point"}
}