{
  "type": "Feature",
  "properties": {
    "iso:country":"DE",
    "sg:address":"Voltastr 16",
    "sg:city":"Bergheim",
    "sg:phone":"+49 2271/98460",
    "sg:postcode":"50129",
    "sg:province":"Nordrhein-Westfalen",
    "wof:name":"Engels",
    "wof:placetype":"venue"
},
  "geometry": {"coordinates":[6.680292,50.990643],"type":"Point"}
}