{
  "type": "Feature",
  "properties": {
    "iso:country":"DE",
    "sg:address":"M\u00f6hlenbreede 22",
    "sg:city":"Timmendorfer Strand",
    "sg:phone":"+49 4503/4684",
    "sg:postcode":"23669",
    "sg:province":"Schleswig-Holstein",
    "wof:name":"Eckard Mielke Architekt",
    "wof:placetype":"venue"
},
  "geometry": {"coordinates":[10.764413,53.992546],"type":"Point"}
}