{
  "type": "Feature",
  "properties": {
    "iso:country":"DE",
    "sg:address":"Goethestr. 1",
    "sg:city":"Herzogenrath",
    "sg:phone":"+49 2406/63818",
    "sg:postcode":"52134",
    "sg:province":"Nordrhein-Westfalen",
    "wof:name":"Josef Zentis",
    "wof:placetype":"venue"
},
  "geometry": {"coordinates":[6.12346,50.88974],"type":"Point"}
}