{
  "type": "Feature",
  "properties": {
    "iso:country":"DE",
    "sg:address":"Neulandstr. 18",
    "sg:city":"Achern",
    "sg:phone":"+49 7841/3057",
    "sg:postcode":"77855",
    "sg:province":"Baden-W\u00fcrttemberg",
    "wof:name":"Arko Pharma Vertrieb Gmbh",
    "wof:placetype":"venue"
},
  "geometry": {"coordinates":[8.0637407303,48.6376724243],"type":"Point"}
}