{
  "type": "Feature",
  "properties": {
    "iso:country":"DE",
    "sg:address":"Hauptstr. 35",
    "sg:city":"Todenb\u00fcttel",
    "sg:phone":"+49 4874/258",
    "sg:postcode":"24819",
    "sg:province":"Schleswig-Holstein",
    "wof:name":"C. Jaacks",
    "wof:placetype":"venue"
},
  "geometry": {"coordinates":[9.561143,54.129173],"type":"Point"}
}