{
  "type": "Feature",
  "properties": {
    "iso:country":"DE",
    "sg:address":"Waldenburger Str. 5",
    "sg:city":"Neutraubling",
    "sg:phone":"+49 9401/80185",
    "sg:postcode":"93073",
    "sg:province":"Bayern",
    "wof:name":"Gottfried Melcher Augenoptiker",
    "wof:placetype":"venue"
},
  "geometry": {"coordinates":[12.2002696991,48.9907112122],"type":"Point"}
}