{
  "type": "Feature",
  "properties": {
    "iso:country":"DE",
    "sg:address":"Deutschherrenstr. 12",
    "sg:city":"Waldbreitbach",
    "sg:phone":"+49 2638/5738",
    "sg:postcode":"56588",
    "sg:province":"Rheinland-Pfalz",
    "wof:name":"M. Und E. R\u00f6der Modewaren",
    "wof:placetype":"venue"
},
  "geometry": {"coordinates":[7.420654,50.551182],"type":"Point"}
}