{
  "type": "Feature",
  "properties": {
    "iso:country":"DE",
    "sg:address":"Paulistr. 10",
    "sg:city":"Erlangen",
    "sg:phone":"+49 9131/22957",
    "sg:postcode":"91054",
    "sg:province":"Bayern",
    "wof:name":"Backstage",
    "wof:placetype":"venue"
},
  "geometry": {"coordinates":[11.002195,49.598],"type":"Point"}
}