{
  "type": "Feature",
  "properties": {
    "iso:country":"DE",
    "sg:address":"Hofstr. 14",
    "sg:city":"Buchen",
    "sg:phone":"+49 6281/2599",
    "sg:postcode":"74722",
    "sg:province":"Baden-W\u00fcrttemberg",
    "wof:name":"Zidas Industrieservice Gmbh",
    "wof:placetype":"venue"
},
  "geometry": {"coordinates":[9.324499,49.520557],"type":"Point"}
}