{
  "type": "Feature",
  "properties": {
    "iso:country":"DE",
    "sg:address":"Auf der Erzgrub 15",
    "sg:city":"Altendiez",
    "sg:phone":"+49 6432/83421",
    "sg:postcode":"65624",
    "sg:province":"Rheinland-Pfalz",
    "wof:name":"Rudi Jahn Hamburg-mannheimer",
    "wof:placetype":"venue"
},
  "geometry": {"coordinates":[7.9782800674,50.3656654358],"type":"Point"}
}