{
  "type": "Feature",
  "properties": {
    "iso:country":"DE",
    "sg:address":"Dorfstr. 51",
    "sg:city":"Go\u00dfmar",
    "sg:postcode":"15926",
    "sg:province":"Brandenburg",
    "wof:name":"Agrargenossenschaft Go\u00dfmar Eg",
    "wof:placetype":"venue"
},
  "geometry": {"coordinates":[13.705565,51.850864],"type":"Point"}
}