{
  "type": "Feature",
  "properties": {
    "iso:country":"DE",
    "sg:address":"Zu den Neuen Wiesen 1",
    "sg:city":"Hohenahr",
    "sg:phone":"+49 6446/2451",
    "sg:postcode":"35644",
    "sg:province":"Hessen",
    "wof:name":"Franke",
    "wof:placetype":"venue"
},
  "geometry": {"coordinates":[8.5216808319,50.6793289185],"type":"Point"}
}