{
  "type": "Feature",
  "properties": {
    "iso:country":"DE",
    "sg:address":"Ottobeurer Str. 10",
    "sg:city":"Markt Rettenbach",
    "sg:phone":"+49 8392/220",
    "sg:postcode":"87733",
    "sg:province":"Bayern",
    "wof:name":"Marien-apotheke",
    "wof:placetype":"venue"
},
  "geometry": {"coordinates":[10.393579,47.94804],"type":"Point"}
}