{
  "type": "Feature",
  "properties": {
    "iso:country":"DE",
    "sg:address":"Pf. 14 65",
    "sg:city":"Dippoldiswalde",
    "sg:postcode":"01741",
    "sg:province":"Sachsen",
    "wof:name":"4color",
    "wof:placetype":"venue"
},
  "geometry": {"coordinates":[13.670543,50.895725],"type":"Point"}
}