{
  "type": "Feature",
  "properties": {
    "iso:country":"DE",
    "sg:address":"An der Schanz 9",
    "sg:city":"D\u00fcsseldorf",
    "sg:phone":"+49 211/404133",
    "sg:postcode":"40489",
    "sg:province":"Nordrhein-Westfalen",
    "wof:name":"Friebe Consultants Mittelstands Beratungs- Und",
    "wof:placetype":"venue"
},
  "geometry": {"coordinates":[6.7412757874,51.3240394592],"type":"Point"}
}