{
  "type": "Feature",
  "properties": {
    "iso:country":"DE",
    "sg:address":"Obere Siegfriedstr. 12",
    "sg:city":"Mossautal",
    "sg:phone":"+49 6062/63615",
    "sg:postcode":"64756",
    "sg:province":"Hessen",
    "wof:name":"Gabriele Und Joachim Bessert",
    "wof:placetype":"venue"
},
  "geometry": {"coordinates":[8.932098,49.622444],"type":"Point"}
}