{
  "type": "Feature",
  "properties": {
    "iso:country":"DE",
    "sg:address":"Hauptstr. 51",
    "sg:city":"Baesweiler",
    "sg:phone":"+49 2401/53737",
    "sg:postcode":"52499",
    "sg:province":"Nordrhein-Westfalen",
    "wof:name":"Bartholemy",
    "wof:placetype":"venue"
},
  "geometry": {"coordinates":[6.203624,50.922451],"type":"Point"}
}