{
  "type": "Feature",
  "properties": {
    "iso:country":"DE",
    "sg:address":"Zur M\u00fchle 2",
    "sg:city":"Northeim",
    "sg:phone":"+49 5551/952924",
    "sg:postcode":"37154",
    "sg:province":"Niedersachsen",
    "wof:name":"Restaurant Truck-stop",
    "wof:placetype":"venue"
},
  "geometry": {"coordinates":[9.9668550491,51.7490386963],"type":"Point"}
}