{
  "type": "Feature",
  "properties": {
    "iso:country":"DE",
    "sg:address":"Weidenhof",
    "sg:city":"W\u00e4chtersbach",
    "sg:phone":"+49 6053/2822",
    "sg:postcode":"63607",
    "sg:province":"Hessen",
    "wof:name":"Achim M\u00fcller",
    "wof:placetype":"venue"
},
  "geometry": {"coordinates":[9.313823,50.267078],"type":"Point"}
}