{
  "type": "Feature",
  "properties": {
    "iso:country":"DE",
    "sg:address":"Scharnhorststr. 38 a",
    "sg:city":"Leipzig",
    "sg:postcode":"04275",
    "sg:province":"Sachsen",
    "wof:name":"Christliche Gemeinde Koinonia Leipzig E. V.",
    "wof:placetype":"venue"
},
  "geometry": {"coordinates":[12.3805847168,51.3194389343],"type":"Point"}
}