{
  "type": "Feature",
  "properties": {
    "iso:country":"DE",
    "sg:address":"Bierstatterstr.3",
    "sg:city":"Wiesbaden",
    "sg:phone":"+49 4961/1609290",
    "sg:postcode":"65189",
    "sg:province":"Hessen",
    "wof:name":"Good News Communications Gmbh",
    "wof:placetype":"venue"
},
  "geometry": {"coordinates":[8.248262,50.080177],"type":"Point"}
}