{
  "type": "Feature",
  "properties": {
    "iso:country":"DE",
    "sg:address":"Rheineckstr. 45",
    "sg:city":"Memmingen",
    "sg:phone":"+49 8331/7580",
    "sg:postcode":"87700",
    "sg:province":"Bayern",
    "wof:name":"Diakonisches Werk E. V.",
    "wof:placetype":"venue"
},
  "geometry": {"coordinates":[10.173332,47.983448],"type":"Point"}
}