{
  "type": "Feature",
  "properties": {
    "iso:country":"DE",
    "sg:address":"Friesenring 34",
    "sg:city":"M\u00fcnster",
    "sg:phone":"+49 251/27091",
    "sg:postcode":"48147",
    "sg:province":"Nordrhein-Westfalen",
    "wof:name":"Evangelischer Arbeitskreis F\u00fcr Jugendschutz",
    "wof:placetype":"venue"
},
  "geometry": {"coordinates":[7.616932869,51.9743309021],"type":"Point"}
}