{
  "type": "Feature",
  "properties": {
    "iso:country":"DE",
    "sg:address":"Dinkelackerweg 6",
    "sg:city":"Rheinfelden",
    "sg:phone":"+49 7623/795410",
    "sg:postcode":"79618",
    "sg:province":"Baden-W\u00fcrttemberg",
    "wof:name":"Michael Hess",
    "wof:placetype":"venue"
},
  "geometry": {"coordinates":[7.78875494,47.5594482422],"type":"Point"}
}