{
  "type": "Feature",
  "properties": {
    "iso:country":"DE",
    "sg:address":"Am Wasserturm 40",
    "sg:city":"K\u00f6then",
    "sg:phone":"+49 3496/557997",
    "sg:postcode":"06366",
    "sg:province":"Sachsen-Anhalt",
    "wof:name":"Bbv Bergrechts- Besitz- Und Verwaltungsgesellschaft Mbh",
    "wof:placetype":"venue"
},
  "geometry": {"coordinates":[11.9789466858,51.7458572388],"type":"Point"}
}