{
  "type": "Feature",
  "properties": {
    "iso:country":"DE",
    "sg:address":"Forstacker 7",
    "sg:city":"R\u00f6ttenbach",
    "sg:phone":"+49 9195/7113",
    "sg:postcode":"91341",
    "sg:province":"Bayern",
    "wof:name":"Early Bird Gmbh",
    "wof:placetype":"venue"
},
  "geometry": {"coordinates":[10.9216022491,49.6633529663],"type":"Point"}
}