{
  "type": "Feature",
  "properties": {
    "iso:country":"DE",
    "sg:address":"Arnekenstr. 22",
    "sg:city":"Hildesheim",
    "sg:postcode":"31134",
    "sg:province":"Niedersachsen",
    "wof:name":"Niemz Gesch\u00e4ftsf\u00fchrungs Gmbh",
    "wof:placetype":"venue"
},
  "geometry": {"coordinates":[9.9504461288,52.1548080444],"type":"Point"}
}