{
  "type": "Feature",
  "properties": {
    "iso:country":"DE",
    "sg:address":"Genthiner Str. 11",
    "sg:city":"Halle",
    "sg:phone":"+49 345/5800044",
    "sg:postcode":"06132",
    "sg:province":"Sachsen-Anhalt",
    "wof:name":"G\u00fcnter Rodenstein Immobilienmakler",
    "wof:placetype":"venue"
},
  "geometry": {"coordinates":[11.9706773758,51.4428024292],"type":"Point"}
}