{
  "type": "Feature",
  "properties": {
    "iso:country":"DE",
    "sg:address":"Birkenweg 3",
    "sg:city":"Rain",
    "sg:phone":"+49 9090/4523",
    "sg:postcode":"86641",
    "sg:province":"Bayern",
    "wof:name":"W. Rei\u00dfner",
    "wof:placetype":"venue"
},
  "geometry": {"coordinates":[10.929055,48.684986],"type":"Point"}
}