{
  "type": "Feature",
  "properties": {
    "iso:country":"DE",
    "sg:address":"Schwarzer Weg 25",
    "sg:city":"Perleberg",
    "sg:phone":"+49 3876/788369",
    "sg:postcode":"19348",
    "sg:province":"Brandenburg",
    "wof:name":"Artschys K\u00fcchenservice",
    "wof:placetype":"venue"
},
  "geometry": {"coordinates":[11.8428812027,53.0675964355],"type":"Point"}
}