{
  "type": "Feature",
  "properties": {
    "iso:country":"DE",
    "sg:address":"Hostenbacher Str. 24",
    "sg:city":"V\u00f6lklingen",
    "sg:phone":"+49 6898/26817",
    "sg:postcode":"66333",
    "sg:province":"Saarland",
    "wof:name":"Hans Pfeiffer & Co. Gmbh",
    "wof:placetype":"venue"
},
  "geometry": {"coordinates":[6.83634,49.248676],"type":"Point"}
}