{
  "type": "Feature",
  "properties": {
    "iso:country":"DE",
    "sg:address":"Alleestr. 3",
    "sg:city":"Potsdam",
    "sg:phone":"+49 331/2800394",
    "sg:postcode":"14469",
    "sg:province":"Brandenburg",
    "wof:name":"Kommunalpolitisches Forum Land Brandenburg E. V.",
    "wof:placetype":"venue"
},
  "geometry": {"coordinates":[13.0605068207,52.409160614],"type":"Point"}
}