{
  "type": "Feature",
  "properties": {
    "iso:country":"DE",
    "sg:address":"Weberstr. 20",
    "sg:city":"Coesfeld",
    "sg:phone":"+49 2541/71249",
    "sg:postcode":"48653",
    "sg:province":"Nordrhein-Westfalen",
    "wof:name":"Fleige-stoffe Textilgro\u00dfhandel Gmbh",
    "wof:placetype":"venue"
},
  "geometry": {"coordinates":[7.17003,51.947182],"type":"Point"}
}