{
  "type": "Feature",
  "properties": {
    "iso:country":"DE",
    "sg:address":"Mainzer Str. 18",
    "sg:city":"Bischofsheim",
    "sg:phone":"+49 6144/7682",
    "sg:postcode":"65474",
    "sg:province":"Hessen",
    "wof:name":"Hans Gerbig",
    "wof:placetype":"venue"
},
  "geometry": {"coordinates":[8.352869,49.99052],"type":"Point"}
}