{
  "type": "Feature",
  "properties": {
    "iso:country":"DE",
    "sg:address":"Neckarstr. 9",
    "sg:city":"Rothenberg",
    "sg:phone":"+49 6275/340",
    "sg:postcode":"64757",
    "sg:province":"Hessen",
    "wof:name":"Gerhard Schwinn",
    "wof:placetype":"venue"
},
  "geometry": {"coordinates":[8.9022598267,49.4903831482],"type":"Point"}
}