{
  "type": "Feature",
  "properties": {
    "iso:country":"DE",
    "sg:address":"Langgasse 8",
    "sg:city":"Wiesbaden",
    "sg:phone":"+49 611/9100020",
    "sg:postcode":"65183",
    "sg:province":"Hessen",
    "wof:name":"Bonita Gmbh & Co. Kg",
    "wof:placetype":"venue"
},
  "geometry": {"coordinates":[8.238987,50.083057],"type":"Point"}
}