{
  "type": "Feature",
  "properties": {
    "iso:country":"DE",
    "sg:address":"Odilostr. 37",
    "sg:city":"Berlin",
    "sg:phone":"+49 30/40536190",
    "sg:postcode":"13467",
    "sg:province":"Berlin",
    "wof:name":"Rudolf Motza Bau- Und Handelsgesellschaft Mbh",
    "wof:placetype":"venue"
},
  "geometry": {"coordinates":[13.3051319122,52.624080658],"type":"Point"}
}