{
  "type": "Feature",
  "properties": {
    "iso:country":"DE",
    "sg:address":"Kirchgasse 76",
    "sg:city":"Wiesbaden",
    "sg:phone":"+49 611/999030",
    "sg:postcode":"65183",
    "sg:province":"Hessen",
    "wof:name":"John Silver Tours Gmbh",
    "wof:placetype":"venue"
},
  "geometry": {"coordinates":[8.2386140823,50.0825309753],"type":"Point"}
}