{
  "type": "Feature",
  "properties": {
    "iso:country":"DE",
    "sg:address":"Ruppenkampstr. 2",
    "sg:city":"Osnabr\u00fcck",
    "sg:phone":"+49 541/72906",
    "sg:postcode":"49084",
    "sg:province":"Niedersachsen",
    "wof:name":"Herbert Kopmann",
    "wof:placetype":"venue"
},
  "geometry": {"coordinates":[8.087875,52.279182],"type":"Point"}
}