{
  "type": "Feature",
  "properties": {
    "iso:country":"DE",
    "sg:address":"Wiesenstr. 11",
    "sg:city":"Chemnitz",
    "sg:phone":"+49 371/6446474",
    "sg:postcode":"09111",
    "sg:province":"Sachsen",
    "wof:name":"Eleba Elektroanlagen",
    "wof:placetype":"venue"
},
  "geometry": {"coordinates":[12.92656,50.827442],"type":"Point"}
}