{
  "type": "Feature",
  "properties": {
    "iso:country":"DE",
    "sg:address":"Friedhofstr. 23",
    "sg:city":"Sommerloch",
    "sg:phone":"+49 6706/6110",
    "sg:postcode":"55595",
    "sg:province":"Rheinland-Pfalz",
    "wof:name":"Vestner Gmbh",
    "wof:placetype":"venue"
},
  "geometry": {"coordinates":[7.758330822,49.8761405945],"type":"Point"}
}