{
  "type": "Feature",
  "properties": {
    "iso:country":"DE",
    "sg:address":"Klinkerberg 31",
    "sg:city":"Augsburg",
    "sg:phone":"+49 821/158903",
    "sg:postcode":"86152",
    "sg:province":"Bayern",
    "wof:name":"Eu-ba Reisen Export-import Gmbh",
    "wof:placetype":"venue"
},
  "geometry": {"coordinates":[10.8849334717,48.3731918335],"type":"Point"}
}