{
  "type": "Feature",
  "properties": {
    "iso:country":"DE",
    "sg:address":"Hauptstr. 2",
    "sg:city":"Herbertingen",
    "sg:phone":"+49 4975/865080",
    "sg:postcode":"88518",
    "sg:province":"Baden-W\u00fcrttemberg",
    "wof:name":"Kreissparkasse",
    "wof:placetype":"venue"
},
  "geometry": {"coordinates":[9.438045,48.060795],"type":"Point"}
}