{
  "type": "Feature",
  "properties": {
    "iso:country":"DE",
    "sg:address":"Fichtenstr 6",
    "sg:city":"Niedernhausen",
    "sg:phone":"+49 6127/1056",
    "sg:postcode":"65527",
    "sg:province":"Hessen",
    "wof:name":"Elcon Me\u00df- Und Regelanlagen Engineering Gmbh",
    "wof:placetype":"venue"
},
  "geometry": {"coordinates":[8.3113451004,50.1697502136],"type":"Point"}
}