{
  "type": "Feature",
  "properties": {
    "iso:country":"DE",
    "sg:address":"Birkigter Hang 20",
    "sg:city":"Dresden",
    "sg:phone":"+49 351/4010830",
    "sg:postcode":"01189",
    "sg:province":"Sachsen",
    "wof:name":"Paul Gmbh",
    "wof:placetype":"venue"
},
  "geometry": {"coordinates":[13.687456,51.008064],"type":"Point"}
}