{
  "type": "Feature",
  "properties": {
    "iso:country":"DE",
    "sg:address":"Industriestr 7",
    "sg:city":"Rheinbach",
    "sg:phone":"+49 2226/913300",
    "sg:postcode":"53359",
    "sg:province":"Nordrhein-Westfalen",
    "wof:name":"Westhydraulik-becker Beh\u00e4lter-, Apparate- Und Stahlbau Dresden Gmbh",
    "wof:placetype":"venue"
},
  "geometry": {"coordinates":[6.95613,50.634964],"type":"Point"}
}