{
  "type": "Feature",
  "properties": {
    "iso:country":"DE",
    "sg:address":"Nu\u00dfallee 10",
    "sg:city":"Bonn",
    "sg:phone":"+49 228/732804",
    "sg:postcode":"53115",
    "sg:province":"Nordrhein-Westfalen",
    "wof:name":"Anatomisches Institut",
    "wof:placetype":"venue"
},
  "geometry": {"coordinates":[7.0892281532,50.7267456055],"type":"Point"}
}