{
  "type": "Feature",
  "properties": {
    "iso:country":"DE",
    "sg:address":"Kurpfalzstr. 10a",
    "sg:city":"Sinsheim",
    "sg:phone":"+49 7261/979800",
    "sg:postcode":"74889",
    "sg:province":"Baden-W\u00fcrttemberg",
    "wof:name":"Darmreinigung,darmerkrankung,haarausfall,cellulite",
    "wof:placetype":"venue"
},
  "geometry": {"coordinates":[8.896856,49.252228],"type":"Point"}
}