{
  "type": "Feature",
  "properties": {
    "iso:country":"DE",
    "sg:address":"Kottenheimer Str.",
    "sg:city":"Ettringen",
    "sg:phone":"+49 2651/6854",
    "sg:postcode":"56729",
    "sg:province":"Rheinland-Pfalz",
    "wof:name":"H. Pung Steinmetzbetrieb",
    "wof:placetype":"venue"
},
  "geometry": {"coordinates":[7.2245998383,50.3599433899],"type":"Point"}
}