{
  "type": "Feature",
  "properties": {
    "iso:country":"DE",
    "sg:address":"Stresemannstr. 3-5",
    "sg:city":"Koblenz",
    "sg:phone":"+49 261/1200",
    "sg:postcode":"56068",
    "sg:province":"Rheinland-Pfalz",
    "wof:name":"Bibliothek Der Bezirksregierung Koblenz",
    "wof:placetype":"venue"
},
  "geometry": {"coordinates":[7.602381,50.357334],"type":"Point"}
}