{
  "type": "Feature",
  "properties": {
    "iso:country":"DE",
    "sg:address":"Zehnthofstr. 1",
    "sg:city":"Oestrich-Winkel",
    "sg:phone":"+49 6723/1647",
    "sg:postcode":"65375",
    "sg:province":"Hessen",
    "wof:name":"Volkmar Isinger",
    "wof:placetype":"venue"
},
  "geometry": {"coordinates":[8.02998,50.005802],"type":"Point"}
}