{
  "type": "Feature",
  "properties": {
    "iso:country":"DE",
    "sg:address":"Friesickestr. 33",
    "sg:city":"Berlin",
    "sg:postcode":"13086",
    "sg:province":"Berlin",
    "wof:name":"City Press Gmbh",
    "wof:placetype":"venue"
},
  "geometry": {"coordinates":[13.4406690598,52.5539550781],"type":"Point"}
}