{
  "type": "Feature",
  "properties": {
    "iso:country":"DE",
    "sg:address":"Johannes-Girmes-Str. 116",
    "sg:city":"Grefrath",
    "sg:phone":"+49 2158/5395",
    "sg:postcode":"47929",
    "sg:province":"Nordrhein-Westfalen",
    "wof:name":"Hans Verlinden Immobilienmakler",
    "wof:placetype":"venue"
},
  "geometry": {"coordinates":[6.3726902008,51.3338928223],"type":"Point"}
}