{
  "type": "Feature",
  "properties": {
    "iso:country":"DE",
    "sg:address":"Gottlob-Bauknecht-Str. 11",
    "sg:city":"Calw",
    "sg:phone":"+49 7051/12136",
    "sg:postcode":"75365",
    "sg:province":"Baden-W\u00fcrttemberg",
    "wof:name":"Stefan Kuhn Gmbh",
    "wof:placetype":"venue"
},
  "geometry": {"coordinates":[8.7646942139,48.7061080933],"type":"Point"}
}