{
  "type": "Feature",
  "properties": {
    "iso:country":"DE",
    "sg:address":"Kirchstr. 5",
    "sg:city":"Gersten",
    "sg:phone":"+49 5904/402",
    "sg:postcode":"49838",
    "sg:province":"Niedersachsen",
    "wof:name":"Aloys Rauen",
    "wof:placetype":"venue"
},
  "geometry": {"coordinates":[7.496083,52.570324],"type":"Point"}
}