{
  "type": "Feature",
  "properties": {
    "iso:country":"DE",
    "sg:address":"Obere Gasse 24",
    "sg:city":"Marktheidenfeld",
    "sg:postcode":"97828",
    "sg:province":"Bayern",
    "wof:name":"Sng Schiffs-neubau Generalvertretungsges. Mbh",
    "wof:placetype":"venue"
},
  "geometry": {"coordinates":[9.5988750458,49.8459396362],"type":"Point"}
}