{
  "type": "Feature",
  "properties": {
    "iso:country":"DE",
    "sg:address":"Marktgasse 2",
    "sg:city":"Oberviechtach",
    "sg:phone":"+49 9671/1539",
    "sg:postcode":"92526",
    "sg:province":"Bayern",
    "wof:name":"Weigl",
    "wof:placetype":"venue"
},
  "geometry": {"coordinates":[12.419351,49.46022],"type":"Point"}
}