{
  "type": "Feature",
  "properties": {
    "iso:country":"DE",
    "sg:address":"Siegstr. 11 a",
    "sg:city":"Wissen",
    "sg:phone":"+49 2742/72150",
    "sg:postcode":"57537",
    "sg:province":"Rheinland-Pfalz",
    "wof:name":"Ideal-imbi\u00df",
    "wof:placetype":"venue"
},
  "geometry": {"coordinates":[7.7326478958,50.7840766907],"type":"Point"}
}