{
  "type": "Feature",
  "properties": {
    "iso:country":"DE",
    "sg:address":"Richard-Wagner-Str. 49",
    "sg:city":"K\u00f6nigsbrunn",
    "sg:phone":"+49 8231/6699",
    "sg:postcode":"86343",
    "sg:province":"Bayern",
    "wof:name":"Klaus Niederhofer",
    "wof:placetype":"venue"
},
  "geometry": {"coordinates":[10.8980951309,48.2875366211],"type":"Point"}
}