{
  "type": "Feature",
  "properties": {
    "iso:country":"DE",
    "sg:address":"Dorfstr. 29",
    "sg:city":"Drelsdorf",
    "sg:phone":"+49 4671/721",
    "sg:postcode":"25853",
    "sg:province":"Schleswig-Holstein",
    "wof:name":"Der B\u00fcchergarten Antiquariat Und Buchhandlung",
    "wof:placetype":"venue"
},
  "geometry": {"coordinates":[9.0465192795,54.605178833],"type":"Point"}
}