{
  "type": "Feature",
  "properties": {
    "iso:country":"DE",
    "sg:address":"F\u00fcchsleinstr. 15",
    "sg:city":"W\u00fcrzburg",
    "sg:phone":"+49 931/2031",
    "sg:postcode":"97080",
    "sg:province":"Bayern",
    "wof:name":"Beratungsstelle Bei Der Universit\u00e4ts-nervenklinik",
    "wof:placetype":"venue"
},
  "geometry": {"coordinates":[9.9322299957,49.8044395447],"type":"Point"}
}