{
  "type": "Feature",
  "properties": {
    "iso:country":"DE",
    "sg:address":"Dorfstr. 15",
    "sg:city":"Gro\u00df Polzin",
    "sg:phone":"+49 39724/26866",
    "sg:postcode":"17390",
    "sg:province":"Mecklenburg-Vorpommern",
    "wof:name":"Bohr- Brunnen Und Umwelt- Technik Sch\u00fcler Gmbh & Co. Kg",
    "wof:placetype":"venue"
},
  "geometry": {"coordinates":[13.5926189423,53.8939361572],"type":"Point"}
}