{
  "type": "Feature",
  "properties": {
    "iso:country":"DE",
    "sg:address":"J\u00e4gerallee 28",
    "sg:city":"Potsdam",
    "sg:postcode":"14469",
    "sg:province":"Brandenburg",
    "wof:name":"Concept-bau 2000 Gmbh",
    "wof:placetype":"venue"
},
  "geometry": {"coordinates":[13.0531301498,52.4045982361],"type":"Point"}
}