{
  "type": "Feature",
  "properties": {
    "iso:country":"DE",
    "sg:address":"Lagerstr. 6",
    "sg:city":"Kr\u00f6pelin",
    "sg:phone":"+49 38292/344",
    "sg:postcode":"18236",
    "sg:province":"Mecklenburg-Vorpommern",
    "wof:name":"Dombrowski Bau Gmbh",
    "wof:placetype":"venue"
},
  "geometry": {"coordinates":[11.791486,54.068352],"type":"Point"}
}