{
  "type": "Feature",
  "properties": {
    "iso:country":"DE",
    "sg:address":"Zeppelinstr. 13",
    "sg:city":"Mahlow",
    "sg:phone":"+49 3379/39214",
    "sg:postcode":"15831",
    "sg:province":"Brandenburg",
    "wof:name":"Reinhard Rudas",
    "wof:placetype":"venue"
},
  "geometry": {"coordinates":[13.395346,52.374645],"type":"Point"}
}