{
  "type": "Feature",
  "properties": {
    "iso:country":"DE",
    "sg:address":"M\u00fcnchinger Str. 34",
    "sg:city":"Ditzingen",
    "sg:phone":"+49 7156/8309",
    "sg:postcode":"71254",
    "sg:province":"Baden-W\u00fcrttemberg",
    "wof:name":"M. J. Kecker",
    "wof:placetype":"venue"
},
  "geometry": {"coordinates":[9.0707798004,48.8285446167],"type":"Point"}
}