{
  "type": "Feature",
  "properties": {
    "iso:country":"DE",
    "sg:address":"Wispensteiner Str. 5",
    "sg:city":"Alfeld",
    "sg:phone":"+49 5181/5953",
    "sg:postcode":"31061",
    "sg:province":"Niedersachsen",
    "wof:name":"Wolfgang Meyer",
    "wof:placetype":"venue"
},
  "geometry": {"coordinates":[9.838804,51.961201],"type":"Point"}
}