{
  "type": "Feature",
  "properties": {
    "iso:country":"DE",
    "sg:address":"Adriastr. 23",
    "sg:city":"Lampertheim",
    "sg:phone":"+49 6206/52375",
    "sg:postcode":"68623",
    "sg:province":"Hessen",
    "wof:name":"Edmund Kleiser Architekt",
    "wof:placetype":"venue"
},
  "geometry": {"coordinates":[8.489828,49.586212],"type":"Point"}
}