{
  "type": "Feature",
  "properties": {
    "iso:country":"DE",
    "sg:address":"Hermann-L\u00f6ns-Str. 9",
    "sg:city":"Siegen",
    "sg:phone":"+49 271/83314",
    "sg:postcode":"57078",
    "sg:province":"Nordrhein-Westfalen",
    "wof:name":"Ewald Knebel Steuerberater",
    "wof:placetype":"venue"
},
  "geometry": {"coordinates":[7.9963102341,50.907661438],"type":"Point"}
}