{
  "type": "Feature",
  "properties": {
    "iso:country":"DE",
    "sg:address":"K\u00f6nigstra\u00dfe 53",
    "sg:city":"Duisburg",
    "sg:phone":"+49 203",
    "sg:postcode":"47051",
    "sg:province":"Nordrhein-Westfalen",
    "wof:name":"City-management Duisburg",
    "wof:placetype":"venue"
},
  "geometry": {"coordinates":[6.770761,51.432652],"type":"Point"}
}