{
  "type": "Feature",
  "properties": {
    "iso:country":"DE",
    "sg:address":"Alt-Rudow 41",
    "sg:city":"Berlin",
    "sg:phone":"+49 30/6691060",
    "sg:postcode":"12357",
    "sg:province":"Berlin",
    "wof:name":"Heinz-ulrich Fechner",
    "wof:placetype":"venue"
},
  "geometry": {"coordinates":[13.4940710068,52.4191360474],"type":"Point"}
}