{
  "type": "Feature",
  "properties": {
    "iso:country":"DE",
    "sg:address":"Am Vogelherd 22 b",
    "sg:city":"Landshut",
    "sg:phone":"+49 871/55597",
    "sg:postcode":"84028",
    "sg:province":"Bayern",
    "wof:name":"Willibald Zeilhofer Architekt",
    "wof:placetype":"venue"
},
  "geometry": {"coordinates":[12.178198,48.536251],"type":"Point"}
}