{
  "type": "Feature",
  "properties": {
    "iso:country":"DE",
    "sg:address":"Ludwigstr. 8",
    "sg:city":"Lohr",
    "sg:phone":"+49 9352/89111",
    "sg:postcode":"97816",
    "sg:province":"Bayern",
    "wof:name":"Accurat Unabh\u00e4ngige Versicherungsmakler Gmbh",
    "wof:placetype":"venue"
},
  "geometry": {"coordinates":[8.6070337296,50.6864356995],"type":"Point"}
}