{
  "type": "Feature",
  "properties": {
    "iso:country":"DE",
    "sg:address":"Chiemgaustr. 51",
    "sg:city":"Evenhausen",
    "sg:phone":"+49 8075/1339",
    "sg:postcode":"83552",
    "sg:province":"Bayern",
    "wof:name":"Alois Huber Ingenieur",
    "wof:placetype":"venue"
},
  "geometry": {"coordinates":[12.2861499786,48.0256462097],"type":"Point"}
}