{
  "type": "Feature",
  "properties": {
    "iso:country":"DE",
    "sg:address":"Rott 210",
    "sg:city":"Krefeld",
    "sg:phone":"+49 2151/505344",
    "sg:postcode":"47800",
    "sg:province":"Nordrhein-Westfalen",
    "wof:name":"K. T. Vogel",
    "wof:placetype":"venue"
},
  "geometry": {"coordinates":[6.5973658562,51.3491516113],"type":"Point"}
}