{
  "type": "Feature",
  "properties": {
    "iso:country":"DE",
    "sg:address":"Marienstr. 118",
    "sg:city":"Neuss",
    "sg:phone":"+49 2131/57537",
    "sg:postcode":"41462",
    "sg:province":"Nordrhein-Westfalen",
    "wof:name":"Reinsch Gmbh",
    "wof:placetype":"venue"
},
  "geometry": {"coordinates":[6.672517,51.203667],"type":"Point"}
}