{
  "type": "Feature",
  "properties": {
    "iso:country":"DE",
    "sg:address":"Pestalozzistr. 13",
    "sg:city":"Helbra",
    "sg:phone":"+49 34772/27255",
    "sg:postcode":"06311",
    "sg:province":"Sachsen-Anhalt",
    "wof:name":"Hotel-restaurant Zum Rautenkranz",
    "wof:placetype":"venue"
},
  "geometry": {"coordinates":[11.492893219,51.5572357178],"type":"Point"}
}