{
  "type": "Feature",
  "properties": {
    "iso:country":"DE",
    "sg:address":"Masurenweg 8",
    "sg:city":"Braunschweig",
    "sg:phone":"+49 531/512354",
    "sg:postcode":"38112",
    "sg:province":"Niedersachsen",
    "wof:name":"Adolf Spandau",
    "wof:placetype":"venue"
},
  "geometry": {"coordinates":[10.4692687988,52.3025398254],"type":"Point"}
}