{
  "type": "Feature",
  "properties": {
    "iso:country":"DE",
    "sg:address":"Rosenau 84",
    "sg:city":"Grafenau",
    "sg:phone":"+49 8552/1334",
    "sg:postcode":"94481",
    "sg:province":"Bayern",
    "wof:name":"Hermann Scheichenzuber",
    "wof:placetype":"venue"
},
  "geometry": {"coordinates":[13.4109554291,48.8734512329],"type":"Point"}
}