{
  "type": "Feature",
  "properties": {
    "iso:country":"DE",
    "sg:address":"Am Meinhard",
    "sg:city":"Meinhard",
    "sg:phone":"+49 5651/5932",
    "sg:postcode":"37276",
    "sg:province":"Hessen",
    "wof:name":"Klamotte",
    "wof:placetype":"venue"
},
  "geometry": {"coordinates":[10.0593566895,51.2223548889],"type":"Point"}
}