{
  "type": "Feature",
  "properties": {
    "iso:country":"DE",
    "sg:address":"Schmiedestr. 1",
    "sg:city":"Nieb\u00fcll",
    "sg:phone":"+49 4661/8513",
    "sg:postcode":"25899",
    "sg:province":"Schleswig-Holstein",
    "wof:name":"Nieb\u00fcller Backstube Werner Hansen",
    "wof:placetype":"venue"
},
  "geometry": {"coordinates":[8.831618,54.782936],"type":"Point"}
}