{
  "type": "Feature",
  "properties": {
    "iso:country":"DE",
    "sg:address":"Spiegelstr. 11",
    "sg:city":"M\u00fcnchen",
    "sg:phone":"+49 89/886935",
    "sg:postcode":"81241",
    "sg:province":"Bayern",
    "wof:name":"M. Hofmann",
    "wof:placetype":"venue"
},
  "geometry": {"coordinates":[11.460037,48.148232],"type":"Point"}
}