{
  "type": "Feature",
  "properties": {
    "iso:country":"DE",
    "sg:address":"Haunstetter Str. 91",
    "sg:city":"K\u00f6nigsbrunn",
    "sg:phone":"+49 8231/918901",
    "sg:postcode":"86343",
    "sg:province":"Bayern",
    "wof:name":"Restaurant Felfela",
    "wof:placetype":"venue"
},
  "geometry": {"coordinates":[10.8930778503,48.2807731628],"type":"Point"}
}