{
  "type": "Feature",
  "properties": {
    "iso:country":"DE",
    "sg:address":"Pfortener Str. 24",
    "sg:city":"Gera",
    "sg:phone":"+49 365/7106369",
    "sg:postcode":"07545",
    "sg:province":"Th\u00fcringen",
    "wof:name":"H & N Elektro-vertrieb Gmbh",
    "wof:placetype":"venue"
},
  "geometry": {"coordinates":[12.0867004395,50.8641433716],"type":"Point"}
}