{
  "type": "Feature",
  "properties": {
    "iso:country":"DE",
    "sg:address":"Frauenrichter Str. 27",
    "sg:city":"Weiden",
    "sg:postcode":"92637",
    "sg:province":"Bayern",
    "wof:name":"Flechter-bau E. K.",
    "wof:placetype":"venue"
},
  "geometry": {"coordinates":[12.15112,49.672989],"type":"Point"}
}