{
  "type": "Feature",
  "properties": {
    "iso:country":"DE",
    "sg:address":"Kapellenweg 7",
    "sg:city":"Altom\u00fcnster",
    "sg:phone":"+49 8254/1094",
    "sg:postcode":"85250",
    "sg:province":"Bayern",
    "wof:name":"Gemeindeb\u00fccherei",
    "wof:placetype":"venue"
},
  "geometry": {"coordinates":[11.265243,48.377415],"type":"Point"}
}