{
  "type": "Feature",
  "properties": {
    "iso:country":"DE",
    "sg:address":"Anemolter Str. 19",
    "sg:city":"Stolzenau",
    "sg:phone":"+49 5761/1413",
    "sg:postcode":"31592",
    "sg:province":"Niedersachsen",
    "wof:name":"Karl Schwen",
    "wof:placetype":"venue"
},
  "geometry": {"coordinates":[9.072052,52.539806],"type":"Point"}
}