{
  "type": "Feature",
  "properties": {
    "iso:country":"DE",
    "sg:address":"Berliner Allee 2",
    "sg:city":"Friesack",
    "sg:phone":"+49 33235/1592",
    "sg:postcode":"14662",
    "sg:province":"Brandenburg",
    "wof:name":"Elf-minol-tankstelle",
    "wof:placetype":"venue"
},
  "geometry": {"coordinates":[12.5842971802,52.7281951904],"type":"Point"}
}