{
  "type": "Feature",
  "properties": {
    "iso:country":"DE",
    "sg:address":"Provinzialstr. 75",
    "sg:city":"Dortmund",
    "sg:phone":"+49 231/636745",
    "sg:postcode":"44388",
    "sg:province":"Nordrhein-Westfalen",
    "wof:name":"Korfu-grill",
    "wof:placetype":"venue"
},
  "geometry": {"coordinates":[7.3260641098,51.4943885803],"type":"Point"}
}