{
  "type": "Feature",
  "properties": {
    "iso:country":"DE",
    "sg:address":"Flurstr. 2",
    "sg:city":"H\u00fcffler",
    "sg:phone":"+49 6384/339",
    "sg:postcode":"66909",
    "sg:province":"Rheinland-Pfalz",
    "wof:name":"Heinrich Feick",
    "wof:placetype":"venue"
},
  "geometry": {"coordinates":[7.3901019096,49.4961662292],"type":"Point"}
}