{
  "type": "Feature",
  "properties": {
    "iso:country":"DE",
    "sg:address":"Diess-Str. 16",
    "sg:city":"K\u00f6sslarn",
    "sg:phone":"+49 8536",
    "sg:postcode":"94149",
    "sg:province":"Bayern",
    "wof:name":"Cg Touristic",
    "wof:placetype":"venue"
},
  "geometry": {"coordinates":[13.1124944687,48.3724746704],"type":"Point"}
}