{
  "type": "Feature",
  "properties": {
    "iso:country":"DE",
    "sg:address":"Alter Hof 4",
    "sg:city":"Neunkirchen",
    "sg:phone":"+49 9153/1379",
    "sg:postcode":"91233",
    "sg:province":"Bayern",
    "wof:name":"Katholisches Pfarramt Kreuzauffindung",
    "wof:placetype":"venue"
},
  "geometry": {"coordinates":[11.360376358,49.5416069031],"type":"Point"}
}