{
  "type": "Feature",
  "properties": {
    "iso:country":"DE",
    "sg:address":"Aichener Str. 8",
    "sg:city":"Walkertshofen",
    "sg:phone":"+49 8239/214",
    "sg:postcode":"86877",
    "sg:province":"Bayern",
    "wof:name":"Hwv Hans Wiblishauser Verwaltungs- Gmbh & Co. Kg",
    "wof:placetype":"venue"
},
  "geometry": {"coordinates":[10.5861721039,48.225063324],"type":"Point"}
}