{
  "type": "Feature",
  "properties": {
    "iso:country":"DE",
    "sg:address":"Hammerspitzweg 4",
    "sg:city":"Oberstdorf",
    "sg:phone":"+49 8322/2143",
    "sg:postcode":"87561",
    "sg:province":"Bayern",
    "wof:name":"Gasthaus Mariandl Inh. M. Kirsten",
    "wof:placetype":"venue"
},
  "geometry": {"coordinates":[10.2807302475,47.4021072388],"type":"Point"}
}