{
  "type": "Feature",
  "properties": {
    "iso:country":"DE",
    "sg:address":"Englerthstr. 13",
    "sg:city":"Eschweiler",
    "sg:phone":"+49 2403/36959",
    "sg:postcode":"52249",
    "sg:province":"Nordrhein-Westfalen",
    "wof:name":"Annette Bourseaux",
    "wof:placetype":"venue"
},
  "geometry": {"coordinates":[6.266284,50.819069],"type":"Point"}
}