{
  "type": "Feature",
  "properties": {
    "iso:country":"DE",
    "sg:address":"Ringstr. 2",
    "sg:city":"Beilngries",
    "sg:phone":"+49 8461/1267",
    "sg:postcode":"92339",
    "sg:province":"Bayern",
    "wof:name":"Josef Hildersperger",
    "wof:placetype":"venue"
},
  "geometry": {"coordinates":[11.474629,49.033009],"type":"Point"}
}