{
  "type": "Feature",
  "properties": {
    "iso:country":"DE",
    "sg:address":"Kapellenstr. 15",
    "sg:city":"Ober-Olm",
    "sg:phone":"+49 6136/87675",
    "sg:postcode":"55270",
    "sg:province":"Rheinland-Pfalz",
    "wof:name":"Willi Eckert",
    "wof:placetype":"venue"
},
  "geometry": {"coordinates":[8.189394,49.934753],"type":"Point"}
}