{
  "type": "Feature",
  "properties": {
    "iso:country":"DE",
    "sg:address":"Hammer Dorfstr. 126",
    "sg:city":"D\u00fcsseldorf",
    "sg:phone":"+49 211/305968",
    "sg:postcode":"40221",
    "sg:province":"Nordrhein-Westfalen",
    "wof:name":"Creative Typographie Rudolf Frerichs Gmbh",
    "wof:placetype":"venue"
},
  "geometry": {"coordinates":[6.740745,51.208084],"type":"Point"}
}