{
  "type": "Feature",
  "properties": {
    "iso:country":"DE",
    "sg:address":"Am Stichkanal 38a",
    "sg:city":"Berlin",
    "sg:phone":"+49 30/8175091",
    "sg:postcode":"14167",
    "sg:province":"Berlin",
    "wof:name":"Herta Birkholz Inh. Wolfgang Krolik",
    "wof:placetype":"venue"
},
  "geometry": {"coordinates":[13.2867918015,52.4123764038],"type":"Point"}
}