{
  "type": "Feature",
  "properties": {
    "iso:country":"DE",
    "sg:address":"Kemptener Str. 122",
    "sg:city":"K\u00f6nigsbrunn",
    "sg:phone":"+49 8231/4075",
    "sg:postcode":"86343",
    "sg:province":"Bayern",
    "wof:name":"Rupert J. Kerpl",
    "wof:placetype":"venue"
},
  "geometry": {"coordinates":[10.8817653656,48.2780151367],"type":"Point"}
}