{
  "type": "Feature",
  "properties": {
    "iso:country":"DE",
    "sg:address":"Leutersbergstr. 50",
    "sg:city":"Sch\u00f6nau",
    "sg:phone":"+49 6228/911220",
    "sg:postcode":"69250",
    "sg:province":"Baden-W\u00fcrttemberg",
    "wof:name":"Oskar Wolf Architekt",
    "wof:placetype":"venue"
},
  "geometry": {"coordinates":[8.805083,49.459946],"type":"Point"}
}