{
  "type": "Feature",
  "properties": {
    "iso:country":"DE",
    "sg:address":"Eichkoppelweg 97",
    "sg:city":"Kronshagen",
    "sg:phone":"+49 431/545510",
    "sg:postcode":"24119",
    "sg:province":"Schleswig-Holstein",
    "wof:name":"Karl Knuth Gmbh & Co.",
    "wof:placetype":"venue"
},
  "geometry": {"coordinates":[10.0994138718,54.3381538391],"type":"Point"}
}