{
  "type": "Feature",
  "properties": {
    "iso:country":"DE",
    "sg:address":"Schrothstr. 8",
    "sg:city":"Weiden",
    "sg:phone":"+49 961/31919",
    "sg:postcode":"92637",
    "sg:province":"Bayern",
    "wof:name":"Helmuth Huber Architekt",
    "wof:placetype":"venue"
},
  "geometry": {"coordinates":[12.171549,49.701149],"type":"Point"}
}