{
  "type": "Feature",
  "properties": {
    "iso:country":"DE",
    "sg:address":"Turmstr. 33",
    "sg:city":"L\u00f6rrach",
    "sg:phone":"+49 7621/2318",
    "sg:postcode":"79539",
    "sg:province":"Baden-W\u00fcrttemberg",
    "wof:name":"Rolf Renk",
    "wof:placetype":"venue"
},
  "geometry": {"coordinates":[7.6622419357,47.6126823425],"type":"Point"}
}