{
  "type": "Feature",
  "properties": {
    "iso:country":"DE",
    "sg:address":"Nassachstr. 9",
    "sg:city":"Breiteng\u00fc\u00dfbach",
    "sg:phone":"+49 9544/1414",
    "sg:postcode":"96149",
    "sg:province":"Bayern",
    "wof:name":"Moritz & Moritz Gmbh",
    "wof:placetype":"venue"
},
  "geometry": {"coordinates":[10.886209,49.97382],"type":"Point"}
}