{
  "type": "Feature",
  "properties": {
    "iso:country":"DE",
    "sg:address":"Ochsenwerder Elbdeich 71",
    "sg:city":"Hamburg",
    "sg:phone":"+49 40/7372787",
    "sg:postcode":"21037",
    "sg:province":"Hamburg",
    "wof:name":"G\u00fcnter Stoop",
    "wof:placetype":"venue"
},
  "geometry": {"coordinates":[10.084095,53.455761],"type":"Point"}
}