{
  "type": "Feature",
  "properties": {
    "iso:country":"DE",
    "sg:address":"Brunohler Str. 54",
    "sg:city":"Gummersbach",
    "sg:phone":"+49 2261/790510",
    "sg:postcode":"51645",
    "sg:province":"Nordrhein-Westfalen",
    "wof:name":"Michel-f\u00fckking",
    "wof:placetype":"venue"
},
  "geometry": {"coordinates":[7.5050292015,50.9923858643],"type":"Point"}
}