{
  "type": "Feature",
  "properties": {
    "iso:country":"DE",
    "sg:address":"Kahlenbergsweg 24",
    "sg:city":"Ratingen",
    "sg:postcode":"40885",
    "sg:province":"Nordrhein-Westfalen",
    "wof:name":"Interdent-dela Zahntechnik Gmbh",
    "wof:placetype":"venue"
},
  "geometry": {"coordinates":[6.8684968948,51.3599472046],"type":"Point"}
}