{
  "type": "Feature",
  "properties": {
    "iso:country":"DE",
    "sg:address":"Gehrenstr. 33",
    "sg:city":"Neuhausen",
    "sg:phone":"+49 7467/478",
    "sg:postcode":"78579",
    "sg:province":"Baden-W\u00fcrttemberg",
    "wof:name":"M. Mattes",
    "wof:placetype":"venue"
},
  "geometry": {"coordinates":[8.9301137924,47.9689178467],"type":"Point"}
}