{
  "type": "Feature",
  "properties": {
    "iso:country":"DE",
    "sg:address":"Daimlerstr 15",
    "sg:city":"Altensteig",
    "sg:phone":"+49 7453/8064",
    "sg:postcode":"72213",
    "sg:province":"Baden-W\u00fcrttemberg",
    "wof:name":"Dalli-baukasten-schalungssysteme Gmbh",
    "wof:placetype":"venue"
},
  "geometry": {"coordinates":[8.5916547775,48.5803833008],"type":"Point"}
}