{
  "type": "Feature",
  "properties": {
    "iso:country":"DE",
    "sg:address":"Bremer Str. 203",
    "sg:city":"Hamburg",
    "sg:phone":"+49 40/7603273",
    "sg:postcode":"21073",
    "sg:province":"Hamburg",
    "wof:name":"G\u00fcnter Kall\u00e4we",
    "wof:placetype":"venue"
},
  "geometry": {"coordinates":[9.9617424011,53.4480133057],"type":"Point"}
}