{
  "type": "Feature",
  "properties": {
    "iso:country":"DE",
    "sg:address":"Niederichstr. 6",
    "sg:city":"K\u00f6ln",
    "sg:postcode":"50668",
    "sg:province":"Nordrhein-Westfalen",
    "wof:name":"Sozialwissenschaftliche Forschung U. Praxis F\u00fcr Frauen",
    "wof:placetype":"venue"
},
  "geometry": {"coordinates":[6.9634718895,50.948223114],"type":"Point"}
}