{
  "type": "Feature",
  "properties": {
    "iso:country":"DE",
    "sg:address":"Maurenbrecherstr. 15",
    "sg:city":"D\u00fcsseldorf",
    "sg:phone":"+49 211/622176",
    "sg:postcode":"40239",
    "sg:province":"Nordrhein-Westfalen",
    "wof:name":"Erna Grefges",
    "wof:placetype":"venue"
},
  "geometry": {"coordinates":[6.803563,51.247795],"type":"Point"}
}