{
  "type": "Feature",
  "properties": {
    "iso:country":"DE",
    "sg:address":"Rheiner Landstr. 9",
    "sg:city":"Osnabr\u00fcck",
    "sg:phone":"+49 541/94120",
    "sg:postcode":"49078",
    "sg:province":"Niedersachsen",
    "wof:name":"Planungsb\u00fcro Rohling Beteiligungs-gmbh",
    "wof:placetype":"venue"
},
  "geometry": {"coordinates":[8.0191869736,52.27394104],"type":"Point"}
}