{
  "type": "Feature",
  "properties": {
    "iso:country":"DE",
    "sg:address":"St.-Martins-Platz 5",
    "sg:city":"Pfullendorf",
    "sg:phone":"+49 7552/5735",
    "sg:postcode":"88630",
    "sg:province":"Baden-W\u00fcrttemberg",
    "wof:name":"K. Matt",
    "wof:placetype":"venue"
},
  "geometry": {"coordinates":[9.204685,47.9049],"type":"Point"}
}