{
  "type": "Feature",
  "properties": {
    "iso:country":"DE",
    "sg:address":"Hauptstr. 5",
    "sg:city":"Obersontheim",
    "sg:phone":"+49 7973/222",
    "sg:postcode":"74423",
    "sg:province":"Baden-W\u00fcrttemberg",
    "wof:name":"G\u00fcnther Hartmann",
    "wof:placetype":"venue"
},
  "geometry": {"coordinates":[9.897692,49.057709],"type":"Point"}
}