{
  "type": "Feature",
  "properties": {
    "iso:country":"DE",
    "sg:address":"Koppelbergstr. 9",
    "sg:city":"Teterow",
    "sg:postcode":"17166",
    "sg:province":"Mecklenburg-Vorpommern",
    "wof:name":"Fdt F\u00f6rder- Und Deponie- Technik Gmbh",
    "wof:placetype":"venue"
},
  "geometry": {"coordinates":[12.607365,53.76384],"type":"Point"}
}