{
  "type": "Feature",
  "properties": {
    "iso:country":"DE",
    "sg:address":"Poggenpohl 8",
    "sg:city":"Hamberge",
    "sg:phone":"+49 451/892680",
    "sg:postcode":"23619",
    "sg:province":"Schleswig-Holstein",
    "wof:name":"Manfred M\u00f6ller",
    "wof:placetype":"venue"
},
  "geometry": {"coordinates":[10.610873,53.846279],"type":"Point"}
}