{
  "type": "Feature",
  "properties": {
    "iso:country":"DE",
    "sg:address":"Salem 15",
    "sg:city":"Gorschendorf",
    "sg:phone":"+49 3994/632621",
    "sg:postcode":"17139",
    "sg:province":"Mecklenburg-Vorpommern",
    "wof:name":"Fliedereck Barner-meincke Gmbh",
    "wof:placetype":"venue"
},
  "geometry": {"coordinates":[12.7640514374,53.7425613403],"type":"Point"}
}