{
  "type": "Feature",
  "properties": {
    "iso:country":"DE",
    "sg:address":"Friedrich-Ebert-Str. 11",
    "sg:city":"L\u00f6wenberg",
    "sg:phone":"+49 33094/50448",
    "sg:postcode":"16775",
    "sg:province":"Brandenburg",
    "wof:name":"G\u00fcnter Wiese",
    "wof:placetype":"venue"
},
  "geometry": {"coordinates":[13.1529979706,52.8968353271],"type":"Point"}
}