{
  "type": "Feature",
  "properties": {
    "iso:country":"DE",
    "sg:address":"Mummelseeweg 15",
    "sg:city":"Villingen-Schwenningen",
    "sg:phone":"+49 7720/36897",
    "sg:postcode":"78054",
    "sg:province":"Baden-W\u00fcrttemberg",
    "wof:name":"R. Jost",
    "wof:placetype":"venue"
},
  "geometry": {"coordinates":[8.51064,48.056622],"type":"Point"}
}