{
  "type": "Feature",
  "properties": {
    "iso:country":"DE",
    "sg:address":"Hauptstr. 29",
    "sg:city":"Scheibenberg",
    "sg:phone":"+49 37349/8810",
    "sg:postcode":"09481",
    "sg:province":"Sachsen",
    "wof:name":"Gasthof-pension Erbgericht",
    "wof:placetype":"venue"
},
  "geometry": {"coordinates":[12.9021272659,50.5361785889],"type":"Point"}
}