{
  "type": "Feature",
  "properties": {
    "iso:country":"DE",
    "sg:address":"Klobikauer Str. 1d",
    "sg:city":"Merseburg",
    "sg:phone":"+49 3461/722099",
    "sg:postcode":"06217",
    "sg:province":"Sachsen-Anhalt",
    "wof:name":"Merco - Mtw",
    "wof:placetype":"venue"
},
  "geometry": {"coordinates":[11.988332,51.353565],"type":"Point"}
}