{
  "type": "Feature",
  "properties": {
    "iso:country":"DE",
    "sg:address":"Lerchenfeldstr. 3-7",
    "sg:city":"Willich",
    "sg:phone":"+49 2156/41492",
    "sg:postcode":"47877",
    "sg:province":"Nordrhein-Westfalen",
    "wof:name":"Ahg Ripkens",
    "wof:placetype":"venue"
},
  "geometry": {"coordinates":[6.4621100426,51.2799911499],"type":"Point"}
}