{
  "type": "Feature",
  "properties": {
    "iso:country":"DE",
    "sg:address":"Cottbuser Platz 2",
    "sg:city":"Guben",
    "sg:phone":"+49 3561",
    "sg:postcode":"03172",
    "sg:province":"Brandenburg",
    "wof:name":"Feuerwer Zu Jeder Jahreszeit",
    "wof:placetype":"venue"
},
  "geometry": {"coordinates":[14.706011,51.955757],"type":"Point"}
}