{
  "type": "Feature",
  "properties": {
    "iso:country":"DE",
    "sg:city":"Efringen-Kirchen",
    "sg:phone":"+49 7628/95383",
    "sg:postcode":"79588",
    "sg:province":"Baden-W\u00fcrttemberg",
    "wof:name":"D. L\u00fcke",
    "wof:placetype":"venue"
},
  "geometry": {"coordinates":[7.564715,47.649891],"type":"Point"}
}