{
  "type": "Feature",
  "properties": {
    "iso:country":"DE",
    "sg:address":"Oberdorfweg 9",
    "sg:city":"Hinterhermsdorf",
    "sg:postcode":"01855",
    "sg:province":"Sachsen",
    "wof:name":"Evangelisches Pfarramt Hinterhermsdorf",
    "wof:placetype":"venue"
},
  "geometry": {"coordinates":[14.3599596024,50.9254722595],"type":"Point"}
}