{
  "type": "Feature",
  "properties": {
    "iso:country":"DE",
    "sg:address":"Graf-Adolf-Str. 22",
    "sg:city":"D\u00fcsseldorf",
    "sg:phone":"+49 211/130710",
    "sg:postcode":"40212",
    "sg:province":"Nordrhein-Westfalen",
    "wof:name":"Deutsche Telekom Medien Gmbh",
    "wof:placetype":"venue"
},
  "geometry": {"coordinates":[6.781329155,51.2190856934],"type":"Point"}
}