{
  "type": "Feature",
  "properties": {
    "iso:country":"DE",
    "sg:address":"Bahnhofstr. 4",
    "sg:city":"Hengersberg",
    "sg:phone":"+49 9901/6265",
    "sg:postcode":"94491",
    "sg:province":"Bayern",
    "wof:name":"Graf Sport Und Schuh Inh. Susanne Bogner",
    "wof:placetype":"venue"
},
  "geometry": {"coordinates":[13.051112175,48.7730178833],"type":"Point"}
}