{
  "type": "Feature",
  "properties": {
    "iso:country":"DE",
    "sg:address":"Trondheimstr. 12",
    "sg:city":"Darmstadt",
    "sg:phone":"+49 6151/57924",
    "sg:postcode":"64297",
    "sg:province":"Hessen",
    "wof:name":"G\u00fcnter H. Heinrichs Rechtsanwalt Und Notar",
    "wof:placetype":"venue"
},
  "geometry": {"coordinates":[8.6568021774,49.8091773987],"type":"Point"}
}