{
  "type": "Feature",
  "properties": {
    "iso:country":"DE",
    "sg:address":"Hauptstr. 97",
    "sg:city":"Steinbach-Hallenberg",
    "sg:phone":"+49 36847/42122",
    "sg:postcode":"98587",
    "sg:province":"Th\u00fcringen",
    "wof:name":"Sabine K\u00f6nig",
    "wof:placetype":"venue"
},
  "geometry": {"coordinates":[10.5693569183,50.7028617859],"type":"Point"}
}