{
  "type": "Feature",
  "properties": {
    "iso:country":"DE",
    "sg:address":"Kurt-Schumacher-Str. 10",
    "sg:city":"Frankfurt",
    "sg:phone":"+49 4969/21302",
    "sg:postcode":"60311",
    "sg:province":"Hessen",
    "wof:name":"Mainova",
    "wof:placetype":"venue"
},
  "geometry": {"coordinates":[8.688378,50.112164],"type":"Point"}
}