{
  "type": "Feature",
  "properties": {
    "iso:country":"DE",
    "sg:address":"Im Hunnental 8",
    "sg:city":"Hahnheim",
    "sg:postcode":"55278",
    "sg:province":"Rheinland-Pfalz",
    "wof:name":"Sport-shop",
    "wof:placetype":"venue"
},
  "geometry": {"coordinates":[8.244379,49.86137],"type":"Point"}
}