{
  "type": "Feature",
  "properties": {
    "iso:country":"DE",
    "sg:address":"Feursstr. 15 b",
    "sg:city":"Olching",
    "sg:phone":"+49 8142/13037",
    "sg:postcode":"82140",
    "sg:province":"Bayern",
    "wof:name":"B\u00e4ren-apotheke E. K.",
    "wof:placetype":"venue"
},
  "geometry": {"coordinates":[11.334983,48.211601],"type":"Point"}
}