{
  "type": "Feature",
  "properties": {
    "iso:country":"DE",
    "sg:address":"Wolfratshauser Str. 94 c",
    "sg:city":"M\u00fcnchen",
    "sg:phone":"+49 89/531012",
    "sg:postcode":"81379",
    "sg:province":"Bayern",
    "wof:name":"Horst Schreiber Rechtsanwalt",
    "wof:placetype":"venue"
},
  "geometry": {"coordinates":[11.5389471054,48.0914993286],"type":"Point"}
}