{
  "type": "Feature",
  "properties": {
    "iso:country":"DE",
    "sg:address":"Hauptstr. 1",
    "sg:city":"Lichtenau",
    "sg:postcode":"09244",
    "sg:province":"Sachsen",
    "wof:name":"Gasthof Oberlichtenau",
    "wof:placetype":"venue"
},
  "geometry": {"coordinates":[12.9738464355,50.9355316162],"type":"Point"}
}