{
  "type": "Feature",
  "properties": {
    "iso:country":"DE",
    "sg:address":"Gro\u00dfenhainer Str. 22",
    "sg:city":"Merzdorf",
    "sg:phone":"+49 3533/8573",
    "sg:postcode":"04932",
    "sg:province":"Brandenburg",
    "wof:name":"Sigismund Rieger",
    "wof:placetype":"venue"
},
  "geometry": {"coordinates":[13.531724,51.401562],"type":"Point"}
}