{
  "type": "Feature",
  "properties": {
    "iso:country":"DE",
    "sg:address":"Landkirchener Weg 49",
    "sg:city":"Burg",
    "sg:phone":"+49 4371/2095",
    "sg:postcode":"23769",
    "sg:province":"Schleswig-Holstein",
    "wof:name":"Esso-station",
    "wof:placetype":"venue"
},
  "geometry": {"coordinates":[11.184015274,54.4425430298],"type":"Point"}
}