{
  "type": "Feature",
  "properties": {
    "iso:country":"DE",
    "sg:address":"Blossersberger Str. 2",
    "sg:city":"Viechtach",
    "sg:phone":"+49 9942/8325",
    "sg:postcode":"94234",
    "sg:province":"Bayern",
    "wof:name":"Napoleon",
    "wof:placetype":"venue"
},
  "geometry": {"coordinates":[12.891411,49.081142],"type":"Point"}
}