{
  "type": "Feature",
  "properties": {
    "iso:country":"DE",
    "sg:address":"Sch\u00f6nauer Str 35",
    "sg:city":"Zobes",
    "sg:phone":"+49 3741/411101",
    "sg:postcode":"08541",
    "sg:province":"Sachsen",
    "wof:name":"Vogtland",
    "wof:placetype":"venue"
},
  "geometry": {"coordinates":[12.2592353821,50.5091171265],"type":"Point"}
}