{
  "type": "Feature",
  "properties": {
    "iso:country":"DE",
    "sg:address":"M\u00fchlenweg 20",
    "sg:city":"Emmerthal",
    "sg:phone":"+49 5155/235",
    "sg:postcode":"31860",
    "sg:province":"Niedersachsen",
    "wof:name":"Katholisches Pfarramt Hl. Familie",
    "wof:placetype":"venue"
},
  "geometry": {"coordinates":[9.3876113892,52.0426940918],"type":"Point"}
}