{
  "type": "Feature",
  "properties": {
    "iso:country":"DE",
    "sg:address":"Parkstr. 34",
    "sg:city":"Gauting",
    "sg:phone":"+49 89/8507561",
    "sg:postcode":"82131",
    "sg:province":"Bayern",
    "wof:name":"Moths Gmbh",
    "wof:placetype":"venue"
},
  "geometry": {"coordinates":[11.372251,48.068428],"type":"Point"}
}