{
  "type": "Feature",
  "properties": {
    "iso:country":"DE",
    "sg:address":"Luisenstr. 30",
    "sg:city":"Bocholt",
    "sg:phone":"+49 2871/37628",
    "sg:postcode":"46397",
    "sg:province":"Nordrhein-Westfalen",
    "wof:name":"Paul Kartenk\u00e4mper",
    "wof:placetype":"venue"
},
  "geometry": {"coordinates":[6.6270389557,51.8420639038],"type":"Point"}
}