{
  "type": "Feature",
  "properties": {
    "iso:country":"DE",
    "sg:city":"Wilhelmshaven",
    "sg:phone":"+49 4421/995152",
    "sg:postcode":"26388",
    "sg:province":"Niedersachsen",
    "wof:name":"Dr.musik Veranstaltungstechnik",
    "wof:placetype":"venue"
},
  "geometry": {"coordinates":[8.092445,53.574169],"type":"Point"}
}