{
  "type": "Feature",
  "properties": {
    "iso:country":"DE",
    "sg:address":"Detmolder Str. 6-10",
    "sg:city":"Oerlinghausen",
    "sg:postcode":"33813",
    "sg:province":"Nordrhein-Westfalen",
    "wof:name":"Leinen-export Gmbh",
    "wof:placetype":"venue"
},
  "geometry": {"coordinates":[8.6659708023,51.9591369629],"type":"Point"}
}