{
  "type": "Feature",
  "properties": {
    "iso:country":"DE",
    "sg:address":"Am Heideberg 2",
    "sg:city":"Gro\u00df Machnow",
    "sg:phone":"+49 33708/2320",
    "sg:postcode":"15806",
    "sg:province":"Brandenburg",
    "wof:name":"Askem Anlagen- Und Stahlbau Gmbh",
    "wof:placetype":"venue"
},
  "geometry": {"coordinates":[13.44803,52.215515],"type":"Point"}
}