{
  "type": "Feature",
  "properties": {
    "iso:country":"DE",
    "sg:address":"Geschwister-Scholl-Str. 10 a",
    "sg:city":"Erfurt",
    "sg:phone":"+49 361/5611093",
    "sg:postcode":"99085",
    "sg:province":"Th\u00fcringen",
    "wof:name":"Kurdischer D\u00f6ner",
    "wof:placetype":"venue"
},
  "geometry": {"coordinates":[11.044883728,50.9816093445],"type":"Point"}
}