{
  "type": "Feature",
  "properties": {
    "iso:country":"DE",
    "sg:address":"Waldweg",
    "sg:city":"Mandelbachtal",
    "sg:phone":"+49 4968/04353",
    "sg:postcode":"66399",
    "sg:province":"Saarland",
    "wof:name":"Homepage Des Sch\u00fctzenvereins Bliesmengen-bolchen",
    "wof:placetype":"venue"
},
  "geometry": {"coordinates":[7.120453,49.146107],"type":"Point"}
}