{
  "type": "Feature",
  "properties": {
    "iso:country":"DE",
    "sg:address":"Postfach 102865",
    "sg:city":"Bochum",
    "sg:postcode":"44728",
    "sg:province":"Nordrhein-Westfalen",
    "wof:name":"Vbw Gesellschaft F\u00fcr Schl\u00fcsselfertiges Bauen Mbh",
    "wof:placetype":"venue"
},
  "geometry": {"coordinates":[7.21181,51.482899],"type":"Point"}
}