{
  "type": "Feature",
  "properties": {
    "iso:country":"DE",
    "sg:address":"Rheinstr. 111",
    "sg:city":"M\u00fcnster-Sarmsheim",
    "sg:phone":"+49 6721/402717",
    "sg:postcode":"55424",
    "sg:province":"Rheinland-Pfalz",
    "wof:name":"Pizzeriada Peppe",
    "wof:placetype":"venue"
},
  "geometry": {"coordinates":[7.8958091736,49.9421195984],"type":"Point"}
}