{
  "type": "Feature",
  "properties": {
    "iso:country":"DE",
    "sg:address":"Kirchenstr. 12",
    "sg:city":"Ludwigshafen",
    "sg:phone":"+49 621/655206",
    "sg:postcode":"67069",
    "sg:province":"Rheinland-Pfalz",
    "wof:name":"Hans-peter B\u00e4cker",
    "wof:placetype":"venue"
},
  "geometry": {"coordinates":[8.4033193588,49.5206756592],"type":"Point"}
}