{
  "type": "Feature",
  "properties": {
    "iso:country":"DE",
    "sg:address":"Curtiusstr. 63",
    "sg:city":"Berlin",
    "sg:phone":"+49 30/8116983",
    "sg:postcode":"12205",
    "sg:province":"Berlin",
    "wof:name":"Eckart Albrecht",
    "wof:placetype":"venue"
},
  "geometry": {"coordinates":[13.286054,52.439278],"type":"Point"}
}