{
  "type": "Feature",
  "properties": {
    "iso:country":"DE",
    "sg:address":"Norderstr. 42",
    "sg:city":"Husum",
    "sg:phone":"+49 4841/83480",
    "sg:postcode":"25813",
    "sg:province":"Schleswig-Holstein",
    "wof:name":"Reiner Stadel",
    "wof:placetype":"venue"
},
  "geometry": {"coordinates":[9.0559720993,54.4780960083],"type":"Point"}
}