{
  "type": "Feature",
  "properties": {
    "iso:country":"DE",
    "sg:address":"Bertha-von-Suttner-Str. 1",
    "sg:city":"Potsdam",
    "sg:phone":"+49 331/2800788",
    "sg:postcode":"14469",
    "sg:province":"Brandenburg",
    "wof:name":"Film-art Potsdam Gmbh",
    "wof:placetype":"venue"
},
  "geometry": {"coordinates":[13.0598869324,52.4066162109],"type":"Point"}
}