{
  "type": "Feature",
  "properties": {
    "iso:country":"DE",
    "sg:address":"Hebelstr. 19 a",
    "sg:city":"Rheinfelden",
    "sg:phone":"+49 7623/72480",
    "sg:postcode":"79618",
    "sg:province":"Baden-W\u00fcrttemberg",
    "wof:name":"Pro Plan Automatisierungstechnik Gmbh",
    "wof:placetype":"venue"
},
  "geometry": {"coordinates":[7.7847080231,47.5599060059],"type":"Point"}
}