{
  "type": "Feature",
  "properties": {
    "iso:country":"DE",
    "sg:address":"Karlsbader Str. 126",
    "sg:city":"Sehmatal-Sehma",
    "sg:phone":"+49 3733/66973",
    "sg:postcode":"09465",
    "sg:province":"Sachsen",
    "wof:name":"Albert P\u00e4\u00dfler",
    "wof:placetype":"venue"
},
  "geometry": {"coordinates":[12.9739236832,50.4863433838],"type":"Point"}
}