{
  "type": "Feature",
  "properties": {
    "iso:country":"DE",
    "sg:address":"Kleine Rurstr. 17",
    "sg:city":"J\u00fclich",
    "sg:phone":"+49 2461/345938",
    "sg:postcode":"52428",
    "sg:province":"Nordrhein-Westfalen",
    "wof:name":"Christiane Lammertz",
    "wof:placetype":"venue"
},
  "geometry": {"coordinates":[6.356597,50.921143],"type":"Point"}
}