{
  "type": "Feature",
  "properties": {
    "iso:country":"DE",
    "sg:address":"Austr. 17",
    "sg:city":"\u00d6hringen",
    "sg:phone":"+49 7941/2206",
    "sg:postcode":"74613",
    "sg:province":"Baden-W\u00fcrttemberg",
    "wof:name":"A. Lintner",
    "wof:placetype":"venue"
},
  "geometry": {"coordinates":[9.4893770218,49.2056541443],"type":"Point"}
}