{
  "type": "Feature",
  "properties": {
    "iso:country":"DE",
    "sg:address":"Am Wasserturm 2",
    "sg:city":"Wermelskirchen",
    "sg:phone":"+49 4921/9672490",
    "sg:postcode":"42929",
    "sg:province":"Nordrhein-Westfalen",
    "wof:name":"Bader Peter Gmbh",
    "wof:placetype":"venue"
},
  "geometry": {"coordinates":[7.228871,51.145382],"type":"Point"}
}