{
  "type": "Feature",
  "properties": {
    "iso:country":"DE",
    "sg:address":"Saalstr. 9",
    "sg:city":"Wei\u00dfenfels",
    "sg:phone":"+49 3443/302170",
    "sg:postcode":"06667",
    "sg:province":"Sachsen-Anhalt",
    "wof:name":"K\u00e4mpf",
    "wof:placetype":"venue"
},
  "geometry": {"coordinates":[11.9687099457,51.2002563477],"type":"Point"}
}