{
  "type": "Feature",
  "properties": {
    "iso:country":"DE",
    "sg:address":"Kapellenweg 3",
    "sg:city":"Markt Bibart",
    "sg:phone":"+49 9162/8221",
    "sg:postcode":"91477",
    "sg:province":"Bayern",
    "wof:name":"Ernst Weber",
    "wof:placetype":"venue"
},
  "geometry": {"coordinates":[10.4258432388,49.6524772644],"type":"Point"}
}