{
  "type": "Feature",
  "properties": {
    "iso:country":"DE",
    "sg:address":"Kapuzinerstr. 3a",
    "sg:city":"Dillingen",
    "sg:phone":"+49 9071/2552",
    "sg:postcode":"89407",
    "sg:province":"Bayern",
    "wof:name":"Alois Frank Rechtsanwalt",
    "wof:placetype":"venue"
},
  "geometry": {"coordinates":[10.49609375,48.5779342651],"type":"Point"}
}