{
  "type": "Feature",
  "properties": {
    "iso:country":"DE",
    "sg:address":"Auf den W\u00fcsten 10",
    "sg:city":"Marburg",
    "sg:phone":"+49 6421/51837",
    "sg:postcode":"35043",
    "sg:province":"Hessen",
    "wof:name":"Assessment Center - Bewerbungstraining - Interviews",
    "wof:placetype":"venue"
},
  "geometry": {"coordinates":[8.7737083435,50.7769546509],"type":"Point"}
}