{
  "type": "Feature",
  "properties": {
    "iso:country":"DE",
    "sg:address":"Steinhaldestr. 47",
    "sg:city":"Heilbronn",
    "sg:phone":"+49 7131/488820",
    "sg:postcode":"74078",
    "sg:province":"Baden-W\u00fcrttemberg",
    "wof:name":"Etm Elektrotechnische Montagen Gmbh",
    "wof:placetype":"venue"
},
  "geometry": {"coordinates":[9.1703281403,49.1549797058],"type":"Point"}
}