{
  "type": "Feature",
  "properties": {
    "iso:country":"DE",
    "sg:address":"Barzther Str. 16",
    "sg:city":"Trebbin",
    "sg:phone":"+49 33731/607",
    "sg:postcode":"14959",
    "sg:province":"Brandenburg",
    "wof:name":"Sparkasse",
    "wof:placetype":"venue"
},
  "geometry": {"coordinates":[13.216627,52.21743],"type":"Point"}
}