{
  "type": "Feature",
  "properties": {
    "iso:country":"DE",
    "sg:address":"Arnoldstra\u00dfe 76",
    "sg:city":"Hamburg",
    "sg:phone":"+49 40/391233",
    "sg:postcode":"22763",
    "sg:province":"Hamburg",
    "wof:name":"Kinderorthop\u00e4die",
    "wof:placetype":"venue"
},
  "geometry": {"coordinates":[9.922329,53.54834],"type":"Point"}
}