{
  "type": "Feature",
  "properties": {
    "iso:country":"DE",
    "sg:address":"Iltisstr. 49",
    "sg:city":"Kiel",
    "sg:phone":"+49 431/731637",
    "sg:postcode":"24143",
    "sg:province":"Schleswig-Holstein",
    "wof:name":"Bambule",
    "wof:placetype":"venue"
},
  "geometry": {"coordinates":[10.1470575333,54.3078918457],"type":"Point"}
}