{
  "type": "Feature",
  "properties": {
    "iso:country":"DE",
    "sg:address":"M\u00fcnsterstr. 107",
    "sg:city":"D\u00fclmen",
    "sg:phone":"+49 2594/3001",
    "sg:postcode":"48249",
    "sg:province":"Nordrhein-Westfalen",
    "wof:name":"Anton Pennekamp Bp-tankstelle",
    "wof:placetype":"venue"
},
  "geometry": {"coordinates":[7.2845678329,51.8363418579],"type":"Point"}
}