{
  "type": "Feature",
  "properties": {
    "iso:country":"DE",
    "sg:address":"K\u00f6bbingser M\u00fchle 2",
    "sg:city":"Iserlohn",
    "sg:phone":"+49 4923/7194900",
    "sg:postcode":"58640",
    "sg:province":"Nordrhein-Westfalen",
    "wof:name":"Alfred Reinecke Gmbh & Co Kg",
    "wof:placetype":"venue"
},
  "geometry": {"coordinates":[7.70168,51.422371],"type":"Point"}
}