{
  "type": "Feature",
  "properties": {
    "iso:country":"DE",
    "sg:address":"Gro\u00dfe Fischerweide 4",
    "sg:city":"Worms",
    "sg:phone":"+49 6241/24640",
    "sg:postcode":"67547",
    "sg:province":"Rheinland-Pfalz",
    "wof:name":"Metallbau Philipp Jung Gmbh & Co. Kg",
    "wof:placetype":"venue"
},
  "geometry": {"coordinates":[8.369687,49.632256],"type":"Point"}
}