{
  "type": "Feature",
  "properties": {
    "iso:country":"DE",
    "sg:address":"M\u00fchlenstr. 20",
    "sg:city":"Langelsheim",
    "sg:phone":"+49 5326/2831",
    "sg:postcode":"38685",
    "sg:province":"Niedersachsen",
    "wof:name":"Die Stadtklause",
    "wof:placetype":"venue"
},
  "geometry": {"coordinates":[10.3305892944,51.9385871887],"type":"Point"}
}