{
  "type": "Feature",
  "properties": {
    "iso:country":"DE",
    "sg:address":"Ameke-Berg 9",
    "sg:city":"Drensteinfurt",
    "sg:phone":"+49 2387/205",
    "sg:postcode":"48317",
    "sg:province":"Nordrhein-Westfalen",
    "wof:name":"Norbert Holtrup Gmbh",
    "wof:placetype":"venue"
},
  "geometry": {"coordinates":[7.762119,51.76527],"type":"Point"}
}