{
  "type": "Feature",
  "properties": {
    "iso:country":"DE",
    "sg:address":"Merkenfritzer Weg 16",
    "sg:city":"Hirzenhain",
    "sg:phone":"+49 6045/1376",
    "sg:postcode":"63697",
    "sg:province":"Hessen",
    "wof:name":"Ev. Pfarramt Hirzenhain",
    "wof:placetype":"venue"
},
  "geometry": {"coordinates":[9.1396684647,50.3932647705],"type":"Point"}
}