{
  "type": "Feature",
  "properties": {
    "iso:country":"DE",
    "sg:address":"K\u00f6nigstr. 1",
    "sg:city":"Bestwig",
    "sg:phone":"+49 2904/4533",
    "sg:postcode":"59909",
    "sg:province":"Nordrhein-Westfalen",
    "wof:name":"Josef H\u00f6mberg",
    "wof:placetype":"venue"
},
  "geometry": {"coordinates":[8.4259319305,51.3706703186],"type":"Point"}
}