{
  "type": "Feature",
  "properties": {
    "iso:country":"DE",
    "sg:address":"Rheinallee 130",
    "sg:city":"Mainz",
    "sg:phone":"+49 6131/686901",
    "sg:postcode":"55120",
    "sg:province":"Rheinland-Pfalz",
    "wof:name":"M\u00f6bel-hedderich Gmbh & Co. Kg",
    "wof:placetype":"venue"
},
  "geometry": {"coordinates":[8.203849,50.029579],"type":"Point"}
}