{
  "type": "Feature",
  "properties": {
    "iso:country":"DE",
    "sg:address":"Oberbilker Allee 202",
    "sg:city":"D\u00fcsseldorf",
    "sg:phone":"+49 211/784904",
    "sg:postcode":"40227",
    "sg:province":"Nordrhein-Westfalen",
    "wof:name":"Gangelshof",
    "wof:placetype":"venue"
},
  "geometry": {"coordinates":[6.8003492355,51.210723877],"type":"Point"}
}