{
  "type": "Feature",
  "properties": {
    "iso:country":"DE",
    "sg:address":"Maybachstr. 2",
    "sg:city":"Gelsenkirchen",
    "sg:phone":"+49 209/976040",
    "sg:postcode":"45891",
    "sg:province":"Nordrhein-Westfalen",
    "wof:name":"Elba-b\u00fcrosysteme Erich Kraut Gmbh & Co.",
    "wof:placetype":"venue"
},
  "geometry": {"coordinates":[7.0778198242,51.5460929871],"type":"Point"}
}