{
  "type": "Feature",
  "properties": {
    "iso:country":"DE",
    "sg:address":"Jakob-Latscha-Str. 7",
    "sg:city":"Dreieich",
    "sg:phone":"+49 6103/63612",
    "sg:postcode":"63303",
    "sg:province":"Hessen",
    "wof:name":"Walter Zipper Architekt",
    "wof:placetype":"venue"
},
  "geometry": {"coordinates":[8.663515,50.02063],"type":"Point"}
}