{
  "type": "Feature",
  "properties": {
    "iso:country":"DE",
    "sg:address":"Coppistr. 76",
    "sg:city":"Leipzig",
    "sg:phone":"+49 341/9126095",
    "sg:postcode":"04157",
    "sg:province":"Sachsen",
    "wof:name":"Elektro P\u00f6tzsch Kg",
    "wof:placetype":"venue"
},
  "geometry": {"coordinates":[12.36925,51.367329],"type":"Point"}
}