{
  "type": "Feature",
  "properties": {
    "iso:country":"DE",
    "sg:address":"Hahnenweiler 1",
    "sg:city":"Merklingen",
    "sg:phone":"+49 4973/376235",
    "sg:postcode":"89188",
    "sg:province":"Baden-W\u00fcrttemberg",
    "wof:name":"Sparkasse",
    "wof:placetype":"venue"
},
  "geometry": {"coordinates":[9.756398,48.509918],"type":"Point"}
}