{
  "type": "Feature",
  "properties": {
    "iso:country":"DE",
    "sg:address":"Engelsweg 41",
    "sg:city":"W\u00fcrzburg",
    "sg:phone":"+49 931/60439",
    "sg:postcode":"97084",
    "sg:province":"Bayern",
    "wof:name":"Kurt Simon",
    "wof:placetype":"venue"
},
  "geometry": {"coordinates":[9.9604206085,49.7195549011],"type":"Point"}
}