{
  "type": "Feature",
  "properties": {
    "iso:country":"DE",
    "sg:address":"An der B 31",
    "sg:city":"Breisach",
    "sg:postcode":"79206",
    "sg:province":"Baden-W\u00fcrttemberg",
    "wof:name":"S\u00fcdwestentsorgung Gmbh",
    "wof:placetype":"venue"
},
  "geometry": {"coordinates":[7.5821070671,48.0282096863],"type":"Point"}
}