{
  "type": "Feature",
  "properties": {
    "iso:country":"DE",
    "sg:address":"Amselstr. 15",
    "sg:city":"Mannheim",
    "sg:phone":"+49 621/777850",
    "sg:postcode":"68307",
    "sg:province":"Baden-W\u00fcrttemberg",
    "wof:name":"Wisser Dienstleistungs- Gesellschaft Baden-w\u00fcrttemberg",
    "wof:placetype":"venue"
},
  "geometry": {"coordinates":[8.4577598572,49.549118042],"type":"Point"}
}