{
  "type": "Feature",
  "properties": {
    "iso:country":"DE",
    "sg:address":"Gernsstr. 15",
    "sg:city":"Hannover",
    "sg:phone":"+49 511/6497862",
    "sg:postcode":"30659",
    "sg:province":"Niedersachsen",
    "wof:name":"K.-h. Wintzenburg Rechtsanwalt",
    "wof:placetype":"venue"
},
  "geometry": {"coordinates":[9.8032808304,52.4169807434],"type":"Point"}
}