{
  "type": "Feature",
  "properties": {
    "iso:country":"DE",
    "sg:address":"Hommersumer Str. 126",
    "sg:city":"Goch",
    "sg:phone":"+49 2823/3784",
    "sg:postcode":"47574",
    "sg:province":"Nordrhein-Westfalen",
    "wof:name":"Bernd Eufinger",
    "wof:placetype":"venue"
},
  "geometry": {"coordinates":[6.10396,51.68581],"type":"Point"}
}