{
  "type": "Feature",
  "properties": {
    "iso:country":"DE",
    "sg:address":"Buchenstr 14",
    "sg:city":"Reichenbach",
    "sg:phone":"+49 3765/12990",
    "sg:postcode":"08468",
    "sg:province":"Sachsen",
    "wof:name":"Kunststoff-schwei\u00dftechnik Horst Kainath",
    "wof:placetype":"venue"
},
  "geometry": {"coordinates":[12.321337,50.63393],"type":"Point"}
}