{
  "type": "Feature",
  "properties": {
    "iso:country":"DE",
    "sg:address":"Theeberg 25",
    "sg:city":"Eddelak",
    "sg:phone":"+49 4855/8308",
    "sg:postcode":"25715",
    "sg:province":"Schleswig-Holstein",
    "wof:name":"S. Borwieck",
    "wof:placetype":"venue"
},
  "geometry": {"coordinates":[9.158346,53.952358],"type":"Point"}
}