{
  "type": "Feature",
  "properties": {
    "iso:country":"DE",
    "sg:address":"Brennereistr. 1",
    "sg:city":"Hemmingen",
    "sg:phone":"+49 7150/959810",
    "sg:postcode":"71282",
    "sg:province":"Baden-W\u00fcrttemberg",
    "wof:name":"Jack D\u00f6lle",
    "wof:placetype":"venue"
},
  "geometry": {"coordinates":[9.040431,48.866116],"type":"Point"}
}