{
  "type": "Feature",
  "properties": {
    "iso:country":"DE",
    "sg:address":"Herrenberger Str. 10",
    "sg:city":"Nagold",
    "sg:phone":"+49 7452/61004",
    "sg:postcode":"72202",
    "sg:province":"Baden-W\u00fcrttemberg",
    "wof:name":"Iks Irion Kommunikations Systeme",
    "wof:placetype":"venue"
},
  "geometry": {"coordinates":[8.7268877029,48.5507125854],"type":"Point"}
}