{
  "type": "Feature",
  "properties": {
    "iso:country":"DE",
    "sg:address":"Hagenstr. 36",
    "sg:city":"Nordhorn",
    "sg:phone":"+49 5921/18992",
    "sg:postcode":"48529",
    "sg:province":"Niedersachsen",
    "wof:name":"City-friseur M. Schulz",
    "wof:placetype":"venue"
},
  "geometry": {"coordinates":[7.0714221001,52.4366912842],"type":"Point"}
}