{
  "type": "Feature",
  "properties": {
    "iso:country":"DE",
    "sg:address":"Eckenerstr. 30",
    "sg:city":"Hamm",
    "sg:phone":"+49 2381/974433",
    "sg:postcode":"59075",
    "sg:province":"Nordrhein-Westfalen",
    "wof:name":"Abag-technik Gmbh",
    "wof:placetype":"venue"
},
  "geometry": {"coordinates":[7.776726,51.69072],"type":"Point"}
}