{
  "type": "Feature",
  "properties": {
    "iso:country":"DE",
    "sg:address":"Waldecker Str. 2",
    "sg:city":"Naumburg",
    "sg:phone":"+49 5625/922365",
    "sg:postcode":"34311",
    "sg:province":"Hessen",
    "wof:name":"Blumenscheune L\u00d6ber Gbr",
    "wof:placetype":"venue"
},
  "geometry": {"coordinates":[9.191852,51.273754],"type":"Point"}
}