{
  "type": "Feature",
  "properties": {
    "iso:country":"DE",
    "sg:address":"Osterstr 43",
    "sg:city":"Hannover",
    "sg:phone":"+49 511/325887",
    "sg:postcode":"30159",
    "sg:province":"Niedersachsen",
    "wof:name":"Draht-hentschel Louis Hentschel Betriebsgesellschaft Mbh",
    "wof:placetype":"venue"
},
  "geometry": {"coordinates":[9.738807,52.3708],"type":"Point"}
}