{
  "type": "Feature",
  "properties": {
    "iso:country":"DE",
    "sg:address":"Friedrichswall 11",
    "sg:city":"Hannover",
    "sg:phone":"+49 511/36770",
    "sg:postcode":"30159",
    "sg:province":"Niedersachsen",
    "wof:name":"Grand Hotel Maritim",
    "wof:placetype":"venue"
},
  "geometry": {"coordinates":[9.737446785,52.3686294556],"type":"Point"}
}