{
  "type": "Feature",
  "properties": {
    "iso:country":"DE",
    "sg:address":"Gr\u00fcner Winkel 15",
    "sg:city":"Kolkwitz",
    "sg:postcode":"03099",
    "sg:province":"Brandenburg",
    "wof:name":"Eco-domo Gmbh",
    "wof:placetype":"venue"
},
  "geometry": {"coordinates":[14.26163,51.741203],"type":"Point"}
}