{
  "type": "Feature",
  "properties": {
    "iso:country":"DE",
    "sg:address":"Schnepferflur",
    "sg:city":"R\u00fcdesheim am Rhein",
    "sg:phone":"+49 6722/2988",
    "sg:postcode":"65385",
    "sg:province":"Hessen",
    "wof:name":"Heinz Heim",
    "wof:placetype":"venue"
},
  "geometry": {"coordinates":[7.9230999947,49.979019165],"type":"Point"}
}