{
  "type": "Feature",
  "properties": {
    "iso:country":"DE",
    "sg:address":"Scharnhorststr. 19",
    "sg:city":"Neustadt",
    "sg:phone":"+49 5032/65770",
    "sg:postcode":"31535",
    "sg:province":"Niedersachsen",
    "wof:name":"Leye Tankservice",
    "wof:placetype":"venue"
},
  "geometry": {"coordinates":[11.5727052689,53.3836517334],"type":"Point"}
}