{
  "type": "Feature",
  "properties": {
    "iso:country":"DE",
    "sg:address":"Kart\u00e4userstr. 77",
    "sg:city":"Freiburg",
    "sg:phone":"+49 761/33388",
    "sg:postcode":"79104",
    "sg:province":"Baden-W\u00fcrttemberg",
    "wof:name":"Psychozosiale Beratungsstelle D. Ag F. Gef\u00e4hrdetenhilfe",
    "wof:placetype":"venue"
},
  "geometry": {"coordinates":[7.881,47.993011],"type":"Point"}
}