{
  "type": "Feature",
  "properties": {
    "iso:country":"DE",
    "sg:address":"Hauptstr. 97",
    "sg:city":"Remchingen",
    "sg:phone":"+49 7232/70008",
    "sg:postcode":"75196",
    "sg:province":"Baden-W\u00fcrttemberg",
    "wof:name":"Cosma",
    "wof:placetype":"venue"
},
  "geometry": {"coordinates":[8.571162,48.951668],"type":"Point"}
}