{
  "type": "Feature",
  "properties": {
    "iso:country":"DE",
    "sg:address":"Fleigenweg 36",
    "sg:city":"Steinfurt",
    "sg:phone":"+49 2552/60843",
    "sg:postcode":"48565",
    "sg:province":"Nordrhein-Westfalen",
    "wof:name":"Elsabeth U. Hansj. Heinrich",
    "wof:placetype":"venue"
},
  "geometry": {"coordinates":[7.4005498886,52.1423988342],"type":"Point"}
}