{
  "type": "Feature",
  "properties": {
    "iso:country":"DE",
    "sg:address":"Kannegie\u00dfer-Ring 7",
    "sg:city":"Vlotho",
    "sg:phone":"+49 5733/120",
    "sg:postcode":"32602",
    "sg:province":"Nordrhein-Westfalen",
    "wof:name":"Kannegiesser Gmbh",
    "wof:placetype":"venue"
},
  "geometry": {"coordinates":[8.827331,52.137753],"type":"Point"}
}