{
  "type": "Feature",
  "properties": {
    "iso:country":"DE",
    "sg:address":"Niedertor 3",
    "sg:city":"Grefrath",
    "sg:phone":"+49 2158/5921",
    "sg:postcode":"47929",
    "sg:province":"Nordrhein-Westfalen",
    "wof:name":"Wilfried Hommes",
    "wof:placetype":"venue"
},
  "geometry": {"coordinates":[6.3819870949,51.3215141296],"type":"Point"}
}