{
  "type": "Feature",
  "properties": {
    "iso:country":"DE",
    "sg:address":"Eisestr. 23",
    "sg:city":"Stuttgart",
    "sg:phone":"+49 711/7288484",
    "sg:postcode":"70567",
    "sg:province":"Baden-W\u00fcrttemberg",
    "wof:name":"H. Auchter",
    "wof:placetype":"venue"
},
  "geometry": {"coordinates":[9.1581048965,48.7283706665],"type":"Point"}
}