{
  "type": "Feature",
  "properties": {
    "iso:country":"DE",
    "sg:address":"Dorenwaid 79",
    "sg:city":"Gestratz",
    "sg:phone":"+49 8383/628",
    "sg:postcode":"88167",
    "sg:province":"Bayern",
    "wof:name":"G\u00e4stehaus Willi Schmid",
    "wof:placetype":"venue"
},
  "geometry": {"coordinates":[9.9948759079,47.6673545837],"type":"Point"}
}