{
  "type": "Feature",
  "properties": {
    "iso:country":"DE",
    "sg:address":"Hubertusstr. 25a",
    "sg:city":"Bonn",
    "sg:phone":"+49 4922/8251118",
    "sg:postcode":"53125",
    "sg:province":"Nordrhein-Westfalen",
    "wof:name":"Karl-heinz Spitzl Gmbh",
    "wof:placetype":"venue"
},
  "geometry": {"coordinates":[7.069276,50.693146],"type":"Point"}
}