{
  "type": "Feature",
  "properties": {
    "iso:country":"DE",
    "sg:address":"Louisenstr. 84",
    "sg:city":"Bad Homburg",
    "sg:postcode":"61348",
    "sg:province":"Hessen",
    "wof:name":"Eurocash Ag",
    "wof:placetype":"venue"
},
  "geometry": {"coordinates":[8.6208286285,50.2251205444],"type":"Point"}
}