{
  "type": "Feature",
  "properties": {
    "iso:country":"DE",
    "sg:address":"Katharinastr. 35",
    "sg:city":"Bochum",
    "sg:phone":"+49 4923/416011",
    "sg:postcode":"44793",
    "sg:province":"Nordrhein-Westfalen",
    "wof:name":"Raiffeisen Ruhrgebiet Eg",
    "wof:placetype":"venue"
},
  "geometry": {"coordinates":[7.2120108604,51.4755134583],"type":"Point"}
}