{
  "type": "Feature",
  "properties": {
    "iso:country":"DE",
    "sg:address":"Rheinstr. 151",
    "sg:city":"Wesseling",
    "sg:phone":"+49 2236/5167",
    "sg:postcode":"50389",
    "sg:province":"Nordrhein-Westfalen",
    "wof:name":"Im H\u00e4ppche Bei Jupp Und Linda",
    "wof:placetype":"venue"
},
  "geometry": {"coordinates":[7.0248179436,50.808681488],"type":"Point"}
}