{
  "type": "Feature",
  "properties": {
    "iso:country":"DE",
    "sg:address":"In Der S\u00fcdflur 5",
    "sg:city":"Bamberg",
    "sg:phone":"+49 951/912230",
    "sg:postcode":"96050",
    "sg:province":"Bayern",
    "wof:name":"G\u00d6hl Strassenbau Gmbh",
    "wof:placetype":"venue"
},
  "geometry": {"coordinates":[10.913199,49.877968],"type":"Point"}
}