{
  "type": "Feature",
  "properties": {
    "iso:country":"DE",
    "sg:address":"B\u00fcrgermeister-Schmitt-Str. 2-4",
    "sg:city":"Mainz",
    "sg:phone":"+49 6131/959210",
    "sg:postcode":"55129",
    "sg:province":"Rheinland-Pfalz",
    "wof:name":"G. Janss Steuerberater",
    "wof:placetype":"venue"
},
  "geometry": {"coordinates":[8.2803144455,49.9625015259],"type":"Point"}
}