{
  "type": "Feature",
  "properties": {
    "iso:country":"DE",
    "sg:address":"Hauptstr. 28",
    "sg:city":"Suderburg",
    "sg:phone":"+49 5826/277",
    "sg:postcode":"29556",
    "sg:province":"Niedersachsen",
    "wof:name":"Gerhard M\u00fcller",
    "wof:placetype":"venue"
},
  "geometry": {"coordinates":[10.4499492645,52.8960914612],"type":"Point"}
}