{
  "type": "Feature",
  "properties": {
    "iso:country":"DE",
    "sg:address":"Frankfurter Str. 49",
    "sg:city":"Braunschweig",
    "sg:phone":"+49 531/80072",
    "sg:postcode":"38122",
    "sg:province":"Niedersachsen",
    "wof:name":"Daimler Chrysler Bank Gmbh",
    "wof:placetype":"venue"
},
  "geometry": {"coordinates":[10.511441,52.246357],"type":"Point"}
}