{
  "type": "Feature",
  "properties": {
    "iso:country":"DE",
    "sg:address":"Auf der Mede 13",
    "sg:city":"Apelern",
    "sg:phone":"+49 5043/3127",
    "sg:postcode":"31552",
    "sg:province":"Niedersachsen",
    "wof:name":"Schulb\u00fccherei Brunhild P\u00e4tzold",
    "wof:placetype":"venue"
},
  "geometry": {"coordinates":[9.3399,52.289021],"type":"Point"}
}