{
  "type": "Feature",
  "properties": {
    "iso:country":"DE",
    "sg:address":"Kantstr. 107",
    "sg:city":"Berlin",
    "sg:phone":"+49 30/3275518",
    "sg:postcode":"10627",
    "sg:province":"Berlin",
    "wof:name":"Carl Schuhmann Kg",
    "wof:placetype":"venue"
},
  "geometry": {"coordinates":[13.3050079346,52.5065574646],"type":"Point"}
}