{
  "type": "Feature",
  "properties": {
    "iso:country":"DE",
    "sg:address":"Marktplatz 6",
    "sg:city":"Iphofen",
    "sg:phone":"+49 9323/3301",
    "sg:postcode":"97346",
    "sg:province":"Bayern",
    "wof:name":"Markt-apotheke E. K.",
    "wof:placetype":"venue"
},
  "geometry": {"coordinates":[10.260791,49.704533],"type":"Point"}
}