{
  "type": "Feature",
  "properties": {
    "iso:country":"DE",
    "sg:address":"Dorfstr. 10",
    "sg:city":"Werneck",
    "sg:phone":"+49 9722/8412",
    "sg:postcode":"97440",
    "sg:province":"Bayern",
    "wof:name":"Albin Sauer",
    "wof:placetype":"venue"
},
  "geometry": {"coordinates":[10.0941371918,50.0065841675],"type":"Point"}
}