{
  "type": "Feature",
  "properties": {
    "iso:country":"DE",
    "sg:address":"Baaken 6",
    "sg:city":"Werne",
    "sg:phone":"+49 2389/52363",
    "sg:postcode":"59368",
    "sg:province":"Nordrhein-Westfalen",
    "wof:name":"Ernst G\u00fcnnewig",
    "wof:placetype":"venue"
},
  "geometry": {"coordinates":[7.6185112,51.6643714905],"type":"Point"}
}