{
  "type": "Feature",
  "properties": {
    "iso:country":"DE",
    "sg:address":"Schatzbogen 52",
    "sg:city":"M\u00fcnchen",
    "sg:postcode":"81829",
    "sg:province":"Bayern",
    "wof:name":"Dussmann Ag & Co. Kgaa Zwndl. M\u00fcnchen",
    "wof:placetype":"venue"
},
  "geometry": {"coordinates":[11.6598033905,48.1327438354],"type":"Point"}
}