{
  "type": "Feature",
  "properties": {
    "iso:country":"DE",
    "sg:address":"Auf der Maate 8",
    "sg:city":"Alfeld",
    "sg:phone":"+49 5181/4522",
    "sg:postcode":"31061",
    "sg:province":"Niedersachsen",
    "wof:name":"Rolf Sievers",
    "wof:placetype":"venue"
},
  "geometry": {"coordinates":[9.8657064438,52.0008583069],"type":"Point"}
}