{
  "type": "Feature",
  "properties": {
    "iso:country":"DE",
    "sg:address":"Sch\u00fctzenstr. 60",
    "sg:city":"Solingen",
    "sg:phone":"+49 212/42142",
    "sg:postcode":"42659",
    "sg:province":"Nordrhein-Westfalen",
    "wof:name":"Bike & Sportshop Riedel Gmbh",
    "wof:placetype":"venue"
},
  "geometry": {"coordinates":[7.094603,51.164062],"type":"Point"}
}