{
  "type": "Feature",
  "properties": {
    "iso:country":"DE",
    "sg:address":"Lange Str. 110",
    "sg:city":"M\u00f6ssingen",
    "sg:phone":"+49 7473/26161",
    "sg:postcode":"72116",
    "sg:province":"Baden-W\u00fcrttemberg",
    "wof:name":"D. Haug & R. Kl\u00f6pfel Schreinerei",
    "wof:placetype":"venue"
},
  "geometry": {"coordinates":[9.051362,48.413109],"type":"Point"}
}