{
  "type": "Feature",
  "properties": {
    "iso:country":"DE",
    "sg:address":"Hindenburgstr. 7",
    "sg:city":"Laichingen",
    "sg:phone":"+49 7333/922117",
    "sg:postcode":"89150",
    "sg:province":"Baden-W\u00fcrttemberg",
    "wof:name":"Dr. E. Betz",
    "wof:placetype":"venue"
},
  "geometry": {"coordinates":[9.6862239838,48.4864311218],"type":"Point"}
}