{
  "type": "Feature",
  "properties": {
    "iso:country":"DE",
    "sg:address":"Obweg 44",
    "sg:city":"Pfronten",
    "sg:phone":"+49 8363/8594",
    "sg:postcode":"87459",
    "sg:province":"Bayern",
    "wof:name":"Philipp Trenkle",
    "wof:placetype":"venue"
},
  "geometry": {"coordinates":[10.5477523804,47.5796432495],"type":"Point"}
}