{
  "type": "Feature",
  "properties": {
    "iso:country":"DE",
    "sg:address":"Kirchgasse 101",
    "sg:city":"Wolfmannshausen",
    "sg:postcode":"98631",
    "sg:province":"Th\u00fcringen",
    "wof:name":"Gemeindeschwesterstation",
    "wof:placetype":"venue"
},
  "geometry": {"coordinates":[10.457526,50.428978],"type":"Point"}
}