{
  "type": "Feature",
  "properties": {
    "iso:country":"DE",
    "sg:address":"D\u00fcrener Str. 241",
    "sg:city":"K\u00f6ln",
    "sg:phone":"+49 221/404612",
    "sg:postcode":"50931",
    "sg:province":"Nordrhein-Westfalen",
    "wof:name":"Holger Kirschbaum Heilpraktiker",
    "wof:placetype":"venue"
},
  "geometry": {"coordinates":[6.9108200073,50.9287490845],"type":"Point"}
}