{
  "type": "Feature",
  "properties": {
    "iso:country":"DE",
    "sg:address":"Hauptstr. 48",
    "sg:city":"Ihringen",
    "sg:phone":"+49 7668/294",
    "sg:postcode":"79241",
    "sg:province":"Baden-W\u00fcrttemberg",
    "wof:name":"Weinstube Kiechle",
    "wof:placetype":"venue"
},
  "geometry": {"coordinates":[7.6791110039,48.0496101379],"type":"Point"}
}