{
  "type": "Feature",
  "properties": {
    "iso:country":"DE",
    "sg:address":"Niederhofheimer Str. 53 a",
    "sg:city":"Hofheim",
    "sg:phone":"+49 6192/96460",
    "sg:postcode":"65719",
    "sg:province":"Hessen",
    "wof:name":"Atw Automatisierungstechnik Wittek Gmbh",
    "wof:placetype":"venue"
},
  "geometry": {"coordinates":[8.4567184448,50.0936012268],"type":"Point"}
}