{
  "type": "Feature",
  "properties": {
    "iso:country":"DE",
    "sg:address":"Fritz-Reuter-Str. 34",
    "sg:city":"Erkrath",
    "sg:phone":"+49 2104/33185",
    "sg:postcode":"40699",
    "sg:province":"Nordrhein-Westfalen",
    "wof:name":"Sbkhochdruckreiniger Gmbh",
    "wof:placetype":"venue"
},
  "geometry": {"coordinates":[6.918774128,51.2033195496],"type":"Point"}
}