{
  "type": "Feature",
  "properties": {
    "iso:country":"DE",
    "sg:address":"Herzog-Max-Str. 2",
    "sg:city":"Aichach",
    "sg:phone":"+49 8251/3513",
    "sg:postcode":"86551",
    "sg:province":"Bayern",
    "wof:name":"Johann H\u00f6rmann",
    "wof:placetype":"venue"
},
  "geometry": {"coordinates":[11.153393,48.472099],"type":"Point"}
}