{
  "type": "Feature",
  "properties": {
    "iso:country":"DE",
    "sg:address":"St. Ulrichsplatz 3",
    "sg:city":"Dillingen",
    "sg:phone":"+49 9071/727142",
    "sg:postcode":"89407",
    "sg:province":"Bayern",
    "wof:name":"Cimt Telezentrum Dillingen Interactive Media And",
    "wof:placetype":"venue"
},
  "geometry": {"coordinates":[10.4905319214,48.5772514343],"type":"Point"}
}