{
  "type": "Feature",
  "properties": {
    "iso:country":"DE",
    "sg:address":"Lessingstr. 10",
    "sg:city":"Dinslaken",
    "sg:phone":"+49 2064/2840",
    "sg:postcode":"46535",
    "sg:province":"Nordrhein-Westfalen",
    "wof:name":"Karl Volz",
    "wof:placetype":"venue"
},
  "geometry": {"coordinates":[6.737848,51.563618],"type":"Point"}
}