{
  "type": "Feature",
  "properties": {
    "iso:country":"DE",
    "sg:address":"Lange Str. 21",
    "sg:city":"Moringen",
    "sg:phone":"+49 5554/2295",
    "sg:postcode":"37186",
    "sg:province":"Niedersachsen",
    "wof:name":"Fr. Piepenbrink",
    "wof:placetype":"venue"
},
  "geometry": {"coordinates":[9.87077,51.700562],"type":"Point"}
}