{
  "type": "Feature",
  "properties": {
    "iso:country":"DE",
    "sg:address":"An der Autobahn 8",
    "sg:city":"Hude",
    "sg:postcode":"27798",
    "sg:province":"Niedersachsen",
    "wof:name":"H. -g. Duesmann Vertriebsges. F\u00fcr Fenster Und T\u00fcren",
    "wof:placetype":"venue"
},
  "geometry": {"coordinates":[8.3600091934,53.0662193298],"type":"Point"}
}