{
  "type": "Feature",
  "properties": {
    "iso:country":"DE",
    "sg:address":"Handelmannweg 12",
    "sg:city":"Hamburg",
    "sg:phone":"+49 40/88128721",
    "sg:postcode":"22605",
    "sg:province":"Hamburg",
    "wof:name":"Herbert Petersen Architekt",
    "wof:placetype":"venue"
},
  "geometry": {"coordinates":[9.882972,53.549152],"type":"Point"}
}