{
  "type": "Feature",
  "properties": {
    "iso:country":"DE",
    "sg:address":"Br\u00fcderstr 5",
    "sg:city":"Kehl",
    "sg:phone":"+49 7851/955387",
    "sg:postcode":"77694",
    "sg:province":"Baden-W\u00fcrttemberg",
    "wof:name":"Ms Distribution",
    "wof:placetype":"venue"
},
  "geometry": {"coordinates":[7.821301,48.567791],"type":"Point"}
}