{
  "type": "Feature",
  "properties": {
    "iso:country":"DE",
    "sg:address":"Hauptstr. 13",
    "sg:city":"Pfullendorf",
    "sg:phone":"+49 7552/8213",
    "sg:postcode":"88630",
    "sg:province":"Baden-W\u00fcrttemberg",
    "wof:name":"Lamm",
    "wof:placetype":"venue"
},
  "geometry": {"coordinates":[9.257273674,47.9250946045],"type":"Point"}
}