{
  "type": "Feature",
  "properties": {
    "iso:country":"DE",
    "sg:address":"Gereonsdriesch 4",
    "sg:city":"K\u00f6ln",
    "sg:phone":"+49 221/134922",
    "sg:postcode":"50670",
    "sg:province":"Nordrhein-Westfalen",
    "wof:name":"Kath. Pfarramt St. Gereon",
    "wof:placetype":"venue"
},
  "geometry": {"coordinates":[6.9460558891,50.9428405762],"type":"Point"}
}