{
  "type": "Feature",
  "properties": {
    "iso:country":"DE",
    "sg:address":"Bischofsholer Damm 24",
    "sg:city":"Hannover",
    "sg:phone":"+49 511/810514",
    "sg:postcode":"30173",
    "sg:province":"Niedersachsen",
    "wof:name":"Irmgard Stahlhut",
    "wof:placetype":"venue"
},
  "geometry": {"coordinates":[9.7643957138,52.3680419922],"type":"Point"}
}