{
  "type": "Feature",
  "properties": {
    "iso:country":"DE",
    "sg:address":"Ernst-Th\u00e4lmann-Str. 11",
    "sg:city":"Helbra",
    "sg:postcode":"06311",
    "sg:province":"Sachsen-Anhalt",
    "wof:name":"B. Ahlborn",
    "wof:placetype":"venue"
},
  "geometry": {"coordinates":[11.4899196625,51.556930542],"type":"Point"}
}