{
  "type": "Feature",
  "properties": {
    "iso:country":"DE",
    "sg:address":"Feldmannskamp 13",
    "sg:city":"Wettringen",
    "sg:phone":"+49 172",
    "sg:postcode":"48493",
    "sg:province":"Nordrhein-Westfalen",
    "wof:name":"Medien-dienst Ewering",
    "wof:placetype":"venue"
},
  "geometry": {"coordinates":[7.3356289864,52.2218818665],"type":"Point"}
}