{
  "type": "Feature",
  "properties": {
    "iso:country":"DE",
    "sg:address":"Lange Str. 13",
    "sg:city":"Krakow",
    "sg:postcode":"18292",
    "sg:province":"Mecklenburg-Vorpommern",
    "wof:name":"Uwe Schade",
    "wof:placetype":"venue"
},
  "geometry": {"coordinates":[12.36573,53.682449],"type":"Point"}
}