{
  "type": "Feature",
  "properties": {
    "iso:country":"DE",
    "sg:address":"Im Reihing 3",
    "sg:city":"Trochtelfingen",
    "sg:phone":"+49 7124/92960",
    "sg:postcode":"72818",
    "sg:province":"Baden-W\u00fcrttemberg",
    "wof:name":"Daigler Gmbh",
    "wof:placetype":"venue"
},
  "geometry": {"coordinates":[9.272524,48.308201],"type":"Point"}
}