{
  "type": "Feature",
  "properties": {
    "iso:country":"DE",
    "sg:address":"Hausmannstr. 17",
    "sg:city":"Hanau",
    "sg:postcode":"63452",
    "sg:province":"Hessen",
    "wof:name":"Profibau Gmbh",
    "wof:placetype":"venue"
},
  "geometry": {"coordinates":[8.903926,50.141293],"type":"Point"}
}