{
  "type": "Feature",
  "properties": {
    "iso:country":"DE",
    "sg:address":"Schlo\u00dfstr. 5",
    "sg:city":"Koblenz",
    "sg:phone":"+49 261/37609",
    "sg:postcode":"56068",
    "sg:province":"Rheinland-Pfalz",
    "wof:name":"Rainer Schiffhauer Steuerberater",
    "wof:placetype":"venue"
},
  "geometry": {"coordinates":[7.5974311829,50.3561782837],"type":"Point"}
}