{
  "type": "Feature",
  "properties": {
    "iso:country":"DE",
    "sg:address":"Bielefelder Str. 41",
    "sg:city":"Lennestadt",
    "sg:phone":"+49 2721/120271",
    "sg:postcode":"57368",
    "sg:province":"Nordrhein-Westfalen",
    "wof:name":"Ulrich Baier Rechtsanwalt",
    "wof:placetype":"venue"
},
  "geometry": {"coordinates":[8.0659503937,51.1485710144],"type":"Point"}
}