{
  "type": "Feature",
  "properties": {
    "iso:country":"DE",
    "sg:address":"Schlo\u00dfweg 7",
    "sg:city":"M\u00fchlberg",
    "sg:phone":"+49 35342/354",
    "sg:postcode":"04931",
    "sg:province":"Brandenburg",
    "wof:name":"Dr. Hans-joachim J\u00e4ger Tierarzt",
    "wof:placetype":"venue"
},
  "geometry": {"coordinates":[13.211684227,51.433555603],"type":"Point"}
}