{
  "type": "Feature",
  "properties": {
    "iso:country":"DE",
    "sg:address":"Ortsstr. 14",
    "sg:city":"P\u00f6cking",
    "sg:phone":"+49 8151/16254",
    "sg:postcode":"82343",
    "sg:province":"Bayern",
    "wof:name":"Josef Benedikt",
    "wof:placetype":"venue"
},
  "geometry": {"coordinates":[11.28636,47.987179],"type":"Point"}
}