{
  "type": "Feature",
  "properties": {
    "iso:country":"DE",
    "sg:address":"Bonhoefferstr. 38",
    "sg:city":"Celle",
    "sg:phone":"+49 5141/950015",
    "sg:postcode":"29223",
    "sg:province":"Niedersachsen",
    "wof:name":"Cart-reisen",
    "wof:placetype":"venue"
},
  "geometry": {"coordinates":[10.0438261032,52.6380691528],"type":"Point"}
}