{
  "type": "Feature",
  "properties": {
    "iso:country":"DE",
    "sg:address":"Neue-Land-Str. 13a",
    "sg:city":"Hannover",
    "sg:phone":"+49 511/5490313",
    "sg:postcode":"30655",
    "sg:province":"Niedersachsen",
    "wof:name":"Wulf Wintha Maschinenhandels- Gmbh",
    "wof:placetype":"venue"
},
  "geometry": {"coordinates":[9.807691,52.395088],"type":"Point"}
}