{
  "type": "Feature",
  "properties": {
    "iso:country":"DE",
    "sg:address":"Herrenwies 30",
    "sg:city":"Forbach",
    "sg:phone":"+49 7226/232",
    "sg:postcode":"76596",
    "sg:province":"Baden-W\u00fcrttemberg",
    "wof:name":"Waldesruh",
    "wof:placetype":"venue"
},
  "geometry": {"coordinates":[8.275231,48.6577],"type":"Point"}
}