{
  "type": "Feature",
  "properties": {
    "iso:country":"DE",
    "sg:address":"Schillerstr. 21",
    "sg:city":"G\u00f6ttingen",
    "sg:phone":"+49 551/706210",
    "sg:postcode":"37083",
    "sg:province":"Niedersachsen",
    "wof:name":"Beratungs- Und Behandlungsstelle",
    "wof:placetype":"venue"
},
  "geometry": {"coordinates":[9.937637,51.525307],"type":"Point"}
}