{
  "type": "Feature",
  "properties": {
    "iso:country":"DE",
    "sg:address":"Am Lautrupsbach 8-10",
    "sg:city":"Flensburg",
    "sg:phone":"+49 4946/1144710",
    "sg:postcode":"24937",
    "sg:province":"Schleswig-Holstein",
    "wof:name":"A P Kloster Gmbh & Co Kg",
    "wof:placetype":"venue"
},
  "geometry": {"coordinates":[9.4417009354,54.792930603],"type":"Point"}
}