{
  "type": "Feature",
  "properties": {
    "iso:country":"DE",
    "sg:address":"Schlei\u00dfheimerstra\u00dfe 130",
    "sg:city":"M\u00fcnchen",
    "sg:phone":"+49 89",
    "sg:postcode":"80797",
    "sg:province":"Bayern",
    "wof:name":"Orthop\u00e4dische Gemeinschaftspraxis Am Nordbad / M\u00fcnchen",
    "wof:placetype":"venue"
},
  "geometry": {"coordinates":[11.563192,48.159569],"type":"Point"}
}