{
  "type": "Feature",
  "properties": {
    "iso:country":"DE",
    "sg:address":"Bensersieler Str. 4",
    "sg:city":"Esens",
    "sg:phone":"+49 4971/92970",
    "sg:postcode":"26427",
    "sg:province":"Niedersachsen",
    "wof:name":"Peter-friedrich-ludwig-stift",
    "wof:placetype":"venue"
},
  "geometry": {"coordinates":[7.613025,53.649967],"type":"Point"}
}