{
  "type": "Feature",
  "properties": {
    "iso:country":"DE",
    "sg:address":"Martin-Vierengel-Str. 1",
    "sg:city":"Miltenberg",
    "sg:postcode":"63897",
    "sg:province":"Bayern",
    "wof:name":"Frische Saat Gmbh",
    "wof:placetype":"venue"
},
  "geometry": {"coordinates":[9.2465,49.707481],"type":"Point"}
}