{
  "type": "Feature",
  "properties": {
    "iso:country":"DE",
    "sg:address":"Humboldtstr. 11",
    "sg:city":"Bottrop",
    "sg:phone":"+49 2041/688874",
    "sg:postcode":"46236",
    "sg:province":"Nordrhein-Westfalen",
    "wof:name":"Norbert Verf\u00fcrth Architekt",
    "wof:placetype":"venue"
},
  "geometry": {"coordinates":[6.931157,51.51712],"type":"Point"}
}