{
  "type": "Feature",
  "properties": {
    "iso:country":"DE",
    "sg:address":"Jennerstr. 15",
    "sg:city":"M\u00fcnchen",
    "sg:phone":"+49 89/8189660",
    "sg:postcode":"80999",
    "sg:province":"Bayern",
    "wof:name":"Adolf Kreim Steuerberater",
    "wof:placetype":"venue"
},
  "geometry": {"coordinates":[11.4461288452,48.1814537048],"type":"Point"}
}