{
  "type": "Feature",
  "properties": {
    "iso:country":"DE",
    "sg:address":"Maria-Ward-Str. 2",
    "sg:city":"Rattelsdorf",
    "sg:phone":"+49 9547/6290",
    "sg:postcode":"96179",
    "sg:province":"Bayern",
    "wof:name":"Michael Groh",
    "wof:placetype":"venue"
},
  "geometry": {"coordinates":[10.9006652832,50.0118942261],"type":"Point"}
}