{
  "type": "Feature",
  "properties": {
    "iso:country":"DE",
    "sg:address":"Kruppstr. 86",
    "sg:city":"Essen",
    "sg:phone":"+49 201/89205",
    "sg:postcode":"45145",
    "sg:province":"Nordrhein-Westfalen",
    "wof:name":"Sewa Verwaltungsges. F\u00fcr Sediment- Und",
    "wof:placetype":"venue"
},
  "geometry": {"coordinates":[6.996175766,51.4467658997],"type":"Point"}
}