{
  "type": "Feature",
  "properties": {
    "iso:country":"DE",
    "sg:address":"L\u00f6bauer Str. 49",
    "sg:city":"Leipzig",
    "sg:postcode":"04347",
    "sg:province":"Sachsen",
    "wof:name":"Jugendklubhaus J\u00f6rgen Schmidtchen",
    "wof:placetype":"venue"
},
  "geometry": {"coordinates":[12.4155225754,51.3568878174],"type":"Point"}
}