{
  "type": "Feature",
  "properties": {
    "iso:country":"DE",
    "sg:address":"Kreuzgang 9",
    "sg:city":"Burg",
    "sg:phone":"+49 3921/984633",
    "sg:postcode":"39288",
    "sg:province":"Sachsen-Anhalt",
    "wof:name":"Hannelore Schwabe Praxis F\u00fcr Physiotherapie",
    "wof:placetype":"venue"
},
  "geometry": {"coordinates":[11.851651,52.274036],"type":"Point"}
}