{
  "type": "Feature",
  "properties": {
    "iso:country":"DE",
    "sg:address":"Hauptstr. 31",
    "sg:city":"Kierspe",
    "sg:phone":"+49 2269/7899",
    "sg:postcode":"58566",
    "sg:province":"Nordrhein-Westfalen",
    "wof:name":"C. Rode Und S. Palka",
    "wof:placetype":"venue"
},
  "geometry": {"coordinates":[7.4988708496,51.1124572754],"type":"Point"}
}