{
  "type": "Feature",
  "properties": {
    "iso:country":"DE",
    "sg:address":"Plauensche Str. 10",
    "sg:city":"J\u00f6\u00dfnitz",
    "sg:phone":"+49 3741/521264",
    "sg:postcode":"08547",
    "sg:province":"Sachsen",
    "wof:name":"R. Goller",
    "wof:placetype":"venue"
},
  "geometry": {"coordinates":[12.138829,50.537121],"type":"Point"}
}