{
  "type": "Feature",
  "properties": {
    "iso:country":"DE",
    "sg:address":"Wellbrocker Weg 49",
    "sg:city":"Herford",
    "sg:phone":"+49 5221/16440",
    "sg:postcode":"32051",
    "sg:province":"Nordrhein-Westfalen",
    "wof:name":"Becker Fenstertechnik Gmbh & Co. Kg",
    "wof:placetype":"venue"
},
  "geometry": {"coordinates":[8.657194,52.125072],"type":"Point"}
}