{
  "type": "Feature",
  "properties": {
    "iso:country":"DE",
    "sg:address":"Carlsplatz 1",
    "sg:city":"\u00dcbach-Palenberg",
    "sg:phone":"+49 2451/93980",
    "sg:postcode":"52531",
    "sg:province":"Nordrhein-Westfalen",
    "wof:name":"W\u00f6bker Und Kollegen",
    "wof:placetype":"venue"
},
  "geometry": {"coordinates":[6.1194939613,50.9198150635],"type":"Point"}
}