{
  "type": "Feature",
  "properties": {
    "iso:country":"DE",
    "sg:address":"Lange Str. 21",
    "sg:city":"B\u00fcckeburg",
    "sg:phone":"+49 4957/222910",
    "sg:postcode":"31675",
    "sg:province":"Niedersachsen",
    "wof:name":"Commerzbank Ag",
    "wof:placetype":"venue"
},
  "geometry": {"coordinates":[9.04777,52.260242],"type":"Point"}
}