{
  "type": "Feature",
  "properties": {
    "iso:country":"DE",
    "sg:address":"Wannaer Weg 16",
    "sg:city":"Nordholz",
    "sg:phone":"+49 4741/7744",
    "sg:postcode":"27637",
    "sg:province":"Niedersachsen",
    "wof:name":"Rolf Horeis",
    "wof:placetype":"venue"
},
  "geometry": {"coordinates":[8.702576,53.743244],"type":"Point"}
}