{
  "type": "Feature",
  "properties": {
    "iso:country":"DE",
    "sg:address":"Bismarckstr. 56-62",
    "sg:city":"K\u00f6ln",
    "sg:phone":"+49 221/9514700",
    "sg:postcode":"50672",
    "sg:province":"Nordrhein-Westfalen",
    "wof:name":"Zwei Plus Zwei Marketing Gmbh",
    "wof:placetype":"venue"
},
  "geometry": {"coordinates":[6.933949,50.940952],"type":"Point"}
}