{
  "type": "Feature",
  "properties": {
    "iso:country":"DE",
    "sg:address":"Franz-Volk-Str. 22",
    "sg:city":"Offenburg",
    "sg:phone":"+49 781/75110",
    "sg:postcode":"77652",
    "sg:province":"Baden-W\u00fcrttemberg",
    "wof:name":"Walter Kubin",
    "wof:placetype":"venue"
},
  "geometry": {"coordinates":[7.9436011314,48.4780769348],"type":"Point"}
}