{
  "type": "Feature",
  "properties": {
    "iso:country":"DE",
    "sg:address":"Marienplatz 6",
    "sg:city":"Dingolfing",
    "sg:phone":"+49 8731/60898",
    "sg:postcode":"84130",
    "sg:province":"Bayern",
    "wof:name":"Bavariast\u00fcberl",
    "wof:placetype":"venue"
},
  "geometry": {"coordinates":[12.4986429214,48.6291046143],"type":"Point"}
}