{
  "type": "Feature",
  "properties": {
    "iso:country":"DE",
    "sg:address":"Alte Amberger Str. 31",
    "sg:city":"Grafenw\u00f6hr",
    "sg:phone":"+49 9641/2247",
    "sg:postcode":"92655",
    "sg:province":"Bayern",
    "wof:name":"Konrad Bauer",
    "wof:placetype":"venue"
},
  "geometry": {"coordinates":[11.903647,49.716488],"type":"Point"}
}