{
  "type": "Feature",
  "properties": {
    "iso:country":"DE",
    "sg:address":"Kipperstr. 80a",
    "sg:city":"Hagen",
    "sg:phone":"+49 2331/40891",
    "sg:postcode":"58135",
    "sg:province":"Nordrhein-Westfalen",
    "wof:name":"Kunststoffwerk Erdmann & Pickrun Gmbh",
    "wof:placetype":"venue"
},
  "geometry": {"coordinates":[7.404481,51.33477],"type":"Point"}
}