{
  "type": "Feature",
  "properties": {
    "iso:country":"DE",
    "sg:address":"Martin-Luther-Str. 11",
    "sg:city":"Frankfurt",
    "sg:phone":"+49 69/4960096",
    "sg:postcode":"60316",
    "sg:province":"Hessen",
    "wof:name":"Schwarzenberg Architekt",
    "wof:placetype":"venue"
},
  "geometry": {"coordinates":[8.697445,50.124836],"type":"Point"}
}