{
  "type": "Feature",
  "properties": {
    "iso:country":"DE",
    "sg:address":"G\u00fcterweg 89",
    "sg:city":"Walthersdorf",
    "sg:phone":"+49 3733/65859",
    "sg:postcode":"09474",
    "sg:province":"Sachsen",
    "wof:name":"Rainer Hofmann",
    "wof:placetype":"venue"
},
  "geometry": {"coordinates":[12.949042,50.542019],"type":"Point"}
}