{
  "type": "Feature",
  "properties": {
    "iso:country":"DE",
    "sg:address":"Radelandstr. 79",
    "sg:city":"Berlin",
    "sg:postcode":"13589",
    "sg:province":"Berlin",
    "wof:name":"Web Vision E. K.",
    "wof:placetype":"venue"
},
  "geometry": {"coordinates":[13.181517,52.558235],"type":"Point"}
}