{
  "type": "Feature",
  "properties": {
    "iso:country":"DE",
    "sg:address":"Im Riegel 18",
    "sg:city":"Neresheim",
    "sg:phone":"+49 7326/9639529",
    "sg:postcode":"73450",
    "sg:province":"Baden-W\u00fcrttemberg",
    "wof:name":"Gladius Werkzeug Gmbh",
    "wof:placetype":"venue"
},
  "geometry": {"coordinates":[10.3000812531,48.7589912415],"type":"Point"}
}