{
  "type": "Feature",
  "properties": {
    "iso:country":"DE",
    "sg:address":"Klingenberger Str. 4",
    "sg:city":"Flein",
    "sg:phone":"+49 7131/574257",
    "sg:postcode":"74223",
    "sg:province":"Baden-W\u00fcrttemberg",
    "wof:name":"Hans Heidenreich",
    "wof:placetype":"venue"
},
  "geometry": {"coordinates":[9.203153,49.104446],"type":"Point"}
}