{
  "type": "Feature",
  "properties": {
    "iso:country":"DE",
    "sg:address":"Rosenstr. 10",
    "sg:city":"Schwerin",
    "sg:phone":"+49 385/3261015",
    "sg:postcode":"19061",
    "sg:province":"Mecklenburg-Vorpommern",
    "wof:name":"Frank Koch",
    "wof:placetype":"venue"
},
  "geometry": {"coordinates":[11.417416,53.606575],"type":"Point"}
}