{
  "type": "Feature",
  "properties": {
    "iso:country":"DE",
    "sg:address":"Textorstr. 26",
    "sg:city":"Frankfurt",
    "sg:phone":"+49 69/613131",
    "sg:postcode":"60594",
    "sg:province":"Hessen",
    "wof:name":"Textorkeller",
    "wof:placetype":"venue"
},
  "geometry": {"coordinates":[8.6879386902,50.1022148132],"type":"Point"}
}