{
  "type": "Feature",
  "properties": {
    "iso:country":"DE",
    "sg:address":"L\u00f6rracher Str. 80",
    "sg:city":"Steinen",
    "sg:phone":"+49 7627/1310",
    "sg:postcode":"79585",
    "sg:province":"Baden-W\u00fcrttemberg",
    "wof:name":"Schwimmbad",
    "wof:placetype":"venue"
},
  "geometry": {"coordinates":[7.7244858742,47.6413803101],"type":"Point"}
}