{
  "type": "Feature",
  "properties": {
    "iso:country":"DE",
    "sg:address":"Breslauer Str. 6a",
    "sg:city":"Ottersberg",
    "sg:postcode":"28870",
    "sg:province":"Niedersachsen",
    "wof:name":"Pharmetic Ag",
    "wof:placetype":"venue"
},
  "geometry": {"coordinates":[9.160106,53.105663],"type":"Point"}
}