{
  "type": "Feature",
  "properties": {
    "iso:country":"DE",
    "sg:address":"Yorckstr. 2",
    "sg:city":"Pforzheim",
    "sg:phone":"+49 7231/53695",
    "sg:postcode":"75177",
    "sg:province":"Baden-W\u00fcrttemberg",
    "wof:name":"F\u00fcrst Bl\u00fccher",
    "wof:placetype":"venue"
},
  "geometry": {"coordinates":[8.7149038315,48.8983192444],"type":"Point"}
}