{
  "type": "Feature",
  "properties": {
    "iso:country":"DE",
    "sg:address":"Von-Th\u00fcnen-Str. 2",
    "sg:city":"Bremen",
    "sg:phone":"+49 421/485880",
    "sg:postcode":"28307",
    "sg:province":"Bremen",
    "wof:name":"Trafik Bremen Transportger\u00e4te Handels-gmbh",
    "wof:placetype":"venue"
},
  "geometry": {"coordinates":[8.96624,53.039459],"type":"Point"}
}