{
  "type": "Feature",
  "properties": {
    "iso:country":"DE",
    "sg:address":"Bertolt-Brecht-Str. 26",
    "sg:city":"Erftstadt",
    "sg:phone":"+49 2235/42644",
    "sg:postcode":"50374",
    "sg:province":"Nordrhein-Westfalen",
    "wof:name":"Helga Diefenthal",
    "wof:placetype":"venue"
},
  "geometry": {"coordinates":[6.8179340363,50.8037033081],"type":"Point"}
}