{
  "type": "Feature",
  "properties": {
    "iso:country":"DE",
    "sg:address":"Krugstr. 22",
    "sg:city":"Wolfsburg",
    "sg:phone":"+49 5308/910132",
    "sg:postcode":"38444",
    "sg:province":"Niedersachsen",
    "wof:name":"L. Wilde",
    "wof:placetype":"venue"
},
  "geometry": {"coordinates":[10.7467012405,52.3599700928],"type":"Point"}
}