{
  "type": "Feature",
  "properties": {
    "iso:country":"DE",
    "sg:address":"Ringstr. 50",
    "sg:city":"Kempten",
    "sg:phone":"+49 831/91112",
    "sg:postcode":"87439",
    "sg:province":"Bayern",
    "wof:name":"Dieter Meisburger",
    "wof:placetype":"venue"
},
  "geometry": {"coordinates":[10.281988,47.752476],"type":"Point"}
}