{
  "type": "Feature",
  "properties": {
    "iso:country":"DE",
    "sg:address":"H\u00f6rnumer Str. 22",
    "sg:city":"Rantum",
    "sg:phone":"+49 4651/23242",
    "sg:postcode":"25980",
    "sg:province":"Schleswig-Holstein",
    "wof:name":"Hotel Rantumer Hof",
    "wof:placetype":"venue"
},
  "geometry": {"coordinates":[8.3739547729,54.8927459717],"type":"Point"}
}