{
  "type": "Feature",
  "properties": {
    "iso:country":"DE",
    "sg:address":"Walddorfer Str. 51",
    "sg:city":"Altenriet",
    "sg:phone":"+49 7127/92340",
    "sg:postcode":"72657",
    "sg:province":"Baden-W\u00fcrttemberg",
    "wof:name":"Bstv Bau-stahl Verlegetechnik Gmbh",
    "wof:placetype":"venue"
},
  "geometry": {"coordinates":[9.218821,48.589954],"type":"Point"}
}