{
  "type": "Feature",
  "properties": {
    "iso:country":"DE",
    "sg:address":"Welzheimer Str. 6",
    "sg:city":"Gschwend",
    "sg:phone":"+49 7972/372",
    "sg:postcode":"74417",
    "sg:province":"Baden-W\u00fcrttemberg",
    "wof:name":"Horst Retter",
    "wof:placetype":"venue"
},
  "geometry": {"coordinates":[9.7422809601,48.9343719482],"type":"Point"}
}