{
  "type": "Feature",
  "properties": {
    "iso:country":"DE",
    "sg:address":"Exeterweg 32",
    "sg:city":"Bad Homburg",
    "sg:postcode":"61352",
    "sg:province":"Hessen",
    "wof:name":"L Service Gmbh",
    "wof:placetype":"venue"
},
  "geometry": {"coordinates":[8.6498270035,50.2223854065],"type":"Point"}
}