{
  "type": "Feature",
  "properties": {
    "iso:country":"DE",
    "sg:address":"Rosenstr. 11",
    "sg:city":"Hemdingen",
    "sg:phone":"+49 4123/4966",
    "sg:postcode":"25485",
    "sg:province":"Schleswig-Holstein",
    "wof:name":"Siegfried Schulz Immobilienmakler",
    "wof:placetype":"venue"
},
  "geometry": {"coordinates":[9.8352890015,53.759765625],"type":"Point"}
}