{
  "type": "Feature",
  "properties": {
    "iso:country":"DE",
    "sg:address":"Sielstr. 10",
    "sg:city":"Butjadingen",
    "sg:phone":"+49 4733/235",
    "sg:postcode":"26969",
    "sg:province":"Niedersachsen",
    "wof:name":"Friedrich Ulpts Seefischerei",
    "wof:placetype":"venue"
},
  "geometry": {"coordinates":[8.3506498337,53.5931892395],"type":"Point"}
}