{
  "type": "Feature",
  "properties": {
    "iso:country":"DE",
    "sg:address":"Am Silbersee",
    "sg:city":"Lohsa",
    "sg:postcode":"02999",
    "sg:province":"Sachsen",
    "wof:name":"Campingplatz",
    "wof:placetype":"venue"
},
  "geometry": {"coordinates":[14.392497,51.370041],"type":"Point"}
}