{
  "type": "Feature",
  "properties": {
    "iso:country":"DE",
    "sg:address":"Wallbrunnstr. 1",
    "sg:city":"L\u00f6rrach",
    "sg:phone":"+49 7621/13129",
    "sg:postcode":"79539",
    "sg:province":"Baden-W\u00fcrttemberg",
    "wof:name":"Angelika Reiss-meurer Porzellanhaus",
    "wof:placetype":"venue"
},
  "geometry": {"coordinates":[7.6619100571,47.6116828918],"type":"Point"}
}