{
  "type": "Feature",
  "properties": {
    "iso:country":"DE",
    "sg:address":"Altstadt 105",
    "sg:city":"Landshut",
    "sg:phone":"+49 871/22516",
    "sg:postcode":"84028",
    "sg:province":"Bayern",
    "wof:name":"Solar Betriebs- Und Beteiligungsgesellschaft F\u00fcr",
    "wof:placetype":"venue"
},
  "geometry": {"coordinates":[12.151965,48.538479],"type":"Point"}
}