{
  "type": "Feature",
  "properties": {
    "iso:country":"DE",
    "sg:address":"Babenhauser Str. 15",
    "sg:city":"Bielefeld",
    "sg:phone":"+49 521/885997",
    "sg:postcode":"33613",
    "sg:province":"Nordrhein-Westfalen",
    "wof:name":"Fr\u00fcchte Garten",
    "wof:placetype":"venue"
},
  "geometry": {"coordinates":[8.5141496658,52.0580596924],"type":"Point"}
}