{
  "type": "Feature",
  "properties": {
    "iso:country":"DE",
    "sg:address":"Bismarckstr. 82",
    "sg:city":"Hamburg",
    "sg:phone":"+49 40/4207790",
    "sg:postcode":"20253",
    "sg:province":"Hamburg",
    "wof:name":"Broadcast Engineering And Training Michael M\u00fccher",
    "wof:placetype":"venue"
},
  "geometry": {"coordinates":[9.9689559937,53.5763969421],"type":"Point"}
}