{
  "type": "Feature",
  "properties": {
    "iso:country":"DE",
    "sg:address":"Rosenplatz 1 a",
    "sg:city":"M\u00fcnster",
    "sg:phone":"+49 251/42816",
    "sg:postcode":"48143",
    "sg:province":"Nordrhein-Westfalen",
    "wof:name":"Josef Kontrup",
    "wof:placetype":"venue"
},
  "geometry": {"coordinates":[7.6211071014,51.9653244019],"type":"Point"}
}