{
  "type": "Feature",
  "properties": {
    "iso:country":"DE",
    "sg:address":"Leonberger Str. 24",
    "sg:city":"Ludwigsburg",
    "sg:phone":"+49 7141/923989",
    "sg:postcode":"71638",
    "sg:province":"Baden-W\u00fcrttemberg",
    "wof:name":"Hoffmeister",
    "wof:placetype":"venue"
},
  "geometry": {"coordinates":[9.190168,48.890602],"type":"Point"}
}