{
  "type": "Feature",
  "properties": {
    "iso:country":"DE",
    "sg:address":"Vor den Br\u00fcchen 1",
    "sg:city":"Olpe",
    "sg:phone":"+49 2761/62361",
    "sg:postcode":"57462",
    "sg:province":"Nordrhein-Westfalen",
    "wof:name":"Katholisches Pfarramt St. Georg",
    "wof:placetype":"venue"
},
  "geometry": {"coordinates":[7.9138040543,51.0215148926],"type":"Point"}
}