{
  "type": "Feature",
  "properties": {
    "iso:country":"DE",
    "sg:address":"Felsenstr. 46",
    "sg:city":"Heidenheim",
    "sg:phone":"+49 7321/44531",
    "sg:postcode":"89518",
    "sg:province":"Baden-W\u00fcrttemberg",
    "wof:name":"Body & Hair",
    "wof:placetype":"venue"
},
  "geometry": {"coordinates":[10.148579,48.680813],"type":"Point"}
}