{
  "type": "Feature",
  "properties": {
    "iso:country":"DE",
    "sg:address":"Am Schlart 1",
    "sg:city":"Bad Zwischenahn",
    "sg:phone":"+49 4403/58415",
    "sg:postcode":"26160",
    "sg:province":"Niedersachsen",
    "wof:name":"Roswitha Schaupeter Rechtsanw\u00e4ltin",
    "wof:placetype":"venue"
},
  "geometry": {"coordinates":[8.0313577652,53.1824111938],"type":"Point"}
}