{
  "type": "Feature",
  "properties": {
    "iso:country":"DE",
    "sg:address":"Am Markt 3",
    "sg:city":"H\u00f6xter",
    "sg:phone":"+49 5271/7503",
    "sg:postcode":"37671",
    "sg:province":"Nordrhein-Westfalen",
    "wof:name":"B\u00fcrgerstuben",
    "wof:placetype":"venue"
},
  "geometry": {"coordinates":[9.3823566437,51.7744216919],"type":"Point"}
}