{
  "type": "Feature",
  "properties": {
    "iso:country":"DE",
    "sg:address":"Steinweg 10",
    "sg:city":"Kellm\u00fcnz",
    "sg:postcode":"89293",
    "sg:province":"Bayern",
    "wof:name":"S & S Metalltechnik Ohg",
    "wof:placetype":"venue"
},
  "geometry": {"coordinates":[10.121755,48.126312],"type":"Point"}
}