{
  "type": "Feature",
  "properties": {
    "iso:country":"DE",
    "sg:address":"Steinb\u00fcschelweg 3",
    "sg:city":"Kurort Jonsdorf",
    "sg:phone":"+49 35844/70610",
    "sg:postcode":"02796",
    "sg:province":"Sachsen",
    "wof:name":"G\u00fcnter Kunze",
    "wof:placetype":"venue"
},
  "geometry": {"coordinates":[14.7086305618,50.857673645],"type":"Point"}
}