{
  "type": "Feature",
  "properties": {
    "iso:country":"DE",
    "sg:address":"Unterh\u00fctzer Str 11",
    "sg:city":"Remscheid",
    "sg:phone":"+49 2191/83451",
    "sg:postcode":"42857",
    "sg:province":"Nordrhein-Westfalen",
    "wof:name":"Kutsch",
    "wof:placetype":"venue"
},
  "geometry": {"coordinates":[7.167257,51.192333],"type":"Point"}
}