{
  "type": "Feature",
  "properties": {
    "iso:country":"DE",
    "sg:address":"Hinter der Mauer 6",
    "sg:city":"Immenhausen",
    "sg:phone":"+49 5673/2571",
    "sg:postcode":"34376",
    "sg:province":"Hessen",
    "wof:name":"Karl-ernst Berg",
    "wof:placetype":"venue"
},
  "geometry": {"coordinates":[9.4832019806,51.4286766052],"type":"Point"}
}