{
  "type": "Feature",
  "properties": {
    "iso:country":"DE",
    "sg:address":"Bautzner Str. 45-47",
    "sg:city":"Dresden",
    "sg:phone":"+49 351/808380",
    "sg:postcode":"01099",
    "sg:province":"Sachsen",
    "wof:name":"Recycling Dr. Steffen Sickert Gmbh",
    "wof:placetype":"venue"
},
  "geometry": {"coordinates":[13.754655838,51.0629806519],"type":"Point"}
}