{
  "type": "Feature",
  "properties": {
    "iso:country":"DE",
    "sg:address":"Winterstr. 44a",
    "sg:city":"Karlsruhe",
    "sg:phone":"+49 721/32456",
    "sg:postcode":"76137",
    "sg:province":"Baden-W\u00fcrttemberg",
    "wof:name":"Fritz Kirsten Kunstmaler",
    "wof:placetype":"venue"
},
  "geometry": {"coordinates":[8.409658,48.998123],"type":"Point"}
}