{
  "type": "Feature",
  "properties": {
    "iso:country":"DE",
    "sg:address":"Gutenbergstr. 21-23",
    "sg:city":"Neus\u00e4\u00df",
    "sg:phone":"+49 821/460510",
    "sg:postcode":"86356",
    "sg:province":"Bayern",
    "wof:name":"Columbus Treppen Gmbh",
    "wof:placetype":"venue"
},
  "geometry": {"coordinates":[10.8260173798,48.3976974487],"type":"Point"}
}