{
  "type": "Feature",
  "properties": {
    "iso:country":"DE",
    "sg:address":"Stuttgarter Str. 120",
    "sg:city":"Eislingen",
    "sg:phone":"+49 7161/999050",
    "sg:postcode":"73054",
    "sg:province":"Baden-W\u00fcrttemberg",
    "wof:name":"Weku Hofmann Fahrradgro\u00dfhandlung Gmbh",
    "wof:placetype":"venue"
},
  "geometry": {"coordinates":[9.6941251755,48.696182251],"type":"Point"}
}