{
  "type": "Feature",
  "properties": {
    "iso:country":"DE",
    "sg:address":"Neanderstr. 54",
    "sg:city":"Duisburg",
    "sg:phone":"+49 203/579934",
    "sg:postcode":"47139",
    "sg:province":"Nordrhein-Westfalen",
    "wof:name":"S. Mels",
    "wof:placetype":"venue"
},
  "geometry": {"coordinates":[6.7393279076,51.4720611572],"type":"Point"}
}