{
  "type": "Feature",
  "properties": {
    "iso:country":"DE",
    "sg:address":"Karlsburg 25",
    "sg:city":"Winnemark",
    "sg:phone":"+49 4644/442",
    "sg:postcode":"24398",
    "sg:province":"Schleswig-Holstein",
    "wof:name":"Wilhelm F\u00fclling",
    "wof:placetype":"venue"
},
  "geometry": {"coordinates":[9.95216,54.621368],"type":"Point"}
}