{
  "type": "Feature",
  "properties": {
    "iso:country":"DE",
    "sg:address":"Heidklift 10",
    "sg:city":"Bedburg",
    "sg:phone":"+49 2272/2412",
    "sg:postcode":"50181",
    "sg:province":"Nordrhein-Westfalen",
    "wof:name":"L\u00fcpges Getr\u00e4nke-vertrieb Gmbh",
    "wof:placetype":"venue"
},
  "geometry": {"coordinates":[6.536973,51.002525],"type":"Point"}
}