{
  "type": "Feature",
  "properties": {
    "iso:country":"DE",
    "sg:address":"Kaiser-Wilhelm-Str. 3",
    "sg:city":"B\u00fcnde",
    "sg:phone":"+49 5223/2494",
    "sg:postcode":"32257",
    "sg:province":"Nordrhein-Westfalen",
    "wof:name":"Rolf-udo Gizinski",
    "wof:placetype":"venue"
},
  "geometry": {"coordinates":[8.586203,52.198544],"type":"Point"}
}