{
  "type": "Feature",
  "properties": {
    "iso:country":"DE",
    "sg:address":"Eiffestr. 74",
    "sg:city":"Hamburg",
    "sg:phone":"+49 40/2517190",
    "sg:postcode":"20537",
    "sg:province":"Hamburg",
    "wof:name":"Toa Electronics Europe Gmbh",
    "wof:placetype":"venue"
},
  "geometry": {"coordinates":[10.0393848419,53.5523109436],"type":"Point"}
}