{
  "type": "Feature",
  "properties": {
    "iso:country":"DE",
    "sg:address":"Sonnenstr. 21",
    "sg:city":"Feldkirchen",
    "sg:phone":"+49 89/9032982",
    "sg:postcode":"85622",
    "sg:province":"Bayern",
    "wof:name":"P. Oswald Immobilienmakler",
    "wof:placetype":"venue"
},
  "geometry": {"coordinates":[11.7319107056,48.1504974365],"type":"Point"}
}