{
  "type": "Feature",
  "properties": {
    "iso:country":"DE",
    "sg:address":"Klaustaler Str. 28",
    "sg:city":"Berlin",
    "sg:postcode":"13187",
    "sg:province":"Berlin",
    "wof:name":"Wehi- Gmbh",
    "wof:placetype":"venue"
},
  "geometry": {"coordinates":[13.421382,52.575104],"type":"Point"}
}