{
  "type": "Feature",
  "properties": {
    "iso:country":"DE",
    "sg:address":"Hauptstr. 16",
    "sg:city":"Pei\u00dfenberg",
    "sg:phone":"+49 8803/3055",
    "sg:postcode":"82380",
    "sg:province":"Bayern",
    "wof:name":"M\u00f6bel-mit",
    "wof:placetype":"venue"
},
  "geometry": {"coordinates":[11.07825,47.802662],"type":"Point"}
}