{
  "type": "Feature",
  "properties": {
    "iso:country":"DE",
    "sg:address":"Pampusstr. 7",
    "sg:city":"Kaarst",
    "sg:phone":"+49 2131/519432",
    "sg:postcode":"41564",
    "sg:province":"Nordrhein-Westfalen",
    "wof:name":"Arnim Groh",
    "wof:placetype":"venue"
},
  "geometry": {"coordinates":[6.606006,51.196232],"type":"Point"}
}