{
  "type": "Feature",
  "properties": {
    "iso:country":"DE",
    "sg:address":"Bismarckring 21",
    "sg:city":"Wiesbaden",
    "sg:phone":"+49 611/308000",
    "sg:postcode":"65183",
    "sg:province":"Hessen",
    "wof:name":"Hedda Schmitter Rechtsanw\u00e4ltin",
    "wof:placetype":"venue"
},
  "geometry": {"coordinates":[8.2299203873,50.0801925659],"type":"Point"}
}