{
  "type": "Feature",
  "properties": {
    "iso:country":"DE",
    "sg:address":"Zschernichen 8",
    "sg:city":"Langenleuba-Niederhain",
    "sg:phone":"+49 34497/70276",
    "sg:postcode":"04618",
    "sg:province":"Th\u00fcringen",
    "wof:name":"I. Neef",
    "wof:placetype":"venue"
},
  "geometry": {"coordinates":[12.5517625809,50.9582901001],"type":"Point"}
}