{
  "type": "Feature",
  "properties": {
    "iso:country":"DE",
    "sg:address":"Franz-Mehring-Str. 133",
    "sg:city":"Zwickau",
    "sg:postcode":"08058",
    "sg:province":"Sachsen",
    "wof:name":"Rene Weck Handelsgesch\u00e4ft E. K.",
    "wof:placetype":"venue"
},
  "geometry": {"coordinates":[12.486155,50.74168],"type":"Point"}
}