{
  "type": "Feature",
  "properties": {
    "iso:country":"DE",
    "sg:address":"Rubensstr. 20a",
    "sg:city":"Wuppertal",
    "sg:phone":"+49 202/7388596",
    "sg:postcode":"42329",
    "sg:province":"Nordrhein-Westfalen",
    "wof:name":"Impulse E. V.",
    "wof:placetype":"venue"
},
  "geometry": {"coordinates":[7.0680718422,51.2287559509],"type":"Point"}
}