{
  "type": "Feature",
  "properties": {
    "iso:country":"DE",
    "sg:address":"K\u00f6lner Str. 68",
    "sg:city":"Hellenthal",
    "sg:phone":"+49 2482/2265",
    "sg:postcode":"53940",
    "sg:province":"Nordrhein-Westfalen",
    "wof:name":"Gustav Piehler",
    "wof:placetype":"venue"
},
  "geometry": {"coordinates":[6.441148,50.490566],"type":"Point"}
}