{
  "type": "Feature",
  "properties": {
    "iso:country":"DE",
    "sg:address":"Betzenh\u00f6lle 31",
    "sg:city":"Neunkirchen",
    "sg:phone":"+49 6821/982810",
    "sg:postcode":"66538",
    "sg:province":"Saarland",
    "wof:name":"Ebert Renaturierung Gmbh",
    "wof:placetype":"venue"
},
  "geometry": {"coordinates":[7.165724,49.336937],"type":"Point"}
}