{
  "type": "Feature",
  "properties": {
    "iso:country":"DE",
    "sg:address":"Am Markt 19",
    "sg:city":"Pirna",
    "sg:phone":"+49 3501/529363",
    "sg:postcode":"01796",
    "sg:province":"Sachsen",
    "wof:name":"Wei\u00dfer Schwan",
    "wof:placetype":"venue"
},
  "geometry": {"coordinates":[13.9413194656,50.9627342224],"type":"Point"}
}