{
  "type": "Feature",
  "properties": {
    "iso:country":"DE",
    "sg:address":"Am Ilmbach 22",
    "sg:city":"Leutenberg",
    "sg:phone":"+49 36734/22325",
    "sg:postcode":"07338",
    "sg:province":"Th\u00fcringen",
    "wof:name":"Harry Hinkelmann",
    "wof:placetype":"venue"
},
  "geometry": {"coordinates":[11.453194,50.564133],"type":"Point"}
}