{
  "type": "Feature",
  "properties": {
    "iso:country":"DE",
    "sg:address":"Reusaer Waldhaus 1",
    "sg:city":"Plauen",
    "sg:phone":"+49 3741/472811",
    "sg:postcode":"08529",
    "sg:province":"Sachsen",
    "wof:name":"Jugendherberge Reusaer Waldhaus",
    "wof:placetype":"venue"
},
  "geometry": {"coordinates":[12.1563692093,50.4862518311],"type":"Point"}
}