{
  "type": "Feature",
  "properties": {
    "iso:country":"DE",
    "sg:address":"Moselstr. 1",
    "sg:city":"Castrop-Rauxel",
    "sg:phone":"+49 2305/973700",
    "sg:postcode":"44579",
    "sg:province":"Nordrhein-Westfalen",
    "wof:name":"Ruhrbaustoffwerke Gmbh & Co. Kg",
    "wof:placetype":"venue"
},
  "geometry": {"coordinates":[7.29589,51.587593],"type":"Point"}
}