{
  "type": "Feature",
  "properties": {
    "iso:country":"DE",
    "sg:address":"Alleenweg 1",
    "sg:city":"Bad D\u00fcrrheim",
    "sg:phone":"+49 7726/5735",
    "sg:postcode":"78073",
    "sg:province":"Baden-W\u00fcrttemberg",
    "wof:name":"Haus Rieble",
    "wof:placetype":"venue"
},
  "geometry": {"coordinates":[8.5302734375,48.0153694153],"type":"Point"}
}