{
  "type": "Feature",
  "properties": {
    "iso:country":"DE",
    "sg:address":"Angerbergstr. 66",
    "sg:city":"Bleicherode",
    "sg:phone":"+49 36338/42187",
    "sg:postcode":"99752",
    "sg:province":"Th\u00fcringen",
    "wof:name":"Elektro-becker-sanit\u00e4r Gmbh",
    "wof:placetype":"venue"
},
  "geometry": {"coordinates":[10.5690813065,51.4363365173],"type":"Point"}
}