{
  "type": "Feature",
  "properties": {
    "iso:country":"DE",
    "sg:address":"Im Oberdorf 34",
    "sg:city":"Twistringen",
    "sg:phone":"+49 4243/8034",
    "sg:postcode":"27239",
    "sg:province":"Niedersachsen",
    "wof:name":"Otto Bavendiek",
    "wof:placetype":"venue"
},
  "geometry": {"coordinates":[8.645088,52.787987],"type":"Point"}
}