{
  "type": "Feature",
  "properties": {
    "iso:country":"DE",
    "sg:address":"Duisburger Str. 402",
    "sg:city":"Duisburg",
    "sg:phone":"+49 2066/56364",
    "sg:postcode":"47198",
    "sg:province":"Nordrhein-Westfalen",
    "wof:name":"Johann Heckes",
    "wof:placetype":"venue"
},
  "geometry": {"coordinates":[6.6957759857,51.4584999084],"type":"Point"}
}