{
  "type": "Feature",
  "properties": {
    "iso:country":"DE",
    "sg:address":"Tulpenstr. 1",
    "sg:city":"Hannover",
    "sg:phone":"+49 511/7010663",
    "sg:postcode":"30167",
    "sg:province":"Niedersachsen",
    "wof:name":"Wilkening & Blase",
    "wof:placetype":"venue"
},
  "geometry": {"coordinates":[9.7240600586,52.3850517273],"type":"Point"}
}