{
  "type": "Feature",
  "properties": {
    "iso:country":"DE",
    "sg:address":"Leipziger Str. 349",
    "sg:city":"Kassel",
    "sg:phone":"+49 4956/1951550",
    "sg:postcode":"34123",
    "sg:province":"Hessen",
    "wof:name":"Uwe Folkerts",
    "wof:placetype":"venue"
},
  "geometry": {"coordinates":[9.550321,51.295429],"type":"Point"}
}