{
  "type": "Feature",
  "properties": {
    "iso:country":"DE",
    "sg:address":"Am Str\u00fccksken 32",
    "sg:city":"Duisburg",
    "sg:phone":"+49 2065/4110",
    "sg:postcode":"47228",
    "sg:province":"Nordrhein-Westfalen",
    "wof:name":"Transamerica Trailer Leasing Gmbh",
    "wof:placetype":"venue"
},
  "geometry": {"coordinates":[6.701538,51.417683],"type":"Point"}
}