{
  "type": "Feature",
  "properties": {
    "iso:country":"DE",
    "sg:address":"Winzerstr. 9",
    "sg:city":"Kolitzheim",
    "sg:phone":"+49 9381/802683",
    "sg:postcode":"97509",
    "sg:province":"Bayern",
    "wof:name":"Adtur Finanz Innovationen Gmbh",
    "wof:placetype":"venue"
},
  "geometry": {"coordinates":[10.1950531006,49.9049491882],"type":"Point"}
}