{
  "type": "Feature",
  "properties": {
    "iso:country":"DE",
    "sg:address":"Am Hang 6",
    "sg:city":"Hungen",
    "sg:phone":"+49 6036/2676",
    "sg:postcode":"35410",
    "sg:province":"Hessen",
    "wof:name":"Angela Und Klaus Bayer",
    "wof:placetype":"venue"
},
  "geometry": {"coordinates":[8.8295793533,50.4407081604],"type":"Point"}
}