{
  "type": "Feature",
  "properties": {
    "iso:country":"DE",
    "sg:address":"Ellerstr. 172",
    "sg:city":"D\u00fcsseldorf",
    "sg:postcode":"40227",
    "sg:province":"Nordrhein-Westfalen",
    "wof:name":"Mm-trend Gmbh",
    "wof:placetype":"venue"
},
  "geometry": {"coordinates":[6.803156,51.214184],"type":"Point"}
}