{
  "type": "Feature",
  "properties": {
    "iso:country":"DE",
    "sg:address":"Markgrafenstr. 5",
    "sg:city":"Dielheim",
    "sg:phone":"+49 6222/73151",
    "sg:postcode":"69234",
    "sg:province":"Baden-W\u00fcrttemberg",
    "wof:name":"Winzergenossenschaft Eg",
    "wof:placetype":"venue"
},
  "geometry": {"coordinates":[8.73453,49.288784],"type":"Point"}
}