{
  "type": "Feature",
  "properties": {
    "iso:country":"DE",
    "sg:address":"Lengerckestieg 7",
    "sg:city":"Hamburg",
    "sg:phone":"+49 40/6770037",
    "sg:postcode":"22041",
    "sg:province":"Hamburg",
    "wof:name":"Cpw-rahlstedt Ohg",
    "wof:placetype":"venue"
},
  "geometry": {"coordinates":[10.069184,53.576683],"type":"Point"}
}