{
  "type": "Feature",
  "properties": {
    "iso:country":"DE",
    "sg:address":"Buttermarkt 5-7",
    "sg:city":"K\u00f6ln",
    "sg:phone":"+49 221/2581383",
    "sg:postcode":"50667",
    "sg:province":"Nordrhein-Westfalen",
    "wof:name":"Angelsport-gees",
    "wof:placetype":"venue"
},
  "geometry": {"coordinates":[6.962229,50.936916],"type":"Point"}
}