{
  "type": "Feature",
  "properties": {
    "iso:country":"DE",
    "sg:address":"Skagerrakstr. 35 a",
    "sg:city":"Gelsenkirchen",
    "sg:phone":"+49 209/144412",
    "sg:postcode":"45888",
    "sg:province":"Nordrhein-Westfalen",
    "wof:name":"Herbert Zimmermann Praxis F\u00fcr Physikalische",
    "wof:placetype":"venue"
},
  "geometry": {"coordinates":[7.128433,51.517731],"type":"Point"}
}