{
  "type": "Feature",
  "properties": {
    "iso:country":"DE",
    "sg:address":"Schleifer Weg 2",
    "sg:city":"Neusch\u00f6nau",
    "sg:phone":"+49 8552/91778",
    "sg:postcode":"94556",
    "sg:province":"Bayern",
    "wof:name":"Pension Fohlenhof",
    "wof:placetype":"venue"
},
  "geometry": {"coordinates":[13.47078228,48.8999328613],"type":"Point"}
}