{
  "type": "Feature",
  "properties": {
    "iso:country":"DE",
    "sg:address":"Langenkamp 8",
    "sg:city":"Essen",
    "sg:phone":"+49 171 8584665",
    "sg:postcode":"45147",
    "sg:province":"Nordrhein-Westfalen",
    "wof:name":"1&1 Firstclass E-shops, Professionelle Internet-l\u00f6sungen",
    "wof:placetype":"venue"
},
  "geometry": {"coordinates":[6.9731221199,51.4397544861],"type":"Point"}
}