{
  "type": "Feature",
  "properties": {
    "iso:country":"DE",
    "sg:address":"Brunnenstr. 4",
    "sg:city":"Tuttlingen",
    "sg:phone":"+49 7461/73016",
    "sg:postcode":"78532",
    "sg:province":"Baden-W\u00fcrttemberg",
    "wof:name":"Trenkler B\u00fcrotechnik Gmbh",
    "wof:placetype":"venue"
},
  "geometry": {"coordinates":[8.8222818375,47.9831771851],"type":"Point"}
}