{
  "type": "Feature",
  "properties": {
    "iso:country":"DE",
    "sg:address":"Karlstr. 2",
    "sg:city":"Heyerode",
    "sg:phone":"+49 36024/52686",
    "sg:postcode":"99988",
    "sg:province":"Th\u00fcringen",
    "wof:name":"Michael Henning",
    "wof:placetype":"venue"
},
  "geometry": {"coordinates":[10.318336,51.163479],"type":"Point"}
}