{
  "type": "Feature",
  "properties": {
    "iso:country":"DE",
    "sg:address":"Goethestr. 20",
    "sg:city":"Zeil",
    "sg:phone":"+49 9524/6224",
    "sg:postcode":"97475",
    "sg:province":"Bayern",
    "wof:name":"Georg Scheuring",
    "wof:placetype":"venue"
},
  "geometry": {"coordinates":[10.595711,50.01461],"type":"Point"}
}