{
  "type": "Feature",
  "properties": {
    "iso:country":"DE",
    "sg:address":"Holunderweg 16",
    "sg:city":"Steinheim",
    "sg:phone":"+49 7329/5291",
    "sg:postcode":"89555",
    "sg:province":"Baden-W\u00fcrttemberg",
    "wof:name":"Rainer Niederberger Ingenieur",
    "wof:placetype":"venue"
},
  "geometry": {"coordinates":[10.0624809265,48.6965637207],"type":"Point"}
}