{
  "type": "Feature",
  "properties": {
    "iso:country":"DE",
    "sg:address":"K\u00fcrenzer Str. 60",
    "sg:city":"Berlin",
    "sg:phone":"+49 30/5406209",
    "sg:postcode":"12681",
    "sg:province":"Berlin",
    "wof:name":"G\u00fcnter Nicke",
    "wof:placetype":"venue"
},
  "geometry": {"coordinates":[13.534988,52.517033],"type":"Point"}
}