{
  "type": "Feature",
  "properties": {
    "iso:country":"DE",
    "sg:address":"Oranienstr. 10",
    "sg:city":"Berlin",
    "sg:phone":"+49 30/2170685",
    "sg:postcode":"10997",
    "sg:province":"Berlin",
    "wof:name":"Prestige Augenoptik Gmbh",
    "wof:placetype":"venue"
},
  "geometry": {"coordinates":[13.4241790771,52.5000762939],"type":"Point"}
}