{
  "type": "Feature",
  "properties": {
    "iso:country":"DE",
    "sg:address":"Puschkinstr. 28e",
    "sg:city":"Frankfurt",
    "sg:phone":"+49 335/504381",
    "sg:postcode":"15236",
    "sg:province":"Brandenburg",
    "wof:name":"Idoma Gmbh",
    "wof:placetype":"venue"
},
  "geometry": {"coordinates":[14.5330228806,52.3364067078],"type":"Point"}
}