{
  "type": "Feature",
  "properties": {
    "iso:country":"DE",
    "sg:address":"Yorckstr. 28",
    "sg:city":"Leipzig",
    "sg:phone":"+49 341/4794481",
    "sg:postcode":"04159",
    "sg:province":"Sachsen",
    "wof:name":"G\u00fcnter Helbig",
    "wof:placetype":"venue"
},
  "geometry": {"coordinates":[12.3471517563,51.3696098328],"type":"Point"}
}