{
  "type": "Feature",
  "properties": {
    "iso:country":"DE",
    "sg:address":"Hammersbacher Str. 1",
    "sg:city":"Bruchk\u00f6bel",
    "sg:phone":"+49 6181/97180",
    "sg:postcode":"63486",
    "sg:province":"Hessen",
    "wof:name":"Miketta Bauzentrum Gmbh & Co. Verwaltungs Kg",
    "wof:placetype":"venue"
},
  "geometry": {"coordinates":[8.9222402573,50.1844825745],"type":"Point"}
}