{
  "type": "Feature",
  "properties": {
    "iso:country":"DE",
    "sg:address":"Eckener Weg 2",
    "sg:city":"Itzehoe",
    "sg:phone":"+49 4821/9687",
    "sg:postcode":"25524",
    "sg:province":"Schleswig-Holstein",
    "wof:name":"Wolfgang Rehfeldt",
    "wof:placetype":"venue"
},
  "geometry": {"coordinates":[9.5246248245,53.9282417297],"type":"Point"}
}