{
  "type": "Feature",
  "properties": {
    "iso:country":"DE",
    "sg:address":"Hechinger Str. 1",
    "sg:city":"Albstadt",
    "sg:phone":"+49 7432/171118",
    "sg:postcode":"72461",
    "sg:province":"Baden-W\u00fcrttemberg",
    "wof:name":"Kik",
    "wof:placetype":"venue"
},
  "geometry": {"coordinates":[9.017528,48.25478],"type":"Point"}
}