{
  "type": "Feature",
  "properties": {
    "iso:country":"DE",
    "sg:address":"Berliner Str. 14-16",
    "sg:city":"Kaiserslautern",
    "sg:phone":"+49 631/3703760",
    "sg:postcode":"67659",
    "sg:province":"Rheinland-Pfalz",
    "wof:name":"Autolackiererei Sch\u00e4fer Gmbh",
    "wof:placetype":"venue"
},
  "geometry": {"coordinates":[7.746201,49.443592],"type":"Point"}
}