{
  "type": "Feature",
  "properties": {
    "iso:country":"DE",
    "sg:address":"Bahnhofstr. 74",
    "sg:city":"Asperg",
    "sg:phone":"+49 7141/664740",
    "sg:postcode":"71679",
    "sg:province":"Baden-W\u00fcrttemberg",
    "wof:name":"Wilhelm Holzwarth",
    "wof:placetype":"venue"
},
  "geometry": {"coordinates":[9.144118,48.906906],"type":"Point"}
}