{
  "type": "Feature",
  "properties": {
    "iso:country":"DE",
    "sg:address":"Carl-Benz-Weg 12",
    "sg:city":"\u00dcberlingen",
    "sg:phone":"+49 7551/921950",
    "sg:postcode":"88662",
    "sg:province":"Baden-W\u00fcrttemberg",
    "wof:name":"Volksbank Eg",
    "wof:placetype":"venue"
},
  "geometry": {"coordinates":[9.171335,47.766193],"type":"Point"}
}