{
  "type": "Feature",
  "properties": {
    "iso:country":"DE",
    "sg:address":"Wei\u00dfachener Str. 46",
    "sg:city":"Bergen",
    "sg:postcode":"83346",
    "sg:province":"Bayern",
    "wof:name":"Dental Team Gmbh",
    "wof:placetype":"venue"
},
  "geometry": {"coordinates":[12.5800914764,47.8047332764],"type":"Point"}
}