{
  "type": "Feature",
  "properties": {
    "iso:country":"DE",
    "sg:address":"Habichtweg 12",
    "sg:city":"Krailling",
    "sg:phone":"+49 89/8561157",
    "sg:postcode":"82152",
    "sg:province":"Bayern",
    "wof:name":"Roger Naumann Gmbh",
    "wof:placetype":"venue"
},
  "geometry": {"coordinates":[11.403157,48.101833],"type":"Point"}
}