{
  "type": "Feature",
  "properties": {
    "iso:country":"DE",
    "sg:address":"F\u00fcrstenrieder Str. 245",
    "sg:city":"M\u00fcnchen",
    "sg:phone":"+49 89/7144004",
    "sg:postcode":"81377",
    "sg:province":"Bayern",
    "wof:name":"Schenk Immobilienmakler",
    "wof:placetype":"venue"
},
  "geometry": {"coordinates":[11.5026273727,48.1136322021],"type":"Point"}
}