{
  "type": "Feature",
  "properties": {
    "iso:country":"DE",
    "sg:address":"Am Pichelssee 7",
    "sg:city":"Berlin",
    "sg:postcode":"13595",
    "sg:province":"Berlin",
    "wof:name":"H - Plus - N Bautr\u00e4ger Gmbh",
    "wof:placetype":"venue"
},
  "geometry": {"coordinates":[13.200948,52.511189],"type":"Point"}
}