{
  "type": "Feature",
  "properties": {
    "iso:country":"DE",
    "sg:address":"Scheffoldstr. 83",
    "sg:city":"Schw\u00e4bisch Gm\u00fcnd",
    "sg:phone":"+49 7171/878582",
    "sg:postcode":"73529",
    "sg:province":"Baden-W\u00fcrttemberg",
    "wof:name":"Rite-track Deutschland E. K.",
    "wof:placetype":"venue"
},
  "geometry": {"coordinates":[9.827535,48.78561],"type":"Point"}
}