{
  "type": "Feature",
  "properties": {
    "iso:country":"DE",
    "sg:address":"Damm 2",
    "sg:city":"Oldenburg",
    "sg:phone":"+49 441/26726",
    "sg:postcode":"26135",
    "sg:province":"Niedersachsen",
    "wof:name":"Bohle Und True-bohle Rechtsanw\u00e4lte",
    "wof:placetype":"venue"
},
  "geometry": {"coordinates":[8.2170410156,53.1362075806],"type":"Point"}
}