{
  "type": "Feature",
  "properties": {
    "iso:country":"DE",
    "sg:address":"Karlstadter Str. 94",
    "sg:city":"Gem\u00fcnden",
    "sg:phone":"+49 9351/8583",
    "sg:postcode":"97737",
    "sg:province":"Bayern",
    "wof:name":"Erwin Bald",
    "wof:placetype":"venue"
},
  "geometry": {"coordinates":[9.7251138687,50.0248451233],"type":"Point"}
}