{
  "type": "Feature",
  "properties": {
    "iso:country":"DE",
    "sg:address":"Begonienstr. 3",
    "sg:city":"B\u00f6blingen",
    "sg:phone":"+49 7031/671553",
    "sg:postcode":"71034",
    "sg:province":"Baden-W\u00fcrttemberg",
    "wof:name":"Kurt J\u00fcnthner Steuerberater",
    "wof:placetype":"venue"
},
  "geometry": {"coordinates":[9.0073947906,48.6869888306],"type":"Point"}
}