{
  "type": "Feature",
  "properties": {
    "iso:country":"DE",
    "sg:address":"Kirchstr.",
    "sg:city":"Gie\u00dfen",
    "sg:phone":"+49 641/51447",
    "sg:postcode":"35396",
    "sg:province":"Hessen",
    "wof:name":"Ev. Pfarramt Gemeinde Wieseck 1",
    "wof:placetype":"venue"
},
  "geometry": {"coordinates":[8.7084560394,50.6051712036],"type":"Point"}
}