{
  "type": "Feature",
  "properties": {
    "iso:country":"DE",
    "sg:address":"Stader Str. 274",
    "sg:city":"Hamburg",
    "sg:postcode":"21075",
    "sg:province":"Hamburg",
    "wof:name":"Labenzke Beteiligungsges. Mbh",
    "wof:placetype":"venue"
},
  "geometry": {"coordinates":[9.926159,53.470829],"type":"Point"}
}