{
  "type": "Feature",
  "properties": {
    "iso:country":"DE",
    "sg:address":"Jahnstr 5",
    "sg:city":"Schonungen",
    "sg:phone":"+49 9721/75110",
    "sg:postcode":"97453",
    "sg:province":"Bayern",
    "wof:name":"Ant Gmbh",
    "wof:placetype":"venue"
},
  "geometry": {"coordinates":[10.30322,50.049717],"type":"Point"}
}