{
  "type": "Feature",
  "properties": {
    "iso:country":"DE",
    "sg:address":"Wiesbadener Str. 7",
    "sg:city":"Idstein",
    "sg:postcode":"65510",
    "sg:province":"Hessen",
    "wof:name":"F. Winter Finanzberater",
    "wof:placetype":"venue"
},
  "geometry": {"coordinates":[8.2671976089,50.2205581665],"type":"Point"}
}