{
  "type": "Feature",
  "properties": {
    "iso:country":"DE",
    "sg:address":"Rodheimer Str. 34",
    "sg:city":"Gie\u00dfen",
    "sg:phone":"+49 641/85566",
    "sg:postcode":"35398",
    "sg:province":"Hessen",
    "wof:name":"Digitron",
    "wof:placetype":"venue"
},
  "geometry": {"coordinates":[8.6638259888,50.589012146],"type":"Point"}
}