{
  "type": "Feature",
  "properties": {
    "iso:country":"DE",
    "sg:address":"Pestalozziweg 62",
    "sg:city":"Delligsen",
    "sg:phone":"+49 5187/1230",
    "sg:postcode":"31073",
    "sg:province":"Niedersachsen",
    "wof:name":"Contref Gmbh",
    "wof:placetype":"venue"
},
  "geometry": {"coordinates":[9.8009548187,51.9378738403],"type":"Point"}
}