{
  "type": "Feature",
  "properties": {
    "iso:country":"DE",
    "sg:address":"Riederinger Str. 16",
    "sg:city":"Kirchseeon",
    "sg:postcode":"85614",
    "sg:province":"Bayern",
    "wof:name":"Glp Gesells. F. Leiter-platten Gmbh & Co. Vertriebs Kg",
    "wof:placetype":"venue"
},
  "geometry": {"coordinates":[11.867190361,48.0757789612],"type":"Point"}
}