{
  "type": "Feature",
  "properties": {
    "iso:country":"DE",
    "sg:address":"Holzrichterweg 15G",
    "sg:city":"Dortmund",
    "sg:phone":"+49 231/7270595",
    "sg:postcode":"44229",
    "sg:province":"Nordrhein-Westfalen",
    "wof:name":"Herotec International Gmbh",
    "wof:placetype":"venue"
},
  "geometry": {"coordinates":[7.463666,51.443989],"type":"Point"}
}