{
  "type": "Feature",
  "properties": {
    "iso:country":"DE",
    "sg:address":"Hochstr. 75",
    "sg:city":"Sonsbeck",
    "sg:phone":"+49 2838/91966",
    "sg:postcode":"47665",
    "sg:province":"Nordrhein-Westfalen",
    "wof:name":"Adler-apotheke Inh. Ursula N\u00fcckel Und",
    "wof:placetype":"venue"
},
  "geometry": {"coordinates":[6.376646,51.607948],"type":"Point"}
}