{
  "type": "Feature",
  "properties": {
    "iso:country":"DE",
    "sg:address":"Filchnerstr. 16",
    "sg:city":"Neu-Ulm",
    "sg:phone":"+49 731/800180",
    "sg:postcode":"89231",
    "sg:province":"Bayern",
    "wof:name":"Tst-touchless Sensor Technology Ag",
    "wof:placetype":"venue"
},
  "geometry": {"coordinates":[10.005605,48.376064],"type":"Point"}
}