{
  "type": "Feature",
  "properties": {
    "iso:country":"DE",
    "sg:address":"Stresemannstr. 20",
    "sg:city":"Hagen",
    "sg:phone":"+49 2331/22864",
    "sg:postcode":"58095",
    "sg:province":"Nordrhein-Westfalen",
    "wof:name":"Restaurant Peking China",
    "wof:placetype":"venue"
},
  "geometry": {"coordinates":[7.462706089,51.3605766296],"type":"Point"}
}