{
  "type": "Feature",
  "properties": {
    "iso:country":"DE",
    "sg:address":"Hauptstr. 15",
    "sg:city":"Zahrensdorf",
    "sg:phone":"+49 38483/20501",
    "sg:postcode":"19412",
    "sg:province":"Mecklenburg-Vorpommern",
    "wof:name":"Verwaltung Landwirt- Schaftsgesellschaft",
    "wof:placetype":"venue"
},
  "geometry": {"coordinates":[11.672669,53.758457],"type":"Point"}
}