{
  "type": "Feature",
  "properties": {
    "iso:country":"DE",
    "sg:address":"Holsteiner Chaussee 437",
    "sg:city":"Ellerbek",
    "sg:phone":"+49 40/5501525",
    "sg:postcode":"25474",
    "sg:province":"Schleswig-Holstein",
    "wof:name":"Hermann Reumann",
    "wof:placetype":"venue"
},
  "geometry": {"coordinates":[9.90705,53.651478],"type":"Point"}
}