{
  "type": "Feature",
  "properties": {
    "iso:country":"DE",
    "sg:address":"Fritz-Erler-Str. 13",
    "sg:city":"Offenbach",
    "sg:phone":"+49 69/891898",
    "sg:postcode":"63073",
    "sg:province":"Hessen",
    "wof:name":"Redaktion Vkmb-notizen Verein F. Kurzschrift Masch.-",
    "wof:placetype":"venue"
},
  "geometry": {"coordinates":[8.8001813889,50.0858230591],"type":"Point"}
}