{
  "type": "Feature",
  "properties": {
    "iso:country":"DE",
    "sg:address":"L\u00fctjenseer Str. 13",
    "sg:city":"Trittau",
    "sg:phone":"+49 4154/999792",
    "sg:postcode":"22946",
    "sg:province":"Schleswig-Holstein",
    "wof:name":"Helmut Oesterling Rechtsanwalt",
    "wof:placetype":"venue"
},
  "geometry": {"coordinates":[10.4001684189,53.6206741333],"type":"Point"}
}