{
  "type": "Feature",
  "properties": {
    "iso:country":"DE",
    "sg:address":"Pyraser Str. 1",
    "sg:city":"Hilpoltstein",
    "sg:phone":"+49 9174/48456",
    "sg:postcode":"91161",
    "sg:province":"Bayern",
    "wof:name":"Richard Schr\u00f6der Ingenieur",
    "wof:placetype":"venue"
},
  "geometry": {"coordinates":[11.1690740585,49.1791496277],"type":"Point"}
}