{
  "type": "Feature",
  "properties": {
    "iso:country":"DE",
    "sg:address":"Birkenweg 8",
    "sg:city":"Gr\u00e4venwiesbach",
    "sg:phone":"+49 6086/645",
    "sg:postcode":"61279",
    "sg:province":"Hessen",
    "wof:name":"Pro Solution Gmbh",
    "wof:placetype":"venue"
},
  "geometry": {"coordinates":[8.4600057602,50.3911705017],"type":"Point"}
}