{
  "type": "Feature",
  "properties": {
    "iso:country":"DE",
    "sg:address":"Brandenburger Str. 22",
    "sg:city":"Bielefeld",
    "sg:phone":"+49 521/65468",
    "sg:postcode":"33602",
    "sg:province":"Nordrhein-Westfalen",
    "wof:name":"Hans M. Tidick E. K.",
    "wof:placetype":"venue"
},
  "geometry": {"coordinates":[8.53807,52.027672],"type":"Point"}
}