{
  "type": "Feature",
  "properties": {
    "iso:country":"DE",
    "sg:address":"Damaschkeallee",
    "sg:city":"Cottbus",
    "sg:phone":"+49 355/712358",
    "sg:postcode":"03042",
    "sg:province":"Brandenburg",
    "wof:name":"Vereinsgastst\u00e4tte Kgv Sonnenaufgang E. V.",
    "wof:placetype":"venue"
},
  "geometry": {"coordinates":[14.3544845581,51.7520751953],"type":"Point"}
}