{
  "type": "Feature",
  "properties": {
    "iso:country":"DE",
    "sg:address":"Eichendorffstr. 6",
    "sg:city":"Neugersdorf",
    "sg:postcode":"02727",
    "sg:province":"Sachsen",
    "wof:name":"Cookies Gastst\u00e4tten- Betriebs Gmbh",
    "wof:placetype":"venue"
},
  "geometry": {"coordinates":[14.6040010452,50.9782867432],"type":"Point"}
}