{
  "type": "Feature",
  "properties": {
    "iso:country":"DE",
    "sg:address":"K\u00f6lner Str. 2",
    "sg:city":"Solingen",
    "sg:phone":"+49 212/10714",
    "sg:postcode":"42651",
    "sg:province":"Nordrhein-Westfalen",
    "wof:name":"Armin Schwirzer Stahlwaren",
    "wof:placetype":"venue"
},
  "geometry": {"coordinates":[7.0800151825,51.1646652222],"type":"Point"}
}