{
  "type": "Feature",
  "properties": {
    "iso:country":"DE",
    "sg:address":"Keplerstr. 2",
    "sg:city":"Rheinstetten",
    "sg:postcode":"76287",
    "sg:province":"Baden-W\u00fcrttemberg",
    "wof:name":"Hurricane Diskotheken Und Gastst\u00e4tten-",
    "wof:placetype":"venue"
},
  "geometry": {"coordinates":[8.2752437592,48.958782196],"type":"Point"}
}