{
  "type": "Feature",
  "properties": {
    "iso:country":"DE",
    "sg:address":"Mitterweg 4",
    "sg:city":"Kirchroth",
    "sg:phone":"+49 9428/8723",
    "sg:postcode":"94356",
    "sg:province":"Bayern",
    "wof:name":"Josef Und Resi Fischer",
    "wof:placetype":"venue"
},
  "geometry": {"coordinates":[12.5538377762,48.967666626],"type":"Point"}
}