{
  "type": "Feature",
  "properties": {
    "iso:country":"DE",
    "sg:address":"Karl-Stirner-Str. 4",
    "sg:city":"Ellwangen",
    "sg:phone":"+49 7961/2765",
    "sg:postcode":"73479",
    "sg:province":"Baden-W\u00fcrttemberg",
    "wof:name":"R. Hengster",
    "wof:placetype":"venue"
},
  "geometry": {"coordinates":[10.125192,48.953949],"type":"Point"}
}