{
  "type": "Feature",
  "properties": {
    "iso:country":"DE",
    "sg:address":"Friedrichstr. 4",
    "sg:city":"Brilon",
    "sg:phone":"+49 2961/8449",
    "sg:postcode":"59929",
    "sg:province":"Nordrhein-Westfalen",
    "wof:name":"St. Engelbert-apotheke",
    "wof:placetype":"venue"
},
  "geometry": {"coordinates":[8.569009,51.396336],"type":"Point"}
}