{
  "type": "Feature",
  "properties": {
    "iso:country":"DE",
    "sg:address":"Scheffelstr. 9",
    "sg:city":"Immendingen",
    "sg:phone":"+49 7462/7114",
    "sg:postcode":"78194",
    "sg:province":"Baden-W\u00fcrttemberg",
    "wof:name":"Walter Dreher",
    "wof:placetype":"venue"
},
  "geometry": {"coordinates":[8.7319917679,47.9440116882],"type":"Point"}
}