{
  "type": "Feature",
  "properties": {
    "iso:country":"DE",
    "sg:address":"Poststr 5",
    "sg:city":"Breitungen",
    "sg:phone":"+49 2241/9070",
    "sg:postcode":"98597",
    "sg:province":"Th\u00fcringen",
    "wof:name":"Rhe H\u00e4ndel Engineering Gmbh & Co Kg",
    "wof:placetype":"venue"
},
  "geometry": {"coordinates":[7.20018,50.768421],"type":"Point"}
}