{
  "type": "Feature",
  "properties": {
    "iso:country":"DE",
    "sg:address":"Hauptstr. 90",
    "sg:city":"Schefflenz",
    "sg:phone":"+49 6293/95844",
    "sg:postcode":"74850",
    "sg:province":"Baden-W\u00fcrttemberg",
    "wof:name":"Meichelbeck Holzbau Gmbh",
    "wof:placetype":"venue"
},
  "geometry": {"coordinates":[9.280663,49.414169],"type":"Point"}
}