{
  "type": "Feature",
  "properties": {
    "iso:country":"DE",
    "sg:address":"M\u00fchlhagener Str. 20",
    "sg:city":"Murnau",
    "sg:phone":"+49 8841/99034",
    "sg:postcode":"82418",
    "sg:province":"Bayern",
    "wof:name":"Mp Disco Gmbh",
    "wof:placetype":"venue"
},
  "geometry": {"coordinates":[11.213536,47.667274],"type":"Point"}
}