{
  "type": "Feature",
  "properties": {
    "iso:country":"DE",
    "sg:address":"Willi-Mauthe-Weg 12",
    "sg:city":"Weilheim",
    "sg:phone":"+49 881/69339",
    "sg:postcode":"82362",
    "sg:province":"Bayern",
    "wof:name":"Gerhard Romann Anlageberater",
    "wof:placetype":"venue"
},
  "geometry": {"coordinates":[11.1535930634,47.8473548889],"type":"Point"}
}