{
  "type": "Feature",
  "properties": {
    "iso:country":"DE",
    "sg:address":"Bahnstr. 69",
    "sg:city":"Langen",
    "sg:phone":"+49 6103/22637",
    "sg:postcode":"63225",
    "sg:province":"Hessen",
    "wof:name":"Einhorn-apotheke Dr. Gabriele Huhle-kreutzer",
    "wof:placetype":"venue"
},
  "geometry": {"coordinates":[8.666122,49.990673],"type":"Point"}
}