{
  "type": "Feature",
  "properties": {
    "iso:country":"DE",
    "sg:address":"Joseph-Haydn-Str. 7",
    "sg:city":"Mannheim",
    "sg:phone":"+49 621/4310493",
    "sg:postcode":"68165",
    "sg:province":"Baden-W\u00fcrttemberg",
    "wof:name":"Dr. B\u00f6ringer & Partner Steuerberatungsges. Mbh",
    "wof:placetype":"venue"
},
  "geometry": {"coordinates":[8.4841356277,49.4777908325],"type":"Point"}
}