{
  "type": "Feature",
  "properties": {
    "iso:country":"DE",
    "sg:address":"Hohe Wende 11",
    "sg:city":"L\u00fcbeck",
    "sg:phone":"+49 4502/73733",
    "sg:postcode":"23570",
    "sg:province":"Schleswig-Holstein",
    "wof:name":"Dr. Werner Sch\u00f6n Rechtsanwalt",
    "wof:placetype":"venue"
},
  "geometry": {"coordinates":[10.8808383942,53.9762382507],"type":"Point"}
}