{
  "type": "Feature",
  "properties": {
    "iso:country":"DE",
    "sg:address":"Hallerstr. 34",
    "sg:city":"Wegberg",
    "sg:phone":"+49 2434/1224",
    "sg:postcode":"41844",
    "sg:province":"Nordrhein-Westfalen",
    "wof:name":"Gerhard Slykermann",
    "wof:placetype":"venue"
},
  "geometry": {"coordinates":[6.244776,51.173958],"type":"Point"}
}