{
  "type": "Feature",
  "properties": {
    "iso:country":"DE",
    "sg:address":"M\u00f6tscher Str. 19",
    "sg:city":"Bitburg",
    "sg:phone":"+49 6561/7818",
    "sg:postcode":"54634",
    "sg:province":"Rheinland-Pfalz",
    "wof:name":"H. Franzen Immobilienmakler",
    "wof:placetype":"venue"
},
  "geometry": {"coordinates":[6.5247092247,49.9674758911],"type":"Point"}
}