{
  "type": "Feature",
  "properties": {
    "iso:country":"DE",
    "sg:address":"Alte Poststr. 10",
    "sg:city":"Rehburg-Loccum",
    "sg:phone":"+49 5037/98540",
    "sg:postcode":"31547",
    "sg:province":"Niedersachsen",
    "wof:name":"Apotheke Bad Rehburg",
    "wof:placetype":"venue"
},
  "geometry": {"coordinates":[9.223389,52.438999],"type":"Point"}
}