{
  "type": "Feature",
  "properties": {
    "iso:country":"DE",
    "sg:address":"Wallstr. 68",
    "sg:city":"K\u00f6then",
    "sg:phone":"+49 3496/310012",
    "sg:postcode":"06366",
    "sg:province":"Sachsen-Anhalt",
    "wof:name":"H. L\u00e4rtz",
    "wof:placetype":"venue"
},
  "geometry": {"coordinates":[11.971392,51.750561],"type":"Point"}
}