{
  "type": "Feature",
  "properties": {
    "iso:country":"DE",
    "sg:address":"K\u00f6lner-Tor-Platz 3",
    "sg:city":"Wipperf\u00fcrth",
    "sg:phone":"+49 2267/7700",
    "sg:postcode":"51688",
    "sg:province":"Nordrhein-Westfalen",
    "wof:name":"Rosemarie Van Gerven Praxis F\u00fcr Krankengymnastik",
    "wof:placetype":"venue"
},
  "geometry": {"coordinates":[7.391396,51.115391],"type":"Point"}
}