{
  "type": "Feature",
  "properties": {
    "iso:country":"DE",
    "sg:address":"Gutenbergstr. 9",
    "sg:city":"Villingen-Schwenningen",
    "sg:postcode":"78056",
    "sg:province":"Baden-W\u00fcrttemberg",
    "wof:name":"Haba Vermittlungs-gmbh",
    "wof:placetype":"venue"
},
  "geometry": {"coordinates":[8.5443286896,48.0635375977],"type":"Point"}
}