{
  "type": "Feature",
  "properties": {
    "iso:country":"DE",
    "sg:address":"Londoner Ring 7",
    "sg:city":"Ludwigshafen",
    "sg:phone":"+49 621/664469",
    "sg:postcode":"67069",
    "sg:province":"Rheinland-Pfalz",
    "wof:name":"Neue Apotheke",
    "wof:placetype":"venue"
},
  "geometry": {"coordinates":[8.38891,49.541698],"type":"Point"}
}