{
  "type": "Feature",
  "properties": {
    "iso:country":"DE",
    "sg:address":"Kreuzweg 111",
    "sg:city":"D\u00fclmen",
    "sg:phone":"+49 2594/98797",
    "sg:postcode":"48249",
    "sg:province":"Nordrhein-Westfalen",
    "wof:name":"Jahnke Und Hahne Gmbh & Co.kg",
    "wof:placetype":"venue"
},
  "geometry": {"coordinates":[7.2884531021,51.8285369873],"type":"Point"}
}