{
  "type": "Feature",
  "properties": {
    "iso:country":"DE",
    "sg:address":"Am Kirchberg 1",
    "sg:city":"Anger",
    "sg:phone":"+49 8656/218",
    "sg:postcode":"83454",
    "sg:province":"Bayern",
    "wof:name":"Hotel Hochstaufen",
    "wof:placetype":"venue"
},
  "geometry": {"coordinates":[12.8582706451,47.8028450012],"type":"Point"}
}