{
  "type": "Feature",
  "properties": {
    "iso:country":"DE",
    "sg:address":"Vor dem Walburgertor 5",
    "sg:city":"Soest",
    "sg:phone":"+49 2921/8870",
    "sg:postcode":"59494",
    "sg:province":"Nordrhein-Westfalen",
    "wof:name":"City Markt",
    "wof:placetype":"venue"
},
  "geometry": {"coordinates":[8.1107673645,51.5784988403],"type":"Point"}
}