{
  "type": "Feature",
  "properties": {
    "iso:country":"DE",
    "sg:address":"Bahnhofstr. 22-24",
    "sg:city":"Schwarzenbach a d Saale",
    "sg:phone":"+49 9284/351",
    "sg:postcode":"95126",
    "sg:province":"Bayern",
    "wof:name":"W. Th\u00fcmmler Kg Vorm. Fr. Baecher",
    "wof:placetype":"venue"
},
  "geometry": {"coordinates":[11.9347801208,50.2223892212],"type":"Point"}
}