{
  "type": "Feature",
  "properties": {
    "iso:country":"DE",
    "sg:address":"Inntalstr. 36",
    "sg:city":"Bad F\u00fcssing",
    "sg:phone":"+49 8537/257",
    "sg:postcode":"94072",
    "sg:province":"Bayern",
    "wof:name":"Katholisches Pfarramt",
    "wof:placetype":"venue"
},
  "geometry": {"coordinates":[13.3240318298,48.3443374634],"type":"Point"}
}