{
  "type": "Feature",
  "properties": {
    "iso:country":"DE",
    "sg:address":"Harztorwall 21",
    "sg:city":"Wolfenb\u00fcttel",
    "sg:phone":"+49 5331/2566",
    "sg:postcode":"38300",
    "sg:province":"Niedersachsen",
    "wof:name":"Hartmut M\u00fcller",
    "wof:placetype":"venue"
},
  "geometry": {"coordinates":[10.540646,52.156757],"type":"Point"}
}