{
  "type": "Feature",
  "properties": {
    "iso:country":"DE",
    "sg:address":"Am Bruchwald 22",
    "sg:city":"Sulzbach",
    "sg:phone":"+49 4968/9790720",
    "sg:postcode":"66280",
    "sg:province":"Saarland",
    "wof:name":"Euro-locks Sicherheitseinrichtungen",
    "wof:placetype":"venue"
},
  "geometry": {"coordinates":[7.0820989609,49.2891960144],"type":"Point"}
}