{
  "type": "Feature",
  "properties": {
    "iso:country":"DE",
    "sg:address":"Immenhorstweg 5",
    "sg:city":"Emmerich",
    "sg:phone":"+49 2822/10880",
    "sg:postcode":"46446",
    "sg:province":"Nordrhein-Westfalen",
    "wof:name":"Erwin Vennemann",
    "wof:placetype":"venue"
},
  "geometry": {"coordinates":[6.2467098236,51.8553390503],"type":"Point"}
}