{
  "type": "Feature",
  "properties": {
    "iso:country":"DE",
    "sg:address":"Hufeisenstr. 77",
    "sg:city":"Damme",
    "sg:phone":"+49 5491/4569",
    "sg:postcode":"49401",
    "sg:province":"Niedersachsen",
    "wof:name":"Dr. Gerrit Tjeerd Strijkstra Tierarzt",
    "wof:placetype":"venue"
},
  "geometry": {"coordinates":[8.1585283279,52.4995880127],"type":"Point"}
}