{
  "type": "Feature",
  "properties": {
    "iso:country":"DE",
    "sg:address":"Firreler Str. 91",
    "sg:city":"Firrel",
    "sg:phone":"+49 4946/791",
    "sg:postcode":"26835",
    "sg:province":"Niedersachsen",
    "wof:name":"Heinz De Buhr Gmbh",
    "wof:placetype":"venue"
},
  "geometry": {"coordinates":[7.6727762222,53.3357696533],"type":"Point"}
}