{
  "type": "Feature",
  "properties": {
    "iso:country":"DE",
    "sg:address":"Siekweg 30 C",
    "sg:city":"G\u00f6ttingen",
    "sg:phone":"+49 4955/1998910",
    "sg:postcode":"37081",
    "sg:province":"Niedersachsen",
    "wof:name":"West-moebel Einrichtungshaus W.g. Pauli Gmbh & Co. Kg",
    "wof:placetype":"venue"
},
  "geometry": {"coordinates":[9.8902301788,51.5279006958],"type":"Point"}
}