{
  "type": "Feature",
  "properties": {
    "iso:country":"DE",
    "sg:address":"Frohe Zukunft 37",
    "sg:city":"Halle",
    "sg:postcode":"06118",
    "sg:province":"Sachsen-Anhalt",
    "wof:name":"Fs Massivhaus Gmbh",
    "wof:placetype":"venue"
},
  "geometry": {"coordinates":[11.999177,51.509411],"type":"Point"}
}