{
  "type": "Feature",
  "properties": {
    "iso:country":"DE",
    "sg:address":"Geer 79",
    "sg:city":"Coesfeld",
    "sg:phone":"+49 2546/98798",
    "sg:postcode":"48653",
    "sg:province":"Nordrhein-Westfalen",
    "wof:name":"W. Und B. Olesinski",
    "wof:placetype":"venue"
},
  "geometry": {"coordinates":[7.195397,51.898903],"type":"Point"}
}