{
  "type": "Feature",
  "properties": {
    "iso:country":"DE",
    "sg:address":"Industriestr. 31",
    "sg:city":"Nast\u00e4tten",
    "sg:phone":"+49 6772/93740",
    "sg:postcode":"56355",
    "sg:province":"Rheinland-Pfalz",
    "wof:name":"K. D. Voss H\u00e4utehandel Gmbh",
    "wof:placetype":"venue"
},
  "geometry": {"coordinates":[7.851178,50.196156],"type":"Point"}
}