{
  "type": "Feature",
  "properties": {
    "iso:country":"DE",
    "sg:address":"Heidackerstr. 11",
    "sg:city":"Langenfeld",
    "sg:postcode":"40764",
    "sg:province":"Nordrhein-Westfalen",
    "wof:name":"Www.bestattungshilfe24. De/ Gmbh",
    "wof:placetype":"venue"
},
  "geometry": {"coordinates":[6.9927,51.128227],"type":"Point"}
}