{
  "type": "Feature",
  "properties": {
    "iso:country":"DE",
    "sg:address":"Hirtenstr. 9",
    "sg:city":"Wennigsen",
    "sg:phone":"+49 5103/7776",
    "sg:postcode":"30974",
    "sg:province":"Niedersachsen",
    "wof:name":"Hirsch",
    "wof:placetype":"venue"
},
  "geometry": {"coordinates":[9.56956,52.273956],"type":"Point"}
}