{
  "type": "Feature",
  "properties": {
    "iso:country":"DE",
    "sg:address":"Nienburger Str. 36",
    "sg:city":"Rehden",
    "sg:phone":"+49 5446/634",
    "sg:postcode":"49453",
    "sg:province":"Niedersachsen",
    "wof:name":"Georg Hafer",
    "wof:placetype":"venue"
},
  "geometry": {"coordinates":[8.484131,52.609356],"type":"Point"}
}