{
  "type": "Feature",
  "properties": {
    "iso:country":"DE",
    "sg:address":"Giebinger Str. 2",
    "sg:city":"Fahrenzhausen",
    "sg:phone":"+49 8133/2395",
    "sg:postcode":"85777",
    "sg:province":"Bayern",
    "wof:name":"Landgasthof Spanbauer Inh. W. Kratzer",
    "wof:placetype":"venue"
},
  "geometry": {"coordinates":[11.5300445557,48.3573112488],"type":"Point"}
}