{
  "type": "Feature",
  "properties": {
    "iso:country":"DE",
    "sg:address":"Jahnstr. 29",
    "sg:city":"Mainhausen",
    "sg:phone":"+49 6182/922922",
    "sg:postcode":"63533",
    "sg:province":"Hessen",
    "wof:name":"Pwa Electronic Service- Und Vertriebs Gmbh",
    "wof:placetype":"venue"
},
  "geometry": {"coordinates":[8.9946298599,50.0216598511],"type":"Point"}
}