{
  "type": "Feature",
  "properties": {
    "iso:country":"DE",
    "sg:address":"Johann-von-Weerth-Str. 18",
    "sg:city":"Freiburg",
    "sg:phone":"+49 761/406826",
    "sg:postcode":"79100",
    "sg:province":"Baden-W\u00fcrttemberg",
    "wof:name":"Sylvia Mahler Und Hella Crone Praxis F\u00fcr Krankengymnastik",
    "wof:placetype":"venue"
},
  "geometry": {"coordinates":[7.838415,47.98587],"type":"Point"}
}