{
  "type": "Feature",
  "properties": {
    "iso:country":"DE",
    "sg:address":"Schlo\u00dfplatz 4",
    "sg:city":"Itzgrund",
    "sg:phone":"+49 9533/393",
    "sg:postcode":"96274",
    "sg:province":"Bayern",
    "wof:name":"Ev. Luth. Pfarramt",
    "wof:placetype":"venue"
},
  "geometry": {"coordinates":[10.8665151596,50.101436615],"type":"Point"}
}