{
  "type": "Feature",
  "properties": {
    "iso:country":"DE",
    "sg:address":"Hallgartenstr. 49",
    "sg:city":"Frankfurt",
    "sg:phone":"+49 69/459158",
    "sg:postcode":"60389",
    "sg:province":"Hessen",
    "wof:name":"Baumeister Josef Link",
    "wof:placetype":"venue"
},
  "geometry": {"coordinates":[8.697201,50.130024],"type":"Point"}
}