{
  "type": "Feature",
  "properties": {
    "iso:country":"DE",
    "sg:address":"Brodacker 14",
    "sg:city":"Wienhausen",
    "sg:phone":"+49 5082/1583",
    "sg:postcode":"29342",
    "sg:province":"Niedersachsen",
    "wof:name":"Er Transport Gmbh",
    "wof:placetype":"venue"
},
  "geometry": {"coordinates":[10.2542619705,52.5757102966],"type":"Point"}
}