{
  "type": "Feature",
  "properties": {
    "iso:country":"DE",
    "sg:address":"Motzstrasse 32",
    "sg:city":"Berlin",
    "sg:phone":"+49 30",
    "sg:postcode":"10777",
    "sg:province":"Berlin",
    "wof:name":"Motzbuch",
    "wof:placetype":"venue"
},
  "geometry": {"coordinates":[13.3473110199,52.4975967407],"type":"Point"}
}