{
  "type": "Feature",
  "properties": {
    "iso:country":"DE",
    "sg:address":"Droysenstr. 5",
    "sg:city":"Berlin",
    "sg:phone":"+49 30/3233003",
    "sg:postcode":"10629",
    "sg:province":"Berlin",
    "wof:name":"Arw Planungsgemeinschaft & Projektierung Gmbh",
    "wof:placetype":"venue"
},
  "geometry": {"coordinates":[13.300346,52.501621],"type":"Point"}
}