{
  "type": "Feature",
  "properties": {
    "iso:country":"DE",
    "sg:address":"D\u00fcsseldorfer Str. 113",
    "sg:city":"Ratingen",
    "sg:phone":"+49 2102/28877",
    "sg:postcode":"40878",
    "sg:province":"Nordrhein-Westfalen",
    "wof:name":"Parf\u00fcmerie-kosmetik Jasmin",
    "wof:placetype":"venue"
},
  "geometry": {"coordinates":[6.841696,51.292477],"type":"Point"}
}