{
  "type": "Feature",
  "properties": {
    "iso:country":"DE",
    "sg:address":"S\u00fcsterfeldstr. 81",
    "sg:city":"Aachen",
    "sg:phone":"+49 241/889730",
    "sg:postcode":"52072",
    "sg:province":"Nordrhein-Westfalen",
    "wof:name":"Dr. Kr\u00e4tzig Ingenieurgesellschaft Mbh",
    "wof:placetype":"venue"
},
  "geometry": {"coordinates":[6.063270092,50.7867660522],"type":"Point"}
}