{
  "type": "Feature",
  "properties": {
    "iso:country":"DE",
    "sg:address":"Kirchheimer Str. 20",
    "sg:city":"Lenningen",
    "sg:phone":"+49 7026/7002",
    "sg:postcode":"73252",
    "sg:province":"Baden-W\u00fcrttemberg",
    "wof:name":"G. Sailer",
    "wof:placetype":"venue"
},
  "geometry": {"coordinates":[9.4653358459,48.5605773926],"type":"Point"}
}