{
  "type": "Feature",
  "properties": {
    "iso:country":"DE",
    "sg:address":"Goldbachstr. 13",
    "sg:city":"N\u00fcrnberg",
    "sg:phone":"+49 911/401321",
    "sg:postcode":"90480",
    "sg:province":"Bayern",
    "wof:name":"Birgit K\u00fcfner",
    "wof:placetype":"venue"
},
  "geometry": {"coordinates":[11.1119356155,49.4454879761],"type":"Point"}
}