{
  "type": "Feature",
  "properties": {
    "iso:country":"DE",
    "sg:address":"Breite Str. 41",
    "sg:city":"Zerbst",
    "sg:phone":"+49 3923/786116",
    "sg:postcode":"39261",
    "sg:province":"Sachsen-Anhalt",
    "wof:name":"D. Quack",
    "wof:placetype":"venue"
},
  "geometry": {"coordinates":[12.0901689529,51.9649581909],"type":"Point"}
}