{
  "type": "Feature",
  "properties": {
    "iso:country":"DE",
    "sg:address":"Auf dem Flage 2",
    "sg:city":"D\u00f6tlingen",
    "sg:phone":"+49 4433/282",
    "sg:postcode":"27801",
    "sg:province":"Niedersachsen",
    "wof:name":"Hermann Vogt",
    "wof:placetype":"venue"
},
  "geometry": {"coordinates":[8.424443,52.930771],"type":"Point"}
}