{
  "type": "Feature",
  "properties": {
    "iso:country":"DE",
    "sg:address":"Koopmannstr. 23",
    "sg:city":"Duisburg",
    "sg:phone":"+49 203/4177884",
    "sg:postcode":"47138",
    "sg:province":"Nordrhein-Westfalen",
    "wof:name":"Emu Entwicklung Me\u00dftechnik Umwelt Gmbh",
    "wof:placetype":"venue"
},
  "geometry": {"coordinates":[6.7968530655,51.4671821594],"type":"Point"}
}