{
  "type": "Feature",
  "properties": {
    "iso:country":"DE",
    "sg:address":"Carl-Hamel-Str 15",
    "sg:city":"Chemnitz",
    "sg:phone":"+49 371/271990",
    "sg:postcode":"09116",
    "sg:province":"Sachsen",
    "wof:name":"Glumann Maschinenbau Ag",
    "wof:placetype":"venue"
},
  "geometry": {"coordinates":[12.883642,50.81316],"type":"Point"}
}