{
  "type": "Feature",
  "properties": {
    "iso:country":"DE",
    "sg:address":"Feldstr. 10a",
    "sg:city":"Bremerhaven",
    "sg:phone":"+49 471/35093",
    "sg:postcode":"27574",
    "sg:province":"Bremen",
    "wof:name":"Hartwig Menge",
    "wof:placetype":"venue"
},
  "geometry": {"coordinates":[8.602293,53.528362],"type":"Point"}
}