{
  "type": "Feature",
  "properties": {
    "iso:country":"DE",
    "sg:address":"Krummacherstr. 200",
    "sg:city":"Wuppertal",
    "sg:phone":"+49 202/713779",
    "sg:postcode":"42115",
    "sg:province":"Nordrhein-Westfalen",
    "wof:name":"D. Stede Steuerberater",
    "wof:placetype":"venue"
},
  "geometry": {"coordinates":[7.1046662331,51.2602043152],"type":"Point"}
}