{
  "type": "Feature",
  "properties": {
    "iso:country":"DE",
    "sg:address":"Appenweierer Str. 45",
    "sg:city":"Oberkirch",
    "sg:postcode":"77704",
    "sg:province":"Baden-W\u00fcrttemberg",
    "wof:name":"Arboreus Software Gmbh",
    "wof:placetype":"venue"
},
  "geometry": {"coordinates":[8.0683574677,48.5357246399],"type":"Point"}
}