{
  "type": "Feature",
  "properties": {
    "iso:country":"DE",
    "sg:address":"Platanenweg 9",
    "sg:city":"Nordkirchen",
    "sg:phone":"+49 2596/3476",
    "sg:postcode":"59394",
    "sg:province":"Nordrhein-Westfalen",
    "wof:name":"Schulz U. Kiene",
    "wof:placetype":"venue"
},
  "geometry": {"coordinates":[7.5217,51.736843],"type":"Point"}
}