{
  "type": "Feature",
  "properties": {
    "iso:country":"DE",
    "sg:address":"Nordstr. 8",
    "sg:city":"Wermelskirchen",
    "sg:phone":"+49 2196/5461",
    "sg:postcode":"42929",
    "sg:province":"Nordrhein-Westfalen",
    "wof:name":"Hans-joachim Stein Rechtsanwalt",
    "wof:placetype":"venue"
},
  "geometry": {"coordinates":[7.2101988792,51.1418457031],"type":"Point"}
}