{
  "type": "Feature",
  "properties": {
    "iso:country":"DE",
    "sg:address":"Soester Str. 29",
    "sg:city":"Erwitte",
    "sg:phone":"+49 2943/2445",
    "sg:postcode":"59597",
    "sg:province":"Nordrhein-Westfalen",
    "wof:name":"D & S Sandstrahltechnik Bertsch Gmbh & Co. Kg",
    "wof:placetype":"venue"
},
  "geometry": {"coordinates":[8.329909,51.611233],"type":"Point"}
}