{
  "type": "Feature",
  "properties": {
    "iso:country":"DE",
    "sg:address":"Friedrich-Ebert-Str 123",
    "sg:city":"Detmold",
    "sg:phone":"+49 5231/83689",
    "sg:postcode":"32760",
    "sg:province":"Nordrhein-Westfalen",
    "wof:name":"Waw Werbeagentur Delf P. M\u00f6ller Gmbh",
    "wof:placetype":"venue"
},
  "geometry": {"coordinates":[8.838716,51.924232],"type":"Point"}
}