{
  "type": "Feature",
  "properties": {
    "iso:country":"DE",
    "sg:address":"K\u00f6nigsbergstr. 4",
    "sg:city":"Gerolzhofen",
    "sg:phone":"+49 9382/8577",
    "sg:postcode":"97447",
    "sg:province":"Bayern",
    "wof:name":"Arnold B\u00f6rdlein Ingenieur Und Architekt",
    "wof:placetype":"venue"
},
  "geometry": {"coordinates":[10.348534,49.893345],"type":"Point"}
}