{
  "type": "Feature",
  "properties": {
    "iso:country":"DE",
    "sg:address":"Augustastr. 47",
    "sg:city":"Duisburg",
    "sg:postcode":"47137",
    "sg:province":"Nordrhein-Westfalen",
    "wof:name":"Klaus Heger",
    "wof:placetype":"venue"
},
  "geometry": {"coordinates":[6.7754821777,51.4698066711],"type":"Point"}
}