{
  "type": "Feature",
  "properties": {
    "iso:country":"DE",
    "sg:address":"Kettengasse 14",
    "sg:city":"Bad Bergzabern",
    "sg:phone":"+49 6343/7589",
    "sg:postcode":"76887",
    "sg:province":"Rheinland-Pfalz",
    "wof:name":"Willi Sanwald Grabdenkm\u00e4ler",
    "wof:placetype":"venue"
},
  "geometry": {"coordinates":[7.9983119965,49.1009254456],"type":"Point"}
}