{
  "type": "Feature",
  "properties": {
    "iso:country":"DE",
    "sg:address":"M\u00f6rschgasse 35",
    "sg:city":"Speyer",
    "sg:phone":"+49 6232/74715",
    "sg:postcode":"67346",
    "sg:province":"Rheinland-Pfalz",
    "wof:name":"Zeitsprung",
    "wof:placetype":"venue"
},
  "geometry": {"coordinates":[8.433557,49.321503],"type":"Point"}
}