{
  "type": "Feature",
  "properties": {
    "iso:country":"DE",
    "sg:address":"Immengarten 49",
    "sg:city":"Hildesheim",
    "sg:phone":"+49 4951/2134282",
    "sg:postcode":"31134",
    "sg:province":"Niedersachsen",
    "wof:name":"J.c. Kornacker",
    "wof:placetype":"venue"
},
  "geometry": {"coordinates":[9.962179,52.147804],"type":"Point"}
}