{
  "type": "Feature",
  "properties": {
    "iso:country":"DE",
    "sg:address":"Pfarrgasse 6",
    "sg:city":"Pfaffenhofen",
    "sg:phone":"+49 7046/2103",
    "sg:postcode":"74397",
    "sg:province":"Baden-W\u00fcrttemberg",
    "wof:name":"Ev. Pfarramt",
    "wof:placetype":"venue"
},
  "geometry": {"coordinates":[8.976559639,49.0639572144],"type":"Point"}
}