{
  "type": "Feature",
  "properties": {
    "iso:country":"DE",
    "sg:address":"Bundesstr 10-12",
    "sg:city":"Ehrenkirchen",
    "sg:phone":"+49 7633/948814",
    "sg:postcode":"79238",
    "sg:province":"Baden-W\u00fcrttemberg",
    "wof:name":"Teamsport-schlaefer",
    "wof:placetype":"venue"
},
  "geometry": {"coordinates":[7.7176408768,47.930973053],"type":"Point"}
}