{
  "type": "Feature",
  "properties": {
    "iso:country":"DE",
    "sg:address":"Gutenbergstr. 1",
    "sg:city":"Dreieich",
    "sg:phone":"+49 6074/5597",
    "sg:postcode":"63303",
    "sg:province":"Hessen",
    "wof:name":"Lettmayer & Reitz",
    "wof:placetype":"venue"
},
  "geometry": {"coordinates":[8.753768,49.983467],"type":"Point"}
}