{
  "type": "Feature",
  "properties": {
    "iso:country":"DE",
    "sg:address":"Ackerstrasse 17",
    "sg:city":"Ibbenbueren",
    "sg:phone":"+49 5451/505412",
    "sg:postcode":"49477",
    "sg:province":"Nordrhein-Westfalen",
    "wof:name":"Centrox Multimedia Entwicklungsgesellschaft",
    "wof:placetype":"venue"
},
  "geometry": {"coordinates":[7.702439,52.272865],"type":"Point"}
}