{
  "type": "Feature",
  "properties": {
    "iso:country":"DE",
    "sg:address":"Friedrichswalde 34",
    "sg:city":"Bahretal",
    "sg:phone":"+49 35025/50761",
    "sg:postcode":"01819",
    "sg:province":"Sachsen",
    "wof:name":"Horst Baubkus",
    "wof:placetype":"venue"
},
  "geometry": {"coordinates":[13.9066267014,50.8999786377],"type":"Point"}
}