{
  "type": "Feature",
  "properties": {
    "iso:country":"DE",
    "sg:address":"Lipschitzallee 68",
    "sg:city":"Berlin",
    "sg:phone":"+49 30/6032071",
    "sg:postcode":"12353",
    "sg:province":"Berlin",
    "wof:name":"Seniorenwohnhaus Haus Pommern",
    "wof:placetype":"venue"
},
  "geometry": {"coordinates":[13.463277,52.424789],"type":"Point"}
}