{
  "type": "Feature",
  "properties": {
    "iso:country":"DE",
    "sg:address":"Neue Torstr. 4",
    "sg:city":"Burgdorf",
    "sg:phone":"+49 5136/2275",
    "sg:postcode":"31303",
    "sg:province":"Niedersachsen",
    "wof:name":"Walter Block",
    "wof:placetype":"venue"
},
  "geometry": {"coordinates":[10.007476,52.447323],"type":"Point"}
}