{
  "type": "Feature",
  "properties": {
    "iso:country":"DE",
    "sg:address":"Friedhofsallee 57a",
    "sg:city":"L\u00fcbeck",
    "sg:phone":"+49 451/491681",
    "sg:postcode":"23554",
    "sg:province":"Schleswig-Holstein",
    "wof:name":"K. Wegener Steinmetzbetrieb",
    "wof:placetype":"venue"
},
  "geometry": {"coordinates":[10.6607818604,53.8872642517],"type":"Point"}
}