{
  "type": "Feature",
  "properties": {
    "iso:country":"DE",
    "sg:address":"\u00d6schelbronner Str. 2",
    "sg:city":"G\u00e4ufelden",
    "sg:phone":"+49 4970/3271356",
    "sg:postcode":"71126",
    "sg:province":"Baden-W\u00fcrttemberg",
    "wof:name":"Volksbank Herrenberg Eg",
    "wof:placetype":"venue"
},
  "geometry": {"coordinates":[8.848007,48.562542],"type":"Point"}
}