{
  "type": "Feature",
  "properties": {
    "iso:country":"DE",
    "sg:address":"Sebastiangasse 8",
    "sg:city":"Eichst\u00e4tt",
    "sg:phone":"+49 8421/1583",
    "sg:postcode":"85072",
    "sg:province":"Bayern",
    "wof:name":"Gerhard Ullmann",
    "wof:placetype":"venue"
},
  "geometry": {"coordinates":[11.179945,48.891068],"type":"Point"}
}