{
  "type": "Feature",
  "properties": {
    "iso:country":"DE",
    "sg:address":"Ruhloweg 5",
    "sg:city":"Stuvenborn",
    "sg:phone":"+49 4194/7596",
    "sg:postcode":"24641",
    "sg:province":"Schleswig-Holstein",
    "wof:name":"Gerhard K\u00fcster",
    "wof:placetype":"venue"
},
  "geometry": {"coordinates":[10.128659,53.852409],"type":"Point"}
}