{
  "type": "Feature",
  "properties": {
    "iso:country":"DE",
    "sg:address":"Kirchstr. 11",
    "sg:city":"Besigheim",
    "sg:phone":"+49 7143/801040",
    "sg:postcode":"74354",
    "sg:province":"Baden-W\u00fcrttemberg",
    "wof:name":"Ps-reisen Gmbh",
    "wof:placetype":"venue"
},
  "geometry": {"coordinates":[9.1408138275,49.0006370544],"type":"Point"}
}