{
  "type": "Feature",
  "properties": {
    "iso:country":"DE",
    "sg:address":"Gr\u00fcnberger Str 140",
    "sg:city":"Gie\u00dfen",
    "sg:phone":"+49 641/4955997",
    "sg:postcode":"35394",
    "sg:province":"Hessen",
    "wof:name":"Crazy Metal Gbr Backes & Albach",
    "wof:placetype":"venue"
},
  "geometry": {"coordinates":[8.710413,50.586884],"type":"Point"}
}