{
  "type": "Feature",
  "properties": {
    "iso:country":"DE",
    "sg:address":"Zielstattstr. 117",
    "sg:city":"M\u00fcnchen",
    "sg:phone":"+49 89/784183",
    "sg:postcode":"81379",
    "sg:province":"Bayern",
    "wof:name":"H. Rehwald Ingenieur",
    "wof:placetype":"venue"
},
  "geometry": {"coordinates":[11.5189027786,48.1017494202],"type":"Point"}
}