{
  "type": "Feature",
  "properties": {
    "iso:country":"DE",
    "sg:address":"Stra\u00dfe der Glasmacher 28-32",
    "sg:city":"Wei\u00dfwasser",
    "sg:postcode":"02943",
    "sg:province":"Sachsen",
    "wof:name":"Kohlehandel Cottbus Gmbh",
    "wof:placetype":"venue"
},
  "geometry": {"coordinates":[14.647775,51.503902],"type":"Point"}
}