{
  "type": "Feature",
  "properties": {
    "iso:country":"DE",
    "sg:address":"Zehmeplatz 13",
    "sg:city":"Frankfurt",
    "sg:phone":"+49 335/321168",
    "sg:postcode":"15230",
    "sg:province":"Brandenburg",
    "wof:name":"Josef M\u00fcller Rechtsanwalt",
    "wof:placetype":"venue"
},
  "geometry": {"coordinates":[14.5500583649,52.3411445618],"type":"Point"}
}