{
  "type": "Feature",
  "properties": {
    "iso:country":"DE",
    "sg:address":"Lohstr. 133",
    "sg:city":"Stockelsdorf",
    "sg:phone":"+49 451/22242",
    "sg:postcode":"23617",
    "sg:province":"Schleswig-Holstein",
    "wof:name":"Musik-pub Rookie",
    "wof:placetype":"venue"
},
  "geometry": {"coordinates":[10.6688423157,53.9046058655],"type":"Point"}
}