{
  "type": "Feature",
  "properties": {
    "iso:country":"DE",
    "sg:address":"Manfred-W\u00f6rner-Str. 150",
    "sg:city":"G\u00f6ppingen",
    "sg:phone":"+49 7161/685450",
    "sg:postcode":"73037",
    "sg:province":"Baden-W\u00fcrttemberg",
    "wof:name":"Smp Auto. Project Computer- Vertriebsgesellschaft Mbh",
    "wof:placetype":"venue"
},
  "geometry": {"coordinates":[9.689546,48.713078],"type":"Point"}
}