{
  "type": "Feature",
  "properties": {
    "iso:country":"DE",
    "sg:address":"Bruckbach 29",
    "sg:city":"Brennberg",
    "sg:phone":"+49 9484/323",
    "sg:postcode":"93179",
    "sg:province":"Bayern",
    "wof:name":"Gastst\u00e4tte Johann Doblinger",
    "wof:placetype":"venue"
},
  "geometry": {"coordinates":[12.3655452728,49.0759887695],"type":"Point"}
}