{
  "type": "Feature",
  "properties": {
    "iso:country":"DE",
    "sg:address":"Ziegeleistr. 2",
    "sg:city":"Leer",
    "sg:phone":"+49 491/61817",
    "sg:postcode":"26789",
    "sg:province":"Niedersachsen",
    "wof:name":"Wilhelm Harbers",
    "wof:placetype":"venue"
},
  "geometry": {"coordinates":[7.414324,53.222363],"type":"Point"}
}