{
  "type": "Feature",
  "properties": {
    "iso:country":"DE",
    "sg:address":"Hosenm\u00fchle",
    "sg:city":"H\u00f6ckendorf",
    "sg:phone":"+49 35055/61231",
    "sg:postcode":"01774",
    "sg:province":"Sachsen",
    "wof:name":"Willfried Mende Gmbh",
    "wof:placetype":"venue"
},
  "geometry": {"coordinates":[13.5515546799,50.9210891724],"type":"Point"}
}