{
  "type": "Feature",
  "properties": {
    "iso:country":"DE",
    "sg:address":"Tullastr. 18",
    "sg:city":"Rheinau",
    "sg:phone":"+49 7853/675",
    "sg:postcode":"77866",
    "sg:province":"Baden-W\u00fcrttemberg",
    "wof:name":"Heinz Resch",
    "wof:placetype":"venue"
},
  "geometry": {"coordinates":[7.894261837,48.6251144409],"type":"Point"}
}