{
  "type": "Feature",
  "properties": {
    "iso:country":"DE",
    "sg:address":"Pertzstr. 1",
    "sg:city":"Hannover",
    "sg:postcode":"30625",
    "sg:province":"Niedersachsen",
    "wof:name":"Partner-, Kontaktvermittlung - Startseite",
    "wof:placetype":"venue"
},
  "geometry": {"coordinates":[9.795287,52.376606],"type":"Point"}
}