{
  "type": "Feature",
  "properties": {
    "iso:country":"DE",
    "sg:address":"Schwerzer Str.",
    "sg:city":"Niemberg",
    "sg:phone":"+49 34604/20195",
    "sg:postcode":"06188",
    "sg:province":"Sachsen-Anhalt",
    "wof:name":"Pflanzenschutz Wurth Inh. Brigitte Wurth",
    "wof:placetype":"venue"
},
  "geometry": {"coordinates":[12.105565,51.554329],"type":"Point"}
}