{
  "type": "Feature",
  "properties": {
    "iso:country":"DE",
    "sg:address":"Ro\u00dfmarkt 12",
    "sg:city":"Frankfurt",
    "sg:phone":"+49 69/291021",
    "sg:postcode":"60311",
    "sg:province":"Hessen",
    "wof:name":"Reiseb\u00fcro Ro\u00dfmarkt W. Rump & Co. Kg",
    "wof:placetype":"venue"
},
  "geometry": {"coordinates":[8.6772251129,50.112247467],"type":"Point"}
}