{
  "type": "Feature",
  "properties": {
    "iso:country":"DE",
    "sg:address":"Untere Klosterstr. 54",
    "sg:city":"\u00d6stringen",
    "sg:phone":"+49 7259/8756",
    "sg:postcode":"76684",
    "sg:province":"Baden-W\u00fcrttemberg",
    "wof:name":"Reiner Jenner",
    "wof:placetype":"venue"
},
  "geometry": {"coordinates":[8.756564,49.177212],"type":"Point"}
}