{
  "type": "Feature",
  "properties": {
    "iso:country":"DE",
    "sg:address":"Arberger Hafendamm 8",
    "sg:city":"Bremen",
    "sg:phone":"+49 421/415080",
    "sg:postcode":"28309",
    "sg:province":"Bremen",
    "wof:name":"Propan Gmbh & Co. Kg Propangasvertriebsstelle",
    "wof:placetype":"venue"
},
  "geometry": {"coordinates":[8.8788461685,53.0500984192],"type":"Point"}
}