{
  "type": "Feature",
  "properties": {
    "iso:country":"DE",
    "sg:address":"Wildenbruchstr. 24",
    "sg:city":"Gelsenkirchen",
    "sg:phone":"+49 209/142052",
    "sg:postcode":"45888",
    "sg:province":"Nordrhein-Westfalen",
    "wof:name":"Grafica Desktop Publishing Gmbh",
    "wof:placetype":"venue"
},
  "geometry": {"coordinates":[7.106835,51.507191],"type":"Point"}
}