{
  "type": "Feature",
  "properties": {
    "iso:country":"DE",
    "sg:address":"Sven-Hedin-Str. 14",
    "sg:city":"Berlin",
    "sg:phone":"+49 30/8175063",
    "sg:postcode":"14163",
    "sg:province":"Berlin",
    "wof:name":"Peter Konicki",
    "wof:placetype":"venue"
},
  "geometry": {"coordinates":[13.2369041443,52.4380874634],"type":"Point"}
}