{
  "type": "Feature",
  "properties": {
    "iso:country":"DE",
    "sg:address":"Walter-Eckhard-Str. 37",
    "sg:city":"D\u00f6beln",
    "sg:phone":"+49 3431/701672",
    "sg:postcode":"04720",
    "sg:province":"Sachsen",
    "wof:name":"Frauenrath & Sch\u00f6del Gbr",
    "wof:placetype":"venue"
},
  "geometry": {"coordinates":[13.1289596558,51.135181427],"type":"Point"}
}