{
  "type": "Feature",
  "properties": {
    "iso:country":"DE",
    "sg:address":"Gro\u00df Hove 66",
    "sg:city":"Jork",
    "sg:phone":"+49 4162/94152",
    "sg:postcode":"21635",
    "sg:province":"Niedersachsen",
    "wof:name":"J. Von Der Beck",
    "wof:placetype":"venue"
},
  "geometry": {"coordinates":[9.745013237,53.5305557251],"type":"Point"}
}