{
  "type": "Feature",
  "properties": {
    "iso:country":"DE",
    "sg:address":"Annastr. 32",
    "sg:city":"Langenfeld",
    "sg:phone":"+49 2173/986880",
    "sg:postcode":"40764",
    "sg:province":"Nordrhein-Westfalen",
    "wof:name":"Restaurant Akropolis",
    "wof:placetype":"venue"
},
  "geometry": {"coordinates":[6.9507861137,51.1368026733],"type":"Point"}
}