{
  "type": "Feature",
  "properties": {
    "iso:country":"DE",
    "sg:address":"Karl-Marx-Str. 10 a",
    "sg:city":"Spremberg",
    "sg:phone":"+49 3563/96784",
    "sg:postcode":"03130",
    "sg:province":"Brandenburg",
    "wof:name":"Wunderlich",
    "wof:placetype":"venue"
},
  "geometry": {"coordinates":[14.372492,51.565605],"type":"Point"}
}