{
  "type": "Feature",
  "properties": {
    "iso:country":"DE",
    "sg:address":"Bahnhofstr. 9",
    "sg:city":"Oelde",
    "sg:phone":"+49 2522/2857",
    "sg:postcode":"59302",
    "sg:province":"Nordrhein-Westfalen",
    "wof:name":"Heinrich Kleinekemper",
    "wof:placetype":"venue"
},
  "geometry": {"coordinates":[8.143048,51.826721],"type":"Point"}
}