{
  "type": "Feature",
  "properties": {
    "iso:country":"DE",
    "sg:address":"F\u00e4hrstr. 76",
    "sg:city":"D\u00fcsseldorf",
    "sg:phone":"+49 211/3981609",
    "sg:postcode":"40221",
    "sg:province":"Nordrhein-Westfalen",
    "wof:name":"Hans J. Ley",
    "wof:placetype":"venue"
},
  "geometry": {"coordinates":[6.75233,51.206165],"type":"Point"}
}