{
  "type": "Feature",
  "properties": {
    "iso:country":"DE",
    "sg:address":"Dornspachstr. 24",
    "sg:city":"Zittau",
    "sg:phone":"+49 3583/700200",
    "sg:postcode":"02763",
    "sg:province":"Sachsen",
    "wof:name":"Heinz Lange",
    "wof:placetype":"venue"
},
  "geometry": {"coordinates":[14.817587,50.904011],"type":"Point"}
}