{
  "type": "Feature",
  "properties": {
    "iso:country":"DE",
    "sg:address":"Bubenhofenstr. 3",
    "sg:city":"Burladingen",
    "sg:phone":"+49 7475/7366",
    "sg:postcode":"72393",
    "sg:province":"Baden-W\u00fcrttemberg",
    "wof:name":"R. Emele",
    "wof:placetype":"venue"
},
  "geometry": {"coordinates":[9.1672153473,48.2738189697],"type":"Point"}
}