{
  "type": "Feature",
  "properties": {
    "iso:country":"DE",
    "sg:address":"Ritterlandweg 49",
    "sg:city":"Berlin",
    "sg:phone":"+49 30/4916489",
    "sg:postcode":"13409",
    "sg:province":"Berlin",
    "wof:name":"H\u00e4usler Verzahn- Und Drehtechnik Gmbh",
    "wof:placetype":"venue"
},
  "geometry": {"coordinates":[13.374889,52.560871],"type":"Point"}
}