{
  "type": "Feature",
  "properties": {
    "iso:country":"DE",
    "sg:address":"Gneversdorfer Weg 27",
    "sg:city":"L\u00fcbeck",
    "sg:phone":"+49 4502/2692",
    "sg:postcode":"23570",
    "sg:province":"Schleswig-Holstein",
    "wof:name":"Otto Leiske",
    "wof:placetype":"venue"
},
  "geometry": {"coordinates":[10.8533668518,53.9704971313],"type":"Point"}
}