{
  "type": "Feature",
  "properties": {
    "iso:country":"DE",
    "sg:address":"Gutachstr. 30",
    "sg:city":"Titisee-Neustadt",
    "sg:phone":"+49 7651/2774",
    "sg:postcode":"79822",
    "sg:province":"Baden-W\u00fcrttemberg",
    "wof:name":"Minimal",
    "wof:placetype":"venue"
},
  "geometry": {"coordinates":[8.2048931122,47.9181060791],"type":"Point"}
}