{
  "type": "Feature",
  "properties": {
    "iso:country":"DE",
    "sg:address":"Louisenstr. 120",
    "sg:city":"Bad Homburg",
    "sg:phone":"+49 6172/451856",
    "sg:postcode":"61348",
    "sg:province":"Hessen",
    "wof:name":"Gemeinder & Partner Public-relations Gmbh",
    "wof:placetype":"venue"
},
  "geometry": {"coordinates":[8.6254148483,50.2230567932],"type":"Point"}
}