{
  "type": "Feature",
  "properties": {
    "iso:country":"DE",
    "sg:address":"Breisgauer Str. 29",
    "sg:city":"Freiburg",
    "sg:phone":"+49 761/82841",
    "sg:postcode":"79110",
    "sg:province":"Baden-W\u00fcrttemberg",
    "wof:name":"Bernhard Saier",
    "wof:placetype":"venue"
},
  "geometry": {"coordinates":[7.8029828072,48.014831543],"type":"Point"}
}