{
  "type": "Feature",
  "properties": {
    "iso:country":"DE",
    "sg:address":"Sunderkampstr. 27",
    "sg:city":"B\u00fcnde",
    "sg:phone":"+49 5223/6611",
    "sg:postcode":"32257",
    "sg:province":"Nordrhein-Westfalen",
    "wof:name":"Dustmann Verwaltungs-gmbh",
    "wof:placetype":"venue"
},
  "geometry": {"coordinates":[8.563059,52.195007],"type":"Point"}
}