{
  "type": "Feature",
  "properties": {
    "iso:country":"DE",
    "sg:address":"Windhukstr 81-83",
    "sg:city":"Wuppertal",
    "sg:phone":"+49 202/2641430",
    "sg:postcode":"42277",
    "sg:province":"Nordrhein-Westfalen",
    "wof:name":"Pepin Produktions Gmbh",
    "wof:placetype":"venue"
},
  "geometry": {"coordinates":[7.236726,51.285381],"type":"Point"}
}