{
  "type": "Feature",
  "properties": {
    "iso:country":"DE",
    "sg:address":"Sch\u00fctzenstr. 1",
    "sg:city":"Gro\u00df-Gerau",
    "sg:phone":"+49 6152/82266",
    "sg:postcode":"64521",
    "sg:province":"Hessen",
    "wof:name":"Einstein",
    "wof:placetype":"venue"
},
  "geometry": {"coordinates":[8.4798803329,49.9236183167],"type":"Point"}
}