{
  "type": "Feature",
  "properties": {
    "iso:country":"DE",
    "sg:address":"Ernst-Th\u00e4lmann-Platz 2",
    "sg:city":"Hirschfelde",
    "sg:phone":"+49 35843/25721",
    "sg:postcode":"02788",
    "sg:province":"Sachsen",
    "wof:name":"Ronald Krause",
    "wof:placetype":"venue"
},
  "geometry": {"coordinates":[14.8896436691,50.94556427],"type":"Point"}
}