{
  "type": "Feature",
  "properties": {
    "iso:country":"DE",
    "sg:address":"Betriebsstr. 3",
    "sg:city":"Offenberg",
    "sg:phone":"+49 991/284811",
    "sg:postcode":"94560",
    "sg:province":"Bayern",
    "wof:name":"Becker Carbon Gmbh",
    "wof:placetype":"venue"
},
  "geometry": {"coordinates":[12.886759758,48.8608169556],"type":"Point"}
}