{
  "type": "Feature",
  "properties": {
    "iso:country":"DE",
    "sg:address":"Ippensen 24",
    "sg:city":"Kreiensen",
    "sg:phone":"+49 5563/1241",
    "sg:postcode":"37547",
    "sg:province":"Niedersachsen",
    "wof:name":"Paul Knaak",
    "wof:placetype":"venue"
},
  "geometry": {"coordinates":[9.953712,51.839741],"type":"Point"}
}