{
  "type": "Feature",
  "properties": {
    "iso:country":"DE",
    "sg:address":"Industriestr 35",
    "sg:city":"Stuhr",
    "sg:phone":"+49 421/89940",
    "sg:postcode":"28816",
    "sg:province":"Niedersachsen",
    "wof:name":"Kwb Karl W. Burmeister Gmbh & Co Kg",
    "wof:placetype":"venue"
},
  "geometry": {"coordinates":[8.755188,52.991253],"type":"Point"}
}