{
  "type": "Feature",
  "properties": {
    "iso:country":"DE",
    "sg:address":"Birkenweg 3",
    "sg:city":"Westerland",
    "sg:phone":"+49 4651/23033",
    "sg:postcode":"25980",
    "sg:province":"Schleswig-Holstein",
    "wof:name":"G\u00e4stehaus Haus Muckl",
    "wof:placetype":"venue"
},
  "geometry": {"coordinates":[8.3166790009,54.9067764282],"type":"Point"}
}