{
  "type": "Feature",
  "properties": {
    "iso:country":"DE",
    "sg:address":"Im Sperber 24",
    "sg:city":"Frankfurt",
    "sg:phone":"+49 6109/2813",
    "sg:postcode":"60388",
    "sg:province":"Hessen",
    "wof:name":"Sch\u00f6ne Aussicht Hotel Und Gastst\u00e4tte",
    "wof:placetype":"venue"
},
  "geometry": {"coordinates":[8.7556171417,50.1544570923],"type":"Point"}
}