{
  "type": "Feature",
  "properties": {
    "iso:country":"DE",
    "sg:address":"Kirchstr. 131",
    "sg:city":"Duisburg",
    "sg:phone":"+49 2066/35525",
    "sg:postcode":"47198",
    "sg:province":"Nordrhein-Westfalen",
    "wof:name":"Monika Redlich-adams Rechtsanw\u00e4ltin",
    "wof:placetype":"venue"
},
  "geometry": {"coordinates":[6.6839962006,51.4510688782],"type":"Point"}
}