{
  "type": "Feature",
  "properties": {
    "iso:country":"DE",
    "sg:address":"Ludwig-Ganghofer-Str. 5",
    "sg:city":"Gr\u00fcnwald",
    "sg:phone":"+49 89/6418080",
    "sg:postcode":"82031",
    "sg:province":"Bayern",
    "wof:name":"Richter Ingenieurges. Mbh",
    "wof:placetype":"venue"
},
  "geometry": {"coordinates":[11.5297555923,48.0456619263],"type":"Point"}
}