{
  "type": "Feature",
  "properties": {
    "iso:country":"DE",
    "sg:address":"Waltherstr. 2",
    "sg:city":"Dresden",
    "sg:phone":"+49 351/4996430",
    "sg:postcode":"01067",
    "sg:province":"Sachsen",
    "wof:name":"Dresdener M\u00dchlen Kg",
    "wof:placetype":"venue"
},
  "geometry": {"coordinates":[13.713062,51.06263],"type":"Point"}
}