{
  "type": "Feature",
  "properties": {
    "iso:country":"DE",
    "sg:address":"Am Zimmerplatz 3",
    "sg:city":"Heuchelheim",
    "sg:phone":"+49 641/9607971",
    "sg:postcode":"35452",
    "sg:province":"Hessen",
    "wof:name":"Betten F\u00fcr Alle Gmbh",
    "wof:placetype":"venue"
},
  "geometry": {"coordinates":[8.6327762604,50.5778694153],"type":"Point"}
}