{
  "type": "Feature",
  "properties": {
    "iso:country":"DE",
    "sg:address":"Bergstr. 14",
    "sg:city":"Freital",
    "sg:phone":"+49 351/4760180",
    "sg:postcode":"01705",
    "sg:province":"Sachsen",
    "wof:name":"Margit H\u00e4nchen",
    "wof:placetype":"venue"
},
  "geometry": {"coordinates":[13.635403,50.992653],"type":"Point"}
}