{
  "type": "Feature",
  "properties": {
    "iso:country":"DE",
    "sg:address":"Dittmarstr. 85/1",
    "sg:city":"Heilbronn",
    "sg:phone":"+49 7131/178099",
    "sg:postcode":"74074",
    "sg:province":"Baden-W\u00fcrttemberg",
    "wof:name":"Udo Reyda Ingenieur",
    "wof:placetype":"venue"
},
  "geometry": {"coordinates":[9.2398338318,49.1340293884],"type":"Point"}
}