{
  "type": "Feature",
  "properties": {
    "iso:country":"DE",
    "sg:address":"Sch\u00f6nningstedter Str. 33",
    "sg:city":"Reinbek",
    "sg:phone":"+49 40/7224463",
    "sg:postcode":"21465",
    "sg:province":"Schleswig-Holstein",
    "wof:name":"Richard & Co. Bestattungsinstitut",
    "wof:placetype":"venue"
},
  "geometry": {"coordinates":[10.255389,53.516548],"type":"Point"}
}