{
  "type": "Feature",
  "properties": {
    "iso:country":"DE",
    "sg:address":"Arthur-Wilke-Str. 1",
    "sg:city":"Premnitz",
    "sg:phone":"+49 3386/243201",
    "sg:postcode":"14727",
    "sg:province":"Brandenburg",
    "wof:name":"Kvs Kunststoffverarbeitungs U Service Gmbh",
    "wof:placetype":"venue"
},
  "geometry": {"coordinates":[12.3356351852,52.531124115],"type":"Point"}
}