{
  "type": "Feature",
  "properties": {
    "iso:country":"DE",
    "sg:address":"Holzm\u00fchlenstr. 56",
    "sg:city":"Hamburg",
    "sg:postcode":"22041",
    "sg:province":"Hamburg",
    "wof:name":"Maus Verwaltungs Gmbh",
    "wof:placetype":"venue"
},
  "geometry": {"coordinates":[10.0803718567,53.581161499],"type":"Point"}
}