{
  "type": "Feature",
  "properties": {
    "iso:country":"DE",
    "sg:address":"Dorfring 8",
    "sg:city":"Ganderkesee",
    "sg:phone":"+49 4223/3355",
    "sg:postcode":"27777",
    "sg:province":"Niedersachsen",
    "wof:name":"Heinecke Kg Fachbetrieb F\u00fcr",
    "wof:placetype":"venue"
},
  "geometry": {"coordinates":[8.5110797882,53.0970916748],"type":"Point"}
}