{
  "type": "Feature",
  "properties": {
    "iso:country":"DE",
    "sg:address":"Dornholzh\u00e4user Str. 9",
    "sg:city":"Oberursel",
    "sg:phone":"+49 6172/35666",
    "sg:postcode":"61440",
    "sg:province":"Hessen",
    "wof:name":"Walter R. Ro\u00dfmann",
    "wof:placetype":"venue"
},
  "geometry": {"coordinates":[8.579792,50.228592],"type":"Point"}
}