{
  "type": "Feature",
  "properties": {
    "iso:country":"DE",
    "sg:address":"Moselufer 5",
    "sg:city":"\u00dcrzig",
    "sg:phone":"+49 6532/4530",
    "sg:postcode":"54539",
    "sg:province":"Rheinland-Pfalz",
    "wof:name":"Werner Schmitz",
    "wof:placetype":"venue"
},
  "geometry": {"coordinates":[7.0037140846,49.9769706726],"type":"Point"}
}