{
  "type": "Feature",
  "properties": {
    "iso:country":"DE",
    "sg:address":"Vorstadt 4",
    "sg:city":"Stadtlauringen",
    "sg:phone":"+49 9724/2979",
    "sg:postcode":"97488",
    "sg:province":"Bayern",
    "wof:name":"Ger\u00e4temuseum Georg Bauer",
    "wof:placetype":"venue"
},
  "geometry": {"coordinates":[10.362845,50.189442],"type":"Point"}
}