{
  "type": "Feature",
  "properties": {
    "iso:country":"DE",
    "sg:address":"Thomas-Hauser-Str. 6",
    "sg:city":"M\u00fcnchen",
    "sg:phone":"+49 89/422503",
    "sg:postcode":"81829",
    "sg:province":"Bayern",
    "wof:name":"Paul Eckenweber",
    "wof:placetype":"venue"
},
  "geometry": {"coordinates":[11.653442,48.132202],"type":"Point"}
}