{
  "type": "Feature",
  "properties": {
    "iso:country":"DE",
    "sg:address":"Carstensstr. 47",
    "sg:city":"Celle",
    "sg:phone":"+49 5141/41888",
    "sg:postcode":"29225",
    "sg:province":"Niedersachsen",
    "wof:name":"B. Seibel",
    "wof:placetype":"venue"
},
  "geometry": {"coordinates":[10.0573825836,52.6130104065],"type":"Point"}
}