{
  "type": "Feature",
  "properties": {
    "iso:country":"DE",
    "sg:address":"Rudolf-Guby-Str. 4",
    "sg:city":"Passau",
    "sg:phone":"+49 851/590290",
    "sg:postcode":"94032",
    "sg:province":"Bayern",
    "wof:name":"Landeszentralbank Im Freistaat Bayern",
    "wof:placetype":"venue"
},
  "geometry": {"coordinates":[13.4489116669,48.5675201416],"type":"Point"}
}