{
  "type": "Feature",
  "properties": {
    "iso:country":"DE",
    "sg:address":"Johann-Kolb-Str.19",
    "sg:city":"Illertissen",
    "sg:phone":"+49 7303",
    "sg:postcode":"89257",
    "sg:province":"Bayern",
    "wof:name":"J\u00fcrgens Diskus Shop",
    "wof:placetype":"venue"
},
  "geometry": {"coordinates":[10.1036481857,48.2167396545],"type":"Point"}
}