{
  "type": "Feature",
  "properties": {
    "iso:country":"DE",
    "sg:address":"Hauptstr. 20",
    "sg:city":"Ahrensdorf",
    "sg:phone":"+49 3378/800016",
    "sg:postcode":"14974",
    "sg:province":"Brandenburg",
    "wof:name":"Manfred Walter",
    "wof:placetype":"venue"
},
  "geometry": {"coordinates":[13.1949110031,52.3159828186],"type":"Point"}
}