{
  "type": "Feature",
  "properties": {
    "iso:country":"DE",
    "sg:address":"Gartenstr. 4",
    "sg:city":"M\u00fchlheim",
    "sg:phone":"+49 6108/66466",
    "sg:postcode":"63165",
    "sg:province":"Hessen",
    "wof:name":"Peter Ruderich Ingenieur",
    "wof:placetype":"venue"
},
  "geometry": {"coordinates":[8.8541288376,50.0926818848],"type":"Point"}
}