{
  "type": "Feature",
  "properties": {
    "iso:country":"DE",
    "sg:address":"Nichtinghausen 4",
    "sg:city":"Eslohe",
    "sg:phone":"+49 2973/3541",
    "sg:postcode":"59889",
    "sg:province":"Nordrhein-Westfalen",
    "wof:name":"Josef G\u00f6dde",
    "wof:placetype":"venue"
},
  "geometry": {"coordinates":[8.263003,51.28373],"type":"Point"}
}