{
  "type": "Feature",
  "properties": {
    "iso:country":"DE",
    "sg:address":"Altensteinweg 12",
    "sg:city":"Badenweiler",
    "sg:phone":"+49 2758/653",
    "sg:postcode":"79410",
    "sg:province":"Baden-W\u00fcrttemberg",
    "wof:name":"Dr. T. Gerke",
    "wof:placetype":"venue"
},
  "geometry": {"coordinates":[7.7040529251,47.8046073914],"type":"Point"}
}