{
  "type": "Feature",
  "properties": {
    "iso:country":"DE",
    "sg:address":"Luisenstr. 23",
    "sg:city":"Viernheim",
    "sg:phone":"+49 6204/72400",
    "sg:postcode":"68519",
    "sg:province":"Hessen",
    "wof:name":"Pizzeria Da Nino",
    "wof:placetype":"venue"
},
  "geometry": {"coordinates":[8.579249382,49.5394477844],"type":"Point"}
}