{
  "type": "Feature",
  "properties": {
    "iso:country":"DE",
    "sg:address":"Bergheimer Str. 492",
    "sg:city":"Neuss",
    "sg:phone":"+49 2131/462298",
    "sg:postcode":"41466",
    "sg:province":"Nordrhein-Westfalen",
    "wof:name":"Pizzeria Casanova",
    "wof:placetype":"venue"
},
  "geometry": {"coordinates":[6.6847949028,51.1688728333],"type":"Point"}
}