{
  "type": "Feature",
  "properties": {
    "iso:country":"DE",
    "sg:address":"Ochsenbergweg 44",
    "sg:city":"Wildeshausen",
    "sg:postcode":"27793",
    "sg:province":"Niedersachsen",
    "wof:name":"Ks Service Gmbh",
    "wof:placetype":"venue"
},
  "geometry": {"coordinates":[8.4681625366,52.9029083252],"type":"Point"}
}