{
  "type": "Feature",
  "properties": {
    "iso:country":"DE",
    "sg:address":"Couvenstr. 6",
    "sg:city":"D\u00fcsseldorf",
    "sg:phone":"+49 211/166740",
    "sg:postcode":"40211",
    "sg:province":"Nordrhein-Westfalen",
    "wof:name":"Prada Germany Gmbh",
    "wof:placetype":"venue"
},
  "geometry": {"coordinates":[6.788520813,51.2310028076],"type":"Point"}
}