{
  "type": "Feature",
  "properties": {
    "iso:country":"DE",
    "sg:address":"St.-J\u00fcrgen-Platz 1",
    "sg:city":"Flensburg",
    "sg:phone":"+49 461/25212",
    "sg:postcode":"24943",
    "sg:province":"Schleswig-Holstein",
    "wof:name":"Quambusch Billig-umz\u00fcge- Flensburg",
    "wof:placetype":"venue"
},
  "geometry": {"coordinates":[9.4431638718,54.7882156372],"type":"Point"}
}