{
  "type": "Feature",
  "properties": {
    "iso:country":"DE",
    "sg:address":"Walramsneustr. 2 B",
    "sg:city":"Trier",
    "sg:phone":"+49 651/975070",
    "sg:postcode":"54290",
    "sg:province":"Rheinland-Pfalz",
    "wof:name":"Universa Versicherungen",
    "wof:placetype":"venue"
},
  "geometry": {"coordinates":[6.6379089355,49.7577857971],"type":"Point"}
}