{
  "type": "Feature",
  "properties": {
    "iso:country":"DE",
    "sg:address":"Villa Berg 1",
    "sg:city":"Stuttgart",
    "sg:phone":"+49 711/166680",
    "sg:postcode":"70190",
    "sg:province":"Baden-W\u00fcrttemberg",
    "wof:name":"Haus Des Dokumentarfilms",
    "wof:placetype":"venue"
},
  "geometry": {"coordinates":[9.2084217072,48.7920303345],"type":"Point"}
}