{
  "type": "Feature",
  "properties": {
    "iso:country":"DE",
    "sg:address":"Seedorfer Str. 18",
    "sg:city":"Dunningen",
    "sg:phone":"+49 7403/238",
    "sg:postcode":"78655",
    "sg:province":"Baden-W\u00fcrttemberg",
    "wof:name":"W. Jauch",
    "wof:placetype":"venue"
},
  "geometry": {"coordinates":[8.501988,48.214485],"type":"Point"}
}