{
  "type": "Feature",
  "properties": {
    "iso:country":"DE",
    "sg:address":"Orlaweg",
    "sg:city":"P\u00f6\u00dfneck",
    "sg:phone":"+49 7842/8399",
    "sg:postcode":"07381",
    "sg:province":"Th\u00fcringen",
    "wof:name":"E. Brodel",
    "wof:placetype":"venue"
},
  "geometry": {"coordinates":[11.6127901077,50.7096595764],"type":"Point"}
}