{
  "type": "Feature",
  "properties": {
    "iso:country":"DE",
    "sg:address":"Hauptstr. 93",
    "sg:city":"Herborn",
    "sg:phone":"+49 2772/3677",
    "sg:postcode":"35745",
    "sg:province":"Hessen",
    "wof:name":"Zoo-samen Sch\u00e4fer",
    "wof:placetype":"venue"
},
  "geometry": {"coordinates":[8.304499,50.681637],"type":"Point"}
}