{
  "type": "Feature",
  "properties": {
    "iso:country":"DE",
    "sg:address":"Am Weidengarten 10",
    "sg:city":"Lauterbach",
    "sg:phone":"+49 6641/919530",
    "sg:postcode":"36341",
    "sg:province":"Hessen",
    "wof:name":"Br\u00fcck & Theis",
    "wof:placetype":"venue"
},
  "geometry": {"coordinates":[9.385858,50.642876],"type":"Point"}
}