{
  "type": "Feature",
  "properties": {
    "iso:country":"DE",
    "sg:address":"Bajuwarenstr. 93",
    "sg:city":"M\u00fcnchen",
    "sg:phone":"+49 89/6881325",
    "sg:postcode":"81825",
    "sg:province":"Bayern",
    "wof:name":"Viehl Und Partner",
    "wof:placetype":"venue"
},
  "geometry": {"coordinates":[11.66089,48.1194],"type":"Point"}
}