{
  "type": "Feature",
  "properties": {
    "iso:country":"DE",
    "sg:address":"Neusser Str. 339",
    "sg:city":"M\u00f6nchengladbach",
    "sg:phone":"+49 2161/601818",
    "sg:postcode":"41065",
    "sg:province":"Nordrhein-Westfalen",
    "wof:name":"Ellen Beier",
    "wof:placetype":"venue"
},
  "geometry": {"coordinates":[6.4789958,51.2040328979],"type":"Point"}
}