{
  "type": "Feature",
  "properties": {
    "iso:country":"DE",
    "sg:address":"Borkener Str. 4",
    "sg:city":"S\u00fcdlohn",
    "sg:phone":"+49 2862/89142",
    "sg:postcode":"46354",
    "sg:province":"Nordrhein-Westfalen",
    "wof:name":"Heinrich Wehling",
    "wof:placetype":"venue"
},
  "geometry": {"coordinates":[6.854805,51.933125],"type":"Point"}
}