{
  "type": "Feature",
  "properties": {
    "iso:country":"DE",
    "sg:address":"Seeholzweg 10",
    "sg:city":"Unterm\u00fcnkheim",
    "sg:phone":"+49 7944/708",
    "sg:postcode":"74547",
    "sg:province":"Baden-W\u00fcrttemberg",
    "wof:name":"Karl Schmuderer Mech. Werkstatt",
    "wof:placetype":"venue"
},
  "geometry": {"coordinates":[9.719502,49.174992],"type":"Point"}
}