{
  "type": "Feature",
  "properties": {
    "iso:country":"DE",
    "sg:address":"Marktstr. 16",
    "sg:city":"Schelklingen",
    "sg:phone":"+49 7394/93030",
    "sg:postcode":"89601",
    "sg:province":"Baden-W\u00fcrttemberg",
    "wof:name":"G\u00f6tz Baustein Immobilien Wohn- Und Gewerbebau Gmbh",
    "wof:placetype":"venue"
},
  "geometry": {"coordinates":[9.7338266373,48.3752365112],"type":"Point"}
}