{
  "type": "Feature",
  "properties": {
    "iso:country":"DE",
    "sg:address":"Sonnenwendstr. 93",
    "sg:city":"Bad D\u00fcrkheim",
    "sg:phone":"+49 6322/8673",
    "sg:postcode":"67098",
    "sg:province":"Rheinland-Pfalz",
    "wof:name":"E & H Montagebau Gmbh",
    "wof:placetype":"venue"
},
  "geometry": {"coordinates":[8.154076,49.458317],"type":"Point"}
}