{
  "type": "Feature",
  "properties": {
    "iso:country":"DE",
    "sg:address":"Herrlichkeitstr. 123",
    "sg:city":"Hemmoor",
    "sg:phone":"+49 4771/7777",
    "sg:postcode":"21745",
    "sg:province":"Niedersachsen",
    "wof:name":"Walter Schwarz",
    "wof:placetype":"venue"
},
  "geometry": {"coordinates":[9.118350029,53.6964607239],"type":"Point"}
}