{
  "type": "Feature",
  "properties": {
    "iso:country":"DE",
    "sg:address":"Hildesheimer Str. 4",
    "sg:city":"Nordstemmen",
    "sg:phone":"+49 5069/2581",
    "sg:postcode":"31171",
    "sg:province":"Niedersachsen",
    "wof:name":"Twt Innenausbau- Und Malerarbeiten Gmbh",
    "wof:placetype":"venue"
},
  "geometry": {"coordinates":[9.792594,52.15181],"type":"Point"}
}