{
  "type": "Feature",
  "properties": {
    "iso:country":"DE",
    "sg:address":"Gr\u00fcnthaler Str. 19",
    "sg:city":"Olbernhau",
    "sg:phone":"+49 37360/2571",
    "sg:postcode":"09526",
    "sg:province":"Sachsen",
    "wof:name":"D. Richter",
    "wof:placetype":"venue"
},
  "geometry": {"coordinates":[13.3388223648,50.6605529785],"type":"Point"}
}