{
  "type": "Feature",
  "properties": {
    "iso:country":"DE",
    "sg:address":"Ballhofstr. 12",
    "sg:city":"Hannover",
    "sg:phone":"+49 511/329712",
    "sg:postcode":"30159",
    "sg:province":"Niedersachsen",
    "wof:name":"Kalauer-bistro-bierpub",
    "wof:placetype":"venue"
},
  "geometry": {"coordinates":[9.7327404022,52.372718811],"type":"Point"}
}