{
  "type": "Feature",
  "properties": {
    "iso:country":"DE",
    "sg:address":"Ahornstr 18",
    "sg:city":"Mammendorf",
    "sg:phone":"+49 8145/860",
    "sg:postcode":"82291",
    "sg:province":"Bayern",
    "wof:name":"Ariella Gmbh",
    "wof:placetype":"venue"
},
  "geometry": {"coordinates":[11.171679,48.207539],"type":"Point"}
}