{
  "type": "Feature",
  "properties": {
    "iso:country":"DE",
    "sg:address":"Waldstr. 10",
    "sg:city":"Stuttgart",
    "sg:phone":"+49 711/7696110",
    "sg:postcode":"70597",
    "sg:province":"Baden-W\u00fcrttemberg",
    "wof:name":"Ingenieurb\u00fcro F\u00fcr Elektro- Technik Werner Schwarz Gmbh",
    "wof:placetype":"venue"
},
  "geometry": {"coordinates":[9.177854538,48.7502975464],"type":"Point"}
}