{
  "type": "Feature",
  "properties": {
    "iso:country":"DE",
    "sg:address":"Gr\u00fcne Wiesenstr. 21",
    "sg:city":"Herborn",
    "sg:phone":"+49 2777/387",
    "sg:postcode":"35745",
    "sg:province":"Hessen",
    "wof:name":"Karl-heinz Reuschling",
    "wof:placetype":"venue"
},
  "geometry": {"coordinates":[8.228077,50.669205],"type":"Point"}
}