{
  "type": "Feature",
  "properties": {
    "iso:country":"DE",
    "sg:address":"Prinzregentenplatz 10",
    "sg:city":"M\u00fcnchen",
    "sg:postcode":"81675",
    "sg:province":"Bayern",
    "wof:name":"Micro Age Deutschland Gmbh",
    "wof:placetype":"venue"
},
  "geometry": {"coordinates":[11.6046028137,48.1392707825],"type":"Point"}
}