{
  "type": "Feature",
  "properties": {
    "iso:country":"DE",
    "sg:address":"Nesselrodestr. 9",
    "sg:city":"K\u00f6ln",
    "sg:phone":"+49 221/842475",
    "sg:postcode":"50735",
    "sg:province":"Nordrhein-Westfalen",
    "wof:name":"W. Kohls Feuerl\u00f6scher Gmbh",
    "wof:placetype":"venue"
},
  "geometry": {"coordinates":[6.962943,50.97718],"type":"Point"}
}