{
  "type": "Feature",
  "properties": {
    "iso:country":"DE",
    "sg:address":"Fr\u00f6belstr. 8",
    "sg:city":"Neustadt",
    "sg:phone":"+49 6321/83222",
    "sg:postcode":"67433",
    "sg:province":"Rheinland-Pfalz",
    "wof:name":"R\u00fcffel",
    "wof:placetype":"venue"
},
  "geometry": {"coordinates":[8.1356363297,49.3518218994],"type":"Point"}
}