{
  "type": "Feature",
  "properties": {
    "iso:country":"DE",
    "sg:address":"Helbersdorfer Str.",
    "sg:city":"Chemnitz",
    "sg:postcode":"09120",
    "sg:province":"Sachsen",
    "wof:name":"Beratungs- Und Buchdienst- Gesellschaft Des Bauern-",
    "wof:placetype":"venue"
},
  "geometry": {"coordinates":[12.9000101089,50.8105964661],"type":"Point"}
}