{
  "type": "Feature",
  "properties": {
    "iso:country":"DE",
    "sg:address":"Knooper Weg 25",
    "sg:city":"Kiel",
    "sg:phone":"+49 431/95857",
    "sg:postcode":"24103",
    "sg:province":"Schleswig-Holstein",
    "wof:name":"Photo Dose Gmbh",
    "wof:placetype":"venue"
},
  "geometry": {"coordinates":[10.1267690659,54.3226318359],"type":"Point"}
}