{
  "type": "Feature",
  "properties": {
    "iso:country":"DE",
    "sg:address":"Pelzm\u00fchlenstr. 25",
    "sg:city":"Chemnitz",
    "sg:phone":"+49 371/8577998",
    "sg:postcode":"09117",
    "sg:province":"Sachsen",
    "wof:name":"Schwimmhalle Sport- Und Freizeitcenter",
    "wof:placetype":"venue"
},
  "geometry": {"coordinates":[12.830450058,50.8192443848],"type":"Point"}
}